{
  "type": "Feature",
  "properties": {
    "iso:country":"US",
    "sg:address":"417 Romaine Creek Rd",
    "sg:city":"Fenton",
    "sg:classifiers":[
        {
            "category":"Personal",
            "subcategory":"Beauty Salon",
            "type":"Services"
        }
    ],
    "sg:phone":"+1 636 326 9962",
    "sg:postcode":"63026",
    "sg:province":"MO",
    "sg:tags":[
        "hair",
        "stylist"
    ],
    "wof:name":"Kay's Beauty Shop",
    "wof:placetype":"venue"
},
  "geometry": {"coordinates":[-90.433646,38.470031],"type":"Point"}
}