{
  "type": "Feature",
  "properties": {
    "iso:country":"US",
    "sg:address":"613 E Harrison St",
    "sg:city":"Republic",
    "sg:classifiers":[
        {
            "category":"Building & Trades",
            "subcategory":"Plumbing",
            "type":"Services"
        }
    ],
    "sg:phone":"+1 417 732 1889",
    "sg:postcode":"65738",
    "sg:province":"MO",
    "sg:tags":[
        "conditioning",
        "air",
        "system",
        "contractor"
    ],
    "wof:name":"Ruckman Heating & Cooling",
    "wof:placetype":"venue"
},
  "geometry": {"coordinates":[-93.47005799999999,37.120251],"type":"Point"}
}