{
  "type": "Feature",
  "properties": {
    "iso:country":"US",
    "sg:address":"7 W Park Dr",
    "sg:city":"O Fallon",
    "sg:classifiers":[
        {
            "category":"Shopping",
            "subcategory":"Shoes",
            "type":"Retail Goods"
        }
    ],
    "sg:phone":"+1 636 441 8336",
    "sg:postcode":"63366",
    "sg:province":"MO",
    "wof:name":"Hands Over Feet",
    "wof:placetype":"venue"
},
  "geometry": {"coordinates":[-90.71348999999999,38.796929],"type":"Point"}
}