{
  "type": "Feature",
  "properties": {
    "iso:country":"US",
    "sg:address":"1228 N Yarberry Ave",
    "sg:city":"Springfield",
    "sg:classifiers":[
        {
            "category":"Building & Trades",
            "subcategory":"Construction",
            "type":"Services"
        }
    ],
    "sg:phone":"+1 417 224 5900",
    "sg:postcode":"65802",
    "sg:province":"MO",
    "sg:tags":[
        "house"
    ],
    "wof:name":"Mike Dobbs Homes Inc",
    "wof:placetype":"venue"
},
  "geometry": {"coordinates":[-93.21773899999999,37.219556],"type":"Point"}
}