{
  "type": "Feature",
  "properties": {
    "iso:country":"US",
    "sg:address":"1420 Woodswether Rd",
    "sg:city":"Kansas City",
    "sg:classifiers":[
        {
            "category":"Wholesale",
            "subcategory":"Scrap",
            "type":"Manufacturing & Wholesale Goods"
        }
    ],
    "sg:phone":"+1 816 842 7372",
    "sg:postcode":"64105",
    "sg:province":"MO",
    "sg:tags":[
        "metal"
    ],
    "wof:name":"Secondary Resources Inc",
    "wof:placetype":"venue"
},
  "geometry": {"coordinates":[-94.601482,39.108277],"type":"Point"}
}