{
  "type": "Feature",
  "properties": {
    "iso:country":"US",
    "sg:address":"9843 Sandy Valley Rd",
    "sg:city":"Hillsboro",
    "sg:classifiers":[
        {
            "category":"Professional",
            "subcategory":"Management & Consulting",
            "type":"Services"
        }
    ],
    "sg:phone":"+1 636 797 5155",
    "sg:postcode":"63050",
    "sg:province":"MO",
    "sg:tags":[
        "business"
    ],
    "wof:name":"Maberry Benefits",
    "wof:placetype":"venue"
},
  "geometry": {"coordinates":[-90.50823,38.261283],"type":"Point"}
}