{
  "type": "Feature",
  "properties": {
    "iso:country":"US",
    "sg:address":"130 Hwy C",
    "sg:city":"St Peters",
    "sg:classifiers":[
        {
            "category":"Building & Trades",
            "subcategory":"Landscaping Services",
            "type":"Services"
        }
    ],
    "sg:phone":"+1 636 397 7217",
    "sg:postcode":"63376",
    "sg:province":"MO",
    "sg:tags":[
        "landscape",
        "contractor"
    ],
    "wof:name":"Conoyer Bros Landscaping Inc",
    "wof:placetype":"venue"
},
  "geometry": {"coordinates":[-90.629983,38.805396],"type":"Point"}
}