{
  "type": "Feature",
  "properties": {
    "iso:country":"US",
    "sg:address":"512 S Mc Canse St",
    "sg:city":"Mount Vernon",
    "sg:classifiers":[
        {
            "category":"Shopping",
            "subcategory":"Discount & Variety Stores",
            "type":"Retail Goods"
        }
    ],
    "sg:phone":"+1 417 466 7955",
    "sg:postcode":"65712",
    "sg:province":"MO",
    "wof:name":"B&D Family Enterprises Inc",
    "wof:placetype":"venue"
},
  "geometry": {"coordinates":[-93.81495,37.100282],"type":"Point"}
}