{
  "type": "Feature",
  "properties": {
    "iso:country":"US",
    "sg:address":"1205 NE Coronado Ct",
    "sg:city":"Lees Summit",
    "sg:classifiers":[
        {
            "category":"Professional",
            "subcategory":"Computer Services",
            "type":"Services"
        }
    ],
    "sg:phone":"+1 816 554 3928",
    "sg:postcode":"64086",
    "sg:province":"MO",
    "sg:tags":[
        "motion",
        "picture",
        "datum"
    ],
    "wof:name":"Glasenhardt Productions",
    "wof:placetype":"venue"
},
  "geometry": {"coordinates":[-94.36263099999999,38.935038],"type":"Point"}
}