{
  "type": "Feature",
  "properties": {
    "iso:country":"US",
    "sg:address":"7360 Forsyth Blvd",
    "sg:city":"Saint Louis",
    "sg:classifiers":[
        {
            "category":"Autos & Motor Vehicles",
            "subcategory":"Fuel & Gas Station",
            "type":"Retail Goods"
        }
    ],
    "sg:phone":"+1 314 725 7558",
    "sg:postcode":"63105",
    "sg:province":"MO",
    "wof:name":"Woodard's Forsyth Amoco-Bp Service",
    "wof:placetype":"venue"
},
  "geometry": {"coordinates":[-90.328003,38.648701],"type":"Point"}
}