{
  "type": "Feature",
  "properties": {
    "iso:country":"US",
    "sg:address":"3320 S Range Line Rd",
    "sg:city":"Joplin",
    "sg:classifiers":[
        {
            "category":"Travel",
            "subcategory":"Hotels & Motels",
            "type":"Entertainment"
        }
    ],
    "sg:phone":"+1 417 781 0500",
    "sg:postcode":"64804",
    "sg:province":"MO",
    "sg:tags":[
        "lounge"
    ],
    "wof:name":"Ramada Inn",
    "wof:placetype":"venue"
},
  "geometry": {"coordinates":[-94.478506,37.054899],"type":"Point"}
}