{
  "type": "Feature",
  "properties": {
    "iso:country":"US",
    "sg:address":"7254 State Hwy 94",
    "sg:city":"Mokane",
    "sg:phone":"+1 573 676 5854",
    "sg:postcode":"65059",
    "sg:province":"MO",
    "sg:tags":[
        "farm",
        "cotton"
    ],
    "wof:name":"Jimmy Meyer",
    "wof:placetype":"venue"
},
  "geometry": {"coordinates":[-91.89782599999999,38.660356],"type":"Point"}
}