{
  "type": "Feature",
  "properties": {
    "iso:country":"US",
    "sg:address":"318 E Scioto St",
    "sg:city":"St James",
    "sg:classifiers":[
        {
            "category":"Recreation",
            "type":"Entertainment"
        }
    ],
    "sg:phone":"+1 573 265 7269",
    "sg:postcode":"65559",
    "sg:province":"MO",
    "sg:tags":[
        "hall",
        "auditorium"
    ],
    "wof:name":"Catholic Church Parish Hall",
    "wof:placetype":"venue"
},
  "geometry": {"coordinates":[-91.608988,37.997176],"type":"Point"}
}