{
  "type": "Feature",
  "properties": {
    "iso:country":"US",
    "sg:address":"1003 Wildwood Dr",
    "sg:city":"Dexter",
    "sg:classifiers":[
        {
            "category":"Government",
            "subcategory":"Jail",
            "type":"Public Place"
        }
    ],
    "sg:phone":"+1 573 624 9434",
    "sg:postcode":"63841",
    "sg:province":"MO",
    "sg:tags":[
        "probation",
        "parole"
    ],
    "wof:name":"District 37",
    "wof:placetype":"venue"
},
  "geometry": {"coordinates":[-89.992327,36.80579],"type":"Point"}
}