{
  "type": "Feature",
  "properties": {
    "iso:country":"US",
    "sg:address":"1180 Millcreek Rd",
    "sg:city":"Lebanon",
    "sg:classifiers":[
        {
            "category":"Restaurant",
            "type":"Food & Drink"
        }
    ],
    "sg:phone":"+1 417 588 2587",
    "sg:postcode":"65536",
    "sg:province":"MO",
    "sg:tags":[
        "style",
        "family"
    ],
    "wof:name":"Bell Restaurant",
    "wof:placetype":"venue"
},
  "geometry": {"coordinates":[-92.636124,37.68018],"type":"Point"}
}