{
  "type": "Feature",
  "properties": {
    "iso:country":"US",
    "sg:address":"101 S 2nd St",
    "sg:city":"Hayti",
    "sg:classifiers":[
        {
            "category":"Organizations",
            "subcategory":"Religious Organization",
            "type":"Services"
        }
    ],
    "sg:phone":"+1 573 359 1625",
    "sg:postcode":"63851",
    "sg:province":"MO",
    "sg:tags":[
        "church"
    ],
    "wof:name":"Calvary Baptist Church",
    "wof:placetype":"venue"
},
  "geometry": {"coordinates":[-89.75032299999999,36.233002],"type":"Point"}
}