{
  "type": "Feature",
  "properties": {
    "iso:country":"US",
    "sg:address":"399 SE 228th St",
    "sg:city":"Plattsburg",
    "sg:phone":"+1 816 930 2038",
    "sg:postcode":"64477",
    "sg:province":"MO",
    "sg:tags":[
        "farm",
        "wheat"
    ],
    "wof:name":"James Henly",
    "wof:placetype":"venue"
},
  "geometry": {"coordinates":[-94.415436,39.506462],"type":"Point"}
}