{
  "type": "Feature",
  "properties": {
    "iso:country":"US",
    "sg:address":"513 Walnut St",
    "sg:city":"Kansas City",
    "sg:classifiers":[
        {
            "category":"Professional",
            "subcategory":"Business Services",
            "type":"Services"
        }
    ],
    "sg:phone":"+1 816 842 4983",
    "sg:postcode":"64106",
    "sg:province":"MO",
    "wof:name":"Slaughter L S & Assoc L L C",
    "wof:placetype":"venue"
},
  "geometry": {"coordinates":[-94.58136,39.108017],"type":"Point"}
}