{
  "type": "Feature",
  "properties": {
    "iso:country":"US",
    "sg:address":"12488 Audrain Road 971",
    "sg:city":"Thompson",
    "sg:classifiers":[
        {
            "category":"Insurance",
            "subcategory":"Insurance Agent",
            "type":"Services"
        }
    ],
    "sg:phone":"+1 573 581 7521",
    "sg:postcode":"65285",
    "sg:province":"MO",
    "sg:tags":[
        "life",
        "carrier"
    ],
    "wof:name":"Crop Insurance Agency",
    "wof:placetype":"venue"
},
  "geometry": {"coordinates":[-92.03621699999999,39.158415],"type":"Point"}
}