{
  "type": "Feature",
  "properties": {
    "iso:country":"US",
    "sg:address":"6389 Smiley Ave",
    "sg:city":"St Louis",
    "sg:classifiers":[
        {
            "category":"Professional",
            "subcategory":"Advertising",
            "type":"Services"
        }
    ],
    "sg:phone":"+1 314 486 3028",
    "sg:postcode":"63139",
    "sg:province":"MO",
    "sg:tags":[
        "mail"
    ],
    "wof:name":"Shopper's Edge/Smart Shopper",
    "wof:placetype":"venue"
},
  "geometry": {"coordinates":[-90.29551499999999,38.605898],"type":"Point"}
}