{
  "type": "Feature",
  "properties": {
    "iso:country":"US",
    "sg:address":"4038 Manhattan Ave",
    "sg:city":"Saint Peters",
    "sg:classifiers":[
        {
            "category":"Building & Trades",
            "subcategory":"Construction",
            "type":"Services"
        }
    ],
    "sg:phone":"+1 636 928 8221",
    "sg:postcode":"63376",
    "sg:province":"MO",
    "sg:tags":[
        "hanging",
        "contractor"
    ],
    "wof:name":"Lm Painting",
    "wof:placetype":"venue"
},
  "geometry": {"coordinates":[-90.57216699999999,38.782035],"type":"Point"}
}