{
  "type": "Feature",
  "properties": {
    "iso:country":"US",
    "sg:address":"3611 NE 78 St",
    "sg:city":"Kansas City",
    "sg:classifiers":[
        {
            "category":"Manufacturing",
            "subcategory":"Printing",
            "type":"Manufacturing & Wholesale Goods"
        }
    ],
    "sg:phone":"+1 816 468 0469",
    "sg:postcode":"64119",
    "sg:province":"MO",
    "sg:tags":[
        "book"
    ],
    "wof:name":"S&H Publishing Inc",
    "wof:placetype":"venue"
},
  "geometry": {"coordinates":[-94.536912,39.235066],"type":"Point"}
}