{
  "type": "Feature",
  "properties": {
    "iso:country":"US",
    "sg:address":"1313 S Madison Ave",
    "sg:city":"Aurora",
    "sg:classifiers":[
        {
            "category":"Shopping",
            "type":"Retail Goods"
        }
    ],
    "sg:phone":"+1 417 678 4313",
    "sg:postcode":"65605",
    "sg:province":"MO",
    "sg:tags":[
        "merchandise"
    ],
    "wof:name":"Dales General Store",
    "wof:placetype":"venue"
},
  "geometry": {"coordinates":[-93.721563,36.961819],"type":"Point"}
}