{
  "type": "Feature",
  "properties": {
    "iso:country":"US",
    "sg:address":"510 W 3rd St",
    "sg:city":"Fair Play",
    "sg:classifiers":[
        {
            "category":"Retail",
            "subcategory":"Portrait Studio",
            "type":"Services"
        }
    ],
    "sg:phone":"+1 417 654 2453",
    "sg:postcode":"65649",
    "sg:province":"MO",
    "sg:tags":[
        "photo"
    ],
    "wof:name":"Signs Prtrits By Charles Curry",
    "wof:placetype":"venue"
},
  "geometry": {"coordinates":[-93.58048100000001,37.631875],"type":"Point"}
}