{
  "type": "Feature",
  "properties": {
    "iso:country":"US",
    "sg:address":"222 E Water St",
    "sg:city":"Springfield",
    "sg:classifiers":[
        {
            "category":"Professional",
            "type":"Services"
        }
    ],
    "sg:phone":"+1 417 869 1113",
    "sg:postcode":"65806",
    "sg:province":"MO",
    "wof:name":"Commonworks",
    "wof:placetype":"venue"
},
  "geometry": {"coordinates":[-93.289973,37.210765],"type":"Point"}
}