{
  "type": "Feature",
  "properties": {
    "iso:country":"US",
    "sg:address":"1939 Crampton Ct",
    "sg:city":"Chesterfield",
    "sg:classifiers":[
        {
            "category":"Professional",
            "subcategory":"Engineering",
            "type":"Services"
        }
    ],
    "sg:phone":"+1 636 394 5823",
    "sg:postcode":"63017",
    "sg:province":"MO",
    "sg:tags":[
        "engineer"
    ],
    "wof:name":"Loftus Co",
    "wof:placetype":"venue"
},
  "geometry": {"coordinates":[-90.52501100000001,38.629241],"type":"Point"}
}