{
  "type": "Feature",
  "properties": {
    "iso:country":"US",
    "sg:address":"1603 Manufacturers Dr",
    "sg:city":"Fenton",
    "sg:classifiers":[
        {
            "category":"Manufacturing",
            "subcategory":"Glass & Minerals",
            "type":"Manufacturing & Wholesale Goods"
        },
        {
            "category":"Home & Garden",
            "subcategory":"Home Furnishings",
            "type":"Retail Goods"
        }
    ],
    "sg:phone":"+1 636 326 7670",
    "sg:postcode":"63026",
    "sg:province":"MO",
    "sg:tags":[
        "product",
        "mirror",
        "mfg"
    ],
    "wof:name":"Hitchcock & Butterfield",
    "wof:placetype":"venue"
},
  "geometry": {"coordinates":[-90.444014,38.534863],"type":"Point"}
}