{
  "type": "Feature",
  "properties": {
    "iso:country":"US",
    "sg:address":"8355 N Congress Ave",
    "sg:city":"Kansas City",
    "sg:classifiers":[
        {
            "category":"Health Services",
            "subcategory":"Doctor",
            "type":"Services"
        }
    ],
    "sg:phone":"+1 816 587 9500",
    "sg:postcode":"64152",
    "sg:province":"MO",
    "wof:name":"Scott M Nguyen",
    "wof:placetype":"venue"
},
  "geometry": {"coordinates":[-94.66825300000001,39.243619],"type":"Point"}
}