{
  "type": "Feature",
  "properties": {
    "iso:country":"US",
    "sg:address":"4805 NW 64 Ter",
    "sg:city":"Kansas City",
    "sg:classifiers":[
        {
            "category":"Professional",
            "subcategory":"Business Services",
            "type":"Services"
        }
    ],
    "sg:phone":"+1 816 741 8144",
    "sg:postcode":"64151",
    "sg:province":"MO",
    "wof:name":"Window Treatments & More",
    "wof:placetype":"venue"
},
  "geometry": {"coordinates":[-94.63475099999999,39.211197],"type":"Point"}
}