{
  "type": "Feature",
  "properties": {
    "iso:country":"US",
    "sg:address":"8008 Carondelet Ave",
    "sg:city":"Clayton",
    "sg:classifiers":[
        {
            "category":"Professional",
            "subcategory":"Lawyer & Legal Services",
            "type":"Services"
        }
    ],
    "sg:phone":"+1 314 863 1902",
    "sg:postcode":"63105",
    "sg:province":"MO",
    "sg:tags":[
        "attorney"
    ],
    "sg:website":"www.autoaccidenthelp.com",
    "wof:name":"John M Cichelero",
    "wof:placetype":"venue"
},
  "geometry": {"coordinates":[-90.3415,38.649117],"type":"Point"}
}