{
  "type": "Feature",
  "properties": {
    "addr:full":"2208 Bernadette Dr Columbia MO 65203",
    "addr:housenumber":"2208",
    "addr:postcode":"65203",
    "addr:street":"Bernadette Dr",
    "iso:country":"US",
    "sg:address":"2208 Bernadette Dr",
    "sg:city":"Columbia",
    "sg:classifiers":[
        {
            "category":"Shopping",
            "subcategory":"Books",
            "type":"Retail Goods"
        }
    ],
    "sg:phone":"+1 573 445 4080",
    "sg:postcode":"65203",
    "sg:province":"MO",
    "wof:name":"Barnes & Noble",
    "wof:placetype":"venue"
},
  "geometry": {"coordinates":[-92.37370799999999,38.965928],"type":"Point"}
}