{
  "type": "Feature",
  "properties": {
    "iso:country":"US",
    "sg:address":"282 Bayshore Dr",
    "sg:city":"Reeds Spring",
    "sg:classifiers":[
        {
            "category":"Building & Trades",
            "subcategory":"Electrical",
            "type":"Services"
        }
    ],
    "sg:phone":"+1 417 338 8338",
    "sg:postcode":"65737",
    "sg:province":"MO",
    "sg:tags":[
        "electrical",
        "contractor"
    ],
    "wof:name":"Love Electric",
    "wof:placetype":"venue"
},
  "geometry": {"coordinates":[-93.395173,36.639167],"type":"Point"}
}