{
  "type": "Feature",
  "properties": {
    "iso:country":"US",
    "sg:address":"5209 Waterman Blvd",
    "sg:city":"Saint Louis",
    "sg:classifiers":[
        {
            "category":"Education",
            "subcategory":"Preschool",
            "type":"Public Place"
        },
        {
            "category":"Education",
            "subcategory":"School",
            "type":"Public Place"
        }
    ],
    "sg:phone":"+1 314 361 6411",
    "sg:postcode":"63108",
    "sg:province":"MO",
    "sg:tags":[
        "elementary"
    ],
    "wof:name":"Schools",
    "wof:placetype":"venue"
},
  "geometry": {"coordinates":[-90.271103,38.6488],"type":"Point"}
}