{
  "type": "Feature",
  "properties": {
    "iso:country":"US",
    "sg:address":"701 Wren Ave",
    "sg:city":"Ballwin",
    "sg:classifiers":[
        {
            "category":"Education",
            "subcategory":"School",
            "type":"Public Place"
        }
    ],
    "sg:phone":"+1 314 415 7300",
    "sg:postcode":"63021",
    "sg:province":"MO",
    "wof:name":"Parkway Southwest Middle",
    "wof:placetype":"venue"
},
  "geometry": {"coordinates":[-90.522898,38.576797],"type":"Point"}
}