{
  "type": "Feature",
  "properties": {
    "iso:country":"US",
    "sg:address":"6426 Glenmore Ave",
    "sg:city":"St Louis",
    "sg:classifiers":[
        {
            "category":"Health Services",
            "subcategory":"Clinic",
            "type":"Services"
        }
    ],
    "sg:phone":"+1 314 381 9134",
    "sg:postcode":"63121",
    "sg:province":"MO",
    "sg:tags":[
        "home"
    ],
    "wof:name":"Pcs Home Health Inc",
    "wof:placetype":"venue"
},
  "geometry": {"coordinates":[-90.283547,38.691729],"type":"Point"}
}