{
  "type": "Feature",
  "properties": {
    "iso:country":"US",
    "sg:address":"1611 E 10th St",
    "sg:city":"Rolla",
    "sg:classifiers":[
        {
            "category":"Home & Garden",
            "subcategory":"Garden Supply",
            "type":"Retail Goods"
        },
        {
            "category":"Building & Trades",
            "subcategory":"Landscaping Services",
            "type":"Services"
        }
    ],
    "sg:phone":"+1 573 364 7700",
    "sg:postcode":"65401",
    "sg:province":"MO",
    "sg:tags":[
        "nursery",
        "center",
        "landscape",
        "contractor"
    ],
    "wof:name":"Suncliff Greenhouses & Nursery",
    "wof:placetype":"venue"
},
  "geometry": {"coordinates":[-91.743512,37.951521],"type":"Point"}
}