{
  "type": "Feature",
  "properties": {
    "iso:country":"US",
    "sg:address":"6801 E Mount Zion Church Rd",
    "sg:city":"Hallsville",
    "sg:classifiers":[
        {
            "category":"Social Services",
            "subcategory":"Child Care",
            "type":"Services"
        }
    ],
    "sg:phone":"+1 573 696 2601",
    "sg:postcode":"65255",
    "sg:province":"MO",
    "sg:tags":[
        "day"
    ],
    "wof:name":"Carters Day Care",
    "wof:placetype":"venue"
},
  "geometry": {"coordinates":[-92.221873,39.073705],"type":"Point"}
}