{
  "type": "Feature",
  "properties": {
    "iso:country":"US",
    "sg:address":"8000 Maryland Ave",
    "sg:city":"St Louis",
    "sg:classifiers":[
        {
            "category":"Real Estate",
            "subcategory":"Real Estate Operator",
            "type":"Services"
        }
    ],
    "sg:phone":"+1 314 863 1900",
    "sg:postcode":"63105",
    "sg:province":"MO",
    "sg:tags":[
        "condominium"
    ],
    "wof:name":"Maryland Walk",
    "wof:placetype":"venue"
},
  "geometry": {"coordinates":[-90.34120799999999,38.651962],"type":"Point"}
}