{
  "type": "Feature",
  "properties": {
    "addr:full":"1100 N Morley St Moberly MO 65270",
    "addr:housenumber":"1100",
    "addr:postcode":"65270",
    "addr:street":"N Morley St",
    "iso:country":"US",
    "sg:address":"1100 N Morley St",
    "sg:city":"Moberly",
    "sg:classifiers":[
        {
            "category":"Food & Beverages",
            "subcategory":"Groceries & Convenience Stores",
            "type":"Retail Goods"
        }
    ],
    "sg:phone":"+1 660 263 5635",
    "sg:postcode":"65270",
    "sg:province":"MO",
    "wof:name":"Break Time",
    "wof:placetype":"venue"
},
  "geometry": {"coordinates":[-92.433189,39.430612],"type":"Point"}
}