{
  "type": "Feature",
  "properties": {
    "iso:country":"US",
    "sg:address":"3 Main St",
    "sg:city":"Whiteoak",
    "sg:classifiers":[
        {
            "category":"Professional",
            "subcategory":"Business Services",
            "type":"Services"
        },
        {
            "category":"Government",
            "subcategory":"Post Office",
            "type":"Public Place"
        }
    ],
    "sg:phone":"+1 573 888 0700",
    "sg:postcode":"63880",
    "sg:province":"MO",
    "sg:tags":[
        "mail",
        "shipping"
    ],
    "sg:website":"http://www.usps.com",
    "wof:name":"USPS - United States Post Office",
    "wof:placetype":"venue"
},
  "geometry": {"coordinates":[-90.025372,36.329643],"type":"Point"}
}