{
  "type": "Feature",
  "properties": {
    "iso:country":"US",
    "sg:address":"3751 S Jefferson Ave",
    "sg:city":"Saint Louis",
    "sg:classifiers":[
        {
            "category":"Autos & Motor Vehicles",
            "subcategory":"Fuel & Gas Station",
            "type":"Retail Goods"
        }
    ],
    "sg:phone":"+1 314 776 6080",
    "sg:postcode":"63118",
    "sg:province":"MO",
    "sg:tags":[
        "convenience",
        "gasoline",
        "grocery",
        "store"
    ],
    "sg:website":"www.quiktrip.com",
    "wof:name":"Quiktrip",
    "wof:placetype":"venue"
},
  "geometry": {"coordinates":[-90.226975,38.586763],"type":"Point"}
}