{
  "type": "Feature",
  "properties": {
    "iso:country":"US",
    "sg:address":"415 Iffrig Rd",
    "sg:city":"St Peters",
    "sg:classifiers":[
        {
            "category":"Building & Trades",
            "subcategory":"Landscaping Services",
            "type":"Services"
        }
    ],
    "sg:phone":"+1 636 279 1338",
    "sg:postcode":"63376",
    "sg:province":"MO",
    "sg:tags":[
        "topsoil"
    ],
    "wof:name":"Dardenne Valley Top Soil",
    "wof:placetype":"venue"
},
  "geometry": {"coordinates":[-90.62025,38.80719],"type":"Point"}
}