{
  "type": "Feature",
  "properties": {
    "iso:country":"US",
    "sg:address":"1246 Colby Dr",
    "sg:city":"Saint Peters",
    "sg:classifiers":[
        {
            "category":"Building & Trades",
            "subcategory":"Landscaping Services",
            "type":"Services"
        }
    ],
    "sg:phone":"+1 636 441 6171",
    "sg:postcode":"63376",
    "sg:province":"MO",
    "wof:name":"Total Lawn Care",
    "wof:placetype":"venue"
},
  "geometry": {"coordinates":[-90.6019,38.777566],"type":"Point"}
}