{
  "type": "Feature",
  "properties": {
    "iso:country":"US",
    "sg:address":"2703 NW Platte Rd",
    "sg:city":"Riverside",
    "sg:classifiers":[
        {
            "category":"Insurance",
            "subcategory":"Insurance Agent",
            "type":"Services"
        },
        {
            "category":"Insurance",
            "subcategory":"Hazard Insurance",
            "type":"Services"
        }
    ],
    "sg:phone":"+1 816 505 2900",
    "sg:postcode":"64150",
    "sg:province":"MO",
    "sg:tags":[
        "business",
        "auto",
        "recreational",
        "commercial",
        "motorcycle",
        "vehicle",
        "marine",
        "boat"
    ],
    "sg:website":"http://www.freedominsurance4u.com",
    "wof:name":"Freedom Insurance Group",
    "wof:placetype":"venue"
},
  "geometry": {"coordinates":[-94.612883,39.172174],"type":"Point"}
}