{
  "type": "Feature",
  "properties": {
    "iso:country":"US",
    "sg:address":"1804 W Pearce Blvd",
    "sg:city":"Wentzville",
    "sg:classifiers":[
        {
            "category":"Real Estate",
            "subcategory":"Real Estate Agent",
            "type":"Services"
        }
    ],
    "sg:phone":"+1 636 698 9000",
    "sg:postcode":"63385",
    "sg:province":"MO",
    "sg:website":"www.remax-team-mo.com",
    "wof:name":"Re/Max Team",
    "wof:placetype":"venue"
},
  "geometry": {"coordinates":[-90.88755399999999,38.805958],"type":"Point"}
}