{
  "type": "Feature",
  "properties": {
    "iso:country":"US",
    "sg:address":"834 Hwy 42",
    "sg:city":"Iberia",
    "sg:classifiers":[
        {
            "category":"Retail",
            "subcategory":"Animal Services",
            "type":"Services"
        }
    ],
    "sg:phone":"+1 573 793 2957",
    "sg:postcode":"65486",
    "sg:province":"MO",
    "wof:name":"Grooming By Design/Boarding",
    "wof:placetype":"venue"
},
  "geometry": {"coordinates":[-92.297168,38.089228],"type":"Point"}
}