{
  "type": "Feature",
  "properties": {
    "iso:country":"US",
    "sg:address":"5535 Delmar Blvd",
    "sg:city":"Saint Louis",
    "sg:classifiers":[
        {
            "category":"Health Services",
            "subcategory":"Doctor",
            "type":"Services"
        },
        {
            "category":"Health Services",
            "subcategory":"Hospital",
            "type":"Services"
        }
    ],
    "sg:phone":"+1 314 361 2273",
    "sg:postcode":"63112",
    "sg:province":"MO",
    "wof:name":"St Louis Connectcare Community Health Centers",
    "wof:placetype":"venue"
},
  "geometry": {"coordinates":[-90.280098,38.6535],"type":"Point"}
}