{
  "type": "Feature",
  "properties": {
    "iso:country":"US",
    "sg:address":"1435 N Grand Blvd",
    "sg:city":"St Louis",
    "sg:classifiers":[
        {
            "category":"Education",
            "subcategory":"School",
            "type":"Public Place"
        },
        {
            "category":"Education",
            "subcategory":"Special Training",
            "type":"Public Place"
        }
    ],
    "sg:phone":"+1 314 535 0422",
    "sg:postcode":"63106",
    "sg:province":"MO",
    "sg:tags":[
        "consulting",
        "business"
    ],
    "wof:name":"Al Mu Minun",
    "wof:placetype":"venue"
},
  "geometry": {"coordinates":[-90.226074,38.64815],"type":"Point"}
}