{
  "type": "Feature",
  "properties": {
    "iso:country":"US",
    "sg:address":"722 S Meramec Ave",
    "sg:city":"Saint Louis",
    "sg:classifiers":[
        {
            "category":"Professional",
            "subcategory":"Business Services",
            "type":"Services"
        }
    ],
    "sg:phone":"+1 314 726 6140",
    "sg:postcode":"63105",
    "sg:province":"MO",
    "wof:name":"Lysographics",
    "wof:placetype":"venue"
},
  "geometry": {"coordinates":[-90.34085,38.64116],"type":"Point"}
}