{
  "type": "Feature",
  "properties": {
    "iso:country":"US",
    "sg:address":"3100 Terrace St",
    "sg:city":"Kansas City",
    "sg:classifiers":[
        {
            "category":"Wholesale",
            "subcategory":"Machinery & Supplies",
            "type":"Manufacturing & Wholesale Goods"
        }
    ],
    "sg:phone":"+1 816 531 5700",
    "sg:postcode":"64111",
    "sg:province":"MO",
    "sg:tags":[
        "industrial"
    ],
    "wof:name":"Fastenal Company",
    "wof:placetype":"venue"
},
  "geometry": {"coordinates":[-94.601629,39.067724],"type":"Point"}
}