{
  "type": "Feature",
  "properties": {
    "iso:country":"US",
    "sg:address":"14226 Ladue Rd",
    "sg:city":"Chesterfield",
    "sg:classifiers":[
        {
            "category":"Manufacturing",
            "subcategory":"Toys & Sporting Goods",
            "type":"Manufacturing & Wholesale Goods"
        },
        {
            "category":"Shopping",
            "subcategory":"Bicycles & Sporting Goods",
            "type":"Retail Goods"
        }
    ],
    "sg:phone":"+1 314 469 8636",
    "sg:postcode":"63017",
    "sg:province":"MO",
    "sg:tags":[
        "goods-wholesale",
        "manufacturer"
    ],
    "sg:website":"http://www.trackvendor.com",
    "wof:name":"Esses Pen & Pencil Discount & Imprinters",
    "wof:placetype":"venue"
},
  "geometry": {"coordinates":[-90.51759800000001,38.664679],"type":"Point"}
}