{
  "type": "Feature",
  "properties": {
    "iso:country":"US",
    "sg:address":"906 E North Ave Space G",
    "sg:city":"Belton",
    "sg:classifiers":[
        {
            "category":"Utilities",
            "subcategory":"Mobile Phone",
            "type":"Services"
        },
        {
            "category":"Shopping",
            "subcategory":"Mobile Phones",
            "type":"Retail Goods"
        }
    ],
    "sg:phone":"+1 816 331 0972",
    "sg:postcode":"64012",
    "sg:province":"MO",
    "sg:tags":[
        "supply",
        "communication",
        "telephone",
        "wireless",
        "equipment",
        "cellular"
    ],
    "sg:website":"http://www.sprint.com",
    "wof:name":"Sprint Store",
    "wof:placetype":"venue"
},
  "geometry": {"coordinates":[-94.518955,38.813923],"type":"Point"}
}