{
  "type": "Feature",
  "properties": {
    "iso:country":"US",
    "sg:address":"8717 Big Bend Blvd",
    "sg:city":"St Louis",
    "sg:classifiers":[
        {
            "category":"Professional",
            "subcategory":"Accounting & Tax Preparation",
            "type":"Services"
        }
    ],
    "sg:phone":"+1 314 962 0404",
    "sg:postcode":"63119",
    "sg:province":"MO",
    "sg:tags":[
        "accountant"
    ],
    "wof:name":"J J Schorfheide CPA",
    "wof:placetype":"venue"
},
  "geometry": {"coordinates":[-90.35936599999999,38.582527],"type":"Point"}
}