{
  "type": "Feature",
  "properties": {
    "iso:country":"US",
    "sg:address":"919 W Harmony St",
    "sg:city":"Neosho",
    "sg:classifiers":[
        {
            "category":"Shopping",
            "subcategory":"Department Store",
            "type":"Retail Goods"
        },
        {
            "category":"Home & Garden",
            "subcategory":"Household Appliances",
            "type":"Retail Goods"
        }
    ],
    "sg:phone":"+1 417 659 2000",
    "sg:postcode":"64850",
    "sg:province":"MO",
    "sg:tags":[
        "major"
    ],
    "wof:name":"Sears Hometown Store",
    "wof:placetype":"venue"
},
  "geometry": {"coordinates":[-94.381963,36.868993],"type":"Point"}
}