{
  "type": "Feature",
  "properties": {
    "iso:country":"US",
    "sg:address":"410 S Front St",
    "sg:city":"Orrick",
    "sg:classifiers":[
        {
            "category":"Professional",
            "type":"Services"
        }
    ],
    "sg:phone":"+1 816 496 3336",
    "sg:postcode":"64077",
    "sg:province":"MO",
    "sg:tags":[
        "establishment"
    ],
    "wof:name":"Gts Co",
    "wof:placetype":"venue"
},
  "geometry": {"coordinates":[-94.119049,39.212014],"type":"Point"}
}