{
  "type": "Feature",
  "properties": {
    "iso:country":"US",
    "sg:address":"4201 E 12 St",
    "sg:city":"Kansas City",
    "sg:classifiers":[
        {
            "category":"Restaurant",
            "type":"Food & Drink"
        }
    ],
    "sg:phone":"+1 816 231 4336",
    "sg:postcode":"64127",
    "sg:province":"MO",
    "sg:tags":[
        "eating"
    ],
    "wof:name":"Back Street Rest & Lounge",
    "wof:placetype":"venue"
},
  "geometry": {"coordinates":[-94.532538,39.098168],"type":"Point"}
}