{
  "type": "Feature",
  "properties": {
    "iso:country":"US",
    "sg:address":"2621 Benton Blvd",
    "sg:city":"Kansas City",
    "sg:classifiers":[
        {
            "category":"Organizations",
            "subcategory":"Religious Organization",
            "type":"Services"
        }
    ],
    "sg:phone":"+1 816 861 6612",
    "sg:postcode":"64127",
    "sg:province":"MO",
    "sg:tags":[
        "church"
    ],
    "wof:name":"Highland Baptist Church",
    "wof:placetype":"venue"
},
  "geometry": {"coordinates":[-94.548901,39.077338],"type":"Point"}
}