{
  "type": "Feature",
  "properties": {
    "iso:country":"US",
    "sg:address":"126 Westwoods Dr",
    "sg:city":"Liberty",
    "sg:classifiers":[
        {
            "category":"Banks & Credit Unions",
            "subcategory":"Investment Brokerage",
            "type":"Services"
        }
    ],
    "sg:phone":"+1 816 781 8782",
    "sg:postcode":"64068",
    "sg:province":"MO",
    "sg:tags":[
        "consultant",
        "planning",
        "financial"
    ],
    "wof:name":"Thomann Financial Svc Inc",
    "wof:placetype":"venue"
},
  "geometry": {"coordinates":[-94.436593,39.24783],"type":"Point"}
}