{
  "type": "Feature",
  "properties": {
    "iso:country":"US",
    "sg:address":"301 Clark St",
    "sg:city":"Richmond",
    "sg:classifiers":[
        {
            "category":"Professional",
            "subcategory":"Business Services",
            "type":"Services"
        }
    ],
    "sg:phone":"+1 816 517 3213",
    "sg:postcode":"64085",
    "sg:province":"MO",
    "sg:tags":[
        "appraiser"
    ],
    "wof:name":"Rippy Appraisal Co",
    "wof:placetype":"venue"
},
  "geometry": {"coordinates":[-93.96160999999999,39.276403],"type":"Point"}
}