{
  "type": "Feature",
  "properties": {
    "iso:country":"US",
    "sg:address":"2016 S Big Bend Blvd",
    "sg:city":"Saint Louis",
    "sg:classifiers":[
        {
            "category":"Professional",
            "subcategory":"Lawyer & Legal Services",
            "type":"Services"
        }
    ],
    "sg:phone":"+1 314 995 3936",
    "sg:postcode":"63117",
    "sg:province":"MO",
    "wof:name":"Rose Ann Feldman",
    "wof:placetype":"venue"
},
  "geometry": {"coordinates":[-90.321089,38.621728],"type":"Point"}
}