{
  "type": "Feature",
  "properties": {
    "iso:country":"US",
    "sg:address":"1246 Main St",
    "sg:city":"Imperial",
    "sg:classifiers":[
        {
            "category":"Restaurant",
            "type":"Food & Drink"
        }
    ],
    "sg:menulink":"http://www.allmenus.com/mo/imperial/122187-quiznos-sub/menu/",
    "sg:phone":"+1 636 464 7827",
    "sg:postcode":"63052",
    "sg:province":"MO",
    "sg:tags":[
        "wrap",
        "american",
        "sandwich"
    ],
    "wof:name":"Quiznos Sub",
    "wof:placetype":"venue"
},
  "geometry": {"coordinates":[-90.3873,38.369609],"type":"Point"}
}