{
  "type": "Feature",
  "properties": {
    "iso:country":"US",
    "sg:address":"35 Lake Rd",
    "sg:city":"Labadie",
    "sg:classifiers":[
        {
            "category":"Manufacturing",
            "subcategory":"Buildings",
            "type":"Manufacturing & Wholesale Goods"
        },
        {
            "category":"Building & Trades",
            "subcategory":"Construction",
            "type":"Services"
        }
    ],
    "sg:phone":"+1 636 742 3387",
    "sg:postcode":"63055",
    "sg:province":"MO",
    "sg:tags":[
        "bathroom",
        "altering",
        "builder",
        "carpenter",
        "contractor",
        "excavation",
        "planning",
        "home",
        "remodeling",
        "kitchen"
    ],
    "wof:name":"Fitzpatrick Construction Co., Inc.",
    "wof:placetype":"venue"
},
  "geometry": {"coordinates":[-90.85084500000001,38.518093],"type":"Point"}
}