{
  "type": "Feature",
  "properties": {
    "iso:country":"US",
    "sg:address":"1120 S Morley St",
    "sg:city":"Moberly",
    "sg:classifiers":[
        {
            "category":"Retail",
            "subcategory":"Auto Repair",
            "type":"Services"
        }
    ],
    "sg:phone":"+1 660 263 7221",
    "sg:postcode":"65270",
    "sg:province":"MO",
    "sg:tags":[
        "automobile",
        "used",
        "general"
    ],
    "wof:name":"Performance Center",
    "wof:placetype":"venue"
},
  "geometry": {"coordinates":[-92.433863,39.407842],"type":"Point"}
}