{
  "type": "Feature",
  "properties": {
    "iso:country":"US",
    "sg:address":"1001 High St",
    "sg:city":"New Haven",
    "sg:classifiers":[
        {
            "category":"Professional",
            "type":"Services"
        }
    ],
    "sg:phone":"+1 573 237 2688",
    "sg:postcode":"63068",
    "sg:province":"MO",
    "sg:tags":[
        "establishment"
    ],
    "wof:name":"Zork's Nest",
    "wof:placetype":"venue"
},
  "geometry": {"coordinates":[-91.218311,38.615898],"type":"Point"}
}