{
  "type": "Feature",
  "properties": {
    "iso:country":"US",
    "sg:address":"11601 Co Rd 4031",
    "sg:city":"Holts Summit",
    "sg:classifiers":[
        {
            "category":"Building & Trades",
            "subcategory":"Construction",
            "type":"Services"
        }
    ],
    "sg:phone":"+1 573 896 4879",
    "sg:postcode":"65043",
    "sg:province":"MO",
    "sg:tags":[
        "contractor"
    ],
    "wof:name":"Mid Missouri Roofing & Glass",
    "wof:placetype":"venue"
},
  "geometry": {"coordinates":[-92.09541400000001,38.638979],"type":"Point"}
}