{
  "type": "Feature",
  "properties": {
    "iso:country":"US",
    "sg:address":"601 E 5th St",
    "sg:city":"Rolla",
    "sg:classifiers":[
        {
            "category":"Social Services",
            "subcategory":"Child Care",
            "type":"Services"
        }
    ],
    "sg:phone":"+1 573 364 0788",
    "sg:postcode":"65401",
    "sg:province":"MO",
    "sg:tags":[
        "center",
        "day"
    ],
    "wof:name":"Miss Jeannies Child Care Cttg",
    "wof:placetype":"venue"
},
  "geometry": {"coordinates":[-91.76411299999999,37.947789],"type":"Point"}
}