{
  "type": "Feature",
  "properties": {
    "iso:country":"US",
    "sg:address":"1464 Hoelzer Ct",
    "sg:city":"Pacific",
    "sg:classifiers":[
        {
            "category":"Wholesale",
            "subcategory":"Machinery & Supplies",
            "type":"Manufacturing & Wholesale Goods"
        }
    ],
    "sg:phone":"+1 636 271 6400",
    "sg:postcode":"63069",
    "sg:province":"MO",
    "sg:tags":[
        "valve"
    ],
    "sg:website":"http://www.winter-technologies.com",
    "wof:name":"Wintech",
    "wof:placetype":"venue"
},
  "geometry": {"coordinates":[-90.757953,38.459577],"type":"Point"}
}