{
  "type": "Feature",
  "properties": {
    "iso:country":"US",
    "sg:address":"1920 Swift Ave",
    "sg:city":"Kansas City",
    "sg:classifiers":[
        {
            "category":"Banks & Credit Unions",
            "subcategory":"Bank",
            "type":"Services"
        }
    ],
    "sg:phone":"+1 816 471 7787",
    "sg:postcode":"64116",
    "sg:province":"MO",
    "sg:tags":[
        "loan"
    ],
    "wof:name":"Trans Credit",
    "wof:placetype":"venue"
},
  "geometry": {"coordinates":[-94.577366,39.14252],"type":"Point"}
}