{
  "type": "Feature",
  "properties": {
    "iso:country":"US",
    "sg:address":"2208 Holly Ave",
    "sg:city":"Kennett",
    "sg:classifiers":[
        {
            "category":"Building & Trades",
            "subcategory":"Construction",
            "type":"Services"
        }
    ],
    "sg:phone":"+1 573 785 7993",
    "sg:postcode":"63857",
    "sg:province":"MO",
    "sg:tags":[
        "gen",
        "contract"
    ],
    "wof:name":"Norton C E Gen Contractor",
    "wof:placetype":"venue"
},
  "geometry": {"coordinates":[-90.024852,36.244462],"type":"Point"}
}