{
  "type": "Feature",
  "properties": {
    "iso:country":"US",
    "sg:address":"2909 N 23rd St",
    "sg:city":"Ozark",
    "sg:classifiers":[
        {
            "category":"Bars & Pubs",
            "type":"Food & Drink"
        }
    ],
    "sg:phone":"+1 417 581 0520",
    "sg:postcode":"65721",
    "sg:province":"MO",
    "sg:tags":[
        "brew"
    ],
    "wof:name":"Cartoon's Oyster Bar & Grill Inc",
    "wof:placetype":"venue"
},
  "geometry": {"coordinates":[-93.23338800000001,37.078936],"type":"Point"}
}