{
  "type": "Feature",
  "properties": {
    "iso:country":"US",
    "sg:address":"2398 State Hwy 53",
    "sg:city":"Poplar Bluff",
    "sg:classifiers":[
        {
            "category":"Manufacturing",
            "subcategory":"Metals",
            "type":"Manufacturing & Wholesale Goods"
        }
    ],
    "sg:phone":"+1 573 686 3318",
    "sg:postcode":"63901",
    "sg:province":"MO",
    "sg:tags":[
        "tool"
    ],
    "sg:website":"www.foxymfg.com",
    "wof:name":"Foxy Manufacturing",
    "wof:placetype":"venue"
},
  "geometry": {"coordinates":[-90.379378,36.719323],"type":"Point"}
}