{
  "type": "Feature",
  "properties": {
    "iso:country":"US",
    "sg:address":"102 NE Crescent St",
    "sg:city":"Lees Summit",
    "sg:classifiers":[
        {
            "category":"Banks & Credit Unions",
            "subcategory":"Bank",
            "type":"Services"
        }
    ],
    "sg:phone":"+1 816 524 3338",
    "sg:postcode":"64086",
    "sg:province":"MO",
    "sg:tags":[
        "savings",
        "loan",
        "chartered",
        "state"
    ],
    "wof:name":"FSA Calling Cards",
    "wof:placetype":"venue"
},
  "geometry": {"coordinates":[-94.332202,38.918942],"type":"Point"}
}