{
  "type": "Feature",
  "properties": {
    "iso:country":"US",
    "sg:address":"1200 S Lindbergh Blvd",
    "sg:city":"Saint Louis",
    "sg:classifiers":[
        {
            "category":"Social Services",
            "type":"Services"
        }
    ],
    "sg:phone":"+1 314 432 7927",
    "sg:postcode":"63131",
    "sg:province":"MO",
    "wof:name":"Epworth Counseling Services",
    "wof:placetype":"venue"
},
  "geometry": {"coordinates":[-90.40566200000001,38.636782],"type":"Point"}
}