{
  "type": "Feature",
  "properties": {
    "iso:country":"US",
    "sg:address":"15816 Kersten Ridge Ct",
    "sg:city":"Chesterfield",
    "sg:classifiers":[
        {
            "category":"Communications",
            "type":"Services"
        }
    ],
    "sg:phone":"+1 636 537 3921",
    "sg:postcode":"63017",
    "sg:province":"MO",
    "wof:name":"Brunner Communication",
    "wof:placetype":"venue"
},
  "geometry": {"coordinates":[-90.563301,38.630755],"type":"Point"}
}