{
  "type": "Feature",
  "properties": {
    "iso:country":"US",
    "sg:address":"4132 N US Hwy 67",
    "sg:city":"Florissant",
    "sg:classifiers":[
        {
            "category":"Autos & Motor Vehicles",
            "subcategory":"Fuel & Gas Station",
            "type":"Retail Goods"
        }
    ],
    "sg:phone":"+1 314 741 4844",
    "sg:postcode":"63034",
    "sg:province":"MO",
    "sg:tags":[
        "station",
        "gasoline",
        "oil"
    ],
    "wof:name":"Mobil Mart",
    "wof:placetype":"venue"
},
  "geometry": {"coordinates":[-90.28011100000001,38.815976],"type":"Point"}
}