{
  "type": "Feature",
  "properties": {
    "iso:country":"US",
    "sg:address":"8359 E State Hwy 76",
    "sg:city":"Kirbyville",
    "sg:classifiers":[
        {
            "category":"Wholesale",
            "subcategory":"Plants",
            "type":"Manufacturing & Wholesale Goods"
        }
    ],
    "sg:phone":"+1 417 546 3051",
    "sg:postcode":"65679",
    "sg:province":"MO",
    "sg:tags":[
        "ornamental",
        "nursery",
        "supply"
    ],
    "wof:name":"Stecz Gardens",
    "wof:placetype":"venue"
},
  "geometry": {"coordinates":[-93.124465,36.631443],"type":"Point"}
}