{
  "type": "Feature",
  "properties": {
    "addr:full":"412 W Buchanan St Kirksville MO 63501",
    "addr:housenumber":"412",
    "addr:postcode":"63501",
    "addr:street":"W Buchanan St",
    "iso:country":"US",
    "sg:address":"412 W Buchanan St",
    "sg:city":"Kirksville",
    "sg:classifiers":[
        {
            "category":"Organizations",
            "subcategory":"Community Association",
            "type":"Services"
        }
    ],
    "sg:phone":"+1 660 665 9400",
    "sg:postcode":"63501",
    "sg:province":"MO",
    "wof:name":"Independent Order of Odd",
    "wof:placetype":"venue"
},
  "geometry": {"coordinates":[-92.58752200000001,40.198108],"type":"Point"}
}