{
  "type": "Feature",
  "properties": {
    "iso:country":"US",
    "sg:address":"11321 Revere Ln",
    "sg:city":"St Louis",
    "sg:classifiers":[
        {
            "category":"Building & Trades",
            "subcategory":"Plumbing",
            "type":"Services"
        }
    ],
    "sg:phone":"+1 314 894 1535",
    "sg:postcode":"63128",
    "sg:province":"MO",
    "sg:tags":[
        "contractor",
        "mechanical"
    ],
    "wof:name":"Jobaire Inc",
    "wof:placetype":"venue"
},
  "geometry": {"coordinates":[-90.346597,38.520956],"type":"Point"}
}