{
  "type": "Feature",
  "properties": {
    "iso:country":"US",
    "sg:address":"198 Avery Ln",
    "sg:city":"Troy",
    "sg:classifiers":[
        {
            "category":"Social Services",
            "type":"Services"
        }
    ],
    "sg:phone":"+1 636 528 3818",
    "sg:postcode":"63379",
    "sg:province":"MO",
    "sg:tags":[
        "individual",
        "family"
    ],
    "wof:name":"MO Div of Youth Services",
    "wof:placetype":"venue"
},
  "geometry": {"coordinates":[-90.913167,39.013261],"type":"Point"}
}