{
  "type": "Feature",
  "properties": {
    "iso:country":"US",
    "sg:address":"206 E Mill St",
    "sg:city":"Butler",
    "sg:classifiers":[
        {
            "category":"Recreation",
            "type":"Entertainment"
        }
    ],
    "sg:phone":"+1 660 200 2062",
    "sg:postcode":"64730",
    "sg:province":"MO",
    "sg:tags":[
        "parks"
    ],
    "wof:name":"City Of Butler Parks Dept",
    "wof:placetype":"venue"
},
  "geometry": {"coordinates":[-94.32764899999999,38.263725],"type":"Point"}
}