{
  "type": "Feature",
  "properties": {
    "iso:country":"US",
    "sg:address":"6233 Chatham Ave",
    "sg:city":"St Louis",
    "sg:classifiers":[
        {
            "category":"Organizations",
            "subcategory":"Religious Organization",
            "type":"Services"
        }
    ],
    "sg:phone":"+1 314 382 6469",
    "sg:postcode":"63133",
    "sg:province":"MO",
    "sg:tags":[
        "church"
    ],
    "wof:name":"New Emmanuel Missionary Bapt",
    "wof:placetype":"venue"
},
  "geometry": {"coordinates":[-90.29259999999999,38.673514],"type":"Point"}
}