{
  "type": "Feature",
  "properties": {
    "addr:full":"1215 N Green St Kirksville MO 63501",
    "addr:housenumber":"1215",
    "addr:postcode":"63501",
    "addr:street":"N Green St",
    "iso:country":"US",
    "sg:address":"1215 N Green St",
    "sg:city":"Kirksville",
    "sg:classifiers":[
        {
            "category":"Retail",
            "subcategory":"Auto Repair",
            "type":"Services"
        }
    ],
    "sg:phone":"+1 660 665 6068",
    "sg:postcode":"63501",
    "sg:province":"MO",
    "sg:tags":[
        "automobile",
        "lubrication",
        "automotive"
    ],
    "wof:name":"Grease Lightning",
    "wof:placetype":"venue"
},
  "geometry": {"coordinates":[-92.581507,40.204023],"type":"Point"}
}