{
  "type": "Feature",
  "properties": {
    "iso:country":"US",
    "sg:address":"691 Trade Center Blvd",
    "sg:city":"Chesterfield",
    "sg:classifiers":[
        {
            "category":"Insurance",
            "subcategory":"Insurance Agent",
            "type":"Services"
        }
    ],
    "sg:phone":"+1 636 519 0422",
    "sg:postcode":"63005",
    "sg:province":"MO",
    "wof:name":"Mortgage Guaranty Ins Corp",
    "wof:placetype":"venue"
},
  "geometry": {"coordinates":[-90.62494,38.668113],"type":"Point"}
}