{
  "type": "Feature",
  "properties": {
    "iso:country":"US",
    "sg:address":"8152 N Congress Ave",
    "sg:city":"Kansas City",
    "sg:classifiers":[
        {
            "category":"Recreation",
            "type":"Entertainment"
        }
    ],
    "sg:phone":"+1 816 741 7963",
    "sg:postcode":"64152",
    "sg:province":"MO",
    "sg:tags":[
        "pool",
        "swimming"
    ],
    "wof:name":"Park Hill Aquatic Center",
    "wof:placetype":"venue"
},
  "geometry": {"coordinates":[-94.668414,39.241234],"type":"Point"}
}