{
  "type": "Feature",
  "properties": {
    "iso:country":"US",
    "sg:address":"117 Walnut St",
    "sg:city":"Slater",
    "sg:classifiers":[
        {
            "category":"Government",
            "subcategory":"Fire Station",
            "type":"Public Place"
        }
    ],
    "sg:phone":"+1 660 529 2243",
    "sg:postcode":"65349",
    "sg:province":"MO",
    "sg:tags":[
        "department"
    ],
    "wof:name":"Slater City Fire Dept",
    "wof:placetype":"venue"
},
  "geometry": {"coordinates":[-93.058931,39.219725],"type":"Point"}
}