{
  "type": "Feature",
  "properties": {
    "iso:country":"US",
    "sg:address":"10 Royallridge Ct",
    "sg:city":"O Fallon",
    "sg:classifiers":[
        {
            "category":"Building & Trades",
            "subcategory":"Construction",
            "type":"Services"
        }
    ],
    "sg:phone":"+1 636 980 3270",
    "sg:postcode":"63368",
    "sg:province":"MO",
    "sg:tags":[
        "rubber",
        "product",
        "contractor",
        "fabricated",
        "mfg"
    ],
    "wof:name":"Rock Doctors Inc",
    "wof:placetype":"venue"
},
  "geometry": {"coordinates":[-90.701098,38.765],"type":"Point"}
}