{
  "type": "Feature",
  "properties": {
    "iso:country":"US",
    "sg:address":"225 Tina St",
    "sg:city":"Hollister",
    "sg:classifiers":[
        {
            "category":"Autos & Motor Vehicles",
            "subcategory":"Auto Supplies",
            "type":"Retail Goods"
        },
        {
            "category":"Wholesale",
            "subcategory":"Electrical",
            "type":"Manufacturing & Wholesale Goods"
        }
    ],
    "sg:phone":"+1 417 332 1897",
    "sg:postcode":"65672",
    "sg:province":"MO",
    "sg:tags":[
        "battery",
        "automobile",
        "part",
        "accessory"
    ],
    "wof:name":"O'reilly Auto Parts",
    "wof:placetype":"venue"
},
  "geometry": {"coordinates":[-93.302152,36.574346],"type":"Point"}
}