{
  "type": "Feature",
  "properties": {
    "iso:country":"US",
    "sg:address":"407 N High St",
    "sg:city":"California",
    "sg:classifiers":[
        {
            "category":"Real Estate",
            "subcategory":"Real Estate Services",
            "type":"Services"
        }
    ],
    "sg:phone":"+1 573 796 2412",
    "sg:postcode":"65018",
    "sg:province":"MO",
    "sg:tags":[
        "abstract",
        "title"
    ],
    "wof:name":"Missouri Abstract & Title Co",
    "wof:placetype":"venue"
},
  "geometry": {"coordinates":[-92.565399,38.63611],"type":"Point"}
}