{
  "type": "Feature",
  "properties": {
    "iso:country":"US",
    "sg:address":"613 Maran Dr",
    "sg:city":"Saint Charles",
    "sg:classifiers":[
        {
            "category":"Professional",
            "subcategory":"Business Services",
            "type":"Services"
        }
    ],
    "sg:phone":"+1 636 723 0830",
    "sg:postcode":"63301",
    "sg:province":"MO",
    "wof:name":"David Thornhill",
    "wof:placetype":"venue"
},
  "geometry": {"coordinates":[-90.517839,38.794347],"type":"Point"}
}