{
  "type": "Feature",
  "properties": {
    "iso:country":"US",
    "sg:address":"3234 Roberts St",
    "sg:city":"Kansas City",
    "sg:classifiers":[
        {
            "category":"Professional",
            "type":"Services"
        }
    ],
    "sg:phone":"+1 816 920 6846",
    "sg:postcode":"64124",
    "sg:province":"MO",
    "wof:name":"Rich Shepard",
    "wof:placetype":"venue"
},
  "geometry": {"coordinates":[-94.54254899999999,39.107014],"type":"Point"}
}