{
  "type": "Feature",
  "properties": {
    "iso:country":"US",
    "sg:address":"27 Green Valley Dr",
    "sg:city":"Fenton",
    "sg:classifiers":[
        {
            "category":"Building & Trades",
            "subcategory":"Construction",
            "type":"Services"
        }
    ],
    "sg:phone":"+1 636 343 7943",
    "sg:postcode":"63026",
    "sg:province":"MO",
    "sg:tags":[
        "house",
        "consulting",
        "management"
    ],
    "wof:name":"Texas Refineries Inc",
    "wof:placetype":"venue"
},
  "geometry": {"coordinates":[-90.477183,38.494366],"type":"Point"}
}