{
  "type": "Feature",
  "properties": {
    "iso:country":"US",
    "sg:address":"1083 Ozark Care Dr",
    "sg:city":"Osage Beach",
    "sg:classifiers":[
        {
            "category":"Health Services",
            "subcategory":"Nursing And Care Facility",
            "type":"Services"
        }
    ],
    "sg:phone":"+1 573 348 1711",
    "sg:postcode":"65065",
    "sg:province":"MO",
    "sg:tags":[
        "home",
        "convalescent"
    ],
    "wof:name":"Ozark Care Ctr",
    "wof:placetype":"venue"
},
  "geometry": {"coordinates":[-92.684901,38.119325],"type":"Point"}
}