{
  "type": "Feature",
  "properties": {
    "iso:country":"US",
    "sg:address":"2023 Seven Pines Dr",
    "sg:city":"St Louis",
    "sg:classifiers":[
        {
            "category":"Shopping",
            "type":"Retail Goods"
        },
        {
            "category":"Communications",
            "type":"Services"
        }
    ],
    "sg:phone":"+1 314 275 8049",
    "sg:postcode":"63146",
    "sg:province":"MO",
    "sg:tags":[
        "carrier",
        "merchandise"
    ],
    "sg:website":"www.signaltel.com",
    "wof:name":"Signal Telephone",
    "wof:placetype":"venue"
},
  "geometry": {"coordinates":[-90.47683499999999,38.70007],"type":"Point"}
}