{
  "type": "Feature",
  "properties": {
    "iso:country":"US",
    "sg:address":"1450 N 13th St",
    "sg:city":"Saint Louis",
    "sg:classifiers":[
        {
            "category":"Wholesale",
            "subcategory":"Groceries",
            "type":"Manufacturing & Wholesale Goods"
        }
    ],
    "sg:phone":"+1 314 621 1151",
    "sg:postcode":"63106",
    "sg:province":"MO",
    "sg:tags":[
        "eating",
        "general"
    ],
    "wof:name":"Gli Food Services",
    "wof:placetype":"venue"
},
  "geometry": {"coordinates":[-90.194323,38.639999],"type":"Point"}
}