{
  "type": "Feature",
  "properties": {
    "iso:country":"US",
    "sg:address":"1445 NW 800 Rd",
    "sg:city":"Urich",
    "sg:classifiers":[
        {
            "category":"Farming",
            "subcategory":"Livestock Farm",
            "type":"Manufacturing & Wholesale Goods"
        }
    ],
    "sg:phone":"+1 660 638 4551",
    "sg:postcode":"64788",
    "sg:province":"MO",
    "sg:tags":[
        "beef",
        "feedlot",
        "cattle"
    ],
    "wof:name":"Melvin Browning",
    "wof:placetype":"venue"
},
  "geometry": {"coordinates":[-94.017234,38.479417],"type":"Point"}
}