{
  "type": "Feature",
  "properties": {
    "iso:country":"US",
    "sg:address":"7 Ponca Trl",
    "sg:city":"Saint Louis",
    "sg:classifiers":[
        {
            "category":"Professional",
            "subcategory":"Computer Services",
            "type":"Services"
        }
    ],
    "sg:phone":"+1 314 835 1145",
    "sg:postcode":"63122",
    "sg:province":"MO",
    "sg:tags":[
        "consulting",
        "it"
    ],
    "wof:name":"Quadrint Inc",
    "wof:placetype":"venue"
},
  "geometry": {"coordinates":[-90.446867,38.56632],"type":"Point"}
}