{
  "type": "Feature",
  "properties": {
    "iso:country":"US",
    "sg:address":"6200 NW 70 St",
    "sg:city":"Kansas City",
    "sg:classifiers":[
        {
            "category":"Professional",
            "subcategory":"Management & Consulting",
            "type":"Services"
        }
    ],
    "sg:phone":"+1 816 746 3854",
    "sg:postcode":"64151",
    "sg:province":"MO",
    "sg:tags":[
        "business"
    ],
    "wof:name":"Tristan Consulting",
    "wof:placetype":"venue"
},
  "geometry": {"coordinates":[-94.65105699999999,39.221137],"type":"Point"}
}