{
  "type": "Feature",
  "properties": {
    "iso:country":"US",
    "sg:address":"545 Branson Landing Blvd",
    "sg:city":"Branson",
    "sg:classifiers":[
        {
            "category":"Health Services",
            "subcategory":"Doctor",
            "type":"Services"
        }
    ],
    "sg:phone":"+1 417 348 8990",
    "sg:postcode":"65616",
    "sg:province":"MO",
    "sg:tags":[
        "physician",
        "reproductive",
        "endocrinology",
        "surgeons",
        "surgeon",
        "metabolism",
        "diabetes"
    ],
    "wof:name":"Skaggs Diabetes Endocrinology Care",
    "wof:placetype":"venue"
},
  "geometry": {"coordinates":[-93.21392299999999,36.640982],"type":"Point"}
}