{
  "type": "Feature",
  "properties": {
    "iso:country":"US",
    "sg:address":"305 N Sturgeon St",
    "sg:city":"Montgomery City",
    "sg:classifiers":[
        {
            "category":"Manufacturing",
            "subcategory":"Food",
            "type":"Manufacturing & Wholesale Goods"
        },
        {
            "category":"Food & Beverages",
            "subcategory":"Bakery",
            "type":"Retail Goods"
        }
    ],
    "sg:phone":"+1 573 564 2573",
    "sg:postcode":"63361",
    "sg:province":"MO",
    "sg:tags":[
        "baker",
        "product",
        "mfg"
    ],
    "wof:name":"Sugar & Spice Laura's Delight",
    "wof:placetype":"venue"
},
  "geometry": {"coordinates":[-91.506516,38.97906],"type":"Point"}
}