{
  "type": "Feature",
  "properties": {
    "iso:country":"US",
    "sg:address":"2741 Goose Landing Dr",
    "sg:city":"Pacific",
    "sg:classifiers":[
        {
            "category":"Real Estate",
            "subcategory":"Developer",
            "type":"Services"
        }
    ],
    "sg:phone":"+1 636 257 6612",
    "sg:postcode":"63069",
    "sg:province":"MO",
    "wof:name":"Bhat Tif Developer, Inc.",
    "wof:placetype":"venue"
},
  "geometry": {"coordinates":[-90.725805,38.45921],"type":"Point"}
}