{
  "type": "Feature",
  "properties": {
    "iso:country":"US",
    "sg:address":"620 W Brook St",
    "sg:city":"Neosho",
    "sg:classifiers":[
        {
            "category":"Retail",
            "subcategory":"Car Wash",
            "type":"Services"
        }
    ],
    "sg:phone":"+1 417 451 1427",
    "sg:postcode":"64850",
    "sg:province":"MO",
    "wof:name":"Spot-Not",
    "wof:placetype":"venue"
},
  "geometry": {"coordinates":[-94.37714,36.871954],"type":"Point"}
}