{
  "type": "Feature",
  "properties": {
    "iso:country":"US",
    "sg:address":"1011 W Jackson Blvd",
    "sg:city":"Jackson",
    "sg:classifiers":[
        {
            "category":"Organizations",
            "subcategory":"Community Association",
            "type":"Services"
        }
    ],
    "sg:phone":"+1 573 243 4429",
    "sg:postcode":"63755",
    "sg:province":"MO",
    "wof:name":"Veterans of Foreign Wars",
    "wof:placetype":"venue"
},
  "geometry": {"coordinates":[-89.67844700000001,37.380032],"type":"Point"}
}