{
  "type": "Feature",
  "properties": {
    "iso:country":"US",
    "sg:address":"1166 Jeffries Rd",
    "sg:city":"Osage Beach",
    "sg:classifiers":[
        {
            "category":"Travel",
            "subcategory":"Hotels & Motels",
            "type":"Entertainment"
        }
    ],
    "sg:phone":"+1 573 348 2929",
    "sg:postcode":"65065",
    "sg:province":"MO",
    "sg:tags":[
        "operation"
    ],
    "wof:name":"Point Breeze Resort",
    "wof:placetype":"venue"
},
  "geometry": {"coordinates":[-92.650317,38.137314],"type":"Point"}
}