{
  "type": "Feature",
  "properties": {
    "iso:country":"US",
    "sg:address":"10675 Hwy 100",
    "sg:city":"Berger",
    "sg:classifiers":[
        {
            "category":"Building & Trades",
            "subcategory":"Electrical",
            "type":"Services"
        }
    ],
    "sg:phone":"+1 573 237 2630",
    "sg:postcode":"63014",
    "sg:province":"MO",
    "sg:tags":[
        "electrical",
        "contractor"
    ],
    "wof:name":"Kase Electric",
    "wof:placetype":"venue"
},
  "geometry": {"coordinates":[-91.292857,38.61625],"type":"Point"}
}