{
  "type": "Feature",
  "properties": {
    "iso:country":"US",
    "sg:address":"4702 Mattis Rd",
    "sg:city":"St Louis",
    "sg:classifiers":[
        {
            "category":"Banks & Credit Unions",
            "subcategory":"Bank",
            "type":"Services"
        }
    ],
    "sg:phone":"+1 314 487 5628",
    "sg:postcode":"63128",
    "sg:province":"MO",
    "sg:tags":[
        "state"
    ],
    "sg:website":"www.southpointecu.com",
    "wof:name":"Southpointe Credit Union",
    "wof:placetype":"venue"
},
  "geometry": {"coordinates":[-90.361166,38.500451],"type":"Point"}
}