{
  "type": "Feature",
  "properties": {
    "iso:country":"US",
    "sg:address":"714 Greenbriar Ter",
    "sg:city":"Saint Joseph",
    "sg:classifiers":[
        {
            "category":"Farming",
            "subcategory":"Livestock Farm",
            "type":"Manufacturing & Wholesale Goods"
        }
    ],
    "sg:phone":"+1 816 233 6462",
    "sg:postcode":"64506",
    "sg:province":"MO",
    "sg:tags":[
        "beef",
        "feedlot",
        "cattle"
    ],
    "wof:name":"P & J Cattle Company Inc",
    "wof:placetype":"venue"
},
  "geometry": {"coordinates":[-94.773342,39.77318],"type":"Point"}
}