{
  "type": "Feature",
  "properties": {
    "iso:country":"US",
    "sg:address":"6401 Scanlan Ave",
    "sg:city":"St Louis",
    "sg:classifiers":[
        {
            "category":"Organizations",
            "subcategory":"Religious Organization",
            "type":"Services"
        }
    ],
    "sg:phone":"+1 314 647 4567",
    "sg:postcode":"63139",
    "sg:province":"MO",
    "sg:tags":[
        "church"
    ],
    "sg:website":"www.southwestbaptistchurch.org",
    "wof:name":"Southwest Baptist Church Child",
    "wof:placetype":"venue"
},
  "geometry": {"coordinates":[-90.299059,38.605325],"type":"Point"}
}