{
  "type": "Feature",
  "properties": {
    "iso:country":"US",
    "sg:address":"2900 N Buckner Tarsney Rd",
    "sg:city":"Buckner",
    "sg:classifiers":[
        {
            "category":"Farming",
            "subcategory":"Nursery",
            "type":"Manufacturing & Wholesale Goods"
        }
    ],
    "sg:phone":"+1 816 650 5581",
    "sg:postcode":"64016",
    "sg:province":"MO",
    "sg:tags":[
        "greenhouse"
    ],
    "wof:name":"Frye Greenhouse & Country Mark",
    "wof:placetype":"venue"
},
  "geometry": {"coordinates":[-94.196291,39.147966],"type":"Point"}
}