{
  "type": "Feature",
  "properties": {
    "iso:country":"US",
    "sg:address":"6900 Stilwell Ave",
    "sg:city":"Kansas City",
    "sg:classifiers":[
        {
            "category":"Freight",
            "type":"Transportation"
        }
    ],
    "sg:phone":"+1 816 231 4329",
    "sg:postcode":"64120",
    "sg:province":"MO",
    "sg:tags":[
        "warehouse",
        "self",
        "storage"
    ],
    "wof:name":"Metropark Warehouse",
    "wof:placetype":"venue"
},
  "geometry": {"coordinates":[-94.503002,39.14399],"type":"Point"}
}