{
  "type": "Feature",
  "properties": {
    "addr:full":"8503 Manchester Rd St Louis MO 63144",
    "addr:housenumber":"8503",
    "addr:postcode":"63144",
    "addr:street":"Manchester Rd",
    "iso:country":"US",
    "sg:address":"8503 Manchester Rd",
    "sg:city":"St Louis",
    "sg:classifiers":[
        {
            "category":"Food & Beverages",
            "subcategory":"Bakery",
            "type":"Retail Goods"
        }
    ],
    "sg:phone":"+1 314 961 4328",
    "sg:postcode":"63144",
    "sg:province":"MO",
    "sg:tags":[
        "baker"
    ],
    "wof:name":"Dolly Madison",
    "wof:placetype":"venue"
},
  "geometry": {"coordinates":[-90.343952,38.612395],"type":"Point"}
}