{
  "type": "Feature",
  "properties": {
    "iso:country":"US",
    "sg:address":"6601 Olive Blvd",
    "sg:city":"Saint Louis",
    "sg:classifiers":[
        {
            "category":"Banks & Credit Unions",
            "subcategory":"Financial Services",
            "type":"Services"
        }
    ],
    "sg:phone":"+1 314 726 0807",
    "sg:postcode":"63130",
    "sg:province":"MO",
    "sg:tags":[
        "company",
        "investment"
    ],
    "wof:name":"Sanrol Enterprises LLC",
    "wof:placetype":"venue"
},
  "geometry": {"coordinates":[-90.30765,38.663049],"type":"Point"}
}