{
  "type": "Feature",
  "properties": {
    "iso:country":"US",
    "sg:address":"1 Westminster Sq",
    "sg:city":"St Peters",
    "sg:classifiers":[
        {
            "category":"Building & Trades",
            "subcategory":"Cleaning & Sanitation",
            "type":"Services"
        }
    ],
    "sg:phone":"+1 636 397 1701",
    "sg:postcode":"63376",
    "sg:province":"MO",
    "sg:tags":[
        "fireplace",
        "chimney"
    ],
    "wof:name":"Custom Fireplace",
    "wof:placetype":"venue"
},
  "geometry": {"coordinates":[-90.61515,38.77576],"type":"Point"}
}