{
  "type": "Feature",
  "properties": {
    "iso:country":"US",
    "sg:address":"1239 Claycrest Dr",
    "sg:city":"Saint Charles",
    "sg:classifiers":[
        {
            "category":"Professional",
            "subcategory":"Business Services",
            "type":"Services"
        }
    ],
    "sg:phone":"+1 636 939 4905",
    "sg:postcode":"63304",
    "sg:province":"MO",
    "wof:name":"R&R Distributors",
    "wof:placetype":"venue"
},
  "geometry": {"coordinates":[-90.621397,38.734617],"type":"Point"}
}