{
  "type": "Feature",
  "properties": {
    "iso:country":"US",
    "sg:address":"4449 Jarboe St",
    "sg:city":"Kansas City",
    "sg:classifiers":[
        {
            "category":"Personal",
            "subcategory":"Beauty Salon",
            "type":"Services"
        }
    ],
    "sg:phone":"+1 816 756 1300",
    "sg:postcode":"64111",
    "sg:province":"MO",
    "wof:name":"Salon Organica",
    "wof:placetype":"venue"
},
  "geometry": {"coordinates":[-94.59938,39.047107],"type":"Point"}
}