{
  "type": "Feature",
  "properties": {
    "iso:country":"US",
    "sg:address":"201 N Beckwith St",
    "sg:city":"Malden",
    "sg:classifiers":[
        {
            "category":"Landmark",
            "subcategory":"Historic",
            "type":"Public Place"
        },
        {
            "category":"Museum",
            "type":"Entertainment"
        }
    ],
    "sg:phone":"+1 573 276 5008",
    "sg:postcode":"63863",
    "sg:province":"MO",
    "sg:tags":[
        "historical"
    ],
    "sg:website":"http://www.maldenmuseum.com",
    "wof:name":"Malden Historical Museum Inc",
    "wof:placetype":"venue"
},
  "geometry": {"coordinates":[-89.96772,36.55949],"type":"Point"}
}