{
  "type": "Feature",
  "properties": {
    "iso:country":"US",
    "sg:address":"207 E Washington St",
    "sg:city":"Kirksville",
    "sg:classifiers":[
        {
            "category":"Organizations",
            "subcategory":"Religious Organization",
            "type":"Services"
        }
    ],
    "sg:phone":"+1 660 627 2273",
    "sg:postcode":"63501",
    "sg:province":"MO",
    "wof:name":"First Baptist Church",
    "wof:placetype":"venue"
},
  "geometry": {"coordinates":[-92.582013,40.194797],"type":"Point"}
}