{
  "type": "Feature",
  "properties": {
    "iso:country":"US",
    "sg:address":"1411 Locust St",
    "sg:city":"Saint Louis",
    "sg:classifiers":[
        {
            "category":"Organizations",
            "subcategory":"Religious Organization",
            "type":"Services"
        }
    ],
    "sg:phone":"+1 314 421 3020",
    "sg:postcode":"63103",
    "sg:province":"MO",
    "sg:website":"www.hereshelpnet.org",
    "wof:name":"New Life Evangelistic Center",
    "wof:placetype":"venue"
},
  "geometry": {"coordinates":[-90.199997,38.631302],"type":"Point"}
}