{
  "type": "Feature",
  "properties": {
    "iso:country":"US",
    "sg:address":"19 Centre Pt",
    "sg:city":"Saint Charles",
    "sg:classifiers":[
        {
            "category":"Building & Trades",
            "subcategory":"Construction",
            "type":"Services"
        }
    ],
    "sg:phone":"+1 636 477 8093",
    "sg:postcode":"63304",
    "sg:province":"MO",
    "sg:tags":[
        "contractor"
    ],
    "wof:name":"McCane Company Inc",
    "wof:placetype":"venue"
},
  "geometry": {"coordinates":[-90.584237,38.749055],"type":"Point"}
}