{
  "type": "Feature",
  "properties": {
    "iso:country":"US",
    "sg:address":"6770 Mall Dr",
    "sg:city":"Cedar Hill",
    "sg:classifiers":[
        {
            "category":"Restaurant",
            "type":"Food & Drink"
        }
    ],
    "sg:phone":"+1 636 285 8862",
    "sg:postcode":"63016",
    "sg:province":"MO",
    "wof:name":"Big River Bar & Grill",
    "wof:placetype":"venue"
},
  "geometry": {"coordinates":[-90.650535,38.350955],"type":"Point"}
}