{
  "type": "Feature",
  "properties": {
    "iso:country":"US",
    "sg:address":"15444 Manchester Rd",
    "sg:city":"Ballwin",
    "sg:classifiers":[
        {
            "category":"Personal",
            "subcategory":"Beauty Salon",
            "type":"Services"
        }
    ],
    "sg:phone":"+1 636 527 9599",
    "sg:postcode":"63011",
    "sg:province":"MO",
    "sg:tags":[
        "manicuring"
    ],
    "wof:name":"Five Star Nails",
    "wof:placetype":"venue"
},
  "geometry": {"coordinates":[-90.564969,38.592834],"type":"Point"}
}