{
  "type": "Feature",
  "properties": {
    "iso:country":"US",
    "sg:address":"5380 Martin Luther King Blvd",
    "sg:city":"St Louis",
    "sg:classifiers":[
        {
            "category":"Food & Beverages",
            "subcategory":"Groceries & Convenience Stores",
            "type":"Retail Goods"
        }
    ],
    "sg:phone":"+1 314 454 0634",
    "sg:postcode":"63140",
    "sg:province":"MO",
    "wof:name":"Mrs Milo's Soul Food & Bbq",
    "wof:placetype":"venue"
},
  "geometry": {"coordinates":[-90.323874,38.7303],"type":"Point"}
}