{
  "type": "Feature",
  "properties": {
    "iso:country":"US",
    "sg:address":"13190 Woodridge",
    "sg:city":"Platte City",
    "sg:classifiers":[
        {
            "category":"Professional",
            "type":"Services"
        }
    ],
    "sg:phone":"+1 816 453 0889",
    "sg:postcode":"64079",
    "sg:province":"MO",
    "wof:name":"Samanna Ltd",
    "wof:placetype":"venue"
},
  "geometry": {"coordinates":[-94.765293,39.330183],"type":"Point"}
}