{
  "type": "Feature",
  "properties": {
    "iso:country":"US",
    "sg:address":"390 S Lincoln Dr",
    "sg:city":"Troy",
    "sg:classifiers":[
        {
            "category":"Wholesale",
            "subcategory":"Machinery & Supplies",
            "type":"Manufacturing & Wholesale Goods"
        }
    ],
    "sg:phone":"+1 636 462 5198",
    "sg:postcode":"63379",
    "sg:province":"MO",
    "wof:name":"L & S Small Engines",
    "wof:placetype":"venue"
},
  "geometry": {"coordinates":[-90.966308,38.973424],"type":"Point"}
}