{
  "type": "Feature",
  "properties": {
    "iso:country":"US",
    "sg:address":"306 E Hyde Park Ave",
    "sg:city":"St Joseph",
    "sg:classifiers":[
        {
            "category":"Food & Beverages",
            "subcategory":"Bakery",
            "type":"Retail Goods"
        }
    ],
    "sg:phone":"+1 816 238 2525",
    "sg:postcode":"64504",
    "sg:province":"MO",
    "sg:tags":[
        "doughnut"
    ],
    "wof:name":"Cardinal Country Donuts",
    "wof:placetype":"venue"
},
  "geometry": {"coordinates":[-94.856458,39.711553],"type":"Point"}
}