{
  "type": "Feature",
  "properties": {
    "iso:country":"US",
    "sg:address":"3710 S Jefferson Ave",
    "sg:city":"Saint Louis",
    "sg:classifiers":[
        {
            "category":"Wholesale",
            "subcategory":"Non-durable Goods",
            "type":"Manufacturing & Wholesale Goods"
        }
    ],
    "sg:phone":"+1 314 772 7121",
    "sg:postcode":"63118",
    "sg:province":"MO",
    "wof:name":"Grey Star Trading",
    "wof:placetype":"venue"
},
  "geometry": {"coordinates":[-90.226842,38.586298],"type":"Point"}
}