{
  "type": "Feature",
  "properties": {
    "iso:country":"US",
    "sg:address":"2725 Cantrell Rd",
    "sg:city":"Harrisonville",
    "sg:classifiers":[
        {
            "category":"Shopping",
            "subcategory":"Computers & Home Electronics",
            "type":"Retail Goods"
        }
    ],
    "sg:phone":"+1 816 887 5155",
    "sg:postcode":"64701",
    "sg:province":"MO",
    "sg:tags":[
        "consumer"
    ],
    "wof:name":"Radio Shack",
    "wof:placetype":"venue"
},
  "geometry": {"coordinates":[-94.37282999999999,38.660578],"type":"Point"}
}