{
  "type": "Feature",
  "properties": {
    "iso:country":"US",
    "sg:address":"90 Algana Ct",
    "sg:city":"St Peters",
    "sg:classifiers":[
        {
            "category":"Manufacturing",
            "subcategory":"Signs",
            "type":"Manufacturing & Wholesale Goods"
        },
        {
            "category":"Manufacturing",
            "subcategory":"Printing",
            "type":"Manufacturing & Wholesale Goods"
        }
    ],
    "sg:phone":"+1 636 928 3590",
    "sg:postcode":"63376",
    "sg:province":"MO",
    "sg:tags":[
        "commercial"
    ],
    "wof:name":"Precision Silk Screening Inc",
    "wof:placetype":"venue"
},
  "geometry": {"coordinates":[-90.582883,38.801651],"type":"Point"}
}