{
  "type": "Feature",
  "properties": {
    "iso:country":"US",
    "sg:address":"7935 Big Bend Blvd",
    "sg:city":"Saint Louis",
    "sg:classifiers":[
        {
            "category":"Shopping",
            "subcategory":"Used Merchandise",
            "type":"Retail Goods"
        }
    ],
    "sg:phone":"+1 314 961 2440",
    "sg:postcode":"63119",
    "sg:province":"MO",
    "sg:tags":[
        "clothing",
        "secondhand"
    ],
    "wof:name":"Second Hand Boutique",
    "wof:placetype":"venue"
},
  "geometry": {"coordinates":[-90.334457,38.594874],"type":"Point"}
}