{
  "type": "Feature",
  "properties": {
    "iso:country":"US",
    "sg:address":"1711 W Battlefield Rd",
    "sg:city":"Springfield",
    "sg:classifiers":[
        {
            "category":"Personal",
            "subcategory":"Beauty Salon",
            "type":"Services"
        }
    ],
    "sg:phone":"+1 417 889 4446",
    "sg:postcode":"65807",
    "sg:province":"MO",
    "sg:tags":[
        "manicuring"
    ],
    "wof:name":"American Nail Art Studio",
    "wof:placetype":"venue"
},
  "geometry": {"coordinates":[-93.314785,37.160261],"type":"Point"}
}