{
  "type": "Feature",
  "properties": {
    "iso:country":"US",
    "sg:address":"16121 S Adams Rd",
    "sg:city":"Pleasant Hill",
    "sg:classifiers":[
        {
            "category":"Building & Trades",
            "subcategory":"Construction",
            "type":"Services"
        }
    ],
    "sg:phone":"+1 816 697 2181",
    "sg:postcode":"64080",
    "sg:province":"MO",
    "wof:name":"Rda Construction Co",
    "wof:placetype":"venue"
},
  "geometry": {"coordinates":[-94.167181,38.821778],"type":"Point"}
}