{
  "type": "Feature",
  "properties": {
    "iso:country":"US",
    "sg:address":"665 Strothcamp Rd",
    "sg:city":"Cuba",
    "sg:classifiers":[
        {
            "category":"Wholesale",
            "subcategory":"Furniture",
            "type":"Manufacturing & Wholesale Goods"
        }
    ],
    "sg:phone":"+1 573 885 0355",
    "sg:postcode":"65453",
    "sg:province":"MO",
    "wof:name":"McAllister Vollmar Inc",
    "wof:placetype":"venue"
},
  "geometry": {"coordinates":[-91.448108,38.171385],"type":"Point"}
}