{
  "type": "Feature",
  "properties": {
    "iso:country":"US",
    "sg:address":"13277 State Rte E D",
    "sg:city":"Savannah",
    "sg:classifiers":[
        {
            "category":"Social Services",
            "subcategory":"Job Training",
            "type":"Services"
        },
        {
            "category":"Health Services",
            "subcategory":"Health Practitioner",
            "type":"Services"
        },
        {
            "category":"Social Services",
            "subcategory":"Retirement Home",
            "type":"Services"
        },
        {
            "category":"Social Services",
            "subcategory":"Adult Care",
            "type":"Services"
        }
    ],
    "sg:phone":"+1 816 324 5991",
    "sg:postcode":"64485",
    "sg:province":"MO",
    "sg:tags":[
        "living",
        "nursing",
        "homes-skilled",
        "nurses-home",
        "assisted",
        "addiction-information",
        "facility",
        "treatment",
        "gambling"
    ],
    "wof:name":"Shady Lawn Nursing Home",
    "wof:placetype":"venue"
},
  "geometry": {"coordinates":[-94.784423,39.94322],"type":"Point"}
}