{
  "type": "Feature",
  "properties": {
    "iso:country":"US",
    "sg:address":"9 Oakleigh Ln",
    "sg:city":"Saint Louis",
    "sg:classifiers":[
        {
            "category":"Professional",
            "subcategory":"Business Services",
            "type":"Services"
        }
    ],
    "sg:phone":"+1 314 567 0255",
    "sg:postcode":"63124",
    "sg:province":"MO",
    "wof:name":"N M Interiors",
    "wof:placetype":"venue"
},
  "geometry": {"coordinates":[-90.383014,38.657528],"type":"Point"}
}