{
  "type": "Feature",
  "properties": {
    "iso:country":"US",
    "sg:address":"1277 Wardfield Rd",
    "sg:city":"Robertsville",
    "sg:classifiers":[
        {
            "category":"Retail",
            "subcategory":"Repair Shop",
            "type":"Services"
        }
    ],
    "sg:phone":"+1 636 629 8368",
    "sg:postcode":"63072",
    "sg:province":"MO",
    "wof:name":"Saint Clair Upholstery",
    "wof:placetype":"venue"
},
  "geometry": {"coordinates":[-90.80718299999999,38.344244],"type":"Point"}
}