{
  "type": "Feature",
  "properties": {
    "iso:country":"US",
    "sg:address":"25761 State Hwy 20",
    "sg:city":"Corder",
    "sg:phone":"+1 660 394 2649",
    "sg:postcode":"64021",
    "sg:province":"MO",
    "sg:tags":[
        "farm",
        "corn"
    ],
    "wof:name":"Hubert Dickmeier",
    "wof:placetype":"venue"
},
  "geometry": {"coordinates":[-93.63107599999999,39.108418],"type":"Point"}
}