{
  "type": "Feature",
  "properties": {
    "iso:country":"US",
    "sg:address":"400 W Culton St",
    "sg:city":"Warrensburg",
    "sg:classifiers":[
        {
            "category":"Place Of Worship",
            "subcategory":"Church",
            "type":"Public Place"
        },
        {
            "category":"Place Of Worship",
            "type":"Public Place"
        },
        {
            "category":"Organizations",
            "subcategory":"Religious Organization",
            "type":"Services"
        }
    ],
    "sg:phone":"+1 660 747 5369",
    "sg:postcode":"64093",
    "sg:province":"MO",
    "sg:tags":[
        "churches-pentecostal-independent",
        "churches-pentecostal"
    ],
    "wof:name":"Jesus Saves Pentecostal Church",
    "wof:placetype":"venue"
},
  "geometry": {"coordinates":[-93.748062,38.764462],"type":"Point"}
}