{
  "type": "Feature",
  "properties": {
    "iso:country":"US",
    "sg:address":"2704 Saint Marys Ave",
    "sg:city":"Hannibal",
    "sg:classifiers":[
        {
            "category":"Insurance",
            "subcategory":"Insurance Agent",
            "type":"Services"
        },
        {
            "category":"Insurance",
            "subcategory":"Hazard Insurance",
            "type":"Services"
        },
        {
            "category":"Insurance",
            "subcategory":"Title Insurance",
            "type":"Services"
        }
    ],
    "sg:phone":"+1 573 221 8263",
    "sg:postcode":"63401",
    "sg:province":"MO",
    "sg:tags":[
        "auto",
        "homeowner"
    ],
    "sg:website":"http://apps.amfam.com/agentlocator/JUTTERBA?sourceid=yp3",
    "wof:name":"American Family Insurance- Jason Utterback",
    "wof:placetype":"venue"
},
  "geometry": {"coordinates":[-91.385419,39.705033],"type":"Point"}
}