{
  "type": "Feature",
  "properties": {
    "iso:country":"US",
    "sg:address":"2010 Van Brunt Blvd",
    "sg:city":"Kansas City",
    "sg:classifiers":[
        {
            "category":"Organizations",
            "subcategory":"Religious Organization",
            "type":"Services"
        }
    ],
    "sg:phone":"+1 816 241 4600",
    "sg:postcode":"64127",
    "sg:province":"MO",
    "sg:tags":[
        "church"
    ],
    "wof:name":"Bread Of Life Community Bptst",
    "wof:placetype":"venue"
},
  "geometry": {"coordinates":[-94.52105400000001,39.085215],"type":"Point"}
}