{
  "type": "Feature",
  "properties": {
    "iso:country":"US",
    "sg:address":"650 Big Bend Rd",
    "sg:city":"Ballwin",
    "sg:classifiers":[
        {
            "category":"Building & Trades",
            "subcategory":"Construction",
            "type":"Services"
        }
    ],
    "sg:phone":"+1 636 227 2242",
    "sg:postcode":"63021",
    "sg:province":"MO",
    "sg:tags":[
        "general",
        "contractor"
    ],
    "wof:name":"O B Construction Svc",
    "wof:placetype":"venue"
},
  "geometry": {"coordinates":[-90.51673599999999,38.567153],"type":"Point"}
}