{
  "type": "Feature",
  "properties": {
    "iso:country":"US",
    "sg:address":"13901 State Hwy 350",
    "sg:city":"Kansas City",
    "sg:classifiers":[
        {
            "category":"Building & Trades",
            "subcategory":"Construction",
            "type":"Services"
        }
    ],
    "sg:phone":"+1 816 525 5888",
    "sg:postcode":"64139",
    "sg:province":"MO",
    "sg:tags":[
        "roofing",
        "guttering",
        "contractor"
    ],
    "wof:name":"OSullivan Guttering & Roofing",
    "wof:placetype":"venue"
},
  "geometry": {"coordinates":[-94.418193,38.952789],"type":"Point"}
}