{
  "type": "Feature",
  "properties": {
    "iso:country":"US",
    "sg:address":"501 E Washington St",
    "sg:city":"Cuba",
    "sg:classifiers":[
        {
            "category":"Communications",
            "subcategory":"Newspaper",
            "type":"Services"
        },
        {
            "category":"Wholesale",
            "subcategory":"Books, Periodicals, & Newspapers",
            "type":"Manufacturing & Wholesale Goods"
        }
    ],
    "sg:phone":"+1 573 885 7460",
    "sg:postcode":"65453",
    "sg:province":"MO",
    "sg:tags":[
        "dealers-wholesale",
        "news"
    ],
    "wof:name":"Free River Publishing",
    "wof:placetype":"venue"
},
  "geometry": {"coordinates":[-91.399788,38.06369],"type":"Point"}
}