{
  "type": "Feature",
  "properties": {
    "iso:country":"US",
    "sg:address":"1633 Summit Estates Dr",
    "sg:city":"O Fallon",
    "sg:classifiers":[
        {
            "category":"Manufacturing",
            "subcategory":"Glass & Minerals",
            "type":"Manufacturing & Wholesale Goods"
        }
    ],
    "sg:phone":"+1 636 240 8003",
    "sg:postcode":"63366",
    "sg:province":"MO",
    "sg:tags":[
        "ready",
        "concrete",
        "mfg"
    ],
    "wof:name":"Fresh Mix Mobile Concrete",
    "wof:placetype":"venue"
},
  "geometry": {"coordinates":[-90.751592,38.828381],"type":"Point"}
}