{
  "type": "Feature",
  "properties": {
    "iso:country":"US",
    "sg:address":"165 E Hoedown Dr",
    "sg:city":"Columbia",
    "sg:classifiers":[
        {
            "category":"Personal",
            "subcategory":"Beauty Salon",
            "type":"Services"
        }
    ],
    "sg:phone":"+1 573 449 3070",
    "sg:postcode":"65203",
    "sg:province":"MO",
    "sg:tags":[
        "spa",
        "day"
    ],
    "wof:name":"Sedona Spa & Therapeutic Mssg",
    "wof:placetype":"venue"
},
  "geometry": {"coordinates":[-92.342654,38.885329],"type":"Point"}
}