{
  "type": "Feature",
  "properties": {
    "iso:country":"US",
    "sg:address":"9400 Sterling Pl",
    "sg:city":"Saint Louis",
    "sg:classifiers":[
        {
            "category":"Building & Trades",
            "subcategory":"Construction",
            "type":"Services"
        }
    ],
    "sg:phone":"+1 314 631 8507",
    "sg:postcode":"63123",
    "sg:province":"MO",
    "sg:tags":[
        "contractor"
    ],
    "wof:name":"Brinker Contracting",
    "wof:placetype":"venue"
},
  "geometry": {"coordinates":[-90.32144700000001,38.552358],"type":"Point"}
}