{
  "type": "Feature",
  "properties": {
    "iso:country":"US",
    "sg:address":"5901 E Front St",
    "sg:city":"Kansas City",
    "sg:classifiers":[
        {
            "category":"Manufacturing",
            "subcategory":"Tools & Machinery",
            "type":"Manufacturing & Wholesale Goods"
        }
    ],
    "sg:phone":"+1 816 241 3700",
    "sg:postcode":"64120",
    "sg:province":"MO",
    "sg:tags":[
        "equipment",
        "safety",
        "clothing"
    ],
    "sg:website":"www.orrsafety.com",
    "wof:name":"Orr Safety Corp",
    "wof:placetype":"venue"
},
  "geometry": {"coordinates":[-94.508791,39.130307],"type":"Point"}
}