{
  "type": "Feature",
  "properties": {
    "iso:country":"US",
    "sg:address":"9206 NW 59 Ter",
    "sg:city":"Kansas City",
    "sg:classifiers":[
        {
            "category":"Building & Trades",
            "subcategory":"Construction",
            "type":"Services"
        }
    ],
    "sg:phone":"+1 816 746 5241",
    "sg:postcode":"64152",
    "sg:province":"MO",
    "sg:tags":[
        "house",
        "general",
        "contractor"
    ],
    "wof:name":"Enloe Construction & Imprvmt",
    "wof:placetype":"venue"
},
  "geometry": {"coordinates":[-94.68754199999999,39.202281],"type":"Point"}
}