{
  "type": "Feature",
  "properties": {
    "iso:country":"US",
    "sg:address":"1715 Linn St",
    "sg:city":"Kansas City",
    "sg:classifiers":[
        {
            "category":"Shopping",
            "subcategory":"Clothing, Apparel, & Fashions",
            "type":"Retail Goods"
        }
    ],
    "sg:phone":"+1 816 472 5200",
    "sg:postcode":"64116",
    "sg:province":"MO",
    "sg:tags":[
        "uniform"
    ],
    "sg:website":"www.usuniforms.com",
    "wof:name":"United States Uniforms",
    "wof:placetype":"venue"
},
  "geometry": {"coordinates":[-94.56795099999999,39.138264],"type":"Point"}
}