{
  "type": "Feature",
  "properties": {
    "addr:full":"7300 NW Katie Cir Parkville MO 64152",
    "addr:housenumber":"7300",
    "addr:postcode":"64152",
    "addr:street":"Nw Katie Cir",
    "iso:country":"US",
    "sg:address":"7300 NW Katie Cir",
    "sg:city":"Parkville",
    "sg:classifiers":[
        {
            "category":"Shopping",
            "type":"Retail Goods"
        }
    ],
    "sg:phone":"+1 816 746 6886",
    "sg:postcode":"64152",
    "sg:province":"MO",
    "sg:tags":[
        "cosmetic",
        "perfume"
    ],
    "wof:name":"Jafra Cosmetics",
    "wof:placetype":"venue"
},
  "geometry": {"coordinates":[-94.688543,39.226333],"type":"Point"}
}