{
  "type": "Feature",
  "properties": {
    "iso:country":"US",
    "sg:address":"1503 W Austin Blvd",
    "sg:city":"Nevada",
    "sg:classifiers":[
        {
            "category":"Restaurant",
            "type":"Food & Drink"
        }
    ],
    "sg:phone":"+1 417 667 2424",
    "sg:postcode":"64772",
    "sg:province":"MO",
    "sg:tags":[
        "eating"
    ],
    "wof:name":"Pizza Hut",
    "wof:placetype":"venue"
},
  "geometry": {"coordinates":[-94.376035,37.837655],"type":"Point"}
}