{
  "type": "Feature",
  "properties": {
    "iso:country":"US",
    "sg:address":"2500 S Halliburton St",
    "sg:city":"Kirksville",
    "sg:classifiers":[
        {
            "category":"Building & Trades",
            "subcategory":"Cleaning & Sanitation",
            "type":"Services"
        }
    ],
    "sg:phone":"+1 660 627 2517",
    "sg:postcode":"63501",
    "sg:province":"MO",
    "sg:tags":[
        "house"
    ],
    "wof:name":"Custom Clean",
    "wof:placetype":"venue"
},
  "geometry": {"coordinates":[-92.57663100000001,40.174234],"type":"Point"}
}