{
  "type": "Feature",
  "properties": {
    "iso:country":"US",
    "sg:address":"12005 State Hwy 28",
    "sg:city":"Dixon",
    "sg:classifiers":[
        {
            "category":"Retail",
            "subcategory":"Auto Repair",
            "type":"Services"
        }
    ],
    "sg:phone":"+1 573 759 6342",
    "sg:postcode":"65459",
    "sg:province":"MO",
    "sg:tags":[
        "repairing",
        "automobile"
    ],
    "wof:name":"Express Auto Svc",
    "wof:placetype":"venue"
},
  "geometry": {"coordinates":[-92.093648,37.984884],"type":"Point"}
}