{
  "type": "Feature",
  "properties": {
    "iso:country":"US",
    "sg:address":"702 W Main St",
    "sg:city":"Sedalia",
    "sg:classifiers":[
        {
            "category":"Retail",
            "subcategory":"Auto Repair",
            "type":"Services"
        }
    ],
    "sg:phone":"+1 660 826 3399",
    "sg:postcode":"65301",
    "sg:province":"MO",
    "sg:tags":[
        "repairing",
        "automobile"
    ],
    "wof:name":"Wright's Auto Repair",
    "wof:placetype":"venue"
},
  "geometry": {"coordinates":[-93.236144,38.712253],"type":"Point"}
}