{
  "type": "Feature",
  "properties": {
    "iso:country":"US",
    "sg:address":"116 N Atterberry St",
    "sg:city":"Atlanta",
    "sg:classifiers":[
        {
            "category":"Professional",
            "subcategory":"Business Services",
            "type":"Services"
        }
    ],
    "sg:phone":"+1 660 239 4476",
    "sg:postcode":"63530",
    "sg:province":"MO",
    "sg:tags":[
        "auctioneer"
    ],
    "wof:name":"Christy's Auction Svc",
    "wof:placetype":"venue"
},
  "geometry": {"coordinates":[-92.47937400000001,39.899722],"type":"Point"}
}