{
  "type": "Feature",
  "properties": {
    "addr:full":"8346 Watson Rd Webster Groves MO 63119",
    "addr:housenumber":"8346",
    "addr:postcode":"63119",
    "addr:street":"Watson Rd",
    "iso:country":"US",
    "sg:address":"8346 Watson Rd",
    "sg:city":"Webster Groves",
    "sg:classifiers":[
        {
            "category":"Restaurant",
            "type":"Food & Drink"
        }
    ],
    "sg:menulink":"http://www.allmenus.com/mo/gravois/83954-dominos-pizza/menu/",
    "sg:phone":"+1 314 843 5353",
    "sg:postcode":"63119",
    "sg:province":"MO",
    "sg:tags":[
        "american",
        "wing",
        "pizza"
    ],
    "wof:name":"Domino's Pizza",
    "wof:placetype":"venue"
},
  "geometry": {"coordinates":[-90.351186,38.566133],"type":"Point"}
}