{
  "type": "Feature",
  "properties": {
    "iso:country":"US",
    "sg:address":"3208 Lemone Industrial Blvd",
    "sg:city":"Columbia",
    "sg:classifiers":[
        {
            "category":"Shopping",
            "type":"Retail Goods"
        }
    ],
    "sg:phone":"+1 573 442 8877",
    "sg:postcode":"65201",
    "sg:province":"MO",
    "sg:tags":[
        "equipment",
        "merchandise"
    ],
    "wof:name":"American Homepatient",
    "wof:placetype":"venue"
},
  "geometry": {"coordinates":[-92.291706,38.915349],"type":"Point"}
}