{
  "type": "Feature",
  "properties": {
    "iso:country":"US",
    "sg:address":"126 Hollyleaf Dr",
    "sg:city":"Ballwin",
    "sg:classifiers":[
        {
            "category":"Retail",
            "subcategory":"Portrait Studio",
            "type":"Services"
        }
    ],
    "sg:phone":"+1 636 394 1166",
    "sg:postcode":"63021",
    "sg:province":"MO",
    "sg:tags":[
        "photographer",
        "photo"
    ],
    "sg:website":"www.goldsphoto.com",
    "wof:name":"Golds Photography and Video",
    "wof:placetype":"venue"
},
  "geometry": {"coordinates":[-90.543516,38.570426],"type":"Point"}
}