{
  "type": "Feature",
  "properties": {
    "iso:country":"US",
    "sg:address":"200 S Davis St",
    "sg:city":"Hamilton",
    "sg:classifiers":[
        {
            "category":"Government",
            "subcategory":"Fire Station",
            "type":"Public Place"
        }
    ],
    "sg:phone":"+1 816 583 2143",
    "sg:postcode":"64644",
    "sg:province":"MO",
    "sg:tags":[
        "consultant",
        "protection"
    ],
    "wof:name":"Hfpd Investments",
    "wof:placetype":"venue"
},
  "geometry": {"coordinates":[-93.998108,39.741318],"type":"Point"}
}