{
  "type": "Feature",
  "properties": {
    "iso:country":"US",
    "sg:address":"24940 Spencer Rd",
    "sg:city":"Waynesville",
    "sg:classifiers":[
        {
            "category":"Structure",
            "subcategory":"Office Building",
            "type":"Public Place"
        }
    ],
    "sg:phone":"+1 573 774 6222",
    "sg:postcode":"65583",
    "sg:province":"MO",
    "sg:tags":[
        "park"
    ],
    "wof:name":"Mabong Properties",
    "wof:placetype":"venue"
},
  "geometry": {"coordinates":[-92.205924,37.799631],"type":"Point"}
}