{
  "type": "Feature",
  "properties": {
    "iso:country":"US",
    "sg:address":"901 E Auburn Dr",
    "sg:city":"Ash Grove",
    "sg:classifiers":[
        {
            "category":"Freight",
            "type":"Transportation"
        }
    ],
    "sg:phone":"+1 417 672 2868",
    "sg:postcode":"65604",
    "sg:province":"MO",
    "sg:tags":[
        "general"
    ],
    "wof:name":"J & J Storage",
    "wof:placetype":"venue"
},
  "geometry": {"coordinates":[-93.57253,37.31751],"type":"Point"}
}