{
  "type": "Feature",
  "properties": {
    "iso:country":"US",
    "sg:address":"230 N Washington Ave",
    "sg:city":"Union",
    "sg:classifiers":[
        {
            "category":"Personal",
            "subcategory":"Beauty Salon",
            "type":"Services"
        }
    ],
    "sg:phone":"+1 636 583 5869",
    "sg:postcode":"63084",
    "sg:province":"MO",
    "wof:name":"Hair Expo",
    "wof:placetype":"venue"
},
  "geometry": {"coordinates":[-91.008923,38.447416],"type":"Point"}
}