{
  "type": "Feature",
  "properties": {
    "iso:country":"US",
    "sg:address":"5 Marlin Ln",
    "sg:city":"Buffalo",
    "sg:classifiers":[
        {
            "category":"Autos & Motor Vehicles",
            "subcategory":"Automobile Sales",
            "type":"Retail Goods"
        }
    ],
    "sg:phone":"+1 417 345 5767",
    "sg:postcode":"65622",
    "sg:province":"MO",
    "sg:tags":[
        "dealers-used",
        "car",
        "used",
        "cars-wholesale"
    ],
    "wof:name":"Faulkner Auto Sales",
    "wof:placetype":"venue"
},
  "geometry": {"coordinates":[-93.102193,37.656799],"type":"Point"}
}