{
  "type": "Feature",
  "properties": {
    "iso:country":"US",
    "sg:address":"119 E Main St",
    "sg:city":"Smithville",
    "sg:classifiers":[
        {
            "category":"Professional",
            "subcategory":"Lawyer & Legal Services",
            "type":"Services"
        }
    ],
    "sg:phone":"+1 816 532 3895",
    "sg:postcode":"64089",
    "sg:province":"MO",
    "sg:tags":[
        "attorney",
        "practice"
    ],
    "sg:website":"http://www.lawofficemo.com",
    "wof:name":"Andreck Evans Melm Widger",
    "wof:placetype":"venue"
},
  "geometry": {"coordinates":[-94.580675,39.387127],"type":"Point"}
}