{
  "type": "Feature",
  "properties": {
    "iso:country":"US",
    "sg:address":"1096 S Highway Dr",
    "sg:city":"Fenton",
    "sg:classifiers":[
        {
            "category":"Restaurant",
            "type":"Food & Drink"
        }
    ],
    "sg:menulink":"http://www.allmenus.com/mo/bonhomme/11485-dennys/menu/",
    "sg:phone":"+1 636 343 1480",
    "sg:postcode":"63026",
    "sg:province":"MO",
    "sg:tags":[
        "american",
        "diner"
    ],
    "wof:name":"Denny's",
    "wof:placetype":"venue"
},
  "geometry": {"coordinates":[-90.466793,38.542455],"type":"Point"}
}