{
  "type": "Feature",
  "properties": {
    "iso:country":"US",
    "sg:address":"5200 Shaw Ave",
    "sg:city":"St Louis",
    "sg:classifiers":[
        {
            "category":"Professional",
            "subcategory":"Art Services",
            "type":"Services"
        }
    ],
    "sg:phone":"+1 314 771 7227",
    "sg:postcode":"63110",
    "sg:province":"MO",
    "sg:tags":[
        "photographer"
    ],
    "wof:name":"Scott Smith Photography",
    "wof:placetype":"venue"
},
  "geometry": {"coordinates":[-90.27459899999999,38.618151],"type":"Point"}
}