{
  "type": "Feature",
  "properties": {
    "iso:country":"US",
    "sg:address":"246 SE 15th Rd",
    "sg:city":"Lamar",
    "sg:classifiers":[
        {
            "category":"Professional",
            "type":"Services"
        }
    ],
    "sg:phone":"+1 417 682 3716",
    "sg:postcode":"64759",
    "sg:province":"MO",
    "wof:name":"Bill Baker",
    "wof:placetype":"venue"
},
  "geometry": {"coordinates":[-94.25457299999999,37.477785],"type":"Point"}
}