{
  "type": "Feature",
  "properties": {
    "iso:country":"US",
    "sg:address":"604 Kinzer St",
    "sg:city":"Poplar Bluff",
    "sg:classifiers":[
        {
            "category":"Wholesale",
            "subcategory":"Durable Goods & Equipment",
            "type":"Manufacturing & Wholesale Goods"
        }
    ],
    "sg:phone":"+1 573 686 6832",
    "sg:postcode":"63901",
    "sg:province":"MO",
    "wof:name":"F & S Supplies",
    "wof:placetype":"venue"
},
  "geometry": {"coordinates":[-90.39846,36.760132],"type":"Point"}
}