{
  "type": "Feature",
  "properties": {
    "iso:country":"US",
    "sg:address":"1705 E Liberty St",
    "sg:city":"Mexico",
    "sg:classifiers":[
        {
            "category":"Communications",
            "type":"Services"
        }
    ],
    "sg:phone":"+1 800 748 8222",
    "sg:postcode":"65265",
    "sg:province":"MO",
    "sg:tags":[
        "sound",
        "equipment",
        "system"
    ],
    "sg:website":"http://www.soundsolutionsinc.com",
    "wof:name":"Sound Solutions",
    "wof:placetype":"venue"
},
  "geometry": {"coordinates":[-91.884387,39.170565],"type":"Point"}
}