{
  "type": "Feature",
  "properties": {
    "iso:country":"US",
    "sg:address":"7535 Genesta St",
    "sg:city":"Saint Louis",
    "sg:classifiers":[
        {
            "category":"Professional",
            "type":"Services"
        }
    ],
    "sg:phone":"+1 314 481 3590",
    "sg:postcode":"63123",
    "sg:province":"MO",
    "wof:name":"Doris Landfather",
    "wof:placetype":"venue"
},
  "geometry": {"coordinates":[-90.309648,38.572088],"type":"Point"}
}