{
  "type": "Feature",
  "properties": {
    "iso:country":"US",
    "sg:address":"1734 State Highway F",
    "sg:city":"Portageville",
    "sg:classifiers":[
        {
            "category":"Manufacturing",
            "subcategory":"Food",
            "type":"Manufacturing & Wholesale Goods"
        },
        {
            "category":"Farming",
            "subcategory":"Farm",
            "type":"Manufacturing & Wholesale Goods"
        }
    ],
    "sg:phone":"+1 573 379 5697",
    "sg:postcode":"63873",
    "sg:province":"MO",
    "sg:tags":[
        "corn",
        "product"
    ],
    "wof:name":"Priggel Family Farms",
    "wof:placetype":"venue"
},
  "geometry": {"coordinates":[-89.70190599999999,36.442095],"type":"Point"}
}