{
  "type": "Feature",
  "properties": {
    "iso:country":"US",
    "sg:address":"525 Main St",
    "sg:city":"Weston",
    "sg:classifiers":[
        {
            "category":"Shopping",
            "subcategory":"Gifts & Souvenirs",
            "type":"Retail Goods"
        }
    ],
    "sg:phone":"+1 816 386 5807",
    "sg:postcode":"64098",
    "sg:province":"MO",
    "sg:tags":[
        "jewelry"
    ],
    "wof:name":"Perfect Accents",
    "wof:placetype":"venue"
},
  "geometry": {"coordinates":[-94.901258,39.411539],"type":"Point"}
}