{
  "type": "Feature",
  "properties": {
    "iso:country":"US",
    "sg:address":"1490 Schoettler Rd",
    "sg:city":"Chesterfield",
    "sg:classifiers":[
        {
            "category":"Building & Trades",
            "subcategory":"Construction",
            "type":"Services"
        }
    ],
    "sg:phone":"+1 636 532 2727",
    "sg:postcode":"63017",
    "sg:province":"MO",
    "sg:tags":[
        "chemical",
        "home",
        "contractor"
    ],
    "wof:name":"America Home Builders",
    "wof:placetype":"venue"
},
  "geometry": {"coordinates":[-90.545616,38.646649],"type":"Point"}
}