{
  "type": "Feature",
  "properties": {
    "iso:country":"US",
    "sg:address":"3513 NW Lake Dr",
    "sg:city":"Lees Summit",
    "sg:classifiers":[
        {
            "category":"Real Estate",
            "subcategory":"Real Estate Agent",
            "type":"Services"
        }
    ],
    "sg:phone":"+1 816 373 6721",
    "sg:postcode":"64064",
    "sg:province":"MO",
    "wof:name":"Vest Real Estate Co",
    "wof:placetype":"venue"
},
  "geometry": {"coordinates":[-94.385019,38.977839],"type":"Point"}
}