{
  "type": "Feature",
  "properties": {
    "iso:country":"US",
    "sg:address":"1901 N Commercial St",
    "sg:city":"Harrisonville",
    "sg:classifiers":[
        {
            "category":"Recreation",
            "type":"Entertainment"
        }
    ],
    "sg:phone":"+1 816 884 4419",
    "sg:postcode":"64701",
    "sg:province":"MO",
    "sg:tags":[
        "merchandise"
    ],
    "wof:name":"Designing Frames",
    "wof:placetype":"venue"
},
  "geometry": {"coordinates":[-94.35991300000001,38.662315],"type":"Point"}
}