{
  "type": "Feature",
  "properties": {
    "iso:country":"US",
    "sg:address":"209 Lusher",
    "sg:city":"Salisbury",
    "sg:classifiers":[
        {
            "category":"Social Services",
            "subcategory":"Child Care",
            "type":"Services"
        }
    ],
    "sg:phone":"+1 660 388 6977",
    "sg:postcode":"65281",
    "sg:province":"MO",
    "wof:name":"Just Kidding Childcare",
    "wof:placetype":"venue"
},
  "geometry": {"coordinates":[-92.799176,39.426401],"type":"Point"}
}