{
  "type": "Feature",
  "properties": {
    "iso:country":"US",
    "sg:address":"132 NW Hwy M",
    "sg:city":"Clinton",
    "sg:classifiers":[
        {
            "category":"Professional",
            "type":"Services"
        }
    ],
    "sg:phone":"+1 660 885 6394",
    "sg:postcode":"64735",
    "sg:province":"MO",
    "sg:tags":[
        "establishment"
    ],
    "wof:name":"Auto Shop",
    "wof:placetype":"venue"
},
  "geometry": {"coordinates":[-93.782004,38.518061],"type":"Point"}
}