{
  "type": "Feature",
  "properties": {
    "iso:country":"US",
    "sg:address":"116 A St",
    "sg:city":"Bonne Terre",
    "sg:classifiers":[
        {
            "category":"Building & Trades",
            "subcategory":"Landscaping Services",
            "type":"Services"
        }
    ],
    "sg:phone":"+1 573 358 7903",
    "sg:postcode":"63628",
    "sg:province":"MO",
    "sg:tags":[
        "tree"
    ],
    "wof:name":"AAA Tree Svc",
    "wof:placetype":"venue"
},
  "geometry": {"coordinates":[-90.55895200000001,37.921759],"type":"Point"}
}