{
  "type": "Feature",
  "properties": {
    "iso:country":"US",
    "sg:address":"212 N Clay Ave",
    "sg:city":"St Louis",
    "sg:classifiers":[
        {
            "category":"Building & Trades",
            "subcategory":"Construction",
            "type":"Services"
        }
    ],
    "sg:phone":"+1 314 821 7646",
    "sg:postcode":"63122",
    "sg:province":"MO",
    "sg:tags":[
        "repairing",
        "carpentry",
        "remodeling",
        "contractor"
    ],
    "sg:website":"www.riggsconstruction.com",
    "wof:name":"Riggs Construction Co Inc",
    "wof:placetype":"venue"
},
  "geometry": {"coordinates":[-90.40855999999999,38.583225],"type":"Point"}
}