{
  "type": "Feature",
  "properties": {
    "iso:country":"US",
    "sg:address":"5910 Natural Bridge Ave",
    "sg:city":"Saint Louis",
    "sg:classifiers":[
        {
            "category":"Bars & Pubs",
            "type":"Food & Drink"
        }
    ],
    "sg:phone":"+1 314 383 6355",
    "sg:postcode":"63120",
    "sg:province":"MO",
    "sg:tags":[
        "drinking"
    ],
    "wof:name":"Bizzels Lounge",
    "wof:placetype":"venue"
},
  "geometry": {"coordinates":[-90.273099,38.687253],"type":"Point"}
}