{
  "type": "Feature",
  "properties": {
    "iso:country":"US",
    "sg:address":"1200 State Hwy Uu",
    "sg:city":"Burfordville",
    "sg:classifiers":[
        {
            "category":"Farming",
            "subcategory":"Livestock Farm",
            "type":"Manufacturing & Wholesale Goods"
        }
    ],
    "sg:phone":"+1 573 243 5572",
    "sg:postcode":"63739",
    "sg:province":"MO",
    "sg:tags":[
        "beef",
        "feedlot",
        "cattle"
    ],
    "wof:name":"Carl Criddle",
    "wof:placetype":"venue"
},
  "geometry": {"coordinates":[-89.824602,37.380052],"type":"Point"}
}