{
  "type": "Feature",
  "properties": {
    "iso:country":"US",
    "sg:address":"3969 W Outer Rd",
    "sg:city":"Arnold",
    "sg:classifiers":[
        {
            "category":"Manufacturing",
            "subcategory":"Furniture",
            "type":"Manufacturing & Wholesale Goods"
        }
    ],
    "sg:phone":"+1 636 464 4644",
    "sg:postcode":"63010",
    "sg:province":"MO",
    "sg:tags":[
        "laminate",
        "mfg",
        "plastic"
    ],
    "wof:name":"Plastic Veneers Inc",
    "wof:placetype":"venue"
},
  "geometry": {"coordinates":[-90.383398,38.40023],"type":"Point"}
}