{
  "type": "Feature",
  "properties": {
    "addr:full":"3949 Mid Rivers Mall Dr Saint Peters MO 63376",
    "addr:housenumber":"3949",
    "addr:postcode":"63376",
    "addr:street":"Mid Rivers Mall Dr",
    "iso:country":"US",
    "sg:address":"3949 Mid Rivers Mall Dr",
    "sg:city":"Saint Peters",
    "sg:classifiers":[
        {
            "category":"Restaurant",
            "type":"Food & Drink"
        }
    ],
    "sg:phone":"+1 636 970 2681",
    "sg:postcode":"63376",
    "sg:province":"MO",
    "sg:tags":[
        "shop",
        "sub"
    ],
    "wof:name":"Subway",
    "wof:placetype":"venue"
},
  "geometry": {"coordinates":[-90.634523,38.745092],"type":"Point"}
}