{
  "type": "Feature",
  "properties": {
    "iso:country":"US",
    "sg:address":"5634 Morganford Rd",
    "sg:city":"Saint Louis",
    "sg:classifiers":[
        {
            "category":"Building & Trades",
            "subcategory":"Plumbing",
            "type":"Services"
        }
    ],
    "sg:phone":"+1 314 353 7320",
    "sg:postcode":"63116",
    "sg:province":"MO",
    "sg:tags":[
        "contractor"
    ],
    "wof:name":"St Cyres Heating",
    "wof:placetype":"venue"
},
  "geometry": {"coordinates":[-90.269075,38.576167],"type":"Point"}
}