{
  "type": "Feature",
  "properties": {
    "iso:country":"US",
    "sg:address":"1318 Highway A",
    "sg:city":"Iberia",
    "sg:classifiers":[
        {
            "category":"Manufacturing",
            "subcategory":"Buildings",
            "type":"Manufacturing & Wholesale Goods"
        },
        {
            "category":"Building & Trades",
            "subcategory":"Construction",
            "type":"Services"
        }
    ],
    "sg:phone":"+1 573 793 2184",
    "sg:postcode":"65486",
    "sg:province":"MO",
    "sg:tags":[
        "management",
        "builder",
        "contractor",
        "industrial",
        "contractors-commercial",
        "home",
        "estimate"
    ],
    "wof:name":"Straight Line Construction",
    "wof:placetype":"venue"
},
  "geometry": {"coordinates":[-92.26076,38.148949],"type":"Point"}
}