{
  "type": "Feature",
  "properties": {
    "addr:full":"1221 E 32nd St Joplin MO 64804",
    "addr:housenumber":"1221",
    "addr:postcode":"64804",
    "addr:street":"E 32Nd St",
    "iso:country":"US",
    "sg:address":"1221 E 32nd St",
    "sg:city":"Joplin",
    "sg:classifiers":[
        {
            "category":"Shopping",
            "subcategory":"Discount & Variety Stores",
            "type":"Retail Goods"
        }
    ],
    "sg:phone":"+1 417 625 1532",
    "sg:postcode":"64804",
    "sg:province":"MO",
    "wof:name":"Dollar General",
    "wof:placetype":"venue"
},
  "geometry": {"coordinates":[-94.50238400000001,37.054963],"type":"Point"}
}