{
  "type": "Feature",
  "properties": {
    "iso:country":"US",
    "sg:address":"21 County Highway 466",
    "sg:city":"Steele",
    "sg:classifiers":[
        {
            "category":"Place Of Worship",
            "subcategory":"Church",
            "type":"Public Place"
        },
        {
            "category":"Place Of Worship",
            "type":"Public Place"
        },
        {
            "category":"Organizations",
            "subcategory":"Religious Organization",
            "type":"Services"
        }
    ],
    "sg:phone":"+1 573 695 3667",
    "sg:postcode":"63877",
    "sg:province":"MO",
    "sg:tags":[
        "god",
        "god-independent",
        "churches-assemblies"
    ],
    "wof:name":"Assembly Of God Church",
    "wof:placetype":"venue"
},
  "geometry": {"coordinates":[-89.894284,36.096005],"type":"Point"}
}