{
  "type": "Feature",
  "properties": {
    "iso:country":"US",
    "sg:address":"3691 N Mission Ln",
    "sg:city":"Joplin",
    "sg:classifiers":[
        {
            "category":"Building & Trades",
            "subcategory":"Construction",
            "type":"Services"
        }
    ],
    "sg:phone":"+1 417 624 1206",
    "sg:postcode":"64801",
    "sg:province":"MO",
    "sg:tags":[
        "house"
    ],
    "wof:name":"Deml Jerry MBL Hm Repr & Svc",
    "wof:placetype":"venue"
},
  "geometry": {"coordinates":[-94.54555999999999,37.127349],"type":"Point"}
}