{
  "type": "Feature",
  "properties": {
    "iso:country":"US",
    "sg:address":"10379 Forest Brook Ln",
    "sg:city":"St Louis",
    "sg:classifiers":[
        {
            "category":"Shopping",
            "type":"Retail Goods"
        }
    ],
    "sg:phone":"+1 314 991 1466",
    "sg:postcode":"63146",
    "sg:province":"MO",
    "sg:tags":[
        "banner"
    ],
    "wof:name":"WYCO Sales Co",
    "wof:placetype":"venue"
},
  "geometry": {"coordinates":[-90.405289,38.679444],"type":"Point"}
}