{
  "type": "Feature",
  "properties": {
    "iso:country":"US",
    "sg:address":"2230 Union Rd",
    "sg:city":"St Louis",
    "sg:classifiers":[
        {
            "category":"Restaurant",
            "type":"Food & Drink"
        }
    ],
    "sg:phone":"+1 314 631 6161",
    "sg:postcode":"63125",
    "sg:province":"MO",
    "wof:name":"Papa John's Pizza",
    "wof:placetype":"venue"
},
  "geometry": {"coordinates":[-90.31433800000001,38.52809],"type":"Point"}
}