{
  "type": "Feature",
  "properties": {
    "iso:country":"US",
    "sg:address":"1831 Sidney St",
    "sg:city":"Saint Louis",
    "sg:classifiers":[
        {
            "category":"Restaurant",
            "type":"Food & Drink"
        }
    ],
    "sg:phone":"+1 314 773 7755",
    "sg:postcode":"63104",
    "sg:province":"MO",
    "sg:tags":[
        "new",
        "american"
    ],
    "sg:website":"www.nichestlouis.com",
    "wof:name":"Niche",
    "wof:placetype":"venue"
},
  "geometry": {"coordinates":[-90.215349,38.603019],"type":"Point"}
}