{
  "type": "Feature",
  "properties": {
    "iso:country":"US",
    "sg:address":"22270 Audrain Rd 320",
    "sg:city":"Mexico",
    "sg:classifiers":[
        {
            "category":"Building & Trades",
            "subcategory":"Construction",
            "type":"Services"
        }
    ],
    "sg:phone":"+1 573 581 0373",
    "sg:postcode":"65265",
    "sg:province":"MO",
    "sg:tags":[
        "co",
        "animal",
        "contractor"
    ],
    "wof:name":"Snell Tel-Com Inc",
    "wof:placetype":"venue"
},
  "geometry": {"coordinates":[-91.88826899999999,39.214145],"type":"Point"}
}