{
  "type": "Feature",
  "properties": {
    "iso:country":"US",
    "sg:address":"3931 Kentucky Ave",
    "sg:city":"Joplin",
    "sg:classifiers":[
        {
            "category":"Organizations",
            "subcategory":"Religious Organization",
            "type":"Services"
        }
    ],
    "sg:phone":"+1 417 781 5801",
    "sg:postcode":"64804",
    "sg:province":"MO",
    "wof:name":"Rhema Bible Training Center",
    "wof:placetype":"venue"
},
  "geometry": {"coordinates":[-94.510116,37.045937],"type":"Point"}
}