{
  "type": "Feature",
  "properties": {
    "iso:country":"US",
    "sg:address":"9645 Dielman Rock Island Industrial Dr",
    "sg:city":"St Louis",
    "sg:classifiers":[
        {
            "category":"Building & Trades",
            "subcategory":"Construction",
            "type":"Services"
        }
    ],
    "sg:phone":"+1 314 432 3770",
    "sg:postcode":"63132",
    "sg:province":"MO",
    "sg:tags":[
        "repairing",
        "remodeling",
        "contractor"
    ],
    "wof:name":"Drain Construction",
    "wof:placetype":"venue"
},
  "geometry": {"coordinates":[-90.379361,38.683023],"type":"Point"}
}