{
  "type": "Feature",
  "properties": {
    "iso:country":"US",
    "sg:address":"1105 Cherry St",
    "sg:city":"Lamar",
    "sg:classifiers":[
        {
            "category":"Building & Trades",
            "subcategory":"Construction",
            "type":"Services"
        }
    ],
    "sg:phone":"+1 417 681 0125",
    "sg:postcode":"64759",
    "sg:province":"MO",
    "sg:tags":[
        "repairing",
        "remodeling",
        "contractor"
    ],
    "wof:name":"Fast Eddie Hot Rod Shop",
    "wof:placetype":"venue"
},
  "geometry": {"coordinates":[-94.279156,37.494462],"type":"Point"}
}