{
  "type": "Feature",
  "properties": {
    "iso:country":"US",
    "sg:address":"104 W Main St",
    "sg:city":"Bowling Green",
    "sg:classifiers":[
        {
            "category":"Home & Garden",
            "subcategory":"Hardware",
            "type":"Retail Goods"
        }
    ],
    "sg:phone":"+1 573 324 5302",
    "sg:postcode":"63334",
    "sg:province":"MO",
    "wof:name":"Schroeder Hardware",
    "wof:placetype":"venue"
},
  "geometry": {"coordinates":[-91.194239,39.341901],"type":"Point"}
}