{
  "type": "Feature",
  "properties": {
    "iso:country":"US",
    "sg:address":"2856 S Glenstone Ave",
    "sg:city":"Springfield",
    "sg:classifiers":[
        {
            "category":"Shopping",
            "type":"Retail Goods"
        }
    ],
    "sg:phone":"+1 417 882 2283",
    "sg:postcode":"65804",
    "sg:province":"MO",
    "sg:tags":[
        "cards",
        "sport",
        "baseball",
        "memorabilia"
    ],
    "wof:name":"Caveman By Vintage Stock",
    "wof:placetype":"venue"
},
  "geometry": {"coordinates":[-93.262489,37.16063],"type":"Point"}
}