{
  "type": "Feature",
  "properties": {
    "iso:country":"US",
    "sg:address":"6329 Windham Ave",
    "sg:city":"St Louis",
    "sg:classifiers":[
        {
            "category":"Retail",
            "subcategory":"Car Wash",
            "type":"Services"
        }
    ],
    "sg:phone":"+1 314 383 3153",
    "sg:postcode":"63120",
    "sg:province":"MO",
    "sg:tags":[
        "polishing",
        "washing"
    ],
    "wof:name":"Tony's Mobile Car Wash",
    "wof:placetype":"venue"
},
  "geometry": {"coordinates":[-90.266564,38.700222],"type":"Point"}
}