{
  "type": "Feature",
  "properties": {
    "iso:country":"US",
    "sg:address":"3285 Old Hwy 100",
    "sg:city":"Villa Ridge",
    "sg:classifiers":[
        {
            "category":"Retail",
            "subcategory":"Repair Shop",
            "type":"Services"
        }
    ],
    "sg:phone":"+1 636 742 0263",
    "sg:postcode":"63089",
    "sg:province":"MO",
    "sg:tags":[
        "pipeline",
        "maintenance"
    ],
    "wof:name":"Phillips Pipeline Co",
    "wof:placetype":"venue"
},
  "geometry": {"coordinates":[-90.894108,38.498741],"type":"Point"}
}