{
  "type": "Feature",
  "properties": {
    "iso:country":"US",
    "sg:address":"10440 Capitol Pl",
    "sg:city":"Saint Louis",
    "sg:classifiers":[
        {
            "category":"Professional",
            "subcategory":"Business Services",
            "type":"Services"
        }
    ],
    "sg:phone":"+1 314 725 6466",
    "sg:postcode":"63131",
    "sg:province":"MO",
    "sg:tags":[
        "consulting"
    ],
    "wof:name":"Aloyse Design",
    "wof:placetype":"venue"
},
  "geometry": {"coordinates":[-90.409716,38.64173],"type":"Point"}
}