{
  "type": "Feature",
  "properties": {
    "iso:country":"US",
    "sg:address":"38755 State Hwy 146",
    "sg:city":"Gilman City",
    "sg:phone":"+1 660 876 5281",
    "sg:postcode":"64642",
    "sg:province":"MO",
    "sg:tags":[
        "farm",
        "corn",
        "soybean"
    ],
    "wof:name":"Rankin Farms",
    "wof:placetype":"venue"
},
  "geometry": {"coordinates":[-93.87810500000001,40.151647],"type":"Point"}
}