{
  "type": "Feature",
  "properties": {
    "iso:country":"US",
    "sg:address":"2324 Chaffee Dr",
    "sg:city":"St Louis",
    "sg:classifiers":[
        {
            "category":"Retail",
            "subcategory":"Repair Shop",
            "type":"Services"
        }
    ],
    "sg:phone":"+1 314 664 3900",
    "sg:postcode":"63146",
    "sg:province":"MO",
    "sg:tags":[
        "equipment"
    ],
    "wof:name":"Royalab",
    "wof:placetype":"venue"
},
  "geometry": {"coordinates":[-90.436787,38.704123],"type":"Point"}
}