{
  "type": "Feature",
  "properties": {
    "iso:country":"US",
    "sg:address":"4801 E Linwood Blvd",
    "sg:city":"Kansas City",
    "sg:classifiers":[
        {
            "category":"Organizations",
            "subcategory":"Community Association",
            "type":"Services"
        }
    ],
    "sg:phone":"+1 816 922 2887",
    "sg:postcode":"64128",
    "sg:province":"MO",
    "sg:tags":[
        "military"
    ],
    "wof:name":"American Veterans",
    "wof:placetype":"venue"
},
  "geometry": {"coordinates":[-94.528222,39.067274],"type":"Point"}
}