{
  "type": "Feature",
  "properties": {
    "iso:country":"US",
    "sg:address":"410 W Main St",
    "sg:city":"Festus",
    "sg:classifiers":[
        {
            "category":"Utilities",
            "subcategory":"Natural Gas",
            "type":"Services"
        }
    ],
    "sg:phone":"+1 636 931 8383",
    "sg:postcode":"63028",
    "sg:province":"MO",
    "sg:website":"www.lacledegas.com",
    "wof:name":"Missouri Natural Gas Co",
    "wof:placetype":"venue"
},
  "geometry": {"coordinates":[-90.394351,38.21972],"type":"Point"}
}