{
  "type": "Feature",
  "properties": {
    "iso:country":"US",
    "sg:address":"5925 Stedman Rd",
    "sg:city":"Columbia",
    "sg:classifiers":[
        {
            "category":"Building & Trades",
            "subcategory":"Plumbing",
            "type":"Services"
        }
    ],
    "sg:phone":"+1 573 447 4381",
    "sg:postcode":"65203",
    "sg:province":"MO",
    "sg:tags":[
        "contractor"
    ],
    "wof:name":"Air Tech Of Mid Missouri",
    "wof:placetype":"venue"
},
  "geometry": {"coordinates":[-92.421325,38.893193],"type":"Point"}
}