{
  "type": "Feature",
  "properties": {
    "iso:country":"US",
    "sg:address":"8370 Watson Rd",
    "sg:city":"Saint Louis",
    "sg:classifiers":[
        {
            "category":"Retail",
            "subcategory":"Repair Shop",
            "type":"Services"
        }
    ],
    "sg:phone":"+1 314 843 3010",
    "sg:postcode":"63119",
    "sg:province":"MO",
    "wof:name":"Helens Clock Company",
    "wof:placetype":"venue"
},
  "geometry": {"coordinates":[-90.352193,38.565899],"type":"Point"}
}