{
  "type": "Feature",
  "properties": {
    "iso:country":"US",
    "sg:address":"1101 S Grand Ave",
    "sg:city":"Carthage",
    "sg:classifiers":[
        {
            "category":"Retail",
            "subcategory":"Laundry & Dry Cleaning",
            "type":"Services"
        }
    ],
    "sg:phone":"+1 417 358 7441",
    "sg:postcode":"64836",
    "sg:province":"MO",
    "sg:tags":[
        "cleaners"
    ],
    "wof:name":"Fast One Hour Cleaners",
    "wof:placetype":"venue"
},
  "geometry": {"coordinates":[-94.30954699999999,37.169287],"type":"Point"}
}