{
  "type": "Feature",
  "properties": {
    "iso:country":"US",
    "sg:address":"16438 Hickory Pine Ln",
    "sg:city":"Ballwin",
    "sg:classifiers":[
        {
            "category":"Retail",
            "subcategory":"Laundry & Dry Cleaning",
            "type":"Services"
        }
    ],
    "sg:phone":"+1 636 458 0022",
    "sg:postcode":"63011",
    "sg:province":"MO",
    "sg:tags":[
        "cleaners",
        "rug",
        "carpet"
    ],
    "wof:name":"M & M Custom Cleaning",
    "wof:placetype":"venue"
},
  "geometry": {"coordinates":[-90.615424,38.58534],"type":"Point"}
}