{
  "type": "Feature",
  "properties": {
    "iso:country":"US",
    "sg:address":"64 N Clark St",
    "sg:city":"Sullivan",
    "sg:classifiers":[
        {
            "category":"Utilities",
            "subcategory":"Telephone",
            "type":"Services"
        },
        {
            "category":"Professional",
            "subcategory":"Advertising",
            "type":"Services"
        }
    ],
    "sg:phone":"+1 573 468 8081",
    "sg:postcode":"63080",
    "sg:province":"MO",
    "sg:tags":[
        "guide"
    ],
    "sg:website":"www.fidnet.com",
    "wof:name":"Fidelity Communications Co",
    "wof:placetype":"venue"
},
  "geometry": {"coordinates":[-91.160922,38.210642],"type":"Point"}
}