{
  "type": "Feature",
  "properties": {
    "iso:country":"US",
    "sg:address":"901 NE Colbern Rd",
    "sg:city":"Lees Summit",
    "sg:classifiers":[
        {
            "category":"Autos & Motor Vehicles",
            "subcategory":"Fuel & Gas Station",
            "type":"Retail Goods"
        }
    ],
    "sg:phone":"+1 816 524 4760",
    "sg:postcode":"64086",
    "sg:province":"MO",
    "sg:tags":[
        "oil"
    ],
    "wof:name":"Rush Hour 3-66",
    "wof:placetype":"venue"
},
  "geometry": {"coordinates":[-94.357884,38.94605],"type":"Point"}
}