{
  "type": "Feature",
  "properties": {
    "iso:country":"US",
    "sg:address":"614 W 3rd St",
    "sg:city":"Mountain Grove",
    "sg:classifiers":[
        {
            "category":"Restaurant",
            "type":"Food & Drink"
        }
    ],
    "sg:menulink":"http://www.allmenus.com/mo/mountain-grove/201738-sonic/menu/",
    "sg:phone":"+1 417 926 5322",
    "sg:postcode":"65711",
    "sg:province":"MO",
    "sg:tags":[
        "burger",
        "american"
    ],
    "wof:name":"Sonic",
    "wof:placetype":"venue"
},
  "geometry": {"coordinates":[-92.272548,37.130973],"type":"Point"}
}