{
  "type": "Feature",
  "properties": {
    "iso:country":"US",
    "sg:address":"1505 S Maiden Ln",
    "sg:city":"Joplin",
    "sg:classifiers":[
        {
            "category":"Manufacturing",
            "subcategory":"Metals",
            "type":"Manufacturing & Wholesale Goods"
        }
    ],
    "sg:phone":"+1 417 781 3200",
    "sg:postcode":"64801",
    "sg:province":"MO",
    "sg:tags":[
        "product",
        "wire",
        "fabricated"
    ],
    "sg:website":"www.labarge.com",
    "wof:name":"LA Barge Electronics",
    "wof:placetype":"venue"
},
  "geometry": {"coordinates":[-94.53142699999999,37.075555],"type":"Point"}
}