{
  "type": "Feature",
  "properties": {
    "iso:country":"US",
    "sg:address":"105 N Main St",
    "sg:city":"Vienna",
    "sg:classifiers":[
        {
            "category":"Place Of Worship",
            "subcategory":"Church",
            "type":"Public Place"
        },
        {
            "category":"Place Of Worship",
            "type":"Public Place"
        },
        {
            "category":"Education",
            "subcategory":"School",
            "type":"Public Place"
        }
    ],
    "sg:phone":"+1 573 422 3950",
    "sg:postcode":"65582",
    "sg:province":"MO",
    "sg:tags":[
        "churches-catholic-traditional",
        "religious",
        "churches-catholic",
        "interest"
    ],
    "wof:name":"Visitation Interparish School",
    "wof:placetype":"venue"
},
  "geometry": {"coordinates":[-91.94685,38.187889],"type":"Point"}
}