{
  "type": "Feature",
  "properties": {
    "iso:country":"US",
    "sg:address":"4625 Gravois Ave.",
    "sg:city":"St Louis",
    "sg:classifiers":[
        {
            "category":"Restaurant",
            "type":"Food & Drink"
        }
    ],
    "sg:phone":"+1 314 481 8000",
    "sg:postcode":"63116",
    "sg:province":"MO",
    "sg:tags":[
        "modern",
        "mediterranean",
        "european"
    ],
    "sg:website":"laganinipizzeria.com/",
    "wof:name":"Laganini Pizzeria & Restaurant",
    "wof:placetype":"venue"
},
  "geometry": {"coordinates":[-90.264396,38.583475],"type":"Point"}
}