{
  "type": "Feature",
  "properties": {
    "iso:country":"US",
    "sg:address":"2031 Cape la Croix Rd",
    "sg:city":"Cape Girardeau",
    "sg:classifiers":[
        {
            "category":"Personal",
            "subcategory":"Tanning Parlor",
            "type":"Services"
        },
        {
            "category":"Personal",
            "type":"Services"
        }
    ],
    "sg:phone":"+1 573 334 0298",
    "sg:postcode":"63701",
    "sg:province":"MO",
    "sg:tags":[
        "salon"
    ],
    "wof:name":"Under The Sun",
    "wof:placetype":"venue"
},
  "geometry": {"coordinates":[-89.57328800000001,37.337369],"type":"Point"}
}