{
  "type": "Feature",
  "properties": {
    "iso:country":"US",
    "sg:address":"20502 E 351st St",
    "sg:city":"Archie",
    "sg:classifiers":[
        {
            "category":"Building & Trades",
            "subcategory":"Construction",
            "type":"Services"
        }
    ],
    "sg:phone":"+1 816 430 5248",
    "sg:postcode":"64725",
    "sg:province":"MO",
    "sg:tags":[
        "home",
        "family",
        "contractor"
    ],
    "wof:name":"Lotspeich Construction Co Inc",
    "wof:placetype":"venue"
},
  "geometry": {"coordinates":[-94.367474,38.480035],"type":"Point"}
}