{
  "type": "Feature",
  "properties": {
    "iso:country":"US",
    "sg:address":"912 Kersting Rd",
    "sg:city":"Wentzville",
    "sg:classifiers":[
        {
            "category":"Farming",
            "subcategory":"Farm",
            "type":"Manufacturing & Wholesale Goods"
        }
    ],
    "sg:phone":"+1 636 327 4433",
    "sg:postcode":"63385",
    "sg:province":"MO",
    "wof:name":"Sommer Farms Inc",
    "wof:placetype":"venue"
},
  "geometry": {"coordinates":[-90.78854800000001,38.832899],"type":"Point"}
}