{
  "type": "Feature",
  "properties": {
    "iso:country":"US",
    "sg:address":"322 SE Douglas St",
    "sg:city":"Lees Summit",
    "sg:classifiers":[
        {
            "category":"Shopping",
            "subcategory":"Computers & Home Electronics",
            "type":"Retail Goods"
        }
    ],
    "sg:phone":"+1 816 524 1047",
    "sg:postcode":"64063",
    "sg:province":"MO",
    "sg:tags":[
        "repair"
    ],
    "wof:name":"G & T Electronics",
    "wof:placetype":"venue"
},
  "geometry": {"coordinates":[-94.375964,38.912159],"type":"Point"}
}