{
  "type": "Feature",
  "properties": {
    "iso:country":"US",
    "sg:address":"22395 US Hwy 65",
    "sg:city":"Sedalia",
    "sg:classifiers":[
        {
            "category":"Building & Trades",
            "subcategory":"Construction",
            "type":"Services"
        }
    ],
    "sg:phone":"+1 660 827 5542",
    "sg:postcode":"65301",
    "sg:province":"MO",
    "sg:tags":[
        "excavation",
        "contractor",
        "general"
    ],
    "wof:name":"Needy Custom Contracting Inc",
    "wof:placetype":"venue"
},
  "geometry": {"coordinates":[-93.226164,38.74992],"type":"Point"}
}