{
  "type": "Feature",
  "properties": {
    "iso:country":"US",
    "sg:address":"713 Camelot Estates Dr",
    "sg:city":"Hillsboro",
    "sg:classifiers":[
        {
            "category":"Insurance",
            "subcategory":"Insurance Agent",
            "type":"Services"
        }
    ],
    "sg:phone":"+1 636 789 4532",
    "sg:postcode":"63050",
    "sg:province":"MO",
    "wof:name":"Prudential Insurance Agency",
    "wof:placetype":"venue"
},
  "geometry": {"coordinates":[-90.572231,38.228423],"type":"Point"}
}