{
  "type": "Feature",
  "properties": {
    "iso:country":"US",
    "sg:address":"2318 N Lindbergh Blvd",
    "sg:city":"St Louis",
    "sg:classifiers":[
        {
            "category":"Building & Trades",
            "subcategory":"Pest Control",
            "type":"Services"
        }
    ],
    "sg:phone":"+1 314 542 0322",
    "sg:postcode":"63114",
    "sg:province":"MO",
    "wof:name":"Educational Entomology Cnsltnt",
    "wof:placetype":"venue"
},
  "geometry": {"coordinates":[-90.408874,38.705246],"type":"Point"}
}