{
  "type": "Feature",
  "properties": {
    "iso:country":"US",
    "sg:address":"1406 US Hwy 40",
    "sg:city":"Blue Springs",
    "sg:classifiers":[
        {
            "category":"Banks & Credit Unions",
            "subcategory":"Investment Brokerage",
            "type":"Services"
        }
    ],
    "sg:phone":"+1 816 220 8647",
    "sg:postcode":"64015",
    "sg:province":"MO",
    "sg:tags":[
        "advisory",
        "financial"
    ],
    "wof:name":"Clayton Financial Group",
    "wof:placetype":"venue"
},
  "geometry": {"coordinates":[-94.281701,39.009316],"type":"Point"}
}