{
  "type": "Feature",
  "properties": {
    "iso:country":"US",
    "sg:address":"304 S Walnut St",
    "sg:city":"Steele",
    "sg:classifiers":[
        {
            "category":"Food & Beverages",
            "subcategory":"Groceries & Convenience Stores",
            "type":"Retail Goods"
        }
    ],
    "sg:phone":"+1 573 695 7487",
    "sg:postcode":"63877",
    "sg:province":"MO",
    "sg:website":"http://www.flashmarketinc.com",
    "wof:name":"Flash Market, Inc.",
    "wof:placetype":"venue"
},
  "geometry": {"coordinates":[-89.832836,36.081576],"type":"Point"}
}