{
  "type": "Feature",
  "properties": {
    "iso:country":"US",
    "sg:address":"1115 Olivette Executive Pkwy",
    "sg:city":"St Louis",
    "sg:classifiers":[
        {
            "category":"Professional",
            "subcategory":"Management & Consulting",
            "type":"Services"
        }
    ],
    "sg:phone":"+1 314 569 7100",
    "sg:postcode":"63132",
    "sg:province":"MO",
    "sg:tags":[
        "counselor",
        "public",
        "relations"
    ],
    "sg:website":"www.millenniumcom.com",
    "wof:name":"Millennium Communications Inc",
    "wof:placetype":"venue"
},
  "geometry": {"coordinates":[-90.37241400000001,38.675871],"type":"Point"}
}