{
  "type": "Feature",
  "properties": {
    "iso:country":"US",
    "sg:address":"415 E Liberty St",
    "sg:city":"Mexico",
    "sg:classifiers":[
        {
            "category":"Banks & Credit Unions",
            "subcategory":"Bank",
            "type":"Services"
        }
    ],
    "sg:phone":"+1 573 582 1390",
    "sg:postcode":"65265",
    "sg:province":"MO",
    "sg:tags":[
        "depository",
        "banking"
    ],
    "wof:name":"Cash 4u",
    "wof:placetype":"venue"
},
  "geometry": {"coordinates":[-91.87944,39.17051],"type":"Point"}
}