{
  "type": "Feature",
  "properties": {
    "iso:country":"US",
    "sg:address":"5800 Old Little Antire Rd",
    "sg:city":"High Ridge",
    "sg:classifiers":[
        {
            "category":"Utilities",
            "subcategory":"Sewage",
            "type":"Services"
        }
    ],
    "sg:phone":"+1 636 376 3331",
    "sg:postcode":"63049",
    "sg:province":"MO",
    "sg:tags":[
        "system",
        "sewerage"
    ],
    "wof:name":"Northwest Public Sewer Dist",
    "wof:placetype":"venue"
},
  "geometry": {"coordinates":[-90.540283,38.45644],"type":"Point"}
}