{
  "type": "Feature",
  "properties": {
    "iso:country":"US",
    "sg:address":"3738 State Hwy Jj",
    "sg:city":"Blue Eye",
    "sg:classifiers":[
        {
            "category":"Organizations",
            "subcategory":"Non-profit Organization",
            "type":"Services"
        }
    ],
    "sg:phone":"+1 417 779 3932",
    "sg:postcode":"65611",
    "sg:province":"AR",
    "sg:tags":[
        "social"
    ],
    "wof:name":"Committee For Combs Landing",
    "wof:placetype":"venue"
},
  "geometry": {"coordinates":[-93.343254,36.582823],"type":"Point"}
}