{
  "type": "Feature",
  "properties": {
    "iso:country":"US",
    "sg:address":"1301 Washington Ave",
    "sg:city":"St Louis",
    "sg:classifiers":[
        {
            "category":"Real Estate",
            "subcategory":"Real Estate Agent",
            "type":"Services"
        }
    ],
    "sg:phone":"+1 314 231 2264",
    "sg:postcode":"63103",
    "sg:province":"MO",
    "sg:tags":[
        "desk",
        "space"
    ],
    "wof:name":"Fashion Square LLC",
    "wof:placetype":"venue"
},
  "geometry": {"coordinates":[-90.199557,38.632358],"type":"Point"}
}