{
  "type": "Feature",
  "properties": {
    "iso:country":"US",
    "sg:address":"109 E 31st St S",
    "sg:city":"Independence",
    "sg:classifiers":[
        {
            "category":"Personal",
            "type":"Services"
        },
        {
            "category":"Structure",
            "subcategory":"Warehouse",
            "type":"Public Place"
        },
        {
            "category":"Retail",
            "subcategory":"Storage",
            "type":"Services"
        }
    ],
    "sg:phone":"+1 888 772 2293",
    "sg:postcode":"64055",
    "sg:province":"MO",
    "sg:tags":[
        "moving-self",
        "full",
        "warehouses-public-commercial",
        "automobile",
        "household",
        "recreational",
        "commercial",
        "campers-storage",
        "vehicle",
        "mover",
        "self",
        "boat"
    ],
    "sg:website":"http://www.beststoragespace.net/callus/sp-001-003a",
    "wof:name":"Public Storage - Independence",
    "wof:placetype":"venue"
},
  "geometry": {"coordinates":[-94.427879,39.065142],"type":"Point"}
}