{
  "type": "Feature",
  "properties": {
    "iso:country":"US",
    "sg:address":"215 S Washington St",
    "sg:city":"Neosho",
    "sg:classifiers":[
        {
            "category":"Travel",
            "subcategory":"Travel Agent",
            "type":"Entertainment"
        }
    ],
    "sg:phone":"+1 417 451 9963",
    "sg:postcode":"64850",
    "sg:province":"MO",
    "sg:tags":[
        "agency",
        "bureau"
    ],
    "wof:name":"Travel With Us",
    "wof:placetype":"venue"
},
  "geometry": {"coordinates":[-94.36716199999999,36.868453],"type":"Point"}
}