{
  "type": "Feature",
  "properties": {
    "iso:country":"US",
    "sg:address":"105 S Buchanan St",
    "sg:city":"Maryville",
    "sg:classifiers":[
        {
            "category":"Personal",
            "subcategory":"Beauty Salon",
            "type":"Services"
        }
    ],
    "sg:phone":"+1 660 562 3200",
    "sg:postcode":"64468",
    "sg:province":"MO",
    "sg:tags":[
        "shop"
    ],
    "wof:name":"Salon I",
    "wof:placetype":"venue"
},
  "geometry": {"coordinates":[-94.874105,40.346005],"type":"Point"}
}