{
  "type": "Feature",
  "properties": {
    "iso:country":"US",
    "sg:address":"3301 State Rd H",
    "sg:city":"Fulton",
    "sg:classifiers":[
        {
            "category":"Organizations",
            "subcategory":"Religious Organization",
            "type":"Services"
        }
    ],
    "sg:phone":"+1 573 592 0180",
    "sg:postcode":"65251",
    "sg:province":"MO",
    "wof:name":"Carrington Baptist Church",
    "wof:placetype":"venue"
},
  "geometry": {"coordinates":[-92.058498,38.808232],"type":"Point"}
}