{
  "type": "Feature",
  "properties": {
    "iso:country":"US",
    "sg:address":"7907 NW 76 Ter",
    "sg:city":"Kansas City",
    "sg:classifiers":[
        {
            "category":"Shopping",
            "subcategory":"Crafts & Fabrics",
            "type":"Retail Goods"
        }
    ],
    "sg:phone":"+1 816 741 2677",
    "sg:postcode":"64152",
    "sg:province":"MO",
    "sg:tags":[
        "sewing"
    ],
    "wof:name":"Itchin To Stitch",
    "wof:placetype":"venue"
},
  "geometry": {"coordinates":[-94.671674,39.235578],"type":"Point"}
}