{
  "type": "Feature",
  "properties": {
    "iso:country":"US",
    "sg:address":"850 S Breeze Rd",
    "sg:city":"O Fallon",
    "sg:classifiers":[
        {
            "category":"Building & Trades",
            "subcategory":"Construction",
            "type":"Services"
        },
        {
            "category":"Professional",
            "subcategory":"Management & Consulting",
            "type":"Services"
        }
    ],
    "sg:phone":"+1 636 447 0711",
    "sg:postcode":"63304",
    "sg:province":"MO",
    "sg:tags":[
        "control",
        "erosion",
        "contractor"
    ],
    "wof:name":"Ron's Erosion Control",
    "wof:placetype":"venue"
},
  "geometry": {"coordinates":[-90.659721,38.722207],"type":"Point"}
}