{
  "type": "Feature",
  "properties": {
    "addr:full":"17121 US Hwy 40 Independence MO 64055",
    "addr:postcode":"17121;64055",
    "addr:street":"Us Hwy 40",
    "iso:country":"US",
    "sg:address":"17121 US Hwy 40",
    "sg:city":"Independence",
    "sg:classifiers":[
        {
            "category":"Autos & Motor Vehicles",
            "subcategory":"Fuel & Gas Station",
            "type":"Retail Goods"
        }
    ],
    "sg:phone":"+1 816 373 5724",
    "sg:postcode":"64055",
    "sg:province":"MO",
    "sg:tags":[
        "oil"
    ],
    "wof:name":"Conoco",
    "wof:placetype":"venue"
},
  "geometry": {"coordinates":[-94.377754,39.033983],"type":"Point"}
}