{
  "type": "Feature",
  "properties": {
    "iso:country":"US",
    "sg:address":"1202 Wildwood",
    "sg:city":"Republic",
    "sg:classifiers":[
        {
            "category":"Building & Trades",
            "subcategory":"Construction",
            "type":"Services"
        }
    ],
    "sg:phone":"+1 417 732 8011",
    "sg:postcode":"65738",
    "sg:province":"MO",
    "sg:tags":[
        "masonry",
        "contractor"
    ],
    "wof:name":"Detherow Masonary Construction",
    "wof:placetype":"venue"
},
  "geometry": {"coordinates":[-93.46027599999999,37.119558],"type":"Point"}
}