{
  "type": "Feature",
  "properties": {
    "iso:country":"US",
    "sg:address":"33200 E 179th St",
    "sg:city":"Pleasant Hill",
    "sg:classifiers":[
        {
            "category":"Real Estate",
            "subcategory":"Real Estate Operator",
            "type":"Services"
        }
    ],
    "sg:phone":"+1 816 987 5787",
    "sg:postcode":"64080",
    "sg:province":"MO",
    "sg:tags":[
        "property",
        "lessor"
    ],
    "wof:name":"Roy Kennedy",
    "wof:placetype":"venue"
},
  "geometry": {"coordinates":[-94.219069,38.790532],"type":"Point"}
}