{
  "type": "Feature",
  "properties": {
    "iso:country":"US",
    "sg:address":"720 Olive St",
    "sg:city":"St Louis",
    "sg:classifiers":[
        {
            "category":"Shopping",
            "subcategory":"Clothing, Apparel, & Fashions",
            "type":"Retail Goods"
        }
    ],
    "sg:phone":"+1 314 436 6969",
    "sg:postcode":"63101",
    "sg:province":"MO",
    "sg:tags":[
        "leather"
    ],
    "wof:name":"Fur & Leather Gallery",
    "wof:placetype":"venue"
},
  "geometry": {"coordinates":[-90.191316,38.62826],"type":"Point"}
}