{
  "type": "Feature",
  "properties": {
    "iso:country":"US",
    "sg:address":"1504 Hamilton Ave",
    "sg:city":"Saint Louis",
    "sg:classifiers":[
        {
            "category":"Food & Beverages",
            "subcategory":"Liquor & Beverages",
            "type":"Retail Goods"
        }
    ],
    "sg:phone":"+1 314 385 8283",
    "sg:postcode":"63112",
    "sg:province":"MO",
    "sg:tags":[
        "beer",
        "wine",
        "spirit",
        "alcoholic"
    ],
    "wof:name":"Phoenix Package Liquor II",
    "wof:placetype":"venue"
},
  "geometry": {"coordinates":[-90.28220399999999,38.674],"type":"Point"}
}