{
  "type": "Feature",
  "properties": {
    "iso:country":"US",
    "sg:address":"515 Maple St",
    "sg:city":"Greenfield",
    "sg:classifiers":[
        {
            "category":"Restaurant",
            "type":"Food & Drink"
        }
    ],
    "sg:menulink":"http://www.allmenus.com/mo/center/148645-subway/menu/",
    "sg:phone":"+1 417 637 5860",
    "sg:postcode":"65661",
    "sg:province":"MO",
    "sg:tags":[
        "american",
        "sandwich"
    ],
    "wof:name":"Subway",
    "wof:placetype":"venue"
},
  "geometry": {"coordinates":[-93.845637,37.412296],"type":"Point"}
}