{
  "type": "Feature",
  "properties": {
    "iso:country":"US",
    "sg:address":"2715 Parthenon Dr",
    "sg:city":"De Soto",
    "sg:classifiers":[
        {
            "category":"Professional",
            "subcategory":"Employment Agencies",
            "type":"Services"
        }
    ],
    "sg:phone":"+1 636 586 6451",
    "sg:postcode":"63020",
    "sg:province":"MO",
    "sg:tags":[
        "staffing"
    ],
    "wof:name":"Express Personnel Services",
    "wof:placetype":"venue"
},
  "geometry": {"coordinates":[-90.460967,38.137368],"type":"Point"}
}