{
  "type": "Feature",
  "properties": {
    "iso:country":"US",
    "sg:address":"1050 E Walnut St",
    "sg:city":"Springfield",
    "sg:classifiers":[
        {
            "category":"Professional",
            "subcategory":"Detective & Security Services",
            "type":"Services"
        }
    ],
    "sg:phone":"+1 417 832 9888",
    "sg:postcode":"65806",
    "sg:province":"MO",
    "sg:tags":[
        "investigator"
    ],
    "wof:name":"J Miller Investigation Svc",
    "wof:placetype":"venue"
},
  "geometry": {"coordinates":[-93.281137,37.206584],"type":"Point"}
}