{
  "type": "Feature",
  "properties": {
    "iso:country":"US",
    "sg:address":"307 N Missouri St",
    "sg:city":"Potosi",
    "sg:classifiers":[
        {
            "category":"Health Services",
            "subcategory":"Optometrist",
            "type":"Services"
        }
    ],
    "sg:phone":"+1 573 438 3415",
    "sg:postcode":"63664",
    "sg:province":"MO",
    "wof:name":"Potosi Optometric Ctr",
    "wof:placetype":"venue"
},
  "geometry": {"coordinates":[-90.78592999999999,37.938055],"type":"Point"}
}