{
  "type": "Feature",
  "properties": {
    "iso:country":"US",
    "sg:address":"78 S Odell Ave",
    "sg:city":"Marshall",
    "sg:classifiers":[
        {
            "category":"Organizations",
            "subcategory":"Religious Organization",
            "type":"Services"
        }
    ],
    "sg:phone":"+1 660 886 5546",
    "sg:postcode":"65340",
    "sg:province":"MO",
    "wof:name":"First Baptist Church",
    "wof:placetype":"venue"
},
  "geometry": {"coordinates":[-93.194804,39.120675],"type":"Point"}
}