{
  "type": "Feature",
  "properties": {
    "iso:country":"US",
    "sg:address":"629 E Morgan St",
    "sg:city":"Boonville",
    "sg:classifiers":[
        {
            "category":"Retail",
            "subcategory":"Funeral Services",
            "type":"Services"
        }
    ],
    "sg:phone":"+1 660 882 2311",
    "sg:postcode":"65233",
    "sg:province":"MO",
    "sg:tags":[
        "director"
    ],
    "wof:name":"B W Thacher Funeral Home",
    "wof:placetype":"venue"
},
  "geometry": {"coordinates":[-92.74212799999999,38.976927],"type":"Point"}
}