{
  "type": "Feature",
  "properties": {
    "iso:country":"US",
    "sg:address":"19550 E 39th St S Ste 330",
    "sg:city":"Independence",
    "sg:classifiers":[
        {
            "category":"Health Services",
            "subcategory":"Medical Lab",
            "type":"Services"
        }
    ],
    "sg:phone":"+1 866 322 7154",
    "sg:postcode":"64057",
    "sg:province":"MO",
    "wof:name":"STD Tests Independence STD Testing Center",
    "wof:placetype":"venue"
},
  "geometry": {"coordinates":[-94.350332,39.047749],"type":"Point"}
}