{
  "type": "Feature",
  "properties": {
    "iso:country":"US",
    "sg:address":"12628 State Hwy 86",
    "sg:city":"Neosho",
    "sg:classifiers":[
        {
            "category":"Manufacturing",
            "subcategory":"Glass & Minerals",
            "type":"Manufacturing & Wholesale Goods"
        }
    ],
    "sg:phone":"+1 417 451 5650",
    "sg:postcode":"64850",
    "sg:province":"MO",
    "sg:tags":[
        "stone",
        "cut",
        "product"
    ],
    "wof:name":"Ozark Homes Warehouse & Stge",
    "wof:placetype":"venue"
},
  "geometry": {"coordinates":[-94.342753,36.869328],"type":"Point"}
}