{
  "type": "Feature",
  "properties": {
    "iso:country":"US",
    "sg:address":"7516 N Broadway",
    "sg:city":"St Louis",
    "sg:classifiers":[
        {
            "category":"Professional",
            "subcategory":"Accounting & Tax Preparation",
            "type":"Services"
        }
    ],
    "sg:phone":"+1 314 385 8300",
    "sg:postcode":"63147",
    "sg:province":"MO",
    "sg:tags":[
        "return",
        "filing"
    ],
    "wof:name":"Atkins & Associates Inc",
    "wof:placetype":"venue"
},
  "geometry": {"coordinates":[-90.22959899999999,38.703216],"type":"Point"}
}