{
  "type": "Feature",
  "properties": {
    "iso:country":"US",
    "sg:address":"3265 Pine Cliff Rd",
    "sg:city":"Glencoe",
    "sg:classifiers":[
        {
            "category":"Professional",
            "type":"Services"
        }
    ],
    "sg:phone":"+1 636 458 3666",
    "sg:postcode":"63038",
    "sg:province":"MO",
    "wof:name":"Eyermann",
    "wof:placetype":"venue"
},
  "geometry": {"coordinates":[-90.623983,38.561771],"type":"Point"}
}