{
  "type": "Feature",
  "properties": {
    "iso:country":"US",
    "sg:address":"1030 S Crysler Ave",
    "sg:city":"Independence",
    "sg:classifiers":[
        {
            "category":"Government",
            "subcategory":"Office",
            "type":"Public Place"
        }
    ],
    "sg:phone":"+1 816 325 7627",
    "sg:postcode":"64052",
    "sg:province":"MO",
    "sg:tags":[
        "village"
    ],
    "sg:website":"www.ci.independence.mo.us",
    "wof:name":"Street Maintenance",
    "wof:placetype":"venue"
},
  "geometry": {"coordinates":[-94.432326,39.082063],"type":"Point"}
}