{
  "type": "Feature",
  "properties": {
    "iso:country":"US",
    "sg:address":"45 Jason Ct",
    "sg:city":"St Charles",
    "sg:classifiers":[
        {
            "category":"Retail",
            "subcategory":"Animal Services",
            "type":"Services"
        }
    ],
    "sg:phone":"+1 636 441 9442",
    "sg:postcode":"63304",
    "sg:province":"MO",
    "sg:tags":[
        "pet",
        "grooming",
        "washing"
    ],
    "wof:name":"Designer Dogs",
    "wof:placetype":"venue"
},
  "geometry": {"coordinates":[-90.655935,38.726771],"type":"Point"}
}