{
  "type": "Feature",
  "properties": {
    "iso:country":"US",
    "sg:address":"4936 Christy Blvd",
    "sg:city":"St Louis",
    "sg:classifiers":[
        {
            "category":"Insurance",
            "subcategory":"Insurance Agent",
            "type":"Services"
        }
    ],
    "sg:phone":"+1 314 353 5773",
    "sg:postcode":"63116",
    "sg:province":"MO",
    "wof:name":"Rodney D Young Insurance",
    "wof:placetype":"venue"
},
  "geometry": {"coordinates":[-90.276532,38.58468],"type":"Point"}
}