{
  "type": "Feature",
  "properties": {
    "iso:country":"US",
    "sg:address":"8550 N Granby Ave",
    "sg:city":"Kansas City",
    "sg:classifiers":[
        {
            "category":"Shopping",
            "subcategory":"Shoes",
            "type":"Retail Goods"
        }
    ],
    "sg:phone":"+1 816 420 8862",
    "sg:postcode":"64154",
    "sg:province":"MO",
    "wof:name":"Trutnas Investment Company",
    "wof:placetype":"venue"
},
  "geometry": {"coordinates":[-94.627545,39.25193],"type":"Point"}
}