{
  "type": "Feature",
  "properties": {
    "iso:country":"US",
    "sg:address":"9807 S 40 Dr",
    "sg:city":"St Louis",
    "sg:classifiers":[
        {
            "category":"Manufacturing",
            "subcategory":"Food",
            "type":"Manufacturing & Wholesale Goods"
        }
    ],
    "sg:phone":"+1 314 787 2828",
    "sg:postcode":"63124",
    "sg:province":"MO",
    "sg:tags":[
        "preparation",
        "mfg"
    ],
    "sg:website":"www.custombits.com",
    "wof:name":"Custom Industries Usa Inc",
    "wof:placetype":"venue"
},
  "geometry": {"coordinates":[-90.38732,38.632519],"type":"Point"}
}