{
  "type": "Feature",
  "properties": {
    "iso:country":"US",
    "sg:address":"608 S 2 St",
    "sg:city":"Platte City",
    "sg:classifiers":[
        {
            "category":"Shopping",
            "subcategory":"Used Merchandise",
            "type":"Retail Goods"
        }
    ],
    "sg:phone":"+1 816 858 4149",
    "sg:postcode":"64079",
    "sg:province":"MO",
    "sg:tags":[
        "shop",
        "consignment"
    ],
    "wof:name":"Platte River Shop",
    "wof:placetype":"venue"
},
  "geometry": {"coordinates":[-94.78233899999999,39.369279],"type":"Point"}
}