{
  "type": "Feature",
  "properties": {
    "iso:country":"US",
    "sg:address":"6234 Lenox Ave",
    "sg:city":"Saint Louis",
    "sg:classifiers":[
        {
            "category":"Building & Trades",
            "subcategory":"Construction",
            "type":"Services"
        }
    ],
    "sg:phone":"+1 314 721 5646",
    "sg:postcode":"63133",
    "sg:province":"MO",
    "sg:tags":[
        "general",
        "contractor"
    ],
    "wof:name":"Exact Construction",
    "wof:placetype":"venue"
},
  "geometry": {"coordinates":[-90.292085,38.672324],"type":"Point"}
}