{
  "type": "Feature",
  "properties": {
    "iso:country":"US",
    "sg:address":"206 N Main St",
    "sg:city":"Concordia",
    "sg:classifiers":[
        {
            "category":"Restaurant",
            "type":"Food & Drink"
        }
    ],
    "sg:menulink":"http://www.allmenus.com/mo/freedom/225267-caseys-general-store/menu/",
    "sg:postcode":"64020",
    "sg:province":"MO",
    "sg:tags":[
        "american",
        "pizza"
    ],
    "wof:name":"Casey's General Store",
    "wof:placetype":"venue"
},
  "geometry": {"coordinates":[-93.567826,38.990395],"type":"Point"}
}