{
  "type": "Feature",
  "properties": {
    "iso:country":"US",
    "sg:address":"914 Main St",
    "sg:city":"Lexington",
    "sg:classifiers":[
        {
            "category":"Wholesale",
            "subcategory":"Durable Goods & Equipment",
            "type":"Manufacturing & Wholesale Goods"
        }
    ],
    "sg:phone":"+1 660 259 3512",
    "sg:postcode":"64067",
    "sg:province":"MO",
    "wof:name":"Tats Antiques",
    "wof:placetype":"venue"
},
  "geometry": {"coordinates":[-93.883511,39.185609],"type":"Point"}
}