{
  "type": "Feature",
  "properties": {
    "iso:country":"US",
    "sg:address":"1329 Horan Dr",
    "sg:city":"Fenton",
    "sg:classifiers":[
        {
            "category":"Wholesale",
            "subcategory":"Computers",
            "type":"Manufacturing & Wholesale Goods"
        }
    ],
    "sg:phone":"+1 636 349 4556",
    "sg:postcode":"63026",
    "sg:province":"MO",
    "wof:name":"Lowery Computer Sales & Lease",
    "wof:placetype":"venue"
},
  "geometry": {"coordinates":[-90.472104,38.538364],"type":"Point"}
}