{
  "type": "Feature",
  "properties": {
    "iso:country":"US",
    "sg:address":"903 S Odell Ave",
    "sg:city":"Marshall",
    "sg:classifiers":[
        {
            "category":"Banks & Credit Unions",
            "subcategory":"Investment Brokerage",
            "type":"Services"
        }
    ],
    "sg:phone":"+1 660 886 3600",
    "sg:postcode":"65340",
    "sg:province":"MO",
    "sg:tags":[
        "security"
    ],
    "wof:name":"Mike Mc Kay Investment Svc",
    "wof:placetype":"venue"
},
  "geometry": {"coordinates":[-93.19505700000001,39.111119],"type":"Point"}
}