{
  "type": "Feature",
  "properties": {
    "iso:country":"US",
    "sg:address":"111 E Pitman St",
    "sg:city":"O Fallon",
    "sg:classifiers":[
        {
            "category":"Personal",
            "type":"Services"
        }
    ],
    "sg:phone":"+1 636 978 6331",
    "sg:postcode":"63366",
    "sg:province":"MO",
    "sg:tags":[
        "therapist",
        "massage"
    ],
    "wof:name":"Tranqility Massage Therapy Ctr",
    "wof:placetype":"venue"
},
  "geometry": {"coordinates":[-90.69531499999999,38.806825],"type":"Point"}
}