{
  "type": "Feature",
  "properties": {
    "iso:country":"US",
    "sg:address":"2227 Benton St",
    "sg:city":"St Louis",
    "sg:classifiers":[
        {
            "category":"Building & Trades",
            "subcategory":"Construction",
            "type":"Services"
        }
    ],
    "sg:phone":"+1 314 231 5799",
    "sg:postcode":"63106",
    "sg:province":"MO",
    "sg:tags":[
        "stone",
        "pointing",
        "contractor"
    ],
    "wof:name":"Schwidde Tuckpointing LLC",
    "wof:placetype":"venue"
},
  "geometry": {"coordinates":[-90.207633,38.649312],"type":"Point"}
}