{
  "type": "Feature",
  "properties": {
    "iso:country":"US",
    "sg:address":"301 W Central Ave",
    "sg:city":"Carthage",
    "sg:classifiers":[
        {
            "category":"Autos & Motor Vehicles",
            "subcategory":"Fuel & Gas Station",
            "type":"Retail Goods"
        },
        {
            "category":"Food & Beverages",
            "subcategory":"Groceries & Convenience Stores",
            "type":"Retail Goods"
        }
    ],
    "sg:phone":"+1 417 358 9251",
    "sg:postcode":"64836",
    "sg:province":"MO",
    "sg:website":"http://www.graceenergy.com",
    "wof:name":"Fastrip",
    "wof:placetype":"venue"
},
  "geometry": {"coordinates":[-94.312569,37.178661],"type":"Point"}
}