{
  "type": "Feature",
  "properties": {
    "iso:country":"US",
    "sg:address":"6350 Delmar Blvd",
    "sg:city":"Saint Louis",
    "sg:classifiers":[
        {
            "category":"Cinema",
            "subcategory":"Movie Theater",
            "type":"Entertainment"
        }
    ],
    "sg:phone":"+1 314 995 6270",
    "sg:postcode":"63130",
    "sg:province":"MO",
    "sg:website":"www.landmarktheatres.com/market/...",
    "wof:name":"Tivoli Theatre",
    "wof:placetype":"venue"
},
  "geometry": {"coordinates":[-90.302803,38.655899],"type":"Point"}
}