{
  "type": "Feature",
  "properties": {
    "iso:country":"US",
    "sg:address":"2721 N Courtney Rd",
    "sg:city":"Independence",
    "sg:classifiers":[
        {
            "category":"Building & Trades",
            "subcategory":"Construction",
            "type":"Services"
        }
    ],
    "sg:phone":"+1 816 257 5105",
    "sg:postcode":"64058",
    "sg:province":"MO",
    "sg:tags":[
        "roofing",
        "contractor"
    ],
    "wof:name":"Johnsons Roofing Svc Inc",
    "wof:placetype":"venue"
},
  "geometry": {"coordinates":[-94.391859,39.153651],"type":"Point"}
}