{
  "type": "Feature",
  "properties": {
    "iso:country":"US",
    "sg:address":"313 S Providence Rd",
    "sg:city":"Columbia",
    "sg:classifiers":[
        {
            "category":"Insurance",
            "subcategory":"Insurance Agent",
            "type":"Services"
        }
    ],
    "sg:phone":"+1 573 874 1909",
    "sg:postcode":"65203",
    "sg:province":"MO",
    "wof:name":"AAA Insurance",
    "wof:placetype":"venue"
},
  "geometry": {"coordinates":[-92.334307,38.948751],"type":"Point"}
}