{
  "type": "Feature",
  "properties": {
    "iso:country":"US",
    "sg:address":"101 W 4th St",
    "sg:city":"Fulton",
    "sg:classifiers":[
        {
            "category":"Real Estate",
            "subcategory":"Real Estate Services",
            "type":"Services"
        },
        {
            "category":"Insurance",
            "subcategory":"Insurance Agent",
            "type":"Services"
        }
    ],
    "sg:phone":"+1 573 642 6565",
    "sg:postcode":"65251",
    "sg:province":"MO",
    "sg:tags":[
        "abstract",
        "title"
    ],
    "wof:name":"Guaranty Land Title Insurance, Inc.",
    "wof:placetype":"venue"
},
  "geometry": {"coordinates":[-91.949519,38.846716],"type":"Point"}
}