{
  "type": "Feature",
  "properties": {
    "iso:country":"US",
    "sg:address":"219 S Oak St",
    "sg:city":"Union",
    "sg:classifiers":[
        {
            "category":"Building & Trades",
            "subcategory":"Plumbing",
            "type":"Services"
        }
    ],
    "sg:phone":"+1 636 583 8404",
    "sg:postcode":"63084",
    "sg:province":"MO",
    "sg:tags":[
        "air",
        "heating",
        "conditioning",
        "contractor"
    ],
    "wof:name":"B & S Heating & Cooling Inc",
    "wof:placetype":"venue"
},
  "geometry": {"coordinates":[-91.00658300000001,38.44397],"type":"Point"}
}