{
  "type": "Feature",
  "properties": {
    "iso:country":"US",
    "sg:address":"903 Saint Francis St",
    "sg:city":"Kennett",
    "sg:classifiers":[
        {
            "category":"Personal",
            "subcategory":"Beauty Salon",
            "type":"Services"
        }
    ],
    "sg:phone":"+1 573 888 4095",
    "sg:postcode":"63857",
    "sg:province":"MO",
    "wof:name":"Westgate Beauty Salon",
    "wof:placetype":"venue"
},
  "geometry": {"coordinates":[-90.065826,36.236526],"type":"Point"}
}