{
  "type": "Feature",
  "properties": {
    "iso:country":"US",
    "sg:address":"120 S Missouri St",
    "sg:city":"Jackson",
    "sg:classifiers":[
        {
            "category":"Professional",
            "subcategory":"Management & Consulting",
            "type":"Services"
        },
        {
            "category":"Professional",
            "subcategory":"Advertising",
            "type":"Services"
        }
    ],
    "sg:phone":"+1 573 243 9307",
    "sg:postcode":"63755",
    "sg:province":"MO",
    "sg:tags":[
        "mail",
        "program",
        "direct",
        "marketing"
    ],
    "wof:name":"Direct Line Marketing LLC",
    "wof:placetype":"venue"
},
  "geometry": {"coordinates":[-89.66883,37.382458],"type":"Point"}
}