{
  "type": "Feature",
  "properties": {
    "iso:country":"US",
    "sg:address":"9040 Manchester Rd",
    "sg:city":"St Louis",
    "sg:classifiers":[
        {
            "category":"Shopping",
            "subcategory":"Used Merchandise",
            "type":"Retail Goods"
        }
    ],
    "sg:phone":"+1 314 968 4255",
    "sg:postcode":"63144",
    "sg:province":"MO",
    "sg:tags":[
        "book",
        "rare",
        "dealer"
    ],
    "wof:name":"Patten Books",
    "wof:placetype":"venue"
},
  "geometry": {"coordinates":[-90.35435200000001,38.612436],"type":"Point"}
}