{
  "type": "Feature",
  "properties": {
    "iso:country":"US",
    "sg:address":"113 Madison St",
    "sg:city":"Jefferson City",
    "sg:classifiers":[
        {
            "category":"Organizations",
            "subcategory":"Professional Association",
            "type":"Services"
        }
    ],
    "sg:phone":"+1 573 636 6905",
    "sg:postcode":"65101",
    "sg:province":"MO",
    "wof:name":"Missouri Soc Anesthesiologists",
    "wof:placetype":"venue"
},
  "geometry": {"coordinates":[-92.169805,38.577151],"type":"Point"}
}