{
  "type": "Feature",
  "properties": {
    "iso:country":"US",
    "sg:address":"505 Fay Street Suite 210",
    "sg:city":"Columbia",
    "sg:classifiers":[
        {
            "category":"Professional",
            "subcategory":"Computer Services",
            "type":"Services"
        }
    ],
    "sg:phone":"+1 573 356 5181",
    "sg:postcode":"65203",
    "sg:province":"MO",
    "sg:tags":[
        "schedule",
        "calendar",
        "e-commerce",
        "bookings",
        "appointments",
        "reservations",
        "saas"
    ],
    "sg:website":"http://www.bookd.com",
    "wof:name":"Book'd",
    "wof:placetype":"venue"
},
  "geometry": {"coordinates":[-91.962355,38.949691],"type":"Point"}
}