{
  "type": "Feature",
  "properties": {
    "iso:country":"US",
    "sg:address":"11477 Olive Blvd",
    "sg:city":"Creve Coeur",
    "sg:classifiers":[
        {
            "category":"Health Services",
            "subcategory":"Optometrist",
            "type":"Services"
        }
    ],
    "sg:phone":"+1 314 567 3884",
    "sg:postcode":"63141",
    "sg:province":"MO",
    "wof:name":"Crown Optical",
    "wof:placetype":"venue"
},
  "geometry": {"coordinates":[-90.433958,38.671278],"type":"Point"}
}