{
  "type": "Feature",
  "properties": {
    "iso:country":"US",
    "sg:address":"4168 Meramec St",
    "sg:city":"Saint Louis",
    "sg:classifiers":[
        {
            "category":"Shopping",
            "subcategory":"Bicycles & Sporting Goods",
            "type":"Retail Goods"
        }
    ],
    "sg:phone":"+1 314 771 9595",
    "sg:postcode":"63116",
    "sg:province":"MO",
    "sg:website":"www.bagmaster.com",
    "wof:name":"Bagmaster Mfg Inc",
    "wof:placetype":"venue"
},
  "geometry": {"coordinates":[-90.260608,38.58931],"type":"Point"}
}