{
  "type": "Feature",
  "properties": {
    "iso:country":"US",
    "sg:address":"1845 West St",
    "sg:city":"Mexico",
    "sg:classifiers":[
        {
            "category":"Restaurant",
            "type":"Food & Drink"
        }
    ],
    "sg:menulink":"http://www.allmenus.com/mo/salt-river/225630-caseys-general-store/menu/",
    "sg:postcode":"65265",
    "sg:province":"MO",
    "sg:tags":[
        "american",
        "pizza"
    ],
    "wof:name":"Casey's General Store",
    "wof:placetype":"venue"
},
  "geometry": {"coordinates":[-91.892426,39.156668],"type":"Point"}
}