{
  "type": "Feature",
  "properties": {
    "iso:country":"US",
    "sg:address":"331 Main St",
    "sg:city":"New Madrid",
    "sg:classifiers":[
        {
            "category":"Building & Trades",
            "subcategory":"Equipment Rental",
            "type":"Services"
        }
    ],
    "sg:phone":"+1 573 748 5616",
    "sg:postcode":"63869",
    "sg:province":"MO",
    "sg:tags":[
        "leasing",
        "furniture"
    ],
    "wof:name":"Wagley Rentals & Svc",
    "wof:placetype":"venue"
},
  "geometry": {"coordinates":[-89.526906,36.585908],"type":"Point"}
}