{
  "type": "Feature",
  "properties": {
    "iso:country":"US",
    "sg:address":"19601 S David Sapp Rd",
    "sg:city":"Hartsburg",
    "sg:classifiers":[
        {
            "category":"Farming",
            "subcategory":"Livestock Farm",
            "type":"Manufacturing & Wholesale Goods"
        }
    ],
    "sg:phone":"+1 573 657 2871",
    "sg:postcode":"65039",
    "sg:province":"MO",
    "sg:tags":[
        "beef",
        "feedlot",
        "cattle"
    ],
    "wof:name":"Michael Williams",
    "wof:placetype":"venue"
},
  "geometry": {"coordinates":[-92.26821200000001,38.716751],"type":"Point"}
}