{
  "type": "Feature",
  "properties": {
    "iso:country":"US",
    "sg:address":"1728 Timber Ridge Estates Dr",
    "sg:city":"Ballwin",
    "sg:classifiers":[
        {
            "category":"Farming",
            "subcategory":"Farm",
            "type":"Manufacturing & Wholesale Goods"
        }
    ],
    "sg:phone":"+1 636 273 9646",
    "sg:postcode":"63011",
    "sg:province":"MO",
    "wof:name":"Shamrock Trading",
    "wof:placetype":"venue"
},
  "geometry": {"coordinates":[-90.612587,38.594407],"type":"Point"}
}