{
  "type": "Feature",
  "properties": {
    "iso:country":"US",
    "sg:address":"8952 NW Bethany Church Rd",
    "sg:city":"Stewartsville",
    "sg:classifiers":[
        {
            "category":"Farming",
            "subcategory":"Livestock Farm",
            "type":"Manufacturing & Wholesale Goods"
        }
    ],
    "sg:phone":"+1 816 539 2473",
    "sg:postcode":"64490",
    "sg:province":"MO",
    "sg:tags":[
        "animal",
        "general"
    ],
    "wof:name":"Delaney Farms Inc",
    "wof:placetype":"venue"
},
  "geometry": {"coordinates":[-94.489347,39.691483],"type":"Point"}
}