{
  "type": "Feature",
  "properties": {
    "iso:country":"US",
    "sg:address":"4013 US Hwy 65",
    "sg:city":"Sedalia",
    "sg:classifiers":[
        {
            "category":"Utilities",
            "subcategory":"Refuse",
            "type":"Services"
        }
    ],
    "sg:phone":"+1 660 827 4477",
    "sg:postcode":"65301",
    "sg:province":"MO",
    "sg:tags":[
        "system"
    ],
    "wof:name":"Sedalia Container Service Inc",
    "wof:placetype":"venue"
},
  "geometry": {"coordinates":[-93.251384,38.680576],"type":"Point"}
}