{
  "type": "Feature",
  "properties": {
    "iso:country":"US",
    "sg:address":"1001 N Middle St",
    "sg:city":"Farmington",
    "sg:classifiers":[
        {
            "category":"Shopping",
            "subcategory":"Jewelry",
            "type":"Retail Goods"
        }
    ],
    "sg:phone":"+1 573 756 6982",
    "sg:postcode":"63640",
    "sg:province":"MO",
    "sg:tags":[
        "repair"
    ],
    "wof:name":"Bobbis Drams Thngs Cstm Jwlers",
    "wof:placetype":"venue"
},
  "geometry": {"coordinates":[-90.415021,37.790166],"type":"Point"}
}