{
  "type": "Feature",
  "properties": {
    "iso:country":"US",
    "sg:address":"229 Broadway",
    "sg:city":"Hannibal",
    "sg:classifiers":[
        {
            "category":"Building & Trades",
            "subcategory":"Construction",
            "type":"Services"
        }
    ],
    "sg:phone":"+1 573 221 3434",
    "sg:postcode":"63401",
    "sg:province":"MO",
    "sg:tags":[
        "home",
        "builder"
    ],
    "wof:name":"Fidelity Home Svc Inc",
    "wof:placetype":"venue"
},
  "geometry": {"coordinates":[-91.355987,39.709499],"type":"Point"}
}