{
  "type": "Feature",
  "properties": {
    "iso:country":"US",
    "sg:address":"55 E Main St",
    "sg:city":"Adrian",
    "sg:classifiers":[
        {
            "category":"Real Estate",
            "subcategory":"Real Estate Agent",
            "type":"Services"
        }
    ],
    "sg:phone":"+1 816 297 2882",
    "sg:postcode":"64720",
    "sg:province":"MO",
    "wof:name":"Homestead Realty",
    "wof:placetype":"venue"
},
  "geometry": {"coordinates":[-94.352977,38.397345],"type":"Point"}
}