{
  "type": "Feature",
  "properties": {
    "iso:country":"US",
    "sg:address":"12836 Tesson Ferry Rd",
    "sg:city":"Saint Louis",
    "sg:classifiers":[
        {
            "category":"Social Services",
            "subcategory":"Child Care",
            "type":"Services"
        }
    ],
    "sg:phone":"+1 314 842 3587",
    "sg:postcode":"63128",
    "sg:province":"MO",
    "sg:tags":[
        "day"
    ],
    "wof:name":"La Petite Academy Inc",
    "wof:placetype":"venue"
},
  "geometry": {"coordinates":[-90.381145,38.497574],"type":"Point"}
}