{
  "type": "Feature",
  "properties": {
    "iso:country":"US",
    "sg:address":"7115 N Stewart Rd",
    "sg:city":"Liberty",
    "sg:classifiers":[
        {
            "category":"Real Estate",
            "subcategory":"Real Estate Operator",
            "type":"Services"
        }
    ],
    "sg:phone":"+1 816 781 8696",
    "sg:postcode":"64068",
    "sg:province":"MO",
    "sg:tags":[
        "mobile",
        "home",
        "site"
    ],
    "wof:name":"Westwood Manor Mobile Home Pk",
    "wof:placetype":"venue"
},
  "geometry": {"coordinates":[-94.46931499999999,39.224294],"type":"Point"}
}