{
  "type": "Feature",
  "properties": {
    "iso:country":"US",
    "sg:address":"1 Town Sq",
    "sg:city":"Kansas City",
    "sg:classifiers":[
        {
            "category":"Professional",
            "subcategory":"Lawyer & Legal Services",
            "type":"Services"
        }
    ],
    "sg:phone":"+1 816 471 3414",
    "sg:postcode":"64116",
    "sg:province":"MO",
    "wof:name":"S P Williams Atty",
    "wof:placetype":"venue"
},
  "geometry": {"coordinates":[-94.57605,39.141071],"type":"Point"}
}