{
  "type": "Feature",
  "properties": {
    "addr:full":"10850 Ambassador Blvd Saint Louis MO 63132",
    "addr:housenumber":"10850",
    "addr:postcode":"63132",
    "addr:street":"Ambassador Blvd",
    "iso:country":"US",
    "sg:address":"10850 Ambassador Blvd",
    "sg:city":"Saint Louis",
    "sg:classifiers":[
        {
            "category":"Wholesale",
            "subcategory":"Groceries",
            "type":"Manufacturing & Wholesale Goods"
        }
    ],
    "sg:phone":"+1 314 991 3162",
    "sg:postcode":"63132",
    "sg:province":"MO",
    "sg:tags":[
        "consulting",
        "management",
        "general"
    ],
    "wof:name":"US Foodservice",
    "wof:placetype":"venue"
},
  "geometry": {"coordinates":[-90.39895300000001,38.683952],"type":"Point"}
}