{
  "type": "Feature",
  "properties": {
    "iso:country":"US",
    "sg:address":"3864 State Hwy 13",
    "sg:city":"Dunnegan",
    "sg:classifiers":[
        {
            "category":"Manufacturing",
            "subcategory":"Building Materials",
            "type":"Manufacturing & Wholesale Goods"
        },
        {
            "category":"Home & Garden",
            "subcategory":"Furniture",
            "type":"Retail Goods"
        }
    ],
    "sg:phone":"+1 417 654 2441",
    "sg:postcode":"65640",
    "sg:province":"MO",
    "sg:tags":[
        "mfg",
        "builder",
        "kitchen",
        "custom",
        "wood",
        "cabinet",
        "household",
        "furn"
    ],
    "wof:name":"Johnson's Country Crafts",
    "wof:placetype":"venue"
},
  "geometry": {"coordinates":[-93.50656499999999,37.694196],"type":"Point"}
}