{
  "type": "Feature",
  "properties": {
    "iso:country":"US",
    "sg:address":"1707 NE 74 Ter",
    "sg:city":"Kansas City",
    "sg:classifiers":[
        {
            "category":"Organizations",
            "subcategory":"Non-profit Organization",
            "type":"Services"
        }
    ],
    "sg:phone":"+1 816 468 4684",
    "sg:postcode":"64118",
    "sg:province":"MO",
    "sg:tags":[
        "info",
        "addiction",
        "abuse",
        "treatment",
        "drug"
    ],
    "wof:name":"New Concept Substance Abuse",
    "wof:placetype":"venue"
},
  "geometry": {"coordinates":[-94.558926,39.228783],"type":"Point"}
}