{
  "type": "Feature",
  "properties": {
    "iso:country":"US",
    "sg:address":"15820 Clayton Rd",
    "sg:city":"Ellisville",
    "sg:classifiers":[
        {
            "category":"Organizations",
            "subcategory":"Community Association",
            "type":"Services"
        }
    ],
    "sg:phone":"+1 636 386 1789",
    "sg:postcode":"63011",
    "sg:province":"MO",
    "sg:tags":[
        "educational"
    ],
    "wof:name":"Constitutional Coalition",
    "wof:placetype":"venue"
},
  "geometry": {"coordinates":[-90.585689,38.604852],"type":"Point"}
}