{
  "type": "Feature",
  "properties": {
    "iso:country":"US",
    "sg:address":"1220 SE Scenic Dr",
    "sg:city":"Blue Springs",
    "sg:classifiers":[
        {
            "category":"Building & Trades",
            "subcategory":"Construction",
            "type":"Services"
        }
    ],
    "sg:phone":"+1 816 229 3348",
    "sg:postcode":"64014",
    "sg:province":"MO",
    "sg:tags":[
        "house"
    ],
    "wof:name":"Srd Homes",
    "wof:placetype":"venue"
},
  "geometry": {"coordinates":[-94.24144200000001,39.003832],"type":"Point"}
}