{
  "type": "Feature",
  "properties": {
    "iso:country":"US",
    "sg:address":"6518 Village Rd",
    "sg:city":"Jefferson City",
    "sg:classifiers":[
        {
            "category":"Building & Trades",
            "subcategory":"Construction",
            "type":"Services"
        }
    ],
    "sg:phone":"+1 573 395 4258",
    "sg:postcode":"65101",
    "sg:province":"MO",
    "sg:tags":[
        "excavation",
        "contractor"
    ],
    "wof:name":"Wilbers Excavating",
    "wof:placetype":"venue"
},
  "geometry": {"coordinates":[-92.08446600000001,38.488239],"type":"Point"}
}