{
  "type": "Feature",
  "properties": {
    "iso:country":"US",
    "sg:address":"101 S Glenwood Ave",
    "sg:city":"Columbia",
    "sg:classifiers":[
        {
            "category":"Real Estate",
            "subcategory":"Real Estate Services",
            "type":"Services"
        },
        {
            "category":"Real Estate",
            "subcategory":"Surveying",
            "type":"Services"
        }
    ],
    "sg:phone":"+1 573 443 1106",
    "sg:postcode":"65203",
    "sg:province":"MO",
    "sg:tags":[
        "industrial",
        "appraisers-commercial",
        "appraiser"
    ],
    "wof:name":"Westerfield Appraisals & Brokerage Inc",
    "wof:placetype":"venue"
},
  "geometry": {"coordinates":[-92.347222,38.950261],"type":"Point"}
}