{
  "type": "Feature",
  "properties": {
    "iso:country":"US",
    "sg:address":"102 Bayshore Dr",
    "sg:city":"Reeds Spring",
    "sg:classifiers":[
        {
            "category":"Social Services",
            "subcategory":"Child Care",
            "type":"Services"
        }
    ],
    "sg:phone":"+1 417 338 2487",
    "sg:postcode":"65737",
    "sg:province":"MO",
    "sg:tags":[
        "day",
        "night"
    ],
    "wof:name":"Evelyn Knudson State Care",
    "wof:placetype":"venue"
},
  "geometry": {"coordinates":[-93.396698,36.639047],"type":"Point"}
}