{
  "type": "Feature",
  "properties": {
    "iso:country":"US",
    "sg:address":"15765 State Hwy 13",
    "sg:city":"Reeds Spring",
    "sg:classifiers":[
        {
            "category":"Social Services",
            "type":"Services"
        }
    ],
    "sg:phone":"+1 417 272 3850",
    "sg:postcode":"65737",
    "sg:province":"MO",
    "sg:tags":[
        "mission"
    ],
    "wof:name":"Revival Fires World Mission",
    "wof:placetype":"venue"
},
  "geometry": {"coordinates":[-93.398439,36.673298],"type":"Point"}
}