{
  "type": "Feature",
  "properties": {
    "iso:country":"US",
    "sg:address":"215 N Grant Ave",
    "sg:city":"Springfield",
    "sg:classifiers":[
        {
            "category":"Building & Trades",
            "subcategory":"Construction",
            "type":"Services"
        }
    ],
    "sg:phone":"+1 417 862 4322",
    "sg:postcode":"65806",
    "sg:province":"MO",
    "sg:tags":[
        "hanging",
        "painter",
        "contractor"
    ],
    "wof:name":"G & G Painting Co",
    "wof:placetype":"venue"
},
  "geometry": {"coordinates":[-93.29879,37.208734],"type":"Point"}
}