{
  "type": "Feature",
  "properties": {
    "iso:country":"US",
    "sg:address":"802 E Breckenridge St",
    "sg:city":"Mexico",
    "sg:classifiers":[
        {
            "category":"Place Of Worship",
            "type":"Public Place"
        }
    ],
    "sg:phone":"+1 573 673 2080",
    "sg:postcode":"65265",
    "sg:province":"MO",
    "sg:tags":[
        "church"
    ],
    "wof:name":"Little Dixie Shrine Club Holding Corporation",
    "wof:placetype":"venue"
},
  "geometry": {"coordinates":[-91.875839,39.166698],"type":"Point"}
}