{
  "type": "Feature",
  "properties": {
    "iso:country":"US",
    "sg:address":"211 E Elm St",
    "sg:city":"Drexel",
    "sg:classifiers":[
        {
            "category":"Education",
            "subcategory":"Library",
            "type":"Public Place"
        }
    ],
    "sg:phone":"+1 816 657 4740",
    "sg:postcode":"64742",
    "sg:province":"MO",
    "sg:website":"http://www.casscountypubliclibrary.com",
    "wof:name":"Drexel Branch Library",
    "wof:placetype":"venue"
},
  "geometry": {"coordinates":[-94.608355,38.483306],"type":"Point"}
}