{
  "type": "Feature",
  "properties": {
    "iso:country":"US",
    "sg:address":"3695 S Oak Hill Ln",
    "sg:city":"Rogersville",
    "sg:classifiers":[
        {
            "category":"Building & Trades",
            "subcategory":"Construction",
            "type":"Services"
        }
    ],
    "sg:phone":"+1 417 753 2877",
    "sg:postcode":"65742",
    "sg:province":"MO",
    "sg:tags":[
        "woodworker"
    ],
    "wof:name":"Waltner Custom Woodcraft",
    "wof:placetype":"venue"
},
  "geometry": {"coordinates":[-93.068584,37.141788],"type":"Point"}
}