{
  "type": "Feature",
  "properties": {
    "iso:country":"US",
    "sg:address":"1100 N Morley St",
    "sg:city":"Moberly",
    "sg:classifiers":[
        {
            "category":"Retail",
            "subcategory":"Animal Services",
            "type":"Services"
        }
    ],
    "sg:phone":"+1 660 263 3595",
    "sg:postcode":"65270",
    "sg:province":"MO",
    "sg:tags":[
        "pet"
    ],
    "wof:name":"Animal Magic",
    "wof:placetype":"venue"
},
  "geometry": {"coordinates":[-92.433189,39.430612],"type":"Point"}
}