{
  "type": "Feature",
  "properties": {
    "iso:country":"US",
    "sg:address":"1820 Delmar Blvd",
    "sg:city":"St Louis",
    "sg:classifiers":[
        {
            "category":"Professional",
            "subcategory":"Testing Lab",
            "type":"Services"
        }
    ],
    "sg:phone":"+1 314 241 8772",
    "sg:postcode":"63103",
    "sg:province":"MO",
    "sg:tags":[
        "laboratory"
    ],
    "sg:website":"www.mo-ana-labs.com",
    "wof:name":"Missouri Analytical Lab Inc",
    "wof:placetype":"venue"
},
  "geometry": {"coordinates":[-90.205422,38.635134],"type":"Point"}
}