{
  "type": "Feature",
  "properties": {
    "iso:country":"US",
    "sg:address":"4642 Shenandoah Ave",
    "sg:city":"St Louis",
    "sg:classifiers":[
        {
            "category":"Banks & Credit Unions",
            "subcategory":"Bank",
            "type":"Services"
        }
    ],
    "sg:phone":"+1 314 776 6100",
    "sg:postcode":"63110",
    "sg:province":"MO",
    "sg:tags":[
        "loan",
        "real estate"
    ],
    "wof:name":"Loanscapes",
    "wof:placetype":"venue"
},
  "geometry": {"coordinates":[-90.266666,38.612397],"type":"Point"}
}