{
  "type": "Feature",
  "properties": {
    "iso:country":"US",
    "sg:address":"902 Thompson Blvd",
    "sg:city":"Sedalia",
    "sg:classifiers":[
        {
            "category":"Shopping",
            "subcategory":"Shoes",
            "type":"Retail Goods"
        },
        {
            "category":"Shopping",
            "subcategory":"Computers & Home Electronics",
            "type":"Retail Goods"
        }
    ],
    "sg:phone":"+1 660 827 1500",
    "sg:postcode":"65301",
    "sg:province":"MO",
    "sg:tags":[
        "apparel",
        "equipment",
        "dealer",
        "footwear"
    ],
    "wof:name":"Precision Computers Inc",
    "wof:placetype":"venue"
},
  "geometry": {"coordinates":[-93.26506500000001,38.70613],"type":"Point"}
}