{
  "type": "Feature",
  "properties": {
    "iso:country":"US",
    "sg:address":"16892 Co Rd 248",
    "sg:city":"Bloomfield",
    "sg:phone":"+1 573 568 2585",
    "sg:postcode":"63825",
    "sg:province":"MO",
    "sg:tags":[
        "farm",
        "grain",
        "cash"
    ],
    "wof:name":"Gary Smothers",
    "wof:placetype":"venue"
},
  "geometry": {"coordinates":[-89.96253299999999,36.99899],"type":"Point"}
}