{
  "type": "Feature",
  "properties": {
    "iso:country":"US",
    "sg:address":"222 E High St",
    "sg:city":"Jefferson City",
    "sg:classifiers":[
        {
            "category":"Bars & Pubs",
            "type":"Food & Drink"
        }
    ],
    "sg:phone":"+1 573 659 9009",
    "sg:postcode":"65101",
    "sg:province":"MO",
    "wof:name":"Pitchers",
    "wof:placetype":"venue"
},
  "geometry": {"coordinates":[-92.170917,38.575805],"type":"Point"}
}