{
  "type": "Feature",
  "properties": {
    "iso:country":"US",
    "sg:address":"103 Mill St",
    "sg:city":"Urbana",
    "sg:classifiers":[
        {
            "category":"Retail",
            "subcategory":"Car Wash",
            "type":"Services"
        }
    ],
    "sg:phone":"+1 816 682 4780",
    "sg:postcode":"65767",
    "sg:province":"MO",
    "sg:tags":[
        "automobile",
        "detail",
        "clean"
    ],
    "wof:name":"On-Site Detail",
    "wof:placetype":"venue"
},
  "geometry": {"coordinates":[-93.164361,37.840922],"type":"Point"}
}