{
  "type": "Feature",
  "properties": {
    "iso:country":"US",
    "sg:address":"3519 Country Club Dr",
    "sg:city":"Jefferson City",
    "sg:classifiers":[
        {
            "category":"Restaurant",
            "type":"Food & Drink"
        }
    ],
    "sg:menulink":"http://www.allmenus.com/mo/jefferson/127859-red-lobster/menu/",
    "sg:phone":"+1 573 635 6737",
    "sg:postcode":"65109",
    "sg:province":"MO",
    "sg:tags":[
        "seafood",
        "american"
    ],
    "wof:name":"Red Lobster",
    "wof:placetype":"venue"
},
  "geometry": {"coordinates":[-92.25045799999999,38.584011],"type":"Point"}
}