{
  "type": "Feature",
  "properties": {
    "iso:country":"US",
    "sg:address":"6992 E State Hwy 76",
    "sg:city":"Kirbyville",
    "sg:classifiers":[
        {
            "category":"Professional",
            "type":"Services"
        }
    ],
    "sg:phone":"+1 417 339 3071",
    "sg:postcode":"65679",
    "sg:province":"MO",
    "sg:tags":[
        "establishment"
    ],
    "wof:name":"Smoken With Uncle Willey",
    "wof:placetype":"venue"
},
  "geometry": {"coordinates":[-93.123375,36.63151],"type":"Point"}
}