{
  "type": "Feature",
  "properties": {
    "iso:country":"US",
    "sg:address":"4928 Main St",
    "sg:city":"Kansas City",
    "sg:classifiers":[
        {
            "category":"Government",
            "subcategory":"Fire Station",
            "type":"Public Place"
        }
    ],
    "sg:phone":"+1 816 784 9200",
    "sg:postcode":"64112",
    "sg:province":"MO",
    "sg:tags":[
        "protection"
    ],
    "wof:name":"Fire Dept- Station 32",
    "wof:placetype":"venue"
},
  "geometry": {"coordinates":[-94.587228,39.038231],"type":"Point"}
}