{
  "type": "Feature",
  "properties": {
    "iso:country":"US",
    "sg:address":"1923 N Patterson Ave",
    "sg:city":"Springfield",
    "sg:classifiers":[
        {
            "category":"Freight",
            "type":"Transportation"
        }
    ],
    "sg:phone":"+1 417 865 1601",
    "sg:postcode":"65803",
    "sg:province":"MO",
    "sg:tags":[
        "trucking"
    ],
    "wof:name":"Wayne Choate Dump Trucking",
    "wof:placetype":"venue"
},
  "geometry": {"coordinates":[-93.247536,37.230537],"type":"Point"}
}