{
  "type": "Feature",
  "properties": {
    "iso:country":"US",
    "sg:address":"187 Concord Plaza Shopping Center",
    "sg:city":"Saint Louis",
    "sg:classifiers":[
        {
            "category":"Restaurant",
            "type":"Food & Drink"
        }
    ],
    "sg:phone":"+1 314 843 4996",
    "sg:postcode":"63128",
    "sg:province":"MO",
    "sg:tags":[
        "eating"
    ],
    "wof:name":"Destination Dining St Louis",
    "wof:placetype":"venue"
},
  "geometry": {"coordinates":[-90.36165,38.524428],"type":"Point"}
}