{
  "type": "Feature",
  "properties": {
    "iso:country":"US",
    "sg:address":"515 E Concord St",
    "sg:city":"Appleton City",
    "sg:classifiers":[
        {
            "category":"Professional",
            "subcategory":"Research",
            "type":"Services"
        }
    ],
    "sg:phone":"+1 660 476 2300",
    "sg:postcode":"64724",
    "sg:province":"MO",
    "sg:tags":[
        "environmental",
        "ecological"
    ],
    "wof:name":"C & R Ind Hygiene",
    "wof:placetype":"venue"
},
  "geometry": {"coordinates":[-94.02141899999999,38.184318],"type":"Point"}
}