{
  "type": "Feature",
  "properties": {
    "iso:country":"US",
    "sg:address":"1597 Pleasant Ridge Rd",
    "sg:city":"Anderson",
    "sg:classifiers":[
        {
            "category":"Building & Trades",
            "subcategory":"Construction",
            "type":"Services"
        }
    ],
    "sg:phone":"+1 417 845 0990",
    "sg:postcode":"64831",
    "sg:province":"MO",
    "sg:tags":[
        "siding",
        "contractor"
    ],
    "wof:name":"R & J Exteriors",
    "wof:placetype":"venue"
},
  "geometry": {"coordinates":[-94.405964,36.612068],"type":"Point"}
}