{
  "type": "Feature",
  "properties": {
    "addr:full":"1653 Larkin Williams Rd Fenton MO 63026",
    "addr:housenumber":"1653",
    "addr:postcode":"63026",
    "addr:street":"Larkin Williams Rd",
    "iso:country":"US",
    "sg:address":"1653 Larkin Williams Rd",
    "sg:city":"Fenton",
    "sg:classifiers":[
        {
            "category":"Real Estate",
            "subcategory":"Real Estate Services",
            "type":"Services"
        }
    ],
    "sg:phone":"+1 314 336 1200",
    "sg:postcode":"63026",
    "sg:province":"MO",
    "sg:tags":[
        "company",
        "title"
    ],
    "wof:name":"First American Title Ins Co",
    "wof:placetype":"venue"
},
  "geometry": {"coordinates":[-90.455011,38.537548],"type":"Point"}
}