{
  "type": "Feature",
  "properties": {
    "iso:country":"US",
    "sg:address":"5925 W Florissant Ave",
    "sg:city":"St Louis",
    "sg:classifiers":[
        {
            "category":"Organizations",
            "subcategory":"Religious Organization",
            "type":"Services"
        }
    ],
    "sg:phone":"+1 314 385 1777",
    "sg:postcode":"63136",
    "sg:province":"MO",
    "sg:tags":[
        "church"
    ],
    "wof:name":"St Louis District Christian",
    "wof:placetype":"venue"
},
  "geometry": {"coordinates":[-90.24941099999999,38.706844],"type":"Point"}
}