{
  "type": "Feature",
  "properties": {
    "iso:country":"US",
    "sg:address":"6550 Nollman Rd",
    "sg:city":"High Ridge",
    "sg:classifiers":[
        {
            "category":"Building & Trades",
            "subcategory":"Construction",
            "type":"Services"
        }
    ],
    "sg:phone":"+1 636 677 1490",
    "sg:postcode":"63049",
    "sg:province":"MO",
    "sg:tags":[
        "carpentry",
        "contractor"
    ],
    "wof:name":"Roberts Windows & Doors",
    "wof:placetype":"venue"
},
  "geometry": {"coordinates":[-90.562904,38.467894],"type":"Point"}
}