{
  "type": "Feature",
  "properties": {
    "iso:country":"US",
    "sg:address":"12816 13 St",
    "sg:city":"Grandview",
    "sg:classifiers":[
        {
            "category":"Professional",
            "subcategory":"Accounting & Tax Preparation",
            "type":"Services"
        }
    ],
    "sg:phone":"+1 816 966 8277",
    "sg:postcode":"64030",
    "sg:province":"MO",
    "wof:name":"Webs",
    "wof:placetype":"venue"
},
  "geometry": {"coordinates":[-94.529769,38.896336],"type":"Point"}
}