{
  "type": "Feature",
  "properties": {
    "iso:country":"US",
    "sg:address":"6340 Northwood Ave",
    "sg:city":"Saint Louis",
    "sg:classifiers":[
        {
            "category":"Organizations",
            "subcategory":"Non-profit Organization",
            "type":"Services"
        }
    ],
    "sg:phone":"+1 314 721 3878",
    "sg:postcode":"63105",
    "sg:province":"MO",
    "sg:tags":[
        "service/non-profit",
        "community"
    ],
    "sg:website":"www.anthropaideia.com",
    "wof:name":"Anthropaideia",
    "wof:placetype":"venue"
},
  "geometry": {"coordinates":[-90.306434,38.638545],"type":"Point"}
}