{
  "type": "Feature",
  "properties": {
    "iso:country":"US",
    "sg:address":"300 S John Q Hammons Pkwy",
    "sg:city":"Springfield",
    "sg:classifiers":[
        {
            "category":"Professional",
            "subcategory":"Management & Consulting",
            "type":"Services"
        }
    ],
    "sg:phone":"+1 417 864 4957",
    "sg:postcode":"65806",
    "sg:province":"MO",
    "wof:name":"Greene Cnty Brd For The Dvlpmn",
    "wof:placetype":"venue"
},
  "geometry": {"coordinates":[-93.281305,37.208093],"type":"Point"}
}