{
  "type": "Feature",
  "properties": {
    "iso:country":"US",
    "sg:address":"1430 NW 75 St",
    "sg:city":"Kansas City",
    "sg:classifiers":[
        {
            "category":"Organizations",
            "subcategory":"Religious Organization",
            "type":"Services"
        }
    ],
    "sg:phone":"+1 816 420 8181",
    "sg:postcode":"64118",
    "sg:province":"MO",
    "wof:name":"Lynda Randle Ministries",
    "wof:placetype":"venue"
},
  "geometry": {"coordinates":[-94.597829,39.231592],"type":"Point"}
}