{
  "type": "Feature",
  "properties": {
    "iso:country":"US",
    "sg:address":"1107 Main St",
    "sg:city":"Blue Springs",
    "sg:classifiers":[
        {
            "category":"Personal",
            "subcategory":"Beauty Salon",
            "type":"Services"
        }
    ],
    "sg:phone":"+1 816 228 1363",
    "sg:postcode":"64015",
    "sg:province":"MO",
    "wof:name":"Mar Shels Hair & Nail Studio",
    "wof:placetype":"venue"
},
  "geometry": {"coordinates":[-94.279011,39.01849],"type":"Point"}
}