{
  "type": "Feature",
  "properties": {
    "iso:country":"US",
    "sg:address":"13040 Crossland Rd",
    "sg:city":"Cabool",
    "sg:classifiers":[
        {
            "category":"Insurance",
            "subcategory":"Hazard Insurance",
            "type":"Services"
        }
    ],
    "sg:phone":"+1 417 962 5013",
    "sg:postcode":"65689",
    "sg:province":"MO",
    "sg:tags":[
        "commercial",
        "business"
    ],
    "wof:name":"Kenneth & Pamela Mcmann",
    "wof:placetype":"venue"
},
  "geometry": {"coordinates":[-92.112863,37.180117],"type":"Point"}
}