{
  "type": "Feature",
  "properties": {
    "iso:country":"US",
    "sg:address":"3405 US Hwy 61",
    "sg:city":"Festus",
    "sg:classifiers":[
        {
            "category":"Food & Beverages",
            "subcategory":"Specialty",
            "type":"Retail Goods"
        }
    ],
    "sg:phone":"+1 636 937 2068",
    "sg:postcode":"63028",
    "sg:province":"MO",
    "wof:name":"Midwest Natural Herb Store",
    "wof:placetype":"venue"
},
  "geometry": {"coordinates":[-90.321235,38.14225],"type":"Point"}
}