{
  "type": "Feature",
  "properties": {
    "iso:country":"US",
    "sg:address":"27 S County Centerway",
    "sg:city":"St Louis",
    "sg:classifiers":[
        {
            "category":"Professional",
            "type":"Services"
        },
        {
            "category":"Shopping",
            "subcategory":"Clothing, Apparel, & Fashions",
            "type":"Retail Goods"
        }
    ],
    "sg:phone":"+1 314 984 9655",
    "sg:postcode":"63129",
    "sg:province":"MO",
    "sg:tags":[
        "handbag"
    ],
    "wof:name":"H Squared",
    "wof:placetype":"venue"
},
  "geometry": {"coordinates":[-90.32947799999999,38.505297],"type":"Point"}
}