{
  "type": "Feature",
  "properties": {
    "iso:country":"US",
    "sg:address":"3021 Cravens Rd",
    "sg:city":"Poplar Bluff",
    "sg:classifiers":[
        {
            "category":"Wholesale",
            "subcategory":"Auto Parts",
            "type":"Manufacturing & Wholesale Goods"
        }
    ],
    "sg:phone":"+1 573 785 1703",
    "sg:postcode":"63901",
    "sg:province":"MO",
    "sg:tags":[
        "used"
    ],
    "wof:name":"Blh Auto Salvage",
    "wof:placetype":"venue"
},
  "geometry": {"coordinates":[-90.427717,36.728744],"type":"Point"}
}