{
  "type": "Feature",
  "properties": {
    "iso:country":"US",
    "sg:address":"653 State Hwy 92",
    "sg:city":"Kearney",
    "sg:classifiers":[
        {
            "category":"Retail",
            "subcategory":"Laundry & Dry Cleaning",
            "type":"Services"
        }
    ],
    "sg:phone":"+1 816 628 4181",
    "sg:postcode":"64060",
    "sg:province":"MO",
    "sg:tags":[
        "cleaners"
    ],
    "wof:name":"Royal Cleaners",
    "wof:placetype":"venue"
},
  "geometry": {"coordinates":[-94.353128,39.367733],"type":"Point"}
}