{
  "type": "Feature",
  "properties": {
    "iso:country":"US",
    "sg:address":"206 SE 2 St",
    "sg:city":"Lees Summit",
    "sg:classifiers":[
        {
            "category":"Professional",
            "subcategory":"Accounting & Tax Preparation",
            "type":"Services"
        }
    ],
    "sg:phone":"+1 816 525 7787",
    "sg:postcode":"64063",
    "sg:province":"MO",
    "sg:tags":[
        "return",
        "filing"
    ],
    "wof:name":"Mallory Accounting Corp",
    "wof:placetype":"venue"
},
  "geometry": {"coordinates":[-94.374349,38.915296],"type":"Point"}
}