{
  "type": "Feature",
  "properties": {
    "iso:country":"US",
    "sg:address":"911 N Broadway St",
    "sg:city":"Knob Noster",
    "sg:classifiers":[
        {
            "category":"Real Estate",
            "subcategory":"Real Estate Agent",
            "type":"Services"
        }
    ],
    "sg:phone":"+1 660 563 3202",
    "sg:postcode":"65336",
    "sg:province":"MO",
    "sg:tags":[
        "residential",
        "rental"
    ],
    "wof:name":"T C T Inc",
    "wof:placetype":"venue"
},
  "geometry": {"coordinates":[-93.558178,38.774348],"type":"Point"}
}