{
  "type": "Feature",
  "properties": {
    "iso:country":"US",
    "sg:address":"1702 E Seminole St",
    "sg:city":"Springfield",
    "sg:classifiers":[
        {
            "category":"Real Estate",
            "subcategory":"Developer",
            "type":"Services"
        }
    ],
    "sg:phone":"+1 417 881 9499",
    "sg:postcode":"65804",
    "sg:province":"MO",
    "sg:tags":[
        "national",
        "cemetery"
    ],
    "wof:name":"Springfield National Cemetery",
    "wof:placetype":"venue"
},
  "geometry": {"coordinates":[-93.262569,37.174226],"type":"Point"}
}