{
  "type": "Feature",
  "properties": {
    "iso:country":"US",
    "sg:address":"20 US Hwy 60 Bus",
    "sg:city":"Dexter",
    "sg:classifiers":[
        {
            "category":"Retail",
            "subcategory":"Auto Repair",
            "type":"Services"
        }
    ],
    "sg:phone":"+1 573 624 6633",
    "sg:postcode":"63841",
    "sg:province":"MO",
    "sg:tags":[
        "body",
        "automobile",
        "painting"
    ],
    "wof:name":"Ray Pixley Auto Body",
    "wof:placetype":"venue"
},
  "geometry": {"coordinates":[-89.951645,36.799129],"type":"Point"}
}