{
  "type": "Feature",
  "properties": {
    "iso:country":"US",
    "sg:address":"609 E Myrtle St",
    "sg:city":"Independence",
    "sg:classifiers":[
        {
            "category":"Retail",
            "subcategory":"Repair Shop",
            "type":"Services"
        }
    ],
    "sg:phone":"+1 816 461 1617",
    "sg:postcode":"64055",
    "sg:province":"MO",
    "wof:name":"Sheer Quality Cleaning",
    "wof:placetype":"venue"
},
  "geometry": {"coordinates":[-94.40613999999999,39.076042],"type":"Point"}
}