{
  "type": "Feature",
  "properties": {
    "iso:country":"US",
    "sg:address":"7409 Co Rd 417",
    "sg:city":"Fulton",
    "sg:classifiers":[
        {
            "category":"Building & Trades",
            "subcategory":"Construction",
            "type":"Services"
        }
    ],
    "sg:phone":"+1 573 642 1823",
    "sg:postcode":"65251",
    "sg:province":"MO",
    "sg:tags":[
        "house"
    ],
    "wof:name":"Cg Homes",
    "wof:placetype":"venue"
},
  "geometry": {"coordinates":[-91.981495,38.790579],"type":"Point"}
}