{
  "type": "Feature",
  "properties": {
    "iso:country":"US",
    "sg:address":"2401 Frederick Ave",
    "sg:city":"Saint Joseph",
    "sg:classifiers":[
        {
            "category":"Health Services",
            "subcategory":"Doctor",
            "type":"Services"
        }
    ],
    "sg:phone":"+1 816 279 9761",
    "sg:postcode":"64506",
    "sg:province":"MO",
    "wof:name":"Jones Larry A",
    "wof:placetype":"venue"
},
  "geometry": {"coordinates":[-94.830725,39.776782],"type":"Point"}
}