{
  "type": "Feature",
  "properties": {
    "iso:country":"US",
    "sg:address":"10380 State Hwy 171",
    "sg:city":"Carl Junction",
    "sg:classifiers":[
        {
            "category":"Manufacturing",
            "subcategory":"Building Materials",
            "type":"Manufacturing & Wholesale Goods"
        }
    ],
    "sg:phone":"+1 417 649 6500",
    "sg:postcode":"64834",
    "sg:province":"MO",
    "sg:tags":[
        "installs",
        "cabinetry",
        "mfg"
    ],
    "wof:name":"Southwest Custom Cabinets Inc",
    "wof:placetype":"venue"
},
  "geometry": {"coordinates":[-94.564001,37.210081],"type":"Point"}
}