{
  "type": "Feature",
  "properties": {
    "iso:country":"US",
    "sg:address":"1222 W 39 St",
    "sg:city":"Kansas City",
    "sg:classifiers":[
        {
            "category":"Personal",
            "subcategory":"Beauty Salon",
            "type":"Services"
        }
    ],
    "sg:phone":"+1 816 531 3393",
    "sg:postcode":"64111",
    "sg:province":"MO",
    "sg:tags":[
        "shop"
    ],
    "wof:name":"Dyeabolique",
    "wof:placetype":"venue"
},
  "geometry": {"coordinates":[-94.601219,39.057196],"type":"Point"}
}