{
  "type": "Feature",
  "properties": {
    "iso:country":"US",
    "sg:address":"4104 SE Valleyview Ln",
    "sg:city":"Holt",
    "sg:classifiers":[
        {
            "category":"Building & Trades",
            "subcategory":"Construction",
            "type":"Services"
        }
    ],
    "sg:phone":"+1 816 741 3038",
    "sg:postcode":"64048",
    "sg:province":"MO",
    "sg:tags":[
        "concrete",
        "contractor"
    ],
    "wof:name":"Dishingers Concrete",
    "wof:placetype":"venue"
},
  "geometry": {"coordinates":[-94.339102,39.465183],"type":"Point"}
}