{
  "type": "Feature",
  "properties": {
    "iso:country":"US",
    "sg:address":"15380 Highcroft Dr",
    "sg:city":"Chesterfield",
    "sg:classifiers":[
        {
            "category":"Education",
            "subcategory":"School",
            "type":"Public Place"
        }
    ],
    "sg:phone":"+1 314 415 6400",
    "sg:postcode":"63017",
    "sg:province":"MO",
    "sg:website":"www.pkwy.k12.mo.us",
    "wof:name":"Highcroft Ridge Elementary",
    "wof:placetype":"venue"
},
  "geometry": {"coordinates":[-90.549634,38.645855],"type":"Point"}
}