{
  "type": "Feature",
  "properties": {
    "iso:country":"US",
    "sg:address":"5119 NW 85 St",
    "sg:city":"Kansas City",
    "sg:classifiers":[
        {
            "category":"Real Estate",
            "subcategory":"Real Estate Agent",
            "type":"Services"
        }
    ],
    "sg:phone":"+1 816 414 4058",
    "sg:postcode":"64154",
    "sg:province":"MO",
    "wof:name":"Jenny L Burkhead",
    "wof:placetype":"venue"
},
  "geometry": {"coordinates":[-94.637857,39.249088],"type":"Point"}
}