{
  "type": "Feature",
  "properties": {
    "iso:country":"US",
    "sg:address":"548 S Main St",
    "sg:city":"Concordia",
    "sg:classifiers":[
        {
            "category":"Professional",
            "subcategory":"Credit Reporting & Collection",
            "type":"Services"
        }
    ],
    "sg:phone":"+1 660 463 7400",
    "sg:postcode":"64020",
    "sg:province":"MO",
    "sg:tags":[
        "agency"
    ],
    "wof:name":"Great River Accounts Svc",
    "wof:placetype":"venue"
},
  "geometry": {"coordinates":[-93.568192,38.983827],"type":"Point"}
}