{
  "type": "Feature",
  "properties": {
    "iso:country":"US",
    "sg:address":"605 E Commercial St",
    "sg:city":"Kennett",
    "sg:classifiers":[
        {
            "category":"Manufacturing",
            "subcategory":"Food",
            "type":"Manufacturing & Wholesale Goods"
        },
        {
            "category":"Food & Beverages",
            "subcategory":"Supermarket",
            "type":"Retail Goods"
        },
        {
            "category":"Food & Beverages",
            "subcategory":"Groceries & Convenience Stores",
            "type":"Retail Goods"
        }
    ],
    "sg:phone":"+1 573 888 3458",
    "sg:postcode":"63857",
    "sg:province":"MO",
    "sg:tags":[
        "product",
        "super"
    ],
    "wof:name":"Riceland Foods Inc.",
    "wof:placetype":"venue"
},
  "geometry": {"coordinates":[-90.051613,36.243969],"type":"Point"}
}