{
  "type": "Feature",
  "properties": {
    "iso:country":"US",
    "sg:address":"10816 Hillcrest Rd",
    "sg:city":"Kansas City",
    "sg:classifiers":[
        {
            "category":"Organizations",
            "subcategory":"Religious Organization",
            "type":"Services"
        }
    ],
    "sg:phone":"+1 816 761 3637",
    "sg:postcode":"64134",
    "sg:province":"MO",
    "sg:tags":[
        "church"
    ],
    "wof:name":"Trinity Bible Church",
    "wof:placetype":"venue"
},
  "geometry": {"coordinates":[-94.52301300000001,38.929147],"type":"Point"}
}