{
  "type": "Feature",
  "properties": {
    "iso:country":"US",
    "sg:address":"4268 N Oak Fwy",
    "sg:city":"Kansas City",
    "sg:classifiers":[
        {
            "category":"Health Services",
            "subcategory":"Doctor",
            "type":"Services"
        }
    ],
    "sg:phone":"+1 816 452 5800",
    "sg:postcode":"64116",
    "sg:province":"MO",
    "sg:tags":[
        "dentist"
    ],
    "wof:name":"Richard M Lanning DDS",
    "wof:placetype":"venue"
},
  "geometry": {"coordinates":[-94.576808,39.172084],"type":"Point"}
}