{
  "type": "Feature",
  "properties": {
    "iso:country":"US",
    "sg:address":"27165 Airport Trl",
    "sg:city":"Kirksville",
    "sg:classifiers":[
        {
            "category":"Airport",
            "type":"Transportation"
        }
    ],
    "sg:phone":"+1 660 627 0390",
    "sg:postcode":"63501",
    "sg:province":"MO",
    "sg:tags":[
        "aircraft",
        "maintenance"
    ],
    "wof:name":"D & R Airmotive",
    "wof:placetype":"venue"
},
  "geometry": {"coordinates":[-92.540335,40.092179],"type":"Point"}
}