{
  "type": "Feature",
  "properties": {
    "iso:country":"US",
    "sg:address":"709 N Gallatin St",
    "sg:city":"Hamilton",
    "sg:classifiers":[
        {
            "category":"Farming",
            "subcategory":"Livestock Farm",
            "type":"Manufacturing & Wholesale Goods"
        }
    ],
    "sg:phone":"+1 816 583 4025",
    "sg:postcode":"64644",
    "sg:province":"MO",
    "sg:tags":[
        "ranch"
    ],
    "wof:name":"Kenneth Bell",
    "wof:placetype":"venue"
},
  "geometry": {"coordinates":[-94.00294700000001,39.748099],"type":"Point"}
}