{
  "type": "Feature",
  "properties": {
    "iso:country":"US",
    "sg:address":"3200 Woodbine Dr",
    "sg:city":"Columbia",
    "sg:classifiers":[
        {
            "category":"Health Services",
            "subcategory":"Optometrist",
            "type":"Services"
        }
    ],
    "sg:phone":"+1 573 874 2030",
    "sg:postcode":"65203",
    "sg:province":"MO",
    "wof:name":"Jeffery M Gamble OD",
    "wof:placetype":"venue"
},
  "geometry": {"coordinates":[-92.363687,38.9175],"type":"Point"}
}