{
  "type": "Feature",
  "properties": {
    "iso:country":"US",
    "sg:address":"15103 Hwy 17",
    "sg:city":"Eugene",
    "sg:classifiers":[
        {
            "category":"Manufacturing",
            "subcategory":"Glass & Minerals",
            "type":"Manufacturing & Wholesale Goods"
        }
    ],
    "sg:phone":"+1 573 498 3876",
    "sg:postcode":"65032",
    "sg:province":"MO",
    "sg:tags":[
        "concrete",
        "product",
        "cut",
        "mfg"
    ],
    "wof:name":"Eugene Quarries LLC",
    "wof:placetype":"venue"
},
  "geometry": {"coordinates":[-92.397426,38.372574],"type":"Point"}
}