{
  "type": "Feature",
  "properties": {
    "iso:country":"US",
    "sg:address":"50 Co Rd 410",
    "sg:city":"Poplar Bluff",
    "sg:classifiers":[
        {
            "category":"Building & Trades",
            "subcategory":"Construction",
            "type":"Services"
        }
    ],
    "sg:phone":"+1 573 686 2899",
    "sg:postcode":"63901",
    "sg:province":"MO",
    "sg:tags":[
        "carpentry",
        "material",
        "contractor"
    ],
    "wof:name":"Bluff Overhead Door Inc",
    "wof:placetype":"venue"
},
  "geometry": {"coordinates":[-90.53729800000001,36.84616],"type":"Point"}
}