{
  "type": "Feature",
  "properties": {
    "iso:country":"US",
    "sg:address":"610 Calhoun St",
    "sg:city":"Chillicothe",
    "sg:classifiers":[
        {
            "category":"Autos & Motor Vehicles",
            "subcategory":"Auto Supplies",
            "type":"Retail Goods"
        }
    ],
    "sg:phone":"+1 660 646 4515",
    "sg:postcode":"64601",
    "sg:province":"MO",
    "sg:tags":[
        "automobile",
        "parts",
        "accessory",
        "part",
        "accessories-wholesale",
        "manufacturer"
    ],
    "wof:name":"Republic Automotive Parts Sales, Inc",
    "wof:placetype":"venue"
},
  "geometry": {"coordinates":[-93.551436,39.795158],"type":"Point"}
}