{
  "type": "Feature",
  "properties": {
    "iso:country":"US",
    "sg:address":"10073 Manchester Rd",
    "sg:city":"Kirkwood",
    "sg:classifiers":[
        {
            "category":"Education",
            "subcategory":"College",
            "type":"Public Place"
        }
    ],
    "sg:phone":"+1 314 965 2285",
    "sg:postcode":"63122",
    "sg:province":"MO",
    "sg:tags":[
        "academic",
        "school"
    ],
    "wof:name":"Missouri College",
    "wof:placetype":"venue"
},
  "geometry": {"coordinates":[-90.387624,38.602769],"type":"Point"}
}