{
  "type": "Feature",
  "properties": {
    "iso:country":"US",
    "sg:address":"7323 Prospect Ave",
    "sg:city":"Kansas City",
    "sg:classifiers":[
        {
            "category":"Retail",
            "subcategory":"Auto Repair",
            "type":"Services"
        }
    ],
    "sg:phone":"+1 816 333 2900",
    "sg:postcode":"64132",
    "sg:province":"MO",
    "sg:tags":[
        "repairing",
        "automobile",
        "general"
    ],
    "wof:name":"B & R Auto Repair",
    "wof:placetype":"venue"
},
  "geometry": {"coordinates":[-94.55709,38.993005],"type":"Point"}
}