{
  "type": "Feature",
  "properties": {
    "iso:country":"US",
    "sg:address":"2305 Stoney End Ct",
    "sg:city":"Florissant",
    "sg:classifiers":[
        {
            "category":"Professional",
            "subcategory":"Business Services",
            "type":"Services"
        }
    ],
    "sg:phone":"+1 314 831 5595",
    "sg:postcode":"63031",
    "sg:province":"MO",
    "wof:name":"Sullivan Distributing",
    "wof:placetype":"venue"
},
  "geometry": {"coordinates":[-90.346155,38.825817],"type":"Point"}
}