{
  "type": "Feature",
  "properties": {
    "iso:country":"US",
    "sg:address":"105 S Ozark",
    "sg:city":"Lewistown",
    "sg:classifiers":[
        {
            "category":"Building & Trades",
            "subcategory":"Construction",
            "type":"Services"
        }
    ],
    "sg:phone":"+1 573 497 9383",
    "sg:postcode":"63452",
    "sg:province":"MO",
    "sg:tags":[
        "company"
    ],
    "wof:name":"ACFS-Russel Myers",
    "wof:placetype":"venue"
},
  "geometry": {"coordinates":[-91.81485499999999,40.081538],"type":"Point"}
}