{
  "type": "Feature",
  "properties": {
    "iso:country":"US",
    "sg:address":"105 W 3rd St",
    "sg:city":"Dixon",
    "sg:classifiers":[
        {
            "category":"Building & Trades",
            "subcategory":"Construction",
            "type":"Services"
        }
    ],
    "sg:phone":"+1 573 759 2220",
    "sg:postcode":"65459",
    "sg:province":"MO",
    "sg:tags":[
        "layer",
        "carpet"
    ],
    "wof:name":"ARK Flooring",
    "wof:placetype":"venue"
},
  "geometry": {"coordinates":[-92.09519299999999,37.993158],"type":"Point"}
}