{
  "type": "Feature",
  "properties": {
    "addr:full":"440 N Kirkwood Rd St Louis MO 63122",
    "addr:housenumber":"440",
    "addr:postcode":"63122",
    "addr:street":"N Kirkwood Rd",
    "iso:country":"US",
    "sg:address":"440 N Kirkwood Rd",
    "sg:city":"St Louis",
    "sg:classifiers":[
        {
            "category":"Shopping",
            "subcategory":"Bicycles & Sporting Goods",
            "type":"Retail Goods"
        }
    ],
    "sg:phone":"+1 314 962 7229",
    "sg:postcode":"63122",
    "sg:province":"MO",
    "sg:website":"www.alpineshop.com",
    "wof:name":"Alpine Shop",
    "wof:placetype":"venue"
},
  "geometry": {"coordinates":[-90.406195,38.586096],"type":"Point"}
}