{
  "type": "Feature",
  "properties": {
    "iso:country":"US",
    "sg:address":"6 W Main St",
    "sg:city":"Sullivan",
    "sg:classifiers":[
        {
            "category":"Manufacturing",
            "subcategory":"Printing",
            "type":"Manufacturing & Wholesale Goods"
        }
    ],
    "sg:phone":"+1 573 860 6397",
    "sg:postcode":"63080",
    "sg:province":"MO",
    "sg:tags":[
        "newspaper"
    ],
    "wof:name":"Press-Journal News",
    "wof:placetype":"venue"
},
  "geometry": {"coordinates":[-91.158778,38.210226],"type":"Point"}
}