{
  "type": "Feature",
  "properties": {
    "iso:country":"US",
    "sg:address":"7976 E Hwy B",
    "sg:city":"Stockton",
    "sg:classifiers":[
        {
            "category":"Farming",
            "subcategory":"Livestock Farm",
            "type":"Manufacturing & Wholesale Goods"
        }
    ],
    "sg:phone":"+1 417 398 2662",
    "sg:postcode":"65785",
    "sg:province":"MO",
    "sg:tags":[
        "feedlot",
        "field",
        "crop",
        "beef",
        "cattle"
    ],
    "wof:name":"King Theron",
    "wof:placetype":"venue"
},
  "geometry": {"coordinates":[-93.94147700000001,37.622739],"type":"Point"}
}