{
  "type": "Feature",
  "properties": {
    "iso:country":"US",
    "sg:address":"10600 N Pomona Ave",
    "sg:city":"Kansas City",
    "sg:classifiers":[
        {
            "category":"Airline",
            "type":"Transportation"
        }
    ],
    "sg:phone":"+1 816 734 9443",
    "sg:postcode":"64153",
    "sg:province":"MO",
    "sg:tags":[
        "contractor",
        "over",
        "express",
        "for",
        "night"
    ],
    "wof:name":"Hock Transport Inc",
    "wof:placetype":"venue"
},
  "geometry": {"coordinates":[-94.671104,39.285376],"type":"Point"}
}