{
  "type": "Feature",
  "properties": {
    "iso:country":"US",
    "sg:address":"5990 Page Blvd",
    "sg:city":"Saint Louis",
    "sg:classifiers":[
        {
            "category":"Social Services",
            "subcategory":"Child Care",
            "type":"Services"
        }
    ],
    "sg:phone":"+1 314 725 5710",
    "sg:postcode":"63112",
    "sg:province":"MO",
    "sg:tags":[
        "day"
    ],
    "wof:name":"Good Shepherd Infant-Toddler Center",
    "wof:placetype":"venue"
},
  "geometry": {"coordinates":[-90.28838500000001,38.669518],"type":"Point"}
}