{
  "type": "Feature",
  "properties": {
    "iso:country":"US",
    "sg:address":"21 N Meramec Ave",
    "sg:city":"St Louis",
    "sg:classifiers":[
        {
            "category":"Professional",
            "type":"Services"
        }
    ],
    "sg:phone":"+1 314 862 4484",
    "sg:postcode":"63105",
    "sg:province":"MO",
    "sg:tags":[
        "establishment"
    ],
    "wof:name":"Dunne Bodet LLC",
    "wof:placetype":"venue"
},
  "geometry": {"coordinates":[-90.339556,38.651518],"type":"Point"}
}