{
  "type": "Feature",
  "properties": {
    "iso:country":"US",
    "sg:address":"1305 NE Douglas St",
    "sg:city":"Lees Summit",
    "sg:classifiers":[
        {
            "category":"Bakery",
            "type":"Food & Drink"
        }
    ],
    "sg:menulink":"http://www.allmenus.com/mo/prairie/105878-panera-bread/menu/",
    "sg:phone":"+1 816 524 4500",
    "sg:postcode":"64086",
    "sg:province":"MO",
    "sg:tags":[
        "american",
        "sandwich",
        "pastry"
    ],
    "wof:name":"Panera Bread",
    "wof:placetype":"venue"
},
  "geometry": {"coordinates":[-94.378523,38.935739],"type":"Point"}
}