{
  "type": "Feature",
  "properties": {
    "iso:country":"US",
    "sg:address":"827 Texas Ct",
    "sg:city":"O Fallon",
    "sg:classifiers":[
        {
            "category":"Wholesale",
            "subcategory":"Machinery & Supplies",
            "type":"Manufacturing & Wholesale Goods"
        }
    ],
    "sg:phone":"+1 636 272 2266",
    "sg:postcode":"63366",
    "sg:province":"MO",
    "sg:tags":[
        "distributor",
        "engine",
        "aircraft",
        "parts"
    ],
    "wof:name":"Aviation Mtl Technical Support",
    "wof:placetype":"venue"
},
  "geometry": {"coordinates":[-90.751879,38.808592],"type":"Point"}
}