{
  "type": "Feature",
  "properties": {
    "iso:country":"US",
    "sg:address":"4100 N Newstead Ave",
    "sg:city":"Saint Louis",
    "sg:classifiers":[
        {
            "category":"Building & Trades",
            "subcategory":"Construction",
            "type":"Services"
        }
    ],
    "sg:phone":"+1 314 382 6947",
    "sg:postcode":"63115",
    "sg:province":"MO",
    "sg:tags":[
        "home",
        "general"
    ],
    "wof:name":"Progressive Home Sales & Rmdlg",
    "wof:placetype":"venue"
},
  "geometry": {"coordinates":[-90.232968,38.674504],"type":"Point"}
}