{
  "type": "Feature",
  "properties": {
    "iso:country":"US",
    "sg:address":"2058 Donnell Dr",
    "sg:city":"Barnhart",
    "sg:classifiers":[
        {
            "category":"Building & Trades",
            "subcategory":"Construction",
            "type":"Services"
        }
    ],
    "sg:phone":"+1 314 267 2215",
    "sg:postcode":"63012",
    "sg:province":"MO",
    "sg:tags":[
        "carpentry",
        "contractor"
    ],
    "wof:name":"Win Awn Company",
    "wof:placetype":"venue"
},
  "geometry": {"coordinates":[-90.41381699999999,38.34514],"type":"Point"}
}