{
  "type": "Feature",
  "properties": {
    "iso:country":"US",
    "sg:address":"500 E Pine St",
    "sg:city":"Poplar Bluff",
    "sg:classifiers":[
        {
            "category":"Autos & Motor Vehicles",
            "subcategory":"Automobile Sales",
            "type":"Retail Goods"
        }
    ],
    "sg:phone":"+1 573 686 0195",
    "sg:postcode":"63901",
    "sg:province":"MO",
    "sg:tags":[
        "car",
        "dealer"
    ],
    "wof:name":"Phelps Auto Sales",
    "wof:placetype":"venue"
},
  "geometry": {"coordinates":[-90.384423,36.757871],"type":"Point"}
}