{
  "type": "Feature",
  "properties": {
    "iso:country":"US",
    "sg:address":"5513 Providence Place Dr",
    "sg:city":"Saint Louis",
    "sg:classifiers":[
        {
            "category":"Professional",
            "subcategory":"Computer Services",
            "type":"Services"
        }
    ],
    "sg:phone":"+1 314 894 9556",
    "sg:postcode":"63129",
    "sg:province":"MO",
    "sg:tags":[
        "design",
        "system"
    ],
    "wof:name":"M & L Tech Network",
    "wof:placetype":"venue"
},
  "geometry": {"coordinates":[-90.35364800000001,38.477017],"type":"Point"}
}