{
  "type": "Feature",
  "properties": {
    "iso:country":"US",
    "sg:address":"407 Market St",
    "sg:city":"Hermann",
    "sg:classifiers":[
        {
            "category":"Shopping",
            "subcategory":"Gifts & Souvenirs",
            "type":"Retail Goods"
        }
    ],
    "sg:phone":"+1 573 486 5107",
    "sg:postcode":"65041",
    "sg:province":"MO",
    "wof:name":"Special Creations",
    "wof:placetype":"venue"
},
  "geometry": {"coordinates":[-91.437815,38.704276],"type":"Point"}
}