{
  "type": "Feature",
  "properties": {
    "iso:country":"US",
    "sg:address":"1863 Bluebird Rd",
    "sg:city":"Cabool",
    "sg:classifiers":[
        {
            "category":"Autos & Motor Vehicles",
            "subcategory":"Auto Supplies",
            "type":"Retail Goods"
        }
    ],
    "sg:phone":"+1 417 962 2299",
    "sg:postcode":"65689",
    "sg:province":"MO",
    "sg:tags":[
        "automobile",
        "rebuilt",
        "part",
        "supplies-used"
    ],
    "wof:name":"L&E Automotive",
    "wof:placetype":"venue"
},
  "geometry": {"coordinates":[-92.101068,37.108496],"type":"Point"}
}