{
  "type": "Feature",
  "properties": {
    "iso:country":"US",
    "sg:address":"927 Main Plaza Dr Ste 3",
    "sg:city":"Wentzville",
    "sg:classifiers":[
        {
            "category":"Banks & Credit Unions",
            "subcategory":"Investment Brokerage",
            "type":"Services"
        }
    ],
    "sg:phone":"+1 636 639 6700",
    "sg:postcode":"63385",
    "sg:province":"MO",
    "sg:website":"http://www.edwardjones.com",
    "wof:name":"Edward Jones 18141",
    "wof:placetype":"venue"
},
  "geometry": {"coordinates":[-90.85036599999999,38.820037],"type":"Point"}
}