{
  "type": "Feature",
  "properties": {
    "iso:country":"US",
    "sg:address":"116 W 3 St",
    "sg:city":"Kansas City",
    "sg:classifiers":[
        {
            "category":"Professional",
            "subcategory":"Management & Consulting",
            "type":"Services"
        }
    ],
    "sg:phone":"+1 816 472 1930",
    "sg:postcode":"64105",
    "sg:province":"MO",
    "sg:tags":[
        "relations",
        "counselor",
        "public",
        "business"
    ],
    "sg:website":"www.janemobley.com",
    "wof:name":"Jane Mobley Associates Inc",
    "wof:placetype":"venue"
},
  "geometry": {"coordinates":[-94.58569199999999,39.109494],"type":"Point"}
}