{
  "type": "Feature",
  "properties": {
    "iso:country":"US",
    "sg:address":"220 Jan Howard Expy",
    "sg:city":"West Plains",
    "sg:classifiers":[
        {
            "category":"Travel",
            "subcategory":"Hotels & Motels",
            "type":"Entertainment"
        }
    ],
    "sg:phone":"+1 417 257 2711",
    "sg:postcode":"65775",
    "sg:province":"MO",
    "sg:tags":[
        "operation",
        "fitness",
        "physical",
        "facility"
    ],
    "sg:website":"www.bestwestern.com",
    "wof:name":"Best Western Inn",
    "wof:placetype":"venue"
},
  "geometry": {"coordinates":[-91.877471,36.727815],"type":"Point"}
}