{
  "type": "Feature",
  "properties": {
    "iso:country":"US",
    "sg:address":"24265 Sprint Ln",
    "sg:city":"Waynesville",
    "sg:classifiers":[
        {
            "category":"Personal",
            "subcategory":"Beauty Salon",
            "type":"Services"
        }
    ],
    "sg:phone":"+1 573 774 6208",
    "sg:postcode":"65583",
    "sg:province":"MO",
    "wof:name":"Alexander, Marshel L",
    "wof:placetype":"venue"
},
  "geometry": {"coordinates":[-92.198818,37.808926],"type":"Point"}
}