{
  "type": "Feature",
  "properties": {
    "iso:country":"US",
    "sg:address":"6806 Gravois Ave",
    "sg:city":"Saint Louis",
    "sg:classifiers":[
        {
            "category":"Retail",
            "subcategory":"Auto Repair",
            "type":"Services"
        }
    ],
    "sg:phone":"+1 314 352 1100",
    "sg:postcode":"63116",
    "sg:province":"MO",
    "sg:tags":[
        "body",
        "shop",
        "painting",
        "automobile"
    ],
    "wof:name":"Losito Brothers Auto Body Reprg",
    "wof:placetype":"venue"
},
  "geometry": {"coordinates":[-90.284302,38.570999],"type":"Point"}
}