{
  "type": "Feature",
  "properties": {
    "iso:country":"US",
    "sg:address":"11227 Twitty Dr",
    "sg:city":"Rolla",
    "sg:classifiers":[
        {
            "category":"Freight",
            "type":"Transportation"
        }
    ],
    "sg:phone":"+1 573 364 5721",
    "sg:postcode":"65401",
    "sg:province":"MO",
    "sg:tags":[
        "broker",
        "trucking"
    ],
    "wof:name":"Turtle Trucking",
    "wof:placetype":"venue"
},
  "geometry": {"coordinates":[-91.75655399999999,37.968304],"type":"Point"}
}