{
  "type": "Feature",
  "properties": {
    "iso:country":"US",
    "sg:address":"3865 Lemay Ferry Rd",
    "sg:city":"Saint Louis",
    "sg:classifiers":[
        {
            "category":"Social Services",
            "subcategory":"Job Training",
            "type":"Services"
        }
    ],
    "sg:phone":"+1 314 845 1922",
    "sg:postcode":"63125",
    "sg:province":"MO",
    "sg:tags":[
        "specialty",
        "outpatient"
    ],
    "wof:name":"Metropltan Emplyment Rhblttion",
    "wof:placetype":"venue"
},
  "geometry": {"coordinates":[-90.32384500000001,38.508047],"type":"Point"}
}