{
  "type": "Feature",
  "properties": {
    "iso:country":"US",
    "sg:address":"6800 US Hwy 24",
    "sg:city":"Palmyra",
    "sg:classifiers":[
        {
            "category":"Real Estate",
            "subcategory":"Real Estate Operator",
            "type":"Services"
        }
    ],
    "sg:phone":"+1 573 221 6209",
    "sg:postcode":"63461",
    "sg:province":"MO",
    "sg:tags":[
        "property",
        "lessor"
    ],
    "wof:name":"Frazier Paugh",
    "wof:placetype":"venue"
},
  "geometry": {"coordinates":[-91.531649,39.692609],"type":"Point"}
}