{
  "type": "Feature",
  "properties": {
    "iso:country":"US",
    "sg:address":"120 S Laura St",
    "sg:city":"Maryville",
    "sg:classifiers":[
        {
            "category":"Organizations",
            "subcategory":"Religious Organization",
            "type":"Services"
        }
    ],
    "sg:phone":"+1 660 582 7500",
    "sg:postcode":"64468",
    "sg:province":"MO",
    "wof:name":"Laura Street Baptist Church",
    "wof:placetype":"venue"
},
  "geometry": {"coordinates":[-94.85995699999999,40.345196],"type":"Point"}
}