{
  "type": "Feature",
  "properties": {
    "iso:country":"US",
    "sg:address":"402 6th St",
    "sg:city":"Boonville",
    "sg:classifiers":[
        {
            "category":"Personal",
            "subcategory":"Beauty Salon",
            "type":"Services"
        }
    ],
    "sg:phone":"+1 660 882 3327",
    "sg:postcode":"65233",
    "sg:province":"MO",
    "wof:name":"Shearific Cuts N More",
    "wof:placetype":"venue"
},
  "geometry": {"coordinates":[-92.742266,38.97577],"type":"Point"}
}