{
  "type": "Feature",
  "properties": {
    "iso:country":"US",
    "sg:address":"341 W Madison Ave",
    "sg:city":"Saint Louis",
    "sg:classifiers":[
        {
            "category":"Professional",
            "subcategory":"Business Services",
            "type":"Services"
        }
    ],
    "sg:phone":"+1 314 821 8112",
    "sg:postcode":"63122",
    "sg:province":"MO",
    "wof:name":"Benchmark Home Inspections",
    "wof:placetype":"venue"
},
  "geometry": {"coordinates":[-90.41238199999999,38.580321],"type":"Point"}
}