{
  "type": "Feature",
  "properties": {
    "iso:country":"US",
    "sg:address":"709 S Broadway St",
    "sg:city":"Oak Grove",
    "sg:classifiers":[
        {
            "category":"Food & Beverages",
            "subcategory":"Bakery",
            "type":"Retail Goods"
        }
    ],
    "sg:phone":"+1 816 625 3666",
    "sg:postcode":"64075",
    "sg:province":"MO",
    "wof:name":"Tc Donuts",
    "wof:placetype":"venue"
},
  "geometry": {"coordinates":[-94.128901,39.01079],"type":"Point"}
}