{
  "type": "Feature",
  "properties": {
    "iso:country":"US",
    "sg:address":"28959 Odessa Ave",
    "sg:city":"Anabel",
    "sg:classifiers":[
        {
            "category":"Farming",
            "subcategory":"Farm",
            "type":"Manufacturing & Wholesale Goods"
        }
    ],
    "sg:phone":"+1 660 699 3431",
    "sg:postcode":"63431",
    "sg:province":"MO",
    "sg:tags":[
        "livestock",
        "crop",
        "general"
    ],
    "wof:name":"Don Schumann",
    "wof:placetype":"venue"
},
  "geometry": {"coordinates":[-92.330838,39.7647],"type":"Point"}
}