{
  "type": "Feature",
  "properties": {
    "iso:country":"US",
    "sg:address":"206 Depot St",
    "sg:city":"Potosi",
    "sg:classifiers":[
        {
            "category":"Autos & Motor Vehicles",
            "subcategory":"Auto Supplies",
            "type":"Retail Goods"
        }
    ],
    "sg:phone":"+1 573 436 5823",
    "sg:postcode":"63664",
    "sg:province":"MO",
    "sg:tags":[
        "lube",
        "oil"
    ],
    "wof:name":"Potosi Oil & Lube",
    "wof:placetype":"venue"
},
  "geometry": {"coordinates":[-90.782927,37.934065],"type":"Point"}
}