{
  "type": "Feature",
  "properties": {
    "iso:country":"US",
    "sg:address":"1319 Old Hwy 50 E",
    "sg:city":"Union",
    "sg:classifiers":[
        {
            "category":"Retail",
            "subcategory":"Auto Repair",
            "type":"Services"
        }
    ],
    "sg:phone":"+1 636 583 4408",
    "sg:postcode":"63084",
    "sg:province":"MO",
    "sg:tags":[
        "body",
        "shop",
        "general"
    ],
    "wof:name":"County Wide Collision Repair",
    "wof:placetype":"venue"
},
  "geometry": {"coordinates":[-90.97525400000001,38.433891],"type":"Point"}
}