{
  "type": "Feature",
  "properties": {
    "iso:country":"US",
    "sg:address":"18716 Grove Cir",
    "sg:city":"Independence",
    "sg:classifiers":[
        {
            "category":"Building & Trades",
            "subcategory":"Construction",
            "type":"Services"
        }
    ],
    "sg:phone":"+1 816 796 0678",
    "sg:postcode":"64058",
    "sg:province":"MO",
    "sg:tags":[
        "hanging",
        "contractor"
    ],
    "wof:name":"Heritage One Inc",
    "wof:placetype":"venue"
},
  "geometry": {"coordinates":[-94.353877,39.140536],"type":"Point"}
}