{
  "type": "Feature",
  "properties": {
    "iso:country":"US",
    "sg:address":"231 S Bemiston Ave",
    "sg:city":"St Louis",
    "sg:classifiers":[
        {
            "category":"Professional",
            "subcategory":"Advertising",
            "type":"Services"
        }
    ],
    "sg:phone":"+1 314 322 6605",
    "sg:postcode":"63105",
    "sg:province":"MO",
    "sg:tags":[
        "mail",
        "direct"
    ],
    "wof:name":"Virtual Design House",
    "wof:placetype":"venue"
},
  "geometry": {"coordinates":[-90.337445,38.646569],"type":"Point"}
}