{
  "type": "Feature",
  "properties": {
    "iso:country":"US",
    "sg:address":"8 Courtney Pl",
    "sg:city":"Warrenton",
    "sg:phone":"+1 636 456 3430",
    "sg:postcode":"63383",
    "sg:province":"MO",
    "sg:tags":[
        "beef",
        "farm",
        "corn",
        "soybean",
        "cattle",
        "feedlot"
    ],
    "wof:name":"Hopewell Valley Farms",
    "wof:placetype":"venue"
},
  "geometry": {"coordinates":[-91.16341,38.805682],"type":"Point"}
}