{
  "type": "Feature",
  "properties": {
    "iso:country":"US",
    "sg:address":"8812 Blue Ridge Blvd",
    "sg:city":"Kansas City",
    "sg:classifiers":[
        {
            "category":"Autos & Motor Vehicles",
            "subcategory":"Automobile Sales",
            "type":"Retail Goods"
        }
    ],
    "sg:phone":"+1 816 763 8088",
    "sg:postcode":"64138",
    "sg:province":"MO",
    "sg:tags":[
        "used"
    ],
    "wof:name":"Vista Auto Mart",
    "wof:placetype":"venue"
},
  "geometry": {"coordinates":[-94.49777400000001,38.96227],"type":"Point"}
}