{
  "type": "Feature",
  "properties": {
    "iso:country":"US",
    "sg:address":"2219 W College St",
    "sg:city":"Springfield",
    "sg:classifiers":[
        {
            "category":"Personal",
            "subcategory":"Beauty Salon",
            "type":"Services"
        }
    ],
    "sg:phone":"+1 417 869 0933",
    "sg:postcode":"65806",
    "sg:province":"MO",
    "sg:tags":[
        "shop"
    ],
    "wof:name":"Golden Girls Family Salon",
    "wof:placetype":"venue"
},
  "geometry": {"coordinates":[-93.322785,37.208878],"type":"Point"}
}