{
  "type": "Feature",
  "properties": {
    "iso:country":"US",
    "sg:address":"7316 Twin River Rd",
    "sg:city":"Eureka",
    "sg:classifiers":[
        {
            "category":"Retail",
            "subcategory":"Repair Shop",
            "type":"Services"
        }
    ],
    "sg:phone":"+1 636 938 4739",
    "sg:postcode":"63025",
    "sg:province":"MO",
    "wof:name":"American Motorcycle Co",
    "wof:placetype":"venue"
},
  "geometry": {"coordinates":[-90.599479,38.471779],"type":"Point"}
}