{
  "type": "Feature",
  "properties": {
    "iso:country":"US",
    "sg:address":"2779 Darla Ct",
    "sg:city":"Saint Louis",
    "sg:classifiers":[
        {
            "category":"Freight",
            "type":"Transportation"
        }
    ],
    "sg:phone":"+1 314 868 4518",
    "sg:postcode":"63136",
    "sg:province":"MO",
    "sg:tags":[
        "gravel",
        "hauling"
    ],
    "wof:name":"New Millenium",
    "wof:placetype":"venue"
},
  "geometry": {"coordinates":[-90.267433,38.731811],"type":"Point"}
}