{
  "type": "Feature",
  "properties": {
    "iso:country":"US",
    "sg:address":"1235 E Cherokee St",
    "sg:city":"Springfield",
    "sg:classifiers":[
        {
            "category":"Personal",
            "subcategory":"Beauty Salon",
            "type":"Services"
        }
    ],
    "sg:phone":"+1 417 885 2889",
    "sg:postcode":"65804",
    "sg:province":"MO",
    "sg:tags":[
        "shop"
    ],
    "wof:name":"Martaun's Beauty Salon",
    "wof:placetype":"venue"
},
  "geometry": {"coordinates":[-93.274486,37.178246],"type":"Point"}
}