{
  "type": "Feature",
  "properties": {
    "iso:country":"US",
    "sg:address":"218 N Joplin Ave",
    "sg:city":"Joplin",
    "sg:classifiers":[
        {
            "category":"Building & Trades",
            "subcategory":"Construction",
            "type":"Services"
        }
    ],
    "sg:phone":"+1 417 782 5646",
    "sg:postcode":"64801",
    "sg:province":"MO",
    "sg:tags":[
        "house"
    ],
    "wof:name":"Charlie Call",
    "wof:placetype":"venue"
},
  "geometry": {"coordinates":[-94.51426600000001,37.092688],"type":"Point"}
}