{
  "type": "Feature",
  "properties": {
    "iso:country":"US",
    "sg:address":"1846 E Meadowmere St",
    "sg:city":"Springfield",
    "sg:classifiers":[
        {
            "category":"Building & Trades",
            "subcategory":"Construction",
            "type":"Services"
        }
    ],
    "sg:phone":"+1 417 883 6555",
    "sg:postcode":"65804",
    "sg:province":"MO",
    "sg:tags":[
        "glass",
        "contractor"
    ],
    "wof:name":"Springfield Glass Company",
    "wof:placetype":"venue"
},
  "geometry": {"coordinates":[-93.260741,37.190967],"type":"Point"}
}