{
  "type": "Feature",
  "properties": {
    "iso:country":"US",
    "sg:address":"604 SE Industrial Dr",
    "sg:city":"Blue Springs",
    "sg:classifiers":[
        {
            "category":"Building & Trades",
            "subcategory":"Construction",
            "type":"Services"
        }
    ],
    "sg:phone":"+1 816 229 6620",
    "sg:postcode":"64014",
    "sg:province":"MO",
    "sg:tags":[
        "general",
        "contractor"
    ],
    "wof:name":"Realm Construction Inc",
    "wof:placetype":"venue"
},
  "geometry": {"coordinates":[-94.250777,39.011033],"type":"Point"}
}