{
  "type": "Feature",
  "properties": {
    "iso:country":"US",
    "sg:address":"6161 Bradley Manor Pl",
    "sg:city":"Saint Louis",
    "sg:classifiers":[
        {
            "category":"Building & Trades",
            "subcategory":"Construction",
            "type":"Services"
        }
    ],
    "sg:phone":"+1 314 892 7496",
    "sg:postcode":"63129",
    "sg:province":"MO",
    "sg:tags":[
        "excavation",
        "contractor"
    ],
    "wof:name":"David P Bradley Excavating Co",
    "wof:placetype":"venue"
},
  "geometry": {"coordinates":[-90.34679800000001,38.459521],"type":"Point"}
}