{
  "type": "Feature",
  "properties": {
    "iso:country":"US",
    "sg:address":"10 Carriage Hills Ct",
    "sg:city":"Cedar Hill",
    "sg:classifiers":[
        {
            "category":"Health Services",
            "subcategory":"Clinic",
            "type":"Services"
        },
        {
            "category":"Health Services",
            "subcategory":"Medical Lab",
            "type":"Services"
        }
    ],
    "sg:phone":"+1 636 274 7179",
    "sg:postcode":"63016",
    "sg:province":"MO",
    "sg:tags":[
        "laboratory"
    ],
    "wof:name":"Mobile Medical Solutions Inc",
    "wof:placetype":"venue"
},
  "geometry": {"coordinates":[-90.579504,38.335039],"type":"Point"}
}