{
  "type": "Feature",
  "properties": {
    "iso:country":"US",
    "sg:address":"2836 W Division St",
    "sg:city":"Springfield",
    "sg:classifiers":[
        {
            "category":"Manufacturing",
            "subcategory":"Glass & Minerals",
            "type":"Manufacturing & Wholesale Goods"
        }
    ],
    "sg:phone":"+1 417 862 9203",
    "sg:postcode":"65802",
    "sg:province":"MO",
    "sg:tags":[
        "ready",
        "mix",
        "mfg",
        "concrete"
    ],
    "wof:name":"Springfield Ready Mix Co Inc",
    "wof:placetype":"venue"
},
  "geometry": {"coordinates":[-93.33333,37.22555],"type":"Point"}
}