{
  "type": "Feature",
  "properties": {
    "iso:country":"US",
    "sg:address":"11211 Sherwood Oak Ct",
    "sg:city":"Saint Louis",
    "sg:classifiers":[
        {
            "category":"Wholesale",
            "subcategory":"Machinery & Supplies",
            "type":"Manufacturing & Wholesale Goods"
        }
    ],
    "sg:phone":"+1 314 991 2043",
    "sg:postcode":"63146",
    "sg:province":"MO",
    "sg:tags":[
        "equipment",
        "industrial",
        "transportation"
    ],
    "wof:name":"Rail Bearing Service Corp",
    "wof:placetype":"venue"
},
  "geometry": {"coordinates":[-90.41959900000001,38.68273],"type":"Point"}
}