{
  "type": "Feature",
  "properties": {
    "iso:country":"US",
    "sg:address":"3801 Baeumner Dr",
    "sg:city":"Arnold",
    "sg:classifiers":[
        {
            "category":"Manufacturing",
            "subcategory":"Building Materials",
            "type":"Manufacturing & Wholesale Goods"
        }
    ],
    "sg:phone":"+1 636 464 3374",
    "sg:postcode":"63010",
    "sg:province":"MO",
    "sg:tags":[
        "mfg"
    ],
    "wof:name":"Schell Stairbuilding Inc",
    "wof:placetype":"venue"
},
  "geometry": {"coordinates":[-90.372844,38.408815],"type":"Point"}
}