{
  "type": "Feature",
  "properties": {
    "iso:country":"US",
    "sg:address":"9021 State Hwy 15",
    "sg:city":"Mexico",
    "sg:classifiers":[
        {
            "category":"Building & Trades",
            "subcategory":"Plumbing",
            "type":"Services"
        }
    ],
    "sg:phone":"+1 573 581 8849",
    "sg:postcode":"65265",
    "sg:province":"MO",
    "sg:tags":[
        "plumbing",
        "contractor"
    ],
    "wof:name":"Hildebrand Plumbing & Heating",
    "wof:placetype":"venue"
},
  "geometry": {"coordinates":[-91.90426100000001,39.224169],"type":"Point"}
}