{
  "type": "Feature",
  "properties": {
    "iso:country":"US",
    "sg:address":"3631 Charlotte St",
    "sg:city":"Kansas City",
    "sg:classifiers":[
        {
            "category":"Building & Trades",
            "subcategory":"Construction",
            "type":"Services"
        }
    ],
    "sg:phone":"+1 816 216 1630",
    "sg:postcode":"64109",
    "sg:province":"MO",
    "sg:tags":[
        "site",
        "clean"
    ],
    "sg:website":"www.jana1.com",
    "wof:name":"Compusolve Janitorial Bldng",
    "wof:placetype":"venue"
},
  "geometry": {"coordinates":[-94.575357,39.059447],"type":"Point"}
}