{
  "type": "Feature",
  "properties": {
    "iso:country":"US",
    "sg:address":"21924 State Hwy 38",
    "sg:city":"Marshfield",
    "sg:classifiers":[
        {
            "category":"Farming",
            "subcategory":"Livestock Farm",
            "type":"Manufacturing & Wholesale Goods"
        }
    ],
    "sg:phone":"+1 417 468 5638",
    "sg:postcode":"65706",
    "sg:province":"MO",
    "sg:tags":[
        "beef",
        "feedlot",
        "cattle"
    ],
    "wof:name":"Beason Farms",
    "wof:placetype":"venue"
},
  "geometry": {"coordinates":[-92.829425,37.306543],"type":"Point"}
}