{
  "type": "Feature",
  "properties": {
    "iso:country":"US",
    "sg:address":"402 Hawthorne St",
    "sg:city":"Smithville",
    "sg:classifiers":[
        {
            "category":"Retail",
            "subcategory":"Portrait Studio",
            "type":"Services"
        }
    ],
    "sg:phone":"+1 816 532 1020",
    "sg:postcode":"64089",
    "sg:province":"MO",
    "sg:tags":[
        "photo"
    ],
    "wof:name":"Wright Choice",
    "wof:placetype":"venue"
},
  "geometry": {"coordinates":[-94.579251,39.39265],"type":"Point"}
}