{
  "type": "Feature",
  "properties": {
    "iso:country":"US",
    "sg:address":"1218 E Elm St",
    "sg:city":"Jefferson City",
    "sg:classifiers":[
        {
            "category":"Social Services",
            "subcategory":"Child Care",
            "type":"Services"
        }
    ],
    "sg:phone":"+1 573 634 4034",
    "sg:postcode":"65101",
    "sg:province":"MO",
    "sg:tags":[
        "day"
    ],
    "wof:name":"Raithels Day Care",
    "wof:placetype":"venue"
},
  "geometry": {"coordinates":[-92.160962,38.563052],"type":"Point"}
}