{
  "type": "Feature",
  "properties": {
    "iso:country":"US",
    "sg:address":"Tower Grove East",
    "sg:city":"Saint Louis",
    "sg:classifiers":[
        {
            "category":"Education",
            "subcategory":"Special Training",
            "type":"Public Place"
        }
    ],
    "sg:phone":"+1 314 954 7913",
    "sg:postcode":"63118",
    "sg:province":"MO",
    "sg:tags":[
        "tutor",
        "tutoring",
        "private"
    ],
    "sg:website":"GatewayTestPrep.com",
    "wof:name":"Gateway LSAT",
    "wof:placetype":"venue"
},
  "geometry": {"coordinates":[-90.237066,38.602958],"type":"Point"}
}