{
  "type": "Feature",
  "properties": {
    "iso:country":"US",
    "sg:address":"3401 E Ridgeview St",
    "sg:city":"Springfield",
    "sg:classifiers":[
        {
            "category":"Food & Beverages",
            "subcategory":"Groceries & Convenience Stores",
            "type":"Retail Goods"
        }
    ],
    "sg:phone":"+1 417 891 2702",
    "sg:postcode":"65804",
    "sg:province":"MO",
    "sg:website":"http://www.pfiwestern.com",
    "wof:name":"Diamond Ridge Market",
    "wof:placetype":"venue"
},
  "geometry": {"coordinates":[-93.227842,37.159296],"type":"Point"}
}