{
  "type": "Feature",
  "properties": {
    "iso:country":"US",
    "sg:address":"2107 Lucas Ave",
    "sg:city":"Saint Louis",
    "sg:classifiers":[
        {
            "category":"Wholesale",
            "subcategory":"Office Equipment",
            "type":"Manufacturing & Wholesale Goods"
        }
    ],
    "sg:phone":"+1 314 849 5392",
    "sg:postcode":"63103",
    "sg:province":"MO",
    "wof:name":"Postmarq Inc",
    "wof:placetype":"venue"
},
  "geometry": {"coordinates":[-90.210373,38.635251],"type":"Point"}
}