{
  "type": "Feature",
  "properties": {
    "iso:country":"US",
    "sg:address":"3470 Hampton Ave Ste 102",
    "sg:city":"Saint Louis",
    "sg:classifiers":[
        {
            "category":"Health Services",
            "subcategory":"Chiropractor",
            "type":"Services"
        }
    ],
    "sg:phone":"+1 314 352 6608",
    "sg:postcode":"63139",
    "sg:province":"MO",
    "wof:name":"Ganley Mary P DC",
    "wof:placetype":"venue"
},
  "geometry": {"coordinates":[-90.292503,38.598598],"type":"Point"}
}