{
  "type": "Feature",
  "properties": {
    "iso:country":"US",
    "sg:address":"613 NE Woods Chapel Rd",
    "sg:city":"Lees Summit",
    "sg:classifiers":[
        {
            "category":"Insurance",
            "subcategory":"Insurance Agent",
            "type":"Services"
        }
    ],
    "sg:phone":"+1 816 524 9933",
    "sg:postcode":"64064",
    "sg:province":"MO",
    "wof:name":"American Family Insurance",
    "wof:placetype":"venue"
},
  "geometry": {"coordinates":[-94.367136,38.982709],"type":"Point"}
}