{
  "type": "Feature",
  "properties": {
    "iso:country":"US",
    "sg:address":"116 May Rd Ste C",
    "sg:city":"Wentzville",
    "sg:classifiers":[
        {
            "category":"Fast Food",
            "type":"Food & Drink"
        },
        {
            "category":"Restaurant",
            "type":"Food & Drink"
        }
    ],
    "sg:phone":"+1 636 332 0448",
    "sg:postcode":"63385",
    "sg:province":"MO",
    "sg:tags":[
        "mexican",
        "take"
    ],
    "sg:website":"http://www.genxmex.com",
    "wof:name":"Gen X Mex",
    "wof:placetype":"venue"
},
  "geometry": {"coordinates":[-90.882957,38.81076],"type":"Point"}
}