{
  "type": "Feature",
  "properties": {
    "iso:country":"US",
    "sg:address":"6520 Sagamore Rd",
    "sg:city":"Mission Hills",
    "sg:classifiers":[
        {
            "category":"Manufacturing",
            "subcategory":"Paper Products",
            "type":"Manufacturing & Wholesale Goods"
        }
    ],
    "sg:phone":"+1 913 236 4437",
    "sg:postcode":"66208",
    "sg:province":"MO",
    "wof:name":"Ga Pacific Corp",
    "wof:placetype":"venue"
},
  "geometry": {"coordinates":[-94.610231,39.008535],"type":"Point"}
}