{
  "type": "Feature",
  "properties": {
    "iso:country":"US",
    "sg:address":"644 Emge Rd",
    "sg:city":"O Fallon",
    "sg:classifiers":[
        {
            "category":"Building & Trades",
            "subcategory":"Construction",
            "type":"Services"
        }
    ],
    "sg:phone":"+1 636 978 7706",
    "sg:postcode":"63366",
    "sg:province":"MO",
    "sg:tags":[
        "house"
    ],
    "wof:name":"Total Home Remodeling",
    "wof:placetype":"venue"
},
  "geometry": {"coordinates":[-90.71410299999999,38.814863],"type":"Point"}
}