{
  "type": "Feature",
  "properties": {
    "iso:country":"US",
    "sg:address":"113 S Gex St",
    "sg:city":"La Plata",
    "sg:classifiers":[
        {
            "category":"Shopping",
            "subcategory":"Pharmacy",
            "type":"Retail Goods"
        }
    ],
    "sg:phone":"+1 660 332 4456",
    "sg:postcode":"63549",
    "sg:province":"MO",
    "wof:name":"LA Plata Pharmacy",
    "wof:placetype":"venue"
},
  "geometry": {"coordinates":[-92.491641,40.023257],"type":"Point"}
}