{
  "type": "Feature",
  "properties": {
    "iso:country":"US",
    "sg:address":"1200 NE 81st Ter",
    "sg:city":"Kansas City",
    "sg:classifiers":[
        {
            "category":"Organizations",
            "subcategory":"Religious Organization",
            "type":"Services"
        }
    ],
    "sg:phone":"+1 816 468 9691",
    "sg:postcode":"64118",
    "sg:province":"MO",
    "sg:tags":[
        "personal"
    ],
    "wof:name":"Evangelical Community Church",
    "wof:placetype":"venue"
},
  "geometry": {"coordinates":[-94.564364,39.241018],"type":"Point"}
}