{
  "type": "Feature",
  "properties": {
    "iso:country":"US",
    "sg:address":"12093 Co Rd 8030",
    "sg:city":"Rolla",
    "sg:classifiers":[
        {
            "category":"Retail",
            "subcategory":"Auto Repair",
            "type":"Services"
        }
    ],
    "sg:phone":"+1 573 364 2700",
    "sg:postcode":"65401",
    "sg:province":"MO",
    "sg:tags":[
        "repairing",
        "automobile",
        "general"
    ],
    "wof:name":"Old Folks Home",
    "wof:placetype":"venue"
},
  "geometry": {"coordinates":[-91.770893,37.971107],"type":"Point"}
}