{
  "type": "Feature",
  "properties": {
    "iso:country":"US",
    "sg:address":"2701 Southeast Trl",
    "sg:city":"Saint Joseph",
    "sg:classifiers":[
        {
            "category":"Farming",
            "subcategory":"Farm",
            "type":"Manufacturing & Wholesale Goods"
        }
    ],
    "sg:phone":"+1 816 233 6476",
    "sg:postcode":"64506",
    "sg:province":"MO",
    "sg:tags":[
        "crop",
        "general"
    ],
    "wof:name":"Fredrick Hannah",
    "wof:placetype":"venue"
},
  "geometry": {"coordinates":[-94.82674799999999,39.792277],"type":"Point"}
}