{
  "type": "Feature",
  "properties": {
    "iso:country":"US",
    "sg:address":"1885 N Bluff St",
    "sg:city":"Fulton",
    "sg:classifiers":[
        {
            "category":"Recreation",
            "type":"Entertainment"
        },
        {
            "category":"Sports & Exercise",
            "subcategory":"Gym",
            "type":"Entertainment"
        }
    ],
    "sg:phone":"+1 573 642 8999",
    "sg:postcode":"65251",
    "sg:province":"MO",
    "sg:tags":[
        "arts",
        "facility",
        "instruction",
        "martial",
        "fitness",
        "physical"
    ],
    "wof:name":"A T A Blackbelt Academy",
    "wof:placetype":"venue"
},
  "geometry": {"coordinates":[-91.94395,38.864525],"type":"Point"}
}