{
  "type": "Feature",
  "properties": {
    "iso:country":"US",
    "sg:address":"412 S Davis St",
    "sg:city":"Hamilton",
    "sg:classifiers":[
        {
            "category":"Manufacturing",
            "subcategory":"Printing",
            "type":"Manufacturing & Wholesale Goods"
        }
    ],
    "sg:phone":"+1 816 583 2116",
    "sg:postcode":"64644",
    "sg:province":"MO",
    "sg:tags":[
        "newspaper",
        "publishers-periodical"
    ],
    "sg:website":"http://www.caldwell-countynews.com",
    "wof:name":"L & L Publications Inc",
    "wof:placetype":"venue"
},
  "geometry": {"coordinates":[-93.998115,39.739596],"type":"Point"}
}