{
  "type": "Feature",
  "properties": {
    "iso:country":"US",
    "sg:address":"314 Forest Parkway Dr",
    "sg:city":"Ballwin",
    "sg:classifiers":[
        {
            "category":"Professional",
            "subcategory":"Computer Services",
            "type":"Services"
        }
    ],
    "sg:phone":"+1 636 227 1120",
    "sg:postcode":"63021",
    "sg:province":"MO",
    "sg:tags":[
        "design",
        "datum",
        "system"
    ],
    "wof:name":"Volt Delta Resources Inc",
    "wof:placetype":"venue"
},
  "geometry": {"coordinates":[-90.501077,38.586451],"type":"Point"}
}