{
  "type": "Feature",
  "properties": {
    "iso:country":"US",
    "sg:address":"14472 Hwy Aw",
    "sg:city":"Plato",
    "sg:phone":"+1 417 458 4487",
    "sg:postcode":"65552",
    "sg:province":"MO",
    "sg:tags":[
        "beef",
        "farm",
        "crop",
        "field",
        "cattle",
        "feedlot"
    ],
    "wof:name":"Russell Friend",
    "wof:placetype":"venue"
},
  "geometry": {"coordinates":[-92.14033999999999,37.578553],"type":"Point"}
}