{
  "type": "Feature",
  "properties": {
    "iso:country":"US",
    "sg:address":"14352 S Outer 40",
    "sg:city":"Chesterfield",
    "sg:classifiers":[
        {
            "category":"Banks & Credit Unions",
            "subcategory":"Bank",
            "type":"Services"
        }
    ],
    "sg:phone":"+1 314 275 2244",
    "sg:postcode":"63017",
    "sg:province":"MO",
    "sg:tags":[
        "mortgage"
    ],
    "wof:name":"James B Nutter & Company",
    "wof:placetype":"venue"
},
  "geometry": {"coordinates":[-90.526321,38.645618],"type":"Point"}
}