{
  "type": "Feature",
  "properties": {
    "iso:country":"US",
    "sg:address":"105 NW Noel St",
    "sg:city":"Lees Summit",
    "sg:classifiers":[
        {
            "category":"Real Estate",
            "subcategory":"Real Estate Agent",
            "type":"Services"
        }
    ],
    "sg:phone":"+1 816 517 2433",
    "sg:postcode":"64063",
    "sg:province":"MO",
    "wof:name":"Appraisal Midwest",
    "wof:placetype":"venue"
},
  "geometry": {"coordinates":[-94.387125,38.916631],"type":"Point"}
}