{
  "type": "Feature",
  "properties": {
    "iso:country":"US",
    "sg:address":"1103 Kingshighway",
    "sg:city":"Rolla",
    "sg:classifiers":[
        {
            "category":"Education",
            "subcategory":"College",
            "type":"Public Place"
        }
    ],
    "sg:phone":"+1 573 368 4569",
    "sg:postcode":"65401",
    "sg:province":"MO",
    "sg:tags":[
        "academic",
        "school"
    ],
    "wof:name":"Webster University Graduate",
    "wof:placetype":"venue"
},
  "geometry": {"coordinates":[-91.784943,37.944365],"type":"Point"}
}