{
  "type": "Feature",
  "properties": {
    "iso:country":"US",
    "sg:address":"1331 W Main St",
    "sg:city":"Union",
    "sg:classifiers":[
        {
            "category":"Professional",
            "subcategory":"Management & Consulting",
            "type":"Services"
        }
    ],
    "sg:phone":"+1 636 583 6169",
    "sg:postcode":"63084",
    "sg:province":"MO",
    "sg:tags":[
        "business"
    ],
    "wof:name":"Jedrey Consulting",
    "wof:placetype":"venue"
},
  "geometry": {"coordinates":[-91.033216,38.445241],"type":"Point"}
}