{
  "type": "Feature",
  "properties": {
    "iso:country":"US",
    "sg:address":"174 Shepley Dr",
    "sg:city":"St Louis",
    "sg:classifiers":[
        {
            "category":"Education",
            "subcategory":"School",
            "type":"Public Place"
        }
    ],
    "sg:phone":"+1 314 868 4561",
    "sg:postcode":"63137",
    "sg:province":"MO",
    "wof:name":"Highland School",
    "wof:placetype":"venue"
},
  "geometry": {"coordinates":[-90.197945,38.755636],"type":"Point"}
}