{
  "type": "Feature",
  "properties": {
    "iso:country":"US",
    "sg:address":"3442 W US Hwy 160",
    "sg:city":"West Plains",
    "sg:classifiers":[
        {
            "category":"Wholesale",
            "subcategory":"Machinery & Supplies",
            "type":"Manufacturing & Wholesale Goods"
        },
        {
            "category":"Manufacturing",
            "subcategory":"Motor Vehicles & Parts",
            "type":"Manufacturing & Wholesale Goods"
        }
    ],
    "sg:phone":"+1 417 256 6658",
    "sg:postcode":"65775",
    "sg:province":"MO",
    "sg:tags":[
        "equipment",
        "transportation",
        "trailer",
        "mfg"
    ],
    "wof:name":"Southern Missouri Trailer Svc",
    "wof:placetype":"venue"
},
  "geometry": {"coordinates":[-91.956233,36.629995],"type":"Point"}
}