{
  "type": "Feature",
  "properties": {
    "iso:country":"US",
    "sg:address":"114 W 47th St",
    "sg:city":"Kansas City",
    "sg:classifiers":[
        {
            "category":"Ice Cream",
            "type":"Food & Drink"
        }
    ],
    "sg:menulink":"http://www.allmenus.com/mo/kaw/184049-cold-stone-creamery/menu/",
    "sg:phone":"+1 816 531 8200",
    "sg:postcode":"64112",
    "sg:province":"MO",
    "sg:tags":[
        "smoothy",
        "juice",
        "american"
    ],
    "wof:name":"Cold Stone Creamery",
    "wof:placetype":"venue"
},
  "geometry": {"coordinates":[-94.589005,39.042282],"type":"Point"}
}