{
  "type": "Feature",
  "properties": {
    "iso:country":"US",
    "sg:address":"17225 Co Rd 7320",
    "sg:city":"Newburg",
    "sg:classifiers":[
        {
            "category":"Manufacturing",
            "subcategory":"Buildings",
            "type":"Manufacturing & Wholesale Goods"
        }
    ],
    "sg:phone":"+1 573 762 3391",
    "sg:postcode":"65550",
    "sg:province":"MO",
    "sg:tags":[
        "home",
        "log",
        "cabin"
    ],
    "sg:website":"www.oaklogs.com",
    "wof:name":"D L & C Co",
    "wof:placetype":"venue"
},
  "geometry": {"coordinates":[-91.88421,37.922979],"type":"Point"}
}