{
  "type": "Feature",
  "properties": {
    "iso:country":"US",
    "sg:address":"777 Willow Creek Dr",
    "sg:city":"Fenton",
    "sg:classifiers":[
        {
            "category":"Home & Garden",
            "subcategory":"Hardware",
            "type":"Retail Goods"
        }
    ],
    "sg:phone":"+1 636 343 9098",
    "sg:postcode":"63026",
    "sg:province":"MO",
    "wof:name":"Dreams Come True",
    "wof:placetype":"venue"
},
  "geometry": {"coordinates":[-90.45851399999999,38.491295],"type":"Point"}
}