{
  "type": "Feature",
  "properties": {
    "iso:country":"US",
    "sg:address":"5012 Royal Burgess Dr",
    "sg:city":"Saint Charles",
    "sg:classifiers":[
        {
            "category":"Manufacturing",
            "subcategory":"Signs",
            "type":"Manufacturing & Wholesale Goods"
        }
    ],
    "sg:phone":"+1 636 928 7386",
    "sg:postcode":"63304",
    "sg:province":"MO",
    "sg:tags":[
        "specialty",
        "mfg"
    ],
    "wof:name":"Kelly Signs",
    "wof:placetype":"venue"
},
  "geometry": {"coordinates":[-90.629938,38.725996],"type":"Point"}
}