{
  "type": "Feature",
  "properties": {
    "iso:country":"US",
    "sg:address":"7100 Eastwood Trfy",
    "sg:city":"Kansas City",
    "sg:classifiers":[
        {
            "category":"Banks & Credit Unions",
            "subcategory":"Investment Brokerage",
            "type":"Services"
        }
    ],
    "sg:phone":"+1 816 923 5967",
    "sg:postcode":"64129",
    "sg:province":"MO",
    "sg:tags":[
        "advisory",
        "financial"
    ],
    "wof:name":"Mister Money Financial Svc",
    "wof:placetype":"venue"
},
  "geometry": {"coordinates":[-94.501966,39.031151],"type":"Point"}
}