{
  "type": "Feature",
  "properties": {
    "iso:country":"US",
    "sg:address":"139 Irish Ln",
    "sg:city":"Branson",
    "sg:classifiers":[
        {
            "category":"Personal",
            "type":"Services"
        },
        {
            "category":"Retail",
            "subcategory":"Auto Rental",
            "type":"Services"
        },
        {
            "category":"Building & Trades",
            "subcategory":"Equipment Rental",
            "type":"Services"
        },
        {
            "category":"Retail",
            "subcategory":"Storage",
            "type":"Services"
        }
    ],
    "sg:phone":"+1 417 335 4868",
    "sg:postcode":"65616",
    "sg:province":"MO",
    "sg:tags":[
        "renting",
        "moving-self",
        "leasing",
        "car",
        "truck",
        "mover",
        "trailer",
        "contractors'"
    ],
    "sg:website":"http://www.uhaul.com",
    "wof:name":"U-Haul Co",
    "wof:placetype":"venue"
},
  "geometry": {"coordinates":[-93.294864,36.604174],"type":"Point"}
}