{
  "type": "Feature",
  "properties": {
    "iso:country":"US",
    "sg:address":"17517 US Hwy 24",
    "sg:city":"Independence",
    "sg:classifiers":[
        {
            "category":"Personal",
            "subcategory":"Tanning Parlor",
            "type":"Services"
        }
    ],
    "sg:phone":"+1 816 796 7778",
    "sg:postcode":"64056",
    "sg:province":"MO",
    "sg:tags":[
        "salon"
    ],
    "wof:name":"Tan-Talizer",
    "wof:placetype":"venue"
},
  "geometry": {"coordinates":[-94.370983,39.120432],"type":"Point"}
}