{
  "type": "Feature",
  "properties": {
    "iso:country":"US",
    "sg:address":"425 S Union Ave",
    "sg:city":"Springfield",
    "sg:classifiers":[
        {
            "category":"Professional",
            "subcategory":"Research",
            "type":"Services"
        }
    ],
    "sg:phone":"+1 417 831 2533",
    "sg:postcode":"65802",
    "sg:province":"MO",
    "sg:tags":[
        "organization",
        "noncommercial"
    ],
    "wof:name":"M D A",
    "wof:placetype":"venue"
},
  "geometry": {"coordinates":[-93.233459,37.208265],"type":"Point"}
}