{
  "type": "Feature",
  "properties": {
    "iso:country":"US",
    "sg:address":"300 N Connecticut St",
    "sg:city":"King City",
    "sg:classifiers":[
        {
            "category":"Insurance",
            "subcategory":"Insurance Agent",
            "type":"Services"
        }
    ],
    "sg:phone":"+1 660 535 4391",
    "sg:postcode":"64463",
    "sg:province":"MO",
    "wof:name":"Lewis Agency",
    "wof:placetype":"venue"
},
  "geometry": {"coordinates":[-94.52373,40.054637],"type":"Point"}
}