{
  "type": "Feature",
  "properties": {
    "iso:country":"US",
    "sg:address":"204 W Linwood Blvd",
    "sg:city":"Kansas City",
    "sg:classifiers":[
        {
            "category":"Building & Trades",
            "subcategory":"Construction",
            "type":"Services"
        }
    ],
    "sg:phone":"+1 816 931 1080",
    "sg:postcode":"64111",
    "sg:province":"MO",
    "sg:tags":[
        "contractor",
        "help",
        "supply"
    ],
    "wof:name":"Terra 2 Inc",
    "wof:placetype":"venue"
},
  "geometry": {"coordinates":[-94.58889499999999,39.06765],"type":"Point"}
}