{
  "type": "Feature",
  "properties": {
    "iso:country":"US",
    "sg:address":"1015 Clark Dr",
    "sg:city":"Fenton",
    "sg:classifiers":[
        {
            "category":"Personal",
            "subcategory":"Beauty Salon",
            "type":"Services"
        }
    ],
    "sg:phone":"+1 636 343 4861",
    "sg:postcode":"63026",
    "sg:province":"MO",
    "sg:tags":[
        "shop"
    ],
    "wof:name":"T G's Beauty Salon",
    "wof:placetype":"venue"
},
  "geometry": {"coordinates":[-90.470794,38.494891],"type":"Point"}
}