{
  "type": "Feature",
  "properties": {
    "addr:full":"6614 Clayton Rd 167 St Louis MO 63117",
    "addr:housenumber":"6614",
    "addr:postcode":"63117",
    "addr:street":"Clayton Rd 167",
    "iso:country":"US",
    "sg:address":"6614 Clayton Rd 167",
    "sg:city":"St Louis",
    "sg:classifiers":[
        {
            "category":"Building & Trades",
            "subcategory":"Plumbing",
            "type":"Services"
        }
    ],
    "sg:phone":"+1 314 822 5290",
    "sg:postcode":"63117",
    "sg:province":"MO",
    "sg:website":"richmondheightsmo.rotorooter.com",
    "wof:name":"Roto-Rooter Plumbing & Drain Services",
    "wof:placetype":"venue"
},
  "geometry": {"coordinates":[-90.315535,38.634506],"type":"Point"}
}