{
  "type": "Feature",
  "properties": {
    "iso:country":"US",
    "sg:address":"101 N Range Line Rd",
    "sg:city":"Joplin",
    "sg:classifiers":[
        {
            "category":"Health Services",
            "subcategory":"Medical Lab",
            "type":"Services"
        }
    ],
    "sg:phone":"+1 417 621 4832",
    "sg:postcode":"64801",
    "sg:province":"MO",
    "sg:tags":[
        "laboratory"
    ],
    "wof:name":"St John's Quicklab",
    "wof:placetype":"venue"
},
  "geometry": {"coordinates":[-94.47687500000001,37.093661],"type":"Point"}
}