{
  "type": "Feature",
  "properties": {
    "iso:country":"US",
    "sg:address":"15496 Pike 322",
    "sg:city":"Bowling Green",
    "sg:phone":"+1 573 324 3590",
    "sg:postcode":"63334",
    "sg:province":"MO",
    "sg:tags":[
        "farm",
        "corn",
        "beef",
        "feedlot",
        "cattle"
    ],
    "wof:name":"Paul Merz",
    "wof:placetype":"venue"
},
  "geometry": {"coordinates":[-91.19188200000001,39.220393],"type":"Point"}
}