{
  "type": "Feature",
  "properties": {
    "iso:country":"US",
    "sg:address":"1037 Madison 9213",
    "sg:city":"Fredericktown",
    "sg:classifiers":[
        {
            "category":"Farming",
            "subcategory":"Livestock Farm",
            "type":"Manufacturing & Wholesale Goods"
        }
    ],
    "sg:phone":"+1 573 783 2878",
    "sg:postcode":"63645",
    "sg:province":"MO",
    "sg:tags":[
        "hog",
        "or",
        "feedlot"
    ],
    "wof:name":"Allgier Farms Inc",
    "wof:placetype":"venue"
},
  "geometry": {"coordinates":[-90.289776,37.588864],"type":"Point"}
}