{
  "type": "Feature",
  "properties": {
    "iso:country":"US",
    "sg:address":"501 US Hwy 60 Bus",
    "sg:city":"Dexter",
    "sg:classifiers":[
        {
            "category":"Local Transit",
            "type":"Transportation"
        }
    ],
    "sg:phone":"+1 573 624 4528",
    "sg:postcode":"63841",
    "sg:province":"MO",
    "sg:tags":[
        "ambulance"
    ],
    "wof:name":"Stoddard County Ambulance",
    "wof:placetype":"venue"
},
  "geometry": {"coordinates":[-89.965541,36.800153],"type":"Point"}
}