{
  "type": "Feature",
  "properties": {
    "iso:country":"US",
    "sg:address":"1225 Ozark St",
    "sg:city":"Kansas City",
    "sg:classifiers":[
        {
            "category":"Manufacturing",
            "subcategory":"Chemicals & Compounds",
            "type":"Manufacturing & Wholesale Goods"
        }
    ],
    "sg:phone":"+1 816 471 1788",
    "sg:postcode":"64116",
    "sg:province":"MO",
    "sg:tags":[
        "adhesive",
        "sealant"
    ],
    "sg:website":"www.wel-cote.com",
    "wof:name":"Welco Manufacturing Co",
    "wof:placetype":"venue"
},
  "geometry": {"coordinates":[-94.564581,39.132429],"type":"Point"}
}