{
  "type": "Feature",
  "properties": {
    "iso:country":"US",
    "sg:address":"3063 W Scott St",
    "sg:city":"Springfield",
    "sg:classifiers":[
        {
            "category":"Professional",
            "type":"Services"
        }
    ],
    "sg:phone":"+1 417 865 9225",
    "sg:postcode":"65803",
    "sg:province":"MO",
    "wof:name":"Weedwackers",
    "wof:placetype":"venue"
},
  "geometry": {"coordinates":[-93.339001,37.220492],"type":"Point"}
}