{
  "type": "Feature",
  "properties": {
    "iso:country":"US",
    "sg:address":"720 Olive St",
    "sg:city":"St Louis",
    "sg:classifiers":[
        {
            "category":"Arts & Performance",
            "subcategory":"Theater",
            "type":"Entertainment"
        }
    ],
    "sg:phone":"+1 314 231 9797",
    "sg:postcode":"63101",
    "sg:province":"MO",
    "sg:tags":[
        "television",
        "station",
        "representative"
    ],
    "wof:name":"Harrington Righter & Parsons",
    "wof:placetype":"venue"
},
  "geometry": {"coordinates":[-90.191316,38.62826],"type":"Point"}
}