{
  "type": "Feature",
  "properties": {
    "iso:country":"US",
    "sg:address":"1265 Orchard Village Ln",
    "sg:city":"Ballwin",
    "sg:classifiers":[
        {
            "category":"Health Services",
            "subcategory":"Clinic",
            "type":"Services"
        }
    ],
    "sg:phone":"+1 636 391 7002",
    "sg:postcode":"63021",
    "sg:province":"MO",
    "wof:name":"N&R Medical Systems Inc",
    "wof:placetype":"venue"
},
  "geometry": {"coordinates":[-90.497783,38.590903],"type":"Point"}
}