{
  "type": "Feature",
  "properties": {
    "iso:country":"US",
    "sg:address":"625 Kimbar Estates Dr",
    "sg:city":"New Haven",
    "sg:classifiers":[
        {
            "category":"Farming",
            "subcategory":"Livestock Farm",
            "type":"Manufacturing & Wholesale Goods"
        }
    ],
    "sg:phone":"+1 573 237 3708",
    "sg:postcode":"63068",
    "sg:province":"MO",
    "sg:tags":[
        "hog",
        "or",
        "feedlot"
    ],
    "wof:name":"Michael Trachsel",
    "wof:placetype":"venue"
},
  "geometry": {"coordinates":[-91.23721,38.599239],"type":"Point"}
}