{
  "type": "Feature",
  "properties": {
    "iso:country":"US",
    "sg:address":"9709 Hwy 50 W",
    "sg:city":"Centertown",
    "sg:classifiers":[
        {
            "category":"Professional",
            "type":"Services"
        }
    ],
    "sg:phone":"+1 573 584 9485",
    "sg:postcode":"65023",
    "sg:province":"MO",
    "sg:tags":[
        "hearing",
        "reporter"
    ],
    "wof:name":"Diana Tankersley",
    "wof:placetype":"venue"
},
  "geometry": {"coordinates":[-92.372415,38.611311],"type":"Point"}
}