{
  "type": "Feature",
  "properties": {
    "iso:country":"US",
    "sg:address":"1926 Union Blvd",
    "sg:city":"Saint Louis",
    "sg:classifiers":[
        {
            "category":"Retail",
            "subcategory":"Laundry & Dry Cleaning",
            "type":"Services"
        }
    ],
    "sg:phone":"+1 314 454 0607",
    "sg:postcode":"63113",
    "sg:province":"MO",
    "sg:tags":[
        "cleaner",
        "plant",
        "drycleaning"
    ],
    "wof:name":"Brook's 45 Minute Cleaners",
    "wof:placetype":"venue"
},
  "geometry": {"coordinates":[-90.26570100000001,38.6684],"type":"Point"}
}