{
  "type": "Feature",
  "properties": {
    "iso:country":"US",
    "sg:address":"7534 Manchester Rd",
    "sg:city":"Saint Louis",
    "sg:classifiers":[
        {
            "category":"Shopping",
            "subcategory":"Bicycles & Sporting Goods",
            "type":"Retail Goods"
        }
    ],
    "sg:phone":"+1 314 781 9566",
    "sg:postcode":"63143",
    "sg:province":"MO",
    "sg:tags":[
        "bike"
    ],
    "sg:website":"www.maplewoodbicycle.com/",
    "wof:name":"Maplewood Bicycle",
    "wof:placetype":"venue"
},
  "geometry": {"coordinates":[-90.32559999999999,38.6129],"type":"Point"}
}