{
  "type": "Feature",
  "properties": {
    "iso:country":"US",
    "sg:address":"1710 Commercial St",
    "sg:city":"St Joseph",
    "sg:classifiers":[
        {
            "category":"Building & Trades",
            "subcategory":"Electrical",
            "type":"Services"
        }
    ],
    "sg:phone":"+1 816 364 3610",
    "sg:postcode":"64503",
    "sg:province":"MO",
    "sg:tags":[
        "electric",
        "contractor"
    ],
    "wof:name":"South Park Electric",
    "wof:placetype":"venue"
},
  "geometry": {"coordinates":[-94.840756,39.7382],"type":"Point"}
}