{
  "type": "Feature",
  "properties": {
    "iso:country":"US",
    "sg:address":"914 Witter St",
    "sg:city":"Jefferson City",
    "sg:classifiers":[
        {
            "category":"Building & Trades",
            "subcategory":"Construction",
            "type":"Services"
        }
    ],
    "sg:phone":"+1 573 634 2543",
    "sg:postcode":"65101",
    "sg:province":"MO",
    "sg:tags":[
        "contractor"
    ],
    "wof:name":"Feltrop Drywall",
    "wof:placetype":"venue"
},
  "geometry": {"coordinates":[-92.16377199999999,38.558936],"type":"Point"}
}