{
  "type": "Feature",
  "properties": {
    "iso:country":"US",
    "sg:address":"1704 W Linda Ln",
    "sg:city":"Robertsville",
    "sg:classifiers":[
        {
            "category":"Building & Trades",
            "subcategory":"Construction",
            "type":"Services"
        }
    ],
    "sg:phone":"+1 636 629 6095",
    "sg:postcode":"63072",
    "sg:province":"MO",
    "sg:tags":[
        "roofing",
        "industrial",
        "contractors-commercial",
        "contractor"
    ],
    "wof:name":"Commercial Roofing Solutions L",
    "wof:placetype":"venue"
},
  "geometry": {"coordinates":[-90.83394,38.323969],"type":"Point"}
}