{
  "type": "Feature",
  "properties": {
    "iso:country":"US",
    "sg:address":"3324 Tepee Ct",
    "sg:city":"Independence",
    "sg:classifiers":[
        {
            "category":"Building & Trades",
            "subcategory":"Construction",
            "type":"Services"
        }
    ],
    "sg:phone":"+1 816 795 8772",
    "sg:postcode":"64057",
    "sg:province":"MO",
    "sg:tags":[
        "heavy"
    ],
    "wof:name":"Pollard & Assoc",
    "wof:placetype":"venue"
},
  "geometry": {"coordinates":[-94.35554999999999,39.060368],"type":"Point"}
}