{
  "type": "Feature",
  "properties": {
    "iso:country":"US",
    "sg:address":"6251 W Farm Rd 18",
    "sg:city":"Willard",
    "sg:classifiers":[
        {
            "category":"Building & Trades",
            "subcategory":"Pest Control",
            "type":"Services"
        }
    ],
    "sg:phone":"+1 417 742 2726",
    "sg:postcode":"65781",
    "sg:province":"MO",
    "wof:name":"Country Pest Control",
    "wof:placetype":"venue"
},
  "geometry": {"coordinates":[-93.404554,37.400849],"type":"Point"}
}