{
  "type": "Feature",
  "properties": {
    "iso:country":"US",
    "sg:address":"3604 Pershall Rd",
    "sg:city":"Ferguson",
    "sg:classifiers":[
        {
            "category":"Real Estate",
            "subcategory":"Real Estate Operator",
            "type":"Services"
        }
    ],
    "sg:phone":"+1 314 521 2232",
    "sg:postcode":"63135",
    "sg:province":"MO",
    "sg:tags":[
        "building",
        "apartment",
        "apt"
    ],
    "wof:name":"Knolls Townhomes",
    "wof:placetype":"venue"
},
  "geometry": {"coordinates":[-90.29499199999999,38.771234],"type":"Point"}
}