{
  "type": "Feature",
  "properties": {
    "iso:country":"US",
    "sg:address":"500 E Harrison St",
    "sg:city":"Republic",
    "sg:classifiers":[
        {
            "category":"Shopping",
            "type":"Retail Goods"
        }
    ],
    "sg:phone":"+1 573 465 2733",
    "sg:postcode":"65738",
    "sg:province":"MO",
    "sg:tags":[
        "merchandise"
    ],
    "wof:name":"Agape Thrift Store",
    "wof:placetype":"venue"
},
  "geometry": {"coordinates":[-93.473637,37.119807],"type":"Point"}
}