{
  "type": "Feature",
  "properties": {
    "iso:country":"US",
    "sg:address":"500 NW Peace Pkwy",
    "sg:city":"Raymore",
    "sg:classifiers":[
        {
            "category":"Organizations",
            "subcategory":"Religious Organization",
            "type":"Services"
        }
    ],
    "sg:phone":"+1 816 322 0561",
    "sg:postcode":"64081",
    "sg:province":"MO",
    "sg:tags":[
        "church"
    ],
    "sg:website":"www.raymorecc.org",
    "wof:name":"Raymore Christian Church",
    "wof:placetype":"venue"
},
  "geometry": {"coordinates":[-94.406716,38.922674],"type":"Point"}
}