{
  "type": "Feature",
  "properties": {
    "iso:country":"US",
    "sg:address":"202 Scott Wayne Dr",
    "sg:city":"Nixa",
    "sg:classifiers":[
        {
            "category":"Retail",
            "subcategory":"Laundry & Dry Cleaning",
            "type":"Services"
        }
    ],
    "sg:phone":"+1 417 725 1109",
    "sg:postcode":"65714",
    "sg:province":"MO",
    "sg:tags":[
        "cleaners",
        "rug",
        "carpet"
    ],
    "wof:name":"Levite Carpet Care",
    "wof:placetype":"venue"
},
  "geometry": {"coordinates":[-93.290921,37.058432],"type":"Point"}
}