{
  "type": "Feature",
  "properties": {
    "iso:country":"US",
    "sg:address":"120 S Main St",
    "sg:city":"Clinton",
    "sg:classifiers":[
        {
            "category":"Shopping",
            "subcategory":"Clothing, Apparel, & Fashions",
            "type":"Retail Goods"
        }
    ],
    "sg:phone":"+1 660 885 8002",
    "sg:postcode":"64735",
    "sg:province":"MO",
    "wof:name":"Eberting's Apparel",
    "wof:placetype":"venue"
},
  "geometry": {"coordinates":[-93.776071,38.370464],"type":"Point"}
}