{
  "type": "Feature",
  "properties": {
    "iso:country":"US",
    "sg:address":"4315 N Penny Ct",
    "sg:city":"Ozark",
    "sg:classifiers":[
        {
            "category":"Shopping",
            "subcategory":"Party Supplies",
            "type":"Retail Goods"
        }
    ],
    "sg:phone":"+1 417 582 1909",
    "sg:postcode":"65721",
    "sg:province":"MO",
    "sg:tags":[
        "tents-rental"
    ],
    "wof:name":"Rent A Tent",
    "wof:placetype":"venue"
},
  "geometry": {"coordinates":[-93.21311300000001,37.059017],"type":"Point"}
}