{
  "type": "Feature",
  "properties": {
    "iso:country":"US",
    "sg:address":"809 Elmont Rd",
    "sg:city":"Sullivan",
    "sg:classifiers":[
        {
            "category":"Professional",
            "type":"Services"
        }
    ],
    "sg:phone":"+1 573 860 5366",
    "sg:postcode":"63080",
    "sg:province":"MO",
    "sg:tags":[
        "establishment"
    ],
    "wof:name":"Esthetic Concepts",
    "wof:placetype":"venue"
},
  "geometry": {"coordinates":[-91.17800800000001,38.208087],"type":"Point"}
}