{
  "type": "Feature",
  "properties": {
    "iso:country":"US",
    "sg:address":"16611 Spring Valley Rd",
    "sg:city":"Belton",
    "sg:classifiers":[
        {
            "category":"Retail",
            "subcategory":"Portrait Studio",
            "type":"Services"
        }
    ],
    "sg:phone":"+1 816 331 1404",
    "sg:postcode":"64012",
    "sg:province":"MO",
    "sg:tags":[
        "photo"
    ],
    "wof:name":"Wedding Photography",
    "wof:placetype":"venue"
},
  "geometry": {"coordinates":[-94.497401,38.820482],"type":"Point"}
}