{
  "type": "Feature",
  "properties": {
    "iso:country":"US",
    "sg:address":"701 Walton Dr",
    "sg:city":"Farmington",
    "sg:classifiers":[
        {
            "category":"Real Estate",
            "subcategory":"Real Estate Services",
            "type":"Services"
        },
        {
            "category":"Banks & Credit Unions",
            "subcategory":"Bank",
            "type":"Services"
        },
        {
            "category":"Banks & Credit Unions",
            "subcategory":"Financial Services",
            "type":"Services"
        }
    ],
    "sg:phone":"+1 573 756 6639",
    "sg:postcode":"63640",
    "sg:province":"MO",
    "sg:tags":[
        "commercial",
        "loan",
        "saving"
    ],
    "sg:website":"http://www.bank-star.com",
    "wof:name":"Bank Star of The Leadbelt",
    "wof:placetype":"venue"
},
  "geometry": {"coordinates":[-90.434107,37.788895],"type":"Point"}
}