{
  "type": "Feature",
  "properties": {
    "iso:country":"US",
    "sg:address":"611 S 2nd St",
    "sg:city":"Maitland",
    "sg:classifiers":[
        {
            "category":"Wholesale",
            "subcategory":"Farm Supplies",
            "type":"Manufacturing & Wholesale Goods"
        }
    ],
    "sg:phone":"+1 660 935 2246",
    "sg:postcode":"64466",
    "sg:province":"MO",
    "sg:tags":[
        "feed"
    ],
    "wof:name":"Diggs Farms",
    "wof:placetype":"venue"
},
  "geometry": {"coordinates":[-95.076421,40.197951],"type":"Point"}
}