{
  "type": "Feature",
  "properties": {
    "iso:country":"US",
    "sg:address":"200 Sunview Rd",
    "sg:city":"Hollister",
    "sg:classifiers":[
        {
            "category":"Wholesale",
            "subcategory":"Books, Periodicals, & Newspapers",
            "type":"Manufacturing & Wholesale Goods"
        }
    ],
    "sg:phone":"+1 417 337 3717",
    "sg:postcode":"65672",
    "sg:province":"MO",
    "sg:tags":[
        "dealers-wholesale",
        "news"
    ],
    "wof:name":"Cbmc News",
    "wof:placetype":"venue"
},
  "geometry": {"coordinates":[-93.285695,36.558546],"type":"Point"}
}