{
  "type": "Feature",
  "properties": {
    "iso:country":"US",
    "sg:address":"1380 E Republic Rd",
    "sg:city":"Springfield",
    "sg:classifiers":[
        {
            "category":"Cinema",
            "subcategory":"Movie Rental",
            "type":"Entertainment"
        }
    ],
    "sg:phone":"+1 417 890 1818",
    "sg:postcode":"65804",
    "sg:province":"MO",
    "sg:tags":[
        "video",
        "tape"
    ],
    "wof:name":"Video Update",
    "wof:placetype":"venue"
},
  "geometry": {"coordinates":[-93.2724,37.137485],"type":"Point"}
}