{
  "type": "Feature",
  "properties": {
    "iso:country":"US",
    "sg:address":"9323 E 83 St",
    "sg:city":"Kansas City",
    "sg:classifiers":[
        {
            "category":"Shopping",
            "subcategory":"Clothing, Apparel, & Fashions",
            "type":"Retail Goods"
        }
    ],
    "sg:phone":"+1 816 741 2894",
    "sg:postcode":"64138",
    "sg:province":"MO",
    "wof:name":"Platinum & Lace",
    "wof:placetype":"venue"
},
  "geometry": {"coordinates":[-94.471186,38.972636],"type":"Point"}
}