{
  "type": "Feature",
  "properties": {
    "iso:country":"US",
    "sg:address":"5548 Lehigh Ln",
    "sg:city":"Imperial",
    "sg:classifiers":[
        {
            "category":"Professional",
            "subcategory":"Employment Agencies",
            "type":"Services"
        }
    ],
    "sg:phone":"+1 636 464 3674",
    "sg:postcode":"63052",
    "sg:province":"MO",
    "wof:name":"Career Specialist Inc & E",
    "wof:placetype":"venue"
},
  "geometry": {"coordinates":[-90.37103500000001,38.382168],"type":"Point"}
}