{
  "type": "Feature",
  "properties": {
    "iso:country":"US",
    "sg:address":"9911 S Brown Rd",
    "sg:city":"Oak Grove",
    "sg:classifiers":[
        {
            "category":"Building & Trades",
            "subcategory":"Construction",
            "type":"Services"
        }
    ],
    "sg:phone":"+1 816 697 2235",
    "sg:postcode":"64075",
    "sg:province":"MO",
    "sg:tags":[
        "hanging",
        "contractor"
    ],
    "wof:name":"Scharfenkamp Painting",
    "wof:placetype":"venue"
},
  "geometry": {"coordinates":[-94.199444,38.93635],"type":"Point"}
}