{
  "type": "Feature",
  "properties": {
    "iso:country":"US",
    "sg:address":"157 Forest Pkwy",
    "sg:city":"Valley Park",
    "sg:classifiers":[
        {
            "category":"Building & Trades",
            "subcategory":"Construction",
            "type":"Services"
        }
    ],
    "sg:phone":"+1 636 861 1417",
    "sg:postcode":"63088",
    "sg:province":"MO",
    "sg:tags":[
        "hanging",
        "contractor"
    ],
    "wof:name":"Townsend Painting & Decorating",
    "wof:placetype":"venue"
},
  "geometry": {"coordinates":[-90.496274,38.564424],"type":"Point"}
}