{
  "type": "Feature",
  "properties": {
    "iso:country":"US",
    "sg:address":"3255 Griffith Rd",
    "sg:city":"Farmington",
    "sg:classifiers":[
        {
            "category":"Professional",
            "subcategory":"Engineering",
            "type":"Services"
        },
        {
            "category":"Manufacturing",
            "subcategory":"Textiles",
            "type":"Manufacturing & Wholesale Goods"
        }
    ],
    "sg:phone":"+1 573 518 0022",
    "sg:postcode":"63640",
    "sg:province":"MO",
    "sg:tags":[
        "mill",
        "fabric",
        "engineer"
    ],
    "wof:name":"Shannon & Wilson Inc",
    "wof:placetype":"venue"
},
  "geometry": {"coordinates":[-90.48691599999999,37.859208],"type":"Point"}
}