{
  "type": "Feature",
  "properties": {
    "iso:country":"US",
    "sg:address":"4670 Lansdowne Ave",
    "sg:city":"St Louis",
    "sg:classifiers":[
        {
            "category":"Professional",
            "subcategory":"Computer Services",
            "type":"Services"
        }
    ],
    "sg:phone":"+1 314 481 5900",
    "sg:postcode":"63116",
    "sg:province":"MO",
    "wof:name":"Advantage CTI Communications",
    "wof:placetype":"venue"
},
  "geometry": {"coordinates":[-90.272036,38.587064],"type":"Point"}
}