{
  "type": "Feature",
  "properties": {
    "iso:country":"US",
    "sg:address":"13051 Mc Donald Rd",
    "sg:city":"Centralia",
    "sg:classifiers":[
        {
            "category":"Manufacturing",
            "subcategory":"Furniture",
            "type":"Manufacturing & Wholesale Goods"
        }
    ],
    "sg:phone":"+1 573 682 2533",
    "sg:postcode":"65240",
    "sg:province":"MO",
    "sg:tags":[
        "household",
        "wood",
        "mfg"
    ],
    "wof:name":"Heirlooms",
    "wof:placetype":"venue"
},
  "geometry": {"coordinates":[-92.118916,39.103547],"type":"Point"}
}