{
  "type": "Feature",
  "properties": {
    "iso:country":"US",
    "sg:address":"221 Lamp and Lantern Village",
    "sg:city":"Chesterfield",
    "sg:classifiers":[
        {
            "category":"Home & Garden",
            "subcategory":"Hardware",
            "type":"Retail Goods"
        }
    ],
    "sg:phone":"+1 636 386 7733",
    "sg:postcode":"63017",
    "sg:province":"MO",
    "sg:website":"www.acestl.com",
    "wof:name":"Ace Hardware",
    "wof:placetype":"venue"
},
  "geometry": {"coordinates":[-90.516496,38.625102],"type":"Point"}
}