{
  "type": "Feature",
  "properties": {
    "addr:full":"1010 NW Woods Chapel Rd Blue Springs MO 64015",
    "addr:housenumber":"1010",
    "addr:postcode":"64015",
    "addr:street":"Nw Woods Chapel Rd",
    "iso:country":"US",
    "sg:address":"1010 NW Woods Chapel Rd",
    "sg:city":"Blue Springs",
    "sg:classifiers":[
        {
            "category":"Shopping",
            "subcategory":"Clothing, Apparel, & Fashions",
            "type":"Retail Goods"
        }
    ],
    "sg:phone":"+1 816 228 9903",
    "sg:postcode":"64015",
    "sg:province":"MO",
    "sg:tags":[
        "shop",
        "beauty"
    ],
    "wof:name":"Images",
    "wof:placetype":"venue"
},
  "geometry": {"coordinates":[-94.304334,39.029394],"type":"Point"}
}