{
  "type": "Feature",
  "properties": {
    "iso:country":"US",
    "sg:address":"55 Branch Rd",
    "sg:city":"Eldon",
    "sg:classifiers":[
        {
            "category":"Real Estate",
            "subcategory":"Real Estate Operator",
            "type":"Services"
        },
        {
            "category":"Organizations",
            "subcategory":"Community Association",
            "type":"Services"
        }
    ],
    "sg:phone":"+1 573 365 0366",
    "sg:postcode":"65049",
    "sg:province":"MO",
    "sg:tags":[
        "residential",
        "construction",
        "condominium"
    ],
    "wof:name":"Spinnaker Point Condominium S",
    "wof:placetype":"venue"
},
  "geometry": {"coordinates":[-92.63518999999999,38.216139],"type":"Point"}
}