{
  "type": "Feature",
  "properties": {
    "iso:country":"US",
    "sg:address":"1100 Manresa Ln",
    "sg:city":"Florissant",
    "sg:classifiers":[
        {
            "category":"Professional",
            "subcategory":"Computer Services",
            "type":"Services"
        }
    ],
    "sg:phone":"+1 314 839 8510",
    "sg:postcode":"63031",
    "sg:province":"MO",
    "sg:tags":[
        "related"
    ],
    "wof:name":"I 400 Inc",
    "wof:placetype":"venue"
},
  "geometry": {"coordinates":[-90.354128,38.794134],"type":"Point"}
}