{
  "type": "Feature",
  "properties": {
    "iso:country":"US",
    "sg:address":"1806 W 11th St",
    "sg:city":"Sedalia",
    "sg:classifiers":[
        {
            "category":"Personal",
            "subcategory":"Beauty Salon",
            "type":"Services"
        }
    ],
    "sg:phone":"+1 660 826 4888",
    "sg:postcode":"65301",
    "sg:province":"MO",
    "sg:tags":[
        "shop"
    ],
    "wof:name":"Hot Tips Nail Salon",
    "wof:placetype":"venue"
},
  "geometry": {"coordinates":[-93.251583,38.702554],"type":"Point"}
}