{
  "type": "Feature",
  "properties": {
    "iso:country":"US",
    "sg:address":"510 Rue de Leon",
    "sg:city":"Bonne Terre",
    "sg:classifiers":[
        {
            "category":"Professional",
            "subcategory":"Business Services",
            "type":"Services"
        },
        {
            "category":"Wholesale",
            "subcategory":"Non-durable Goods",
            "type":"Manufacturing & Wholesale Goods"
        }
    ],
    "sg:phone":"+1 573 358 0722",
    "sg:postcode":"63628",
    "sg:province":"MO",
    "sg:tags":[
        "badge"
    ],
    "wof:name":"Sign Of Man Of Missouri",
    "wof:placetype":"venue"
},
  "geometry": {"coordinates":[-90.630804,37.907943],"type":"Point"}
}