{
  "type": "Feature",
  "properties": {
    "iso:country":"US",
    "sg:address":"113 N Railroad St",
    "sg:city":"Oran",
    "sg:classifiers":[
        {
            "category":"Home & Garden",
            "subcategory":"Hardware",
            "type":"Retail Goods"
        }
    ],
    "sg:phone":"+1 573 262 2233",
    "sg:postcode":"63771",
    "sg:province":"MO",
    "sg:tags":[
        "store"
    ],
    "wof:name":"Eftink Hardware",
    "wof:placetype":"venue"
},
  "geometry": {"coordinates":[-89.655421,37.085367],"type":"Point"}
}