{
  "type": "Feature",
  "properties": {
    "iso:country":"US",
    "sg:address":"1750 S Hanley Rd",
    "sg:city":"Saint Louis",
    "sg:classifiers":[
        {
            "category":"Professional",
            "subcategory":"Detective & Security Services",
            "type":"Services"
        }
    ],
    "sg:phone":"+1 314 644 1974",
    "sg:postcode":"63144",
    "sg:province":"MO",
    "sg:tags":[
        "guard"
    ],
    "wof:name":"Whelan Security Co",
    "wof:placetype":"venue"
},
  "geometry": {"coordinates":[-90.334473,38.623056],"type":"Point"}
}