{
  "type": "Feature",
  "properties": {
    "iso:country":"US",
    "sg:address":"7591 Olive Blvd",
    "sg:city":"St Louis",
    "sg:classifiers":[
        {
            "category":"Shopping",
            "subcategory":"Used Merchandise",
            "type":"Retail Goods"
        }
    ],
    "sg:phone":"+1 314 721 7768",
    "sg:postcode":"63130",
    "sg:province":"MO",
    "sg:tags":[
        "antique"
    ],
    "wof:name":"Spot Antiques",
    "wof:placetype":"venue"
},
  "geometry": {"coordinates":[-90.336249,38.672256],"type":"Point"}
}