{
  "type": "Feature",
  "properties": {
    "iso:country":"US",
    "sg:address":"2620 Old Orchard Rd",
    "sg:city":"Perryville",
    "sg:classifiers":[
        {
            "category":"Professional",
            "type":"Services"
        }
    ],
    "sg:phone":"+1 573 547 2076",
    "sg:postcode":"63755",
    "sg:province":"MO",
    "sg:tags":[
        "establishment"
    ],
    "wof:name":"Emmendorfer Family Inc",
    "wof:placetype":"venue"
},
  "geometry": {"coordinates":[-89.60951,37.363501],"type":"Point"}
}