{
  "type": "Feature",
  "properties": {
    "iso:country":"US",
    "sg:address":"777 S New Ballas Rd",
    "sg:city":"Saint Louis",
    "sg:classifiers":[
        {
            "category":"Health Services",
            "subcategory":"Doctor",
            "type":"Services"
        }
    ],
    "sg:phone":"+1 314 997 7972",
    "sg:postcode":"63141",
    "sg:province":"MO",
    "wof:name":"Barry S Goldenberg",
    "wof:placetype":"venue"
},
  "geometry": {"coordinates":[-90.443534,38.641359],"type":"Point"}
}