{
  "type": "Feature",
  "properties": {
    "iso:country":"US",
    "sg:address":"921 Walnut St",
    "sg:city":"Kansas City",
    "sg:classifiers":[
        {
            "category":"Banks & Credit Unions",
            "subcategory":"Bank",
            "type":"Services"
        }
    ],
    "sg:phone":"+1 816 843 2000",
    "sg:postcode":"64106",
    "sg:province":"MO",
    "sg:tags":[
        "other",
        "plan",
        "card"
    ],
    "wof:name":"UMB Bank",
    "wof:placetype":"venue"
},
  "geometry": {"coordinates":[-94.581878,39.102533],"type":"Point"}
}