{
  "type": "Feature",
  "properties": {
    "iso:country":"US",
    "sg:address":"40 E Lockwood Ave",
    "sg:city":"Webster Groves",
    "sg:classifiers":[
        {
            "category":"Home & Garden",
            "subcategory":"Hardware",
            "type":"Retail Goods"
        }
    ],
    "sg:phone":"+1 314 961 4522",
    "sg:postcode":"63119",
    "sg:province":"MO",
    "wof:name":"Mac True Value Hardware",
    "wof:placetype":"venue"
},
  "geometry": {"coordinates":[-90.356476,38.592614],"type":"Point"}
}