{
  "type": "Feature",
  "properties": {
    "iso:country":"US",
    "sg:address":"2602 Frederick Ave",
    "sg:city":"Saint Joseph",
    "sg:classifiers":[
        {
            "category":"Real Estate",
            "subcategory":"Real Estate Agent",
            "type":"Services"
        }
    ],
    "sg:phone":"+1 816 364 2021",
    "sg:postcode":"64506",
    "sg:province":"MO",
    "wof:name":"Hummer Management & Realty Co",
    "wof:placetype":"venue"
},
  "geometry": {"coordinates":[-94.828146,39.776758],"type":"Point"}
}