{
  "type": "Feature",
  "properties": {
    "iso:country":"US",
    "sg:address":"5426 State Hwy 30",
    "sg:city":"Saint Louis",
    "sg:classifiers":[
        {
            "category":"Wholesale",
            "subcategory":"Groceries",
            "type":"Manufacturing & Wholesale Goods"
        }
    ],
    "sg:phone":"+1 314 645 3914",
    "sg:postcode":"63116",
    "sg:province":"MO",
    "sg:tags":[
        "general"
    ],
    "wof:name":"Urzis Blue Ridge Market",
    "wof:placetype":"venue"
},
  "geometry": {"coordinates":[-90.271027,38.578196],"type":"Point"}
}