{
  "type": "Feature",
  "properties": {
    "iso:country":"US",
    "sg:address":"13007 Olive Blvd",
    "sg:city":"St Louis",
    "sg:classifiers":[
        {
            "category":"Food & Beverages",
            "subcategory":"Groceries & Convenience Stores",
            "type":"Retail Goods"
        }
    ],
    "sg:phone":"+1 314 439 5599",
    "sg:postcode":"63141",
    "sg:province":"MO",
    "wof:name":"786 Pakistani-Indian Middle",
    "wof:placetype":"venue"
},
  "geometry": {"coordinates":[-90.481646,38.682788],"type":"Point"}
}