{
  "type": "Feature",
  "properties": {
    "iso:country":"US",
    "sg:address":"2230 S Norton Ave",
    "sg:city":"Independence",
    "sg:classifiers":[
        {
            "category":"Shopping",
            "subcategory":"Used Merchandise",
            "type":"Retail Goods"
        },
        {
            "category":"Shopping",
            "subcategory":"Jewelry",
            "type":"Retail Goods"
        }
    ],
    "sg:phone":"+1 816 252 4144",
    "sg:postcode":"64050",
    "sg:province":"MO",
    "sg:tags":[
        "pawnbroker"
    ],
    "wof:name":"23rd Street Pawn",
    "wof:placetype":"venue"
},
  "geometry": {"coordinates":[-94.43856599999999,39.082659],"type":"Point"}
}