{
  "type": "Feature",
  "properties": {
    "iso:country":"US",
    "sg:address":"907 W 18th St",
    "sg:city":"Trenton",
    "sg:classifiers":[
        {
            "category":"Professional",
            "subcategory":"Business Services",
            "type":"Services"
        }
    ],
    "sg:phone":"+1 660 359 3081",
    "sg:postcode":"64683",
    "sg:province":"MO",
    "sg:tags":[
        "consultant",
        "management"
    ],
    "wof:name":"The Provorses",
    "wof:placetype":"venue"
},
  "geometry": {"coordinates":[-93.626767,40.082677],"type":"Point"}
}