{
  "type": "Feature",
  "properties": {
    "iso:country":"US",
    "sg:address":"103 W Lockwood Ave",
    "sg:city":"St Louis",
    "sg:classifiers":[
        {
            "category":"Professional",
            "subcategory":"Advertising",
            "type":"Services"
        }
    ],
    "sg:phone":"+1 314 918 7788",
    "sg:postcode":"63119",
    "sg:province":"MO",
    "sg:tags":[
        "counselor",
        "agency"
    ],
    "wof:name":"Hess Newmark Owens Wolf Public",
    "wof:placetype":"venue"
},
  "geometry": {"coordinates":[-90.36087499999999,38.593255],"type":"Point"}
}