{
  "type": "Feature",
  "properties": {
    "iso:country":"US",
    "sg:address":"3025 Clinton Rd",
    "sg:city":"Sedalia",
    "sg:classifiers":[
        {
            "category":"Freight",
            "type":"Transportation"
        }
    ],
    "sg:phone":"+1 660 826 7875",
    "sg:postcode":"65301",
    "sg:province":"MO",
    "sg:tags":[
        "commercial",
        "storage"
    ],
    "wof:name":"Easy-Stor",
    "wof:placetype":"venue"
},
  "geometry": {"coordinates":[-93.249278,38.685298],"type":"Point"}
}