{
  "type": "Feature",
  "properties": {
    "iso:country":"US",
    "sg:address":"6 W 9th St",
    "sg:city":"Fulton",
    "sg:classifiers":[
        {
            "category":"Organizations",
            "subcategory":"Religious Organization",
            "type":"Services"
        }
    ],
    "sg:phone":"+1 573 642 7758",
    "sg:postcode":"65251",
    "sg:province":"MO",
    "sg:tags":[
        "church"
    ],
    "wof:name":"St Alban's Episcopal Church",
    "wof:placetype":"venue"
},
  "geometry": {"coordinates":[-91.948362,38.85447],"type":"Point"}
}