{
  "type": "Feature",
  "properties": {
    "iso:country":"US",
    "sg:address":"5739 N Polk Dr",
    "sg:city":"Kansas City",
    "sg:classifiers":[
        {
            "category":"Wholesale",
            "subcategory":"Vending Machines",
            "type":"Manufacturing & Wholesale Goods"
        }
    ],
    "sg:phone":"+1 816 741 8065",
    "sg:postcode":"64151",
    "sg:province":"MO",
    "sg:tags":[
        "food",
        "beverage"
    ],
    "wof:name":"Vending Unlimited",
    "wof:placetype":"venue"
},
  "geometry": {"coordinates":[-94.637202,39.199055],"type":"Point"}
}