{
  "type": "Feature",
  "properties": {
    "iso:country":"US",
    "sg:address":"1420 McVey St",
    "sg:city":"Chillicothe",
    "sg:classifiers":[
        {
            "category":"Social Services",
            "subcategory":"Child Care",
            "type":"Services"
        }
    ],
    "sg:phone":"+1 660 646 5999",
    "sg:postcode":"64601",
    "sg:province":"MO",
    "sg:tags":[
        "day"
    ],
    "wof:name":"Devines Day Care",
    "wof:placetype":"venue"
},
  "geometry": {"coordinates":[-93.54358999999999,39.80228],"type":"Point"}
}