{
  "type": "Feature",
  "properties": {
    "iso:country":"US",
    "sg:address":"309 E Water St",
    "sg:city":"Springfield",
    "sg:classifiers":[
        {
            "category":"Professional",
            "subcategory":"Business Services",
            "type":"Services"
        }
    ],
    "sg:phone":"+1 417 863 1925",
    "sg:postcode":"65806",
    "sg:province":"MO",
    "sg:tags":[
        "recording",
        "studio"
    ],
    "sg:website":"www.nationalaudiocompany.com",
    "wof:name":"National Audio",
    "wof:placetype":"venue"
},
  "geometry": {"coordinates":[-93.290947,37.210915],"type":"Point"}
}