{
  "type": "Feature",
  "properties": {
    "iso:country":"US",
    "sg:address":"1072 Gravois Rd",
    "sg:city":"Fenton",
    "sg:classifiers":[
        {
            "category":"Building & Trades",
            "subcategory":"Landscaping Services",
            "type":"Services"
        }
    ],
    "sg:phone":"+1 636 343 0303",
    "sg:postcode":"63026",
    "sg:province":"MO",
    "sg:tags":[
        "landscape"
    ],
    "wof:name":"Boss Landscape Contractor Inc",
    "wof:placetype":"venue"
},
  "geometry": {"coordinates":[-90.47410000000001,38.49796],"type":"Point"}
}