{
  "type": "Feature",
  "properties": {
    "iso:country":"US",
    "sg:address":"408 Morningside Dr",
    "sg:city":"St Peters",
    "sg:classifiers":[
        {
            "category":"Professional",
            "subcategory":"Computer Services",
            "type":"Services"
        }
    ],
    "sg:phone":"+1 636 397 4147",
    "sg:postcode":"63376",
    "sg:province":"MO",
    "sg:tags":[
        "consultant",
        "designer",
        "related"
    ],
    "wof:name":"Michael Worsham Inc",
    "wof:placetype":"venue"
},
  "geometry": {"coordinates":[-90.614902,38.767232],"type":"Point"}
}