{
  "type": "Feature",
  "properties": {
    "iso:country":"US",
    "sg:address":"45 Holly Rd",
    "sg:city":"Iberia",
    "sg:classifiers":[
        {
            "category":"Farming",
            "subcategory":"Livestock Farm",
            "type":"Manufacturing & Wholesale Goods"
        },
        {
            "category":"Farming",
            "subcategory":"Farm",
            "type":"Manufacturing & Wholesale Goods"
        }
    ],
    "sg:phone":"+1 573 793 2552",
    "sg:postcode":"65486",
    "sg:province":"MO",
    "sg:tags":[
        "ranch"
    ],
    "wof:name":"Family Memorial Planning",
    "wof:placetype":"venue"
},
  "geometry": {"coordinates":[-92.265049,38.162121],"type":"Point"}
}