{
  "type": "Feature",
  "properties": {
    "iso:country":"US",
    "sg:address":"1910 US Hwy 69",
    "sg:city":"Excelsior Springs",
    "sg:classifiers":[
        {
            "category":"Manufacturing",
            "subcategory":"Glass & Minerals",
            "type":"Manufacturing & Wholesale Goods"
        }
    ],
    "sg:phone":"+1 816 637 3622",
    "sg:postcode":"64024",
    "sg:province":"MO",
    "sg:tags":[
        "ready",
        "concrete",
        "mfg"
    ],
    "wof:name":"Green Ready Mix",
    "wof:placetype":"venue"
},
  "geometry": {"coordinates":[-94.262306,39.334385],"type":"Point"}
}