{
  "type": "Feature",
  "properties": {
    "iso:country":"US",
    "sg:address":"612 W Main St",
    "sg:city":"Jackson",
    "sg:classifiers":[
        {
            "category":"Insurance",
            "subcategory":"Insurance Agent",
            "type":"Services"
        }
    ],
    "sg:phone":"+1 573 243 1334",
    "sg:postcode":"63755",
    "sg:province":"MO",
    "wof:name":"Gene E Wills Insurance Svc",
    "wof:placetype":"venue"
},
  "geometry": {"coordinates":[-89.675218,37.38345],"type":"Point"}
}