{
  "type": "Feature",
  "properties": {
    "iso:country":"US",
    "sg:address":"1551 N Courtney Rd",
    "sg:city":"Independence",
    "sg:classifiers":[
        {
            "category":"Retail",
            "subcategory":"Auto Repair",
            "type":"Services"
        }
    ],
    "sg:phone":"+1 816 461 7500",
    "sg:postcode":"64050",
    "sg:province":"MO",
    "sg:tags":[
        "automobile",
        "general",
        "restoration",
        "classic"
    ],
    "wof:name":"Auto Customs Underground LLC",
    "wof:placetype":"venue"
},
  "geometry": {"coordinates":[-94.40528399999999,39.132428],"type":"Point"}
}