{
  "type": "Feature",
  "properties": {
    "addr:full":"2125 E Jackson Blvd Jackson MO 63755",
    "addr:housenumber":"2125",
    "addr:postcode":"63755",
    "addr:street":"E Jackson Blvd",
    "iso:country":"US",
    "sg:address":"2125 E Jackson Blvd",
    "sg:city":"Jackson",
    "sg:classifiers":[
        {
            "category":"Banks & Credit Unions",
            "subcategory":"Bank",
            "type":"Services"
        },
        {
            "category":"Banks & Credit Unions",
            "subcategory":"Financial Services",
            "type":"Services"
        }
    ],
    "sg:phone":"+1 573 243 9778",
    "sg:postcode":"63755",
    "sg:province":"MO",
    "sg:tags":[
        "commercial",
        "loan",
        "saving"
    ],
    "wof:name":"First National Bank",
    "wof:placetype":"venue"
},
  "geometry": {"coordinates":[-89.646164,37.37044],"type":"Point"}
}