{
  "type": "Feature",
  "properties": {
    "iso:country":"US",
    "sg:address":"1 Pratt Pl",
    "sg:city":"Florissant",
    "sg:classifiers":[
        {
            "category":"Real Estate",
            "subcategory":"Real Estate Operator",
            "type":"Services"
        }
    ],
    "sg:phone":"+1 314 839 5000",
    "sg:postcode":"63031",
    "sg:province":"MO",
    "sg:tags":[
        "building",
        "home",
        "apartment",
        "convalescent",
        "nursing"
    ],
    "sg:website":"http://www.villaatriverwood.com",
    "wof:name":"Villa At Riverwood",
    "wof:placetype":"venue"
},
  "geometry": {"coordinates":[-90.365532,38.804218],"type":"Point"}
}