{
  "type": "Feature",
  "properties": {
    "iso:country":"US",
    "sg:address":"318 E Park Central East St",
    "sg:city":"Springfield",
    "sg:classifiers":[
        {
            "category":"Professional",
            "subcategory":"Lawyer & Legal Services",
            "type":"Services"
        }
    ],
    "sg:phone":"+1 417 883 8000",
    "sg:postcode":"65806",
    "sg:province":"MO",
    "wof:name":"Attorneys",
    "wof:placetype":"venue"
},
  "geometry": {"coordinates":[-93.290102,37.208845],"type":"Point"}
}