{
  "type": "Feature",
  "properties": {
    "iso:country":"US",
    "sg:address":"12128 Blue Ridge Exd",
    "sg:city":"Grandview",
    "sg:classifiers":[
        {
            "category":"Restaurant",
            "type":"Food & Drink"
        }
    ],
    "sg:phone":"+1 816 761 8043",
    "sg:postcode":"64030",
    "sg:province":"MO",
    "sg:tags":[
        "eating"
    ],
    "wof:name":"El Maguay Restaurant",
    "wof:placetype":"venue"
},
  "geometry": {"coordinates":[-94.526933,38.906333],"type":"Point"}
}