{
  "type": "Feature",
  "properties": {
    "iso:country":"US",
    "sg:address":"13252 Bonroyal Dr",
    "sg:city":"Saint Louis",
    "sg:classifiers":[
        {
            "category":"Manufacturing",
            "subcategory":"Tools & Machinery",
            "type":"Manufacturing & Wholesale Goods"
        }
    ],
    "sg:phone":"+1 314 822 5119",
    "sg:postcode":"63131",
    "sg:province":"MO",
    "sg:tags":[
        "industry"
    ],
    "wof:name":"Millar Myers & Assoc Inc",
    "wof:placetype":"venue"
},
  "geometry": {"coordinates":[-90.46427799999999,38.600037],"type":"Point"}
}