{
  "type": "Feature",
  "properties": {
    "iso:country":"US",
    "sg:address":"10 Community Plz",
    "sg:city":"Sullivan",
    "sg:classifiers":[
        {
            "category":"Health Services",
            "subcategory":"Doctor",
            "type":"Services"
        }
    ],
    "sg:phone":"+1 573 860 2552",
    "sg:postcode":"63080",
    "sg:province":"MO",
    "sg:tags":[
        "dentist"
    ],
    "sg:website":"http://www.drbrace.com",
    "wof:name":"Brace Barry DMD",
    "wof:placetype":"venue"
},
  "geometry": {"coordinates":[-91.165564,38.216673],"type":"Point"}
}