{
  "type": "Feature",
  "properties": {
    "iso:country":"US",
    "sg:address":"419 S 14th St",
    "sg:city":"Bowling Green",
    "sg:classifiers":[
        {
            "category":"Social Services",
            "subcategory":"Child Care",
            "type":"Services"
        }
    ],
    "sg:phone":"+1 573 324 3417",
    "sg:postcode":"63334",
    "sg:province":"MO",
    "sg:tags":[
        "day"
    ],
    "wof:name":"Turnboughs Day Care",
    "wof:placetype":"venue"
},
  "geometry": {"coordinates":[-91.207634,39.338202],"type":"Point"}
}