{
  "type": "Feature",
  "properties": {
    "iso:country":"US",
    "sg:address":"6805 E 98 Ter",
    "sg:city":"Kansas City",
    "sg:classifiers":[
        {
            "category":"Professional",
            "subcategory":"Business Services",
            "type":"Services"
        }
    ],
    "sg:phone":"+1 816 761 0430",
    "sg:postcode":"64134",
    "sg:province":"MO",
    "wof:name":"Matti & Assoc Educational Serv",
    "wof:placetype":"venue"
},
  "geometry": {"coordinates":[-94.50823800000001,38.946588],"type":"Point"}
}