{
  "type": "Feature",
  "properties": {
    "iso:country":"US",
    "sg:address":"3 N Spanish St",
    "sg:city":"Cape Girardeau",
    "sg:classifiers":[
        {
            "category":"Personal",
            "subcategory":"Beauty Salon",
            "type":"Services"
        }
    ],
    "sg:phone":"+1 573 334 5692",
    "sg:postcode":"63701",
    "sg:province":"MO",
    "sg:tags":[
        "shop"
    ],
    "wof:name":"Shirley's Hair Fashions",
    "wof:placetype":"venue"
},
  "geometry": {"coordinates":[-89.519554,37.303915],"type":"Point"}
}