{
  "type": "Feature",
  "properties": {
    "iso:country":"US",
    "sg:address":"702 S Fox Ridge Dr",
    "sg:city":"Raymore",
    "sg:classifiers":[
        {
            "category":"Communications",
            "type":"Services"
        }
    ],
    "sg:phone":"+1 816 322 9555",
    "sg:postcode":"64083",
    "sg:province":"MO",
    "wof:name":"Jm Communications",
    "wof:placetype":"venue"
},
  "geometry": {"coordinates":[-94.483589,38.794824],"type":"Point"}
}