{
  "type": "Feature",
  "properties": {
    "iso:country":"US",
    "sg:address":"107 E 2nd St",
    "sg:city":"Mountain Grove",
    "sg:classifiers":[
        {
            "category":"Shopping",
            "subcategory":"Jewelry",
            "type":"Retail Goods"
        }
    ],
    "sg:phone":"+1 417 926 3626",
    "sg:postcode":"65711",
    "sg:province":"MO",
    "sg:tags":[
        "jeweler"
    ],
    "wof:name":"Shannon Jewelry",
    "wof:placetype":"venue"
},
  "geometry": {"coordinates":[-92.26322500000001,37.129902],"type":"Point"}
}