{
  "type": "Feature",
  "properties": {
    "iso:country":"US",
    "sg:address":"328 E Walnut St",
    "sg:city":"Thayer",
    "sg:classifiers":[
        {
            "category":"Real Estate",
            "subcategory":"Real Estate Services",
            "type":"Services"
        },
        {
            "category":"Real Estate",
            "subcategory":"Real Estate Agent",
            "type":"Services"
        }
    ],
    "sg:phone":"+1 417 264 7000",
    "sg:postcode":"65791",
    "sg:province":"MO",
    "sg:tags":[
        "buyer",
        "broker"
    ],
    "sg:website":"http://www.century21.com",
    "wof:name":"Century 21",
    "wof:placetype":"venue"
},
  "geometry": {"coordinates":[-91.540656,36.523417],"type":"Point"}
}