{
  "type": "Feature",
  "properties": {
    "iso:country":"US",
    "sg:address":"318 E Broadway St",
    "sg:city":"Monett",
    "sg:classifiers":[
        {
            "category":"Retail",
            "subcategory":"Portrait Studio",
            "type":"Services"
        }
    ],
    "sg:phone":"+1 417 236 0110",
    "sg:postcode":"65708",
    "sg:province":"MO",
    "sg:tags":[
        "photographer",
        "photo"
    ],
    "wof:name":"Connie's Photography",
    "wof:placetype":"venue"
},
  "geometry": {"coordinates":[-93.9235,36.920871],"type":"Point"}
}