{
  "type": "Feature",
  "properties": {
    "iso:country":"US",
    "sg:address":"105 N Maple Ave",
    "sg:city":"Hannibal",
    "sg:classifiers":[
        {
            "category":"Insurance",
            "subcategory":"Insurance Agent",
            "type":"Services"
        }
    ],
    "sg:phone":"+1 573 221 2668",
    "sg:postcode":"63401",
    "sg:province":"MO",
    "sg:tags":[
        "real estate"
    ],
    "wof:name":"Raible & Brown Realtors",
    "wof:placetype":"venue"
},
  "geometry": {"coordinates":[-91.367217,39.705226],"type":"Point"}
}