{
  "type": "Feature",
  "properties": {
    "iso:country":"US",
    "sg:address":"1821 S Baltimore St",
    "sg:city":"Kirksville",
    "sg:classifiers":[
        {
            "category":"Autos & Motor Vehicles",
            "subcategory":"Automobile Sales",
            "type":"Retail Goods"
        }
    ],
    "sg:phone":"+1 660 665 5500",
    "sg:postcode":"63501",
    "sg:province":"MO",
    "sg:tags":[
        "car",
        "dealer"
    ],
    "wof:name":"Auto Villa",
    "wof:placetype":"venue"
},
  "geometry": {"coordinates":[-92.571833,40.179607],"type":"Point"}
}