{
  "type": "Feature",
  "properties": {
    "iso:country":"US",
    "sg:address":"1301 Forum Dr",
    "sg:city":"Rolla",
    "sg:classifiers":[
        {
            "category":"Banks & Credit Unions",
            "subcategory":"Bank",
            "type":"Services"
        },
        {
            "category":"Banks & Credit Unions",
            "subcategory":"Financial Services",
            "type":"Services"
        }
    ],
    "sg:phone":"+1 573 368 5612",
    "sg:postcode":"65401",
    "sg:province":"MO",
    "sg:tags":[
        "saving",
        "loan",
        "commercial"
    ],
    "sg:website":"http://usbank.com",
    "wof:name":"Us Bank",
    "wof:placetype":"venue"
},
  "geometry": {"coordinates":[-91.752332,37.953433],"type":"Point"}
}