{
  "type": "Feature",
  "properties": {
    "iso:country":"US",
    "sg:address":"4858 Werner Rd",
    "sg:city":"High Ridge",
    "sg:classifiers":[
        {
            "category":"Retail",
            "subcategory":"Animal Services",
            "type":"Services"
        }
    ],
    "sg:phone":"+1 636 677 7626",
    "sg:postcode":"63049",
    "sg:province":"MO",
    "wof:name":"Cardi Ridge Kennels",
    "wof:placetype":"venue"
},
  "geometry": {"coordinates":[-90.50452900000001,38.460916],"type":"Point"}
}