{
  "type": "Feature",
  "properties": {
    "iso:country":"US",
    "sg:address":"131 N Monroe St",
    "sg:city":"Versailles",
    "sg:classifiers":[
        {
            "category":"Home & Garden",
            "subcategory":"Furniture",
            "type":"Retail Goods"
        }
    ],
    "sg:phone":"+1 573 378 4228",
    "sg:postcode":"65084",
    "sg:province":"MO",
    "sg:tags":[
        "electronics",
        "appliance"
    ],
    "wof:name":"Versailles Furniture & Appls",
    "wof:placetype":"venue"
},
  "geometry": {"coordinates":[-92.84187900000001,38.432098],"type":"Point"}
}