{
  "type": "Feature",
  "properties": {
    "iso:country":"US",
    "sg:address":"7413 State Hwy T",
    "sg:city":"Shelbina",
    "sg:classifiers":[
        {
            "category":"Farming",
            "subcategory":"Livestock Farm",
            "type":"Manufacturing & Wholesale Goods"
        }
    ],
    "sg:phone":"+1 573 588 4211",
    "sg:postcode":"63468",
    "sg:province":"MO",
    "sg:tags":[
        "hog",
        "or",
        "feedlot"
    ],
    "wof:name":"Latchford Farms",
    "wof:placetype":"venue"
},
  "geometry": {"coordinates":[-91.950169,39.674729],"type":"Point"}
}