{
  "type": "Feature",
  "properties": {
    "iso:country":"US",
    "sg:address":"1308 E Republic Rd",
    "sg:city":"Springfield",
    "sg:classifiers":[
        {
            "category":"Shopping",
            "subcategory":"Clothing, Apparel, & Fashions",
            "type":"Retail Goods"
        }
    ],
    "sg:phone":"+1 417 887 5448",
    "sg:postcode":"65804",
    "sg:province":"MO",
    "wof:name":"Panache Boutique",
    "wof:placetype":"venue"
},
  "geometry": {"coordinates":[-93.275581,37.137573],"type":"Point"}
}