{
  "type": "Feature",
  "properties": {
    "iso:country":"US",
    "sg:address":"108 E Jasper St",
    "sg:city":"Versailles",
    "sg:classifiers":[
        {
            "category":"Retail",
            "subcategory":"Auto Repair",
            "type":"Services"
        }
    ],
    "sg:phone":"+1 573 378 6778",
    "sg:postcode":"65084",
    "sg:province":"MO",
    "sg:tags":[
        "repairing",
        "automobile"
    ],
    "wof:name":"G Y Auto Ctr",
    "wof:placetype":"venue"
},
  "geometry": {"coordinates":[-92.84182699999999,38.430862],"type":"Point"}
}