{
  "type": "Feature",
  "properties": {
    "iso:country":"US",
    "sg:address":"1955 W Elm St",
    "sg:city":"Lebanon",
    "sg:classifiers":[
        {
            "category":"Travel",
            "subcategory":"Hotels & Motels",
            "type":"Entertainment"
        },
        {
            "category":"Retail",
            "subcategory":"Event Space",
            "type":"Services"
        }
    ],
    "sg:phone":"+1 800 345 8082",
    "sg:postcode":"65536",
    "sg:province":"MO",
    "sg:tags":[
        "facility",
        "banquet",
        "reception",
        "lodging",
        "corporate",
        "hall"
    ],
    "sg:website":"http://ad.doubleclick.net/clk;222816988;46581822;v?http://www.hiexpress.com/redirect?path=hd&brandCode=ex&hotelCode=lbomo&_PMID=99601036&cm_mmc=mdpr-_-yellowpages-_-ex-_-lbomo",
    "wof:name":"Holiday Inn Express Hotel & Suites Lebanon",
    "wof:placetype":"venue"
},
  "geometry": {"coordinates":[-92.667762,37.650619],"type":"Point"}
}