{
  "type": "Feature",
  "properties": {
    "iso:country":"US",
    "sg:address":"3654 Gravois Ave",
    "sg:city":"Saint Louis",
    "sg:classifiers":[
        {
            "category":"Health Services",
            "subcategory":"Dentist",
            "type":"Services"
        }
    ],
    "sg:phone":"+1 314 865 3838",
    "sg:postcode":"63116",
    "sg:province":"MO",
    "wof:name":"Southside Dental Care",
    "wof:placetype":"venue"
},
  "geometry": {"coordinates":[-90.24645200000001,38.591804],"type":"Point"}
}