{
  "type": "Feature",
  "properties": {
    "iso:country":"US",
    "sg:address":"1305 Gloria",
    "sg:city":"Jackson",
    "sg:classifiers":[
        {
            "category":"Education",
            "subcategory":"Dance Studio",
            "type":"Public Place"
        }
    ],
    "sg:phone":"+1 573 243 1176",
    "sg:postcode":"63755",
    "sg:province":"MO",
    "sg:tags":[
        "instruction",
        "dancing"
    ],
    "wof:name":"Dance Extensions",
    "wof:placetype":"venue"
},
  "geometry": {"coordinates":[-89.637714,37.367112],"type":"Point"}
}