{
  "type": "Feature",
  "properties": {
    "iso:country":"US",
    "sg:address":"10155 Corporate Square Dr",
    "sg:city":"Saint Louis",
    "sg:classifiers":[
        {
            "category":"Communications",
            "subcategory":"Radio Station",
            "type":"Services"
        }
    ],
    "sg:phone":"+1 314 692 5108",
    "sg:postcode":"63132",
    "sg:province":"MO",
    "sg:tags":[
        "broadcasting"
    ],
    "wof:name":"Katz Magic 108 FM",
    "wof:placetype":"venue"
},
  "geometry": {"coordinates":[-90.402829,38.679651],"type":"Point"}
}