{
  "type": "Feature",
  "properties": {
    "iso:country":"US",
    "sg:address":"24 NW 114th Ct",
    "sg:city":"Kansas City",
    "sg:classifiers":[
        {
            "category":"Retail",
            "subcategory":"Auto Repair",
            "type":"Services"
        }
    ],
    "sg:phone":"+1 816 985 8045",
    "sg:postcode":"64155",
    "sg:province":"MO",
    "sg:tags":[
        "heavy",
        "mobile",
        "truck",
        "equipment"
    ],
    "wof:name":"Bricker Maintenance & Repair",
    "wof:placetype":"venue"
},
  "geometry": {"coordinates":[-94.57992,39.30184],"type":"Point"}
}