{
  "type": "Feature",
  "properties": {
    "iso:country":"US",
    "sg:address":"206 Ridgeway Ave",
    "sg:city":"Trenton",
    "sg:classifiers":[
        {
            "category":"Wholesale",
            "subcategory":"Vending Machines",
            "type":"Manufacturing & Wholesale Goods"
        }
    ],
    "sg:phone":"+1 660 359 2351",
    "sg:postcode":"64683",
    "sg:province":"MO",
    "wof:name":"Peyton Amusement & Vending",
    "wof:placetype":"venue"
},
  "geometry": {"coordinates":[-93.614082,40.069129],"type":"Point"}
}