{
  "type": "Feature",
  "properties": {
    "iso:country":"US",
    "sg:address":"204 S Center St",
    "sg:city":"Clarence",
    "sg:classifiers":[
        {
            "category":"Freight",
            "type":"Transportation"
        }
    ],
    "sg:phone":"+1 660 699 8111",
    "sg:postcode":"63437",
    "sg:province":"MO",
    "sg:tags":[
        "livestock",
        "hauling"
    ],
    "wof:name":"Danny Collins Trucking",
    "wof:placetype":"venue"
},
  "geometry": {"coordinates":[-92.261246,39.741429],"type":"Point"}
}