{
  "type": "Feature",
  "properties": {
    "iso:country":"US",
    "sg:address":"802 N Walnut St",
    "sg:city":"Cameron",
    "sg:classifiers":[
        {
            "category":"Personal",
            "subcategory":"Beauty Salon",
            "type":"Services"
        }
    ],
    "sg:phone":"+1 816 632 6449",
    "sg:postcode":"64429",
    "sg:province":"MO",
    "sg:tags":[
        "shop"
    ],
    "wof:name":"P J's Guys & Gals",
    "wof:placetype":"venue"
},
  "geometry": {"coordinates":[-94.235405,39.746866],"type":"Point"}
}