{
  "type": "Feature",
  "properties": {
    "iso:country":"US",
    "sg:address":"2565 N Bluff St",
    "sg:city":"Fulton",
    "sg:classifiers":[
        {
            "category":"Shopping",
            "subcategory":"Florist",
            "type":"Retail Goods"
        }
    ],
    "sg:phone":"+1 573 592 7715",
    "sg:postcode":"65251",
    "sg:province":"MO",
    "wof:name":"Johnson Gardens",
    "wof:placetype":"venue"
},
  "geometry": {"coordinates":[-91.943836,38.867226],"type":"Point"}
}