{
  "type": "Feature",
  "properties": {
    "iso:country":"US",
    "sg:address":"11948 US Hwy 59",
    "sg:city":"Saint Joseph",
    "sg:classifiers":[
        {
            "category":"Building & Trades",
            "subcategory":"Landscaping Services",
            "type":"Services"
        }
    ],
    "sg:phone":"+1 816 688 7907",
    "sg:postcode":"64504",
    "sg:province":"MO",
    "wof:name":"Dowell S Lawn Service",
    "wof:placetype":"venue"
},
  "geometry": {"coordinates":[-94.962295,39.639025],"type":"Point"}
}