{
  "type": "Feature",
  "properties": {
    "iso:country":"US",
    "sg:address":"104 Walnut Dr",
    "sg:city":"Carrollton",
    "sg:classifiers":[
        {
            "category":"Organizations",
            "subcategory":"Community Association",
            "type":"Services"
        }
    ],
    "sg:phone":"+1 660 542 0700",
    "sg:postcode":"64633",
    "sg:province":"MO",
    "sg:tags":[
        "military"
    ],
    "wof:name":"Veterans Of Foreign Wars 1773",
    "wof:placetype":"venue"
},
  "geometry": {"coordinates":[-93.511523,39.360568],"type":"Point"}
}