{
  "type": "Feature",
  "properties": {
    "iso:country":"US",
    "sg:address":"1004 Carondelet Dr W",
    "sg:city":"Kansas City",
    "sg:classifiers":[
        {
            "category":"Banks & Credit Unions",
            "subcategory":"Bank",
            "type":"Services"
        }
    ],
    "sg:phone":"+1 816 860 8360",
    "sg:postcode":"64114",
    "sg:province":"MO",
    "sg:tags":[
        "national",
        "commercial"
    ],
    "wof:name":"U M B Bank N A",
    "wof:placetype":"venue"
},
  "geometry": {"coordinates":[-94.604381,38.935319],"type":"Point"}
}