{
  "type": "Feature",
  "properties": {
    "iso:country":"US",
    "sg:address":"216 US Hwy 60 Bus",
    "sg:city":"Dexter",
    "sg:classifiers":[
        {
            "category":"Manufacturing",
            "subcategory":"Food",
            "type":"Manufacturing & Wholesale Goods"
        }
    ],
    "sg:phone":"+1 573 624 4920",
    "sg:postcode":"63841",
    "sg:province":"MO",
    "sg:tags":[
        "bakery",
        "prod",
        "cookie"
    ],
    "wof:name":"Faye's Pastry Shop",
    "wof:placetype":"venue"
},
  "geometry": {"coordinates":[-89.96166100000001,36.799784],"type":"Point"}
}