{
  "type": "Feature",
  "properties": {
    "iso:country":"US",
    "sg:address":"13254 Co Rd 354",
    "sg:city":"St Joseph",
    "sg:classifiers":[
        {
            "category":"Building & Trades",
            "subcategory":"Construction",
            "type":"Services"
        }
    ],
    "sg:phone":"+1 816 233 6882",
    "sg:postcode":"64505",
    "sg:province":"MO",
    "sg:tags":[
        "downspouts",
        "gutter"
    ],
    "wof:name":"Smith's Seamless Guttering",
    "wof:placetype":"venue"
},
  "geometry": {"coordinates":[-94.79656300000001,39.843169],"type":"Point"}
}