{
  "type": "Feature",
  "properties": {
    "iso:country":"US",
    "sg:address":"3031 S Limit Ave",
    "sg:city":"Sedalia",
    "sg:classifiers":[
        {
            "category":"Government",
            "subcategory":"Police Station",
            "type":"Public Place"
        },
        {
            "category":"Professional",
            "subcategory":"Lawyer & Legal Services",
            "type":"Services"
        }
    ],
    "sg:phone":"+1 660 826 9065",
    "sg:postcode":"65301",
    "sg:province":"MO",
    "sg:tags":[
        "criminal",
        "attorney",
        "accident",
        "personal",
        "automobile",
        "traffic",
        "injury",
        "law"
    ],
    "sg:website":"http://www.sedaliaattorney.com",
    "wof:name":"Christopher J. Spangler",
    "wof:placetype":"venue"
},
  "geometry": {"coordinates":[-93.251186,38.685878],"type":"Point"}
}