{
  "type": "Feature",
  "properties": {
    "iso:country":"US",
    "sg:address":"501 S 2nd St",
    "sg:city":"Piedmont",
    "sg:classifiers":[
        {
            "category":"Home & Garden",
            "subcategory":"Building Materials",
            "type":"Retail Goods"
        }
    ],
    "sg:phone":"+1 573 223 4928",
    "sg:postcode":"63957",
    "sg:province":"MO",
    "sg:tags":[
        "mixed",
        "concrete",
        "concrete-ready"
    ],
    "wof:name":"Duncan Ready-Mixed Concrete",
    "wof:placetype":"venue"
},
  "geometry": {"coordinates":[-90.69921100000001,37.151711],"type":"Point"}
}