{
  "type": "Feature",
  "properties": {
    "iso:country":"US",
    "sg:address":"770 Green Ridge Dr",
    "sg:city":"Catawissa",
    "sg:classifiers":[
        {
            "category":"Professional",
            "type":"Services"
        }
    ],
    "sg:phone":"+1 636 271 7255",
    "sg:postcode":"63015",
    "sg:province":"MO",
    "wof:name":"David Risse",
    "wof:placetype":"venue"
},
  "geometry": {"coordinates":[-90.777185,38.40016],"type":"Point"}
}