{
  "type": "Feature",
  "properties": {
    "iso:country":"US",
    "sg:address":"1340 Lockett Ln",
    "sg:city":"Saint Louis",
    "sg:classifiers":[
        {
            "category":"Building & Trades",
            "subcategory":"Plumbing",
            "type":"Services"
        }
    ],
    "sg:phone":"+1 314 821 2550",
    "sg:postcode":"63122",
    "sg:province":"MO",
    "sg:tags":[
        "contractor"
    ],
    "wof:name":"Marks Plmg & Repr Servic",
    "wof:placetype":"venue"
},
  "geometry": {"coordinates":[-90.43070299999999,38.594081],"type":"Point"}
}