{
  "type": "Feature",
  "properties": {
    "iso:country":"US",
    "sg:address":"3733 Lindell Blvd",
    "sg:city":"Saint Louis",
    "sg:classifiers":[
        {
            "category":"Real Estate",
            "subcategory":"Real Estate Operator",
            "type":"Services"
        }
    ],
    "sg:phone":"+1 314 446 4500",
    "sg:postcode":"63108",
    "sg:province":"MO",
    "sg:tags":[
        "apartment"
    ],
    "wof:name":"Coronado Place",
    "wof:placetype":"venue"
},
  "geometry": {"coordinates":[-90.237846,38.638436],"type":"Point"}
}