{
  "type": "Feature",
  "properties": {
    "addr:full":"9737 Manchester Rd Saint Louis MO 63119",
    "addr:housenumber":"9737",
    "addr:postcode":"63119",
    "addr:street":"Manchester Rd",
    "iso:country":"US",
    "sg:address":"9737 Manchester Rd",
    "sg:city":"Saint Louis",
    "sg:classifiers":[
        {
            "category":"Restaurant",
            "type":"Food & Drink"
        }
    ],
    "sg:menulink":"http://www.allmenus.com/mo/clayton/54965-china-inn/menu/",
    "sg:phone":"+1 314 968 8823",
    "sg:postcode":"63119",
    "sg:province":"MO",
    "sg:tags":[
        "asian",
        "chinese"
    ],
    "wof:name":"China Inn",
    "wof:placetype":"venue"
},
  "geometry": {"coordinates":[-90.370757,38.608006],"type":"Point"}
}