{
  "type": "Feature",
  "properties": {
    "iso:country":"US",
    "sg:address":"406 Commercial St",
    "sg:city":"Cape Girardeau",
    "sg:classifiers":[
        {
            "category":"Retail",
            "subcategory":"Auto Repair",
            "type":"Services"
        }
    ],
    "sg:phone":"+1 573 651 3575",
    "sg:postcode":"63703",
    "sg:province":"MO",
    "sg:tags":[
        "body"
    ],
    "wof:name":"Dewrock Autobody",
    "wof:placetype":"venue"
},
  "geometry": {"coordinates":[-89.55234,37.298289],"type":"Point"}
}