{
  "type": "Feature",
  "properties": {
    "iso:country":"US",
    "sg:address":"105 Jamestown Mall",
    "sg:city":"Florissant",
    "sg:classifiers":[
        {
            "category":"Shopping",
            "subcategory":"Books",
            "type":"Retail Goods"
        }
    ],
    "sg:phone":"+1 314 741 9277",
    "sg:postcode":"63034",
    "sg:province":"MO",
    "sg:tags":[
        "dealer"
    ],
    "wof:name":"Knowing Books & Cafe",
    "wof:placetype":"venue"
},
  "geometry": {"coordinates":[-90.249415,38.821013],"type":"Point"}
}