{
  "type": "Feature",
  "properties": {
    "iso:country":"US",
    "sg:address":"138 S 5th St",
    "sg:city":"Saint Charles",
    "sg:classifiers":[
        {
            "category":"Insurance",
            "subcategory":"Insurance Agent",
            "type":"Services"
        }
    ],
    "sg:phone":"+1 636 949 5999",
    "sg:postcode":"63301",
    "sg:province":"MO",
    "wof:name":"Allstate",
    "wof:placetype":"venue"
},
  "geometry": {"coordinates":[-90.48609500000001,38.782604],"type":"Point"}
}