{
  "type": "Feature",
  "properties": {
    "iso:country":"US",
    "sg:address":"313 E Old Route 66 Ste 22",
    "sg:city":"Strafford",
    "sg:classifiers":[
        {
            "category":"Professional",
            "subcategory":"Computer Services",
            "type":"Services"
        },
        {
            "category":"Wholesale",
            "subcategory":"Computers",
            "type":"Manufacturing & Wholesale Goods"
        }
    ],
    "sg:phone":"+1 209 256 4125",
    "sg:postcode":"65757",
    "sg:province":"MO",
    "sg:tags":[
        "equipment",
        "software"
    ],
    "wof:name":"American E Auctions Inc",
    "wof:placetype":"venue"
},
  "geometry": {"coordinates":[-93.112002,37.269129],"type":"Point"}
}