{
  "type": "Feature",
  "properties": {
    "iso:country":"US",
    "sg:address":"307 W Hudson St",
    "sg:city":"Wellsville",
    "sg:classifiers":[
        {
            "category":"Food & Beverages",
            "subcategory":"Groceries & Convenience Stores",
            "type":"Retail Goods"
        }
    ],
    "sg:phone":"+1 573 684 2812",
    "sg:postcode":"63384",
    "sg:province":"MO",
    "wof:name":"Fastlane Convenience Store",
    "wof:placetype":"venue"
},
  "geometry": {"coordinates":[-91.571586,39.073425],"type":"Point"}
}