{
  "type": "Feature",
  "properties": {
    "iso:country":"US",
    "sg:address":"164 Court St",
    "sg:city":"Marshall",
    "sg:classifiers":[
        {
            "category":"Insurance",
            "subcategory":"Insurance Agent",
            "type":"Services"
        }
    ],
    "sg:phone":"+1 660 886 9694",
    "sg:postcode":"65340",
    "sg:province":"MO",
    "wof:name":"Farmers Insurance Group",
    "wof:placetype":"venue"
},
  "geometry": {"coordinates":[-93.19778700000001,39.120798],"type":"Point"}
}