{
  "type": "Feature",
  "properties": {
    "iso:country":"US",
    "sg:address":"2021 Burlington St",
    "sg:city":"Kansas City",
    "sg:classifiers":[
        {
            "category":"Retail",
            "subcategory":"Auto Repair",
            "type":"Services"
        }
    ],
    "sg:phone":"+1 816 842 2666",
    "sg:postcode":"64116",
    "sg:province":"MO",
    "sg:tags":[
        "transmission",
        "automotive",
        "shop"
    ],
    "wof:name":"Northtown Transmission Service",
    "wof:placetype":"venue"
},
  "geometry": {"coordinates":[-94.580203,39.143631],"type":"Point"}
}