{
  "type": "Feature",
  "properties": {
    "iso:country":"US",
    "sg:address":"5435 S Farm Road 139",
    "sg:city":"Springfield",
    "sg:classifiers":[
        {
            "category":"Insurance",
            "subcategory":"Hazard Insurance",
            "type":"Services"
        }
    ],
    "sg:phone":"+1 417 883 2187",
    "sg:postcode":"65810",
    "sg:province":"MO",
    "wof:name":"David Barrett",
    "wof:placetype":"venue"
},
  "geometry": {"coordinates":[-93.329082,37.115825],"type":"Point"}
}