{
  "type": "Feature",
  "properties": {
    "iso:country":"US",
    "sg:address":"3015 Turkey Creek Rd",
    "sg:city":"Joplin",
    "sg:classifiers":[
        {
            "category":"Autos & Motor Vehicles",
            "subcategory":"Automobile Sales",
            "type":"Retail Goods"
        }
    ],
    "sg:phone":"+1 417 623 5660",
    "sg:postcode":"64801",
    "sg:province":"MO",
    "sg:tags":[
        "car",
        "dealer"
    ],
    "sg:website":"www.joplinford.com",
    "wof:name":"Joplin Ford Lincoln Mercury",
    "wof:placetype":"venue"
},
  "geometry": {"coordinates":[-94.47648700000001,37.093721],"type":"Point"}
}