{
  "type": "Feature",
  "properties": {
    "iso:country":"US",
    "sg:address":"1000 US Hwy 36 Bus",
    "sg:city":"Monroe City",
    "sg:classifiers":[
        {
            "category":"Autos & Motor Vehicles",
            "subcategory":"Auto Supplies",
            "type":"Retail Goods"
        }
    ],
    "sg:phone":"+1 573 735 4795",
    "sg:postcode":"63456",
    "sg:province":"MO",
    "sg:tags":[
        "tire"
    ],
    "wof:name":"Monroe Tire & Battery Inc",
    "wof:placetype":"venue"
},
  "geometry": {"coordinates":[-91.71444700000001,39.662793],"type":"Point"}
}