{
  "type": "Feature",
  "properties": {
    "iso:country":"US",
    "sg:address":"3660 E Sunshine St",
    "sg:city":"Springfield",
    "sg:classifiers":[
        {
            "category":"Shopping",
            "subcategory":"Optical Goods",
            "type":"Retail Goods"
        }
    ],
    "sg:phone":"+1 417 886 8620",
    "sg:postcode":"65809",
    "sg:province":"MO",
    "wof:name":"Sam's Optical",
    "wof:placetype":"venue"
},
  "geometry": {"coordinates":[-93.21817,37.180017],"type":"Point"}
}