{
  "type": "Feature",
  "properties": {
    "iso:country":"US",
    "sg:address":"3212 Sutton Blvd",
    "sg:city":"Saint Louis",
    "sg:classifiers":[
        {
            "category":"Real Estate",
            "subcategory":"Real Estate Operator",
            "type":"Services"
        }
    ],
    "sg:phone":"+1 314 647 1272",
    "sg:postcode":"63143",
    "sg:province":"MO",
    "sg:tags":[
        "building",
        "nonresidential"
    ],
    "wof:name":"American Legion Maplewood",
    "wof:placetype":"venue"
},
  "geometry": {"coordinates":[-90.32098999999999,38.605702],"type":"Point"}
}