{
  "type": "Feature",
  "properties": {
    "iso:country":"US",
    "sg:address":"203 Clinton St",
    "sg:city":"Lathrop",
    "sg:classifiers":[
        {
            "category":"Real Estate",
            "subcategory":"Real Estate Operator",
            "type":"Services"
        }
    ],
    "sg:phone":"+1 816 528 3686",
    "sg:postcode":"64465",
    "sg:province":"MO",
    "sg:tags":[
        "apartment"
    ],
    "wof:name":"Valley View Apartments",
    "wof:placetype":"venue"
},
  "geometry": {"coordinates":[-94.323942,39.546358],"type":"Point"}
}