{
  "type": "Feature",
  "properties": {
    "iso:country":"US",
    "sg:address":"32918 State Highway Pp",
    "sg:city":"Macon",
    "sg:classifiers":[
        {
            "category":"Personal",
            "subcategory":"Beauty Salon",
            "type":"Services"
        }
    ],
    "sg:phone":"+1 660 385 4131",
    "sg:postcode":"63552",
    "sg:province":"MO",
    "wof:name":"Donna's Beauty Shop",
    "wof:placetype":"venue"
},
  "geometry": {"coordinates":[-92.426785,39.722532],"type":"Point"}
}