{
  "type": "Feature",
  "properties": {
    "iso:country":"US",
    "sg:address":"1047 E Gaines Dr",
    "sg:city":"Clinton",
    "sg:classifiers":[
        {
            "category":"Government",
            "subcategory":"Office",
            "type":"Public Place"
        }
    ],
    "sg:phone":"+1 660 885 4022",
    "sg:postcode":"64735",
    "sg:province":"MO",
    "sg:tags":[
        "transportation"
    ],
    "wof:name":"Missouri Dept Hwy & Trnsp",
    "wof:placetype":"venue"
},
  "geometry": {"coordinates":[-93.756793,38.388285],"type":"Point"}
}