{
  "type": "Feature",
  "properties": {
    "iso:country":"US",
    "sg:address":"715 Broadway St",
    "sg:city":"Joplin",
    "sg:classifiers":[
        {
            "category":"Home & Garden",
            "subcategory":"Furniture",
            "type":"Retail Goods"
        }
    ],
    "sg:phone":"+1 417 782 4386",
    "sg:postcode":"64801",
    "sg:province":"MO",
    "wof:name":"One Of A Kind",
    "wof:placetype":"venue"
},
  "geometry": {"coordinates":[-94.50502299999999,37.09195],"type":"Point"}
}