{
  "type": "Feature",
  "properties": {
    "iso:country":"US",
    "sg:address":"546 N Elm Ave",
    "sg:city":"Saint Louis",
    "sg:classifiers":[
        {
            "category":"Real Estate",
            "subcategory":"Real Estate Operator",
            "type":"Services"
        }
    ],
    "sg:phone":"+1 314 968 3511",
    "sg:postcode":"63119",
    "sg:province":"MO",
    "sg:tags":[
        "building",
        "apartment"
    ],
    "wof:name":"Douglass Manor Apartments",
    "wof:placetype":"venue"
},
  "geometry": {"coordinates":[-90.35647,38.602115],"type":"Point"}
}