{
  "type": "Feature",
  "properties": {
    "iso:country":"US",
    "sg:address":"1920 Cass Ave",
    "sg:city":"Saint Louis",
    "sg:classifiers":[
        {
            "category":"Social Services",
            "type":"Services"
        }
    ],
    "sg:phone":"+1 314 621 2166",
    "sg:postcode":"63106",
    "sg:province":"MO",
    "wof:name":"C O V A M",
    "wof:placetype":"venue"
},
  "geometry": {"coordinates":[-90.203636,38.64305],"type":"Point"}
}