{
  "type": "Feature",
  "properties": {
    "iso:country":"US",
    "sg:address":"406 S Ohio Ave",
    "sg:city":"Sedalia",
    "sg:classifiers":[
        {
            "category":"Manufacturing",
            "subcategory":"Printing",
            "type":"Manufacturing & Wholesale Goods"
        }
    ],
    "sg:phone":"+1 660 827 2425",
    "sg:postcode":"65301",
    "sg:province":"MO",
    "sg:tags":[
        "newspaper"
    ],
    "wof:name":"Sedalia News Journal",
    "wof:placetype":"venue"
},
  "geometry": {"coordinates":[-93.228297,38.707711],"type":"Point"}
}