{
  "type": "Feature",
  "properties": {
    "iso:country":"US",
    "sg:address":"354 Major Ter",
    "sg:city":"Holts Summit",
    "sg:classifiers":[
        {
            "category":"Freight",
            "type":"Transportation"
        }
    ],
    "sg:phone":"+1 573 896 5379",
    "sg:postcode":"65043",
    "sg:province":"MO",
    "sg:tags":[
        "operator",
        "local",
        "trucking"
    ],
    "wof:name":"Larry Wolfmeier Trucking LLC",
    "wof:placetype":"venue"
},
  "geometry": {"coordinates":[-92.110685,38.631584],"type":"Point"}
}