{
  "type": "Feature",
  "properties": {
    "iso:country":"US",
    "sg:address":"1212 SW Luttrell Rd",
    "sg:city":"Blue Springs",
    "sg:classifiers":[
        {
            "category":"Insurance",
            "subcategory":"Insurance Agent",
            "type":"Services"
        }
    ],
    "sg:phone":"+1 816 228 6966",
    "sg:postcode":"64015",
    "sg:province":"MO",
    "sg:tags":[
        "co"
    ],
    "wof:name":"Millers Mutual Insurance Assn",
    "wof:placetype":"venue"
},
  "geometry": {"coordinates":[-94.277343,39.006044],"type":"Point"}
}