{
  "type": "Feature",
  "properties": {
    "iso:country":"US",
    "sg:address":"4303 S Providence Rd",
    "sg:city":"Columbia",
    "sg:classifiers":[
        {
            "category":"Professional",
            "subcategory":"Accounting & Tax Preparation",
            "type":"Services"
        }
    ],
    "sg:phone":"+1 573 442 9619",
    "sg:postcode":"65203",
    "sg:province":"MO",
    "sg:tags":[
        "business"
    ],
    "wof:name":"United HRB",
    "wof:placetype":"venue"
},
  "geometry": {"coordinates":[-92.335082,38.903792],"type":"Point"}
}