{
  "type": "Feature",
  "properties": {
    "iso:country":"US",
    "sg:address":"203 E Meadow St",
    "sg:city":"Smithville",
    "sg:classifiers":[
        {
            "category":"Autos & Motor Vehicles",
            "subcategory":"Auto Supplies",
            "type":"Retail Goods"
        }
    ],
    "sg:phone":"+1 816 532 0446",
    "sg:postcode":"64089",
    "sg:province":"MO",
    "sg:tags":[
        "automobile",
        "parts"
    ],
    "wof:name":"Carquest Auto Parts",
    "wof:placetype":"venue"
},
  "geometry": {"coordinates":[-94.57893199999999,39.386201],"type":"Point"}
}