{
  "type": "Feature",
  "properties": {
    "iso:country":"US",
    "sg:address":"5110 N Broadway",
    "sg:city":"Saint Louis",
    "sg:classifiers":[
        {
            "category":"Food & Beverages",
            "subcategory":"Meat & Fish",
            "type":"Retail Goods"
        }
    ],
    "sg:phone":"+1 314 621 0900",
    "sg:postcode":"63147",
    "sg:province":"MO",
    "sg:tags":[
        "shop"
    ],
    "sg:website":"www.savewayfood.com",
    "wof:name":"Saveway Food Co",
    "wof:placetype":"venue"
},
  "geometry": {"coordinates":[-90.207001,38.677502],"type":"Point"}
}