{
  "type": "Feature",
  "properties": {
    "iso:country":"US",
    "sg:address":"RR 1 Box 1530",
    "sg:city":"Doniphan",
    "sg:classifiers":[
        {
            "category":"Home & Garden",
            "subcategory":"Building Materials",
            "type":"Retail Goods"
        },
        {
            "category":"Building & Trades",
            "subcategory":"Construction",
            "type":"Services"
        }
    ],
    "sg:phone":"+1 573 354 2504",
    "sg:postcode":"63935",
    "sg:province":"MO",
    "sg:tags":[
        "concrete",
        "staining",
        "contractor"
    ],
    "wof:name":"David Hinkle Cement Contractor",
    "wof:placetype":"venue"
},
  "geometry": {"coordinates":[-90.807632,36.618374],"type":"Point"}
}