{
  "type": "Feature",
  "properties": {
    "iso:country":"US",
    "sg:address":"111 NW 253rd Rd",
    "sg:city":"Clinton",
    "sg:classifiers":[
        {
            "category":"Professional",
            "subcategory":"Secretarial Services",
            "type":"Services"
        },
        {
            "category":"Professional",
            "subcategory":"Employment Agencies",
            "type":"Services"
        }
    ],
    "sg:phone":"+1 660 885 2489",
    "sg:postcode":"64735",
    "sg:province":"MO",
    "sg:tags":[
        "typing"
    ],
    "wof:name":"Secretarial & Computer Services By Carol",
    "wof:placetype":"venue"
},
  "geometry": {"coordinates":[-93.80408300000001,38.383931],"type":"Point"}
}