{
  "type": "Feature",
  "properties": {
    "iso:country":"US",
    "sg:address":"2531 Hampton Ave",
    "sg:city":"Saint Louis",
    "sg:classifiers":[
        {
            "category":"Banks & Credit Unions",
            "subcategory":"Atm",
            "type":"Services"
        }
    ],
    "sg:phone":"+1 314 351 3878",
    "sg:postcode":"63139",
    "sg:province":"MO",
    "sg:tags":[
        "bankruptcy"
    ],
    "sg:website":"www.stlbankruptcyattorney.com",
    "wof:name":"Affordable Bankruptcy",
    "wof:placetype":"venue"
},
  "geometry": {"coordinates":[-90.28804,38.612927],"type":"Point"}
}