{
  "type": "Feature",
  "properties": {
    "iso:country":"US",
    "sg:address":"199 Lensing Rd",
    "sg:city":"Rhineland",
    "sg:classifiers":[
        {
            "category":"Shopping",
            "subcategory":"Gifts & Souvenirs",
            "type":"Retail Goods"
        }
    ],
    "sg:phone":"+1 573 236 4579",
    "sg:postcode":"65069",
    "sg:province":"MO",
    "sg:tags":[
        "shop"
    ],
    "wof:name":"Special Creations",
    "wof:placetype":"venue"
},
  "geometry": {"coordinates":[-91.56039,38.711069],"type":"Point"}
}