{
  "type": "Feature",
  "properties": {
    "iso:country":"US",
    "sg:address":"1620 Watson St",
    "sg:city":"Saint Charles",
    "sg:classifiers":[
        {
            "category":"Restaurant",
            "type":"Food & Drink"
        }
    ],
    "sg:phone":"+1 636 925 1448",
    "sg:postcode":"63301",
    "sg:province":"MO",
    "sg:tags":[
        "eating"
    ],
    "wof:name":"Lyons Frozen Custard",
    "wof:placetype":"venue"
},
  "geometry": {"coordinates":[-90.496903,38.787432],"type":"Point"}
}