{
  "type": "Feature",
  "properties": {
    "iso:country":"US",
    "sg:address":"478 NW 5th St",
    "sg:city":"Trenton",
    "sg:classifiers":[
        {
            "category":"Personal",
            "subcategory":"Beauty Salon",
            "type":"Services"
        }
    ],
    "sg:phone":"+1 660 485 6600",
    "sg:postcode":"64683",
    "sg:province":"MO",
    "sg:tags":[
        "shop"
    ],
    "wof:name":"Urton Robert & Kelli",
    "wof:placetype":"venue"
},
  "geometry": {"coordinates":[-93.60368099999999,40.13948],"type":"Point"}
}