{
  "type": "Feature",
  "properties": {
    "iso:country":"US",
    "sg:address":"1574 Autumn Leaf Dr",
    "sg:city":"Ballwin",
    "sg:classifiers":[
        {
            "category":"Building & Trades",
            "subcategory":"Construction",
            "type":"Services"
        }
    ],
    "sg:phone":"+1 636 225 0900",
    "sg:postcode":"63021",
    "sg:province":"MO",
    "sg:tags":[
        "fence",
        "contractor"
    ],
    "wof:name":"Rainbow Iron & Fence",
    "wof:placetype":"venue"
},
  "geometry": {"coordinates":[-90.50392600000001,38.562356],"type":"Point"}
}