{
  "type": "Feature",
  "properties": {
    "iso:country":"US",
    "sg:address":"2336 Pohlman Rd",
    "sg:city":"Florissant",
    "sg:classifiers":[
        {
            "category":"Professional",
            "type":"Services"
        }
    ],
    "sg:phone":"+1 314 831 6999",
    "sg:postcode":"63033",
    "sg:province":"MO",
    "wof:name":"Showers of Blessings LLC",
    "wof:placetype":"venue"
},
  "geometry": {"coordinates":[-90.28086,38.783484],"type":"Point"}
}