{
  "type": "Feature",
  "properties": {
    "iso:country":"US",
    "sg:address":"342 E Degraffenreid St",
    "sg:city":"Springfield",
    "sg:classifiers":[
        {
            "category":"Professional",
            "subcategory":"Business Services",
            "type":"Services"
        }
    ],
    "sg:phone":"+1 417 823 3815",
    "sg:postcode":"65810",
    "sg:province":"MO",
    "wof:name":"Schutz Associates Inc",
    "wof:placetype":"venue"
},
  "geometry": {"coordinates":[-93.29308,37.13028],"type":"Point"}
}