{
  "type": "Feature",
  "properties": {
    "iso:country":"US",
    "sg:address":"3502 Bagnell Dam Blvd",
    "sg:city":"Lake Ozark",
    "sg:classifiers":[
        {
            "category":"Autos & Motor Vehicles",
            "subcategory":"Boat Sales",
            "type":"Retail Goods"
        }
    ],
    "sg:phone":"+1 573 365 4144",
    "sg:postcode":"65049",
    "sg:province":"MO",
    "wof:name":"Double Diamond Boat Brokers",
    "wof:placetype":"venue"
},
  "geometry": {"coordinates":[-92.61640300000001,38.175713],"type":"Point"}
}