{
  "type": "Feature",
  "properties": {
    "iso:country":"US",
    "sg:address":"1007 N Douglas St",
    "sg:city":"Malden",
    "sg:classifiers":[
        {
            "category":"Utilities",
            "subcategory":"Mobile Phone",
            "type":"Services"
        }
    ],
    "sg:phone":"+1 573 276 9978",
    "sg:postcode":"63863",
    "sg:province":"MO",
    "sg:tags":[
        "telephone",
        "cellular"
    ],
    "wof:name":"Wireless Retail Inc",
    "wof:placetype":"venue"
},
  "geometry": {"coordinates":[-89.97070600000001,36.569966],"type":"Point"}
}