{
  "type": "Feature",
  "properties": {
    "iso:country":"US",
    "sg:address":"3916 Cora Ave",
    "sg:city":"Saint Louis",
    "sg:classifiers":[
        {
            "category":"Social Services",
            "subcategory":"Child Care",
            "type":"Services"
        }
    ],
    "sg:phone":"+1 314 383 2727",
    "sg:postcode":"63115",
    "sg:province":"MO",
    "sg:tags":[
        "day"
    ],
    "wof:name":"Gomillia's Ann Day/Night Care",
    "wof:placetype":"venue"
},
  "geometry": {"coordinates":[-90.240402,38.673],"type":"Point"}
}