{
  "type": "Feature",
  "properties": {
    "iso:country":"US",
    "sg:address":"2 Buckhammon Pl",
    "sg:city":"St Louis",
    "sg:classifiers":[
        {
            "category":"Wholesale",
            "subcategory":"Apparel",
            "type":"Manufacturing & Wholesale Goods"
        },
        {
            "category":"Professional",
            "subcategory":"Advertising",
            "type":"Services"
        }
    ],
    "sg:phone":"+1 314 991 8116",
    "sg:postcode":"63124",
    "sg:province":"MO",
    "sg:tags":[
        "product",
        "promotional"
    ],
    "wof:name":"Triumph Enterprises LLC",
    "wof:placetype":"venue"
},
  "geometry": {"coordinates":[-90.36832200000001,38.6564],"type":"Point"}
}