{
  "type": "Feature",
  "properties": {
    "iso:country":"US",
    "sg:address":"1101 Myra St",
    "sg:city":"Moberly",
    "sg:classifiers":[
        {
            "category":"Organizations",
            "subcategory":"Religious Organization",
            "type":"Services"
        }
    ],
    "sg:phone":"+1 660 263 6548",
    "sg:postcode":"65270",
    "sg:province":"MO",
    "sg:tags":[
        "church"
    ],
    "wof:name":"West Park United Methodist Ch",
    "wof:placetype":"venue"
},
  "geometry": {"coordinates":[-92.451534,39.425516],"type":"Point"}
}