{
  "type": "Feature",
  "properties": {
    "iso:country":"US",
    "sg:address":"2212 SW Wall St",
    "sg:city":"Blue Springs",
    "sg:classifiers":[
        {
            "category":"Arts & Performance",
            "subcategory":"Theater",
            "type":"Entertainment"
        }
    ],
    "sg:phone":"+1 816 224 8259",
    "sg:postcode":"64015",
    "sg:province":"MO",
    "sg:tags":[
        "group"
    ],
    "wof:name":"Sundowners Country Theather",
    "wof:placetype":"venue"
},
  "geometry": {"coordinates":[-94.29025,38.983709],"type":"Point"}
}