{
  "type": "Feature",
  "properties": {
    "iso:country":"US",
    "sg:address":"2335 Dougherty Ferry Rd",
    "sg:city":"St Louis",
    "sg:classifiers":[
        {
            "category":"Health Services",
            "subcategory":"Doctor",
            "type":"Services"
        }
    ],
    "sg:phone":"+1 314 909 0400",
    "sg:postcode":"63122",
    "sg:province":"MO",
    "sg:tags":[
        "physician",
        "surgeon"
    ],
    "wof:name":"Heartgen",
    "wof:placetype":"venue"
},
  "geometry": {"coordinates":[-90.44786999999999,38.581631],"type":"Point"}
}