{
  "type": "Feature",
  "properties": {
    "iso:country":"US",
    "sg:address":"2849 Gretna Rd",
    "sg:city":"Branson",
    "sg:classifiers":[
        {
            "category":"Restaurant",
            "type":"Food & Drink"
        }
    ],
    "sg:postcode":"65616",
    "sg:province":"MO",
    "sg:tags":[
        "house",
        "steak"
    ],
    "wof:name":"Majestic Steak House",
    "wof:placetype":"venue"
},
  "geometry": {"coordinates":[-93.264757,36.648536],"type":"Point"}
}