{
  "type": "Feature",
  "properties": {
    "iso:country":"US",
    "sg:address":"505 Potosi St",
    "sg:city":"Farmington",
    "sg:classifiers":[
        {
            "category":"Personal",
            "subcategory":"Beauty Salon",
            "type":"Services"
        }
    ],
    "sg:phone":"+1 573 756 5419",
    "sg:postcode":"63640",
    "sg:province":"MO",
    "sg:tags":[
        "shop"
    ],
    "wof:name":"Guys & Gals Resale Shop",
    "wof:placetype":"venue"
},
  "geometry": {"coordinates":[-90.42970800000001,37.787151],"type":"Point"}
}