{
  "type": "Feature",
  "properties": {
    "iso:country":"US",
    "sg:address":"2107 S Willard Ave",
    "sg:city":"Joplin",
    "sg:classifiers":[
        {
            "category":"Organizations",
            "subcategory":"Religious Organization",
            "type":"Services"
        }
    ],
    "sg:phone":"+1 417 623 7828",
    "sg:postcode":"64804",
    "sg:province":"MO",
    "wof:name":"Joplin Heights Baptist Church",
    "wof:placetype":"venue"
},
  "geometry": {"coordinates":[-94.54001,37.06778],"type":"Point"}
}