{
  "type": "Feature",
  "properties": {
    "iso:country":"US",
    "sg:address":"131 Front St",
    "sg:city":"Green Castle",
    "sg:classifiers":[
        {
            "category":"Shopping",
            "subcategory":"Discount & Variety Stores",
            "type":"Retail Goods"
        }
    ],
    "sg:phone":"+1 660 874 4020",
    "sg:postcode":"63544",
    "sg:province":"MO",
    "wof:name":"Second Choice",
    "wof:placetype":"venue"
},
  "geometry": {"coordinates":[-92.881022,40.262151],"type":"Point"}
}