{
  "type": "Feature",
  "properties": {
    "iso:country":"US",
    "sg:address":"8725 Big Bend Blvd",
    "sg:city":"St Louis",
    "sg:classifiers":[
        {
            "category":"Professional",
            "subcategory":"Business Services",
            "type":"Services"
        }
    ],
    "sg:phone":"+1 314 962 4752",
    "sg:postcode":"63119",
    "sg:province":"MO",
    "sg:tags":[
        "appraiser"
    ],
    "wof:name":"Elizabeth M Blagbrough",
    "wof:placetype":"venue"
},
  "geometry": {"coordinates":[-90.359245,38.582635],"type":"Point"}
}