{
  "type": "Feature",
  "properties": {
    "iso:country":"US",
    "sg:address":"21216 Jesse James Farm Rd",
    "sg:city":"Kearney",
    "sg:classifiers":[
        {
            "category":"Government",
            "subcategory":"Office",
            "type":"Public Place"
        },
        {
            "category":"Museum",
            "type":"Entertainment"
        }
    ],
    "sg:phone":"+1 816 628 6065",
    "sg:postcode":"64060",
    "sg:province":"MO",
    "sg:tags":[
        "village"
    ],
    "wof:name":"Jesse James Farm & Museum",
    "wof:placetype":"venue"
},
  "geometry": {"coordinates":[-94.329916,39.389946],"type":"Point"}
}