{
  "type": "Feature",
  "properties": {
    "iso:country":"US",
    "sg:address":"301 N Main St",
    "sg:city":"Paris",
    "sg:classifiers":[
        {
            "category":"Banks & Credit Unions",
            "subcategory":"Bank",
            "type":"Services"
        }
    ],
    "sg:phone":"+1 660 327 4175",
    "sg:postcode":"65275",
    "sg:province":"MO",
    "sg:tags":[
        "saving",
        "commercial"
    ],
    "sg:website":"http://www.umb.com",
    "wof:name":"Umb Financial Corp",
    "wof:placetype":"venue"
},
  "geometry": {"coordinates":[-92.00009799999999,39.484957],"type":"Point"}
}