{
  "type": "Feature",
  "properties": {
    "iso:country":"US",
    "sg:address":"413 Hanley Industrial Ct",
    "sg:city":"St Louis",
    "sg:classifiers":[
        {
            "category":"Shopping",
            "type":"Retail Goods"
        }
    ],
    "sg:phone":"+1 314 727 6249",
    "sg:postcode":"63144",
    "sg:province":"MO",
    "sg:tags":[
        "art",
        "gallery",
        "merchandise",
        "dealer"
    ],
    "wof:name":"Productive Living",
    "wof:placetype":"venue"
},
  "geometry": {"coordinates":[-90.33738200000001,38.618824],"type":"Point"}
}