{
  "type": "Feature",
  "properties": {
    "iso:country":"US",
    "sg:address":"9132 Hwy Bb",
    "sg:city":"Hillsboro",
    "sg:classifiers":[
        {
            "category":"Retail",
            "subcategory":"Auto Repair",
            "type":"Services"
        }
    ],
    "sg:phone":"+1 636 285 4311",
    "sg:postcode":"63050",
    "sg:province":"MO",
    "sg:tags":[
        "body",
        "automobile",
        "restoration",
        "classic"
    ],
    "wof:name":"Stick's Chevy Shed",
    "wof:placetype":"venue"
},
  "geometry": {"coordinates":[-90.596782,38.287233],"type":"Point"}
}