{
  "type": "Feature",
  "properties": {
    "iso:country":"US",
    "sg:address":"6903 Blue Ridge Blvd",
    "sg:city":"Raytown",
    "sg:classifiers":[
        {
            "category":"Food & Beverages",
            "subcategory":"Groceries & Convenience Stores",
            "type":"Retail Goods"
        }
    ],
    "sg:phone":"+1 816 358 8262",
    "sg:postcode":"64133",
    "sg:province":"MO",
    "sg:website":"http://www.circlek.com",
    "wof:name":"Circle K",
    "wof:placetype":"venue"
},
  "geometry": {"coordinates":[-94.482438,38.998828],"type":"Point"}
}