{
  "type": "Feature",
  "properties": {
    "addr:full":"2311 W Main St Sedalia MO 65301",
    "addr:housenumber":"2311",
    "addr:postcode":"65301",
    "addr:street":"W Main St",
    "iso:country":"US",
    "sg:address":"2311 W Main St",
    "sg:city":"Sedalia",
    "sg:classifiers":[
        {
            "category":"Social Services",
            "type":"Services"
        }
    ],
    "sg:phone":"+1 660 826 5039",
    "sg:postcode":"65301",
    "sg:province":"MO",
    "sg:tags":[
        "organization",
        "welfare"
    ],
    "wof:name":"Meals On Wheels",
    "wof:placetype":"venue"
},
  "geometry": {"coordinates":[-93.258509,38.713875],"type":"Point"}
}