{
  "type": "Feature",
  "properties": {
    "iso:country":"US",
    "sg:address":"1311 N Morley St",
    "sg:city":"Moberly",
    "sg:classifiers":[
        {
            "category":"Home & Garden",
            "subcategory":"Household Appliances",
            "type":"Retail Goods"
        }
    ],
    "sg:phone":"+1 660 263 4252",
    "sg:postcode":"65270",
    "sg:province":"MO",
    "sg:tags":[
        "repair",
        "electrical"
    ],
    "wof:name":"Action Maytag HM Appl Sls Ser",
    "wof:placetype":"venue"
},
  "geometry": {"coordinates":[-92.433207,39.432521],"type":"Point"}
}