{
  "type": "Feature",
  "properties": {
    "iso:country":"US",
    "sg:address":"911 Walnut St",
    "sg:city":"Kansas City",
    "sg:classifiers":[
        {
            "category":"Government",
            "subcategory":"Office",
            "type":"Public Place"
        }
    ],
    "sg:phone":"+1 816 426 7763",
    "sg:postcode":"64106",
    "sg:province":"MO",
    "wof:name":"US Inspector General",
    "wof:placetype":"venue"
},
  "geometry": {"coordinates":[-94.581883,39.102406],"type":"Point"}
}