{
  "type": "Feature",
  "properties": {
    "iso:country":"US",
    "sg:address":"8630 Delmar Blvd",
    "sg:city":"Saint Louis",
    "sg:classifiers":[
        {
            "category":"Health Services",
            "subcategory":"Doctor",
            "type":"Services"
        }
    ],
    "sg:phone":"+1 636 936 1704",
    "sg:postcode":"63124",
    "sg:province":"MO",
    "sg:tags":[
        "medical"
    ],
    "wof:name":"Jonathan Bortz Dr",
    "wof:placetype":"venue"
},
  "geometry": {"coordinates":[-90.35900599999999,38.660761],"type":"Point"}
}