{
  "type": "Feature",
  "properties": {
    "iso:country":"US",
    "sg:address":"219 W 4th St",
    "sg:city":"Salem",
    "sg:classifiers":[
        {
            "category":"Sports & Exercise",
            "subcategory":"Gym",
            "type":"Entertainment"
        },
        {
            "category":"Arena",
            "subcategory":"Sports Club",
            "type":"Entertainment"
        }
    ],
    "sg:phone":"+1 573 729 0010",
    "sg:postcode":"65560",
    "sg:province":"MO",
    "sg:tags":[
        "health",
        "gymnasium"
    ],
    "wof:name":"Purefitness",
    "wof:placetype":"venue"
},
  "geometry": {"coordinates":[-91.537552,37.645448],"type":"Point"}
}