{
  "type": "Feature",
  "properties": {
    "iso:country":"US",
    "sg:address":"2576 Lisa Dr",
    "sg:city":"Cape Girardeau",
    "sg:classifiers":[
        {
            "category":"Professional",
            "subcategory":"Business Services",
            "type":"Services"
        }
    ],
    "sg:phone":"+1 573 339 1177",
    "sg:postcode":"63701",
    "sg:province":"MO",
    "wof:name":"McMeel Enterprises",
    "wof:placetype":"venue"
},
  "geometry": {"coordinates":[-89.557633,37.334861],"type":"Point"}
}