{
  "type": "Feature",
  "properties": {
    "iso:country":"US",
    "sg:address":"122 State Hwy 13",
    "sg:city":"Warrensburg",
    "sg:classifiers":[
        {
            "category":"Retail",
            "subcategory":"Auto Repair",
            "type":"Services"
        }
    ],
    "sg:phone":"+1 660 429 5885",
    "sg:postcode":"64093",
    "sg:province":"MO",
    "sg:tags":[
        "body",
        "automobile",
        "painting"
    ],
    "wof:name":"Rick's Classic Car Rustoration",
    "wof:placetype":"venue"
},
  "geometry": {"coordinates":[-93.735758,38.762495],"type":"Point"}
}