{
  "type": "Feature",
  "properties": {
    "iso:country":"US",
    "sg:address":"7884 Co Rd 717",
    "sg:city":"Dexter",
    "sg:classifiers":[
        {
            "category":"Retail",
            "subcategory":"Auto Repair",
            "type":"Services"
        }
    ],
    "sg:phone":"+1 573 624 2226",
    "sg:postcode":"63841",
    "sg:province":"MO",
    "sg:tags":[
        "body",
        "automobile",
        "painting"
    ],
    "wof:name":"Parkview Auto Body Repair",
    "wof:placetype":"venue"
},
  "geometry": {"coordinates":[-89.93509299999999,36.729935],"type":"Point"}
}