{
  "type": "Feature",
  "properties": {
    "iso:country":"US",
    "sg:address":"10904 NW Walnut Creek Dr",
    "sg:city":"Kansas City",
    "sg:classifiers":[
        {
            "category":"Professional",
            "type":"Services"
        }
    ],
    "sg:phone":"+1 816 587 0758",
    "sg:postcode":"64152",
    "sg:province":"MO",
    "wof:name":"Frank Simmer",
    "wof:placetype":"venue"
},
  "geometry": {"coordinates":[-94.70774,39.201139],"type":"Point"}
}