{
  "type": "Feature",
  "properties": {
    "iso:country":"US",
    "sg:address":"299 Mid Rivers Mall Dr",
    "sg:city":"St Peters",
    "sg:classifiers":[
        {
            "category":"Restaurant",
            "type":"Food & Drink"
        }
    ],
    "sg:phone":"+1 636 970 2675",
    "sg:postcode":"63376",
    "sg:province":"MO",
    "wof:name":"Mc Donald's",
    "wof:placetype":"venue"
},
  "geometry": {"coordinates":[-90.62438,38.79199],"type":"Point"}
}