{
  "type": "Feature",
  "properties": {
    "iso:country":"US",
    "sg:address":"1368 Raycrest Ln",
    "sg:city":"Saint Louis",
    "sg:classifiers":[
        {
            "category":"Farming",
            "subcategory":"Farm",
            "type":"Manufacturing & Wholesale Goods"
        }
    ],
    "sg:phone":"+1 314 966 0616",
    "sg:postcode":"63126",
    "sg:province":"MO",
    "sg:tags":[
        "crop",
        "general"
    ],
    "wof:name":"Marvin L Smith Farms",
    "wof:placetype":"venue"
},
  "geometry": {"coordinates":[-90.389353,38.56128],"type":"Point"}
}