{
  "type": "Feature",
  "properties": {
    "iso:country":"US",
    "sg:address":"201 W 9th St",
    "sg:city":"Cassville",
    "sg:classifiers":[
        {
            "category":"Professional",
            "subcategory":"Lawyer & Legal Services",
            "type":"Services"
        }
    ],
    "sg:phone":"+1 417 847 4144",
    "sg:postcode":"65625",
    "sg:province":"MO",
    "sg:tags":[
        "attorney"
    ],
    "wof:name":"Melton & Herrin",
    "wof:placetype":"venue"
},
  "geometry": {"coordinates":[-93.868298,36.680014],"type":"Point"}
}