{
  "type": "Feature",
  "properties": {
    "iso:country":"US",
    "sg:address":"2925 N Florissant Ave",
    "sg:city":"St Louis",
    "sg:classifiers":[
        {
            "category":"Retail",
            "subcategory":"Auto Repair",
            "type":"Services"
        }
    ],
    "sg:phone":"+1 314 588 7902",
    "sg:postcode":"63107",
    "sg:province":"MO",
    "sg:tags":[
        "repairing",
        "automobile"
    ],
    "wof:name":"Scott's Auto Shop",
    "wof:placetype":"venue"
},
  "geometry": {"coordinates":[-90.200858,38.652077],"type":"Point"}
}