{
  "type": "Feature",
  "properties": {
    "iso:country":"US",
    "sg:address":"1223 Woods Station Pl",
    "sg:city":"Ballwin",
    "sg:classifiers":[
        {
            "category":"Professional",
            "type":"Services"
        }
    ],
    "sg:phone":"+1 636 529 0635",
    "sg:postcode":"63021",
    "sg:province":"MO",
    "wof:name":"St Louis Leveling Inc",
    "wof:placetype":"venue"
},
  "geometry": {"coordinates":[-90.497294,38.572299],"type":"Point"}
}