{
  "type": "Feature",
  "properties": {
    "iso:country":"US",
    "sg:address":"1710 Old Airport Rd",
    "sg:city":"West Plains",
    "sg:classifiers":[
        {
            "category":"Government",
            "subcategory":"Office",
            "type":"Public Place"
        }
    ],
    "sg:phone":"+1 417 255 0764",
    "sg:postcode":"65775",
    "sg:province":"MO",
    "sg:tags":[
        "village"
    ],
    "wof:name":"West Plains Generator Plant",
    "wof:placetype":"venue"
},
  "geometry": {"coordinates":[-91.865854,36.747202],"type":"Point"}
}