{
  "type": "Feature",
  "properties": {
    "iso:country":"US",
    "sg:address":"8 S Sarah St",
    "sg:city":"Saint Louis",
    "sg:classifiers":[
        {
            "category":"Bars & Pubs",
            "type":"Food & Drink"
        }
    ],
    "sg:phone":"+1 314 535 0551",
    "sg:postcode":"63108",
    "sg:province":"MO",
    "sg:tags":[
        "gastropubs"
    ],
    "sg:website":"www.thescottisharms.com",
    "wof:name":"The Scottish Arms",
    "wof:placetype":"venue"
},
  "geometry": {"coordinates":[-90.24678299999999,38.637084],"type":"Point"}
}