{
  "type": "Feature",
  "properties": {
    "iso:country":"US",
    "sg:address":"4620 Mexico Rd",
    "sg:city":"St Peters",
    "sg:classifiers":[
        {
            "category":"Insurance",
            "subcategory":"Title Insurance",
            "type":"Services"
        },
        {
            "category":"Real Estate",
            "subcategory":"Real Estate Services",
            "type":"Services"
        }
    ],
    "sg:phone":"+1 636 916 3388",
    "sg:postcode":"63376",
    "sg:province":"MO",
    "sg:tags":[
        "company",
        "carrier"
    ],
    "wof:name":"Cave Springs Title LLC",
    "wof:placetype":"venue"
},
  "geometry": {"coordinates":[-90.58087999999999,38.792048],"type":"Point"}
}