{
  "type": "Feature",
  "properties": {
    "iso:country":"US",
    "sg:address":"428 Lantana Ln",
    "sg:city":"Saint Peters",
    "sg:classifiers":[
        {
            "category":"Professional",
            "type":"Services"
        }
    ],
    "sg:phone":"+1 636 939 0573",
    "sg:postcode":"63376",
    "sg:province":"MO",
    "wof:name":"Tevlin Consumer Products",
    "wof:placetype":"venue"
},
  "geometry": {"coordinates":[-90.585797,38.786777],"type":"Point"}
}