{
  "type": "Feature",
  "properties": {
    "iso:country":"US",
    "sg:address":"2509 Stark Ave",
    "sg:city":"Kansas City",
    "sg:classifiers":[
        {
            "category":"Building & Trades",
            "subcategory":"Landscaping Services",
            "type":"Services"
        }
    ],
    "sg:phone":"+1 816 252 3624",
    "sg:postcode":"64129",
    "sg:province":"MO",
    "sg:tags":[
        "lawn",
        "maintenance",
        "grounds"
    ],
    "wof:name":"J & J Griffin Inc",
    "wof:placetype":"venue"
},
  "geometry": {"coordinates":[-94.47880000000001,39.079347],"type":"Point"}
}