{
  "type": "Feature",
  "properties": {
    "iso:country":"US",
    "sg:address":"4580 Gibson Ave",
    "sg:city":"St Louis",
    "sg:classifiers":[
        {
            "category":"Social Services",
            "subcategory":"Child Care",
            "type":"Services"
        }
    ],
    "sg:phone":"+1 314 289 7524",
    "sg:postcode":"63110",
    "sg:province":"MO",
    "wof:name":"Robin's Nest Of Love",
    "wof:placetype":"venue"
},
  "geometry": {"coordinates":[-90.261128,38.629511],"type":"Point"}
}