{
  "type": "Feature",
  "properties": {
    "iso:country":"US",
    "sg:address":"724 Homestead Dr",
    "sg:city":"Moberly",
    "sg:classifiers":[
        {
            "category":"Building & Trades",
            "subcategory":"Construction",
            "type":"Services"
        },
        {
            "category":"Utilities",
            "type":"Services"
        }
    ],
    "sg:phone":"+1 660 263 1286",
    "sg:postcode":"65270",
    "sg:province":"MO",
    "sg:tags":[
        "excavation",
        "dredging-services",
        "contractor"
    ],
    "wof:name":"Crawford Bulldozing",
    "wof:placetype":"venue"
},
  "geometry": {"coordinates":[-92.447778,39.405234],"type":"Point"}
}