{
  "type": "Feature",
  "properties": {
    "iso:country":"US",
    "sg:address":"630 Belson Ct",
    "sg:city":"Saint Louis",
    "sg:classifiers":[
        {
            "category":"Real Estate",
            "subcategory":"Real Estate Operator",
            "type":"Services"
        }
    ],
    "sg:phone":"+1 314 822 9693",
    "sg:postcode":"63122",
    "sg:province":"MO",
    "sg:tags":[
        "building",
        "apartment"
    ],
    "wof:name":"Conway Development",
    "wof:placetype":"venue"
},
  "geometry": {"coordinates":[-90.392032,38.595461],"type":"Point"}
}