{
  "type": "Feature",
  "properties": {
    "iso:country":"US",
    "sg:address":"2509 NE Independence Ave",
    "sg:city":"Lees Summit",
    "sg:classifiers":[
        {
            "category":"Retail",
            "subcategory":"Auto Repair",
            "type":"Services"
        }
    ],
    "sg:phone":"+1 816 524 3330",
    "sg:postcode":"64064",
    "sg:province":"MO",
    "sg:tags":[
        "body"
    ],
    "wof:name":"Summit Auto Body Carstar",
    "wof:placetype":"venue"
},
  "geometry": {"coordinates":[-94.361701,38.958882],"type":"Point"}
}