{
  "type": "Feature",
  "properties": {
    "addr:full":"621 N Morley St Moberly MO 65270",
    "addr:housenumber":"621",
    "addr:postcode":"65270",
    "addr:street":"N Morley St",
    "iso:country":"US",
    "sg:address":"621 N Morley St",
    "sg:city":"Moberly",
    "sg:classifiers":[
        {
            "category":"Autos & Motor Vehicles",
            "subcategory":"Auto Supplies",
            "type":"Retail Goods"
        }
    ],
    "sg:phone":"+1 660 263 8636",
    "sg:postcode":"65270",
    "sg:province":"MO",
    "sg:tags":[
        "parts",
        "accessory"
    ],
    "sg:website":"www.autozone.com",
    "wof:name":"Autozone",
    "wof:placetype":"venue"
},
  "geometry": {"coordinates":[-92.43343299999999,39.425578],"type":"Point"}
}