{
  "type": "Feature",
  "properties": {
    "iso:country":"US",
    "sg:address":"551 W Karsch Blvd",
    "sg:city":"Farmington",
    "sg:classifiers":[
        {
            "category":"Restaurant",
            "type":"Food & Drink"
        }
    ],
    "sg:menulink":"http://www.allmenus.com/mo/st-francois/80594-papa-johns-pizza/menu/",
    "sg:phone":"+1 573 756 4777",
    "sg:postcode":"63640",
    "sg:province":"MO",
    "sg:tags":[
        "american",
        "pizza"
    ],
    "wof:name":"Papa John's Pizza",
    "wof:placetype":"venue"
},
  "geometry": {"coordinates":[-90.432085,37.790383],"type":"Point"}
}