{
  "type": "Feature",
  "properties": {
    "iso:country":"US",
    "sg:address":"733 Poplar St",
    "sg:city":"Poplar Bluff",
    "sg:classifiers":[
        {
            "category":"Professional",
            "subcategory":"Art Services",
            "type":"Services"
        }
    ],
    "sg:phone":"+1 573 686 4779",
    "sg:postcode":"63901",
    "sg:province":"MO",
    "sg:tags":[
        "photographer"
    ],
    "wof:name":"A J's Photography",
    "wof:placetype":"venue"
},
  "geometry": {"coordinates":[-90.39973000000001,36.756706],"type":"Point"}
}