{
  "type": "Feature",
  "properties": {
    "iso:country":"US",
    "sg:address":"5024 Griffin Rd",
    "sg:city":"Sappington",
    "sg:classifiers":[
        {
            "category":"Professional",
            "subcategory":"Lawyer & Legal Services",
            "type":"Services"
        }
    ],
    "sg:phone":"+1 314 849 5955",
    "sg:postcode":"63128",
    "sg:province":"MO",
    "sg:tags":[
        "attorney"
    ],
    "wof:name":"Paul A Grana",
    "wof:placetype":"venue"
},
  "geometry": {"coordinates":[-90.38250600000001,38.490648],"type":"Point"}
}