{
  "type": "Feature",
  "properties": {
    "iso:country":"US",
    "sg:address":"11040 County Road 568",
    "sg:city":"Senath",
    "sg:classifiers":[
        {
            "category":"Retail",
            "subcategory":"Repair Shop",
            "type":"Services"
        },
        {
            "category":"Professional",
            "subcategory":"Detective & Security Services",
            "type":"Services"
        }
    ],
    "sg:phone":"+1 573 738 2382",
    "sg:postcode":"63876",
    "sg:province":"MO",
    "sg:tags":[
        "skip",
        "tracing",
        "bail",
        "bond"
    ],
    "wof:name":"Walker Bail Bonds",
    "wof:placetype":"venue"
},
  "geometry": {"coordinates":[-90.195553,36.104812],"type":"Point"}
}