{
  "type": "Feature",
  "properties": {
    "iso:country":"US",
    "sg:address":"209 S Woods Mill Rd Apt 2",
    "sg:city":"Chesterfield",
    "sg:classifiers":[
        {
            "category":"Professional",
            "subcategory":"Management & Consulting",
            "type":"Services"
        },
        {
            "category":"Manufacturing",
            "subcategory":"Food",
            "type":"Manufacturing & Wholesale Goods"
        },
        {
            "category":"Farming",
            "subcategory":"Farm",
            "type":"Manufacturing & Wholesale Goods"
        }
    ],
    "sg:phone":"+1 314 317 9273",
    "sg:postcode":"63017",
    "sg:province":"MO",
    "sg:tags":[
        "product",
        "corn"
    ],
    "wof:name":"Orville Bryan",
    "wof:placetype":"venue"
},
  "geometry": {"coordinates":[-90.507805,38.652945],"type":"Point"}
}