{
  "type": "Feature",
  "properties": {
    "iso:country":"US",
    "sg:address":"301 Main St",
    "sg:city":"Purcell",
    "sg:classifiers":[
        {
            "category":"Government",
            "subcategory":"Office",
            "type":"Public Place"
        }
    ],
    "sg:phone":"+1 417 525 4847",
    "sg:postcode":"64857",
    "sg:province":"MO",
    "sg:tags":[
        "village"
    ],
    "wof:name":"City Of Purcell",
    "wof:placetype":"venue"
},
  "geometry": {"coordinates":[-94.43567400000001,37.242444],"type":"Point"}
}