{
  "type": "Feature",
  "properties": {
    "iso:country":"US",
    "sg:address":"9418 Eastchester Dr",
    "sg:city":"Saint Louis",
    "sg:classifiers":[
        {
            "category":"Banks & Credit Unions",
            "subcategory":"Investment Brokerage",
            "type":"Services"
        }
    ],
    "sg:phone":"+1 314 867 5565",
    "sg:postcode":"63136",
    "sg:province":"MO",
    "sg:tags":[
        "preparation",
        "tax",
        "security",
        "return"
    ],
    "wof:name":"Halls Tax Service",
    "wof:placetype":"venue"
},
  "geometry": {"coordinates":[-90.24221900000001,38.731227],"type":"Point"}
}