{
  "type": "Feature",
  "properties": {
    "iso:country":"US",
    "sg:address":"45740 Shiel Ln",
    "sg:city":"Monroe City",
    "sg:classifiers":[
        {
            "category":"Farming",
            "subcategory":"Livestock Farm",
            "type":"Manufacturing & Wholesale Goods"
        }
    ],
    "sg:phone":"+1 573 735 4084",
    "sg:postcode":"63456",
    "sg:province":"MO",
    "sg:tags":[
        "hog",
        "or",
        "feedlot"
    ],
    "wof:name":"N Williams",
    "wof:placetype":"venue"
},
  "geometry": {"coordinates":[-91.600859,39.634573],"type":"Point"}
}