{
  "type": "Feature",
  "properties": {
    "iso:country":"US",
    "sg:address":"4630 J C Nichols Pkwy",
    "sg:city":"Kansas City",
    "sg:classifiers":[
        {
            "category":"Food & Beverages",
            "subcategory":"Liquor & Beverages",
            "type":"Retail Goods"
        }
    ],
    "sg:phone":"+1 816 753 9463",
    "sg:postcode":"64112",
    "sg:province":"MO",
    "sg:tags":[
        "wine"
    ],
    "wof:name":"Connoisseur",
    "wof:placetype":"venue"
},
  "geometry": {"coordinates":[-94.58823599999999,39.043022],"type":"Point"}
}