{
  "type": "Feature",
  "properties": {
    "iso:country":"US",
    "sg:address":"412 N Lincoln St",
    "sg:city":"Neosho",
    "sg:classifiers":[
        {
            "category":"Personal",
            "subcategory":"Beauty Salon",
            "type":"Services"
        }
    ],
    "sg:phone":"+1 417 451 9282",
    "sg:postcode":"64850",
    "sg:province":"MO",
    "sg:tags":[
        "shop"
    ],
    "wof:name":"Exsalonce",
    "wof:placetype":"venue"
},
  "geometry": {"coordinates":[-94.375426,36.873097],"type":"Point"}
}