{
  "type": "Feature",
  "properties": {
    "iso:country":"US",
    "sg:address":"515 Walnut St",
    "sg:city":"Cabool",
    "sg:classifiers":[
        {
            "category":"Personal",
            "subcategory":"Beauty Salon",
            "type":"Services"
        }
    ],
    "sg:phone":"+1 417 962 3510",
    "sg:postcode":"65689",
    "sg:province":"MO",
    "wof:name":"The Country Vogue Beauty Salon",
    "wof:placetype":"venue"
},
  "geometry": {"coordinates":[-92.097805,37.124674],"type":"Point"}
}