{
  "type": "Feature",
  "properties": {
    "iso:country":"US",
    "sg:address":"40544 State Hwy Y",
    "sg:city":"Graham",
    "sg:classifiers":[
        {
            "category":"Professional",
            "type":"Services"
        }
    ],
    "sg:phone":"+1 660 939 4440",
    "sg:postcode":"64455",
    "sg:province":"MO",
    "sg:tags":[
        "farm",
        "supply"
    ],
    "wof:name":"County Line AG Services LLC",
    "wof:placetype":"venue"
},
  "geometry": {"coordinates":[-95.022244,40.136376],"type":"Point"}
}