{
  "type": "Feature",
  "properties": {
    "iso:country":"US",
    "sg:address":"2180 N US-67",
    "sg:city":"Florissant",
    "sg:classifiers":[
        {
            "category":"Restaurant",
            "type":"Food & Drink"
        }
    ],
    "sg:menulink":"http://www.allmenus.com/mo/florissant/35906-bob-evans/menu/",
    "sg:phone":"+1 314 921 5440",
    "sg:postcode":"63033",
    "sg:province":"MO",
    "sg:tags":[
        "american"
    ],
    "wof:name":"Bob Evans",
    "wof:placetype":"venue"
},
  "geometry": {"coordinates":[-90.31196300000001,38.802217],"type":"Point"}
}