{
  "type": "Feature",
  "properties": {
    "iso:country":"US",
    "sg:address":"1715 Deer Tracks Trl",
    "sg:city":"St Louis",
    "sg:classifiers":[
        {
            "category":"Professional",
            "subcategory":"Management & Consulting",
            "type":"Services"
        }
    ],
    "sg:phone":"+1 314 821 5600",
    "sg:postcode":"63131",
    "sg:province":"MO",
    "sg:tags":[
        "medical",
        "administration",
        "business"
    ],
    "wof:name":"Medaphis Physician Svc",
    "wof:placetype":"venue"
},
  "geometry": {"coordinates":[-90.45320100000001,38.608814],"type":"Point"}
}