{
  "type": "Feature",
  "properties": {
    "iso:country":"US",
    "sg:address":"19131 Nolker Rd",
    "sg:city":"Rayville",
    "sg:classifiers":[
        {
            "category":"Professional",
            "type":"Services"
        }
    ],
    "sg:phone":"+1 816 580 3584",
    "sg:postcode":"64084",
    "sg:province":"MO",
    "wof:name":"Ej S Services",
    "wof:placetype":"venue"
},
  "geometry": {"coordinates":[-94.060191,39.434022],"type":"Point"}
}