{
  "type": "Feature",
  "properties": {
    "iso:country":"US",
    "sg:address":"3101 Mercier St",
    "sg:city":"Kansas City",
    "sg:classifiers":[
        {
            "category":"Freight",
            "type":"Transportation"
        }
    ],
    "sg:phone":"+1 816 716 3344",
    "sg:postcode":"64111",
    "sg:province":"MO",
    "sg:tags":[
        "operator",
        "local",
        "trucking"
    ],
    "wof:name":"Jere Wilson Moving",
    "wof:placetype":"venue"
},
  "geometry": {"coordinates":[-94.600033,39.0714],"type":"Point"}
}