{
  "type": "Feature",
  "properties": {
    "addr:full":"9816 E 87th St Kansas City MO 64138",
    "addr:housenumber":"9816",
    "addr:postcode":"64138",
    "addr:street":"E 87Th St",
    "iso:country":"US",
    "sg:address":"9816 E 87th St",
    "sg:city":"Kansas City",
    "sg:classifiers":[
        {
            "category":"Insurance",
            "subcategory":"Insurance Agent",
            "type":"Services"
        }
    ],
    "sg:phone":"+1 816 358 7800",
    "sg:postcode":"64138",
    "sg:province":"MO",
    "sg:tags":[
        "agency"
    ],
    "wof:name":"State Farm Insurance",
    "wof:placetype":"venue"
},
  "geometry": {"coordinates":[-94.466461,38.96528],"type":"Point"}
}