{
  "type": "Feature",
  "properties": {
    "iso:country":"US",
    "sg:address":"1550 E Battlefield Rd",
    "sg:city":"Springfield",
    "sg:classifiers":[
        {
            "category":"Shopping",
            "subcategory":"Jewelry",
            "type":"Retail Goods"
        }
    ],
    "sg:phone":"+1 417 823 8628",
    "sg:postcode":"65804",
    "sg:province":"MO",
    "sg:tags":[
        "jeweler"
    ],
    "wof:name":"Crest Jewelers Inc",
    "wof:placetype":"venue"
},
  "geometry": {"coordinates":[-93.26536900000001,37.159354],"type":"Point"}
}