{
  "type": "Feature",
  "properties": {
    "iso:country":"US",
    "sg:address":"6767 Southwest Ave",
    "sg:city":"Saint Louis",
    "sg:classifiers":[
        {
            "category":"Building & Trades",
            "subcategory":"Construction",
            "type":"Services"
        }
    ],
    "sg:phone":"+1 314 531 5207",
    "sg:postcode":"63143",
    "sg:province":"MO",
    "sg:tags":[
        "contractor"
    ],
    "wof:name":"B S I Construction",
    "wof:placetype":"venue"
},
  "geometry": {"coordinates":[-90.304896,38.613375],"type":"Point"}
}