{
  "type": "Feature",
  "properties": {
    "iso:country":"US",
    "sg:address":"1105 Independence St",
    "sg:city":"Cape Girardeau",
    "sg:classifiers":[
        {
            "category":"Autos & Motor Vehicles",
            "subcategory":"Automobile Sales",
            "type":"Retail Goods"
        }
    ],
    "sg:phone":"+1 573 335 2215",
    "sg:postcode":"63703",
    "sg:province":"MO",
    "sg:tags":[
        "used"
    ],
    "wof:name":"Cape United Auto Inc",
    "wof:placetype":"venue"
},
  "geometry": {"coordinates":[-89.533796,37.304835],"type":"Point"}
}