{
  "type": "Feature",
  "properties": {
    "iso:country":"US",
    "sg:address":"1972 Ridge Lake Dr",
    "sg:city":"Chesterfield",
    "sg:classifiers":[
        {
            "category":"Wholesale",
            "subcategory":"Jewelry",
            "type":"Manufacturing & Wholesale Goods"
        }
    ],
    "sg:phone":"+1 636 532 8220",
    "sg:postcode":"63017",
    "sg:province":"MO",
    "sg:tags":[
        "distributor",
        "watch"
    ],
    "sg:website":"www.falconwatch.com",
    "wof:name":"Falcon Watch Co",
    "wof:placetype":"venue"
},
  "geometry": {"coordinates":[-90.54881399999999,38.635192],"type":"Point"}
}