{
  "type": "Feature",
  "properties": {
    "iso:country":"US",
    "sg:address":"7809 E 171st St",
    "sg:city":"Belton",
    "sg:classifiers":[
        {
            "category":"Restaurant",
            "type":"Food & Drink"
        }
    ],
    "sg:menulink":"http://www.allmenus.com/mo/raymore/190918-burger-king/menu/",
    "sg:phone":"+1 816 322 2492",
    "sg:postcode":"64012",
    "sg:province":"MO",
    "sg:tags":[
        "burger",
        "american"
    ],
    "wof:name":"Burger King",
    "wof:placetype":"venue"
},
  "geometry": {"coordinates":[-94.50125800000001,38.813182],"type":"Point"}
}