{
  "type": "Feature",
  "properties": {
    "iso:country":"US",
    "sg:address":"1580 NE Neawanna Dr",
    "sg:city":"Lees Summit",
    "sg:classifiers":[
        {
            "category":"Building & Trades",
            "subcategory":"Construction",
            "type":"Services"
        }
    ],
    "sg:phone":"+1 816 668 9908",
    "sg:postcode":"64086",
    "sg:province":"MO",
    "sg:tags":[
        "restoration",
        "cleaning",
        "patio",
        "deck"
    ],
    "wof:name":"Deck Renovators",
    "wof:placetype":"venue"
},
  "geometry": {"coordinates":[-94.351023,38.938278],"type":"Point"}
}