{
  "type": "Feature",
  "properties": {
    "iso:country":"US",
    "sg:address":"9844 Manchester Rd",
    "sg:city":"Webster Groves",
    "sg:classifiers":[
        {
            "category":"Shopping",
            "subcategory":"Florist",
            "type":"Retail Goods"
        }
    ],
    "sg:phone":"+1 314 918 7227",
    "sg:postcode":"63119",
    "sg:province":"MO",
    "wof:name":"House & Hedge",
    "wof:placetype":"venue"
},
  "geometry": {"coordinates":[-90.37387099999999,38.606707],"type":"Point"}
}