{
  "type": "Feature",
  "properties": {
    "iso:country":"US",
    "sg:address":"346 Holloway Rd",
    "sg:city":"Ballwin",
    "sg:classifiers":[
        {
            "category":"Recreation",
            "type":"Entertainment"
        }
    ],
    "sg:phone":"+1 636 256 9740",
    "sg:postcode":"63011",
    "sg:province":"MO",
    "sg:tags":[
        "boat"
    ],
    "wof:name":"Cherokee Landing",
    "wof:placetype":"venue"
},
  "geometry": {"coordinates":[-90.53861000000001,38.603339],"type":"Point"}
}