{
  "type": "Feature",
  "properties": {
    "iso:country":"US",
    "sg:address":"916 Camargo Dr",
    "sg:city":"Ballwin",
    "sg:classifiers":[
        {
            "category":"Wholesale",
            "subcategory":"Machinery & Supplies",
            "type":"Manufacturing & Wholesale Goods"
        },
        {
            "category":"Wholesale",
            "subcategory":"Durable Goods & Equipment",
            "type":"Manufacturing & Wholesale Goods"
        }
    ],
    "sg:phone":"+1 636 394 3281",
    "sg:postcode":"63011",
    "sg:province":"MO",
    "sg:tags":[
        "industrial",
        "representative",
        "manufacturer"
    ],
    "wof:name":"Chem Pro Equipment Co",
    "wof:placetype":"venue"
},
  "geometry": {"coordinates":[-90.57391800000001,38.614621],"type":"Point"}
}