{
  "type": "Feature",
  "properties": {
    "iso:country":"US",
    "sg:address":"420 Rte U",
    "sg:city":"Centertown",
    "sg:classifiers":[
        {
            "category":"Wholesale",
            "subcategory":"Machinery & Supplies",
            "type":"Manufacturing & Wholesale Goods"
        }
    ],
    "sg:phone":"+1 573 584 9396",
    "sg:postcode":"65023",
    "sg:province":"MO",
    "sg:tags":[
        "pump"
    ],
    "wof:name":"Joe D Green Pump Svc",
    "wof:placetype":"venue"
},
  "geometry": {"coordinates":[-92.415234,38.604176],"type":"Point"}
}