{
  "type": "Feature",
  "properties": {
    "iso:country":"US",
    "sg:address":"2220 Hwy M",
    "sg:city":"Barnhart",
    "sg:classifiers":[
        {
            "category":"Building & Trades",
            "subcategory":"Cleaning & Sanitation",
            "type":"Services"
        }
    ],
    "sg:phone":"+1 636 467 5739",
    "sg:postcode":"63012",
    "sg:province":"MO",
    "sg:tags":[
        "fireplace",
        "chimney"
    ],
    "wof:name":"Fireflies Chimney Cleaning",
    "wof:placetype":"venue"
},
  "geometry": {"coordinates":[-90.41476,38.354702],"type":"Point"}
}