{
  "type": "Feature",
  "properties": {
    "iso:country":"US",
    "sg:address":"208 Spring St",
    "sg:city":"Excelsior Spgs",
    "sg:classifiers":[
        {
            "category":"Professional",
            "type":"Services"
        }
    ],
    "sg:phone":"+1 816 637 3395",
    "sg:postcode":"64024",
    "sg:province":"MO",
    "sg:tags":[
        "establishment"
    ],
    "wof:name":"Excelsior Springs AA",
    "wof:placetype":"venue"
},
  "geometry": {"coordinates":[-94.22409399999999,39.341837],"type":"Point"}
}