{
  "type": "Feature",
  "properties": {
    "iso:country":"US",
    "sg:address":"1031 Treeline Ct",
    "sg:city":"Ballwin",
    "sg:classifiers":[
        {
            "category":"Real Estate",
            "subcategory":"Real Estate Operator",
            "type":"Services"
        }
    ],
    "sg:phone":"+1 636 227 7592",
    "sg:postcode":"63021",
    "sg:province":"MO",
    "sg:tags":[
        "building",
        "apartment"
    ],
    "wof:name":"Canterbury Apts",
    "wof:placetype":"venue"
},
  "geometry": {"coordinates":[-90.50624000000001,38.585736],"type":"Point"}
}