{
  "type": "Feature",
  "properties": {
    "iso:country":"US",
    "sg:address":"3852 Nelson Dr",
    "sg:city":"Saint Louis",
    "sg:classifiers":[
        {
            "category":"Food & Beverages",
            "subcategory":"Liquor & Beverages",
            "type":"Retail Goods"
        }
    ],
    "sg:phone":"+1 314 389 7147",
    "sg:postcode":"63121",
    "sg:province":"MO",
    "sg:tags":[
        "alcoholic"
    ],
    "wof:name":"Package Boiler Service Co",
    "wof:placetype":"venue"
},
  "geometry": {"coordinates":[-90.28463600000001,38.702212],"type":"Point"}
}