{
  "type": "Feature",
  "properties": {
    "iso:country":"US",
    "sg:address":"16000 E 283rd St",
    "sg:city":"Harrisonville",
    "sg:classifiers":[
        {
            "category":"Farming",
            "subcategory":"Livestock Farm",
            "type":"Manufacturing & Wholesale Goods"
        }
    ],
    "sg:phone":"+1 816 380 2390",
    "sg:postcode":"64701",
    "sg:province":"MO",
    "sg:tags":[
        "beef",
        "feedlot",
        "cattle"
    ],
    "wof:name":"Robert Hickerson",
    "wof:placetype":"venue"
},
  "geometry": {"coordinates":[-94.414641,38.604625],"type":"Point"}
}