{
  "type": "Feature",
  "properties": {
    "iso:country":"US",
    "sg:address":"2100 Locust St",
    "sg:city":"Saint Louis",
    "sg:classifiers":[
        {
            "category":"Real Estate",
            "subcategory":"Architect",
            "type":"Services"
        }
    ],
    "sg:phone":"+1 314 241 2420",
    "sg:postcode":"63103",
    "sg:province":"MO",
    "wof:name":"Cohen Architecture",
    "wof:placetype":"venue"
},
  "geometry": {"coordinates":[-90.209486,38.633086],"type":"Point"}
}