{
  "type": "Feature",
  "properties": {
    "iso:country":"US",
    "sg:address":"32885 Maries Road 504",
    "sg:city":"Dixon",
    "sg:classifiers":[
        {
            "category":"Retail",
            "subcategory":"Repair Shop",
            "type":"Services"
        }
    ],
    "sg:phone":"+1 573 759 6153",
    "sg:postcode":"65459",
    "sg:province":"MO",
    "wof:name":"Davis Boat Repair & Welding",
    "wof:placetype":"venue"
},
  "geometry": {"coordinates":[-91.99433999999999,38.045903],"type":"Point"}
}