{
  "type": "Feature",
  "properties": {
    "iso:country":"US",
    "sg:address":"219 Mosher Ave",
    "sg:city":"Asbury",
    "sg:classifiers":[
        {
            "category":"Sports & Exercise",
            "subcategory":"Race Track",
            "type":"Entertainment"
        }
    ],
    "sg:phone":"+1 417 642 5599",
    "sg:postcode":"64832",
    "sg:province":"MO",
    "sg:tags":[
        "operation",
        "racing",
        "or"
    ],
    "wof:name":"MO-Kan Dragway",
    "wof:placetype":"venue"
},
  "geometry": {"coordinates":[-94.60764399999999,37.270648],"type":"Point"}
}