{
  "type": "Feature",
  "properties": {
    "iso:country":"US",
    "sg:address":"1128 N Farm Rd 123",
    "sg:city":"Springfield",
    "sg:classifiers":[
        {
            "category":"Wholesale",
            "subcategory":"Non-durable Goods",
            "type":"Manufacturing & Wholesale Goods"
        }
    ],
    "sg:phone":"+1 417 832 8888",
    "sg:postcode":"65802",
    "sg:province":"MO",
    "sg:tags":[
        "merchandise",
        "general"
    ],
    "wof:name":"Plantation Distributors Inc",
    "wof:placetype":"venue"
},
  "geometry": {"coordinates":[-93.366803,37.220387],"type":"Point"}
}