{
  "type": "Feature",
  "properties": {
    "iso:country":"US",
    "sg:address":"463 Lafayette Ct",
    "sg:city":"Ballwin",
    "sg:classifiers":[
        {
            "category":"Shopping",
            "subcategory":"Used Merchandise",
            "type":"Retail Goods"
        }
    ],
    "sg:phone":"+1 636 394 6336",
    "sg:postcode":"63011",
    "sg:province":"MO",
    "sg:tags":[
        "shop",
        "consignment"
    ],
    "wof:name":"ABC Kids Inc",
    "wof:placetype":"venue"
},
  "geometry": {"coordinates":[-90.592241,38.604873],"type":"Point"}
}