{
  "type": "Feature",
  "properties": {
    "iso:country":"US",
    "sg:address":"1901 E 32nd St Ste 4",
    "sg:city":"Joplin",
    "sg:classifiers":[
        {
            "category":"Shopping",
            "subcategory":"Clothing, Apparel, & Fashions",
            "type":"Retail Goods"
        }
    ],
    "sg:phone":"+1 417 621 0222",
    "sg:postcode":"64804",
    "sg:province":"MO",
    "sg:tags":[
        "apparel",
        "women's"
    ],
    "wof:name":"Well Dressed",
    "wof:placetype":"venue"
},
  "geometry": {"coordinates":[-94.534415,37.055353],"type":"Point"}
}