{
  "type": "Feature",
  "properties": {
    "iso:country":"US",
    "sg:address":"6435 N State Route A",
    "sg:city":"Maysville",
    "sg:classifiers":[
        {
            "category":"Retail",
            "subcategory":"Auto Repair",
            "type":"Services"
        }
    ],
    "sg:phone":"+1 816 449 9909",
    "sg:postcode":"64469",
    "sg:province":"MO",
    "sg:tags":[
        "engine",
        "engines-rebuild",
        "exchange",
        "rebuilding"
    ],
    "wof:name":"B And C Small Engine Repair",
    "wof:placetype":"venue"
},
  "geometry": {"coordinates":[-94.346182,39.988509],"type":"Point"}
}