{
  "type": "Feature",
  "properties": {
    "iso:country":"US",
    "sg:address":"1215 Hidden Oak Rd",
    "sg:city":"Chesterfield",
    "sg:classifiers":[
        {
            "category":"Retail",
            "subcategory":"Laundry & Dry Cleaning",
            "type":"Services"
        }
    ],
    "sg:phone":"+1 636 532 3026",
    "sg:postcode":"63017",
    "sg:province":"MO",
    "wof:name":"Alu Custom Clothier",
    "wof:placetype":"venue"
},
  "geometry": {"coordinates":[-90.538698,38.652712],"type":"Point"}
}