{
  "type": "Feature",
  "properties": {
    "iso:country":"US",
    "sg:address":"112 Oak St",
    "sg:city":"Mountain View",
    "sg:classifiers":[
        {
            "category":"Health Services",
            "subcategory":"Doctor",
            "type":"Services"
        }
    ],
    "sg:phone":"+1 417 934 5605",
    "sg:postcode":"65548",
    "sg:province":"MO",
    "sg:tags":[
        "physician",
        "surgeon"
    ],
    "wof:name":"Southern Mo Regional Genetics",
    "wof:placetype":"venue"
},
  "geometry": {"coordinates":[-91.702769,36.995769],"type":"Point"}
}