{
  "type": "Feature",
  "properties": {
    "iso:country":"US",
    "sg:address":"7887 SE Dykes Rd",
    "sg:city":"Holt",
    "sg:classifiers":[
        {
            "category":"Building & Trades",
            "subcategory":"Construction",
            "type":"Services"
        }
    ],
    "sg:phone":"+1 816 320 3950",
    "sg:postcode":"64048",
    "sg:province":"MO",
    "sg:tags":[
        "concrete",
        "contractor"
    ],
    "wof:name":"Bennette Concrete",
    "wof:placetype":"venue"
},
  "geometry": {"coordinates":[-94.313603,39.458828],"type":"Point"}
}