{
  "type": "Feature",
  "properties": {
    "iso:country":"US",
    "sg:address":"1431 Page Industrial Blvd",
    "sg:city":"Saint Louis",
    "sg:classifiers":[
        {
            "category":"Retail",
            "subcategory":"Repair Shop",
            "type":"Services"
        }
    ],
    "sg:phone":"+1 314 487 6800",
    "sg:postcode":"63132",
    "sg:province":"MO",
    "sg:tags":[
        "armature",
        "electrical",
        "rewinding"
    ],
    "wof:name":"Warfield Elc & Lift Trck Mtrs",
    "wof:placetype":"venue"
},
  "geometry": {"coordinates":[-90.385989,38.686278],"type":"Point"}
}