{
  "type": "Feature",
  "properties": {
    "iso:country":"US",
    "sg:address":"1600 W 37 St",
    "sg:city":"Kansas City",
    "sg:classifiers":[
        {
            "category":"Professional",
            "type":"Services"
        }
    ],
    "sg:phone":"+1 816 931 0494",
    "sg:postcode":"64111",
    "sg:province":"MO",
    "sg:tags":[
        "establishment"
    ],
    "wof:name":"Strategic Marketing & Mailing",
    "wof:placetype":"venue"
},
  "geometry": {"coordinates":[-94.60494799999999,39.060552],"type":"Point"}
}