{
  "type": "Feature",
  "properties": {
    "iso:country":"US",
    "sg:address":"27 Ronnies Plz",
    "sg:city":"St Louis",
    "sg:classifiers":[
        {
            "category":"Government",
            "subcategory":"Office",
            "type":"Public Place"
        }
    ],
    "sg:phone":"+1 314 843 5223",
    "sg:postcode":"63126",
    "sg:province":"MO",
    "sg:tags":[
        "county"
    ],
    "wof:name":"South County License Bureau",
    "wof:placetype":"venue"
},
  "geometry": {"coordinates":[-90.360764,38.526913],"type":"Point"}
}