{
  "type": "Feature",
  "properties": {
    "iso:country":"US",
    "sg:address":"451 Covered Bridge Rd",
    "sg:city":"Columbia",
    "sg:classifiers":[
        {
            "category":"Restaurant",
            "type":"Food & Drink"
        }
    ],
    "sg:phone":"+1 573 442 3479",
    "sg:postcode":"65203",
    "sg:province":"MO",
    "sg:tags":[
        "caterer"
    ],
    "wof:name":"Truffles Fine Catering LLC",
    "wof:placetype":"venue"
},
  "geometry": {"coordinates":[-92.350663,38.865252],"type":"Point"}
}