{
  "type": "Feature",
  "properties": {
    "iso:country":"US",
    "sg:address":"1844 French St",
    "sg:city":"Piedmont",
    "sg:classifiers":[
        {
            "category":"Organizations",
            "subcategory":"Religious Organization",
            "type":"Services"
        }
    ],
    "sg:phone":"+1 573 223 2594",
    "sg:postcode":"63957",
    "sg:province":"MO",
    "wof:name":"Kingdom Hall",
    "wof:placetype":"venue"
},
  "geometry": {"coordinates":[-90.688705,37.168725],"type":"Point"}
}