{
  "type": "Feature",
  "properties": {
    "iso:country":"US",
    "sg:address":"6606 NE Antioch Rd",
    "sg:city":"Kansas City",
    "sg:classifiers":[
        {
            "category":"Building & Trades",
            "subcategory":"Landscaping Services",
            "type":"Services"
        }
    ],
    "sg:phone":"+1 816 455 3409",
    "sg:postcode":"64119",
    "sg:province":"MO",
    "sg:tags":[
        "sod",
        "sodding"
    ],
    "wof:name":"K C Turf Master",
    "wof:placetype":"venue"
},
  "geometry": {"coordinates":[-94.53545200000001,39.214741],"type":"Point"}
}