{
  "type": "Feature",
  "properties": {
    "addr:full":"640 Chain of Rocks Dr Saint Louis MO 63137",
    "addr:housenumber":"640",
    "addr:postcode":"63137",
    "addr:street":"Chain Of Rocks Dr",
    "iso:country":"US",
    "sg:address":"640 Chain of Rocks Dr",
    "sg:city":"Saint Louis",
    "sg:classifiers":[
        {
            "category":"Education",
            "subcategory":"Vocational School",
            "type":"Public Place"
        }
    ],
    "sg:phone":"+1 314 868 5602",
    "sg:postcode":"63137",
    "sg:province":"MO",
    "sg:tags":[
        "processing",
        "datum"
    ],
    "wof:name":"Human Resource Services",
    "wof:placetype":"venue"
},
  "geometry": {"coordinates":[-90.223074,38.729427],"type":"Point"}
}