{
  "type": "Feature",
  "properties": {
    "iso:country":"US",
    "sg:address":"2028 Clay St",
    "sg:city":"Kansas City",
    "sg:classifiers":[
        {
            "category":"Professional",
            "subcategory":"Accounting & Tax Preparation",
            "type":"Services"
        }
    ],
    "sg:phone":"+1 816 471 4877",
    "sg:postcode":"64116",
    "sg:province":"MO",
    "sg:tags":[
        "accountant"
    ],
    "wof:name":"Thomas J Hershewe CPA",
    "wof:placetype":"venue"
},
  "geometry": {"coordinates":[-94.57855000000001,39.143516],"type":"Point"}
}