{
  "type": "Feature",
  "properties": {
    "iso:country":"US",
    "sg:address":"2940 N River Rd",
    "sg:city":"Saint Charles",
    "sg:classifiers":[
        {
            "category":"Wholesale",
            "subcategory":"Auto Parts",
            "type":"Manufacturing & Wholesale Goods"
        }
    ],
    "sg:phone":"+1 636 946 6919",
    "sg:postcode":"63301",
    "sg:province":"MO",
    "sg:tags":[
        "shop",
        "repair",
        "used",
        "automotive"
    ],
    "wof:name":"Auto Slavage Midwest Recyclers",
    "wof:placetype":"venue"
},
  "geometry": {"coordinates":[-90.460123,38.815082],"type":"Point"}
}