{
  "type": "Feature",
  "properties": {
    "iso:country":"US",
    "sg:address":"125 S Frankford Ave",
    "sg:city":"Novinger",
    "sg:classifiers":[
        {
            "category":"Bars & Pubs",
            "type":"Food & Drink"
        },
        {
            "category":"Restaurant",
            "type":"Food & Drink"
        }
    ],
    "sg:phone":"+1 660 488 5300",
    "sg:postcode":"63559",
    "sg:province":"MO",
    "sg:tags":[
        "tavern",
        "brew"
    ],
    "wof:name":"Chevy's Bar & Grill",
    "wof:placetype":"venue"
},
  "geometry": {"coordinates":[-92.708384,40.230297],"type":"Point"}
}