{
  "type": "Feature",
  "properties": {
    "iso:country":"US",
    "sg:address":"135 Perry St",
    "sg:city":"Moscow Mills",
    "sg:classifiers":[
        {
            "category":"Building & Trades",
            "subcategory":"Construction",
            "type":"Services"
        }
    ],
    "sg:phone":"+1 636 366 4565",
    "sg:postcode":"63301",
    "sg:province":"MO",
    "sg:tags":[
        "house"
    ],
    "wof:name":"American Dream Builders",
    "wof:placetype":"venue"
},
  "geometry": {"coordinates":[-90.484835,38.776668],"type":"Point"}
}