{
  "type": "Feature",
  "properties": {
    "iso:country":"US",
    "sg:address":"1015 Locust St Ste 425",
    "sg:city":"Saint Louis",
    "sg:classifiers":[
        {
            "category":"Professional",
            "subcategory":"Accounting & Tax Preparation",
            "type":"Services"
        }
    ],
    "sg:phone":"+1 314 231 5105",
    "sg:postcode":"63101",
    "sg:province":"MO",
    "sg:tags":[
        "accountant"
    ],
    "wof:name":"Massie Fudemberg Goldberg Llc Cert Pub Accts",
    "wof:placetype":"venue"
},
  "geometry": {"coordinates":[-90.194397,38.630001],"type":"Point"}
}