{
  "type": "Feature",
  "properties": {
    "iso:country":"US",
    "sg:address":"5680 Telegraph Rd",
    "sg:city":"St Louis",
    "sg:classifiers":[
        {
            "category":"Personal",
            "subcategory":"Beauty Salon",
            "type":"Services"
        }
    ],
    "sg:phone":"+1 314 846 5099",
    "sg:postcode":"63129",
    "sg:province":"MO",
    "wof:name":"Great Lengths Salon",
    "wof:placetype":"venue"
},
  "geometry": {"coordinates":[-90.30569,38.467535],"type":"Point"}
}