{
  "type": "Feature",
  "properties": {
    "iso:country":"US",
    "sg:address":"4053 Lake Rd",
    "sg:city":"Jefferson City",
    "sg:classifiers":[
        {
            "category":"Farming",
            "subcategory":"Livestock Farm",
            "type":"Manufacturing & Wholesale Goods"
        }
    ],
    "sg:phone":"+1 573 395 4671",
    "sg:postcode":"65101",
    "sg:province":"MO",
    "sg:tags":[
        "dairy",
        "beef",
        "feedlot",
        "cattle"
    ],
    "wof:name":"Roger Bruemmer",
    "wof:placetype":"venue"
},
  "geometry": {"coordinates":[-92.13310300000001,38.485377],"type":"Point"}
}