{
  "type": "Feature",
  "properties": {
    "iso:country":"US",
    "sg:address":"2585 Tandy Rd",
    "sg:city":"Fordland",
    "sg:classifiers":[
        {
            "category":"Shopping",
            "subcategory":"Computers & Home Electronics",
            "type":"Retail Goods"
        }
    ],
    "sg:phone":"+1 417 738 2881",
    "sg:postcode":"65652",
    "sg:province":"MO",
    "sg:tags":[
        "equipment",
        "audio-visual"
    ],
    "sg:website":"http://www.seaudiovisual.com",
    "wof:name":"Southeastern Audio Visual Inc",
    "wof:placetype":"venue"
},
  "geometry": {"coordinates":[-92.891906,37.148354],"type":"Point"}
}