{
  "type": "Feature",
  "properties": {
    "iso:country":"US",
    "sg:address":"3296 Sage Ct",
    "sg:city":"Saint Louis",
    "sg:classifiers":[
        {
            "category":"Building & Trades",
            "subcategory":"Construction",
            "type":"Services"
        }
    ],
    "sg:phone":"+1 314 894 4549",
    "sg:postcode":"63129",
    "sg:province":"MO",
    "sg:tags":[
        "house"
    ],
    "wof:name":"Enzian Inc",
    "wof:placetype":"venue"
},
  "geometry": {"coordinates":[-90.33467,38.478666],"type":"Point"}
}