{
  "type": "Feature",
  "properties": {
    "iso:country":"US",
    "sg:address":"1100 Lemay Ferry Rd",
    "sg:city":"Saint Louis",
    "sg:classifiers":[
        {
            "category":"Restaurant",
            "type":"Food & Drink"
        }
    ],
    "sg:phone":"+1 314 638 0026",
    "sg:postcode":"63125",
    "sg:province":"MO",
    "sg:tags":[
        "mexican"
    ],
    "wof:name":"La Casa Frijole",
    "wof:placetype":"venue"
},
  "geometry": {"coordinates":[-90.286147,38.534419],"type":"Point"}
}