{
  "type": "Feature",
  "properties": {
    "iso:country":"US",
    "sg:address":"4015 Saint Louis Ave",
    "sg:city":"Saint Louis",
    "sg:classifiers":[
        {
            "category":"Social Services",
            "subcategory":"Child Care",
            "type":"Services"
        }
    ],
    "sg:phone":"+1 314 652 0809",
    "sg:postcode":"63107",
    "sg:province":"MO",
    "sg:tags":[
        "day"
    ],
    "wof:name":"Lively Stone Child Development Center",
    "wof:placetype":"venue"
},
  "geometry": {"coordinates":[-90.229301,38.659199],"type":"Point"}
}