{
  "type": "Feature",
  "properties": {
    "iso:country":"US",
    "sg:address":"13 Evergreen Ln",
    "sg:city":"Festus",
    "sg:classifiers":[
        {
            "category":"Real Estate",
            "subcategory":"Real Estate Operator",
            "type":"Services"
        }
    ],
    "sg:phone":"+1 636 931 6631",
    "sg:postcode":"63028",
    "sg:province":"MO",
    "sg:tags":[
        "mobile",
        "home",
        "site"
    ],
    "wof:name":"Lifestyle Mobile Home Park",
    "wof:placetype":"venue"
},
  "geometry": {"coordinates":[-90.45763700000001,38.170354],"type":"Point"}
}