{
  "type": "Feature",
  "properties": {
    "iso:country":"US",
    "sg:address":"2111 Shelby St",
    "sg:city":"Higginsville",
    "sg:classifiers":[
        {
            "category":"Organizations",
            "subcategory":"Non-profit Organization",
            "type":"Services"
        }
    ],
    "sg:phone":"+1 660 584 5445",
    "sg:postcode":"64037",
    "sg:province":"MO",
    "sg:tags":[
        "fund",
        "counselor",
        "raising"
    ],
    "wof:name":"Show Me Fund Raising",
    "wof:placetype":"venue"
},
  "geometry": {"coordinates":[-93.715812,39.072937],"type":"Point"}
}