{
  "type": "Feature",
  "properties": {
    "iso:country":"US",
    "sg:address":"503 Clark St",
    "sg:city":"Canton",
    "sg:classifiers":[
        {
            "category":"Shopping",
            "subcategory":"Florist",
            "type":"Retail Goods"
        }
    ],
    "sg:phone":"+1 573 288 3836",
    "sg:postcode":"63435",
    "sg:province":"MO",
    "wof:name":"Flower Mill & Trading Post",
    "wof:placetype":"venue"
},
  "geometry": {"coordinates":[-91.521709,40.131162],"type":"Point"}
}