{
  "type": "Feature",
  "properties": {
    "iso:country":"US",
    "sg:address":"3315 Droste Rd",
    "sg:city":"Saint Charles",
    "sg:classifiers":[
        {
            "category":"Building & Trades",
            "subcategory":"Construction",
            "type":"Services"
        }
    ],
    "sg:phone":"+1 636 485 8853",
    "sg:postcode":"63301",
    "sg:province":"MO",
    "sg:tags":[
        "house"
    ],
    "wof:name":"Hartnett Construction Inc",
    "wof:placetype":"venue"
},
  "geometry": {"coordinates":[-90.52943999999999,38.79945],"type":"Point"}
}