{
  "type": "Feature",
  "properties": {
    "iso:country":"US",
    "sg:address":"933 Gardenview Office Pkwy",
    "sg:city":"Saint Louis",
    "sg:classifiers":[
        {
            "category":"Professional",
            "subcategory":"Engineering",
            "type":"Services"
        }
    ],
    "sg:phone":"+1 314 567 0078",
    "sg:postcode":"63141",
    "sg:province":"MO",
    "wof:name":"Holland & Assoc Inc",
    "wof:placetype":"venue"
},
  "geometry": {"coordinates":[-90.40702899999999,38.674183],"type":"Point"}
}