{
  "type": "Feature",
  "properties": {
    "iso:country":"US",
    "sg:address":"440 Saint Francois St",
    "sg:city":"Florissant",
    "sg:classifiers":[
        {
            "category":"Personal",
            "subcategory":"Barber",
            "type":"Services"
        }
    ],
    "sg:phone":"+1 314 921 3539",
    "sg:postcode":"63031",
    "sg:province":"MO",
    "sg:tags":[
        "shop"
    ],
    "wof:name":"Elliott & Dixon's Barber Salon",
    "wof:placetype":"venue"
},
  "geometry": {"coordinates":[-90.32835799999999,38.794094],"type":"Point"}
}