{
  "type": "Feature",
  "properties": {
    "iso:country":"US",
    "sg:address":"2021 Camille Ct",
    "sg:city":"Liberty",
    "sg:classifiers":[
        {
            "category":"Banks & Credit Unions",
            "subcategory":"Bank",
            "type":"Services"
        }
    ],
    "sg:phone":"+1 816 453 1900",
    "sg:postcode":"64068",
    "sg:province":"MO",
    "sg:tags":[
        "loan",
        "real estate"
    ],
    "wof:name":"Olympic Mortgage",
    "wof:placetype":"venue"
},
  "geometry": {"coordinates":[-94.441839,39.27143],"type":"Point"}
}