{
  "type": "Feature",
  "properties": {
    "iso:country":"US",
    "sg:address":"113 S 4th St",
    "sg:city":"Spickard",
    "sg:classifiers":[
        {
            "category":"Organizations",
            "subcategory":"Community Association",
            "type":"Services"
        }
    ],
    "sg:phone":"+1 660 485 6650",
    "sg:postcode":"64679",
    "sg:province":"MO",
    "wof:name":"American Fderation Grn Millers",
    "wof:placetype":"venue"
},
  "geometry": {"coordinates":[-93.593822,40.242901],"type":"Point"}
}