{
  "type": "Feature",
  "properties": {
    "iso:country":"US",
    "sg:address":"518 Hitt St",
    "sg:city":"Columbia",
    "sg:classifiers":[
        {
            "category":"Education",
            "subcategory":"College",
            "type":"Public Place"
        }
    ],
    "sg:phone":"+1 573 882 3418",
    "sg:postcode":"65201",
    "sg:province":"MO",
    "sg:tags":[
        "union",
        "university",
        "student",
        "for"
    ],
    "wof:name":"Memoiral Unn-Nvrsity MO Campus",
    "wof:placetype":"venue"
},
  "geometry": {"coordinates":[-92.325491,38.945555],"type":"Point"}
}