{
  "type": "Feature",
  "properties": {
    "iso:country":"US",
    "sg:address":"317 N Subway Blvd",
    "sg:city":"Nevada",
    "sg:classifiers":[
        {
            "category":"Personal",
            "subcategory":"Beauty Salon",
            "type":"Services"
        }
    ],
    "sg:phone":"+1 417 667 4447",
    "sg:postcode":"64772",
    "sg:province":"MO",
    "wof:name":"Mane Image",
    "wof:placetype":"venue"
},
  "geometry": {"coordinates":[-94.344835,37.838634],"type":"Point"}
}