{
  "type": "Feature",
  "properties": {
    "iso:country":"US",
    "sg:address":"1000 E 10 St",
    "sg:city":"Kansas City",
    "sg:classifiers":[
        {
            "category":"Retail",
            "subcategory":"Repair Shop",
            "type":"Services"
        },
        {
            "category":"Organizations",
            "subcategory":"Labor Organization",
            "type":"Services"
        }
    ],
    "sg:phone":"+1 816 842 8917",
    "sg:postcode":"64106",
    "sg:province":"MO",
    "sg:tags":[
        "union",
        "ironwork"
    ],
    "wof:name":"Iron Workers Local Union No 10",
    "wof:placetype":"venue"
},
  "geometry": {"coordinates":[-94.569778,39.101887],"type":"Point"}
}