{
  "type": "Feature",
  "properties": {
    "iso:country":"US",
    "sg:address":"601 Old US Hwy 71",
    "sg:city":"Adrian",
    "sg:classifiers":[
        {
            "category":"Organizations",
            "subcategory":"Religious Organization",
            "type":"Services"
        }
    ],
    "sg:phone":"+1 816 297 4248",
    "sg:postcode":"64720",
    "sg:province":"MO",
    "sg:tags":[
        "church"
    ],
    "wof:name":"Victory Assembly Of God",
    "wof:placetype":"venue"
},
  "geometry": {"coordinates":[-94.343998,38.401827],"type":"Point"}
}