{
  "type": "Feature",
  "properties": {
    "iso:country":"US",
    "sg:address":"3823 Raymond Ave",
    "sg:city":"Bridgeton",
    "sg:classifiers":[
        {
            "category":"Arts & Performance",
            "subcategory":"Theater",
            "type":"Entertainment"
        }
    ],
    "sg:phone":"+1 314 770 9279",
    "sg:postcode":"63044",
    "sg:province":"MO",
    "sg:tags":[
        "theatrical"
    ],
    "wof:name":"North American Strongman Soc",
    "wof:placetype":"venue"
},
  "geometry": {"coordinates":[-90.405675,38.737171],"type":"Point"}
}