{
  "type": "Feature",
  "properties": {
    "iso:country":"US",
    "sg:address":"920 E 10th St",
    "sg:city":"Rolla",
    "sg:classifiers":[
        {
            "category":"Organizations",
            "subcategory":"Professional Association",
            "type":"Services"
        }
    ],
    "sg:phone":"+1 573 364 3628",
    "sg:postcode":"65401",
    "sg:province":"MO",
    "sg:tags":[
        "affairs",
        "community"
    ],
    "wof:name":"Rolla Community Dev Corp Inc",
    "wof:placetype":"venue"
},
  "geometry": {"coordinates":[-91.76157499999999,37.951347],"type":"Point"}
}