{
  "type": "Feature",
  "properties": {
    "iso:country":"US",
    "sg:address":"1164 Co Rd 559",
    "sg:city":"Poplar Bluff",
    "sg:classifiers":[
        {
            "category":"Shopping",
            "subcategory":"Bicycles & Sporting Goods",
            "type":"Retail Goods"
        }
    ],
    "sg:phone":"+1 573 776 1486",
    "sg:postcode":"63901",
    "sg:province":"MO",
    "wof:name":"Rocky Top Guns",
    "wof:placetype":"venue"
},
  "geometry": {"coordinates":[-90.354564,36.779148],"type":"Point"}
}