{
  "type": "Feature",
  "properties": {
    "iso:country":"US",
    "sg:address":"2620 E Jackson Blvd",
    "sg:city":"Jackson",
    "sg:classifiers":[
        {
            "category":"Autos & Motor Vehicles",
            "subcategory":"Automobile Sales",
            "type":"Retail Goods"
        }
    ],
    "sg:phone":"+1 573 243 6770",
    "sg:postcode":"63755",
    "sg:province":"MO",
    "sg:tags":[
        "used"
    ],
    "wof:name":"Buy Right Motors Inc",
    "wof:placetype":"venue"
},
  "geometry": {"coordinates":[-89.638042,37.366577],"type":"Point"}
}