{
  "type": "Feature",
  "properties": {
    "iso:country":"US",
    "sg:address":"330 Bolivar St",
    "sg:city":"Jefferson City",
    "sg:classifiers":[
        {
            "category":"Shopping",
            "type":"Retail Goods"
        }
    ],
    "sg:phone":"+1 573 635 8930",
    "sg:postcode":"65101",
    "sg:province":"MO",
    "sg:tags":[
        "merchandise"
    ],
    "wof:name":"Precision Art",
    "wof:placetype":"venue"
},
  "geometry": {"coordinates":[-92.180578,38.582288],"type":"Point"}
}