{
  "type": "Feature",
  "properties": {
    "iso:country":"US",
    "sg:address":"1155 N Eldon Ave",
    "sg:city":"Springfield",
    "sg:classifiers":[
        {
            "category":"Retail",
            "subcategory":"Auto Repair",
            "type":"Services"
        }
    ],
    "sg:phone":"+1 417 863 8976",
    "sg:postcode":"65803",
    "sg:province":"MO",
    "sg:tags":[
        "company",
        "insurance",
        "for"
    ],
    "wof:name":"Insurance Auto Auctions Inc",
    "wof:placetype":"venue"
},
  "geometry": {"coordinates":[-93.357517,37.223284],"type":"Point"}
}