{
  "type": "Feature",
  "properties": {
    "iso:country":"US",
    "sg:address":"911 W Business US Highway 60",
    "sg:city":"Dexter",
    "sg:classifiers":[
        {
            "category":"Shopping",
            "subcategory":"Tobacco",
            "type":"Retail Goods"
        },
        {
            "category":"Food & Beverages",
            "subcategory":"Liquor & Beverages",
            "type":"Retail Goods"
        }
    ],
    "sg:phone":"+1 573 614 4001",
    "sg:postcode":"63841",
    "sg:province":"MO",
    "sg:tags":[
        "cigarette",
        "cigar",
        "store"
    ],
    "wof:name":"Dexter Discount Cig & Beer",
    "wof:placetype":"venue"
},
  "geometry": {"coordinates":[-89.970707,36.803636],"type":"Point"}
}