{
  "type": "Feature",
  "properties": {
    "iso:country":"US",
    "sg:address":"405 S Leonard St",
    "sg:city":"Liberty",
    "sg:classifiers":[
        {
            "category":"Autos & Motor Vehicles",
            "subcategory":"Auto Supplies",
            "type":"Retail Goods"
        }
    ],
    "sg:phone":"+1 816 781 4406",
    "sg:postcode":"64068",
    "sg:province":"MO",
    "sg:tags":[
        "automobile",
        "part"
    ],
    "sg:website":"http://www.vinniejohnson.com",
    "wof:name":"Piston Automotive",
    "wof:placetype":"venue"
},
  "geometry": {"coordinates":[-94.416831,39.239622],"type":"Point"}
}