{
  "type": "Feature",
  "properties": {
    "iso:country":"US",
    "sg:address":"4509 Overbrook Dr",
    "sg:city":"St Louis",
    "sg:classifiers":[
        {
            "category":"Real Estate",
            "subcategory":"Developer",
            "type":"Services"
        }
    ],
    "sg:phone":"+1 314 389 7236",
    "sg:postcode":"63121",
    "sg:province":"MO",
    "wof:name":"Cornerstone Real Estate Advsrs",
    "wof:placetype":"venue"
},
  "geometry": {"coordinates":[-90.290344,38.710256],"type":"Point"}
}