{
  "type": "Feature",
  "properties": {
    "iso:country":"US",
    "sg:address":"40 Platte St",
    "sg:city":"Dearborn",
    "sg:classifiers":[
        {
            "category":"Building & Trades",
            "subcategory":"Construction",
            "type":"Services"
        }
    ],
    "sg:phone":"+1 816 450 8849",
    "sg:postcode":"64439",
    "sg:province":"MO",
    "sg:tags":[
        "house"
    ],
    "wof:name":"Robert Wagers Jr Construction",
    "wof:placetype":"venue"
},
  "geometry": {"coordinates":[-94.799936,39.504642],"type":"Point"}
}