{
  "type": "Feature",
  "properties": {
    "addr:full":"3504 S Range Line Rd Joplin MO 64804",
    "addr:housenumber":"3504",
    "addr:postcode":"64804",
    "addr:street":"S Range Line Rd",
    "iso:country":"US",
    "sg:address":"3504 S Range Line Rd",
    "sg:city":"Joplin",
    "sg:classifiers":[
        {
            "category":"Food & Beverages",
            "subcategory":"Groceries & Convenience Stores",
            "type":"Retail Goods"
        }
    ],
    "sg:phone":"+1 417 627 9583",
    "sg:postcode":"64804",
    "sg:province":"MO",
    "wof:name":"Kum & Go",
    "wof:placetype":"venue"
},
  "geometry": {"coordinates":[-94.478576,37.052531],"type":"Point"}
}