{
  "type": "Feature",
  "properties": {
    "iso:country":"US",
    "sg:address":"4610 Hwy H",
    "sg:city":"Saint Charles",
    "sg:classifiers":[
        {
            "category":"Professional",
            "subcategory":"Business Services",
            "type":"Services"
        }
    ],
    "sg:phone":"+1 636 250 3136",
    "sg:postcode":"63301",
    "sg:province":"MO",
    "wof:name":"Kluesner Kreations",
    "wof:placetype":"venue"
},
  "geometry": {"coordinates":[-90.436233,38.856285],"type":"Point"}
}