{
  "type": "Feature",
  "properties": {
    "iso:country":"US",
    "sg:address":"5485 Union Blvd",
    "sg:city":"Saint Louis",
    "sg:classifiers":[
        {
            "category":"Social Services",
            "subcategory":"Child Care",
            "type":"Services"
        }
    ],
    "sg:phone":"+1 314 383 3737",
    "sg:postcode":"63115",
    "sg:province":"MO",
    "sg:tags":[
        "day"
    ],
    "wof:name":"Kid's Land Child Care",
    "wof:placetype":"venue"
},
  "geometry": {"coordinates":[-90.239629,38.694863],"type":"Point"}
}