{
  "type": "Feature",
  "properties": {
    "addr:full":"8636 N Boardwalk Ave Kansas City MO 64154",
    "addr:housenumber":"8636",
    "addr:postcode":"64154",
    "addr:street":"N Boardwalk Ave",
    "iso:country":"US",
    "sg:address":"8636 N Boardwalk Ave",
    "sg:city":"Kansas City",
    "sg:classifiers":[
        {
            "category":"Home & Garden",
            "subcategory":"Furniture",
            "type":"Retail Goods"
        }
    ],
    "sg:phone":"+1 816 746 1764",
    "sg:postcode":"64154",
    "sg:province":"MO",
    "wof:name":"Bombay Co",
    "wof:placetype":"venue"
},
  "geometry": {"coordinates":[-94.652242,39.252543],"type":"Point"}
}