{
  "type": "Feature",
  "properties": {
    "iso:country":"US",
    "sg:address":"2206 Samuel Stewart Ct",
    "sg:city":"Chesterfield",
    "sg:classifiers":[
        {
            "category":"Building & Trades",
            "subcategory":"Construction",
            "type":"Services"
        }
    ],
    "sg:phone":"+1 636 532 9558",
    "sg:postcode":"63005",
    "sg:province":"MO",
    "sg:tags":[
        "dredging",
        "contractor"
    ],
    "sg:website":"www.er-dredging.com",
    "wof:name":"Energy Resources Inc",
    "wof:placetype":"venue"
},
  "geometry": {"coordinates":[-90.600301,38.624511],"type":"Point"}
}