{
  "type": "Feature",
  "properties": {
    "iso:country":"US",
    "sg:address":"1418 Mable St",
    "sg:city":"Trenton",
    "sg:classifiers":[
        {
            "category":"Building & Trades",
            "subcategory":"Construction",
            "type":"Services"
        }
    ],
    "sg:phone":"+1 660 359 5177",
    "sg:postcode":"64683",
    "sg:province":"MO",
    "sg:tags":[
        "general",
        "contractor"
    ],
    "wof:name":"Robert Porter Construction",
    "wof:placetype":"venue"
},
  "geometry": {"coordinates":[-93.616632,40.079903],"type":"Point"}
}