{
  "type": "Feature",
  "properties": {
    "iso:country":"US",
    "sg:address":"9390 Olive Blvd",
    "sg:city":"Saint Louis",
    "sg:classifiers":[
        {
            "category":"Professional",
            "subcategory":"Computer Services",
            "type":"Services"
        }
    ],
    "sg:phone":"+1 314 993 5713",
    "sg:postcode":"63132",
    "sg:province":"MO",
    "sg:tags":[
        "micro",
        "engineering",
        "consult",
        "network",
        "system"
    ],
    "wof:name":"G S I Inc",
    "wof:placetype":"venue"
},
  "geometry": {"coordinates":[-90.374978,38.67403],"type":"Point"}
}