{
  "type": "Feature",
  "properties": {
    "iso:country":"US",
    "sg:address":"1314 S Michigan Ave",
    "sg:city":"Joplin",
    "sg:classifiers":[
        {
            "category":"Personal",
            "subcategory":"Beauty Salon",
            "type":"Services"
        }
    ],
    "sg:phone":"+1 417 626 8600",
    "sg:postcode":"64801",
    "sg:province":"MO",
    "wof:name":"The Groove",
    "wof:placetype":"venue"
},
  "geometry": {"coordinates":[-94.500641,37.076783],"type":"Point"}
}