{
  "type": "Feature",
  "properties": {
    "iso:country":"US",
    "sg:address":"2733 Cherokee St",
    "sg:city":"St Louis",
    "sg:classifiers":[
        {
            "category":"Shopping",
            "subcategory":"Optical Goods",
            "type":"Retail Goods"
        }
    ],
    "sg:phone":"+1 314 773 7116",
    "sg:postcode":"63118",
    "sg:province":"MO",
    "wof:name":"Leanne's Eyewear",
    "wof:placetype":"venue"
},
  "geometry": {"coordinates":[-90.22995899999999,38.593924],"type":"Point"}
}