{
  "type": "Feature",
  "properties": {
    "iso:country":"US",
    "sg:address":"3429 Troost Ave",
    "sg:city":"Kansas City",
    "sg:classifiers":[
        {
            "category":"Freight",
            "type":"Transportation"
        }
    ],
    "sg:phone":"+1 816 753 3304",
    "sg:postcode":"64109",
    "sg:province":"MO",
    "sg:tags":[
        "special",
        "general"
    ],
    "wof:name":"Midtown Self Storage",
    "wof:placetype":"venue"
},
  "geometry": {"coordinates":[-94.571631,39.06365],"type":"Point"}
}