{
  "type": "Feature",
  "properties": {
    "iso:country":"US",
    "sg:address":"420 W 42nd Ter",
    "sg:city":"Kansas City",
    "sg:classifiers":[
        {
            "category":"Professional",
            "subcategory":"Engineering",
            "type":"Services"
        }
    ],
    "sg:phone":"+1 816 756 1116",
    "sg:postcode":"64111",
    "sg:province":"MO",
    "sg:tags":[
        "consulting",
        "engineer"
    ],
    "wof:name":"P S I",
    "wof:placetype":"venue"
},
  "geometry": {"coordinates":[-94.59177800000001,39.050195],"type":"Point"}
}