{
  "type": "Feature",
  "properties": {
    "iso:country":"US",
    "sg:address":"1711 N Duquesne Rd",
    "sg:city":"Joplin",
    "sg:classifiers":[
        {
            "category":"Manufacturing",
            "subcategory":"Glass & Minerals",
            "type":"Manufacturing & Wholesale Goods"
        }
    ],
    "sg:phone":"+1 417 626 2336",
    "sg:postcode":"64801",
    "sg:province":"MO",
    "sg:tags":[
        "concrete",
        "brick",
        "prod",
        "block"
    ],
    "wof:name":"E F Shea Concrete",
    "wof:placetype":"venue"
},
  "geometry": {"coordinates":[-94.45786200000001,37.106247],"type":"Point"}
}