{
  "type": "Feature",
  "properties": {
    "iso:country":"US",
    "sg:address":"2751 Kirkland Dr",
    "sg:city":"Branson",
    "sg:classifiers":[
        {
            "category":"Place Of Worship",
            "subcategory":"Church",
            "type":"Public Place"
        },
        {
            "category":"Place Of Worship",
            "type":"Public Place"
        }
    ],
    "sg:phone":"+1 417 338 5321",
    "sg:postcode":"65616",
    "sg:province":"MO",
    "sg:tags":[
        "churches-baptist-general",
        "churches-baptist"
    ],
    "wof:name":"Friendly Baptist Church",
    "wof:placetype":"venue"
},
  "geometry": {"coordinates":[-93.303856,36.64206],"type":"Point"}
}