{
  "type": "Feature",
  "properties": {
    "iso:country":"US",
    "sg:address":"107B N Lincoln Dr",
    "sg:city":"Troy",
    "sg:classifiers":[
        {
            "category":"Health Services",
            "subcategory":"Doctor",
            "type":"Services"
        }
    ],
    "sg:phone":"+1 636 462 6411",
    "sg:postcode":"63379",
    "sg:province":"MO",
    "sg:tags":[
        "physician",
        "surgeon"
    ],
    "wof:name":"Frank Bruce S MD",
    "wof:placetype":"venue"
},
  "geometry": {"coordinates":[-90.969776,38.984686],"type":"Point"}
}