{
  "type": "Feature",
  "properties": {
    "iso:country":"US",
    "sg:address":"208 N Central Ave",
    "sg:city":"Eureka",
    "sg:classifiers":[
        {
            "category":"Insurance",
            "subcategory":"Insurance Agent",
            "type":"Services"
        },
        {
            "category":"Insurance",
            "subcategory":"Hazard Insurance",
            "type":"Services"
        },
        {
            "category":"Insurance",
            "subcategory":"Title Insurance",
            "type":"Services"
        },
        {
            "category":"Insurance",
            "subcategory":"Life Insurance",
            "type":"Services"
        }
    ],
    "sg:phone":"+1 636 938 6565",
    "sg:postcode":"63025",
    "sg:province":"MO",
    "sg:tags":[
        "business",
        "auto",
        "commercial",
        "homeowner",
        "motorcycle",
        "renter"
    ],
    "wof:name":"Allstate Insurance Company - Tracie Bibb",
    "wof:placetype":"venue"
},
  "geometry": {"coordinates":[-90.627935,38.504318],"type":"Point"}
}