{
  "type": "Feature",
  "properties": {
    "iso:country":"US",
    "sg:address":"252 Merchant St",
    "sg:city":"Ste Genevieve",
    "sg:classifiers":[
        {
            "category":"Shopping",
            "subcategory":"Used Merchandise",
            "type":"Retail Goods"
        }
    ],
    "sg:phone":"+1 573 883 1017",
    "sg:postcode":"63670",
    "sg:province":"MO",
    "sg:tags":[
        "antique"
    ],
    "wof:name":"Nancy Dee Antiques & Cllctbls",
    "wof:placetype":"venue"
},
  "geometry": {"coordinates":[-90.045208,37.979774],"type":"Point"}
}