{
  "type": "Feature",
  "properties": {
    "iso:country":"US",
    "sg:address":"6408 Highway Aj",
    "sg:city":"Washington",
    "sg:classifiers":[
        {
            "category":"Real Estate",
            "subcategory":"Surveying",
            "type":"Services"
        }
    ],
    "sg:phone":"+1 636 583 7777",
    "sg:postcode":"63090",
    "sg:province":"MO",
    "sg:tags":[
        "surveyor",
        "land",
        "engineer"
    ],
    "wof:name":"Jeremiah D Pellin Mr",
    "wof:placetype":"venue"
},
  "geometry": {"coordinates":[-91.115566,38.459335],"type":"Point"}
}