{
  "type": "Feature",
  "properties": {
    "iso:country":"US",
    "sg:address":"208 E Wilson St",
    "sg:city":"Clinton",
    "sg:classifiers":[
        {
            "category":"Professional",
            "subcategory":"Art Services",
            "type":"Services"
        }
    ],
    "sg:phone":"+1 660 885 2921",
    "sg:postcode":"64735",
    "sg:province":"MO",
    "sg:tags":[
        "commercial",
        "design"
    ],
    "wof:name":"Woodson Roddy Studio",
    "wof:placetype":"venue"
},
  "geometry": {"coordinates":[-93.774174,38.364272],"type":"Point"}
}