{
  "type": "Feature",
  "properties": {
    "iso:country":"US",
    "sg:address":"801 Moreau St",
    "sg:city":"Ste Genevieve",
    "sg:classifiers":[
        {
            "category":"Manufacturing",
            "subcategory":"Tools & Machinery",
            "type":"Manufacturing & Wholesale Goods"
        }
    ],
    "sg:phone":"+1 573 883 8883",
    "sg:postcode":"63670",
    "sg:province":"MO",
    "sg:tags":[
        "equipment",
        "system",
        "automation"
    ],
    "wof:name":"Lee Manufacturing Inc",
    "wof:placetype":"venue"
},
  "geometry": {"coordinates":[-90.04304,37.966078],"type":"Point"}
}