{
  "type": "Feature",
  "properties": {
    "iso:country":"US",
    "sg:address":"10 Country Life Ln",
    "sg:city":"Defiance",
    "sg:classifiers":[
        {
            "category":"Health Services",
            "subcategory":"Nursing And Care Facility",
            "type":"Services"
        }
    ],
    "sg:phone":"+1 636 398 6212",
    "sg:postcode":"63341",
    "sg:province":"MO",
    "sg:tags":[
        "skilled"
    ],
    "wof:name":"Persimmon Place",
    "wof:placetype":"venue"
},
  "geometry": {"coordinates":[-90.81242899999999,38.7036],"type":"Point"}
}