{
  "type": "Feature",
  "properties": {
    "addr:full":"7619 NW Prairie View Rd Kansas City MO 64151",
    "addr:housenumber":"7619",
    "addr:postcode":"64151",
    "addr:street":"Nw Prairie View Rd",
    "iso:country":"US",
    "sg:address":"7619 NW Prairie View Rd",
    "sg:city":"Kansas City",
    "sg:classifiers":[
        {
            "category":"Autos & Motor Vehicles",
            "subcategory":"Auto Supplies",
            "type":"Retail Goods"
        }
    ],
    "sg:phone":"+1 816 584 2685",
    "sg:postcode":"64151",
    "sg:province":"MO",
    "sg:tags":[
        "automobile",
        "parts"
    ],
    "wof:name":"O'REILLY Auto Parts",
    "wof:placetype":"venue"
},
  "geometry": {"coordinates":[-94.658355,39.232952],"type":"Point"}
}