{
  "type": "Feature",
  "properties": {
    "iso:country":"US",
    "sg:address":"9611 Harmony Rd",
    "sg:city":"Carthage",
    "sg:classifiers":[
        {
            "category":"Organizations",
            "subcategory":"Religious Organization",
            "type":"Services"
        }
    ],
    "sg:phone":"+1 417 358 3844",
    "sg:postcode":"64836",
    "sg:province":"MO",
    "sg:tags":[
        "church"
    ],
    "wof:name":"Bethany Baptist Church",
    "wof:placetype":"venue"
},
  "geometry": {"coordinates":[-94.227144,37.164991],"type":"Point"}
}