{
  "type": "Feature",
  "properties": {
    "iso:country":"US",
    "sg:address":"3176 S Parkview Ave",
    "sg:city":"Springfield",
    "sg:classifiers":[
        {
            "category":"Professional",
            "subcategory":"Business Services",
            "type":"Services"
        }
    ],
    "sg:phone":"+1 417 496 8977",
    "sg:postcode":"65804",
    "sg:province":"MO",
    "sg:tags":[
        "fund",
        "promotion",
        "raising"
    ],
    "wof:name":"Forever Endeavor Productions",
    "wof:placetype":"venue"
},
  "geometry": {"coordinates":[-93.233885,37.154455],"type":"Point"}
}