{
  "type": "Feature",
  "properties": {
    "iso:country":"US",
    "sg:address":"401 SW 12 St",
    "sg:city":"Oak Grove",
    "sg:classifiers":[
        {
            "category":"Home & Garden",
            "subcategory":"Building Materials",
            "type":"Retail Goods"
        }
    ],
    "sg:phone":"+1 816 625 3333",
    "sg:postcode":"64075",
    "sg:province":"MO",
    "sg:tags":[
        "mixed",
        "concrete"
    ],
    "wof:name":"JDKU-Cart Concrete",
    "wof:placetype":"venue"
},
  "geometry": {"coordinates":[-94.137286,39.005005],"type":"Point"}
}