{
  "type": "Feature",
  "properties": {
    "iso:country":"US",
    "sg:address":"16419 Village Plaza View Dr",
    "sg:city":"Ballwin",
    "sg:classifiers":[
        {
            "category":"Farming",
            "subcategory":"Livestock Farm",
            "type":"Manufacturing & Wholesale Goods"
        }
    ],
    "sg:phone":"+1 636 458 7994",
    "sg:postcode":"63011",
    "sg:province":"MO",
    "sg:tags":[
        "horse",
        "other",
        "equine"
    ],
    "wof:name":"St Louis National Charity Show",
    "wof:placetype":"venue"
},
  "geometry": {"coordinates":[-90.617521,38.583122],"type":"Point"}
}