{
  "type": "Feature",
  "properties": {
    "iso:country":"US",
    "sg:address":"3161 Fee Fee Rd",
    "sg:city":"Bridgeton",
    "sg:classifiers":[
        {
            "category":"Real Estate",
            "subcategory":"Real Estate Agent",
            "type":"Services"
        }
    ],
    "sg:phone":"+1 314 298 2461",
    "sg:postcode":"63044",
    "sg:province":"MO",
    "wof:name":"Advantage Real Estate Svc",
    "wof:placetype":"venue"
},
  "geometry": {"coordinates":[-90.41385200000001,38.72728],"type":"Point"}
}