{
  "type": "Feature",
  "properties": {
    "iso:country":"US",
    "sg:address":"1231 Parody Ln",
    "sg:city":"St Charles",
    "sg:classifiers":[
        {
            "category":"Retail",
            "subcategory":"Repair Shop",
            "type":"Services"
        }
    ],
    "sg:phone":"+1 314 660 1292",
    "sg:postcode":"63303",
    "sg:province":"MO",
    "sg:tags":[
        "equipment",
        "conditioning",
        "air"
    ],
    "wof:name":"JCL Heating & Cooling",
    "wof:placetype":"venue"
},
  "geometry": {"coordinates":[-90.512451,38.765196],"type":"Point"}
}