{
  "type": "Feature",
  "properties": {
    "iso:country":"US",
    "sg:address":"703 Main St",
    "sg:city":"Trenton",
    "sg:classifiers":[
        {
            "category":"Social Services",
            "type":"Services"
        }
    ],
    "sg:phone":"+1 660 359 2874",
    "sg:postcode":"64683",
    "sg:province":"MO",
    "sg:tags":[
        "organization",
        "welfare"
    ],
    "wof:name":"North Central Missouri Childrn",
    "wof:placetype":"venue"
},
  "geometry": {"coordinates":[-93.61882799999999,40.074208],"type":"Point"}
}