{
  "type": "Feature",
  "properties": {
    "iso:country":"US",
    "sg:address":"19 W Olive St",
    "sg:city":"Aurora",
    "sg:classifiers":[
        {
            "category":"Shopping",
            "subcategory":"Gifts & Souvenirs",
            "type":"Retail Goods"
        },
        {
            "category":"Shopping",
            "subcategory":"Florist",
            "type":"Retail Goods"
        }
    ],
    "sg:phone":"+1 417 678 7673",
    "sg:postcode":"65605",
    "sg:province":"MO",
    "sg:tags":[
        "shop"
    ],
    "wof:name":"Betty's Floral & Gift",
    "wof:placetype":"venue"
},
  "geometry": {"coordinates":[-93.721198,36.975336],"type":"Point"}
}