{
  "type": "Feature",
  "properties": {
    "iso:country":"US",
    "sg:address":"100 N College St",
    "sg:city":"Neosho",
    "sg:classifiers":[
        {
            "category":"Professional",
            "subcategory":"Business Services",
            "type":"Services"
        }
    ],
    "sg:phone":"+1 417 455 0014",
    "sg:postcode":"64850",
    "sg:province":"MO",
    "wof:name":"Hunter Technologies",
    "wof:placetype":"venue"
},
  "geometry": {"coordinates":[-94.370885,36.870827],"type":"Point"}
}