{
  "type": "Feature",
  "properties": {
    "iso:country":"US",
    "sg:address":"40 S Sprigg St",
    "sg:city":"Cape Girardeau",
    "sg:classifiers":[
        {
            "category":"Government",
            "subcategory":"Police Station",
            "type":"Public Place"
        }
    ],
    "sg:phone":"+1 573 335 1635",
    "sg:postcode":"63703",
    "sg:province":"MO",
    "sg:tags":[
        "department",
        "protection"
    ],
    "wof:name":"Cape Girardeau Police Chief",
    "wof:placetype":"venue"
},
  "geometry": {"coordinates":[-89.527007,37.303623],"type":"Point"}
}