{
  "type": "Feature",
  "properties": {
    "iso:country":"US",
    "sg:address":"710 E 24th St",
    "sg:city":"Trenton",
    "sg:classifiers":[
        {
            "category":"Manufacturing",
            "subcategory":"Food",
            "type":"Manufacturing & Wholesale Goods"
        }
    ],
    "sg:phone":"+1 660 359 2030",
    "sg:postcode":"64683",
    "sg:province":"MO",
    "sg:tags":[
        "popcorn",
        "product"
    ],
    "wof:name":"K & W Popcorn Inc",
    "wof:placetype":"venue"
},
  "geometry": {"coordinates":[-93.611429,40.087229],"type":"Point"}
}