{
  "type": "Feature",
  "properties": {
    "iso:country":"US",
    "sg:address":"787 W Neosho St",
    "sg:city":"Granby",
    "sg:classifiers":[
        {
            "category":"Farming",
            "subcategory":"Dairy Farm",
            "type":"Manufacturing & Wholesale Goods"
        }
    ],
    "sg:phone":"+1 417 472 3280",
    "sg:postcode":"64844",
    "sg:province":"MO",
    "wof:name":"Home Town Dairy",
    "wof:placetype":"venue"
},
  "geometry": {"coordinates":[-94.266777,36.908133],"type":"Point"}
}