{
  "type": "Feature",
  "properties": {
    "iso:country":"US",
    "sg:address":"571 S Lincoln Dr",
    "sg:city":"Troy",
    "sg:classifiers":[
        {
            "category":"Manufacturing",
            "subcategory":"Glass & Minerals",
            "type":"Manufacturing & Wholesale Goods"
        }
    ],
    "sg:phone":"+1 636 528 4330",
    "sg:postcode":"63379",
    "sg:province":"MO",
    "sg:tags":[
        "ready",
        "concrete",
        "mfg"
    ],
    "wof:name":"Warren County Concrete",
    "wof:placetype":"venue"
},
  "geometry": {"coordinates":[-90.96067499999999,38.966362],"type":"Point"}
}