{
  "type": "Feature",
  "properties": {
    "iso:country":"US",
    "sg:address":"4501 Walnut St",
    "sg:city":"Kansas City",
    "sg:classifiers":[
        {
            "category":"Organizations",
            "subcategory":"Religious Organization",
            "type":"Services"
        }
    ],
    "sg:phone":"+1 816 931 9900",
    "sg:postcode":"64111",
    "sg:province":"MO",
    "sg:tags":[
        "church"
    ],
    "wof:name":"Gaia Community",
    "wof:placetype":"venue"
},
  "geometry": {"coordinates":[-94.585262,39.043172],"type":"Point"}
}