{
  "type": "Feature",
  "properties": {
    "iso:country":"US",
    "sg:address":"373 W Jackson St",
    "sg:city":"Marshall",
    "sg:classifiers":[
        {
            "category":"Organizations",
            "subcategory":"Religious Organization",
            "type":"Services"
        }
    ],
    "sg:phone":"+1 660 886 3112",
    "sg:postcode":"65340",
    "sg:province":"MO",
    "wof:name":"Saint Peters Convent",
    "wof:placetype":"venue"
},
  "geometry": {"coordinates":[-93.200419,39.117967],"type":"Point"}
}