{
  "type": "Feature",
  "properties": {
    "iso:country":"US",
    "sg:address":"393 W Old Watson Rd",
    "sg:city":"Webster Groves",
    "sg:classifiers":[
        {
            "category":"Education",
            "subcategory":"School",
            "type":"Public Place"
        }
    ],
    "sg:phone":"+1 314 961 5444",
    "sg:postcode":"63119",
    "sg:province":"MO",
    "wof:name":"Queen Of The Holy Rosary",
    "wof:placetype":"venue"
},
  "geometry": {"coordinates":[-90.36770199999999,38.563173],"type":"Point"}
}