{
  "type": "Feature",
  "properties": {
    "iso:country":"US",
    "sg:address":"12232 Saint Charles Rock Rd",
    "sg:city":"Bridgeton",
    "sg:classifiers":[
        {
            "category":"Health Services",
            "subcategory":"Health Practitioner",
            "type":"Services"
        }
    ],
    "sg:phone":"+1 314 298 1760",
    "sg:postcode":"63044",
    "sg:province":"MO",
    "sg:tags":[
        "therapist",
        "physical"
    ],
    "wof:name":"Excel Sports Physical Therapy",
    "wof:placetype":"venue"
},
  "geometry": {"coordinates":[-90.427035,38.751668],"type":"Point"}
}