{
  "type": "Feature",
  "properties": {
    "iso:country":"US",
    "sg:address":"1630 Killingsworth Ave",
    "sg:city":"Bolivar",
    "sg:classifiers":[
        {
            "category":"Banks & Credit Unions",
            "subcategory":"Bank",
            "type":"Services"
        },
        {
            "category":"Banks & Credit Unions",
            "subcategory":"Financial Services",
            "type":"Services"
        }
    ],
    "sg:phone":"+1 417 777 3322",
    "sg:postcode":"65613",
    "sg:province":"MO",
    "sg:tags":[
        "commercial",
        "loan",
        "saving"
    ],
    "sg:website":"http://www.farmersstatebank.com",
    "wof:name":"Farmers State Bank",
    "wof:placetype":"venue"
},
  "geometry": {"coordinates":[-93.435597,37.598527],"type":"Point"}
}