{
  "type": "Feature",
  "properties": {
    "iso:country":"US",
    "sg:address":"1361 Co Rd 536",
    "sg:city":"Caruthersville",
    "sg:phone":"+1 573 359 1033",
    "sg:postcode":"63830",
    "sg:province":"MO",
    "sg:tags":[
        "farm",
        "corn",
        "grain",
        "cash",
        "soybean"
    ],
    "wof:name":"Bill Jean Farm",
    "wof:placetype":"venue"
},
  "geometry": {"coordinates":[-89.71708700000001,36.117623],"type":"Point"}
}