{
  "type": "Feature",
  "properties": {
    "iso:country":"US",
    "sg:address":"1400 S Limit Ave",
    "sg:city":"Sedalia",
    "sg:classifiers":[
        {
            "category":"Fast Food",
            "type":"Food & Drink"
        }
    ],
    "sg:phone":"+1 660 826 0370",
    "sg:postcode":"65301",
    "sg:province":"MO",
    "sg:tags":[
        "restaurant"
    ],
    "sg:website":"http://www.hardees.com",
    "wof:name":"Hardee's",
    "wof:placetype":"venue"
},
  "geometry": {"coordinates":[-93.250519,38.700718],"type":"Point"}
}