{
  "type": "Feature",
  "properties": {
    "iso:country":"US",
    "sg:address":"3625 Holmes St",
    "sg:city":"Kansas City",
    "sg:classifiers":[
        {
            "category":"Shopping",
            "subcategory":"Clothing, Apparel, & Fashions",
            "type":"Retail Goods"
        }
    ],
    "sg:phone":"+1 816 531 5348",
    "sg:postcode":"64109",
    "sg:province":"MO",
    "sg:tags":[
        "civil",
        "flag",
        "war",
        "era"
    ],
    "wof:name":"Key Goods & Arms",
    "wof:placetype":"venue"
},
  "geometry": {"coordinates":[-94.576559,39.059025],"type":"Point"}
}