{
  "type": "Feature",
  "properties": {
    "iso:country":"US",
    "sg:address":"415 W 13 St",
    "sg:city":"Kansas City",
    "sg:classifiers":[
        {
            "category":"Organizations",
            "subcategory":"Religious Organization",
            "type":"Services"
        }
    ],
    "sg:phone":"+1 816 474 8260",
    "sg:postcode":"64105",
    "sg:province":"MO",
    "sg:tags":[
        "church"
    ],
    "sg:website":"www.ghtc-kc.org",
    "wof:name":"Grace & Holy Trinity Cathedral",
    "wof:placetype":"venue"
},
  "geometry": {"coordinates":[-94.589876,39.098721],"type":"Point"}
}