{
  "type": "Feature",
  "properties": {
    "iso:country":"US",
    "sg:address":"1551 Wall St",
    "sg:city":"Saint Charles",
    "sg:classifiers":[
        {
            "category":"Health Services",
            "subcategory":"Doctor",
            "type":"Services"
        }
    ],
    "sg:phone":"+1 636 946 1720",
    "sg:postcode":"63303",
    "sg:province":"MO",
    "sg:tags":[
        "medical"
    ],
    "wof:name":"Saint Charles Clinic Med Group",
    "wof:placetype":"venue"
},
  "geometry": {"coordinates":[-90.524293,38.779747],"type":"Point"}
}