{
  "type": "Feature",
  "properties": {
    "iso:country":"US",
    "sg:address":"110 W Industrial Rd",
    "sg:city":"Fulton",
    "sg:classifiers":[
        {
            "category":"Manufacturing",
            "subcategory":"Tools & Machinery",
            "type":"Manufacturing & Wholesale Goods"
        }
    ],
    "sg:phone":"+1 573 642 5554",
    "sg:postcode":"65251",
    "sg:province":"MO",
    "sg:tags":[
        "surgical",
        "mfg"
    ],
    "wof:name":"PSL Fabrication",
    "wof:placetype":"venue"
},
  "geometry": {"coordinates":[-91.95040899999999,38.871158],"type":"Point"}
}