{
  "type": "Feature",
  "properties": {
    "iso:country":"US",
    "sg:address":"4530 E 75 Ter",
    "sg:city":"Kansas City",
    "sg:classifiers":[
        {
            "category":"Manufacturing",
            "subcategory":"Tools & Machinery",
            "type":"Manufacturing & Wholesale Goods"
        }
    ],
    "sg:phone":"+1 816 363 1030",
    "sg:postcode":"64132",
    "sg:province":"MO",
    "sg:tags":[
        "food",
        "product"
    ],
    "sg:website":"www.salvajor.com",
    "wof:name":"Salvajor Co",
    "wof:placetype":"venue"
},
  "geometry": {"coordinates":[-94.532121,38.988341],"type":"Point"}
}