{
  "type": "Feature",
  "properties": {
    "iso:country":"US",
    "sg:address":"3419 W 32nd St",
    "sg:city":"Sedalia",
    "sg:classifiers":[
        {
            "category":"Building & Trades",
            "subcategory":"Electrical",
            "type":"Services"
        }
    ],
    "sg:phone":"+1 660 827 5611",
    "sg:postcode":"65301",
    "sg:province":"MO",
    "sg:tags":[
        "electrical",
        "contractor"
    ],
    "wof:name":"Kilby Electric",
    "wof:placetype":"venue"
},
  "geometry": {"coordinates":[-93.26883100000001,38.684627],"type":"Point"}
}