{
  "type": "Feature",
  "properties": {
    "iso:country":"US",
    "sg:address":"17954 Beattie Rd",
    "sg:city":"Higginsville",
    "sg:classifiers":[
        {
            "category":"Farming",
            "subcategory":"Livestock Farm",
            "type":"Manufacturing & Wholesale Goods"
        }
    ],
    "sg:phone":"+1 660 584 6440",
    "sg:postcode":"64037",
    "sg:province":"MO",
    "sg:tags":[
        "buyer"
    ],
    "wof:name":"Rian Livestock Corp",
    "wof:placetype":"venue"
},
  "geometry": {"coordinates":[-93.77761099999999,39.072338],"type":"Point"}
}