{
  "type": "Feature",
  "properties": {
    "addr:full":"901 E Saint Louis St Springfield MO 65806",
    "addr:housenumber":"901",
    "addr:postcode":"65806",
    "addr:street":"E Saint Louis St",
    "iso:country":"US",
    "sg:address":"901 E Saint Louis St",
    "sg:city":"Springfield",
    "sg:classifiers":[
        {
            "category":"Government",
            "subcategory":"Office",
            "type":"Public Place"
        }
    ],
    "sg:phone":"+1 417 863 0190",
    "sg:postcode":"65806",
    "sg:province":"MO",
    "sg:tags":[
        "federal",
        "human"
    ],
    "wof:name":"US Social Security Adm",
    "wof:placetype":"venue"
},
  "geometry": {"coordinates":[-93.281854,37.208925],"type":"Point"}
}