{
  "type": "Feature",
  "properties": {
    "iso:country":"US",
    "sg:address":"21421 Ibex Rd",
    "sg:city":"Goodman",
    "sg:classifiers":[
        {
            "category":"Restaurant",
            "type":"Food & Drink"
        }
    ],
    "sg:phone":"+1 417 364 7855",
    "sg:postcode":"64843",
    "sg:province":"MO",
    "sg:tags":[
        "eating"
    ],
    "wof:name":"Low Carb Cafe",
    "wof:placetype":"venue"
},
  "geometry": {"coordinates":[-94.451331,36.769331],"type":"Point"}
}