{
  "type": "Feature",
  "properties": {
    "addr:full":"1403 Hillcrest Plz Doniphan MO 63935",
    "addr:housenumber":"1403",
    "addr:postcode":"63935",
    "addr:street":"Hillcrest Plz",
    "iso:country":"US",
    "sg:address":"1403 Hillcrest Plz",
    "sg:city":"Doniphan",
    "sg:classifiers":[
        {
            "category":"Shopping",
            "subcategory":"Department Store",
            "type":"Retail Goods"
        },
        {
            "category":"Shopping",
            "subcategory":"Discount & Variety Stores",
            "type":"Retail Goods"
        },
        {
            "category":"Shopping",
            "type":"Retail Goods"
        },
        {
            "category":"Food & Beverages",
            "subcategory":"Groceries & Convenience Stores",
            "type":"Retail Goods"
        }
    ],
    "sg:phone":"+1 573 996 3050",
    "sg:postcode":"63935",
    "sg:province":"MO",
    "sg:tags":[
        "merchandise"
    ],
    "sg:website":"http://www.dollargeneral.com",
    "wof:name":"Dollar General",
    "wof:placetype":"venue"
},
  "geometry": {"coordinates":[-90.826078,36.628751],"type":"Point"}
}