{
  "type": "Feature",
  "properties": {
    "iso:country":"US",
    "sg:address":"1132 W Kansas St",
    "sg:city":"Liberty",
    "sg:classifiers":[
        {
            "category":"Community Center",
            "subcategory":"Senior",
            "type":"Public Place"
        },
        {
            "category":"Health Services",
            "subcategory":"Nursing And Care Facility",
            "type":"Services"
        },
        {
            "category":"Health Services",
            "subcategory":"Health Practitioner",
            "type":"Services"
        }
    ],
    "sg:phone":"+1 816 792 8077",
    "sg:postcode":"64068",
    "sg:province":"MO",
    "sg:tags":[
        "home",
        "eldercare-home",
        "citizen"
    ],
    "sg:website":"http://www.homeinstead.com",
    "wof:name":"Home Instead Senior Care",
    "wof:placetype":"venue"
},
  "geometry": {"coordinates":[-94.43877999999999,39.245084],"type":"Point"}
}