{
  "type": "Feature",
  "properties": {
    "iso:country":"US",
    "sg:address":"634 N Main Ave",
    "sg:city":"Republic",
    "sg:classifiers":[
        {
            "category":"Education",
            "subcategory":"School",
            "type":"Public Place"
        }
    ],
    "sg:phone":"+1 417 732 3685",
    "sg:postcode":"65738",
    "sg:province":"MO",
    "wof:name":"Maintenance Dept",
    "wof:placetype":"venue"
},
  "geometry": {"coordinates":[-93.48015599999999,37.126429],"type":"Point"}
}