{
  "type": "Feature",
  "properties": {
    "iso:country":"US",
    "sg:address":"221 N Elgin Ave",
    "sg:city":"Bolivar",
    "sg:classifiers":[
        {
            "category":"Social Services",
            "subcategory":"Child Care",
            "type":"Services"
        }
    ],
    "sg:phone":"+1 417 326 3277",
    "sg:postcode":"65613",
    "sg:province":"MO",
    "sg:tags":[
        "nursery",
        "day"
    ],
    "wof:name":"Red Cupola Childcare Center",
    "wof:placetype":"venue"
},
  "geometry": {"coordinates":[-93.401439,37.616137],"type":"Point"}
}