{
  "type": "Feature",
  "properties": {
    "iso:country":"US",
    "sg:address":"600 N Main St",
    "sg:city":"Piedmont",
    "sg:classifiers":[
        {
            "category":"Food & Beverages",
            "subcategory":"Groceries & Convenience Stores",
            "type":"Retail Goods"
        }
    ],
    "sg:phone":"+1 573 223 7420",
    "sg:postcode":"63957",
    "sg:province":"MO",
    "sg:tags":[
        "grocer"
    ],
    "wof:name":"Lane's Salvage Groceries",
    "wof:placetype":"venue"
},
  "geometry": {"coordinates":[-90.691237,37.159546],"type":"Point"}
}