{
  "type": "Feature",
  "properties": {
    "iso:country":"US",
    "sg:address":"2175 Charbonier Rd",
    "sg:city":"Florissant",
    "sg:classifiers":[
        {
            "category":"Health Services",
            "subcategory":"Doctor",
            "type":"Services"
        }
    ],
    "sg:phone":"+1 314 831 1939",
    "sg:postcode":"63031",
    "sg:province":"MO",
    "sg:tags":[
        "clinic"
    ],
    "wof:name":"Patterson Medical",
    "wof:placetype":"venue"
},
  "geometry": {"coordinates":[-90.358614,38.80855],"type":"Point"}
}