{
  "type": "Feature",
  "properties": {
    "iso:country":"US",
    "sg:address":"16755 Indian Rd",
    "sg:city":"Carthage",
    "sg:classifiers":[
        {
            "category":"Professional",
            "type":"Services"
        }
    ],
    "sg:phone":"+1 417 358 7720",
    "sg:postcode":"64836",
    "sg:province":"MO",
    "wof:name":"Greg Cook",
    "wof:placetype":"venue"
},
  "geometry": {"coordinates":[-94.35941,37.170215],"type":"Point"}
}