{
  "type": "Feature",
  "properties": {
    "iso:country":"US",
    "sg:address":"3945 Main St",
    "sg:city":"Kansas City",
    "sg:classifiers":[
        {
            "category":"Shopping",
            "subcategory":"Stationery & Office Supplies",
            "type":"Retail Goods"
        }
    ],
    "sg:phone":"+1 816 931 2880",
    "sg:postcode":"64111",
    "sg:province":"MO",
    "sg:tags":[
        "equipment",
        "filing",
        "system"
    ],
    "wof:name":"Safeguard Business Systems",
    "wof:placetype":"venue"
},
  "geometry": {"coordinates":[-94.58607600000001,39.055892],"type":"Point"}
}