{
  "type": "Feature",
  "properties": {
    "iso:country":"US",
    "sg:address":"4169 State Hwy Pp",
    "sg:city":"Poplar Bluff",
    "sg:classifiers":[
        {
            "category":"Utilities",
            "subcategory":"Electric",
            "type":"Services"
        }
    ],
    "sg:phone":"+1 573 785 9651",
    "sg:postcode":"63901",
    "sg:province":"MO",
    "sg:tags":[
        "company"
    ],
    "wof:name":"M & A Elect Power Co-Op",
    "wof:placetype":"venue"
},
  "geometry": {"coordinates":[-90.464226,36.767161],"type":"Point"}
}