{
  "type": "Feature",
  "properties": {
    "iso:country":"US",
    "sg:address":"3803 Bent Oak Dr",
    "sg:city":"Columbia",
    "sg:classifiers":[
        {
            "category":"Building & Trades",
            "subcategory":"Construction",
            "type":"Services"
        }
    ],
    "sg:phone":"+1 573 445 5768",
    "sg:postcode":"65203",
    "sg:province":"MO",
    "sg:tags":[
        "painter"
    ],
    "wof:name":"Hill's Painting Of Columbia",
    "wof:placetype":"venue"
},
  "geometry": {"coordinates":[-92.393896,38.92483],"type":"Point"}
}