{
  "type": "Feature",
  "properties": {
    "iso:country":"US",
    "sg:address":"20803 State Hwy Y",
    "sg:city":"Belton",
    "sg:classifiers":[
        {
            "category":"Recreation",
            "type":"Entertainment"
        }
    ],
    "sg:phone":"+1 816 331 4923",
    "sg:postcode":"64012",
    "sg:province":"MO",
    "wof:name":"Plainview Stables",
    "wof:placetype":"venue"
},
  "geometry": {"coordinates":[-94.534132,38.748551],"type":"Point"}
}