{
  "type": "Feature",
  "properties": {
    "iso:country":"US",
    "sg:address":"1101 Lucas Ave",
    "sg:city":"St Louis",
    "sg:classifiers":[
        {
            "category":"Real Estate",
            "subcategory":"Developer",
            "type":"Services"
        }
    ],
    "sg:phone":"+1 314 436 5380",
    "sg:postcode":"63101",
    "sg:province":"MO",
    "wof:name":"Downtown North Dev Group LLC",
    "wof:placetype":"venue"
},
  "geometry": {"coordinates":[-90.196505,38.632303],"type":"Point"}
}