{
  "type": "Feature",
  "properties": {
    "iso:country":"US",
    "sg:address":"818 N 5th St",
    "sg:city":"Festus",
    "sg:classifiers":[
        {
            "category":"Health Services",
            "subcategory":"Doctor",
            "type":"Services"
        }
    ],
    "sg:phone":"+1 636 937 9336",
    "sg:postcode":"63028",
    "sg:province":"MO",
    "sg:tags":[
        "physician",
        "surgeon"
    ],
    "wof:name":"Joseph J Elterman",
    "wof:placetype":"venue"
},
  "geometry": {"coordinates":[-90.398965,38.223994],"type":"Point"}
}