{
  "type": "Feature",
  "properties": {
    "iso:country":"US",
    "sg:address":"1902 Union Blvd",
    "sg:city":"Saint Louis",
    "sg:classifiers":[
        {
            "category":"Social Services",
            "subcategory":"Child Care",
            "type":"Services"
        }
    ],
    "sg:phone":"+1 314 382 8442",
    "sg:postcode":"63113",
    "sg:province":"MO",
    "sg:tags":[
        "day"
    ],
    "wof:name":"Purvey & Porter Small World No 2",
    "wof:placetype":"venue"
},
  "geometry": {"coordinates":[-90.2658,38.668201],"type":"Point"}
}