{
  "type": "Feature",
  "properties": {
    "iso:country":"US",
    "sg:address":"2010 S Stewart Ave",
    "sg:city":"Springfield",
    "sg:classifiers":[
        {
            "category":"Manufacturing",
            "subcategory":"Printing",
            "type":"Manufacturing & Wholesale Goods"
        }
    ],
    "sg:phone":"+1 417 862 0852",
    "sg:postcode":"65804",
    "sg:province":"MO",
    "sg:tags":[
        "newspaper"
    ],
    "wof:name":"Senior Living Newspaper",
    "wof:placetype":"venue"
},
  "geometry": {"coordinates":[-93.260153,37.180796],"type":"Point"}
}