{
  "type": "Feature",
  "properties": {
    "iso:country":"US",
    "sg:address":"611 Cheryl Ann Dr",
    "sg:city":"Wentzville",
    "sg:classifiers":[
        {
            "category":"Building & Trades",
            "subcategory":"Construction",
            "type":"Services"
        }
    ],
    "sg:phone":"+1 636 332 8756",
    "sg:postcode":"63385",
    "sg:province":"MO",
    "sg:tags":[
        "contractor"
    ],
    "wof:name":"Above All Roofing",
    "wof:placetype":"venue"
},
  "geometry": {"coordinates":[-90.86143800000001,38.815735],"type":"Point"}
}