{
  "type": "Feature",
  "properties": {
    "iso:country":"US",
    "sg:address":"507 Hamilton St",
    "sg:city":"Warrensburg",
    "sg:classifiers":[
        {
            "category":"Building & Trades",
            "subcategory":"Construction",
            "type":"Services"
        }
    ],
    "sg:phone":"+1 660 429 1350",
    "sg:postcode":"64093",
    "sg:province":"MO",
    "sg:tags":[
        "house"
    ],
    "wof:name":"B&S Construction",
    "wof:placetype":"venue"
},
  "geometry": {"coordinates":[-93.731407,38.752896],"type":"Point"}
}