{
  "type": "Feature",
  "properties": {
    "iso:country":"US",
    "sg:address":"129 Riverview Dr",
    "sg:city":"Anderson",
    "sg:classifiers":[
        {
            "category":"Professional",
            "subcategory":"Management & Consulting",
            "type":"Services"
        },
        {
            "category":"Professional",
            "subcategory":"Advertising",
            "type":"Services"
        }
    ],
    "sg:phone":"+1 417 850 3498",
    "sg:postcode":"64831",
    "sg:province":"MO",
    "sg:tags":[
        "marketing",
        "program",
        "consultant"
    ],
    "wof:name":"Multi-Marketing & Distribution",
    "wof:placetype":"venue"
},
  "geometry": {"coordinates":[-94.438906,36.64063],"type":"Point"}
}