{
  "type": "Feature",
  "properties": {
    "addr:full":"5531 Hamilton Ave Saint Louis MO 63136",
    "addr:housenumber":"5531",
    "addr:postcode":"63136",
    "addr:street":"Hamilton Ave",
    "iso:country":"US",
    "sg:address":"5531 Hamilton Ave",
    "sg:city":"Saint Louis",
    "sg:classifiers":[
        {
            "category":"Arts & Performance",
            "subcategory":"Theater",
            "type":"Entertainment"
        }
    ],
    "sg:phone":"+1 314 381 4682",
    "sg:postcode":"63136",
    "sg:province":"MO",
    "sg:tags":[
        "group"
    ],
    "wof:name":"Zealous Entertainment Entp",
    "wof:placetype":"venue"
},
  "geometry": {"coordinates":[-90.261157,38.710558],"type":"Point"}
}