{
  "type": "Feature",
  "properties": {
    "iso:country":"US",
    "sg:address":"5904 Beechwood Ct",
    "sg:city":"Kansas City",
    "sg:classifiers":[
        {
            "category":"Professional",
            "subcategory":"Computer Services",
            "type":"Services"
        }
    ],
    "sg:phone":"+1 816 587 3185",
    "sg:postcode":"64152",
    "sg:province":"MO",
    "sg:tags":[
        "programing",
        "custom"
    ],
    "wof:name":"New Angle Technology",
    "wof:placetype":"venue"
},
  "geometry": {"coordinates":[-94.66117800000001,39.206524],"type":"Point"}
}