{
  "type": "Feature",
  "properties": {
    "iso:country":"US",
    "sg:address":"3680 Taylor Ave",
    "sg:city":"Saint Louis",
    "sg:classifiers":[
        {
            "category":"Real Estate",
            "subcategory":"Real Estate Services",
            "type":"Services"
        }
    ],
    "sg:phone":"+1 314 995 0616",
    "sg:postcode":"63044",
    "sg:province":"MO",
    "wof:name":"Majestic Real Estate",
    "wof:placetype":"venue"
},
  "geometry": {"coordinates":[-90.239397,38.671017],"type":"Point"}
}