{
  "type": "Feature",
  "properties": {
    "iso:country":"US",
    "sg:address":"1600 Skyview",
    "sg:city":"Holts Summit",
    "sg:classifiers":[
        {
            "category":"Professional",
            "subcategory":"Management & Consulting",
            "type":"Services"
        }
    ],
    "sg:phone":"+1 573 896 5842",
    "sg:postcode":"65043",
    "sg:province":"MO",
    "sg:tags":[
        "marketing",
        "consultant"
    ],
    "wof:name":"Zimm Comm",
    "wof:placetype":"venue"
},
  "geometry": {"coordinates":[-92.144723,38.614424],"type":"Point"}
}