{
  "type": "Feature",
  "properties": {
    "iso:country":"US",
    "sg:address":"10907 Leighton Ct",
    "sg:city":"Saint Louis",
    "sg:classifiers":[
        {
            "category":"Professional",
            "subcategory":"Research",
            "type":"Services"
        }
    ],
    "sg:phone":"+1 314 583 0835",
    "sg:postcode":"63146",
    "sg:province":"MO",
    "sg:tags":[
        "development",
        "scientific"
    ],
    "wof:name":"Diapeutix Inc",
    "wof:placetype":"venue"
},
  "geometry": {"coordinates":[-90.42156199999999,38.678572],"type":"Point"}
}