{
  "type": "Feature",
  "properties": {
    "iso:country":"US",
    "sg:address":"7412 W Country Hill Rd",
    "sg:city":"Columbia",
    "sg:classifiers":[
        {
            "category":"Building & Trades",
            "subcategory":"Construction",
            "type":"Services"
        }
    ],
    "sg:phone":"+1 573 808 0134",
    "sg:postcode":"65202",
    "sg:province":"MO",
    "sg:tags":[
        "handyman"
    ],
    "sg:website":"http://www.aandbservicesllc.com",
    "wof:name":"A&B Services, LLC",
    "wof:placetype":"venue"
},
  "geometry": {"coordinates":[-92.44914900000001,38.982059],"type":"Point"}
}