{
  "type": "Feature",
  "properties": {
    "iso:country":"US",
    "sg:address":"1819 Wyandotte St",
    "sg:city":"Kansas City",
    "sg:classifiers":[
        {
            "category":"Real Estate",
            "subcategory":"Real Estate Agent",
            "type":"Services"
        }
    ],
    "sg:phone":"+1 816 333 4545",
    "sg:postcode":"64108",
    "sg:province":"MO",
    "wof:name":"Boveri Realty Group LLC",
    "wof:placetype":"venue"
},
  "geometry": {"coordinates":[-94.585926,39.091125],"type":"Point"}
}