{
  "type": "Feature",
  "properties": {
    "iso:country":"US",
    "sg:address":"418 N Byers Ave",
    "sg:city":"Joplin",
    "sg:classifiers":[
        {
            "category":"Health Services",
            "subcategory":"Doctor",
            "type":"Services"
        }
    ],
    "sg:phone":"+1 417 623 7034",
    "sg:postcode":"64801",
    "sg:province":"MO",
    "sg:tags":[
        "physician",
        "surgeon"
    ],
    "wof:name":"Alan Creek DO",
    "wof:placetype":"venue"
},
  "geometry": {"coordinates":[-94.517618,37.095356],"type":"Point"}
}