{
  "type": "Feature",
  "properties": {
    "addr:full":"1784 Wentzville Pkwy Wentzville MO 63385",
    "addr:housenumber":"1784",
    "addr:postcode":"63385",
    "addr:street":"Wentzville Pkwy",
    "iso:country":"US",
    "sg:address":"1784 Wentzville Pkwy",
    "sg:city":"Wentzville",
    "sg:classifiers":[
        {
            "category":"Fast Food",
            "type":"Food & Drink"
        },
        {
            "category":"Restaurant",
            "type":"Food & Drink"
        }
    ],
    "sg:phone":"+1 636 887 4833",
    "sg:postcode":"63385",
    "sg:province":"MO",
    "sg:tags":[
        "mexican",
        "take"
    ],
    "sg:website":"http://www.qdoba.com/",
    "wof:name":"Qdoba Mexican Grill",
    "wof:placetype":"venue"
},
  "geometry": {"coordinates":[-90.877216,38.817471],"type":"Point"}
}