{
  "type": "Feature",
  "properties": {
    "iso:country":"US",
    "sg:address":"15471 Manchester Rd",
    "sg:city":"Ballwin",
    "sg:classifiers":[
        {
            "category":"Utilities",
            "subcategory":"Mobile Phone",
            "type":"Services"
        }
    ],
    "sg:phone":"+1 636 227 4400",
    "sg:postcode":"63011",
    "sg:province":"MO",
    "sg:tags":[
        "communications",
        "cellular"
    ],
    "wof:name":"Verizon",
    "wof:placetype":"venue"
},
  "geometry": {"coordinates":[-90.564328,38.59284],"type":"Point"}
}