{
  "type": "Feature",
  "properties": {
    "iso:country":"US",
    "sg:address":"36817 Highway 87",
    "sg:city":"California",
    "sg:classifiers":[
        {
            "category":"Manufacturing",
            "subcategory":"Buildings",
            "type":"Manufacturing & Wholesale Goods"
        },
        {
            "category":"Building & Trades",
            "subcategory":"Construction",
            "type":"Services"
        }
    ],
    "sg:phone":"+1 573 796 2874",
    "sg:postcode":"65018",
    "sg:province":"MO",
    "sg:tags":[
        "altering",
        "home",
        "builder",
        "remodeling",
        "contractor"
    ],
    "wof:name":"K N Construction",
    "wof:placetype":"venue"
},
  "geometry": {"coordinates":[-92.575248,38.538716],"type":"Point"}
}