{
  "type": "Feature",
  "properties": {
    "iso:country":"US",
    "sg:address":"308 Sibley Rd",
    "sg:city":"Orrick",
    "sg:classifiers":[
        {
            "category":"Manufacturing",
            "subcategory":"Tools & Machinery",
            "type":"Manufacturing & Wholesale Goods"
        }
    ],
    "sg:phone":"+1 816 496 3625",
    "sg:postcode":"64077",
    "sg:province":"MO",
    "sg:tags":[
        "farm",
        "soybean",
        "mfg"
    ],
    "wof:name":"Wilbur Battagler Farms",
    "wof:placetype":"venue"
},
  "geometry": {"coordinates":[-94.136861,39.210969],"type":"Point"}
}