{
  "type": "Feature",
  "properties": {
    "iso:country":"US",
    "sg:address":"2534 N Grand Blvd",
    "sg:city":"Saint Louis",
    "sg:classifiers":[
        {
            "category":"Travel",
            "subcategory":"Hotels & Motels",
            "type":"Entertainment"
        }
    ],
    "sg:phone":"+1 314 534 9164",
    "sg:postcode":"63106",
    "sg:province":"MO",
    "wof:name":"Grand Motel",
    "wof:placetype":"venue"
},
  "geometry": {"coordinates":[-90.222397,38.653],"type":"Point"}
}