{
  "type": "Feature",
  "properties": {
    "iso:country":"US",
    "sg:address":"119 Main St",
    "sg:city":"Steelville",
    "sg:classifiers":[
        {
            "category":"Restaurant",
            "type":"Food & Drink"
        }
    ],
    "sg:phone":"+1 573 775 2077",
    "sg:postcode":"65565",
    "sg:province":"MO",
    "wof:name":"Spare Rib Inn",
    "wof:placetype":"venue"
},
  "geometry": {"coordinates":[-91.354938,37.968028],"type":"Point"}
}