{
  "type": "Feature",
  "properties": {
    "iso:country":"US",
    "sg:address":"8112 Page Ave",
    "sg:city":"St Louis",
    "sg:classifiers":[
        {
            "category":"Manufacturing",
            "subcategory":"Metals",
            "type":"Manufacturing & Wholesale Goods"
        }
    ],
    "sg:phone":"+1 314 721 1300",
    "sg:postcode":"63130",
    "sg:province":"MO",
    "sg:tags":[
        "fence"
    ],
    "wof:name":"Ferguson American Fence Co",
    "wof:placetype":"venue"
},
  "geometry": {"coordinates":[-90.333215,38.683251],"type":"Point"}
}