{
  "type": "Feature",
  "properties": {
    "iso:country":"US",
    "sg:address":"8610 E 89 St",
    "sg:city":"Kansas City",
    "sg:classifiers":[
        {
            "category":"Professional",
            "subcategory":"Accounting & Tax Preparation",
            "type":"Services"
        }
    ],
    "sg:phone":"+1 816 761 1227",
    "sg:postcode":"64138",
    "sg:province":"MO",
    "wof:name":"Thomas E Tharp",
    "wof:placetype":"venue"
},
  "geometry": {"coordinates":[-94.487143,38.962693],"type":"Point"}
}