{
  "type": "Feature",
  "properties": {
    "iso:country":"US",
    "sg:address":"3382 Old Baumgartner Rd",
    "sg:city":"Saint Louis",
    "sg:classifiers":[
        {
            "category":"Wholesale",
            "subcategory":"Vending Machines",
            "type":"Manufacturing & Wholesale Goods"
        }
    ],
    "sg:phone":"+1 314 846 0736",
    "sg:postcode":"63129",
    "sg:province":"MO",
    "sg:tags":[
        "operated",
        "coin",
        "video",
        "amusement"
    ],
    "wof:name":"Amusements Unlimited Inc",
    "wof:placetype":"venue"
},
  "geometry": {"coordinates":[-90.324489,38.469712],"type":"Point"}
}