{
  "type": "Feature",
  "properties": {
    "iso:country":"US",
    "sg:address":"401 Jeb St",
    "sg:city":"Willard",
    "sg:classifiers":[
        {
            "category":"Arts & Performance",
            "subcategory":"Theater",
            "type":"Entertainment"
        }
    ],
    "sg:phone":"+1 417 742 0652",
    "sg:postcode":"65781",
    "sg:province":"MO",
    "sg:tags":[
        "group"
    ],
    "wof:name":"Digitraxx Music 2 Go",
    "wof:placetype":"venue"
},
  "geometry": {"coordinates":[-93.42264,37.29078],"type":"Point"}
}