{
  "type": "Feature",
  "properties": {
    "iso:country":"US",
    "sg:address":"12024 Manchester Rd",
    "sg:city":"Saint Louis",
    "sg:classifiers":[
        {
            "category":"Insurance",
            "subcategory":"Insurance Agent",
            "type":"Services"
        }
    ],
    "sg:phone":"+1 314 822 7174",
    "sg:postcode":"63131",
    "sg:province":"MO",
    "sg:tags":[
        "retail",
        "used",
        "merchandise"
    ],
    "wof:name":"Longshaw Fred Insurance",
    "wof:placetype":"venue"
},
  "geometry": {"coordinates":[-90.43608399999999,38.601887],"type":"Point"}
}