{
  "type": "Feature",
  "properties": {
    "iso:country":"US",
    "sg:address":"1006 W Main St",
    "sg:city":"Imperial",
    "sg:classifiers":[
        {
            "category":"Insurance",
            "subcategory":"Life Insurance",
            "type":"Services"
        }
    ],
    "sg:phone":"+1 636 464 9804",
    "sg:postcode":"63052",
    "sg:province":"MO",
    "sg:tags":[
        "carrier"
    ],
    "wof:name":"Cane Leach McLean Insuran",
    "wof:placetype":"venue"
},
  "geometry": {"coordinates":[-90.376842,38.368947],"type":"Point"}
}