{
  "type": "Feature",
  "properties": {
    "iso:country":"US",
    "sg:address":"1447 Jeffco Blvd",
    "sg:city":"Arnold",
    "sg:classifiers":[
        {
            "category":"Building & Trades",
            "subcategory":"Pest Control",
            "type":"Services"
        }
    ],
    "sg:phone":"+1 636 287 3334",
    "sg:postcode":"63010",
    "sg:province":"MO",
    "wof:name":"Pelster Greg United Spray Svc",
    "wof:placetype":"venue"
},
  "geometry": {"coordinates":[-90.375924,38.434325],"type":"Point"}
}