{
  "type": "Feature",
  "properties": {
    "iso:country":"US",
    "sg:address":"637 Prospect Ave",
    "sg:city":"Kansas City",
    "sg:classifiers":[
        {
            "category":"Manufacturing",
            "subcategory":"Food",
            "type":"Manufacturing & Wholesale Goods"
        },
        {
            "category":"Wholesale",
            "subcategory":"Meat",
            "type":"Manufacturing & Wholesale Goods"
        }
    ],
    "sg:phone":"+1 816 241 4700",
    "sg:postcode":"64124",
    "sg:province":"MO",
    "sg:tags":[
        "frozen",
        "fresh",
        "product",
        "manufacturer"
    ],
    "wof:name":"S & S Meat Company Inc",
    "wof:placetype":"venue"
},
  "geometry": {"coordinates":[-94.551014,39.105274],"type":"Point"}
}