{
  "type": "Feature",
  "properties": {
    "iso:country":"US",
    "sg:address":"16813 E 23rd St S",
    "sg:city":"Independence",
    "sg:classifiers":[
        {
            "category":"Shopping",
            "subcategory":"Used Merchandise",
            "type":"Retail Goods"
        }
    ],
    "sg:phone":"+1 816 833 8905",
    "sg:postcode":"64055",
    "sg:province":"MO",
    "sg:tags":[
        "shop",
        "thrift"
    ],
    "wof:name":"Military Order The Purple",
    "wof:placetype":"venue"
},
  "geometry": {"coordinates":[-94.37764,39.077723],"type":"Point"}
}