{
  "type": "Feature",
  "properties": {
    "iso:country":"US",
    "sg:address":"120 Forest Acres Ln",
    "sg:city":"Troy",
    "sg:classifiers":[
        {
            "category":"Transit Center",
            "subcategory":"Freight",
            "type":"Transportation"
        }
    ],
    "sg:phone":"+1 636 236 0299",
    "sg:postcode":"63379",
    "sg:province":"MO",
    "sg:tags":[
        "trucking-light",
        "hauling"
    ],
    "wof:name":"Schulte Hauling",
    "wof:placetype":"venue"
},
  "geometry": {"coordinates":[-91.028808,38.933831],"type":"Point"}
}