{
  "type": "Feature",
  "properties": {
    "iso:country":"US",
    "sg:address":"9401 Koenig Cir",
    "sg:city":"Saint Louis",
    "sg:classifiers":[
        {
            "category":"Freight",
            "type":"Transportation"
        }
    ],
    "sg:phone":"+1 314 928 7441",
    "sg:postcode":"63134",
    "sg:province":"MO",
    "sg:tags":[
        "arrangement"
    ],
    "wof:name":"Exel",
    "wof:placetype":"venue"
},
  "geometry": {"coordinates":[-90.33752,38.725194],"type":"Point"}
}