{
  "type": "Feature",
  "properties": {
    "iso:country":"US",
    "sg:address":"7616 Wydown Blvd",
    "sg:city":"St Louis",
    "sg:classifiers":[
        {
            "category":"Shopping",
            "subcategory":"Florist",
            "type":"Retail Goods"
        },
        {
            "category":"Professional",
            "subcategory":"Business Services",
            "type":"Services"
        }
    ],
    "sg:phone":"+1 314 727 1166",
    "sg:postcode":"63105",
    "sg:province":"MO",
    "sg:tags":[
        "floral",
        "design"
    ],
    "wof:name":"A Floral Gallery Co",
    "wof:placetype":"venue"
},
  "geometry": {"coordinates":[-90.332994,38.642894],"type":"Point"}
}