{
  "type": "Feature",
  "properties": {
    "iso:country":"US",
    "sg:address":"16039 Lone Grove Rd",
    "sg:city":"Bunceton",
    "sg:classifiers":[
        {
            "category":"Farming",
            "subcategory":"Dairy Farm",
            "type":"Manufacturing & Wholesale Goods"
        }
    ],
    "sg:phone":"+1 660 427 5476",
    "sg:postcode":"65237",
    "sg:province":"MO",
    "wof:name":"Lenz View Dairy",
    "wof:placetype":"venue"
},
  "geometry": {"coordinates":[-92.74074899999999,38.806543],"type":"Point"}
}