{
  "type": "Feature",
  "properties": {
    "iso:country":"US",
    "sg:address":"5901 Lynn View Acres",
    "sg:city":"Hillsboro",
    "sg:classifiers":[
        {
            "category":"Manufacturing",
            "subcategory":"Buildings",
            "type":"Manufacturing & Wholesale Goods"
        }
    ],
    "sg:phone":"+1 636 274 0813",
    "sg:postcode":"63050",
    "sg:province":"MO",
    "sg:tags":[
        "mobile",
        "home",
        "mfg"
    ],
    "wof:name":"R & B Mobile Home Service Inc",
    "wof:placetype":"venue"
},
  "geometry": {"coordinates":[-90.588555,38.298193],"type":"Point"}
}