{
  "type": "Feature",
  "properties": {
    "iso:country":"US",
    "sg:address":"1565 Voltaire Dr",
    "sg:city":"St Louis",
    "sg:classifiers":[
        {
            "category":"Education",
            "subcategory":"Special Training",
            "type":"Public Place"
        }
    ],
    "sg:phone":"+1 314 469 4980",
    "sg:postcode":"63146",
    "sg:province":"MO",
    "sg:tags":[
        "instruction",
        "music"
    ],
    "wof:name":"St Louis School Of Music",
    "wof:placetype":"venue"
},
  "geometry": {"coordinates":[-90.45997199999999,38.689496],"type":"Point"}
}