{
  "type": "Feature",
  "properties": {
    "iso:country":"US",
    "sg:address":"2608 Messanie St",
    "sg:city":"St Joseph",
    "sg:classifiers":[
        {
            "category":"Autos & Motor Vehicles",
            "subcategory":"Automobile Sales",
            "type":"Retail Goods"
        }
    ],
    "sg:phone":"+1 816 364 3139",
    "sg:postcode":"64501",
    "sg:province":"MO",
    "sg:tags":[
        "car",
        "used",
        "dealer"
    ],
    "wof:name":"Premiere Auto Source",
    "wof:placetype":"venue"
},
  "geometry": {"coordinates":[-94.828703,39.762403],"type":"Point"}
}