{
  "type": "Feature",
  "properties": {
    "iso:country":"US",
    "sg:address":"3807 Lemay Ferry Rd",
    "sg:city":"St Louis",
    "sg:classifiers":[
        {
            "category":"Retail",
            "subcategory":"Auto Repair",
            "type":"Services"
        }
    ],
    "sg:phone":"+1 314 894 3490",
    "sg:postcode":"63125",
    "sg:province":"MO",
    "sg:tags":[
        "oil",
        "automobile",
        "lubrication",
        "lube",
        "quick",
        "change"
    ],
    "wof:name":"Valvoline Instant Oil Change",
    "wof:placetype":"venue"
},
  "geometry": {"coordinates":[-90.324285,38.507562],"type":"Point"}
}