{
  "type": "Feature",
  "properties": {
    "iso:country":"US",
    "sg:address":"135 Crown Hill Rd",
    "sg:city":"Excelsior Spgs",
    "sg:classifiers":[
        {
            "category":"Professional",
            "subcategory":"Accounting & Tax Preparation",
            "type":"Services"
        }
    ],
    "sg:phone":"+1 816 637 6311",
    "sg:postcode":"64024",
    "sg:province":"MO",
    "sg:tags":[
        "return",
        "filing"
    ],
    "wof:name":"H & R Block Tax Svc",
    "wof:placetype":"venue"
},
  "geometry": {"coordinates":[-94.24908000000001,39.339709],"type":"Point"}
}