{
  "type": "Feature",
  "properties": {
    "iso:country":"US",
    "sg:address":"7381 E Sunburst Ct",
    "sg:city":"Columbia",
    "sg:classifiers":[
        {
            "category":"Retail",
            "subcategory":"Portrait Studio",
            "type":"Services"
        }
    ],
    "sg:phone":"+1 573 886 8700",
    "sg:postcode":"65201",
    "sg:province":"MO",
    "sg:tags":[
        "photo"
    ],
    "wof:name":"Creations By Nola",
    "wof:placetype":"venue"
},
  "geometry": {"coordinates":[-92.22433700000001,38.95223],"type":"Point"}
}