{
  "type": "Feature",
  "properties": {
    "iso:country":"US",
    "sg:address":"9670 NW Seymour St",
    "sg:city":"Kansas City",
    "sg:classifiers":[
        {
            "category":"Wholesale",
            "subcategory":"Machinery & Supplies",
            "type":"Manufacturing & Wholesale Goods"
        }
    ],
    "sg:phone":"+1 816 880 0004",
    "sg:postcode":"64153",
    "sg:province":"MO",
    "sg:tags":[
        "equipment",
        "irrigation",
        "system"
    ],
    "wof:name":"Ewing Irrigation Golf & Ind",
    "wof:placetype":"venue"
},
  "geometry": {"coordinates":[-94.674252,39.268845],"type":"Point"}
}