{
  "type": "Feature",
  "properties": {
    "iso:country":"US",
    "sg:address":"7505 NW Tiffany Springs Pkwy E",
    "sg:city":"Kansas City",
    "sg:classifiers":[
        {
            "category":"Wholesale",
            "subcategory":"Machinery & Supplies",
            "type":"Manufacturing & Wholesale Goods"
        }
    ],
    "sg:phone":"+1 816 891 9272",
    "sg:postcode":"64153",
    "sg:province":"MO",
    "sg:tags":[
        "food",
        "product"
    ],
    "wof:name":"Wenger Manufacturing Inc",
    "wof:placetype":"venue"
},
  "geometry": {"coordinates":[-94.666517,39.273756],"type":"Point"}
}