{
  "type": "Feature",
  "properties": {
    "iso:country":"US",
    "sg:address":"3612 Arsenal St",
    "sg:city":"Saint Louis",
    "sg:classifiers":[
        {
            "category":"Banks & Credit Unions",
            "subcategory":"Financial Services",
            "type":"Services"
        }
    ],
    "sg:phone":"+1 314 772 8663",
    "sg:postcode":"63116",
    "sg:province":"MO",
    "sg:tags":[
        "broker",
        "mortgage"
    ],
    "wof:name":"USA Mortgage",
    "wof:placetype":"venue"
},
  "geometry": {"coordinates":[-90.24283,38.602725],"type":"Point"}
}