{
  "type": "Feature",
  "properties": {
    "iso:country":"US",
    "sg:address":"8314 E 171st St",
    "sg:city":"Belton",
    "sg:classifiers":[
        {
            "category":"Restaurant",
            "type":"Food & Drink"
        }
    ],
    "sg:menulink":"http://www.allmenus.com/mo/raymore/9997-chartroose-caboose/menu/",
    "sg:phone":"+1 816 318 4335",
    "sg:postcode":"64012",
    "sg:province":"MO",
    "sg:tags":[
        "american"
    ],
    "wof:name":"Chartroose Caboose",
    "wof:placetype":"venue"
},
  "geometry": {"coordinates":[-94.49684600000001,38.813066],"type":"Point"}
}