{
  "type": "Feature",
  "properties": {
    "iso:country":"US",
    "sg:address":"12511 State Hwy Aa",
    "sg:city":"Neosho",
    "sg:classifiers":[
        {
            "category":"Building & Trades",
            "subcategory":"Construction",
            "type":"Services"
        }
    ],
    "sg:phone":"+1 417 451 2181",
    "sg:postcode":"64850",
    "sg:province":"MO",
    "sg:tags":[
        "water",
        "well",
        "drilling"
    ],
    "wof:name":"Cantrell Drilling & Pump Svc",
    "wof:placetype":"venue"
},
  "geometry": {"coordinates":[-94.42360600000001,36.788926],"type":"Point"}
}