{
  "type": "Feature",
  "properties": {
    "iso:country":"US",
    "sg:address":"4581 Commerce Ave",
    "sg:city":"High Ridge",
    "sg:classifiers":[
        {
            "category":"Wholesale",
            "subcategory":"Electrical",
            "type":"Manufacturing & Wholesale Goods"
        }
    ],
    "sg:phone":"+1 636 677 4900",
    "sg:postcode":"63049",
    "sg:province":"MO",
    "sg:tags":[
        "plumbing",
        "equipment"
    ],
    "sg:website":"www.butlersupply.com",
    "wof:name":"Butler Supply Inc",
    "wof:placetype":"venue"
},
  "geometry": {"coordinates":[-90.500011,38.488551],"type":"Point"}
}