{
  "type": "Feature",
  "properties": {
    "iso:country":"US",
    "sg:address":"7663 Watson Rd",
    "sg:city":"Webster Groves",
    "sg:classifiers":[
        {
            "category":"Social Services",
            "type":"Services"
        }
    ],
    "sg:phone":"+1 314 962 7501",
    "sg:postcode":"63119",
    "sg:province":"MO",
    "sg:tags":[
        "care",
        "center",
        "day"
    ],
    "sg:website":"www.ccstl.org",
    "wof:name":"Cardinal Ritter Institute",
    "wof:placetype":"venue"
},
  "geometry": {"coordinates":[-90.330653,38.575851],"type":"Point"}
}