{
  "type": "Feature",
  "properties": {
    "iso:country":"US",
    "sg:address":"1128 Independence Ave",
    "sg:city":"Kennett",
    "sg:classifiers":[
        {
            "category":"Building & Trades",
            "subcategory":"Landscaping Services",
            "type":"Services"
        }
    ],
    "sg:phone":"+1 573 344 1431",
    "sg:postcode":"63857",
    "sg:province":"MO",
    "sg:tags":[
        "lawn",
        "maintenance"
    ],
    "wof:name":"5 C's Lawncare",
    "wof:placetype":"venue"
},
  "geometry": {"coordinates":[-90.033203,36.248111],"type":"Point"}
}