{
  "type": "Feature",
  "properties": {
    "iso:country":"US",
    "sg:address":"4627 Forest Valley Dr",
    "sg:city":"Saint Louis",
    "sg:classifiers":[
        {
            "category":"Building & Trades",
            "subcategory":"Construction",
            "type":"Services"
        }
    ],
    "sg:phone":"+1 314 487 2786",
    "sg:postcode":"63128",
    "sg:province":"MO",
    "sg:tags":[
        "house",
        "co"
    ],
    "wof:name":"Karr Construction",
    "wof:placetype":"venue"
},
  "geometry": {"coordinates":[-90.372406,38.484018],"type":"Point"}
}