{
  "type": "Feature",
  "properties": {
    "iso:country":"US",
    "sg:address":"322 S Brunswick Ave",
    "sg:city":"Marshall",
    "sg:classifiers":[
        {
            "category":"Organizations",
            "subcategory":"Religious Organization",
            "type":"Services"
        }
    ],
    "sg:phone":"+1 660 886 9541",
    "sg:postcode":"65340",
    "sg:province":"MO",
    "sg:tags":[
        "church"
    ],
    "wof:name":"Mount Olive Baptist Church",
    "wof:placetype":"venue"
},
  "geometry": {"coordinates":[-93.19004099999999,39.118273],"type":"Point"}
}