{
  "type": "Feature",
  "properties": {
    "iso:country":"US",
    "sg:address":"1600 S Big Bend Blvd",
    "sg:city":"St Louis",
    "sg:classifiers":[
        {
            "category":"Education",
            "subcategory":"Special Training",
            "type":"Public Place"
        }
    ],
    "sg:phone":"+1 314 727 3355",
    "sg:postcode":"63117",
    "sg:province":"MO",
    "sg:tags":[
        "instruction",
        "music"
    ],
    "wof:name":"Folk School Of St Louis",
    "wof:placetype":"venue"
},
  "geometry": {"coordinates":[-90.32064,38.624334],"type":"Point"}
}