{
  "type": "Feature",
  "properties": {
    "iso:country":"US",
    "sg:address":"421 Chestnut St",
    "sg:city":"Thayer",
    "sg:classifiers":[
        {
            "category":"Building & Trades",
            "subcategory":"Plumbing",
            "type":"Services"
        }
    ],
    "sg:phone":"+1 417 264 7372",
    "sg:postcode":"65791",
    "sg:province":"MO",
    "sg:tags":[
        "plumbing",
        "repair",
        "contractor"
    ],
    "wof:name":"Ken's Plumbing",
    "wof:placetype":"venue"
},
  "geometry": {"coordinates":[-91.542034,36.524025],"type":"Point"}
}