{
  "type": "Feature",
  "properties": {
    "iso:country":"US",
    "sg:address":"15300 E 42 Ter S",
    "sg:city":"Independence",
    "sg:classifiers":[
        {
            "category":"Professional",
            "type":"Services"
        }
    ],
    "sg:phone":"+1 816 478 6163",
    "sg:postcode":"64055",
    "sg:province":"MO",
    "wof:name":"Margaret A Denker",
    "wof:placetype":"venue"
},
  "geometry": {"coordinates":[-94.402067,39.044639],"type":"Point"}
}