{
  "type": "Feature",
  "properties": {
    "iso:country":"US",
    "sg:address":"18808 State Hwy J",
    "sg:city":"Raymore",
    "sg:classifiers":[
        {
            "category":"Building & Trades",
            "subcategory":"Construction",
            "type":"Services"
        }
    ],
    "sg:phone":"+1 816 318 4604",
    "sg:postcode":"64083",
    "sg:province":"MO",
    "sg:tags":[
        "house"
    ],
    "wof:name":"Ernie Beck Construction",
    "wof:placetype":"venue"
},
  "geometry": {"coordinates":[-94.439879,38.781147],"type":"Point"}
}