{
  "type": "Feature",
  "properties": {
    "iso:country":"US",
    "sg:address":"79 Hubble",
    "sg:city":"O Fallon",
    "sg:classifiers":[
        {
            "category":"Personal",
            "type":"Services"
        }
    ],
    "sg:phone":"+1 636 300 8094",
    "sg:postcode":"63366",
    "sg:province":"MO",
    "sg:tags":[
        "miscellaneous"
    ],
    "wof:name":"Phoenix Group",
    "wof:placetype":"venue"
},
  "geometry": {"coordinates":[-90.723281,38.724091],"type":"Point"}
}