{
  "type": "Feature",
  "properties": {
    "iso:country":"US",
    "sg:address":"3214 S Big Bend Blvd",
    "sg:city":"St Louis",
    "sg:classifiers":[
        {
            "category":"Insurance",
            "subcategory":"Insurance Agent",
            "type":"Services"
        }
    ],
    "sg:phone":"+1 314 644 6030",
    "sg:postcode":"63143",
    "sg:province":"MO",
    "wof:name":"Allstate Insurance",
    "wof:placetype":"venue"
},
  "geometry": {"coordinates":[-90.324541,38.604924],"type":"Point"}
}