{
  "type": "Feature",
  "properties": {
    "iso:country":"US",
    "sg:address":"2550 NW 348th St",
    "sg:city":"Stewartsville",
    "sg:classifiers":[
        {
            "category":"Farming",
            "subcategory":"Farm",
            "type":"Manufacturing & Wholesale Goods"
        }
    ],
    "sg:phone":"+1 816 669 3392",
    "sg:postcode":"64490",
    "sg:province":"MO",
    "wof:name":"Thompson Farms",
    "wof:placetype":"venue"
},
  "geometry": {"coordinates":[-94.572304,39.72543],"type":"Point"}
}