{
  "type": "Feature",
  "properties": {
    "iso:country":"US",
    "sg:address":"2408 N Baltimore St",
    "sg:city":"Kirksville",
    "sg:classifiers":[
        {
            "category":"Banks & Credit Unions",
            "subcategory":"Bank",
            "type":"Services"
        }
    ],
    "sg:phone":"+1 660 665 7711",
    "sg:postcode":"63501",
    "sg:province":"MO",
    "sg:tags":[
        "depository",
        "banking",
        "check",
        "cashing"
    ],
    "wof:name":"Check Casher Inc No 7",
    "wof:placetype":"venue"
},
  "geometry": {"coordinates":[-92.58273,40.21796],"type":"Point"}
}