{
  "type": "Feature",
  "properties": {
    "iso:country":"US",
    "sg:address":"4138 San Francisco Ave",
    "sg:city":"Saint Louis",
    "sg:classifiers":[
        {
            "category":"Building & Trades",
            "subcategory":"Plumbing",
            "type":"Services"
        }
    ],
    "sg:phone":"+1 314 533 5078",
    "sg:postcode":"63115",
    "sg:province":"MO",
    "sg:tags":[
        "air",
        "heating",
        "condition",
        "contractor"
    ],
    "wof:name":"Davis Air Conditioning",
    "wof:placetype":"venue"
},
  "geometry": {"coordinates":[-90.22882300000001,38.668242],"type":"Point"}
}