{
  "type": "Feature",
  "properties": {
    "iso:country":"US",
    "sg:address":"3591 Bethel Dr",
    "sg:city":"Summersville",
    "sg:classifiers":[
        {
            "category":"Farming",
            "subcategory":"Livestock Farm",
            "type":"Manufacturing & Wholesale Goods"
        }
    ],
    "sg:phone":"+1 417 932 4239",
    "sg:postcode":"65571",
    "sg:province":"MO",
    "sg:tags":[
        "beef",
        "feedlot",
        "cattle"
    ],
    "wof:name":"Richard Canfield",
    "wof:placetype":"venue"
},
  "geometry": {"coordinates":[-91.708732,37.151159],"type":"Point"}
}