{
  "type": "Feature",
  "properties": {
    "iso:country":"US",
    "sg:address":"5411 Gravois Ave",
    "sg:city":"St Louis",
    "sg:classifiers":[
        {
            "category":"Food & Beverages",
            "subcategory":"Liquor & Beverages",
            "type":"Retail Goods"
        }
    ],
    "sg:phone":"+1 314 351 7744",
    "sg:postcode":"63116",
    "sg:province":"MO",
    "wof:name":"P-X Wine & Spirits",
    "wof:placetype":"venue"
},
  "geometry": {"coordinates":[-90.270158,38.579054],"type":"Point"}
}