{
  "type": "Feature",
  "properties": {
    "iso:country":"US",
    "sg:address":"701 E 23rd St S",
    "sg:city":"Independence",
    "sg:classifiers":[
        {
            "category":"Retail",
            "subcategory":"Animal Services",
            "type":"Services"
        }
    ],
    "sg:phone":"+1 816 461 7753",
    "sg:postcode":"64055",
    "sg:province":"MO",
    "wof:name":"Puttin On Dog Pet Grooming",
    "wof:placetype":"venue"
},
  "geometry": {"coordinates":[-94.40574599999999,39.078849],"type":"Point"}
}