{
  "type": "Feature",
  "properties": {
    "iso:country":"US",
    "sg:address":"6628 Hwy Jj",
    "sg:city":"Florence",
    "sg:classifiers":[
        {
            "category":"Government",
            "subcategory":"Post Office",
            "type":"Public Place"
        }
    ],
    "sg:phone":"+1 660 368 2121",
    "sg:postcode":"65329",
    "sg:province":"MO",
    "wof:name":"Florence Post Office",
    "wof:placetype":"venue"
},
  "geometry": {"coordinates":[-92.97142100000001,38.59817],"type":"Point"}
}