{
  "type": "Feature",
  "properties": {
    "iso:country":"US",
    "sg:address":"7131 Old Hwy 21",
    "sg:city":"Barnhart",
    "sg:classifiers":[
        {
            "category":"Building & Trades",
            "subcategory":"Plumbing",
            "type":"Services"
        }
    ],
    "sg:phone":"+1 636 942 3702",
    "sg:postcode":"63012",
    "sg:province":"MO",
    "sg:tags":[
        "contractor"
    ],
    "wof:name":"Pennington Heating & Cooling",
    "wof:placetype":"venue"
},
  "geometry": {"coordinates":[-90.501114,38.350087],"type":"Point"}
}