{
  "type": "Feature",
  "properties": {
    "iso:country":"US",
    "sg:address":"3460 Hwy Y",
    "sg:city":"New Haven",
    "sg:classifiers":[
        {
            "category":"Wholesale",
            "subcategory":"Farm Supplies",
            "type":"Manufacturing & Wholesale Goods"
        }
    ],
    "sg:phone":"+1 573 237 3831",
    "sg:postcode":"63068",
    "sg:province":"MO",
    "sg:tags":[
        "feed",
        "seed"
    ],
    "wof:name":"Dissen Farm Supply Inc",
    "wof:placetype":"venue"
},
  "geometry": {"coordinates":[-91.27527499999999,38.561372],"type":"Point"}
}