{
  "type": "Feature",
  "properties": {
    "iso:country":"US",
    "sg:address":"1121 Heineman Ln",
    "sg:city":"Bonne Terre",
    "sg:classifiers":[
        {
            "category":"Farming",
            "subcategory":"Livestock Farm",
            "type":"Manufacturing & Wholesale Goods"
        }
    ],
    "sg:phone":"+1 573 358 2078",
    "sg:postcode":"63628",
    "sg:province":"MO",
    "sg:tags":[
        "beef",
        "feedlot",
        "cattle"
    ],
    "wof:name":"Charles Heineman",
    "wof:placetype":"venue"
},
  "geometry": {"coordinates":[-90.58589000000001,37.981623],"type":"Point"}
}