{
  "type": "Feature",
  "properties": {
    "iso:country":"US",
    "sg:address":"11428 Tesson Ferry Rd",
    "sg:city":"St Louis",
    "sg:classifiers":[
        {
            "category":"Health Services",
            "subcategory":"Doctor",
            "type":"Services"
        }
    ],
    "sg:phone":"+1 314 842 0256",
    "sg:postcode":"63123",
    "sg:province":"MO",
    "sg:tags":[
        "dentist"
    ],
    "wof:name":"James E Lillenberg DDS",
    "wof:placetype":"venue"
},
  "geometry": {"coordinates":[-90.356381,38.521827],"type":"Point"}
}