{
  "type": "Feature",
  "properties": {
    "iso:country":"US",
    "sg:address":"417 W McGee St",
    "sg:city":"Springfield",
    "sg:classifiers":[
        {
            "category":"Building & Trades",
            "subcategory":"Electrical",
            "type":"Services"
        }
    ],
    "sg:phone":"+1 417 883 0125",
    "sg:postcode":"65807",
    "sg:province":"MO",
    "sg:tags":[
        "electric",
        "contractor"
    ],
    "wof:name":"Choate Electric Svc",
    "wof:placetype":"venue"
},
  "geometry": {"coordinates":[-93.29563400000001,37.177405],"type":"Point"}
}