{
  "type": "Feature",
  "properties": {
    "iso:country":"US",
    "sg:address":"840 Bricken Pl",
    "sg:city":"St Louis",
    "sg:classifiers":[
        {
            "category":"Professional",
            "subcategory":"Business Services",
            "type":"Services"
        }
    ],
    "sg:phone":"+1 314 909 7377",
    "sg:postcode":"63122",
    "sg:province":"MO",
    "sg:tags":[
        "agent",
        "artist"
    ],
    "wof:name":"Foster Teenuh Represents",
    "wof:placetype":"venue"
},
  "geometry": {"coordinates":[-90.387818,38.6057],"type":"Point"}
}