{
  "type": "Feature",
  "properties": {
    "iso:country":"US",
    "sg:address":"17721 US Hwy 61",
    "sg:city":"Ste Genevieve",
    "sg:classifiers":[
        {
            "category":"Building & Trades",
            "subcategory":"Equipment Rental",
            "type":"Services"
        }
    ],
    "sg:phone":"+1 573 883 2788",
    "sg:postcode":"63670",
    "sg:province":"MO",
    "sg:tags":[
        "crane"
    ],
    "wof:name":"Gegg Materials & Excavating Co",
    "wof:placetype":"venue"
},
  "geometry": {"coordinates":[-90.03170799999999,37.96495],"type":"Point"}
}