{
  "type": "Feature",
  "properties": {
    "iso:country":"US",
    "sg:address":"3462 McKelvey Rd",
    "sg:city":"Bridgeton",
    "sg:classifiers":[
        {
            "category":"Insurance",
            "subcategory":"Insurance Agent",
            "type":"Services"
        }
    ],
    "sg:phone":"+1 314 291 5200",
    "sg:postcode":"63044",
    "sg:province":"MO",
    "wof:name":"Montgomery Glen G",
    "wof:placetype":"venue"
},
  "geometry": {"coordinates":[-90.433412,38.746771],"type":"Point"}
}