{
  "type": "Feature",
  "properties": {
    "addr:full":"109 N Main St Clarkton MO 63837",
    "addr:housenumber":"109",
    "addr:postcode":"63837",
    "addr:street":"N Main St",
    "iso:country":"US",
    "sg:address":"109 N Main St",
    "sg:city":"Clarkton",
    "sg:classifiers":[
        {
            "category":"Government",
            "subcategory":"Post Office",
            "type":"Public Place"
        }
    ],
    "sg:phone":"+1 573 448 5585",
    "sg:postcode":"63837",
    "sg:province":"MO",
    "sg:tags":[
        "postal",
        "us"
    ],
    "wof:name":"US Post Office",
    "wof:placetype":"venue"
},
  "geometry": {"coordinates":[-89.96755400000001,36.452148],"type":"Point"}
}