{
  "type": "Feature",
  "properties": {
    "iso:country":"US",
    "sg:address":"127 SE 215 Rd",
    "sg:city":"Warrensburg",
    "sg:classifiers":[
        {
            "category":"Manufacturing",
            "subcategory":"Textiles",
            "type":"Manufacturing & Wholesale Goods"
        }
    ],
    "sg:phone":"+1 660 747 0649",
    "sg:postcode":"64093",
    "sg:province":"MO",
    "sg:tags":[
        "mill",
        "fabric"
    ],
    "wof:name":"Penny Quilts",
    "wof:placetype":"venue"
},
  "geometry": {"coordinates":[-93.724715,38.727656],"type":"Point"}
}