{
  "type": "Feature",
  "properties": {
    "iso:country":"US",
    "sg:address":"5251 E New Haven Rd",
    "sg:city":"Columbia",
    "sg:classifiers":[
        {
            "category":"Retail",
            "subcategory":"Repair Shop",
            "type":"Services"
        }
    ],
    "sg:phone":"+1 573 442 7868",
    "sg:postcode":"65201",
    "sg:province":"MO",
    "wof:name":"Sharons Seat Weaving",
    "wof:placetype":"venue"
},
  "geometry": {"coordinates":[-92.25984,38.91233],"type":"Point"}
}