{
  "type": "Feature",
  "properties": {
    "iso:country":"US",
    "sg:address":"1817 Gravois Rd",
    "sg:city":"High Ridge",
    "sg:classifiers":[
        {
            "category":"Retail",
            "subcategory":"Funeral Services",
            "type":"Services"
        }
    ],
    "sg:phone":"+1 636 677 5000",
    "sg:postcode":"63049",
    "sg:province":"MO",
    "sg:tags":[
        "cemetery"
    ],
    "wof:name":"Chapel Hill Mortuary Inc",
    "wof:placetype":"venue"
},
  "geometry": {"coordinates":[-90.50273799999999,38.482177],"type":"Point"}
}