{
  "type": "Feature",
  "properties": {
    "iso:country":"US",
    "sg:address":"1410 S Jefferson Ave",
    "sg:city":"St Louis",
    "sg:classifiers":[
        {
            "category":"Real Estate",
            "subcategory":"Real Estate Agent",
            "type":"Services"
        }
    ],
    "sg:phone":"+1 314 773 3414",
    "sg:postcode":"63104",
    "sg:province":"MO",
    "wof:name":"Doug Mueller Properties",
    "wof:placetype":"venue"
},
  "geometry": {"coordinates":[-90.21997500000001,38.618525],"type":"Point"}
}