{
  "type": "Feature",
  "properties": {
    "iso:country":"US",
    "sg:address":"78 Ridgefield Ct",
    "sg:city":"Saint Charles",
    "sg:classifiers":[
        {
            "category":"Professional",
            "subcategory":"Business Services",
            "type":"Services"
        }
    ],
    "sg:phone":"+1 636 928 7814",
    "sg:postcode":"63304",
    "sg:province":"MO",
    "wof:name":"Arthur Sales",
    "wof:placetype":"venue"
},
  "geometry": {"coordinates":[-90.64717400000001,38.73619],"type":"Point"}
}