{
  "type": "Feature",
  "properties": {
    "iso:country":"US",
    "sg:address":"401 State Hwy 80",
    "sg:city":"East Prairie",
    "sg:phone":"+1 573 649 5193",
    "sg:postcode":"63845",
    "sg:province":"MO",
    "sg:tags":[
        "farm",
        "grain",
        "cash",
        "soybean"
    ],
    "wof:name":"Duke Presson Farms",
    "wof:placetype":"venue"
},
  "geometry": {"coordinates":[-89.378479,36.775697],"type":"Point"}
}