{
  "type": "Feature",
  "properties": {
    "iso:country":"US",
    "sg:address":"201 N Pearl Ave",
    "sg:city":"Joplin",
    "sg:classifiers":[
        {
            "category":"Shopping",
            "subcategory":"News",
            "type":"Retail Goods"
        }
    ],
    "sg:phone":"+1 417 627 0060",
    "sg:postcode":"64801",
    "sg:province":"MO",
    "sg:tags":[
        "dealer"
    ],
    "wof:name":"USA Today News Delivery",
    "wof:placetype":"venue"
},
  "geometry": {"coordinates":[-94.51638199999999,37.092982],"type":"Point"}
}