{
  "type": "Feature",
  "properties": {
    "iso:country":"US",
    "sg:address":"139 Wisteria Ln",
    "sg:city":"Troy",
    "sg:classifiers":[
        {
            "category":"Freight",
            "type":"Transportation"
        }
    ],
    "sg:phone":"+1 636 528 2182",
    "sg:postcode":"63379",
    "sg:province":"MO",
    "sg:tags":[
        "distance",
        "long",
        "trucking"
    ],
    "wof:name":"BT & B Trucking",
    "wof:placetype":"venue"
},
  "geometry": {"coordinates":[-91.041691,39.048035],"type":"Point"}
}