{
  "type": "Feature",
  "properties": {
    "iso:country":"US",
    "sg:address":"28 Fox Valley Ctr Ste 28",
    "sg:city":"Arnold",
    "sg:classifiers":[
        {
            "category":"Insurance",
            "subcategory":"Health Insurance",
            "type":"Services"
        }
    ],
    "sg:phone":"+1 636 296 0151",
    "sg:postcode":"63010",
    "sg:province":"MO",
    "sg:tags":[
        "dental"
    ],
    "wof:name":"James O Huisinga Dds",
    "wof:placetype":"venue"
},
  "geometry": {"coordinates":[-90.36948700000001,38.446761],"type":"Point"}
}