{
  "type": "Feature",
  "properties": {
    "iso:country":"US",
    "sg:address":"5714 Old State Hwy 21",
    "sg:city":"Imperial",
    "sg:classifiers":[
        {
            "category":"Autos & Motor Vehicles",
            "subcategory":"Motorcycle Sales",
            "type":"Retail Goods"
        }
    ],
    "sg:phone":"+1 636 942 4800",
    "sg:postcode":"63052",
    "sg:province":"MO",
    "sg:tags":[
        "scooter"
    ],
    "wof:name":"B C Cycle",
    "wof:placetype":"venue"
},
  "geometry": {"coordinates":[-90.49767,38.377474],"type":"Point"}
}