{
  "type": "Feature",
  "properties": {
    "iso:country":"US",
    "sg:address":"208 W Springfield Rd",
    "sg:city":"Sullivan",
    "sg:classifiers":[
        {
            "category":"Autos & Motor Vehicles",
            "subcategory":"Auto Supplies",
            "type":"Retail Goods"
        }
    ],
    "sg:phone":"+1 573 468 4128",
    "sg:postcode":"63080",
    "sg:province":"MO",
    "sg:tags":[
        "station",
        "gasoline"
    ],
    "wof:name":"Harrys Tire Service Inc",
    "wof:placetype":"venue"
},
  "geometry": {"coordinates":[-91.16291699999999,38.213727],"type":"Point"}
}