{
  "type": "Feature",
  "properties": {
    "iso:country":"US",
    "sg:address":"111 E North Front St",
    "sg:city":"Orrick",
    "sg:classifiers":[
        {
            "category":"Fast Food",
            "type":"Food & Drink"
        },
        {
            "category":"Restaurant",
            "type":"Food & Drink"
        }
    ],
    "sg:phone":"+1 816 770 2637",
    "sg:postcode":"64077",
    "sg:province":"MO",
    "wof:name":"Bearcat Den",
    "wof:placetype":"venue"
},
  "geometry": {"coordinates":[-94.122439,39.213562],"type":"Point"}
}