{
  "type": "Feature",
  "properties": {
    "iso:country":"US",
    "sg:address":"688 SW 50th Ave",
    "sg:city":"Chula",
    "sg:classifiers":[
        {
            "category":"Farming",
            "subcategory":"Dairy Farm",
            "type":"Manufacturing & Wholesale Goods"
        }
    ],
    "sg:phone":"+1 660 286 2771",
    "sg:postcode":"64683",
    "sg:province":"MO",
    "wof:name":"Foster and Mac",
    "wof:placetype":"venue"
},
  "geometry": {"coordinates":[-93.688772,39.981441],"type":"Point"}
}