{
  "type": "Feature",
  "properties": {
    "iso:country":"US",
    "sg:address":"201 E 1st St",
    "sg:city":"Eldon",
    "sg:classifiers":[
        {
            "category":"Airport",
            "type":"Transportation"
        }
    ],
    "sg:phone":"+1 573 392 2145",
    "sg:postcode":"65026",
    "sg:province":"MO",
    "wof:name":"Eldon Airport Adm",
    "wof:placetype":"venue"
},
  "geometry": {"coordinates":[-92.58020999999999,38.349593],"type":"Point"}
}