{
  "type": "Feature",
  "properties": {
    "iso:country":"US",
    "sg:address":"22 SE 125 Rd",
    "sg:city":"Warrensburg",
    "sg:classifiers":[
        {
            "category":"Shopping",
            "subcategory":"Used Merchandise",
            "type":"Retail Goods"
        }
    ],
    "sg:phone":"+1 660 747 5164",
    "sg:postcode":"64093",
    "sg:province":"MO",
    "sg:tags":[
        "shop",
        "consignment"
    ],
    "wof:name":"Maga's Resale Boutique",
    "wof:placetype":"venue"
},
  "geometry": {"coordinates":[-93.731486,38.741228],"type":"Point"}
}