{
  "type": "Feature",
  "properties": {
    "iso:country":"US",
    "sg:address":"101 E 2nd St",
    "sg:city":"Clearmont",
    "sg:classifiers":[
        {
            "category":"Real Estate",
            "subcategory":"Real Estate Agent",
            "type":"Services"
        }
    ],
    "sg:phone":"+1 660 729 3317",
    "sg:postcode":"64431",
    "sg:province":"MO",
    "wof:name":"Slaten Realty",
    "wof:placetype":"venue"
},
  "geometry": {"coordinates":[-95.030823,40.508831],"type":"Point"}
}