{
  "type": "Feature",
  "properties": {
    "iso:country":"US",
    "sg:address":"207 N Dogwood St",
    "sg:city":"Savannah",
    "sg:classifiers":[
        {
            "category":"Manufacturing",
            "subcategory":"Food",
            "type":"Manufacturing & Wholesale Goods"
        },
        {
            "category":"Farming",
            "subcategory":"Farm",
            "type":"Manufacturing & Wholesale Goods"
        }
    ],
    "sg:phone":"+1 816 324 6692",
    "sg:postcode":"64485",
    "sg:province":"MO",
    "sg:tags":[
        "corn",
        "product"
    ],
    "wof:name":"Vincent Runnels",
    "wof:placetype":"venue"
},
  "geometry": {"coordinates":[-94.807877,39.94569],"type":"Point"}
}