{
  "type": "Feature",
  "properties": {
    "iso:country":"US",
    "sg:address":"1000 W Nifong Blvd",
    "sg:city":"Columbia",
    "sg:classifiers":[
        {
            "category":"Health Services",
            "subcategory":"Nursing And Care Facility",
            "type":"Services"
        }
    ],
    "sg:phone":"+1 573 499 6070",
    "sg:postcode":"65203",
    "sg:province":"MO",
    "sg:tags":[
        "skilled"
    ],
    "wof:name":"Regional Hospice Central MO",
    "wof:placetype":"venue"
},
  "geometry": {"coordinates":[-92.352154,38.908348],"type":"Point"}
}