{
  "type": "Feature",
  "properties": {
    "iso:country":"US",
    "sg:address":"15314 State Hwy 13",
    "sg:city":"Reeds Spring",
    "sg:classifiers":[
        {
            "category":"Retail",
            "subcategory":"Repair Shop",
            "type":"Services"
        }
    ],
    "sg:phone":"+1 417 739 1871",
    "sg:postcode":"65737",
    "sg:province":"MO",
    "sg:tags":[
        "equipment",
        "lawn",
        "garden"
    ],
    "wof:name":"Maxs Power and Lawn Inc",
    "wof:placetype":"venue"
},
  "geometry": {"coordinates":[-93.40427699999999,36.67013],"type":"Point"}
}