{
  "type": "Feature",
  "properties": {
    "iso:country":"US",
    "sg:address":"702 State Hwy 28",
    "sg:city":"Owensville",
    "sg:classifiers":[
        {
            "category":"Insurance",
            "subcategory":"Insurance Agent",
            "type":"Services"
        }
    ],
    "sg:phone":"+1 573 437 4191",
    "sg:postcode":"65066",
    "sg:province":"MO",
    "wof:name":"Naught-Naught Insurance",
    "wof:placetype":"venue"
},
  "geometry": {"coordinates":[-91.489924,38.347996],"type":"Point"}
}