{
  "type": "Feature",
  "properties": {
    "iso:country":"US",
    "sg:address":"437 State Hwy J",
    "sg:city":"Troy",
    "sg:classifiers":[
        {
            "category":"Government",
            "subcategory":"Office",
            "type":"Public Place"
        }
    ],
    "sg:phone":"+1 636 528 5078",
    "sg:postcode":"63379",
    "sg:province":"MO",
    "sg:tags":[
        "county"
    ],
    "wof:name":"Lincoln County Farmers",
    "wof:placetype":"venue"
},
  "geometry": {"coordinates":[-90.994207,38.958607],"type":"Point"}
}