{
  "type": "Feature",
  "properties": {
    "iso:country":"US",
    "sg:address":"17500 Medical Center Pkwy",
    "sg:city":"Independence",
    "sg:classifiers":[
        {
            "category":"Shopping",
            "subcategory":"Clothing, Apparel, & Fashions",
            "type":"Retail Goods"
        }
    ],
    "sg:phone":"+1 816 373 1111",
    "sg:postcode":"64057",
    "sg:province":"MO",
    "sg:tags":[
        "clothing",
        "boys'"
    ],
    "wof:name":"Clothier Robt W",
    "wof:placetype":"venue"
},
  "geometry": {"coordinates":[-94.373283,39.076439],"type":"Point"}
}