{
  "type": "Feature",
  "properties": {
    "iso:country":"US",
    "sg:address":"7510 E 85 Ter",
    "sg:city":"Kansas City",
    "sg:classifiers":[
        {
            "category":"Real Estate",
            "subcategory":"Real Estate Operator",
            "type":"Services"
        }
    ],
    "sg:phone":"+1 816 737 8690",
    "sg:postcode":"64138",
    "sg:province":"MO",
    "sg:tags":[
        "building",
        "apartment"
    ],
    "wof:name":"Stonewood Apartments",
    "wof:placetype":"venue"
},
  "geometry": {"coordinates":[-94.498352,38.967933],"type":"Point"}
}