{
  "type": "Feature",
  "properties": {
    "iso:country":"US",
    "sg:address":"310 Broadway St",
    "sg:city":"Cape Girardeau",
    "sg:classifiers":[
        {
            "category":"Real Estate",
            "subcategory":"Architect",
            "type":"Services"
        }
    ],
    "sg:phone":"+1 573 334 6666",
    "sg:postcode":"63701",
    "sg:province":"MO",
    "sg:tags":[
        "architectural"
    ],
    "wof:name":"Image Desing",
    "wof:placetype":"venue"
},
  "geometry": {"coordinates":[-89.522034,37.306345],"type":"Point"}
}