{
  "type": "Feature",
  "properties": {
    "iso:country":"US",
    "sg:address":"745 NW Silver Ridge",
    "sg:city":"Lees Summit",
    "sg:classifiers":[
        {
            "category":"Real Estate",
            "subcategory":"Real Estate Agent",
            "type":"Services"
        }
    ],
    "sg:phone":"+1 816 763 9017",
    "sg:postcode":"64081",
    "sg:province":"MO",
    "wof:name":"Ryan Miller Appraisal",
    "wof:placetype":"venue"
},
  "geometry": {"coordinates":[-94.421356,38.928303],"type":"Point"}
}