{
  "type": "Feature",
  "properties": {
    "iso:country":"US",
    "sg:address":"1051 Reddington Timbers",
    "sg:city":"Saint Charles",
    "sg:classifiers":[
        {
            "category":"Retail",
            "subcategory":"Auto Repair",
            "type":"Services"
        }
    ],
    "sg:phone":"+1 314 504 8468",
    "sg:postcode":"63304",
    "sg:province":"MO",
    "sg:tags":[
        "body"
    ],
    "wof:name":"Auto Tint",
    "wof:placetype":"venue"
},
  "geometry": {"coordinates":[-90.593457,38.73338],"type":"Point"}
}