{
  "type": "Feature",
  "properties": {
    "iso:country":"US",
    "sg:address":"205 College St W",
    "sg:city":"Wellington",
    "sg:classifiers":[
        {
            "category":"Structure",
            "subcategory":"Office Building",
            "type":"Public Place"
        }
    ],
    "sg:phone":"+1 573 448 3453",
    "sg:postcode":"64097",
    "sg:province":"MO",
    "sg:tags":[
        "park"
    ],
    "wof:name":"Wellington Properties, Ltd., L.P.",
    "wof:placetype":"venue"
},
  "geometry": {"coordinates":[-93.984881,39.131513],"type":"Point"}
}