{
  "type": "Feature",
  "properties": {
    "iso:country":"US",
    "sg:address":"3623 Hawks Rest Rd",
    "sg:city":"Pacific",
    "sg:classifiers":[
        {
            "category":"Building & Trades",
            "subcategory":"Electrical",
            "type":"Services"
        },
        {
            "category":"Shopping",
            "type":"Retail Goods"
        }
    ],
    "sg:phone":"+1 314 215 4110",
    "sg:postcode":"63069",
    "sg:province":"MO",
    "sg:tags":[
        "telecommunication",
        "supply",
        "telephone",
        "equipment",
        "maintain",
        "install"
    ],
    "wof:name":"Master Communications Inc",
    "wof:placetype":"venue"
},
  "geometry": {"coordinates":[-90.713649,38.550191],"type":"Point"}
}