{
  "type": "Feature",
  "properties": {
    "iso:country":"US",
    "sg:address":"100 E Rollins St",
    "sg:city":"Moberly",
    "sg:classifiers":[
        {
            "category":"Personal",
            "subcategory":"Beauty Salon",
            "type":"Services"
        }
    ],
    "sg:phone":"+1 660 263 5887",
    "sg:postcode":"65270",
    "sg:province":"MO",
    "wof:name":"Hdqtrs.",
    "wof:placetype":"venue"
},
  "geometry": {"coordinates":[-92.436172,39.418621],"type":"Point"}
}