{
  "type": "Feature",
  "properties": {
    "iso:country":"US",
    "sg:address":"3019 Wayne Ave",
    "sg:city":"Poplar Bluff",
    "sg:classifiers":[
        {
            "category":"Building & Trades",
            "subcategory":"Construction",
            "type":"Services"
        }
    ],
    "sg:phone":"+1 573 785 0490",
    "sg:postcode":"63901",
    "sg:province":"MO",
    "sg:tags":[
        "residential",
        "commercial",
        "contractor"
    ],
    "wof:name":"J M L Inc",
    "wof:placetype":"venue"
},
  "geometry": {"coordinates":[-90.426551,36.730192],"type":"Point"}
}