{
  "type": "Feature",
  "properties": {
    "iso:country":"US",
    "sg:address":"7554 E Farm Rd 68",
    "sg:city":"Strafford",
    "sg:classifiers":[
        {
            "category":"Building & Trades",
            "subcategory":"Construction",
            "type":"Services"
        }
    ],
    "sg:phone":"+1 417 887 4132",
    "sg:postcode":"65757",
    "sg:province":"MO",
    "sg:tags":[
        "house",
        "nonresidential"
    ],
    "wof:name":"Russ Construction Company Inc",
    "wof:placetype":"venue"
},
  "geometry": {"coordinates":[-93.127251,37.314209],"type":"Point"}
}