{
  "type": "Feature",
  "properties": {
    "iso:country":"US",
    "sg:address":"12 Main St",
    "sg:city":"St Peters",
    "sg:classifiers":[
        {
            "category":"Building & Trades",
            "subcategory":"Construction",
            "type":"Services"
        }
    ],
    "sg:phone":"+1 636 397 4527",
    "sg:postcode":"63376",
    "sg:province":"MO",
    "sg:tags":[
        "front",
        "paint",
        "store",
        "contractor"
    ],
    "wof:name":"Quality Glass and Mirror Inc",
    "wof:placetype":"venue"
},
  "geometry": {"coordinates":[-90.62725500000001,38.802369],"type":"Point"}
}