{
  "type": "Feature",
  "properties": {
    "iso:country":"US",
    "sg:address":"728 Straub Rd",
    "sg:city":"Chesterfield",
    "sg:classifiers":[
        {
            "category":"Insurance",
            "subcategory":"Hazard Insurance",
            "type":"Services"
        }
    ],
    "sg:phone":"+1 636 227 0267",
    "sg:postcode":"63017",
    "sg:province":"MO",
    "sg:tags":[
        "consulting",
        "carrier",
        "business"
    ],
    "wof:name":"Edward E Cooke & Associates",
    "wof:placetype":"venue"
},
  "geometry": {"coordinates":[-90.53801300000001,38.623436],"type":"Point"}
}