{
  "type": "Feature",
  "properties": {
    "iso:country":"US",
    "sg:address":"1104 Independence St",
    "sg:city":"Cape Girardeau",
    "sg:classifiers":[
        {
            "category":"Social Services",
            "subcategory":"Child Care",
            "type":"Services"
        }
    ],
    "sg:phone":"+1 573 335 0394",
    "sg:postcode":"63703",
    "sg:province":"MO",
    "sg:tags":[
        "day"
    ],
    "wof:name":"McClintons Day Care",
    "wof:placetype":"venue"
},
  "geometry": {"coordinates":[-89.53377399999999,37.304983],"type":"Point"}
}