{
  "type": "Feature",
  "properties": {
    "iso:country":"US",
    "sg:address":"11906 Manchester Rd",
    "sg:city":"St Louis",
    "sg:classifiers":[
        {
            "category":"Professional",
            "subcategory":"Business Services",
            "type":"Services"
        }
    ],
    "sg:phone":"+1 314 965 2085",
    "sg:postcode":"63131",
    "sg:province":"MO",
    "sg:tags":[
        "consulting",
        "management",
        "broker"
    ],
    "sg:website":"www.optimgroup.com",
    "wof:name":"Optim Consulting Group",
    "wof:placetype":"venue"
},
  "geometry": {"coordinates":[-90.432006,38.601047],"type":"Point"}
}