{
  "type": "Feature",
  "properties": {
    "iso:country":"US",
    "sg:address":"607 S 5th St",
    "sg:city":"Saint Charles",
    "sg:classifiers":[
        {
            "category":"Wholesale",
            "subcategory":"Computers",
            "type":"Manufacturing & Wholesale Goods"
        }
    ],
    "sg:phone":"+1 636 949 8850",
    "sg:postcode":"63301",
    "sg:province":"MO",
    "sg:tags":[
        "related"
    ],
    "wof:name":"Pearl Computer",
    "wof:placetype":"venue"
},
  "geometry": {"coordinates":[-90.48863299999999,38.778002],"type":"Point"}
}