{
  "type": "Feature",
  "properties": {
    "iso:country":"US",
    "sg:address":"2844 Thier Dr",
    "sg:city":"High Ridge",
    "sg:classifiers":[
        {
            "category":"Professional",
            "type":"Services"
        }
    ],
    "sg:phone":"+1 636 376 3826",
    "sg:postcode":"63049",
    "sg:province":"MO",
    "wof:name":"Frohwitter Wood Products",
    "wof:placetype":"venue"
},
  "geometry": {"coordinates":[-90.534586,38.463648],"type":"Point"}
}