{
  "type": "Feature",
  "properties": {
    "iso:country":"US",
    "sg:address":"560 S Strack Church Rd",
    "sg:city":"Wright City",
    "sg:classifiers":[
        {
            "category":"Building & Trades",
            "subcategory":"Construction",
            "type":"Services"
        }
    ],
    "sg:phone":"+1 636 456 2694",
    "sg:postcode":"63390",
    "sg:province":"MO",
    "sg:tags":[
        "house"
    ],
    "wof:name":"J T Construction",
    "wof:placetype":"venue"
},
  "geometry": {"coordinates":[-91.074625,38.798468],"type":"Point"}
}