{
  "type": "Feature",
  "properties": {
    "iso:country":"US",
    "sg:address":"19712 Pike 257",
    "sg:city":"Bowling Green",
    "sg:classifiers":[
        {
            "category":"Shopping",
            "subcategory":"Catalog Store",
            "type":"Retail Goods"
        }
    ],
    "sg:phone":"+1 573 324 6238",
    "sg:postcode":"63334",
    "sg:province":"MO",
    "sg:tags":[
        "mail",
        "house"
    ],
    "wof:name":"H & A Industries",
    "wof:placetype":"venue"
},
  "geometry": {"coordinates":[-91.10852199999999,39.339279],"type":"Point"}
}