{
  "type": "Feature",
  "properties": {
    "iso:country":"US",
    "sg:address":"1192 Tealwood Dr",
    "sg:city":"St Charles",
    "sg:classifiers":[
        {
            "category":"Building & Trades",
            "subcategory":"Construction",
            "type":"Services"
        }
    ],
    "sg:phone":"+1 636 300 8080",
    "sg:postcode":"63304",
    "sg:province":"MO",
    "sg:tags":[
        "skylight"
    ],
    "wof:name":"Denco Construction Svc LLC",
    "wof:placetype":"venue"
},
  "geometry": {"coordinates":[-90.670512,38.734249],"type":"Point"}
}