{
  "type": "Feature",
  "properties": {
    "iso:country":"US",
    "sg:address":"4151 Benne Rd",
    "sg:city":"Defiance",
    "sg:classifiers":[
        {
            "category":"Professional",
            "type":"Services"
        }
    ],
    "sg:phone":"+1 636 828 9393",
    "sg:postcode":"63341",
    "sg:province":"MO",
    "sg:tags":[
        "establishment"
    ],
    "wof:name":"Bridlespur Show Grounds",
    "wof:placetype":"venue"
},
  "geometry": {"coordinates":[-90.82611199999999,38.708012],"type":"Point"}
}