{
  "type": "Feature",
  "properties": {
    "iso:country":"US",
    "sg:address":"8200 Longview Rd",
    "sg:city":"Kansas City",
    "sg:classifiers":[
        {
            "category":"Retail",
            "subcategory":"Repair Shop",
            "type":"Services"
        }
    ],
    "sg:phone":"+1 816 763 5272",
    "sg:postcode":"64134",
    "sg:province":"MO",
    "wof:name":"Kalwei Taxidermist",
    "wof:placetype":"venue"
},
  "geometry": {"coordinates":[-94.493596,38.914685],"type":"Point"}
}