{
  "type": "Feature",
  "properties": {
    "iso:country":"US",
    "sg:address":"614 N Walnut St",
    "sg:city":"Cameron",
    "sg:classifiers":[
        {
            "category":"Fast Food",
            "type":"Food & Drink"
        },
        {
            "category":"Restaurant",
            "type":"Food & Drink"
        }
    ],
    "sg:phone":"+1 816 632 2904",
    "sg:postcode":"64429",
    "sg:province":"MO",
    "sg:tags":[
        "mexican"
    ],
    "sg:website":"http://www.tacobell.com",
    "wof:name":"Taco Bell",
    "wof:placetype":"venue"
},
  "geometry": {"coordinates":[-94.23569999999999,39.744355],"type":"Point"}
}