{
  "type": "Feature",
  "properties": {
    "iso:country":"US",
    "sg:address":"9881 NE 292nd St",
    "sg:city":"Cameron",
    "sg:classifiers":[
        {
            "category":"Wholesale",
            "subcategory":"Machinery & Supplies",
            "type":"Manufacturing & Wholesale Goods"
        }
    ],
    "sg:phone":"+1 816 632 2997",
    "sg:postcode":"64429",
    "sg:province":"MO",
    "sg:tags":[
        "equipment",
        "industrial"
    ],
    "wof:name":"T&W Enterprises",
    "wof:placetype":"venue"
},
  "geometry": {"coordinates":[-94.21626000000001,39.621617],"type":"Point"}
}