{
  "type": "Feature",
  "properties": {
    "iso:country":"US",
    "sg:address":"18500 State Hwy U",
    "sg:city":"St James",
    "sg:classifiers":[
        {
            "category":"Manufacturing",
            "subcategory":"Food",
            "type":"Manufacturing & Wholesale Goods"
        }
    ],
    "sg:phone":"+1 573 265 5000",
    "sg:postcode":"65559",
    "sg:province":"MO",
    "sg:tags":[
        "winery"
    ],
    "wof:name":"Heinrichshaus Winery",
    "wof:placetype":"venue"
},
  "geometry": {"coordinates":[-91.543808,38.070703],"type":"Point"}
}