{
  "type": "Feature",
  "properties": {
    "addr:full":"1300 E Republic Rd Springfield MO 65804",
    "addr:housenumber":"1300",
    "addr:postcode":"65804",
    "addr:street":"E Republic Rd",
    "iso:country":"US",
    "sg:address":"1300 E Republic Rd",
    "sg:city":"Springfield",
    "sg:classifiers":[
        {
            "category":"Banks & Credit Unions",
            "subcategory":"Investment Brokerage",
            "type":"Services"
        }
    ],
    "sg:phone":"+1 800 790 5863",
    "sg:postcode":"65804",
    "sg:province":"MO",
    "sg:tags":[
        "firm",
        "brokerage"
    ],
    "wof:name":"Charles Schwab",
    "wof:placetype":"venue"
},
  "geometry": {"coordinates":[-93.275369,37.137563],"type":"Point"}
}