{
  "type": "Feature",
  "properties": {
    "iso:country":"US",
    "sg:address":"1311 Grand Ave",
    "sg:city":"Columbia",
    "sg:classifiers":[
        {
            "category":"Retail",
            "subcategory":"Repair Shop",
            "type":"Services"
        }
    ],
    "sg:phone":"+1 573 443 3333",
    "sg:postcode":"65203",
    "sg:province":"MO",
    "wof:name":"Adams Locksmiths",
    "wof:placetype":"venue"
},
  "geometry": {"coordinates":[-92.336259,38.966054],"type":"Point"}
}