{
  "type": "Feature",
  "properties": {
    "iso:country":"US",
    "sg:address":"601 S Main St",
    "sg:city":"Joplin",
    "sg:classifiers":[
        {
            "category":"Real Estate",
            "subcategory":"Real Estate Services",
            "type":"Services"
        },
        {
            "category":"Real Estate",
            "subcategory":"Real Estate Operator",
            "type":"Services"
        }
    ],
    "sg:phone":"+1 417 782 1550",
    "sg:postcode":"64801",
    "sg:province":"MO",
    "sg:tags":[
        "vacancy",
        "apartment",
        "rental",
        "listing"
    ],
    "wof:name":"Frisco Station Apartment",
    "wof:placetype":"venue"
},
  "geometry": {"coordinates":[-94.51342,37.085461],"type":"Point"}
}