{
  "type": "Feature",
  "properties": {
    "iso:country":"US",
    "sg:address":"854 Peewee Crossing Rd",
    "sg:city":"Seymour",
    "sg:classifiers":[
        {
            "category":"Organizations",
            "subcategory":"Religious Organization",
            "type":"Services"
        }
    ],
    "sg:phone":"+1 417 935 4224",
    "sg:postcode":"65746",
    "sg:province":"MO",
    "wof:name":"Ozark Conservative Menn Church",
    "wof:placetype":"venue"
},
  "geometry": {"coordinates":[-92.720366,37.115052],"type":"Point"}
}