{
  "type": "Feature",
  "properties": {
    "iso:country":"US",
    "sg:address":"2449 Mary Ave",
    "sg:city":"Brentwood",
    "sg:classifiers":[
        {
            "category":"Real Estate",
            "subcategory":"Real Estate Services",
            "type":"Services"
        },
        {
            "category":"Real Estate",
            "subcategory":"Real Estate Agent",
            "type":"Services"
        }
    ],
    "sg:phone":"+1 314 962 4018",
    "sg:postcode":"63144",
    "sg:province":"MO",
    "sg:tags":[
        "buyer",
        "broker"
    ],
    "wof:name":"Wilma Nowell Real Estate",
    "wof:placetype":"venue"
},
  "geometry": {"coordinates":[-90.345484,38.615293],"type":"Point"}
}