{
  "type": "Feature",
  "properties": {
    "iso:country":"US",
    "sg:address":"9530 James A Reed Rd",
    "sg:city":"Kansas City",
    "sg:classifiers":[
        {
            "category":"Health Services",
            "subcategory":"Clinic",
            "type":"Services"
        }
    ],
    "sg:phone":"+1 816 763 8005",
    "sg:postcode":"64134",
    "sg:province":"MO",
    "sg:tags":[
        "home"
    ],
    "wof:name":"Caring Hands",
    "wof:placetype":"venue"
},
  "geometry": {"coordinates":[-94.494193,38.950558],"type":"Point"}
}