{
  "type": "Feature",
  "properties": {
    "iso:country":"US",
    "sg:address":"443 N New Ballas Rd",
    "sg:city":"Saint Louis",
    "sg:classifiers":[
        {
            "category":"Health Services",
            "subcategory":"Health Practitioner",
            "type":"Services"
        }
    ],
    "sg:phone":"+1 314 872 7069",
    "sg:postcode":"63141",
    "sg:province":"MO",
    "wof:name":"Ann Moran",
    "wof:placetype":"venue"
},
  "geometry": {"coordinates":[-90.44335700000001,38.663208],"type":"Point"}
}