{
  "type": "Feature",
  "properties": {
    "iso:country":"US",
    "sg:address":"31 Club Grounds Dr",
    "sg:city":"Florissant",
    "sg:classifiers":[
        {
            "category":"Building & Trades",
            "subcategory":"Construction",
            "type":"Services"
        }
    ],
    "sg:phone":"+1 314 830 4460",
    "sg:postcode":"63033",
    "sg:province":"MO",
    "sg:tags":[
        "house"
    ],
    "wof:name":"A1 Construction & Remodeling",
    "wof:placetype":"venue"
},
  "geometry": {"coordinates":[-90.281665,38.803387],"type":"Point"}
}