{
  "type": "Feature",
  "properties": {
    "iso:country":"US",
    "sg:address":"541 E Saint Louis St",
    "sg:city":"Springfield",
    "sg:classifiers":[
        {
            "category":"Recreation",
            "type":"Entertainment"
        }
    ],
    "sg:phone":"+1 573 449 0116",
    "sg:postcode":"65806",
    "sg:province":"MO",
    "wof:name":"Billards Too",
    "wof:placetype":"venue"
},
  "geometry": {"coordinates":[-93.287324,37.208945],"type":"Point"}
}