{
  "type": "Feature",
  "properties": {
    "iso:country":"US",
    "sg:address":"9702 Cameron Rd",
    "sg:city":"Excelsior Springs",
    "sg:classifiers":[
        {
            "category":"Professional",
            "subcategory":"Business Services",
            "type":"Services"
        }
    ],
    "sg:phone":"+1 816 750 4301",
    "sg:postcode":"64024",
    "sg:province":"MO",
    "wof:name":"S & S Enterprises",
    "wof:placetype":"venue"
},
  "geometry": {"coordinates":[-94.291335,39.268167],"type":"Point"}
}