{
  "type": "Feature",
  "properties": {
    "iso:country":"US",
    "sg:address":"114 N Church St",
    "sg:city":"Fayette",
    "sg:classifiers":[
        {
            "category":"Personal",
            "subcategory":"Beauty Salon",
            "type":"Services"
        }
    ],
    "sg:phone":"+1 660 248 9889",
    "sg:postcode":"65248",
    "sg:province":"MO",
    "wof:name":"Serenity Salon & Spa",
    "wof:placetype":"venue"
},
  "geometry": {"coordinates":[-92.683703,39.145896],"type":"Point"}
}