{
  "type": "Feature",
  "properties": {
    "iso:country":"US",
    "sg:address":"10445 Clayton Rd",
    "sg:city":"Saint Louis",
    "sg:classifiers":[
        {
            "category":"Organizations",
            "subcategory":"Religious Organization",
            "type":"Services"
        }
    ],
    "sg:phone":"+1 314 993 2328",
    "sg:postcode":"63131",
    "sg:province":"MO",
    "wof:name":"Corporation of President of Th",
    "wof:placetype":"venue"
},
  "geometry": {"coordinates":[-90.411222,38.633111],"type":"Point"}
}