{
  "type": "Feature",
  "properties": {
    "iso:country":"US",
    "sg:address":"25 Meandering Ln",
    "sg:city":"St Peters",
    "sg:classifiers":[
        {
            "category":"Insurance",
            "subcategory":"Hazard Insurance",
            "type":"Services"
        }
    ],
    "sg:phone":"+1 636 936 1514",
    "sg:postcode":"63376",
    "sg:province":"MO",
    "sg:tags":[
        "bond"
    ],
    "wof:name":"Americas Bailbonds",
    "wof:placetype":"venue"
},
  "geometry": {"coordinates":[-90.597689,38.776666],"type":"Point"}
}