{
  "type": "Feature",
  "properties": {
    "iso:country":"US",
    "sg:address":"824 N Dakota Dr",
    "sg:city":"Independence",
    "sg:classifiers":[
        {
            "category":"Fast Food",
            "type":"Food & Drink"
        },
        {
            "category":"Restaurant",
            "type":"Food & Drink"
        }
    ],
    "sg:phone":"+1 816 257 9966",
    "sg:postcode":"64056",
    "sg:province":"MO",
    "sg:tags":[
        "take",
        "pizza"
    ],
    "sg:website":"http://www.papamurphys.com/",
    "wof:name":"Papa Murphy's",
    "wof:placetype":"venue"
},
  "geometry": {"coordinates":[-94.371771,39.118742],"type":"Point"}
}