{
  "type": "Feature",
  "properties": {
    "iso:country":"US",
    "sg:address":"835 Broadway St",
    "sg:city":"Cape Girardeau",
    "sg:classifiers":[
        {
            "category":"Restaurant",
            "type":"Food & Drink"
        }
    ],
    "sg:phone":"+1 573 334 0537",
    "sg:postcode":"63701",
    "sg:province":"MO",
    "sg:tags":[
        "eating"
    ],
    "wof:name":"Grace Cafe",
    "wof:placetype":"venue"
},
  "geometry": {"coordinates":[-89.52840399999999,37.3068],"type":"Point"}
}