{
  "type": "Feature",
  "properties": {
    "iso:country":"US",
    "sg:address":"600 E Yerby St",
    "sg:city":"Marshall",
    "sg:classifiers":[
        {
            "category":"Autos & Motor Vehicles",
            "subcategory":"Fuel & Gas Station",
            "type":"Retail Goods"
        }
    ],
    "sg:phone":"+1 660 886 8474",
    "sg:postcode":"65340",
    "sg:province":"MO",
    "sg:tags":[
        "automobile",
        "station",
        "gasoline",
        "used"
    ],
    "wof:name":"Gilliams Automotive Service",
    "wof:placetype":"venue"
},
  "geometry": {"coordinates":[-93.18825099999999,39.114314],"type":"Point"}
}