{
  "type": "Feature",
  "properties": {
    "addr:full":"222 S Meramec Ave St Louis MO 63105",
    "addr:housenumber":"222",
    "addr:postcode":"63105",
    "addr:street":"S Meramec Ave",
    "iso:country":"US",
    "sg:address":"222 S Meramec Ave",
    "sg:city":"St Louis",
    "sg:classifiers":[
        {
            "category":"Insurance",
            "subcategory":"Insurance Agent",
            "type":"Services"
        }
    ],
    "sg:phone":"+1 314 727 4779",
    "sg:postcode":"63105",
    "sg:province":"MO",
    "wof:name":"Metro Financial Group",
    "wof:placetype":"venue"
},
  "geometry": {"coordinates":[-90.340174,38.646182],"type":"Point"}
}