{
  "type": "Feature",
  "properties": {
    "iso:country":"US",
    "sg:address":"6440 Forsyth Blvd",
    "sg:city":"St Louis",
    "sg:classifiers":[
        {
            "category":"Professional",
            "type":"Services"
        },
        {
            "category":"Restaurant",
            "type":"Food & Drink"
        }
    ],
    "sg:phone":"+1 314 935 5210",
    "sg:postcode":"63105",
    "sg:province":"MO",
    "sg:tags":[
        "planning",
        "event"
    ],
    "sg:website":"www.whittemorehouse.org/",
    "wof:name":"Whittemore House",
    "wof:placetype":"venue"
},
  "geometry": {"coordinates":[-90.309191,38.645998],"type":"Point"}
}