{
  "type": "Feature",
  "properties": {
    "iso:country":"US",
    "sg:address":"3325 Tom Sawyer Dr",
    "sg:city":"Florissant",
    "sg:classifiers":[
        {
            "category":"Shopping",
            "subcategory":"Music",
            "type":"Retail Goods"
        }
    ],
    "sg:phone":"+1 314 921 5762",
    "sg:postcode":"63033",
    "sg:province":"MO",
    "wof:name":"Violet Sky Records",
    "wof:placetype":"venue"
},
  "geometry": {"coordinates":[-90.293583,38.786395],"type":"Point"}
}