{
  "type": "Feature",
  "properties": {
    "iso:country":"US",
    "sg:address":"202 Maplewood Dr",
    "sg:city":"Columbia",
    "sg:classifiers":[
        {
            "category":"Food & Beverages",
            "subcategory":"Groceries & Convenience Stores",
            "type":"Retail Goods"
        }
    ],
    "sg:phone":"+1 573 449 7877",
    "sg:postcode":"65203",
    "sg:province":"MO",
    "wof:name":"Hesco Mkt",
    "wof:placetype":"venue"
},
  "geometry": {"coordinates":[-92.36158399999999,38.950785],"type":"Point"}
}