{
  "type": "Feature",
  "properties": {
    "iso:country":"US",
    "sg:address":"1972 State Highway 165",
    "sg:city":"Branson",
    "sg:classifiers":[
        {
            "category":"Shopping",
            "subcategory":"Jewelry",
            "type":"Retail Goods"
        },
        {
            "category":"Manufacturing",
            "subcategory":"Jewelry",
            "type":"Manufacturing & Wholesale Goods"
        }
    ],
    "sg:phone":"+1 417 336 9015",
    "sg:postcode":"65616",
    "sg:province":"MO",
    "sg:tags":[
        "designer",
        "jeweler"
    ],
    "wof:name":"The Italian Charm Co.",
    "wof:placetype":"venue"
},
  "geometry": {"coordinates":[-93.28866600000001,36.603863],"type":"Point"}
}