{
  "type": "Feature",
  "properties": {
    "iso:country":"US",
    "sg:address":"950 Des Peres Ave",
    "sg:city":"St Louis",
    "sg:classifiers":[
        {
            "category":"Building & Trades",
            "subcategory":"Cleaning & Sanitation",
            "type":"Services"
        }
    ],
    "sg:phone":"+1 314 968 8377",
    "sg:postcode":"63119",
    "sg:province":"MO",
    "sg:tags":[
        "janitor"
    ],
    "wof:name":"Clean Cut Creations",
    "wof:placetype":"venue"
},
  "geometry": {"coordinates":[-90.36034100000001,38.607363],"type":"Point"}
}