{
  "type": "Feature",
  "properties": {
    "iso:country":"US",
    "sg:address":"5425 S Broadway",
    "sg:city":"Saint Louis",
    "sg:classifiers":[
        {
            "category":"Government",
            "subcategory":"Post Office",
            "type":"Public Place"
        }
    ],
    "sg:phone":"+1 314 383 6810",
    "sg:postcode":"63111",
    "sg:province":"MO",
    "sg:tags":[
        "postal",
        "us"
    ],
    "wof:name":"US Post Office",
    "wof:placetype":"venue"
},
  "geometry": {"coordinates":[-90.241193,38.563128],"type":"Point"}
}