{
  "type": "Feature",
  "properties": {
    "iso:country":"US",
    "sg:address":"2750 W Bennett St",
    "sg:city":"Springfield",
    "sg:classifiers":[
        {
            "category":"Real Estate",
            "subcategory":"Real Estate Operator",
            "type":"Services"
        }
    ],
    "sg:phone":"+1 417 865 8375",
    "sg:postcode":"65802",
    "sg:province":"MO",
    "sg:tags":[
        "mobile",
        "home",
        "community"
    ],
    "wof:name":"Scenic View Mobile Home Park",
    "wof:placetype":"venue"
},
  "geometry": {"coordinates":[-93.33257999999999,37.19007],"type":"Point"}
}