{
  "type": "Feature",
  "properties": {
    "iso:country":"US",
    "sg:address":"211 S Jefferson Ave",
    "sg:city":"Saint Louis",
    "sg:classifiers":[
        {
            "category":"Communications",
            "subcategory":"Film & Video Production",
            "type":"Services"
        }
    ],
    "sg:phone":"+1 314 534 1940",
    "sg:postcode":"63103",
    "sg:province":"MO",
    "sg:tags":[
        "motion",
        "picture",
        "durable",
        "good"
    ],
    "wof:name":"Swank Audio Visuals",
    "wof:placetype":"venue"
},
  "geometry": {"coordinates":[-90.21677699999999,38.629188],"type":"Point"}
}