{
  "type": "Feature",
  "properties": {
    "iso:country":"US",
    "sg:address":"1931 S Business Highway 65",
    "sg:city":"Hollister",
    "sg:classifiers":[
        {
            "category":"Personal",
            "subcategory":"Tattoo Parlor",
            "type":"Services"
        },
        {
            "category":"Personal",
            "subcategory":"Piercing",
            "type":"Services"
        }
    ],
    "sg:phone":"+1 417 336 8535",
    "sg:postcode":"65672",
    "sg:province":"MO",
    "sg:tags":[
        "body"
    ],
    "wof:name":"Aloha Nonie Lani Tatoo Art Studio",
    "wof:placetype":"venue"
},
  "geometry": {"coordinates":[-93.217873,36.625027],"type":"Point"}
}