{
  "type": "Feature",
  "properties": {
    "iso:country":"US",
    "sg:address":"20704 E Waters Rd",
    "sg:city":"Harrisonville",
    "sg:classifiers":[
        {
            "category":"Shopping",
            "type":"Retail Goods"
        }
    ],
    "sg:phone":"+1 816 884 6239",
    "sg:postcode":"64701",
    "sg:province":"MO",
    "sg:tags":[
        "merchandise"
    ],
    "wof:name":"Horizon Trophies & Awards",
    "wof:placetype":"venue"
},
  "geometry": {"coordinates":[-94.35433399999999,38.677226],"type":"Point"}
}