{
  "type": "Feature",
  "properties": {
    "iso:country":"US",
    "sg:address":"419 Amanda Rd",
    "sg:city":"Ridgedale",
    "sg:classifiers":[
        {
            "category":"Place Of Worship",
            "type":"Public Place"
        }
    ],
    "sg:phone":"+1 417 334 1532",
    "sg:postcode":"65739",
    "sg:province":"MO",
    "sg:tags":[
        "church"
    ],
    "wof:name":"Horizon Christian Church, Inc.",
    "wof:placetype":"venue"
},
  "geometry": {"coordinates":[-93.293855,36.531067],"type":"Point"}
}