{
  "type": "Feature",
  "properties": {
    "iso:country":"US",
    "sg:address":"100 N 16th St",
    "sg:city":"Bethany",
    "sg:classifiers":[
        {
            "category":"Insurance",
            "subcategory":"Insurance Agent",
            "type":"Services"
        }
    ],
    "sg:phone":"+1 660 425 7900",
    "sg:postcode":"64424",
    "sg:province":"MO",
    "wof:name":"Green Hills Insurance Svc",
    "wof:placetype":"venue"
},
  "geometry": {"coordinates":[-94.03467999999999,40.269355],"type":"Point"}
}