{
  "type": "Feature",
  "properties": {
    "iso:country":"US",
    "sg:address":"602 S College Ave",
    "sg:city":"Columbia",
    "sg:classifiers":[
        {
            "category":"Organizations",
            "subcategory":"Community Association",
            "type":"Services"
        }
    ],
    "sg:phone":"+1 573 874 9061",
    "sg:postcode":"65201",
    "sg:province":"MO",
    "sg:tags":[
        "sorority",
        "fraternity"
    ],
    "wof:name":"Alpha Gamma Rho",
    "wof:placetype":"venue"
},
  "geometry": {"coordinates":[-92.32195400000001,38.943259],"type":"Point"}
}