{
  "type": "Feature",
  "properties": {
    "iso:country":"US",
    "sg:address":"19964 Foxridge Dr",
    "sg:city":"Saint Joseph",
    "sg:classifiers":[
        {
            "category":"Professional",
            "type":"Services"
        }
    ],
    "sg:phone":"+1 816 671 9935",
    "sg:postcode":"64505",
    "sg:province":"MO",
    "wof:name":"Platte Valley Resources & MGT",
    "wof:placetype":"venue"
},
  "geometry": {"coordinates":[-94.827522,39.835763],"type":"Point"}
}