{
  "type": "Feature",
  "properties": {
    "iso:country":"US",
    "sg:address":"6639 State Rd Z",
    "sg:city":"Fulton",
    "sg:classifiers":[
        {
            "category":"Professional",
            "subcategory":"Management & Consulting",
            "type":"Services"
        }
    ],
    "sg:phone":"+1 573 592 0728",
    "sg:postcode":"65251",
    "sg:province":"MO",
    "sg:tags":[
        "personal"
    ],
    "wof:name":"Royal Alnce Assoc Chrles Lmper",
    "wof:placetype":"venue"
},
  "geometry": {"coordinates":[-91.899427,38.879978],"type":"Point"}
}