{
  "type": "Feature",
  "properties": {
    "iso:country":"US",
    "sg:address":"8974 Jennings Station Rd",
    "sg:city":"St Louis",
    "sg:classifiers":[
        {
            "category":"Shopping",
            "subcategory":"Clothing, Apparel, & Fashions",
            "type":"Retail Goods"
        }
    ],
    "sg:phone":"+1 314 869 1122",
    "sg:postcode":"63136",
    "sg:province":"MO",
    "sg:tags":[
        "wig",
        "toupee",
        "hairpiece"
    ],
    "wof:name":"Queen's Wig Palace",
    "wof:placetype":"venue"
},
  "geometry": {"coordinates":[-90.24755399999999,38.725793],"type":"Point"}
}