{
  "type": "Feature",
  "properties": {
    "iso:country":"US",
    "sg:address":"215 Shepley Dr",
    "sg:city":"St Louis",
    "sg:classifiers":[
        {
            "category":"Organizations",
            "subcategory":"Religious Organization",
            "type":"Services"
        }
    ],
    "sg:phone":"+1 314 867 9137",
    "sg:postcode":"63137",
    "sg:province":"MO",
    "sg:tags":[
        "church"
    ],
    "wof:name":"West End Mt Carmel Full Gospel",
    "wof:placetype":"venue"
},
  "geometry": {"coordinates":[-90.199898,38.756478],"type":"Point"}
}