{
  "type": "Feature",
  "properties": {
    "iso:country":"US",
    "sg:address":"4467 Aardvark Dr",
    "sg:city":"Joplin",
    "sg:classifiers":[
        {
            "category":"Wholesale",
            "subcategory":"Meat",
            "type":"Manufacturing & Wholesale Goods"
        }
    ],
    "sg:phone":"+1 417 623 8360",
    "sg:postcode":"64804",
    "sg:province":"MO",
    "sg:tags":[
        "plant",
        "packing"
    ],
    "wof:name":"Tri-State Meats",
    "wof:placetype":"venue"
},
  "geometry": {"coordinates":[-94.61373399999999,37.005917],"type":"Point"}
}