{
  "type": "Feature",
  "properties": {
    "iso:country":"US",
    "sg:address":"611 E Harrison St",
    "sg:city":"Kirksville",
    "sg:classifiers":[
        {
            "category":"Building & Trades",
            "subcategory":"Construction",
            "type":"Services"
        }
    ],
    "sg:phone":"+1 660 665 7936",
    "sg:postcode":"63501",
    "sg:province":"MO",
    "sg:tags":[
        "house"
    ],
    "wof:name":"Moore Improvements",
    "wof:placetype":"venue"
},
  "geometry": {"coordinates":[-92.577979,40.195647],"type":"Point"}
}