{
  "type": "Feature",
  "properties": {
    "iso:country":"US",
    "sg:address":"7051 Ward Pkwy N",
    "sg:city":"Kansas City",
    "sg:classifiers":[
        {
            "category":"Professional",
            "subcategory":"Detective & Security Services",
            "type":"Services"
        }
    ],
    "sg:phone":"+1 816 926 0409",
    "sg:postcode":"64113",
    "sg:province":"MO",
    "sg:tags":[
        "investigation"
    ],
    "wof:name":"William L Venable",
    "wof:placetype":"venue"
},
  "geometry": {"coordinates":[-94.60291700000001,39.000208],"type":"Point"}
}