{
  "type": "Feature",
  "properties": {
    "iso:country":"US",
    "sg:address":"8430 E 55 Ter",
    "sg:city":"Kansas City",
    "sg:classifiers":[
        {
            "category":"Real Estate",
            "subcategory":"Real Estate Agent",
            "type":"Services"
        }
    ],
    "sg:phone":"+1 816 743 0565",
    "sg:postcode":"64129",
    "sg:province":"MO",
    "wof:name":"Millicent Irving Realty Co",
    "wof:placetype":"venue"
},
  "geometry": {"coordinates":[-94.48719699999999,39.02331],"type":"Point"}
}