{
  "type": "Feature",
  "properties": {
    "iso:country":"US",
    "sg:address":"122 E Pratt St",
    "sg:city":"De Soto",
    "sg:classifiers":[
        {
            "category":"Social Services",
            "subcategory":"Adult Care",
            "type":"Services"
        }
    ],
    "sg:phone":"+1 636 337 8828",
    "sg:postcode":"63020",
    "sg:province":"MO",
    "sg:tags":[
        "home",
        "residential"
    ],
    "wof:name":"Colonial House",
    "wof:placetype":"venue"
},
  "geometry": {"coordinates":[-90.553797,38.135687],"type":"Point"}
}