{
  "type": "Feature",
  "properties": {
    "iso:country":"US",
    "sg:address":"207 W Washington Ave",
    "sg:city":"Owensville",
    "sg:classifiers":[
        {
            "category":"Organizations",
            "subcategory":"Religious Organization",
            "type":"Services"
        }
    ],
    "sg:phone":"+1 573 437 7822",
    "sg:postcode":"65066",
    "sg:province":"MO",
    "sg:tags":[
        "church"
    ],
    "wof:name":"St Peters Ucc Parsonage",
    "wof:placetype":"venue"
},
  "geometry": {"coordinates":[-91.50304199999999,38.346143],"type":"Point"}
}