{
  "type": "Feature",
  "properties": {
    "iso:country":"US",
    "sg:address":"1609 S Harris Ave",
    "sg:city":"Independence",
    "sg:classifiers":[
        {
            "category":"Professional",
            "subcategory":"Secretarial Services",
            "type":"Services"
        }
    ],
    "sg:phone":"+1 816 254 0038",
    "sg:postcode":"64052",
    "sg:province":"MO",
    "sg:tags":[
        "resume"
    ],
    "wof:name":"Processed Word",
    "wof:placetype":"venue"
},
  "geometry": {"coordinates":[-94.448162,39.087995],"type":"Point"}
}