{
  "type": "Feature",
  "properties": {
    "iso:country":"US",
    "sg:address":"24452 State Hwy 51",
    "sg:city":"Puxico",
    "sg:classifiers":[
        {
            "category":"Autos & Motor Vehicles",
            "subcategory":"Auto Supplies",
            "type":"Retail Goods"
        }
    ],
    "sg:phone":"+1 573 222 3742",
    "sg:postcode":"63960",
    "sg:province":"MO",
    "sg:tags":[
        "automobile",
        "parts"
    ],
    "wof:name":"B & M Auto Parts",
    "wof:placetype":"venue"
},
  "geometry": {"coordinates":[-90.145808,36.966637],"type":"Point"}
}