{
  "type": "Feature",
  "properties": {
    "iso:country":"US",
    "sg:address":"1910 Autumn Hill Dr",
    "sg:city":"O Fallon",
    "sg:classifiers":[
        {
            "category":"Professional",
            "type":"Services"
        }
    ],
    "sg:phone":"+1 636 240 6701",
    "sg:postcode":"63366",
    "sg:province":"MO",
    "wof:name":"Mikes Services",
    "wof:placetype":"venue"
},
  "geometry": {"coordinates":[-90.703087,38.782715],"type":"Point"}
}