{
  "type": "Feature",
  "properties": {
    "iso:country":"US",
    "sg:address":"821 Forqueran St",
    "sg:city":"Slater",
    "sg:phone":"+1 660 529 2201",
    "sg:postcode":"65349",
    "sg:province":"MO",
    "sg:tags":[
        "farm",
        "corn",
        "product"
    ],
    "wof:name":"Keith Head",
    "wof:placetype":"venue"
},
  "geometry": {"coordinates":[-93.053316,39.225613],"type":"Point"}
}