{
  "type": "Feature",
  "properties": {
    "iso:country":"US",
    "sg:address":"1320 E North Ave",
    "sg:city":"Belton",
    "sg:classifiers":[
        {
            "category":"Restaurant",
            "type":"Food & Drink"
        }
    ],
    "sg:menulink":"http://www.allmenus.com/mo/mount-pleasant/37501-papa-murphys/menu/",
    "sg:phone":"+1 816 322 3600",
    "sg:postcode":"64012",
    "sg:province":"MO",
    "sg:tags":[
        "american",
        "pizza"
    ],
    "wof:name":"Papa Murphy's",
    "wof:placetype":"venue"
},
  "geometry": {"coordinates":[-94.51518299999999,38.813749],"type":"Point"}
}