{
  "type": "Feature",
  "properties": {
    "iso:country":"US",
    "sg:address":"104 SW 3 St",
    "sg:city":"Lees Summit",
    "sg:classifiers":[
        {
            "category":"Home & Garden",
            "subcategory":"Carpets & Floor Coverings",
            "type":"Retail Goods"
        }
    ],
    "sg:phone":"+1 816 246 6565",
    "sg:postcode":"64063",
    "sg:province":"MO",
    "sg:tags":[
        "dealer",
        "rug"
    ],
    "wof:name":"Harmon Floor Coverings",
    "wof:placetype":"venue"
},
  "geometry": {"coordinates":[-94.37960699999999,38.911201],"type":"Point"}
}