{
  "type": "Feature",
  "properties": {
    "iso:country":"US",
    "sg:address":"901 S Main St",
    "sg:city":"Auxvasse",
    "sg:classifiers":[
        {
            "category":"Health Services",
            "subcategory":"Health Practitioner",
            "type":"Services"
        }
    ],
    "sg:phone":"+1 573 386 5747",
    "sg:postcode":"65231",
    "sg:province":"MO",
    "wof:name":"Jean Howard Rd",
    "wof:placetype":"venue"
},
  "geometry": {"coordinates":[-91.897319,39.010732],"type":"Point"}
}