{
  "type": "Feature",
  "properties": {
    "iso:country":"US",
    "sg:address":"501 N Main St",
    "sg:city":"Kirksville",
    "sg:classifiers":[
        {
            "category":"Building & Trades",
            "subcategory":"Electrical",
            "type":"Services"
        }
    ],
    "sg:phone":"+1 660 627 5205",
    "sg:postcode":"63501",
    "sg:province":"MO",
    "sg:tags":[
        "electrical",
        "electric",
        "contractor"
    ],
    "wof:name":"Missouri Electrical & Cntrctng",
    "wof:placetype":"venue"
},
  "geometry": {"coordinates":[-92.58538299999999,40.198799],"type":"Point"}
}