{
  "type": "Feature",
  "properties": {
    "iso:country":"US",
    "sg:address":"326 Meadowbrook Dr",
    "sg:city":"Ballwin",
    "sg:classifiers":[
        {
            "category":"Building & Trades",
            "subcategory":"Construction",
            "type":"Services"
        }
    ],
    "sg:phone":"+1 636 227 1839",
    "sg:postcode":"63011",
    "sg:province":"MO",
    "sg:tags":[
        "contractor"
    ],
    "wof:name":"Piel Contracting Co",
    "wof:placetype":"venue"
},
  "geometry": {"coordinates":[-90.562546,38.60542],"type":"Point"}
}