{
  "type": "Feature",
  "properties": {
    "iso:country":"US",
    "sg:address":"302 W College Ave",
    "sg:city":"Fredericktown",
    "sg:classifiers":[
        {
            "category":"Personal",
            "type":"Services"
        }
    ],
    "sg:phone":"+1 573 783 8018",
    "sg:postcode":"63645",
    "sg:province":"MO",
    "wof:name":"Clawson Enterprises",
    "wof:placetype":"venue"
},
  "geometry": {"coordinates":[-90.301164,37.557969],"type":"Point"}
}