{
  "type": "Feature",
  "properties": {
    "iso:country":"US",
    "sg:address":"421 Stratford Rd",
    "sg:city":"Lees Summit",
    "sg:classifiers":[
        {
            "category":"Building & Trades",
            "subcategory":"Landscaping Services",
            "type":"Services"
        }
    ],
    "sg:phone":"+1 816 525 4502",
    "sg:postcode":"64081",
    "sg:province":"MO",
    "wof:name":"Outdoors Man",
    "wof:placetype":"venue"
},
  "geometry": {"coordinates":[-94.386636,38.902611],"type":"Point"}
}