{
  "type": "Feature",
  "properties": {
    "iso:country":"US",
    "sg:address":"509 E Maple St",
    "sg:city":"Shelbina",
    "sg:classifiers":[
        {
            "category":"Mining & Drilling",
            "type":"Manufacturing & Wholesale Goods"
        }
    ],
    "sg:phone":"+1 573 588 4044",
    "sg:postcode":"63468",
    "sg:province":"MO",
    "sg:tags":[
        "quarry"
    ],
    "wof:name":"Charles O'Laughlin Quarry",
    "wof:placetype":"venue"
},
  "geometry": {"coordinates":[-92.030964,39.692818],"type":"Point"}
}