{
  "type": "Feature",
  "properties": {
    "iso:country":"US",
    "sg:address":"1236 Swift Ave",
    "sg:city":"Kansas City",
    "sg:classifiers":[
        {
            "category":"Manufacturing",
            "subcategory":"Tools & Machinery",
            "type":"Manufacturing & Wholesale Goods"
        }
    ],
    "sg:phone":"+1 816 471 3751",
    "sg:postcode":"64116",
    "sg:province":"MO",
    "sg:tags":[
        "machine",
        "shop"
    ],
    "wof:name":"Clegg Machine Works Inc",
    "wof:placetype":"venue"
},
  "geometry": {"coordinates":[-94.577487,39.131683],"type":"Point"}
}