{
  "type": "Feature",
  "properties": {
    "iso:country":"US",
    "sg:address":"13924 S Noland Ct",
    "sg:city":"Independence",
    "sg:classifiers":[
        {
            "category":"Shopping",
            "subcategory":"Shoes",
            "type":"Retail Goods"
        }
    ],
    "sg:phone":"+1 816 461 8770",
    "sg:postcode":"64055",
    "sg:province":"MO",
    "sg:tags":[
        "durable"
    ],
    "wof:name":"Red Wing Shoe Store",
    "wof:placetype":"venue"
},
  "geometry": {"coordinates":[-94.415389,39.054455],"type":"Point"}
}