{
  "type": "Feature",
  "properties": {
    "iso:country":"US",
    "sg:address":"4734 S Spring Ave",
    "sg:city":"Saint Louis",
    "sg:classifiers":[
        {
            "category":"Building & Trades",
            "subcategory":"Construction",
            "type":"Services"
        }
    ],
    "sg:phone":"+1 314 353 0000",
    "sg:postcode":"63116",
    "sg:province":"MO",
    "sg:tags":[
        "house"
    ],
    "wof:name":"Bedfords Home Repair",
    "wof:placetype":"venue"
},
  "geometry": {"coordinates":[-90.25449399999999,38.576791],"type":"Point"}
}