{
  "type": "Feature",
  "properties": {
    "iso:country":"US",
    "sg:address":"9863 Diamond Dr",
    "sg:city":"St Louis",
    "sg:classifiers":[
        {
            "category":"Personal",
            "subcategory":"Beauty Salon",
            "type":"Services"
        }
    ],
    "sg:phone":"+1 314 867 8722",
    "sg:postcode":"63137",
    "sg:province":"MO",
    "sg:tags":[
        "shop"
    ],
    "wof:name":"Shear Perfection",
    "wof:placetype":"venue"
},
  "geometry": {"coordinates":[-90.210611,38.745434],"type":"Point"}
}