{
  "type": "Feature",
  "properties": {
    "iso:country":"US",
    "sg:address":"9222 Lackland Rd",
    "sg:city":"Overland",
    "sg:classifiers":[
        {
            "category":"Retail",
            "subcategory":"Funeral Services",
            "type":"Services"
        }
    ],
    "sg:phone":"+1 314 427 2222",
    "sg:postcode":"63114",
    "sg:province":"MO",
    "sg:tags":[
        "director",
        "home"
    ],
    "wof:name":"Ortmann Funeral Home Inc",
    "wof:placetype":"venue"
},
  "geometry": {"coordinates":[-90.36212,38.700299],"type":"Point"}
}