{
  "type": "Feature",
  "properties": {
    "iso:country":"US",
    "sg:address":"13031 State Highway 25",
    "sg:city":"Dexter",
    "sg:classifiers":[
        {
            "category":"Autos & Motor Vehicles",
            "subcategory":"Auto Supplies",
            "type":"Retail Goods"
        },
        {
            "category":"Retail",
            "subcategory":"Auto Repair",
            "type":"Services"
        }
    ],
    "sg:phone":"+1 573 624 6228",
    "sg:postcode":"63841",
    "sg:province":"MO",
    "sg:tags":[
        "body",
        "lettering",
        "automobile",
        "truck",
        "customizing",
        "painting",
        "repairing"
    ],
    "sg:website":"http://www.willsautobodyshop.com",
    "wof:name":"Will's Body Shop",
    "wof:placetype":"venue"
},
  "geometry": {"coordinates":[-89.946343,36.803172],"type":"Point"}
}