{
  "type": "Feature",
  "properties": {
    "addr:full":"201 N Main St Monroe City MO 63456",
    "addr:housenumber":"201",
    "addr:postcode":"63456",
    "addr:street":"N Main St",
    "iso:country":"US",
    "sg:address":"201 N Main St",
    "sg:city":"Monroe City",
    "sg:classifiers":[
        {
            "category":"Organizations",
            "subcategory":"Community Association",
            "type":"Services"
        }
    ],
    "sg:phone":"+1 573 735 4513",
    "sg:postcode":"63456",
    "sg:province":"MO",
    "wof:name":"International Assoc of LI",
    "wof:placetype":"venue"
},
  "geometry": {"coordinates":[-91.734657,39.653801],"type":"Point"}
}