{
  "type": "Feature",
  "properties": {
    "iso:country":"US",
    "sg:address":"6327 Everett Dr",
    "sg:city":"Saint Louis",
    "sg:classifiers":[
        {
            "category":"Professional",
            "subcategory":"Business Services",
            "type":"Services"
        }
    ],
    "sg:phone":"+1 314 522 8819",
    "sg:postcode":"63134",
    "sg:province":"MO",
    "sg:tags":[
        "group"
    ],
    "wof:name":"Systematic Muzick Inc",
    "wof:placetype":"venue"
},
  "geometry": {"coordinates":[-90.32353000000001,38.751716],"type":"Point"}
}