{
  "type": "Feature",
  "properties": {
    "iso:country":"US",
    "sg:address":"3016 Cherry St",
    "sg:city":"Kansas City",
    "sg:classifiers":[
        {
            "category":"Professional",
            "subcategory":"Art Services",
            "type":"Services"
        }
    ],
    "sg:phone":"+1 816 931 4447",
    "sg:postcode":"64108",
    "sg:province":"MO",
    "sg:tags":[
        "photographer",
        "photography",
        "commercial"
    ],
    "sg:website":"www.markwiens.com",
    "wof:name":"Mark Wiens Photography Inc",
    "wof:placetype":"venue"
},
  "geometry": {"coordinates":[-94.577788,39.071029],"type":"Point"}
}