{
  "type": "Feature",
  "properties": {
    "iso:country":"US",
    "sg:address":"506 Hazel St",
    "sg:city":"Poplar Bluff",
    "sg:classifiers":[
        {
            "category":"Real Estate",
            "subcategory":"Real Estate Agent",
            "type":"Services"
        }
    ],
    "sg:phone":"+1 573 785 2623",
    "sg:postcode":"63901",
    "sg:province":"MO",
    "sg:tags":[
        "authorities",
        "housing"
    ],
    "wof:name":"Poplar Bluff Housing Authority",
    "wof:placetype":"venue"
},
  "geometry": {"coordinates":[-90.383865,36.755547],"type":"Point"}
}