{
  "type": "Feature",
  "properties": {
    "iso:country":"US",
    "sg:address":"815 Bobbins Ln",
    "sg:city":"Florissant",
    "sg:classifiers":[
        {
            "category":"Building & Trades",
            "subcategory":"Construction",
            "type":"Services"
        }
    ],
    "sg:phone":"+1 314 839 4638",
    "sg:postcode":"63033",
    "sg:province":"MO",
    "sg:tags":[
        "hanging",
        "contractor"
    ],
    "wof:name":"Champion Painting Inc",
    "wof:placetype":"venue"
},
  "geometry": {"coordinates":[-90.309662,38.783348],"type":"Point"}
}