{
  "type": "Feature",
  "properties": {
    "iso:country":"US",
    "sg:address":"9200 Olive Blvd",
    "sg:city":"St Louis",
    "sg:classifiers":[
        {
            "category":"Banks & Credit Unions",
            "subcategory":"Investment Brokerage",
            "type":"Services"
        }
    ],
    "sg:phone":"+1 314 567 1614",
    "sg:postcode":"63132",
    "sg:province":"MO",
    "sg:tags":[
        "security"
    ],
    "wof:name":"Edward Jones Co",
    "wof:placetype":"venue"
},
  "geometry": {"coordinates":[-90.36893999999999,38.674102],"type":"Point"}
}