{
  "type": "Feature",
  "properties": {
    "iso:country":"US",
    "sg:address":"6009 Heege Rd",
    "sg:city":"Saint Louis",
    "sg:classifiers":[
        {
            "category":"Organizations",
            "subcategory":"Religious Organization",
            "type":"Services"
        }
    ],
    "sg:phone":"+1 314 353 7776",
    "sg:postcode":"63123",
    "sg:province":"MO",
    "wof:name":"Blue Army Diocesan Marian Ctr",
    "wof:placetype":"venue"
},
  "geometry": {"coordinates":[-90.31850799999999,38.565557],"type":"Point"}
}