{
  "type": "Feature",
  "properties": {
    "iso:country":"US",
    "sg:address":"452 Forest Rd",
    "sg:city":"Catawissa",
    "sg:classifiers":[
        {
            "category":"Wholesale",
            "subcategory":"Medical Equipment & Supplies",
            "type":"Manufacturing & Wholesale Goods"
        }
    ],
    "sg:phone":"+1 636 274 1314",
    "sg:postcode":"63015",
    "sg:province":"MO",
    "sg:tags":[
        "instrument",
        "surgical"
    ],
    "wof:name":"Vogel Instruments Inc",
    "wof:placetype":"venue"
},
  "geometry": {"coordinates":[-90.75774699999999,38.363913],"type":"Point"}
}