{
  "type": "Feature",
  "properties": {
    "iso:country":"US",
    "sg:address":"101 N Chestnut St",
    "sg:city":"Cameron",
    "sg:classifiers":[
        {
            "category":"Government",
            "subcategory":"Fire Station",
            "type":"Public Place"
        }
    ],
    "sg:phone":"+1 816 632 2345",
    "sg:postcode":"64429",
    "sg:province":"MO",
    "sg:tags":[
        "department"
    ],
    "wof:name":"Cameron Fire Dept",
    "wof:placetype":"venue"
},
  "geometry": {"coordinates":[-94.23859899999999,39.739865],"type":"Point"}
}