{
  "type": "Feature",
  "properties": {
    "iso:country":"US",
    "sg:address":"22700 Grass Pad Rd",
    "sg:city":"Platte City",
    "sg:phone":"+1 816 330 3347",
    "sg:postcode":"64079",
    "sg:province":"MO",
    "sg:tags":[
        "farm",
        "hog",
        "tobacco",
        "or",
        "feedlot"
    ],
    "wof:name":"Audrey Anderson Farm",
    "wof:placetype":"venue"
},
  "geometry": {"coordinates":[-94.844612,39.300811],"type":"Point"}
}