{
  "type": "Feature",
  "properties": {
    "iso:country":"US",
    "sg:address":"123 W Hudson St",
    "sg:city":"Wellsville",
    "sg:classifiers":[
        {
            "category":"Manufacturing",
            "subcategory":"Printing",
            "type":"Manufacturing & Wholesale Goods"
        }
    ],
    "sg:phone":"+1 573 684 2929",
    "sg:postcode":"63384",
    "sg:province":"MO",
    "sg:tags":[
        "newspaper"
    ],
    "wof:name":"Optic News",
    "wof:placetype":"venue"
},
  "geometry": {"coordinates":[-91.56965099999999,39.071712],"type":"Point"}
}