{
  "type": "Feature",
  "properties": {
    "iso:country":"US",
    "sg:address":"114 Mountain St",
    "sg:city":"Oran",
    "sg:classifiers":[
        {
            "category":"Professional",
            "subcategory":"Management & Consulting",
            "type":"Services"
        },
        {
            "category":"Retail",
            "subcategory":"Funeral Services",
            "type":"Services"
        }
    ],
    "sg:phone":"+1 573 262 3311",
    "sg:postcode":"63771",
    "sg:province":"MO",
    "sg:tags":[
        "director",
        "embalmer",
        "consultant"
    ],
    "wof:name":"Amick-Burnett Funeral Chapel",
    "wof:placetype":"venue"
},
  "geometry": {"coordinates":[-89.656197,37.086985],"type":"Point"}
}