{
  "type": "Feature",
  "properties": {
    "iso:country":"US",
    "sg:address":"566 S Odell Ave",
    "sg:city":"Marshall",
    "sg:classifiers":[
        {
            "category":"Health Services",
            "subcategory":"Health Practitioner",
            "type":"Services"
        }
    ],
    "sg:phone":"+1 660 886 7307",
    "sg:postcode":"65340",
    "sg:province":"MO",
    "sg:tags":[
        "psychologist"
    ],
    "wof:name":"Frances Spickerman PHD",
    "wof:placetype":"venue"
},
  "geometry": {"coordinates":[-93.19485400000001,39.116467],"type":"Point"}
}