{
  "type": "Feature",
  "properties": {
    "iso:country":"US",
    "sg:address":"1218 N Fulbright Ave",
    "sg:city":"Springfield",
    "sg:classifiers":[
        {
            "category":"Shopping",
            "subcategory":"Gifts & Souvenirs",
            "type":"Retail Goods"
        }
    ],
    "sg:phone":"+1 417 831 0501",
    "sg:postcode":"65802",
    "sg:province":"MO",
    "wof:name":"Coopers Corner Gifts",
    "wof:placetype":"venue"
},
  "geometry": {"coordinates":[-93.329956,37.222521],"type":"Point"}
}