{
  "type": "Feature",
  "properties": {
    "iso:country":"US",
    "sg:address":"1303 Kingsford Dr",
    "sg:city":"Florissant",
    "sg:classifiers":[
        {
            "category":"Building & Trades",
            "subcategory":"Construction",
            "type":"Services"
        }
    ],
    "sg:phone":"+1 314 831 2693",
    "sg:postcode":"63031",
    "sg:province":"MO",
    "sg:tags":[
        "painter"
    ],
    "wof:name":"Bell's Painting Co",
    "wof:placetype":"venue"
},
  "geometry": {"coordinates":[-90.33524300000001,38.821962],"type":"Point"}
}