{
  "type": "Feature",
  "properties": {
    "iso:country":"US",
    "sg:address":"604 W Jefferson Ave",
    "sg:city":"Conway",
    "sg:classifiers":[
        {
            "category":"Shopping",
            "subcategory":"Florist",
            "type":"Retail Goods"
        }
    ],
    "sg:phone":"+1 417 589 6336",
    "sg:postcode":"65632",
    "sg:province":"MO",
    "wof:name":"Conway Floral & Gifts",
    "wof:placetype":"venue"
},
  "geometry": {"coordinates":[-92.827839,37.502694],"type":"Point"}
}