{
  "type": "Feature",
  "properties": {
    "iso:country":"US",
    "sg:address":"407 W Rawlings St",
    "sg:city":"Shelbina",
    "sg:classifiers":[
        {
            "category":"Wholesale",
            "subcategory":"Farm Supplies",
            "type":"Manufacturing & Wholesale Goods"
        }
    ],
    "sg:phone":"+1 573 588 4526",
    "sg:postcode":"63468",
    "sg:province":"MO",
    "sg:tags":[
        "grain"
    ],
    "wof:name":"B Frank Broughton",
    "wof:placetype":"venue"
},
  "geometry": {"coordinates":[-92.045885,39.696641],"type":"Point"}
}