{
  "type": "Feature",
  "properties": {
    "iso:country":"US",
    "sg:address":"5835 Delmar Blvd",
    "sg:city":"Saint Louis",
    "sg:classifiers":[
        {
            "category":"Communications",
            "subcategory":"Newspaper",
            "type":"Services"
        }
    ],
    "sg:phone":"+1 314 454 0066",
    "sg:postcode":"63112",
    "sg:province":"MO",
    "sg:tags":[
        "print",
        "medium"
    ],
    "wof:name":"Korean-American Journal",
    "wof:placetype":"venue"
},
  "geometry": {"coordinates":[-90.288044,38.654501],"type":"Point"}
}