{
  "type": "Feature",
  "properties": {
    "iso:country":"US",
    "sg:address":"630 Axminister Dr",
    "sg:city":"Fenton",
    "sg:classifiers":[
        {
            "category":"Wholesale",
            "subcategory":"Machinery & Supplies",
            "type":"Manufacturing & Wholesale Goods"
        }
    ],
    "sg:phone":"+1 636 349 6000",
    "sg:postcode":"63026",
    "sg:province":"MO",
    "sg:tags":[
        "equipment",
        "industrial",
        "supplies-wholesale"
    ],
    "wof:name":"Midwest Alloys & Technology",
    "wof:placetype":"venue"
},
  "geometry": {"coordinates":[-90.454061,38.536919],"type":"Point"}
}