{
  "type": "Feature",
  "properties": {
    "iso:country":"US",
    "sg:address":"105 S Jefferson St",
    "sg:city":"Kearney",
    "sg:classifiers":[
        {
            "category":"Professional",
            "subcategory":"Advertising",
            "type":"Services"
        }
    ],
    "sg:phone":"+1 816 903 4877",
    "sg:postcode":"64060",
    "sg:province":"MO",
    "sg:tags":[
        "mailing",
        "shipping"
    ],
    "wof:name":"UPS Store",
    "wof:placetype":"venue"
},
  "geometry": {"coordinates":[-94.36225899999999,39.372685],"type":"Point"}
}