{
  "type": "Feature",
  "properties": {
    "iso:country":"US",
    "sg:address":"725 State Hwy 7",
    "sg:city":"Blue Springs",
    "sg:classifiers":[
        {
            "category":"Retail",
            "subcategory":"Auto Rental",
            "type":"Services"
        }
    ],
    "sg:phone":"+1 816 224 4949",
    "sg:postcode":"64014",
    "sg:province":"MO",
    "sg:tags":[
        "renting",
        "automobile"
    ],
    "wof:name":"Enterprise Rent-A-Car",
    "wof:placetype":"venue"
},
  "geometry": {"coordinates":[-94.272598,39.012741],"type":"Point"}
}