{
  "type": "Feature",
  "properties": {
    "iso:country":"US",
    "sg:address":"3915 Indian Ridge Ln",
    "sg:city":"Defiance",
    "sg:classifiers":[
        {
            "category":"Retail",
            "subcategory":"Auto Repair",
            "type":"Services"
        }
    ],
    "sg:phone":"+1 636 798 2147",
    "sg:postcode":"63341",
    "sg:province":"MO",
    "sg:tags":[
        "body",
        "association"
    ],
    "wof:name":"St Louis Chapter of Natio",
    "wof:placetype":"venue"
},
  "geometry": {"coordinates":[-90.804711,38.666793],"type":"Point"}
}