{
  "type": "Feature",
  "properties": {
    "iso:country":"US",
    "sg:address":"821 South Ave",
    "sg:city":"Springfield",
    "sg:classifiers":[
        {
            "category":"Real Estate",
            "subcategory":"Real Estate Operator",
            "type":"Services"
        }
    ],
    "sg:phone":"+1 417 869 5305",
    "sg:postcode":"65806",
    "sg:province":"MO",
    "sg:tags":[
        "apartment"
    ],
    "wof:name":"Southwinds Apartments",
    "wof:placetype":"venue"
},
  "geometry": {"coordinates":[-93.29259399999999,37.199636],"type":"Point"}
}