{
  "type": "Feature",
  "properties": {
    "iso:country":"US",
    "sg:address":"603 Valley St",
    "sg:city":"Lathrop",
    "sg:classifiers":[
        {
            "category":"Organizations",
            "subcategory":"Religious Organization",
            "type":"Services"
        }
    ],
    "sg:phone":"+1 816 528 3197",
    "sg:postcode":"64465",
    "sg:province":"MO",
    "sg:tags":[
        "church"
    ],
    "wof:name":"Jehovah's Witnesses",
    "wof:placetype":"venue"
},
  "geometry": {"coordinates":[-94.32426599999999,39.545373],"type":"Point"}
}