{
  "type": "Feature",
  "properties": {
    "iso:country":"US",
    "sg:address":"1824 Messanie St",
    "sg:city":"St Joseph",
    "sg:classifiers":[
        {
            "category":"Building & Trades",
            "subcategory":"Electrical",
            "type":"Services"
        }
    ],
    "sg:phone":"+1 816 233 3305",
    "sg:postcode":"64507",
    "sg:province":"MO",
    "sg:tags":[
        "electric",
        "contractor"
    ],
    "wof:name":"Stracener Electric",
    "wof:placetype":"venue"
},
  "geometry": {"coordinates":[-94.83769700000001,39.762329],"type":"Point"}
}