{
  "type": "Feature",
  "properties": {
    "iso:country":"US",
    "sg:address":"1401 Triad Center Dr",
    "sg:city":"St Peters",
    "sg:classifiers":[
        {
            "category":"Real Estate",
            "subcategory":"Real Estate Operator",
            "type":"Services"
        }
    ],
    "sg:phone":"+1 636 498 1118",
    "sg:postcode":"63376",
    "sg:province":"MO",
    "sg:tags":[
        "mobile",
        "home",
        "community"
    ],
    "wof:name":"Glengate Estates",
    "wof:placetype":"venue"
},
  "geometry": {"coordinates":[-90.58791600000001,38.755753],"type":"Point"}
}