{
  "type": "Feature",
  "properties": {
    "iso:country":"US",
    "sg:address":"506 N Missouri St Ste A",
    "sg:city":"Macon",
    "sg:classifiers":[
        {
            "category":"Real Estate",
            "subcategory":"Real Estate Services",
            "type":"Services"
        },
        {
            "category":"Real Estate",
            "subcategory":"Real Estate Agent",
            "type":"Services"
        }
    ],
    "sg:phone":"+1 660 385 2016",
    "sg:postcode":"63552",
    "sg:province":"MO",
    "sg:tags":[
        "buyer",
        "broker"
    ],
    "wof:name":"Macon Realty Co",
    "wof:placetype":"venue"
},
  "geometry": {"coordinates":[-92.46516,39.742408],"type":"Point"}
}