{
  "type": "Feature",
  "properties": {
    "iso:country":"US",
    "sg:address":"2400 State Hwy 7",
    "sg:city":"Blue Springs",
    "sg:classifiers":[
        {
            "category":"Retail",
            "subcategory":"Auto Repair",
            "type":"Services"
        }
    ],
    "sg:phone":"+1 816 224 8229",
    "sg:postcode":"64014",
    "sg:province":"MO",
    "sg:tags":[
        "automotive"
    ],
    "wof:name":"Country Club Car Wash",
    "wof:placetype":"venue"
},
  "geometry": {"coordinates":[-94.273186,38.995805],"type":"Point"}
}