{
  "type": "Feature",
  "properties": {
    "iso:country":"US",
    "sg:address":"425 Poplar St",
    "sg:city":"Poplar Bluff",
    "sg:classifiers":[
        {
            "category":"Insurance",
            "subcategory":"Insurance Agent",
            "type":"Services"
        }
    ],
    "sg:phone":"+1 573 785 4055",
    "sg:postcode":"63901",
    "sg:province":"MO",
    "wof:name":"Parks Insurance",
    "wof:placetype":"venue"
},
  "geometry": {"coordinates":[-90.394536,36.755807],"type":"Point"}
}