{
  "type": "Feature",
  "properties": {
    "iso:country":"US",
    "sg:address":"2925 E Chestnut Expy",
    "sg:city":"Springfield",
    "sg:classifiers":[
        {
            "category":"Manufacturing",
            "subcategory":"Retail Goods",
            "type":"Manufacturing & Wholesale Goods"
        }
    ],
    "sg:phone":"+1 417 863 8018",
    "sg:postcode":"65802",
    "sg:province":"MO",
    "sg:tags":[
        "assembly",
        "fabricating"
    ],
    "wof:name":"Bold Fabrications",
    "wof:placetype":"venue"
},
  "geometry": {"coordinates":[-93.236565,37.20996],"type":"Point"}
}