{
  "type": "Feature",
  "properties": {
    "iso:country":"US",
    "sg:address":"911 N Main St",
    "sg:city":"Piedmont",
    "sg:classifiers":[
        {
            "category":"Autos & Motor Vehicles",
            "subcategory":"Fuel & Gas Station",
            "type":"Retail Goods"
        },
        {
            "category":"Autos & Motor Vehicles",
            "subcategory":"Auto Supplies",
            "type":"Retail Goods"
        },
        {
            "category":"Retail",
            "subcategory":"Auto Repair",
            "type":"Services"
        }
    ],
    "sg:phone":"+1 573 223 4926",
    "sg:postcode":"63957",
    "sg:province":"MO",
    "sg:tags":[
        "tire"
    ],
    "wof:name":"Montgomery Auto Care Inc",
    "wof:placetype":"venue"
},
  "geometry": {"coordinates":[-90.690297,37.160839],"type":"Point"}
}