{
  "type": "Feature",
  "properties": {
    "iso:country":"US",
    "sg:address":"5 S Oak St",
    "sg:city":"Eldon",
    "sg:classifiers":[
        {
            "category":"Retail",
            "subcategory":"Funeral Services",
            "type":"Services"
        }
    ],
    "sg:phone":"+1 573 392 5621",
    "sg:postcode":"65026",
    "sg:province":"MO",
    "sg:tags":[
        "director"
    ],
    "wof:name":"Phillips Funeral Home",
    "wof:placetype":"venue"
},
  "geometry": {"coordinates":[-92.580251,38.350413],"type":"Point"}
}