{
  "type": "Feature",
  "properties": {
    "iso:country":"US",
    "sg:address":"16 Westwoods Dr",
    "sg:city":"Liberty",
    "sg:classifiers":[
        {
            "category":"Health Services",
            "subcategory":"Clinic",
            "type":"Services"
        }
    ],
    "sg:phone":"+1 816 792 4966",
    "sg:postcode":"64068",
    "sg:province":"MO",
    "wof:name":"Regional Care Hospice LLC",
    "wof:placetype":"venue"
},
  "geometry": {"coordinates":[-94.435974,39.246327],"type":"Point"}
}