{
  "type": "Feature",
  "properties": {
    "iso:country":"US",
    "sg:address":"920 S Kirkwood Rd",
    "sg:city":"St Louis",
    "sg:classifiers":[
        {
            "category":"Retail",
            "subcategory":"Car Wash",
            "type":"Services"
        }
    ],
    "sg:phone":"+1 314 835 0133",
    "sg:postcode":"63122",
    "sg:province":"MO",
    "sg:tags":[
        "polishing",
        "washing"
    ],
    "wof:name":"Squeaky Clean Car Wash",
    "wof:placetype":"venue"
},
  "geometry": {"coordinates":[-90.406605,38.568679],"type":"Point"}
}