{
  "type": "Feature",
  "properties": {
    "iso:country":"US",
    "sg:address":"421 N Sappington Rd",
    "sg:city":"Kirkwood",
    "sg:classifiers":[
        {
            "category":"Shopping",
            "subcategory":"Gifts & Souvenirs",
            "type":"Retail Goods"
        }
    ],
    "sg:phone":"+1 314 822 2857",
    "sg:postcode":"63122",
    "sg:province":"MO",
    "sg:tags":[
        "shop"
    ],
    "wof:name":"Recycled Rose",
    "wof:placetype":"venue"
},
  "geometry": {"coordinates":[-90.386563,38.588747],"type":"Point"}
}