{
  "type": "Feature",
  "properties": {
    "iso:country":"US",
    "sg:address":"103 Clow Ave",
    "sg:city":"Ewing",
    "sg:classifiers":[
        {
            "category":"Organizations",
            "subcategory":"Religious Organization",
            "type":"Services"
        }
    ],
    "sg:phone":"+1 573 209 3494",
    "sg:postcode":"63440",
    "sg:province":"MO",
    "sg:tags":[
        "church"
    ],
    "wof:name":"Queen Of Peace Church",
    "wof:placetype":"venue"
},
  "geometry": {"coordinates":[-91.72055899999999,40.009335],"type":"Point"}
}