{
  "type": "Feature",
  "properties": {
    "iso:country":"US",
    "sg:address":"5940 NW Waukomis Dr",
    "sg:city":"Kansas City",
    "sg:classifiers":[
        {
            "category":"Government",
            "subcategory":"Office",
            "type":"Public Place"
        }
    ],
    "sg:phone":"+1 816 505 2244",
    "sg:postcode":"64151",
    "sg:province":"MO",
    "sg:tags":[
        "executive",
        "air"
    ],
    "wof:name":"Line Creek CU Center",
    "wof:placetype":"venue"
},
  "geometry": {"coordinates":[-94.608529,39.20248],"type":"Point"}
}