{
  "type": "Feature",
  "properties": {
    "iso:country":"US",
    "sg:address":"20100 E Valleyview Cir",
    "sg:city":"Independence",
    "sg:classifiers":[
        {
            "category":"Restaurant",
            "type":"Food & Drink"
        }
    ],
    "sg:menulink":"http://www.allmenus.com/mo/sni-a-bar/96648-ihop/menu/",
    "sg:phone":"+1 816 795 8787",
    "sg:postcode":"64057",
    "sg:province":"MO",
    "sg:tags":[
        "sandwich",
        "salad",
        "burger",
        "soup",
        "american",
        "steakhouse",
        "wrap"
    ],
    "wof:name":"IHOP",
    "wof:placetype":"venue"
},
  "geometry": {"coordinates":[-94.343619,39.038248],"type":"Point"}
}