{
  "type": "Feature",
  "properties": {
    "iso:country":"US",
    "sg:address":"201 Highway 5 And 240 And 240 & 240",
    "sg:city":"Fayette",
    "sg:phone":"+1 660 248 3335",
    "sg:postcode":"65248",
    "sg:province":"MO",
    "wof:name":"Silver Bell Motel",
    "wof:placetype":"venue"
},
  "geometry": {"coordinates":[-92.69526500000001,39.159426],"type":"Point"}
}