{
  "type": "Feature",
  "properties": {
    "iso:country":"US",
    "sg:address":"8930 Boston Ave",
    "sg:city":"Saint Louis",
    "sg:classifiers":[
        {
            "category":"Education",
            "subcategory":"School",
            "type":"Public Place"
        }
    ],
    "sg:phone":"+1 314 427 8972",
    "sg:postcode":"63121",
    "sg:province":"MO",
    "wof:name":"Normandy School District",
    "wof:placetype":"venue"
},
  "geometry": {"coordinates":[-90.327282,38.714855],"type":"Point"}
}