{
  "type": "Feature",
  "properties": {
    "iso:country":"US",
    "sg:address":"1102 N Benton Ave",
    "sg:city":"Saint Charles",
    "sg:classifiers":[
        {
            "category":"Building & Trades",
            "subcategory":"Electrical",
            "type":"Services"
        }
    ],
    "sg:phone":"+1 636 343 4404",
    "sg:postcode":"63301",
    "sg:province":"MO",
    "sg:tags":[
        "communication",
        "system",
        "for",
        "contractor"
    ],
    "wof:name":"Tihen Communications Inc",
    "wof:placetype":"venue"
},
  "geometry": {"coordinates":[-90.482291,38.792711],"type":"Point"}
}