{
  "type": "Feature",
  "properties": {
    "iso:country":"US",
    "sg:address":"11715 Gravois Rd",
    "sg:city":"St Louis",
    "sg:classifiers":[
        {
            "category":"Restaurant",
            "type":"Food & Drink"
        }
    ],
    "sg:phone":"+1 314 849 2097",
    "sg:postcode":"63127",
    "sg:province":"MO",
    "sg:website":"www.bandanasbbq.com",
    "wof:name":"Bandana's Barbq",
    "wof:placetype":"venue"
},
  "geometry": {"coordinates":[-90.385451,38.532619],"type":"Point"}
}