{
  "type": "Feature",
  "properties": {
    "iso:country":"US",
    "sg:address":"2951 W Kearney St",
    "sg:city":"Springfield",
    "sg:classifiers":[
        {
            "category":"Autos & Motor Vehicles",
            "subcategory":"Automobile Sales",
            "type":"Retail Goods"
        }
    ],
    "sg:phone":"+1 417 831 3999",
    "sg:postcode":"65803",
    "sg:province":"MO",
    "sg:tags":[
        "new",
        "used",
        "car"
    ],
    "sg:website":"http://www.tttsales.com",
    "wof:name":"Hercules Enterprises",
    "wof:placetype":"venue"
},
  "geometry": {"coordinates":[-93.334999,37.241409],"type":"Point"}
}