{
  "type": "Feature",
  "properties": {
    "iso:country":"US",
    "sg:address":"2969 Landau Ct",
    "sg:city":"Saint Charles",
    "sg:classifiers":[
        {
            "category":"Personal",
            "type":"Services"
        }
    ],
    "sg:phone":"+1 636 946 0210",
    "sg:postcode":"63301",
    "sg:province":"MO",
    "wof:name":"Readings By Andy",
    "wof:placetype":"venue"
},
  "geometry": {"coordinates":[-90.53899,38.808395],"type":"Point"}
}