{
  "type": "Feature",
  "properties": {
    "iso:country":"US",
    "sg:address":"1500 W Grand St",
    "sg:city":"Springfield",
    "sg:classifiers":[
        {
            "category":"Retail",
            "subcategory":"Car Wash",
            "type":"Services"
        }
    ],
    "sg:phone":"+1 417 862 8468",
    "sg:postcode":"65807",
    "sg:province":"MO",
    "sg:tags":[
        "polishing",
        "washing"
    ],
    "wof:name":"S & B Mobile Wash",
    "wof:placetype":"venue"
},
  "geometry": {"coordinates":[-93.31262,37.19707],"type":"Point"}
}