{
  "type": "Feature",
  "properties": {
    "iso:country":"US",
    "sg:address":"48 S County Centerway",
    "sg:city":"St Louis",
    "sg:classifiers":[
        {
            "category":"Shopping",
            "subcategory":"Luggage & Leather Goods",
            "type":"Retail Goods"
        }
    ],
    "sg:phone":"+1 314 984 9400",
    "sg:postcode":"63129",
    "sg:province":"MO",
    "wof:name":"Coach Store",
    "wof:placetype":"venue"
},
  "geometry": {"coordinates":[-90.329446,38.505056],"type":"Point"}
}