{
  "type": "Feature",
  "properties": {
    "iso:country":"US",
    "sg:address":"1120 N Florissant Rd",
    "sg:city":"St Louis",
    "sg:classifiers":[
        {
            "category":"Professional",
            "subcategory":"Business Services",
            "type":"Services"
        },
        {
            "category":"Personal",
            "subcategory":"Beauty Salon",
            "type":"Services"
        }
    ],
    "sg:phone":"+1 314 522 6162",
    "sg:postcode":"63135",
    "sg:province":"MO",
    "sg:tags":[
        "shop",
        "embroidery"
    ],
    "sg:website":"www.stylesclothing.com",
    "wof:name":"Styles Clothing Co",
    "wof:placetype":"venue"
},
  "geometry": {"coordinates":[-90.312867,38.762346],"type":"Point"}
}