{
  "type": "Feature",
  "properties": {
    "iso:country":"US",
    "sg:address":"912 Rose St",
    "sg:city":"Kennett",
    "sg:classifiers":[
        {
            "category":"Building & Trades",
            "subcategory":"Construction",
            "type":"Services"
        }
    ],
    "sg:phone":"+1 573 888 1379",
    "sg:postcode":"63857",
    "sg:province":"MO",
    "sg:tags":[
        "house"
    ],
    "wof:name":"Gillette Construction",
    "wof:placetype":"venue"
},
  "geometry": {"coordinates":[-90.049553,36.245372],"type":"Point"}
}