{
  "type": "Feature",
  "properties": {
    "iso:country":"US",
    "sg:address":"8039 Watson Rd",
    "sg:city":"Webster Groves",
    "sg:classifiers":[
        {
            "category":"Professional",
            "subcategory":"Art Services",
            "type":"Services"
        }
    ],
    "sg:phone":"+1 314 962 0270",
    "sg:postcode":"63119",
    "sg:province":"MO",
    "sg:tags":[
        "artist"
    ],
    "wof:name":"P M Graphics",
    "wof:placetype":"venue"
},
  "geometry": {"coordinates":[-90.340238,38.56806],"type":"Point"}
}