{
  "type": "Feature",
  "properties": {
    "iso:country":"US",
    "sg:address":"227 E Excelsior St",
    "sg:city":"Excelsior Spgs",
    "sg:classifiers":[
        {
            "category":"Autos & Motor Vehicles",
            "subcategory":"Automobile Sales",
            "type":"Retail Goods"
        }
    ],
    "sg:phone":"+1 816 630 9800",
    "sg:postcode":"64024",
    "sg:province":"MO",
    "sg:tags":[
        "car",
        "dealer"
    ],
    "wof:name":"Auto Outlet",
    "wof:placetype":"venue"
},
  "geometry": {"coordinates":[-94.221886,39.342795],"type":"Point"}
}