{
  "type": "Feature",
  "properties": {
    "iso:country":"US",
    "sg:address":"403 Lay Ave",
    "sg:city":"Warsaw",
    "sg:classifiers":[
        {
            "category":"Health Services",
            "subcategory":"Doctor",
            "type":"Services"
        }
    ],
    "sg:phone":"+1 660 438 3990",
    "sg:postcode":"65355",
    "sg:province":"MO",
    "sg:tags":[
        "physician",
        "surgeon"
    ],
    "wof:name":"Midwest Internal Medicine",
    "wof:placetype":"venue"
},
  "geometry": {"coordinates":[-93.383596,38.247287],"type":"Point"}
}