{
  "type": "Feature",
  "properties": {
    "iso:country":"US",
    "sg:address":"420 W Monroe St",
    "sg:city":"Mexico",
    "sg:classifiers":[
        {
            "category":"Autos & Motor Vehicles",
            "subcategory":"Fuel & Gas Station",
            "type":"Retail Goods"
        }
    ],
    "sg:phone":"+1 573 581 8684",
    "sg:postcode":"65265",
    "sg:province":"MO",
    "sg:tags":[
        "convenience",
        "station",
        "store"
    ],
    "wof:name":"Kwik Store",
    "wof:placetype":"venue"
},
  "geometry": {"coordinates":[-91.88596099999999,39.17295],"type":"Point"}
}