{
  "type": "Feature",
  "properties": {
    "iso:country":"US",
    "sg:address":"7090 Mexico Rd",
    "sg:city":"Saint Peters",
    "sg:classifiers":[
        {
            "category":"Farming",
            "subcategory":"Dairy Farm",
            "type":"Manufacturing & Wholesale Goods"
        },
        {
            "category":"Ice Cream",
            "type":"Food & Drink"
        },
        {
            "category":"Food & Beverages",
            "subcategory":"Dairy",
            "type":"Retail Goods"
        }
    ],
    "sg:menulink":"http://www.allmenus.com/mo/st-peters/153500-oberweis-dairy/menu/",
    "sg:phone":"+1 636 970 0105",
    "sg:postcode":"63376",
    "sg:province":"MO",
    "sg:tags":[
        "american",
        "ice",
        "cream"
    ],
    "wof:name":"Oberweis Dairy",
    "wof:placetype":"venue"
},
  "geometry": {"coordinates":[-90.62580800000001,38.788372],"type":"Point"}
}