{
  "type": "Feature",
  "properties": {
    "iso:country":"US",
    "sg:address":"3411 W Chestnut Expy",
    "sg:city":"Springfield",
    "sg:classifiers":[
        {
            "category":"Building & Trades",
            "subcategory":"Construction",
            "type":"Services"
        }
    ],
    "sg:phone":"+1 417 866 8266",
    "sg:postcode":"65802",
    "sg:province":"MO",
    "sg:tags":[
        "contractor",
        "specialty",
        "mfg"
    ],
    "wof:name":"Ozark Sandblasting Co",
    "wof:placetype":"venue"
},
  "geometry": {"coordinates":[-93.345493,37.212287],"type":"Point"}
}