{
  "type": "Feature",
  "properties": {
    "iso:country":"US",
    "sg:address":"12 Mount Carmel Rd",
    "sg:city":"Eldon",
    "sg:classifiers":[
        {
            "category":"Organizations",
            "subcategory":"Religious Organization",
            "type":"Services"
        }
    ],
    "sg:phone":"+1 573 392 4884",
    "sg:postcode":"65026",
    "sg:province":"MO",
    "sg:tags":[
        "church"
    ],
    "wof:name":"Mount Carmel Baptist Church",
    "wof:placetype":"venue"
},
  "geometry": {"coordinates":[-92.584155,38.267047],"type":"Point"}
}