{
  "type": "Feature",
  "properties": {
    "iso:country":"US",
    "sg:address":"4003 de Smet Ln",
    "sg:city":"Saint Charles",
    "sg:classifiers":[
        {
            "category":"Communications",
            "subcategory":"Film & Video Production",
            "type":"Services"
        }
    ],
    "sg:phone":"+1 636 441 0526",
    "sg:postcode":"63304",
    "sg:province":"MO",
    "sg:tags":[
        "motion"
    ],
    "wof:name":"Lenders Video Productions",
    "wof:placetype":"venue"
},
  "geometry": {"coordinates":[-90.592384,38.741374],"type":"Point"}
}