{
  "type": "Feature",
  "properties": {
    "iso:country":"US",
    "sg:address":"8012 NE 74 Ter",
    "sg:city":"Kansas City",
    "sg:classifiers":[
        {
            "category":"Freight",
            "type":"Transportation"
        }
    ],
    "sg:phone":"+1 816 415 4260",
    "sg:postcode":"64158",
    "sg:province":"MO",
    "sg:tags":[
        "operator",
        "trucking"
    ],
    "wof:name":"4m Transport Inc",
    "wof:placetype":"venue"
},
  "geometry": {"coordinates":[-94.486715,39.226602],"type":"Point"}
}