{
  "type": "Feature",
  "properties": {
    "iso:country":"US",
    "sg:address":"13522 E State Hwy 76",
    "sg:city":"Taneyville",
    "sg:classifiers":[
        {
            "category":"Insurance",
            "subcategory":"Hazard Insurance",
            "type":"Services"
        }
    ],
    "sg:phone":"+1 417 546 3900",
    "sg:postcode":"65759",
    "sg:province":"MO",
    "sg:tags":[
        "bond"
    ],
    "wof:name":"Queen City Bail Bonds",
    "wof:placetype":"venue"
},
  "geometry": {"coordinates":[-93.049823,36.702703],"type":"Point"}
}