{
  "type": "Feature",
  "properties": {
    "iso:country":"US",
    "sg:address":"3910 Lindell Blvd",
    "sg:city":"Saint Louis",
    "sg:classifiers":[
        {
            "category":"Professional",
            "subcategory":"Lawyer & Legal Services",
            "type":"Services"
        }
    ],
    "sg:phone":"+1 314 533 8228",
    "sg:postcode":"63108",
    "sg:province":"MO",
    "wof:name":"Smith Charles Atty",
    "wof:placetype":"venue"
},
  "geometry": {"coordinates":[-90.241096,38.639099],"type":"Point"}
}