{
  "type": "Feature",
  "properties": {
    "iso:country":"US",
    "sg:address":"719 Cedar Valley Rd",
    "sg:city":"Hollister",
    "sg:classifiers":[
        {
            "category":"Wholesale",
            "subcategory":"Construction Materials",
            "type":"Manufacturing & Wholesale Goods"
        },
        {
            "category":"Home & Garden",
            "subcategory":"Building Materials",
            "type":"Retail Goods"
        },
        {
            "category":"Building & Trades",
            "subcategory":"Construction",
            "type":"Services"
        },
        {
            "category":"Manufacturing",
            "subcategory":"Building Materials",
            "type":"Manufacturing & Wholesale Goods"
        }
    ],
    "sg:phone":"+1 417 337 7133",
    "sg:postcode":"65672",
    "sg:province":"MO",
    "sg:tags":[
        "aggregate",
        "contractor",
        "concrete",
        "mixed",
        "staining",
        "concrete-ready"
    ],
    "wof:name":"Regional Ready Mix",
    "wof:placetype":"venue"
},
  "geometry": {"coordinates":[-93.24359800000001,36.574983],"type":"Point"}
}