{
  "type": "Feature",
  "properties": {
    "iso:country":"US",
    "sg:address":"5462 W Farm Rd 148",
    "sg:city":"Springfield",
    "sg:classifiers":[
        {
            "category":"Building & Trades",
            "subcategory":"Construction",
            "type":"Services"
        }
    ],
    "sg:phone":"+1 417 865 0858",
    "sg:postcode":"65802",
    "sg:province":"MO",
    "sg:tags":[
        "house"
    ],
    "wof:name":"Up Tyte Construction Inc",
    "wof:placetype":"venue"
},
  "geometry": {"coordinates":[-93.395743,37.183365],"type":"Point"}
}