{
  "type": "Feature",
  "properties": {
    "iso:country":"US",
    "sg:address":"101 S Hanley Rd",
    "sg:city":"St Louis",
    "sg:classifiers":[
        {
            "category":"Insurance",
            "subcategory":"Insurance Agent",
            "type":"Services"
        }
    ],
    "sg:phone":"+1 314 725 8394",
    "sg:postcode":"63105",
    "sg:province":"MO",
    "sg:tags":[
        "broker"
    ],
    "sg:website":"www.ipsico.com",
    "wof:name":"International Placement Svcs",
    "wof:placetype":"venue"
},
  "geometry": {"coordinates":[-90.334101,38.649863],"type":"Point"}
}