{
  "type": "Feature",
  "properties": {
    "iso:country":"US",
    "sg:address":"1612 1st St",
    "sg:city":"Kennett",
    "sg:classifiers":[
        {
            "category":"Banks & Credit Unions",
            "subcategory":"Bank",
            "type":"Services"
        }
    ],
    "sg:phone":"+1 573 717 7900",
    "sg:postcode":"63857",
    "sg:province":"MO",
    "sg:tags":[
        "cashing",
        "check"
    ],
    "wof:name":"Delta Cash Advance",
    "wof:placetype":"venue"
},
  "geometry": {"coordinates":[-90.039297,36.236703],"type":"Point"}
}