{
  "type": "Feature",
  "properties": {
    "iso:country":"US",
    "sg:address":"193 Co Rd 4681",
    "sg:city":"Poplar Bluff",
    "sg:classifiers":[
        {
            "category":"Building & Trades",
            "subcategory":"Construction",
            "type":"Services"
        }
    ],
    "sg:phone":"+1 573 686 3338",
    "sg:postcode":"63901",
    "sg:province":"MO",
    "sg:tags":[
        "general",
        "contractor"
    ],
    "wof:name":"KMB Construction Inc",
    "wof:placetype":"venue"
},
  "geometry": {"coordinates":[-90.43656300000001,36.738329],"type":"Point"}
}