{
  "type": "Feature",
  "properties": {
    "iso:country":"US",
    "sg:address":"1632 Barron Rd",
    "sg:city":"Poplar Bluff",
    "sg:classifiers":[
        {
            "category":"Shopping",
            "type":"Retail Goods"
        }
    ],
    "sg:phone":"+1 573 776 7140",
    "sg:postcode":"63901",
    "sg:province":"MO",
    "sg:tags":[
        "trade",
        "merchandise",
        "contractor"
    ],
    "wof:name":"Oasis Pool & Spa",
    "wof:placetype":"venue"
},
  "geometry": {"coordinates":[-90.41471799999999,36.78303],"type":"Point"}
}