{
  "type": "Feature",
  "properties": {
    "iso:country":"US",
    "sg:address":"2744 S Austin Ave",
    "sg:city":"Springfield",
    "sg:classifiers":[
        {
            "category":"Building & Trades",
            "subcategory":"Construction",
            "type":"Services"
        }
    ],
    "sg:phone":"+1 417 887 8696",
    "sg:postcode":"65807",
    "sg:province":"MO",
    "sg:tags":[
        "utility",
        "locating"
    ],
    "wof:name":"SM&p Conduit",
    "wof:placetype":"venue"
},
  "geometry": {"coordinates":[-93.3222,37.163189],"type":"Point"}
}