{
  "type": "Feature",
  "properties": {
    "iso:country":"US",
    "sg:address":"902 Main St",
    "sg:city":"Blue Springs",
    "sg:classifiers":[
        {
            "category":"Manufacturing",
            "subcategory":"Apparel",
            "type":"Manufacturing & Wholesale Goods"
        }
    ],
    "sg:phone":"+1 816 228 5039",
    "sg:postcode":"64015",
    "sg:province":"MO",
    "sg:tags":[
        "flag",
        "banner"
    ],
    "wof:name":"Snyder's Flag Svc",
    "wof:placetype":"venue"
},
  "geometry": {"coordinates":[-94.27676599999999,39.01827],"type":"Point"}
}