{
  "type": "Feature",
  "properties": {
    "iso:country":"US",
    "sg:address":"146 Communications Dr",
    "sg:city":"Hannibal",
    "sg:classifiers":[
        {
            "category":"Organizations",
            "subcategory":"Non-profit Organization",
            "type":"Services"
        },
        {
            "category":"Health Services",
            "subcategory":"Clinic",
            "type":"Services"
        }
    ],
    "sg:phone":"+1 573 248 1196",
    "sg:postcode":"63401",
    "sg:province":"MO",
    "sg:tags":[
        "information",
        "residential",
        "specialty",
        "outpatient",
        "treatment",
        "alcoholism",
        "care"
    ],
    "wof:name":"Hannibal Council On Alcohol &",
    "wof:placetype":"venue"
},
  "geometry": {"coordinates":[-91.391899,39.702294],"type":"Point"}
}