{
  "type": "Feature",
  "properties": {
    "iso:country":"US",
    "sg:address":"981 S Skinker Blvd",
    "sg:city":"Saint Louis",
    "sg:classifiers":[
        {
            "category":"Autos & Motor Vehicles",
            "subcategory":"Fuel & Gas Station",
            "type":"Retail Goods"
        },
        {
            "category":"Landmark",
            "subcategory":"Historic",
            "type":"Public Place"
        }
    ],
    "sg:postcode":"63117",
    "sg:province":"MO",
    "sg:tags":[
        "building",
        "historical"
    ],
    "wof:name":"Giant Amoco Sign",
    "wof:placetype":"venue"
},
  "geometry": {"coordinates":[-90.304225,38.633686],"type":"Point"}
}