{
  "type": "Feature",
  "properties": {
    "iso:country":"US",
    "sg:address":"141 N Main Ave",
    "sg:city":"Republic",
    "sg:classifiers":[
        {
            "category":"Manufacturing",
            "subcategory":"Building Materials",
            "type":"Manufacturing & Wholesale Goods"
        }
    ],
    "sg:phone":"+1 417 732 6868",
    "sg:postcode":"65738",
    "sg:province":"MO",
    "sg:tags":[
        "mfg",
        "household",
        "cabinet",
        "wood",
        "kitchen",
        "furniture"
    ],
    "wof:name":"Boyd Woodworking",
    "wof:placetype":"venue"
},
  "geometry": {"coordinates":[-93.480582,37.119346],"type":"Point"}
}