{
  "type": "Feature",
  "properties": {
    "iso:country":"US",
    "sg:address":"5654 Delmar Blvd",
    "sg:city":"St Louis",
    "sg:classifiers":[
        {
            "category":"Social Services",
            "subcategory":"Child Care",
            "type":"Services"
        }
    ],
    "sg:phone":"+1 314 367 7950",
    "sg:postcode":"63112",
    "sg:province":"MO",
    "sg:website":"www.stellamariscc.org",
    "wof:name":"Stella Maris Child Ctr",
    "wof:placetype":"venue"
},
  "geometry": {"coordinates":[-90.283661,38.653722],"type":"Point"}
}