{
  "type": "Feature",
  "properties": {
    "iso:country":"US",
    "sg:address":"7799 State Hwy 30",
    "sg:city":"Dittmer",
    "sg:classifiers":[
        {
            "category":"Retail",
            "subcategory":"Auto Repair",
            "type":"Services"
        }
    ],
    "sg:phone":"+1 636 285 4377",
    "sg:postcode":"63023",
    "sg:province":"MO",
    "sg:tags":[
        "repairing",
        "automobile"
    ],
    "wof:name":"Evan's Automotive",
    "wof:placetype":"venue"
},
  "geometry": {"coordinates":[-90.69055299999999,38.332426],"type":"Point"}
}