{
  "type": "Feature",
  "properties": {
    "iso:country":"US",
    "sg:address":"36 Scenic View Ct",
    "sg:city":"Saint Charles",
    "sg:classifiers":[
        {
            "category":"Travel",
            "subcategory":"Travel Agent",
            "type":"Entertainment"
        }
    ],
    "sg:phone":"+1 636 441 7123",
    "sg:postcode":"63303",
    "sg:province":"MO",
    "sg:tags":[
        "operator",
        "tour"
    ],
    "wof:name":"Event Tours",
    "wof:placetype":"venue"
},
  "geometry": {"coordinates":[-90.561455,38.720223],"type":"Point"}
}