{
  "type": "Feature",
  "properties": {
    "iso:country":"US",
    "sg:address":"9160 Co Rd 80",
    "sg:city":"Reeds",
    "sg:classifiers":[
        {
            "category":"Building & Trades",
            "subcategory":"Electrical",
            "type":"Services"
        }
    ],
    "sg:phone":"+1 417 358 3762",
    "sg:postcode":"64859",
    "sg:province":"MO",
    "sg:tags":[
        "electric",
        "contractor"
    ],
    "wof:name":"Johnson Electric",
    "wof:placetype":"venue"
},
  "geometry": {"coordinates":[-94.199881,37.184564],"type":"Point"}
}