{
  "type": "Feature",
  "properties": {
    "iso:country":"US",
    "sg:address":"1805 S 8th St",
    "sg:city":"St Louis",
    "sg:classifiers":[
        {
            "category":"Organizations",
            "subcategory":"Religious Organization",
            "type":"Services"
        }
    ],
    "sg:phone":"+1 314 231 4092",
    "sg:postcode":"63104",
    "sg:province":"MO",
    "sg:tags":[
        "church"
    ],
    "sg:website":"www.historictrinitystlouis.org",
    "wof:name":"Trinity Lutheran Church",
    "wof:placetype":"venue"
},
  "geometry": {"coordinates":[-90.203289,38.608157],"type":"Point"}
}