{
  "type": "Feature",
  "properties": {
    "iso:country":"US",
    "sg:address":"6404 Martin Luther King Dr",
    "sg:city":"Saint Louis",
    "sg:classifiers":[
        {
            "category":"Organizations",
            "subcategory":"Religious Organization",
            "type":"Services"
        }
    ],
    "sg:phone":"+1 314 389 2279",
    "sg:postcode":"63133",
    "sg:province":"MO",
    "wof:name":"Evangelist Center Church",
    "wof:placetype":"venue"
},
  "geometry": {"coordinates":[-90.290221,38.677787],"type":"Point"}
}