{
  "type": "Feature",
  "properties": {
    "iso:country":"US",
    "sg:address":"1930 Main St",
    "sg:city":"Kansas City",
    "sg:classifiers":[
        {
            "category":"Professional",
            "subcategory":"Lawyer & Legal Services",
            "type":"Services"
        }
    ],
    "sg:phone":"+1 816 221 8188",
    "sg:postcode":"64108",
    "sg:province":"MO",
    "sg:tags":[
        "firm",
        "law"
    ],
    "wof:name":"Dicus Davis Sands & Collins",
    "wof:placetype":"venue"
},
  "geometry": {"coordinates":[-94.583797,39.089504],"type":"Point"}
}