{
  "type": "Feature",
  "properties": {
    "iso:country":"US",
    "sg:address":"901 Hodiamont Ave",
    "sg:city":"Saint Louis",
    "sg:classifiers":[
        {
            "category":"Building & Trades",
            "subcategory":"Construction",
            "type":"Services"
        }
    ],
    "sg:phone":"+1 314 721 7773",
    "sg:postcode":"63112",
    "sg:province":"MO",
    "sg:tags":[
        "concrete",
        "contractor"
    ],
    "wof:name":"Williams Concrete Contractors",
    "wof:placetype":"venue"
},
  "geometry": {"coordinates":[-90.294865,38.656721],"type":"Point"}
}