{
  "type": "Feature",
  "properties": {
    "iso:country":"US",
    "sg:address":"1102 Main St",
    "sg:city":"Grandview",
    "sg:classifiers":[
        {
            "category":"Professional",
            "subcategory":"Business Services",
            "type":"Services"
        }
    ],
    "sg:phone":"+1 816 763 6010",
    "sg:postcode":"64030",
    "sg:province":"MO",
    "sg:tags":[
        "recording",
        "studio"
    ],
    "wof:name":"Lockdown Records LLC",
    "wof:placetype":"venue"
},
  "geometry": {"coordinates":[-94.533711,38.889313],"type":"Point"}
}