{
  "type": "Feature",
  "properties": {
    "iso:country":"US",
    "sg:address":"301 S Main St",
    "sg:city":"Broseley",
    "sg:classifiers":[
        {
            "category":"Wholesale",
            "subcategory":"Painting Supplies",
            "type":"Manufacturing & Wholesale Goods"
        }
    ],
    "sg:phone":"+1 573 778 9967",
    "sg:postcode":"63901",
    "sg:province":"MO",
    "sg:tags":[
        "equipment",
        "painter"
    ],
    "wof:name":"Faux Shop",
    "wof:placetype":"venue"
},
  "geometry": {"coordinates":[-90.393585,36.754225],"type":"Point"}
}