{
  "type": "Feature",
  "properties": {
    "iso:country":"US",
    "sg:address":"815 W 23rd St S",
    "sg:city":"Independence",
    "sg:classifiers":[
        {
            "category":"Personal",
            "subcategory":"Beauty Salon",
            "type":"Services"
        }
    ],
    "sg:phone":"+1 816 252 4247",
    "sg:postcode":"64055",
    "sg:province":"MO",
    "sg:tags":[
        "school"
    ],
    "wof:name":"Indepndnce College Cosmetology",
    "wof:placetype":"venue"
},
  "geometry": {"coordinates":[-94.42665,39.0795],"type":"Point"}
}