{
  "type": "Feature",
  "properties": {
    "iso:country":"US",
    "sg:address":"3867 E Farm Rd 156",
    "sg:city":"Springfield",
    "sg:classifiers":[
        {
            "category":"Real Estate",
            "subcategory":"Real Estate Agent",
            "type":"Services"
        }
    ],
    "sg:phone":"+1 417 883 5006",
    "sg:postcode":"65809",
    "sg:province":"MO",
    "wof:name":"Garrison Appraisals",
    "wof:placetype":"venue"
},
  "geometry": {"coordinates":[-93.214828,37.16538],"type":"Point"}
}