{
  "type": "Feature",
  "properties": {
    "iso:country":"US",
    "sg:address":"1666 Country Hill Ln",
    "sg:city":"Ballwin",
    "sg:classifiers":[
        {
            "category":"Professional",
            "subcategory":"Management & Consulting",
            "type":"Services"
        }
    ],
    "sg:phone":"+1 636 225 1666",
    "sg:postcode":"63021",
    "sg:province":"MO",
    "sg:tags":[
        "communications",
        "consultant"
    ],
    "wof:name":"Hancock & Hannon Inc",
    "wof:placetype":"venue"
},
  "geometry": {"coordinates":[-90.47971699999999,38.573828],"type":"Point"}
}