{
  "type": "Feature",
  "properties": {
    "iso:country":"US",
    "sg:address":"14 N Sprigg St",
    "sg:city":"Cape Girardeau",
    "sg:classifiers":[
        {
            "category":"Shopping",
            "type":"Retail Goods"
        }
    ],
    "sg:phone":"+1 573 651 6681",
    "sg:postcode":"63701",
    "sg:province":"MO",
    "sg:tags":[
        "cards",
        "sport",
        "baseball",
        "memorabilia"
    ],
    "wof:name":"America's Passtime Sports Card",
    "wof:placetype":"venue"
},
  "geometry": {"coordinates":[-89.526753,37.305421],"type":"Point"}
}