{
  "type": "Feature",
  "properties": {
    "iso:country":"US",
    "sg:address":"26905 Co Rd 429",
    "sg:city":"Saint James",
    "sg:phone":"+1 573 699 4742",
    "sg:postcode":"65559",
    "sg:province":"MO",
    "sg:tags":[
        "farm",
        "corn",
        "wheat"
    ],
    "wof:name":"James Branstetter",
    "wof:placetype":"venue"
},
  "geometry": {"coordinates":[-91.63153,38.106151],"type":"Point"}
}