{
  "type": "Feature",
  "properties": {
    "iso:country":"US",
    "sg:address":"12779 New Halls Ferry Rd",
    "sg:city":"Florissant",
    "sg:classifiers":[
        {
            "category":"Food & Beverages",
            "subcategory":"Liquor & Beverages",
            "type":"Retail Goods"
        }
    ],
    "sg:phone":"+1 314 831 9334",
    "sg:postcode":"63033",
    "sg:province":"MO",
    "sg:tags":[
        "store"
    ],
    "wof:name":"The Liquor Rack",
    "wof:placetype":"venue"
},
  "geometry": {"coordinates":[-90.28347100000001,38.789795],"type":"Point"}
}