{
  "type": "Feature",
  "properties": {
    "iso:country":"US",
    "sg:address":"109 S 2nd St",
    "sg:city":"Deepwater",
    "sg:classifiers":[
        {
            "category":"Wholesale",
            "subcategory":"Painting Supplies",
            "type":"Manufacturing & Wholesale Goods"
        },
        {
            "category":"Home & Garden",
            "subcategory":"Garden Supply",
            "type":"Retail Goods"
        },
        {
            "category":"Wholesale",
            "subcategory":"Construction Materials",
            "type":"Manufacturing & Wholesale Goods"
        },
        {
            "category":"Home & Garden",
            "subcategory":"Hardware",
            "type":"Retail Goods"
        }
    ],
    "sg:phone":"+1 660 696 2667",
    "sg:postcode":"64740",
    "sg:province":"MO",
    "sg:tags":[
        "lawn",
        "paint",
        "equipment",
        "part",
        "plumbing",
        "fixtures",
        "store"
    ],
    "sg:website":"http://www.truevalue.com",
    "wof:name":"Quality True Value Farm & Home",
    "wof:placetype":"venue"
},
  "geometry": {"coordinates":[-93.771915,38.260526],"type":"Point"}
}