{
  "type": "Feature",
  "properties": {
    "iso:country":"US",
    "sg:address":"1114 State Hwy 19",
    "sg:city":"Salem",
    "sg:classifiers":[
        {
            "category":"Recreation",
            "type":"Entertainment"
        }
    ],
    "sg:phone":"+1 573 729 8725",
    "sg:postcode":"65560",
    "sg:province":"MO",
    "sg:tags":[
        "martial",
        "arts",
        "instruction"
    ],
    "wof:name":"Kirker's ATA Black Belt Acad",
    "wof:placetype":"venue"
},
  "geometry": {"coordinates":[-91.535422,37.652359],"type":"Point"}
}