{
  "type": "Feature",
  "properties": {
    "iso:country":"US",
    "sg:address":"14922 Afshari Cir",
    "sg:city":"Florissant",
    "sg:classifiers":[
        {
            "category":"Building & Trades",
            "subcategory":"Construction",
            "type":"Services"
        }
    ],
    "sg:phone":"+1 314 838 5904",
    "sg:postcode":"63034",
    "sg:province":"MO",
    "sg:tags":[
        "roofing",
        "contractor"
    ],
    "wof:name":"Ormsby Roofing Co",
    "wof:placetype":"venue"
},
  "geometry": {"coordinates":[-90.297499,38.858067],"type":"Point"}
}