{
  "type": "Feature",
  "properties": {
    "iso:country":"US",
    "sg:address":"802 N Tucker Blvd",
    "sg:city":"St Louis",
    "sg:classifiers":[
        {
            "category":"Professional",
            "subcategory":"Management & Consulting",
            "type":"Services"
        }
    ],
    "sg:phone":"+1 314 802 5444",
    "sg:postcode":"63101",
    "sg:province":"MO",
    "sg:tags":[
        "consultant",
        "resource",
        "human"
    ],
    "wof:name":"Housing Resource Ctr",
    "wof:placetype":"venue"
},
  "geometry": {"coordinates":[-90.195902,38.633709],"type":"Point"}
}