{
  "type": "Feature",
  "properties": {
    "iso:country":"US",
    "sg:address":"16412 Bishop Rd",
    "sg:city":"Kearney",
    "sg:classifiers":[
        {
            "category":"Farming",
            "subcategory":"Farm",
            "type":"Manufacturing & Wholesale Goods"
        }
    ],
    "sg:phone":"+1 816 628 5509",
    "sg:postcode":"64060",
    "sg:province":"MO",
    "sg:tags":[
        "crop",
        "general"
    ],
    "wof:name":"Peterson John",
    "wof:placetype":"venue"
},
  "geometry": {"coordinates":[-94.34664100000001,39.405059],"type":"Point"}
}