{
  "type": "Feature",
  "properties": {
    "addr:full":"202 2nd St Rushville MO 64484",
    "addr:housenumber":"202",
    "addr:postcode":"64484",
    "addr:street":"2Nd St",
    "iso:country":"US",
    "sg:address":"202 2nd St",
    "sg:city":"Rushville",
    "sg:classifiers":[
        {
            "category":"Personal",
            "subcategory":"Beauty Salon",
            "type":"Services"
        }
    ],
    "sg:phone":"+1 816 688 7876",
    "sg:postcode":"64484",
    "sg:province":"MO",
    "wof:name":"Country Cuts",
    "wof:placetype":"venue"
},
  "geometry": {"coordinates":[-95.025482,39.587092],"type":"Point"}
}