{
  "type": "Feature",
  "properties": {
    "iso:country":"US",
    "sg:address":"200 Ashcroft Rd",
    "sg:city":"Poplar Bluff",
    "sg:classifiers":[
        {
            "category":"Wholesale",
            "subcategory":"Construction Materials",
            "type":"Manufacturing & Wholesale Goods"
        }
    ],
    "sg:phone":"+1 573 785 9831",
    "sg:postcode":"63901",
    "sg:province":"MO",
    "sg:tags":[
        "lumber"
    ],
    "wof:name":"Schaller Hardwood Lumber Co",
    "wof:placetype":"venue"
},
  "geometry": {"coordinates":[-90.390244,36.745813],"type":"Point"}
}