{
  "type": "Feature",
  "properties": {
    "iso:country":"US",
    "sg:address":"3333 Rutger St",
    "sg:city":"Saint Louis",
    "sg:classifiers":[
        {
            "category":"Manufacturing",
            "subcategory":"Metals",
            "type":"Manufacturing & Wholesale Goods"
        }
    ],
    "sg:phone":"+1 314 772 5516",
    "sg:postcode":"63104",
    "sg:province":"MO",
    "wof:name":"Reliable Finishing Co Inc",
    "wof:placetype":"venue"
},
  "geometry": {"coordinates":[-90.232945,38.622621],"type":"Point"}
}