{
  "type": "Feature",
  "properties": {
    "iso:country":"US",
    "sg:address":"4372 Casa Brazilia Dr",
    "sg:city":"Saint Louis",
    "sg:classifiers":[
        {
            "category":"Utilities",
            "subcategory":"Telephone",
            "type":"Services"
        }
    ],
    "sg:phone":"+1 314 487 1008",
    "sg:postcode":"63129",
    "sg:province":"MO",
    "sg:tags":[
        "mail",
        "voice",
        "communications"
    ],
    "wof:name":"Kiss Voice Personal",
    "wof:placetype":"venue"
},
  "geometry": {"coordinates":[-90.326903,38.500356],"type":"Point"}
}