{
  "type": "Feature",
  "properties": {
    "iso:country":"US",
    "sg:address":"2426 S Grand Ave",
    "sg:city":"Carthage",
    "sg:classifiers":[
        {
            "category":"Utilities",
            "subcategory":"Mobile Phone",
            "type":"Services"
        }
    ],
    "sg:phone":"+1 417 358 1900",
    "sg:postcode":"64836",
    "sg:province":"MO",
    "sg:tags":[
        "communication",
        "radiotelephone"
    ],
    "wof:name":"Cellular MBL Systems & Paging",
    "wof:placetype":"venue"
},
  "geometry": {"coordinates":[-94.310264,37.147132],"type":"Point"}
}