{
  "type": "Feature",
  "properties": {
    "iso:country":"US",
    "sg:address":"1012 S 5th St",
    "sg:city":"Saint Charles",
    "sg:classifiers":[
        {
            "category":"Restaurant",
            "type":"Food & Drink"
        }
    ],
    "sg:menulink":"http://www.allmenus.com/mo/lindenwood/233058-lees-famous-recipe-chicken/menu/",
    "sg:phone":"+1 636 949 9966",
    "sg:postcode":"63301",
    "sg:province":"MO",
    "sg:tags":[
        "american"
    ],
    "wof:name":"Lee's Famous Recipe Chicken",
    "wof:placetype":"venue"
},
  "geometry": {"coordinates":[-90.49044000000001,38.774371],"type":"Point"}
}