{
  "type": "Feature",
  "properties": {
    "iso:country":"US",
    "sg:address":"22 N Euclid Ave",
    "sg:city":"Saint Louis",
    "sg:classifiers":[
        {
            "category":"Arts & Performance",
            "subcategory":"Art Gallery",
            "type":"Entertainment"
        }
    ],
    "sg:phone":"+1 314 367 9333",
    "sg:postcode":"63108",
    "sg:province":"MO",
    "wof:name":"The Great Frame Up",
    "wof:placetype":"venue"
},
  "geometry": {"coordinates":[-90.262001,38.641201],"type":"Point"}
}