{
  "type": "Feature",
  "properties": {
    "iso:country":"US",
    "sg:address":"23 NE State Hwy V",
    "sg:city":"Warrensburg",
    "sg:classifiers":[
        {
            "category":"Building & Trades",
            "subcategory":"Construction",
            "type":"Services"
        }
    ],
    "sg:phone":"+1 660 747 9562",
    "sg:postcode":"64093",
    "sg:province":"MO",
    "sg:tags":[
        "house"
    ],
    "wof:name":"Rebeccas Premier Homes",
    "wof:placetype":"venue"
},
  "geometry": {"coordinates":[-93.737515,38.82692],"type":"Point"}
}