{
  "type": "Feature",
  "properties": {
    "iso:country":"US",
    "sg:address":"4552 Flad Ave",
    "sg:city":"Saint Louis",
    "sg:classifiers":[
        {
            "category":"Health Services",
            "subcategory":"Health Practitioner",
            "type":"Services"
        }
    ],
    "sg:phone":"+1 314 361 4214",
    "sg:postcode":"63110",
    "sg:province":"MO",
    "wof:name":"Center For Wellness & Ntrtn",
    "wof:placetype":"venue"
},
  "geometry": {"coordinates":[-90.26298800000001,38.613864],"type":"Point"}
}