{
  "type": "Feature",
  "properties": {
    "iso:country":"US",
    "sg:address":"189 Saylesville Dr",
    "sg:city":"Chesterfield",
    "sg:classifiers":[
        {
            "category":"Health Services",
            "subcategory":"Dentist",
            "type":"Services"
        }
    ],
    "sg:phone":"+1 314 878 3808",
    "sg:postcode":"63017",
    "sg:province":"MO",
    "wof:name":"Mark D Meyers Dds",
    "wof:placetype":"venue"
},
  "geometry": {"coordinates":[-90.514339,38.656806],"type":"Point"}
}