{
  "type": "Feature",
  "properties": {
    "iso:country":"US",
    "sg:address":"1672 W Broadway St",
    "sg:city":"West Plains",
    "sg:classifiers":[
        {
            "category":"Insurance",
            "subcategory":"Insurance Agent",
            "type":"Services"
        }
    ],
    "sg:phone":"+1 417 256 7802",
    "sg:postcode":"65775",
    "sg:province":"MO",
    "wof:name":"Fern Bethel Insurance",
    "wof:placetype":"venue"
},
  "geometry": {"coordinates":[-91.870159,36.731531],"type":"Point"}
}