{
  "type": "Feature",
  "properties": {
    "iso:country":"US",
    "sg:address":"702 Keen St",
    "sg:city":"Raymore",
    "sg:classifiers":[
        {
            "category":"Building & Trades",
            "subcategory":"Construction",
            "type":"Services"
        }
    ],
    "sg:phone":"+1 816 322 2600",
    "sg:postcode":"64083",
    "sg:province":"MO",
    "sg:tags":[
        "roofing",
        "installation",
        "altering",
        "windows-repair",
        "contractor",
        "siding",
        "remodeling",
        "replacement"
    ],
    "sg:website":"http://www.brownrestoration.com",
    "wof:name":"Brown Restoration",
    "wof:placetype":"venue"
},
  "geometry": {"coordinates":[-94.44333899999999,38.806671],"type":"Point"}
}