{
  "type": "Feature",
  "properties": {
    "iso:country":"US",
    "sg:address":"336 S Jefferson St",
    "sg:city":"Neosho",
    "sg:classifiers":[
        {
            "category":"Social Services",
            "type":"Services"
        }
    ],
    "sg:phone":"+1 417 451 4565",
    "sg:postcode":"64850",
    "sg:province":"MO",
    "wof:name":"OZARK Center",
    "wof:placetype":"venue"
},
  "geometry": {"coordinates":[-94.370036,36.866607],"type":"Point"}
}