{
  "type": "Feature",
  "properties": {
    "iso:country":"US",
    "sg:address":"999 Executive Parkway Dr",
    "sg:city":"Saint Louis",
    "sg:classifiers":[
        {
            "category":"Wholesale",
            "subcategory":"Metals & Minerals",
            "type":"Manufacturing & Wholesale Goods"
        }
    ],
    "sg:phone":"+1 314 628 6030",
    "sg:postcode":"63141",
    "sg:province":"MO",
    "sg:tags":[
        "distribution",
        "various",
        "company",
        "owns"
    ],
    "wof:name":"Tsi Holding Company",
    "wof:placetype":"venue"
},
  "geometry": {"coordinates":[-90.47255800000001,38.675193],"type":"Point"}
}