{
  "type": "Feature",
  "properties": {
    "iso:country":"US",
    "sg:address":"502 S Main St",
    "sg:city":"De Soto",
    "sg:classifiers":[
        {
            "category":"Manufacturing",
            "subcategory":"Signs",
            "type":"Manufacturing & Wholesale Goods"
        }
    ],
    "sg:phone":"+1 636 337 0205",
    "sg:postcode":"63020",
    "sg:province":"MO",
    "sg:tags":[
        "specialty",
        "mfg"
    ],
    "wof:name":"Roach Signs",
    "wof:placetype":"venue"
},
  "geometry": {"coordinates":[-90.555278,38.135202],"type":"Point"}
}