{
  "type": "Feature",
  "properties": {
    "iso:country":"US",
    "sg:address":"2100 S 18th Ave",
    "sg:city":"Ozark",
    "sg:classifiers":[
        {
            "category":"Real Estate",
            "subcategory":"Real Estate Services",
            "type":"Services"
        },
        {
            "category":"Professional",
            "subcategory":"Business Services",
            "type":"Services"
        }
    ],
    "sg:phone":"+1 417 693 7478",
    "sg:postcode":"65721",
    "sg:province":"MO",
    "sg:tags":[
        "inspection"
    ],
    "wof:name":"Extra Mile Home Inspection Services",
    "wof:placetype":"venue"
},
  "geometry": {"coordinates":[-93.188931,36.997904],"type":"Point"}
}