{
  "type": "Feature",
  "properties": {
    "iso:country":"US",
    "sg:address":"610 Kingsland Ave",
    "sg:city":"St Louis",
    "sg:classifiers":[
        {
            "category":"Personal",
            "subcategory":"Beauty Salon",
            "type":"Services"
        }
    ],
    "sg:phone":"+1 314 721 4168",
    "sg:postcode":"63130",
    "sg:province":"MO",
    "wof:name":"Salon K",
    "wof:placetype":"venue"
},
  "geometry": {"coordinates":[-90.308643,38.656593],"type":"Point"}
}