{
  "type": "Feature",
  "properties": {
    "iso:country":"US",
    "sg:address":"437 Royal Village Dr",
    "sg:city":"Ballwin",
    "sg:classifiers":[
        {
            "category":"Wholesale",
            "subcategory":"Chemicals & Plastics",
            "type":"Manufacturing & Wholesale Goods"
        }
    ],
    "sg:phone":"+1 636 227 9735",
    "sg:postcode":"63011",
    "sg:province":"MO",
    "wof:name":"Cardinal Chemical Systems",
    "wof:placetype":"venue"
},
  "geometry": {"coordinates":[-90.520916,38.598696],"type":"Point"}
}