{
  "type": "Feature",
  "properties": {
    "iso:country":"US",
    "sg:address":"304 S Clayton Ave",
    "sg:city":"Maryville",
    "sg:classifiers":[
        {
            "category":"Retail",
            "subcategory":"Repair Shop",
            "type":"Services"
        }
    ],
    "sg:phone":"+1 660 582 6400",
    "sg:postcode":"64468",
    "sg:province":"MO",
    "wof:name":"Boettner Piano Tuning & Repair",
    "wof:placetype":"venue"
},
  "geometry": {"coordinates":[-94.884404,40.343978],"type":"Point"}
}