{
  "type": "Feature",
  "properties": {
    "iso:country":"US",
    "sg:address":"222 S Shepherd St",
    "sg:city":"Ironton",
    "sg:classifiers":[
        {
            "category":"Professional",
            "subcategory":"Lawyer & Legal Services",
            "type":"Services"
        }
    ],
    "sg:phone":"+1 573 546 2333",
    "sg:postcode":"63650",
    "sg:province":"MO",
    "sg:tags":[
        "attorney"
    ],
    "wof:name":"Iron Cnty Prosecuting Attorney",
    "wof:placetype":"venue"
},
  "geometry": {"coordinates":[-90.628793,37.598027],"type":"Point"}
}