{
  "type": "Feature",
  "properties": {
    "iso:country":"US",
    "sg:address":"260 E Richardson Ave",
    "sg:city":"Puxico",
    "sg:classifiers":[
        {
            "category":"Restaurant",
            "type":"Food & Drink"
        }
    ],
    "sg:phone":"+1 573 222 6118",
    "sg:postcode":"63960",
    "sg:province":"MO",
    "wof:name":"Mel's Diner",
    "wof:placetype":"venue"
},
  "geometry": {"coordinates":[-90.158153,36.949634],"type":"Point"}
}