{
  "type": "Feature",
  "properties": {
    "iso:country":"US",
    "sg:address":"741 Whispering Forest Dr",
    "sg:city":"Ballwin",
    "sg:classifiers":[
        {
            "category":"Health Services",
            "subcategory":"Clinic",
            "type":"Services"
        }
    ],
    "sg:phone":"+1 636 527 0411",
    "sg:postcode":"63021",
    "sg:province":"MO",
    "sg:tags":[
        "welfare"
    ],
    "wof:name":"Arnold Physical Therapy & Sports Medicine",
    "wof:placetype":"venue"
},
  "geometry": {"coordinates":[-90.560177,38.568583],"type":"Point"}
}