{
  "type": "Feature",
  "properties": {
    "iso:country":"US",
    "sg:address":"1428 State Hwy 47",
    "sg:city":"Warrenton",
    "sg:classifiers":[
        {
            "category":"Health Services",
            "subcategory":"Doctor",
            "type":"Services"
        }
    ],
    "sg:phone":"+1 636 456 1500",
    "sg:postcode":"63383",
    "sg:province":"MO",
    "sg:tags":[
        "physician",
        "surgeon"
    ],
    "wof:name":"Claybrooke Medical Group",
    "wof:placetype":"venue"
},
  "geometry": {"coordinates":[-91.136169,38.831549],"type":"Point"}
}