{
  "type": "Feature",
  "properties": {
    "iso:country":"US",
    "sg:address":"203 S Willow St",
    "sg:city":"Independence",
    "sg:classifiers":[
        {
            "category":"Banks & Credit Unions",
            "subcategory":"Investment Brokerage",
            "type":"Services"
        }
    ],
    "sg:phone":"+1 816 252 9066",
    "sg:postcode":"64053",
    "sg:province":"MO",
    "sg:tags":[
        "security"
    ],
    "wof:name":"Standard Bev Co Investments",
    "wof:placetype":"venue"
},
  "geometry": {"coordinates":[-94.45311100000001,39.107247],"type":"Point"}
}