{
  "type": "Feature",
  "properties": {
    "iso:country":"US",
    "sg:address":"1221 Boonslick Rd",
    "sg:city":"Saint Charles",
    "sg:classifiers":[
        {
            "category":"Health Services",
            "subcategory":"Nursing And Care Facility",
            "type":"Services"
        }
    ],
    "sg:phone":"+1 636 946 6140",
    "sg:postcode":"63301",
    "sg:province":"MO",
    "sg:tags":[
        "skilled"
    ],
    "wof:name":"Charlvoix Healthcare Rehab Ctr",
    "wof:placetype":"venue"
},
  "geometry": {"coordinates":[-90.49869,38.774087],"type":"Point"}
}