{
  "type": "Feature",
  "properties": {
    "iso:country":"US",
    "sg:address":"244 Coachman Way",
    "sg:city":"O Fallon",
    "sg:classifiers":[
        {
            "category":"Professional",
            "type":"Services"
        },
        {
            "category":"Professional",
            "subcategory":"Management & Consulting",
            "type":"Services"
        }
    ],
    "sg:phone":"+1 636 294 8692",
    "sg:postcode":"63368",
    "sg:province":"MO",
    "sg:tags":[
        "establishment"
    ],
    "wof:name":"Andersen Group Inc",
    "wof:placetype":"venue"
},
  "geometry": {"coordinates":[-90.69613699999999,38.748022],"type":"Point"}
}