{
  "type": "Feature",
  "properties": {
    "iso:country":"US",
    "sg:address":"2708A Sutton Blvd",
    "sg:city":"St Louis",
    "sg:classifiers":[
        {
            "category":"Personal",
            "subcategory":"Beauty Salon",
            "type":"Services"
        }
    ],
    "sg:phone":"+1 314 781 4222",
    "sg:postcode":"63143",
    "sg:province":"MO",
    "sg:tags":[
        "hair"
    ],
    "sg:website":"www.novasalonstl.com",
    "wof:name":"Nova Salon",
    "wof:placetype":"venue"
},
  "geometry": {"coordinates":[-90.319504,38.612235],"type":"Point"}
}