{
  "type": "Feature",
  "properties": {
    "iso:country":"US",
    "sg:address":"14862 Manchester Rd",
    "sg:city":"Ballwin",
    "sg:classifiers":[
        {
            "category":"Personal",
            "subcategory":"Beauty Salon",
            "type":"Services"
        }
    ],
    "sg:phone":"+1 636 230 0276",
    "sg:postcode":"63011",
    "sg:province":"MO",
    "wof:name":"Beautyfirst Inc",
    "wof:placetype":"venue"
},
  "geometry": {"coordinates":[-90.540577,38.592932],"type":"Point"}
}