{
  "type": "Feature",
  "properties": {
    "iso:country":"US",
    "sg:address":"140 Short Leaf Cir",
    "sg:city":"Rogersville",
    "sg:classifiers":[
        {
            "category":"Manufacturing",
            "subcategory":"Petroleum Products",
            "type":"Manufacturing & Wholesale Goods"
        }
    ],
    "sg:phone":"+1 417 753 9108",
    "sg:postcode":"65742",
    "sg:province":"MO",
    "sg:tags":[
        "contract"
    ],
    "wof:name":"Regalia Manufacturing",
    "wof:placetype":"venue"
},
  "geometry": {"coordinates":[-93.060627,37.105549],"type":"Point"}
}