{
  "type": "Feature",
  "properties": {
    "iso:country":"US",
    "sg:address":"1708 Providence St",
    "sg:city":"Mexico",
    "sg:classifiers":[
        {
            "category":"Professional",
            "subcategory":"Management & Consulting",
            "type":"Services"
        }
    ],
    "sg:phone":"+1 573 581 8831",
    "sg:postcode":"65265",
    "sg:province":"MO",
    "sg:tags":[
        "business"
    ],
    "wof:name":"Anderson Jean PR For Moll",
    "wof:placetype":"venue"
},
  "geometry": {"coordinates":[-91.905545,39.182247],"type":"Point"}
}