{
  "type": "Feature",
  "properties": {
    "iso:country":"US",
    "sg:address":"20000 E State Rte P",
    "sg:city":"Pleasant Hill",
    "sg:classifiers":[
        {
            "category":"Personal",
            "subcategory":"Beauty Salon",
            "type":"Services"
        }
    ],
    "sg:phone":"+1 816 987 3020",
    "sg:postcode":"64080",
    "sg:province":"MO",
    "sg:tags":[
        "shop"
    ],
    "wof:name":"Country Cove Salon",
    "wof:placetype":"venue"
},
  "geometry": {"coordinates":[-94.361462,38.750426],"type":"Point"}
}