{
  "type": "Feature",
  "properties": {
    "iso:country":"US",
    "sg:address":"217 W Main St",
    "sg:city":"Fredericktown",
    "sg:classifiers":[
        {
            "category":"Banks & Credit Unions",
            "subcategory":"Bank",
            "type":"Services"
        }
    ],
    "sg:phone":"+1 573 783 7244",
    "sg:postcode":"63645",
    "sg:province":"MO",
    "wof:name":"Ozarks Federal Savings & Loan",
    "wof:placetype":"venue"
},
  "geometry": {"coordinates":[-90.296947,37.559668],"type":"Point"}
}