{
  "type": "Feature",
  "properties": {
    "iso:country":"US",
    "sg:address":"105 E Jefferson St",
    "sg:city":"Marshfield",
    "sg:classifiers":[
        {
            "category":"Government",
            "subcategory":"Court House",
            "type":"Public Place"
        }
    ],
    "sg:phone":"+1 417 468 3618",
    "sg:postcode":"65706",
    "sg:province":"MO",
    "sg:tags":[
        "county",
        "counsel"
    ],
    "wof:name":"Webster County Attorney",
    "wof:placetype":"venue"
},
  "geometry": {"coordinates":[-92.906834,37.339175],"type":"Point"}
}