{
  "type": "Feature",
  "properties": {
    "iso:country":"US",
    "sg:address":"704 W Main St",
    "sg:city":"Jefferson City",
    "sg:classifiers":[
        {
            "category":"Professional",
            "subcategory":"Business Services",
            "type":"Services"
        }
    ],
    "sg:phone":"+1 573 659 3610",
    "sg:postcode":"65101",
    "sg:province":"MO",
    "wof:name":"Art Works Galley",
    "wof:placetype":"venue"
},
  "geometry": {"coordinates":[-92.180205,38.584481],"type":"Point"}
}