{
  "type": "Feature",
  "properties": {
    "iso:country":"US",
    "sg:address":"1676 Gravois Rd",
    "sg:city":"High Ridge",
    "sg:classifiers":[
        {
            "category":"Professional",
            "subcategory":"Management & Consulting",
            "type":"Services"
        }
    ],
    "sg:phone":"+1 636 376 4000",
    "sg:postcode":"63049",
    "sg:province":"MO",
    "sg:tags":[
        "a",
        "as",
        "construction",
        "provider",
        "operates"
    ],
    "wof:name":"National Project Management",
    "wof:placetype":"venue"
},
  "geometry": {"coordinates":[-90.49496499999999,38.485551],"type":"Point"}
}