{
  "type": "Feature",
  "properties": {
    "iso:country":"US",
    "sg:address":"300 Douglas Dr",
    "sg:city":"Ashland",
    "sg:classifiers":[
        {
            "category":"Building & Trades",
            "subcategory":"Construction",
            "type":"Services"
        }
    ],
    "sg:phone":"+1 573 657 2824",
    "sg:postcode":"65010",
    "sg:province":"MO",
    "sg:tags":[
        "contractor"
    ],
    "wof:name":"Ashland Gutter Co",
    "wof:placetype":"venue"
},
  "geometry": {"coordinates":[-92.25379,38.769909],"type":"Point"}
}