{
  "type": "Feature",
  "properties": {
    "iso:country":"US",
    "sg:address":"3246 N US Hwy 67",
    "sg:city":"Florissant",
    "sg:classifiers":[
        {
            "category":"Shopping",
            "type":"Retail Goods"
        }
    ],
    "sg:phone":"+1 314 839 8333",
    "sg:postcode":"63033",
    "sg:province":"MO",
    "sg:tags":[
        "pet",
        "shop"
    ],
    "wof:name":"Midwest Aquatics",
    "wof:placetype":"venue"
},
  "geometry": {"coordinates":[-90.295608,38.810759],"type":"Point"}
}