{
  "type": "Feature",
  "properties": {
    "iso:country":"US",
    "sg:address":"103 E Pearce Blvd",
    "sg:city":"Wentzville",
    "sg:classifiers":[
        {
            "category":"Insurance",
            "subcategory":"Insurance Agent",
            "type":"Services"
        }
    ],
    "sg:phone":"+1 636 327 4202",
    "sg:postcode":"63385",
    "sg:province":"MO",
    "wof:name":"Shelter Insurance",
    "wof:placetype":"venue"
},
  "geometry": {"coordinates":[-90.85166099999999,38.812379],"type":"Point"}
}