{
  "type": "Feature",
  "properties": {
    "iso:country":"US",
    "sg:address":"2605 Gerhardt St",
    "sg:city":"Cape Girardeau",
    "sg:classifiers":[
        {
            "category":"Retail",
            "subcategory":"Auto Repair",
            "type":"Services"
        }
    ],
    "sg:phone":"+1 573 334 5059",
    "sg:postcode":"63703",
    "sg:province":"MO",
    "sg:tags":[
        "muffler",
        "exhaust",
        "system"
    ],
    "wof:name":"Mr Muffler Co",
    "wof:placetype":"venue"
},
  "geometry": {"coordinates":[-89.55597299999999,37.284839],"type":"Point"}
}