{
  "type": "Feature",
  "properties": {
    "iso:country":"US",
    "sg:address":"5408 Oak Tree Dr",
    "sg:city":"Arnold",
    "sg:classifiers":[
        {
            "category":"Real Estate",
            "subcategory":"Real Estate Operator",
            "type":"Services"
        }
    ],
    "sg:phone":"+1 636 282 0533",
    "sg:postcode":"63010",
    "sg:province":"MO",
    "sg:tags":[
        "property",
        "lessor"
    ],
    "wof:name":"JB Properties",
    "wof:placetype":"venue"
},
  "geometry": {"coordinates":[-90.45850799999999,38.432874],"type":"Point"}
}