{
  "type": "Feature",
  "properties": {
    "iso:country":"US",
    "sg:address":"3452 Mckelvey Rd",
    "sg:city":"Bridgeton",
    "sg:classifiers":[
        {
            "category":"Health Services",
            "subcategory":"Chiropractor",
            "type":"Services"
        }
    ],
    "sg:phone":"+1 314 739 8841",
    "sg:postcode":"63044",
    "sg:province":"MO",
    "sg:tags":[
        "chiropractic"
    ],
    "sg:website":"http://www.droberle.com",
    "wof:name":"Family Chiropractic Center",
    "wof:placetype":"venue"
},
  "geometry": {"coordinates":[-90.42954899999999,38.749192],"type":"Point"}
}