{
  "type": "Feature",
  "properties": {
    "iso:country":"US",
    "sg:address":"4150 N Hardesty Ave",
    "sg:city":"Kansas City",
    "sg:classifiers":[
        {
            "category":"Professional",
            "type":"Services"
        }
    ],
    "sg:phone":"+1 816 455 8101",
    "sg:postcode":"64117",
    "sg:province":"MO",
    "wof:name":"Mindy G Starner",
    "wof:placetype":"venue"
},
  "geometry": {"coordinates":[-94.517279,39.168543],"type":"Point"}
}