{
  "type": "Feature",
  "properties": {
    "iso:country":"US",
    "sg:address":"310 W Main St",
    "sg:city":"Festus",
    "sg:classifiers":[
        {
            "category":"Health Services",
            "subcategory":"Doctor",
            "type":"Services"
        }
    ],
    "sg:phone":"+1 636 937 6500",
    "sg:postcode":"63028",
    "sg:province":"MO",
    "sg:tags":[
        "clinic"
    ],
    "wof:name":"Pappas Chiropractic",
    "wof:placetype":"venue"
},
  "geometry": {"coordinates":[-90.39321099999999,38.219803],"type":"Point"}
}