{
  "type": "Feature",
  "properties": {
    "iso:country":"US",
    "sg:address":"5204 Lemay Ferry Rd",
    "sg:city":"St Louis",
    "sg:classifiers":[
        {
            "category":"Autos & Motor Vehicles",
            "subcategory":"Fuel & Gas Station",
            "type":"Retail Goods"
        }
    ],
    "sg:phone":"+1 314 892 0655",
    "sg:postcode":"63129",
    "sg:province":"MO",
    "sg:tags":[
        "oil"
    ],
    "wof:name":"Butler Hill Gas & Food",
    "wof:placetype":"venue"
},
  "geometry": {"coordinates":[-90.350161,38.483674],"type":"Point"}
}