{
  "type": "Feature",
  "properties": {
    "iso:country":"US",
    "sg:address":"1101 Hospital Dr Ste 1",
    "sg:city":"Columbia",
    "sg:classifiers":[
        {
            "category":"Health Services",
            "subcategory":"Clinic",
            "type":"Services"
        },
        {
            "category":"Health Services",
            "subcategory":"Hospital",
            "type":"Services"
        }
    ],
    "sg:phone":"+1 573 882 1662",
    "sg:postcode":"65201",
    "sg:province":"MO",
    "wof:name":"University Hospital-Urgent Cr",
    "wof:placetype":"venue"
},
  "geometry": {"coordinates":[-92.329121,38.937624],"type":"Point"}
}