{
  "type": "Feature",
  "properties": {
    "iso:country":"US",
    "sg:address":"1503 NE 56 Ter",
    "sg:city":"Kansas City",
    "sg:classifiers":[
        {
            "category":"Building & Trades",
            "subcategory":"Construction",
            "type":"Services"
        }
    ],
    "sg:phone":"+1 816 483 1755",
    "sg:postcode":"64118",
    "sg:province":"MO",
    "sg:tags":[
        "contractor"
    ],
    "wof:name":"Mink Service Co",
    "wof:placetype":"venue"
},
  "geometry": {"coordinates":[-94.561233,39.196709],"type":"Point"}
}