{
  "type": "Feature",
  "properties": {
    "iso:country":"US",
    "sg:address":"131 Ecology Dr",
    "sg:city":"St Peters",
    "sg:classifiers":[
        {
            "category":"Government",
            "subcategory":"Office",
            "type":"Public Place"
        }
    ],
    "sg:phone":"+1 636 278 2244",
    "sg:postcode":"63376",
    "sg:province":"MO",
    "sg:tags":[
        "village"
    ],
    "wof:name":"St Peters Recycle Dept",
    "wof:placetype":"venue"
},
  "geometry": {"coordinates":[-90.615915,38.804366],"type":"Point"}
}