{
  "type": "Feature",
  "properties": {
    "iso:country":"US",
    "sg:address":"505 W Blue Ridge Blvd",
    "sg:city":"Kansas City",
    "sg:classifiers":[
        {
            "category":"Building & Trades",
            "subcategory":"Construction",
            "type":"Services"
        }
    ],
    "sg:phone":"+1 816 941 8288",
    "sg:postcode":"64145",
    "sg:province":"MO",
    "sg:tags":[
        "roofing",
        "contractor"
    ],
    "wof:name":"Double A Roofing Inc",
    "wof:placetype":"venue"
},
  "geometry": {"coordinates":[-94.604028,38.890723],"type":"Point"}
}