{
  "type": "Feature",
  "properties": {
    "iso:country":"US",
    "sg:address":"217 W 2nd St",
    "sg:city":"Dixon",
    "sg:classifiers":[
        {
            "category":"Retail",
            "subcategory":"Veterinary Services",
            "type":"Services"
        }
    ],
    "sg:phone":"+1 573 759 2685",
    "sg:postcode":"65459",
    "sg:province":"MO",
    "sg:tags":[
        "clinic",
        "hospital",
        "veterinarian",
        "specialty"
    ],
    "wof:name":"Jetvet Veterinarian Clinic",
    "wof:placetype":"venue"
},
  "geometry": {"coordinates":[-92.096649,37.991865],"type":"Point"}
}