{
  "type": "Feature",
  "properties": {
    "iso:country":"US",
    "sg:address":"4 Tallship Cove Ct",
    "sg:city":"O Fallon",
    "sg:classifiers":[
        {
            "category":"Professional",
            "type":"Services"
        }
    ],
    "sg:phone":"+1 636 379 4492",
    "sg:postcode":"63366",
    "sg:province":"MO",
    "sg:tags":[
        "establishment"
    ],
    "wof:name":"Astaris",
    "wof:placetype":"venue"
},
  "geometry": {"coordinates":[-90.720512,38.780479],"type":"Point"}
}