{
  "type": "Feature",
  "properties": {
    "iso:country":"US",
    "sg:address":"300 E Main St",
    "sg:city":"Portageville",
    "sg:classifiers":[
        {
            "category":"Home & Garden",
            "subcategory":"Household Appliances",
            "type":"Retail Goods"
        },
        {
            "category":"Retail",
            "subcategory":"Repair Shop",
            "type":"Services"
        }
    ],
    "sg:phone":"+1 573 379 3821",
    "sg:postcode":"63873",
    "sg:province":"MO",
    "sg:tags":[
        "radio-service",
        "television",
        "major",
        "appliances-small"
    ],
    "wof:name":"Turnage Vergina Service",
    "wof:placetype":"venue"
},
  "geometry": {"coordinates":[-89.698678,36.425373],"type":"Point"}
}