{
  "type": "Feature",
  "properties": {
    "iso:country":"US",
    "sg:address":"10665 Gateway Dr",
    "sg:city":"Neosho",
    "sg:classifiers":[
        {
            "category":"Wholesale",
            "subcategory":"Machinery & Supplies",
            "type":"Manufacturing & Wholesale Goods"
        },
        {
            "category":"Utilities",
            "subcategory":"Fuel Oil & Lpg",
            "type":"Services"
        },
        {
            "category":"Utilities",
            "subcategory":"Natural Gas",
            "type":"Services"
        }
    ],
    "sg:phone":"+1 417 451 2250",
    "sg:postcode":"64850",
    "sg:province":"MO",
    "sg:tags":[
        "gas-industrial",
        "propane",
        "petroleum-bottled",
        "bulk",
        "medical-cylinder",
        "gas-equipment",
        "gas-liquefied"
    ],
    "wof:name":"Al's Gas Co Propane",
    "wof:placetype":"venue"
},
  "geometry": {"coordinates":[-94.412468,36.882345],"type":"Point"}
}