{
  "type": "Feature",
  "properties": {
    "iso:country":"US",
    "sg:address":"904 N Ute St",
    "sg:city":"Independence",
    "sg:classifiers":[
        {
            "category":"Building & Trades",
            "subcategory":"Construction",
            "type":"Services"
        }
    ],
    "sg:phone":"+1 816 682 6644",
    "sg:postcode":"64056",
    "sg:province":"MO",
    "sg:tags":[
        "wallcoverings-installation",
        "wallpaper",
        "painting",
        "contractor"
    ],
    "wof:name":"Kyle Eshleman",
    "wof:placetype":"venue"
},
  "geometry": {"coordinates":[-94.364302,39.118931],"type":"Point"}
}