{
  "type": "Feature",
  "properties": {
    "iso:country":"US",
    "sg:address":"17269 Wild Horse Creek Rd",
    "sg:city":"Chesterfield",
    "sg:classifiers":[
        {
            "category":"Home & Garden",
            "subcategory":"Home Furnishings",
            "type":"Retail Goods"
        }
    ],
    "sg:phone":"+1 636 733 2330",
    "sg:postcode":"63005",
    "sg:province":"MO",
    "sg:tags":[
        "glassware",
        "chinaware"
    ],
    "wof:name":"O'Casey's Irish Crystal",
    "wof:placetype":"venue"
},
  "geometry": {"coordinates":[-90.617631,38.657376],"type":"Point"}
}