{
  "type": "Feature",
  "properties": {
    "iso:country":"US",
    "sg:address":"731 Emerson St",
    "sg:city":"Columbia",
    "sg:classifiers":[
        {
            "category":"Professional",
            "subcategory":"Computer Services",
            "type":"Services"
        }
    ],
    "sg:phone":"+1 573 874 1191",
    "sg:postcode":"65270",
    "sg:province":"MO",
    "wof:name":"HP",
    "wof:placetype":"venue"
},
  "geometry": {"coordinates":[-92.454143,39.424814],"type":"Point"}
}