{
  "type": "Feature",
  "properties": {
    "iso:country":"US",
    "sg:address":"742 Mitchell Ave",
    "sg:city":"New Madrid",
    "sg:phone":"+1 573 748 2258",
    "sg:postcode":"63869",
    "sg:province":"MO",
    "sg:tags":[
        "farm",
        "cotton"
    ],
    "wof:name":"Ann Copeland",
    "wof:placetype":"venue"
},
  "geometry": {"coordinates":[-89.52961000000001,36.592517],"type":"Point"}
}