{
  "type": "Feature",
  "properties": {
    "iso:country":"US",
    "sg:address":"127 S Main St",
    "sg:city":"Rogersville",
    "sg:classifiers":[
        {
            "category":"Organizations",
            "subcategory":"Religious Organization",
            "type":"Services"
        }
    ],
    "sg:phone":"+1 417 753 2819",
    "sg:postcode":"65742",
    "sg:province":"MO",
    "sg:tags":[
        "church"
    ],
    "wof:name":"Rogersville Methodist Church",
    "wof:placetype":"venue"
},
  "geometry": {"coordinates":[-93.057956,37.115014],"type":"Point"}
}