{
  "type": "Feature",
  "properties": {
    "iso:country":"US",
    "sg:address":"2585 NW State Hwy H",
    "sg:city":"Rockville",
    "sg:classifiers":[
        {
            "category":"Farming",
            "subcategory":"Livestock Farm",
            "type":"Manufacturing & Wholesale Goods"
        }
    ],
    "sg:phone":"+1 660 598 4151",
    "sg:postcode":"64780",
    "sg:province":"MO",
    "sg:tags":[
        "animal",
        "general"
    ],
    "wof:name":"Green Valley Ranc H",
    "wof:placetype":"venue"
},
  "geometry": {"coordinates":[-94.00176,38.065074],"type":"Point"}
}