{
  "type": "Feature",
  "properties": {
    "iso:country":"US",
    "sg:address":"318 W Coates St",
    "sg:city":"Moberly",
    "sg:classifiers":[
        {
            "category":"Professional",
            "subcategory":"Accounting & Tax Preparation",
            "type":"Services"
        }
    ],
    "sg:phone":"+1 660 263 7960",
    "sg:postcode":"65270",
    "sg:province":"MO",
    "sg:tags":[
        "bookkeeping",
        "billing",
        "accountants-certified",
        "public"
    ],
    "wof:name":"Callis, Ron Cpa",
    "wof:placetype":"venue"
},
  "geometry": {"coordinates":[-92.439329,39.420795],"type":"Point"}
}