{
  "type": "Feature",
  "properties": {
    "iso:country":"US",
    "sg:address":"2541 Pond Rd",
    "sg:city":"Grover",
    "sg:classifiers":[
        {
            "category":"Professional",
            "type":"Services"
        }
    ],
    "sg:phone":"+1 636 405 0026",
    "sg:postcode":"63038",
    "sg:province":"MO",
    "sg:tags":[
        "establishment"
    ],
    "wof:name":"Grover",
    "wof:placetype":"venue"
},
  "geometry": {"coordinates":[-90.65558,38.583041],"type":"Point"}
}