{
  "type": "Feature",
  "properties": {
    "iso:country":"US",
    "sg:address":"625 New Smizer Mill Rd",
    "sg:city":"Fenton",
    "sg:classifiers":[
        {
            "category":"Government",
            "subcategory":"Court House",
            "type":"Public Place"
        }
    ],
    "sg:phone":"+1 636 343 1007",
    "sg:postcode":"63026",
    "sg:province":"MO",
    "sg:tags":[
        "city"
    ],
    "wof:name":"Fenton Municipal Court",
    "wof:placetype":"venue"
},
  "geometry": {"coordinates":[-90.451733,38.516978],"type":"Point"}
}