{
  "type": "Feature",
  "properties": {
    "iso:country":"US",
    "sg:address":"1727 W 26th St",
    "sg:city":"Joplin",
    "sg:classifiers":[
        {
            "category":"Real Estate",
            "subcategory":"Real Estate Services",
            "type":"Services"
        },
        {
            "category":"Real Estate",
            "subcategory":"Real Estate Agent",
            "type":"Services"
        },
        {
            "category":"Industrial Area",
            "type":"Public Place"
        }
    ],
    "sg:phone":"+1 417 782 5220",
    "sg:postcode":"64804",
    "sg:province":"MO",
    "sg:tags":[
        "development",
        "appraisers-commercial",
        "management",
        "commercial"
    ],
    "sg:website":"http://www.midwestproperties.biz",
    "wof:name":"Midwest Properties & Management Co",
    "wof:placetype":"venue"
},
  "geometry": {"coordinates":[-94.534113,37.06264],"type":"Point"}
}