{
  "type": "Feature",
  "properties": {
    "iso:country":"US",
    "sg:address":"1705 Johnson Industrial Dr",
    "sg:city":"Excelsior Springs",
    "sg:classifiers":[
        {
            "category":"Wholesale",
            "subcategory":"Non-durable Goods",
            "type":"Manufacturing & Wholesale Goods"
        }
    ],
    "sg:phone":"+1 816 336 4332",
    "sg:postcode":"64024",
    "sg:province":"MO",
    "wof:name":"Express Favors Inc",
    "wof:placetype":"venue"
},
  "geometry": {"coordinates":[-94.251942,39.333207],"type":"Point"}
}