{
  "type": "Feature",
  "properties": {
    "iso:country":"US",
    "sg:address":"203 W Mechanic St",
    "sg:city":"Harrisonville",
    "sg:classifiers":[
        {
            "category":"Retail",
            "subcategory":"Laundry & Dry Cleaning",
            "type":"Services"
        }
    ],
    "sg:phone":"+1 816 380 6448",
    "sg:postcode":"64701",
    "sg:province":"MO",
    "wof:name":"Cotton Works Etc",
    "wof:placetype":"venue"
},
  "geometry": {"coordinates":[-94.350241,38.653092],"type":"Point"}
}