{
  "type": "Feature",
  "properties": {
    "iso:country":"US",
    "sg:address":"402 State Hwy 240",
    "sg:city":"Fayette",
    "sg:phone":"+1 660 248 3068",
    "sg:postcode":"65248",
    "sg:province":"MO",
    "sg:tags":[
        "farm",
        "grain",
        "cash"
    ],
    "wof:name":"W Lay",
    "wof:placetype":"venue"
},
  "geometry": {"coordinates":[-92.685565,39.148279],"type":"Point"}
}