{
  "type": "Feature",
  "properties": {
    "iso:country":"US",
    "sg:address":"1605 NE 69 St",
    "sg:city":"Gladstone",
    "sg:classifiers":[
        {
            "category":"Building & Trades",
            "subcategory":"Construction",
            "type":"Services"
        }
    ],
    "sg:phone":"+1 816 761 8804",
    "sg:postcode":"64118",
    "sg:province":"MO",
    "sg:tags":[
        "roofing",
        "contractor"
    ],
    "wof:name":"Nugent Brothers Roofing Inc",
    "wof:placetype":"venue"
},
  "geometry": {"coordinates":[-94.556815,39.219457],"type":"Point"}
}