{
  "type": "Feature",
  "properties": {
    "iso:country":"US",
    "sg:address":"2077 Saint Louis Galleria",
    "sg:city":"Saint Louis",
    "sg:classifiers":[
        {
            "category":"Shopping",
            "subcategory":"Jewelry",
            "type":"Retail Goods"
        }
    ],
    "sg:phone":"+1 314 863 8824",
    "sg:postcode":"63117",
    "sg:province":"MO",
    "wof:name":"Whitehall Jewellers Inc",
    "wof:placetype":"venue"
},
  "geometry": {"coordinates":[-90.34650000000001,38.6377],"type":"Point"}
}