{
  "type": "Feature",
  "properties": {
    "iso:country":"US",
    "sg:address":"10502 Highway 17",
    "sg:city":"Success",
    "sg:classifiers":[
        {
            "category":"Manufacturing",
            "subcategory":"Tools & Machinery",
            "type":"Manufacturing & Wholesale Goods"
        },
        {
            "category":"Retail",
            "subcategory":"Auto Repair",
            "type":"Services"
        }
    ],
    "sg:phone":"+1 417 458 4532",
    "sg:postcode":"65570",
    "sg:province":"MO",
    "sg:tags":[
        "repairing",
        "engines-rebuild",
        "lawn",
        "mowers-sharpening",
        "exchange"
    ],
    "wof:name":"Gabriel's Sales & Service",
    "wof:placetype":"venue"
},
  "geometry": {"coordinates":[-92.076426,37.396005],"type":"Point"}
}