{
  "type": "Feature",
  "properties": {
    "iso:country":"US",
    "sg:address":"613 E Kearney St",
    "sg:city":"Springfield",
    "sg:classifiers":[
        {
            "category":"Education",
            "subcategory":"Vocational School",
            "type":"Public Place"
        }
    ],
    "sg:phone":"+1 417 895 5863",
    "sg:postcode":"65803",
    "sg:province":"MO",
    "wof:name":"Vocational Rehabilitation",
    "wof:placetype":"venue"
},
  "geometry": {"coordinates":[-93.28401100000001,37.240724],"type":"Point"}
}