{
  "type": "Feature",
  "properties": {
    "iso:country":"US",
    "sg:address":"1349 McNutt School Rd",
    "sg:city":"Festus",
    "sg:classifiers":[
        {
            "category":"Real Estate",
            "subcategory":"Real Estate Agent",
            "type":"Services"
        }
    ],
    "sg:phone":"+1 636 931 7653",
    "sg:postcode":"63028",
    "sg:province":"MO",
    "sg:tags":[
        "appraiser"
    ],
    "sg:website":"www.bestchoicehomes.com",
    "wof:name":"Re/Max Best Choice",
    "wof:placetype":"venue"
},
  "geometry": {"coordinates":[-90.423027,38.252175],"type":"Point"}
}