{
  "type": "Feature",
  "properties": {
    "iso:country":"US",
    "sg:address":"85 Ackerman Ct",
    "sg:city":"Winfield",
    "sg:classifiers":[
        {
            "category":"Farming",
            "subcategory":"Farm",
            "type":"Manufacturing & Wholesale Goods"
        }
    ],
    "sg:phone":"+1 636 566 6379",
    "sg:postcode":"63389",
    "sg:province":"MO",
    "wof:name":"Aztar Farms",
    "wof:placetype":"venue"
},
  "geometry": {"coordinates":[-90.815315,39.005045],"type":"Point"}
}