{
  "type": "Feature",
  "properties": {
    "iso:country":"US",
    "sg:address":"1400 Lake Viking Ter",
    "sg:city":"Gallatin",
    "sg:phone":"+1 660 663 3262",
    "sg:postcode":"64640",
    "sg:province":"MO",
    "sg:tags":[
        "farm",
        "corn",
        "soybean"
    ],
    "wof:name":"Larkin Farms Inc",
    "wof:placetype":"venue"
},
  "geometry": {"coordinates":[-94.079471,39.932691],"type":"Point"}
}