{
  "type": "Feature",
  "properties": {
    "iso:country":"US",
    "sg:address":"4029 W Hialeah St",
    "sg:city":"Springfield",
    "sg:classifiers":[
        {
            "category":"Manufacturing",
            "subcategory":"Glass & Minerals",
            "type":"Manufacturing & Wholesale Goods"
        }
    ],
    "sg:phone":"+1 417 863 1104",
    "sg:postcode":"65803",
    "sg:province":"MO",
    "sg:tags":[
        "steel",
        "product",
        "mfg"
    ],
    "wof:name":"True Grace Converter & Hitches",
    "wof:placetype":"venue"
},
  "geometry": {"coordinates":[-93.361389,37.23089],"type":"Point"}
}