{
  "type": "Feature",
  "properties": {
    "iso:country":"US",
    "sg:address":"3525 Hampton Ave",
    "sg:city":"Saint Louis",
    "sg:classifiers":[
        {
            "category":"Insurance",
            "subcategory":"Life Insurance",
            "type":"Services"
        }
    ],
    "sg:phone":"+1 314 351 1029",
    "sg:postcode":"63139",
    "sg:province":"MO",
    "sg:tags":[
        "society",
        "benefit",
        "fraternal"
    ],
    "wof:name":"Catholic Knights of America",
    "wof:placetype":"venue"
},
  "geometry": {"coordinates":[-90.29261,38.598316],"type":"Point"}
}