{
  "type": "Feature",
  "properties": {
    "iso:country":"US",
    "sg:address":"705 Burkarth Rd",
    "sg:city":"Warrensburg",
    "sg:classifiers":[
        {
            "category":"Restaurant",
            "type":"Food & Drink"
        }
    ],
    "sg:phone":"+1 660 747 8618",
    "sg:postcode":"64093",
    "sg:province":"MO",
    "wof:name":"Goody's Steakburgers",
    "wof:placetype":"venue"
},
  "geometry": {"coordinates":[-93.723409,38.771874],"type":"Point"}
}