{
  "type": "Feature",
  "properties": {
    "iso:country":"US",
    "sg:address":"4002 Pickett Rd",
    "sg:city":"St Joseph",
    "sg:classifiers":[
        {
            "category":"Building & Trades",
            "subcategory":"Electrical",
            "type":"Services"
        }
    ],
    "sg:phone":"+1 816 238 3133",
    "sg:postcode":"64503",
    "sg:province":"MO",
    "sg:tags":[
        "electrical",
        "electric",
        "contractor"
    ],
    "wof:name":"Woods & Bruce Electric Co",
    "wof:placetype":"venue"
},
  "geometry": {"coordinates":[-94.795348,39.740675],"type":"Point"}
}