{
  "type": "Feature",
  "properties": {
    "iso:country":"US",
    "sg:address":"2256 S 39th St",
    "sg:city":"St Louis",
    "sg:classifiers":[
        {
            "category":"Social Services",
            "type":"Services"
        }
    ],
    "sg:phone":"+1 314 772 6530",
    "sg:postcode":"63110",
    "sg:province":"MO",
    "sg:tags":[
        "youth",
        "organization",
        "self",
        "center",
        "welfare"
    ],
    "wof:name":"Covenant House Missouri Cmnty",
    "wof:placetype":"venue"
},
  "geometry": {"coordinates":[-90.245909,38.610907],"type":"Point"}
}