{
  "type": "Feature",
  "properties": {
    "iso:country":"US",
    "sg:address":"422 E Broadway St",
    "sg:city":"Monett",
    "sg:classifiers":[
        {
            "category":"Professional",
            "type":"Services"
        }
    ],
    "sg:phone":"+1 417 235 7988",
    "sg:postcode":"65708",
    "sg:province":"MO",
    "wof:name":"El Tijerazo",
    "wof:placetype":"venue"
},
  "geometry": {"coordinates":[-93.92236,36.921161],"type":"Point"}
}