{
  "type": "Feature",
  "properties": {
    "iso:country":"US",
    "sg:address":"620 Steer Creek Way",
    "sg:city":"Kirksville",
    "sg:classifiers":[
        {
            "category":"Organizations",
            "subcategory":"Religious Organization",
            "type":"Services"
        }
    ],
    "sg:phone":"+1 660 665 4945",
    "sg:postcode":"63501",
    "sg:province":"MO",
    "sg:tags":[
        "church"
    ],
    "wof:name":"New Hope Evangelical Church",
    "wof:placetype":"venue"
},
  "geometry": {"coordinates":[-92.54859399999999,40.197478],"type":"Point"}
}