{
  "type": "Feature",
  "properties": {
    "iso:country":"US",
    "sg:address":"101 N Liberty",
    "sg:city":"Bertrand",
    "sg:classifiers":[
        {
            "category":"Retail",
            "subcategory":"Auto Repair",
            "type":"Services"
        }
    ],
    "sg:phone":"+1 573 683 4009",
    "sg:postcode":"63823",
    "sg:province":"MO",
    "sg:tags":[
        "body"
    ],
    "wof:name":"Byrds Auto Body & Repair Shop",
    "wof:placetype":"venue"
},
  "geometry": {"coordinates":[-89.45836799999999,36.909515],"type":"Point"}
}