{
  "type": "Feature",
  "properties": {
    "iso:country":"US",
    "sg:address":"118 N 3rd St",
    "sg:city":"Branson",
    "sg:classifiers":[
        {
            "category":"Health Services",
            "subcategory":"Chiropractor",
            "type":"Services"
        }
    ],
    "sg:phone":"+1 417 334 8828",
    "sg:postcode":"65616",
    "sg:province":"MO",
    "sg:tags":[
        "chiropractic"
    ],
    "wof:name":"A Familys Place Chiropractic",
    "wof:placetype":"venue"
},
  "geometry": {"coordinates":[-93.219505,36.644317],"type":"Point"}
}