{
  "type": "Feature",
  "properties": {
    "iso:country":"US",
    "sg:address":"11 Ronnies Plz",
    "sg:city":"St Louis",
    "sg:classifiers":[
        {
            "category":"Health Services",
            "subcategory":"Doctor",
            "type":"Services"
        }
    ],
    "sg:phone":"+1 314 842 5700",
    "sg:postcode":"63126",
    "sg:province":"MO",
    "sg:tags":[
        "dentist"
    ],
    "wof:name":"Affton Dental Ctr",
    "wof:placetype":"venue"
},
  "geometry": {"coordinates":[-90.36060500000001,38.526913],"type":"Point"}
}