{
  "type": "Feature",
  "properties": {
    "iso:country":"US",
    "sg:address":"4403 NW Dmons Dr",
    "sg:city":"Riverside",
    "sg:classifiers":[
        {
            "category":"Real Estate",
            "subcategory":"Real Estate Services",
            "type":"Services"
        }
    ],
    "sg:phone":"+1 888 216 9710",
    "sg:postcode":"64150",
    "sg:province":"MO",
    "sg:tags":[
        "apartment",
        "management",
        "rental",
        "finder"
    ],
    "wof:name":"Chateau D'Mons",
    "wof:placetype":"venue"
},
  "geometry": {"coordinates":[-94.619083,39.174321],"type":"Point"}
}