{
  "type": "Feature",
  "properties": {
    "iso:country":"US",
    "sg:address":"1801 W Vine St",
    "sg:city":"Harrisonville",
    "sg:classifiers":[
        {
            "category":"Manufacturing",
            "subcategory":"Tools & Machinery",
            "type":"Manufacturing & Wholesale Goods"
        }
    ],
    "sg:phone":"+1 816 884 3534",
    "sg:postcode":"64701",
    "sg:province":"MO",
    "sg:tags":[
        "woodworking"
    ],
    "wof:name":"R B Industries Inc",
    "wof:placetype":"venue"
},
  "geometry": {"coordinates":[-94.361901,38.659862],"type":"Point"}
}