{
  "type": "Feature",
  "properties": {
    "iso:country":"US",
    "sg:address":"681 Larkin Williams Rd",
    "sg:city":"Fenton",
    "sg:classifiers":[
        {
            "category":"Manufacturing",
            "subcategory":"Signs",
            "type":"Manufacturing & Wholesale Goods"
        }
    ],
    "sg:phone":"+1 636 349 3344",
    "sg:postcode":"63026",
    "sg:province":"MO",
    "wof:name":"Pfitzinger Graphics",
    "wof:placetype":"venue"
},
  "geometry": {"coordinates":[-90.437078,38.5163],"type":"Point"}
}