{
  "type": "Feature",
  "properties": {
    "iso:country":"US",
    "sg:address":"8419 Manchester Rd",
    "sg:city":"St Louis",
    "sg:classifiers":[
        {
            "category":"Home & Garden",
            "subcategory":"Garden Supply",
            "type":"Retail Goods"
        }
    ],
    "sg:phone":"+1 314 961 5551",
    "sg:postcode":"63144",
    "sg:province":"MO",
    "sg:tags":[
        "nurseryman"
    ],
    "wof:name":"Teson Farms Garden Ctr",
    "wof:placetype":"venue"
},
  "geometry": {"coordinates":[-90.34267,38.612291],"type":"Point"}
}