{
  "type": "Feature",
  "properties": {
    "iso:country":"US",
    "sg:address":"2012 Meadows Rd",
    "sg:city":"Poplar Bluff",
    "sg:classifiers":[
        {
            "category":"Home & Garden",
            "subcategory":"Building Materials",
            "type":"Retail Goods"
        }
    ],
    "sg:phone":"+1 573 785 4987",
    "sg:postcode":"63901",
    "sg:province":"MO",
    "wof:name":"Eads Sand & Gravel",
    "wof:placetype":"venue"
},
  "geometry": {"coordinates":[-90.42486700000001,36.775567],"type":"Point"}
}