{
  "type": "Feature",
  "properties": {
    "iso:country":"US",
    "sg:address":"5507 Hwy D",
    "sg:city":"Farmington",
    "sg:classifiers":[
        {
            "category":"Building & Trades",
            "subcategory":"Construction",
            "type":"Services"
        }
    ],
    "sg:phone":"+1 573 756 2912",
    "sg:postcode":"63640",
    "sg:province":"MO",
    "sg:tags":[
        "home",
        "improvement"
    ],
    "wof:name":"Govro Electric",
    "wof:placetype":"venue"
},
  "geometry": {"coordinates":[-90.42244599999999,37.84819],"type":"Point"}
}