{
  "type": "Feature",
  "properties": {
    "iso:country":"US",
    "sg:address":"117 E 4th St",
    "sg:city":"Salem",
    "sg:classifiers":[
        {
            "category":"Shopping",
            "subcategory":"Computers & Home Electronics",
            "type":"Retail Goods"
        }
    ],
    "sg:phone":"+1 573 729 2920",
    "sg:postcode":"65560",
    "sg:province":"MO",
    "sg:tags":[
        "equipment",
        "dealer"
    ],
    "wof:name":"Whitedove Computers",
    "wof:placetype":"venue"
},
  "geometry": {"coordinates":[-91.536175,37.645307],"type":"Point"}
}