{
  "type": "Feature",
  "properties": {
    "iso:country":"US",
    "sg:address":"812 N 4th St",
    "sg:city":"Ozark",
    "sg:classifiers":[
        {
            "category":"Professional",
            "subcategory":"Business Services",
            "type":"Services"
        }
    ],
    "sg:phone":"+1 417 582 0793",
    "sg:postcode":"65721",
    "sg:province":"MO",
    "sg:tags":[
        "consultant",
        "coach"
    ],
    "wof:name":"Eagle Vision Consulting",
    "wof:placetype":"venue"
},
  "geometry": {"coordinates":[-93.208091,37.027404],"type":"Point"}
}