{
  "type": "Feature",
  "properties": {
    "iso:country":"US",
    "sg:address":"7733 Kingsbury Blvd",
    "sg:city":"Saint Louis",
    "sg:classifiers":[
        {
            "category":"Professional",
            "subcategory":"Research",
            "type":"Services"
        }
    ],
    "sg:phone":"+1 314 726 3406",
    "sg:postcode":"63105",
    "sg:province":"MO",
    "sg:tags":[
        "organization",
        "noncommercial"
    ],
    "wof:name":"Katherine J Mathews",
    "wof:placetype":"venue"
},
  "geometry": {"coordinates":[-90.335672,38.655787],"type":"Point"}
}