{
  "type": "Feature",
  "properties": {
    "iso:country":"US",
    "sg:address":"11498 Blue Ridge Blvd",
    "sg:city":"Kansas City",
    "sg:classifiers":[
        {
            "category":"Banks & Credit Unions",
            "subcategory":"Bank",
            "type":"Services"
        }
    ],
    "sg:phone":"+1 816 763 1000",
    "sg:postcode":"64134",
    "sg:province":"MO",
    "sg:tags":[
        "institution",
        "business"
    ],
    "wof:name":"Midwest Title Loans",
    "wof:placetype":"venue"
},
  "geometry": {"coordinates":[-94.51200300000001,38.91655],"type":"Point"}
}