{
  "type": "Feature",
  "properties": {
    "iso:country":"US",
    "sg:address":"3451 Texas Ave",
    "sg:city":"Saint Louis",
    "sg:classifiers":[
        {
            "category":"Shopping",
            "subcategory":"Florist",
            "type":"Retail Goods"
        }
    ],
    "sg:phone":"+1 314 865 2621",
    "sg:postcode":"63118",
    "sg:province":"MO",
    "wof:name":"Balloons Unlimited",
    "wof:placetype":"venue"
},
  "geometry": {"coordinates":[-90.22702099999999,38.592555],"type":"Point"}
}