{
  "type": "Feature",
  "properties": {
    "iso:country":"US",
    "sg:address":"2838 Market St",
    "sg:city":"Saint Louis",
    "sg:classifiers":[
        {
            "category":"Retail",
            "subcategory":"Photofinishing",
            "type":"Services"
        }
    ],
    "sg:phone":"+1 314 652 1300",
    "sg:postcode":"63103",
    "sg:province":"MO",
    "sg:tags":[
        "laboratory"
    ],
    "wof:name":"Qualex Inc",
    "wof:placetype":"venue"
},
  "geometry": {"coordinates":[-90.220159,38.631051],"type":"Point"}
}