{
  "type": "Feature",
  "properties": {
    "iso:country":"US",
    "sg:address":"4033 Hwy K",
    "sg:city":"Bonne Terre",
    "sg:classifiers":[
        {
            "category":"Organizations",
            "subcategory":"Religious Organization",
            "type":"Services"
        }
    ],
    "sg:phone":"+1 573 358 7820",
    "sg:postcode":"63628",
    "sg:province":"MO",
    "sg:tags":[
        "church"
    ],
    "wof:name":"Marvin Chapel United Methodist",
    "wof:placetype":"venue"
},
  "geometry": {"coordinates":[-90.47217999999999,37.929294],"type":"Point"}
}