{
  "type": "Feature",
  "properties": {
    "iso:country":"US",
    "sg:address":"307 Kentucky St",
    "sg:city":"West Plains",
    "sg:classifiers":[
        {
            "category":"Shopping",
            "subcategory":"Pharmacy",
            "type":"Retail Goods"
        }
    ],
    "sg:phone":"+1 417 256 7533",
    "sg:postcode":"65775",
    "sg:province":"MO",
    "wof:name":"Super D Drugs",
    "wof:placetype":"venue"
},
  "geometry": {"coordinates":[-91.876122,36.731607],"type":"Point"}
}