{
  "type": "Feature",
  "properties": {
    "iso:country":"US",
    "sg:address":"1415 W Lark Industrial Dr",
    "sg:city":"Fenton",
    "sg:classifiers":[
        {
            "category":"Professional",
            "subcategory":"Engineering",
            "type":"Services"
        }
    ],
    "sg:phone":"+1 636 349 6565",
    "sg:postcode":"63026",
    "sg:province":"MO",
    "sg:tags":[
        "civil",
        "engineer"
    ],
    "wof:name":"Tom V Dismuke",
    "wof:placetype":"venue"
},
  "geometry": {"coordinates":[-90.49685599999999,38.494513],"type":"Point"}
}