{
  "type": "Feature",
  "properties": {
    "iso:country":"US",
    "sg:address":"4825 Fairmount Ave",
    "sg:city":"Kansas City",
    "sg:classifiers":[
        {
            "category":"Manufacturing",
            "subcategory":"Toys & Sporting Goods",
            "type":"Manufacturing & Wholesale Goods"
        }
    ],
    "sg:phone":"+1 816 753 3253",
    "sg:postcode":"64112",
    "sg:province":"MO",
    "sg:tags":[
        "mfg"
    ],
    "wof:name":"EZ Sports Boards",
    "wof:placetype":"venue"
},
  "geometry": {"coordinates":[-94.604428,39.040054],"type":"Point"}
}