{
  "type": "Feature",
  "properties": {
    "iso:country":"US",
    "sg:address":"920 S Jefferson St",
    "sg:city":"Webb City",
    "sg:classifiers":[
        {
            "category":"Personal",
            "subcategory":"Beauty Salon",
            "type":"Services"
        }
    ],
    "sg:phone":"+1 417 673 1777",
    "sg:postcode":"64870",
    "sg:province":"MO",
    "sg:tags":[
        "shop"
    ],
    "wof:name":"Towne & Country Beauty Salon",
    "wof:placetype":"venue"
},
  "geometry": {"coordinates":[-94.47340199999999,37.135742],"type":"Point"}
}