{
  "type": "Feature",
  "properties": {
    "iso:country":"US",
    "sg:address":"1207 W 67 Ter",
    "sg:city":"Kansas City",
    "sg:classifiers":[
        {
            "category":"Professional",
            "subcategory":"Management & Consulting",
            "type":"Services"
        }
    ],
    "sg:phone":"+1 816 444 9900",
    "sg:postcode":"64113",
    "sg:province":"MO",
    "wof:name":"Show ME Success Inc",
    "wof:placetype":"venue"
},
  "geometry": {"coordinates":[-94.607589,39.006862],"type":"Point"}
}