{
  "type": "Feature",
  "properties": {
    "iso:country":"US",
    "sg:address":"703 E Harrison St",
    "sg:city":"Brunswick",
    "sg:classifiers":[
        {
            "category":"Personal",
            "subcategory":"Beauty Salon",
            "type":"Services"
        }
    ],
    "sg:phone":"+1 660 548 3986",
    "sg:postcode":"65236",
    "sg:province":"MO",
    "wof:name":"Doris' Beauty Boutique",
    "wof:placetype":"venue"
},
  "geometry": {"coordinates":[-93.123394,39.423305],"type":"Point"}
}