{
  "type": "Feature",
  "properties": {
    "iso:country":"US",
    "sg:address":"12060 Bellefontaine Rd",
    "sg:city":"Saint Louis",
    "sg:classifiers":[
        {
            "category":"Social Services",
            "subcategory":"Child Care",
            "type":"Services"
        }
    ],
    "sg:phone":"+1 314 355 3895",
    "sg:postcode":"63138",
    "sg:province":"MO",
    "sg:tags":[
        "day"
    ],
    "wof:name":"Bassett Development Center",
    "wof:placetype":"venue"
},
  "geometry": {"coordinates":[-90.214157,38.792888],"type":"Point"}
}