{
  "type": "Feature",
  "properties": {
    "iso:country":"US",
    "sg:address":"2775 N US Hwy 67",
    "sg:city":"Florissant",
    "sg:classifiers":[
        {
            "category":"Retail",
            "subcategory":"Auto Repair",
            "type":"Services"
        }
    ],
    "sg:phone":"+1 314 831 1500",
    "sg:postcode":"63033",
    "sg:province":"MO",
    "sg:tags":[
        "repairing",
        "automobile"
    ],
    "wof:name":"Dobbs Tire & Auto Ctr",
    "wof:placetype":"venue"
},
  "geometry": {"coordinates":[-90.303067,38.806996],"type":"Point"}
}