{
  "type": "Feature",
  "properties": {
    "iso:country":"US",
    "sg:address":"2905 Bartlett St",
    "sg:city":"Bethany",
    "sg:classifiers":[
        {
            "category":"Retail",
            "subcategory":"Auto Repair",
            "type":"Services"
        }
    ],
    "sg:phone":"+1 660 425 4443",
    "sg:postcode":"64424",
    "sg:province":"MO",
    "sg:tags":[
        "wrecker"
    ],
    "wof:name":"Milner's Towing",
    "wof:placetype":"venue"
},
  "geometry": {"coordinates":[-94.022076,40.272206],"type":"Point"}
}