{
  "type": "Feature",
  "properties": {
    "iso:country":"US",
    "sg:address":"206 3rd St",
    "sg:city":"Monett",
    "sg:classifiers":[
        {
            "category":"Real Estate",
            "subcategory":"Real Estate Services",
            "type":"Services"
        }
    ],
    "sg:phone":"+1 417 235 9025",
    "sg:postcode":"65708",
    "sg:province":"MO",
    "sg:tags":[
        "company",
        "abstract",
        "title"
    ],
    "wof:name":"Lawrence County Title Services",
    "wof:placetype":"venue"
},
  "geometry": {"coordinates":[-93.90008,37.02111],"type":"Point"}
}