{
  "type": "Feature",
  "properties": {
    "iso:country":"US",
    "sg:address":"14 Maryland Plaza",
    "sg:city":"Saint Louis",
    "sg:classifiers":[
        {
            "category":"Restaurant",
            "type":"Food & Drink"
        }
    ],
    "sg:phone":"+1 314 678 3385",
    "sg:postcode":"63190",
    "sg:province":"MO",
    "sg:website":"www.barlouieamerica.com",
    "wof:name":"Bar Louie",
    "wof:placetype":"venue"
},
  "geometry": {"coordinates":[-90.26206999999999,38.644849],"type":"Point"}
}