{
  "type": "Feature",
  "properties": {
    "iso:country":"US",
    "sg:address":"1428 W 8th St",
    "sg:city":"West Plains",
    "sg:classifiers":[
        {
            "category":"Organizations",
            "subcategory":"Labor Organization",
            "type":"Services"
        }
    ],
    "sg:phone":"+1 417 256 0708",
    "sg:postcode":"65775",
    "sg:province":"MO",
    "wof:name":"IAM",
    "wof:placetype":"venue"
},
  "geometry": {"coordinates":[-91.87021900000001,36.739192],"type":"Point"}
}