{
  "type": "Feature",
  "properties": {
    "iso:country":"US",
    "sg:address":"1813 Greenbrier Dr",
    "sg:city":"Cape Girardeau",
    "sg:classifiers":[
        {
            "category":"Real Estate",
            "subcategory":"Surveying",
            "type":"Services"
        }
    ],
    "sg:phone":"+1 573 339 7473",
    "sg:postcode":"63701",
    "sg:province":"MO",
    "sg:tags":[
        "surveyor"
    ],
    "wof:name":"Richards Land Surveying",
    "wof:placetype":"venue"
},
  "geometry": {"coordinates":[-89.55162900000001,37.344056],"type":"Point"}
}