{
  "type": "Feature",
  "properties": {
    "iso:country":"US",
    "sg:address":"2203 S 39th St",
    "sg:city":"St Louis",
    "sg:classifiers":[
        {
            "category":"Restaurant",
            "type":"Food & Drink"
        },
        {
            "category":"Bakery",
            "type":"Food & Drink"
        }
    ],
    "sg:phone":"+1 314 771 4278",
    "sg:postcode":"63110",
    "sg:province":"MO",
    "sg:tags":[
        "vegan"
    ],
    "sg:website":"www.sweetartstl.com/",
    "wof:name":"Sweet Art",
    "wof:placetype":"venue"
},
  "geometry": {"coordinates":[-90.246009,38.610975],"type":"Point"}
}