{
  "type": "Feature",
  "properties": {
    "iso:country":"US",
    "sg:address":"4338 E 142nd St",
    "sg:city":"Grandview",
    "sg:classifiers":[
        {
            "category":"Real Estate",
            "subcategory":"Surveying",
            "type":"Services"
        }
    ],
    "sg:phone":"+1 816 761 1200",
    "sg:postcode":"64030",
    "sg:province":"MO",
    "sg:tags":[
        "surveyor"
    ],
    "wof:name":"Chrisman Land Surveyors",
    "wof:placetype":"venue"
},
  "geometry": {"coordinates":[-94.54564999999999,38.868826],"type":"Point"}
}