{
  "type": "Feature",
  "properties": {
    "iso:country":"US",
    "sg:address":"120 E 2nd St",
    "sg:city":"Hermann",
    "sg:classifiers":[
        {
            "category":"Manufacturing",
            "subcategory":"Signs",
            "type":"Manufacturing & Wholesale Goods"
        },
        {
            "category":"Professional",
            "subcategory":"Business Services",
            "type":"Services"
        }
    ],
    "sg:phone":"+1 573 486 3373",
    "sg:postcode":"65041",
    "sg:province":"MO",
    "sg:tags":[
        "specialty",
        "mfg"
    ],
    "wof:name":"My Father's",
    "wof:placetype":"venue"
},
  "geometry": {"coordinates":[-91.437228,38.705997],"type":"Point"}
}