{
  "type": "Feature",
  "properties": {
    "addr:full":"1643 NE Douglas St Lees Summit MO 64086",
    "addr:housenumber":"1643",
    "addr:postcode":"64086",
    "addr:street":"Ne Douglas St Lees",
    "iso:country":"US",
    "sg:address":"1643 NE Douglas St",
    "sg:city":"Lees Summit",
    "sg:classifiers":[
        {
            "category":"Health Services",
            "subcategory":"Medical Lab",
            "type":"Services"
        }
    ],
    "sg:phone":"+1 816 246 0377",
    "sg:postcode":"64086",
    "sg:province":"MO",
    "sg:tags":[
        "laboratory"
    ],
    "wof:name":"Laboratory Corporation America",
    "wof:placetype":"venue"
},
  "geometry": {"coordinates":[-94.37832899999999,38.940552],"type":"Point"}
}