{
  "type": "Feature",
  "properties": {
    "iso:country":"US",
    "sg:address":"4230 Phelps Rd",
    "sg:city":"Independence",
    "sg:classifiers":[
        {
            "category":"Insurance",
            "subcategory":"Insurance Agent",
            "type":"Services"
        }
    ],
    "sg:phone":"+1 816 478 9030",
    "sg:postcode":"64055",
    "sg:province":"MO",
    "wof:name":"Prudential",
    "wof:placetype":"venue"
},
  "geometry": {"coordinates":[-94.403533,39.043304],"type":"Point"}
}