{
  "type": "Feature",
  "properties": {
    "iso:country":"US",
    "sg:address":"18506 State Hwy 13",
    "sg:city":"Reeds Spring",
    "sg:classifiers":[
        {
            "category":"Food & Beverages",
            "subcategory":"Dairy",
            "type":"Retail Goods"
        },
        {
            "category":"Restaurant",
            "type":"Food & Drink"
        }
    ],
    "sg:phone":"+1 417 272 0800",
    "sg:postcode":"65737",
    "sg:province":"MO",
    "sg:tags":[
        "product",
        "parlor",
        "ice",
        "cream"
    ],
    "wof:name":"Scottie's Frozen Custard",
    "wof:placetype":"venue"
},
  "geometry": {"coordinates":[-93.369766,36.702242],"type":"Point"}
}