{
  "type": "Feature",
  "properties": {
    "iso:country":"US",
    "sg:address":"6726 Chippewa St",
    "sg:city":"Saint Louis",
    "sg:classifiers":[
        {
            "category":"Ice Cream",
            "type":"Food & Drink"
        }
    ],
    "sg:phone":"+1 314 481 2652",
    "sg:postcode":"63109",
    "sg:province":"MO",
    "sg:tags":[
        "frozen",
        "yogurt"
    ],
    "sg:website":"www.teddrewes.com/",
    "wof:name":"Ted Drewes Frozen Custard",
    "wof:placetype":"venue"
},
  "geometry": {"coordinates":[-90.307105,38.589634],"type":"Point"}
}