{
  "type": "Feature",
  "properties": {
    "iso:country":"US",
    "sg:address":"1800 Zumbehl Rd",
    "sg:city":"St Charles",
    "sg:classifiers":[
        {
            "category":"Travel",
            "subcategory":"Hotels & Motels",
            "type":"Entertainment"
        }
    ],
    "sg:phone":"+1 636 949 6800",
    "sg:postcode":"63303",
    "sg:province":"MO",
    "sg:tags":[
        "operation"
    ],
    "sg:website":"www.marriott.com",
    "wof:name":"TownePlace Suites By Marriott",
    "wof:placetype":"venue"
},
  "geometry": {"coordinates":[-90.52745899999999,38.775749],"type":"Point"}
}