{
  "type": "Feature",
  "properties": {
    "iso:country":"US",
    "sg:address":"112 East St",
    "sg:city":"Green City",
    "sg:classifiers":[
        {
            "category":"Organizations",
            "subcategory":"Religious Organization",
            "type":"Services"
        }
    ],
    "sg:phone":"+1 660 874 4199",
    "sg:postcode":"63545",
    "sg:province":"MO",
    "sg:tags":[
        "church"
    ],
    "wof:name":"Assembly Of God",
    "wof:placetype":"venue"
},
  "geometry": {"coordinates":[-92.95137800000001,40.267713],"type":"Point"}
}