{
  "type": "Feature",
  "properties": {
    "iso:country":"US",
    "sg:address":"613 Veterns Memorial Pkwy",
    "sg:city":"Warrenton",
    "sg:classifiers":[
        {
            "category":"Recreation",
            "type":"Entertainment"
        }
    ],
    "sg:phone":"+1 636 456 3333",
    "sg:postcode":"63383",
    "sg:province":"MO",
    "sg:tags":[
        "concessionaire"
    ],
    "wof:name":"Albright Concessions",
    "wof:placetype":"venue"
},
  "geometry": {"coordinates":[-91.141688,38.818549],"type":"Point"}
}