{
  "type": "Feature",
  "properties": {
    "iso:country":"US",
    "sg:address":"1924 Golden Hills Dr",
    "sg:city":"Saint Peters",
    "sg:classifiers":[
        {
            "category":"Wholesale",
            "subcategory":"Non-durable Goods",
            "type":"Manufacturing & Wholesale Goods"
        }
    ],
    "sg:phone":"+1 636 928 3927",
    "sg:postcode":"63376",
    "sg:province":"MO",
    "wof:name":"Murphy Distributing",
    "wof:placetype":"venue"
},
  "geometry": {"coordinates":[-90.56834600000001,38.774244],"type":"Point"}
}