{
  "type": "Feature",
  "properties": {
    "iso:country":"US",
    "sg:address":"636 Lemay Ferry Rd",
    "sg:city":"Saint Louis",
    "sg:classifiers":[
        {
            "category":"Professional",
            "type":"Services"
        }
    ],
    "sg:phone":"+1 314 638 3122",
    "sg:postcode":"63125",
    "sg:province":"MO",
    "wof:name":"Best One Phone Services",
    "wof:placetype":"venue"
},
  "geometry": {"coordinates":[-90.27913700000001,38.541243],"type":"Point"}
}