{
  "type": "Feature",
  "properties": {
    "iso:country":"US",
    "sg:address":"1412 I- 70 Bus",
    "sg:city":"Columbia",
    "sg:classifiers":[
        {
            "category":"Autos & Motor Vehicles",
            "subcategory":"Auto Supplies",
            "type":"Retail Goods"
        }
    ],
    "sg:phone":"+1 573 442 1371",
    "sg:postcode":"65201",
    "sg:province":"MO",
    "sg:tags":[
        "tire"
    ],
    "wof:name":"W K Smith Motor Co",
    "wof:placetype":"venue"
},
  "geometry": {"coordinates":[-92.318425,38.963868],"type":"Point"}
}