{
  "type": "Feature",
  "properties": {
    "iso:country":"US",
    "sg:address":"460 State Hwy 291",
    "sg:city":"Lees Summit",
    "sg:classifiers":[
        {
            "category":"Banks & Credit Unions",
            "subcategory":"Bank",
            "type":"Services"
        }
    ],
    "sg:phone":"+1 816 979 4196",
    "sg:postcode":"64086",
    "sg:province":"MO",
    "sg:tags":[
        "loan",
        "real estate"
    ],
    "wof:name":"Bank Of America Mortgage",
    "wof:placetype":"venue"
},
  "geometry": {"coordinates":[-94.361614,38.92002],"type":"Point"}
}