{
  "type": "Feature",
  "properties": {
    "iso:country":"US",
    "sg:address":"332 SE Douglas St",
    "sg:city":"Lees Summit",
    "sg:classifiers":[
        {
            "category":"Professional",
            "subcategory":"Research",
            "type":"Services"
        }
    ],
    "sg:phone":"+1 816 554 3071",
    "sg:postcode":"64063",
    "sg:province":"MO",
    "sg:tags":[
        "environmental",
        "ecological"
    ],
    "wof:name":"Kingston Environmental Inc",
    "wof:placetype":"venue"
},
  "geometry": {"coordinates":[-94.376042,38.912302],"type":"Point"}
}