{
  "type": "Feature",
  "properties": {
    "iso:country":"US",
    "sg:address":"29608 E 65 St",
    "sg:city":"Blue Springs",
    "sg:classifiers":[
        {
            "category":"Autos & Motor Vehicles",
            "subcategory":"Automobile Sales",
            "type":"Retail Goods"
        }
    ],
    "sg:phone":"+1 816 229 5155",
    "sg:postcode":"64014",
    "sg:province":"MO",
    "wof:name":"3-D Cars",
    "wof:placetype":"venue"
},
  "geometry": {"coordinates":[-94.234889,38.99548],"type":"Point"}
}