{
  "type": "Feature",
  "properties": {
    "iso:country":"US",
    "sg:address":"12360 Manchester Rd",
    "sg:city":"St Louis",
    "sg:classifiers":[
        {
            "category":"Personal",
            "subcategory":"Tanning Parlor",
            "type":"Services"
        }
    ],
    "sg:phone":"+1 314 965 8268",
    "sg:postcode":"63131",
    "sg:province":"MO",
    "sg:tags":[
        "salon"
    ],
    "wof:name":"Tan-U",
    "wof:placetype":"venue"
},
  "geometry": {"coordinates":[-90.44378399999999,38.603477],"type":"Point"}
}