{
  "type": "Feature",
  "properties": {
    "iso:country":"US",
    "sg:address":"3045 S Scenic Ave",
    "sg:city":"Springfield",
    "sg:classifiers":[
        {
            "category":"Wholesale",
            "subcategory":"Toys & Hobbies",
            "type":"Manufacturing & Wholesale Goods"
        }
    ],
    "sg:phone":"+1 417 889 1620",
    "sg:postcode":"65807",
    "sg:province":"MO",
    "sg:tags":[
        "wholesaler"
    ],
    "wof:name":"LEX Wholesale",
    "wof:placetype":"venue"
},
  "geometry": {"coordinates":[-93.332104,37.160002],"type":"Point"}
}