{
  "type": "Feature",
  "properties": {
    "iso:country":"US",
    "sg:address":"3010 S Westwood Blvd",
    "sg:city":"Poplar Bluff",
    "sg:classifiers":[
        {
            "category":"Home & Garden",
            "subcategory":"Home Furnishings",
            "type":"Retail Goods"
        }
    ],
    "sg:phone":"+1 573 785 0408",
    "sg:postcode":"63901",
    "sg:province":"MO",
    "sg:tags":[
        "lighting",
        "fixture"
    ],
    "wof:name":"Brass & Oak Discount",
    "wof:placetype":"venue"
},
  "geometry": {"coordinates":[-90.43241,36.733513],"type":"Point"}
}