{
  "type": "Feature",
  "properties": {
    "addr:full":"425 Hunt St Leadwood MO 63653",
    "addr:housenumber":"425",
    "addr:postcode":"63653",
    "addr:street":"Hunt St",
    "iso:country":"US",
    "sg:address":"425 Hunt St",
    "sg:city":"Leadwood",
    "sg:classifiers":[
        {
            "category":"Shopping",
            "subcategory":"Department Store",
            "type":"Retail Goods"
        }
    ],
    "sg:phone":"+1 573 562 7518",
    "sg:postcode":"63653",
    "sg:province":"MO",
    "wof:name":"Dollar General",
    "wof:placetype":"venue"
},
  "geometry": {"coordinates":[-90.586536,37.866791],"type":"Point"}
}