{
  "type": "Feature",
  "properties": {
    "iso:country":"US",
    "sg:address":"103 3rd St",
    "sg:city":"Meta",
    "sg:classifiers":[
        {
            "category":"Government",
            "subcategory":"City Hall",
            "type":"Public Place"
        },
        {
            "category":"Government",
            "subcategory":"Office",
            "type":"Public Place"
        }
    ],
    "sg:phone":"+1 573 229 4439",
    "sg:postcode":"65058",
    "sg:province":"MO",
    "sg:tags":[
        "town",
        "township",
        "planner",
        "government-city",
        "village"
    ],
    "wof:name":"City Of Meta",
    "wof:placetype":"venue"
},
  "geometry": {"coordinates":[-92.167317,38.312191],"type":"Point"}
}