{
  "type": "Feature",
  "properties": {
    "iso:country":"US",
    "sg:address":"355 State Hwy F",
    "sg:city":"Cuba",
    "sg:classifiers":[
        {
            "category":"Travel",
            "subcategory":"Campground",
            "type":"Entertainment"
        }
    ],
    "sg:phone":"+1 573 885 3622",
    "sg:postcode":"65453",
    "sg:province":"MO",
    "wof:name":"Blue Moon Rv & Horse Park",
    "wof:placetype":"venue"
},
  "geometry": {"coordinates":[-91.488266,38.04809],"type":"Point"}
}