{
  "type": "Feature",
  "properties": {
    "iso:country":"US",
    "sg:address":"124 E Morrison St",
    "sg:city":"Fayette",
    "sg:classifiers":[
        {
            "category":"Insurance",
            "subcategory":"Hazard Insurance",
            "type":"Services"
        }
    ],
    "sg:phone":"+1 660 248 3322",
    "sg:postcode":"65248",
    "sg:province":"MO",
    "sg:tags":[
        "commercial",
        "business"
    ],
    "wof:name":"Town & Country Insurance Agcy",
    "wof:placetype":"venue"
},
  "geometry": {"coordinates":[-92.683364,39.145865],"type":"Point"}
}