{
  "type": "Feature",
  "properties": {
    "iso:country":"US",
    "sg:address":"1501 NW Woods Chapel Rd",
    "sg:city":"Blue Springs",
    "sg:classifiers":[
        {
            "category":"Autos & Motor Vehicles",
            "subcategory":"Fuel & Gas Station",
            "type":"Retail Goods"
        }
    ],
    "sg:phone":"+1 816 228 0650",
    "sg:postcode":"64015",
    "sg:province":"MO",
    "sg:tags":[
        "grocery",
        "station",
        "gasoline",
        "oil"
    ],
    "wof:name":"Conoco",
    "wof:placetype":"venue"
},
  "geometry": {"coordinates":[-94.30523599999999,39.032855],"type":"Point"}
}