{
  "type": "Feature",
  "properties": {
    "iso:country":"US",
    "sg:address":"3 Tuscany Park",
    "sg:city":"Saint Louis",
    "sg:classifiers":[
        {
            "category":"Professional",
            "type":"Services"
        }
    ],
    "sg:phone":"+1 314 863 7239",
    "sg:postcode":"63105",
    "sg:province":"MO",
    "wof:name":"Jonathan I Katz",
    "wof:placetype":"venue"
},
  "geometry": {"coordinates":[-90.31834000000001,38.635605],"type":"Point"}
}