{
  "type": "Feature",
  "properties": {
    "iso:country":"US",
    "sg:address":"12732 Bennington Common Ln",
    "sg:city":"St Louis",
    "sg:classifiers":[
        {
            "category":"Wholesale",
            "subcategory":"Machinery & Supplies",
            "type":"Manufacturing & Wholesale Goods"
        },
        {
            "category":"Professional",
            "subcategory":"Management & Consulting",
            "type":"Services"
        }
    ],
    "sg:phone":"+1 314 434 4721",
    "sg:postcode":"63146",
    "sg:province":"MO",
    "sg:tags":[
        "consultant",
        "training",
        "industrial",
        "job",
        "equipment"
    ],
    "wof:name":"Custom Industrial Training",
    "wof:placetype":"venue"
},
  "geometry": {"coordinates":[-90.467229,38.695365],"type":"Point"}
}