{
  "type": "Feature",
  "properties": {
    "iso:country":"US",
    "sg:address":"704 West St",
    "sg:city":"Cassville",
    "sg:classifiers":[
        {
            "category":"Retail",
            "subcategory":"Repair Shop",
            "type":"Services"
        },
        {
            "category":"Home & Garden",
            "subcategory":"Furniture",
            "type":"Retail Goods"
        }
    ],
    "sg:phone":"+1 417 847 5556",
    "sg:postcode":"65625",
    "sg:province":"MO",
    "sg:tags":[
        "small",
        "appliance",
        "store"
    ],
    "sg:website":"http://www.neillshomestore.com",
    "wof:name":"Rick Neill Inc.",
    "wof:placetype":"venue"
},
  "geometry": {"coordinates":[-93.869176,36.678599],"type":"Point"}
}