{
  "type": "Feature",
  "properties": {
    "iso:country":"US",
    "sg:address":"607 W 6th St",
    "sg:city":"Lawson",
    "sg:classifiers":[
        {
            "category":"Fast Food",
            "type":"Food & Drink"
        },
        {
            "category":"Restaurant",
            "type":"Food & Drink"
        },
        {
            "category":"Food & Beverages",
            "subcategory":"Groceries & Convenience Stores",
            "type":"Retail Goods"
        }
    ],
    "sg:phone":"+1 816 628 6072",
    "sg:postcode":"64062",
    "sg:province":"MO",
    "sg:tags":[
        "shop",
        "american",
        "sandwich",
        "take"
    ],
    "sg:website":"http://www.subway.com",
    "wof:name":"Subway",
    "wof:placetype":"venue"
},
  "geometry": {"coordinates":[-94.209461,39.440312],"type":"Point"}
}