{
  "type": "Feature",
  "properties": {
    "iso:country":"US",
    "sg:address":"616 E 63 Ter",
    "sg:city":"Kansas City",
    "sg:classifiers":[
        {
            "category":"Shopping",
            "subcategory":"Pharmacy",
            "type":"Retail Goods"
        }
    ],
    "sg:phone":"+1 816 363 7726",
    "sg:postcode":"64110",
    "sg:province":"MO",
    "wof:name":"Getz Prescription Shops",
    "wof:placetype":"venue"
},
  "geometry": {"coordinates":[-94.58135900000001,39.012818],"type":"Point"}
}