{
  "type": "Feature",
  "properties": {
    "iso:country":"US",
    "sg:address":"121 N Main St",
    "sg:city":"Piedmont",
    "sg:classifiers":[
        {
            "category":"Shopping",
            "subcategory":"Florist",
            "type":"Retail Goods"
        }
    ],
    "sg:phone":"+1 573 223 4742",
    "sg:postcode":"63957",
    "sg:province":"MO",
    "wof:name":"Nana's Flowers From The Heart",
    "wof:placetype":"venue"
},
  "geometry": {"coordinates":[-90.695658,37.154834],"type":"Point"}
}