{
  "type": "Feature",
  "properties": {
    "iso:country":"US",
    "sg:address":"8100 Manchester Rd",
    "sg:city":"St Louis",
    "sg:classifiers":[
        {
            "category":"Restaurant",
            "type":"Food & Drink"
        }
    ],
    "sg:phone":"+1 314 646 1737",
    "sg:postcode":"63144",
    "sg:province":"MO",
    "sg:website":"www.popeyes.com",
    "wof:name":"Popeyes Chicken & Biscuits",
    "wof:placetype":"venue"
},
  "geometry": {"coordinates":[-90.33816299999999,38.611776],"type":"Point"}
}