{
  "type": "Feature",
  "properties": {
    "iso:country":"US",
    "sg:address":"584 SW Co Rd Bb",
    "sg:city":"Centerview",
    "sg:classifiers":[
        {
            "category":"Farming",
            "subcategory":"Livestock Farm",
            "type":"Manufacturing & Wholesale Goods"
        }
    ],
    "sg:phone":"+1 660 747 7080",
    "sg:postcode":"64019",
    "sg:province":"MO",
    "sg:tags":[
        "beef",
        "feedlot",
        "cattle"
    ],
    "wof:name":"Weigand Cattle & Grain",
    "wof:placetype":"venue"
},
  "geometry": {"coordinates":[-93.826768,38.677363],"type":"Point"}
}