{
  "type": "Feature",
  "properties": {
    "iso:country":"US",
    "sg:address":"1001 Lakeview Rd",
    "sg:city":"Mexico",
    "sg:classifiers":[
        {
            "category":"Manufacturing",
            "subcategory":"Buildings",
            "type":"Manufacturing & Wholesale Goods"
        },
        {
            "category":"Building & Trades",
            "subcategory":"Construction",
            "type":"Services"
        }
    ],
    "sg:phone":"+1 573 581 7050",
    "sg:postcode":"65265",
    "sg:province":"MO",
    "sg:tags":[
        "home",
        "builder",
        "contractor"
    ],
    "wof:name":"Montague Construction",
    "wof:placetype":"venue"
},
  "geometry": {"coordinates":[-91.893667,39.155995],"type":"Point"}
}