{
  "type": "Feature",
  "properties": {
    "iso:country":"US",
    "sg:address":"517 E New Melville Rd",
    "sg:city":"Willard",
    "sg:classifiers":[
        {
            "category":"Restaurant",
            "type":"Food & Drink"
        }
    ],
    "sg:phone":"+1 417 742 5081",
    "sg:postcode":"65781",
    "sg:province":"MO",
    "sg:tags":[
        "eating"
    ],
    "wof:name":"AAA Catering",
    "wof:placetype":"venue"
},
  "geometry": {"coordinates":[-93.42153999999999,37.2958],"type":"Point"}
}