{
  "type": "Feature",
  "properties": {
    "iso:country":"US",
    "sg:address":"1522 W 1st St",
    "sg:city":"West Plains",
    "sg:classifiers":[
        {
            "category":"Personal",
            "type":"Services"
        }
    ],
    "sg:phone":"+1 417 256 4082",
    "sg:postcode":"65775",
    "sg:province":"MO",
    "sg:tags":[
        "credit",
        "debt",
        "counseling"
    ],
    "wof:name":"Consumer Credit Counseling Svc",
    "wof:placetype":"venue"
},
  "geometry": {"coordinates":[-91.87217099999999,36.732485],"type":"Point"}
}