{
  "type": "Feature",
  "properties": {
    "iso:country":"US",
    "sg:address":"1343 NE Service Rd",
    "sg:city":"Warrenton",
    "sg:classifiers":[
        {
            "category":"Health Services",
            "subcategory":"Clinic",
            "type":"Services"
        },
        {
            "category":"Community Center",
            "type":"Public Place"
        }
    ],
    "sg:phone":"+1 636 377 2100",
    "sg:postcode":"63383",
    "sg:province":"MO",
    "sg:tags":[
        "medical"
    ],
    "wof:name":"Our Urgent Care",
    "wof:placetype":"venue"
},
  "geometry": {"coordinates":[-91.13051299999999,38.819192],"type":"Point"}
}