{
  "type": "Feature",
  "properties": {
    "iso:country":"US",
    "sg:address":"307 Lynual St",
    "sg:city":"Sikeston",
    "sg:classifiers":[
        {
            "category":"Retail",
            "subcategory":"Auto Repair",
            "type":"Services"
        }
    ],
    "sg:phone":"+1 573 471 7100",
    "sg:postcode":"63801",
    "sg:province":"MO",
    "sg:tags":[
        "truck"
    ],
    "wof:name":"Western Star Trucks",
    "wof:placetype":"venue"
},
  "geometry": {"coordinates":[-89.543467,36.869388],"type":"Point"}
}