{
  "type": "Feature",
  "properties": {
    "iso:country":"US",
    "sg:address":"201 N Hickman St",
    "sg:city":"Puxico",
    "sg:classifiers":[
        {
            "category":"Education",
            "subcategory":"Library",
            "type":"Public Place"
        }
    ],
    "sg:phone":"+1 573 222 3855",
    "sg:postcode":"63960",
    "sg:province":"MO",
    "wof:name":"Puxico City Library",
    "wof:placetype":"venue"
},
  "geometry": {"coordinates":[-90.156533,36.951294],"type":"Point"}
}