{
  "type": "Feature",
  "properties": {
    "iso:country":"US",
    "sg:address":"1854 Marietta St",
    "sg:city":"Cape Girardeau",
    "sg:classifiers":[
        {
            "category":"Manufacturing",
            "subcategory":"Buildings",
            "type":"Manufacturing & Wholesale Goods"
        }
    ],
    "sg:phone":"+1 573 334 1615",
    "sg:postcode":"63701",
    "sg:province":"MO",
    "sg:tags":[
        "prefabricated",
        "wood",
        "mfg"
    ],
    "wof:name":"Fireside Homes",
    "wof:placetype":"venue"
},
  "geometry": {"coordinates":[-89.544321,37.325649],"type":"Point"}
}