{
  "type": "Feature",
  "properties": {
    "iso:country":"US",
    "sg:address":"8100 W Florissant Ave",
    "sg:city":"Saint Louis",
    "sg:classifiers":[
        {
            "category":"Manufacturing",
            "subcategory":"Tools & Machinery",
            "type":"Manufacturing & Wholesale Goods"
        }
    ],
    "sg:phone":"+1 314 553 2293",
    "sg:postcode":"63136",
    "sg:province":"MO",
    "sg:tags":[
        "mfg"
    ],
    "wof:name":"U S Electrical Motors",
    "wof:placetype":"venue"
},
  "geometry": {"coordinates":[-90.277784,38.728851],"type":"Point"}
}