{
  "type": "Feature",
  "properties": {
    "iso:country":"US",
    "sg:address":"26741 Pike 244",
    "sg:city":"Clarksville",
    "sg:classifiers":[
        {
            "category":"Farming",
            "subcategory":"Farm",
            "type":"Manufacturing & Wholesale Goods"
        }
    ],
    "sg:phone":"+1 573 242 3332",
    "sg:postcode":"63336",
    "sg:province":"MO",
    "wof:name":"Holcim Farms",
    "wof:placetype":"venue"
},
  "geometry": {"coordinates":[-90.955962,39.350582],"type":"Point"}
}