{
  "type": "Feature",
  "properties": {
    "iso:country":"US",
    "sg:address":"16464 Burkhardt Pl",
    "sg:city":"Chesterfield",
    "sg:classifiers":[
        {
            "category":"Communications",
            "subcategory":"Radio Station",
            "type":"Services"
        }
    ],
    "sg:phone":"+1 636 530 7070",
    "sg:postcode":"63017",
    "sg:province":"MO",
    "sg:tags":[
        "broadcast"
    ],
    "wof:name":"K Y M C Radio",
    "wof:placetype":"venue"
},
  "geometry": {"coordinates":[-90.571279,38.655644],"type":"Point"}
}