{
  "type": "Feature",
  "properties": {
    "iso:country":"US",
    "sg:address":"7400 N Broadway",
    "sg:city":"St Louis",
    "sg:classifiers":[
        {
            "category":"Freight",
            "type":"Transportation"
        }
    ],
    "sg:phone":"+1 314 381 4400",
    "sg:postcode":"63147",
    "sg:province":"MO",
    "sg:tags":[
        "operator",
        "local",
        "trucking"
    ],
    "sg:website":"www.estesexpress.com",
    "wof:name":"Estes Express Lines Inc",
    "wof:placetype":"venue"
},
  "geometry": {"coordinates":[-90.22837699999999,38.700253],"type":"Point"}
}