{
  "type": "Feature",
  "properties": {
    "iso:country":"US",
    "sg:address":"2230 Highway 17",
    "sg:city":"Summersville",
    "sg:classifiers":[
        {
            "category":"Professional",
            "subcategory":"Management & Consulting",
            "type":"Services"
        }
    ],
    "sg:phone":"+1 417 932 4066",
    "sg:postcode":"65571",
    "sg:province":"MO",
    "sg:tags":[
        "farm"
    ],
    "wof:name":"Paul Derryberry",
    "wof:placetype":"venue"
},
  "geometry": {"coordinates":[-91.663192,37.137562],"type":"Point"}
}