{
  "type": "Feature",
  "properties": {
    "iso:country":"US",
    "sg:address":"2810 Whitener St",
    "sg:city":"Cape Girardeau",
    "sg:classifiers":[
        {
            "category":"Banks & Credit Unions",
            "subcategory":"Investment Brokerage",
            "type":"Services"
        }
    ],
    "sg:phone":"+1 573 334 9659",
    "sg:postcode":"63701",
    "sg:province":"MO",
    "sg:tags":[
        "security"
    ],
    "wof:name":"Edward Jones 25720",
    "wof:placetype":"venue"
},
  "geometry": {"coordinates":[-89.562136,37.309566],"type":"Point"}
}