{
  "type": "Feature",
  "properties": {
    "iso:country":"US",
    "sg:address":"16502 US Hwy 40",
    "sg:city":"Independence",
    "sg:classifiers":[
        {
            "category":"Autos & Motor Vehicles",
            "subcategory":"Fuel & Gas Station",
            "type":"Retail Goods"
        }
    ],
    "sg:phone":"+1 816 478 1056",
    "sg:postcode":"64055",
    "sg:province":"MO",
    "sg:tags":[
        "station",
        "gasoline"
    ],
    "wof:name":"Ultramar Diamond Shamrock",
    "wof:placetype":"venue"
},
  "geometry": {"coordinates":[-94.385386,39.034383],"type":"Point"}
}