{
  "type": "Feature",
  "properties": {
    "iso:country":"US",
    "sg:address":"205 5th St",
    "sg:city":"Purdy",
    "sg:classifiers":[
        {
            "category":"Social Services",
            "subcategory":"Child Care",
            "type":"Services"
        }
    ],
    "sg:phone":"+1 417 442 7835",
    "sg:postcode":"65734",
    "sg:province":"MO",
    "sg:tags":[
        "day"
    ],
    "wof:name":"Playground Day Care",
    "wof:placetype":"venue"
},
  "geometry": {"coordinates":[-93.918572,36.817427],"type":"Point"}
}