{
  "type": "Feature",
  "properties": {
    "iso:country":"US",
    "sg:address":"2850 S Broadway",
    "sg:city":"Saint Louis",
    "sg:classifiers":[
        {
            "category":"Freight",
            "type":"Transportation"
        }
    ],
    "sg:phone":"+1 314 577 1747",
    "sg:postcode":"63118",
    "sg:province":"MO",
    "sg:tags":[
        "local",
        "trucking"
    ],
    "wof:name":"Williamsburg Transport Inc",
    "wof:placetype":"venue"
},
  "geometry": {"coordinates":[-90.208271,38.597952],"type":"Point"}
}