{
  "type": "Feature",
  "properties": {
    "iso:country":"US",
    "sg:address":"31784 W 208th St",
    "sg:city":"Lawson",
    "sg:classifiers":[
        {
            "category":"Farming",
            "subcategory":"Livestock Farm",
            "type":"Manufacturing & Wholesale Goods"
        }
    ],
    "sg:phone":"+1 816 296 7936",
    "sg:postcode":"64062",
    "sg:province":"MO",
    "sg:tags":[
        "beef",
        "feedlot",
        "cattle"
    ],
    "wof:name":"Funk Jack & Lee Ann",
    "wof:placetype":"venue"
},
  "geometry": {"coordinates":[-94.184476,39.469108],"type":"Point"}
}