{
  "type": "Feature",
  "properties": {
    "iso:country":"US",
    "sg:address":"2525 Sublette Ave",
    "sg:city":"St Louis",
    "sg:classifiers":[
        {
            "category":"Freight",
            "type":"Transportation"
        }
    ],
    "sg:phone":"+1 314 645 0366",
    "sg:postcode":"63110",
    "sg:province":"MO",
    "sg:tags":[
        "delivery"
    ],
    "wof:name":"Expedited Services",
    "wof:placetype":"venue"
},
  "geometry": {"coordinates":[-90.28045899999999,38.612175],"type":"Point"}
}