{
  "type": "Feature",
  "properties": {
    "iso:country":"US",
    "sg:address":"5909 Cardinal Creek Dr",
    "sg:city":"Saint Louis",
    "sg:classifiers":[
        {
            "category":"Restaurant",
            "type":"Food & Drink"
        }
    ],
    "sg:phone":"+1 314 894 3373",
    "sg:postcode":"63129",
    "sg:province":"MO",
    "sg:tags":[
        "eating"
    ],
    "wof:name":"Pizza Perfect Ltd",
    "wof:placetype":"venue"
},
  "geometry": {"coordinates":[-90.31013799999999,38.45777],"type":"Point"}
}