{
  "type": "Feature",
  "properties": {
    "iso:country":"US",
    "sg:address":"7314 Raytown Rd Ste A",
    "sg:city":"Raytown",
    "sg:classifiers":[
        {
            "category":"Banks & Credit Unions",
            "subcategory":"Investment Brokerage",
            "type":"Services"
        },
        {
            "category":"Banks & Credit Unions",
            "subcategory":"Bank",
            "type":"Services"
        },
        {
            "category":"Banks & Credit Unions",
            "subcategory":"Financial Services",
            "type":"Services"
        }
    ],
    "sg:phone":"+1 816 353 3646",
    "sg:postcode":"64133",
    "sg:province":"MO",
    "sg:tags":[
        "advisory",
        "consultant",
        "broker",
        "planning",
        "bond",
        "stock"
    ],
    "wof:name":"Theel, George N - Edward Jones",
    "wof:placetype":"venue"
},
  "geometry": {"coordinates":[-94.46424399999999,38.990474],"type":"Point"}
}