{
  "type": "Feature",
  "properties": {
    "iso:country":"US",
    "sg:address":"17601 US Hwy 40",
    "sg:city":"Independence",
    "sg:classifiers":[
        {
            "category":"Home & Garden",
            "subcategory":"Building Materials",
            "type":"Retail Goods"
        }
    ],
    "sg:phone":"+1 816 478 0093",
    "sg:postcode":"64055",
    "sg:province":"MO",
    "sg:tags":[
        "paint"
    ],
    "sg:website":"www.davispaint.com",
    "wof:name":"Davis Paint Stores",
    "wof:placetype":"venue"
},
  "geometry": {"coordinates":[-94.370323,39.033809],"type":"Point"}
}