{
  "type": "Feature",
  "properties": {
    "iso:country":"US",
    "sg:address":"1606 W 75 St",
    "sg:city":"Kansas City",
    "sg:classifiers":[
        {
            "category":"Food & Beverages",
            "subcategory":"Liquor & Beverages",
            "type":"Retail Goods"
        }
    ],
    "sg:phone":"+1 816 361 5255",
    "sg:postcode":"64114",
    "sg:province":"MO",
    "wof:name":"Happy Hollow Wine & Liquor",
    "wof:placetype":"venue"
},
  "geometry": {"coordinates":[-94.607912,38.993022],"type":"Point"}
}