{
  "type": "Feature",
  "properties": {
    "iso:country":"US",
    "sg:address":"3522 Greenwood Blvd",
    "sg:city":"Saint Louis",
    "sg:classifiers":[
        {
            "category":"Bars & Pubs",
            "subcategory":"Nightclub",
            "type":"Food & Drink"
        }
    ],
    "sg:phone":"+1 314 645 6424",
    "sg:postcode":"63143",
    "sg:province":"MO",
    "sg:tags":[
        "nightlife"
    ],
    "wof:name":"Foley's",
    "wof:placetype":"venue"
},
  "geometry": {"coordinates":[-90.320396,38.605598],"type":"Point"}
}