{
  "type": "Feature",
  "properties": {
    "iso:country":"US",
    "sg:address":"233 Timber Tree Ct",
    "sg:city":"Ballwin",
    "sg:classifiers":[
        {
            "category":"Manufacturing",
            "subcategory":"Tools & Machinery",
            "type":"Manufacturing & Wholesale Goods"
        },
        {
            "category":"Industrial Area",
            "type":"Public Place"
        }
    ],
    "sg:phone":"+1 636 273 4352",
    "sg:postcode":"63011",
    "sg:province":"MO",
    "sg:tags":[
        "repair",
        "equipment-repairing",
        "machinery-rebuild"
    ],
    "wof:name":"Bowerman Packaging Machinery",
    "wof:placetype":"venue"
},
  "geometry": {"coordinates":[-90.61425,38.596371],"type":"Point"}
}