{
  "type": "Feature",
  "properties": {
    "iso:country":"US",
    "sg:address":"5939 Goodfellow Blvd",
    "sg:city":"Saint Louis",
    "sg:classifiers":[
        {
            "category":"Sports & Exercise",
            "subcategory":"Sports Center",
            "type":"Entertainment"
        }
    ],
    "sg:phone":"+1 314 381 5730",
    "sg:postcode":"63147",
    "sg:province":"MO",
    "sg:tags":[
        "amateur",
        "team"
    ],
    "wof:name":"New North Side Family Life Center",
    "wof:placetype":"venue"
},
  "geometry": {"coordinates":[-90.25369999999999,38.715302],"type":"Point"}
}