{
  "type": "Feature",
  "properties": {
    "iso:country":"US",
    "sg:address":"880 SE 200 Rd",
    "sg:city":"Clinton",
    "sg:classifiers":[
        {
            "category":"Professional",
            "subcategory":"Employment Agencies",
            "type":"Services"
        }
    ],
    "sg:phone":"+1 660 477 3264",
    "sg:postcode":"64735",
    "sg:province":"MO",
    "sg:tags":[
        "help",
        "supply"
    ],
    "wof:name":"Annies Cleaning Service",
    "wof:placetype":"venue"
},
  "geometry": {"coordinates":[-93.596056,38.332629],"type":"Point"}
}