{
  "type": "Feature",
  "properties": {
    "iso:country":"US",
    "sg:address":"8008 Carondelet Ave",
    "sg:city":"St Louis",
    "sg:classifiers":[
        {
            "category":"Professional",
            "subcategory":"Lawyer & Legal Services",
            "type":"Services"
        }
    ],
    "sg:phone":"+1 314 862 6262",
    "sg:postcode":"63105",
    "sg:province":"MO",
    "sg:tags":[
        "attorney"
    ],
    "wof:name":"Ryals Law Firm",
    "wof:placetype":"venue"
},
  "geometry": {"coordinates":[-90.3415,38.649117],"type":"Point"}
}