{
  "type": "Feature",
  "properties": {
    "iso:country":"US",
    "sg:address":"1404 Tabitha Ln",
    "sg:city":"Greenwood",
    "sg:classifiers":[
        {
            "category":"Building & Trades",
            "subcategory":"Construction",
            "type":"Services"
        }
    ],
    "sg:phone":"+1 816 365 7530",
    "sg:postcode":"64034",
    "sg:province":"MO",
    "sg:tags":[
        "residential",
        "contractor"
    ],
    "wof:name":"Sam Rhoades Building Co Inc",
    "wof:placetype":"venue"
},
  "geometry": {"coordinates":[-94.34563,38.839658],"type":"Point"}
}