{
  "type": "Feature",
  "properties": {
    "iso:country":"US",
    "sg:address":"18542 166th St",
    "sg:city":"Canton",
    "sg:classifiers":[
        {
            "category":"Health Services",
            "subcategory":"Doctor",
            "type":"Services"
        }
    ],
    "sg:phone":"+1 573 288 1086",
    "sg:postcode":"63435",
    "sg:province":"MO",
    "sg:tags":[
        "medical"
    ],
    "wof:name":"Lynne A Johnson MD PA",
    "wof:placetype":"venue"
},
  "geometry": {"coordinates":[-91.545134,40.15458],"type":"Point"}
}