{
  "type": "Feature",
  "properties": {
    "iso:country":"US",
    "sg:address":"14334 Liv 216",
    "sg:city":"Chillicothe",
    "sg:classifiers":[
        {
            "category":"Farming",
            "subcategory":"Livestock Farm",
            "type":"Manufacturing & Wholesale Goods"
        }
    ],
    "sg:phone":"+1 660 639 2531",
    "sg:postcode":"64601",
    "sg:province":"MO",
    "sg:tags":[
        "beef",
        "feedlot",
        "cattle"
    ],
    "wof:name":"Earl Benskin",
    "wof:placetype":"venue"
},
  "geometry": {"coordinates":[-93.508303,39.877887],"type":"Point"}
}