{
  "type": "Feature",
  "properties": {
    "iso:country":"US",
    "sg:address":"288 Hwy Ff",
    "sg:city":"Olean",
    "sg:classifiers":[
        {
            "category":"Retail",
            "subcategory":"Auto Repair",
            "type":"Services"
        }
    ],
    "sg:phone":"+1 573 392 3170",
    "sg:postcode":"65064",
    "sg:province":"MO",
    "sg:tags":[
        "body"
    ],
    "wof:name":"Upton Body Shop",
    "wof:placetype":"venue"
},
  "geometry": {"coordinates":[-92.512218,38.393084],"type":"Point"}
}