{
  "type": "Feature",
  "properties": {
    "iso:country":"US",
    "sg:address":"7362 Wallington Walk",
    "sg:city":"Saint Louis",
    "sg:classifiers":[
        {
            "category":"Professional",
            "type":"Services"
        }
    ],
    "sg:phone":"+1 314 382 4404",
    "sg:postcode":"63121",
    "sg:province":"MO",
    "wof:name":"Snw",
    "wof:placetype":"venue"
},
  "geometry": {"coordinates":[-90.29231799999999,38.71342],"type":"Point"}
}