{
  "type": "Feature",
  "properties": {
    "iso:country":"US",
    "sg:address":"6291 Hillsboro-House Springs Rd",
    "sg:city":"House Springs",
    "sg:classifiers":[
        {
            "category":"Home & Garden",
            "subcategory":"Building Materials",
            "type":"Retail Goods"
        },
        {
            "category":"Retail",
            "subcategory":"Auto Repair",
            "type":"Services"
        }
    ],
    "sg:phone":"+1 636 274 8845",
    "sg:postcode":"63051",
    "sg:province":"MO",
    "sg:tags":[
        "glass",
        "window",
        "installation",
        "plate"
    ],
    "wof:name":"Glass 4 U",
    "wof:placetype":"venue"
},
  "geometry": {"coordinates":[-90.56667899999999,38.356129],"type":"Point"}
}