{
  "type": "Feature",
  "properties": {
    "iso:country":"US",
    "sg:address":"1423 Pleasantview Dr",
    "sg:city":"Saint Charles",
    "sg:classifiers":[
        {
            "category":"Retail",
            "subcategory":"Repair Shop",
            "type":"Services"
        }
    ],
    "sg:phone":"+1 636 946 3906",
    "sg:postcode":"63303",
    "sg:province":"MO",
    "sg:tags":[
        "refrigeration"
    ],
    "wof:name":"K K Service Engineers",
    "wof:placetype":"venue"
},
  "geometry": {"coordinates":[-90.537779,38.778254],"type":"Point"}
}