{
  "type": "Feature",
  "properties": {
    "iso:country":"US",
    "sg:address":"1248 Hanley Industrial Court",
    "sg:city":"St. Louis",
    "sg:classifiers":[
        {
            "category":"Professional",
            "subcategory":"Advertising",
            "type":"Services"
        }
    ],
    "sg:phone":"+1 314 918 7500",
    "sg:postcode":"63144",
    "sg:province":"MO",
    "sg:tags":[
        "marketing",
        "business-development",
        "advertising",
        "online-marketing",
        "branding",
        "brand-marketing",
        "brand-development",
        "white-room"
    ],
    "sg:website":"http://www.orcastl.com",
    "wof:name":"The ORCA Partnership",
    "wof:placetype":"venue"
},
  "geometry": {"coordinates":[-90.339636,38.624912],"type":"Point"}
}