{
  "type": "Feature",
  "properties": {
    "iso:country":"US",
    "sg:address":"491 N Prairie St",
    "sg:city":"East Prairie",
    "sg:classifiers":[
        {
            "category":"Manufacturing",
            "subcategory":"Motor Vehicles & Parts",
            "type":"Manufacturing & Wholesale Goods"
        }
    ],
    "sg:phone":"+1 573 649 3628",
    "sg:postcode":"63855",
    "sg:province":"MO",
    "sg:tags":[
        "exhaust",
        "stacks",
        "system",
        "for",
        "mfg"
    ],
    "wof:name":"Thomure Muffler",
    "wof:placetype":"venue"
},
  "geometry": {"coordinates":[-90.112635,36.041703],"type":"Point"}
}