{
  "type": "Feature",
  "properties": {
    "iso:country":"US",
    "sg:address":"4000 N Oak Fwy",
    "sg:city":"Kansas City",
    "sg:classifiers":[
        {
            "category":"Restaurant",
            "type":"Food & Drink"
        }
    ],
    "sg:phone":"+1 816 452 2149",
    "sg:postcode":"64116",
    "sg:province":"MO",
    "wof:name":"In-A-Tub Inc",
    "wof:placetype":"venue"
},
  "geometry": {"coordinates":[-94.576764,39.168503],"type":"Point"}
}