{
  "type": "Feature",
  "properties": {
    "iso:country":"US",
    "sg:address":"3921 Baltimore Ave",
    "sg:city":"Kansas City",
    "sg:classifiers":[
        {
            "category":"Organizations",
            "subcategory":"Religious Organization",
            "type":"Services"
        }
    ],
    "sg:phone":"+1 816 531 1208",
    "sg:postcode":"64111",
    "sg:province":"MO",
    "wof:name":"First Calvary Baptist Church",
    "wof:placetype":"venue"
},
  "geometry": {"coordinates":[-94.5873,39.055543],"type":"Point"}
}