{
  "type": "Feature",
  "properties": {
    "iso:country":"US",
    "sg:address":"307 E Greenwood St",
    "sg:city":"Springfield",
    "sg:classifiers":[
        {
            "category":"Shopping",
            "subcategory":"Hobbies, Toys, & Games",
            "type":"Retail Goods"
        },
        {
            "category":"Shopping",
            "subcategory":"Crafts & Fabrics",
            "type":"Retail Goods"
        }
    ],
    "sg:phone":"+1 417 823 3965",
    "sg:postcode":"65807",
    "sg:province":"MO",
    "sg:tags":[
        "shop",
        "hobby",
        "model",
        "supply"
    ],
    "wof:name":"Hand Made Needle Craft",
    "wof:placetype":"venue"
},
  "geometry": {"coordinates":[-93.292154,37.163489],"type":"Point"}
}