{
  "type": "Feature",
  "properties": {
    "iso:country":"US",
    "sg:address":"216 N 5th St",
    "sg:city":"Thayer",
    "sg:classifiers":[
        {
            "category":"Bars & Pubs",
            "type":"Food & Drink"
        }
    ],
    "sg:phone":"+1 417 264 3595",
    "sg:postcode":"65791",
    "sg:province":"MO",
    "wof:name":"Irish Dream",
    "wof:placetype":"venue"
},
  "geometry": {"coordinates":[-91.54390600000001,36.52564],"type":"Point"}
}