{
  "type": "Feature",
  "properties": {
    "iso:country":"US",
    "sg:address":"1128 Lorien Ct",
    "sg:city":"Saint Louis",
    "sg:classifiers":[
        {
            "category":"Professional",
            "subcategory":"Management & Consulting",
            "type":"Services"
        }
    ],
    "sg:phone":"+1 314 835 9775",
    "sg:postcode":"63131",
    "sg:province":"MO",
    "wof:name":"Tms",
    "wof:placetype":"venue"
},
  "geometry": {"coordinates":[-90.42818699999999,38.596856],"type":"Point"}
}