{
  "type": "Feature",
  "properties": {
    "iso:country":"US",
    "sg:address":"6550 Progress Pkwy",
    "sg:city":"Cedar Hill",
    "sg:classifiers":[
        {
            "category":"Building & Trades",
            "subcategory":"Construction",
            "type":"Services"
        }
    ],
    "sg:phone":"+1 636 274 7404",
    "sg:postcode":"63016",
    "sg:province":"MO",
    "wof:name":"H & H Con Enhancements LLC",
    "wof:placetype":"venue"
},
  "geometry": {"coordinates":[-90.655418,38.356595],"type":"Point"}
}