{
  "type": "Feature",
  "properties": {
    "iso:country":"US",
    "sg:address":"1211 S Duchesne Dr",
    "sg:city":"St Charles",
    "sg:classifiers":[
        {
            "category":"Building & Trades",
            "subcategory":"Construction",
            "type":"Services"
        }
    ],
    "sg:phone":"+1 636 946 8839",
    "sg:postcode":"63301",
    "sg:province":"MO",
    "sg:tags":[
        "dwelling",
        "family",
        "speculative",
        "general",
        "contractor",
        "builder"
    ],
    "wof:name":"Burkemper Construction",
    "wof:placetype":"venue"
},
  "geometry": {"coordinates":[-90.51555999999999,38.786529],"type":"Point"}
}