{
  "type": "Feature",
  "properties": {
    "iso:country":"US",
    "sg:address":"1215 Boyd St",
    "sg:city":"De Soto",
    "sg:classifiers":[
        {
            "category":"Organizations",
            "subcategory":"Religious Organization",
            "type":"Services"
        }
    ],
    "sg:phone":"+1 636 586 3218",
    "sg:postcode":"63020",
    "sg:province":"MO",
    "wof:name":"Landmark Missionary Baptist",
    "wof:placetype":"venue"
},
  "geometry": {"coordinates":[-90.566276,38.142365],"type":"Point"}
}