{
  "type": "Feature",
  "properties": {
    "iso:country":"US",
    "sg:address":"230 High St",
    "sg:city":"Pacific",
    "sg:classifiers":[
        {
            "category":"Retail",
            "subcategory":"Repair Shop",
            "type":"Services"
        }
    ],
    "sg:phone":"+1 636 257 6686",
    "sg:postcode":"63069",
    "sg:province":"MO",
    "sg:tags":[
        "electrical"
    ],
    "wof:name":"Giger Appliance",
    "wof:placetype":"venue"
},
  "geometry": {"coordinates":[-90.738123,38.489857],"type":"Point"}
}