{
  "type": "Feature",
  "properties": {
    "iso:country":"US",
    "sg:address":"207 Lee St",
    "sg:city":"Fulton",
    "sg:classifiers":[
        {
            "category":"Building & Trades",
            "subcategory":"Construction",
            "type":"Services"
        }
    ],
    "sg:phone":"+1 573 642 7962",
    "sg:postcode":"65251",
    "sg:province":"MO",
    "sg:tags":[
        "hanging",
        "contractor"
    ],
    "wof:name":"Sweede Painting",
    "wof:placetype":"venue"
},
  "geometry": {"coordinates":[-91.947245,38.838034],"type":"Point"}
}