{
  "type": "Feature",
  "properties": {
    "iso:country":"US",
    "sg:address":"535 Ghan Rd",
    "sg:city":"Clever",
    "sg:phone":"+1 417 743 3155",
    "sg:postcode":"65631",
    "sg:province":"MO",
    "sg:tags":[
        "equipment",
        "supply"
    ],
    "wof:name":"Ozarks Espresso Sales",
    "wof:placetype":"venue"
},
  "geometry": {"coordinates":[-93.411241,37.044553],"type":"Point"}
}