{
  "type": "Feature",
  "properties": {
    "iso:country":"US",
    "sg:address":"204 N Lincoln St",
    "sg:city":"Neosho",
    "sg:classifiers":[
        {
            "category":"Health Services",
            "subcategory":"Health Practitioner",
            "type":"Services"
        }
    ],
    "sg:phone":"+1 417 455 0907",
    "sg:postcode":"64850",
    "sg:province":"MO",
    "sg:tags":[
        "therapist",
        "physical"
    ],
    "wof:name":"Freeman Neosho Physical Thrpy",
    "wof:placetype":"venue"
},
  "geometry": {"coordinates":[-94.37553200000001,36.871893],"type":"Point"}
}