{
  "type": "Feature",
  "properties": {
    "iso:country":"US",
    "sg:address":"301 S Vandeventer Ave",
    "sg:city":"St Louis",
    "sg:classifiers":[
        {
            "category":"Wholesale",
            "subcategory":"Hardware",
            "type":"Manufacturing & Wholesale Goods"
        }
    ],
    "sg:phone":"+1 314 371 2773",
    "sg:postcode":"63110",
    "sg:province":"MO",
    "sg:tags":[
        "air",
        "parts",
        "conditioning",
        "supply"
    ],
    "wof:name":"United Refrigeration Inc",
    "wof:placetype":"venue"
},
  "geometry": {"coordinates":[-90.24305099999999,38.632559],"type":"Point"}
}