{
  "type": "Feature",
  "properties": {
    "iso:country":"US",
    "sg:address":"1409 Carriage Bridge Trl",
    "sg:city":"Ballwin",
    "sg:classifiers":[
        {
            "category":"Restaurant",
            "type":"Food & Drink"
        }
    ],
    "sg:phone":"+1 636 861 7002",
    "sg:postcode":"63021",
    "sg:province":"MO",
    "sg:tags":[
        "eating"
    ],
    "wof:name":"Levy Inc",
    "wof:placetype":"venue"
},
  "geometry": {"coordinates":[-90.51541400000001,38.557879],"type":"Point"}
}