{
  "type": "Feature",
  "properties": {
    "iso:country":"US",
    "sg:address":"115 E 69 St",
    "sg:city":"Kansas City",
    "sg:classifiers":[
        {
            "category":"Government",
            "subcategory":"Office",
            "type":"Public Place"
        }
    ],
    "sg:phone":"+1 816 452 5539",
    "sg:postcode":"64113",
    "sg:province":"MO",
    "sg:tags":[
        "executive"
    ],
    "wof:name":"Clay Como Village Cy Exec Off",
    "wof:placetype":"venue"
},
  "geometry": {"coordinates":[-94.587879,39.003138],"type":"Point"}
}