{
  "type": "Feature",
  "properties": {
    "iso:country":"US",
    "sg:address":"35 W Church St",
    "sg:city":"Aurora",
    "sg:classifiers":[
        {
            "category":"Wholesale",
            "subcategory":"Hardware",
            "type":"Manufacturing & Wholesale Goods"
        }
    ],
    "sg:phone":"+1 417 678 2440",
    "sg:postcode":"65605",
    "sg:province":"MO",
    "sg:tags":[
        "equipment",
        "heating",
        "system"
    ],
    "wof:name":"Richards Heating & Air Cond",
    "wof:placetype":"venue"
},
  "geometry": {"coordinates":[-93.72259200000001,36.970982],"type":"Point"}
}