{
  "type": "Feature",
  "properties": {
    "iso:country":"US",
    "sg:address":"401 SW Warns St",
    "sg:city":"Lees Summit",
    "sg:classifiers":[
        {
            "category":"Building & Trades",
            "subcategory":"Cleaning & Sanitation",
            "type":"Services"
        }
    ],
    "sg:phone":"+1 816 525 1522",
    "sg:postcode":"64063",
    "sg:province":"MO",
    "sg:tags":[
        "janitor"
    ],
    "wof:name":"TNC Cleaning Svc",
    "wof:placetype":"venue"
},
  "geometry": {"coordinates":[-94.380127,38.907933],"type":"Point"}
}