{
  "type": "Feature",
  "properties": {
    "iso:country":"US",
    "sg:address":"544 N New Ballas Rd",
    "sg:city":"Saint Louis",
    "sg:classifiers":[
        {
            "category":"Health Services",
            "subcategory":"Doctor",
            "type":"Services"
        }
    ],
    "sg:phone":"+1 314 569 1999",
    "sg:postcode":"63141",
    "sg:province":"MO",
    "sg:tags":[
        "medical"
    ],
    "wof:name":"Genetic Diagnostic Center",
    "wof:placetype":"venue"
},
  "geometry": {"coordinates":[-90.443235,38.665312],"type":"Point"}
}