{
  "type": "Feature",
  "properties": {
    "iso:country":"US",
    "sg:address":"16052 Swingley Ridge Rd",
    "sg:city":"Chesterfield",
    "sg:classifiers":[
        {
            "category":"Banks & Credit Unions",
            "subcategory":"Investment Brokerage",
            "type":"Services"
        }
    ],
    "sg:phone":"+1 636 733 7600",
    "sg:postcode":"63017",
    "sg:province":"MO",
    "sg:tags":[
        "security"
    ],
    "sg:website":"www.smithbarney.com",
    "wof:name":"Smith Barney",
    "wof:placetype":"venue"
},
  "geometry": {"coordinates":[-90.561677,38.654794],"type":"Point"}
}