{
  "type": "Feature",
  "properties": {
    "iso:country":"US",
    "sg:address":"6567 Co Rd 305",
    "sg:city":"Fulton",
    "sg:classifiers":[
        {
            "category":"Food & Beverages",
            "subcategory":"Specialty",
            "type":"Retail Goods"
        }
    ],
    "sg:phone":"+1 573 642 9415",
    "sg:postcode":"65251",
    "sg:province":"MO",
    "wof:name":"Herb People",
    "wof:placetype":"venue"
},
  "geometry": {"coordinates":[-92.013803,38.82305],"type":"Point"}
}