{
  "type": "Feature",
  "properties": {
    "iso:country":"US",
    "sg:address":"1310 N Main St",
    "sg:city":"Auxvasse",
    "sg:classifiers":[
        {
            "category":"Professional",
            "subcategory":"Business Services",
            "type":"Services"
        }
    ],
    "sg:phone":"+1 573 386 3594",
    "sg:postcode":"65231",
    "sg:province":"MO",
    "sg:tags":[
        "auction"
    ],
    "wof:name":"Wilkerson Auction Service",
    "wof:placetype":"venue"
},
  "geometry": {"coordinates":[-91.896744,39.026977],"type":"Point"}
}