{
  "type": "Feature",
  "properties": {
    "iso:country":"US",
    "sg:address":"13 E 3 St",
    "sg:city":"Kansas City",
    "sg:classifiers":[
        {
            "category":"Wholesale",
            "subcategory":"Fruits & Vegetables",
            "type":"Manufacturing & Wholesale Goods"
        }
    ],
    "sg:phone":"+1 816 221 8940",
    "sg:postcode":"64106",
    "sg:province":"MO",
    "wof:name":"Local Harvest",
    "wof:placetype":"venue"
},
  "geometry": {"coordinates":[-94.582284,39.11],"type":"Point"}
}