{
  "type": "Feature",
  "properties": {
    "iso:country":"US",
    "sg:address":"4001 N Kingshighway Blvd",
    "sg:city":"St Louis",
    "sg:classifiers":[
        {
            "category":"Retail",
            "subcategory":"Auto Rental",
            "type":"Services"
        }
    ],
    "sg:phone":"+1 314 381 8454",
    "sg:postcode":"63115",
    "sg:province":"MO",
    "sg:tags":[
        "renting",
        "truck",
        "leasing"
    ],
    "wof:name":"Ryder",
    "wof:placetype":"venue"
},
  "geometry": {"coordinates":[-90.24941699999999,38.679535],"type":"Point"}
}