{
  "type": "Feature",
  "properties": {
    "iso:country":"US",
    "sg:address":"9875 Litzsinger Rd",
    "sg:city":"Saint Louis",
    "sg:classifiers":[
        {
            "category":"Professional",
            "type":"Services"
        }
    ],
    "sg:phone":"+1 314 994 0771",
    "sg:postcode":"63124",
    "sg:province":"MO",
    "wof:name":"Andrew P Thome",
    "wof:placetype":"venue"
},
  "geometry": {"coordinates":[-90.388203,38.62549],"type":"Point"}
}