{
  "type": "Feature",
  "properties": {
    "iso:country":"US",
    "sg:address":"1582 Highway 28",
    "sg:city":"Owensville",
    "sg:classifiers":[
        {
            "category":"Real Estate",
            "subcategory":"Surveying",
            "type":"Services"
        }
    ],
    "sg:phone":"+1 573 437 3541",
    "sg:postcode":"65066",
    "sg:province":"MO",
    "sg:tags":[
        "appraiser"
    ],
    "wof:name":"Connie Smith",
    "wof:placetype":"venue"
},
  "geometry": {"coordinates":[-91.48467599999999,38.353534],"type":"Point"}
}