{
  "type": "Feature",
  "properties": {
    "iso:country":"US",
    "sg:address":"136 Dogwood Dr",
    "sg:city":"Ridgedale",
    "sg:classifiers":[
        {
            "category":"Insurance",
            "subcategory":"Hazard Insurance",
            "type":"Services"
        }
    ],
    "sg:phone":"+1 417 339 3119",
    "sg:postcode":"65739",
    "sg:province":"MO",
    "sg:tags":[
        "commercial",
        "business"
    ],
    "wof:name":"Trilakes Insurance",
    "wof:placetype":"venue"
},
  "geometry": {"coordinates":[-93.28902,36.530011],"type":"Point"}
}