{
  "type": "Feature",
  "properties": {
    "iso:country":"US",
    "sg:address":"29280 State Hwy Z",
    "sg:city":"La Grange",
    "sg:classifiers":[
        {
            "category":"Wholesale",
            "subcategory":"Farm Supplies",
            "type":"Manufacturing & Wholesale Goods"
        }
    ],
    "sg:phone":"+1 573 655 4404",
    "sg:postcode":"63448",
    "sg:province":"MO",
    "sg:tags":[
        "corn",
        "livestock"
    ],
    "wof:name":"Durst Bowman & Knoche Farms",
    "wof:placetype":"venue"
},
  "geometry": {"coordinates":[-91.561044,39.97037],"type":"Point"}
}