{
  "type": "Feature",
  "properties": {
    "iso:country":"US",
    "sg:address":"1540 Strawberry Glen Ct",
    "sg:city":"Ballwin",
    "sg:classifiers":[
        {
            "category":"Professional",
            "subcategory":"Accounting & Tax Preparation",
            "type":"Services"
        }
    ],
    "sg:phone":"+1 636 861 9800",
    "sg:postcode":"63021",
    "sg:province":"MO",
    "sg:tags":[
        "bookkeeping",
        "general"
    ],
    "wof:name":"Biz-Ease",
    "wof:placetype":"venue"
},
  "geometry": {"coordinates":[-90.523596,38.550284],"type":"Point"}
}