{
  "type": "Feature",
  "properties": {
    "iso:country":"US",
    "sg:address":"205 Henquin Dr",
    "sg:city":"St Louis",
    "sg:classifiers":[
        {
            "category":"Food & Beverages",
            "subcategory":"Candy",
            "type":"Retail Goods"
        }
    ],
    "sg:phone":"+1 314 524 7044",
    "sg:postcode":"63135",
    "sg:province":"MO",
    "sg:tags":[
        "confectionery"
    ],
    "wof:name":"C Ray Candy Store",
    "wof:placetype":"venue"
},
  "geometry": {"coordinates":[-90.317679,38.749095],"type":"Point"}
}