{
  "type": "Feature",
  "properties": {
    "iso:country":"US",
    "sg:address":"1763 E State Hwy K",
    "sg:city":"West Plains",
    "sg:classifiers":[
        {
            "category":"Retail",
            "subcategory":"Auto Repair",
            "type":"Services"
        }
    ],
    "sg:phone":"+1 417 256 9461",
    "sg:postcode":"65775",
    "sg:province":"MO",
    "sg:tags":[
        "exhaust"
    ],
    "wof:name":"Davidson Muffler",
    "wof:placetype":"venue"
},
  "geometry": {"coordinates":[-91.892122,36.727273],"type":"Point"}
}