{
  "type": "Feature",
  "properties": {
    "iso:country":"US",
    "sg:address":"5929 E 154th Ter",
    "sg:city":"Grandview",
    "sg:classifiers":[
        {
            "category":"Wholesale",
            "subcategory":"Machinery & Supplies",
            "type":"Manufacturing & Wholesale Goods"
        }
    ],
    "sg:phone":"+1 816 318 9531",
    "sg:postcode":"64030",
    "sg:province":"MO",
    "sg:tags":[
        "equipment",
        "construction",
        "parts",
        "related",
        "sup"
    ],
    "wof:name":"Berry Companies Inc",
    "wof:placetype":"venue"
},
  "geometry": {"coordinates":[-94.527637,38.845084],"type":"Point"}
}