{
  "type": "Feature",
  "properties": {
    "iso:country":"US",
    "sg:address":"865 N Kingshighway St",
    "sg:city":"Cape Girardeau",
    "sg:classifiers":[
        {
            "category":"Personal",
            "subcategory":"Beauty Salon",
            "type":"Services"
        }
    ],
    "sg:phone":"+1 573 335 2588",
    "sg:postcode":"63701",
    "sg:province":"MO",
    "wof:name":"Michele's Place",
    "wof:placetype":"venue"
},
  "geometry": {"coordinates":[-89.555908,37.318657],"type":"Point"}
}