{
  "type": "Feature",
  "properties": {
    "iso:country":"US",
    "sg:address":"544 S D St",
    "sg:city":"Poplar Bluff",
    "sg:classifiers":[
        {
            "category":"Professional",
            "subcategory":"Computer Services",
            "type":"Services"
        }
    ],
    "sg:phone":"+1 573 686 2017",
    "sg:postcode":"63901",
    "sg:province":"MO",
    "sg:tags":[
        "repair"
    ],
    "wof:name":"Busy Bee Home Computer Repair",
    "wof:placetype":"venue"
},
  "geometry": {"coordinates":[-90.387545,36.75051],"type":"Point"}
}