{
  "type": "Feature",
  "properties": {
    "iso:country":"US",
    "sg:address":"9246 State Hwy 51",
    "sg:city":"Broseley",
    "sg:classifiers":[
        {
            "category":"Organizations",
            "subcategory":"Religious Organization",
            "type":"Services"
        }
    ],
    "sg:phone":"+1 573 328 9993",
    "sg:postcode":"63932",
    "sg:province":"MO",
    "sg:tags":[
        "church"
    ],
    "wof:name":"Broseley Community Church",
    "wof:placetype":"venue"
},
  "geometry": {"coordinates":[-90.243354,36.678055],"type":"Point"}
}