{
  "type": "Feature",
  "properties": {
    "iso:country":"US",
    "sg:address":"401 State Hwy 5",
    "sg:city":"Camdenton",
    "sg:classifiers":[
        {
            "category":"Building & Trades",
            "subcategory":"Plumbing",
            "type":"Services"
        }
    ],
    "sg:phone":"+1 573 317 1762",
    "sg:postcode":"65020",
    "sg:province":"MO",
    "sg:tags":[
        "heating",
        "contractor"
    ],
    "wof:name":"Fazio's Heating & Cooling",
    "wof:placetype":"venue"
},
  "geometry": {"coordinates":[-92.75730299999999,38.016763],"type":"Point"}
}