{
  "type": "Feature",
  "properties": {
    "iso:country":"US",
    "sg:address":"2424 N Outer Rd",
    "sg:city":"St Charles",
    "sg:classifiers":[
        {
            "category":"Insurance",
            "subcategory":"Insurance Agent",
            "type":"Services"
        }
    ],
    "sg:phone":"+1 636 441 5780",
    "sg:postcode":"63303",
    "sg:province":"MO",
    "wof:name":"Shelter Insurance",
    "wof:placetype":"venue"
},
  "geometry": {"coordinates":[-90.54397,38.759092],"type":"Point"}
}