{
  "type": "Feature",
  "properties": {
    "iso:country":"US",
    "sg:address":"8220 Delmar Blvd",
    "sg:city":"Saint Louis",
    "sg:classifiers":[
        {
            "category":"Social Services",
            "type":"Services"
        }
    ],
    "sg:phone":"+1 314 997 1110",
    "sg:postcode":"63124",
    "sg:province":"MO",
    "wof:name":"Benefit Counselors Inc",
    "wof:placetype":"venue"
},
  "geometry": {"coordinates":[-90.350616,38.660507],"type":"Point"}
}