{
  "type": "Feature",
  "properties": {
    "iso:country":"US",
    "sg:address":"531 Stewart Cir",
    "sg:city":"Washington",
    "sg:classifiers":[
        {
            "category":"Restaurant",
            "type":"Food & Drink"
        }
    ],
    "sg:phone":"+1 636 390 0644",
    "sg:postcode":"63090",
    "sg:province":"MO",
    "sg:tags":[
        "american"
    ],
    "wof:name":"Lion's Choice",
    "wof:placetype":"venue"
},
  "geometry": {"coordinates":[-91.012727,38.538974],"type":"Point"}
}