{
  "type": "Feature",
  "properties": {
    "iso:country":"US",
    "sg:address":"1361 State Highway 14",
    "sg:city":"Nixa",
    "sg:classifiers":[
        {
            "category":"Health Services",
            "subcategory":"Nursing And Care Facility",
            "type":"Services"
        },
        {
            "category":"Health Services",
            "subcategory":"Health Practitioner",
            "type":"Services"
        },
        {
            "category":"Health Services",
            "subcategory":"Chiropractor",
            "type":"Services"
        }
    ],
    "sg:phone":"+1 417 725 6655",
    "sg:postcode":"65714",
    "sg:province":"MO",
    "sg:tags":[
        "physician",
        "management",
        "pain",
        "naturopathic",
        "chiropractic",
        "nd",
        "acupuncture",
        "medicine",
        "alternative"
    ],
    "sg:website":"http://www.gentlechiropractor.com",
    "wof:name":"Chiropractor Plus",
    "wof:placetype":"venue"
},
  "geometry": {"coordinates":[-93.322589,37.043625],"type":"Point"}
}