{
  "type": "Feature",
  "properties": {
    "iso:country":"US",
    "sg:address":"2552 US Hwy 67",
    "sg:city":"Florissant",
    "sg:classifiers":[
        {
            "category":"Professional",
            "subcategory":"Accounting & Tax Preparation",
            "type":"Services"
        }
    ],
    "sg:phone":"+1 314 830 3737",
    "sg:postcode":"63033",
    "sg:province":"MO",
    "sg:tags":[
        "return",
        "filing"
    ],
    "wof:name":"H & R Block Tax Svc",
    "wof:placetype":"venue"
},
  "geometry": {"coordinates":[-90.30802799999999,38.804158],"type":"Point"}
}