{
  "type": "Feature",
  "properties": {
    "iso:country":"US",
    "sg:address":"214 S Broadway",
    "sg:city":"Salisbury",
    "sg:classifiers":[
        {
            "category":"Shopping",
            "subcategory":"Discount & Variety Stores",
            "type":"Retail Goods"
        }
    ],
    "sg:phone":"+1 660 388 6056",
    "sg:postcode":"65281",
    "sg:province":"MO",
    "sg:website":"http://www.duckwall.com",
    "wof:name":"Alco Discount",
    "wof:placetype":"venue"
},
  "geometry": {"coordinates":[-92.801406,39.423518],"type":"Point"}
}