{
  "type": "Feature",
  "properties": {
    "iso:country":"US",
    "sg:address":"1926 Chouteau Ave",
    "sg:city":"Saint Louis",
    "sg:classifiers":[
        {
            "category":"Professional",
            "subcategory":"Lawyer & Legal Services",
            "type":"Services"
        }
    ],
    "sg:phone":"+1 314 621 2900",
    "sg:postcode":"63103",
    "sg:province":"MO",
    "wof:name":"Haber Anna E.",
    "wof:placetype":"venue"
},
  "geometry": {"coordinates":[-90.21141900000001,38.620631],"type":"Point"}
}