{
  "type": "Feature",
  "properties": {
    "iso:country":"US",
    "sg:address":"807 N Elliott Ave",
    "sg:city":"Aurora",
    "sg:classifiers":[
        {
            "category":"Retail",
            "subcategory":"Laundry & Dry Cleaning",
            "type":"Services"
        }
    ],
    "sg:phone":"+1 417 678 0640",
    "sg:postcode":"65605",
    "sg:province":"MO",
    "sg:tags":[
        "laundries-self"
    ],
    "wof:name":"Red Dawg Laundry",
    "wof:placetype":"venue"
},
  "geometry": {"coordinates":[-93.71758,36.983882],"type":"Point"}
}