{
  "type": "Feature",
  "properties": {
    "iso:country":"US",
    "sg:address":"12066 Charter House Ln",
    "sg:city":"St Louis",
    "sg:classifiers":[
        {
            "category":"Building & Trades",
            "subcategory":"Construction",
            "type":"Services"
        }
    ],
    "sg:phone":"+1 314 997 8700",
    "sg:postcode":"63146",
    "sg:province":"MO",
    "sg:tags":[
        "roofing",
        "contractor"
    ],
    "wof:name":"Georgetown Roofing",
    "wof:placetype":"venue"
},
  "geometry": {"coordinates":[-90.44262999999999,38.675241],"type":"Point"}
}