{
  "type": "Feature",
  "properties": {
    "iso:country":"US",
    "sg:address":"2580 High St",
    "sg:city":"Sarcoxie",
    "sg:classifiers":[
        {
            "category":"Autos & Motor Vehicles",
            "subcategory":"Fuel & Gas Station",
            "type":"Retail Goods"
        }
    ],
    "sg:phone":"+1 417 548 6164",
    "sg:postcode":"64862",
    "sg:province":"MO",
    "sg:tags":[
        "oil"
    ],
    "wof:name":"Double Diamond Citgo",
    "wof:placetype":"venue"
},
  "geometry": {"coordinates":[-94.105149,37.077241],"type":"Point"}
}