{
  "type": "Feature",
  "properties": {
    "iso:country":"US",
    "sg:address":"208 S Elm St",
    "sg:city":"Dixon",
    "sg:classifiers":[
        {
            "category":"Building & Trades",
            "subcategory":"Construction",
            "type":"Services"
        }
    ],
    "sg:phone":"+1 573 759 6907",
    "sg:postcode":"65459",
    "sg:province":"MO",
    "sg:tags":[
        "handyman"
    ],
    "wof:name":"Smith's Golf Cart Repair",
    "wof:placetype":"venue"
},
  "geometry": {"coordinates":[-92.09678700000001,37.994479],"type":"Point"}
}