{
  "type": "Feature",
  "properties": {
    "iso:country":"US",
    "sg:address":"7115 NW Barry Rd",
    "sg:city":"Kansas City",
    "sg:classifiers":[
        {
            "category":"Insurance",
            "subcategory":"Insurance Agent",
            "type":"Services"
        }
    ],
    "sg:phone":"+1 816 587 5466",
    "sg:postcode":"64153",
    "sg:province":"MO",
    "wof:name":"State Farm Insurance",
    "wof:placetype":"venue"
},
  "geometry": {"coordinates":[-94.660409,39.246833],"type":"Point"}
}