{
  "type": "Feature",
  "properties": {
    "iso:country":"US",
    "sg:address":"202 Sun Swept Dr",
    "sg:city":"Troy",
    "sg:classifiers":[
        {
            "category":"Personal",
            "subcategory":"Nail Salon",
            "type":"Services"
        }
    ],
    "sg:phone":"+1 636 528 0411",
    "sg:postcode":"63379",
    "sg:province":"MO",
    "wof:name":"Nails By Caroline",
    "wof:placetype":"venue"
},
  "geometry": {"coordinates":[-91.027067,38.972219],"type":"Point"}
}