{
  "type": "Feature",
  "properties": {
    "iso:country":"US",
    "sg:address":"4126 7 Hills Dr",
    "sg:city":"Florissant",
    "sg:classifiers":[
        {
            "category":"Communications",
            "subcategory":"Film & Video Production",
            "type":"Services"
        },
        {
            "category":"Communications",
            "subcategory":"Television Station",
            "type":"Services"
        }
    ],
    "sg:phone":"+1 314 838 4126",
    "sg:postcode":"63033",
    "sg:province":"MO",
    "sg:tags":[
        "companies-film",
        "producer",
        "tv",
        "program",
        "radio",
        "distributor"
    ],
    "wof:name":"Oblate Media & Communication Corp",
    "wof:placetype":"venue"
},
  "geometry": {"coordinates":[-90.276213,38.776623],"type":"Point"}
}