{
  "type": "Feature",
  "properties": {
    "iso:country":"US",
    "sg:address":"29 Dalton Valley Dr",
    "sg:city":"Saint Peters",
    "sg:classifiers":[
        {
            "category":"Building & Trades",
            "subcategory":"Construction",
            "type":"Services"
        }
    ],
    "sg:phone":"+1 314 520 7700",
    "sg:postcode":"63376",
    "sg:province":"MO",
    "sg:tags":[
        "hanging",
        "contractor"
    ],
    "wof:name":"Lavelle Painting",
    "wof:placetype":"venue"
},
  "geometry": {"coordinates":[-90.679491,38.759584],"type":"Point"}
}