{
  "type": "Feature",
  "properties": {
    "iso:country":"US",
    "sg:address":"711 Old Ballas Rd",
    "sg:city":"Saint Louis",
    "sg:classifiers":[
        {
            "category":"Banks & Credit Unions",
            "subcategory":"Bank",
            "type":"Services"
        }
    ],
    "sg:phone":"+1 314 997 9320",
    "sg:postcode":"63141",
    "sg:province":"MO",
    "sg:tags":[
        "bus",
        "s"
    ],
    "wof:name":"A T & T Capital Holdings Inc",
    "wof:placetype":"venue"
},
  "geometry": {"coordinates":[-90.438613,38.670715],"type":"Point"}
}