{
  "type": "Feature",
  "properties": {
    "iso:country":"US",
    "sg:address":"730 US Hwy 50",
    "sg:city":"Knob Noster",
    "sg:classifiers":[
        {
            "category":"Real Estate",
            "subcategory":"Real Estate Agent",
            "type":"Services"
        }
    ],
    "sg:phone":"+1 660 747 2808",
    "sg:postcode":"65336",
    "sg:province":"MO",
    "sg:tags":[
        "appraiser"
    ],
    "wof:name":"Mid-West Appraisal Svc",
    "wof:placetype":"venue"
},
  "geometry": {"coordinates":[-93.60456600000001,38.77361],"type":"Point"}
}