{
  "type": "Feature",
  "properties": {
    "iso:country":"US",
    "sg:address":"2934 Marshall Ave",
    "sg:city":"St Louis",
    "sg:classifiers":[
        {
            "category":"Social Services",
            "type":"Services"
        }
    ],
    "sg:phone":"+1 314 644 6805",
    "sg:postcode":"63143",
    "sg:province":"MO",
    "sg:tags":[
        "organization",
        "welfare"
    ],
    "wof:name":"Maplewood Health Ministry",
    "wof:placetype":"venue"
},
  "geometry": {"coordinates":[-90.31643800000001,38.611095],"type":"Point"}
}