{
  "type": "Feature",
  "properties": {
    "iso:country":"US",
    "sg:address":"1814 Janie Ln",
    "sg:city":"Nixa",
    "sg:classifiers":[
        {
            "category":"Building & Trades",
            "subcategory":"Landscaping Services",
            "type":"Services"
        }
    ],
    "sg:phone":"+1 417 725 2203",
    "sg:postcode":"65714",
    "sg:province":"MO",
    "wof:name":"Professional Landscape Svcs",
    "wof:placetype":"venue"
},
  "geometry": {"coordinates":[-93.314712,37.082122],"type":"Point"}
}