{
  "type": "Feature",
  "properties": {
    "iso:country":"US",
    "sg:address":"1900 S Ventura Ave",
    "sg:city":"Springfield",
    "sg:classifiers":[
        {
            "category":"Sports & Exercise",
            "subcategory":"Gym",
            "type":"Entertainment"
        }
    ],
    "sg:phone":"+1 417 773 0039",
    "sg:postcode":"65804",
    "sg:province":"MO",
    "sg:tags":[
        "pilate"
    ],
    "wof:name":"Reach Pilates",
    "wof:placetype":"venue"
},
  "geometry": {"coordinates":[-93.24332200000001,37.176922],"type":"Point"}
}