{
  "type": "Feature",
  "properties": {
    "iso:country":"US",
    "sg:address":"6650 Old Hwy 21",
    "sg:city":"Barnhart",
    "sg:classifiers":[
        {
            "category":"Manufacturing",
            "subcategory":"Building Materials",
            "type":"Manufacturing & Wholesale Goods"
        }
    ],
    "sg:phone":"+1 636 942 3040",
    "sg:postcode":"63012",
    "sg:province":"MO",
    "sg:tags":[
        "cabinet"
    ],
    "wof:name":"Ev's Cabinet Shop",
    "wof:placetype":"venue"
},
  "geometry": {"coordinates":[-90.49831,38.35883],"type":"Point"}
}