{
  "type": "Feature",
  "properties": {
    "iso:country":"US",
    "sg:address":"611 Main St",
    "sg:city":"Cassville",
    "sg:classifiers":[
        {
            "category":"Personal",
            "subcategory":"Beauty Salon",
            "type":"Services"
        }
    ],
    "sg:phone":"+1 417 847 4720",
    "sg:postcode":"65625",
    "sg:province":"MO",
    "wof:name":"J & L Hair Fashions",
    "wof:placetype":"venue"
},
  "geometry": {"coordinates":[-93.87004899999999,36.675735],"type":"Point"}
}