{
  "type": "Feature",
  "properties": {
    "iso:country":"US",
    "sg:address":"62 NE Hwy CC",
    "sg:city":"Leeton",
    "sg:classifiers":[
        {
            "category":"Farming",
            "subcategory":"Farm",
            "type":"Manufacturing & Wholesale Goods"
        }
    ],
    "sg:phone":"+1 660 885 5157",
    "sg:postcode":"64761",
    "sg:province":"MO",
    "sg:tags":[
        "crop",
        "general"
    ],
    "wof:name":"Schmidli Farms",
    "wof:placetype":"venue"
},
  "geometry": {"coordinates":[-93.745172,38.524868],"type":"Point"}
}