{
  "type": "Feature",
  "properties": {
    "iso:country":"US",
    "sg:address":"704 Kansas Ave",
    "sg:city":"Montrose",
    "sg:classifiers":[
        {
            "category":"Building & Trades",
            "subcategory":"Construction",
            "type":"Services"
        }
    ],
    "sg:phone":"+1 660 693 4512",
    "sg:postcode":"64770",
    "sg:province":"MO",
    "sg:tags":[
        "company"
    ],
    "wof:name":"Stoddard Construction",
    "wof:placetype":"venue"
},
  "geometry": {"coordinates":[-93.98280200000001,38.262102],"type":"Point"}
}