{
  "type": "Feature",
  "properties": {
    "iso:country":"US",
    "sg:address":"7310 S Highway J",
    "sg:city":"Stockton",
    "sg:classifiers":[
        {
            "category":"Building & Trades",
            "subcategory":"Landscaping Services",
            "type":"Services"
        }
    ],
    "sg:phone":"+1 417 276 3550",
    "sg:postcode":"65785",
    "sg:province":"MO",
    "sg:tags":[
        "lawn"
    ],
    "wof:name":"Carson's Landscape & Design",
    "wof:placetype":"venue"
},
  "geometry": {"coordinates":[-93.74835299999999,37.784314],"type":"Point"}
}