{
  "type": "Feature",
  "properties": {
    "iso:country":"US",
    "sg:address":"1931 Belmont Pl",
    "sg:city":"Independence",
    "sg:classifiers":[
        {
            "category":"Retail",
            "subcategory":"Portrait Studio",
            "type":"Services"
        }
    ],
    "sg:phone":"+1 816 257 5242",
    "sg:postcode":"64057",
    "sg:province":"MO",
    "sg:tags":[
        "photo"
    ],
    "wof:name":"Duanes Photography",
    "wof:placetype":"venue"
},
  "geometry": {"coordinates":[-94.37362,39.081881],"type":"Point"}
}