{
  "type": "Feature",
  "properties": {
    "iso:country":"US",
    "sg:address":"801 S McArthur Ave",
    "sg:city":"Salem",
    "sg:classifiers":[
        {
            "category":"Government",
            "subcategory":"Office",
            "type":"Public Place"
        }
    ],
    "sg:phone":"+1 573 729 3250",
    "sg:postcode":"65560",
    "sg:province":"MO",
    "wof:name":"Dent County Fire Protection",
    "wof:placetype":"venue"
},
  "geometry": {"coordinates":[-91.54037099999999,37.637733],"type":"Point"}
}