{
  "type": "Feature",
  "properties": {
    "iso:country":"US",
    "sg:address":"111 S 2nd St",
    "sg:city":"Odessa",
    "sg:classifiers":[
        {
            "category":"Bars & Pubs",
            "type":"Food & Drink"
        }
    ],
    "sg:phone":"+1 816 633 7433",
    "sg:postcode":"64076",
    "sg:province":"MO",
    "wof:name":"Woody's Tavern Inc",
    "wof:placetype":"venue"
},
  "geometry": {"coordinates":[-93.95363999999999,39.000327],"type":"Point"}
}