{
  "type": "Feature",
  "properties": {
    "iso:country":"US",
    "sg:address":"1101 NE 115th St",
    "sg:city":"Kansas City",
    "sg:classifiers":[
        {
            "category":"Building & Trades",
            "subcategory":"Landscaping Services",
            "type":"Services"
        }
    ],
    "sg:phone":"+1 816 734 0090",
    "sg:postcode":"64155",
    "sg:province":"MO",
    "sg:tags":[
        "lawn",
        "maintenance",
        "grounds"
    ],
    "wof:name":"Dave's Complete Lawn Care",
    "wof:placetype":"venue"
},
  "geometry": {"coordinates":[-94.56636399999999,39.301718],"type":"Point"}
}