{
  "type": "Feature",
  "properties": {
    "iso:country":"US",
    "sg:address":"3269 Morganford Rd",
    "sg:city":"St Louis",
    "sg:classifiers":[
        {
            "category":"Bars & Pubs",
            "subcategory":"Nightclub",
            "type":"Food & Drink"
        }
    ],
    "sg:phone":"+1 314 776 9600",
    "sg:postcode":"63116",
    "sg:province":"MO",
    "sg:tags":[
        "nightlife"
    ],
    "wof:name":"Digger O'dell's Irish Pub",
    "wof:placetype":"venue"
},
  "geometry": {"coordinates":[-90.262279,38.598771],"type":"Point"}
}