{
  "type": "Feature",
  "properties": {
    "iso:country":"US",
    "sg:address":"9715 Ridge Ave",
    "sg:city":"Saint Louis",
    "sg:classifiers":[
        {
            "category":"Banks & Credit Unions",
            "subcategory":"Financial Services",
            "type":"Services"
        }
    ],
    "sg:phone":"+1 314 423 2270",
    "sg:postcode":"63114",
    "sg:province":"MO",
    "sg:tags":[
        "investment",
        "real estate"
    ],
    "wof:name":"Community Sccess Invstmnts LLC",
    "wof:placetype":"venue"
},
  "geometry": {"coordinates":[-90.373304,38.690794],"type":"Point"}
}