{
  "type": "Feature",
  "properties": {
    "iso:country":"US",
    "sg:address":"413 Bayview Dr",
    "sg:city":"Raymore",
    "sg:classifiers":[
        {
            "category":"Building & Trades",
            "subcategory":"Construction",
            "type":"Services"
        }
    ],
    "sg:phone":"+1 816 348 7891",
    "sg:postcode":"64083",
    "sg:province":"MO",
    "wof:name":"Patterson Remodeling Contr",
    "wof:placetype":"venue"
},
  "geometry": {"coordinates":[-94.46749800000001,38.799872],"type":"Point"}
}