{
  "type": "Feature",
  "properties": {
    "iso:country":"US",
    "sg:address":"111 N Main St",
    "sg:city":"Craig",
    "sg:classifiers":[
        {
            "category":"Building & Trades",
            "subcategory":"Electrical",
            "type":"Services"
        }
    ],
    "sg:phone":"+1 660 683 5560",
    "sg:postcode":"64437",
    "sg:province":"MO",
    "sg:tags":[
        "electric",
        "contractor"
    ],
    "wof:name":"Wright Electric & Hardware",
    "wof:placetype":"venue"
},
  "geometry": {"coordinates":[-95.375737,40.193181],"type":"Point"}
}