{
  "type": "Feature",
  "properties": {
    "iso:country":"US",
    "sg:address":"7302 Fairfax Ct",
    "sg:city":"Barnhart",
    "sg:classifiers":[
        {
            "category":"Professional",
            "subcategory":"Business Services",
            "type":"Services"
        }
    ],
    "sg:phone":"+1 314 845 3574",
    "sg:postcode":"63012",
    "sg:province":"MO",
    "wof:name":"S&N Interiors",
    "wof:placetype":"venue"
},
  "geometry": {"coordinates":[-90.409318,38.337275],"type":"Point"}
}