{
  "type": "Feature",
  "properties": {
    "iso:country":"US",
    "sg:address":"11902 Continental Dr",
    "sg:city":"St Louis",
    "sg:classifiers":[
        {
            "category":"Personal",
            "subcategory":"Beauty Salon",
            "type":"Services"
        }
    ],
    "sg:phone":"+1 314 741 1720",
    "sg:postcode":"63138",
    "sg:province":"MO",
    "wof:name":"Diva's Style",
    "wof:placetype":"venue"
},
  "geometry": {"coordinates":[-90.229198,38.790925],"type":"Point"}
}