{
  "type": "Feature",
  "properties": {
    "iso:country":"US",
    "sg:address":"207 E Pine St",
    "sg:city":"Waverly",
    "sg:phone":"+1 660 493 2344",
    "sg:postcode":"64096",
    "sg:province":"MO",
    "sg:tags":[
        "farm",
        "corn",
        "wheat",
        "soybean"
    ],
    "wof:name":"Reker Merlyn Farm",
    "wof:placetype":"venue"
},
  "geometry": {"coordinates":[-93.51622399999999,39.20643],"type":"Point"}
}