{
  "type": "Feature",
  "properties": {
    "iso:country":"US",
    "sg:address":"33 N Ellis St",
    "sg:city":"Cape Girardeau",
    "sg:classifiers":[
        {
            "category":"Shopping",
            "type":"Retail Goods"
        },
        {
            "category":"Building & Trades",
            "subcategory":"Construction",
            "type":"Services"
        }
    ],
    "sg:phone":"+1 573 335 0416",
    "sg:postcode":"63701",
    "sg:province":"MO",
    "sg:tags":[
        "designer",
        "contractor",
        "pool",
        "dealer",
        "merchandise",
        "swimming"
    ],
    "wof:name":"Solar Pools & Chemicals",
    "wof:placetype":"venue"
},
  "geometry": {"coordinates":[-89.528519,37.30473],"type":"Point"}
}