{
  "type": "Feature",
  "properties": {
    "iso:country":"US",
    "sg:address":"3700 Natural Bridge Ave",
    "sg:city":"Saint Louis",
    "sg:classifiers":[
        {
            "category":"Real Estate",
            "subcategory":"Real Estate Operator",
            "type":"Services"
        }
    ],
    "sg:phone":"+1 314 535 6646",
    "sg:postcode":"63107",
    "sg:province":"MO",
    "sg:tags":[
        "apartment"
    ],
    "wof:name":"Allen III Motors",
    "wof:placetype":"venue"
},
  "geometry": {"coordinates":[-90.218803,38.662201],"type":"Point"}
}