{
  "type": "Feature",
  "properties": {
    "iso:country":"US",
    "sg:address":"10455 Blue Ridge Blvd",
    "sg:city":"Kansas City",
    "sg:classifiers":[
        {
            "category":"Restaurant",
            "type":"Food & Drink"
        }
    ],
    "sg:menulink":"http://www.allmenus.com/mo/royal-oaks/201659-sonic/menu/",
    "sg:phone":"+1 816 761 1101",
    "sg:postcode":"64134",
    "sg:province":"MO",
    "sg:tags":[
        "burger",
        "american"
    ],
    "wof:name":"Sonic",
    "wof:placetype":"venue"
},
  "geometry": {"coordinates":[-94.508216,38.934564],"type":"Point"}
}