{
  "type": "Feature",
  "properties": {
    "iso:country":"US",
    "sg:address":"619 Elm St",
    "sg:city":"Chillicothe",
    "sg:classifiers":[
        {
            "category":"Home & Garden",
            "subcategory":"Household Appliances",
            "type":"Retail Goods"
        }
    ],
    "sg:phone":"+1 660 646 3973",
    "sg:postcode":"64601",
    "sg:province":"MO",
    "sg:tags":[
        "refrigerator",
        "freezer"
    ],
    "wof:name":"Livingston County TV & Appl",
    "wof:placetype":"venue"
},
  "geometry": {"coordinates":[-93.55136,39.794124],"type":"Point"}
}