{
  "type": "Feature",
  "properties": {
    "iso:country":"US",
    "sg:address":"3560 E Evergreen St",
    "sg:city":"Springfield",
    "sg:classifiers":[
        {
            "category":"Manufacturing",
            "subcategory":"Buildings",
            "type":"Manufacturing & Wholesale Goods"
        },
        {
            "category":"Building & Trades",
            "subcategory":"Construction",
            "type":"Services"
        }
    ],
    "sg:phone":"+1 417 868 0017",
    "sg:postcode":"65803",
    "sg:province":"MO",
    "sg:tags":[
        "industrial",
        "builder",
        "contractor",
        "contractors-commercial",
        "home",
        "masonry",
        "mason"
    ],
    "sg:website":"http://www.cecobuildings.com",
    "wof:name":"Msi-Masonry Structures Inc",
    "wof:placetype":"venue"
},
  "geometry": {"coordinates":[-93.218172,37.249576],"type":"Point"}
}