{
  "type": "Feature",
  "properties": {
    "iso:country":"US",
    "sg:address":"1315 Cherokee St",
    "sg:city":"Saint Louis",
    "sg:classifiers":[
        {
            "category":"Wholesale",
            "subcategory":"Tobacco Products",
            "type":"Manufacturing & Wholesale Goods"
        }
    ],
    "sg:phone":"+1 314 773 5200",
    "sg:postcode":"63118",
    "sg:province":"MO",
    "sg:tags":[
        "cigarette",
        "cigar",
        "store",
        "candy"
    ],
    "sg:website":"www.moundcityind.com",
    "wof:name":"Mound City Industries Inc",
    "wof:placetype":"venue"
},
  "geometry": {"coordinates":[-90.21639999999999,38.592098],"type":"Point"}
}