{
  "type": "Feature",
  "properties": {
    "iso:country":"US",
    "sg:address":"96 N Franklin St",
    "sg:city":"Kingston",
    "sg:classifiers":[
        {
            "category":"Insurance",
            "subcategory":"Insurance Agent",
            "type":"Services"
        }
    ],
    "sg:phone":"+1 816 586 3531",
    "sg:postcode":"64650",
    "sg:province":"MO",
    "wof:name":"Caldwell County Mutual Ins Co",
    "wof:placetype":"venue"
},
  "geometry": {"coordinates":[-94.03770799999999,39.643428],"type":"Point"}
}