{
  "type": "Feature",
  "properties": {
    "iso:country":"US",
    "sg:address":"1244 US Hwy 60",
    "sg:city":"Republic",
    "sg:classifiers":[
        {
            "category":"Real Estate",
            "subcategory":"Real Estate Services",
            "type":"Services"
        }
    ],
    "sg:phone":"+1 417 732 9883",
    "sg:postcode":"65738",
    "sg:province":"MO",
    "sg:tags":[
        "company",
        "abstract",
        "title"
    ],
    "wof:name":"Great American Title Inc",
    "wof:placetype":"venue"
},
  "geometry": {"coordinates":[-93.458125,37.131461],"type":"Point"}
}