{
  "type": "Feature",
  "properties": {
    "iso:country":"US",
    "sg:address":"19140 Gum Rd",
    "sg:city":"Granby",
    "sg:classifiers":[
        {
            "category":"Professional",
            "subcategory":"Business Services",
            "type":"Services"
        }
    ],
    "sg:phone":"+1 417 472 3267",
    "sg:postcode":"64844",
    "sg:province":"MO",
    "sg:tags":[
        "auction",
        "auctioneer"
    ],
    "wof:name":"Fred Hansford Auctioneer",
    "wof:placetype":"venue"
},
  "geometry": {"coordinates":[-94.296292,36.9474],"type":"Point"}
}