{
  "type": "Feature",
  "properties": {
    "iso:country":"US",
    "sg:address":"549 Ridge Rd",
    "sg:city":"Seymour",
    "sg:classifiers":[
        {
            "category":"Social Services",
            "subcategory":"Child Care",
            "type":"Services"
        }
    ],
    "sg:phone":"+1 417 935 4458",
    "sg:postcode":"65706",
    "sg:province":"MO",
    "sg:tags":[
        "day"
    ],
    "wof:name":"Step Ahead Pre-School",
    "wof:placetype":"venue"
},
  "geometry": {"coordinates":[-92.995007,37.271394],"type":"Point"}
}