{
  "type": "Feature",
  "properties": {
    "iso:country":"US",
    "sg:address":"4002 S Jackson Ave",
    "sg:city":"Joplin",
    "sg:classifiers":[
        {
            "category":"Farming",
            "subcategory":"Farm & Veterinary Services",
            "type":"Manufacturing & Wholesale Goods"
        }
    ],
    "sg:phone":"+1 417 623 4246",
    "sg:postcode":"64804",
    "sg:province":"MO",
    "sg:tags":[
        "livestock"
    ],
    "wof:name":"Broadwater Farms",
    "wof:placetype":"venue"
},
  "geometry": {"coordinates":[-94.52134,37.045065],"type":"Point"}
}