{
  "type": "Feature",
  "properties": {
    "iso:country":"US",
    "sg:address":"1514 SW 6 St",
    "sg:city":"Lees Summit",
    "sg:classifiers":[
        {
            "category":"Professional",
            "subcategory":"Management & Consulting",
            "type":"Services"
        }
    ],
    "sg:phone":"+1 816 525 2622",
    "sg:postcode":"64081",
    "sg:province":"MO",
    "sg:tags":[
        "marketing",
        "consultant"
    ],
    "wof:name":"Hal Warren Co",
    "wof:placetype":"venue"
},
  "geometry": {"coordinates":[-94.403604,38.909119],"type":"Point"}
}