{
  "type": "Feature",
  "properties": {
    "iso:country":"US",
    "sg:address":"1975 Walton Rd",
    "sg:city":"Overland",
    "sg:classifiers":[
        {
            "category":"Wholesale",
            "subcategory":"Wine & Distilled Alcoholic Beverages",
            "type":"Manufacturing & Wholesale Goods"
        }
    ],
    "sg:phone":"+1 314 429 2564",
    "sg:postcode":"63114",
    "sg:province":"MO",
    "wof:name":"Global Grape LLC Wine Importer",
    "wof:placetype":"venue"
},
  "geometry": {"coordinates":[-90.347596,38.689715],"type":"Point"}
}