{
  "type": "Feature",
  "properties": {
    "iso:country":"US",
    "sg:address":"9420 E Truman Rd",
    "sg:city":"Independence",
    "sg:classifiers":[
        {
            "category":"Retail",
            "subcategory":"Auto Repair",
            "type":"Services"
        }
    ],
    "sg:phone":"+1 816 461 4741",
    "sg:postcode":"64052",
    "sg:province":"MO",
    "sg:tags":[
        "automotive"
    ],
    "wof:name":"Pronto Auto Service",
    "wof:placetype":"venue"
},
  "geometry": {"coordinates":[-94.466438,39.095469],"type":"Point"}
}