{
  "type": "Feature",
  "properties": {
    "iso:country":"US",
    "sg:address":"6303 E 140th Ter",
    "sg:city":"Grandview",
    "sg:classifiers":[
        {
            "category":"Restaurant",
            "type":"Food & Drink"
        }
    ],
    "sg:phone":"+1 816 763 8900",
    "sg:postcode":"64030",
    "sg:province":"MO",
    "sg:tags":[
        "seafood"
    ],
    "wof:name":"Couzins Catfish Castle",
    "wof:placetype":"venue"
},
  "geometry": {"coordinates":[-94.51914499999999,38.871006],"type":"Point"}
}