{
  "type": "Feature",
  "properties": {
    "iso:country":"US",
    "sg:address":"1803 Smizer Station Rd",
    "sg:city":"Fenton",
    "sg:classifiers":[
        {
            "category":"Food & Beverages",
            "subcategory":"Bakery",
            "type":"Retail Goods"
        }
    ],
    "sg:phone":"+1 636 825 6633",
    "sg:postcode":"63026",
    "sg:province":"MO",
    "sg:tags":[
        "baker"
    ],
    "wof:name":"Marie's Cheesecakes Allez",
    "wof:placetype":"venue"
},
  "geometry": {"coordinates":[-90.494046,38.53252],"type":"Point"}
}