{
  "type": "Feature",
  "properties": {
    "iso:country":"US",
    "sg:address":"1905 Hardesty Ave",
    "sg:city":"Kansas City",
    "sg:classifiers":[
        {
            "category":"Real Estate",
            "subcategory":"Real Estate Agent",
            "type":"Services"
        },
        {
            "category":"Real Estate",
            "subcategory":"Real Estate Operator",
            "type":"Services"
        }
    ],
    "sg:phone":"+1 816 483 6233",
    "sg:postcode":"64127",
    "sg:province":"MO",
    "sg:tags":[
        "apartment"
    ],
    "wof:name":"Nowlin Hall",
    "wof:placetype":"venue"
},
  "geometry": {"coordinates":[-94.51963499999999,39.086989],"type":"Point"}
}