{
  "type": "Feature",
  "properties": {
    "iso:country":"US",
    "sg:address":"1 Missouri Ave",
    "sg:city":"Viburnum",
    "sg:classifiers":[
        {
            "category":"Government",
            "subcategory":"Office",
            "type":"Public Place"
        }
    ],
    "sg:phone":"+1 573 244 5220",
    "sg:postcode":"65566",
    "sg:province":"MO",
    "wof:name":"Iron County Ambulance",
    "wof:placetype":"venue"
},
  "geometry": {"coordinates":[-91.13576999999999,37.715885],"type":"Point"}
}