{
  "type": "Feature",
  "properties": {
    "iso:country":"US",
    "sg:address":"84 Grasso Plz",
    "sg:city":"St Louis",
    "sg:classifiers":[
        {
            "category":"Health Services",
            "subcategory":"Doctor",
            "type":"Services"
        }
    ],
    "sg:phone":"+1 314 638 9309",
    "sg:postcode":"63123",
    "sg:province":"MO",
    "sg:tags":[
        "clinic"
    ],
    "wof:name":"Affton Medical",
    "wof:placetype":"venue"
},
  "geometry": {"coordinates":[-90.333962,38.551104],"type":"Point"}
}