{
  "type": "Feature",
  "properties": {
    "iso:country":"US",
    "sg:address":"9773 Olive Blvd",
    "sg:city":"Saint Louis",
    "sg:classifiers":[
        {
            "category":"Banks & Credit Unions",
            "subcategory":"Investment Brokerage",
            "type":"Services"
        }
    ],
    "sg:phone":"+1 314 469 9093",
    "sg:postcode":"63132",
    "sg:province":"MO",
    "sg:tags":[
        "security",
        "business"
    ],
    "wof:name":"Edward Jones 17292",
    "wof:placetype":"venue"
},
  "geometry": {"coordinates":[-90.38987299999999,38.673005],"type":"Point"}
}