{
  "type": "Feature",
  "properties": {
    "iso:country":"US",
    "sg:address":"2801 W Main St",
    "sg:city":"Sedalia",
    "sg:classifiers":[
        {
            "category":"Building & Trades",
            "subcategory":"Construction",
            "type":"Services"
        }
    ],
    "sg:phone":"+1 660 826 2052",
    "sg:postcode":"65301",
    "sg:province":"MO",
    "sg:tags":[
        "contractor",
        "nonresidential"
    ],
    "wof:name":"Schultz Wrecking Service",
    "wof:placetype":"venue"
},
  "geometry": {"coordinates":[-93.260739,38.714013],"type":"Point"}
}