{
  "type": "Feature",
  "properties": {
    "iso:country":"US",
    "sg:address":"100 E Main St",
    "sg:city":"Malden",
    "sg:classifiers":[
        {
            "category":"Shopping",
            "subcategory":"Used Merchandise",
            "type":"Retail Goods"
        },
        {
            "category":"Professional",
            "subcategory":"Business Services",
            "type":"Services"
        }
    ],
    "sg:phone":"+1 573 276 3141",
    "sg:postcode":"63863",
    "sg:province":"MO",
    "sg:tags":[
        "flea",
        "market"
    ],
    "wof:name":"Downtown Flea Market The",
    "wof:placetype":"venue"
},
  "geometry": {"coordinates":[-89.966251,36.558253],"type":"Point"}
}