{
  "type": "Feature",
  "properties": {
    "iso:country":"US",
    "sg:address":"1126 N Sprigg St",
    "sg:city":"Cape Girardeau",
    "sg:classifiers":[
        {
            "category":"Food & Beverages",
            "subcategory":"Groceries & Convenience Stores",
            "type":"Retail Goods"
        }
    ],
    "sg:phone":"+1 573 334 3468",
    "sg:postcode":"63701",
    "sg:province":"MO",
    "sg:website":"www.rhodes101.com",
    "wof:name":"Rhodes 101 Stop",
    "wof:placetype":"venue"
},
  "geometry": {"coordinates":[-89.52481299999999,37.31838],"type":"Point"}
}