{
  "type": "Feature",
  "properties": {
    "iso:country":"US",
    "sg:address":"2830 E 7th St",
    "sg:city":"Joplin",
    "sg:classifiers":[
        {
            "category":"Restaurant",
            "type":"Food & Drink"
        }
    ],
    "sg:menulink":"http://www.allmenus.com/mo/joplin/236315-taco-mayo/menu/",
    "sg:phone":"+1 405 691 8226",
    "sg:postcode":"64801",
    "sg:province":"MO",
    "sg:tags":[
        "mexican"
    ],
    "wof:name":"Taco Mayo",
    "wof:placetype":"venue"
},
  "geometry": {"coordinates":[-94.479366,37.084156],"type":"Point"}
}