{
  "type": "Feature",
  "properties": {
    "iso:country":"US",
    "sg:address":"912 Geyer Ave",
    "sg:city":"St Louis",
    "sg:classifiers":[
        {
            "category":"Building & Trades",
            "subcategory":"Construction",
            "type":"Services"
        }
    ],
    "sg:phone":"+1 314 241 7463",
    "sg:postcode":"63104",
    "sg:province":"MO",
    "sg:tags":[
        "contractor",
        "general"
    ],
    "wof:name":"Pazur Roofing Co",
    "wof:placetype":"venue"
},
  "geometry": {"coordinates":[-90.205545,38.608628],"type":"Point"}
}