{
  "type": "Feature",
  "properties": {
    "iso:country":"US",
    "sg:address":"11715 Cragwold Rd",
    "sg:city":"St Louis",
    "sg:classifiers":[
        {
            "category":"Government",
            "subcategory":"Office",
            "type":"Public Place"
        }
    ],
    "sg:phone":"+1 314 301 1500",
    "sg:postcode":"63122",
    "sg:province":"MO",
    "sg:tags":[
        "department",
        "state",
        "conservation",
        "area"
    ],
    "wof:name":"Powder Valley Nature Center",
    "wof:placetype":"venue"
},
  "geometry": {"coordinates":[-90.41925500000001,38.55467],"type":"Point"}
}