{
  "type": "Feature",
  "properties": {
    "iso:country":"US",
    "sg:address":"2628 Hope Ave",
    "sg:city":"St Louis",
    "sg:classifiers":[
        {
            "category":"Banks & Credit Unions",
            "subcategory":"Financial Services",
            "type":"Services"
        },
        {
            "category":"Social Services",
            "type":"Services"
        }
    ],
    "sg:phone":"+1 314 645 1857",
    "sg:postcode":"63143",
    "sg:province":"MO",
    "sg:tags":[
        "organization",
        "apartment",
        "welfare"
    ],
    "wof:name":"United Workers For Blind MO",
    "wof:placetype":"venue"
},
  "geometry": {"coordinates":[-90.314689,38.614269],"type":"Point"}
}