{
  "type": "Feature",
  "properties": {
    "iso:country":"US",
    "sg:address":"342 SW Blue Pkwy",
    "sg:city":"Lees Summit",
    "sg:classifiers":[
        {
            "category":"Education",
            "subcategory":"Dance Studio",
            "type":"Public Place"
        }
    ],
    "sg:phone":"+1 816 246 6776",
    "sg:postcode":"64063",
    "sg:province":"MO",
    "sg:tags":[
        "instruction",
        "dancing"
    ],
    "wof:name":"Monica's School Of Dance",
    "wof:placetype":"venue"
},
  "geometry": {"coordinates":[-94.38112599999999,38.904816],"type":"Point"}
}