{
  "type": "Feature",
  "properties": {
    "iso:country":"US",
    "sg:address":"400 Plaza Ave",
    "sg:city":"Saint Louis",
    "sg:classifiers":[
        {
            "category":"Shopping",
            "subcategory":"Jewelry",
            "type":"Retail Goods"
        }
    ],
    "sg:phone":"+1 314 291 6404",
    "sg:postcode":"63135",
    "sg:province":"MO",
    "wof:name":"Famous Barr Jewelry Dept",
    "wof:placetype":"venue"
},
  "geometry": {"coordinates":[-90.316749,38.733409],"type":"Point"}
}