{
  "type": "Feature",
  "properties": {
    "iso:country":"US",
    "sg:address":"601 Edwin St",
    "sg:city":"Saint Louis",
    "sg:classifiers":[
        {
            "category":"Shopping",
            "subcategory":"Stationery & Office Supplies",
            "type":"Retail Goods"
        }
    ],
    "sg:phone":"+1 314 652 0166",
    "sg:postcode":"63103",
    "sg:province":"MO",
    "sg:tags":[
        "equipment"
    ],
    "sg:website":"www.nationalchair.com",
    "wof:name":"National Chair & Furniture Co",
    "wof:placetype":"venue"
},
  "geometry": {"coordinates":[-90.231737,38.629647],"type":"Point"}
}