{
  "type": "Feature",
  "properties": {
    "iso:country":"US",
    "sg:address":"3622 Bellerive Blvd",
    "sg:city":"Saint Louis",
    "sg:classifiers":[
        {
            "category":"Manufacturing",
            "subcategory":"Jewelry",
            "type":"Manufacturing & Wholesale Goods"
        }
    ],
    "sg:phone":"+1 314 481 5033",
    "sg:postcode":"63116",
    "sg:province":"MO",
    "sg:tags":[
        "stone",
        "metal",
        "precious",
        "mfg"
    ],
    "wof:name":"Earbobs",
    "wof:placetype":"venue"
},
  "geometry": {"coordinates":[-90.258212,38.569105],"type":"Point"}
}