{
  "type": "Feature",
  "properties": {
    "iso:country":"US",
    "sg:address":"16209 Westwoods Business Park",
    "sg:city":"Ellisville",
    "sg:classifiers":[
        {
            "category":"Professional",
            "subcategory":"Business Services",
            "type":"Services"
        }
    ],
    "sg:phone":"+1 636 207 7000",
    "sg:postcode":"63021",
    "sg:province":"MO",
    "sg:tags":[
        "embroidery"
    ],
    "wof:name":"New Image By Yvonne",
    "wof:placetype":"venue"
},
  "geometry": {"coordinates":[-90.599571,38.584845],"type":"Point"}
}