{
  "type": "Feature",
  "properties": {
    "iso:country":"US",
    "sg:address":"108 E 175th St",
    "sg:city":"Belton",
    "sg:classifiers":[
        {
            "category":"Building & Trades",
            "subcategory":"Construction",
            "type":"Services"
        }
    ],
    "sg:phone":"+1 816 322 7854",
    "sg:postcode":"64012",
    "sg:province":"MO",
    "sg:tags":[
        "home",
        "rough",
        "family"
    ],
    "wof:name":"RW Marsh Construction Co",
    "wof:placetype":"venue"
},
  "geometry": {"coordinates":[-94.60343399999999,38.811026],"type":"Point"}
}