{
  "type": "Feature",
  "properties": {
    "iso:country":"US",
    "sg:address":"3150 Gustine Ave",
    "sg:city":"St Louis",
    "sg:classifiers":[
        {
            "category":"Food & Beverages",
            "subcategory":"Groceries & Convenience Stores",
            "type":"Retail Goods"
        }
    ],
    "sg:phone":"+1 314 932 5141",
    "sg:postcode":"63116",
    "sg:province":"MO",
    "sg:website":"gustinemarket.com",
    "wof:name":"Gustine Market",
    "wof:placetype":"venue"
},
  "geometry": {"coordinates":[-90.24960799999999,38.601457],"type":"Point"}
}