{
  "type": "Feature",
  "properties": {
    "iso:country":"US",
    "sg:address":"12 E Meadow Ln",
    "sg:city":"Ballwin",
    "sg:classifiers":[
        {
            "category":"Professional",
            "subcategory":"Management & Consulting",
            "type":"Services"
        }
    ],
    "sg:phone":"+1 636 256 4983",
    "sg:postcode":"63021",
    "sg:province":"MO",
    "sg:tags":[
        "business"
    ],
    "wof:name":"Mark H Brown Associates",
    "wof:placetype":"venue"
},
  "geometry": {"coordinates":[-90.57222,38.592525],"type":"Point"}
}