{
  "type": "Feature",
  "properties": {
    "iso:country":"US",
    "sg:address":"1266 E State Hwy T",
    "sg:city":"Portageville",
    "sg:classifiers":[
        {
            "category":"Home & Garden",
            "subcategory":"Garden Supply",
            "type":"Retail Goods"
        }
    ],
    "sg:phone":"+1 573 379 9036",
    "sg:postcode":"63873",
    "sg:province":"MO",
    "wof:name":"Rons Small Engine",
    "wof:placetype":"venue"
},
  "geometry": {"coordinates":[-89.659139,36.393964],"type":"Point"}
}