{
  "type": "Feature",
  "properties": {
    "iso:country":"US",
    "sg:address":"20423 Newton Rd",
    "sg:city":"Carthage",
    "sg:classifiers":[
        {
            "category":"Shopping",
            "type":"Retail Goods"
        }
    ],
    "sg:phone":"+1 816 763 1459",
    "sg:postcode":"64836",
    "sg:province":"MO",
    "sg:tags":[
        "merchandise"
    ],
    "wof:name":"Defiance Speed Shop",
    "wof:placetype":"venue"
},
  "geometry": {"coordinates":[-94.269957,37.053028],"type":"Point"}
}