{
  "type": "Feature",
  "properties": {
    "iso:country":"US",
    "sg:address":"536 W Ventura Dr",
    "sg:city":"Seymour",
    "sg:classifiers":[
        {
            "category":"Retail",
            "subcategory":"Auto Repair",
            "type":"Services"
        }
    ],
    "sg:phone":"+1 417 935 4174",
    "sg:postcode":"65746",
    "sg:province":"MO",
    "sg:tags":[
        "general"
    ],
    "wof:name":"Mark Burgdorf",
    "wof:placetype":"venue"
},
  "geometry": {"coordinates":[-92.776321,37.137905],"type":"Point"}
}