{
  "type": "Feature",
  "properties": {
    "iso:country":"US",
    "sg:address":"1720 Clearwater Cir",
    "sg:city":"Ozark",
    "sg:classifiers":[
        {
            "category":"Retail",
            "subcategory":"Repair Shop",
            "type":"Services"
        }
    ],
    "sg:phone":"+1 417 581 5757",
    "sg:postcode":"65721",
    "sg:province":"MO",
    "sg:tags":[
        "upholsterer"
    ],
    "wof:name":"All About Upholstery",
    "wof:placetype":"venue"
},
  "geometry": {"coordinates":[-93.22457799999999,37.034267],"type":"Point"}
}