{
  "type": "Feature",
  "properties": {
    "iso:country":"US",
    "sg:address":"14 W Mill St",
    "sg:city":"Liberty",
    "sg:classifiers":[
        {
            "category":"Real Estate",
            "subcategory":"Real Estate Agent",
            "type":"Services"
        }
    ],
    "sg:phone":"+1 816 781 7900",
    "sg:postcode":"64068",
    "sg:province":"MO",
    "wof:name":"Rigby Realty Corp",
    "wof:placetype":"venue"
},
  "geometry": {"coordinates":[-94.420456,39.244824],"type":"Point"}
}