{
  "type": "Feature",
  "properties": {
    "iso:country":"US",
    "sg:address":"269 Palm Dr",
    "sg:city":"Hazelwood",
    "sg:classifiers":[
        {
            "category":"Shopping",
            "subcategory":"Tobacco",
            "type":"Retail Goods"
        }
    ],
    "sg:phone":"+1 314 837 6384",
    "sg:postcode":"63042",
    "sg:province":"MO",
    "sg:tags":[
        "product"
    ],
    "wof:name":"Cigar Premium",
    "wof:placetype":"venue"
},
  "geometry": {"coordinates":[-90.344402,38.783975],"type":"Point"}
}