{
  "type": "Feature",
  "properties": {
    "iso:country":"US",
    "sg:address":"14721 Saille Ct",
    "sg:city":"Florissant",
    "sg:classifiers":[
        {
            "category":"Shopping",
            "subcategory":"Jewelry",
            "type":"Retail Goods"
        }
    ],
    "sg:phone":"+1 314 837 0839",
    "sg:postcode":"63034",
    "sg:province":"MO",
    "wof:name":"Gabb Designs",
    "wof:placetype":"venue"
},
  "geometry": {"coordinates":[-90.291872,38.823779],"type":"Point"}
}