{
  "type": "Feature",
  "properties": {
    "iso:country":"US",
    "sg:address":"203 N Main St",
    "sg:city":"Ionia",
    "sg:classifiers":[
        {
            "category":"Retail",
            "subcategory":"Auto Repair",
            "type":"Services"
        }
    ],
    "sg:phone":"+1 660 285 3425",
    "sg:postcode":"65335",
    "sg:province":"MO",
    "sg:tags":[
        "body",
        "repairing",
        "painting",
        "automobile"
    ],
    "wof:name":"Beeson's Garage & Body Shop",
    "wof:placetype":"venue"
},
  "geometry": {"coordinates":[-93.323691,38.502481],"type":"Point"}
}