{
  "type": "Feature",
  "properties": {
    "iso:country":"US",
    "sg:address":"252 Camelot Dr",
    "sg:city":"Saint Charles",
    "sg:classifiers":[
        {
            "category":"Professional",
            "subcategory":"Business Services",
            "type":"Services"
        }
    ],
    "sg:phone":"+1 636 300 8195",
    "sg:postcode":"63304",
    "sg:province":"MO",
    "wof:name":"Dynasty Interiors Inc",
    "wof:placetype":"venue"
},
  "geometry": {"coordinates":[-90.651088,38.711741],"type":"Point"}
}