{
  "type": "Feature",
  "properties": {
    "iso:country":"US",
    "sg:address":"1520 Kent Rd",
    "sg:city":"Mexico",
    "sg:classifiers":[
        {
            "category":"Wholesale",
            "subcategory":"Metals & Minerals",
            "type":"Manufacturing & Wholesale Goods"
        }
    ],
    "sg:phone":"+1 573 582 0677",
    "sg:postcode":"65265",
    "sg:province":"MO",
    "sg:tags":[
        "die",
        "casting"
    ],
    "wof:name":"Strikodynarad",
    "wof:placetype":"venue"
},
  "geometry": {"coordinates":[-91.904444,39.183314],"type":"Point"}
}