{
  "type": "Feature",
  "properties": {
    "iso:country":"US",
    "sg:address":"100 SW Scherer Rd",
    "sg:city":"Lees Summit",
    "sg:classifiers":[
        {
            "category":"Manufacturing",
            "subcategory":"Tools & Machinery",
            "type":"Manufacturing & Wholesale Goods"
        }
    ],
    "sg:phone":"+1 816 525 3900",
    "sg:postcode":"64082",
    "sg:province":"MO",
    "sg:tags":[
        "industrial",
        "truck"
    ],
    "sg:website":"www.tigermfg.com",
    "wof:name":"Tiger Corp",
    "wof:placetype":"venue"
},
  "geometry": {"coordinates":[-94.373638,38.888858],"type":"Point"}
}