{
  "type": "Feature",
  "properties": {
    "iso:country":"US",
    "sg:address":"5204 Hampton Ave",
    "sg:city":"Saint Louis",
    "sg:classifiers":[
        {
            "category":"Bars & Pubs",
            "subcategory":"Nightclub",
            "type":"Food & Drink"
        }
    ],
    "sg:phone":"+1 314 481 4794",
    "sg:postcode":"63109",
    "sg:province":"MO",
    "sg:tags":[
        "nightlife"
    ],
    "wof:name":"Double D's Den",
    "wof:placetype":"venue"
},
  "geometry": {"coordinates":[-90.293098,38.584],"type":"Point"}
}