{
  "type": "Feature",
  "properties": {
    "addr:full":"3305 Talent Dr Columbia MO 65203",
    "addr:housenumber":"3305",
    "addr:postcode":"65203",
    "addr:street":"Talent Dr",
    "iso:country":"US",
    "sg:address":"3305 Talent Dr",
    "sg:city":"Columbia",
    "sg:classifiers":[
        {
            "category":"Professional",
            "subcategory":"Business Services",
            "type":"Services"
        }
    ],
    "sg:phone":"+1 573 446 1707",
    "sg:postcode":"65203",
    "sg:province":"MO",
    "wof:name":"New York Life",
    "wof:placetype":"venue"
},
  "geometry": {"coordinates":[-92.38542200000001,38.934595],"type":"Point"}
}