{
  "type": "Feature",
  "properties": {
    "iso:country":"US",
    "sg:address":"732 American Inn Rd",
    "sg:city":"Villa Ridge",
    "sg:classifiers":[
        {
            "category":"Retail",
            "subcategory":"Veterinary Services",
            "type":"Services"
        }
    ],
    "sg:phone":"+1 636 451 5688",
    "sg:postcode":"63089",
    "sg:province":"MO",
    "sg:tags":[
        "navy",
        "veteran",
        "vietnam",
        "us",
        "association"
    ],
    "wof:name":"PBR Forces Veterans Assn Inc",
    "wof:placetype":"venue"
},
  "geometry": {"coordinates":[-90.879892,38.438604],"type":"Point"}
}