{
  "type": "Feature",
  "properties": {
    "iso:country":"US",
    "sg:address":"390 Old Hwy 100",
    "sg:city":"Villa Ridge",
    "sg:classifiers":[
        {
            "category":"Organizations",
            "subcategory":"Religious Organization",
            "type":"Services"
        }
    ],
    "sg:phone":"+1 636 271 2323",
    "sg:postcode":"63089",
    "sg:province":"MO",
    "wof:name":"Chri-Jess Inc",
    "wof:placetype":"venue"
},
  "geometry": {"coordinates":[-90.885717,38.487765],"type":"Point"}
}