{
  "type": "Feature",
  "properties": {
    "iso:country":"US",
    "sg:address":"409 S Main St",
    "sg:city":"St Charles",
    "sg:classifiers":[
        {
            "category":"Shopping",
            "type":"Retail Goods"
        },
        {
            "category":"Shopping",
            "subcategory":"Gifts & Souvenirs",
            "type":"Retail Goods"
        }
    ],
    "sg:phone":"+1 636 947 4076",
    "sg:postcode":"63301",
    "sg:province":"MO",
    "sg:tags":[
        "art",
        "gallery",
        "merchandise",
        "dealer"
    ],
    "sg:website":"www.tenaska.com",
    "wof:name":"Goodarts Gallery LLC",
    "wof:placetype":"venue"
},
  "geometry": {"coordinates":[-90.48313,38.777966],"type":"Point"}
}