{
  "type": "Feature",
  "properties": {
    "iso:country":"US",
    "sg:address":"6001 Rockhill Rd",
    "sg:city":"Kansas City",
    "sg:classifiers":[
        {
            "category":"Health Services",
            "subcategory":"Doctor",
            "type":"Services"
        }
    ],
    "sg:phone":"+1 816 276 7600",
    "sg:postcode":"64110",
    "sg:province":"MO",
    "sg:tags":[
        "medical"
    ],
    "wof:name":"Mark Lee",
    "wof:placetype":"venue"
},
  "geometry": {"coordinates":[-94.576706,39.016717],"type":"Point"}
}