{
  "type": "Feature",
  "properties": {
    "iso:country":"US",
    "sg:address":"9939 Zykan Ct",
    "sg:city":"Overland",
    "sg:classifiers":[
        {
            "category":"Building & Trades",
            "subcategory":"Construction",
            "type":"Services"
        }
    ],
    "sg:phone":"+1 314 423 2419",
    "sg:postcode":"63114",
    "sg:province":"MO",
    "sg:tags":[
        "repairing",
        "remodeling",
        "contractor"
    ],
    "wof:name":"Grigsby Robertson Construction",
    "wof:placetype":"venue"
},
  "geometry": {"coordinates":[-90.381491,38.691405],"type":"Point"}
}