{
  "type": "Feature",
  "properties": {
    "iso:country":"US",
    "sg:address":"465 Truman Rd",
    "sg:city":"Osceola",
    "sg:classifiers":[
        {
            "category":"Wholesale",
            "subcategory":"Durable Goods & Equipment",
            "type":"Manufacturing & Wholesale Goods"
        }
    ],
    "sg:phone":"+1 417 646 2188",
    "sg:postcode":"64776",
    "sg:province":"MO",
    "wof:name":"Bobs Health Supplements",
    "wof:placetype":"venue"
},
  "geometry": {"coordinates":[-93.694847,38.050929],"type":"Point"}
}