{
  "type": "Feature",
  "properties": {
    "iso:country":"US",
    "sg:address":"8026 NE 50 St",
    "sg:city":"Kansas City",
    "sg:classifiers":[
        {
            "category":"Building & Trades",
            "subcategory":"Construction",
            "type":"Services"
        }
    ],
    "sg:phone":"+1 816 413 8891",
    "sg:postcode":"64119",
    "sg:province":"MO",
    "sg:tags":[
        "house"
    ],
    "wof:name":"Earthen Treasures Remodeling",
    "wof:placetype":"venue"
},
  "geometry": {"coordinates":[-94.485119,39.185413],"type":"Point"}
}