{
  "type": "Feature",
  "properties": {
    "iso:country":"US",
    "sg:address":"3226 Co Rd 524",
    "sg:city":"Parma",
    "sg:classifiers":[
        {
            "category":"Farming",
            "subcategory":"Farm",
            "type":"Manufacturing & Wholesale Goods"
        }
    ],
    "sg:phone":"+1 573 396 8539",
    "sg:postcode":"63870",
    "sg:province":"MO",
    "sg:tags":[
        "crop",
        "general"
    ],
    "wof:name":"Mark Robertson",
    "wof:placetype":"venue"
},
  "geometry": {"coordinates":[-89.84671,36.584121],"type":"Point"}
}