{
  "type": "Feature",
  "properties": {
    "iso:country":"US",
    "sg:address":"106 S 7th St",
    "sg:city":"Saint Joseph",
    "sg:classifiers":[
        {
            "category":"Professional",
            "subcategory":"Lawyer & Legal Services",
            "type":"Services"
        }
    ],
    "sg:phone":"+1 816 233 3972",
    "sg:postcode":"64501",
    "sg:province":"MO",
    "wof:name":"Kathy L Wood",
    "wof:placetype":"venue"
},
  "geometry": {"coordinates":[-94.851973,39.765863],"type":"Point"}
}