{
  "type": "Feature",
  "properties": {
    "iso:country":"US",
    "sg:address":"131 Locust Rd",
    "sg:city":"Carthage",
    "sg:classifiers":[
        {
            "category":"Utilities",
            "subcategory":"Recycling",
            "type":"Services"
        },
        {
            "category":"Building & Trades",
            "subcategory":"Electrical",
            "type":"Services"
        }
    ],
    "sg:phone":"+1 417 358 8322",
    "sg:postcode":"64836",
    "sg:province":"MO",
    "sg:tags":[
        "wire",
        "products-wholesale",
        "disposal",
        "equipment",
        "waste",
        "manufacturer"
    ],
    "sg:website":"http://www.lpwiretie.com",
    "wof:name":"L&P Wire Tie Systems",
    "wof:placetype":"venue"
},
  "geometry": {"coordinates":[-94.30427,37.17886],"type":"Point"}
}