{
  "type": "Feature",
  "properties": {
    "iso:country":"US",
    "sg:address":"1822 Frederick Ave",
    "sg:city":"St Joseph",
    "sg:classifiers":[
        {
            "category":"Home & Garden",
            "subcategory":"Building Materials",
            "type":"Retail Goods"
        },
        {
            "category":"Building & Trades",
            "subcategory":"Construction",
            "type":"Services"
        }
    ],
    "sg:phone":"+1 816 279 2768",
    "sg:postcode":"64501",
    "sg:province":"MO",
    "sg:tags":[
        "plate",
        "installation",
        "residential",
        "commercial",
        "contractor",
        "glass",
        "window"
    ],
    "wof:name":"Missouri Glass Inc",
    "wof:placetype":"venue"
},
  "geometry": {"coordinates":[-94.83770800000001,39.773616],"type":"Point"}
}