{
  "type": "Feature",
  "properties": {
    "iso:country":"US",
    "sg:address":"106 W 11 St",
    "sg:city":"Kansas City",
    "sg:classifiers":[
        {
            "category":"Real Estate",
            "subcategory":"Architect",
            "type":"Services"
        }
    ],
    "sg:phone":"+1 816 421 1677",
    "sg:postcode":"64105",
    "sg:province":"MO",
    "sg:website":"www.bellknott.com",
    "wof:name":"Bell-Knott & Assoc",
    "wof:placetype":"venue"
},
  "geometry": {"coordinates":[-94.585471,39.100974],"type":"Point"}
}