{
  "type": "Feature",
  "properties": {
    "iso:country":"US",
    "sg:address":"604 N Douglas St",
    "sg:city":"Malden",
    "sg:classifiers":[
        {
            "category":"Manufacturing",
            "subcategory":"Printing",
            "type":"Manufacturing & Wholesale Goods"
        }
    ],
    "sg:phone":"+1 573 276 5477",
    "sg:postcode":"63863",
    "sg:province":"MO",
    "sg:tags":[
        "printer"
    ],
    "wof:name":"Elder Printing Svc",
    "wof:placetype":"venue"
},
  "geometry": {"coordinates":[-89.970615,36.565361],"type":"Point"}
}