{
  "type": "Feature",
  "properties": {
    "iso:country":"US",
    "sg:address":"104 State Hwy 7",
    "sg:city":"Blue Springs",
    "sg:classifiers":[
        {
            "category":"Shopping",
            "type":"Retail Goods"
        }
    ],
    "sg:phone":"+1 816 224 2400",
    "sg:postcode":"64014",
    "sg:province":"MO",
    "sg:tags":[
        "hearing",
        "equipment",
        "supply",
        "impaired"
    ],
    "wof:name":"Hometown Hearing & Audiology",
    "wof:placetype":"venue"
},
  "geometry": {"coordinates":[-94.272381,39.015159],"type":"Point"}
}