{
  "type": "Feature",
  "properties": {
    "iso:country":"US",
    "sg:address":"3923 N Oak Fwy",
    "sg:city":"Kansas City",
    "sg:classifiers":[
        {
            "category":"Professional",
            "type":"Services"
        }
    ],
    "sg:phone":"+1 816 413 8181",
    "sg:postcode":"64116",
    "sg:province":"MO",
    "wof:name":"Shaeffer John",
    "wof:placetype":"venue"
},
  "geometry": {"coordinates":[-94.57672700000001,39.165128],"type":"Point"}
}