{
  "type": "Feature",
  "properties": {
    "iso:country":"US",
    "sg:address":"204 W Pennell St",
    "sg:city":"Carl Junction",
    "sg:classifiers":[
        {
            "category":"Home & Garden",
            "subcategory":"Building Materials",
            "type":"Retail Goods"
        }
    ],
    "sg:phone":"+1 417 649 7276",
    "sg:postcode":"64834",
    "sg:province":"MO",
    "sg:tags":[
        "paint"
    ],
    "wof:name":"Carl Junction Lumber Co",
    "wof:placetype":"venue"
},
  "geometry": {"coordinates":[-94.566592,37.176771],"type":"Point"}
}