{
  "type": "Feature",
  "properties": {
    "iso:country":"US",
    "sg:address":"3301 Co Rd 5500",
    "sg:city":"Willow Springs",
    "sg:phone":"+1 417 469 2398",
    "sg:postcode":"65793",
    "sg:province":"MO",
    "sg:tags":[
        "beef",
        "farm",
        "crop",
        "field",
        "cattle",
        "feedlot"
    ],
    "wof:name":"Frazee Family Farm Inc",
    "wof:placetype":"venue"
},
  "geometry": {"coordinates":[-91.965407,36.945339],"type":"Point"}
}