{
  "type": "Feature",
  "properties": {
    "iso:country":"US",
    "sg:address":"7478 Co Rd 3400",
    "sg:city":"Mountain View",
    "sg:classifiers":[
        {
            "category":"Bus Charters",
            "type":"Transportation"
        }
    ],
    "sg:phone":"+1 417 934 2805",
    "sg:postcode":"65548",
    "sg:province":"MO",
    "sg:tags":[
        "trucking",
        "industry",
        "coach",
        "for",
        "entertainment"
    ],
    "wof:name":"Ozark Mountain Leasing Inc",
    "wof:placetype":"venue"
},
  "geometry": {"coordinates":[-91.770493,36.999042],"type":"Point"}
}