{
  "type": "Feature",
  "properties": {
    "iso:country":"US",
    "sg:address":"1251 Grover Rd",
    "sg:city":"St Louis",
    "sg:classifiers":[
        {
            "category":"Manufacturing",
            "subcategory":"Tools & Machinery",
            "type":"Manufacturing & Wholesale Goods"
        }
    ],
    "sg:phone":"+1 314 845 6699",
    "sg:postcode":"63125",
    "sg:province":"MO",
    "sg:tags":[
        "machine",
        "screw",
        "equipment"
    ],
    "wof:name":"Esco Products & Svc",
    "wof:placetype":"venue"
},
  "geometry": {"coordinates":[-90.28645299999999,38.503266],"type":"Point"}
}