{
  "type": "Feature",
  "properties": {
    "iso:country":"US",
    "sg:address":"13154 Tesson Ferry Rd",
    "sg:city":"Sappington",
    "sg:classifiers":[
        {
            "category":"Bars & Pubs",
            "type":"Food & Drink"
        }
    ],
    "sg:phone":"+1 314 842 8395",
    "sg:postcode":"63128",
    "sg:province":"MO",
    "wof:name":"Night Sky Bar",
    "wof:placetype":"venue"
},
  "geometry": {"coordinates":[-90.383132,38.487557],"type":"Point"}
}