{
  "type": "Feature",
  "properties": {
    "iso:country":"US",
    "sg:address":"1120 SE Murphy Blvd",
    "sg:city":"Joplin",
    "sg:classifiers":[
        {
            "category":"Professional",
            "subcategory":"Lawyer & Legal Services",
            "type":"Services"
        }
    ],
    "sg:phone":"+1 417 781 8530",
    "sg:postcode":"64801",
    "sg:province":"MO",
    "sg:tags":[
        "attorney"
    ],
    "sg:website":"www.hardshipdriverslicense.com",
    "wof:name":"Glades & Assoc",
    "wof:placetype":"venue"
},
  "geometry": {"coordinates":[-94.49893899999999,37.078328],"type":"Point"}
}