{
  "type": "Feature",
  "properties": {
    "iso:country":"US",
    "sg:address":"3030 N Church St",
    "sg:city":"Cape Girardeau",
    "sg:classifiers":[
        {
            "category":"Social Services",
            "subcategory":"Child Care",
            "type":"Services"
        }
    ],
    "sg:phone":"+1 573 335 0910",
    "sg:postcode":"63701",
    "sg:province":"MO",
    "sg:tags":[
        "day"
    ],
    "wof:name":"Riley S Family Day Care",
    "wof:placetype":"venue"
},
  "geometry": {"coordinates":[-89.56648800000001,37.336026],"type":"Point"}
}