{
  "type": "Feature",
  "properties": {
    "iso:country":"US",
    "sg:address":"6415 Running Deer Ln",
    "sg:city":"Osage Beach",
    "sg:classifiers":[
        {
            "category":"Banks & Credit Unions",
            "subcategory":"Investment Brokerage",
            "type":"Services"
        }
    ],
    "sg:phone":"+1 573 280 1323",
    "sg:postcode":"65065",
    "sg:province":"MO",
    "sg:tags":[
        "advisory",
        "financial"
    ],
    "wof:name":"Principal Financial Group",
    "wof:placetype":"venue"
},
  "geometry": {"coordinates":[-92.718678,38.148069],"type":"Point"}
}