{
  "type": "Feature",
  "properties": {
    "iso:country":"US",
    "sg:address":"320 W Ashley Rd",
    "sg:city":"Boonville",
    "sg:classifiers":[
        {
            "category":"Restaurant",
            "type":"Food & Drink"
        }
    ],
    "sg:menulink":"http://www.allmenus.com/mo/boonville/151691-aw-restaurant/menu/",
    "sg:phone":"+1 660 882 7407",
    "sg:postcode":"65233",
    "sg:province":"MO",
    "sg:tags":[
        "burger",
        "american",
        "dog",
        "pub",
        "hot"
    ],
    "wof:name":"A&W Restaurant",
    "wof:placetype":"venue"
},
  "geometry": {"coordinates":[-92.75376300000001,38.963807],"type":"Point"}
}