{
  "type": "Feature",
  "properties": {
    "addr:full":"1098 US Hwy 169 Smithville MO 64089",
    "addr:housenumber":"1098",
    "addr:postcode":"64089",
    "addr:street":"Us Hwy 169",
    "iso:country":"US",
    "sg:address":"1098 US Hwy 169",
    "sg:city":"Smithville",
    "sg:classifiers":[
        {
            "category":"Retail",
            "subcategory":"Auto Rental",
            "type":"Services"
        }
    ],
    "sg:phone":"+1 816 532 3411",
    "sg:postcode":"64089",
    "sg:province":"MO",
    "sg:tags":[
        "renting",
        "truck",
        "leasing"
    ],
    "wof:name":"U-Haul Co",
    "wof:placetype":"venue"
},
  "geometry": {"coordinates":[-94.583738,39.409585],"type":"Point"}
}