{
  "type": "Feature",
  "properties": {
    "iso:country":"US",
    "sg:address":"336 Sovereign Ct",
    "sg:city":"Ballwin",
    "sg:classifiers":[
        {
            "category":"Wholesale",
            "subcategory":"Hardware",
            "type":"Manufacturing & Wholesale Goods"
        }
    ],
    "sg:phone":"+1 636 391 7377",
    "sg:postcode":"63011",
    "sg:province":"MO",
    "wof:name":"Holiday Heating & Cooling",
    "wof:placetype":"venue"
},
  "geometry": {"coordinates":[-90.49048000000001,38.600546],"type":"Point"}
}