{
  "type": "Feature",
  "properties": {
    "iso:country":"US",
    "sg:address":"605 Bus Loop 70 E",
    "sg:city":"Columbia",
    "sg:classifiers":[
        {
            "category":"Retail",
            "subcategory":"Auto Repair",
            "type":"Services"
        }
    ],
    "sg:phone":"+1 573 443 1790",
    "sg:postcode":"65201",
    "sg:province":"MO",
    "sg:tags":[
        "general"
    ],
    "wof:name":"Premeier Automotive Service",
    "wof:placetype":"venue"
},
  "geometry": {"coordinates":[-92.329497,38.964229],"type":"Point"}
}