{
  "type": "Feature",
  "properties": {
    "iso:country":"US",
    "sg:address":"2234 Lakeside Dr",
    "sg:city":"Wentzville",
    "sg:classifiers":[
        {
            "category":"Building & Trades",
            "subcategory":"Landscaping Services",
            "type":"Services"
        }
    ],
    "sg:phone":"+1 636 327 5385",
    "sg:postcode":"63385",
    "sg:province":"MO",
    "wof:name":"Lakeside Service and Supply",
    "wof:placetype":"venue"
},
  "geometry": {"coordinates":[-90.904673,38.797783],"type":"Point"}
}