{
  "type": "Feature",
  "properties": {
    "iso:country":"US",
    "sg:address":"6312 Wyoming St",
    "sg:city":"Saint Louis",
    "sg:classifiers":[
        {
            "category":"Building & Trades",
            "subcategory":"Construction",
            "type":"Services"
        }
    ],
    "sg:phone":"+1 314 781 5837",
    "sg:postcode":"63139",
    "sg:province":"MO",
    "sg:tags":[
        "house"
    ],
    "wof:name":"Garden Patios & Ponds",
    "wof:placetype":"venue"
},
  "geometry": {"coordinates":[-90.294977,38.603948],"type":"Point"}
}