{
  "type": "Feature",
  "properties": {
    "addr:full":"404 S US-71 Savannah MO 64485",
    "addr:housenumber":"404",
    "addr:postcode":"64485",
    "addr:street":"S Us-71",
    "iso:country":"US",
    "sg:address":"404 S US-71",
    "sg:city":"Savannah",
    "sg:classifiers":[
        {
            "category":"Restaurant",
            "type":"Food & Drink"
        }
    ],
    "sg:menulink":"http://www.allmenus.com/mo/nodaway/65820-pizza-hut/menu/",
    "sg:phone":"+1 816 324 3173",
    "sg:postcode":"64485",
    "sg:province":"MO",
    "sg:tags":[
        "american",
        "pizza"
    ],
    "wof:name":"Pizza Hut",
    "wof:placetype":"venue"
},
  "geometry": {"coordinates":[-94.822023,39.937294],"type":"Point"}
}