{
  "type": "Feature",
  "properties": {
    "iso:country":"US",
    "sg:address":"355 NE Gospel Rd",
    "sg:city":"Maysville",
    "sg:classifiers":[
        {
            "category":"Farming",
            "subcategory":"Livestock Farm",
            "type":"Manufacturing & Wholesale Goods"
        }
    ],
    "sg:phone":"+1 816 449 5325",
    "sg:postcode":"64469",
    "sg:province":"MO",
    "sg:tags":[
        "beef",
        "feedlot",
        "cattle"
    ],
    "wof:name":"Helen Jackson",
    "wof:placetype":"venue"
},
  "geometry": {"coordinates":[-94.34919600000001,39.951267],"type":"Point"}
}