{
  "type": "Feature",
  "properties": {
    "iso:country":"US",
    "sg:address":"7210 Wornall Rd",
    "sg:city":"Kansas City",
    "sg:classifiers":[
        {
            "category":"Health Services",
            "subcategory":"Chiropractor",
            "type":"Services"
        }
    ],
    "sg:phone":"+1 816 333 2533",
    "sg:postcode":"64114",
    "sg:province":"MO",
    "wof:name":"Waldo Chiropractic Clinic",
    "wof:placetype":"venue"
},
  "geometry": {"coordinates":[-94.594126,38.996152],"type":"Point"}
}