{
  "type": "Feature",
  "properties": {
    "iso:country":"US",
    "sg:address":"3 Saint Louis Galleria",
    "sg:city":"Saint Louis",
    "sg:classifiers":[
        {
            "category":"Shopping",
            "subcategory":"News",
            "type":"Retail Goods"
        }
    ],
    "sg:phone":"+1 314 721 7299",
    "sg:postcode":"63117",
    "sg:province":"MO",
    "wof:name":"Street Corner News",
    "wof:placetype":"venue"
},
  "geometry": {"coordinates":[-90.345857,38.637645],"type":"Point"}
}