{
  "type": "Feature",
  "properties": {
    "iso:country":"US",
    "sg:address":"650 E Kearney St",
    "sg:city":"Springfield",
    "sg:phone":"+1 417 862 7333",
    "sg:postcode":"65803",
    "sg:province":"MO",
    "sg:website":"http://www.jiffylube.com",
    "wof:name":"Jiffy Lube",
    "wof:placetype":"venue"
},
  "geometry": {"coordinates":[-93.296987,37.240752],"type":"Point"}
}