{
  "type": "Feature",
  "properties": {
    "iso:country":"US",
    "sg:address":"2339 Madison 208",
    "sg:city":"Fredericktown",
    "sg:classifiers":[
        {
            "category":"Building & Trades",
            "subcategory":"Construction",
            "type":"Services"
        }
    ],
    "sg:phone":"+1 573 783 7563",
    "sg:postcode":"63645",
    "sg:province":"MO",
    "sg:tags":[
        "home",
        "builder"
    ],
    "wof:name":"Tom Weyand & Sons",
    "wof:placetype":"venue"
},
  "geometry": {"coordinates":[-90.24261799999999,37.557157],"type":"Point"}
}