{
  "type": "Feature",
  "properties": {
    "addr:full":"1907 E McCarty St Jefferson City MO 65101",
    "addr:housenumber":"1907",
    "addr:postcode":"65101",
    "addr:street":"E Mccarty St",
    "iso:country":"US",
    "sg:address":"1907 E McCarty St",
    "sg:city":"Jefferson City",
    "sg:classifiers":[
        {
            "category":"Food & Beverages",
            "subcategory":"Groceries & Convenience Stores",
            "type":"Retail Goods"
        }
    ],
    "sg:phone":"+1 573 634 2622",
    "sg:postcode":"65101",
    "sg:province":"MO",
    "wof:name":"Break Time",
    "wof:placetype":"venue"
},
  "geometry": {"coordinates":[-92.140702,38.561746],"type":"Point"}
}