{
  "type": "Feature",
  "properties": {
    "iso:country":"US",
    "sg:address":"1726 Rudder Industrial Park Dr",
    "sg:city":"Fenton",
    "sg:classifiers":[
        {
            "category":"Building & Trades",
            "subcategory":"Construction",
            "type":"Services"
        }
    ],
    "sg:phone":"+1 636 349 0838",
    "sg:postcode":"63026",
    "sg:province":"MO",
    "sg:tags":[
        "general",
        "contractor"
    ],
    "wof:name":"Griffith Construction Co",
    "wof:placetype":"venue"
},
  "geometry": {"coordinates":[-90.452789,38.540959],"type":"Point"}
}