{
  "type": "Feature",
  "properties": {
    "iso:country":"US",
    "sg:address":"558 Coach Light Ln",
    "sg:city":"Hazelwood",
    "sg:classifiers":[
        {
            "category":"Professional",
            "subcategory":"Accounting & Tax Preparation",
            "type":"Services"
        }
    ],
    "sg:phone":"+1 314 837 3753",
    "sg:postcode":"63042",
    "sg:province":"MO",
    "sg:tags":[
        "return",
        "filing"
    ],
    "wof:name":"Starboard Financial Service",
    "wof:placetype":"venue"
},
  "geometry": {"coordinates":[-90.35906199999999,38.786306],"type":"Point"}
}