{
  "type": "Feature",
  "properties": {
    "iso:country":"US",
    "sg:address":"808 Richmond Ave",
    "sg:city":"Columbia",
    "sg:classifiers":[
        {
            "category":"Organizations",
            "subcategory":"Community Association",
            "type":"Services"
        }
    ],
    "sg:phone":"+1 573 443 5211",
    "sg:postcode":"65201",
    "sg:province":"MO",
    "wof:name":"Gamma Phi Beta",
    "wof:placetype":"venue"
},
  "geometry": {"coordinates":[-92.331102,38.94145],"type":"Point"}
}