{
  "type": "Feature",
  "properties": {
    "iso:country":"US",
    "sg:address":"4398 Chouteau Ave",
    "sg:city":"St Louis",
    "sg:classifiers":[
        {
            "category":"Professional",
            "type":"Services"
        }
    ],
    "sg:phone":"+1 314 652 9720",
    "sg:postcode":"63110",
    "sg:province":"MO",
    "sg:tags":[
        "sculptor"
    ],
    "sg:website":"www.szostalosculpture.com",
    "wof:name":"Black & White Intl Inc",
    "wof:placetype":"venue"
},
  "geometry": {"coordinates":[-90.25599699999999,38.629501],"type":"Point"}
}