{
  "type": "Feature",
  "properties": {
    "iso:country":"US",
    "sg:address":"28 Maryland Plz",
    "sg:city":"Saint Louis",
    "sg:classifiers":[
        {
            "category":"Shopping",
            "subcategory":"Jewelry",
            "type":"Retail Goods"
        }
    ],
    "sg:phone":"+1 314 361 6556",
    "sg:postcode":"63108",
    "sg:province":"MO",
    "sg:website":"www.mcgintyjewelers.com",
    "wof:name":"McGinty Jewelers On the Plaza",
    "wof:placetype":"venue"
},
  "geometry": {"coordinates":[-90.262574,38.644811],"type":"Point"}
}