{
  "type": "Feature",
  "properties": {
    "iso:country":"US",
    "sg:address":"2709 Cantrell Rd",
    "sg:city":"Harrisonville",
    "sg:classifiers":[
        {
            "category":"Professional",
            "subcategory":"Employment Agencies",
            "type":"Services"
        }
    ],
    "sg:phone":"+1 816 380 2093",
    "sg:postcode":"64701",
    "sg:province":"MO",
    "sg:tags":[
        "consultant",
        "search",
        "executive"
    ],
    "wof:name":"Us Army Recruiting Station",
    "wof:placetype":"venue"
},
  "geometry": {"coordinates":[-94.3732,38.660921],"type":"Point"}
}