{
  "type": "Feature",
  "properties": {
    "iso:country":"US",
    "sg:address":"1 E North St",
    "sg:city":"Marshall",
    "sg:classifiers":[
        {
            "category":"Professional",
            "subcategory":"Lawyer & Legal Services",
            "type":"Services"
        }
    ],
    "sg:phone":"+1 660 886 5531",
    "sg:postcode":"65340",
    "sg:province":"MO",
    "wof:name":"R Lin Alexander",
    "wof:placetype":"venue"
},
  "geometry": {"coordinates":[-93.19658,39.121328],"type":"Point"}
}