{
  "type": "Feature",
  "properties": {
    "iso:country":"US",
    "sg:address":"2401 Hord Ave",
    "sg:city":"Saint Louis",
    "sg:classifiers":[
        {
            "category":"Personal",
            "subcategory":"Beauty Salon",
            "type":"Services"
        }
    ],
    "sg:phone":"+1 314 867 8677",
    "sg:postcode":"63136",
    "sg:province":"MO",
    "sg:tags":[
        "shop"
    ],
    "wof:name":"Connies Tops n Hair",
    "wof:placetype":"venue"
},
  "geometry": {"coordinates":[-90.260909,38.727263],"type":"Point"}
}