{
  "type": "Feature",
  "properties": {
    "iso:country":"US",
    "sg:address":"1941 E Independence St",
    "sg:city":"Springfield",
    "sg:classifiers":[
        {
            "category":"Shopping",
            "type":"Retail Goods"
        },
        {
            "category":"Wholesale",
            "subcategory":"Sporting Goods",
            "type":"Manufacturing & Wholesale Goods"
        }
    ],
    "sg:phone":"+1 417 887 4532",
    "sg:postcode":"65804",
    "sg:province":"MO",
    "sg:tags":[
        "equipment",
        "swimming",
        "pool",
        "supply"
    ],
    "wof:name":"Leslies Swimming Pool Supplies",
    "wof:placetype":"venue"
},
  "geometry": {"coordinates":[-93.260137,37.141858],"type":"Point"}
}