{
  "type": "Feature",
  "properties": {
    "iso:country":"US",
    "sg:address":"4108 Hoffmeister Ave",
    "sg:city":"St Louis",
    "sg:classifiers":[
        {
            "category":"Retail",
            "subcategory":"Auto Repair",
            "type":"Services"
        }
    ],
    "sg:phone":"+1 314 544 5423",
    "sg:postcode":"63125",
    "sg:province":"MO",
    "sg:tags":[
        "wrecker"
    ],
    "wof:name":"M & M Towing",
    "wof:placetype":"venue"
},
  "geometry": {"coordinates":[-90.292552,38.543508],"type":"Point"}
}