{
  "type": "Feature",
  "properties": {
    "iso:country":"US",
    "sg:address":"1000 S Commercial St",
    "sg:city":"Harrisonville",
    "sg:classifiers":[
        {
            "category":"Real Estate",
            "subcategory":"Real Estate Agent",
            "type":"Services"
        }
    ],
    "sg:phone":"+1 816 380 5163",
    "sg:postcode":"64701",
    "sg:province":"MO",
    "sg:tags":[
        "appraiser"
    ],
    "wof:name":"Martha Warren Appraisal Svc",
    "wof:placetype":"venue"
},
  "geometry": {"coordinates":[-94.357303,38.648906],"type":"Point"}
}