{
  "type": "Feature",
  "properties": {
    "iso:country":"US",
    "sg:address":"542 Bratton Ave",
    "sg:city":"West Plains",
    "sg:phone":"+1 417 256 2195",
    "sg:postcode":"65775",
    "sg:province":"MO",
    "sg:tags":[
        "gas"
    ],
    "wof:name":"Best Propane",
    "wof:placetype":"venue"
},
  "geometry": {"coordinates":[-91.846869,36.730744],"type":"Point"}
}