{
  "type": "Feature",
  "properties": {
    "iso:country":"US",
    "sg:address":"1309 Colby Dr",
    "sg:city":"Saint Peters",
    "sg:classifiers":[
        {
            "category":"Professional",
            "subcategory":"Business Services",
            "type":"Services"
        }
    ],
    "sg:phone":"+1 314 565 1415",
    "sg:postcode":"63376",
    "sg:province":"MO",
    "wof:name":"Whitbeck Enterprises LLC",
    "wof:placetype":"venue"
},
  "geometry": {"coordinates":[-90.60742999999999,38.78207],"type":"Point"}
}