{
  "type": "Feature",
  "properties": {
    "iso:country":"US",
    "sg:address":"3157 Buttermilk Spring Rd",
    "sg:city":"Galena",
    "sg:classifiers":[
        {
            "category":"Travel",
            "subcategory":"Hotels & Motels",
            "type":"Entertainment"
        }
    ],
    "sg:phone":"+1 417 538 2333",
    "sg:postcode":"65656",
    "sg:province":"MO",
    "sg:tags":[
        "operation"
    ],
    "wof:name":"Wishwood Resort",
    "wof:placetype":"venue"
},
  "geometry": {"coordinates":[-93.510306,36.65117],"type":"Point"}
}