{
  "type": "Feature",
  "properties": {
    "iso:country":"US",
    "sg:address":"28575 State Highway 6",
    "sg:city":"Gallatin",
    "sg:classifiers":[
        {
            "category":"Home & Garden",
            "subcategory":"Hardware",
            "type":"Retail Goods"
        },
        {
            "category":"Autos & Motor Vehicles",
            "subcategory":"Auto Supplies",
            "type":"Retail Goods"
        },
        {
            "category":"Wholesale",
            "subcategory":"Electrical",
            "type":"Manufacturing & Wholesale Goods"
        }
    ],
    "sg:phone":"+1 660 663 4134",
    "sg:postcode":"64640",
    "sg:province":"MO",
    "sg:tags":[
        "battery",
        "batteries-storage",
        "store"
    ],
    "wof:name":"Country Time Battery",
    "wof:placetype":"venue"
},
  "geometry": {"coordinates":[-93.96257,39.921104],"type":"Point"}
}