{
  "type": "Feature",
  "properties": {
    "iso:country":"US",
    "sg:address":"2851 S Campbell Ave",
    "sg:city":"Springfield",
    "sg:classifiers":[
        {
            "category":"Shopping",
            "subcategory":"Used Merchandise",
            "type":"Retail Goods"
        }
    ],
    "sg:phone":"+1 417 882 7979",
    "sg:postcode":"65807",
    "sg:province":"MO",
    "sg:tags":[
        "furniture"
    ],
    "wof:name":"Lee La's Home Furnishings",
    "wof:placetype":"venue"
},
  "geometry": {"coordinates":[-93.295351,37.164627],"type":"Point"}
}