{
  "type": "Feature",
  "properties": {
    "iso:country":"US",
    "sg:address":"180 English Landing Dr",
    "sg:city":"Kansas City",
    "sg:classifiers":[
        {
            "category":"Professional",
            "type":"Services"
        }
    ],
    "sg:phone":"+1 816 587 9997",
    "sg:postcode":"64152",
    "sg:province":"MO",
    "wof:name":"H M S Beagle",
    "wof:placetype":"venue"
},
  "geometry": {"coordinates":[-94.684735,39.188552],"type":"Point"}
}