{
  "type": "Feature",
  "properties": {
    "iso:country":"US",
    "sg:address":"112 W 4th St",
    "sg:city":"Sedalia",
    "sg:classifiers":[
        {
            "category":"Social Services",
            "type":"Services"
        }
    ],
    "sg:phone":"+1 660 827 0618",
    "sg:postcode":"65301",
    "sg:province":"MO",
    "sg:tags":[
        "organization",
        "welfare"
    ],
    "wof:name":"American Red Cross",
    "wof:placetype":"venue"
},
  "geometry": {"coordinates":[-93.229128,38.707861],"type":"Point"}
}