{
  "type": "Feature",
  "properties": {
    "iso:country":"US",
    "sg:address":"12098 Co Rd 8030",
    "sg:city":"Rolla",
    "sg:classifiers":[
        {
            "category":"Building & Trades",
            "subcategory":"Construction",
            "type":"Services"
        }
    ],
    "sg:phone":"+1 573 341 3675",
    "sg:postcode":"65401",
    "sg:province":"MO",
    "sg:tags":[
        "siding",
        "contractor"
    ],
    "wof:name":"T & T Home Improvements",
    "wof:placetype":"venue"
},
  "geometry": {"coordinates":[-91.77082,37.972896],"type":"Point"}
}