{
  "type": "Feature",
  "properties": {
    "iso:country":"US",
    "sg:address":"214 W 4th St",
    "sg:city":"Fulton",
    "sg:classifiers":[
        {
            "category":"Restaurant",
            "type":"Food & Drink"
        }
    ],
    "sg:phone":"+1 573 642 5097",
    "sg:postcode":"65251",
    "sg:province":"MO",
    "sg:tags":[
        "pizza"
    ],
    "wof:name":"Caseys Pizza",
    "wof:placetype":"venue"
},
  "geometry": {"coordinates":[-91.950201,38.846742],"type":"Point"}
}