{
  "type": "Feature",
  "properties": {
    "iso:country":"US",
    "sg:address":"515 NE 106th St",
    "sg:city":"Kansas City",
    "sg:classifiers":[
        {
            "category":"Education",
            "subcategory":"School",
            "type":"Public Place"
        }
    ],
    "sg:phone":"+1 816 413 6300",
    "sg:postcode":"64155",
    "sg:province":"MO",
    "sg:website":"www.nkcsd.k12.mo.us/nmms",
    "wof:name":"New Mark Middle School",
    "wof:placetype":"venue"
},
  "geometry": {"coordinates":[-94.572782,39.285592],"type":"Point"}
}