{
  "type": "Feature",
  "properties": {
    "iso:country":"US",
    "sg:address":"12935 Gravois Rd",
    "sg:city":"Saint Louis",
    "sg:classifiers":[
        {
            "category":"Wholesale",
            "subcategory":"Machinery & Supplies",
            "type":"Manufacturing & Wholesale Goods"
        }
    ],
    "sg:phone":"+1 314 843 4990",
    "sg:postcode":"63127",
    "sg:province":"MO",
    "sg:tags":[
        "equipment",
        "industrial"
    ],
    "wof:name":"Security Vault Works Inc",
    "wof:placetype":"venue"
},
  "geometry": {"coordinates":[-90.41386300000001,38.51562],"type":"Point"}
}