{
  "type": "Feature",
  "properties": {
    "iso:country":"US",
    "sg:address":"8141 Forsyth Blvd",
    "sg:city":"St Louis",
    "sg:classifiers":[
        {
            "category":"Professional",
            "subcategory":"Business Services",
            "type":"Services"
        },
        {
            "category":"Manufacturing",
            "subcategory":"Printing",
            "type":"Manufacturing & Wholesale Goods"
        }
    ],
    "sg:phone":"+1 314 721 5041",
    "sg:postcode":"63105",
    "sg:province":"MO",
    "sg:tags":[
        "printer"
    ],
    "wof:name":"Alpha Graphics",
    "wof:placetype":"venue"
},
  "geometry": {"coordinates":[-90.34366300000001,38.65228],"type":"Point"}
}