{
  "type": "Feature",
  "properties": {
    "addr:full":"444 Coronado Dr Ballwin MO 63011",
    "addr:housenumber":"444",
    "addr:postcode":"63011",
    "addr:street":"Coronado Dr",
    "iso:country":"US",
    "sg:address":"444 Coronado Dr",
    "sg:city":"Ballwin",
    "sg:classifiers":[
        {
            "category":"Professional",
            "subcategory":"Management & Consulting",
            "type":"Services"
        }
    ],
    "sg:phone":"+1 636 256 4726",
    "sg:postcode":"63011",
    "sg:province":"MO",
    "sg:tags":[
        "legal"
    ],
    "wof:name":"Royal Alliance Associates",
    "wof:placetype":"venue"
},
  "geometry": {"coordinates":[-90.546747,38.605448],"type":"Point"}
}