{
  "type": "Feature",
  "properties": {
    "iso:country":"US",
    "sg:address":"904 S 11th St",
    "sg:city":"St Joseph",
    "sg:classifiers":[
        {
            "category":"Organizations",
            "subcategory":"Religious Organization",
            "type":"Services"
        }
    ],
    "sg:phone":"+1 816 233 3000",
    "sg:postcode":"64503",
    "sg:province":"MO",
    "sg:tags":[
        "church"
    ],
    "wof:name":"Church Of God Rose Of Sharon",
    "wof:placetype":"venue"
},
  "geometry": {"coordinates":[-94.84683800000001,39.75811],"type":"Point"}
}