{
  "type": "Feature",
  "properties": {
    "iso:country":"US",
    "sg:address":"2759 Park Ave",
    "sg:city":"St Louis",
    "sg:classifiers":[
        {
            "category":"Professional",
            "subcategory":"Detective & Security Services",
            "type":"Services"
        },
        {
            "category":"Real Estate",
            "subcategory":"Real Estate Services",
            "type":"Services"
        }
    ],
    "sg:phone":"+1 314 772 1144",
    "sg:postcode":"63104",
    "sg:province":"MO",
    "sg:tags":[
        "finding",
        "car",
        "searching"
    ],
    "sg:website":"www.assetdiscoveryusa.com",
    "wof:name":"Asset Dscovery Locator Systems",
    "wof:placetype":"venue"
},
  "geometry": {"coordinates":[-90.22320499999999,38.618805],"type":"Point"}
}