{
  "type": "Feature",
  "properties": {
    "iso:country":"US",
    "sg:address":"17078 SW Peck Rd",
    "sg:city":"De Kalb",
    "sg:classifiers":[
        {
            "category":"Farming",
            "subcategory":"Farm & Veterinary Services",
            "type":"Manufacturing & Wholesale Goods"
        }
    ],
    "sg:phone":"+1 816 688 7835",
    "sg:postcode":"64440",
    "sg:province":"MO",
    "sg:tags":[
        "preparation",
        "soil"
    ],
    "wof:name":"Easter Custom Spreading Inc",
    "wof:placetype":"venue"
},
  "geometry": {"coordinates":[-94.97306,39.561322],"type":"Point"}
}