{
  "type": "Feature",
  "properties": {
    "iso:country":"US",
    "sg:address":"7852 Troxler Ln",
    "sg:city":"Lawson",
    "sg:classifiers":[
        {
            "category":"Social Services",
            "subcategory":"Child Care",
            "type":"Services"
        }
    ],
    "sg:phone":"+1 816 320 3600",
    "sg:postcode":"64062",
    "sg:province":"MO",
    "sg:tags":[
        "day"
    ],
    "wof:name":"Kid Corral LLC",
    "wof:placetype":"venue"
},
  "geometry": {"coordinates":[-94.272893,39.458546],"type":"Point"}
}