{
  "type": "Feature",
  "properties": {
    "iso:country":"US",
    "sg:address":"304 S Main St",
    "sg:city":"Campbell",
    "sg:classifiers":[
        {
            "category":"Retail",
            "subcategory":"Auto Repair",
            "type":"Services"
        }
    ],
    "sg:phone":"+1 573 246 2070",
    "sg:postcode":"63933",
    "sg:province":"MO",
    "sg:tags":[
        "body"
    ],
    "wof:name":"Davis Body Shop",
    "wof:placetype":"venue"
},
  "geometry": {"coordinates":[-90.07249400000001,36.492374],"type":"Point"}
}