{
  "type": "Feature",
  "properties": {
    "iso:country":"US",
    "sg:address":"719 W Main St",
    "sg:city":"Sedalia",
    "sg:classifiers":[
        {
            "category":"Freight",
            "type":"Transportation"
        }
    ],
    "sg:phone":"+1 660 826 6898",
    "sg:postcode":"65301",
    "sg:province":"MO",
    "sg:tags":[
        "mover"
    ],
    "wof:name":"Doty's Moving & Storage",
    "wof:placetype":"venue"
},
  "geometry": {"coordinates":[-93.235916,38.71205],"type":"Point"}
}