{
  "type": "Feature",
  "properties": {
    "iso:country":"US",
    "sg:address":"102 S 7th St",
    "sg:city":"King City",
    "sg:classifiers":[
        {
            "category":"Building & Trades",
            "subcategory":"Construction",
            "type":"Services"
        }
    ],
    "sg:phone":"+1 660 535 4523",
    "sg:postcode":"64463",
    "sg:province":"MO",
    "sg:tags":[
        "concrete",
        "contractor"
    ],
    "wof:name":"Ray Veale Construction",
    "wof:placetype":"venue"
},
  "geometry": {"coordinates":[-94.51187299999999,40.050674],"type":"Point"}
}