{
  "type": "Feature",
  "properties": {
    "iso:country":"US",
    "sg:address":"3878 W Elm Pl",
    "sg:city":"Arnold",
    "sg:classifiers":[
        {
            "category":"Building & Trades",
            "subcategory":"Construction",
            "type":"Services"
        }
    ],
    "sg:phone":"+1 636 296 5586",
    "sg:postcode":"63010",
    "sg:province":"MO",
    "sg:tags":[
        "nonresidential",
        "architect",
        "mfg"
    ],
    "wof:name":"Architctural Alum Stl Erectors",
    "wof:placetype":"venue"
},
  "geometry": {"coordinates":[-90.403792,38.407224],"type":"Point"}
}