{
  "type": "Feature",
  "properties": {
    "iso:country":"US",
    "sg:address":"3380 Tree Court Industrl Blvd",
    "sg:city":"Saint Louis",
    "sg:classifiers":[
        {
            "category":"Wholesale",
            "subcategory":"Hardware",
            "type":"Manufacturing & Wholesale Goods"
        }
    ],
    "sg:phone":"+1 636 225 3636",
    "sg:postcode":"63122",
    "sg:province":"MO",
    "sg:tags":[
        "refrigeration"
    ],
    "wof:name":"Angevine Company",
    "wof:placetype":"venue"
},
  "geometry": {"coordinates":[-90.460725,38.564865],"type":"Point"}
}