{
  "type": "Feature",
  "properties": {
    "iso:country":"US",
    "sg:address":"10212 Halls Ferry Rd",
    "sg:city":"St Louis",
    "sg:classifiers":[
        {
            "category":"Organizations",
            "subcategory":"Religious Organization",
            "type":"Services"
        }
    ],
    "sg:phone":"+1 314 869 7193",
    "sg:postcode":"63136",
    "sg:province":"MO",
    "sg:tags":[
        "church"
    ],
    "wof:name":"Dwight Mc Daniels Ministerial",
    "wof:placetype":"venue"
},
  "geometry": {"coordinates":[-90.257143,38.759026],"type":"Point"}
}