{
  "type": "Feature",
  "properties": {
    "iso:country":"US",
    "sg:address":"111 N Main St",
    "sg:city":"Hannibal",
    "sg:classifiers":[
        {
            "category":"Home & Garden",
            "subcategory":"Building Materials",
            "type":"Retail Goods"
        },
        {
            "category":"Museum",
            "type":"Entertainment"
        }
    ],
    "sg:phone":"+1 573 231 0133",
    "sg:postcode":"63401",
    "sg:province":"MO",
    "sg:tags":[
        "glass",
        "leaded",
        "gallery"
    ],
    "wof:name":"Raven's Nest Gallery",
    "wof:placetype":"venue"
},
  "geometry": {"coordinates":[-91.35638299999999,39.710408],"type":"Point"}
}