{
  "type": "Feature",
  "properties": {
    "iso:country":"US",
    "sg:address":"1455 N Nicholas Rd",
    "sg:city":"Nixa",
    "sg:classifiers":[
        {
            "category":"Building & Trades",
            "subcategory":"Construction",
            "type":"Services"
        },
        {
            "category":"Utilities",
            "type":"Services"
        }
    ],
    "sg:phone":"+1 417 725 2104",
    "sg:postcode":"65714",
    "sg:province":"MO",
    "sg:tags":[
        "contractor"
    ],
    "wof:name":"Ridge Hill Contractors, Inc.",
    "wof:placetype":"venue"
},
  "geometry": {"coordinates":[-93.325956,37.067964],"type":"Point"}
}