{
  "type": "Feature",
  "properties": {
    "iso:country":"US",
    "sg:address":"201 NE 2nd St",
    "sg:city":"Hardin",
    "sg:classifiers":[
        {
            "category":"Organizations",
            "subcategory":"Religious Organization",
            "type":"Services"
        }
    ],
    "sg:phone":"+1 660 398 4386",
    "sg:postcode":"64035",
    "sg:province":"MO",
    "wof:name":"First Baptist Church",
    "wof:placetype":"venue"
},
  "geometry": {"coordinates":[-93.83317700000001,39.270911],"type":"Point"}
}