{
  "type": "Feature",
  "properties": {
    "iso:country":"US",
    "sg:address":"705 NE Station Dr",
    "sg:city":"Lees Summit",
    "sg:classifiers":[
        {
            "category":"Communications",
            "subcategory":"Film & Video Production",
            "type":"Services"
        }
    ],
    "sg:phone":"+1 816 525 5008",
    "sg:postcode":"64086",
    "sg:province":"MO",
    "sg:tags":[
        "motion"
    ],
    "wof:name":"Kiss Systems",
    "wof:placetype":"venue"
},
  "geometry": {"coordinates":[-94.366275,38.93474],"type":"Point"}
}