{
  "type": "Feature",
  "properties": {
    "iso:country":"US",
    "sg:address":"523 SW Market St",
    "sg:city":"Lees Summit",
    "sg:classifiers":[
        {
            "category":"Building & Trades",
            "subcategory":"Construction",
            "type":"Services"
        }
    ],
    "sg:phone":"+1 816 554 9495",
    "sg:postcode":"64063",
    "sg:province":"MO",
    "sg:tags":[
        "dry wall",
        "contractor"
    ],
    "wof:name":"A M Interiors",
    "wof:placetype":"venue"
},
  "geometry": {"coordinates":[-94.377667,38.907555],"type":"Point"}
}