{
  "type": "Feature",
  "properties": {
    "iso:country":"US",
    "sg:address":"2107 Alameda Ave",
    "sg:city":"St Louis",
    "sg:classifiers":[
        {
            "category":"Real Estate",
            "subcategory":"Real Estate Agent",
            "type":"Services"
        },
        {
            "category":"Professional",
            "subcategory":"Art Services",
            "type":"Services"
        }
    ],
    "sg:phone":"+1 314 646 0642",
    "sg:postcode":"63143",
    "sg:province":"MO",
    "sg:tags":[
        "commercial",
        "design"
    ],
    "wof:name":"Mad Mac Corp",
    "wof:placetype":"venue"
},
  "geometry": {"coordinates":[-90.314584,38.620135],"type":"Point"}
}