{
  "type": "Feature",
  "properties": {
    "iso:country":"US",
    "sg:address":"1304 Main St",
    "sg:city":"Grandview",
    "sg:classifiers":[
        {
            "category":"Building & Trades",
            "subcategory":"Electrical",
            "type":"Services"
        }
    ],
    "sg:phone":"+1 816 765 0344",
    "sg:postcode":"64030",
    "sg:province":"MO",
    "sg:tags":[
        "electrical",
        "contractor"
    ],
    "wof:name":"Freedom Electric",
    "wof:placetype":"venue"
},
  "geometry": {"coordinates":[-94.52797200000001,38.889024],"type":"Point"}
}