{
  "type": "Feature",
  "properties": {
    "iso:country":"US",
    "sg:address":"612 W Maple St",
    "sg:city":"Raymore",
    "sg:classifiers":[
        {
            "category":"Professional",
            "subcategory":"Business Services",
            "type":"Services"
        }
    ],
    "sg:phone":"+1 816 331 5332",
    "sg:postcode":"64083",
    "sg:province":"MO",
    "wof:name":"Gjr Enterprise",
    "wof:placetype":"venue"
},
  "geometry": {"coordinates":[-94.463346,38.80332],"type":"Point"}
}