{
  "type": "Feature",
  "properties": {
    "iso:country":"US",
    "sg:address":"801 Belleau Creek Rd",
    "sg:city":"O Fallon",
    "sg:classifiers":[
        {
            "category":"Food & Beverages",
            "subcategory":"Candy",
            "type":"Retail Goods"
        },
        {
            "category":"Shopping",
            "subcategory":"Discount & Variety Stores",
            "type":"Retail Goods"
        }
    ],
    "sg:phone":"+1 636 978 7973",
    "sg:postcode":"63366",
    "sg:province":"MO",
    "sg:tags":[
        "merchandise",
        "general"
    ],
    "wof:name":"Quick Trip Store 640",
    "wof:placetype":"venue"
},
  "geometry": {"coordinates":[-90.677486,38.801348],"type":"Point"}
}