{
  "type": "Feature",
  "properties": {
    "iso:country":"US",
    "sg:address":"10851 Kroeger Rd",
    "sg:city":"Centralia",
    "sg:phone":"+1 573 682 3492",
    "sg:postcode":"65240",
    "sg:province":"MO",
    "sg:tags":[
        "communications",
        "telegraph"
    ],
    "wof:name":"Beckys Tax Secrets",
    "wof:placetype":"venue"
},
  "geometry": {"coordinates":[-92.173659,39.145947],"type":"Point"}
}