{
  "type": "Feature",
  "properties": {
    "iso:country":"US",
    "sg:address":"706 E Park St",
    "sg:city":"Stockton",
    "sg:classifiers":[
        {
            "category":"Building & Trades",
            "subcategory":"Construction",
            "type":"Services"
        }
    ],
    "sg:phone":"+1 417 276 2288",
    "sg:postcode":"65785",
    "sg:province":"MO",
    "sg:tags":[
        "shop",
        "cabinet"
    ],
    "wof:name":"Randys Cabinets",
    "wof:placetype":"venue"
},
  "geometry": {"coordinates":[-93.78869299999999,37.691324],"type":"Point"}
}