{
  "type": "Feature",
  "properties": {
    "iso:country":"US",
    "sg:address":"3521 Debbie Dr",
    "sg:city":"Festus",
    "sg:classifiers":[
        {
            "category":"Building & Trades",
            "subcategory":"Construction",
            "type":"Services"
        }
    ],
    "sg:phone":"+1 636 931 0921",
    "sg:postcode":"63028",
    "sg:province":"MO",
    "sg:tags":[
        "house"
    ],
    "wof:name":"B G Siding & Home Improvement",
    "wof:placetype":"venue"
},
  "geometry": {"coordinates":[-90.486862,38.220874],"type":"Point"}
}