{
  "type": "Feature",
  "properties": {
    "iso:country":"US",
    "sg:address":"111 Glashop Ln",
    "sg:city":"St Louis",
    "sg:classifiers":[
        {
            "category":"Personal",
            "subcategory":"Beauty Salon",
            "type":"Services"
        }
    ],
    "sg:phone":"+1 314 867 9618",
    "sg:postcode":"63137",
    "sg:province":"MO",
    "sg:tags":[
        "shop"
    ],
    "wof:name":"Hairspray & More",
    "wof:placetype":"venue"
},
  "geometry": {"coordinates":[-90.19512899999999,38.75332],"type":"Point"}
}