{
  "type": "Feature",
  "properties": {
    "iso:country":"US",
    "sg:address":"20 Jasmine Ct",
    "sg:city":"Saint Peters",
    "sg:classifiers":[
        {
            "category":"Building & Trades",
            "subcategory":"Construction",
            "type":"Services"
        }
    ],
    "sg:phone":"+1 636 447 7325",
    "sg:postcode":"63376",
    "sg:province":"MO",
    "sg:tags":[
        "contractor"
    ],
    "wof:name":"Antler Home Services Lc",
    "wof:placetype":"venue"
},
  "geometry": {"coordinates":[-90.561074,38.778412],"type":"Point"}
}