{
  "type": "Feature",
  "properties": {
    "iso:country":"US",
    "sg:address":"1301 NW Englewood Rd",
    "sg:city":"Kansas City",
    "sg:classifiers":[
        {
            "category":"Building & Trades",
            "subcategory":"Construction",
            "type":"Services"
        }
    ],
    "sg:phone":"+1 816 746 5151",
    "sg:postcode":"64118",
    "sg:province":"MO",
    "sg:tags":[
        "home",
        "builder"
    ],
    "wof:name":"Pulte Homes Corp",
    "wof:placetype":"venue"
},
  "geometry": {"coordinates":[-94.594308,39.195885],"type":"Point"}
}