{
  "type": "Feature",
  "properties": {
    "iso:country":"US",
    "sg:address":"18467 County Road 160",
    "sg:city":"Jasper",
    "sg:classifiers":[
        {
            "category":"Farming",
            "subcategory":"Livestock Farm",
            "type":"Manufacturing & Wholesale Goods"
        }
    ],
    "sg:phone":"+1 417 394 2756",
    "sg:postcode":"64755",
    "sg:province":"MO",
    "sg:tags":[
        "ranch"
    ],
    "wof:name":"Kenneth Arnold",
    "wof:placetype":"venue"
},
  "geometry": {"coordinates":[-94.342842,37.340801],"type":"Point"}
}