{
  "type": "Feature",
  "properties": {
    "iso:country":"US",
    "sg:address":"1910 N Grant Ave",
    "sg:city":"Springfield",
    "sg:classifiers":[
        {
            "category":"Health Services",
            "subcategory":"Clinic",
            "type":"Services"
        }
    ],
    "sg:phone":"+1 417 864 9800",
    "sg:postcode":"65803",
    "sg:province":"MO",
    "wof:name":"A Clear Sound",
    "wof:placetype":"venue"
},
  "geometry": {"coordinates":[-93.29786300000001,37.231946],"type":"Point"}
}