{
  "type": "Feature",
  "properties": {
    "iso:country":"US",
    "sg:address":"300 Ripley St",
    "sg:city":"Columbia",
    "sg:classifiers":[
        {
            "category":"Social Services",
            "subcategory":"Child Care",
            "type":"Services"
        }
    ],
    "sg:phone":"+1 573 449 7685",
    "sg:postcode":"65201",
    "sg:province":"MO",
    "sg:tags":[
        "day",
        "night"
    ],
    "wof:name":"Dolores L Heizelman",
    "wof:placetype":"venue"
},
  "geometry": {"coordinates":[-92.318434,38.955484],"type":"Point"}
}