{
  "type": "Feature",
  "properties": {
    "iso:country":"US",
    "sg:address":"13131 Tesson Ferry Rd",
    "sg:city":"St Louis",
    "sg:classifiers":[
        {
            "category":"Health Services",
            "subcategory":"Doctor",
            "type":"Services"
        }
    ],
    "sg:phone":"+1 314 842 9300",
    "sg:postcode":"63128",
    "sg:province":"MO",
    "sg:tags":[
        "dentist"
    ],
    "wof:name":"Blue Line Dental Ctr",
    "wof:placetype":"venue"
},
  "geometry": {"coordinates":[-90.383655,38.486237],"type":"Point"}
}