{
  "type": "Feature",
  "properties": {
    "iso:country":"US",
    "sg:address":"237 State Hwy Vv",
    "sg:city":"Fair Play",
    "sg:classifiers":[
        {
            "category":"Building & Trades",
            "subcategory":"Construction",
            "type":"Services"
        }
    ],
    "sg:phone":"+1 417 654 5009",
    "sg:postcode":"65649",
    "sg:province":"MO",
    "sg:tags":[
        "excavation",
        "contractor"
    ],
    "wof:name":"Randy Hughes Backhoe Svc",
    "wof:placetype":"venue"
},
  "geometry": {"coordinates":[-93.596485,37.588175],"type":"Point"}
}