{
  "type": "Feature",
  "properties": {
    "iso:country":"US",
    "sg:address":"120 W Walnut St",
    "sg:city":"Independence",
    "sg:classifiers":[
        {
            "category":"Social Services",
            "type":"Services"
        }
    ],
    "sg:phone":"+1 816 252 0086",
    "sg:postcode":"64050",
    "sg:province":"MO",
    "sg:tags":[
        "day",
        "center",
        "adult",
        "care"
    ],
    "wof:name":"Developing Potential Inc",
    "wof:placetype":"venue"
},
  "geometry": {"coordinates":[-94.41698599999999,39.090058],"type":"Point"}
}