{
  "type": "Feature",
  "properties": {
    "iso:country":"US",
    "sg:address":"1234 E Bennett St",
    "sg:city":"Springfield",
    "sg:classifiers":[
        {
            "category":"Real Estate",
            "subcategory":"Real Estate Agent",
            "type":"Services"
        }
    ],
    "sg:phone":"+1 417 868 0081",
    "sg:postcode":"65804",
    "sg:province":"MO",
    "wof:name":"Shawn Williams",
    "wof:placetype":"venue"
},
  "geometry": {"coordinates":[-93.27476299999999,37.189053],"type":"Point"}
}