{
  "type": "Feature",
  "properties": {
    "iso:country":"US",
    "sg:address":"1251 Garden Circle Dr",
    "sg:city":"St Louis",
    "sg:classifiers":[
        {
            "category":"Building & Trades",
            "subcategory":"Construction",
            "type":"Services"
        }
    ],
    "sg:phone":"+1 314 487 3399",
    "sg:postcode":"63125",
    "sg:province":"MO",
    "sg:tags":[
        "contractor"
    ],
    "wof:name":"Moellenhoff Building & Realty",
    "wof:placetype":"venue"
},
  "geometry": {"coordinates":[-90.301007,38.521019],"type":"Point"}
}