{
  "type": "Feature",
  "properties": {
    "iso:country":"US",
    "sg:address":"4371 Itaska St",
    "sg:city":"Saint Louis",
    "sg:classifiers":[
        {
            "category":"Professional",
            "subcategory":"Business Services",
            "type":"Services"
        }
    ],
    "sg:phone":"+1 314 481 7829",
    "sg:postcode":"63116",
    "sg:province":"MO",
    "wof:name":"CA Art & Design Studio",
    "wof:placetype":"venue"
},
  "geometry": {"coordinates":[-90.267983,38.583653],"type":"Point"}
}