{
  "type": "Feature",
  "properties": {
    "iso:country":"US",
    "sg:address":"685 Edgar Rd",
    "sg:city":"Saint Louis",
    "sg:classifiers":[
        {
            "category":"Utilities",
            "subcategory":"Telephone",
            "type":"Services"
        }
    ],
    "sg:phone":"+1 314 918 7966",
    "sg:postcode":"63119",
    "sg:province":"MO",
    "sg:tags":[
        "communications"
    ],
    "wof:name":"Qwest",
    "wof:placetype":"venue"
},
  "geometry": {"coordinates":[-90.346586,38.578867],"type":"Point"}
}