{
  "type": "Feature",
  "properties": {
    "iso:country":"US",
    "sg:address":"3520 W Sunshine St",
    "sg:city":"Springfield",
    "sg:classifiers":[
        {
            "category":"Restaurant",
            "type":"Food & Drink"
        }
    ],
    "sg:menulink":"http://www.allmenus.com/mo/springfield/148687-subway/menu/",
    "sg:phone":"+1 417 886 8300",
    "sg:postcode":"65807",
    "sg:province":"MO",
    "sg:tags":[
        "american",
        "sandwich"
    ],
    "wof:name":"Subway",
    "wof:placetype":"venue"
},
  "geometry": {"coordinates":[-93.352261,37.181824],"type":"Point"}
}