{
  "type": "Feature",
  "properties": {
    "iso:country":"US",
    "sg:address":"3424 S Vermont Ave",
    "sg:city":"Independence",
    "sg:classifiers":[
        {
            "category":"Retail",
            "subcategory":"Repair Shop",
            "type":"Services"
        }
    ],
    "sg:phone":"+1 816 836 4897",
    "sg:postcode":"64052",
    "sg:province":"MO",
    "sg:tags":[
        "plumbing",
        "drain",
        "cleaning",
        "sewer"
    ],
    "wof:name":"Rooter Guys",
    "wof:placetype":"venue"
},
  "geometry": {"coordinates":[-94.443354,39.058442],"type":"Point"}
}