{
  "type": "Feature",
  "properties": {
    "iso:country":"US",
    "sg:address":"251 SW Noel St",
    "sg:city":"Lees Summit",
    "sg:classifiers":[
        {
            "category":"Banks & Credit Unions",
            "subcategory":"Bank",
            "type":"Services"
        }
    ],
    "sg:phone":"+1 816 554 3530",
    "sg:postcode":"64063",
    "sg:province":"MO",
    "sg:tags":[
        "mortgage",
        "loan",
        "broker",
        "real estate"
    ],
    "wof:name":"Morrison Capital Corporation",
    "wof:placetype":"venue"
},
  "geometry": {"coordinates":[-94.38728399999999,38.911798],"type":"Point"}
}