{
  "type": "Feature",
  "properties": {
    "iso:country":"US",
    "sg:address":"225 S Main St",
    "sg:city":"Kennett",
    "sg:classifiers":[
        {
            "category":"Shopping",
            "type":"Retail Goods"
        }
    ],
    "sg:phone":"+1 573 717 7880",
    "sg:postcode":"63857",
    "sg:province":"MO",
    "sg:tags":[
        "art",
        "gallery",
        "dealer"
    ],
    "wof:name":"Conder's Art Gallery",
    "wof:placetype":"venue"
},
  "geometry": {"coordinates":[-90.056877,36.235267],"type":"Point"}
}