{
  "type": "Feature",
  "properties": {
    "iso:country":"US",
    "sg:address":"1509 Westport Rd",
    "sg:city":"Kansas City",
    "sg:classifiers":[
        {
            "category":"Professional",
            "subcategory":"Employment Agencies",
            "type":"Services"
        }
    ],
    "sg:phone":"+1 816 931 9950",
    "sg:postcode":"64111",
    "sg:province":"MO",
    "sg:tags":[
        "modeling"
    ],
    "wof:name":"I&I Model Group LLC",
    "wof:placetype":"venue"
},
  "geometry": {"coordinates":[-94.604455,39.050056],"type":"Point"}
}