{
  "type": "Feature",
  "properties": {
    "iso:country":"US",
    "sg:address":"35998 Oz Rd",
    "sg:city":"Salisbury",
    "sg:classifiers":[
        {
            "category":"Farming",
            "subcategory":"Farm",
            "type":"Manufacturing & Wholesale Goods"
        }
    ],
    "sg:phone":"+1 660 388 5553",
    "sg:postcode":"65281",
    "sg:province":"MO",
    "wof:name":"Rodney Lewis",
    "wof:placetype":"venue"
},
  "geometry": {"coordinates":[-92.79898799999999,39.36565],"type":"Point"}
}