{
  "type": "Feature",
  "properties": {
    "iso:country":"US",
    "sg:address":"704 State Hwy 73",
    "sg:city":"Macks Creek",
    "sg:classifiers":[
        {
            "category":"Organizations",
            "subcategory":"Religious Organization",
            "type":"Services"
        }
    ],
    "sg:phone":"+1 573 363 5234",
    "sg:postcode":"65786",
    "sg:province":"MO",
    "wof:name":"Branch Assembly of God",
    "wof:placetype":"venue"
},
  "geometry": {"coordinates":[-93.00641400000001,37.921582],"type":"Point"}
}