{
  "type": "Feature",
  "properties": {
    "iso:country":"US",
    "sg:address":"2234 S Dollison Ave",
    "sg:city":"Springfield",
    "sg:classifiers":[
        {
            "category":"Manufacturing",
            "subcategory":"Petroleum Products",
            "type":"Manufacturing & Wholesale Goods"
        }
    ],
    "sg:phone":"+1 417 823 9660",
    "sg:postcode":"65807",
    "sg:province":"MO",
    "wof:name":"Petroleum Management Equipment",
    "wof:placetype":"venue"
},
  "geometry": {"coordinates":[-93.283834,37.171763],"type":"Point"}
}