{
  "type": "Feature",
  "properties": {
    "iso:country":"US",
    "sg:address":"4527 Virginia Ave",
    "sg:city":"Saint Louis",
    "sg:classifiers":[
        {
            "category":"Real Estate",
            "subcategory":"Architect",
            "type":"Services"
        }
    ],
    "sg:phone":"+1 314 832 3350",
    "sg:postcode":"63111",
    "sg:province":"MO",
    "wof:name":"Anthony Duncan Architect",
    "wof:placetype":"venue"
},
  "geometry": {"coordinates":[-90.24305099999999,38.574583],"type":"Point"}
}