{
  "type": "Feature",
  "properties": {
    "iso:country":"US",
    "sg:address":"237 S Broadview St",
    "sg:city":"Cape Girardeau",
    "sg:classifiers":[
        {
            "category":"Banks & Credit Unions",
            "subcategory":"Bank",
            "type":"Services"
        }
    ],
    "sg:phone":"+1 573 335 0550",
    "sg:postcode":"63703",
    "sg:province":"MO",
    "sg:tags":[
        "loan"
    ],
    "wof:name":"Premier Cash Advance Inc",
    "wof:placetype":"venue"
},
  "geometry": {"coordinates":[-89.55677799999999,37.302405],"type":"Point"}
}