{
  "type": "Feature",
  "properties": {
    "iso:country":"US",
    "sg:address":"851 E 5th St",
    "sg:city":"Washington",
    "sg:classifiers":[
        {
            "category":"Health Services",
            "subcategory":"Doctor",
            "type":"Services"
        }
    ],
    "sg:phone":"+1 636 239 6808",
    "sg:postcode":"63090",
    "sg:province":"MO",
    "sg:tags":[
        "physician",
        "family",
        "practice",
        "surgeons",
        "medicine",
        "surgeon"
    ],
    "wof:name":"Kunkel Robert MD",
    "wof:placetype":"venue"
},
  "geometry": {"coordinates":[-91.002668,38.55245],"type":"Point"}
}