{
  "type": "Feature",
  "properties": {
    "iso:country":"US",
    "sg:address":"980 N Kingshighway St",
    "sg:city":"Saint Charles",
    "sg:classifiers":[
        {
            "category":"Retail",
            "subcategory":"Veterinary Services",
            "type":"Services"
        }
    ],
    "sg:phone":"+1 636 723 2400",
    "sg:postcode":"63301",
    "sg:province":"MO",
    "wof:name":"Crecelius Mike K",
    "wof:placetype":"venue"
},
  "geometry": {"coordinates":[-90.48499,38.791309],"type":"Point"}
}