{
  "type": "Feature",
  "properties": {
    "iso:country":"US",
    "sg:address":"407 E Lafayette",
    "sg:city":"Edina",
    "sg:classifiers":[
        {
            "category":"Retail",
            "subcategory":"Auto Repair",
            "type":"Services"
        }
    ],
    "sg:phone":"+1 660 397 2310",
    "sg:postcode":"63537",
    "sg:province":"MO",
    "sg:tags":[
        "general"
    ],
    "wof:name":"Morgrets Garage Inc",
    "wof:placetype":"venue"
},
  "geometry": {"coordinates":[-92.171425,40.16746],"type":"Point"}
}