{
  "type": "Feature",
  "properties": {
    "iso:country":"US",
    "sg:address":"2197 S Farm Rd 245",
    "sg:city":"Rogersville",
    "sg:classifiers":[
        {
            "category":"Arts & Performance",
            "subcategory":"Theater",
            "type":"Entertainment"
        }
    ],
    "sg:phone":"+1 417 753 2723",
    "sg:postcode":"65742",
    "sg:province":"MO",
    "sg:tags":[
        "live",
        "music"
    ],
    "wof:name":"Ear Wax Sounds & Lights",
    "wof:placetype":"venue"
},
  "geometry": {"coordinates":[-93.09130500000001,37.170681],"type":"Point"}
}