{
  "type": "Feature",
  "properties": {
    "iso:country":"US",
    "sg:address":"266 Oak Ridge Dr",
    "sg:city":"Lake Ozark",
    "sg:classifiers":[
        {
            "category":"Building & Trades",
            "subcategory":"Construction",
            "type":"Services"
        }
    ],
    "sg:phone":"+1 573 964 6220",
    "sg:postcode":"65049",
    "sg:province":"MO",
    "sg:tags":[
        "excavation",
        "excavating",
        "contractor"
    ],
    "wof:name":"Whitman Cash Construction",
    "wof:placetype":"venue"
},
  "geometry": {"coordinates":[-92.620884,38.176191],"type":"Point"}
}