{
  "type": "Feature",
  "properties": {
    "iso:country":"US",
    "sg:address":"8800 NW 112th St",
    "sg:city":"Kansas City",
    "sg:classifiers":[
        {
            "category":"Professional",
            "type":"Services"
        }
    ],
    "sg:phone":"+1 816 243 2020",
    "sg:postcode":"64153",
    "sg:province":"MO",
    "sg:tags":[
        "establishment"
    ],
    "wof:name":"CSG Consultants",
    "wof:placetype":"venue"
},
  "geometry": {"coordinates":[-94.679103,39.29669],"type":"Point"}
}