{
  "type": "Feature",
  "properties": {
    "iso:country":"US",
    "sg:address":"109 Old State Rd",
    "sg:city":"Ballwin",
    "sg:classifiers":[
        {
            "category":"Building & Trades",
            "subcategory":"Electrical",
            "type":"Services"
        },
        {
            "category":"Manufacturing",
            "subcategory":"Electronics",
            "type":"Manufacturing & Wholesale Goods"
        }
    ],
    "sg:phone":"+1 636 227 0152",
    "sg:postcode":"63021",
    "sg:province":"MO",
    "sg:tags":[
        "control",
        "security",
        "electrical",
        "system",
        "contractor"
    ],
    "wof:name":"Pro-Guard Inc",
    "wof:placetype":"venue"
},
  "geometry": {"coordinates":[-90.595354,38.590573],"type":"Point"}
}