{
  "type": "Feature",
  "properties": {
    "iso:country":"US",
    "sg:address":"614 W Bain St",
    "sg:city":"Dexter",
    "sg:classifiers":[
        {
            "category":"Professional",
            "subcategory":"Business Services",
            "type":"Services"
        }
    ],
    "sg:phone":"+1 573 820 0515",
    "sg:postcode":"63841",
    "sg:province":"MO",
    "wof:name":"Sandra G Prunty",
    "wof:placetype":"venue"
},
  "geometry": {"coordinates":[-89.967168,36.791727],"type":"Point"}
}