{
  "type": "Feature",
  "properties": {
    "iso:country":"US",
    "sg:address":"810 Briarwood Ln",
    "sg:city":"Nevada",
    "sg:classifiers":[
        {
            "category":"Professional",
            "subcategory":"Detective & Security Services",
            "type":"Services"
        }
    ],
    "sg:phone":"+1 417 321 0977",
    "sg:postcode":"64772",
    "sg:province":"MO",
    "sg:tags":[
        "information",
        "bureau"
    ],
    "wof:name":"Worthington Mowing Services",
    "wof:placetype":"venue"
},
  "geometry": {"coordinates":[-94.367615,37.828734],"type":"Point"}
}