{
  "type": "Feature",
  "properties": {
    "iso:country":"US",
    "sg:address":"6300 N Oak Fwy",
    "sg:city":"Kansas City",
    "sg:classifiers":[
        {
            "category":"Restaurant",
            "type":"Food & Drink"
        }
    ],
    "sg:phone":"+1 816 453 7111",
    "sg:postcode":"64118",
    "sg:province":"MO",
    "wof:name":"Dominic's Pizza & Pasta",
    "wof:placetype":"venue"
},
  "geometry": {"coordinates":[-94.576347,39.20716],"type":"Point"}
}