{
  "type": "Feature",
  "properties": {
    "iso:country":"US",
    "sg:address":"34541 State Hwy Ff",
    "sg:city":"Bevier",
    "sg:classifiers":[
        {
            "category":"Professional",
            "type":"Services"
        }
    ],
    "sg:phone":"+1 660 775 2610",
    "sg:postcode":"63532",
    "sg:province":"MO",
    "wof:name":"Randy Spickard",
    "wof:placetype":"venue"
},
  "geometry": {"coordinates":[-92.595095,39.688189],"type":"Point"}
}