{
  "type": "Feature",
  "properties": {
    "iso:country":"US",
    "sg:address":"2940 Benton St",
    "sg:city":"Saint Louis",
    "sg:classifiers":[
        {
            "category":"Home & Garden",
            "subcategory":"Carpets & Floor Coverings",
            "type":"Retail Goods"
        }
    ],
    "sg:phone":"+1 314 772 3996",
    "sg:postcode":"63106",
    "sg:province":"MO",
    "sg:tags":[
        "carpeting"
    ],
    "wof:name":"Jjs Flooring & Decorating Co",
    "wof:placetype":"venue"
},
  "geometry": {"coordinates":[-90.218903,38.6502],"type":"Point"}
}