{
  "type": "Feature",
  "properties": {
    "iso:country":"US",
    "sg:address":"241 Paris St",
    "sg:city":"Kansas City",
    "sg:classifiers":[
        {
            "category":"Coffee & Tea",
            "type":"Food & Drink"
        }
    ],
    "sg:menulink":"http://www.allmenus.com/mo/carroll/115233-starbucks-coffee/menu/",
    "sg:phone":"+1 816 243 5700",
    "sg:postcode":"64153",
    "sg:province":"MO",
    "sg:tags":[
        "american"
    ],
    "wof:name":"Starbucks Coffee",
    "wof:placetype":"venue"
},
  "geometry": {"coordinates":[-94.71736300000001,39.303107],"type":"Point"}
}