{
  "type": "Feature",
  "properties": {
    "iso:country":"US",
    "sg:address":"8178 Snowdell Rd",
    "sg:city":"Bonne Terre",
    "sg:classifiers":[
        {
            "category":"Retail",
            "subcategory":"Repair Shop",
            "type":"Services"
        }
    ],
    "sg:phone":"+1 573 358 3697",
    "sg:postcode":"63628",
    "sg:province":"MO",
    "sg:tags":[
        "welding"
    ],
    "wof:name":"Watkins Welding",
    "wof:placetype":"venue"
},
  "geometry": {"coordinates":[-90.404292,37.953627],"type":"Point"}
}