{
  "type": "Feature",
  "properties": {
    "iso:country":"US",
    "sg:address":"26713 S Brickplant Rd",
    "sg:city":"Harrisonville",
    "sg:classifiers":[
        {
            "category":"Building & Trades",
            "subcategory":"Construction",
            "type":"Services"
        }
    ],
    "sg:phone":"+1 816 380 7411",
    "sg:postcode":"64701",
    "sg:province":"MO",
    "sg:tags":[
        "downspouts",
        "gutter"
    ],
    "wof:name":"Goforth Guttering & Siding",
    "wof:placetype":"venue"
},
  "geometry": {"coordinates":[-94.361445,38.632059],"type":"Point"}
}