{
  "type": "Feature",
  "properties": {
    "iso:country":"US",
    "sg:address":"1815 Cape la Croix Rd",
    "sg:city":"Cape Girardeau",
    "sg:classifiers":[
        {
            "category":"Freight",
            "type":"Transportation"
        },
        {
            "category":"Retail",
            "subcategory":"Auto Rental",
            "type":"Services"
        }
    ],
    "sg:phone":"+1 573 332 7867",
    "sg:postcode":"63701",
    "sg:province":"MO",
    "sg:tags":[
        "storage",
        "commercial",
        "truck"
    ],
    "wof:name":"A A A Mini Storage",
    "wof:placetype":"venue"
},
  "geometry": {"coordinates":[-89.570155,37.332298],"type":"Point"}
}