{
  "type": "Feature",
  "properties": {
    "iso:country":"US",
    "sg:address":"6218 Stratford Glen Ct",
    "sg:city":"Saint Louis",
    "sg:classifiers":[
        {
            "category":"Personal",
            "type":"Services"
        }
    ],
    "sg:phone":"+1 314 845 8989",
    "sg:postcode":"63129",
    "sg:province":"MO",
    "wof:name":"Reliable Handyman",
    "wof:placetype":"venue"
},
  "geometry": {"coordinates":[-90.368405,38.463989],"type":"Point"}
}