{
  "type": "Feature",
  "properties": {
    "iso:country":"US",
    "sg:address":"7626 Wydown Blvd",
    "sg:city":"St Louis",
    "sg:classifiers":[
        {
            "category":"Education",
            "subcategory":"Special Training",
            "type":"Public Place"
        }
    ],
    "sg:phone":"+1 314 727 5938",
    "sg:postcode":"63105",
    "sg:province":"MO",
    "sg:tags":[
        "instruction",
        "music"
    ],
    "wof:name":"Clayton Academy of Music",
    "wof:placetype":"venue"
},
  "geometry": {"coordinates":[-90.334947,38.642935],"type":"Point"}
}