{
  "type": "Feature",
  "properties": {
    "iso:country":"US",
    "sg:address":"876 S Rocky Rd",
    "sg:city":"Carthage",
    "sg:classifiers":[
        {
            "category":"Wholesale",
            "subcategory":"Construction Materials",
            "type":"Manufacturing & Wholesale Goods"
        }
    ],
    "sg:phone":"+1 417 358 2332",
    "sg:postcode":"64836",
    "sg:province":"MO",
    "wof:name":"Lumber Specialists Inc",
    "wof:placetype":"venue"
},
  "geometry": {"coordinates":[-94.35186,37.170661],"type":"Point"}
}