{
  "type": "Feature",
  "properties": {
    "iso:country":"US",
    "sg:address":"6443 W Range Farm Ln",
    "sg:city":"Willard",
    "sg:classifiers":[
        {
            "category":"Farming",
            "subcategory":"Farm",
            "type":"Manufacturing & Wholesale Goods"
        }
    ],
    "sg:phone":"+1 417 742 2437",
    "sg:postcode":"65781",
    "sg:province":"MO",
    "wof:name":"Range Farm",
    "wof:placetype":"venue"
},
  "geometry": {"coordinates":[-93.41429599999999,37.375843],"type":"Point"}
}