{
  "type": "Feature",
  "properties": {
    "iso:country":"US",
    "sg:address":"2601 Aurora Ave",
    "sg:city":"Maryville",
    "sg:classifiers":[
        {
            "category":"Manufacturing",
            "subcategory":"Building Materials",
            "type":"Manufacturing & Wholesale Goods"
        }
    ],
    "sg:phone":"+1 660 582 3571",
    "sg:postcode":"64468",
    "sg:province":"MO",
    "sg:tags":[
        "repair",
        "mfg"
    ],
    "wof:name":"World of Wood",
    "wof:placetype":"venue"
},
  "geometry": {"coordinates":[-94.87053400000001,40.319704],"type":"Point"}
}