{
  "type": "Feature",
  "properties": {
    "iso:country":"US",
    "sg:address":"1073 Mace Rd",
    "sg:city":"Osage Beach",
    "sg:classifiers":[
        {
            "category":"Real Estate",
            "subcategory":"Real Estate Operator",
            "type":"Services"
        }
    ],
    "sg:phone":"+1 573 348 1817",
    "sg:postcode":"65065",
    "sg:province":"MO",
    "sg:tags":[
        "apartment"
    ],
    "wof:name":"Osage Beach Senior Housing",
    "wof:placetype":"venue"
},
  "geometry": {"coordinates":[-92.610983,38.16711],"type":"Point"}
}