{
  "type": "Feature",
  "properties": {
    "iso:country":"US",
    "sg:address":"3644 Scarlet Oak Blvd",
    "sg:city":"St Louis",
    "sg:classifiers":[
        {
            "category":"Manufacturing",
            "subcategory":"Tools & Machinery",
            "type":"Manufacturing & Wholesale Goods"
        }
    ],
    "sg:phone":"+1 636 225 5310",
    "sg:postcode":"63122",
    "sg:province":"MO",
    "sg:tags":[
        "shop",
        "repair",
        "industrial",
        "mfg",
        "machine",
        "aircraft",
        "pa",
        "welding"
    ],
    "sg:website":"www.davlan.com",
    "wof:name":"Davlan Engineering Inc",
    "wof:placetype":"venue"
},
  "geometry": {"coordinates":[-90.45483400000001,38.562082],"type":"Point"}
}