{
  "type": "Feature",
  "properties": {
    "iso:country":"US",
    "sg:address":"5085 US Hwy 54",
    "sg:city":"Osage Beach",
    "sg:classifiers":[
        {
            "category":"Restaurant",
            "type":"Food & Drink"
        }
    ],
    "sg:phone":"+1 573 348 5053",
    "sg:postcode":"65065",
    "sg:province":"MO",
    "wof:name":"Potted Steer",
    "wof:placetype":"venue"
},
  "geometry": {"coordinates":[-92.645692,38.133345],"type":"Point"}
}