{
  "type": "Feature",
  "properties": {
    "iso:country":"US",
    "sg:address":"13211 Dunroyal Dr",
    "sg:city":"Saint Louis",
    "sg:classifiers":[
        {
            "category":"Health Services",
            "subcategory":"Doctor",
            "type":"Services"
        }
    ],
    "sg:phone":"+1 314 821 3278",
    "sg:postcode":"63131",
    "sg:province":"MO",
    "sg:tags":[
        "medical"
    ],
    "wof:name":"Joseph Hazan Inc",
    "wof:placetype":"venue"
},
  "geometry": {"coordinates":[-90.46338,38.595398],"type":"Point"}
}