{
  "type": "Feature",
  "properties": {
    "iso:country":"US",
    "sg:address":"1801 Grothe Rd",
    "sg:city":"Wentzville",
    "sg:classifiers":[
        {
            "category":"Building & Trades",
            "subcategory":"Construction",
            "type":"Services"
        }
    ],
    "sg:phone":"+1 636 332 6886",
    "sg:postcode":"63385",
    "sg:province":"MO",
    "sg:tags":[
        "house"
    ],
    "wof:name":"R&C Builders & Ridgway St",
    "wof:placetype":"venue"
},
  "geometry": {"coordinates":[-90.860862,38.844578],"type":"Point"}
}