{
  "type": "Feature",
  "properties": {
    "iso:country":"US",
    "sg:address":"900 Martin Dr",
    "sg:city":"Columbia",
    "sg:classifiers":[
        {
            "category":"Education",
            "subcategory":"Preschool",
            "type":"Public Place"
        }
    ],
    "sg:phone":"+1 573 875 3018",
    "sg:postcode":"65203",
    "sg:province":"MO",
    "sg:tags":[
        "kindergarten"
    ],
    "wof:name":"Stepping Stones Preschool",
    "wof:placetype":"venue"
},
  "geometry": {"coordinates":[-92.37436700000001,38.944649],"type":"Point"}
}