{
  "type": "Feature",
  "properties": {
    "iso:country":"US",
    "sg:address":"19570 Newton Rd",
    "sg:city":"Diamond",
    "sg:classifiers":[
        {
            "category":"Building & Trades",
            "subcategory":"Landscaping Services",
            "type":"Services"
        }
    ],
    "sg:phone":"+1 417 325 7424",
    "sg:postcode":"64840",
    "sg:province":"MO",
    "sg:tags":[
        "tree"
    ],
    "wof:name":"Reasonable Stump Removal",
    "wof:placetype":"venue"
},
  "geometry": {"coordinates":[-94.292843,37.053294],"type":"Point"}
}