{
  "type": "Feature",
  "properties": {
    "iso:country":"US",
    "sg:address":"2700 NW S Outer Rd",
    "sg:city":"Blue Springs",
    "sg:classifiers":[
        {
            "category":"Wholesale",
            "subcategory":"Construction Materials",
            "type":"Manufacturing & Wholesale Goods"
        },
        {
            "category":"Building & Trades",
            "subcategory":"Construction",
            "type":"Services"
        }
    ],
    "sg:phone":"+1 816 228 0330",
    "sg:postcode":"64015",
    "sg:province":"MO",
    "sg:tags":[
        "tile",
        "dealer"
    ],
    "wof:name":"Elite Tile and Stone Inc",
    "wof:placetype":"venue"
},
  "geometry": {"coordinates":[-94.288562,39.031465],"type":"Point"}
}