{
  "type": "Feature",
  "properties": {
    "iso:country":"US",
    "sg:address":"13489 Maries Road 301",
    "sg:city":"Vienna",
    "sg:classifiers":[
        {
            "category":"Organizations",
            "subcategory":"Religious Organization",
            "type":"Services"
        }
    ],
    "sg:phone":"+1 573 744 5843",
    "sg:postcode":"65582",
    "sg:province":"MO",
    "sg:tags":[
        "church"
    ],
    "wof:name":"Faith Fellowship Church",
    "wof:placetype":"venue"
},
  "geometry": {"coordinates":[-91.87418099999999,38.285881],"type":"Point"}
}