{
  "type": "Feature",
  "properties": {
    "iso:country":"US",
    "sg:address":"3010 Olive St",
    "sg:city":"Saint Louis",
    "sg:classifiers":[
        {
            "category":"Social Services",
            "subcategory":"Child Care",
            "type":"Services"
        }
    ],
    "sg:phone":"+1 314 531 9555",
    "sg:postcode":"63103",
    "sg:province":"MO",
    "sg:tags":[
        "day"
    ],
    "wof:name":"Berea Head Start",
    "wof:placetype":"venue"
},
  "geometry": {"coordinates":[-90.221783,38.634657],"type":"Point"}
}