{
  "type": "Feature",
  "properties": {
    "iso:country":"US",
    "sg:address":"125 E Main St",
    "sg:city":"Jackson",
    "sg:classifiers":[
        {
            "category":"Organizations",
            "subcategory":"Professional Association",
            "type":"Services"
        }
    ],
    "sg:phone":"+1 573 243 8131",
    "sg:postcode":"63755",
    "sg:province":"MO",
    "sg:tags":[
        "chambers",
        "commerce"
    ],
    "sg:website":"www.jacksonmo.com",
    "wof:name":"Jackson Chamber Of Commerce",
    "wof:placetype":"venue"
},
  "geometry": {"coordinates":[-89.667298,37.382429],"type":"Point"}
}