{
  "type": "Feature",
  "properties": {
    "iso:country":"US",
    "sg:address":"721 Villa Capri Ct",
    "sg:city":"St Louis",
    "sg:classifiers":[
        {
            "category":"Health Services",
            "subcategory":"Health Practitioner",
            "type":"Services"
        }
    ],
    "sg:phone":"+1 314 432 2549",
    "sg:postcode":"63132",
    "sg:province":"MO",
    "sg:tags":[
        "psychotherapist"
    ],
    "wof:name":"Nicki Mc Clusky",
    "wof:placetype":"venue"
},
  "geometry": {"coordinates":[-90.368352,38.669756],"type":"Point"}
}