{
  "type": "Feature",
  "properties": {
    "addr:full":"1156 NE 84th Ter Kansas City MO 64155",
    "addr:housenumber":"1156",
    "addr:postcode":"64155",
    "addr:street":"Ne 84Th Ter",
    "iso:country":"US",
    "sg:address":"1156 NE 84th Ter",
    "sg:city":"Kansas City",
    "sg:classifiers":[
        {
            "category":"Manufacturing",
            "subcategory":"Printing",
            "type":"Manufacturing & Wholesale Goods"
        }
    ],
    "sg:phone":"+1 816 436 4287",
    "sg:postcode":"64155",
    "sg:province":"MO",
    "sg:tags":[
        "publishing"
    ],
    "wof:name":"Minuteman Press",
    "wof:placetype":"venue"
},
  "geometry": {"coordinates":[-94.565292,39.24745],"type":"Point"}
}