{
  "type": "Feature",
  "properties": {
    "iso:country":"US",
    "sg:address":"6501 E 58 St",
    "sg:city":"Kansas City",
    "sg:classifiers":[
        {
            "category":"Farming",
            "subcategory":"Nursery",
            "type":"Manufacturing & Wholesale Goods"
        }
    ],
    "sg:phone":"+1 816 924 3835",
    "sg:postcode":"64129",
    "sg:province":"MO",
    "sg:tags":[
        "ornamental"
    ],
    "wof:name":"Lewis Greenhouse",
    "wof:placetype":"venue"
},
  "geometry": {"coordinates":[-94.510059,39.019394],"type":"Point"}
}