{
  "type": "Feature",
  "properties": {
    "iso:country":"US",
    "sg:address":"1317 State Hwy 84",
    "sg:city":"Hayti",
    "sg:classifiers":[
        {
            "category":"Education",
            "subcategory":"School",
            "type":"Public Place"
        }
    ],
    "sg:phone":"+1 573 359 0011",
    "sg:postcode":"63851",
    "sg:province":"MO",
    "wof:name":"Oakview Learning Center",
    "wof:placetype":"venue"
},
  "geometry": {"coordinates":[-89.766046,36.233849],"type":"Point"}
}