{
  "type": "Feature",
  "properties": {
    "iso:country":"US",
    "sg:address":"10910 US Hwy 40",
    "sg:city":"Independence",
    "sg:classifiers":[
        {
            "category":"Restaurant",
            "type":"Food & Drink"
        }
    ],
    "sg:phone":"+1 816 353 8990",
    "sg:postcode":"64055",
    "sg:province":"MO",
    "wof:name":"Subway Sandwiches & Salads",
    "wof:placetype":"venue"
},
  "geometry": {"coordinates":[-94.450472,39.051044],"type":"Point"}
}