{
  "type": "Feature",
  "properties": {
    "iso:country":"US",
    "sg:address":"5822 S Grand Blvd",
    "sg:city":"Saint Louis",
    "sg:classifiers":[
        {
            "category":"Shopping",
            "subcategory":"Musical Instruments",
            "type":"Retail Goods"
        }
    ],
    "sg:phone":"+1 314 352 7380",
    "sg:postcode":"63111",
    "sg:province":"MO",
    "sg:tags":[
        "piano",
        "teacher"
    ],
    "wof:name":"Classic Keyboards of St Louis",
    "wof:placetype":"venue"
},
  "geometry": {"coordinates":[-90.256203,38.566601],"type":"Point"}
}