{
  "type": "Feature",
  "properties": {
    "iso:country":"US",
    "sg:address":"401 Edwin St",
    "sg:city":"St Louis",
    "sg:classifiers":[
        {
            "category":"Building & Trades",
            "subcategory":"Construction",
            "type":"Services"
        },
        {
            "category":"Building & Trades",
            "subcategory":"Plumbing",
            "type":"Services"
        }
    ],
    "sg:phone":"+1 314 533 2157",
    "sg:postcode":"63103",
    "sg:province":"MO",
    "sg:tags":[
        "tile",
        "dealer",
        "contractor"
    ],
    "wof:name":"Shower Enclosure Service Co",
    "wof:placetype":"venue"
},
  "geometry": {"coordinates":[-90.23154100000001,38.629681],"type":"Point"}
}