{
  "type": "Feature",
  "properties": {
    "iso:country":"US",
    "sg:address":"600 Silvey St",
    "sg:city":"Columbia",
    "sg:classifiers":[
        {
            "category":"Education",
            "subcategory":"School",
            "type":"Public Place"
        }
    ],
    "sg:phone":"+1 573 446 1981",
    "sg:postcode":"65203",
    "sg:province":"MO",
    "sg:tags":[
        "deaf",
        "for"
    ],
    "wof:name":"Moog Center Columbia",
    "wof:placetype":"venue"
},
  "geometry": {"coordinates":[-92.389616,38.963912],"type":"Point"}
}