{
  "type": "Feature",
  "properties": {
    "iso:country":"US",
    "sg:address":"323 Marceau St",
    "sg:city":"Saint Louis",
    "sg:classifiers":[
        {
            "category":"Organizations",
            "subcategory":"Religious Organization",
            "type":"Services"
        }
    ],
    "sg:phone":"+1 314 631 7985",
    "sg:postcode":"63111",
    "sg:province":"MO",
    "wof:name":"Friendship Day Care",
    "wof:placetype":"venue"
},
  "geometry": {"coordinates":[-90.26653,38.543248],"type":"Point"}
}