{
  "type": "Feature",
  "properties": {
    "iso:country":"US",
    "sg:address":"327 Stoddard St",
    "sg:city":"Monroe City",
    "sg:classifiers":[
        {
            "category":"Retail",
            "subcategory":"Auto Repair",
            "type":"Services"
        }
    ],
    "sg:phone":"+1 573 735 2833",
    "sg:postcode":"63456",
    "sg:province":"MO",
    "sg:tags":[
        "general"
    ],
    "wof:name":"Car Shop",
    "wof:placetype":"venue"
},
  "geometry": {"coordinates":[-91.732232,39.657654],"type":"Point"}
}