{
  "type": "Feature",
  "properties": {
    "iso:country":"US",
    "sg:address":"7536 Wellington Way",
    "sg:city":"St Louis",
    "sg:classifiers":[
        {
            "category":"Real Estate",
            "subcategory":"Real Estate Agent",
            "type":"Services"
        }
    ],
    "sg:phone":"+1 314 863 2103",
    "sg:postcode":"63105",
    "sg:province":"MO",
    "sg:tags":[
        "broker"
    ],
    "wof:name":"Novoson Real Estate",
    "wof:placetype":"venue"
},
  "geometry": {"coordinates":[-90.33207400000001,38.639041],"type":"Point"}
}