{
  "type": "Feature",
  "properties": {
    "iso:country":"US",
    "sg:address":"114 McDonald Ln",
    "sg:city":"O Fallon",
    "sg:classifiers":[
        {
            "category":"Retail",
            "subcategory":"Auto Repair",
            "type":"Services"
        }
    ],
    "sg:phone":"+1 636 281 2111",
    "sg:postcode":"63366",
    "sg:province":"MO",
    "sg:tags":[
        "body",
        "automobile",
        "painting"
    ],
    "wof:name":"Body Shop Inc",
    "wof:placetype":"venue"
},
  "geometry": {"coordinates":[-90.698082,38.801425],"type":"Point"}
}