{
  "type": "Feature",
  "properties": {
    "iso:country":"US",
    "sg:address":"38919 W 115th Ave",
    "sg:city":"Mc Fall",
    "sg:classifiers":[
        {
            "category":"Real Estate",
            "subcategory":"Real Estate Operator",
            "type":"Services"
        }
    ],
    "sg:phone":"+1 660 439 2811",
    "sg:postcode":"64657",
    "sg:province":"MO",
    "sg:tags":[
        "property",
        "lessor"
    ],
    "wof:name":"Clifford Burris",
    "wof:placetype":"venue"
},
  "geometry": {"coordinates":[-94.207472,40.151091],"type":"Point"}
}