{
  "type": "Feature",
  "properties": {
    "iso:country":"US",
    "sg:address":"500 Lake Ave",
    "sg:city":"Webster Groves",
    "sg:classifiers":[
        {
            "category":"Education",
            "subcategory":"Special Training",
            "type":"Public Place"
        }
    ],
    "sg:phone":"+1 314 962 0459",
    "sg:postcode":"63119",
    "sg:province":"MO",
    "sg:tags":[
        "program"
    ],
    "wof:name":"Building Good Beginnings",
    "wof:placetype":"venue"
},
  "geometry": {"coordinates":[-90.341387,38.592182],"type":"Point"}
}