{
  "type": "Feature",
  "properties": {
    "iso:country":"US",
    "sg:address":"1000 NE McCarthy Ave",
    "sg:city":"Kansas City",
    "sg:classifiers":[
        {
            "category":"Professional",
            "subcategory":"Computer Services",
            "type":"Services"
        }
    ],
    "sg:phone":"+1 816 455 4893",
    "sg:postcode":"64118",
    "sg:province":"MO",
    "sg:tags":[
        "programing",
        "custom"
    ],
    "wof:name":"Siding Estimator Inc",
    "wof:placetype":"venue"
},
  "geometry": {"coordinates":[-94.566295,39.197654],"type":"Point"}
}