{
  "type": "Feature",
  "properties": {
    "iso:country":"US",
    "sg:address":"301 E Main St",
    "sg:city":"Fairfax",
    "sg:classifiers":[
        {
            "category":"Restaurant",
            "type":"Food & Drink"
        }
    ],
    "sg:phone":"+1 660 686 2508",
    "sg:postcode":"64446",
    "sg:province":"MO",
    "wof:name":"Dairy Diner",
    "wof:placetype":"venue"
},
  "geometry": {"coordinates":[-95.39276599999999,40.339071],"type":"Point"}
}