{
  "type": "Feature",
  "properties": {
    "iso:country":"US",
    "sg:address":"1755 S Grand Blvd",
    "sg:city":"Saint Louis",
    "sg:classifiers":[
        {
            "category":"Health Services",
            "subcategory":"Doctor",
            "type":"Services"
        }
    ],
    "sg:phone":"+1 314 664 2114",
    "sg:postcode":"63104",
    "sg:province":"MO",
    "wof:name":"Midwest Medical Resources Inc",
    "wof:placetype":"venue"
},
  "geometry": {"coordinates":[-90.239751,38.615845],"type":"Point"}
}