{
  "type": "Feature",
  "properties": {
    "iso:country":"US",
    "sg:address":"14237 Cobble Hill",
    "sg:city":"Chesterfield",
    "sg:classifiers":[
        {
            "category":"Professional",
            "subcategory":"Computer Services",
            "type":"Services"
        }
    ],
    "sg:phone":"+1 314 542 6160",
    "sg:postcode":"63017",
    "sg:province":"MO",
    "sg:tags":[
        "custom",
        "related",
        "programing",
        "an"
    ],
    "wof:name":"At Home Mortgage",
    "wof:placetype":"venue"
},
  "geometry": {"coordinates":[-90.523962,38.656546],"type":"Point"}
}