{
  "type": "Feature",
  "properties": {
    "iso:country":"US",
    "sg:address":"3301 California Ave",
    "sg:city":"Saint Louis",
    "sg:classifiers":[
        {
            "category":"Shopping",
            "subcategory":"Clothing, Apparel, & Fashions",
            "type":"Retail Goods"
        }
    ],
    "sg:phone":"+1 314 566 0280",
    "sg:postcode":"63118",
    "sg:province":"MO",
    "sg:tags":[
        "family",
        "clothes"
    ],
    "wof:name":"Robert Earl Apparel Ltd",
    "wof:placetype":"venue"
},
  "geometry": {"coordinates":[-90.22999799999999,38.593855],"type":"Point"}
}