{
  "type": "Feature",
  "properties": {
    "addr:full":"3805 Meramec St Saint Louis MO 63116",
    "addr:housenumber":"3805",
    "addr:postcode":"63116",
    "addr:street":"Meramec St",
    "iso:country":"US",
    "sg:address":"3805 Meramec St",
    "sg:city":"Saint Louis",
    "sg:classifiers":[
        {
            "category":"Bars & Pubs",
            "type":"Food & Drink"
        }
    ],
    "sg:phone":"+1 314 457 9112",
    "sg:postcode":"63116",
    "sg:province":"MO",
    "sg:tags":[
        "restaurant"
    ],
    "wof:name":"Time-Out Sports Bar & Grill",
    "wof:placetype":"venue"
},
  "geometry": {"coordinates":[-90.248497,38.583],"type":"Point"}
}