{
  "type": "Feature",
  "properties": {
    "addr:full":"1525 E 20th St Joplin MO 64804",
    "addr:housenumber":"1525",
    "addr:postcode":"64804",
    "addr:street":"E 20Th St",
    "iso:country":"US",
    "sg:address":"1525 E 20th St",
    "sg:city":"Joplin",
    "sg:classifiers":[
        {
            "category":"Utilities",
            "subcategory":"Mobile Phone",
            "type":"Services"
        }
    ],
    "sg:phone":"+1 417 659 8989",
    "sg:postcode":"64804",
    "sg:province":"MO",
    "sg:tags":[
        "communication",
        "radiotelephone"
    ],
    "wof:name":"Cingular Wireless LLC",
    "wof:placetype":"venue"
},
  "geometry": {"coordinates":[-94.49778499999999,37.06938],"type":"Point"}
}