{
  "type": "Feature",
  "properties": {
    "iso:country":"US",
    "sg:address":"810 Insbrook Dr",
    "sg:city":"Rolla",
    "sg:classifiers":[
        {
            "category":"Professional",
            "subcategory":"Engineering",
            "type":"Services"
        }
    ],
    "sg:phone":"+1 573 341 2141",
    "sg:postcode":"65401",
    "sg:province":"MO",
    "sg:tags":[
        "consulting",
        "research"
    ],
    "wof:name":"Nyamekye Research & Consultin",
    "wof:placetype":"venue"
},
  "geometry": {"coordinates":[-91.741429,37.9497],"type":"Point"}
}