{
  "type": "Feature",
  "properties": {
    "addr:full":"2910 State Hwy 7 Blue Springs MO 64014",
    "addr:housenumber":"2910",
    "addr:postcode":"64014",
    "addr:street":"State Hwy 7",
    "iso:country":"US",
    "sg:address":"2910 State Hwy 7",
    "sg:city":"Blue Springs",
    "sg:classifiers":[
        {
            "category":"Restaurant",
            "type":"Food & Drink"
        }
    ],
    "sg:phone":"+1 816 220 8885",
    "sg:postcode":"64014",
    "sg:province":"MO",
    "wof:name":"Subway Sandwiches & Salads",
    "wof:placetype":"venue"
},
  "geometry": {"coordinates":[-94.27328199999999,38.993337],"type":"Point"}
}