{
  "type": "Feature",
  "properties": {
    "iso:country":"US",
    "sg:address":"3719 N Briarcliff Rd",
    "sg:city":"Kansas City",
    "sg:classifiers":[
        {
            "category":"Recreation",
            "type":"Entertainment"
        }
    ],
    "sg:phone":"+1 816 459 7462",
    "sg:postcode":"64116",
    "sg:province":"MO",
    "sg:tags":[
        "club",
        "membership"
    ],
    "wof:name":"Alfa Romeo Owners Club",
    "wof:placetype":"venue"
},
  "geometry": {"coordinates":[-94.58403,39.160204],"type":"Point"}
}