{
  "type": "Feature",
  "properties": {
    "iso:country":"US",
    "sg:address":"3140 Lions Den Rd",
    "sg:city":"Imperial",
    "sg:classifiers":[
        {
            "category":"Building & Trades",
            "subcategory":"Landscaping Services",
            "type":"Services"
        }
    ],
    "sg:phone":"+1 636 296 7469",
    "sg:postcode":"63052",
    "sg:province":"MO",
    "sg:tags":[
        "contractor"
    ],
    "wof:name":"Action Landscaping Inc",
    "wof:placetype":"venue"
},
  "geometry": {"coordinates":[-90.43776099999999,38.404246],"type":"Point"}
}