{
  "type": "Feature",
  "properties": {
    "iso:country":"US",
    "sg:address":"11 W Business US Highway 60",
    "sg:city":"Dexter",
    "sg:classifiers":[
        {
            "category":"Insurance",
            "subcategory":"Hazard Insurance",
            "type":"Services"
        }
    ],
    "sg:phone":"+1 573 624 9309",
    "sg:postcode":"63841",
    "sg:province":"MO",
    "sg:tags":[
        "commercial",
        "business"
    ],
    "sg:website":"http://www.countryfinancial.com",
    "wof:name":"Country Insurance Finance & Services",
    "wof:placetype":"venue"
},
  "geometry": {"coordinates":[-89.957793,36.799601],"type":"Point"}
}