{
  "type": "Feature",
  "properties": {
    "iso:country":"US",
    "sg:address":"7 E Dakota St",
    "sg:city":"Butler",
    "sg:classifiers":[
        {
            "category":"Shopping",
            "subcategory":"Florist",
            "type":"Retail Goods"
        }
    ],
    "sg:phone":"+1 660 679 5445",
    "sg:postcode":"64730",
    "sg:province":"MO",
    "wof:name":"Every Bloom N Thing",
    "wof:placetype":"venue"
},
  "geometry": {"coordinates":[-94.33181,38.257362],"type":"Point"}
}