{
  "type": "Feature",
  "properties": {
    "iso:country":"US",
    "sg:address":"1155 Wentzville Pkwy",
    "sg:city":"Wentzville",
    "sg:classifiers":[
        {
            "category":"Real Estate",
            "subcategory":"Real Estate Services",
            "type":"Services"
        }
    ],
    "sg:phone":"+1 636 332 8205",
    "sg:postcode":"63385",
    "sg:province":"MO",
    "sg:tags":[
        "company",
        "title"
    ],
    "wof:name":"U S Title Guaranty Co",
    "wof:placetype":"venue"
},
  "geometry": {"coordinates":[-90.854989,38.82406],"type":"Point"}
}