{
  "type": "Feature",
  "properties": {
    "iso:country":"US",
    "sg:address":"257 Greenyard Ct",
    "sg:city":"Ballwin",
    "sg:classifiers":[
        {
            "category":"Professional",
            "type":"Services"
        }
    ],
    "sg:phone":"+1 314 791 9637",
    "sg:postcode":"63011",
    "sg:province":"MO",
    "wof:name":"Tracey Venable",
    "wof:placetype":"venue"
},
  "geometry": {"coordinates":[-90.54074300000001,38.598727],"type":"Point"}
}