{
  "type": "Feature",
  "properties": {
    "iso:country":"US",
    "sg:address":"5705 N Dawn Ct",
    "sg:city":"Kansas City",
    "sg:classifiers":[
        {
            "category":"Professional",
            "subcategory":"Management & Consulting",
            "type":"Services"
        }
    ],
    "sg:phone":"+1 816 584 8823",
    "sg:postcode":"64151",
    "sg:province":"MO",
    "wof:name":"LKM Marketing Inc",
    "wof:placetype":"venue"
},
  "geometry": {"coordinates":[-94.64244100000001,39.198457],"type":"Point"}
}