{
  "type": "Feature",
  "properties": {
    "iso:country":"US",
    "sg:address":"205 W Pine St",
    "sg:city":"Smithville",
    "sg:classifiers":[
        {
            "category":"Professional",
            "subcategory":"Advertising",
            "type":"Services"
        }
    ],
    "sg:phone":"+1 816 532 3277",
    "sg:postcode":"64089",
    "sg:province":"MO",
    "wof:name":"Classic Media",
    "wof:placetype":"venue"
},
  "geometry": {"coordinates":[-94.58069500000001,39.39852],"type":"Point"}
}