{
  "type": "Feature",
  "properties": {
    "iso:country":"US",
    "sg:address":"4203 Country Ln",
    "sg:city":"Saint Joseph",
    "sg:classifiers":[
        {
            "category":"Banks & Credit Unions",
            "subcategory":"Financial Services",
            "type":"Services"
        }
    ],
    "sg:phone":"+1 816 279 8682",
    "sg:postcode":"64506",
    "sg:province":"MO",
    "sg:tags":[
        "trust",
        "management"
    ],
    "wof:name":"D E Rodkey Trust",
    "wof:placetype":"venue"
},
  "geometry": {"coordinates":[-94.791285,39.780396],"type":"Point"}
}