{
  "type": "Feature",
  "properties": {
    "iso:country":"US",
    "sg:address":"219 Boone Hollow Dr",
    "sg:city":"Wentzville",
    "sg:classifiers":[
        {
            "category":"Manufacturing",
            "subcategory":"Buildings",
            "type":"Manufacturing & Wholesale Goods"
        },
        {
            "category":"Building & Trades",
            "subcategory":"Construction",
            "type":"Services"
        }
    ],
    "sg:phone":"+1 636 327 9839",
    "sg:postcode":"63385",
    "sg:province":"MO",
    "sg:tags":[
        "home",
        "builder",
        "contractor"
    ],
    "wof:name":"Tucker Mj Construction",
    "wof:placetype":"venue"
},
  "geometry": {"coordinates":[-90.874657,38.788059],"type":"Point"}
}