{
  "type": "Feature",
  "properties": {
    "iso:country":"US",
    "sg:address":"6124 Railroad St",
    "sg:city":"Henley",
    "sg:classifiers":[
        {
            "category":"Farming",
            "subcategory":"Livestock Farm",
            "type":"Manufacturing & Wholesale Goods"
        }
    ],
    "sg:phone":"+1 573 498 3432",
    "sg:postcode":"65040",
    "sg:province":"MO",
    "sg:tags":[
        "ranch"
    ],
    "wof:name":"James Koetting",
    "wof:placetype":"venue"
},
  "geometry": {"coordinates":[-92.323804,38.344483],"type":"Point"}
}