{
  "type": "Feature",
  "properties": {
    "iso:country":"US",
    "sg:address":"704 W 2nd St",
    "sg:city":"Rolla",
    "sg:classifiers":[
        {
            "category":"Personal",
            "subcategory":"Beauty Salon",
            "type":"Services"
        }
    ],
    "sg:phone":"+1 573 364 1424",
    "sg:postcode":"65401",
    "sg:province":"MO",
    "wof:name":"Lisa's Hair Salon",
    "wof:placetype":"venue"
},
  "geometry": {"coordinates":[-91.777351,37.945438],"type":"Point"}
}