{
  "type": "Feature",
  "properties": {
    "iso:country":"US",
    "sg:address":"1432 N Broadway",
    "sg:city":"Saint Louis",
    "sg:classifiers":[
        {
            "category":"Bars & Pubs",
            "type":"Food & Drink"
        }
    ],
    "sg:phone":"+1 314 241 4644",
    "sg:postcode":"63102",
    "sg:province":"MO",
    "sg:tags":[
        "nightlife"
    ],
    "wof:name":"Shady Jack Saloon",
    "wof:placetype":"venue"
},
  "geometry": {"coordinates":[-90.18563,38.638797],"type":"Point"}
}