{
  "type": "Feature",
  "properties": {
    "iso:country":"US",
    "sg:address":"33875 Twin Oaks Ln",
    "sg:city":"Brashear",
    "sg:classifiers":[
        {
            "category":"Building & Trades",
            "subcategory":"Construction",
            "type":"Services"
        }
    ],
    "sg:phone":"+1 660 323 5336",
    "sg:postcode":"63533",
    "sg:province":"MO",
    "sg:tags":[
        "excavating",
        "contractor"
    ],
    "wof:name":"Steve's Garage",
    "wof:placetype":"venue"
},
  "geometry": {"coordinates":[-92.40460899999999,40.138517],"type":"Point"}
}