{
  "type": "Feature",
  "properties": {
    "iso:country":"US",
    "sg:address":"3379 US Hwy 67",
    "sg:city":"Florissant",
    "sg:classifiers":[
        {
            "category":"Professional",
            "type":"Services"
        }
    ],
    "sg:phone":"+1 314 921 6000",
    "sg:postcode":"63033",
    "sg:province":"MO",
    "wof:name":"Marcelconcepts",
    "wof:placetype":"venue"
},
  "geometry": {"coordinates":[-90.294471,38.811494],"type":"Point"}
}