{
  "type": "Feature",
  "properties": {
    "iso:country":"US",
    "sg:address":"4643 US Hwy 54",
    "sg:city":"Osage Beach",
    "sg:classifiers":[
        {
            "category":"Manufacturing",
            "subcategory":"Tools & Machinery",
            "type":"Manufacturing & Wholesale Goods"
        }
    ],
    "sg:phone":"+1 573 302 1045",
    "sg:postcode":"65065",
    "sg:province":"MO",
    "sg:tags":[
        "lift",
        "boat"
    ],
    "wof:name":"First Mate Boat Hoist Remote",
    "wof:placetype":"venue"
},
  "geometry": {"coordinates":[-92.630245,38.144083],"type":"Point"}
}