{
  "type": "Feature",
  "properties": {
    "iso:country":"US",
    "sg:address":"3815 Faraon St",
    "sg:city":"St Joseph",
    "sg:classifiers":[
        {
            "category":"Wholesale",
            "subcategory":"Construction Materials",
            "type":"Manufacturing & Wholesale Goods"
        },
        {
            "category":"Building & Trades",
            "subcategory":"Construction",
            "type":"Services"
        }
    ],
    "sg:phone":"+1 816 232 8210",
    "sg:postcode":"64506",
    "sg:province":"MO",
    "sg:tags":[
        "retail",
        "fence",
        "landscape"
    ],
    "wof:name":"Bowen Fence Co",
    "wof:placetype":"venue"
},
  "geometry": {"coordinates":[-94.803541,39.769656],"type":"Point"}
}