{
  "type": "Feature",
  "properties": {
    "iso:country":"US",
    "sg:address":"636 Hawthorne St",
    "sg:city":"Warsaw",
    "sg:classifiers":[
        {
            "category":"Place Of Worship",
            "subcategory":"Church",
            "type":"Public Place"
        },
        {
            "category":"Place Of Worship",
            "type":"Public Place"
        }
    ],
    "sg:phone":"+1 660 438 7450",
    "sg:postcode":"65355",
    "sg:province":"MO",
    "sg:tags":[
        "nazarene",
        "churches-church",
        "churches-nazarene"
    ],
    "wof:name":"Church Of Nazarene",
    "wof:placetype":"venue"
},
  "geometry": {"coordinates":[-93.369919,38.244511],"type":"Point"}
}