{
  "type": "Feature",
  "properties": {
    "iso:country":"US",
    "sg:address":"224 NW Locust St",
    "sg:city":"Lees Summit",
    "sg:classifiers":[
        {
            "category":"Real Estate",
            "subcategory":"Real Estate Operator",
            "type":"Services"
        }
    ],
    "sg:phone":"+1 816 478 2327",
    "sg:postcode":"64064",
    "sg:province":"MO",
    "sg:tags":[
        "building",
        "nonresidential"
    ],
    "wof:name":"Dlf Properties",
    "wof:placetype":"venue"
},
  "geometry": {"coordinates":[-94.38367599999999,38.988333],"type":"Point"}
}