{
  "type": "Feature",
  "properties": {
    "iso:country":"US",
    "sg:address":"400 Park Ct",
    "sg:city":"Kearney",
    "sg:classifiers":[
        {
            "category":"Coffee & Tea",
            "type":"Food & Drink"
        },
        {
            "category":"Restaurant",
            "type":"Food & Drink"
        }
    ],
    "sg:phone":"+1 816 902 6656",
    "sg:postcode":"64060",
    "sg:province":"MO",
    "sg:tags":[
        "shop",
        "espresso"
    ],
    "wof:name":"Mojos To Go",
    "wof:placetype":"venue"
},
  "geometry": {"coordinates":[-94.367401,39.35759],"type":"Point"}
}