{
  "type": "Feature",
  "properties": {
    "iso:country":"US",
    "sg:address":"1332 E Portland St",
    "sg:city":"Springfield",
    "sg:classifiers":[
        {
            "category":"Building & Trades",
            "subcategory":"Electrical",
            "type":"Services"
        }
    ],
    "sg:phone":"+1 417 869 3779",
    "sg:postcode":"65804",
    "sg:province":"MO",
    "sg:tags":[
        "electrical",
        "computer",
        "design",
        "system",
        "contractor"
    ],
    "wof:name":"Dictacomm Services Inc",
    "wof:placetype":"venue"
},
  "geometry": {"coordinates":[-93.273567,37.185362],"type":"Point"}
}