{
  "type": "Feature",
  "properties": {
    "iso:country":"US",
    "sg:address":"16000 E 23rd St S",
    "sg:city":"Independence",
    "sg:classifiers":[
        {
            "category":"Professional",
            "type":"Services"
        }
    ],
    "sg:phone":"+1 816 252 5071",
    "sg:postcode":"64055",
    "sg:province":"MO",
    "wof:name":"Chane R Harris",
    "wof:placetype":"venue"
},
  "geometry": {"coordinates":[-94.386714,39.078204],"type":"Point"}
}