{
  "type": "Feature",
  "properties": {
    "iso:country":"US",
    "sg:address":"120 W Main Cross St",
    "sg:city":"Palmyra",
    "sg:classifiers":[
        {
            "category":"Home & Garden",
            "subcategory":"Garden Supply",
            "type":"Retail Goods"
        }
    ],
    "sg:phone":"+1 573 769 5005",
    "sg:postcode":"63461",
    "sg:province":"MO",
    "sg:tags":[
        "lawn"
    ],
    "wof:name":"Rorison Sales & Svc",
    "wof:placetype":"venue"
},
  "geometry": {"coordinates":[-91.524052,39.799746],"type":"Point"}
}