{
  "type": "Feature",
  "properties": {
    "iso:country":"US",
    "sg:address":"1822 Ferguson Ave",
    "sg:city":"St Louis",
    "sg:classifiers":[
        {
            "category":"Building & Trades",
            "subcategory":"Plumbing",
            "type":"Services"
        }
    ],
    "sg:phone":"+1 314 863 1663",
    "sg:postcode":"63133",
    "sg:province":"MO",
    "sg:tags":[
        "conditioning",
        "air",
        "system",
        "contractor"
    ],
    "wof:name":"Parsons Heating & Cooling",
    "wof:placetype":"venue"
},
  "geometry": {"coordinates":[-90.305115,38.689577],"type":"Point"}
}