{
  "type": "Feature",
  "properties": {
    "iso:country":"US",
    "sg:address":"623 N Main St",
    "sg:city":"Piedmont",
    "sg:classifiers":[
        {
            "category":"Farming",
            "subcategory":"Farm & Veterinary Services",
            "type":"Manufacturing & Wholesale Goods"
        }
    ],
    "sg:phone":"+1 573 223 4819",
    "sg:postcode":"63957",
    "sg:province":"MO",
    "sg:tags":[
        "management"
    ],
    "wof:name":"Tdy Farms Inc",
    "wof:placetype":"venue"
},
  "geometry": {"coordinates":[-90.691408,37.159455],"type":"Point"}
}