{
  "type": "Feature",
  "properties": {
    "iso:country":"US",
    "sg:address":"7178 Lawrence 1110",
    "sg:city":"Mount Vernon",
    "sg:classifiers":[
        {
            "category":"Farming",
            "subcategory":"Livestock Farm",
            "type":"Manufacturing & Wholesale Goods"
        }
    ],
    "sg:phone":"+1 417 452 3128",
    "sg:postcode":"65712",
    "sg:province":"MO",
    "sg:tags":[
        "beef",
        "feedlot",
        "cattle"
    ],
    "wof:name":"Roy Bishop",
    "wof:placetype":"venue"
},
  "geometry": {"coordinates":[-93.857488,37.167986],"type":"Point"}
}