{
  "type": "Feature",
  "properties": {
    "iso:country":"US",
    "sg:address":"401 W Daniels Ave",
    "sg:city":"Vandalia",
    "sg:classifiers":[
        {
            "category":"Personal",
            "subcategory":"Beauty Salon",
            "type":"Services"
        }
    ],
    "sg:phone":"+1 573 594 3113",
    "sg:postcode":"63382",
    "sg:province":"MO",
    "wof:name":"Leota's Beauty Shop",
    "wof:placetype":"venue"
},
  "geometry": {"coordinates":[-91.49447499999999,39.315365],"type":"Point"}
}