{
  "type": "Feature",
  "properties": {
    "iso:country":"US",
    "sg:address":"111 E 1st St",
    "sg:city":"Montgomery City",
    "sg:classifiers":[
        {
            "category":"Insurance",
            "subcategory":"Insurance Agent",
            "type":"Services"
        }
    ],
    "sg:phone":"+1 573 564 2237",
    "sg:postcode":"63361",
    "sg:province":"MO",
    "wof:name":"Scott Agency Inc",
    "wof:placetype":"venue"
},
  "geometry": {"coordinates":[-91.503383,38.977205],"type":"Point"}
}