{
  "type": "Feature",
  "properties": {
    "iso:country":"US",
    "sg:address":"527 E 13th St",
    "sg:city":"Carthage",
    "sg:classifiers":[
        {
            "category":"Organizations",
            "subcategory":"Religious Organization",
            "type":"Services"
        }
    ],
    "sg:phone":"+1 417 358 4526",
    "sg:postcode":"64836",
    "sg:province":"MO",
    "wof:name":"Calvary Baptist Church",
    "wof:placetype":"venue"
},
  "geometry": {"coordinates":[-94.30709299999999,37.165632],"type":"Point"}
}