{
  "type": "Feature",
  "properties": {
    "iso:country":"US",
    "sg:address":"17808 Orrville Rd",
    "sg:city":"Chesterfield",
    "sg:classifiers":[
        {
            "category":"Shopping",
            "subcategory":"Gifts & Souvenirs",
            "type":"Retail Goods"
        }
    ],
    "sg:phone":"+1 636 532 5367",
    "sg:postcode":"63005",
    "sg:province":"MO",
    "sg:tags":[
        "shop"
    ],
    "wof:name":"The Bee Hive Gift Shop Bake",
    "wof:placetype":"venue"
},
  "geometry": {"coordinates":[-90.65754800000001,38.631869],"type":"Point"}
}