{
  "type": "Feature",
  "properties": {
    "iso:country":"US",
    "sg:address":"801 Faraon St",
    "sg:city":"St Joseph",
    "sg:classifiers":[
        {
            "category":"Health Services",
            "subcategory":"Nursing And Care Facility",
            "type":"Services"
        }
    ],
    "sg:phone":"+1 816 271 6124",
    "sg:postcode":"64501",
    "sg:province":"MO",
    "sg:tags":[
        "home",
        "convalescent"
    ],
    "wof:name":"Heartland Division-Geriatric",
    "wof:placetype":"venue"
},
  "geometry": {"coordinates":[-94.85008999999999,39.769048],"type":"Point"}
}