{
  "type": "Feature",
  "properties": {
    "addr:full":"731 N Scott Ave Belton MO 64012",
    "addr:housenumber":"731",
    "addr:postcode":"64012",
    "addr:street":"N Scott Ave",
    "iso:country":"US",
    "sg:address":"731 N Scott Ave",
    "sg:city":"Belton",
    "sg:classifiers":[
        {
            "category":"Home & Garden",
            "subcategory":"Household Appliances",
            "type":"Retail Goods"
        },
        {
            "category":"Retail",
            "subcategory":"Laundry & Dry Cleaning",
            "type":"Services"
        },
        {
            "category":"Building & Trades",
            "subcategory":"Cleaning & Sanitation",
            "type":"Services"
        }
    ],
    "sg:phone":"+1 816 436 1522",
    "sg:postcode":"64012",
    "sg:province":"MO",
    "sg:tags":[
        "cleaner",
        "upholstery",
        "duct",
        "house",
        "rug",
        "air",
        "ventilation",
        "cleaning-industrial",
        "vacuum",
        "curtain",
        "drapery",
        "carpet"
    ],
    "sg:website":"http://www.servicemasterclean.com/reslf/smclean_leadform.asp?url=http://www.servicemasterclean.com/reslf/smclean_leadform.asp&partnerName=YellowPages.com&adName=yptl&HGProp=SMClean",
    "wof:name":"ServiceMaster Clean",
    "wof:placetype":"venue"
},
  "geometry": {"coordinates":[-94.53407900000001,38.82639],"type":"Point"}
}