{
  "type": "Feature",
  "properties": {
    "iso:country":"US",
    "sg:address":"516 Pearl St",
    "sg:city":"Neosho",
    "sg:classifiers":[
        {
            "category":"Personal",
            "type":"Services"
        }
    ],
    "sg:phone":"+1 417 451 9167",
    "sg:postcode":"64850",
    "sg:province":"MO",
    "sg:tags":[
        "therapist",
        "massage"
    ],
    "wof:name":"Health Crafts Wellness Svc",
    "wof:placetype":"venue"
},
  "geometry": {"coordinates":[-94.361749,36.860749],"type":"Point"}
}