{
  "type": "Feature",
  "properties": {
    "iso:country":"US",
    "sg:address":"403 W Main St",
    "sg:city":"Branson",
    "sg:classifiers":[
        {
            "category":"Travel",
            "subcategory":"Hotels & Motels",
            "type":"Entertainment"
        }
    ],
    "sg:phone":"+1 877 574 2464",
    "sg:postcode":"65616",
    "sg:province":"MO",
    "sg:tags":[
        "lodging"
    ],
    "sg:website":"http://book.bestwestern.com/bestwestern/priceAvail.do?propertyCode=26066&cm_mmc=IYP-_-YP-_-property-_-26066",
    "wof:name":"Best Western Landing View Inn & Suites",
    "wof:placetype":"venue"
},
  "geometry": {"coordinates":[-93.220754,36.644162],"type":"Point"}
}