{
  "type": "Feature",
  "properties": {
    "iso:country":"US",
    "sg:address":"100 SW 2 St",
    "sg:city":"Lees Summit",
    "sg:classifiers":[
        {
            "category":"Banks & Credit Unions",
            "subcategory":"Bank",
            "type":"Services"
        }
    ],
    "sg:phone":"+1 816 525 3663",
    "sg:postcode":"64063",
    "sg:province":"MO",
    "sg:tags":[
        "loan"
    ],
    "wof:name":"Gomez Delibrado Lenning",
    "wof:placetype":"venue"
},
  "geometry": {"coordinates":[-94.38060900000001,38.912507],"type":"Point"}
}