{
  "type": "Feature",
  "properties": {
    "iso:country":"US",
    "sg:address":"108 US Hwy 169",
    "sg:city":"Smithville",
    "sg:classifiers":[
        {
            "category":"Building & Trades",
            "subcategory":"Construction",
            "type":"Services"
        }
    ],
    "sg:phone":"+1 816 866 2206",
    "sg:postcode":"64089",
    "sg:province":"MO",
    "sg:tags":[
        "contractor",
        "general"
    ],
    "wof:name":"Mc Kee Construction Inc",
    "wof:placetype":"venue"
},
  "geometry": {"coordinates":[-94.58477600000001,39.387986],"type":"Point"}
}