{
  "type": "Feature",
  "properties": {
    "iso:country":"US",
    "sg:address":"195 S Shelby St",
    "sg:city":"Clarence",
    "sg:phone":"+1 660 699 3757",
    "sg:postcode":"63437",
    "sg:province":"MO",
    "sg:tags":[
        "farm",
        "corn",
        "soybean"
    ],
    "wof:name":"James Chinn",
    "wof:placetype":"venue"
},
  "geometry": {"coordinates":[-92.258177,39.741381],"type":"Point"}
}