{
  "type": "Feature",
  "properties": {
    "iso:country":"US",
    "sg:address":"917 Black Twig Ln",
    "sg:city":"Kirkwood",
    "sg:classifiers":[
        {
            "category":"Real Estate",
            "subcategory":"Real Estate Agent",
            "type":"Services"
        }
    ],
    "sg:phone":"+1 314 821 3373",
    "sg:postcode":"63122",
    "sg:province":"MO",
    "wof:name":"Harry Herring Co",
    "wof:placetype":"venue"
},
  "geometry": {"coordinates":[-90.434726,38.596185],"type":"Point"}
}