{
  "type": "Feature",
  "properties": {
    "addr:full":"425 N New Ballas Rd Saint Louis MO 63141",
    "addr:housenumber":"425",
    "addr:postcode":"63141",
    "addr:street":"N New Ballas Rd",
    "iso:country":"US",
    "sg:address":"425 N New Ballas Rd",
    "sg:city":"Saint Louis",
    "sg:classifiers":[
        {
            "category":"Insurance",
            "subcategory":"Insurance Agent",
            "type":"Services"
        }
    ],
    "sg:phone":"+1 314 432 6464",
    "sg:postcode":"63141",
    "sg:province":"MO",
    "sg:tags":[
        "agency"
    ],
    "wof:name":"Missouri General Insur Agcy",
    "wof:placetype":"venue"
},
  "geometry": {"coordinates":[-90.443358,38.663335],"type":"Point"}
}