{
  "type": "Feature",
  "properties": {
    "iso:country":"US",
    "sg:address":"1010 Frick Ave",
    "sg:city":"Warrenton",
    "sg:classifiers":[
        {
            "category":"Personal",
            "subcategory":"Beauty Salon",
            "type":"Services"
        }
    ],
    "sg:phone":"+1 636 745 8686",
    "sg:postcode":"63383",
    "sg:province":"MO",
    "wof:name":"Images For Hair Inc",
    "wof:placetype":"venue"
},
  "geometry": {"coordinates":[-91.136157,38.819342],"type":"Point"}
}