{
  "type": "Feature",
  "properties": {
    "iso:country":"US",
    "sg:address":"3045 S Delaware Ave",
    "sg:city":"Springfield",
    "sg:classifiers":[
        {
            "category":"Banks & Credit Unions",
            "subcategory":"Bank",
            "type":"Services"
        }
    ],
    "sg:phone":"+1 417 890 5798",
    "sg:postcode":"65804",
    "sg:province":"MO",
    "sg:tags":[
        "loan",
        "real estate"
    ],
    "wof:name":"Allied Home Mortgage Capital",
    "wof:placetype":"venue"
},
  "geometry": {"coordinates":[-93.26716999999999,37.158329],"type":"Point"}
}