{
  "type": "Feature",
  "properties": {
    "iso:country":"US",
    "sg:address":"12727 NW Skyview Ave",
    "sg:city":"Kansas City",
    "sg:classifiers":[
        {
            "category":"Building & Trades",
            "subcategory":"Plumbing",
            "type":"Services"
        }
    ],
    "sg:phone":"+1 816 464 5290",
    "sg:postcode":"64164",
    "sg:province":"MO",
    "sg:tags":[
        "plumbing",
        "electrical",
        "remodeling",
        "contractor"
    ],
    "wof:name":"Edward Jones Pump Svc",
    "wof:placetype":"venue"
},
  "geometry": {"coordinates":[-94.648754,39.318361],"type":"Point"}
}