{
  "type": "Feature",
  "properties": {
    "iso:country":"US",
    "sg:address":"145 Washington St",
    "sg:city":"Ste Genevieve",
    "sg:classifiers":[
        {
            "category":"Social Services",
            "subcategory":"Child Care",
            "type":"Services"
        }
    ],
    "sg:phone":"+1 573 883 7525",
    "sg:postcode":"63670",
    "sg:province":"MO",
    "sg:tags":[
        "kindergarten",
        "academic",
        "school"
    ],
    "wof:name":"First School Daycare",
    "wof:placetype":"venue"
},
  "geometry": {"coordinates":[-90.04400200000001,37.9823],"type":"Point"}
}