{
  "type": "Feature",
  "properties": {
    "iso:country":"US",
    "sg:address":"304 W Walnut St",
    "sg:city":"Independence",
    "sg:classifiers":[
        {
            "category":"Organizations",
            "subcategory":"Professional Association",
            "type":"Services"
        }
    ],
    "sg:phone":"+1 816 461 8888",
    "sg:postcode":"64050",
    "sg:province":"MO",
    "wof:name":"American Association For Tlig",
    "wof:placetype":"venue"
},
  "geometry": {"coordinates":[-94.41928900000001,39.090098],"type":"Point"}
}