{
  "type": "Feature",
  "properties": {
    "iso:country":"US",
    "sg:address":"1212 Valley Ridge Dr",
    "sg:city":"Grain Valley",
    "sg:classifiers":[
        {
            "category":"Wholesale",
            "subcategory":"Machinery & Supplies",
            "type":"Manufacturing & Wholesale Goods"
        }
    ],
    "sg:phone":"+1 816 847 7610",
    "sg:postcode":"64029",
    "sg:province":"MO",
    "sg:tags":[
        "salon",
        "beauty"
    ],
    "wof:name":"Modern Salon Svc",
    "wof:placetype":"venue"
},
  "geometry": {"coordinates":[-94.205832,39.02463],"type":"Point"}
}