{
  "type": "Feature",
  "properties": {
    "iso:country":"US",
    "sg:address":"611 E Capitol Ave",
    "sg:city":"Jefferson City",
    "sg:classifiers":[
        {
            "category":"Professional",
            "subcategory":"Research",
            "type":"Services"
        }
    ],
    "sg:phone":"+1 573 634 2598",
    "sg:postcode":"65101",
    "sg:province":"MO",
    "sg:tags":[
        "foundation"
    ],
    "wof:name":"Missouri Forest Foundation",
    "wof:placetype":"venue"
},
  "geometry": {"coordinates":[-92.164675,38.573348],"type":"Point"}
}