{
  "type": "Feature",
  "properties": {
    "iso:country":"US",
    "sg:address":"1027 Airport Rd",
    "sg:city":"Festus",
    "sg:classifiers":[
        {
            "category":"Freight",
            "type":"Transportation"
        }
    ],
    "sg:phone":"+1 636 937 7504",
    "sg:postcode":"63028",
    "sg:province":"MO",
    "sg:tags":[
        "commercial",
        "storage"
    ],
    "wof:name":"Airport Road Self Storage",
    "wof:placetype":"venue"
},
  "geometry": {"coordinates":[-90.388064,38.195195],"type":"Point"}
}