{
  "type": "Feature",
  "properties": {
    "iso:country":"US",
    "sg:address":"303 S Grove St",
    "sg:city":"Kearney",
    "sg:classifiers":[
        {
            "category":"Organizations",
            "subcategory":"Religious Organization",
            "type":"Services"
        }
    ],
    "sg:phone":"+1 816 628 5693",
    "sg:postcode":"64060",
    "sg:province":"MO",
    "sg:website":"www.kearneyfbc.com",
    "wof:name":"First Baptist Church",
    "wof:placetype":"venue"
},
  "geometry": {"coordinates":[-94.360691,39.370861],"type":"Point"}
}