{
  "type": "Feature",
  "properties": {
    "iso:country":"US",
    "sg:address":"2223 State Hwy 168",
    "sg:city":"Philadelphia",
    "sg:classifiers":[
        {
            "category":"Freight",
            "type":"Transportation"
        }
    ],
    "sg:phone":"+1 573 439 5496",
    "sg:postcode":"63463",
    "sg:province":"MO",
    "sg:tags":[
        "operator",
        "trucking"
    ],
    "wof:name":"Bock John & Son Trucking",
    "wof:placetype":"venue"
},
  "geometry": {"coordinates":[-91.74064,39.838652],"type":"Point"}
}