{
  "type": "Feature",
  "properties": {
    "iso:country":"US",
    "sg:address":"23235 County Road 220",
    "sg:city":"Malden",
    "sg:classifiers":[
        {
            "category":"Professional",
            "subcategory":"Management & Consulting",
            "type":"Services"
        }
    ],
    "sg:phone":"+1 573 276 3854",
    "sg:postcode":"63863",
    "sg:province":"MO",
    "sg:tags":[
        "farm"
    ],
    "wof:name":"Roth Farm Service",
    "wof:placetype":"venue"
},
  "geometry": {"coordinates":[-89.98085,36.52021],"type":"Point"}
}