{
  "type": "Feature",
  "properties": {
    "iso:country":"US",
    "sg:address":"9641 Natural Bridge Rd",
    "sg:city":"St Louis",
    "sg:classifiers":[
        {
            "category":"Wholesale",
            "subcategory":"Machinery & Supplies",
            "type":"Manufacturing & Wholesale Goods"
        }
    ],
    "sg:phone":"+1 314 367 0114",
    "sg:postcode":"63134",
    "sg:province":"MO",
    "sg:tags":[
        "dyer",
        "repair",
        "laundry",
        "equipment",
        "cleaners"
    ],
    "wof:name":"I G Weingaertner & Son Inc",
    "wof:placetype":"venue"
},
  "geometry": {"coordinates":[-90.343789,38.728725],"type":"Point"}
}