{
  "type": "Feature",
  "properties": {
    "iso:country":"US",
    "sg:address":"1417 Ronald Dr",
    "sg:city":"Lebanon",
    "sg:classifiers":[
        {
            "category":"Building & Trades",
            "subcategory":"Construction",
            "type":"Services"
        }
    ],
    "sg:phone":"+1 417 533 1166",
    "sg:postcode":"65536",
    "sg:province":"MO",
    "sg:tags":[
        "wallcoverings-installation",
        "wallpaper",
        "painting",
        "contractor"
    ],
    "wof:name":"Whaley Painting & Power Washin",
    "wof:placetype":"venue"
},
  "geometry": {"coordinates":[-92.682947,37.702081],"type":"Point"}
}