{
  "type": "Feature",
  "properties": {
    "iso:country":"US",
    "sg:address":"3056 Bess Rd",
    "sg:city":"Bonne Terre",
    "sg:classifiers":[
        {
            "category":"Building & Trades",
            "subcategory":"Construction",
            "type":"Services"
        }
    ],
    "sg:phone":"+1 573 358 5495",
    "sg:postcode":"63628",
    "sg:province":"MO",
    "sg:tags":[
        "general",
        "contractor"
    ],
    "wof:name":"Gordon Bess Construction Co",
    "wof:placetype":"venue"
},
  "geometry": {"coordinates":[-90.511302,37.946495],"type":"Point"}
}