{
  "type": "Feature",
  "properties": {
    "iso:country":"US",
    "sg:address":"512 W Broadway Blvd",
    "sg:city":"Sedalia",
    "sg:classifiers":[
        {
            "category":"Home & Garden",
            "subcategory":"Furniture",
            "type":"Retail Goods"
        }
    ],
    "sg:phone":"+1 660 829 0009",
    "sg:postcode":"65301",
    "sg:province":"MO",
    "sg:tags":[
        "store"
    ],
    "wof:name":"Earthen Studio",
    "wof:placetype":"venue"
},
  "geometry": {"coordinates":[-93.232962,38.7044],"type":"Point"}
}