{
  "type": "Feature",
  "properties": {
    "iso:country":"US",
    "sg:address":"3430 S Ashley Ct",
    "sg:city":"Springfield",
    "sg:classifiers":[
        {
            "category":"Manufacturing",
            "subcategory":"Paper Products",
            "type":"Manufacturing & Wholesale Goods"
        }
    ],
    "sg:phone":"+1 417 881 2524",
    "sg:postcode":"65809",
    "sg:province":"MO",
    "sg:tags":[
        "printing",
        "supply"
    ],
    "wof:name":"A-1 Laser Toner Svc",
    "wof:placetype":"venue"
},
  "geometry": {"coordinates":[-93.215867,37.149945],"type":"Point"}
}