{
  "type": "Feature",
  "properties": {
    "iso:country":"US",
    "sg:address":"1304 W Adams Ave",
    "sg:city":"St Louis",
    "sg:classifiers":[
        {
            "category":"Real Estate",
            "subcategory":"Real Estate Agent",
            "type":"Services"
        }
    ],
    "sg:phone":"+1 314 909 7600",
    "sg:postcode":"63122",
    "sg:province":"MO",
    "wof:name":"Corporate Realty Inc",
    "wof:placetype":"venue"
},
  "geometry": {"coordinates":[-90.428545,38.583298],"type":"Point"}
}