{
  "type": "Feature",
  "properties": {
    "iso:country":"US",
    "sg:address":"348 Summit Ave",
    "sg:city":"Saint Louis",
    "sg:classifiers":[
        {
            "category":"Building & Trades",
            "subcategory":"Construction",
            "type":"Services"
        }
    ],
    "sg:phone":"+1 636 305 2787",
    "sg:postcode":"63119",
    "sg:province":"MO",
    "sg:tags":[
        "contractor"
    ],
    "wof:name":"C & C Exteriors Inc",
    "wof:placetype":"venue"
},
  "geometry": {"coordinates":[-90.33953700000001,38.597581],"type":"Point"}
}