{
  "type": "Feature",
  "properties": {
    "iso:country":"US",
    "sg:address":"14762 Manchester Rd",
    "sg:city":"Ballwin",
    "sg:classifiers":[
        {
            "category":"Retail",
            "subcategory":"Repair Shop",
            "type":"Services"
        }
    ],
    "sg:phone":"+1 636 394 2001",
    "sg:postcode":"63011",
    "sg:province":"MO",
    "sg:tags":[
        "television",
        "radio"
    ],
    "wof:name":"VCR-TV Service Ctr",
    "wof:placetype":"venue"
},
  "geometry": {"coordinates":[-90.53408899999999,38.592921],"type":"Point"}
}