{
  "type": "Feature",
  "properties": {
    "iso:country":"US",
    "sg:address":"6430 Pernod Ave",
    "sg:city":"St Louis",
    "sg:classifiers":[
        {
            "category":"Home & Garden",
            "subcategory":"Garden Supply",
            "type":"Retail Goods"
        }
    ],
    "sg:phone":"+1 314 353 0444",
    "sg:postcode":"63139",
    "sg:province":"MO",
    "sg:tags":[
        "nurseryman"
    ],
    "sg:website":"www.unitedgardencenters.com",
    "wof:name":"United Garden Ctr",
    "wof:placetype":"venue"
},
  "geometry": {"coordinates":[-90.298422,38.597159],"type":"Point"}
}