{
  "type": "Feature",
  "properties": {
    "iso:country":"US",
    "sg:address":"3115 W Marty St",
    "sg:city":"Springfield",
    "sg:classifiers":[
        {
            "category":"Retail",
            "subcategory":"Repair Shop",
            "type":"Services"
        },
        {
            "category":"Professional",
            "subcategory":"Computer Services",
            "type":"Services"
        }
    ],
    "sg:phone":"+1 417 882 7479",
    "sg:postcode":"65810",
    "sg:province":"MO",
    "sg:tags":[
        "electrical"
    ],
    "wof:name":"Advanced Electronics Service",
    "wof:placetype":"venue"
},
  "geometry": {"coordinates":[-93.346434,37.124596],"type":"Point"}
}