{
  "type": "Feature",
  "properties": {
    "iso:country":"US",
    "sg:address":"8026 Windsor Rd",
    "sg:city":"Kansas City",
    "sg:classifiers":[
        {
            "category":"Building & Trades",
            "subcategory":"Construction",
            "type":"Services"
        },
        {
            "category":"Home & Garden",
            "subcategory":"Furniture",
            "type":"Retail Goods"
        }
    ],
    "sg:phone":"+1 816 792 1009",
    "sg:postcode":"64167",
    "sg:province":"MO",
    "sg:tags":[
        "wood",
        "cabinet",
        "maker",
        "kitchen",
        "mfg"
    ],
    "wof:name":"H & S Cabinets Inc",
    "wof:placetype":"venue"
},
  "geometry": {"coordinates":[-94.486666,39.325955],"type":"Point"}
}