{
  "type": "Feature",
  "properties": {
    "iso:country":"US",
    "sg:address":"12055 Manchester Rd",
    "sg:city":"Saint Louis",
    "sg:classifiers":[
        {
            "category":"Home & Garden",
            "subcategory":"Mobile Homes",
            "type":"Retail Goods"
        }
    ],
    "sg:phone":"+1 314 965 2920",
    "sg:postcode":"63131",
    "sg:province":"MO",
    "wof:name":"Arthur L Kniffen Homes Inc",
    "wof:placetype":"venue"
},
  "geometry": {"coordinates":[-90.43716999999999,38.602135],"type":"Point"}
}