{
  "type": "Feature",
  "properties": {
    "iso:country":"US",
    "sg:address":"2143 S Cedarbrook Ave",
    "sg:city":"Springfield",
    "sg:classifiers":[
        {
            "category":"Professional",
            "subcategory":"Business Services",
            "type":"Services"
        }
    ],
    "sg:phone":"+1 417 868 8002",
    "sg:postcode":"65804",
    "sg:province":"MO",
    "sg:tags":[
        "consultant",
        "coach"
    ],
    "wof:name":"Integrated Containment Systems",
    "wof:placetype":"venue"
},
  "geometry": {"coordinates":[-93.239946,37.173917],"type":"Point"}
}