{
  "type": "Feature",
  "properties": {
    "iso:country":"US",
    "sg:address":"3260 E Battlefield Rd",
    "sg:city":"Springfield",
    "sg:classifiers":[
        {
            "category":"Shopping",
            "type":"Retail Goods"
        }
    ],
    "sg:phone":"+1 417 890 2627",
    "sg:postcode":"65804",
    "sg:province":"MO",
    "sg:tags":[
        "telephone",
        "cellular"
    ],
    "wof:name":"Celltex Cellular",
    "wof:placetype":"venue"
},
  "geometry": {"coordinates":[-93.228976,37.158116],"type":"Point"}
}