{
  "type": "Feature",
  "properties": {
    "iso:country":"US",
    "sg:address":"31676 Sunnyside Rd",
    "sg:city":"California",
    "sg:classifiers":[
        {
            "category":"Farming",
            "subcategory":"Farm",
            "type":"Manufacturing & Wholesale Goods"
        }
    ],
    "sg:phone":"+1 573 796 4282",
    "sg:postcode":"65018",
    "sg:province":"MO",
    "sg:tags":[
        "camp",
        "crop",
        "general"
    ],
    "wof:name":"String Creek Game Bird Farm",
    "wof:placetype":"venue"
},
  "geometry": {"coordinates":[-92.526591,38.605883],"type":"Point"}
}