{
  "type": "Feature",
  "properties": {
    "iso:country":"US",
    "sg:address":"3551 Cattle Creek Rd",
    "sg:city":"Warm Springs",
    "sg:classifiers":[
        {
            "category":"Organizations",
            "subcategory":"Religious Organization",
            "type":"Services"
        }
    ],
    "sg:phone":"+1 870 647 2576",
    "sg:postcode":"72478",
    "sg:province":"MO",
    "sg:tags":[
        "church"
    ],
    "wof:name":"Palestine Church Of Christ",
    "wof:placetype":"venue"
},
  "geometry": {"coordinates":[-90.983842,36.421326],"type":"Point"}
}