{
  "type": "Feature",
  "properties": {
    "iso:country":"US",
    "sg:address":"907 Cedar St",
    "sg:city":"Bismarck",
    "sg:classifiers":[
        {
            "category":"Manufacturing",
            "subcategory":"Signs",
            "type":"Manufacturing & Wholesale Goods"
        }
    ],
    "sg:phone":"+1 573 431 7333",
    "sg:postcode":"63624",
    "sg:province":"MO",
    "wof:name":"Grisham Rustic Signs",
    "wof:placetype":"venue"
},
  "geometry": {"coordinates":[-90.62481200000001,37.769131],"type":"Point"}
}