{
  "type": "Feature",
  "properties": {
    "iso:country":"US",
    "sg:address":"2207 W 7th St",
    "sg:city":"Joplin",
    "sg:classifiers":[
        {
            "category":"Shopping",
            "type":"Retail Goods"
        }
    ],
    "sg:phone":"+1 417 781 8100",
    "sg:postcode":"64801",
    "sg:province":"MO",
    "sg:tags":[
        "pet",
        "shop",
        "merchandise"
    ],
    "wof:name":"Pet Warehouse Inc",
    "wof:placetype":"venue"
},
  "geometry": {"coordinates":[-94.543004,37.084795],"type":"Point"}
}