{
  "type": "Feature",
  "properties": {
    "iso:country":"US",
    "sg:address":"1748 Baxter Forest Valley Ct",
    "sg:city":"Chesterfield",
    "sg:classifiers":[
        {
            "category":"Organizations",
            "subcategory":"Professional Association",
            "type":"Services"
        }
    ],
    "sg:phone":"+1 636 530 0176",
    "sg:postcode":"63005",
    "sg:province":"MO",
    "sg:tags":[
        "durable",
        "good",
        "business"
    ],
    "wof:name":"Worth & Assoc",
    "wof:placetype":"venue"
},
  "geometry": {"coordinates":[-90.577703,38.642523],"type":"Point"}
}