{
  "type": "Feature",
  "properties": {
    "iso:country":"US",
    "sg:address":"5405 E 194th St",
    "sg:city":"Belton",
    "sg:classifiers":[
        {
            "category":"Building & Trades",
            "subcategory":"Construction",
            "type":"Services"
        }
    ],
    "sg:phone":"+1 816 331 5554",
    "sg:postcode":"64012",
    "sg:province":"MO",
    "sg:tags":[
        "contractor"
    ],
    "wof:name":"Jack Huwar Construction",
    "wof:placetype":"venue"
},
  "geometry": {"coordinates":[-94.536886,38.772841],"type":"Point"}
}