{
  "type": "Feature",
  "properties": {
    "iso:country":"US",
    "sg:address":"318 S Main St",
    "sg:city":"Independence",
    "sg:classifiers":[
        {
            "category":"Food & Beverages",
            "subcategory":"Bakery",
            "type":"Retail Goods"
        }
    ],
    "sg:phone":"+1 816 257 0594",
    "sg:postcode":"64050",
    "sg:province":"MO",
    "wof:name":"Bantam Bakery Shop",
    "wof:placetype":"venue"
},
  "geometry": {"coordinates":[-94.415908,39.089462],"type":"Point"}
}