{
  "type": "Feature",
  "properties": {
    "iso:country":"US",
    "sg:address":"326 E Jackson Blvd",
    "sg:city":"Jackson",
    "sg:classifiers":[
        {
            "category":"Wholesale",
            "subcategory":"Home Furnishings",
            "type":"Manufacturing & Wholesale Goods"
        }
    ],
    "sg:phone":"+1 573 243 0779",
    "sg:postcode":"63755",
    "sg:province":"MO",
    "sg:tags":[
        "glass"
    ],
    "wof:name":"Jackson Glass Inc",
    "wof:placetype":"venue"
},
  "geometry": {"coordinates":[-89.664592,37.376192],"type":"Point"}
}