{
  "type": "Feature",
  "properties": {
    "iso:country":"US",
    "sg:address":"10195 Corporate Square Dr",
    "sg:city":"Saint Louis",
    "sg:classifiers":[
        {
            "category":"Social Services",
            "type":"Services"
        }
    ],
    "sg:phone":"+1 314 516 2740",
    "sg:postcode":"63132",
    "sg:province":"MO",
    "sg:tags":[
        "health",
        "emergency"
    ],
    "wof:name":"Red Cross",
    "wof:placetype":"venue"
},
  "geometry": {"coordinates":[-90.401335,38.679381],"type":"Point"}
}