{
  "type": "Feature",
  "properties": {
    "iso:country":"US",
    "sg:address":"348 Foote Lane Rd",
    "sg:city":"Eldon",
    "sg:classifiers":[
        {
            "category":"Farming",
            "subcategory":"Farm",
            "type":"Manufacturing & Wholesale Goods"
        }
    ],
    "sg:phone":"+1 573 392 3041",
    "sg:postcode":"65026",
    "sg:province":"MO",
    "wof:name":"Henley Farm",
    "wof:placetype":"venue"
},
  "geometry": {"coordinates":[-92.619861,38.298646],"type":"Point"}
}