{
  "type": "Feature",
  "properties": {
    "iso:country":"US",
    "sg:address":"1 Elm St",
    "sg:city":"Chillicothe",
    "sg:classifiers":[
        {
            "category":"Restaurant",
            "type":"Food & Drink"
        }
    ],
    "sg:phone":"+1 660 646 6777",
    "sg:postcode":"64601",
    "sg:province":"MO",
    "sg:tags":[
        "house",
        "steak",
        "barbecue"
    ],
    "wof:name":"Wabash BBQ",
    "wof:placetype":"venue"
},
  "geometry": {"coordinates":[-93.551338,39.787868],"type":"Point"}
}