{
  "type": "Feature",
  "properties": {
    "iso:country":"US",
    "sg:address":"1511 Washington Ave",
    "sg:city":"St. Louis",
    "sg:classifiers":[
        {
            "category":"Restaurant",
            "type":"Food & Drink"
        }
    ],
    "sg:phone":"+1 314 241 0100",
    "sg:postcode":"63103",
    "sg:province":"MO",
    "sg:tags":[
        "traditional",
        "american"
    ],
    "sg:website":"www.ozziesrestaurantandsportsbar...",
    "wof:name":"Ozzie's Restaurant & Sports Bar",
    "wof:placetype":"venue"
},
  "geometry": {"coordinates":[-90.201052,38.633006],"type":"Point"}
}