{
  "type": "Feature",
  "properties": {
    "iso:country":"US",
    "sg:address":"1700 Highway F",
    "sg:city":"Defiance",
    "sg:classifiers":[
        {
            "category":"Manufacturing",
            "subcategory":"Petroleum Products",
            "type":"Manufacturing & Wholesale Goods"
        }
    ],
    "sg:phone":"+1 636 798 3283",
    "sg:postcode":"63341",
    "sg:province":"MO",
    "sg:tags":[
        "contract"
    ],
    "wof:name":"Rainbow Canyon Mfg Corp",
    "wof:placetype":"venue"
},
  "geometry": {"coordinates":[-90.849733,38.648279],"type":"Point"}
}