{
  "type": "Feature",
  "properties": {
    "iso:country":"US",
    "sg:address":"3378 S Scenic Ave",
    "sg:city":"Springfield",
    "sg:classifiers":[
        {
            "category":"Insurance",
            "subcategory":"Hazard Insurance",
            "type":"Services"
        }
    ],
    "sg:phone":"+1 417 887 5353",
    "sg:postcode":"65807",
    "sg:province":"MO",
    "sg:tags":[
        "commercial",
        "business"
    ],
    "wof:name":"Healthpointe Insurance Solutions",
    "wof:placetype":"venue"
},
  "geometry": {"coordinates":[-93.332191,37.153032],"type":"Point"}
}