{
  "type": "Feature",
  "properties": {
    "iso:country":"US",
    "sg:address":"312 Main St",
    "sg:city":"Steelville",
    "sg:classifiers":[
        {
            "category":"Autos & Motor Vehicles",
            "subcategory":"Automobile Sales",
            "type":"Retail Goods"
        }
    ],
    "sg:phone":"+1 573 775 2500",
    "sg:postcode":"65565",
    "sg:province":"MO",
    "sg:tags":[
        "car",
        "dealer"
    ],
    "wof:name":"Jack's Auto Sales",
    "wof:placetype":"venue"
},
  "geometry": {"coordinates":[-91.356559,37.967616],"type":"Point"}
}