{
  "type": "Feature",
  "properties": {
    "iso:country":"US",
    "sg:address":"114 N Leonard St",
    "sg:city":"Liberty",
    "sg:classifiers":[
        {
            "category":"Manufacturing",
            "subcategory":"Buildings",
            "type":"Manufacturing & Wholesale Goods"
        },
        {
            "category":"Building & Trades",
            "subcategory":"Construction",
            "type":"Services"
        }
    ],
    "sg:phone":"+1 913 933 3081",
    "sg:postcode":"64068",
    "sg:province":"MO",
    "sg:tags":[
        "altering",
        "home",
        "builder",
        "remodeling",
        "contractor"
    ],
    "wof:name":"J.T.A Custom Homes, Inc.",
    "wof:placetype":"venue"
},
  "geometry": {"coordinates":[-94.417552,39.247007],"type":"Point"}
}