{
  "type": "Feature",
  "properties": {
    "iso:country":"US",
    "sg:address":"6229 Gravois Ave",
    "sg:city":"St Louis",
    "sg:classifiers":[
        {
            "category":"Professional",
            "type":"Services"
        }
    ],
    "sg:phone":"+1 314 352 0221",
    "sg:postcode":"63116",
    "sg:province":"MO",
    "sg:tags":[
        "establishment"
    ],
    "wof:name":"Penny Pincher's",
    "wof:placetype":"venue"
},
  "geometry": {"coordinates":[-90.27969899999999,38.574312],"type":"Point"}
}