{
  "type": "Feature",
  "properties": {
    "iso:country":"US",
    "sg:address":"1731 Sergeant Pepper St",
    "sg:city":"Union",
    "sg:classifiers":[
        {
            "category":"Freight",
            "type":"Transportation"
        }
    ],
    "sg:phone":"+1 636 584 0633",
    "sg:postcode":"63084",
    "sg:province":"MO",
    "sg:tags":[
        "operator",
        "local",
        "trucking"
    ],
    "wof:name":"Frossard Trucking Inc",
    "wof:placetype":"venue"
},
  "geometry": {"coordinates":[-90.956529,38.435756],"type":"Point"}
}