{
  "type": "Feature",
  "properties": {
    "iso:country":"US",
    "sg:address":"1109 E 13th St",
    "sg:city":"Sedalia",
    "sg:classifiers":[
        {
            "category":"Organizations",
            "subcategory":"Religious Organization",
            "type":"Services"
        }
    ],
    "sg:phone":"+1 660 829 3000",
    "sg:postcode":"65301",
    "sg:province":"MO",
    "sg:tags":[
        "church"
    ],
    "wof:name":"Victory Worship Center",
    "wof:placetype":"venue"
},
  "geometry": {"coordinates":[-93.214687,38.699647],"type":"Point"}
}