{
  "type": "Feature",
  "properties": {
    "iso:country":"US",
    "sg:address":"4116 Defoe Dr",
    "sg:city":"Columbia",
    "sg:classifiers":[
        {
            "category":"Building & Trades",
            "subcategory":"Landscaping Services",
            "type":"Services"
        }
    ],
    "sg:phone":"+1 573 447 0799",
    "sg:postcode":"65203",
    "sg:province":"MO",
    "wof:name":"Mark Lange Lawn & Decks",
    "wof:placetype":"venue"
},
  "geometry": {"coordinates":[-92.395456,38.953834],"type":"Point"}
}