{
  "type": "Feature",
  "properties": {
    "iso:country":"US",
    "sg:address":"6414 Hampton Ave",
    "sg:city":"Saint Louis",
    "sg:classifiers":[
        {
            "category":"Home & Garden",
            "subcategory":"Home Furnishings",
            "type":"Retail Goods"
        }
    ],
    "sg:phone":"+1 314 481 3358",
    "sg:postcode":"63109",
    "sg:province":"MO",
    "sg:tags":[
        "bath",
        "kitchen"
    ],
    "sg:website":"www.pargreen.com",
    "wof:name":"Pargreen Sales Engineering",
    "wof:placetype":"venue"
},
  "geometry": {"coordinates":[-90.294759,38.57405],"type":"Point"}
}