{
  "type": "Feature",
  "properties": {
    "iso:country":"US",
    "sg:address":"3120 Lemay Ferry Rd",
    "sg:city":"St Louis",
    "sg:classifiers":[
        {
            "category":"Education",
            "subcategory":"School",
            "type":"Public Place"
        }
    ],
    "sg:phone":"+1 314 467 5000",
    "sg:postcode":"63125",
    "sg:province":"MO",
    "sg:tags":[
        "district"
    ],
    "sg:website":"www.mehlvilleschooldistrict.com",
    "wof:name":"Mehlville School District",
    "wof:placetype":"venue"
},
  "geometry": {"coordinates":[-90.315068,38.514039],"type":"Point"}
}