{
  "type": "Feature",
  "properties": {
    "iso:country":"US",
    "sg:address":"8649 Brookshire Ln",
    "sg:city":"Saint Louis",
    "sg:classifiers":[
        {
            "category":"Professional",
            "subcategory":"Business Services",
            "type":"Services"
        }
    ],
    "sg:phone":"+1 314 991 0624",
    "sg:postcode":"63132",
    "sg:province":"MO",
    "sg:tags":[
        "travel",
        "agency"
    ],
    "wof:name":"Mustard Seed Travel",
    "wof:placetype":"venue"
},
  "geometry": {"coordinates":[-90.35827,38.667042],"type":"Point"}
}