{
  "type": "Feature",
  "properties": {
    "iso:country":"US",
    "sg:address":"810 NE 46 Ter",
    "sg:city":"Kansas City",
    "sg:classifiers":[
        {
            "category":"Social Services",
            "subcategory":"Child Care",
            "type":"Services"
        }
    ],
    "sg:phone":"+1 816 453 5842",
    "sg:postcode":"64116",
    "sg:province":"MO",
    "sg:tags":[
        "day"
    ],
    "wof:name":"Wee Care Preschool",
    "wof:placetype":"venue"
},
  "geometry": {"coordinates":[-94.569157,39.178419],"type":"Point"}
}