{
  "type": "Feature",
  "properties": {
    "iso:country":"US",
    "sg:address":"804 E High St",
    "sg:city":"Jefferson City",
    "sg:classifiers":[
        {
            "category":"Shopping",
            "subcategory":"Used Merchandise",
            "type":"Retail Goods"
        }
    ],
    "sg:phone":"+1 573 636 5509",
    "sg:postcode":"65101",
    "sg:province":"MO",
    "wof:name":"Bare Necessities Collectibles",
    "wof:placetype":"venue"
},
  "geometry": {"coordinates":[-92.163444,38.570434],"type":"Point"}
}