{
  "type": "Feature",
  "properties": {
    "iso:country":"US",
    "sg:address":"124 W 3rd St",
    "sg:city":"Maryville",
    "sg:classifiers":[
        {
            "category":"Manufacturing",
            "subcategory":"Printing",
            "type":"Manufacturing & Wholesale Goods"
        }
    ],
    "sg:phone":"+1 660 562 2715",
    "sg:postcode":"64468",
    "sg:province":"MO",
    "sg:tags":[
        "newspaper"
    ],
    "wof:name":"Democrat Headquarters",
    "wof:placetype":"venue"
},
  "geometry": {"coordinates":[-94.873851,40.34785],"type":"Point"}
}