{
  "type": "Feature",
  "properties": {
    "iso:country":"US",
    "sg:address":"1157 Elbring Dr",
    "sg:city":"St Louis",
    "sg:classifiers":[
        {
            "category":"Arts & Performance",
            "subcategory":"Theater",
            "type":"Entertainment"
        }
    ],
    "sg:phone":"+1 314 432 0606",
    "sg:postcode":"63132",
    "sg:province":"MO",
    "sg:tags":[
        "band",
        "orchestra",
        "group"
    ],
    "wof:name":"Elegant Ensembles",
    "wof:placetype":"venue"
},
  "geometry": {"coordinates":[-90.37335,38.675231],"type":"Point"}
}