{
  "type": "Feature",
  "properties": {
    "iso:country":"US",
    "sg:address":"7864 Red Bird Ln",
    "sg:city":"Bonne Terre",
    "sg:classifiers":[
        {
            "category":"Home & Garden",
            "subcategory":"Household Appliances",
            "type":"Retail Goods"
        }
    ],
    "sg:phone":"+1 573 358 0846",
    "sg:postcode":"63628",
    "sg:province":"MO",
    "wof:name":"Appliance World",
    "wof:placetype":"venue"
},
  "geometry": {"coordinates":[-90.525263,37.932805],"type":"Point"}
}