{
  "type": "Feature",
  "properties": {
    "iso:country":"US",
    "sg:address":"4003 Gravois Rd",
    "sg:city":"House Springs",
    "sg:classifiers":[
        {
            "category":"Building & Trades",
            "subcategory":"Landscaping Services",
            "type":"Services"
        }
    ],
    "sg:phone":"+1 636 671 2900",
    "sg:postcode":"63051",
    "sg:province":"MO",
    "sg:tags":[
        "landscape",
        "contractor"
    ],
    "wof:name":"Aim To Please Lawn & Landscape",
    "wof:placetype":"venue"
},
  "geometry": {"coordinates":[-90.552982,38.425672],"type":"Point"}
}