{
  "type": "Feature",
  "properties": {
    "iso:country":"US",
    "sg:address":"805 S Mine la Motte St",
    "sg:city":"Fredericktown",
    "sg:classifiers":[
        {
            "category":"Personal",
            "subcategory":"Beauty Salon",
            "type":"Services"
        },
        {
            "category":"Personal",
            "subcategory":"Tanning Parlor",
            "type":"Services"
        }
    ],
    "sg:phone":"+1 573 783 5980",
    "sg:postcode":"63645",
    "sg:province":"MO",
    "wof:name":"The Rite Cut Beauty & Tanning Salon",
    "wof:placetype":"venue"
},
  "geometry": {"coordinates":[-90.291549,37.547559],"type":"Point"}
}