{
  "type": "Feature",
  "properties": {
    "iso:country":"US",
    "sg:address":"5642 Troost Ave",
    "sg:city":"Kansas City",
    "sg:classifiers":[
        {
            "category":"Retail",
            "subcategory":"Car Wash",
            "type":"Services"
        }
    ],
    "sg:phone":"+1 816 333 4690",
    "sg:postcode":"64110",
    "sg:province":"MO",
    "sg:tags":[
        "carwash"
    ],
    "wof:name":"Mega Wash LLC",
    "wof:placetype":"venue"
},
  "geometry": {"coordinates":[-94.574037,39.024349],"type":"Point"}
}