{
  "type": "Feature",
  "properties": {
    "iso:country":"US",
    "sg:address":"1000 E 11 St",
    "sg:city":"Kansas City",
    "sg:classifiers":[
        {
            "category":"Wholesale",
            "subcategory":"Construction Materials",
            "type":"Manufacturing & Wholesale Goods"
        }
    ],
    "sg:phone":"+1 816 472 6622",
    "sg:postcode":"64106",
    "sg:province":"MO",
    "sg:tags":[
        "wholesaler",
        "acoustical",
        "ceiling",
        "specialty",
        "wa"
    ],
    "wof:name":"Wagner Interior Supply Inc",
    "wof:placetype":"venue"
},
  "geometry": {"coordinates":[-94.569835,39.10069],"type":"Point"}
}