{
  "type": "Feature",
  "properties": {
    "iso:country":"US",
    "sg:address":"103 S Lincoln Ave",
    "sg:city":"Monett",
    "sg:classifiers":[
        {
            "category":"Professional",
            "subcategory":"Art Services",
            "type":"Services"
        }
    ],
    "sg:phone":"+1 417 235 8848",
    "sg:postcode":"65708",
    "sg:province":"MO",
    "sg:tags":[
        "taxidermist"
    ],
    "wof:name":"Reflections Of Fifth Sixth Day",
    "wof:placetype":"venue"
},
  "geometry": {"coordinates":[-93.926689,36.906659],"type":"Point"}
}