{
  "type": "Feature",
  "properties": {
    "iso:country":"US",
    "sg:address":"919 N Oakland Ave",
    "sg:city":"Mountain Grove",
    "sg:classifiers":[
        {
            "category":"Wholesale",
            "subcategory":"Dairy",
            "type":"Manufacturing & Wholesale Goods"
        }
    ],
    "sg:phone":"+1 417 926 4737",
    "sg:postcode":"65711",
    "sg:province":"MO",
    "sg:tags":[
        "canned",
        "product",
        "or",
        "except",
        "dried"
    ],
    "wof:name":"Loanstar Milk Producers",
    "wof:placetype":"venue"
},
  "geometry": {"coordinates":[-92.265435,37.138028],"type":"Point"}
}