{
  "type": "Feature",
  "properties": {
    "iso:country":"US",
    "sg:address":"1401 N Kingshighway Blvd",
    "sg:city":"Saint Louis",
    "sg:classifiers":[
        {
            "category":"Professional",
            "subcategory":"Business Services",
            "type":"Services"
        }
    ],
    "sg:phone":"+1 314 361 6111",
    "sg:postcode":"63113",
    "sg:province":"MO",
    "wof:name":"EZ Fundraising",
    "wof:placetype":"venue"
},
  "geometry": {"coordinates":[-90.26173799999999,38.661863],"type":"Point"}
}