{
  "type": "Feature",
  "properties": {
    "iso:country":"US",
    "sg:address":"9260 Watson Rd",
    "sg:city":"St Louis",
    "sg:classifiers":[
        {
            "category":"Restaurant",
            "type":"Food & Drink"
        }
    ],
    "sg:phone":"+1 314 849 5030",
    "sg:postcode":"63126",
    "sg:province":"MO",
    "sg:tags":[
        "pizza"
    ],
    "wof:name":"Pizza Hut",
    "wof:placetype":"venue"
},
  "geometry": {"coordinates":[-90.37456,38.559676],"type":"Point"}
}