{
  "type": "Feature",
  "properties": {
    "iso:country":"US",
    "sg:address":"2711 Maurer Ave",
    "sg:city":"Saint Louis",
    "sg:classifiers":[
        {
            "category":"Professional",
            "type":"Services"
        }
    ],
    "sg:phone":"+1 314 385 5611",
    "sg:postcode":"63121",
    "sg:province":"MO",
    "wof:name":"Lamont Tabbs",
    "wof:placetype":"venue"
},
  "geometry": {"coordinates":[-90.293333,38.692079],"type":"Point"}
}