{
  "type": "Feature",
  "properties": {
    "iso:country":"US",
    "sg:address":"3000 S Jefferson",
    "sg:city":"St Louis",
    "sg:classifiers":[
        {
            "category":"Professional",
            "subcategory":"Lawyer & Legal Services",
            "type":"Services"
        }
    ],
    "sg:phone":"+1 314 872 2120",
    "sg:postcode":"63118",
    "sg:province":"MO",
    "sg:tags":[
        "personal",
        "injury"
    ],
    "sg:website":"www.markdeanlaw.com",
    "wof:name":"Law Offices of Mark Dean",
    "wof:placetype":"venue"
},
  "geometry": {"coordinates":[-90.22375,38.599507],"type":"Point"}
}