{
  "type": "Feature",
  "properties": {
    "iso:country":"US",
    "sg:address":"11338 Sycamore Ter",
    "sg:city":"Kansas City",
    "sg:classifiers":[
        {
            "category":"Shopping",
            "subcategory":"Gifts & Souvenirs",
            "type":"Retail Goods"
        }
    ],
    "sg:phone":"+1 816 761 1154",
    "sg:postcode":"64134",
    "sg:province":"MO",
    "wof:name":"Smyth Fabtastick Gifts",
    "wof:placetype":"venue"
},
  "geometry": {"coordinates":[-94.49752599999999,38.918912],"type":"Point"}
}