{
  "type": "Feature",
  "properties": {
    "addr:full":"308 N Mc Coy Ave Joplin MO 64801",
    "addr:housenumber":"308",
    "addr:postcode":"64801",
    "addr:street":"N Mc Coy Ave",
    "iso:country":"US",
    "sg:address":"308 N Mc Coy Ave",
    "sg:city":"Joplin",
    "sg:classifiers":[
        {
            "category":"Food & Beverages",
            "subcategory":"Specialty",
            "type":"Retail Goods"
        }
    ],
    "sg:phone":"+1 417 358 6665",
    "sg:postcode":"64801",
    "sg:province":"MO",
    "wof:name":"Merle Norman Cosmetics",
    "wof:placetype":"venue"
},
  "geometry": {"coordinates":[-94.532825,37.094106],"type":"Point"}
}