{
  "type": "Feature",
  "properties": {
    "iso:country":"US",
    "sg:address":"3501 Co Rd 328",
    "sg:city":"Jackson",
    "sg:classifiers":[
        {
            "category":"Social Services",
            "subcategory":"Child Care",
            "type":"Services"
        }
    ],
    "sg:phone":"+1 573 243 4493",
    "sg:postcode":"63755",
    "sg:province":"MO",
    "sg:tags":[
        "day"
    ],
    "wof:name":"Ms Peggy's Creative Childcare",
    "wof:placetype":"venue"
},
  "geometry": {"coordinates":[-89.70918,37.38412],"type":"Point"}
}