{
  "type": "Feature",
  "properties": {
    "iso:country":"US",
    "sg:address":"653 State Hwy Z",
    "sg:city":"Cape Girardeau",
    "sg:classifiers":[
        {
            "category":"Education",
            "subcategory":"School",
            "type":"Public Place"
        }
    ],
    "sg:phone":"+1 573 243 9580",
    "sg:postcode":"63701",
    "sg:province":"MO",
    "wof:name":"Gordonville School",
    "wof:placetype":"venue"
},
  "geometry": {"coordinates":[-89.676204,37.311028],"type":"Point"}
}