{
  "type": "Feature",
  "properties": {
    "iso:country":"US",
    "sg:address":"1128 Aspen Dr",
    "sg:city":"Liberty",
    "sg:classifiers":[
        {
            "category":"Building & Trades",
            "subcategory":"Construction",
            "type":"Services"
        }
    ],
    "sg:phone":"+1 816 415 8089",
    "sg:postcode":"64068",
    "sg:province":"MO",
    "sg:tags":[
        "painter"
    ],
    "wof:name":"John Juenger",
    "wof:placetype":"venue"
},
  "geometry": {"coordinates":[-94.406795,39.23235],"type":"Point"}
}