{
  "type": "Feature",
  "properties": {
    "iso:country":"US",
    "sg:address":"1115 N Prairie St",
    "sg:city":"Bloomfield",
    "sg:classifiers":[
        {
            "category":"Professional",
            "type":"Services"
        }
    ],
    "sg:phone":"+1 573 568 3051",
    "sg:postcode":"63825",
    "sg:province":"MO",
    "sg:tags":[
        "establishment"
    ],
    "wof:name":"Castor Township",
    "wof:placetype":"venue"
},
  "geometry": {"coordinates":[-89.928423,36.894835],"type":"Point"}
}