{
  "type": "Feature",
  "properties": {
    "iso:country":"US",
    "sg:address":"2386 W Jackson Blvd",
    "sg:city":"Jackson",
    "sg:classifiers":[
        {
            "category":"Health Services",
            "subcategory":"Doctor",
            "type":"Services"
        },
        {
            "category":"Health Services",
            "subcategory":"Clinic",
            "type":"Services"
        }
    ],
    "sg:phone":"+1 573 651 3691",
    "sg:postcode":"63755",
    "sg:province":"MO",
    "sg:tags":[
        "psychological",
        "psychologist"
    ],
    "wof:name":"Jerrell L Driver Phd",
    "wof:placetype":"venue"
},
  "geometry": {"coordinates":[-89.700164,37.384347],"type":"Point"}
}