{
  "type": "Feature",
  "properties": {
    "iso:country":"US",
    "sg:address":"8402 Edwards Rd",
    "sg:city":"Orrick",
    "sg:classifiers":[
        {
            "category":"Farming",
            "subcategory":"Farm",
            "type":"Manufacturing & Wholesale Goods"
        }
    ],
    "sg:phone":"+1 816 750 4480",
    "sg:postcode":"64077",
    "sg:province":"MO",
    "sg:tags":[
        "crop",
        "general"
    ],
    "wof:name":"Darrel Padgett",
    "wof:placetype":"venue"
},
  "geometry": {"coordinates":[-94.25903599999999,39.249941],"type":"Point"}
}