{
  "type": "Feature",
  "properties": {
    "iso:country":"US",
    "sg:address":"3355 Shepherd Of The Hills Expy",
    "sg:city":"Branson",
    "sg:classifiers":[
        {
            "category":"Travel",
            "subcategory":"Hotels & Motels",
            "type":"Entertainment"
        },
        {
            "category":"Travel",
            "subcategory":"Bed & Breakfast",
            "type":"Entertainment"
        }
    ],
    "sg:phone":"+1 417 336 6600",
    "sg:postcode":"65616",
    "sg:province":"MO",
    "sg:tags":[
        "inn"
    ],
    "sg:website":"http://www.bransonorangeblossominn.com",
    "wof:name":"Orange Blossom Inn",
    "wof:placetype":"venue"
},
  "geometry": {"coordinates":[-93.286485,36.652684],"type":"Point"}
}