{
  "type": "Feature",
  "properties": {
    "iso:country":"US",
    "sg:address":"2649 Pestalozzi St",
    "sg:city":"Saint Louis",
    "sg:classifiers":[
        {
            "category":"Professional",
            "subcategory":"Employment Agencies",
            "type":"Services"
        }
    ],
    "sg:phone":"+1 314 865 4453",
    "sg:postcode":"63118",
    "sg:province":"MO",
    "wof:name":"Near Sthside Emplyment Clition",
    "wof:placetype":"venue"
},
  "geometry": {"coordinates":[-90.225801,38.60164],"type":"Point"}
}