{
  "type": "Feature",
  "properties": {
    "iso:country":"US",
    "sg:address":"600 Park Ln",
    "sg:city":"Chillicothe",
    "sg:classifiers":[
        {
            "category":"Shopping",
            "subcategory":"Pharmacy",
            "type":"Retail Goods"
        }
    ],
    "sg:phone":"+1 660 707 0080",
    "sg:postcode":"64601",
    "sg:province":"MO",
    "wof:name":"Medicine Shoppe Pharmacy",
    "wof:placetype":"venue"
},
  "geometry": {"coordinates":[-93.550586,39.806958],"type":"Point"}
}