{
  "type": "Feature",
  "properties": {
    "iso:country":"US",
    "sg:address":"7491 Big Bend Blvd",
    "sg:city":"Saint Louis",
    "sg:classifiers":[
        {
            "category":"Restaurant",
            "type":"Food & Drink"
        }
    ],
    "sg:menulink":"http://www.allmenus.com/mo/webster-groves/219192-zinnia/menu/",
    "sg:phone":"+1 314 962 0572",
    "sg:postcode":"63119",
    "sg:province":"MO",
    "sg:tags":[
        "new",
        "american"
    ],
    "wof:name":"Zinnia",
    "wof:placetype":"venue"
},
  "geometry": {"coordinates":[-90.32711399999999,38.600539],"type":"Point"}
}