{
  "type": "Feature",
  "properties": {
    "iso:country":"US",
    "sg:address":"647 State Hwy 92",
    "sg:city":"Kearney",
    "sg:classifiers":[
        {
            "category":"Food & Beverages",
            "subcategory":"Liquor & Beverages",
            "type":"Retail Goods"
        }
    ],
    "sg:phone":"+1 816 628 3939",
    "sg:postcode":"64060",
    "sg:province":"MO",
    "wof:name":"Paradise Liquors",
    "wof:placetype":"venue"
},
  "geometry": {"coordinates":[-94.35326999999999,39.367732],"type":"Point"}
}