{
  "type": "Feature",
  "properties": {
    "iso:country":"US",
    "sg:address":"3920 N Chouteau Trfy",
    "sg:city":"Kansas City",
    "sg:classifiers":[
        {
            "category":"Restaurant",
            "type":"Food & Drink"
        }
    ],
    "sg:phone":"+1 816 452 3150",
    "sg:postcode":"64117",
    "sg:province":"MO",
    "wof:name":"Harry's T's Corner Bar",
    "wof:placetype":"venue"
},
  "geometry": {"coordinates":[-94.532206,39.165862],"type":"Point"}
}