{
  "type": "Feature",
  "properties": {
    "iso:country":"US",
    "sg:address":"123 S 2nd St",
    "sg:city":"Poplar Bluff",
    "sg:classifiers":[
        {
            "category":"Professional",
            "subcategory":"Lawyer & Legal Services",
            "type":"Services"
        }
    ],
    "sg:phone":"+1 573 686 7281",
    "sg:postcode":"63901",
    "sg:province":"MO",
    "sg:tags":[
        "attorney"
    ],
    "sg:website":"www.littlelawoffice.com",
    "wof:name":"Little & Schellhammer",
    "wof:placetype":"venue"
},
  "geometry": {"coordinates":[-90.392141,36.755907],"type":"Point"}
}