{
  "type": "Feature",
  "properties": {
    "iso:country":"US",
    "sg:address":"1360 Randol Ave",
    "sg:city":"Cape Girardeau",
    "sg:classifiers":[
        {
            "category":"Education",
            "subcategory":"School",
            "type":"Public Place"
        }
    ],
    "sg:phone":"+1 573 335 5310",
    "sg:postcode":"63701",
    "sg:province":"MO",
    "wof:name":"Alma Schrader Elementary Schl",
    "wof:placetype":"venue"
},
  "geometry": {"coordinates":[-89.554473,37.32741],"type":"Point"}
}