{
  "type": "Feature",
  "properties": {
    "iso:country":"US",
    "sg:address":"1937 Park Ave",
    "sg:city":"Saint Louis",
    "sg:classifiers":[
        {
            "category":"Retail",
            "subcategory":"Laundry & Dry Cleaning",
            "type":"Services"
        }
    ],
    "sg:phone":"+1 314 436 1355",
    "sg:postcode":"63104",
    "sg:province":"MO",
    "wof:name":"Frontenac Cleaners West End Inc",
    "wof:placetype":"venue"
},
  "geometry": {"coordinates":[-90.212926,38.617459],"type":"Point"}
}