{
  "type": "Feature",
  "properties": {
    "iso:country":"US",
    "sg:address":"711 S Daviess St",
    "sg:city":"Gallatin",
    "sg:classifiers":[
        {
            "category":"Home & Garden",
            "subcategory":"Furniture",
            "type":"Retail Goods"
        },
        {
            "category":"Wholesale",
            "subcategory":"Home Furnishings",
            "type":"Manufacturing & Wholesale Goods"
        }
    ],
    "sg:phone":"+1 660 663 9220",
    "sg:postcode":"64640",
    "sg:province":"MO",
    "sg:tags":[
        "equipment-wholesale",
        "kitchen",
        "equipment-household",
        "manufacturer",
        "cabinet"
    ],
    "wof:name":"Calhoon Cabinets",
    "wof:placetype":"venue"
},
  "geometry": {"coordinates":[-93.963447,39.908785],"type":"Point"}
}