{
  "type": "Feature",
  "properties": {
    "iso:country":"US",
    "sg:address":"691 E Cherry St",
    "sg:city":"Troy",
    "sg:classifiers":[
        {
            "category":"Shopping",
            "type":"Retail Goods"
        }
    ],
    "sg:phone":"+1 636 462 2701",
    "sg:postcode":"63379",
    "sg:province":"MO",
    "sg:tags":[
        "merchandise"
    ],
    "wof:name":"Apple Hearing Solutions",
    "wof:placetype":"venue"
},
  "geometry": {"coordinates":[-90.973884,38.981925],"type":"Point"}
}