{
  "type": "Feature",
  "properties": {
    "iso:country":"US",
    "sg:address":"511 Main St",
    "sg:city":"Belton",
    "sg:classifiers":[
        {
            "category":"Retail",
            "subcategory":"Veterinary Services",
            "type":"Services"
        }
    ],
    "sg:phone":"+1 816 331 3120",
    "sg:postcode":"64012",
    "sg:province":"MO",
    "sg:tags":[
        "merchandise",
        "animal"
    ],
    "wof:name":"Belton Animal Clinic",
    "wof:placetype":"venue"
},
  "geometry": {"coordinates":[-94.53062300000001,38.810485],"type":"Point"}
}