{
  "type": "Feature",
  "properties": {
    "iso:country":"US",
    "sg:address":"1515 Pat Dr",
    "sg:city":"Saint Joseph",
    "sg:classifiers":[
        {
            "category":"Travel",
            "subcategory":"Hotels & Motels",
            "type":"Entertainment"
        }
    ],
    "sg:phone":"+1 816 233 3328",
    "sg:postcode":"64506",
    "sg:province":"MO",
    "wof:name":"Super 8 Motel",
    "wof:placetype":"venue"
},
  "geometry": {"coordinates":[-94.77436400000001,39.783078],"type":"Point"}
}