{
  "type": "Feature",
  "properties": {
    "iso:country":"US",
    "sg:address":"1955 Washington St",
    "sg:city":"Florissant",
    "sg:classifiers":[
        {
            "category":"Building & Trades",
            "subcategory":"Construction",
            "type":"Services"
        }
    ],
    "sg:phone":"+1 314 838 9800",
    "sg:postcode":"63033",
    "sg:province":"MO",
    "sg:tags":[
        "system",
        "contractor",
        "air conditioning"
    ],
    "wof:name":"B & B Heating & Cooling Inc",
    "wof:placetype":"venue"
},
  "geometry": {"coordinates":[-90.31433800000001,38.780486],"type":"Point"}
}