{
  "type": "Feature",
  "properties": {
    "iso:country":"US",
    "sg:address":"2721 Indiana Ave",
    "sg:city":"Joplin",
    "sg:classifiers":[
        {
            "category":"Professional",
            "type":"Services"
        }
    ],
    "sg:phone":"+1 417 781 0888",
    "sg:postcode":"64804",
    "sg:province":"MO",
    "wof:name":"Lee G Howard",
    "wof:placetype":"venue"
},
  "geometry": {"coordinates":[-94.50500700000001,37.059753],"type":"Point"}
}