{
  "type": "Feature",
  "properties": {
    "iso:country":"US",
    "sg:address":"7 Pricewoods Ln",
    "sg:city":"Saint Louis",
    "sg:classifiers":[
        {
            "category":"Manufacturing",
            "subcategory":"Tools & Machinery",
            "type":"Manufacturing & Wholesale Goods"
        }
    ],
    "sg:phone":"+1 314 993 2508",
    "sg:postcode":"63132",
    "sg:province":"MO",
    "sg:tags":[
        "medical",
        "retail",
        "product"
    ],
    "wof:name":"Auxagen Inc",
    "wof:placetype":"venue"
},
  "geometry": {"coordinates":[-90.363719,38.663279],"type":"Point"}
}