{
  "type": "Feature",
  "properties": {
    "iso:country":"US",
    "sg:address":"8 Hilltop Village Center Dr",
    "sg:city":"Eureka",
    "sg:classifiers":[
        {
            "category":"Organizations",
            "subcategory":"Non-profit Organization",
            "type":"Services"
        },
        {
            "category":"Social Services",
            "type":"Services"
        }
    ],
    "sg:phone":"+1 636 938 4221",
    "sg:postcode":"63025",
    "sg:province":"MO",
    "sg:tags":[
        "alternative",
        "abortion"
    ],
    "wof:name":"Birthright-Tri County Eureka",
    "wof:placetype":"venue"
},
  "geometry": {"coordinates":[-90.635705,38.506483],"type":"Point"}
}