{
  "type": "Feature",
  "properties": {
    "iso:country":"US",
    "sg:address":"400 Blase Ave",
    "sg:city":"Saint Louis",
    "sg:classifiers":[
        {
            "category":"Bars & Pubs",
            "type":"Food & Drink"
        }
    ],
    "sg:phone":"+1 314 389 2800",
    "sg:postcode":"63147",
    "sg:province":"MO",
    "sg:tags":[
        "drinking",
        "nightlife"
    ],
    "wof:name":"Rock House Tavern",
    "wof:placetype":"venue"
},
  "geometry": {"coordinates":[-90.228798,38.707298],"type":"Point"}
}