{
  "type": "Feature",
  "properties": {
    "iso:country":"US",
    "sg:address":"7263 Balson Ave",
    "sg:city":"St Louis",
    "sg:classifiers":[
        {
            "category":"Professional",
            "subcategory":"Art Services",
            "type":"Services"
        }
    ],
    "sg:phone":"+1 314 863 0224",
    "sg:postcode":"63130",
    "sg:province":"MO",
    "sg:tags":[
        "graphic",
        "designer"
    ],
    "wof:name":"Traci Moore Graphics",
    "wof:placetype":"venue"
},
  "geometry": {"coordinates":[-90.32319,38.663716],"type":"Point"}
}