{
  "type": "Feature",
  "properties": {
    "iso:country":"US",
    "sg:address":"31503 E Pink Hill Rd",
    "sg:city":"Grain Valley",
    "sg:classifiers":[
        {
            "category":"Farming",
            "subcategory":"Farm",
            "type":"Manufacturing & Wholesale Goods"
        }
    ],
    "sg:phone":"+1 816 229 5122",
    "sg:postcode":"64029",
    "sg:province":"MO",
    "sg:tags":[
        "crop",
        "general"
    ],
    "wof:name":"Hontz Farms",
    "wof:placetype":"venue"
},
  "geometry": {"coordinates":[-94.210581,39.05058],"type":"Point"}
}