{
  "type": "Feature",
  "properties": {
    "iso:country":"US",
    "sg:address":"10600 Raytown Rd",
    "sg:city":"Kansas City",
    "sg:classifiers":[
        {
            "category":"Wholesale",
            "subcategory":"Machinery & Supplies",
            "type":"Manufacturing & Wholesale Goods"
        },
        {
            "category":"Autos & Motor Vehicles",
            "subcategory":"Automobile Sales",
            "type":"Retail Goods"
        }
    ],
    "sg:phone":"+1 816 761 0130",
    "sg:postcode":"64134",
    "sg:province":"MO",
    "sg:tags":[
        "farm",
        "raw",
        "product",
        "material",
        "trailer"
    ],
    "wof:name":"Horse Trailer Sales & Repair",
    "wof:placetype":"venue"
},
  "geometry": {"coordinates":[-94.473012,38.932078],"type":"Point"}
}