{
  "type": "Feature",
  "properties": {
    "iso:country":"US",
    "sg:address":"1208 Kathy St",
    "sg:city":"Fulton",
    "sg:classifiers":[
        {
            "category":"Organizations",
            "subcategory":"Community Association",
            "type":"Services"
        }
    ],
    "sg:phone":"+1 573 642 4149",
    "sg:postcode":"65251",
    "sg:province":"MO",
    "wof:name":"A Reliable Pest Control",
    "wof:placetype":"venue"
},
  "geometry": {"coordinates":[-91.928179,38.861836],"type":"Point"}
}