{
  "type": "Feature",
  "properties": {
    "iso:country":"US",
    "sg:address":"134 N Main St",
    "sg:city":"Seymour",
    "sg:classifiers":[
        {
            "category":"Real Estate",
            "subcategory":"Real Estate Agent",
            "type":"Services"
        }
    ],
    "sg:phone":"+1 417 935 2624",
    "sg:postcode":"65746",
    "sg:province":"MO",
    "wof:name":"Dorthy M Cline Realty",
    "wof:placetype":"venue"
},
  "geometry": {"coordinates":[-92.768056,37.149445],"type":"Point"}
}