{
  "type": "Feature",
  "properties": {
    "iso:country":"US",
    "sg:address":"5031 Manchester Ave",
    "sg:city":"Saint Louis",
    "sg:classifiers":[
        {
            "category":"Professional",
            "type":"Services"
        }
    ],
    "sg:phone":"+1 314 495 4999",
    "sg:postcode":"63110",
    "sg:province":"MO",
    "sg:tags":[
        "caterer"
    ],
    "wof:name":"Let's DO Lunch",
    "wof:placetype":"venue"
},
  "geometry": {"coordinates":[-90.269368,38.625226],"type":"Point"}
}