{
  "type": "Feature",
  "properties": {
    "iso:country":"US",
    "sg:address":"11 Geyer Wood Ln",
    "sg:city":"Saint Louis",
    "sg:classifiers":[
        {
            "category":"Manufacturing",
            "subcategory":"Furniture",
            "type":"Manufacturing & Wholesale Goods"
        }
    ],
    "sg:phone":"+1 314 821 8606",
    "sg:postcode":"63131",
    "sg:province":"MO",
    "sg:tags":[
        "bedding",
        "for",
        "animal",
        "mfg"
    ],
    "wof:name":"J & M Stuart Company Inc",
    "wof:placetype":"venue"
},
  "geometry": {"coordinates":[-90.41628900000001,38.61729],"type":"Point"}
}