{
  "type": "Feature",
  "properties": {
    "iso:country":"US",
    "sg:address":"1601 Gibson St",
    "sg:city":"West Plains",
    "sg:classifiers":[
        {
            "category":"Manufacturing",
            "subcategory":"Tools & Machinery",
            "type":"Manufacturing & Wholesale Goods"
        }
    ],
    "sg:phone":"+1 417 256 9726",
    "sg:postcode":"65775",
    "sg:province":"MO",
    "sg:tags":[
        "control",
        "mfg"
    ],
    "wof:name":"U S Marine Corps",
    "wof:placetype":"venue"
},
  "geometry": {"coordinates":[-91.874768,36.74273],"type":"Point"}
}