{
  "type": "Feature",
  "properties": {
    "addr:full":"10578 Page Ave St Louis MO 63132",
    "addr:housenumber":"10578",
    "addr:postcode":"63132",
    "addr:street":"Page Ave",
    "iso:country":"US",
    "sg:address":"10578 Page Ave",
    "sg:city":"St Louis",
    "sg:classifiers":[
        {
            "category":"Banks & Credit Unions",
            "subcategory":"Bank",
            "type":"Services"
        }
    ],
    "sg:phone":"+1 314 423 4949",
    "sg:postcode":"63132",
    "sg:province":"MO",
    "sg:tags":[
        "depository",
        "banking",
        "check",
        "cashing"
    ],
    "wof:name":"Ace Cash Express",
    "wof:placetype":"venue"
},
  "geometry": {"coordinates":[-90.393118,38.691764],"type":"Point"}
}