{
  "type": "Feature",
  "properties": {
    "iso:country":"US",
    "sg:address":"1928 Independence Ave",
    "sg:city":"Kennett",
    "sg:classifiers":[
        {
            "category":"Real Estate",
            "subcategory":"Real Estate Operator",
            "type":"Services"
        }
    ],
    "sg:phone":"+1 573 717 0601",
    "sg:postcode":"63857",
    "sg:province":"MO",
    "sg:tags":[
        "apartment"
    ],
    "wof:name":"Hillis E George And Ramah George",
    "wof:placetype":"venue"
},
  "geometry": {"coordinates":[-90.029233,36.251999],"type":"Point"}
}