{
  "type": "Feature",
  "properties": {
    "iso:country":"US",
    "sg:address":"106 N 3rd St",
    "sg:city":"Elsberry",
    "sg:classifiers":[
        {
            "category":"Manufacturing",
            "subcategory":"Printing",
            "type":"Manufacturing & Wholesale Goods"
        }
    ],
    "sg:phone":"+1 573 898 9814",
    "sg:postcode":"63343",
    "sg:province":"MO",
    "sg:tags":[
        "newspaper"
    ],
    "wof:name":"Elsberry Democrat",
    "wof:placetype":"venue"
},
  "geometry": {"coordinates":[-90.783267,39.166459],"type":"Point"}
}