{
  "type": "Feature",
  "properties": {
    "addr:full":"3635 S Big Bend Blvd Saint Louis MO 63143",
    "addr:housenumber":"3635",
    "addr:postcode":"63143",
    "addr:street":"S Big Bend Blvd",
    "iso:country":"US",
    "sg:address":"3635 S Big Bend Blvd",
    "sg:city":"Saint Louis",
    "sg:classifiers":[
        {
            "category":"Restaurant",
            "type":"Food & Drink"
        }
    ],
    "sg:menulink":"http://www.allmenus.com/mo/webster-groves/194370-mcdonalds/menu/",
    "sg:postcode":"63143",
    "sg:province":"MO",
    "sg:tags":[
        "burger",
        "american"
    ],
    "wof:name":"McDonald's",
    "wof:placetype":"venue"
},
  "geometry": {"coordinates":[-90.32614100000001,38.601939],"type":"Point"}
}