{
  "type": "Feature",
  "properties": {
    "iso:country":"US",
    "sg:address":"147 Hays Dr",
    "sg:city":"Eldon",
    "sg:classifiers":[
        {
            "category":"Manufacturing",
            "subcategory":"Lumber",
            "type":"Manufacturing & Wholesale Goods"
        }
    ],
    "sg:phone":"+1 573 392 5271",
    "sg:postcode":"65026",
    "sg:province":"MO",
    "sg:tags":[
        "product",
        "sawmill",
        "special"
    ],
    "wof:name":"Eldon Wood Products Co Inc",
    "wof:placetype":"venue"
},
  "geometry": {"coordinates":[-92.57990599999999,38.309056],"type":"Point"}
}