{
  "type": "Feature",
  "properties": {
    "iso:country":"US",
    "sg:address":"177 Concord Plaza Shopping Center",
    "sg:city":"Saint Louis",
    "sg:classifiers":[
        {
            "category":"Professional",
            "subcategory":"Management & Consulting",
            "type":"Services"
        }
    ],
    "sg:phone":"+1 314 842 8850",
    "sg:postcode":"63128",
    "sg:province":"MO",
    "sg:tags":[
        "arts",
        "instructor",
        "marshal"
    ],
    "wof:name":"Vaghi Martial Arts",
    "wof:placetype":"venue"
},
  "geometry": {"coordinates":[-90.361724,38.524429],"type":"Point"}
}