{
  "type": "Feature",
  "properties": {
    "iso:country":"US",
    "sg:address":"Lumiere Place Casino 999 N 2nd St",
    "sg:city":"St. Louis",
    "sg:classifiers":[
        {
            "category":"Restaurant",
            "type":"Food & Drink"
        }
    ],
    "sg:phone":"+1 314 881 7595",
    "sg:postcode":"63102",
    "sg:province":"MO",
    "sg:tags":[
        "steakhouse"
    ],
    "sg:website":"www.lumiereplace.com/sleek",
    "wof:name":"SLeeK",
    "wof:placetype":"venue"
},
  "geometry": {"coordinates":[-90.184017,38.633072],"type":"Point"}
}