{
  "type": "Feature",
  "properties": {
    "iso:country":"US",
    "sg:address":"120 S Main St",
    "sg:city":"Edina",
    "sg:classifiers":[
        {
            "category":"Education",
            "subcategory":"Library",
            "type":"Public Place"
        }
    ],
    "sg:phone":"+1 660 397 2460",
    "sg:postcode":"63537",
    "sg:province":"MO",
    "wof:name":"Knox County Library",
    "wof:placetype":"venue"
},
  "geometry": {"coordinates":[-92.172685,40.167362],"type":"Point"}
}