{
  "type": "Feature",
  "properties": {
    "iso:country":"US",
    "sg:address":"1921 NE Tudor Rd",
    "sg:city":"Lees Summit",
    "sg:classifiers":[
        {
            "category":"Insurance",
            "subcategory":"Insurance Agent",
            "type":"Services"
        }
    ],
    "sg:phone":"+1 816 524 2378",
    "sg:postcode":"64086",
    "sg:province":"MO",
    "wof:name":"Timber & Tuck Ins",
    "wof:placetype":"venue"
},
  "geometry": {"coordinates":[-94.33461699999999,38.93463],"type":"Point"}
}