{
  "type": "Feature",
  "properties": {
    "addr:full":"3000 E Sunshine St Springfield MO 65804",
    "addr:housenumber":"3000",
    "addr:postcode":"65804",
    "addr:street":"E Sunshine St",
    "iso:country":"US",
    "sg:address":"3000 E Sunshine St",
    "sg:city":"Springfield",
    "sg:classifiers":[
        {
            "category":"Banks & Credit Unions",
            "subcategory":"Investment Brokerage",
            "type":"Services"
        }
    ],
    "sg:phone":"+1 417 887 0082",
    "sg:postcode":"65804",
    "sg:province":"MO",
    "sg:tags":[
        "security"
    ],
    "wof:name":"Edward Jones Co",
    "wof:placetype":"venue"
},
  "geometry": {"coordinates":[-93.237342,37.180594],"type":"Point"}
}