{
  "type": "Feature",
  "properties": {
    "iso:country":"US",
    "sg:address":"944 S Golden Ave",
    "sg:city":"Springfield",
    "sg:classifiers":[
        {
            "category":"Professional",
            "type":"Services"
        }
    ],
    "sg:phone":"+1 417 862 2980",
    "sg:postcode":"65802",
    "sg:province":"MO",
    "wof:name":"Linda King Svc",
    "wof:placetype":"venue"
},
  "geometry": {"coordinates":[-93.340102,37.198044],"type":"Point"}
}