{
  "type": "Feature",
  "properties": {
    "iso:country":"US",
    "sg:address":"122 S Dover St",
    "sg:city":"Bonne Terre",
    "sg:classifiers":[
        {
            "category":"Building & Trades",
            "subcategory":"Construction",
            "type":"Services"
        }
    ],
    "sg:phone":"+1 314 913 7899",
    "sg:postcode":"63628",
    "sg:province":"MO",
    "sg:tags":[
        "site",
        "clean"
    ],
    "wof:name":"Suzy Homemaker",
    "wof:placetype":"venue"
},
  "geometry": {"coordinates":[-90.543516,37.919643],"type":"Point"}
}