{
  "type": "Feature",
  "properties": {
    "iso:country":"US",
    "sg:address":"1028 Sinnock Ave",
    "sg:city":"Moberly",
    "sg:classifiers":[
        {
            "category":"Building & Trades",
            "subcategory":"Electrical",
            "type":"Services"
        },
        {
            "category":"Utilities",
            "subcategory":"Electric",
            "type":"Services"
        }
    ],
    "sg:phone":"+1 660 263 1947",
    "sg:postcode":"65270",
    "sg:province":"MO",
    "sg:tags":[
        "company",
        "electrical",
        "contractor"
    ],
    "wof:name":"Long Electric",
    "wof:placetype":"venue"
},
  "geometry": {"coordinates":[-92.42208599999999,39.431183],"type":"Point"}
}