{
  "type": "Feature",
  "properties": {
    "iso:country":"US",
    "sg:address":"302 E Mc Daniel St",
    "sg:city":"Springfield",
    "sg:classifiers":[
        {
            "category":"Shopping",
            "subcategory":"Clothing, Apparel, & Fashions",
            "type":"Retail Goods"
        }
    ],
    "sg:phone":"+1 417 831 5888",
    "sg:postcode":"65806",
    "sg:province":"MO",
    "wof:name":"Silver Alpaca",
    "wof:placetype":"venue"
},
  "geometry": {"coordinates":[-93.289945,37.208067],"type":"Point"}
}