{
  "type": "Feature",
  "properties": {
    "iso:country":"US",
    "sg:address":"1905 Clear Ct",
    "sg:city":"Columbia",
    "sg:classifiers":[
        {
            "category":"Freight",
            "type":"Transportation"
        }
    ],
    "sg:phone":"+1 573 445 9226",
    "sg:postcode":"65203",
    "sg:province":"MO",
    "sg:tags":[
        "operator",
        "local",
        "trucking"
    ],
    "wof:name":"Kemper Moving",
    "wof:placetype":"venue"
},
  "geometry": {"coordinates":[-92.395397,38.932932],"type":"Point"}
}