{
  "type": "Feature",
  "properties": {
    "iso:country":"US",
    "sg:address":"846 Shore Point Rd",
    "sg:city":"Blue Eye",
    "sg:classifiers":[
        {
            "category":"Building & Trades",
            "subcategory":"Construction",
            "type":"Services"
        }
    ],
    "sg:phone":"+1 417 779 4002",
    "sg:postcode":"65611",
    "sg:province":"AR",
    "sg:tags":[
        "house"
    ],
    "wof:name":"Taylor Made Construction LLC",
    "wof:placetype":"venue"
},
  "geometry": {"coordinates":[-93.34188899999999,36.565677],"type":"Point"}
}