{
  "type": "Feature",
  "properties": {
    "iso:country":"US",
    "sg:address":"1831 Scherer Pkwy",
    "sg:city":"St Charles",
    "sg:classifiers":[
        {
            "category":"Wholesale",
            "subcategory":"Machinery & Supplies",
            "type":"Manufacturing & Wholesale Goods"
        }
    ],
    "sg:phone":"+1 636 949 9979",
    "sg:postcode":"63303",
    "sg:province":"MO",
    "sg:tags":[
        "tool"
    ],
    "wof:name":"DCT Ind Supply Co",
    "wof:placetype":"venue"
},
  "geometry": {"coordinates":[-90.52255100000001,38.766131],"type":"Point"}
}