{
  "type": "Feature",
  "properties": {
    "iso:country":"US",
    "sg:address":"504 W US Hwy 60",
    "sg:city":"Mountain View",
    "sg:classifiers":[
        {
            "category":"Shopping",
            "type":"Retail Goods"
        }
    ],
    "sg:phone":"+1 417 934 5529",
    "sg:postcode":"65548",
    "sg:province":"MO",
    "sg:tags":[
        "merchandise"
    ],
    "wof:name":"Global Communications",
    "wof:placetype":"venue"
},
  "geometry": {"coordinates":[-91.70717999999999,37.000859],"type":"Point"}
}