{
  "type": "Feature",
  "properties": {
    "iso:country":"US",
    "sg:address":"503 Walnut St",
    "sg:city":"Kansas City",
    "sg:classifiers":[
        {
            "category":"Restaurant",
            "type":"Food & Drink"
        }
    ],
    "sg:phone":"+1 816 471 0017",
    "sg:postcode":"64106",
    "sg:province":"MO",
    "sg:tags":[
        "eating"
    ],
    "sg:website":"www.kabalkc.com",
    "wof:name":"Kabal Restaurant & Night Club",
    "wof:placetype":"venue"
},
  "geometry": {"coordinates":[-94.581259,39.107662],"type":"Point"}
}