{
  "type": "Feature",
  "properties": {
    "iso:country":"US",
    "sg:address":"2345 Pohlman Rd",
    "sg:city":"Florissant",
    "sg:classifiers":[
        {
            "category":"Building & Trades",
            "subcategory":"Pest Control",
            "type":"Services"
        }
    ],
    "sg:phone":"+1 314 918 7440",
    "sg:postcode":"63033",
    "sg:province":"MO",
    "wof:name":"C B S Pest Control",
    "wof:placetype":"venue"
},
  "geometry": {"coordinates":[-90.280964,38.783636],"type":"Point"}
}