{
  "type": "Feature",
  "properties": {
    "iso:country":"US",
    "sg:address":"100 W Lone Jack Lees Summit Rd",
    "sg:city":"Lone Jack",
    "sg:classifiers":[
        {
            "category":"Personal",
            "subcategory":"Beauty Salon",
            "type":"Services"
        }
    ],
    "sg:phone":"+1 816 697 2662",
    "sg:postcode":"64070",
    "sg:province":"MO",
    "wof:name":"Kathy's Kuttin Korner",
    "wof:placetype":"venue"
},
  "geometry": {"coordinates":[-94.173148,38.872059],"type":"Point"}
}