{
  "type": "Feature",
  "properties": {
    "iso:country":"US",
    "sg:address":"54 THE LEGENDS PKWY STE 153",
    "sg:city":"EUREKA",
    "sg:classifiers":[
        {
            "category":"Personal",
            "type":"Services"
        },
        {
            "category":"Building & Trades",
            "subcategory":"Cleaning & Sanitation",
            "type":"Services"
        }
    ],
    "sg:phone":"+1 636 549 8631",
    "sg:postcode":"63025",
    "sg:province":"MO",
    "sg:tags":[
        "house",
        "window",
        "butlers'",
        "maids'",
        "contractor"
    ],
    "wof:name":"Merry Maids",
    "wof:placetype":"venue"
},
  "geometry": {"coordinates":[-90.629554,38.494168],"type":"Point"}
}