{
  "type": "Feature",
  "properties": {
    "iso:country":"US",
    "sg:address":"17088 Co Rd M",
    "sg:city":"Purdin",
    "sg:classifiers":[
        {
            "category":"Farming",
            "subcategory":"Farm",
            "type":"Manufacturing & Wholesale Goods"
        }
    ],
    "sg:phone":"+1 660 244 3621",
    "sg:postcode":"64674",
    "sg:province":"MO",
    "sg:tags":[
        "general"
    ],
    "wof:name":"Rinehart Farms",
    "wof:placetype":"venue"
},
  "geometry": {"coordinates":[-93.074692,39.937378],"type":"Point"}
}