{
  "type": "Feature",
  "properties": {
    "iso:country":"US",
    "sg:address":"913 E Broadway",
    "sg:city":"Columbia",
    "sg:classifiers":[
        {
            "category":"Shopping",
            "subcategory":"Clothing, Apparel, & Fashions",
            "type":"Retail Goods"
        }
    ],
    "sg:phone":"+1 573 449 3243",
    "sg:postcode":"65201",
    "sg:province":"MO",
    "sg:tags":[
        "store"
    ],
    "wof:name":"USA Styles Kids Fashions",
    "wof:placetype":"venue"
},
  "geometry": {"coordinates":[-92.326533,38.951585],"type":"Point"}
}