{
  "type": "Feature",
  "properties": {
    "iso:country":"US",
    "sg:address":"3029 S Delaware Ave",
    "sg:city":"Springfield",
    "sg:classifiers":[
        {
            "category":"Wholesale",
            "subcategory":"Drugs",
            "type":"Manufacturing & Wholesale Goods"
        }
    ],
    "sg:phone":"+1 417 889 1900",
    "sg:postcode":"65804",
    "sg:province":"MO",
    "sg:tags":[
        "beauty",
        "supply"
    ],
    "wof:name":"Specialty Premiums Plus Inc",
    "wof:placetype":"venue"
},
  "geometry": {"coordinates":[-93.267224,37.159098],"type":"Point"}
}