{
  "type": "Feature",
  "properties": {
    "iso:country":"US",
    "sg:address":"111 E 3rd St",
    "sg:city":"Miller",
    "sg:classifiers":[
        {
            "category":"Government",
            "subcategory":"Office",
            "type":"Public Place"
        }
    ],
    "sg:phone":"+1 417 452 2300",
    "sg:postcode":"65707",
    "sg:province":"MO",
    "wof:name":"Miller County Benefit Road",
    "wof:placetype":"venue"
},
  "geometry": {"coordinates":[-93.84147900000001,37.216295],"type":"Point"}
}