{
  "type": "Feature",
  "properties": {
    "iso:country":"US",
    "sg:address":"6646 Raven Rd",
    "sg:city":"Granby",
    "sg:classifiers":[
        {
            "category":"Building & Trades",
            "subcategory":"Construction",
            "type":"Services"
        }
    ],
    "sg:phone":"+1 417 472 7466",
    "sg:postcode":"64844",
    "sg:province":"MO",
    "sg:tags":[
        "builder",
        "operative"
    ],
    "wof:name":"S & S Construction",
    "wof:placetype":"venue"
},
  "geometry": {"coordinates":[-94.243155,36.973641],"type":"Point"}
}