{
  "type": "Feature",
  "properties": {
    "iso:country":"US",
    "sg:address":"300 W Mineral St",
    "sg:city":"De Soto",
    "sg:classifiers":[
        {
            "category":"Social Services",
            "subcategory":"Child Care",
            "type":"Services"
        }
    ],
    "sg:phone":"+1 636 586 3453",
    "sg:postcode":"63020",
    "sg:province":"MO",
    "wof:name":"De Soto Head Start",
    "wof:placetype":"venue"
},
  "geometry": {"coordinates":[-90.55807,38.13896],"type":"Point"}
}