{
  "type": "Feature",
  "properties": {
    "iso:country":"US",
    "sg:address":"415 Main St",
    "sg:city":"New London",
    "sg:classifiers":[
        {
            "category":"Shopping",
            "subcategory":"Bicycles & Sporting Goods",
            "type":"Retail Goods"
        }
    ],
    "sg:phone":"+1 573 985 3388",
    "sg:postcode":"63459",
    "sg:province":"MO",
    "sg:tags":[
        "bait",
        "fishing"
    ],
    "wof:name":"Terry's Bait & Tackle",
    "wof:placetype":"venue"
},
  "geometry": {"coordinates":[-91.400982,39.585383],"type":"Point"}
}