{
  "type": "Feature",
  "properties": {
    "iso:country":"US",
    "sg:address":"2800 Community Ln",
    "sg:city":"High Ridge",
    "sg:classifiers":[
        {
            "category":"Social Services",
            "type":"Services"
        }
    ],
    "sg:phone":"+1 636 677 4578",
    "sg:postcode":"63049",
    "sg:province":"MO",
    "sg:tags":[
        "senior",
        "citizen"
    ],
    "wof:name":"Mid-East Area Agency On Aging",
    "wof:placetype":"venue"
},
  "geometry": {"coordinates":[-90.533903,38.463977],"type":"Point"}
}