{
  "type": "Feature",
  "properties": {
    "iso:country":"US",
    "sg:address":"924 Masterson St",
    "sg:city":"Kennett",
    "sg:classifiers":[
        {
            "category":"Arts & Performance",
            "subcategory":"Theater",
            "type":"Entertainment"
        }
    ],
    "sg:phone":"+1 573 888 9515",
    "sg:postcode":"63857",
    "sg:province":"MO",
    "sg:tags":[
        "live",
        "music"
    ],
    "wof:name":"Studio DJ Goldie",
    "wof:placetype":"venue"
},
  "geometry": {"coordinates":[-90.03928500000001,36.244948],"type":"Point"}
}