{
  "type": "Feature",
  "properties": {
    "iso:country":"US",
    "sg:address":"1247 Hardesty Ave",
    "sg:city":"Kansas City",
    "sg:classifiers":[
        {
            "category":"Wholesale",
            "subcategory":"Groceries",
            "type":"Manufacturing & Wholesale Goods"
        },
        {
            "category":"Wholesale",
            "subcategory":"Meat",
            "type":"Manufacturing & Wholesale Goods"
        }
    ],
    "sg:phone":"+1 816 241 4848",
    "sg:postcode":"64127",
    "sg:province":"MO",
    "sg:tags":[
        "plant",
        "food",
        "broker",
        "relations",
        "packing",
        "public"
    ],
    "wof:name":"Dewco Marketing Associates",
    "wof:placetype":"venue"
},
  "geometry": {"coordinates":[-94.519334,39.094156],"type":"Point"}
}