{
  "type": "Feature",
  "properties": {
    "iso:country":"US",
    "sg:address":"1605 US Hwy 24",
    "sg:city":"Independence",
    "sg:classifiers":[
        {
            "category":"Shopping",
            "subcategory":"Musical Instruments",
            "type":"Retail Goods"
        }
    ],
    "sg:phone":"+1 816 833 3331",
    "sg:postcode":"64050",
    "sg:province":"MO",
    "wof:name":"Rogers Music Station",
    "wof:placetype":"venue"
},
  "geometry": {"coordinates":[-94.43583599999999,39.102064],"type":"Point"}
}