{
  "type": "Feature",
  "properties": {
    "iso:country":"US",
    "sg:address":"16834 Westglen Farms Dr",
    "sg:city":"Ballwin",
    "sg:classifiers":[
        {
            "category":"Professional",
            "subcategory":"Management & Consulting",
            "type":"Services"
        }
    ],
    "sg:phone":"+1 636 273 3740",
    "sg:postcode":"63011",
    "sg:province":"MO",
    "wof:name":"Knehans Consulting",
    "wof:placetype":"venue"
},
  "geometry": {"coordinates":[-90.62841,38.592837],"type":"Point"}
}