{
  "type": "Feature",
  "properties": {
    "iso:country":"US",
    "sg:address":"17146 Manchester Rd",
    "sg:city":"Grover",
    "sg:classifiers":[
        {
            "category":"Bus Charters",
            "type":"Transportation"
        }
    ],
    "sg:phone":"+1 636 458 2044",
    "sg:postcode":"63040",
    "sg:province":"MO",
    "sg:tags":[
        "rental"
    ],
    "sg:website":"www.laidlaw.com",
    "wof:name":"Laidlaw Transit Inc",
    "wof:placetype":"venue"
},
  "geometry": {"coordinates":[-90.653122,38.579775],"type":"Point"}
}