{
  "type": "Feature",
  "properties": {
    "iso:country":"US",
    "sg:address":"1483 Scenic Dr",
    "sg:city":"Arnold",
    "sg:classifiers":[
        {
            "category":"Building & Trades",
            "subcategory":"Plumbing",
            "type":"Services"
        }
    ],
    "sg:phone":"+1 636 296 3236",
    "sg:postcode":"63010",
    "sg:province":"MO",
    "sg:tags":[
        "plumbing",
        "contractor"
    ],
    "wof:name":"A & R Plumbing & Sewer Clng",
    "wof:placetype":"venue"
},
  "geometry": {"coordinates":[-90.404951,38.447068],"type":"Point"}
}