{
  "type": "Feature",
  "properties": {
    "iso:country":"US",
    "sg:address":"1567 N Warson Rd",
    "sg:city":"St Louis",
    "sg:classifiers":[
        {
            "category":"Wholesale",
            "subcategory":"Chemicals & Plastics",
            "type":"Manufacturing & Wholesale Goods"
        }
    ],
    "sg:phone":"+1 314 427 5577",
    "sg:postcode":"63132",
    "sg:province":"MO",
    "sg:tags":[
        "oxygen"
    ],
    "wof:name":"SOS Technologies",
    "wof:placetype":"venue"
},
  "geometry": {"coordinates":[-90.395262,38.687334],"type":"Point"}
}