{
  "type": "Feature",
  "properties": {
    "iso:country":"US",
    "sg:address":"74 US Hwy 69",
    "sg:city":"Kansas City",
    "sg:classifiers":[
        {
            "category":"Wholesale",
            "subcategory":"Machinery & Supplies",
            "type":"Manufacturing & Wholesale Goods"
        },
        {
            "category":"Home & Garden",
            "subcategory":"Hardware",
            "type":"Retail Goods"
        }
    ],
    "sg:phone":"+1 816 452 7873",
    "sg:postcode":"64119",
    "sg:province":"MO",
    "sg:tags":[
        "tool"
    ],
    "wof:name":"Clark's Tool",
    "wof:placetype":"venue"
},
  "geometry": {"coordinates":[-94.504898,39.197673],"type":"Point"}
}