{
  "type": "Feature",
  "properties": {
    "iso:country":"US",
    "sg:address":"130 S Stewart Rd",
    "sg:city":"Liberty",
    "sg:classifiers":[
        {
            "category":"Health Services",
            "subcategory":"Clinic",
            "type":"Services"
        },
        {
            "category":"Health Services",
            "subcategory":"Hospital",
            "type":"Services"
        }
    ],
    "sg:phone":"+1 816 407 2310",
    "sg:postcode":"64068",
    "sg:province":"MO",
    "sg:tags":[
        "medical"
    ],
    "wof:name":"Work Health Solutions",
    "wof:placetype":"venue"
},
  "geometry": {"coordinates":[-94.454581,39.243442],"type":"Point"}
}