{
  "type": "Feature",
  "properties": {
    "iso:country":"US",
    "sg:address":"1318 Saint Paul Rd",
    "sg:city":"Ballwin",
    "sg:classifiers":[
        {
            "category":"Professional",
            "subcategory":"Detective & Security Services",
            "type":"Services"
        }
    ],
    "sg:phone":"+1 636 394 5024",
    "sg:postcode":"63021",
    "sg:province":"MO",
    "sg:tags":[
        "information",
        "bureau"
    ],
    "wof:name":"Yankowski Removal Service Dba",
    "wof:placetype":"venue"
},
  "geometry": {"coordinates":[-90.581536,38.546452],"type":"Point"}
}