{
  "type": "Feature",
  "properties": {
    "iso:country":"US",
    "sg:address":"9402 W Farm Rd 76",
    "sg:city":"Willard",
    "sg:classifiers":[
        {
            "category":"Farming",
            "subcategory":"Dairy Farm",
            "type":"Manufacturing & Wholesale Goods"
        }
    ],
    "sg:phone":"+1 417 742 3365",
    "sg:postcode":"65781",
    "sg:province":"MO",
    "wof:name":"Gene Smith",
    "wof:placetype":"venue"
},
  "geometry": {"coordinates":[-93.48089299999999,37.311313],"type":"Point"}
}