{
  "type": "Feature",
  "properties": {
    "iso:country":"US",
    "sg:address":"230 N Catamount Blvd",
    "sg:city":"Reeds Spring",
    "sg:classifiers":[
        {
            "category":"Professional",
            "subcategory":"Management & Consulting",
            "type":"Services"
        }
    ],
    "sg:phone":"+1 866 394 8864",
    "sg:postcode":"65737",
    "sg:province":"MO",
    "wof:name":"Grand American Marketing",
    "wof:placetype":"venue"
},
  "geometry": {"coordinates":[-93.36771299999999,36.715288],"type":"Point"}
}