{
  "type": "Feature",
  "properties": {
    "iso:country":"US",
    "sg:address":"1947 S Ingram Mill Rd",
    "sg:city":"Springfield",
    "sg:classifiers":[
        {
            "category":"Real Estate",
            "subcategory":"Real Estate Operator",
            "type":"Services"
        }
    ],
    "sg:phone":"+1 417 886 8008",
    "sg:postcode":"65804",
    "sg:province":"MO",
    "sg:tags":[
        "apartment"
    ],
    "wof:name":"Meheli Pines Apartments",
    "wof:placetype":"venue"
},
  "geometry": {"coordinates":[-93.22582300000001,37.178054],"type":"Point"}
}