{
  "type": "Feature",
  "properties": {
    "iso:country":"US",
    "sg:address":"7349 W Farm Rd 170",
    "sg:city":"Republic",
    "sg:classifiers":[
        {
            "category":"Building & Trades",
            "subcategory":"Construction",
            "type":"Services"
        }
    ],
    "sg:phone":"+1 417 883 7704",
    "sg:postcode":"65738",
    "sg:province":"MO",
    "sg:tags":[
        "excavation",
        "contractor"
    ],
    "wof:name":"Paul Jones Excavating Inc",
    "wof:placetype":"venue"
},
  "geometry": {"coordinates":[-93.438231,37.139939],"type":"Point"}
}