{
  "type": "Feature",
  "properties": {
    "iso:country":"US",
    "sg:address":"15800 E 23rd St S",
    "sg:city":"Independence",
    "sg:classifiers":[
        {
            "category":"Autos & Motor Vehicles",
            "subcategory":"Fuel & Gas Station",
            "type":"Retail Goods"
        }
    ],
    "sg:phone":"+1 816 254 0855",
    "sg:postcode":"64055",
    "sg:province":"MO",
    "sg:tags":[
        "oil"
    ],
    "wof:name":"Gas Mart USA",
    "wof:placetype":"venue"
},
  "geometry": {"coordinates":[-94.38954,39.078341],"type":"Point"}
}