{
  "type": "Feature",
  "properties": {
    "iso:country":"US",
    "sg:address":"25370 State Hwy 17",
    "sg:city":"Waynesville",
    "sg:classifiers":[
        {
            "category":"Autos & Motor Vehicles",
            "subcategory":"Automobile Sales",
            "type":"Retail Goods"
        }
    ],
    "sg:phone":"+1 573 774 5817",
    "sg:postcode":"65583",
    "sg:province":"MO",
    "sg:tags":[
        "car",
        "used",
        "dealer"
    ],
    "wof:name":"Hilltop Motors",
    "wof:placetype":"venue"
},
  "geometry": {"coordinates":[-92.245439,37.791577],"type":"Point"}
}