{
  "type": "Feature",
  "properties": {
    "iso:country":"US",
    "sg:address":"1235 E Cherokee St",
    "sg:city":"Springfield",
    "sg:classifiers":[
        {
            "category":"Health Services",
            "subcategory":"Hospital",
            "type":"Services"
        }
    ],
    "sg:phone":"+1 417 885 2000",
    "sg:postcode":"65804",
    "sg:province":"MO",
    "sg:website":"http://www.stjohns.net",
    "wof:name":"Saint Jhns Bhavioral Hlth Care",
    "wof:placetype":"venue"
},
  "geometry": {"coordinates":[-93.275208,37.17831],"type":"Point"}
}