{
  "type": "Feature",
  "properties": {
    "iso:country":"US",
    "sg:address":"15680 Dresden Lake Ct",
    "sg:city":"Chesterfield",
    "sg:classifiers":[
        {
            "category":"Professional",
            "subcategory":"Management & Consulting",
            "type":"Services"
        }
    ],
    "sg:phone":"+1 636 386 4800",
    "sg:postcode":"63017",
    "sg:province":"MO",
    "sg:tags":[
        "business"
    ],
    "wof:name":"Con-Cure Corp",
    "wof:placetype":"venue"
},
  "geometry": {"coordinates":[-90.55750399999999,38.63606],"type":"Point"}
}