{
  "type": "Feature",
  "properties": {
    "iso:country":"US",
    "sg:address":"166 Rocky Ridge Ln",
    "sg:city":"Forsyth",
    "sg:classifiers":[
        {
            "category":"Government",
            "subcategory":"Police Station",
            "type":"Public Place"
        }
    ],
    "sg:phone":"+1 417 546 3086",
    "sg:postcode":"65653",
    "sg:province":"MO",
    "sg:tags":[
        "department"
    ],
    "wof:name":"License Office Forsyth",
    "wof:placetype":"venue"
},
  "geometry": {"coordinates":[-93.095805,36.675425],"type":"Point"}
}