{
  "type": "Feature",
  "properties": {
    "iso:country":"US",
    "sg:address":"1911 Industrial Dr",
    "sg:city":"Liberty",
    "sg:phone":"+1 816 415 3330",
    "sg:postcode":"64068",
    "sg:province":"MO",
    "wof:name":"Value Place",
    "wof:placetype":"venue"
},
  "geometry": {"coordinates":[-94.451372,39.255595],"type":"Point"}
}