{
  "type": "Feature",
  "properties": {
    "iso:country":"US",
    "sg:address":"6104 Dinosaur Dr",
    "sg:city":"Imperial",
    "sg:classifiers":[
        {
            "category":"Manufacturing",
            "subcategory":"Tools & Machinery",
            "type":"Manufacturing & Wholesale Goods"
        }
    ],
    "sg:phone":"+1 636 464 6336",
    "sg:postcode":"63052",
    "sg:province":"MO",
    "sg:tags":[
        "devices",
        "mfg"
    ],
    "wof:name":"Satelite Location",
    "wof:placetype":"venue"
},
  "geometry": {"coordinates":[-90.388875,38.366342],"type":"Point"}
}