{
  "type": "Feature",
  "properties": {
    "iso:country":"US",
    "sg:address":"101 Hickory St",
    "sg:city":"New Haven",
    "sg:classifiers":[
        {
            "category":"Wholesale",
            "subcategory":"Groceries",
            "type":"Manufacturing & Wholesale Goods"
        }
    ],
    "sg:phone":"+1 573 237 3076",
    "sg:postcode":"63068",
    "sg:province":"MO",
    "sg:tags":[
        "beverage"
    ],
    "wof:name":"Pepsi-Cola Bottling Co",
    "wof:placetype":"venue"
},
  "geometry": {"coordinates":[-91.21653499999999,38.602088],"type":"Point"}
}