{
  "type": "Feature",
  "properties": {
    "iso:country":"US",
    "sg:address":"26757 November Rd",
    "sg:city":"Forest City",
    "sg:phone":"+1 660 446 3657",
    "sg:postcode":"64451",
    "sg:province":"MO",
    "sg:tags":[
        "farm",
        "soybean"
    ],
    "wof:name":"Robert Elliott",
    "wof:placetype":"venue"
},
  "geometry": {"coordinates":[-95.17899300000001,40.027618],"type":"Point"}
}