{
  "type": "Feature",
  "properties": {
    "iso:country":"US",
    "sg:address":"10777 Tri Acre Ln",
    "sg:city":"Ste Genevieve",
    "sg:classifiers":[
        {
            "category":"Organizations",
            "subcategory":"Religious Organization",
            "type":"Services"
        }
    ],
    "sg:phone":"+1 573 883 7122",
    "sg:postcode":"63670",
    "sg:province":"MO",
    "sg:tags":[
        "church"
    ],
    "wof:name":"Second Baptist Church",
    "wof:placetype":"venue"
},
  "geometry": {"coordinates":[-90.160076,37.966686],"type":"Point"}
}