{
  "type": "Feature",
  "properties": {
    "iso:country":"US",
    "sg:address":"704 Lilac Ave",
    "sg:city":"Webster Groves",
    "sg:classifiers":[
        {
            "category":"Professional",
            "subcategory":"Business Services",
            "type":"Services"
        }
    ],
    "sg:phone":"+1 314 961 6325",
    "sg:postcode":"63119",
    "sg:province":"MO",
    "sg:tags":[
        "auctioneer"
    ],
    "wof:name":"Russell D Watkins Co",
    "wof:placetype":"venue"
},
  "geometry": {"coordinates":[-90.348868,38.577605],"type":"Point"}
}