{
  "type": "Feature",
  "properties": {
    "iso:country":"US",
    "sg:address":"2900 Forum Blvd",
    "sg:city":"Columbia",
    "sg:classifiers":[
        {
            "category":"Recreation",
            "type":"Entertainment"
        }
    ],
    "sg:phone":"+1 573 449 2606",
    "sg:postcode":"65203",
    "sg:province":"MO",
    "sg:tags":[
        "club",
        "membership"
    ],
    "wof:name":"Club Woodrail",
    "wof:placetype":"venue"
},
  "geometry": {"coordinates":[-92.36297999999999,38.920739],"type":"Point"}
}