{
  "type": "Feature",
  "properties": {
    "iso:country":"US",
    "sg:address":"1031 Highmont Dr",
    "sg:city":"St Louis",
    "sg:classifiers":[
        {
            "category":"Building & Trades",
            "subcategory":"Landscaping Services",
            "type":"Services"
        }
    ],
    "sg:phone":"+1 314 374 3256",
    "sg:postcode":"63135",
    "sg:province":"MO",
    "sg:tags":[
        "landscape",
        "contractor"
    ],
    "wof:name":"M H Mulch Masters",
    "wof:placetype":"venue"
},
  "geometry": {"coordinates":[-90.28636899999999,38.742187],"type":"Point"}
}