{
  "type": "Feature",
  "properties": {
    "iso:country":"US",
    "sg:address":"3 Doctors Park",
    "sg:city":"Cape Girardeau",
    "sg:classifiers":[
        {
            "category":"Health Services",
            "subcategory":"Doctor",
            "type":"Services"
        }
    ],
    "sg:phone":"+1 573 334 7748",
    "sg:postcode":"63703",
    "sg:province":"MO",
    "sg:tags":[
        "physician",
        "surgeon"
    ],
    "wof:name":"Cape Girardeau Urology Assoc",
    "wof:placetype":"venue"
},
  "geometry": {"coordinates":[-89.575424,37.299224],"type":"Point"}
}