{
  "type": "Feature",
  "properties": {
    "iso:country":"US",
    "sg:address":"6633 Moss Hollow Rd",
    "sg:city":"Barnhart",
    "sg:classifiers":[
        {
            "category":"Government",
            "subcategory":"Fire Station",
            "type":"Public Place"
        }
    ],
    "sg:phone":"+1 636 948 4433",
    "sg:postcode":"63012",
    "sg:province":"MO",
    "sg:tags":[
        "department"
    ],
    "wof:name":"Antonia Fire Dept",
    "wof:placetype":"venue"
},
  "geometry": {"coordinates":[-90.42656700000001,38.35228],"type":"Point"}
}