{
  "type": "Feature",
  "properties": {
    "iso:country":"US",
    "sg:address":"13031 Winchester Ave",
    "sg:city":"Grandview",
    "sg:classifiers":[
        {
            "category":"Place Of Worship",
            "subcategory":"Church",
            "type":"Public Place"
        },
        {
            "category":"Place Of Worship",
            "type":"Public Place"
        }
    ],
    "sg:phone":"+1 816 763 3532",
    "sg:postcode":"64030",
    "sg:province":"MO",
    "sg:tags":[
        "lutheran",
        "america",
        "churches-lutheran",
        "churches-lutheran-evangelical"
    ],
    "wof:name":"Prince Pace Lthran Church-Elca",
    "wof:placetype":"venue"
},
  "geometry": {"coordinates":[-94.511914,38.887585],"type":"Point"}
}