{
  "type": "Feature",
  "properties": {
    "iso:country":"US",
    "sg:address":"2718 Russell Blvd",
    "sg:city":"St Louis",
    "sg:classifiers":[
        {
            "category":"Communications",
            "type":"Services"
        }
    ],
    "sg:phone":"+1 314 772 2456",
    "sg:postcode":"63104",
    "sg:province":"MO",
    "wof:name":"Integrity Communications Inc",
    "wof:placetype":"venue"
},
  "geometry": {"coordinates":[-90.225981,38.611537],"type":"Point"}
}