{
  "type": "Feature",
  "properties": {
    "iso:country":"US",
    "sg:address":"1236 Jungermann Rd",
    "sg:city":"St Peters",
    "sg:classifiers":[
        {
            "category":"Organizations",
            "subcategory":"Membership Organization",
            "type":"Services"
        }
    ],
    "sg:phone":"+1 636 477 0716",
    "sg:postcode":"63376",
    "sg:province":"MO",
    "sg:tags":[
        "athletic"
    ],
    "wof:name":"Disabled Athlete Sports Assn",
    "wof:placetype":"venue"
},
  "geometry": {"coordinates":[-90.57842100000001,38.778372],"type":"Point"}
}