{
  "type": "Feature",
  "properties": {
    "iso:country":"US",
    "sg:address":"712 SW 6 St",
    "sg:city":"Lees Summit",
    "sg:classifiers":[
        {
            "category":"Building & Trades",
            "subcategory":"Pest Control",
            "type":"Services"
        }
    ],
    "sg:phone":"+1 816 524 7121",
    "sg:postcode":"64081",
    "sg:province":"MO",
    "wof:name":"Foxx Pest Control & Hm Scrty",
    "wof:placetype":"venue"
},
  "geometry": {"coordinates":[-94.390343,38.907489],"type":"Point"}
}