{
  "type": "Feature",
  "properties": {
    "iso:country":"US",
    "sg:address":"3346 Sherri Dr",
    "sg:city":"Bernie",
    "sg:classifiers":[
        {
            "category":"Transit Center",
            "subcategory":"Freight",
            "type":"Transportation"
        },
        {
            "category":"Freight",
            "type":"Transportation"
        }
    ],
    "sg:phone":"+1 573 293 4507",
    "sg:postcode":"63822",
    "sg:province":"MO",
    "sg:tags":[
        "local",
        "trucking-motor",
        "trucking"
    ],
    "wof:name":"Larry Summers Trucking",
    "wof:placetype":"venue"
},
  "geometry": {"coordinates":[-89.984444,36.664069],"type":"Point"}
}