{
  "type": "Feature",
  "properties": {
    "iso:country":"US",
    "sg:address":"3010 Sunburst Dr",
    "sg:city":"Smithville",
    "sg:classifiers":[
        {
            "category":"Farming",
            "subcategory":"Livestock Farm",
            "type":"Manufacturing & Wholesale Goods"
        }
    ],
    "sg:phone":"+1 816 532 3922",
    "sg:postcode":"64089",
    "sg:province":"MO",
    "sg:tags":[
        "beef",
        "feedlot",
        "cattle"
    ],
    "wof:name":"Barry Toates",
    "wof:placetype":"venue"
},
  "geometry": {"coordinates":[-94.542272,39.341174],"type":"Point"}
}