{
  "type": "Feature",
  "properties": {
    "iso:country":"US",
    "sg:address":"2606 N Bluff St",
    "sg:city":"Fulton",
    "sg:classifiers":[
        {
            "category":"Retail",
            "subcategory":"Auto Repair",
            "type":"Services"
        }
    ],
    "sg:phone":"+1 573 642 0984",
    "sg:postcode":"65251",
    "sg:province":"MO",
    "sg:tags":[
        "body",
        "muffler",
        "install"
    ],
    "wof:name":"Muffler Center The",
    "wof:placetype":"venue"
},
  "geometry": {"coordinates":[-91.943541,38.879063],"type":"Point"}
}