{
  "type": "Feature",
  "properties": {
    "iso:country":"US",
    "sg:address":"414 Market St",
    "sg:city":"Hermann",
    "sg:classifiers":[
        {
            "category":"Bars & Pubs",
            "type":"Food & Drink"
        }
    ],
    "sg:phone":"+1 573 486 5223",
    "sg:postcode":"65041",
    "sg:province":"MO",
    "sg:tags":[
        "tavern"
    ],
    "wof:name":"Sharp Corner Tavern",
    "wof:placetype":"venue"
},
  "geometry": {"coordinates":[-91.437977,38.704221],"type":"Point"}
}