{
  "type": "Feature",
  "properties": {
    "iso:country":"US",
    "sg:address":"215 N High St",
    "sg:city":"Jackson",
    "sg:classifiers":[
        {
            "category":"Government",
            "subcategory":"Jail",
            "type":"Public Place"
        }
    ],
    "sg:phone":"+1 573 243 3551",
    "sg:postcode":"63755",
    "sg:province":"MO",
    "sg:tags":[
        "county",
        "govt",
        "institution"
    ],
    "wof:name":"County Jail",
    "wof:placetype":"venue"
},
  "geometry": {"coordinates":[-89.667405,37.384322],"type":"Point"}
}