{
  "type": "Feature",
  "properties": {
    "iso:country":"US",
    "sg:address":"7707 NW Prairie View Rd",
    "sg:city":"Kansas City",
    "sg:classifiers":[
        {
            "category":"Real Estate",
            "subcategory":"Real Estate Agent",
            "type":"Services"
        }
    ],
    "sg:phone":"+1 816 587 5084",
    "sg:postcode":"64151",
    "sg:province":"MO",
    "sg:tags":[
        "finding",
        "apartment",
        "rental"
    ],
    "wof:name":"Apartment & Rental Connections",
    "wof:placetype":"venue"
},
  "geometry": {"coordinates":[-94.658686,39.234062],"type":"Point"}
}