{
  "type": "Feature",
  "properties": {
    "iso:country":"US",
    "sg:address":"3825 S Grand Ave",
    "sg:city":"Independence",
    "sg:classifiers":[
        {
            "category":"Real Estate",
            "subcategory":"Real Estate Agent",
            "type":"Services"
        }
    ],
    "sg:phone":"+1 816 461 1000",
    "sg:postcode":"64055",
    "sg:province":"MO",
    "wof:name":"Hub Realty Inc",
    "wof:placetype":"venue"
},
  "geometry": {"coordinates":[-94.430122,39.051164],"type":"Point"}
}