{
  "type": "Feature",
  "properties": {
    "iso:country":"US",
    "sg:address":"103 W Broadway",
    "sg:city":"Columbia",
    "sg:classifiers":[
        {
            "category":"Education",
            "subcategory":"Special Training",
            "type":"Public Place"
        }
    ],
    "sg:phone":"+1 573 449 8312",
    "sg:postcode":"65203",
    "sg:province":"MO",
    "wof:name":"School Of Metaphysics",
    "wof:placetype":"venue"
},
  "geometry": {"coordinates":[-92.341917,38.951468],"type":"Point"}
}