{
  "type": "Feature",
  "properties": {
    "iso:country":"US",
    "sg:address":"11653 Gravois Rd",
    "sg:city":"St Louis",
    "sg:classifiers":[
        {
            "category":"Professional",
            "subcategory":"Art Services",
            "type":"Services"
        }
    ],
    "sg:phone":"+1 314 849 9890",
    "sg:postcode":"63126",
    "sg:province":"MO",
    "sg:tags":[
        "graphic",
        "designer"
    ],
    "sg:website":"www.graphxco.com",
    "wof:name":"Graphics Co",
    "wof:placetype":"venue"
},
  "geometry": {"coordinates":[-90.38211,38.535133],"type":"Point"}
}