{
  "type": "Feature",
  "properties": {
    "iso:country":"US",
    "sg:address":"174 Clarkson Rd",
    "sg:city":"Ellisville",
    "sg:classifiers":[
        {
            "category":"Shopping",
            "subcategory":"Computers & Home Electronics",
            "type":"Retail Goods"
        }
    ],
    "sg:phone":"+1 314 576 9615",
    "sg:postcode":"63011",
    "sg:province":"MO",
    "sg:tags":[
        "software"
    ],
    "wof:name":"ATC Support Svc",
    "wof:placetype":"venue"
},
  "geometry": {"coordinates":[-90.585812,38.597386],"type":"Point"}
}