{
  "type": "Feature",
  "properties": {
    "iso:country":"US",
    "sg:address":"6910 N Holmes St",
    "sg:city":"Kansas City",
    "sg:classifiers":[
        {
            "category":"Building & Trades",
            "subcategory":"Construction",
            "type":"Services"
        }
    ],
    "sg:phone":"+1 816 436 9100",
    "sg:postcode":"64118",
    "sg:province":"MO",
    "sg:tags":[
        "home",
        "builder",
        "operative",
        "house"
    ],
    "wof:name":"J D Nelson Building Co",
    "wof:placetype":"venue"
},
  "geometry": {"coordinates":[-94.57159299999999,39.220104],"type":"Point"}
}