{
  "type": "Feature",
  "properties": {
    "iso:country":"US",
    "sg:address":"2934 Southwest Blvd",
    "sg:city":"Kansas City",
    "sg:classifiers":[
        {
            "category":"Restaurant",
            "type":"Food & Drink"
        }
    ],
    "sg:phone":"+1 816 960 7072",
    "sg:postcode":"64108",
    "sg:province":"MO",
    "sg:tags":[
        "eating"
    ],
    "wof:name":"Del Rio Bar and Grill",
    "wof:placetype":"venue"
},
  "geometry": {"coordinates":[-94.60422800000001,39.074898],"type":"Point"}
}