{
  "type": "Feature",
  "properties": {
    "addr:full":"812 S Main St Concordia MO 64020",
    "addr:housenumber":"812",
    "addr:postcode":"64020",
    "addr:street":"S Main St",
    "iso:country":"US",
    "sg:address":"812 S Main St",
    "sg:city":"Concordia",
    "sg:classifiers":[
        {
            "category":"Utilities",
            "subcategory":"Telephone",
            "type":"Services"
        }
    ],
    "sg:phone":"+1 660 463 2298",
    "sg:postcode":"64020",
    "sg:province":"MO",
    "sg:tags":[
        "company"
    ],
    "wof:name":"Century Tel",
    "wof:placetype":"venue"
},
  "geometry": {"coordinates":[-93.568355,38.981039],"type":"Point"}
}