{
  "type": "Feature",
  "properties": {
    "iso:country":"US",
    "sg:address":"965 State Hwy 215",
    "sg:city":"Morrisville",
    "sg:classifiers":[
        {
            "category":"Retail",
            "subcategory":"Repair Shop",
            "type":"Services"
        }
    ],
    "sg:phone":"+1 417 376 2396",
    "sg:postcode":"65710",
    "sg:province":"MO",
    "sg:tags":[
        "refrigeration"
    ],
    "wof:name":"Kahlar & Rogers Htg & A LLC",
    "wof:placetype":"venue"
},
  "geometry": {"coordinates":[-93.432243,37.481639],"type":"Point"}
}