{
  "type": "Feature",
  "properties": {
    "iso:country":"US",
    "sg:address":"875 Atalanta Ave",
    "sg:city":"Saint Louis",
    "sg:classifiers":[
        {
            "category":"Social Services",
            "type":"Services"
        }
    ],
    "sg:phone":"+1 314 961 9334",
    "sg:postcode":"63119",
    "sg:province":"MO",
    "wof:name":"W Russell Payne PHD",
    "wof:placetype":"venue"
},
  "geometry": {"coordinates":[-90.336314,38.60313],"type":"Point"}
}