{
  "type": "Feature",
  "properties": {
    "iso:country":"US",
    "sg:address":"301 E Missouri St",
    "sg:city":"Kirksville",
    "sg:classifiers":[
        {
            "category":"Professional",
            "subcategory":"Accounting & Tax Preparation",
            "type":"Services"
        }
    ],
    "sg:phone":"+1 660 665 5460",
    "sg:postcode":"63501",
    "sg:province":"MO",
    "sg:tags":[
        "accountant"
    ],
    "wof:name":"Fitzgerald & Floyd",
    "wof:placetype":"venue"
},
  "geometry": {"coordinates":[-92.58093,40.196403],"type":"Point"}
}