{
  "type": "Feature",
  "properties": {
    "iso:country":"US",
    "sg:address":"107 N Jackson St",
    "sg:city":"Shelbyville",
    "sg:classifiers":[
        {
            "category":"Retail",
            "subcategory":"Funeral Services",
            "type":"Services"
        }
    ],
    "sg:phone":"+1 573 633 2311",
    "sg:postcode":"63469",
    "sg:province":"MO",
    "wof:name":"Greening-Eagan-Hayes Inc",
    "wof:placetype":"venue"
},
  "geometry": {"coordinates":[-92.041662,39.806826],"type":"Point"}
}