{
  "type": "Feature",
  "properties": {
    "iso:country":"US",
    "sg:address":"4528 S Broadway",
    "sg:city":"Saint Louis",
    "sg:classifiers":[
        {
            "category":"Manufacturing",
            "subcategory":"Metals",
            "type":"Manufacturing & Wholesale Goods"
        }
    ],
    "sg:phone":"+1 314 481 8291",
    "sg:postcode":"63111",
    "sg:province":"MO",
    "sg:tags":[
        "shop",
        "screw",
        "job",
        "machine",
        "parts"
    ],
    "wof:name":"Otten Products Co",
    "wof:placetype":"venue"
},
  "geometry": {"coordinates":[-90.23373100000001,38.573627],"type":"Point"}
}