{
  "type": "Feature",
  "properties": {
    "iso:country":"US",
    "sg:address":"5266 State Rd Yy",
    "sg:city":"Montgomery City",
    "sg:classifiers":[
        {
            "category":"Real Estate",
            "subcategory":"Real Estate Agent",
            "type":"Services"
        }
    ],
    "sg:phone":"+1 573 254 3395",
    "sg:postcode":"63361",
    "sg:province":"MO",
    "sg:tags":[
        "appraiser"
    ],
    "wof:name":"Schroer Appraisal",
    "wof:placetype":"venue"
},
  "geometry": {"coordinates":[-91.646598,38.865469],"type":"Point"}
}