{
  "type": "Feature",
  "properties": {
    "iso:country":"US",
    "sg:address":"15745 NW 134th St",
    "sg:city":"Platte City",
    "sg:classifiers":[
        {
            "category":"Building & Trades",
            "subcategory":"Construction",
            "type":"Services"
        }
    ],
    "sg:phone":"+1 816 858 5193",
    "sg:postcode":"64079",
    "sg:province":"MO",
    "sg:tags":[
        "hanging",
        "electrical",
        "contractor"
    ],
    "wof:name":"Home Maintenance & Repair",
    "wof:placetype":"venue"
},
  "geometry": {"coordinates":[-94.76161,39.336868],"type":"Point"}
}