{
  "type": "Feature",
  "properties": {
    "iso:country":"US",
    "sg:address":"218 Reasor Dr",
    "sg:city":"Saint Louis",
    "sg:classifiers":[
        {
            "category":"Retail",
            "subcategory":"Repair Shop",
            "type":"Services"
        }
    ],
    "sg:phone":"+1 314 522 3793",
    "sg:postcode":"63135",
    "sg:province":"MO",
    "wof:name":"C JS Delivery & More Inc",
    "wof:placetype":"venue"
},
  "geometry": {"coordinates":[-90.31935799999999,38.762623],"type":"Point"}
}