{
  "type": "Feature",
  "properties": {
    "iso:country":"US",
    "sg:address":"5412 Sycamore Ave",
    "sg:city":"Kansas City",
    "sg:classifiers":[
        {
            "category":"Professional",
            "type":"Services"
        }
    ],
    "sg:phone":"+1 816 923 1678",
    "sg:postcode":"64129",
    "sg:province":"MO",
    "wof:name":"Reginald J Williams",
    "wof:placetype":"venue"
},
  "geometry": {"coordinates":[-94.49212799999999,39.025507],"type":"Point"}
}