{
  "type": "Feature",
  "properties": {
    "iso:country":"US",
    "sg:address":"1181 Prairie Dell Rd",
    "sg:city":"Union",
    "sg:classifiers":[
        {
            "category":"Building & Trades",
            "subcategory":"Landscaping Services",
            "type":"Services"
        }
    ],
    "sg:phone":"+1 636 583 3068",
    "sg:postcode":"63084",
    "sg:province":"MO",
    "sg:tags":[
        "consultant",
        "designer",
        "landscape",
        "contractor"
    ],
    "wof:name":"Fletcher Enterprises Inc",
    "wof:placetype":"venue"
},
  "geometry": {"coordinates":[-90.95873400000001,38.395617],"type":"Point"}
}