{
  "type": "Feature",
  "properties": {
    "iso:country":"US",
    "sg:address":"400 Russell Blvd",
    "sg:city":"St Louis",
    "sg:classifiers":[
        {
            "category":"Wholesale",
            "subcategory":"Machinery & Supplies",
            "type":"Manufacturing & Wholesale Goods"
        }
    ],
    "sg:phone":"+1 314 771 0700",
    "sg:postcode":"63104",
    "sg:province":"MO",
    "sg:tags":[
        "equipment",
        "pump",
        "industrial",
        "mfg"
    ],
    "sg:website":"www.nutvault.com",
    "wof:name":"Pioneer Industrial Corp",
    "wof:placetype":"venue"
},
  "geometry": {"coordinates":[-90.202096,38.605261],"type":"Point"}
}