{
  "type": "Feature",
  "properties": {
    "iso:country":"US",
    "sg:address":"864 Atalanta Ave",
    "sg:city":"Webster Groves",
    "sg:classifiers":[
        {
            "category":"Building & Trades",
            "subcategory":"Cleaning & Sanitation",
            "type":"Services"
        }
    ],
    "sg:phone":"+1 314 968 0987",
    "sg:postcode":"63119",
    "sg:province":"MO",
    "sg:tags":[
        "downspout",
        "gutter"
    ],
    "wof:name":"M & P Window Washing & Gutter",
    "wof:placetype":"venue"
},
  "geometry": {"coordinates":[-90.336049,38.602945],"type":"Point"}
}