{
  "type": "Feature",
  "properties": {
    "iso:country":"US",
    "sg:address":"613 N Main St",
    "sg:city":"Mt Vernon",
    "sg:classifiers":[
        {
            "category":"Organizations",
            "subcategory":"Religious Organization",
            "type":"Services"
        }
    ],
    "sg:phone":"+1 417 466 7844",
    "sg:postcode":"65712",
    "sg:province":"MO",
    "sg:tags":[
        "church"
    ],
    "wof:name":"Mo Baptist Childern",
    "wof:placetype":"venue"
},
  "geometry": {"coordinates":[-93.818556,37.106269],"type":"Point"}
}