{
  "type": "Feature",
  "properties": {
    "iso:country":"US",
    "sg:address":"10920 Schuetz Rd",
    "sg:city":"St Louis",
    "sg:classifiers":[
        {
            "category":"Real Estate",
            "subcategory":"Real Estate Agent",
            "type":"Services"
        }
    ],
    "sg:phone":"+1 314 432 4000",
    "sg:postcode":"63146",
    "sg:province":"MO",
    "sg:tags":[
        "management"
    ],
    "wof:name":"Deutsch Management Corp",
    "wof:placetype":"venue"
},
  "geometry": {"coordinates":[-90.407774,38.684335],"type":"Point"}
}