{
  "type": "Feature",
  "properties": {
    "iso:country":"US",
    "sg:address":"1321 Hwy K",
    "sg:city":"O Fallon",
    "sg:classifiers":[
        {
            "category":"Shopping",
            "subcategory":"Discount & Variety Stores",
            "type":"Retail Goods"
        }
    ],
    "sg:phone":"+1 636 980 1375",
    "sg:postcode":"63366",
    "sg:province":"MO",
    "sg:website":"www.dollartree.com",
    "wof:name":"Dollar Tree",
    "wof:placetype":"venue"
},
  "geometry": {"coordinates":[-90.698639,38.792414],"type":"Point"}
}