{
  "type": "Feature",
  "properties": {
    "iso:country":"US",
    "sg:address":"547 Branson Landing Blvd",
    "sg:city":"Branson",
    "sg:classifiers":[
        {
            "category":"Health Services",
            "subcategory":"Doctor",
            "type":"Services"
        }
    ],
    "sg:phone":"+1 417 334 1093",
    "sg:postcode":"65616",
    "sg:province":"MO",
    "sg:tags":[
        "physician",
        "surgeon",
        "surgeons",
        "surgery-general"
    ],
    "wof:name":"Wonder, Donald K Md Facs",
    "wof:placetype":"venue"
},
  "geometry": {"coordinates":[-93.213923,36.640979],"type":"Point"}
}