{
  "type": "Feature",
  "properties": {
    "iso:country":"US",
    "sg:address":"1815 S Kathleen Way",
    "sg:city":"Kearney",
    "sg:classifiers":[
        {
            "category":"Retail",
            "subcategory":"Laundry & Dry Cleaning",
            "type":"Services"
        }
    ],
    "sg:phone":"+1 816 628 5602",
    "sg:postcode":"64060",
    "sg:province":"MO",
    "sg:tags":[
        "cleaners",
        "rug",
        "carpet"
    ],
    "wof:name":"Pratt Carpet Cleaning",
    "wof:placetype":"venue"
},
  "geometry": {"coordinates":[-94.346513,39.353691],"type":"Point"}
}