{
  "type": "Feature",
  "properties": {
    "addr:full":"1615 E State Highway 76 Stej Branson MO 65616",
    "addr:housenumber":"1615",
    "addr:postcode":"65616",
    "addr:street":"E State Highway 76",
    "iso:country":"US",
    "sg:address":"1615 E State Highway 76 Stej",
    "sg:city":"Branson",
    "sg:classifiers":[
        {
            "category":"Fast Food",
            "type":"Food & Drink"
        },
        {
            "category":"Restaurant",
            "type":"Food & Drink"
        },
        {
            "category":"Food & Beverages",
            "subcategory":"Groceries & Convenience Stores",
            "type":"Retail Goods"
        }
    ],
    "sg:phone":"+1 417 334 7827",
    "sg:postcode":"65616",
    "sg:province":"MO",
    "sg:tags":[
        "shop",
        "american",
        "sandwich",
        "take"
    ],
    "sg:website":"http://www.subway.com",
    "wof:name":"Subway",
    "wof:placetype":"venue"
},
  "geometry": {"coordinates":[-93.28476000000001,36.638245],"type":"Point"}
}