{
  "type": "Feature",
  "properties": {
    "iso:country":"US",
    "sg:address":"4807 Oxford Dr",
    "sg:city":"Imperial",
    "sg:classifiers":[
        {
            "category":"Banks & Credit Unions",
            "subcategory":"Financial Services",
            "type":"Services"
        }
    ],
    "sg:phone":"+1 636 296 5508",
    "sg:postcode":"63052",
    "sg:province":"MO",
    "sg:tags":[
        "investor"
    ],
    "wof:name":"Northcutt Investment",
    "wof:placetype":"venue"
},
  "geometry": {"coordinates":[-90.406105,38.406449],"type":"Point"}
}