{
  "type": "Feature",
  "properties": {
    "iso:country":"US",
    "sg:address":"5102 Midday Dr",
    "sg:city":"Florissant",
    "sg:classifiers":[
        {
            "category":"Health Services",
            "subcategory":"Clinic",
            "type":"Services"
        }
    ],
    "sg:phone":"+1 314 837 0572",
    "sg:postcode":"63033",
    "sg:province":"MO",
    "sg:tags":[
        "home"
    ],
    "wof:name":"Divine Home Health Care",
    "wof:placetype":"venue"
},
  "geometry": {"coordinates":[-90.257907,38.795697],"type":"Point"}
}