{
  "type": "Feature",
  "properties": {
    "iso:country":"US",
    "sg:address":"3137 Locust St",
    "sg:city":"Saint Louis",
    "sg:classifiers":[
        {
            "category":"Wholesale",
            "subcategory":"Electrical",
            "type":"Manufacturing & Wholesale Goods"
        }
    ],
    "sg:phone":"+1 314 533 2800",
    "sg:postcode":"63103",
    "sg:province":"MO",
    "sg:tags":[
        "alarm",
        "burglar",
        "system",
        "key",
        "locksmith"
    ],
    "wof:name":"Baumann Safe & Alarm",
    "wof:placetype":"venue"
},
  "geometry": {"coordinates":[-90.22489899999999,38.636299],"type":"Point"}
}