{
  "type": "Feature",
  "properties": {
    "addr:full":"2937 S Grand Ave Carthage MO 64836",
    "addr:housenumber":"2937",
    "addr:postcode":"64836",
    "addr:street":"S Grand Ave",
    "iso:country":"US",
    "sg:address":"2937 S Grand Ave",
    "sg:city":"Carthage",
    "sg:classifiers":[
        {
            "category":"Restaurant",
            "type":"Food & Drink"
        }
    ],
    "sg:phone":"+1 417 358 4016",
    "sg:postcode":"64836",
    "sg:province":"MO",
    "wof:name":"El Charro",
    "wof:placetype":"venue"
},
  "geometry": {"coordinates":[-94.31107299999999,37.135689],"type":"Point"}
}