{
  "type": "Feature",
  "properties": {
    "iso:country":"US",
    "sg:address":"5690 N Farm Rd 151",
    "sg:city":"Springfield",
    "sg:classifiers":[
        {
            "category":"Organizations",
            "subcategory":"Religious Organization",
            "type":"Services"
        }
    ],
    "sg:phone":"+1 417 833 0709",
    "sg:postcode":"65803",
    "sg:province":"MO",
    "wof:name":"Gospel Tab",
    "wof:placetype":"venue"
},
  "geometry": {"coordinates":[-93.299764,37.299629],"type":"Point"}
}