{
  "type": "Feature",
  "properties": {
    "addr:full":"510 S Cavalier Ave Springfield MO 65802",
    "addr:housenumber":"510",
    "addr:postcode":"65802",
    "addr:street":"S Cavalier Ave",
    "iso:country":"US",
    "sg:address":"510 S Cavalier Ave",
    "sg:city":"Springfield",
    "sg:classifiers":[
        {
            "category":"Wholesale",
            "subcategory":"Stationery",
            "type":"Manufacturing & Wholesale Goods"
        }
    ],
    "sg:phone":"+1 417 869 0707",
    "sg:postcode":"65802",
    "sg:province":"MO",
    "sg:tags":[
        "product",
        "paper"
    ],
    "sg:website":"www.xpedx.com",
    "wof:name":"Xpedx",
    "wof:placetype":"venue"
},
  "geometry": {"coordinates":[-93.231342,37.203841],"type":"Point"}
}