{
  "type": "Feature",
  "properties": {
    "iso:country":"US",
    "sg:address":"3653 E Sunshine St",
    "sg:city":"Springfield",
    "sg:classifiers":[
        {
            "category":"Bars & Pubs",
            "type":"Food & Drink"
        },
        {
            "category":"Restaurant",
            "type":"Food & Drink"
        },
        {
            "category":"Bars & Pubs",
            "subcategory":"Lounge",
            "type":"Food & Drink"
        }
    ],
    "sg:phone":"+1 417 823 8882",
    "sg:postcode":"65809",
    "sg:province":"MO",
    "sg:tags":[
        "brew",
        "grill",
        "cocktail"
    ],
    "wof:name":"Parlor 88 Lounge",
    "wof:placetype":"venue"
},
  "geometry": {"coordinates":[-93.220451,37.180216],"type":"Point"}
}