{
  "type": "Feature",
  "properties": {
    "iso:country":"US",
    "sg:address":"829 Southwest Blvd",
    "sg:city":"Kansas City",
    "sg:classifiers":[
        {
            "category":"Banks & Credit Unions",
            "subcategory":"Bank",
            "type":"Services"
        }
    ],
    "sg:phone":"+1 816 842 4564",
    "sg:postcode":"64108",
    "sg:province":"MO",
    "sg:tags":[
        "depository",
        "banking"
    ],
    "wof:name":"Order Express",
    "wof:placetype":"venue"
},
  "geometry": {"coordinates":[-94.59383699999999,39.08472],"type":"Point"}
}