{
  "type": "Feature",
  "properties": {
    "addr:full":"2324 S Brentwood Blvd Saint Louis MO 63144",
    "addr:housenumber":"2324",
    "addr:postcode":"63144",
    "addr:street":"S Brentwood Blvd",
    "iso:country":"US",
    "sg:address":"2324 S Brentwood Blvd",
    "sg:city":"Saint Louis",
    "sg:classifiers":[
        {
            "category":"Insurance",
            "subcategory":"Insurance Agent",
            "type":"Services"
        }
    ],
    "sg:phone":"+1 314 968 0612",
    "sg:postcode":"63144",
    "sg:province":"MO",
    "wof:name":"Webb Insurance Agency",
    "wof:placetype":"venue"
},
  "geometry": {"coordinates":[-90.348415,38.619675],"type":"Point"}
}