{
  "type": "Feature",
  "properties": {
    "iso:country":"US",
    "sg:address":"23725 Red Oak Rd",
    "sg:city":"Waynesville",
    "sg:classifiers":[
        {
            "category":"Retail",
            "subcategory":"Animal Services",
            "type":"Services"
        }
    ],
    "sg:phone":"+1 573 774 2900",
    "sg:postcode":"65583",
    "sg:province":"MO",
    "wof:name":"Rocky Top Pet Kennel",
    "wof:placetype":"venue"
},
  "geometry": {"coordinates":[-92.273374,37.817599],"type":"Point"}
}