{
  "type": "Feature",
  "properties": {
    "iso:country":"US",
    "sg:address":"1114 E Darby Pl",
    "sg:city":"Springfield",
    "sg:classifiers":[
        {
            "category":"Professional",
            "subcategory":"Art Services",
            "type":"Services"
        }
    ],
    "sg:phone":"+1 417 886 2408",
    "sg:postcode":"65810",
    "sg:province":"MO",
    "sg:tags":[
        "interior",
        "designer",
        "decorator"
    ],
    "wof:name":"Piece Of Cake Decorating",
    "wof:placetype":"venue"
},
  "geometry": {"coordinates":[-93.28023899999999,37.118362],"type":"Point"}
}