{
  "type": "Feature",
  "properties": {
    "iso:country":"US",
    "sg:address":"243 Keystone Rd",
    "sg:city":"Branson",
    "sg:classifiers":[
        {
            "category":"Shopping",
            "type":"Retail Goods"
        }
    ],
    "sg:phone":"+1 417 294 4444",
    "sg:postcode":"65616",
    "sg:province":"MO",
    "sg:tags":[
        "merchandise"
    ],
    "wof:name":"The Travel More Store",
    "wof:placetype":"venue"
},
  "geometry": {"coordinates":[-93.248988,36.671481],"type":"Point"}
}