{
  "type": "Feature",
  "properties": {
    "iso:country":"US",
    "sg:address":"2855 Southwest Blvd",
    "sg:city":"Kansas City",
    "sg:classifiers":[
        {
            "category":"Wholesale",
            "subcategory":"Stationery",
            "type":"Manufacturing & Wholesale Goods"
        }
    ],
    "sg:phone":"+1 816 561 1200",
    "sg:postcode":"64108",
    "sg:province":"MO",
    "sg:tags":[
        "equipment",
        "supply"
    ],
    "wof:name":"Miller-Bevco",
    "wof:placetype":"venue"
},
  "geometry": {"coordinates":[-94.602757,39.075669],"type":"Point"}
}