{
  "type": "Feature",
  "properties": {
    "iso:country":"US",
    "sg:address":"2149 E Sunshine St",
    "sg:city":"Springfield",
    "sg:classifiers":[
        {
            "category":"Real Estate",
            "subcategory":"Real Estate Operator",
            "type":"Services"
        }
    ],
    "sg:phone":"+1 417 881 1612",
    "sg:postcode":"65804",
    "sg:province":"MO",
    "sg:tags":[
        "building",
        "apartment"
    ],
    "wof:name":"Columns Four Apartments",
    "wof:placetype":"venue"
},
  "geometry": {"coordinates":[-93.25422500000001,37.181361],"type":"Point"}
}