{
  "type": "Feature",
  "properties": {
    "iso:country":"US",
    "sg:address":"150 N Meramec Ave",
    "sg:city":"Saint Louis",
    "sg:classifiers":[
        {
            "category":"Professional",
            "subcategory":"Computer Services",
            "type":"Services"
        }
    ],
    "sg:phone":"+1 314 727 4448",
    "sg:postcode":"63105",
    "sg:province":"MO",
    "sg:tags":[
        "programing",
        "custom"
    ],
    "wof:name":"Demand Solutions",
    "wof:placetype":"venue"
},
  "geometry": {"coordinates":[-90.33931,38.65207],"type":"Point"}
}