{
  "type": "Feature",
  "properties": {
    "iso:country":"US",
    "sg:address":"3246 US Hwy 67",
    "sg:city":"Florissant",
    "sg:classifiers":[
        {
            "category":"Banks & Credit Unions",
            "subcategory":"Bank",
            "type":"Services"
        }
    ],
    "sg:phone":"+1 314 837 5001",
    "sg:postcode":"63033",
    "sg:province":"MO",
    "sg:tags":[
        "loan"
    ],
    "wof:name":"Sunbelt Credit Corp-Missouri",
    "wof:placetype":"venue"
},
  "geometry": {"coordinates":[-90.295608,38.810759],"type":"Point"}
}