{
  "type": "Feature",
  "properties": {
    "iso:country":"US",
    "sg:address":"1835 Colhoun St",
    "sg:city":"Saint Joseph",
    "sg:classifiers":[
        {
            "category":"Autos & Motor Vehicles",
            "subcategory":"Auto Supplies",
            "type":"Retail Goods"
        }
    ],
    "sg:phone":"+1 816 232 4465",
    "sg:postcode":"64501",
    "sg:province":"MO",
    "wof:name":"Firestone",
    "wof:placetype":"venue"
},
  "geometry": {"coordinates":[-94.837908,39.773961],"type":"Point"}
}