{
  "type": "Feature",
  "properties": {
    "iso:country":"US",
    "sg:address":"2771 Chouteau Ave",
    "sg:city":"St Louis",
    "sg:classifiers":[
        {
            "category":"Wholesale",
            "subcategory":"Auto Parts",
            "type":"Manufacturing & Wholesale Goods"
        }
    ],
    "sg:phone":"+1 314 772 6900",
    "sg:postcode":"63105",
    "sg:province":"MO",
    "sg:tags":[
        "automobile",
        "supply"
    ],
    "wof:name":"Middle Atlantic Warehouse",
    "wof:placetype":"venue"
},
  "geometry": {"coordinates":[-90.222542,38.623116],"type":"Point"}
}