{
  "type": "Feature",
  "properties": {
    "iso:country":"US",
    "sg:address":"3107 Cook Rd",
    "sg:city":"St Joseph",
    "sg:classifiers":[
        {
            "category":"Social Services",
            "subcategory":"Child Care",
            "type":"Services"
        }
    ],
    "sg:phone":"+1 816 364 5685",
    "sg:postcode":"64506",
    "sg:province":"MO",
    "sg:website":"www.kindercare.com",
    "wof:name":"Kinder Care Learning Ctr",
    "wof:placetype":"venue"
},
  "geometry": {"coordinates":[-94.818623,39.806685],"type":"Point"}
}