{
  "type": "Feature",
  "properties": {
    "iso:country":"US",
    "sg:address":"2045 Old Leasburg Rd",
    "sg:city":"Leasburg",
    "sg:classifiers":[
        {
            "category":"Place Of Worship",
            "subcategory":"Church",
            "type":"Public Place"
        },
        {
            "category":"Place Of Worship",
            "type":"Public Place"
        }
    ],
    "sg:phone":"+1 573 245 6551",
    "sg:postcode":"65535",
    "sg:province":"MO",
    "sg:tags":[
        "churches-interdenominational",
        "churches-various",
        "denomination"
    ],
    "wof:name":"Int'l Health And Lifestyle Ministry",
    "wof:placetype":"venue"
},
  "geometry": {"coordinates":[-91.258018,38.085438],"type":"Point"}
}