{
  "type": "Feature",
  "properties": {
    "iso:country":"US",
    "sg:address":"15200 S Highway 39",
    "sg:city":"Stockton",
    "sg:classifiers":[
        {
            "category":"Personal",
            "subcategory":"Beauty Salon",
            "type":"Services"
        }
    ],
    "sg:phone":"+1 417 276 4900",
    "sg:postcode":"65785",
    "sg:province":"MO",
    "wof:name":"Divine Images",
    "wof:placetype":"venue"
},
  "geometry": {"coordinates":[-93.808089,37.676531],"type":"Point"}
}