{
  "type": "Feature",
  "properties": {
    "iso:country":"US",
    "sg:address":"7245 N Oak Fwy",
    "sg:city":"Kansas City",
    "sg:classifiers":[
        {
            "category":"Banks & Credit Unions",
            "subcategory":"Bank",
            "type":"Services"
        }
    ],
    "sg:phone":"+1 816 436 4384",
    "sg:postcode":"64118",
    "sg:province":"MO",
    "wof:name":"Kansas City Credit Union",
    "wof:placetype":"venue"
},
  "geometry": {"coordinates":[-94.576024,39.225874],"type":"Point"}
}