{
  "type": "Feature",
  "properties": {
    "iso:country":"US",
    "sg:address":"829 Fall Crown Ln",
    "sg:city":"Fenton",
    "sg:classifiers":[
        {
            "category":"Health Services",
            "subcategory":"Doctor",
            "type":"Services"
        }
    ],
    "sg:phone":"+1 636 349 7818",
    "sg:postcode":"63026",
    "sg:province":"MO",
    "sg:tags":[
        "osteopathic"
    ],
    "wof:name":"Honey Do Custom PTG",
    "wof:placetype":"venue"
},
  "geometry": {"coordinates":[-90.45714,38.50758],"type":"Point"}
}