{
  "type": "Feature",
  "properties": {
    "iso:country":"US",
    "sg:address":"2600 Forum Blvd",
    "sg:city":"Columbia",
    "sg:classifiers":[
        {
            "category":"Banks & Credit Unions",
            "subcategory":"Investment Brokerage",
            "type":"Services"
        }
    ],
    "sg:phone":"+1 573 446 5947",
    "sg:postcode":"65203",
    "sg:province":"MO",
    "wof:name":"Prima Investments Inc",
    "wof:placetype":"venue"
},
  "geometry": {"coordinates":[-92.365364,38.922703],"type":"Point"}
}