{
  "type": "Feature",
  "properties": {
    "iso:country":"US",
    "sg:address":"1595 Denmark Rd",
    "sg:city":"Union",
    "sg:classifiers":[
        {
            "category":"Real Estate",
            "subcategory":"Real Estate Services",
            "type":"Services"
        }
    ],
    "sg:phone":"+1 636 584 7510",
    "sg:postcode":"63084",
    "sg:province":"MO",
    "sg:tags":[
        "company",
        "title"
    ],
    "wof:name":"Us Title",
    "wof:placetype":"venue"
},
  "geometry": {"coordinates":[-90.960841,38.431321],"type":"Point"}
}