{
  "type": "Feature",
  "properties": {
    "iso:country":"US",
    "sg:address":"200 E 14th Ave",
    "sg:city":"N Kansas City",
    "sg:classifiers":[
        {
            "category":"Wholesale",
            "subcategory":"Stationery",
            "type":"Manufacturing & Wholesale Goods"
        }
    ],
    "sg:phone":"+1 816 254 2424",
    "sg:postcode":"64116",
    "sg:province":"MO",
    "sg:tags":[
        "box",
        "fiber"
    ],
    "wof:name":"Imaging Solutions & Packaging",
    "wof:placetype":"venue"
},
  "geometry": {"coordinates":[-94.578379,39.134178],"type":"Point"}
}