{
  "type": "Feature",
  "properties": {
    "iso:country":"US",
    "sg:address":"4237 Bayless Ave",
    "sg:city":"Saint Louis",
    "sg:classifiers":[
        {
            "category":"Restaurant",
            "type":"Food & Drink"
        }
    ],
    "sg:phone":"+1 314 544 6161",
    "sg:postcode":"63123",
    "sg:province":"MO",
    "sg:tags":[
        "eating"
    ],
    "wof:name":"Saint Louis Pizza & Wing Co",
    "wof:placetype":"venue"
},
  "geometry": {"coordinates":[-90.292446,38.548393],"type":"Point"}
}