{
  "type": "Feature",
  "properties": {
    "iso:country":"US",
    "sg:address":"11 S Division St",
    "sg:city":"Bonne Terre",
    "sg:classifiers":[
        {
            "category":"Banks & Credit Unions",
            "subcategory":"Investment Brokerage",
            "type":"Services"
        }
    ],
    "sg:phone":"+1 573 358 0195",
    "sg:postcode":"63628",
    "sg:province":"MO",
    "sg:tags":[
        "security"
    ],
    "wof:name":"Edward Jones 17230",
    "wof:placetype":"venue"
},
  "geometry": {"coordinates":[-90.55555099999999,37.922419],"type":"Point"}
}