{
  "type": "Feature",
  "properties": {
    "iso:country":"US",
    "sg:address":"12016 Grand Ave",
    "sg:city":"Kansas City",
    "sg:classifiers":[
        {
            "category":"Autos & Motor Vehicles",
            "subcategory":"Automobile Sales",
            "type":"Retail Goods"
        }
    ],
    "sg:phone":"+1 816 421 1776",
    "sg:postcode":"64145",
    "sg:province":"MO",
    "sg:tags":[
        "truck"
    ],
    "wof:name":"Interstate Truck & Trailer Inc",
    "wof:placetype":"venue"
},
  "geometry": {"coordinates":[-94.59106300000001,38.907895],"type":"Point"}
}