{
  "type": "Feature",
  "properties": {
    "iso:country":"US",
    "sg:address":"400 Jefferson",
    "sg:city":"Waverly",
    "sg:classifiers":[
        {
            "category":"Building & Trades",
            "subcategory":"Plumbing",
            "type":"Services"
        }
    ],
    "sg:phone":"+1 660 493 2300",
    "sg:postcode":"64096",
    "sg:province":"MO",
    "sg:tags":[
        "conditioning",
        "air",
        "system",
        "contractor"
    ],
    "wof:name":"Economy Heating & Air",
    "wof:placetype":"venue"
},
  "geometry": {"coordinates":[-93.520038,39.208529],"type":"Point"}
}