{
  "type": "Feature",
  "properties": {
    "iso:country":"US",
    "sg:address":"3 N Oaks Plz",
    "sg:city":"Saint Louis",
    "sg:classifiers":[
        {
            "category":"Building & Trades",
            "subcategory":"Locksmith",
            "type":"Services"
        }
    ],
    "sg:phone":"+1 314 385 2022",
    "sg:postcode":"63121",
    "sg:province":"MO",
    "sg:tags":[
        "key"
    ],
    "wof:name":"Modern Key & Lock Service",
    "wof:placetype":"venue"
},
  "geometry": {"coordinates":[-90.290199,38.701],"type":"Point"}
}