{
  "type": "Feature",
  "properties": {
    "iso:country":"US",
    "sg:address":"717 Jay Blvd",
    "sg:city":"Henrietta",
    "sg:classifiers":[
        {
            "category":"Freight",
            "type":"Transportation"
        }
    ],
    "sg:phone":"+1 816 494 5439",
    "sg:postcode":"64036",
    "sg:province":"MO",
    "sg:tags":[
        "commercial",
        "storage"
    ],
    "wof:name":"Ample Storage",
    "wof:placetype":"venue"
},
  "geometry": {"coordinates":[-93.942847,39.237919],"type":"Point"}
}