{
  "type": "Feature",
  "properties": {
    "iso:country":"US",
    "sg:address":"8536 N Ambassador Dr",
    "sg:city":"Kansas City",
    "sg:classifiers":[
        {
            "category":"Shopping",
            "type":"Retail Goods"
        }
    ],
    "sg:phone":"+1 816 382 3000",
    "sg:postcode":"64154",
    "sg:province":"MO",
    "sg:tags":[
        "merchandise"
    ],
    "wof:name":"Lowcarb Superstore",
    "wof:placetype":"venue"
},
  "geometry": {"coordinates":[-94.649843,39.248923],"type":"Point"}
}