{
  "type": "Feature",
  "properties": {
    "iso:country":"US",
    "sg:address":"40 S County Centerway",
    "sg:city":"Saint Louis",
    "sg:classifiers":[
        {
            "category":"Shopping",
            "subcategory":"Clothing, Apparel, & Fashions",
            "type":"Retail Goods"
        }
    ],
    "sg:phone":"+1 314 966 4112",
    "sg:postcode":"63129",
    "sg:province":"MO",
    "wof:name":"Wet Seal Inc",
    "wof:placetype":"venue"
},
  "geometry": {"coordinates":[-90.329494,38.505114],"type":"Point"}
}