{
  "type": "Feature",
  "properties": {
    "iso:country":"US",
    "sg:address":"605 Meadowlark Ln",
    "sg:city":"Tipton",
    "sg:classifiers":[
        {
            "category":"Retail",
            "subcategory":"Auto Repair",
            "type":"Services"
        }
    ],
    "sg:phone":"+1 660 433 5795",
    "sg:postcode":"65081",
    "sg:province":"MO",
    "sg:tags":[
        "body",
        "automobile",
        "painting"
    ],
    "wof:name":"Burlingame Paint & Auto Shop",
    "wof:placetype":"venue"
},
  "geometry": {"coordinates":[-92.794212,38.655298],"type":"Point"}
}