{
  "type": "Feature",
  "properties": {
    "iso:country":"US",
    "sg:address":"122 N Main St",
    "sg:city":"Maryville",
    "sg:classifiers":[
        {
            "category":"Home & Garden",
            "subcategory":"Furniture",
            "type":"Retail Goods"
        }
    ],
    "sg:phone":"+1 660 562 3558",
    "sg:postcode":"64468",
    "sg:province":"MO",
    "wof:name":"Priced Right Furn & Flooring",
    "wof:placetype":"venue"
},
  "geometry": {"coordinates":[-94.87303799999999,40.346279],"type":"Point"}
}