{
  "type": "Feature",
  "properties": {
    "iso:country":"US",
    "sg:address":"9313 Manchester Rd",
    "sg:city":"Saint Louis",
    "sg:classifiers":[
        {
            "category":"Recreation",
            "type":"Entertainment"
        }
    ],
    "sg:phone":"+1 314 993 6482",
    "sg:postcode":"63119",
    "sg:province":"MO",
    "sg:tags":[
        "club",
        "bridge",
        "membership"
    ],
    "wof:name":"Dorchester Bridge Club",
    "wof:placetype":"venue"
},
  "geometry": {"coordinates":[-90.36037,38.610759],"type":"Point"}
}