{
  "type": "Feature",
  "properties": {
    "iso:country":"US",
    "sg:address":"12036 Blue Ridge Ext",
    "sg:city":"Grandview",
    "sg:classifiers":[
        {
            "category":"Personal",
            "type":"Services"
        },
        {
            "category":"Sports & Exercise",
            "subcategory":"Gym",
            "type":"Entertainment"
        },
        {
            "category":"Health Services",
            "subcategory":"Health Practitioner",
            "type":"Services"
        },
        {
            "category":"Arena",
            "subcategory":"Sports Club",
            "type":"Entertainment"
        }
    ],
    "sg:phone":"+1 800 615 7352",
    "sg:postcode":"64030",
    "sg:province":"MO",
    "sg:tags":[
        "control",
        "trainer",
        "weight",
        "consultant",
        "program",
        "fitness",
        "physical"
    ],
    "sg:website":"http://kansascity.citysearch.com/profile/external/36355717/grandview_mo/curves.html?publisher=yellowpages&reference_id=1&placement=ypwebsitemip",
    "wof:name":"Curves",
    "wof:placetype":"venue"
},
  "geometry": {"coordinates":[-94.52722900000001,38.905801],"type":"Point"}
}