{
  "type": "Feature",
  "properties": {
    "iso:country":"US",
    "sg:address":"1001 W Main St",
    "sg:city":"Richmond",
    "sg:classifiers":[
        {
            "category":"Restaurant",
            "type":"Food & Drink"
        }
    ],
    "sg:phone":"+1 816 776 3333",
    "sg:postcode":"64085",
    "sg:province":"MO",
    "sg:tags":[
        "eating"
    ],
    "wof:name":"Joyce's Family Restaurant",
    "wof:placetype":"venue"
},
  "geometry": {"coordinates":[-93.990303,39.278646],"type":"Point"}
}