{
  "type": "Feature",
  "properties": {
    "iso:country":"US",
    "sg:address":"1417 N National Ave",
    "sg:city":"Springfield",
    "sg:classifiers":[
        {
            "category":"Manufacturing",
            "subcategory":"Printing",
            "type":"Manufacturing & Wholesale Goods"
        }
    ],
    "sg:phone":"+1 417 887 1960",
    "sg:postcode":"65802",
    "sg:province":"MO",
    "sg:tags":[
        "commercial",
        "lithographic"
    ],
    "wof:name":"J-Mack Printing",
    "wof:placetype":"venue"
},
  "geometry": {"coordinates":[-93.275322,37.225504],"type":"Point"}
}