{
  "type": "Feature",
  "properties": {
    "iso:country":"US",
    "sg:address":"2920 S Range Line Rd",
    "sg:city":"Joplin",
    "sg:classifiers":[
        {
            "category":"Insurance",
            "subcategory":"Insurance Agent",
            "type":"Services"
        }
    ],
    "sg:phone":"+1 417 623 3076",
    "sg:postcode":"64804",
    "sg:province":"MO",
    "wof:name":"Meditech",
    "wof:placetype":"venue"
},
  "geometry": {"coordinates":[-94.478335,37.057799],"type":"Point"}
}