{
  "type": "Feature",
  "properties": {
    "iso:country":"US",
    "sg:address":"317 Auglaize Ave",
    "sg:city":"Tipton",
    "sg:classifiers":[
        {
            "category":"Professional",
            "subcategory":"Research",
            "type":"Services"
        }
    ],
    "sg:phone":"+1 660 433 2895",
    "sg:postcode":"65081",
    "sg:province":"MO",
    "sg:tags":[
        "nonphysical",
        "commercial"
    ],
    "wof:name":"Comstock Research Co",
    "wof:placetype":"venue"
},
  "geometry": {"coordinates":[-92.77422300000001,38.660581],"type":"Point"}
}