{
  "type": "Feature",
  "properties": {
    "iso:country":"US",
    "sg:address":"1924 Indiana Ave",
    "sg:city":"Kansas City",
    "sg:classifiers":[
        {
            "category":"Professional",
            "subcategory":"Business Services",
            "type":"Services"
        },
        {
            "category":"Professional",
            "subcategory":"Management & Consulting",
            "type":"Services"
        }
    ],
    "sg:phone":"+1 816 241 4889",
    "sg:postcode":"64127",
    "sg:province":"MO",
    "sg:tags":[
        "event"
    ],
    "wof:name":"Total Experience Event Plannin",
    "wof:placetype":"venue"
},
  "geometry": {"coordinates":[-94.54271300000001,39.087914],"type":"Point"}
}