{
  "type": "Feature",
  "properties": {
    "iso:country":"US",
    "sg:address":"1905 W 32nd St",
    "sg:city":"Joplin",
    "sg:classifiers":[
        {
            "category":"Health Services",
            "subcategory":"Nursing And Care Facility",
            "type":"Services"
        }
    ],
    "sg:phone":"+1 417 625 2325",
    "sg:postcode":"64804",
    "sg:province":"MO",
    "sg:tags":[
        "hospice"
    ],
    "wof:name":"Hospice At St John's",
    "wof:placetype":"venue"
},
  "geometry": {"coordinates":[-94.536951,37.0554],"type":"Point"}
}