{
  "type": "Feature",
  "properties": {
    "iso:country":"US",
    "sg:address":"8225 Bellair Rd",
    "sg:city":"Pilot Grove",
    "sg:phone":"+1 660 834 3935",
    "sg:postcode":"65276",
    "sg:province":"MO",
    "sg:tags":[
        "farm",
        "corn"
    ],
    "wof:name":"Bernard Martin",
    "wof:placetype":"venue"
},
  "geometry": {"coordinates":[-92.90683799999999,38.868739],"type":"Point"}
}