{
  "type": "Feature",
  "properties": {
    "iso:country":"US",
    "sg:address":"14 Misty Lou Ct",
    "sg:city":"Fenton",
    "sg:classifiers":[
        {
            "category":"Shopping",
            "subcategory":"Clothing, Apparel, & Fashions",
            "type":"Retail Goods"
        }
    ],
    "sg:phone":"+1 636 305 2756",
    "sg:postcode":"63026",
    "sg:province":"MO",
    "sg:tags":[
        "tailor",
        "custom"
    ],
    "wof:name":"Demetres Custom Tailors",
    "wof:placetype":"venue"
},
  "geometry": {"coordinates":[-90.475596,38.507565],"type":"Point"}
}