{
  "type": "Feature",
  "properties": {
    "iso:country":"US",
    "sg:address":"852 Riske Ln",
    "sg:city":"Wentzville",
    "sg:classifiers":[
        {
            "category":"Farming",
            "subcategory":"Livestock Farm",
            "type":"Manufacturing & Wholesale Goods"
        }
    ],
    "sg:phone":"+1 636 262 0600",
    "sg:postcode":"63385",
    "sg:province":"MO",
    "sg:tags":[
        "horse"
    ],
    "wof:name":"Steelhorsetech",
    "wof:placetype":"venue"
},
  "geometry": {"coordinates":[-90.84798,38.739981],"type":"Point"}
}