{
  "type": "Feature",
  "properties": {
    "iso:country":"US",
    "sg:address":"8240 W State Hwy 266",
    "sg:city":"Springfield",
    "sg:classifiers":[
        {
            "category":"Home & Garden",
            "subcategory":"Furniture",
            "type":"Retail Goods"
        }
    ],
    "sg:phone":"+1 417 865 6658",
    "sg:postcode":"65802",
    "sg:province":"MO",
    "wof:name":"Barnes Town & Country Furn",
    "wof:placetype":"venue"
},
  "geometry": {"coordinates":[-93.457793,37.21348],"type":"Point"}
}