{
  "type": "Feature",
  "properties": {
    "iso:country":"US",
    "sg:address":"1627 Main St",
    "sg:city":"Kansas City",
    "sg:classifiers":[
        {
            "category":"Real Estate",
            "subcategory":"Architect",
            "type":"Services"
        }
    ],
    "sg:phone":"+1 816 421 1300",
    "sg:postcode":"64108",
    "sg:province":"KS",
    "wof:name":"George Butler Assoc Inc",
    "wof:placetype":"venue"
},
  "geometry": {"coordinates":[-94.583429,39.093729],"type":"Point"}
}