{
  "type": "Feature",
  "properties": {
    "iso:country":"US",
    "sg:address":"716 Crown Industrial Ct Ste J",
    "sg:city":"Chesterfield",
    "sg:classifiers":[
        {
            "category":"Wholesale",
            "subcategory":"Medical Equipment & Supplies",
            "type":"Manufacturing & Wholesale Goods"
        }
    ],
    "sg:phone":"+1 636 530 1664",
    "sg:postcode":"63005",
    "sg:province":"MO",
    "sg:tags":[
        "assistive",
        "aid",
        "device",
        "hearing"
    ],
    "sg:website":"http://www.oaktreeproducts.com",
    "wof:name":"Oaktree Products, Inc.",
    "wof:placetype":"venue"
},
  "geometry": {"coordinates":[-90.63954200000001,38.669267],"type":"Point"}
}