{
  "type": "Feature",
  "properties": {
    "iso:country":"US",
    "sg:address":"16403 NE 184th St",
    "sg:city":"Holt",
    "sg:classifiers":[
        {
            "category":"Retail",
            "subcategory":"Laundry & Dry Cleaning",
            "type":"Services"
        }
    ],
    "sg:phone":"+1 816 264 3282",
    "sg:postcode":"64048",
    "sg:province":"MO",
    "sg:tags":[
        "cleaners",
        "rug",
        "carpet"
    ],
    "wof:name":"Howdeshell Carpet Steam Clng",
    "wof:placetype":"venue"
},
  "geometry": {"coordinates":[-94.379834,39.426678],"type":"Point"}
}