{
  "type": "Feature",
  "properties": {
    "iso:country":"US",
    "sg:address":"596 Fieldstone Ln",
    "sg:city":"Ballwin",
    "sg:classifiers":[
        {
            "category":"Shopping",
            "subcategory":"Beauty & Cosmetics",
            "type":"Retail Goods"
        }
    ],
    "sg:phone":"+1 636 230 3090",
    "sg:postcode":"63011",
    "sg:province":"MO",
    "sg:tags":[
        "perfume",
        "salons-equipment",
        "supply"
    ],
    "wof:name":"Jaimerson Eugene",
    "wof:placetype":"venue"
},
  "geometry": {"coordinates":[-90.532904,38.619497],"type":"Point"}
}