{
  "type": "Feature",
  "properties": {
    "iso:country":"US",
    "sg:address":"171 Gravois Bluffs Plaza Dr",
    "sg:city":"Fenton",
    "sg:classifiers":[
        {
            "category":"Shopping",
            "subcategory":"Party Supplies",
            "type":"Retail Goods"
        },
        {
            "category":"Personal",
            "type":"Services"
        }
    ],
    "sg:phone":"+1 636 717 1155",
    "sg:postcode":"63026",
    "sg:province":"MO",
    "sg:tags":[
        "favors",
        "decoration",
        "planning",
        "wedding",
        "rental",
        "event"
    ],
    "sg:website":"http://www.partyamerica.com",
    "wof:name":"Party Universe",
    "wof:placetype":"venue"
},
  "geometry": {"coordinates":[-90.446925,38.502036],"type":"Point"}
}