{
  "type": "Feature",
  "properties": {
    "iso:country":"US",
    "sg:address":"6309 Delmar Blvd",
    "sg:city":"Saint Louis",
    "sg:classifiers":[
        {
            "category":"Personal",
            "type":"Services"
        },
        {
            "category":"Personal",
            "subcategory":"Tattoo Parlor",
            "type":"Services"
        }
    ],
    "sg:phone":"+1 314 725 1499",
    "sg:postcode":"63130",
    "sg:province":"MO",
    "sg:tags":[
        "tattooing",
        "piercing"
    ],
    "sg:website":"www.ironagestudio.com/",
    "wof:name":"Iron Age Studios",
    "wof:placetype":"venue"
},
  "geometry": {"coordinates":[-90.303006,38.6558],"type":"Point"}
}