{
  "type": "Feature",
  "properties": {
    "iso:country":"US",
    "sg:address":"600 NE 46 St",
    "sg:city":"Kansas City",
    "sg:classifiers":[
        {
            "category":"Social Services",
            "subcategory":"Child Care",
            "type":"Services"
        }
    ],
    "sg:phone":"+1 816 453 2248",
    "sg:postcode":"64116",
    "sg:province":"MO",
    "sg:website":"www.iccdaycare.org",
    "wof:name":"In The Co Of Children",
    "wof:placetype":"venue"
},
  "geometry": {"coordinates":[-94.574226,39.177576],"type":"Point"}
}