{
  "type": "Feature",
  "properties": {
    "iso:country":"US",
    "sg:address":"1502 S Main St",
    "sg:city":"Joplin",
    "sg:classifiers":[
        {
            "category":"Shopping",
            "subcategory":"Computers & Home Electronics",
            "type":"Retail Goods"
        }
    ],
    "sg:phone":"+1 417 781 3341",
    "sg:postcode":"64804",
    "sg:province":"MO",
    "sg:tags":[
        "equipment",
        "electronic",
        "supply"
    ],
    "wof:name":"Four State TV",
    "wof:placetype":"venue"
},
  "geometry": {"coordinates":[-94.514008,37.074082],"type":"Point"}
}