{
  "type": "Feature",
  "properties": {
    "iso:country":"US",
    "sg:address":"101 State Dr Ste 200",
    "sg:city":"Hollister",
    "sg:classifiers":[
        {
            "category":"Professional",
            "subcategory":"Lawyer & Legal Services",
            "type":"Services"
        }
    ],
    "sg:phone":"+1 417 335 8683",
    "sg:postcode":"65672",
    "sg:province":"MO",
    "sg:tags":[
        "attorney",
        "practice"
    ],
    "wof:name":"Akers, David S",
    "wof:placetype":"venue"
},
  "geometry": {"coordinates":[-93.242844,36.600101],"type":"Point"}
}