{
  "type": "Feature",
  "properties": {
    "iso:country":"US",
    "sg:address":"111 N Range Line Rd",
    "sg:city":"Joplin",
    "sg:classifiers":[
        {
            "category":"Utilities",
            "subcategory":"Mobile Phone",
            "type":"Services"
        }
    ],
    "sg:phone":"+1 417 626 0366",
    "sg:postcode":"64801",
    "sg:province":"MO",
    "sg:tags":[
        "telephone",
        "cellular"
    ],
    "wof:name":"Verizon Wireless",
    "wof:placetype":"venue"
},
  "geometry": {"coordinates":[-94.476804,37.09353],"type":"Point"}
}