{
  "type": "Feature",
  "properties": {
    "iso:country":"US",
    "sg:address":"14604 Kayak Rd",
    "sg:city":"Mound City",
    "sg:phone":"+1 660 442 3294",
    "sg:postcode":"64470",
    "sg:province":"MO",
    "sg:tags":[
        "farm",
        "grain",
        "cash"
    ],
    "wof:name":"Lewis Smith",
    "wof:placetype":"venue"
},
  "geometry": {"coordinates":[-95.229535,40.197563],"type":"Point"}
}