{
  "type": "Feature",
  "properties": {
    "iso:country":"US",
    "sg:address":"6040 N Lindbergh Blvd",
    "sg:city":"Hazelwood",
    "sg:classifiers":[
        {
            "category":"Manufacturing",
            "subcategory":"Food",
            "type":"Manufacturing & Wholesale Goods"
        },
        {
            "category":"Farming",
            "subcategory":"Dairy Farm",
            "type":"Manufacturing & Wholesale Goods"
        },
        {
            "category":"Farming",
            "subcategory":"Farm",
            "type":"Manufacturing & Wholesale Goods"
        },
        {
            "category":"Ice Cream",
            "type":"Food & Drink"
        },
        {
            "category":"Food & Beverages",
            "subcategory":"Dairy",
            "type":"Retail Goods"
        }
    ],
    "sg:phone":"+1 314 731 1150",
    "sg:postcode":"63042",
    "sg:province":"MO",
    "sg:tags":[
        "frozen",
        "dessert",
        "product",
        "desserts-manufacturers",
        "distributor"
    ],
    "wof:name":"Prairie Farms Dairy",
    "wof:placetype":"venue"
},
  "geometry": {"coordinates":[-90.366226,38.769131],"type":"Point"}
}