{
  "type": "Feature",
  "properties": {
    "iso:country":"US",
    "sg:address":"2669 Market St",
    "sg:city":"Hannibal",
    "sg:classifiers":[
        {
            "category":"Manufacturing",
            "subcategory":"Glass & Minerals",
            "type":"Manufacturing & Wholesale Goods"
        }
    ],
    "sg:phone":"+1 573 221 0094",
    "sg:postcode":"63401",
    "sg:province":"MO",
    "sg:tags":[
        "ready"
    ],
    "wof:name":"Mark Twain Redi Mix Inc",
    "wof:placetype":"venue"
},
  "geometry": {"coordinates":[-91.38515,39.691938],"type":"Point"}
}