{
  "type": "Feature",
  "properties": {
    "iso:country":"US",
    "sg:address":"1610 State Hwy 7",
    "sg:city":"Blue Springs",
    "sg:classifiers":[
        {
            "category":"Insurance",
            "subcategory":"Insurance Agent",
            "type":"Services"
        }
    ],
    "sg:phone":"+1 816 224 6116",
    "sg:postcode":"64014",
    "sg:province":"MO",
    "wof:name":"Direct General Ins Agency",
    "wof:placetype":"venue"
},
  "geometry": {"coordinates":[-94.27310900000001,38.999327],"type":"Point"}
}