{
  "type": "Feature",
  "properties": {
    "iso:country":"US",
    "sg:address":"4100 Gravois Ave",
    "sg:city":"Saint Louis",
    "sg:classifiers":[
        {
            "category":"Retail",
            "subcategory":"Auto Rental",
            "type":"Services"
        }
    ],
    "sg:phone":"+1 314 664 2502",
    "sg:postcode":"63116",
    "sg:province":"MO",
    "sg:tags":[
        "car"
    ],
    "sg:website":"enterprise.com.",
    "wof:name":"Enterprise Rent-A-Car",
    "wof:placetype":"venue"
},
  "geometry": {"coordinates":[-90.255589,38.589425],"type":"Point"}
}