{
  "type": "Feature",
  "properties": {
    "iso:country":"US",
    "sg:address":"3651 Forest Park Ave",
    "sg:city":"Saint Louis",
    "sg:classifiers":[
        {
            "category":"Banks & Credit Unions",
            "subcategory":"Bank",
            "type":"Services"
        }
    ],
    "sg:phone":"+1 314 534 7610",
    "sg:postcode":"63108",
    "sg:province":"MO",
    "wof:name":"St Louis Community Credit Union",
    "wof:placetype":"venue"
},
  "geometry": {"coordinates":[-90.236524,38.634644],"type":"Point"}
}