{
  "type": "Feature",
  "properties": {
    "iso:country":"US",
    "sg:address":"108 Whisper Creek Dr",
    "sg:city":"Wentzville",
    "sg:classifiers":[
        {
            "category":"Real Estate",
            "subcategory":"Developer",
            "type":"Services"
        }
    ],
    "sg:phone":"+1 636 332 1733",
    "sg:postcode":"63385",
    "sg:province":"MO",
    "wof:name":"Owen & Sons Development",
    "wof:placetype":"venue"
},
  "geometry": {"coordinates":[-90.85688500000001,38.778783],"type":"Point"}
}