{
  "type": "Feature",
  "properties": {
    "iso:country":"US",
    "sg:address":"702 W Boone St",
    "sg:city":"Ash Grove",
    "sg:classifiers":[
        {
            "category":"Food & Beverages",
            "subcategory":"Groceries & Convenience Stores",
            "type":"Retail Goods"
        }
    ],
    "sg:phone":"+1 417 751 9557",
    "sg:postcode":"65604",
    "sg:province":"MO",
    "wof:name":"Reflections Flea Market",
    "wof:placetype":"venue"
},
  "geometry": {"coordinates":[-93.595185,37.322966],"type":"Point"}
}