{
  "type": "Feature",
  "properties": {
    "iso:country":"US",
    "sg:address":"9415 Branch Rd",
    "sg:city":"Lohman",
    "sg:classifiers":[
        {
            "category":"Retail",
            "subcategory":"Laundry & Dry Cleaning",
            "type":"Services"
        }
    ],
    "sg:phone":"+1 573 782 3524",
    "sg:postcode":"65053",
    "sg:province":"MO",
    "wof:name":"Four Seasons Crpt Uphl Cleanin",
    "wof:placetype":"venue"
},
  "geometry": {"coordinates":[-92.37597599999999,38.537676],"type":"Point"}
}