{
  "type": "Feature",
  "properties": {
    "addr:full":"4329 N Chouteau Trfy Kansas City MO 64117",
    "addr:housenumber":"4329",
    "addr:postcode":"64117",
    "addr:street":"N Chouteau Trfy",
    "iso:country":"US",
    "sg:address":"4329 N Chouteau Trfy",
    "sg:city":"Kansas City",
    "sg:classifiers":[
        {
            "category":"Professional",
            "subcategory":"Accounting & Tax Preparation",
            "type":"Services"
        }
    ],
    "sg:phone":"+1 816 453 5905",
    "sg:postcode":"64117",
    "sg:province":"MO",
    "sg:tags":[
        "return",
        "filing"
    ],
    "wof:name":"H & R Block Tax Svc",
    "wof:placetype":"venue"
},
  "geometry": {"coordinates":[-94.533894,39.171807],"type":"Point"}
}