{
  "type": "Feature",
  "properties": {
    "iso:country":"US",
    "sg:address":"4 Pga National Ct",
    "sg:city":"O Fallon",
    "sg:classifiers":[
        {
            "category":"Manufacturing",
            "subcategory":"Printing",
            "type":"Manufacturing & Wholesale Goods"
        }
    ],
    "sg:phone":"+1 636 379 8715",
    "sg:postcode":"63366",
    "sg:province":"MO",
    "sg:tags":[
        "periodical"
    ],
    "wof:name":"This Is It Sports Managing",
    "wof:placetype":"venue"
},
  "geometry": {"coordinates":[-90.72221999999999,38.794615],"type":"Point"}
}