{
  "type": "Feature",
  "properties": {
    "iso:country":"US",
    "sg:address":"225 N US Hwy 169",
    "sg:city":"Gower",
    "sg:classifiers":[
        {
            "category":"Retail",
            "subcategory":"Car Wash",
            "type":"Services"
        }
    ],
    "sg:phone":"+1 816 424 3825",
    "sg:postcode":"64454",
    "sg:province":"MO",
    "sg:tags":[
        "carwash",
        "polishing",
        "washing"
    ],
    "wof:name":"Auto Spa",
    "wof:placetype":"venue"
},
  "geometry": {"coordinates":[-94.59602599999999,39.616224],"type":"Point"}
}