{
  "type": "Feature",
  "properties": {
    "iso:country":"US",
    "sg:address":"4702 Eastern Ave",
    "sg:city":"Kansas City",
    "sg:classifiers":[
        {
            "category":"Building & Trades",
            "subcategory":"Construction",
            "type":"Services"
        }
    ],
    "sg:phone":"+1 816 861 6726",
    "sg:postcode":"64129",
    "sg:province":"MO",
    "sg:tags":[
        "plastering",
        "contractor"
    ],
    "wof:name":"Midland Plastering Co Inc",
    "wof:placetype":"venue"
},
  "geometry": {"coordinates":[-94.498884,39.039366],"type":"Point"}
}