{
  "type": "Feature",
  "properties": {
    "iso:country":"US",
    "sg:address":"528 E 19th Ave",
    "sg:city":"Kansas City",
    "sg:classifiers":[
        {
            "category":"Manufacturing",
            "subcategory":"Tools & Machinery",
            "type":"Manufacturing & Wholesale Goods"
        }
    ],
    "sg:phone":"+1 816 753 2150",
    "sg:postcode":"64116",
    "sg:province":"MO",
    "sg:tags":[
        "food",
        "product"
    ],
    "sg:website":"www.kochsupplies.com",
    "wof:name":"BUNZL Koch Supplies",
    "wof:placetype":"venue"
},
  "geometry": {"coordinates":[-94.57517,39.141697],"type":"Point"}
}