{
  "type": "Feature",
  "properties": {
    "iso:country":"US",
    "sg:address":"10330 N Main St",
    "sg:city":"Kansas City",
    "sg:classifiers":[
        {
            "category":"Shopping",
            "subcategory":"Discount & Variety Stores",
            "type":"Retail Goods"
        }
    ],
    "sg:phone":"+1 816 734 8399",
    "sg:postcode":"64155",
    "sg:province":"MO",
    "sg:tags":[
        "merchandise",
        "general"
    ],
    "wof:name":"People & Pets Portraits",
    "wof:placetype":"venue"
},
  "geometry": {"coordinates":[-94.580623,39.281992],"type":"Point"}
}