{
  "type": "Feature",
  "properties": {
    "iso:country":"US",
    "sg:address":"905 S Neosho Blvd",
    "sg:city":"Neosho",
    "sg:classifiers":[
        {
            "category":"Insurance",
            "subcategory":"Insurance Agent",
            "type":"Services"
        },
        {
            "category":"Insurance",
            "subcategory":"Hazard Insurance",
            "type":"Services"
        },
        {
            "category":"Insurance",
            "subcategory":"Title Insurance",
            "type":"Services"
        },
        {
            "category":"Insurance",
            "subcategory":"Life Insurance",
            "type":"Services"
        }
    ],
    "sg:phone":"+1 417 451 0299",
    "sg:postcode":"64850",
    "sg:province":"MO",
    "sg:tags":[
        "business",
        "auto",
        "commercial",
        "homeowner",
        "motorcycle",
        "renter"
    ],
    "wof:name":"Allstate Insurance Company - Robert Thogmartin",
    "wof:placetype":"venue"
},
  "geometry": {"coordinates":[-94.383509,36.857714],"type":"Point"}
}