{
  "type": "Feature",
  "properties": {
    "iso:country":"US",
    "sg:address":"1307 SW Highland Dr",
    "sg:city":"Lees Summit",
    "sg:classifiers":[
        {
            "category":"Building & Trades",
            "subcategory":"Construction",
            "type":"Services"
        }
    ],
    "sg:phone":"+1 816 525 2505",
    "sg:postcode":"64081",
    "sg:province":"MO",
    "sg:tags":[
        "repairing",
        "remodeling",
        "contractor"
    ],
    "wof:name":"Jersett Quality Builders Inc",
    "wof:placetype":"venue"
},
  "geometry": {"coordinates":[-94.38488599999999,38.898125],"type":"Point"}
}