{
  "type": "Feature",
  "properties": {
    "iso:country":"US",
    "sg:address":"302 E Richardson Ave",
    "sg:city":"Puxico",
    "sg:classifiers":[
        {
            "category":"Personal",
            "subcategory":"Beauty Salon",
            "type":"Services"
        }
    ],
    "sg:phone":"+1 573 222 9950",
    "sg:postcode":"63960",
    "sg:province":"MO",
    "wof:name":"Cutting Edge",
    "wof:placetype":"venue"
},
  "geometry": {"coordinates":[-90.154967,36.949364],"type":"Point"}
}