{
  "type": "Feature",
  "properties": {
    "iso:country":"US",
    "sg:address":"309 W Cherokee St",
    "sg:city":"South West City",
    "sg:classifiers":[
        {
            "category":"Health Services",
            "subcategory":"Medical Lab",
            "type":"Services"
        }
    ],
    "sg:phone":"+1 417 762 3738",
    "sg:postcode":"64863",
    "sg:province":"MO",
    "sg:tags":[
        "laboratory"
    ],
    "wof:name":"Adams Orthodontic Lab",
    "wof:placetype":"venue"
},
  "geometry": {"coordinates":[-94.61451700000001,36.514886],"type":"Point"}
}