{
  "type": "Feature",
  "properties": {
    "iso:country":"US",
    "sg:address":"534 Pine St",
    "sg:city":"Farmington",
    "sg:classifiers":[
        {
            "category":"Shopping",
            "subcategory":"Clothing, Apparel, & Fashions",
            "type":"Retail Goods"
        }
    ],
    "sg:phone":"+1 573 701 9253",
    "sg:postcode":"63640",
    "sg:province":"MO",
    "wof:name":"Glitz",
    "wof:placetype":"venue"
},
  "geometry": {"coordinates":[-90.40894299999999,37.788428],"type":"Point"}
}