{
  "type": "Feature",
  "properties": {
    "iso:country":"US",
    "sg:address":"803 N 1st St",
    "sg:city":"Clarksdale",
    "sg:classifiers":[
        {
            "category":"Personal",
            "subcategory":"Beauty Salon",
            "type":"Services"
        }
    ],
    "sg:phone":"+1 816 393 5443",
    "sg:postcode":"64430",
    "sg:province":"MO",
    "sg:tags":[
        "shop"
    ],
    "wof:name":"Country Curl",
    "wof:placetype":"venue"
},
  "geometry": {"coordinates":[-94.548495,39.814485],"type":"Point"}
}