{
  "type": "Feature",
  "properties": {
    "iso:country":"US",
    "sg:address":"7605 Natural Bridge Rd",
    "sg:city":"St Louis",
    "sg:classifiers":[
        {
            "category":"Health Services",
            "subcategory":"Doctor",
            "type":"Services"
        }
    ],
    "sg:phone":"+1 314 679 7800",
    "sg:postcode":"63121",
    "sg:province":"MO",
    "sg:tags":[
        "clinic"
    ],
    "wof:name":"North County Community Health",
    "wof:placetype":"venue"
},
  "geometry": {"coordinates":[-90.303048,38.706348],"type":"Point"}
}