{
  "type": "Feature",
  "properties": {
    "iso:country":"US",
    "sg:address":"1479 Longhorn Rd",
    "sg:city":"Elkland",
    "sg:classifiers":[
        {
            "category":"Professional",
            "subcategory":"Art Services",
            "type":"Services"
        }
    ],
    "sg:phone":"+1 417 933 5432",
    "sg:postcode":"65644",
    "sg:province":"MO",
    "sg:tags":[
        "commercial",
        "design"
    ],
    "wof:name":"AJS Vinyl Graphics & Sign",
    "wof:placetype":"venue"
},
  "geometry": {"coordinates":[-93.051008,37.429266],"type":"Point"}
}