{
  "type": "Feature",
  "properties": {
    "iso:country":"US",
    "sg:address":"118 W 4th St",
    "sg:city":"Salem",
    "sg:classifiers":[
        {
            "category":"Wholesale",
            "subcategory":"Furniture",
            "type":"Manufacturing & Wholesale Goods"
        },
        {
            "category":"Home & Garden",
            "subcategory":"Furniture",
            "type":"Retail Goods"
        }
    ],
    "sg:phone":"+1 573 739 1150",
    "sg:postcode":"65560",
    "sg:province":"MO",
    "sg:tags":[
        "store",
        "furniture-wholesale",
        "manufacturer"
    ],
    "wof:name":"Jj Alenbeck Furniture",
    "wof:placetype":"venue"
},
  "geometry": {"coordinates":[-91.536464,37.645441],"type":"Point"}
}