{
  "type": "Feature",
  "properties": {
    "iso:country":"US",
    "sg:address":"4878 State Hwy Pp",
    "sg:city":"Fordland",
    "sg:phone":"+1 417 753 2329",
    "sg:postcode":"65652",
    "sg:province":"MO",
    "sg:tags":[
        "farm",
        "field",
        "crop"
    ],
    "wof:name":"Phil Ewing",
    "wof:placetype":"venue"
},
  "geometry": {"coordinates":[-93.013243,37.17346],"type":"Point"}
}