{
  "type": "Feature",
  "properties": {
    "iso:country":"US",
    "sg:address":"1222 N Truman Blvd",
    "sg:city":"Festus",
    "sg:classifiers":[
        {
            "category":"Personal",
            "subcategory":"Beauty Salon",
            "type":"Services"
        }
    ],
    "sg:phone":"+1 636 933 0808",
    "sg:postcode":"63028",
    "sg:province":"MO",
    "wof:name":"Vonda's Hair Studio",
    "wof:placetype":"venue"
},
  "geometry": {"coordinates":[-90.394651,38.202584],"type":"Point"}
}