{
  "type": "Feature",
  "properties": {
    "iso:country":"US",
    "sg:address":"817 Clark Ave",
    "sg:city":"Jefferson City",
    "sg:classifiers":[
        {
            "category":"Building & Trades",
            "subcategory":"Cleaning & Sanitation",
            "type":"Services"
        }
    ],
    "sg:phone":"+1 573 635 6774",
    "sg:postcode":"65101",
    "sg:province":"MO",
    "sg:tags":[
        "janitorial"
    ],
    "wof:name":"Andrews Janitorial Service",
    "wof:placetype":"venue"
},
  "geometry": {"coordinates":[-92.163989,38.561388],"type":"Point"}
}