{
  "type": "Feature",
  "properties": {
    "iso:country":"US",
    "sg:address":"215 Ofallon Plz",
    "sg:city":"O Fallon",
    "sg:classifiers":[
        {
            "category":"Bars & Pubs",
            "type":"Food & Drink"
        },
        {
            "category":"Bars & Pubs",
            "subcategory":"Sports Bar",
            "type":"Food & Drink"
        }
    ],
    "sg:menulink":"http://www.allmenus.com/mo/wentzville/157788-hot-shots-sports-bar-and-grill/menu/",
    "sg:phone":"+1 636 379 4859",
    "sg:postcode":"63366",
    "sg:province":"MO",
    "sg:tags":[
        "american"
    ],
    "wof:name":"Hot Shots Sports Bar And Grill",
    "wof:placetype":"venue"
},
  "geometry": {"coordinates":[-90.699085,38.808909],"type":"Point"}
}