{
  "type": "Feature",
  "properties": {
    "iso:country":"US",
    "sg:address":"3319 Post View Dr",
    "sg:city":"O Fallon",
    "sg:classifiers":[
        {
            "category":"Building & Trades",
            "subcategory":"Construction",
            "type":"Services"
        }
    ],
    "sg:phone":"+1 636 561 1309",
    "sg:postcode":"63368",
    "sg:province":"MO",
    "sg:tags":[
        "house"
    ],
    "wof:name":"Kelly Remodeling",
    "wof:placetype":"venue"
},
  "geometry": {"coordinates":[-90.75261999999999,38.75378],"type":"Point"}
}