{
  "type": "Feature",
  "properties": {
    "iso:country":"US",
    "sg:address":"7801 N Broadway Ave",
    "sg:city":"Kansas City",
    "sg:classifiers":[
        {
            "category":"Building & Trades",
            "subcategory":"Plumbing",
            "type":"Services"
        }
    ],
    "sg:phone":"+1 816 436 5621",
    "sg:postcode":"64118",
    "sg:province":"MO",
    "sg:tags":[
        "plumbing",
        "contractor"
    ],
    "wof:name":"Stone's Plumbing Co",
    "wof:placetype":"venue"
},
  "geometry": {"coordinates":[-94.58514700000001,39.234998],"type":"Point"}
}