{
  "type": "Feature",
  "properties": {
    "iso:country":"US",
    "sg:address":"712 SE Diamond Ct",
    "sg:city":"Blue Springs",
    "sg:classifiers":[
        {
            "category":"Building & Trades",
            "subcategory":"Construction",
            "type":"Services"
        }
    ],
    "sg:phone":"+1 816 229 8750",
    "sg:postcode":"64014",
    "sg:province":"MO",
    "sg:tags":[
        "carpentry",
        "contractor"
    ],
    "wof:name":"Hc Trim Contracting Inc",
    "wof:placetype":"venue"
},
  "geometry": {"coordinates":[-94.259517,38.990933],"type":"Point"}
}