{
  "type": "Feature",
  "properties": {
    "iso:country":"US",
    "sg:address":"3135 Meramec St",
    "sg:city":"Saint Louis",
    "sg:classifiers":[
        {
            "category":"Organizations",
            "subcategory":"Religious Organization",
            "type":"Services"
        }
    ],
    "sg:phone":"+1 314 352 3697",
    "sg:postcode":"63118",
    "sg:province":"MO",
    "wof:name":"St Anthony of Padua Church",
    "wof:placetype":"venue"
},
  "geometry": {"coordinates":[-90.23872900000001,38.5804],"type":"Point"}
}