{
  "type": "Feature",
  "properties": {
    "iso:country":"US",
    "sg:address":"100 Sky Vue Dr",
    "sg:city":"Raymore",
    "sg:classifiers":[
        {
            "category":"Organizations",
            "subcategory":"Membership Organization",
            "type":"Services"
        }
    ],
    "sg:phone":"+1 816 331 9225",
    "sg:postcode":"64083",
    "sg:province":"MO",
    "sg:tags":[
        "athletic"
    ],
    "wof:name":"Missouri Valley Assn Aau",
    "wof:placetype":"venue"
},
  "geometry": {"coordinates":[-94.447475,38.800551],"type":"Point"}
}