{
  "type": "Feature",
  "properties": {
    "iso:country":"US",
    "sg:address":"1301 W Cherry St",
    "sg:city":"Nevada",
    "sg:classifiers":[
        {
            "category":"Social Services",
            "subcategory":"Child Care",
            "type":"Services"
        }
    ],
    "sg:phone":"+1 417 667 5304",
    "sg:postcode":"64772",
    "sg:province":"MO",
    "sg:tags":[
        "day"
    ],
    "wof:name":"Williams Day Care",
    "wof:placetype":"venue"
},
  "geometry": {"coordinates":[-94.37430500000001,37.838678],"type":"Point"}
}