{
  "type": "Feature",
  "properties": {
    "iso:country":"US",
    "sg:address":"10645 Plato Dr",
    "sg:city":"Plato",
    "sg:classifiers":[
        {
            "category":"Education",
            "subcategory":"School",
            "type":"Public Place"
        }
    ],
    "sg:phone":"+1 417 458 4700",
    "sg:postcode":"65552",
    "sg:province":"MO",
    "wof:name":"Plato Elementary School",
    "wof:placetype":"venue"
},
  "geometry": {"coordinates":[-92.220075,37.503162],"type":"Point"}
}