{
  "type": "Feature",
  "properties": {
    "iso:country":"US",
    "sg:address":"1341 N Geyer Rd",
    "sg:city":"Saint Louis",
    "sg:classifiers":[
        {
            "category":"Bars & Pubs",
            "type":"Food & Drink"
        }
    ],
    "sg:phone":"+1 314 965 5335",
    "sg:postcode":"63122",
    "sg:province":"MO",
    "sg:tags":[
        "drinking"
    ],
    "wof:name":"OXY Breath",
    "wof:placetype":"venue"
},
  "geometry": {"coordinates":[-90.415873,38.604097],"type":"Point"}
}