{
  "type": "Feature",
  "properties": {
    "iso:country":"US",
    "sg:address":"1109 S Baltimore St",
    "sg:city":"Kirksville",
    "sg:classifiers":[
        {
            "category":"Wholesale",
            "subcategory":"Auto Parts",
            "type":"Manufacturing & Wholesale Goods"
        }
    ],
    "sg:phone":"+1 660 665 4601",
    "sg:postcode":"63501",
    "sg:province":"MO",
    "wof:name":"Midwest Jobbers 406",
    "wof:placetype":"venue"
},
  "geometry": {"coordinates":[-92.571881,40.186845],"type":"Point"}
}