{
  "type": "Feature",
  "properties": {
    "iso:country":"US",
    "sg:address":"655 E Springfield Rd",
    "sg:city":"Sullivan",
    "sg:classifiers":[
        {
            "category":"Organizations",
            "subcategory":"Membership Organization",
            "type":"Services"
        }
    ],
    "sg:phone":"+1 573 860 7222",
    "sg:postcode":"63080",
    "sg:province":"MO",
    "sg:tags":[
        "athletic"
    ],
    "wof:name":"Sullivan Boys Baseball Assoc",
    "wof:placetype":"venue"
},
  "geometry": {"coordinates":[-91.15249300000001,38.222022],"type":"Point"}
}