{
  "type": "Feature",
  "properties": {
    "iso:country":"US",
    "sg:address":"209 Morehouse St",
    "sg:city":"Barnard",
    "sg:classifiers":[
        {
            "category":"Education",
            "subcategory":"School",
            "type":"Public Place"
        }
    ],
    "sg:phone":"+1 660 652 3221",
    "sg:postcode":"64423",
    "sg:province":"MO",
    "wof:name":"Barnard Superintendent Ofc",
    "wof:placetype":"venue"
},
  "geometry": {"coordinates":[-94.82221800000001,40.177211],"type":"Point"}
}