{
  "type": "Feature",
  "properties": {
    "iso:country":"US",
    "sg:address":"10088 Manchester Rd",
    "sg:city":"Saint Louis",
    "sg:classifiers":[
        {
            "category":"Shopping",
            "subcategory":"Used Merchandise",
            "type":"Retail Goods"
        }
    ],
    "sg:phone":"+1 314 918 9100",
    "sg:postcode":"63122",
    "sg:province":"MO",
    "sg:tags":[
        "new",
        "clothing",
        "m",
        "secondhand"
    ],
    "wof:name":"Kangaroo Kids Inc",
    "wof:placetype":"venue"
},
  "geometry": {"coordinates":[-90.386736,38.602744],"type":"Point"}
}