{
  "type": "Feature",
  "properties": {
    "iso:country":"US",
    "sg:address":"520 S 22nd St",
    "sg:city":"Unionville",
    "sg:classifiers":[
        {
            "category":"Retail",
            "subcategory":"Auto Repair",
            "type":"Services"
        }
    ],
    "sg:phone":"+1 660 947 7093",
    "sg:postcode":"63565",
    "sg:province":"MO",
    "sg:tags":[
        "body",
        "automobile",
        "painting",
        "repairing"
    ],
    "wof:name":"Autobody Solution",
    "wof:placetype":"venue"
},
  "geometry": {"coordinates":[-93.009085,40.472989],"type":"Point"}
}