{
  "type": "Feature",
  "properties": {
    "iso:country":"US",
    "sg:address":"4945 N Bellaire Ave",
    "sg:city":"Kansas City",
    "sg:classifiers":[
        {
            "category":"Building & Trades",
            "subcategory":"Landscaping Services",
            "type":"Services"
        }
    ],
    "sg:phone":"+1 816 453 0375",
    "sg:postcode":"64119",
    "sg:province":"MO",
    "wof:name":"Gillespies P Turf Management",
    "wof:placetype":"venue"
},
  "geometry": {"coordinates":[-94.510792,39.18352],"type":"Point"}
}