{
  "type": "Feature",
  "properties": {
    "iso:country":"US",
    "sg:address":"327 S Kansas Ave",
    "sg:city":"Marceline",
    "sg:classifiers":[
        {
            "category":"Education",
            "subcategory":"School",
            "type":"Public Place"
        }
    ],
    "sg:phone":"+1 660 376 3580",
    "sg:postcode":"64658",
    "sg:province":"MO",
    "wof:name":"Mc Cartan Memorial School",
    "wof:placetype":"venue"
},
  "geometry": {"coordinates":[-92.952693,39.712444],"type":"Point"}
}