{
  "type": "Feature",
  "properties": {
    "iso:country":"US",
    "sg:address":"437 S Marshall St",
    "sg:city":"Marshfield",
    "sg:classifiers":[
        {
            "category":"Personal",
            "subcategory":"Beauty Salon",
            "type":"Services"
        }
    ],
    "sg:phone":"+1 417 859 3501",
    "sg:postcode":"65706",
    "sg:province":"MO",
    "sg:tags":[
        "hair",
        "shop",
        "stylist"
    ],
    "wof:name":"Robinette Beauty Salon",
    "wof:placetype":"venue"
},
  "geometry": {"coordinates":[-92.906927,37.334793],"type":"Point"}
}