{
  "type": "Feature",
  "properties": {
    "iso:country":"US",
    "sg:address":"204 E Boone St",
    "sg:city":"Ash Grove",
    "sg:classifiers":[
        {
            "category":"Wholesale",
            "subcategory":"Construction Materials",
            "type":"Manufacturing & Wholesale Goods"
        }
    ],
    "sg:phone":"+1 417 751 2399",
    "sg:postcode":"65604",
    "sg:province":"MO",
    "sg:tags":[
        "pallet",
        "skid"
    ],
    "wof:name":"C & M Pallets",
    "wof:placetype":"venue"
},
  "geometry": {"coordinates":[-93.57912899999999,37.319152],"type":"Point"}
}