{
  "type": "Feature",
  "properties": {
    "iso:country":"US",
    "sg:address":"304 Claymont Cove Ct",
    "sg:city":"Ballwin",
    "sg:classifiers":[
        {
            "category":"Fast Food",
            "type":"Food & Drink"
        },
        {
            "category":"Restaurant",
            "type":"Food & Drink"
        },
        {
            "category":"Food & Beverages",
            "subcategory":"Groceries & Convenience Stores",
            "type":"Retail Goods"
        }
    ],
    "sg:phone":"+1 636 536 4740",
    "sg:postcode":"63011",
    "sg:province":"MO",
    "sg:tags":[
        "shop",
        "american",
        "sandwich",
        "take"
    ],
    "sg:website":"http://www.quiznos.com",
    "wof:name":"Quiznos Classic Subs",
    "wof:placetype":"venue"
},
  "geometry": {"coordinates":[-90.55490399999999,38.605383],"type":"Point"}
}