{
  "type": "Feature",
  "properties": {
    "iso:country":"US",
    "sg:address":"33800 Kensington Ln",
    "sg:city":"Richland",
    "sg:classifiers":[
        {
            "category":"Retail",
            "subcategory":"Animal Services",
            "type":"Services"
        }
    ],
    "sg:phone":"+1 573 765 5147",
    "sg:postcode":"65556",
    "sg:province":"MO",
    "wof:name":"D&M Kennel",
    "wof:placetype":"venue"
},
  "geometry": {"coordinates":[-92.424868,37.845412],"type":"Point"}
}