{
  "type": "Feature",
  "properties": {
    "iso:country":"US",
    "sg:address":"2140 SE 7 St",
    "sg:city":"Lees Summit",
    "sg:classifiers":[
        {
            "category":"Organizations",
            "subcategory":"Non-profit Organization",
            "type":"Services"
        }
    ],
    "sg:phone":"+1 816 525 6991",
    "sg:postcode":"64063",
    "sg:province":"MO",
    "sg:tags":[
        "social"
    ],
    "wof:name":"Northern Explosion Vbc In",
    "wof:placetype":"venue"
},
  "geometry": {"coordinates":[-94.33023900000001,38.905437],"type":"Point"}
}