{
  "type": "Feature",
  "properties": {
    "iso:country":"US",
    "sg:address":"315 N Cox Ave",
    "sg:city":"Joplin",
    "sg:classifiers":[
        {
            "category":"Manufacturing",
            "subcategory":"Buildings",
            "type":"Manufacturing & Wholesale Goods"
        },
        {
            "category":"Building & Trades",
            "subcategory":"Construction",
            "type":"Services"
        }
    ],
    "sg:phone":"+1 417 781 4621",
    "sg:postcode":"64801",
    "sg:province":"MO",
    "sg:tags":[
        "management",
        "altering",
        "builder",
        "contractor",
        "home",
        "remodeling"
    ],
    "wof:name":"Spellman Associates Inc",
    "wof:placetype":"venue"
},
  "geometry": {"coordinates":[-94.504881,37.093727],"type":"Point"}
}