{
  "type": "Feature",
  "properties": {
    "iso:country":"US",
    "sg:address":"107 N Main St",
    "sg:city":"St Charles",
    "sg:classifiers":[
        {
            "category":"Shopping",
            "subcategory":"Used Merchandise",
            "type":"Retail Goods"
        }
    ],
    "sg:phone":"+1 636 724 2295",
    "sg:postcode":"63301",
    "sg:province":"MO",
    "sg:tags":[
        "flea",
        "market"
    ],
    "wof:name":"Jil Flea Market & Oldies",
    "wof:placetype":"venue"
},
  "geometry": {"coordinates":[-90.48094500000001,38.782208],"type":"Point"}
}