{
  "type": "Feature",
  "properties": {
    "iso:country":"US",
    "sg:address":"211 S Main St Ste B",
    "sg:city":"Ironton",
    "sg:classifiers":[
        {
            "category":"Health Services",
            "subcategory":"Dentist",
            "type":"Services"
        }
    ],
    "sg:phone":"+1 573 546 3368",
    "sg:postcode":"63650",
    "sg:province":"MO",
    "wof:name":"Charles L Mchenry Dds",
    "wof:placetype":"venue"
},
  "geometry": {"coordinates":[-90.627607,37.598184],"type":"Point"}
}