{
  "type": "Feature",
  "properties": {
    "iso:country":"US",
    "sg:address":"210 E 7th St",
    "sg:city":"Mountain View",
    "sg:classifiers":[
        {
            "category":"Real Estate",
            "subcategory":"Real Estate Operator",
            "type":"Services"
        }
    ],
    "sg:phone":"+1 417 934 6815",
    "sg:postcode":"65548",
    "sg:province":"MO",
    "sg:tags":[
        "apartment"
    ],
    "wof:name":"Mountain View Senior Citizen",
    "wof:placetype":"venue"
},
  "geometry": {"coordinates":[-91.70072399999999,37.001299],"type":"Point"}
}