{
  "type": "Feature",
  "properties": {
    "iso:country":"US",
    "sg:address":"8416 N Lindbergh Blvd",
    "sg:city":"Florissant",
    "sg:classifiers":[
        {
            "category":"Restaurant",
            "type":"Food & Drink"
        }
    ],
    "sg:menulink":"http://www.allmenus.com/mo/lewis-and-clark/37086-hunan-delight/menu/",
    "sg:phone":"+1 314 838 1822",
    "sg:postcode":"63031",
    "sg:province":"MO",
    "sg:tags":[
        "asian",
        "chinese"
    ],
    "wof:name":"Hunan Delight",
    "wof:placetype":"venue"
},
  "geometry": {"coordinates":[-90.342332,38.793622],"type":"Point"}
}