{
  "type": "Feature",
  "properties": {
    "iso:country":"US",
    "sg:address":"13600 Quince Rd",
    "sg:city":"Neosho",
    "sg:classifiers":[
        {
            "category":"Retail",
            "subcategory":"Repair Shop",
            "type":"Services"
        }
    ],
    "sg:phone":"+1 417 451 0604",
    "sg:postcode":"64850",
    "sg:province":"MO",
    "wof:name":"Bradford Roy L",
    "wof:placetype":"venue"
},
  "geometry": {"coordinates":[-94.40255999999999,36.802813],"type":"Point"}
}