{
  "type": "Feature",
  "properties": {
    "iso:country":"US",
    "sg:address":"1227 Adams St",
    "sg:city":"Jefferson City",
    "sg:classifiers":[
        {
            "category":"Professional",
            "subcategory":"Business Services",
            "type":"Services"
        }
    ],
    "sg:phone":"+1 573 636 6057",
    "sg:postcode":"65101",
    "sg:province":"MO",
    "wof:name":"J Cremer Pkg Enterprises LLC",
    "wof:placetype":"venue"
},
  "geometry": {"coordinates":[-92.18058000000001,38.563714],"type":"Point"}
}