{
  "type": "Feature",
  "properties": {
    "iso:country":"US",
    "sg:address":"548 Birkhead Rd",
    "sg:city":"Winfield",
    "sg:classifiers":[
        {
            "category":"Building & Trades",
            "subcategory":"Landscaping Services",
            "type":"Services"
        }
    ],
    "sg:phone":"+1 636 566 8094",
    "sg:postcode":"63389",
    "sg:province":"MO",
    "wof:name":"Crowders Lawn Service",
    "wof:placetype":"venue"
},
  "geometry": {"coordinates":[-90.79190199999999,38.994132],"type":"Point"}
}