{
  "type": "Feature",
  "properties": {
    "iso:country":"US",
    "sg:address":"1820 Market St",
    "sg:city":"St Louis",
    "sg:classifiers":[
        {
            "category":"Restaurant",
            "type":"Food & Drink"
        }
    ],
    "sg:phone":"+1 314 421 0553",
    "sg:postcode":"63103",
    "sg:province":"MO",
    "wof:name":"A & W Family Restaurant",
    "wof:placetype":"venue"
},
  "geometry": {"coordinates":[-90.208922,38.629748],"type":"Point"}
}