{
  "type": "Feature",
  "properties": {
    "iso:country":"US",
    "sg:address":"246 SW 601st Rd",
    "sg:city":"Centerview",
    "sg:classifiers":[
        {
            "category":"Real Estate",
            "subcategory":"Real Estate Operator",
            "type":"Services"
        }
    ],
    "sg:phone":"+1 660 656 3526",
    "sg:postcode":"64019",
    "sg:province":"MO",
    "sg:tags":[
        "building",
        "nonresidential"
    ],
    "wof:name":"Hartland Properties",
    "wof:placetype":"venue"
},
  "geometry": {"coordinates":[-93.860467,38.728641],"type":"Point"}
}