{
  "type": "Feature",
  "properties": {
    "iso:country":"US",
    "sg:address":"919 Edgemont Blvd",
    "sg:city":"Perryville",
    "sg:classifiers":[
        {
            "category":"Autos & Motor Vehicles",
            "subcategory":"Automobile Sales",
            "type":"Retail Goods"
        }
    ],
    "sg:phone":"+1 573 547 8629",
    "sg:postcode":"63775",
    "sg:province":"MO",
    "sg:tags":[
        "new",
        "car"
    ],
    "wof:name":"Dale F Schamburg",
    "wof:placetype":"venue"
},
  "geometry": {"coordinates":[-89.874712,37.721018],"type":"Point"}
}