{
  "type": "Feature",
  "properties": {
    "addr:full":"231 Highway 47 E Troy MO 63379",
    "addr:housenumber":"231",
    "addr:postcode":"63379",
    "addr:street":"Highway 47 E",
    "iso:country":"US",
    "sg:address":"231 Highway 47 E",
    "sg:city":"Troy",
    "sg:classifiers":[
        {
            "category":"Fast Food",
            "type":"Food & Drink"
        },
        {
            "category":"Restaurant",
            "type":"Food & Drink"
        }
    ],
    "sg:phone":"+1 636 528 7222",
    "sg:postcode":"63379",
    "sg:province":"MO",
    "sg:tags":[
        "american",
        "hot",
        "hamburger",
        "dog",
        "take"
    ],
    "sg:website":"http://www.hardees.com",
    "wof:name":"Hardee's",
    "wof:placetype":"venue"
},
  "geometry": {"coordinates":[-90.968491,38.986778],"type":"Point"}
}