{
  "type": "Feature",
  "properties": {
    "iso:country":"US",
    "sg:address":"14905 W Farm Rd 52",
    "sg:city":"Ash Grove",
    "sg:classifiers":[
        {
            "category":"Local Transit",
            "type":"Transportation"
        }
    ],
    "sg:phone":"+1 417 471 1111",
    "sg:postcode":"65604",
    "sg:province":"MO",
    "sg:tags":[
        "passenger"
    ],
    "wof:name":"First Class Limousine",
    "wof:placetype":"venue"
},
  "geometry": {"coordinates":[-93.615027,37.354561],"type":"Point"}
}