{
  "type": "Feature",
  "properties": {
    "addr:full":"1735 S Grant Ave Marshall MO 65340",
    "addr:housenumber":"1735",
    "addr:postcode":"65340",
    "addr:street":"S Grant Ave",
    "iso:country":"US",
    "sg:address":"1735 S Grant Ave",
    "sg:city":"Marshall",
    "sg:classifiers":[
        {
            "category":"Place Of Worship",
            "subcategory":"Church",
            "type":"Public Place"
        },
        {
            "category":"Place Of Worship",
            "type":"Public Place"
        }
    ],
    "sg:phone":"+1 660 886 4345",
    "sg:postcode":"65340",
    "sg:province":"MO",
    "sg:tags":[
        "churches-episcopal-anglican",
        "churches-episcopal"
    ],
    "wof:name":"Trinity Episcopal Church",
    "wof:placetype":"venue"
},
  "geometry": {"coordinates":[-93.207317,39.102623],"type":"Point"}
}