{
  "type": "Feature",
  "properties": {
    "iso:country":"US",
    "sg:address":"13652 Manchester Rd",
    "sg:city":"St Louis",
    "sg:classifiers":[
        {
            "category":"Manufacturing",
            "subcategory":"Signs",
            "type":"Manufacturing & Wholesale Goods"
        }
    ],
    "sg:phone":"+1 314 966 2620",
    "sg:postcode":"63131",
    "sg:province":"MO",
    "sg:website":"www.dalesigns.com",
    "wof:name":"Dale Sign Svc",
    "wof:placetype":"venue"
},
  "geometry": {"coordinates":[-90.476833,38.596266],"type":"Point"}
}