{
  "type": "Feature",
  "properties": {
    "iso:country":"US",
    "sg:address":"3206 N Spring St",
    "sg:city":"Independence",
    "sg:classifiers":[
        {
            "category":"Education",
            "subcategory":"Special Training",
            "type":"Public Place"
        }
    ],
    "sg:phone":"+1 816 836 1075",
    "sg:postcode":"64050",
    "sg:province":"MO",
    "wof:name":"Solid Rock Christian Academy",
    "wof:placetype":"venue"
},
  "geometry": {"coordinates":[-94.41976,39.128115],"type":"Point"}
}