{
  "type": "Feature",
  "properties": {
    "iso:country":"US",
    "sg:address":"2016 Marconi Ave",
    "sg:city":"St. Louis",
    "sg:classifiers":[
        {
            "category":"Personal",
            "subcategory":"Skin Care",
            "type":"Services"
        }
    ],
    "sg:phone":"+1 314 601 3904",
    "sg:postcode":"63110",
    "sg:province":"MO",
    "sg:website":"www.herbariasoap.com",
    "wof:name":"Herbaria",
    "wof:placetype":"venue"
},
  "geometry": {"coordinates":[-90.272493,38.616156],"type":"Point"}
}