{
  "type": "Feature",
  "properties": {
    "iso:country":"US",
    "sg:address":"5000 W Kearney St",
    "sg:city":"Springfield",
    "sg:classifiers":[
        {
            "category":"Airport",
            "type":"Transportation"
        }
    ],
    "sg:phone":"+1 417 869 0300",
    "sg:postcode":"65803",
    "sg:province":"MO",
    "sg:tags":[
        "executive"
    ],
    "wof:name":"Springfield Regional Airport",
    "wof:placetype":"venue"
},
  "geometry": {"coordinates":[-93.378309,37.241781],"type":"Point"}
}