{
  "type": "Feature",
  "properties": {
    "iso:country":"US",
    "sg:address":"10201 E 75 St",
    "sg:city":"Kansas City",
    "sg:classifiers":[
        {
            "category":"Building & Trades",
            "subcategory":"Construction",
            "type":"Services"
        }
    ],
    "sg:phone":"+1 816 737 2953",
    "sg:postcode":"64138",
    "sg:province":"MO",
    "sg:tags":[
        "general",
        "industrial",
        "commercial",
        "contractor"
    ],
    "wof:name":"David E Ross Construction Co",
    "wof:placetype":"venue"
},
  "geometry": {"coordinates":[-94.46213899999999,38.986892],"type":"Point"}
}