{
  "type": "Feature",
  "properties": {
    "iso:country":"US",
    "sg:address":"2715 N Glenstone Ave",
    "sg:city":"Springfield",
    "sg:classifiers":[
        {
            "category":"Travel",
            "subcategory":"Hotels & Motels",
            "type":"Entertainment"
        }
    ],
    "sg:phone":"+1 417 863 8400",
    "sg:postcode":"65803",
    "sg:province":"MO",
    "sg:tags":[
        "operation"
    ],
    "wof:name":"Drury Inn & Suites",
    "wof:placetype":"venue"
},
  "geometry": {"coordinates":[-93.26081000000001,37.246079],"type":"Point"}
}