{
  "type": "Feature",
  "properties": {
    "iso:country":"US",
    "sg:address":"5559 State Hwy P",
    "sg:city":"Cuba",
    "sg:classifiers":[
        {
            "category":"Building & Trades",
            "subcategory":"Construction",
            "type":"Services"
        }
    ],
    "sg:phone":"+1 573 885 7874",
    "sg:postcode":"65453",
    "sg:province":"MO",
    "sg:tags":[
        "contractor"
    ],
    "wof:name":"Cuba Contracting",
    "wof:placetype":"venue"
},
  "geometry": {"coordinates":[-91.380528,38.137706],"type":"Point"}
}