{
  "type": "Feature",
  "properties": {
    "iso:country":"US",
    "sg:address":"4912 E Farm Rd 170",
    "sg:city":"Rogersville",
    "sg:classifiers":[
        {
            "category":"Building & Trades",
            "subcategory":"Construction",
            "type":"Services"
        }
    ],
    "sg:phone":"+1 417 889 0867",
    "sg:postcode":"65742",
    "sg:province":"MO",
    "sg:tags":[
        "contractor"
    ],
    "wof:name":"Petersen Masonry",
    "wof:placetype":"venue"
},
  "geometry": {"coordinates":[-93.19041900000001,37.135008],"type":"Point"}
}