{
  "type": "Feature",
  "properties": {
    "iso:country":"US",
    "sg:address":"101 N Bishop Ave",
    "sg:city":"Rolla",
    "sg:classifiers":[
        {
            "category":"Home & Garden",
            "subcategory":"Carpets & Floor Coverings",
            "type":"Retail Goods"
        }
    ],
    "sg:phone":"+1 573 341 9100",
    "sg:postcode":"65401",
    "sg:province":"MO",
    "wof:name":"Artistry Carpet One Inc",
    "wof:placetype":"venue"
},
  "geometry": {"coordinates":[-91.77736,37.945405],"type":"Point"}
}