{
  "type": "Feature",
  "properties": {
    "iso:country":"US",
    "sg:address":"211 W Linwood Blvd",
    "sg:city":"Kansas City",
    "sg:classifiers":[
        {
            "category":"Education",
            "subcategory":"School",
            "type":"Public Place"
        }
    ],
    "sg:phone":"+1 816 457 6044",
    "sg:postcode":"64111",
    "sg:province":"MO",
    "wof:name":"Cristo Rey School",
    "wof:placetype":"venue"
},
  "geometry": {"coordinates":[-94.589073,39.06746],"type":"Point"}
}