{
  "type": "Feature",
  "properties": {
    "iso:country":"US",
    "sg:address":"820 Electric St",
    "sg:city":"Farmington",
    "sg:classifiers":[
        {
            "category":"Local Transit",
            "type":"Transportation"
        }
    ],
    "sg:phone":"+1 573 756 6764",
    "sg:postcode":"63640",
    "sg:province":"MO",
    "sg:tags":[
        "ambulance"
    ],
    "sg:website":"www.sscad.org",
    "wof:name":"St Francois County Ambulance",
    "wof:placetype":"venue"
},
  "geometry": {"coordinates":[-90.437237,37.799514],"type":"Point"}
}