{
  "type": "Feature",
  "properties": {
    "iso:country":"US",
    "sg:address":"2301 Highway A",
    "sg:city":"Washington",
    "sg:classifiers":[
        {
            "category":"Bars & Pubs",
            "type":"Food & Drink"
        },
        {
            "category":"Restaurant",
            "type":"Food & Drink"
        },
        {
            "category":"Bars & Pubs",
            "subcategory":"Lounge",
            "type":"Food & Drink"
        }
    ],
    "sg:phone":"+1 636 390 0167",
    "sg:postcode":"63090",
    "sg:province":"MO",
    "sg:tags":[
        "grill",
        "cocktail"
    ],
    "sg:website":"http://www.millers-grill.com",
    "wof:name":"Miller's Grill Inc",
    "wof:placetype":"venue"
},
  "geometry": {"coordinates":[-91.020592,38.534119],"type":"Point"}
}