{
  "type": "Feature",
  "properties": {
    "iso:country":"US",
    "sg:address":"25 Camelot Ct",
    "sg:city":"High Ridge",
    "sg:classifiers":[
        {
            "category":"Retail",
            "subcategory":"Auto Repair",
            "type":"Services"
        }
    ],
    "sg:phone":"+1 314 220 3322",
    "sg:postcode":"63049",
    "sg:province":"MO",
    "sg:tags":[
        "body"
    ],
    "wof:name":"Dents r US",
    "wof:placetype":"venue"
},
  "geometry": {"coordinates":[-90.49381700000001,38.447139],"type":"Point"}
}