{
  "type": "Feature",
  "properties": {
    "iso:country":"US",
    "sg:address":"101 W Liberty St",
    "sg:city":"Farmington",
    "sg:classifiers":[
        {
            "category":"Professional",
            "subcategory":"Management & Consulting",
            "type":"Services"
        },
        {
            "category":"Professional",
            "subcategory":"Lawyer & Legal Services",
            "type":"Services"
        }
    ],
    "sg:phone":"+1 573 756 4543",
    "sg:postcode":"63640",
    "sg:province":"MO",
    "sg:tags":[
        "attorney",
        "law",
        "business",
        "family",
        "divorce",
        "practice",
        "consultant",
        "criminal",
        "bankruptcy"
    ],
    "wof:name":"Colson & Mackay L L C",
    "wof:placetype":"venue"
},
  "geometry": {"coordinates":[-90.42169199999999,37.781261],"type":"Point"}
}