{
  "type": "Feature",
  "properties": {
    "iso:country":"US",
    "sg:address":"1217 McKinley Ave",
    "sg:city":"St Louis",
    "sg:classifiers":[
        {
            "category":"Arts & Performance",
            "subcategory":"Theater",
            "type":"Entertainment"
        }
    ],
    "sg:phone":"+1 314 961 5107",
    "sg:postcode":"63119",
    "sg:province":"MO",
    "sg:tags":[
        "musician"
    ],
    "wof:name":"Jed Hadfield",
    "wof:placetype":"venue"
},
  "geometry": {"coordinates":[-90.368242,38.611762],"type":"Point"}
}