{
  "type": "Feature",
  "properties": {
    "iso:country":"US",
    "sg:address":"3919 Shenandoah Ave",
    "sg:city":"Saint Louis",
    "sg:classifiers":[
        {
            "category":"Organizations",
            "subcategory":"Non-profit Organization",
            "type":"Services"
        }
    ],
    "sg:phone":"+1 314 773 3313",
    "sg:postcode":"63110",
    "sg:province":"MO",
    "sg:tags":[
        "aging",
        "membership",
        "for"
    ],
    "wof:name":"AARP",
    "wof:placetype":"venue"
},
  "geometry": {"coordinates":[-90.248408,38.610381],"type":"Point"}
}