{
  "type": "Feature",
  "properties": {
    "iso:country":"US",
    "sg:address":"1516 Sail Island Ct",
    "sg:city":"Chesterfield",
    "sg:classifiers":[
        {
            "category":"Banks & Credit Unions",
            "subcategory":"Financial Services",
            "type":"Services"
        }
    ],
    "sg:phone":"+1 636 532 3284",
    "sg:postcode":"63017",
    "sg:province":"MO",
    "sg:tags":[
        "financing"
    ],
    "wof:name":"Diversified Funding Inc",
    "wof:placetype":"venue"
},
  "geometry": {"coordinates":[-90.551175,38.625121],"type":"Point"}
}