{
  "type": "Feature",
  "properties": {
    "iso:country":"US",
    "sg:address":"921 W State Route 92",
    "sg:city":"Kearney",
    "sg:classifiers":[
        {
            "category":"Bars & Pubs",
            "type":"Food & Drink"
        }
    ],
    "sg:menulink":"http://www.allmenus.com/mo/kearney/12157-pizza-shoppe--pub/menu/",
    "sg:phone":"+1 816 903 3544",
    "sg:postcode":"64060",
    "sg:province":"MO",
    "sg:tags":[
        "american",
        "pizza"
    ],
    "wof:name":"Pizza Shoppe & Pub",
    "wof:placetype":"venue"
},
  "geometry": {"coordinates":[-94.37943799999999,39.367833],"type":"Point"}
}