{
  "type": "Feature",
  "properties": {
    "iso:country":"US",
    "sg:address":"13368 Hwy 135",
    "sg:city":"Stover",
    "sg:classifiers":[
        {
            "category":"Real Estate",
            "subcategory":"Real Estate Agent",
            "type":"Services"
        }
    ],
    "sg:phone":"+1 573 377 2008",
    "sg:postcode":"65078",
    "sg:province":"MO",
    "wof:name":"Cain Lloyd & Nellie",
    "wof:placetype":"venue"
},
  "geometry": {"coordinates":[-93.023419,38.494119],"type":"Point"}
}