{
  "type": "Feature",
  "properties": {
    "iso:country":"US",
    "sg:address":"110A Tyler St",
    "sg:city":"Thayer",
    "sg:classifiers":[
        {
            "category":"Professional",
            "subcategory":"Detective & Security Services",
            "type":"Services"
        }
    ],
    "sg:phone":"+1 417 264 2677",
    "sg:postcode":"65791",
    "sg:province":"MO",
    "sg:tags":[
        "control",
        "monitoring",
        "fire",
        "consultant",
        "alarm",
        "system",
        "equipment"
    ],
    "wof:name":"Moark Safety Systems",
    "wof:placetype":"venue"
},
  "geometry": {"coordinates":[-91.547408,36.535424],"type":"Point"}
}