{
  "type": "Feature",
  "properties": {
    "iso:country":"US",
    "sg:address":"212 W Main St",
    "sg:city":"Maysville",
    "sg:classifiers":[
        {
            "category":"Shopping",
            "subcategory":"Florist",
            "type":"Retail Goods"
        }
    ],
    "sg:phone":"+1 816 449 5246",
    "sg:postcode":"64469",
    "sg:province":"MO",
    "wof:name":"Country Creation",
    "wof:placetype":"venue"
},
  "geometry": {"coordinates":[-94.360856,39.889412],"type":"Point"}
}