{
  "type": "Feature",
  "properties": {
    "iso:country":"US",
    "sg:address":"3530 Jeffco Blvd",
    "sg:city":"Arnold",
    "sg:classifiers":[
        {
            "category":"Health Services",
            "subcategory":"Doctor",
            "type":"Services"
        }
    ],
    "sg:phone":"+1 636 461 2142",
    "sg:postcode":"63010",
    "sg:province":"MO",
    "sg:tags":[
        "physician",
        "surgeon"
    ],
    "wof:name":"C. Jeffrey Sippel",
    "wof:placetype":"venue"
},
  "geometry": {"coordinates":[-90.379436,38.413174],"type":"Point"}
}