{
  "type": "Feature",
  "properties": {
    "iso:country":"US",
    "sg:address":"2904 Wingate Ct",
    "sg:city":"St Louis",
    "sg:classifiers":[
        {
            "category":"Professional",
            "subcategory":"Accounting & Tax Preparation",
            "type":"Services"
        }
    ],
    "sg:phone":"+1 314 691 2749",
    "sg:postcode":"63119",
    "sg:province":"MO",
    "sg:tags":[
        "return",
        "filing"
    ],
    "wof:name":"Kachulis Accounting & Tax Svc",
    "wof:placetype":"venue"
},
  "geometry": {"coordinates":[-90.36197,38.606847],"type":"Point"}
}