{
  "type": "Feature",
  "properties": {
    "iso:country":"US",
    "sg:address":"24821 Hwy 135",
    "sg:city":"Stover",
    "sg:classifiers":[
        {
            "category":"Building & Trades",
            "subcategory":"Construction",
            "type":"Services"
        }
    ],
    "sg:phone":"+1 573 377 2773",
    "sg:postcode":"65078",
    "sg:province":"MO",
    "sg:tags":[
        "contractor"
    ],
    "wof:name":"Conner Custom Fencing",
    "wof:placetype":"venue"
},
  "geometry": {"coordinates":[-92.962462,38.343413],"type":"Point"}
}