{
  "type": "Feature",
  "properties": {
    "iso:country":"US",
    "sg:address":"212 Lafayette St",
    "sg:city":"Jefferson City",
    "sg:classifiers":[
        {
            "category":"Professional",
            "subcategory":"Lawyer & Legal Services",
            "type":"Services"
        }
    ],
    "sg:phone":"+1 573 634 3234",
    "sg:postcode":"65101",
    "sg:province":"MO",
    "wof:name":"Sinclair Rogers Inc",
    "wof:placetype":"venue"
},
  "geometry": {"coordinates":[-92.163732,38.572401],"type":"Point"}
}