{
  "type": "Feature",
  "properties": {
    "iso:country":"US",
    "sg:address":"601 N Carr St",
    "sg:city":"Wentzville",
    "sg:classifiers":[
        {
            "category":"Education",
            "subcategory":"School",
            "type":"Public Place"
        }
    ],
    "sg:phone":"+1 636 327 3839",
    "sg:postcode":"63385",
    "sg:province":"MO",
    "sg:website":"www.wentzville.k12.mo.us",
    "wof:name":"East Elementary School",
    "wof:placetype":"venue"
},
  "geometry": {"coordinates":[-90.85275,38.81554],"type":"Point"}
}