{
  "type": "Feature",
  "properties": {
    "addr:full":"229 S Rollins St Centralia MO 65240",
    "addr:housenumber":"229",
    "addr:postcode":"65240",
    "addr:street":"S Rollins St",
    "iso:country":"US",
    "sg:address":"229 S Rollins St",
    "sg:city":"Centralia",
    "sg:classifiers":[
        {
            "category":"Organizations",
            "subcategory":"Religious Organization",
            "type":"Services"
        }
    ],
    "sg:phone":"+1 573 682 3215",
    "sg:postcode":"65240",
    "sg:province":"MO",
    "sg:tags":[
        "clergy"
    ],
    "wof:name":"First Christian Church",
    "wof:placetype":"venue"
},
  "geometry": {"coordinates":[-92.138125,39.210139],"type":"Point"}
}