{
  "type": "Feature",
  "properties": {
    "iso:country":"US",
    "sg:address":"607 E 7th St",
    "sg:city":"Joplin",
    "sg:classifiers":[
        {
            "category":"Wholesale",
            "subcategory":"Office Equipment",
            "type":"Manufacturing & Wholesale Goods"
        },
        {
            "category":"Professional",
            "subcategory":"Printing & Photocopies",
            "type":"Services"
        },
        {
            "category":"Shopping",
            "subcategory":"Computers & Home Electronics",
            "type":"Retail Goods"
        }
    ],
    "sg:phone":"+1 417 627 0585",
    "sg:postcode":"64801",
    "sg:province":"MO",
    "sg:tags":[
        "scanning",
        "printer",
        "supply",
        "duplicating",
        "copying",
        "plotting"
    ],
    "wof:name":"Lettershop The",
    "wof:placetype":"venue"
},
  "geometry": {"coordinates":[-94.507285,37.083939],"type":"Point"}
}