{
  "type": "Feature",
  "properties": {
    "iso:country":"US",
    "sg:address":"5124 Lydia Ave",
    "sg:city":"Kansas City",
    "sg:classifiers":[
        {
            "category":"Real Estate",
            "subcategory":"Real Estate Agent",
            "type":"Services"
        }
    ],
    "sg:phone":"+1 816 444 6520",
    "sg:postcode":"64110",
    "sg:province":"MO",
    "wof:name":"Rockhurst Properties",
    "wof:placetype":"venue"
},
  "geometry": {"coordinates":[-94.56887,39.03293],"type":"Point"}
}