{
  "type": "Feature",
  "properties": {
    "iso:country":"US",
    "sg:address":"2155 Oriole Dr",
    "sg:city":"Florissant",
    "sg:classifiers":[
        {
            "category":"Freight",
            "type":"Transportation"
        }
    ],
    "sg:phone":"+1 314 830 0658",
    "sg:postcode":"63033",
    "sg:province":"MO",
    "sg:tags":[
        "operator",
        "local",
        "trucking"
    ],
    "wof:name":"Taylor Trucking Co",
    "wof:placetype":"venue"
},
  "geometry": {"coordinates":[-90.312262,38.805339],"type":"Point"}
}