{
  "type": "Feature",
  "properties": {
    "iso:country":"US",
    "sg:address":"215 S Elm St",
    "sg:city":"Elmer",
    "sg:phone":"+1 660 825 4282",
    "sg:postcode":"63538",
    "sg:province":"MO",
    "sg:tags":[
        "beef",
        "farm",
        "ranch",
        "soybean",
        "cattle",
        "feedlot"
    ],
    "wof:name":"Larry Fletcher",
    "wof:placetype":"venue"
},
  "geometry": {"coordinates":[-92.64826600000001,39.954255],"type":"Point"}
}