{
  "type": "Feature",
  "properties": {
    "iso:country":"US",
    "sg:address":"49 N Orchard Blvd",
    "sg:city":"Fair Grove",
    "sg:classifiers":[
        {
            "category":"Shopping",
            "type":"Retail Goods"
        }
    ],
    "sg:phone":"+1 417 759 6303",
    "sg:postcode":"65648",
    "sg:province":"MO",
    "sg:tags":[
        "farm",
        "supply"
    ],
    "wof:name":"Fair Grove Feed & Trading Post",
    "wof:placetype":"venue"
},
  "geometry": {"coordinates":[-93.15363499999999,37.384715],"type":"Point"}
}