{
  "type": "Feature",
  "properties": {
    "iso:country":"US",
    "sg:address":"1400 Ferguson Ave",
    "sg:city":"Saint Louis",
    "sg:classifiers":[
        {
            "category":"Education",
            "subcategory":"Music School",
            "type":"Public Place"
        }
    ],
    "sg:phone":"+1 314 727 4512",
    "sg:postcode":"63133",
    "sg:province":"MO",
    "sg:tags":[
        "instrument",
        "teacher",
        "musical"
    ],
    "wof:name":"St Louis Music Inc",
    "wof:placetype":"venue"
},
  "geometry": {"coordinates":[-90.3078,38.6805],"type":"Point"}
}