{
  "type": "Feature",
  "properties": {
    "iso:country":"US",
    "sg:address":"4405 NW D'Mons Dr",
    "sg:city":"Riverside",
    "sg:classifiers":[
        {
            "category":"Real Estate",
            "subcategory":"Real Estate Agent",
            "type":"Services"
        }
    ],
    "sg:phone":"+1 816 741 1594",
    "sg:postcode":"64150",
    "sg:province":"MO",
    "sg:tags":[
        "finding",
        "apartment",
        "rental"
    ],
    "wof:name":"Chateau D'Mons",
    "wof:placetype":"venue"
},
  "geometry": {"coordinates":[-94.620136,39.175436],"type":"Point"}
}