{
  "type": "Feature",
  "properties": {
    "iso:country":"US",
    "sg:address":"8415 Woodson Dr",
    "sg:city":"Kansas City",
    "sg:classifiers":[
        {
            "category":"Shopping",
            "subcategory":"Musical Instruments",
            "type":"Retail Goods"
        }
    ],
    "sg:phone":"+1 816 353 2731",
    "sg:postcode":"64138",
    "sg:province":"MO",
    "sg:tags":[
        "sheet",
        "music"
    ],
    "wof:name":"American Music Co Inc",
    "wof:placetype":"venue"
},
  "geometry": {"coordinates":[-94.44483200000001,38.969207],"type":"Point"}
}