{
  "type": "Feature",
  "properties": {
    "iso:country":"US",
    "sg:address":"616 E 63 St",
    "sg:city":"Kansas City",
    "sg:classifiers":[
        {
            "category":"Professional",
            "type":"Services"
        },
        {
            "category":"Professional",
            "subcategory":"Business Services",
            "type":"Services"
        }
    ],
    "sg:phone":"+1 816 444 9400",
    "sg:postcode":"64110",
    "sg:province":"MO",
    "sg:tags":[
        "establishment"
    ],
    "wof:name":"Pinecrest Fund",
    "wof:placetype":"venue"
},
  "geometry": {"coordinates":[-94.579335,39.013532],"type":"Point"}
}