{
  "type": "Feature",
  "properties": {
    "iso:country":"US",
    "sg:address":"13365 Olive Blvd",
    "sg:city":"Chesterfield",
    "sg:classifiers":[
        {
            "category":"Wholesale",
            "subcategory":"Groceries",
            "type":"Manufacturing & Wholesale Goods"
        }
    ],
    "sg:phone":"+1 314 205 1882",
    "sg:postcode":"63017",
    "sg:province":"MO",
    "wof:name":"East East Oriental Grocery Str",
    "wof:placetype":"venue"
},
  "geometry": {"coordinates":[-90.495273,38.680616],"type":"Point"}
}