{
  "type": "Feature",
  "properties": {
    "iso:country":"US",
    "sg:address":"221 W Park Ave",
    "sg:city":"Union",
    "sg:classifiers":[
        {
            "category":"Building & Trades",
            "subcategory":"Plumbing",
            "type":"Services"
        }
    ],
    "sg:phone":"+1 636 742 3614",
    "sg:postcode":"63084",
    "sg:province":"MO",
    "sg:tags":[
        "plumber",
        "industrial",
        "contractors-commercial"
    ],
    "wof:name":"Tobben Contracting Plumbing",
    "wof:placetype":"venue"
},
  "geometry": {"coordinates":[-91.012034,38.450508],"type":"Point"}
}