{
  "type": "Feature",
  "properties": {
    "iso:country":"US",
    "sg:address":"1234 Cedar Ridge Dr",
    "sg:city":"St Louis",
    "sg:classifiers":[
        {
            "category":"Wholesale",
            "subcategory":"Machinery & Supplies",
            "type":"Manufacturing & Wholesale Goods"
        }
    ],
    "sg:phone":"+1 314 962 7280",
    "sg:postcode":"63146",
    "sg:province":"MO",
    "sg:tags":[
        "janitor"
    ],
    "wof:name":"Midwest Supply Co",
    "wof:placetype":"venue"
},
  "geometry": {"coordinates":[-90.47140899999999,38.684057],"type":"Point"}
}