{
  "type": "Feature",
  "properties": {
    "iso:country":"US",
    "sg:address":"970 W San Martin St",
    "sg:city":"Bolivar",
    "sg:classifiers":[
        {
            "category":"Deli",
            "type":"Food & Drink"
        },
        {
            "category":"Restaurant",
            "type":"Food & Drink"
        }
    ],
    "sg:phone":"+1 417 326 3354",
    "sg:postcode":"65613",
    "sg:province":"MO",
    "sg:tags":[
        "delicatessen"
    ],
    "wof:name":"Moms Deli",
    "wof:placetype":"venue"
},
  "geometry": {"coordinates":[-93.421396,37.593643],"type":"Point"}
}