{
  "type": "Feature",
  "properties": {
    "iso:country":"US",
    "sg:address":"307 E Kearney St",
    "sg:city":"Springfield",
    "sg:classifiers":[
        {
            "category":"Autos & Motor Vehicles",
            "subcategory":"Auto Supplies",
            "type":"Retail Goods"
        }
    ],
    "sg:phone":"+1 417 869 7394",
    "sg:postcode":"65803",
    "sg:province":"MO",
    "sg:tags":[
        "tire"
    ],
    "wof:name":"Mitchem Tire & Wheel",
    "wof:placetype":"venue"
},
  "geometry": {"coordinates":[-93.28875499999999,37.240574],"type":"Point"}
}