{
  "type": "Feature",
  "properties": {
    "iso:country":"US",
    "sg:address":"613 Main St",
    "sg:city":"Mindenmines",
    "sg:classifiers":[
        {
            "category":"Government",
            "subcategory":"Office",
            "type":"Public Place"
        }
    ],
    "sg:phone":"+1 417 842 3216",
    "sg:postcode":"64769",
    "sg:province":"MO",
    "sg:tags":[
        "city"
    ],
    "wof:name":"Mindenmines City Hall",
    "wof:placetype":"venue"
},
  "geometry": {"coordinates":[-94.58901299999999,37.474215],"type":"Point"}
}