{
  "type": "Feature",
  "properties": {
    "iso:country":"US",
    "sg:address":"7745 Carondelet Ave",
    "sg:city":"St Louis",
    "sg:classifiers":[
        {
            "category":"Professional",
            "subcategory":"Advertising",
            "type":"Services"
        }
    ],
    "sg:phone":"+1 314 721 0525",
    "sg:postcode":"63105",
    "sg:province":"MO",
    "sg:tags":[
        "counselor"
    ],
    "wof:name":"IMAP",
    "wof:placetype":"venue"
},
  "geometry": {"coordinates":[-90.335955,38.648778],"type":"Point"}
}