{
  "type": "Feature",
  "properties": {
    "iso:country":"US",
    "sg:address":"2290 N Farm Rd 105",
    "sg:city":"Springfield",
    "sg:classifiers":[
        {
            "category":"Home & Garden",
            "subcategory":"Furniture",
            "type":"Retail Goods"
        }
    ],
    "sg:phone":"+1 417 861 8522",
    "sg:postcode":"65802",
    "sg:province":"MO",
    "wof:name":"General Merchandise and Stuff",
    "wof:placetype":"venue"
},
  "geometry": {"coordinates":[-93.410371,37.240909],"type":"Point"}
}