{
  "type": "Feature",
  "properties": {
    "iso:country":"US",
    "sg:address":"3802 S Crysler Ave",
    "sg:city":"Independence",
    "sg:classifiers":[
        {
            "category":"Home & Garden",
            "subcategory":"Carpets & Floor Coverings",
            "type":"Retail Goods"
        }
    ],
    "sg:phone":"+1 816 254 4420",
    "sg:postcode":"64055",
    "sg:province":"MO",
    "wof:name":"KB Floor Specialties",
    "wof:placetype":"venue"
},
  "geometry": {"coordinates":[-94.433606,39.051475],"type":"Point"}
}