{
  "type": "Feature",
  "properties": {
    "iso:country":"US",
    "sg:address":"1429 S Munn Ave",
    "sg:city":"Maryville",
    "sg:classifiers":[
        {
            "category":"Education",
            "subcategory":"School",
            "type":"Public Place"
        }
    ],
    "sg:phone":"+1 660 562 4111",
    "sg:postcode":"64468",
    "sg:province":"MO",
    "wof:name":"Special Education Co-Op",
    "wof:placetype":"venue"
},
  "geometry": {"coordinates":[-94.883377,40.331945],"type":"Point"}
}