{
  "type": "Feature",
  "properties": {
    "iso:country":"US",
    "sg:address":"9203 E 82 St",
    "sg:city":"Kansas City",
    "sg:classifiers":[
        {
            "category":"Professional",
            "subcategory":"Accounting & Tax Preparation",
            "type":"Services"
        }
    ],
    "sg:phone":"+1 816 358 8285",
    "sg:postcode":"64138",
    "sg:province":"MO",
    "wof:name":"Stribling Financial Group Inc",
    "wof:placetype":"venue"
},
  "geometry": {"coordinates":[-94.473904,38.974489],"type":"Point"}
}