{
  "type": "Feature",
  "properties": {
    "iso:country":"US",
    "sg:address":"2017 Chouteau Ave",
    "sg:city":"Saint Louis",
    "sg:classifiers":[
        {
            "category":"Food & Beverages",
            "subcategory":"Groceries & Convenience Stores",
            "type":"Retail Goods"
        }
    ],
    "sg:phone":"+1 314 241 7799",
    "sg:postcode":"63103",
    "sg:province":"MO",
    "sg:website":"www.grandpetitemarket.com",
    "wof:name":"Grand Petite Market",
    "wof:placetype":"venue"
},
  "geometry": {"coordinates":[-90.212937,38.621234],"type":"Point"}
}