{
  "type": "Feature",
  "properties": {
    "iso:country":"US",
    "sg:address":"108 N Main St",
    "sg:city":"De Soto",
    "sg:classifiers":[
        {
            "category":"Shopping",
            "subcategory":"Florist",
            "type":"Retail Goods"
        }
    ],
    "sg:phone":"+1 636 586 4800",
    "sg:postcode":"63020",
    "sg:province":"MO",
    "wof:name":"All About Flowers",
    "wof:placetype":"venue"
},
  "geometry": {"coordinates":[-90.55348499999999,38.139854],"type":"Point"}
}