{
  "type": "Feature",
  "properties": {
    "iso:country":"US",
    "sg:address":"4613 Independence Ave",
    "sg:city":"Kansas City",
    "sg:classifiers":[
        {
            "category":"Banks & Credit Unions",
            "subcategory":"Bank",
            "type":"Services"
        }
    ],
    "sg:phone":"+1 816 241 5348",
    "sg:postcode":"64124",
    "sg:province":"MO",
    "sg:tags":[
        "loan"
    ],
    "wof:name":"Cash 2U Payday Loans",
    "wof:placetype":"venue"
},
  "geometry": {"coordinates":[-94.52730699999999,39.105428],"type":"Point"}
}