{
  "type": "Feature",
  "properties": {
    "iso:country":"US",
    "sg:address":"713 E Liberty St",
    "sg:city":"Farmington",
    "sg:classifiers":[
        {
            "category":"Real Estate",
            "subcategory":"Real Estate Operator",
            "type":"Services"
        }
    ],
    "sg:phone":"+1 573 756 5145",
    "sg:postcode":"63640",
    "sg:province":"MO",
    "sg:tags":[
        "apartment"
    ],
    "wof:name":"Bertram Properties",
    "wof:placetype":"venue"
},
  "geometry": {"coordinates":[-90.413049,37.780426],"type":"Point"}
}