{
  "type": "Feature",
  "properties": {
    "iso:country":"US",
    "sg:address":"7750 Clayton Rd",
    "sg:city":"St Louis",
    "sg:classifiers":[
        {
            "category":"Wholesale",
            "subcategory":"Machinery & Supplies",
            "type":"Manufacturing & Wholesale Goods"
        }
    ],
    "sg:phone":"+1 314 644 5400",
    "sg:postcode":"63117",
    "sg:province":"MO",
    "sg:tags":[
        "equipment",
        "bottler"
    ],
    "wof:name":"Anchor Glass Container Corp",
    "wof:placetype":"venue"
},
  "geometry": {"coordinates":[-90.33696500000001,38.637653],"type":"Point"}
}