{
  "type": "Feature",
  "properties": {
    "iso:country":"US",
    "sg:address":"4022 Oak Brook Dr",
    "sg:city":"De Soto",
    "sg:classifiers":[
        {
            "category":"Building & Trades",
            "subcategory":"Cleaning & Sanitation",
            "type":"Services"
        }
    ],
    "sg:phone":"+1 636 337 2235",
    "sg:postcode":"63020",
    "sg:province":"MO",
    "sg:tags":[
        "maintenance"
    ],
    "wof:name":"A Clean Escape",
    "wof:placetype":"venue"
},
  "geometry": {"coordinates":[-90.474422,38.115047],"type":"Point"}
}