{
  "type": "Feature",
  "properties": {
    "iso:country":"US",
    "sg:address":"712 E Booneslick Rd",
    "sg:city":"Warrenton",
    "sg:classifiers":[
        {
            "category":"Building & Trades",
            "subcategory":"Plumbing",
            "type":"Services"
        }
    ],
    "sg:phone":"+1 636 456 4244",
    "sg:postcode":"63383",
    "sg:province":"MO",
    "sg:tags":[
        "plumbing",
        "contractor"
    ],
    "wof:name":"Hoffman Plumbing",
    "wof:placetype":"venue"
},
  "geometry": {"coordinates":[-91.137659,38.81175],"type":"Point"}
}