{
  "type": "Feature",
  "properties": {
    "iso:country":"US",
    "sg:address":"200 W Hunts Rd",
    "sg:city":"Bernie",
    "sg:classifiers":[
        {
            "category":"Health Services",
            "subcategory":"Clinic",
            "type":"Services"
        }
    ],
    "sg:phone":"+1 573 293 6836",
    "sg:postcode":"63822",
    "sg:province":"MO",
    "sg:tags":[
        "maintenance",
        "welfare"
    ],
    "sg:website":"http://www.semohealthnetwork.org",
    "wof:name":"Semo Health Network",
    "wof:placetype":"venue"
},
  "geometry": {"coordinates":[-89.968063,36.677021],"type":"Point"}
}