{
  "type": "Feature",
  "properties": {
    "iso:country":"US",
    "sg:address":"201 E Lexington St",
    "sg:city":"Richmond",
    "sg:classifiers":[
        {
            "category":"Personal",
            "subcategory":"Beauty Salon",
            "type":"Services"
        }
    ],
    "sg:phone":"+1 816 776 5544",
    "sg:postcode":"64085",
    "sg:province":"MO",
    "sg:tags":[
        "hair",
        "stylist"
    ],
    "wof:name":"House of Hair",
    "wof:placetype":"venue"
},
  "geometry": {"coordinates":[-93.975151,39.276909],"type":"Point"}
}