{
  "type": "Feature",
  "properties": {
    "iso:country":"US",
    "sg:address":"713 Kathryn St",
    "sg:city":"Nixa",
    "sg:classifiers":[
        {
            "category":"Wholesale",
            "subcategory":"Hardware",
            "type":"Manufacturing & Wholesale Goods"
        },
        {
            "category":"Retail",
            "subcategory":"Repair Shop",
            "type":"Services"
        }
    ],
    "sg:phone":"+1 417 724 1411",
    "sg:postcode":"65714",
    "sg:province":"MO",
    "sg:tags":[
        "refrigeration",
        "related"
    ],
    "wof:name":"Chilly Willee of Missouri",
    "wof:placetype":"venue"
},
  "geometry": {"coordinates":[-93.308572,37.060278],"type":"Point"}
}