{
  "type": "Feature",
  "properties": {
    "iso:country":"US",
    "sg:address":"4345 E Ravens Ridge Dr",
    "sg:city":"Columbia",
    "sg:classifiers":[
        {
            "category":"Building & Trades",
            "subcategory":"Construction",
            "type":"Services"
        }
    ],
    "sg:phone":"+1 573 875 6755",
    "sg:postcode":"65201",
    "sg:province":"MO",
    "sg:tags":[
        "house"
    ],
    "wof:name":"Wesbury Construction Co Inc",
    "wof:placetype":"venue"
},
  "geometry": {"coordinates":[-92.27115999999999,38.921013],"type":"Point"}
}