{
  "type": "Feature",
  "properties": {
    "iso:country":"US",
    "sg:address":"610 S Woodbine Rd",
    "sg:city":"Saint Joseph",
    "sg:classifiers":[
        {
            "category":"Insurance",
            "subcategory":"Insurance Agent",
            "type":"Services"
        }
    ],
    "sg:phone":"+1 816 279 2985",
    "sg:postcode":"64507",
    "sg:province":"MO",
    "wof:name":"Bachannas County Farm Bureau",
    "wof:placetype":"venue"
},
  "geometry": {"coordinates":[-94.79669699999999,39.761946],"type":"Point"}
}