{
  "type": "Feature",
  "properties": {
    "iso:country":"US",
    "sg:address":"1227 Hudson Hills Dr",
    "sg:city":"Saint Louis",
    "sg:classifiers":[
        {
            "category":"Professional",
            "subcategory":"Management & Consulting",
            "type":"Services"
        }
    ],
    "sg:phone":"+1 314 521 2267",
    "sg:postcode":"63135",
    "sg:province":"MO",
    "sg:tags":[
        "business"
    ],
    "wof:name":"Adams Consulting Group",
    "wof:placetype":"venue"
},
  "geometry": {"coordinates":[-90.28245800000001,38.760951],"type":"Point"}
}