{
  "type": "Feature",
  "properties": {
    "iso:country":"US",
    "sg:address":"8727 Dunn Rd",
    "sg:city":"Hazelwood",
    "sg:classifiers":[
        {
            "category":"Organizations",
            "subcategory":"Religious Organization",
            "type":"Services"
        }
    ],
    "sg:phone":"+1 314 830 2803",
    "sg:postcode":"63042",
    "sg:province":"MO",
    "sg:tags":[
        "place",
        "worship",
        "church"
    ],
    "sg:website":"http://spiritandtruthchurch.com",
    "wof:name":"Spirit & Truth Church",
    "wof:placetype":"venue"
},
  "geometry": {"coordinates":[-90.338081,38.776243],"type":"Point"}
}