{
  "type": "Feature",
  "properties": {
    "iso:country":"US",
    "sg:address":"1473 Shelby 118",
    "sg:city":"Leonard",
    "sg:classifiers":[
        {
            "category":"Farming",
            "subcategory":"Livestock Farm",
            "type":"Manufacturing & Wholesale Goods"
        },
        {
            "category":"Farming",
            "subcategory":"Farm",
            "type":"Manufacturing & Wholesale Goods"
        }
    ],
    "sg:phone":"+1 660 762 4664",
    "sg:postcode":"63451",
    "sg:province":"MO",
    "sg:tags":[
        "feeding"
    ],
    "wof:name":"Russel Miles",
    "wof:placetype":"venue"
},
  "geometry": {"coordinates":[-92.19438599999999,39.92523],"type":"Point"}
}