{
  "type": "Feature",
  "properties": {
    "iso:country":"US",
    "sg:address":"3100 Corporate Exchange Ct",
    "sg:city":"Bridgeton",
    "sg:classifiers":[
        {
            "category":"Manufacturing",
            "subcategory":"Chemicals & Compounds",
            "type":"Manufacturing & Wholesale Goods"
        }
    ],
    "sg:phone":"+1 314 645 6600",
    "sg:postcode":"63044",
    "sg:province":"MO",
    "sg:tags":[
        "preparation",
        "pharmaceutical",
        "mfg"
    ],
    "wof:name":"K V Logistics",
    "wof:placetype":"venue"
},
  "geometry": {"coordinates":[-90.44376800000001,38.759204],"type":"Point"}
}