{
  "type": "Feature",
  "properties": {
    "iso:country":"US",
    "sg:address":"2829 Howard St Ofc",
    "sg:city":"Saint Louis",
    "sg:classifiers":[
        {
            "category":"Real Estate",
            "subcategory":"Real Estate Services",
            "type":"Services"
        }
    ],
    "sg:phone":"+1 314 534 0344",
    "sg:postcode":"63106",
    "sg:province":"MO",
    "sg:tags":[
        "management",
        "property"
    ],
    "wof:name":"Jeff Vander Lou Elderly Housing Package 21",
    "wof:placetype":"venue"
},
  "geometry": {"coordinates":[-90.21639999999999,38.646599],"type":"Point"}
}