{
  "type": "Feature",
  "properties": {
    "iso:country":"US",
    "sg:address":"1220 S Main St",
    "sg:city":"Joplin",
    "sg:classifiers":[
        {
            "category":"Personal",
            "subcategory":"Beauty Salon",
            "type":"Services"
        }
    ],
    "sg:phone":"+1 417 621 0322",
    "sg:postcode":"64801",
    "sg:province":"MO",
    "wof:name":"Chica Bella Salon & Day Spa",
    "wof:placetype":"venue"
},
  "geometry": {"coordinates":[-94.513859,37.077572],"type":"Point"}
}