{
  "type": "Feature",
  "properties": {
    "iso:country":"US",
    "sg:address":"3701 S Ponca Dr",
    "sg:city":"Independence",
    "sg:classifiers":[
        {
            "category":"Bars & Pubs",
            "type":"Food & Drink"
        },
        {
            "category":"Shopping",
            "subcategory":"Party Supplies",
            "type":"Retail Goods"
        },
        {
            "category":"Sports & Exercise",
            "subcategory":"Bowling",
            "type":"Entertainment"
        }
    ],
    "sg:phone":"+1 816 795 8630",
    "sg:postcode":"64057",
    "sg:province":"MO",
    "sg:tags":[
        "children's",
        "planning"
    ],
    "sg:website":"http://www.amf.com",
    "wof:name":"AMF Independence Lanes",
    "wof:placetype":"venue"
},
  "geometry": {"coordinates":[-94.363579,39.051851],"type":"Point"}
}