{
  "type": "Feature",
  "properties": {
    "iso:country":"US",
    "sg:address":"2738 N. Hwy 67",
    "sg:city":"Florissant",
    "sg:classifiers":[
        {
            "category":"Restaurant",
            "type":"Food & Drink"
        }
    ],
    "sg:menulink":"http://www.allmenus.com/mo/florissant/34126-no-1-china-restaurant/menu/",
    "sg:phone":"+1 314 830 3330",
    "sg:postcode":"63033",
    "sg:province":"MO",
    "sg:tags":[
        "asian",
        "chinese"
    ],
    "wof:name":"No. 1 China Restaurant",
    "wof:placetype":"venue"
},
  "geometry": {"coordinates":[-90.30371599999999,38.80665],"type":"Point"}
}