{
  "type": "Feature",
  "properties": {
    "iso:country":"US",
    "sg:address":"820 Jb Hunt Ct",
    "sg:city":"Ellisville",
    "sg:classifiers":[
        {
            "category":"Professional",
            "subcategory":"Computer Services",
            "type":"Services"
        }
    ],
    "sg:phone":"+1 636 386 8840",
    "sg:postcode":"63021",
    "sg:province":"MO",
    "sg:tags":[
        "software"
    ],
    "wof:name":"Trend Micro Incorporated",
    "wof:placetype":"venue"
},
  "geometry": {"coordinates":[-90.56535599999999,38.586051],"type":"Point"}
}