{
  "type": "Feature",
  "properties": {
    "iso:country":"US",
    "sg:address":"546 Arbor Meadow Dr",
    "sg:city":"Ballwin",
    "sg:classifiers":[
        {
            "category":"Building & Trades",
            "subcategory":"Construction",
            "type":"Services"
        }
    ],
    "sg:phone":"+1 636 527 9100",
    "sg:postcode":"63021",
    "sg:province":"MO",
    "sg:tags":[
        "home",
        "improvement"
    ],
    "wof:name":"Kitchell Services Ballwin",
    "wof:placetype":"venue"
},
  "geometry": {"coordinates":[-90.552502,38.564598],"type":"Point"}
}