{
  "type": "Feature",
  "properties": {
    "addr:full":"6935 Greenholly Dr Saint Louis MO 63123",
    "addr:housenumber":"6935",
    "addr:postcode":"63123",
    "addr:street":"Greenholly Dr",
    "iso:country":"US",
    "sg:address":"6935 Greenholly Dr",
    "sg:city":"Saint Louis",
    "sg:classifiers":[
        {
            "category":"Farming",
            "subcategory":"Livestock Farm",
            "type":"Manufacturing & Wholesale Goods"
        }
    ],
    "sg:phone":"+1 314 832 1357",
    "sg:postcode":"63123",
    "sg:province":"MO",
    "sg:tags":[
        "beef",
        "feedlot",
        "cattle"
    ],
    "wof:name":"Robert Hughey",
    "wof:placetype":"venue"
},
  "geometry": {"coordinates":[-90.316177,38.578508],"type":"Point"}
}