{
  "type": "Feature",
  "properties": {
    "iso:country":"US",
    "sg:address":"2134 S Hillcrest Ave",
    "sg:city":"Springfield",
    "sg:classifiers":[
        {
            "category":"Home & Garden",
            "subcategory":"Carpets & Floor Coverings",
            "type":"Retail Goods"
        }
    ],
    "sg:phone":"+1 417 889 6254",
    "sg:postcode":"65807",
    "sg:province":"MO",
    "sg:tags":[
        "vinyl"
    ],
    "wof:name":"Camtech RC Vinyl",
    "wof:placetype":"venue"
},
  "geometry": {"coordinates":[-93.336755,37.177672],"type":"Point"}
}