{
  "type": "Feature",
  "properties": {
    "iso:country":"US",
    "sg:address":"1000 State Hwy 32",
    "sg:city":"Salem",
    "sg:classifiers":[
        {
            "category":"Retail",
            "subcategory":"Funeral Services",
            "type":"Services"
        }
    ],
    "sg:phone":"+1 573 729 5555",
    "sg:postcode":"65560",
    "sg:province":"MO",
    "sg:tags":[
        "director"
    ],
    "wof:name":"Wilson Mortuary",
    "wof:placetype":"venue"
},
  "geometry": {"coordinates":[-91.546032,37.636087],"type":"Point"}
}