{
  "type": "Feature",
  "properties": {
    "iso:country":"US",
    "sg:address":"500 Jefferson St",
    "sg:city":"Fulton",
    "sg:classifiers":[
        {
            "category":"Insurance",
            "subcategory":"Insurance Agent",
            "type":"Services"
        },
        {
            "category":"Insurance",
            "subcategory":"Hazard Insurance",
            "type":"Services"
        },
        {
            "category":"Insurance",
            "subcategory":"Title Insurance",
            "type":"Services"
        }
    ],
    "sg:phone":"+1 573 642 6823",
    "sg:postcode":"65251",
    "sg:province":"MO",
    "sg:tags":[
        "auto",
        "homeowner"
    ],
    "sg:website":"http://apps.amfam.com/agentlocator/?sourceid=yp3",
    "wof:name":"American Family Insurance- Krystal Steggemann",
    "wof:placetype":"venue"
},
  "geometry": {"coordinates":[-91.950104,38.84745],"type":"Point"}
}