{
  "type": "Feature",
  "properties": {
    "iso:country":"US",
    "sg:address":"691 SE 671 Rd",
    "sg:city":"Knob Noster",
    "sg:classifiers":[
        {
            "category":"Education",
            "subcategory":"Special Training",
            "type":"Public Place"
        }
    ],
    "sg:phone":"+1 660 747 9432",
    "sg:postcode":"65336",
    "sg:province":"MO",
    "sg:tags":[
        "instruction",
        "driving"
    ],
    "wof:name":"Wendell Brandes Driving Trnng",
    "wof:placetype":"venue"
},
  "geometry": {"coordinates":[-93.622856,38.657208],"type":"Point"}
}