{
  "type": "Feature",
  "properties": {
    "iso:country":"US",
    "sg:address":"9890 Hwy 185",
    "sg:city":"Sullivan",
    "sg:classifiers":[
        {
            "category":"Organizations",
            "subcategory":"Religious Organization",
            "type":"Services"
        }
    ],
    "sg:phone":"+1 573 860 4847",
    "sg:postcode":"63080",
    "sg:province":"MO",
    "wof:name":"Cave Springs Baptist Church",
    "wof:placetype":"venue"
},
  "geometry": {"coordinates":[-91.22307600000001,38.27847],"type":"Point"}
}