{
  "type": "Feature",
  "properties": {
    "iso:country":"US",
    "sg:address":"24632 Hollow Rd",
    "sg:city":"Purdin",
    "sg:classifiers":[
        {
            "category":"Farming",
            "subcategory":"Farm",
            "type":"Manufacturing & Wholesale Goods"
        }
    ],
    "sg:phone":"+1 660 244 3622",
    "sg:postcode":"64674",
    "sg:province":"MO",
    "sg:tags":[
        "crop",
        "general"
    ],
    "wof:name":"Woodside Lindel",
    "wof:placetype":"venue"
},
  "geometry": {"coordinates":[-93.083783,39.943619],"type":"Point"}
}