{
  "type": "Feature",
  "properties": {
    "iso:country":"US",
    "sg:address":"843 State Hwy 13",
    "sg:city":"Leeton",
    "sg:classifiers":[
        {
            "category":"Wholesale",
            "subcategory":"Machinery & Supplies",
            "type":"Manufacturing & Wholesale Goods"
        },
        {
            "category":"Shopping",
            "type":"Retail Goods"
        }
    ],
    "sg:phone":"+1 660 653 4727",
    "sg:postcode":"64761",
    "sg:province":"MO",
    "sg:tags":[
        "farm",
        "equipment",
        "tractor",
        "mower"
    ],
    "wof:name":"C & L Auto Sales",
    "wof:placetype":"venue"
},
  "geometry": {"coordinates":[-93.739696,38.633001],"type":"Point"}
}