{
  "type": "Feature",
  "properties": {
    "iso:country":"US",
    "sg:address":"126 Valley Rd",
    "sg:city":"St Louis",
    "sg:classifiers":[
        {
            "category":"Professional",
            "type":"Services"
        }
    ],
    "sg:phone":"+1 314 962 1600",
    "sg:postcode":"63119",
    "sg:province":"MO",
    "sg:tags":[
        "establishment"
    ],
    "wof:name":"Technology Advantage",
    "wof:placetype":"venue"
},
  "geometry": {"coordinates":[-90.354401,38.588835],"type":"Point"}
}