{
  "type": "Feature",
  "properties": {
    "iso:country":"US",
    "sg:address":"11728 Hidden Lake Dr",
    "sg:city":"St Louis",
    "sg:classifiers":[
        {
            "category":"Health Services",
            "subcategory":"Nursing And Care Facility",
            "type":"Services"
        }
    ],
    "sg:phone":"+1 314 355 8833",
    "sg:postcode":"63138",
    "sg:province":"MO",
    "sg:tags":[
        "home",
        "retirement",
        "community"
    ],
    "sg:website":"www.lssmo.org",
    "wof:name":"Hidden Lake",
    "wof:placetype":"venue"
},
  "geometry": {"coordinates":[-90.225904,38.783543],"type":"Point"}
}