{
  "type": "Feature",
  "properties": {
    "iso:country":"US",
    "sg:address":"8001 Natural Bridge Rd",
    "sg:city":"St Louis",
    "sg:classifiers":[
        {
            "category":"Education",
            "subcategory":"Special Training",
            "type":"Public Place"
        },
        {
            "category":"Health Services",
            "subcategory":"Health Practitioner",
            "type":"Services"
        }
    ],
    "sg:phone":"+1 314 516 5000",
    "sg:postcode":"63121",
    "sg:province":"MO",
    "sg:tags":[
        "information",
        "school",
        "college"
    ],
    "sg:website":"www.umslbookstore.com",
    "wof:name":"University Missouri St Louis",
    "wof:placetype":"venue"
},
  "geometry": {"coordinates":[-90.313762,38.706924],"type":"Point"}
}