{
  "type": "Feature",
  "properties": {
    "iso:country":"US",
    "sg:address":"6501 Weldon Springs Rd",
    "sg:city":"Saint Charles",
    "sg:classifiers":[
        {
            "category":"Recreation",
            "type":"Entertainment"
        }
    ],
    "sg:phone":"+1 636 926 8873",
    "sg:postcode":"63304",
    "sg:province":"MO",
    "wof:name":"Persimmon Woods Gold CLB Maint",
    "wof:placetype":"venue"
},
  "geometry": {"coordinates":[-90.69329,38.720953],"type":"Point"}
}