{
  "type": "Feature",
  "properties": {
    "iso:country":"US",
    "sg:address":"112 N Huffman Ave",
    "sg:city":"Strafford",
    "sg:classifiers":[
        {
            "category":"Professional",
            "subcategory":"Computer Services",
            "type":"Services"
        }
    ],
    "sg:phone":"+1 417 736 3406",
    "sg:postcode":"65757",
    "sg:province":"MO",
    "sg:tags":[
        "consultant",
        "designer",
        "system",
        "related"
    ],
    "wof:name":"Computer Imaging",
    "wof:placetype":"venue"
},
  "geometry": {"coordinates":[-93.13009,37.271035],"type":"Point"}
}