{
  "type": "Feature",
  "properties": {
    "iso:country":"US",
    "sg:address":"309 N Main St",
    "sg:city":"Chamois",
    "sg:classifiers":[
        {
            "category":"Health Services",
            "subcategory":"Doctor",
            "type":"Services"
        }
    ],
    "sg:phone":"+1 573 763 5400",
    "sg:postcode":"65024",
    "sg:province":"MO",
    "sg:tags":[
        "physician",
        "surgeon"
    ],
    "wof:name":"Family Medical Ctr",
    "wof:placetype":"venue"
},
  "geometry": {"coordinates":[-91.76976000000001,38.677828],"type":"Point"}
}