{
  "type": "Feature",
  "properties": {
    "iso:country":"US",
    "sg:address":"425 W Phipps St",
    "sg:city":"La Plata",
    "sg:classifiers":[
        {
            "category":"Social Services",
            "subcategory":"Child Care",
            "type":"Services"
        }
    ],
    "sg:phone":"+1 660 332 7890",
    "sg:postcode":"63549",
    "sg:province":"MO",
    "sg:tags":[
        "day"
    ],
    "wof:name":"Raymers Day Care",
    "wof:placetype":"venue"
},
  "geometry": {"coordinates":[-92.49698100000001,40.02433],"type":"Point"}
}