{
  "type": "Feature",
  "properties": {
    "iso:country":"US",
    "sg:address":"362 Brookes Dr",
    "sg:city":"Hazelwood",
    "sg:classifiers":[
        {
            "category":"Organizations",
            "subcategory":"Religious Organization",
            "type":"Services"
        }
    ],
    "sg:phone":"+1 314 731 4604",
    "sg:postcode":"63042",
    "sg:province":"MO",
    "wof:name":"Lampstand Ministry",
    "wof:placetype":"venue"
},
  "geometry": {"coordinates":[-90.36202299999999,38.777348],"type":"Point"}
}