{
  "type": "Feature",
  "properties": {
    "iso:country":"US",
    "sg:address":"4444 State Hwy F",
    "sg:city":"Cuba",
    "sg:classifiers":[
        {
            "category":"Farming",
            "subcategory":"Livestock Farm",
            "type":"Manufacturing & Wholesale Goods"
        }
    ],
    "sg:phone":"+1 573 885 7235",
    "sg:postcode":"65453",
    "sg:province":"MO",
    "sg:tags":[
        "beef",
        "feedlot",
        "cattle"
    ],
    "wof:name":"Jerome Cunnigham Farm",
    "wof:placetype":"venue"
},
  "geometry": {"coordinates":[-91.49829,38.09636],"type":"Point"}
}