{
  "type": "Feature",
  "properties": {
    "iso:country":"US",
    "sg:address":"1 Midwest Dr",
    "sg:city":"Pacific",
    "sg:classifiers":[
        {
            "category":"Retail",
            "subcategory":"Car Wash",
            "type":"Services"
        }
    ],
    "sg:phone":"+1 636 271 6210",
    "sg:postcode":"63069",
    "sg:province":"MO",
    "sg:website":"http://www.wallisco.com",
    "wof:name":"Great River Wash",
    "wof:placetype":"venue"
},
  "geometry": {"coordinates":[-90.757294,38.459],"type":"Point"}
}