{
  "type": "Feature",
  "properties": {
    "iso:country":"US",
    "sg:address":"6633 Olive Blvd",
    "sg:city":"Saint Louis",
    "sg:classifiers":[
        {
            "category":"Building & Trades",
            "subcategory":"Construction",
            "type":"Services"
        }
    ],
    "sg:phone":"+1 314 721 8100",
    "sg:postcode":"63130",
    "sg:province":"MO",
    "sg:tags":[
        "contractor"
    ],
    "wof:name":"Muccigrosso Construction Inc",
    "wof:placetype":"venue"
},
  "geometry": {"coordinates":[-90.305801,38.6628],"type":"Point"}
}