{
  "type": "Feature",
  "properties": {
    "iso:country":"US",
    "sg:address":"200 E Commercial St",
    "sg:city":"Charleston",
    "sg:classifiers":[
        {
            "category":"Shopping",
            "type":"Retail Goods"
        },
        {
            "category":"Museum",
            "type":"Entertainment"
        }
    ],
    "sg:phone":"+1 573 683 4503",
    "sg:postcode":"63834",
    "sg:province":"MO",
    "sg:tags":[
        "art",
        "gallery",
        "dealer"
    ],
    "wof:name":"Red Geranium Studio & Gallery",
    "wof:placetype":"venue"
},
  "geometry": {"coordinates":[-89.34927999999999,36.923381],"type":"Point"}
}