{
  "type": "Feature",
  "properties": {
    "iso:country":"US",
    "sg:address":"271 Clarkson Executive Park",
    "sg:city":"Ellisville",
    "sg:classifiers":[
        {
            "category":"Professional",
            "subcategory":"Advertising",
            "type":"Services"
        }
    ],
    "sg:phone":"+1 636 386 8300",
    "sg:postcode":"63011",
    "sg:province":"MO",
    "sg:tags":[
        "guide"
    ],
    "wof:name":"Thomas Register LLC",
    "wof:placetype":"venue"
},
  "geometry": {"coordinates":[-90.586133,38.600283],"type":"Point"}
}