{
  "type": "Feature",
  "properties": {
    "iso:country":"US",
    "sg:address":"1127 S Weaver Ave",
    "sg:city":"Springfield",
    "sg:classifiers":[
        {
            "category":"Professional",
            "subcategory":"Computer Services",
            "type":"Services"
        }
    ],
    "sg:phone":"+1 417 865 1889",
    "sg:postcode":"65807",
    "sg:province":"MO",
    "sg:tags":[
        "design",
        "system"
    ],
    "wof:name":"Antimedia Enterprises",
    "wof:placetype":"venue"
},
  "geometry": {"coordinates":[-93.30472399999999,37.195544],"type":"Point"}
}