{
  "type": "Feature",
  "properties": {
    "addr:full":"9846 Watson Rd Saint Louis MO 63126",
    "addr:housenumber":"9846",
    "addr:postcode":"63126",
    "addr:street":"Watson Rd",
    "iso:country":"US",
    "sg:address":"9846 Watson Rd",
    "sg:city":"Saint Louis",
    "sg:classifiers":[
        {
            "category":"Bakery",
            "type":"Food & Drink"
        }
    ],
    "sg:menulink":"http://www.allmenus.com/mo/gravois/238003-sweet-tomatoes/menu/",
    "sg:phone":"+1 314 966 3882",
    "sg:postcode":"63126",
    "sg:province":"MO",
    "sg:tags":[
        "soup",
        "american",
        "pastry",
        "salad"
    ],
    "wof:name":"Sweet Tomatoes",
    "wof:placetype":"venue"
},
  "geometry": {"coordinates":[-90.391127,38.555885],"type":"Point"}
}