{
  "type": "Feature",
  "properties": {
    "iso:country":"US",
    "sg:address":"7447 Dale Ave",
    "sg:city":"Richmond Heights",
    "sg:classifiers":[
        {
            "category":"Government",
            "subcategory":"Fire Station",
            "type":"Public Place"
        }
    ],
    "sg:phone":"+1 314 645 8800",
    "sg:postcode":"63117",
    "sg:province":"MO",
    "sg:tags":[
        "department"
    ],
    "sg:website":"www.richmondheights.org",
    "wof:name":"Richmond Heights Fire Dept",
    "wof:placetype":"venue"
},
  "geometry": {"coordinates":[-90.319303,38.62803],"type":"Point"}
}