{
  "type": "Feature",
  "properties": {
    "iso:country":"US",
    "sg:address":"601 US Hwy 61",
    "sg:city":"New Madrid",
    "sg:classifiers":[
        {
            "category":"Banks & Credit Unions",
            "subcategory":"Bank",
            "type":"Services"
        }
    ],
    "sg:phone":"+1 573 748 2220",
    "sg:postcode":"63869",
    "sg:province":"MO",
    "wof:name":"Union Planters Bank",
    "wof:placetype":"venue"
},
  "geometry": {"coordinates":[-89.54216599999999,36.59147],"type":"Point"}
}