{
  "type": "Feature",
  "properties": {
    "iso:country":"US",
    "sg:address":"137 St Robert Blvd",
    "sg:city":"Waynesville",
    "sg:classifiers":[
        {
            "category":"Organizations",
            "subcategory":"Professional Association",
            "type":"Services"
        }
    ],
    "sg:phone":"+1 573 336 5121",
    "sg:postcode":"65584",
    "sg:province":"MO",
    "sg:tags":[
        "chamber",
        "commerce"
    ],
    "wof:name":"Robert Waynesville-Saint Area",
    "wof:placetype":"venue"
},
  "geometry": {"coordinates":[-92.14407799999999,37.826667],"type":"Point"}
}