{
  "type": "Feature",
  "properties": {
    "iso:country":"US",
    "sg:address":"4911 Barnes Hospital Plz",
    "sg:city":"St Louis",
    "sg:classifiers":[
        {
            "category":"Health Services",
            "subcategory":"Doctor",
            "type":"Services"
        }
    ],
    "sg:phone":"+1 314 286 2400",
    "sg:postcode":"63110",
    "sg:province":"MO",
    "sg:tags":[
        "physician",
        "surgeon"
    ],
    "wof:name":"Washington University Medical",
    "wof:placetype":"venue"
},
  "geometry": {"coordinates":[-90.26588099999999,38.635229],"type":"Point"}
}