{
  "type": "Feature",
  "properties": {
    "iso:country":"US",
    "sg:address":"1304 State St",
    "sg:city":"Charleston",
    "sg:classifiers":[
        {
            "category":"Building & Trades",
            "subcategory":"Electrical",
            "type":"Services"
        }
    ],
    "sg:phone":"+1 573 683 3490",
    "sg:postcode":"63834",
    "sg:province":"MO",
    "sg:tags":[
        "electrical",
        "contractor"
    ],
    "wof:name":"Rolwing Electric Company",
    "wof:placetype":"venue"
},
  "geometry": {"coordinates":[-89.329195,36.925144],"type":"Point"}
}