{
  "type": "Feature",
  "properties": {
    "iso:country":"US",
    "sg:address":"1715 W Worley St",
    "sg:city":"Columbia",
    "sg:classifiers":[
        {
            "category":"Health Services",
            "subcategory":"Health Practitioner",
            "type":"Services"
        }
    ],
    "sg:phone":"+1 573 446 1614",
    "sg:postcode":"65203",
    "sg:province":"MO",
    "sg:tags":[
        "psychologist"
    ],
    "wof:name":"Columbia Psychological Svcs",
    "wof:placetype":"venue"
},
  "geometry": {"coordinates":[-92.3635,38.96042],"type":"Point"}
}