{
  "type": "Feature",
  "properties": {
    "iso:country":"US",
    "sg:address":"4641 Morganford Rd",
    "sg:city":"St Louis",
    "sg:classifiers":[
        {
            "category":"Building & Trades",
            "subcategory":"Cleaning & Sanitation",
            "type":"Services"
        }
    ],
    "sg:phone":"+1 314 832 4817",
    "sg:postcode":"63116",
    "sg:province":"MO",
    "sg:tags":[
        "janitor"
    ],
    "wof:name":"Compass Cleaning Svc",
    "wof:placetype":"venue"
},
  "geometry": {"coordinates":[-90.266368,38.584024],"type":"Point"}
}