{
  "type": "Feature",
  "properties": {
    "iso:country":"US",
    "sg:address":"800 SW Sunset St",
    "sg:city":"Blue Springs",
    "sg:classifiers":[
        {
            "category":"Restaurant",
            "type":"Food & Drink"
        }
    ],
    "sg:phone":"+1 816 224 3130",
    "sg:postcode":"64015",
    "sg:province":"MO",
    "sg:tags":[
        "eating"
    ],
    "wof:name":"El Maguey Mexican Restaurant",
    "wof:placetype":"venue"
},
  "geometry": {"coordinates":[-94.277276,39.008066],"type":"Point"}
}