{
  "type": "Feature",
  "properties": {
    "iso:country":"US",
    "sg:address":"319 S 10th St",
    "sg:city":"Hannibal",
    "sg:classifiers":[
        {
            "category":"Retail",
            "subcategory":"Auto Repair",
            "type":"Services"
        }
    ],
    "sg:phone":"+1 573 248 3115",
    "sg:postcode":"63401",
    "sg:province":"MO",
    "sg:tags":[
        "repairing",
        "automobile"
    ],
    "wof:name":"Danny's Auto Repair Svc",
    "wof:placetype":"venue"
},
  "geometry": {"coordinates":[-91.363497,39.704163],"type":"Point"}
}