{
  "type": "Feature",
  "properties": {
    "iso:country":"US",
    "sg:address":"1161 E Oak Tree Ln",
    "sg:city":"Springfield",
    "sg:classifiers":[
        {
            "category":"Building & Trades",
            "subcategory":"Construction",
            "type":"Services"
        }
    ],
    "sg:phone":"+1 417 881 5174",
    "sg:postcode":"65810",
    "sg:province":"MO",
    "sg:tags":[
        "tile-contractors",
        "contractor"
    ],
    "wof:name":"Adams, Richard Tile",
    "wof:placetype":"venue"
},
  "geometry": {"coordinates":[-93.27980700000001,37.113079],"type":"Point"}
}