{
  "type": "Feature",
  "properties": {
    "iso:country":"US",
    "sg:address":"5516 NW Seminole Dr",
    "sg:city":"Kansas City",
    "sg:classifiers":[
        {
            "category":"Professional",
            "subcategory":"Engineering",
            "type":"Services"
        }
    ],
    "sg:phone":"+1 816 587 3123",
    "sg:postcode":"64152",
    "sg:province":"MO",
    "wof:name":"Engineering Specialties",
    "wof:placetype":"venue"
},
  "geometry": {"coordinates":[-94.70620700000001,39.197281],"type":"Point"}
}