{
  "type": "Feature",
  "properties": {
    "iso:country":"US",
    "sg:address":"2462 Taylor Rd",
    "sg:city":"Grover",
    "sg:classifiers":[
        {
            "category":"Banks & Credit Unions",
            "subcategory":"Bank",
            "type":"Services"
        }
    ],
    "sg:phone":"+1 636 405 2492",
    "sg:postcode":"63040",
    "sg:province":"MO",
    "sg:tags":[
        "saving",
        "commercial"
    ],
    "sg:website":"http://www.firstbanks.com",
    "wof:name":"First Bank",
    "wof:placetype":"venue"
},
  "geometry": {"coordinates":[-90.627477,38.581067],"type":"Point"}
}