{
  "type": "Feature",
  "properties": {
    "iso:country":"US",
    "sg:address":"7645 Wydown Blvd",
    "sg:city":"Saint Louis",
    "sg:classifiers":[
        {
            "category":"Travel",
            "subcategory":"Travel Agent",
            "type":"Entertainment"
        }
    ],
    "sg:phone":"+1 314 863 3026",
    "sg:postcode":"63105",
    "sg:province":"MO",
    "sg:tags":[
        "agency"
    ],
    "wof:name":"Mid West Travel Service Inc",
    "wof:placetype":"venue"
},
  "geometry": {"coordinates":[-90.334746,38.643132],"type":"Point"}
}