{
  "type": "Feature",
  "properties": {
    "iso:country":"US",
    "sg:address":"2310 Co Rd 435",
    "sg:city":"Jackson",
    "sg:classifiers":[
        {
            "category":"Farming",
            "subcategory":"Livestock Farm",
            "type":"Manufacturing & Wholesale Goods"
        }
    ],
    "sg:phone":"+1 573 243 4806",
    "sg:postcode":"63755",
    "sg:province":"MO",
    "sg:tags":[
        "beef",
        "feedlot",
        "cattle"
    ],
    "wof:name":"Roger Schwab",
    "wof:placetype":"venue"
},
  "geometry": {"coordinates":[-89.666506,37.424801],"type":"Point"}
}