{
  "type": "Feature",
  "properties": {
    "iso:country":"US",
    "sg:address":"4790 Executive Centre Pkwy",
    "sg:city":"St Peters",
    "sg:classifiers":[
        {
            "category":"Health Services",
            "subcategory":"Doctor",
            "type":"Services"
        }
    ],
    "sg:phone":"+1 636 939 4224",
    "sg:postcode":"63376",
    "sg:province":"MO",
    "sg:tags":[
        "physician",
        "surgeon"
    ],
    "wof:name":"Sheldon L Davis MD",
    "wof:placetype":"venue"
},
  "geometry": {"coordinates":[-90.610349,38.795742],"type":"Point"}
}