{
  "type": "Feature",
  "properties": {
    "iso:country":"US",
    "sg:address":"6700 Manchester Ave",
    "sg:city":"Saint Louis",
    "sg:classifiers":[
        {
            "category":"Restaurant",
            "type":"Food & Drink"
        }
    ],
    "sg:phone":"+1 314 645 4209",
    "sg:postcode":"63139",
    "sg:province":"MO",
    "sg:tags":[
        "eating"
    ],
    "wof:name":"Kmart Little Ceasars Pizza Stn",
    "wof:placetype":"venue"
},
  "geometry": {"coordinates":[-90.304655,38.617869],"type":"Point"}
}