{
  "type": "Feature",
  "properties": {
    "iso:country":"US",
    "sg:address":"6102 Page Blvd",
    "sg:city":"St Louis",
    "sg:classifiers":[
        {
            "category":"Banks & Credit Unions",
            "subcategory":"Bank",
            "type":"Services"
        }
    ],
    "sg:phone":"+1 314 726 2070",
    "sg:postcode":"63133",
    "sg:province":"MO",
    "sg:tags":[
        "cashing",
        "check"
    ],
    "wof:name":"Money Doctor Inc",
    "wof:placetype":"venue"
},
  "geometry": {"coordinates":[-90.289632,38.670353],"type":"Point"}
}