{
  "type": "Feature",
  "properties": {
    "iso:country":"US",
    "sg:address":"269 Adams Ave",
    "sg:city":"St Robert",
    "sg:classifiers":[
        {
            "category":"Real Estate",
            "subcategory":"Real Estate Operator",
            "type":"Services"
        }
    ],
    "sg:phone":"+1 573 336 3201",
    "sg:postcode":"65584",
    "sg:province":"MO",
    "sg:tags":[
        "mobile",
        "home",
        "site",
        "community"
    ],
    "wof:name":"Tulane Trailer Court",
    "wof:placetype":"venue"
},
  "geometry": {"coordinates":[-92.14247,37.816483],"type":"Point"}
}