{
  "type": "Feature",
  "properties": {
    "iso:country":"US",
    "sg:address":"7344 Manchester Rd",
    "sg:city":"Maplewood",
    "sg:classifiers":[
        {
            "category":"Bars & Pubs",
            "type":"Food & Drink"
        },
        {
            "category":"Restaurant",
            "type":"Food & Drink"
        }
    ],
    "sg:phone":"+1 314 645 4803",
    "sg:postcode":"63143",
    "sg:province":"MO",
    "sg:tags":[
        "tapa",
        "cajun/creole"
    ],
    "sg:website":"boogaloostl.com",
    "wof:name":"Boogaloo",
    "wof:placetype":"venue"
},
  "geometry": {"coordinates":[-90.318288,38.612997],"type":"Point"}
}