{
  "type": "Feature",
  "properties": {
    "iso:country":"US",
    "sg:address":"901 S Main St",
    "sg:city":"Gallatin",
    "sg:classifiers":[
        {
            "category":"Personal",
            "subcategory":"Beauty Salon",
            "type":"Services"
        }
    ],
    "sg:phone":"+1 660 663 3838",
    "sg:postcode":"64640",
    "sg:province":"MO",
    "wof:name":"Tanya's Styling Salon",
    "wof:placetype":"venue"
},
  "geometry": {"coordinates":[-93.961319,39.910562],"type":"Point"}
}