{
  "type": "Feature",
  "properties": {
    "iso:country":"US",
    "sg:address":"6337 E Ridgeline Dr",
    "sg:city":"Springfield",
    "sg:classifiers":[
        {
            "category":"Building & Trades",
            "subcategory":"Construction",
            "type":"Services"
        }
    ],
    "sg:phone":"+1 417 889 6060",
    "sg:postcode":"65809",
    "sg:province":"MO",
    "sg:tags":[
        "house",
        "builder",
        "operative"
    ],
    "wof:name":"Bill Overholt Custom Homes",
    "wof:placetype":"venue"
},
  "geometry": {"coordinates":[-93.15741,37.176721],"type":"Point"}
}