{
  "type": "Feature",
  "properties": {
    "iso:country":"US",
    "sg:address":"2614 Independence Ave",
    "sg:city":"Kansas City",
    "sg:classifiers":[
        {
            "category":"Personal",
            "subcategory":"Beauty Salon",
            "type":"Services"
        }
    ],
    "sg:phone":"+1 816 920 7700",
    "sg:postcode":"64124",
    "sg:province":"MO",
    "sg:tags":[
        "manicuring"
    ],
    "wof:name":"L & N Nails",
    "wof:placetype":"venue"
},
  "geometry": {"coordinates":[-94.55117199999999,39.106383],"type":"Point"}
}