{
  "type": "Feature",
  "properties": {
    "iso:country":"US",
    "sg:address":"613 Congress St",
    "sg:city":"La Belle",
    "sg:classifiers":[
        {
            "category":"Personal",
            "subcategory":"Beauty Salon",
            "type":"Services"
        }
    ],
    "sg:phone":"+1 660 462 3901",
    "sg:postcode":"63447",
    "sg:province":"MO",
    "sg:tags":[
        "shop"
    ],
    "wof:name":"Generations",
    "wof:placetype":"venue"
},
  "geometry": {"coordinates":[-91.91756100000001,40.113038],"type":"Point"}
}