{
  "type": "Feature",
  "properties": {
    "iso:country":"US",
    "sg:address":"577 Bell Ave",
    "sg:city":"Chesterfield",
    "sg:classifiers":[
        {
            "category":"Wholesale",
            "subcategory":"Machinery & Supplies",
            "type":"Manufacturing & Wholesale Goods"
        }
    ],
    "sg:phone":"+1 636 532 7651",
    "sg:postcode":"63005",
    "sg:province":"MO",
    "sg:tags":[
        "tractor"
    ],
    "wof:name":"John Fabick Tractor Co",
    "wof:placetype":"venue"
},
  "geometry": {"coordinates":[-90.648672,38.662971],"type":"Point"}
}