{
  "type": "Feature",
  "properties": {
    "iso:country":"US",
    "sg:address":"20510 E 181st St",
    "sg:city":"Pleasant Hill",
    "sg:classifiers":[
        {
            "category":"Building & Trades",
            "subcategory":"Electrical",
            "type":"Services"
        }
    ],
    "sg:phone":"+1 816 805 5400",
    "sg:postcode":"64080",
    "sg:province":"MO",
    "sg:tags":[
        "electric",
        "contractor"
    ],
    "wof:name":"City Wide Electric",
    "wof:placetype":"venue"
},
  "geometry": {"coordinates":[-94.35139100000001,38.791217],"type":"Point"}
}