{
  "type": "Feature",
  "properties": {
    "iso:country":"US",
    "sg:address":"12537 Audrain Rd 9931",
    "sg:city":"Mexico",
    "sg:classifiers":[
        {
            "category":"Building & Trades",
            "subcategory":"Construction",
            "type":"Services"
        }
    ],
    "sg:phone":"+1 573 582 0096",
    "sg:postcode":"65265",
    "sg:province":"MO",
    "sg:tags":[
        "nonresidential",
        "contractor"
    ],
    "wof:name":"Larry Nichols Construction",
    "wof:placetype":"venue"
},
  "geometry": {"coordinates":[-91.93491299999999,39.153976],"type":"Point"}
}