{
  "type": "Feature",
  "properties": {
    "iso:country":"US",
    "sg:address":"400 US Hwy 60 Bus",
    "sg:city":"Mountain Grove",
    "sg:classifiers":[
        {
            "category":"Mining & Drilling",
            "type":"Manufacturing & Wholesale Goods"
        }
    ],
    "sg:phone":"+1 417 926 4550",
    "sg:postcode":"65711",
    "sg:province":"MO",
    "sg:tags":[
        "oil",
        "gas",
        "producer"
    ],
    "wof:name":"Mountain Grove Oil Co",
    "wof:placetype":"venue"
},
  "geometry": {"coordinates":[-92.268034,37.130927],"type":"Point"}
}