{
  "type": "Feature",
  "properties": {
    "iso:country":"US",
    "sg:address":"3106 Flora Ave",
    "sg:city":"Kansas City",
    "sg:classifiers":[
        {
            "category":"Organizations",
            "subcategory":"Religious Organization",
            "type":"Services"
        }
    ],
    "sg:phone":"+1 816 923 2022",
    "sg:postcode":"64109",
    "sg:province":"MO",
    "sg:tags":[
        "church"
    ],
    "wof:name":"St Vincent De Paul Roman Cthlc",
    "wof:placetype":"venue"
},
  "geometry": {"coordinates":[-94.56571599999999,39.068606],"type":"Point"}
}