{
  "type": "Feature",
  "properties": {
    "iso:country":"US",
    "sg:address":"2113 James Downey Rd",
    "sg:city":"Independence",
    "sg:classifiers":[
        {
            "category":"Building & Trades",
            "subcategory":"Construction",
            "type":"Services"
        }
    ],
    "sg:phone":"+1 816 726 1280",
    "sg:postcode":"64057",
    "sg:province":"MO",
    "sg:tags":[
        "house"
    ],
    "wof:name":"A Plus Remodeling",
    "wof:placetype":"venue"
},
  "geometry": {"coordinates":[-94.376705,39.08266],"type":"Point"}
}