{
  "type": "Feature",
  "properties": {
    "iso:country":"US",
    "sg:address":"1032 Cherokee",
    "sg:city":"Seneca",
    "sg:classifiers":[
        {
            "category":"Restaurant",
            "type":"Food & Drink"
        }
    ],
    "sg:phone":"+1 417 776 8766",
    "sg:postcode":"64865",
    "sg:province":"MO",
    "wof:name":"Richard's Place",
    "wof:placetype":"venue"
},
  "geometry": {"coordinates":[-94.61133700000001,36.842229],"type":"Point"}
}