{
  "type": "Feature",
  "properties": {
    "iso:country":"US",
    "sg:address":"16986 Hwy K",
    "sg:city":"Chula",
    "sg:classifiers":[
        {
            "category":"Restaurant",
            "type":"Food & Drink"
        }
    ],
    "sg:phone":"+1 660 639 2234",
    "sg:postcode":"64635",
    "sg:province":"MO",
    "sg:tags":[
        "club",
        "membership",
        "eating"
    ],
    "wof:name":"Chula Country Club",
    "wof:placetype":"venue"
},
  "geometry": {"coordinates":[-93.466081,39.922288],"type":"Point"}
}