{
  "type": "Feature",
  "properties": {
    "iso:country":"US",
    "sg:address":"3516 NE Lacewood Cir",
    "sg:city":"Lees Summit",
    "sg:classifiers":[
        {
            "category":"Organizations",
            "subcategory":"Community Association",
            "type":"Services"
        }
    ],
    "sg:phone":"+1 816 373 6869",
    "sg:postcode":"64064",
    "sg:province":"MO",
    "sg:tags":[
        "educational"
    ],
    "wof:name":"Johnnie Mc Mehen Wells",
    "wof:placetype":"venue"
},
  "geometry": {"coordinates":[-94.37649399999999,38.978694],"type":"Point"}
}