{
  "type": "Feature",
  "properties": {
    "addr:full":"7320 S Lindbergh Blvd Saint Louis MO 63125",
    "addr:housenumber":"7320",
    "addr:postcode":"63125",
    "addr:street":"S Lindbergh Blvd",
    "iso:country":"US",
    "sg:address":"7320 S Lindbergh Blvd",
    "sg:city":"Saint Louis",
    "sg:classifiers":[
        {
            "category":"Home & Garden",
            "subcategory":"Home Furnishings",
            "type":"Retail Goods"
        }
    ],
    "sg:phone":"+1 314 845 3448",
    "sg:postcode":"63125",
    "sg:province":"MO",
    "wof:name":"Pier 1",
    "wof:placetype":"venue"
},
  "geometry": {"coordinates":[-90.32745,38.506885],"type":"Point"}
}