{
  "type": "Feature",
  "properties": {
    "iso:country":"US",
    "sg:address":"9007 NE 157th St",
    "sg:city":"Smithville",
    "sg:classifiers":[
        {
            "category":"Real Estate",
            "subcategory":"Real Estate Operator",
            "type":"Services"
        }
    ],
    "sg:phone":"+1 816 532 2303",
    "sg:postcode":"64089",
    "sg:province":"MO",
    "sg:tags":[
        "apartment"
    ],
    "wof:name":"Cedarwood Apartments",
    "wof:placetype":"venue"
},
  "geometry": {"coordinates":[-94.46833599999999,39.377117],"type":"Point"}
}