{
  "type": "Feature",
  "properties": {
    "iso:country":"US",
    "sg:address":"2802 Joslin Ln",
    "sg:city":"Saint Joseph",
    "sg:classifiers":[
        {
            "category":"Health Services",
            "subcategory":"Doctor",
            "type":"Services"
        }
    ],
    "sg:phone":"+1 816 279 3776",
    "sg:postcode":"64506",
    "sg:province":"MO",
    "sg:tags":[
        "medical"
    ],
    "wof:name":"Steven K Rowe",
    "wof:placetype":"venue"
},
  "geometry": {"coordinates":[-94.824175,39.784968],"type":"Point"}
}