{
  "type": "Feature",
  "properties": {
    "iso:country":"US",
    "sg:address":"114 S Dallas St",
    "sg:city":"Urbana",
    "sg:classifiers":[
        {
            "category":"Manufacturing",
            "subcategory":"Printing",
            "type":"Manufacturing & Wholesale Goods"
        }
    ],
    "sg:phone":"+1 417 993 4741",
    "sg:postcode":"65767",
    "sg:province":"MO",
    "sg:tags":[
        "screen"
    ],
    "wof:name":"Sports Section",
    "wof:placetype":"venue"
},
  "geometry": {"coordinates":[-93.171263,37.841649],"type":"Point"}
}