{
  "type": "Feature",
  "properties": {
    "iso:country":"US",
    "sg:address":"3167 Liv 531",
    "sg:city":"Chillicothe",
    "sg:classifiers":[
        {
            "category":"Home & Garden",
            "subcategory":"Building Materials",
            "type":"Retail Goods"
        }
    ],
    "sg:phone":"+1 660 646 7204",
    "sg:postcode":"64601",
    "sg:province":"MO",
    "wof:name":"Cedar Ridge Paintball",
    "wof:placetype":"venue"
},
  "geometry": {"coordinates":[-93.622502,39.930812],"type":"Point"}
}