{
  "type": "Feature",
  "properties": {
    "iso:country":"US",
    "sg:address":"11206 E Bannister Rd",
    "sg:city":"Kansas City",
    "sg:classifiers":[
        {
            "category":"Communications",
            "subcategory":"Film & Video Production",
            "type":"Services"
        }
    ],
    "sg:phone":"+1 816 763 8410",
    "sg:postcode":"64134",
    "sg:province":"MO",
    "sg:tags":[
        "motion",
        "picture",
        "apartment",
        "building",
        "operator"
    ],
    "wof:name":"Lw Properties",
    "wof:placetype":"venue"
},
  "geometry": {"coordinates":[-94.45146200000001,38.950116],"type":"Point"}
}