{
  "type": "Feature",
  "properties": {
    "iso:country":"US",
    "sg:address":"7207 State Hwy 1",
    "sg:city":"Kansas City",
    "sg:classifiers":[
        {
            "category":"Retail",
            "subcategory":"Portrait Studio",
            "type":"Services"
        }
    ],
    "sg:phone":"+1 816 436 1369",
    "sg:postcode":"64119",
    "sg:province":"MO",
    "sg:tags":[
        "photo"
    ],
    "wof:name":"Wal-Mart Prtrait Studio 01120",
    "wof:placetype":"venue"
},
  "geometry": {"coordinates":[-94.547498,39.226231],"type":"Point"}
}