{
  "type": "Feature",
  "properties": {
    "iso:country":"US",
    "sg:address":"2010 Chapel Plaza Ct",
    "sg:city":"Columbia",
    "sg:classifiers":[
        {
            "category":"Banks & Credit Unions",
            "subcategory":"Bank",
            "type":"Services"
        }
    ],
    "sg:phone":"+1 573 445 6746",
    "sg:postcode":"65203",
    "sg:province":"MO",
    "sg:tags":[
        "mortgage"
    ],
    "wof:name":"Countrywide",
    "wof:placetype":"venue"
},
  "geometry": {"coordinates":[-92.36462299999999,38.927803],"type":"Point"}
}