{
  "type": "Feature",
  "properties": {
    "iso:country":"US",
    "sg:address":"2101 S Main St",
    "sg:city":"Joplin",
    "sg:classifiers":[
        {
            "category":"Autos & Motor Vehicles",
            "subcategory":"Auto Supplies",
            "type":"Retail Goods"
        }
    ],
    "sg:phone":"+1 417 626 8855",
    "sg:postcode":"64804",
    "sg:province":"MO",
    "wof:name":"Tire & Automotive Center",
    "wof:placetype":"venue"
},
  "geometry": {"coordinates":[-94.514253,37.067001],"type":"Point"}
}