{
  "type": "Feature",
  "properties": {
    "iso:country":"US",
    "sg:address":"101 E Arrow St",
    "sg:city":"Marshall",
    "sg:classifiers":[
        {
            "category":"Government",
            "subcategory":"Office",
            "type":"Public Place"
        }
    ],
    "sg:phone":"+1 660 886 8699",
    "sg:postcode":"65340",
    "sg:province":"MO",
    "sg:tags":[
        "parish",
        "government-county"
    ],
    "wof:name":"Saline County Public Administrator",
    "wof:placetype":"venue"
},
  "geometry": {"coordinates":[-93.196053,39.120312],"type":"Point"}
}