{
  "type": "Feature",
  "properties": {
    "iso:country":"US",
    "sg:address":"203 18th",
    "sg:city":"Cassville",
    "sg:classifiers":[
        {
            "category":"Freight",
            "type":"Transportation"
        }
    ],
    "sg:phone":"+1 417 847 4885",
    "sg:postcode":"65625",
    "sg:province":"MO",
    "sg:tags":[
        "operator",
        "trucking"
    ],
    "wof:name":"Beesons Trucking",
    "wof:placetype":"venue"
},
  "geometry": {"coordinates":[-93.864249,36.688559],"type":"Point"}
}