{
  "type": "Feature",
  "properties": {
    "iso:country":"US",
    "sg:address":"1324 Hampton Ave",
    "sg:city":"Saint Louis",
    "sg:classifiers":[
        {
            "category":"Restaurant",
            "type":"Food & Drink"
        }
    ],
    "sg:menulink":"http://www.allmenus.com/mo/st-louis/195683-taco-bell/menu/",
    "sg:phone":"+1 314 647 2139",
    "sg:postcode":"63139",
    "sg:province":"MO",
    "sg:tags":[
        "mexican"
    ],
    "wof:name":"Taco Bell",
    "wof:placetype":"venue"
},
  "geometry": {"coordinates":[-90.287392,38.625824],"type":"Point"}
}