{
  "type": "Feature",
  "properties": {
    "iso:country":"US",
    "sg:address":"166 Lincoln St",
    "sg:city":"Forsyth",
    "sg:classifiers":[
        {
            "category":"Home & Garden",
            "subcategory":"Furniture",
            "type":"Retail Goods"
        }
    ],
    "sg:phone":"+1 417 546 4166",
    "sg:postcode":"65653",
    "sg:province":"MO",
    "sg:tags":[
        "cabinet"
    ],
    "wof:name":"Wyatt Custom Woodworking",
    "wof:placetype":"venue"
},
  "geometry": {"coordinates":[-93.09792299999999,36.685596],"type":"Point"}
}