{
  "type": "Feature",
  "properties": {
    "iso:country":"US",
    "sg:address":"1349 Garrett St",
    "sg:city":"West Plains",
    "sg:classifiers":[
        {
            "category":"Professional",
            "subcategory":"Computer Services",
            "type":"Services"
        }
    ],
    "sg:phone":"+1 417 255 1703",
    "sg:postcode":"65775",
    "sg:province":"MO",
    "sg:tags":[
        "datum"
    ],
    "wof:name":"Rivet Web Design",
    "wof:placetype":"venue"
},
  "geometry": {"coordinates":[-91.86569299999999,36.727927],"type":"Point"}
}