{
  "type": "Feature",
  "properties": {
    "iso:country":"US",
    "sg:address":"17877 Maplewood Dr",
    "sg:city":"Rocky Mount",
    "sg:classifiers":[
        {
            "category":"Professional",
            "subcategory":"Business Services",
            "type":"Services"
        }
    ],
    "sg:phone":"+1 573 392 5408",
    "sg:postcode":"65072",
    "sg:province":"MO",
    "wof:name":"Boyd Enterprises",
    "wof:placetype":"venue"
},
  "geometry": {"coordinates":[-92.75091500000001,38.266617],"type":"Point"}
}