{
  "type": "Feature",
  "properties": {
    "iso:country":"US",
    "sg:address":"9015 Gravois Rd",
    "sg:city":"St Louis",
    "sg:classifiers":[
        {
            "category":"Real Estate",
            "subcategory":"Real Estate Agent",
            "type":"Services"
        }
    ],
    "sg:phone":"+1 314 352 0002",
    "sg:postcode":"63123",
    "sg:province":"MO",
    "sg:tags":[
        "management"
    ],
    "wof:name":"Managed Planning Inc",
    "wof:placetype":"venue"
},
  "geometry": {"coordinates":[-90.314341,38.555214],"type":"Point"}
}