{
  "type": "Feature",
  "properties": {
    "iso:country":"US",
    "sg:address":"1107 W 27th St S",
    "sg:city":"Independence",
    "sg:classifiers":[
        {
            "category":"Restaurant",
            "type":"Food & Drink"
        },
        {
            "category":"Ice Cream",
            "type":"Food & Drink"
        }
    ],
    "sg:phone":"+1 816 461 0175",
    "sg:postcode":"64052",
    "sg:province":"MO",
    "sg:tags":[
        "frozen",
        "dessert"
    ],
    "wof:name":"Doc's Mercantile Ltd",
    "wof:placetype":"venue"
},
  "geometry": {"coordinates":[-94.426938,39.071431],"type":"Point"}
}