{
  "type": "Feature",
  "properties": {
    "iso:country":"US",
    "sg:address":"16999 Lea Ave",
    "sg:city":"Belton",
    "sg:classifiers":[
        {
            "category":"Building & Trades",
            "subcategory":"Locksmith",
            "type":"Services"
        }
    ],
    "sg:phone":"+1 816 425 3154",
    "sg:postcode":"64012",
    "sg:province":"MO",
    "sg:tags":[
        "lock"
    ],
    "wof:name":"LOCK TO POP 24 HR LOCKSMITH",
    "wof:placetype":"venue"
},
  "geometry": {"coordinates":[-94.498222,38.816269],"type":"Point"}
}