{
  "type": "Feature",
  "properties": {
    "iso:country":"US",
    "sg:address":"16377 Gopher Way",
    "sg:city":"Kirksville",
    "sg:classifiers":[
        {
            "category":"Building & Trades",
            "subcategory":"Plumbing",
            "type":"Services"
        }
    ],
    "sg:phone":"+1 660 665 1616",
    "sg:postcode":"63501",
    "sg:province":"MO",
    "sg:tags":[
        "heating",
        "contractor"
    ],
    "wof:name":"Treasure's Plumbing & Heating",
    "wof:placetype":"venue"
},
  "geometry": {"coordinates":[-92.553659,40.250813],"type":"Point"}
}