{
  "type": "Feature",
  "properties": {
    "iso:country":"US",
    "sg:address":"200 N Main Ave",
    "sg:city":"Republic",
    "sg:classifiers":[
        {
            "category":"Sports & Exercise",
            "subcategory":"Gym",
            "type":"Entertainment"
        }
    ],
    "sg:phone":"+1 417 732 2322",
    "sg:postcode":"65738",
    "sg:province":"MO",
    "sg:tags":[
        "club",
        "health",
        "studio",
        "gymnasium"
    ],
    "wof:name":"Shapes Fitness For Women",
    "wof:placetype":"venue"
},
  "geometry": {"coordinates":[-93.48049899999999,37.120029],"type":"Point"}
}