{
  "type": "Feature",
  "properties": {
    "iso:country":"US",
    "sg:address":"6216 Bailey Pl",
    "sg:city":"Saint Louis",
    "sg:classifiers":[
        {
            "category":"Food & Beverages",
            "subcategory":"Groceries & Convenience Stores",
            "type":"Retail Goods"
        }
    ],
    "sg:phone":"+1 314 385 8728",
    "sg:postcode":"63121",
    "sg:province":"MO",
    "wof:name":"Lees Food Shop",
    "wof:placetype":"venue"
},
  "geometry": {"coordinates":[-90.281367,38.685181],"type":"Point"}
}