{
  "type": "Feature",
  "properties": {
    "iso:country":"US",
    "sg:address":"2296 N Arbor Creek Ln",
    "sg:city":"Springfield",
    "sg:classifiers":[
        {
            "category":"Building & Trades",
            "subcategory":"Landscaping Services",
            "type":"Services"
        }
    ],
    "sg:phone":"+1 417 865 1600",
    "sg:postcode":"65802",
    "sg:province":"MO",
    "sg:tags":[
        "tree"
    ],
    "wof:name":"Ryans Tnt Lawn & Tree",
    "wof:placetype":"venue"
},
  "geometry": {"coordinates":[-93.20777,37.235674],"type":"Point"}
}