{
  "type": "Feature",
  "properties": {
    "iso:country":"US",
    "sg:address":"2424 State Hwy C",
    "sg:city":"Seymour",
    "sg:classifiers":[
        {
            "category":"Building & Trades",
            "subcategory":"Landscaping Services",
            "type":"Services"
        }
    ],
    "sg:phone":"+1 417 935 4356",
    "sg:postcode":"65746",
    "sg:province":"MO",
    "wof:name":"Pauls Bobcat Work Inc",
    "wof:placetype":"venue"
},
  "geometry": {"coordinates":[-92.75380199999999,37.187275],"type":"Point"}
}