{
  "type": "Feature",
  "properties": {
    "iso:country":"US",
    "sg:address":"108 S Monroe St",
    "sg:city":"Raymore",
    "sg:classifiers":[
        {
            "category":"Building & Trades",
            "subcategory":"Construction",
            "type":"Services"
        }
    ],
    "sg:phone":"+1 816 331 6121",
    "sg:postcode":"64083",
    "sg:province":"MO",
    "sg:tags":[
        "house"
    ],
    "wof:name":"Barry E Keele Builder",
    "wof:placetype":"venue"
},
  "geometry": {"coordinates":[-94.45032500000001,38.803187],"type":"Point"}
}