{
  "type": "Feature",
  "properties": {
    "iso:country":"US",
    "sg:address":"926 N 3rd St",
    "sg:city":"Clinton",
    "sg:classifiers":[
        {
            "category":"Real Estate",
            "subcategory":"Real Estate Operator",
            "type":"Services"
        }
    ],
    "sg:phone":"+1 660 885 4215",
    "sg:postcode":"64735",
    "sg:province":"MO",
    "sg:tags":[
        "mobile",
        "home",
        "site",
        "community"
    ],
    "wof:name":"Plaza Mobile Home Court",
    "wof:placetype":"venue"
},
  "geometry": {"coordinates":[-93.77188599999999,38.379347],"type":"Point"}
}