{
  "type": "Feature",
  "properties": {
    "iso:country":"US",
    "sg:address":"51 Wilshire Ter",
    "sg:city":"St Louis",
    "sg:classifiers":[
        {
            "category":"Professional",
            "subcategory":"Computer Services",
            "type":"Services"
        }
    ],
    "sg:phone":"+1 314 220 7898",
    "sg:postcode":"63119",
    "sg:province":"MO",
    "sg:tags":[
        "repair"
    ],
    "wof:name":"All Computer Needs",
    "wof:placetype":"venue"
},
  "geometry": {"coordinates":[-90.36447,38.572941],"type":"Point"}
}