{
  "type": "Feature",
  "properties": {
    "iso:country":"US",
    "sg:address":"1425 Stein Rd",
    "sg:city":"St Louis",
    "sg:classifiers":[
        {
            "category":"Social Services",
            "subcategory":"Child Care",
            "type":"Services"
        },
        {
            "category":"Professional",
            "type":"Services"
        }
    ],
    "sg:phone":"+1 314 521 7733",
    "sg:postcode":"63135",
    "sg:province":"MO",
    "wof:name":"More That ABC",
    "wof:placetype":"venue"
},
  "geometry": {"coordinates":[-90.281329,38.756858],"type":"Point"}
}