{
  "type": "Feature",
  "properties": {
    "iso:country":"US",
    "sg:address":"3131 Ten Pin Ln",
    "sg:city":"Joplin",
    "sg:classifiers":[
        {
            "category":"Sports & Exercise",
            "subcategory":"Bowling",
            "type":"Entertainment"
        }
    ],
    "sg:phone":"+1 417 624 8652",
    "sg:postcode":"64801",
    "sg:province":"MO",
    "sg:tags":[
        "center"
    ],
    "wof:name":"Richard, Carl Bowl East",
    "wof:placetype":"venue"
},
  "geometry": {"coordinates":[-94.475987,37.10528],"type":"Point"}
}