{
  "type": "Feature",
  "properties": {
    "iso:country":"US",
    "sg:address":"1005 E Champ Clark Dr",
    "sg:city":"Bowling Green",
    "sg:classifiers":[
        {
            "category":"Home & Garden",
            "subcategory":"Furniture",
            "type":"Retail Goods"
        }
    ],
    "sg:phone":"+1 573 324 3355",
    "sg:postcode":"63334",
    "sg:province":"MO",
    "wof:name":"Robinson's Furniture Inc",
    "wof:placetype":"venue"
},
  "geometry": {"coordinates":[-91.181854,39.336698],"type":"Point"}
}