{
  "type": "Feature",
  "properties": {
    "iso:country":"US",
    "sg:address":"3701 Main St",
    "sg:city":"Kansas City",
    "sg:classifiers":[
        {
            "category":"Food & Beverages",
            "subcategory":"Groceries & Convenience Stores",
            "type":"Retail Goods"
        }
    ],
    "sg:phone":"+1 816 753 2520",
    "sg:postcode":"64111",
    "sg:province":"MO",
    "sg:tags":[
        "grocer"
    ],
    "wof:name":"West African Groceries Inc",
    "wof:placetype":"venue"
},
  "geometry": {"coordinates":[-94.585999,39.058382],"type":"Point"}
}