{
  "type": "Feature",
  "properties": {
    "iso:country":"US",
    "sg:address":"7200 Manchester Rd",
    "sg:city":"Saint Louis",
    "sg:classifiers":[
        {
            "category":"Health Services",
            "subcategory":"Doctor",
            "type":"Services"
        },
        {
            "category":"Health Services",
            "subcategory":"Dentist",
            "type":"Services"
        }
    ],
    "sg:phone":"+1 314 781 1774",
    "sg:postcode":"63143",
    "sg:province":"MO",
    "wof:name":"Kwiatkouski Ana DO",
    "wof:placetype":"venue"
},
  "geometry": {"coordinates":[-90.3134,38.614498],"type":"Point"}
}