{
  "type": "Feature",
  "properties": {
    "addr:full":"7200 Manchester Rd Saint Louis MO 63143",
    "addr:housenumber":"7200",
    "addr:postcode":"63143",
    "addr:street":"Manchester Rd",
    "iso:country":"US",
    "sg:address":"7200 Manchester Rd",
    "sg:city":"Saint Louis",
    "sg:classifiers":[
        {
            "category":"Health Services",
            "subcategory":"Doctor",
            "type":"Services"
        },
        {
            "category":"Health Services",
            "subcategory":"Dentist",
            "type":"Services"
        }
    ],
    "sg:phone":"+1 314 781 1774",
    "sg:postcode":"63143",
    "sg:province":"MO",
    "wof:name":"Kwiatkouski Ana DO",
    "wof:placetype":"venue"
},
  "geometry": {"coordinates":[-90.3134,38.614498],"type":"Point"}
}