{
  "type": "Feature",
  "properties": {
    "iso:country":"US",
    "sg:address":"1062 E Linden Ave",
    "sg:city":"Saint Louis",
    "sg:classifiers":[
        {
            "category":"Wholesale",
            "subcategory":"Groceries",
            "type":"Manufacturing & Wholesale Goods"
        }
    ],
    "sg:phone":"+1 314 821 5345",
    "sg:postcode":"63117",
    "sg:province":"MO",
    "sg:tags":[
        "general"
    ],
    "wof:name":"Vibs Caribbean Heat",
    "wof:placetype":"venue"
},
  "geometry": {"coordinates":[-90.340363,38.635241],"type":"Point"}
}