{
  "type": "Feature",
  "properties": {
    "iso:country":"US",
    "sg:address":"120 E Nifong Blvd Ste A",
    "sg:city":"Columbia",
    "sg:classifiers":[
        {
            "category":"Restaurant",
            "type":"Food & Drink"
        }
    ],
    "sg:phone":"+1 573 875 8588",
    "sg:postcode":"65203",
    "sg:province":"MO",
    "sg:tags":[
        "asian",
        "pan",
        "japanese"
    ],
    "wof:name":"Osaka Japanese Restaurant",
    "wof:placetype":"venue"
},
  "geometry": {"coordinates":[-92.336029,38.90794],"type":"Point"}
}