{
  "type": "Feature",
  "properties": {
    "iso:country":"US",
    "sg:address":"709 Herschel St",
    "sg:city":"Belton",
    "sg:classifiers":[
        {
            "category":"Organizations",
            "subcategory":"Religious Organization",
            "type":"Services"
        }
    ],
    "sg:phone":"+1 816 331 2408",
    "sg:postcode":"64012",
    "sg:province":"MO",
    "sg:tags":[
        "church"
    ],
    "wof:name":"El-Bethel Baptist Church",
    "wof:placetype":"venue"
},
  "geometry": {"coordinates":[-94.531347,38.809662],"type":"Point"}
}