{
  "type": "Feature",
  "properties": {
    "iso:country":"US",
    "sg:address":"1900 S Grand Ave",
    "sg:city":"Carthage",
    "sg:classifiers":[
        {
            "category":"Organizations",
            "subcategory":"Religious Organization",
            "type":"Services"
        }
    ],
    "sg:phone":"+1 417 358 7787",
    "sg:postcode":"64836",
    "sg:province":"MO",
    "sg:tags":[
        "church"
    ],
    "sg:website":"www.dongcong.net",
    "wof:name":"Congregation Of The Mother",
    "wof:placetype":"venue"
},
  "geometry": {"coordinates":[-94.31000299999999,37.156528],"type":"Point"}
}