{
  "type": "Feature",
  "properties": {
    "iso:country":"US",
    "sg:address":"39879 277th St",
    "sg:city":"Ravenwood",
    "sg:classifiers":[
        {
            "category":"Farming",
            "subcategory":"Farm",
            "type":"Manufacturing & Wholesale Goods"
        }
    ],
    "sg:phone":"+1 660 937 2647",
    "sg:postcode":"64479",
    "sg:province":"MO",
    "sg:tags":[
        "crop",
        "general"
    ],
    "wof:name":"Donald Adwell",
    "wof:placetype":"venue"
},
  "geometry": {"coordinates":[-94.629452,40.318438],"type":"Point"}
}