{
  "type": "Feature",
  "properties": {
    "iso:country":"US",
    "sg:address":"227 Pennington Ln",
    "sg:city":"Chesterfield",
    "sg:classifiers":[
        {
            "category":"Professional",
            "subcategory":"Management & Consulting",
            "type":"Services"
        }
    ],
    "sg:phone":"+1 636 227 3205",
    "sg:postcode":"63005",
    "sg:province":"MO",
    "wof:name":"Healthcare Advisory Panel LLC",
    "wof:placetype":"venue"
},
  "geometry": {"coordinates":[-90.593416,38.609701],"type":"Point"}
}