{
  "type": "Feature",
  "properties": {
    "iso:country":"US",
    "sg:address":"300 Ramsey Dr",
    "sg:city":"Sullivan",
    "sg:classifiers":[
        {
            "category":"Professional",
            "subcategory":"Detective & Security Services",
            "type":"Services"
        }
    ],
    "sg:phone":"+1 573 468 2000",
    "sg:postcode":"63080",
    "sg:province":"MO",
    "sg:tags":[
        "guard",
        "patrol"
    ],
    "wof:name":"Ace Security",
    "wof:placetype":"venue"
},
  "geometry": {"coordinates":[-91.16738100000001,38.206661],"type":"Point"}
}