{
  "type": "Feature",
  "properties": {
    "iso:country":"US",
    "sg:address":"115 Canepa Rd",
    "sg:city":"Festus",
    "sg:classifiers":[
        {
            "category":"Retail",
            "subcategory":"Laundry & Dry Cleaning",
            "type":"Services"
        }
    ],
    "sg:phone":"+1 636 937 8171",
    "sg:postcode":"63028",
    "sg:province":"MO",
    "sg:tags":[
        "cleaners",
        "upholstery"
    ],
    "wof:name":"Alpha-1 Carpet Care",
    "wof:placetype":"venue"
},
  "geometry": {"coordinates":[-90.370064,38.168177],"type":"Point"}
}