{
  "type": "Feature",
  "properties": {
    "iso:country":"US",
    "sg:address":"350 Wildwood Dr N",
    "sg:city":"Branson",
    "sg:classifiers":[
        {
            "category":"Arts & Performance",
            "subcategory":"Theater",
            "type":"Entertainment"
        }
    ],
    "sg:phone":"+1 417 335 3905",
    "sg:postcode":"65653",
    "sg:province":"MO",
    "sg:tags":[
        "theatrical",
        "business"
    ],
    "wof:name":"Keepin It Company",
    "wof:placetype":"venue"
},
  "geometry": {"coordinates":[-93.269201,36.645036],"type":"Point"}
}