{
  "type": "Feature",
  "properties": {
    "iso:country":"US",
    "sg:address":"2039 NW 49 Ter",
    "sg:city":"Kansas City",
    "sg:classifiers":[
        {
            "category":"Government",
            "subcategory":"Police Station",
            "type":"Public Place"
        }
    ],
    "sg:phone":"+1 816 741 1330",
    "sg:postcode":"64151",
    "sg:province":"MO",
    "sg:tags":[
        "department",
        "protection"
    ],
    "wof:name":"Northmoor Police Department",
    "wof:placetype":"venue"
},
  "geometry": {"coordinates":[-94.604974,39.183823],"type":"Point"}
}