{
  "type": "Feature",
  "properties": {
    "iso:country":"US",
    "sg:address":"12096 Saint Charles Rock Rd",
    "sg:city":"Hazelwood",
    "sg:classifiers":[
        {
            "category":"Building & Trades",
            "subcategory":"Construction",
            "type":"Services"
        }
    ],
    "sg:phone":"+1 314 739 1990",
    "sg:postcode":"63044",
    "sg:province":"MO",
    "sg:tags":[
        "home",
        "builder"
    ],
    "wof:name":"Pentrex Development Corp",
    "wof:placetype":"venue"
},
  "geometry": {"coordinates":[-90.422714,38.747824],"type":"Point"}
}