{
  "type": "Feature",
  "properties": {
    "iso:country":"US",
    "sg:address":"4974 Heege Rd",
    "sg:city":"St Louis",
    "sg:classifiers":[
        {
            "category":"Social Services",
            "subcategory":"Child Care",
            "type":"Services"
        }
    ],
    "sg:phone":"+1 314 832 9475",
    "sg:postcode":"63123",
    "sg:province":"MO",
    "wof:name":"Edgewood Children's Ctr",
    "wof:placetype":"venue"
},
  "geometry": {"coordinates":[-90.30211,38.558352],"type":"Point"}
}