{
  "type": "Feature",
  "properties": {
    "iso:country":"US",
    "sg:address":"4300 E 12 St",
    "sg:city":"Kansas City",
    "sg:classifiers":[
        {
            "category":"Wholesale",
            "subcategory":"Scrap",
            "type":"Manufacturing & Wholesale Goods"
        }
    ],
    "sg:phone":"+1 816 483 1225",
    "sg:postcode":"64127",
    "sg:province":"MO",
    "sg:tags":[
        "recycling",
        "metal",
        "center"
    ],
    "wof:name":"12th Street Recycling Inc",
    "wof:placetype":"venue"
},
  "geometry": {"coordinates":[-94.530209,39.098093],"type":"Point"}
}