{
  "type": "Feature",
  "properties": {
    "iso:country":"US",
    "sg:address":"1919 Wilson Ave",
    "sg:city":"Chesterfield",
    "sg:classifiers":[
        {
            "category":"Professional",
            "subcategory":"Management & Consulting",
            "type":"Services"
        }
    ],
    "sg:phone":"+1 636 532 4202",
    "sg:postcode":"63005",
    "sg:province":"MO",
    "sg:tags":[
        "marketing",
        "consultant"
    ],
    "wof:name":"AVB Marketing",
    "wof:placetype":"venue"
},
  "geometry": {"coordinates":[-90.580461,38.636038],"type":"Point"}
}