{
  "type": "Feature",
  "properties": {
    "iso:country":"US",
    "sg:address":"1250 Old Cape Rd",
    "sg:city":"Jackson",
    "sg:classifiers":[
        {
            "category":"Real Estate",
            "subcategory":"Real Estate Services",
            "type":"Services"
        },
        {
            "category":"Professional",
            "subcategory":"Business Services",
            "type":"Services"
        },
        {
            "category":"Real Estate",
            "subcategory":"Surveying",
            "type":"Services"
        }
    ],
    "sg:phone":"+1 573 204 0034",
    "sg:postcode":"63755",
    "sg:province":"MO",
    "sg:tags":[
        "commercial",
        "appraisers-business",
        "industrial",
        "appraisers-commercial",
        "appraiser"
    ],
    "wof:name":"Conrad Appraisal Consulting Co",
    "wof:placetype":"venue"
},
  "geometry": {"coordinates":[-89.653859,37.374669],"type":"Point"}
}