{
  "type": "Feature",
  "properties": {
    "iso:country":"US",
    "sg:address":"8610 W Robin Ln",
    "sg:city":"Republic",
    "sg:classifiers":[
        {
            "category":"Farming",
            "subcategory":"Dairy Farm",
            "type":"Manufacturing & Wholesale Goods"
        }
    ],
    "sg:phone":"+1 417 732 6085",
    "sg:postcode":"65738",
    "sg:province":"MO",
    "wof:name":"Robert Britain",
    "wof:placetype":"venue"
},
  "geometry": {"coordinates":[-93.466077,37.167117],"type":"Point"}
}