{
  "type": "Feature",
  "properties": {
    "iso:country":"US",
    "sg:address":"913 Bolger Ct",
    "sg:city":"Fenton",
    "sg:classifiers":[
        {
            "category":"Health Services",
            "subcategory":"Clinic",
            "type":"Services"
        }
    ],
    "sg:phone":"+1 636 305 9599",
    "sg:postcode":"63026",
    "sg:province":"MO",
    "sg:tags":[
        "specialty",
        "outpatient"
    ],
    "wof:name":"Work Center Inc",
    "wof:placetype":"venue"
},
  "geometry": {"coordinates":[-90.45898699999999,38.540811],"type":"Point"}
}