{
  "type": "Feature",
  "properties": {
    "iso:country":"US",
    "sg:address":"1442 S Boyle Ave",
    "sg:city":"St Louis",
    "sg:classifiers":[
        {
            "category":"Wholesale",
            "subcategory":"Machinery & Supplies",
            "type":"Manufacturing & Wholesale Goods"
        }
    ],
    "sg:phone":"+1 314 531 3191",
    "sg:postcode":"63110",
    "sg:province":"MO",
    "sg:tags":[
        "die",
        "tool",
        "industrial",
        "maker"
    ],
    "wof:name":"Banner Machine Tool & Sup Co",
    "wof:placetype":"venue"
},
  "geometry": {"coordinates":[-90.253439,38.624403],"type":"Point"}
}