{
  "type": "Feature",
  "properties": {
    "iso:country":"US",
    "sg:address":"1120 Millcreek Rd",
    "sg:city":"Lebanon",
    "sg:classifiers":[
        {
            "category":"Banks & Credit Unions",
            "subcategory":"Investment Brokerage",
            "type":"Services"
        }
    ],
    "sg:phone":"+1 417 588 3364",
    "sg:postcode":"65536",
    "sg:province":"MO",
    "sg:tags":[
        "advisory"
    ],
    "wof:name":"Larrison Investment Inc",
    "wof:placetype":"venue"
},
  "geometry": {"coordinates":[-92.636124,37.68018],"type":"Point"}
}