{
  "type": "Feature",
  "properties": {
    "iso:country":"US",
    "sg:address":"2130 Jefferson St",
    "sg:city":"Kansas City",
    "sg:classifiers":[
        {
            "category":"Building & Trades",
            "subcategory":"Equipment Rental",
            "type":"Services"
        }
    ],
    "sg:phone":"+1 816 471 5078",
    "sg:postcode":"64108",
    "sg:province":"MO",
    "sg:tags":[
        "moving",
        "supply"
    ],
    "wof:name":"Budget",
    "wof:placetype":"venue"
},
  "geometry": {"coordinates":[-94.59265000000001,39.086096],"type":"Point"}
}