{
  "type": "Feature",
  "properties": {
    "iso:country":"US",
    "sg:address":"33 S County Center Way",
    "sg:city":"Saint Louis",
    "sg:classifiers":[
        {
            "category":"Food & Beverages",
            "subcategory":"Bakery",
            "type":"Retail Goods"
        }
    ],
    "sg:phone":"+1 314 892 3395",
    "sg:postcode":"63129",
    "sg:province":"MO",
    "wof:name":"Auntie Annes",
    "wof:placetype":"venue"
},
  "geometry": {"coordinates":[-90.329414,38.505253],"type":"Point"}
}