{
  "type": "Feature",
  "properties": {
    "iso:country":"US",
    "sg:address":"17644 Myrtlewood Dr",
    "sg:city":"Chesterfield",
    "sg:classifiers":[
        {
            "category":"Professional",
            "subcategory":"Management & Consulting",
            "type":"Services"
        }
    ],
    "sg:phone":"+1 636 536 6061",
    "sg:postcode":"63005",
    "sg:province":"MO",
    "sg:tags":[
        "science",
        "consultant",
        "academic"
    ],
    "wof:name":"Dg Holiday Consulting",
    "wof:placetype":"venue"
},
  "geometry": {"coordinates":[-90.635876,38.637148],"type":"Point"}
}