{
  "type": "Feature",
  "properties": {
    "iso:country":"US",
    "sg:address":"3418 Robyn Ann Dr",
    "sg:city":"Saint Charles",
    "sg:classifiers":[
        {
            "category":"Building & Trades",
            "subcategory":"Construction",
            "type":"Services"
        }
    ],
    "sg:phone":"+1 636 928 1211",
    "sg:postcode":"63303",
    "sg:province":"MO",
    "sg:tags":[
        "concrete",
        "contractor"
    ],
    "wof:name":"Bryan S Foundations Inc",
    "wof:placetype":"venue"
},
  "geometry": {"coordinates":[-90.56977999999999,38.727],"type":"Point"}
}