{
  "type": "Feature",
  "properties": {
    "iso:country":"US",
    "sg:address":"6314 Delmar Blvd",
    "sg:city":"St Louis",
    "sg:classifiers":[
        {
            "category":"Shopping",
            "subcategory":"Music",
            "type":"Retail Goods"
        }
    ],
    "sg:phone":"+1 314 726 6277",
    "sg:postcode":"63130",
    "sg:province":"MO",
    "sg:tags":[
        "tape"
    ],
    "sg:website":"www.streetsiderecords.net",
    "wof:name":"Streetside Records",
    "wof:placetype":"venue"
},
  "geometry": {"coordinates":[-90.30280500000001,38.655656],"type":"Point"}
}