{
  "type": "Feature",
  "properties": {
    "iso:country":"US",
    "sg:address":"4059 Broadway St",
    "sg:city":"Kansas City",
    "sg:classifiers":[
        {
            "category":"Restaurant",
            "type":"Food & Drink"
        }
    ],
    "sg:phone":"+1 816 931 6630",
    "sg:postcode":"64111",
    "sg:province":"MO",
    "sg:tags":[
        "eating"
    ],
    "wof:name":"Corner Restaurant The",
    "wof:placetype":"venue"
},
  "geometry": {"coordinates":[-94.59054399999999,39.053464],"type":"Point"}
}