{
  "type": "Feature",
  "properties": {
    "iso:country":"US",
    "sg:address":"138 NW 400 Rd",
    "sg:city":"Clinton",
    "sg:classifiers":[
        {
            "category":"Shopping",
            "subcategory":"Musical Instruments",
            "type":"Retail Goods"
        }
    ],
    "sg:phone":"+1 660 885 4420",
    "sg:postcode":"64735",
    "sg:province":"MO",
    "wof:name":"Picks N Sticks",
    "wof:placetype":"venue"
},
  "geometry": {"coordinates":[-93.77936800000001,38.425763],"type":"Point"}
}