{
  "type": "Feature",
  "properties": {
    "iso:country":"US",
    "sg:address":"300 12th St W",
    "sg:city":"Lamar",
    "sg:classifiers":[
        {
            "category":"Autos & Motor Vehicles",
            "subcategory":"Fuel & Gas Station",
            "type":"Retail Goods"
        }
    ],
    "sg:phone":"+1 417 682 3371",
    "sg:postcode":"64759",
    "sg:province":"MO",
    "sg:tags":[
        "oil"
    ],
    "wof:name":"Steve's Coastal Svc",
    "wof:placetype":"venue"
},
  "geometry": {"coordinates":[-94.279805,37.49341],"type":"Point"}
}