{
  "type": "Feature",
  "properties": {
    "iso:country":"US",
    "sg:address":"125 W Argonne Dr",
    "sg:city":"Kirkwood",
    "sg:classifiers":[
        {
            "category":"Manufacturing",
            "subcategory":"Printing",
            "type":"Manufacturing & Wholesale Goods"
        }
    ],
    "sg:phone":"+1 314 966 3413",
    "sg:postcode":"63122",
    "sg:province":"MO",
    "sg:tags":[
        "commercial",
        "b",
        "lithographic",
        "typesetting"
    ],
    "sg:website":"www.messengerprint.com",
    "wof:name":"Messenger Printing Co",
    "wof:placetype":"venue"
},
  "geometry": {"coordinates":[-90.408126,38.581323],"type":"Point"}
}