{
  "type": "Feature",
  "properties": {
    "iso:country":"US",
    "sg:address":"1179 Jamunda Walk",
    "sg:city":"Saint Louis",
    "sg:classifiers":[
        {
            "category":"Wholesale",
            "subcategory":"Machinery & Supplies",
            "type":"Manufacturing & Wholesale Goods"
        }
    ],
    "sg:phone":"+1 314 416 7162",
    "sg:postcode":"63129",
    "sg:province":"MO",
    "sg:tags":[
        "equipment",
        "establishment"
    ],
    "wof:name":"All Star Vending",
    "wof:placetype":"venue"
},
  "geometry": {"coordinates":[-90.32719299999999,38.500688],"type":"Point"}
}