{
  "type": "Feature",
  "properties": {
    "iso:country":"US",
    "sg:address":"203 W Commercial St",
    "sg:city":"Lebanon",
    "sg:classifiers":[
        {
            "category":"Professional",
            "subcategory":"Printing & Photocopies",
            "type":"Services"
        },
        {
            "category":"Professional",
            "subcategory":"Credit Reporting & Collection",
            "type":"Services"
        }
    ],
    "sg:phone":"+1 417 533 7661",
    "sg:postcode":"65536",
    "sg:province":"MO",
    "sg:tags":[
        "plaque",
        "medal",
        "award",
        "trophies"
    ],
    "wof:name":"Innovative Computerized Engraving",
    "wof:placetype":"venue"
},
  "geometry": {"coordinates":[-92.664751,37.67974],"type":"Point"}
}