{
  "type": "Feature",
  "properties": {
    "iso:country":"US",
    "sg:address":"321 Goodson Dr",
    "sg:city":"Jackson",
    "sg:classifiers":[
        {
            "category":"Organizations",
            "subcategory":"Community Association",
            "type":"Services"
        }
    ],
    "sg:phone":"+1 573 243 0184",
    "sg:postcode":"63755",
    "sg:province":"MO",
    "wof:name":"Optimist Club Foundation",
    "wof:placetype":"venue"
},
  "geometry": {"coordinates":[-89.662353,37.395175],"type":"Point"}
}