{
  "type": "Feature",
  "properties": {
    "iso:country":"US",
    "sg:address":"415 N Stadium Blvd",
    "sg:city":"Columbia",
    "sg:classifiers":[
        {
            "category":"Fast Food",
            "type":"Food & Drink"
        },
        {
            "category":"Restaurant",
            "type":"Food & Drink"
        }
    ],
    "sg:phone":"+1 573 445 6211",
    "sg:postcode":"65203",
    "sg:province":"MO",
    "sg:tags":[
        "hamburger",
        "hot",
        "dog",
        "american",
        "take",
        "chicken"
    ],
    "sg:website":"http://www.mcdonalds.com",
    "wof:name":"McDonald's",
    "wof:placetype":"venue"
},
  "geometry": {"coordinates":[-92.371317,38.96016],"type":"Point"}
}