{
  "type": "Feature",
  "properties": {
    "iso:country":"US",
    "sg:address":"14 E Columbia St",
    "sg:city":"Farmington",
    "sg:classifiers":[
        {
            "category":"Building & Trades",
            "subcategory":"Construction",
            "type":"Services"
        }
    ],
    "sg:phone":"+1 573 756 9191",
    "sg:postcode":"63640",
    "sg:province":"MO",
    "sg:tags":[
        "house"
    ],
    "wof:name":"Touch of Class",
    "wof:placetype":"venue"
},
  "geometry": {"coordinates":[-90.420885,37.780404],"type":"Point"}
}