{
  "type": "Feature",
  "properties": {
    "iso:country":"US",
    "sg:address":"6525 Towne Woods Dr",
    "sg:city":"Saint Louis",
    "sg:classifiers":[
        {
            "category":"Sports & Exercise",
            "subcategory":"Gym",
            "type":"Entertainment"
        }
    ],
    "sg:phone":"+1 314 846 0044",
    "sg:postcode":"63129",
    "sg:province":"MO",
    "sg:tags":[
        "physical",
        "fitness"
    ],
    "wof:name":"USA Karate Clubs Inc",
    "wof:placetype":"venue"
},
  "geometry": {"coordinates":[-90.317633,38.446475],"type":"Point"}
}