{
  "type": "Feature",
  "properties": {
    "iso:country":"US",
    "sg:address":"10630 Tesshire Dr",
    "sg:city":"Saint Louis",
    "sg:classifiers":[
        {
            "category":"Retail",
            "subcategory":"Auto Repair",
            "type":"Services"
        }
    ],
    "sg:phone":"+1 314 843 0340",
    "sg:postcode":"63123",
    "sg:province":"MO",
    "sg:tags":[
        "transmission"
    ],
    "wof:name":"Performance Transmision",
    "wof:placetype":"venue"
},
  "geometry": {"coordinates":[-90.343367,38.533102],"type":"Point"}
}