{
  "type": "Feature",
  "properties": {
    "iso:country":"US",
    "sg:address":"17 Rio Vista Dr",
    "sg:city":"St Charles",
    "sg:classifiers":[
        {
            "category":"Wholesale",
            "subcategory":"Painting Supplies",
            "type":"Manufacturing & Wholesale Goods"
        }
    ],
    "sg:phone":"+1 636 724 4240",
    "sg:postcode":"63303",
    "sg:province":"MO",
    "sg:tags":[
        "equipment",
        "painter"
    ],
    "sg:website":"www.oldworldbrush.com",
    "wof:name":"Old World Brush & Tool",
    "wof:placetype":"venue"
},
  "geometry": {"coordinates":[-90.50004,38.75645],"type":"Point"}
}