{
  "type": "Feature",
  "properties": {
    "iso:country":"US",
    "sg:address":"119 W Main St",
    "sg:city":"Jackson",
    "sg:classifiers":[
        {
            "category":"Shopping",
            "subcategory":"Jewelry",
            "type":"Retail Goods"
        }
    ],
    "sg:phone":"+1 573 243 3534",
    "sg:postcode":"63755",
    "sg:province":"MO",
    "sg:tags":[
        "jeweler"
    ],
    "wof:name":"Lindsey's Jewelry",
    "wof:placetype":"venue"
},
  "geometry": {"coordinates":[-89.668008,37.382505],"type":"Point"}
}