{
  "type": "Feature",
  "properties": {
    "iso:country":"US",
    "sg:address":"860 Mid Point Dr",
    "sg:city":"O Fallon",
    "sg:classifiers":[
        {
            "category":"Freight",
            "type":"Transportation"
        }
    ],
    "sg:phone":"+1 636 980 1312",
    "sg:postcode":"63366",
    "sg:province":"MO",
    "sg:tags":[
        "who",
        "special",
        "general"
    ],
    "wof:name":"Safe Lock Storage",
    "wof:placetype":"venue"
},
  "geometry": {"coordinates":[-90.71797100000001,38.799518],"type":"Point"}
}