{
  "type": "Feature",
  "properties": {
    "iso:country":"US",
    "sg:address":"1703 Walker Ridge Ct",
    "sg:city":"Chesterfield",
    "sg:classifiers":[
        {
            "category":"Shopping",
            "subcategory":"Bicycles & Sporting Goods",
            "type":"Retail Goods"
        }
    ],
    "sg:phone":"+1 636 530 1950",
    "sg:postcode":"63017",
    "sg:province":"MO",
    "sg:tags":[
        "equipment",
        "golf",
        "supply"
    ],
    "wof:name":"Golf People",
    "wof:placetype":"venue"
},
  "geometry": {"coordinates":[-90.565623,38.634156],"type":"Point"}
}