{
  "type": "Feature",
  "properties": {
    "iso:country":"US",
    "sg:address":"1000 S Maple Ave",
    "sg:city":"Salisbury",
    "sg:classifiers":[
        {
            "category":"Education",
            "subcategory":"School",
            "type":"Public Place"
        }
    ],
    "sg:phone":"+1 660 388 6699",
    "sg:postcode":"65281",
    "sg:province":"MO",
    "wof:name":"Salisbury Superintendent",
    "wof:placetype":"venue"
},
  "geometry": {"coordinates":[-92.8044,39.415279],"type":"Point"}
}