{
  "type": "Feature",
  "properties": {
    "iso:country":"US",
    "sg:address":"10714 Clarendon Ave",
    "sg:city":"Overland",
    "sg:classifiers":[
        {
            "category":"Wholesale",
            "subcategory":"Office Equipment",
            "type":"Manufacturing & Wholesale Goods"
        }
    ],
    "sg:phone":"+1 314 428 4339",
    "sg:postcode":"63114",
    "sg:province":"MO",
    "sg:tags":[
        "machine",
        "duplicating",
        "copying"
    ],
    "wof:name":"Gibson Office Machines",
    "wof:placetype":"venue"
},
  "geometry": {"coordinates":[-90.39747300000001,38.710196],"type":"Point"}
}