{
  "type": "Feature",
  "properties": {
    "iso:country":"US",
    "sg:address":"26771 Maple Way",
    "sg:city":"Greentop",
    "sg:classifiers":[
        {
            "category":"Farming",
            "subcategory":"Farm",
            "type":"Manufacturing & Wholesale Goods"
        }
    ],
    "sg:phone":"+1 660 949 2507",
    "sg:postcode":"63546",
    "sg:province":"MO",
    "sg:tags":[
        "crop",
        "general"
    ],
    "wof:name":"Albert Morgan Farm",
    "wof:placetype":"venue"
},
  "geometry": {"coordinates":[-92.530424,40.337581],"type":"Point"}
}