{
  "type": "Feature",
  "properties": {
    "iso:country":"US",
    "sg:address":"3804 SW Harbor Cir",
    "sg:city":"Lees Summit",
    "sg:classifiers":[
        {
            "category":"Building & Trades",
            "subcategory":"Construction",
            "type":"Services"
        }
    ],
    "sg:phone":"+1 816 537 5300",
    "sg:postcode":"64082",
    "sg:province":"MO",
    "sg:tags":[
        "hanging",
        "contractor"
    ],
    "wof:name":"Renew Painting",
    "wof:placetype":"venue"
},
  "geometry": {"coordinates":[-94.390376,38.850785],"type":"Point"}
}