{
  "type": "Feature",
  "properties": {
    "iso:country":"US",
    "sg:address":"1780 Old Hwy 50 E",
    "sg:city":"Union",
    "sg:classifiers":[
        {
            "category":"Health Services",
            "subcategory":"Doctor",
            "type":"Services"
        }
    ],
    "sg:phone":"+1 636 583 9300",
    "sg:postcode":"63084",
    "sg:province":"MO",
    "sg:tags":[
        "medical"
    ],
    "wof:name":"Dwyer Jerome V MD",
    "wof:placetype":"venue"
},
  "geometry": {"coordinates":[-90.950411,38.43655],"type":"Point"}
}