{
  "type": "Feature",
  "properties": {
    "addr:full":"5419 Lilian Ave Saint Louis MO 63120",
    "addr:postcode":"5419;63120",
    "addr:street":"Lilian Ave",
    "iso:country":"US",
    "sg:address":"5419 Lilian Ave",
    "sg:city":"Saint Louis",
    "sg:classifiers":[
        {
            "category":"Personal",
            "subcategory":"Beauty Salon",
            "type":"Services"
        }
    ],
    "sg:phone":"+1 314 381 1515",
    "sg:postcode":"63120",
    "sg:province":"MO",
    "sg:tags":[
        "hair"
    ],
    "wof:name":"Supreme Hair Studio",
    "wof:placetype":"venue"
},
  "geometry": {"coordinates":[-90.250621,38.692686],"type":"Point"}
}