{
  "type": "Feature",
  "properties": {
    "iso:country":"US",
    "sg:address":"3624 Mitchell Ave",
    "sg:city":"St Joseph",
    "sg:classifiers":[
        {
            "category":"Manufacturing",
            "subcategory":"Tools & Machinery",
            "type":"Manufacturing & Wholesale Goods"
        }
    ],
    "sg:phone":"+1 816 364 0111",
    "sg:postcode":"64507",
    "sg:province":"MO",
    "sg:tags":[
        "light",
        "gas"
    ],
    "wof:name":"Gas Giant",
    "wof:placetype":"venue"
},
  "geometry": {"coordinates":[-94.804108,39.755162],"type":"Point"}
}