{
  "type": "Feature",
  "properties": {
    "iso:country":"US",
    "sg:address":"17209 US Hwy 71",
    "sg:city":"Belton",
    "sg:classifiers":[
        {
            "category":"Recreation",
            "type":"Entertainment"
        }
    ],
    "sg:phone":"+1 816 331 3882",
    "sg:postcode":"64012",
    "sg:province":"MO",
    "sg:tags":[
        "skating",
        "rink"
    ],
    "wof:name":"Ray Bel Skate Ctr",
    "wof:placetype":"venue"
},
  "geometry": {"coordinates":[-94.503422,38.813152],"type":"Point"}
}