{
  "type": "Feature",
  "properties": {
    "iso:country":"US",
    "sg:address":"1903 N Barnes Ave",
    "sg:city":"Springfield",
    "sg:classifiers":[
        {
            "category":"Manufacturing",
            "subcategory":"Motor Vehicles & Parts",
            "type":"Manufacturing & Wholesale Goods"
        }
    ],
    "sg:phone":"+1 417 866 6363",
    "sg:postcode":"65802",
    "sg:province":"MO",
    "sg:tags":[
        "automobile"
    ],
    "sg:website":"www.limousinebuilders.com",
    "wof:name":"Springfield Coach Builders",
    "wof:placetype":"venue"
},
  "geometry": {"coordinates":[-93.251884,37.23232],"type":"Point"}
}