{
  "type": "Feature",
  "properties": {
    "iso:country":"US",
    "sg:address":"6931 Prospect Ave",
    "sg:city":"Kansas City",
    "sg:classifiers":[
        {
            "category":"Personal",
            "subcategory":"Beauty Salon",
            "type":"Services"
        },
        {
            "category":"Personal",
            "subcategory":"Barber",
            "type":"Services"
        }
    ],
    "sg:phone":"+1 816 363 9805",
    "sg:postcode":"64132",
    "sg:province":"MO",
    "sg:tags":[
        "shop"
    ],
    "wof:name":"Northerns Barber & Beauty Shop",
    "wof:placetype":"venue"
},
  "geometry": {"coordinates":[-94.556736,38.999933],"type":"Point"}
}