{
  "type": "Feature",
  "properties": {
    "iso:country":"US",
    "sg:address":"5519 S Lindbergh Blvd",
    "sg:city":"St Louis",
    "sg:classifiers":[
        {
            "category":"Recreation",
            "type":"Entertainment"
        },
        {
            "category":"Shopping",
            "subcategory":"Bicycles & Sporting Goods",
            "type":"Retail Goods"
        }
    ],
    "sg:phone":"+1 314 842 9938",
    "sg:postcode":"63123",
    "sg:province":"MO",
    "sg:tags":[
        "paint",
        "ball",
        "sport"
    ],
    "wof:name":"Paintball Outfitters Inc",
    "wof:placetype":"venue"
},
  "geometry": {"coordinates":[-90.35709,38.524215],"type":"Point"}
}