{
  "type": "Feature",
  "properties": {
    "iso:country":"US",
    "sg:address":"1202 South St",
    "sg:city":"Bethany",
    "sg:classifiers":[
        {
            "category":"Farming",
            "subcategory":"Livestock Farm",
            "type":"Manufacturing & Wholesale Goods"
        }
    ],
    "sg:phone":"+1 660 425 6703",
    "sg:postcode":"64424",
    "sg:province":"MO",
    "sg:tags":[
        "beef",
        "feedlot",
        "cattle"
    ],
    "wof:name":"Callaway Farms Inc",
    "wof:placetype":"venue"
},
  "geometry": {"coordinates":[-94.03841799999999,40.257666],"type":"Point"}
}