{
  "type": "Feature",
  "properties": {
    "iso:country":"US",
    "sg:address":"23 Little Quail Trl",
    "sg:city":"Wentzville",
    "sg:classifiers":[
        {
            "category":"Restaurant",
            "type":"Food & Drink"
        }
    ],
    "sg:phone":"+1 636 332 5484",
    "sg:postcode":"63385",
    "sg:province":"MO",
    "sg:tags":[
        "eating"
    ],
    "wof:name":"Its A Dogs World",
    "wof:placetype":"venue"
},
  "geometry": {"coordinates":[-90.806906,38.859458],"type":"Point"}
}