{
  "type": "Feature",
  "properties": {
    "iso:country":"US",
    "sg:address":"1602 High St",
    "sg:city":"Sarcoxie",
    "sg:classifiers":[
        {
            "category":"Professional",
            "subcategory":"Business Services",
            "type":"Services"
        }
    ],
    "sg:phone":"+1 417 548 7755",
    "sg:postcode":"64862",
    "sg:province":"MO",
    "sg:tags":[
        "auction",
        "auctioneer"
    ],
    "wof:name":"Auctioneer And Realastate",
    "wof:placetype":"venue"
},
  "geometry": {"coordinates":[-94.128547,37.071572],"type":"Point"}
}