{
  "type": "Feature",
  "properties": {
    "addr:full":"2012 S Elliott Ave Aurora MO 65605",
    "addr:housenumber":"2012",
    "addr:postcode":"65605",
    "addr:street":"S Elliott Ave",
    "iso:country":"US",
    "sg:address":"2012 S Elliott Ave",
    "sg:city":"Aurora",
    "sg:classifiers":[
        {
            "category":"Wholesale",
            "subcategory":"Medical Equipment & Supplies",
            "type":"Manufacturing & Wholesale Goods"
        }
    ],
    "sg:phone":"+1 417 678 2673",
    "sg:postcode":"65605",
    "sg:province":"MO",
    "sg:tags":[
        "physician",
        "surgeon"
    ],
    "sg:website":"www.apria.com",
    "wof:name":"Apria Healthcare Inc",
    "wof:placetype":"venue"
},
  "geometry": {"coordinates":[-93.718357,36.952716],"type":"Point"}
}