{
  "type": "Feature",
  "properties": {
    "iso:country":"US",
    "sg:address":"107 W 3rd St",
    "sg:city":"Salisbury",
    "sg:classifiers":[
        {
            "category":"Professional",
            "subcategory":"Accounting & Tax Preparation",
            "type":"Services"
        }
    ],
    "sg:phone":"+1 660 388 5465",
    "sg:postcode":"65281",
    "sg:province":"MO",
    "sg:tags":[
        "return"
    ],
    "wof:name":"Sims Jerald J Tax Consultant",
    "wof:placetype":"venue"
},
  "geometry": {"coordinates":[-92.802111,39.422755],"type":"Point"}
}