{
  "type": "Feature",
  "properties": {
    "iso:country":"US",
    "sg:address":"981 E Main St",
    "sg:city":"Jackson",
    "sg:classifiers":[
        {
            "category":"Real Estate",
            "subcategory":"Real Estate Services",
            "type":"Services"
        },
        {
            "category":"Real Estate",
            "subcategory":"Real Estate Agent",
            "type":"Services"
        }
    ],
    "sg:phone":"+1 573 243 6082",
    "sg:postcode":"63755",
    "sg:province":"MO",
    "sg:tags":[
        "management"
    ],
    "wof:name":"Larry Bill Inc",
    "wof:placetype":"venue"
},
  "geometry": {"coordinates":[-89.65783,37.381458],"type":"Point"}
}