{
  "type": "Feature",
  "properties": {
    "iso:country":"US",
    "sg:address":"2829 James Rd",
    "sg:city":"Hannibal",
    "sg:classifiers":[
        {
            "category":"Retail",
            "subcategory":"Auto Repair",
            "type":"Services"
        }
    ],
    "sg:phone":"+1 573 221 4282",
    "sg:postcode":"63401",
    "sg:province":"MO",
    "sg:tags":[
        "muffler",
        "exhaust",
        "system"
    ],
    "wof:name":"A Accurate Exhaust",
    "wof:placetype":"venue"
},
  "geometry": {"coordinates":[-91.38793099999999,39.705722],"type":"Point"}
}