{
  "type": "Feature",
  "properties": {
    "iso:country":"US",
    "sg:address":"11155 W State Hwy M",
    "sg:city":"Martinsville",
    "sg:classifiers":[
        {
            "category":"Organizations",
            "subcategory":"Religious Organization",
            "type":"Services"
        }
    ],
    "sg:phone":"+1 660 845 2336",
    "sg:postcode":"64467",
    "sg:province":"MO",
    "sg:tags":[
        "church"
    ],
    "wof:name":"New Harmany Baptist Church",
    "wof:placetype":"venue"
},
  "geometry": {"coordinates":[-94.20988699999999,40.398749],"type":"Point"}
}