{
  "type": "Feature",
  "properties": {
    "iso:country":"US",
    "sg:address":"2502 Main St",
    "sg:city":"Lexington",
    "sg:classifiers":[
        {
            "category":"Building & Trades",
            "subcategory":"Plumbing",
            "type":"Services"
        }
    ],
    "sg:phone":"+1 660 259 3550",
    "sg:postcode":"64067",
    "sg:province":"MO",
    "sg:tags":[
        "contractor"
    ],
    "wof:name":"Lafayette Plumbing & Heating",
    "wof:placetype":"venue"
},
  "geometry": {"coordinates":[-93.862419,39.184984],"type":"Point"}
}