{
  "type": "Feature",
  "properties": {
    "iso:country":"US",
    "sg:address":"1205 Sunset Dr",
    "sg:city":"Carrollton",
    "sg:classifiers":[
        {
            "category":"Insurance",
            "subcategory":"Hazard Insurance",
            "type":"Services"
        }
    ],
    "sg:phone":"+1 660 542 0908",
    "sg:postcode":"64633",
    "sg:province":"MO",
    "sg:tags":[
        "commercial",
        "business"
    ],
    "wof:name":"Scott, Doug",
    "wof:placetype":"venue"
},
  "geometry": {"coordinates":[-93.482161,39.37219],"type":"Point"}
}