{
  "type": "Feature",
  "properties": {
    "iso:country":"US",
    "sg:address":"8224 Strothkamp Ln",
    "sg:city":"Sullivan",
    "sg:classifiers":[
        {
            "category":"Farming",
            "subcategory":"Livestock Farm",
            "type":"Manufacturing & Wholesale Goods"
        }
    ],
    "sg:phone":"+1 573 627 3389",
    "sg:postcode":"63080",
    "sg:province":"MO",
    "sg:tags":[
        "beef",
        "feedlot",
        "cattle"
    ],
    "wof:name":"Norris Ruwwe",
    "wof:placetype":"venue"
},
  "geometry": {"coordinates":[-91.34164199999999,38.239638],"type":"Point"}
}