{
  "type": "Feature",
  "properties": {
    "iso:country":"US",
    "sg:address":"2126 Saint Louis Galleria",
    "sg:city":"Saint Louis",
    "sg:classifiers":[
        {
            "category":"Shopping",
            "subcategory":"Clothing, Apparel, & Fashions",
            "type":"Retail Goods"
        }
    ],
    "sg:phone":"+1 314 863 3820",
    "sg:postcode":"63117",
    "sg:province":"MO",
    "wof:name":"Hollister",
    "wof:placetype":"venue"
},
  "geometry": {"coordinates":[-90.346338,38.637739],"type":"Point"}
}