{
  "type": "Feature",
  "properties": {
    "iso:country":"US",
    "sg:address":"3209 N Buckner Tarsney Rd",
    "sg:city":"Buckner",
    "sg:classifiers":[
        {
            "category":"Farming",
            "subcategory":"Farm",
            "type":"Manufacturing & Wholesale Goods"
        }
    ],
    "sg:phone":"+1 816 650 3542",
    "sg:postcode":"64016",
    "sg:province":"MO",
    "wof:name":"Gross Farms",
    "wof:placetype":"venue"
},
  "geometry": {"coordinates":[-94.195701,39.155075],"type":"Point"}
}