{
  "type": "Feature",
  "properties": {
    "iso:country":"US",
    "sg:address":"8060 Clayton Rd",
    "sg:city":"Saint Louis",
    "sg:classifiers":[
        {
            "category":"Health Services",
            "subcategory":"Doctor",
            "type":"Services"
        }
    ],
    "sg:phone":"+1 314 726 2277",
    "sg:postcode":"63117",
    "sg:province":"MO",
    "sg:tags":[
        "medical"
    ],
    "wof:name":"Robert L Lamberg MD",
    "wof:placetype":"venue"
},
  "geometry": {"coordinates":[-90.345336,38.638006],"type":"Point"}
}