{
  "type": "Feature",
  "properties": {
    "iso:country":"US",
    "sg:address":"1221 Branch St",
    "sg:city":"Platte City",
    "sg:classifiers":[
        {
            "category":"Retail",
            "subcategory":"Laundry & Dry Cleaning",
            "type":"Services"
        }
    ],
    "sg:phone":"+1 816 858 5112",
    "sg:postcode":"64079",
    "sg:province":"MO",
    "wof:name":"Elite Cleaners & Village",
    "wof:placetype":"venue"
},
  "geometry": {"coordinates":[-94.771018,39.363135],"type":"Point"}
}