{
  "type": "Feature",
  "properties": {
    "iso:country":"US",
    "sg:address":"101 S Allen St",
    "sg:city":"Centralia",
    "sg:classifiers":[
        {
            "category":"Insurance",
            "subcategory":"Insurance Agent",
            "type":"Services"
        }
    ],
    "sg:phone":"+1 573 682 2112",
    "sg:postcode":"65240",
    "sg:province":"MO",
    "wof:name":"Angell & Co",
    "wof:placetype":"venue"
},
  "geometry": {"coordinates":[-92.13888,39.21156],"type":"Point"}
}