{
  "type": "Feature",
  "properties": {
    "iso:country":"US",
    "sg:address":"9016 Saint Charles Rock Rd",
    "sg:city":"St Louis",
    "sg:classifiers":[
        {
            "category":"Professional",
            "subcategory":"Lawyer & Legal Services",
            "type":"Services"
        }
    ],
    "sg:phone":"+1 314 733 1900",
    "sg:postcode":"63114",
    "sg:province":"MO",
    "sg:tags":[
        "attorney"
    ],
    "wof:name":"Liberty Tax Svc",
    "wof:placetype":"venue"
},
  "geometry": {"coordinates":[-90.354203,38.712754],"type":"Point"}
}