{
  "type": "Feature",
  "properties": {
    "iso:country":"US",
    "sg:address":"202 E Booneslick Rd",
    "sg:city":"Warrenton",
    "sg:classifiers":[
        {
            "category":"Personal",
            "subcategory":"Beauty Salon",
            "type":"Services"
        }
    ],
    "sg:phone":"+1 636 456 1180",
    "sg:postcode":"63383",
    "sg:province":"MO",
    "wof:name":"Advance Beauty College",
    "wof:placetype":"venue"
},
  "geometry": {"coordinates":[-91.145287,38.811254],"type":"Point"}
}