{
  "type": "Feature",
  "properties": {
    "iso:country":"US",
    "sg:address":"13159 Taussig Ave",
    "sg:city":"Bridgeton",
    "sg:classifiers":[
        {
            "category":"Government",
            "subcategory":"Office",
            "type":"Public Place"
        }
    ],
    "sg:phone":"+1 314 291 8643",
    "sg:postcode":"63044",
    "sg:province":"MO",
    "sg:tags":[
        "township",
        "government-city",
        "village"
    ],
    "sg:website":"http://www.bridgetonmo.com",
    "wof:name":"Athletic Complex",
    "wof:placetype":"venue"
},
  "geometry": {"coordinates":[-90.42973000000001,38.776749],"type":"Point"}
}