{
  "type": "Feature",
  "properties": {
    "iso:country":"US",
    "sg:address":"1057 Tampa Ave",
    "sg:city":"Saint Louis",
    "sg:classifiers":[
        {
            "category":"Arts & Performance",
            "subcategory":"Theater",
            "type":"Entertainment"
        }
    ],
    "sg:phone":"+1 314 961 0839",
    "sg:postcode":"63119",
    "sg:province":"MO",
    "sg:tags":[
        "group"
    ],
    "wof:name":"Doctor Shoe Vegas",
    "wof:placetype":"venue"
},
  "geometry": {"coordinates":[-90.32900100000001,38.599664],"type":"Point"}
}