{
  "type": "Feature",
  "properties": {
    "iso:country":"US",
    "sg:address":"1 NW 106th Ter",
    "sg:city":"Kansas City",
    "sg:classifiers":[
        {
            "category":"Professional",
            "subcategory":"Accounting & Tax Preparation",
            "type":"Services"
        }
    ],
    "sg:phone":"+1 816 734 2700",
    "sg:postcode":"64155",
    "sg:province":"MO",
    "wof:name":"No Te Business Services",
    "wof:placetype":"venue"
},
  "geometry": {"coordinates":[-94.581638,39.286505],"type":"Point"}
}