{
  "type": "Feature",
  "properties": {
    "iso:country":"US",
    "sg:address":"4372 Owens Dr",
    "sg:city":"St Louis",
    "sg:classifiers":[
        {
            "category":"Personal",
            "type":"Services"
        },
        {
            "category":"Personal",
            "subcategory":"Beauty Salon",
            "type":"Services"
        }
    ],
    "sg:phone":"+1 314 894 5517",
    "sg:postcode":"63128",
    "sg:province":"MO",
    "sg:tags":[
        "shop",
        "electrologist"
    ],
    "wof:name":"Allied Health Associates",
    "wof:placetype":"venue"
},
  "geometry": {"coordinates":[-90.368841,38.4758],"type":"Point"}
}