{
  "type": "Feature",
  "properties": {
    "addr:full":"416 Northland Dr Cameron MO 64429",
    "addr:housenumber":"416",
    "addr:postcode":"64429",
    "addr:street":"Northland Dr",
    "iso:country":"US",
    "sg:address":"416 Northland Dr",
    "sg:city":"Cameron",
    "sg:classifiers":[
        {
            "category":"Wholesale",
            "subcategory":"Farm Supplies",
            "type":"Manufacturing & Wholesale Goods"
        }
    ],
    "sg:phone":"+1 816 632 3258",
    "sg:postcode":"64429",
    "sg:province":"MO",
    "wof:name":"Orscheln Farm & Home",
    "wof:placetype":"venue"
},
  "geometry": {"coordinates":[-94.234246,39.750817],"type":"Point"}
}