{
  "type": "Feature",
  "properties": {
    "iso:country":"US",
    "sg:address":"2111 Bentley Plz",
    "sg:city":"Fenton",
    "sg:classifiers":[
        {
            "category":"Freight",
            "type":"Transportation"
        }
    ],
    "sg:phone":"+1 636 825 0707",
    "sg:postcode":"63026",
    "sg:province":"MO",
    "sg:tags":[
        "trucking"
    ],
    "wof:name":"Intermodal Transport Logistics",
    "wof:placetype":"venue"
},
  "geometry": {"coordinates":[-90.492924,38.532505],"type":"Point"}
}