{
  "type": "Feature",
  "properties": {
    "iso:country":"US",
    "sg:address":"147 S Main St",
    "sg:city":"Laurie",
    "sg:classifiers":[
        {
            "category":"Real Estate",
            "subcategory":"Real Estate Agent",
            "type":"Services"
        }
    ],
    "sg:phone":"+1 573 374 5206",
    "sg:postcode":"65037",
    "sg:province":"MO",
    "sg:website":"www.realestate.com",
    "wof:name":"Re/Max At The Lake",
    "wof:placetype":"venue"
},
  "geometry": {"coordinates":[-92.831164,38.197317],"type":"Point"}
}