{
  "type": "Feature",
  "properties": {
    "iso:country":"US",
    "sg:address":"203 W Frank St",
    "sg:city":"Edgerton",
    "sg:classifiers":[
        {
            "category":"Personal",
            "type":"Services"
        }
    ],
    "sg:phone":"+1 816 790 3403",
    "sg:postcode":"64444",
    "sg:province":"MO",
    "wof:name":"CJS Tanning",
    "wof:placetype":"venue"
},
  "geometry": {"coordinates":[-94.630321,39.505563],"type":"Point"}
}