{
  "type": "Feature",
  "properties": {
    "iso:country":"US",
    "sg:address":"2012 Chapel Ridge Rd",
    "sg:city":"Columbia",
    "sg:classifiers":[
        {
            "category":"Recreation",
            "type":"Entertainment"
        }
    ],
    "sg:phone":"+1 573 875 7188",
    "sg:postcode":"65203",
    "sg:province":"MO",
    "sg:tags":[
        "instruction",
        "gymnastic"
    ],
    "wof:name":"Academy Of Fine Arts",
    "wof:placetype":"venue"
},
  "geometry": {"coordinates":[-92.385486,38.934483],"type":"Point"}
}