{
  "type": "Feature",
  "properties": {
    "iso:country":"US",
    "sg:address":"7823 Racine Dr",
    "sg:city":"Saint Louis",
    "sg:classifiers":[
        {
            "category":"Social Services",
            "subcategory":"Child Care",
            "type":"Services"
        }
    ],
    "sg:phone":"+1 314 727 1202",
    "sg:postcode":"63133",
    "sg:province":"MO",
    "sg:tags":[
        "day"
    ],
    "wof:name":"Mount Beulah Missionary Baptist Church & Academy",
    "wof:placetype":"venue"
},
  "geometry": {"coordinates":[-90.325897,38.682999],"type":"Point"}
}