{
  "type": "Feature",
  "properties": {
    "iso:country":"US",
    "sg:address":"901 NW 15 St",
    "sg:city":"Blue Springs",
    "sg:classifiers":[
        {
            "category":"Organizations",
            "subcategory":"Religious Organization",
            "type":"Services"
        }
    ],
    "sg:phone":"+1 816 228 2070",
    "sg:postcode":"64015",
    "sg:province":"MO",
    "sg:tags":[
        "church"
    ],
    "wof:name":"Jehovah's Witnesses",
    "wof:placetype":"venue"
},
  "geometry": {"coordinates":[-94.281121,39.026934],"type":"Point"}
}