{
  "type": "Feature",
  "properties": {
    "iso:country":"US",
    "sg:address":"111 E 1st St N",
    "sg:city":"Wright City",
    "sg:classifiers":[
        {
            "category":"Personal",
            "subcategory":"Beauty Salon",
            "type":"Services"
        }
    ],
    "sg:phone":"+1 636 745 3840",
    "sg:postcode":"63390",
    "sg:province":"MO",
    "wof:name":"Wright City Hair Fashions",
    "wof:placetype":"venue"
},
  "geometry": {"coordinates":[-91.019243,38.828009],"type":"Point"}
}