{
  "type": "Feature",
  "properties": {
    "iso:country":"US",
    "sg:address":"16005 NW 135th St",
    "sg:city":"Platte City",
    "sg:classifiers":[
        {
            "category":"Professional",
            "subcategory":"Business Services",
            "type":"Services"
        }
    ],
    "sg:phone":"+1 816 858 0165",
    "sg:postcode":"64079",
    "sg:province":"MO",
    "wof:name":"Avon Independent Sales Rep",
    "wof:placetype":"venue"
},
  "geometry": {"coordinates":[-94.766164,39.33851],"type":"Point"}
}