{
  "type": "Feature",
  "properties": {
    "iso:country":"US",
    "sg:address":"905 E Langsford Rd",
    "sg:city":"Lees Summit",
    "sg:classifiers":[
        {
            "category":"Retail",
            "subcategory":"Laundry & Dry Cleaning",
            "type":"Services"
        }
    ],
    "sg:phone":"+1 816 524 2599",
    "sg:postcode":"64063",
    "sg:province":"MO",
    "sg:tags":[
        "cleaners",
        "plant",
        "drycleaning"
    ],
    "wof:name":"Fosters Cleaners & Shirt Ldry",
    "wof:placetype":"venue"
},
  "geometry": {"coordinates":[-94.36066,38.917495],"type":"Point"}
}