{
  "type": "Feature",
  "properties": {
    "iso:country":"US",
    "sg:address":"156 Gray Ave",
    "sg:city":"Saint Louis",
    "sg:classifiers":[
        {
            "category":"Health Services",
            "subcategory":"Doctor",
            "type":"Services"
        }
    ],
    "sg:phone":"+1 314 963 1996",
    "sg:postcode":"63119",
    "sg:province":"MO",
    "sg:tags":[
        "medical"
    ],
    "wof:name":"R Brasington MD",
    "wof:placetype":"venue"
},
  "geometry": {"coordinates":[-90.36137100000001,38.590304],"type":"Point"}
}