{
  "type": "Feature",
  "properties": {
    "addr:full":"1018 Missouri Ave St Robert MO 65584",
    "addr:housenumber":"1018",
    "addr:postcode":"65584",
    "addr:street":"Missouri Ave St",
    "iso:country":"US",
    "sg:address":"1018 Missouri Ave",
    "sg:city":"St Robert",
    "sg:classifiers":[
        {
            "category":"Restaurant",
            "type":"Food & Drink"
        }
    ],
    "sg:phone":"+1 573 336 5922",
    "sg:postcode":"65584",
    "sg:province":"MO",
    "wof:name":"Subway Sandwiches & Salads",
    "wof:placetype":"venue"
},
  "geometry": {"coordinates":[-92.13609700000001,37.796037],"type":"Point"}
}