{
  "type": "Feature",
  "properties": {
    "iso:country":"US",
    "sg:address":"167 Mockingbird Ln",
    "sg:city":"Cape Girardeau",
    "sg:classifiers":[
        {
            "category":"Building & Trades",
            "subcategory":"Landscaping Services",
            "type":"Services"
        }
    ],
    "sg:phone":"+1 573 335 7484",
    "sg:postcode":"63701",
    "sg:province":"MO",
    "sg:tags":[
        "landscape"
    ],
    "wof:name":"Overbeck Enterprises",
    "wof:placetype":"venue"
},
  "geometry": {"coordinates":[-89.643478,37.261202],"type":"Point"}
}