{
  "type": "Feature",
  "properties": {
    "iso:country":"US",
    "sg:address":"13354 Manchester Rd",
    "sg:city":"Saint Louis",
    "sg:classifiers":[
        {
            "category":"Professional",
            "subcategory":"Employment Agencies",
            "type":"Services"
        }
    ],
    "sg:phone":"+1 314 965 1617",
    "sg:postcode":"63131",
    "sg:province":"MO",
    "sg:tags":[
        "temporary",
        "staffing"
    ],
    "wof:name":"First Call Team Inc",
    "wof:placetype":"venue"
},
  "geometry": {"coordinates":[-90.46720000000001,38.60026],"type":"Point"}
}