{
  "type": "Feature",
  "properties": {
    "iso:country":"US",
    "sg:address":"441 NW Highway 7",
    "sg:city":"Clinton",
    "sg:classifiers":[
        {
            "category":"Manufacturing",
            "subcategory":"Food",
            "type":"Manufacturing & Wholesale Goods"
        },
        {
            "category":"Farming",
            "subcategory":"Farm",
            "type":"Manufacturing & Wholesale Goods"
        }
    ],
    "sg:phone":"+1 660 885 4508",
    "sg:postcode":"64735",
    "sg:province":"MO",
    "sg:tags":[
        "corn",
        "product"
    ],
    "wof:name":"Robert White",
    "wof:placetype":"venue"
},
  "geometry": {"coordinates":[-93.834824,38.399799],"type":"Point"}
}