{
  "type": "Feature",
  "properties": {
    "iso:country":"US",
    "sg:address":"1200 E 6th St",
    "sg:city":"Sedalia",
    "sg:classifiers":[
        {
            "category":"Personal",
            "subcategory":"Beauty Salon",
            "type":"Services"
        }
    ],
    "sg:phone":"+1 660 826 5510",
    "sg:postcode":"65301",
    "sg:province":"MO",
    "wof:name":"Majestic Beauty Salon",
    "wof:placetype":"venue"
},
  "geometry": {"coordinates":[-93.21345599999999,38.705442],"type":"Point"}
}