{
  "type": "Feature",
  "properties": {
    "iso:country":"US",
    "sg:address":"19630 State Hwy Dd",
    "sg:city":"Crocker",
    "sg:classifiers":[
        {
            "category":"Shopping",
            "subcategory":"Hobbies, Toys, & Games",
            "type":"Retail Goods"
        }
    ],
    "sg:phone":"+1 573 736 2708",
    "sg:postcode":"65452",
    "sg:province":"MO",
    "sg:tags":[
        "equipment",
        "ceramic",
        "supply"
    ],
    "wof:name":"Lilee Ceramics",
    "wof:placetype":"venue"
},
  "geometry": {"coordinates":[-92.20165900000001,37.90699],"type":"Point"}
}