{
  "type": "Feature",
  "properties": {
    "iso:country":"US",
    "sg:address":"2120 Parkway Dr",
    "sg:city":"Saint Peters",
    "sg:classifiers":[
        {
            "category":"Government",
            "subcategory":"Office",
            "type":"Public Place"
        }
    ],
    "sg:phone":"+1 636 926 1150",
    "sg:postcode":"63376",
    "sg:province":"MO",
    "sg:tags":[
        "division",
        "security",
        "employment"
    ],
    "wof:name":"Division Work Force Dev",
    "wof:placetype":"venue"
},
  "geometry": {"coordinates":[-90.572953,38.79757],"type":"Point"}
}