{
  "type": "Feature",
  "properties": {
    "iso:country":"US",
    "sg:address":"16260 Truman Rd",
    "sg:city":"Ballwin",
    "sg:classifiers":[
        {
            "category":"Banks & Credit Unions",
            "subcategory":"Bank",
            "type":"Services"
        }
    ],
    "sg:phone":"+1 314 298 0055",
    "sg:postcode":"63011",
    "sg:province":"MO",
    "sg:tags":[
        "state"
    ],
    "wof:name":"Vantage Credit Union",
    "wof:placetype":"venue"
},
  "geometry": {"coordinates":[-90.608204,38.588157],"type":"Point"}
}