{
  "type": "Feature",
  "properties": {
    "iso:country":"US",
    "sg:address":"4258 Countryside Ct",
    "sg:city":"Fulton",
    "sg:classifiers":[
        {
            "category":"Education",
            "subcategory":"Special Training",
            "type":"Public Place"
        }
    ],
    "sg:phone":"+1 573 642 8169",
    "sg:postcode":"65251",
    "sg:province":"MO",
    "wof:name":"Mathematics Consultant",
    "wof:placetype":"venue"
},
  "geometry": {"coordinates":[-92.137175,38.908504],"type":"Point"}
}