{
  "type": "Feature",
  "properties": {
    "iso:country":"US",
    "sg:address":"7409 N Wabash Ave",
    "sg:city":"Kansas City",
    "sg:classifiers":[
        {
            "category":"Shopping",
            "subcategory":"Books",
            "type":"Retail Goods"
        }
    ],
    "sg:phone":"+1 816 436 5228",
    "sg:postcode":"64118",
    "sg:province":"MO",
    "wof:name":"Academic Book Services",
    "wof:placetype":"venue"
},
  "geometry": {"coordinates":[-94.549604,39.229152],"type":"Point"}
}