{
  "type": "Feature",
  "properties": {
    "iso:country":"US",
    "sg:address":"1417 N Market St",
    "sg:city":"Saint Louis",
    "sg:classifiers":[
        {
            "category":"Real Estate",
            "subcategory":"Architect",
            "type":"Services"
        }
    ],
    "sg:phone":"+1 314 588 9920",
    "sg:postcode":"63106",
    "sg:province":"MO",
    "wof:name":"Fff Architectural Enterprises",
    "wof:placetype":"venue"
},
  "geometry": {"coordinates":[-90.196781,38.648016],"type":"Point"}
}