{
  "type": "Feature",
  "properties": {
    "iso:country":"US",
    "sg:address":"1728 Rudder Industrial Park Dr",
    "sg:city":"Fenton",
    "sg:classifiers":[
        {
            "category":"Building & Trades",
            "subcategory":"Plumbing",
            "type":"Services"
        }
    ],
    "sg:phone":"+1 636 349 6023",
    "sg:postcode":"63026",
    "sg:province":"MO",
    "sg:tags":[
        "conditioning",
        "air",
        "system",
        "contractor"
    ],
    "wof:name":"MMI",
    "wof:placetype":"venue"
},
  "geometry": {"coordinates":[-90.45277400000001,38.540925],"type":"Point"}
}