{
  "type": "Feature",
  "properties": {
    "iso:country":"US",
    "sg:address":"4022 S Broadway",
    "sg:city":"Saint Louis",
    "sg:classifiers":[
        {
            "category":"Personal",
            "subcategory":"Barber",
            "type":"Services"
        }
    ],
    "sg:phone":"+1 314 457 9708",
    "sg:postcode":"63118",
    "sg:province":"MO",
    "wof:name":"Off Broadway Barber & Beauty Salon",
    "wof:placetype":"venue"
},
  "geometry": {"coordinates":[-90.227709,38.581744],"type":"Point"}
}