{
  "type": "Feature",
  "properties": {
    "iso:country":"US",
    "sg:address":"113 Blue Jay Dr",
    "sg:city":"Liberty",
    "sg:classifiers":[
        {
            "category":"Place Of Worship",
            "type":"Public Place"
        }
    ],
    "sg:phone":"+1 816 479 2903",
    "sg:postcode":"64068",
    "sg:province":"MO",
    "sg:tags":[
        "church"
    ],
    "wof:name":"New Hope Counseling Associates",
    "wof:placetype":"venue"
},
  "geometry": {"coordinates":[-94.44898999999999,39.243481],"type":"Point"}
}