{
  "type": "Feature",
  "properties": {
    "iso:country":"US",
    "sg:address":"1705 S Broadway",
    "sg:city":"Saint Louis",
    "sg:classifiers":[
        {
            "category":"Professional",
            "subcategory":"Employment Agencies",
            "type":"Services"
        }
    ],
    "sg:phone":"+1 314 802 7005",
    "sg:postcode":"63104",
    "sg:province":"MO",
    "wof:name":"Ur Way Employment Agency",
    "wof:placetype":"venue"
},
  "geometry": {"coordinates":[-90.199679,38.609041],"type":"Point"}
}