{
  "type": "Feature",
  "properties": {
    "iso:country":"US",
    "sg:address":"514 Karen Dr",
    "sg:city":"Holts Summit",
    "sg:classifiers":[
        {
            "category":"Building & Trades",
            "subcategory":"Construction",
            "type":"Services"
        }
    ],
    "sg:phone":"+1 573 896 4183",
    "sg:postcode":"65043",
    "sg:province":"MO",
    "sg:tags":[
        "sewer",
        "contractor"
    ],
    "wof:name":"City-Holts Summit Sewer Dept",
    "wof:placetype":"venue"
},
  "geometry": {"coordinates":[-92.118033,38.641436],"type":"Point"}
}