{
  "type": "Feature",
  "properties": {
    "iso:country":"US",
    "sg:address":"590 Weiss Rd",
    "sg:city":"Saint Peters",
    "sg:classifiers":[
        {
            "category":"Building & Trades",
            "subcategory":"Construction",
            "type":"Services"
        }
    ],
    "sg:phone":"+1 636 240 3929",
    "sg:postcode":"63376",
    "sg:province":"MO",
    "sg:tags":[
        "house"
    ],
    "wof:name":"New Castle Custom Builders LLC",
    "wof:placetype":"venue"
},
  "geometry": {"coordinates":[-90.65892599999999,38.762289],"type":"Point"}
}