{
  "type": "Feature",
  "properties": {
    "iso:country":"US",
    "sg:address":"7265 Co Rd 336",
    "sg:city":"Palmyra",
    "sg:phone":"+1 573 769 2874",
    "sg:postcode":"63461",
    "sg:province":"MO",
    "sg:tags":[
        "farm",
        "corn",
        "soybean"
    ],
    "wof:name":"Brent Hoerr Farms Inc",
    "wof:placetype":"venue"
},
  "geometry": {"coordinates":[-91.50474,39.866492],"type":"Point"}
}