{
  "type": "Feature",
  "properties": {
    "iso:country":"US",
    "sg:address":"1279 Rehmert Rd",
    "sg:city":"Bland",
    "sg:classifiers":[
        {
            "category":"Professional",
            "subcategory":"Business Services",
            "type":"Services"
        }
    ],
    "sg:phone":"+1 573 646 3680",
    "sg:postcode":"65014",
    "sg:province":"MO",
    "sg:tags":[
        "auctioneer"
    ],
    "wof:name":"Roger Stockton Auction Svc",
    "wof:placetype":"venue"
},
  "geometry": {"coordinates":[-91.588115,38.326132],"type":"Point"}
}