{
  "type": "Feature",
  "properties": {
    "iso:country":"US",
    "sg:address":"3610 S 42nd Ter",
    "sg:city":"Saint Joseph",
    "sg:classifiers":[
        {
            "category":"Real Estate",
            "subcategory":"Real Estate Operator",
            "type":"Services"
        }
    ],
    "sg:phone":"+1 816 279 9874",
    "sg:postcode":"64503",
    "sg:province":"MO",
    "sg:tags":[
        "property",
        "lessor"
    ],
    "wof:name":"Mika 2 Farms Inc",
    "wof:placetype":"venue"
},
  "geometry": {"coordinates":[-94.793589,39.7311],"type":"Point"}
}