{
  "type": "Feature",
  "properties": {
    "iso:country":"US",
    "sg:address":"1300 Grand Ave",
    "sg:city":"Cuba",
    "sg:classifiers":[
        {
            "category":"Organizations",
            "subcategory":"Religious Organization",
            "type":"Services"
        }
    ],
    "sg:phone":"+1 573 885 2491",
    "sg:postcode":"65453",
    "sg:province":"MO",
    "sg:tags":[
        "church"
    ],
    "wof:name":"United Pentecostal Church",
    "wof:placetype":"venue"
},
  "geometry": {"coordinates":[-91.389824,38.066525],"type":"Point"}
}