{
  "type": "Feature",
  "properties": {
    "iso:country":"US",
    "sg:address":"2566 S Brentwood Blvd",
    "sg:city":"Saint Louis",
    "sg:classifiers":[
        {
            "category":"Manufacturing",
            "subcategory":"Signs",
            "type":"Manufacturing & Wholesale Goods"
        }
    ],
    "sg:phone":"+1 314 878 0066",
    "sg:postcode":"63144",
    "sg:province":"MO",
    "sg:tags":[
        "specialty",
        "mfg"
    ],
    "wof:name":"Fastsigns",
    "wof:placetype":"venue"
},
  "geometry": {"coordinates":[-90.34855399999999,38.616397],"type":"Point"}
}