{
  "type": "Feature",
  "properties": {
    "iso:country":"US",
    "sg:address":"2925 N Belt Hwy",
    "sg:city":"Saint Joseph",
    "sg:classifiers":[
        {
            "category":"Shopping",
            "subcategory":"Optical Goods",
            "type":"Retail Goods"
        }
    ],
    "sg:phone":"+1 816 364 0450",
    "sg:postcode":"64506",
    "sg:province":"MO",
    "wof:name":"Grier Andrea Od",
    "wof:placetype":"venue"
},
  "geometry": {"coordinates":[-94.80815800000001,39.789961],"type":"Point"}
}