{
  "type": "Feature",
  "properties": {
    "iso:country":"US",
    "sg:address":"4 NE 1st Ln",
    "sg:city":"Lamar",
    "sg:classifiers":[
        {
            "category":"Retail",
            "subcategory":"Veterinary Services",
            "type":"Services"
        }
    ],
    "sg:phone":"+1 417 682 3611",
    "sg:postcode":"64759",
    "sg:province":"MO",
    "wof:name":"All Creatures and Small",
    "wof:placetype":"venue"
},
  "geometry": {"coordinates":[-94.29744599999999,37.508254],"type":"Point"}
}