{
  "type": "Feature",
  "properties": {
    "iso:country":"US",
    "sg:address":"2118 Michigan Ave",
    "sg:city":"Arnold",
    "sg:classifiers":[
        {
            "category":"Retail",
            "subcategory":"Car Wash",
            "type":"Services"
        },
        {
            "category":"Manufacturing",
            "subcategory":"Glass & Minerals",
            "type":"Manufacturing & Wholesale Goods"
        },
        {
            "category":"Retail",
            "subcategory":"Auto Repair",
            "type":"Services"
        }
    ],
    "sg:phone":"+1 636 296 6571",
    "sg:postcode":"63010",
    "sg:province":"MO",
    "sg:tags":[
        "body",
        "plate",
        "classic",
        "scooters-repairing",
        "automobile",
        "detailing",
        "glass-auto",
        "window",
        "motorcycle",
        "motor",
        "painting",
        "repairing",
        "restoration-antique"
    ],
    "sg:website":"http://www.autobodys-unlimited.com/",
    "wof:name":"Auto Bodies Unlimited",
    "wof:placetype":"venue"
},
  "geometry": {"coordinates":[-90.380608,38.435928],"type":"Point"}
}