{
  "type": "Feature",
  "properties": {
    "iso:country":"US",
    "sg:address":"309 Rb Rd",
    "sg:city":"Stockton",
    "sg:classifiers":[
        {
            "category":"Social Services",
            "subcategory":"Job Training",
            "type":"Services"
        }
    ],
    "sg:phone":"+1 417 276 2401",
    "sg:postcode":"65785",
    "sg:province":"MO",
    "sg:tags":[
        "rehabilitation"
    ],
    "wof:name":"Stockton Rehabilitation Clinic",
    "wof:placetype":"venue"
},
  "geometry": {"coordinates":[-93.794633,37.686684],"type":"Point"}
}