{
  "type": "Feature",
  "properties": {
    "iso:country":"US",
    "sg:address":"616 S Main St",
    "sg:city":"Palmyra",
    "sg:classifiers":[
        {
            "category":"Social Services",
            "subcategory":"Child Care",
            "type":"Services"
        }
    ],
    "sg:phone":"+1 573 769 2847",
    "sg:postcode":"63461",
    "sg:province":"MO",
    "sg:tags":[
        "day"
    ],
    "wof:name":"Cuddle Bugs Daycare",
    "wof:placetype":"venue"
},
  "geometry": {"coordinates":[-91.52318200000001,39.795041],"type":"Point"}
}