{
  "type": "Feature",
  "properties": {
    "iso:country":"US",
    "sg:address":"3742 Broadway St",
    "sg:city":"Kansas City",
    "sg:classifiers":[
        {
            "category":"Restaurant",
            "type":"Food & Drink"
        }
    ],
    "sg:phone":"+1 816 561 1099",
    "sg:postcode":"64111",
    "sg:province":"MO",
    "sg:tags":[
        "drinking",
        "eating"
    ],
    "wof:name":"Newsroom",
    "wof:placetype":"venue"
},
  "geometry": {"coordinates":[-94.590722,39.059122],"type":"Point"}
}