{
  "type": "Feature",
  "properties": {
    "iso:country":"US",
    "sg:address":"4 Harris Ct",
    "sg:city":"Cedar Hill",
    "sg:classifiers":[
        {
            "category":"Building & Trades",
            "subcategory":"Construction",
            "type":"Services"
        }
    ],
    "sg:phone":"+1 636 274 3807",
    "sg:postcode":"63016",
    "sg:province":"MO",
    "sg:tags":[
        "house"
    ],
    "wof:name":"CT Decorating & Remodeling",
    "wof:placetype":"venue"
},
  "geometry": {"coordinates":[-90.645782,38.367999],"type":"Point"}
}