{
  "type": "Feature",
  "properties": {
    "iso:country":"US",
    "sg:address":"4859 Greenwood Acres",
    "sg:city":"Imperial",
    "sg:classifiers":[
        {
            "category":"Transit Center",
            "subcategory":"Freight",
            "type":"Transportation"
        },
        {
            "category":"Freight",
            "type":"Transportation"
        }
    ],
    "sg:phone":"+1 314 657 7154",
    "sg:postcode":"63052",
    "sg:province":"MO",
    "sg:tags":[
        "local",
        "trucking-motor",
        "trucking"
    ],
    "wof:name":"Yar Co",
    "wof:placetype":"venue"
},
  "geometry": {"coordinates":[-90.491829,38.401611],"type":"Point"}
}