{
  "type": "Feature",
  "properties": {
    "iso:country":"US",
    "sg:address":"1009 E Pearce Blvd",
    "sg:city":"Wentzville",
    "sg:classifiers":[
        {
            "category":"Restaurant",
            "type":"Food & Drink"
        }
    ],
    "sg:phone":"+1 636 327 6992",
    "sg:postcode":"63385",
    "sg:province":"MO",
    "wof:name":"Pete's Drive-In",
    "wof:placetype":"venue"
},
  "geometry": {"coordinates":[-90.84474899999999,38.813532],"type":"Point"}
}