{
  "type": "Feature",
  "properties": {
    "iso:country":"US",
    "sg:address":"4322 Aldine Ave",
    "sg:city":"Saint Louis",
    "sg:classifiers":[
        {
            "category":"Education",
            "subcategory":"School",
            "type":"Public Place"
        }
    ],
    "sg:phone":"+1 314 652 4951",
    "sg:postcode":"63113",
    "sg:province":"MO",
    "wof:name":"Marshall Branch School No 1",
    "wof:placetype":"venue"
},
  "geometry": {"coordinates":[-90.243118,38.656597],"type":"Point"}
}