{
  "type": "Feature",
  "properties": {
    "iso:country":"US",
    "sg:address":"2500 Tomahawk Dr",
    "sg:city":"Arnold",
    "sg:classifiers":[
        {
            "category":"Education",
            "subcategory":"School",
            "type":"Public Place"
        }
    ],
    "sg:phone":"+1 636 282 1470",
    "sg:postcode":"63010",
    "sg:province":"MO",
    "wof:name":"Lone Dell Elementary School",
    "wof:placetype":"venue"
},
  "geometry": {"coordinates":[-90.417834,38.429838],"type":"Point"}
}