{
  "type": "Feature",
  "properties": {
    "iso:country":"US",
    "sg:address":"4002 Potomac St",
    "sg:city":"St Louis",
    "sg:classifiers":[
        {
            "category":"Personal",
            "subcategory":"Beauty Salon",
            "type":"Services"
        }
    ],
    "sg:phone":"+1 314 773 3033",
    "sg:postcode":"63116",
    "sg:province":"MO",
    "wof:name":"Eva Marie's Beauty Shop",
    "wof:placetype":"venue"
},
  "geometry": {"coordinates":[-90.25638600000001,38.594911],"type":"Point"}
}