{
  "type": "Feature",
  "properties": {
    "iso:country":"US",
    "sg:address":"3205 N Twyman Rd",
    "sg:city":"Independence",
    "sg:classifiers":[
        {
            "category":"Organizations",
            "subcategory":"Non-profit Organization",
            "type":"Services"
        }
    ],
    "sg:phone":"+1 816 650 4058",
    "sg:postcode":"64058",
    "sg:province":"MO",
    "wof:name":"Sky's The Limit",
    "wof:placetype":"venue"
},
  "geometry": {"coordinates":[-94.30254600000001,39.155196],"type":"Point"}
}