{
  "type": "Feature",
  "properties": {
    "iso:country":"US",
    "sg:address":"2923 Lemay Ferry Rd",
    "sg:city":"St Louis",
    "sg:classifiers":[
        {
            "category":"Wholesale",
            "subcategory":"Computers",
            "type":"Manufacturing & Wholesale Goods"
        },
        {
            "category":"Professional",
            "subcategory":"Computer Services",
            "type":"Services"
        }
    ],
    "sg:phone":"+1 314 845 7222",
    "sg:postcode":"63125",
    "sg:province":"MO",
    "sg:tags":[
        "consultant",
        "designer",
        "education",
        "system",
        "provides"
    ],
    "wof:name":"Edutec Resources Inc",
    "wof:placetype":"venue"
},
  "geometry": {"coordinates":[-90.312324,38.515814],"type":"Point"}
}