{
  "type": "Feature",
  "properties": {
    "iso:country":"US",
    "sg:address":"394 State Hwy 19",
    "sg:city":"Montgomery City",
    "sg:classifiers":[
        {
            "category":"Education",
            "subcategory":"School",
            "type":"Public Place"
        }
    ],
    "sg:phone":"+1 573 564 2278",
    "sg:postcode":"63361",
    "sg:province":"MO",
    "sg:tags":[
        "high"
    ],
    "sg:website":"www.mc-wildcats.org",
    "wof:name":"Mongomery County High School",
    "wof:placetype":"venue"
},
  "geometry": {"coordinates":[-91.501841,38.973792],"type":"Point"}
}