{
  "type": "Feature",
  "properties": {
    "iso:country":"US",
    "sg:address":"316 N Ken Ave",
    "sg:city":"Springfield",
    "sg:classifiers":[
        {
            "category":"Organizations",
            "subcategory":"Religious Organization",
            "type":"Services"
        }
    ],
    "sg:phone":"+1 417 865 9159",
    "sg:postcode":"65802",
    "sg:province":"MO",
    "sg:tags":[
        "church"
    ],
    "wof:name":"New Hope Baptist Church",
    "wof:placetype":"venue"
},
  "geometry": {"coordinates":[-93.2383,37.209669],"type":"Point"}
}