{
  "type": "Feature",
  "properties": {
    "iso:country":"US",
    "sg:address":"1302 Clarkson Clayton Center",
    "sg:city":"Ellisville",
    "sg:classifiers":[
        {
            "category":"Professional",
            "subcategory":"Employment Agencies",
            "type":"Services"
        }
    ],
    "sg:phone":"+1 636 527 2882",
    "sg:postcode":"63011",
    "sg:province":"MO",
    "sg:tags":[
        "opportunity"
    ],
    "wof:name":"Bonacare",
    "wof:placetype":"venue"
},
  "geometry": {"coordinates":[-90.58651,38.603385],"type":"Point"}
}