{
  "type": "Feature",
  "properties": {
    "iso:country":"US",
    "sg:address":"4146 Garfield Ave",
    "sg:city":"St Louis",
    "sg:classifiers":[
        {
            "category":"Social Services",
            "subcategory":"Child Care",
            "type":"Services"
        }
    ],
    "sg:phone":"+1 314 535 9501",
    "sg:postcode":"63113",
    "sg:province":"MO",
    "sg:tags":[
        "kindergarten",
        "academic",
        "school"
    ],
    "wof:name":"YWCA St Louis Head Start",
    "wof:placetype":"venue"
},
  "geometry": {"coordinates":[-90.236842,38.655941],"type":"Point"}
}