{
  "type": "Feature",
  "properties": {
    "iso:country":"US",
    "sg:address":"9450 Manchester Rd",
    "sg:city":"Saint Louis",
    "sg:classifiers":[
        {
            "category":"Real Estate",
            "subcategory":"Developer",
            "type":"Services"
        }
    ],
    "sg:phone":"+1 314 962 2400",
    "sg:postcode":"63119",
    "sg:province":"MO",
    "sg:tags":[
        "commercial",
        "administration",
        "contract",
        "for"
    ],
    "wof:name":"Mills Corporation",
    "wof:placetype":"venue"
},
  "geometry": {"coordinates":[-90.362574,38.609718],"type":"Point"}
}