{
  "type": "Feature",
  "properties": {
    "iso:country":"US",
    "sg:address":"135 Linda Ln",
    "sg:city":"Union",
    "sg:classifiers":[
        {
            "category":"Retail",
            "subcategory":"Portrait Studio",
            "type":"Services"
        }
    ],
    "sg:phone":"+1 636 583 8736",
    "sg:postcode":"63084",
    "sg:province":"MO",
    "sg:tags":[
        "laboratory",
        "photofinishing",
        "photo"
    ],
    "wof:name":"Gaugh Photography",
    "wof:placetype":"venue"
},
  "geometry": {"coordinates":[-90.98866599999999,38.452835],"type":"Point"}
}