{
  "type": "Feature",
  "properties": {
    "iso:country":"US",
    "sg:address":"6510 NW Prairie View Rd",
    "sg:city":"Kansas City",
    "sg:classifiers":[
        {
            "category":"Banks & Credit Unions",
            "subcategory":"Bank",
            "type":"Services"
        }
    ],
    "sg:phone":"+1 816 746 4555",
    "sg:postcode":"64151",
    "sg:province":"MO",
    "sg:tags":[
        "state"
    ],
    "wof:name":"Bank Of Weston",
    "wof:placetype":"venue"
},
  "geometry": {"coordinates":[-94.642889,39.214381],"type":"Point"}
}