{
  "type": "Feature",
  "properties": {
    "iso:country":"US",
    "sg:address":"15305 Manchester Rd",
    "sg:city":"Ballwin",
    "sg:classifiers":[
        {
            "category":"Professional",
            "type":"Services"
        }
    ],
    "sg:phone":"+1 636 591 0108",
    "sg:postcode":"63011",
    "sg:province":"MO",
    "wof:name":"Feathered Friends",
    "wof:placetype":"venue"
},
  "geometry": {"coordinates":[-90.558256,38.592917],"type":"Point"}
}