{
  "type": "Feature",
  "properties": {
    "iso:country":"US",
    "sg:address":"3813 W State Highway 90",
    "sg:city":"Noel",
    "sg:classifiers":[
        {
            "category":"Personal",
            "subcategory":"Beauty Salon",
            "type":"Services"
        }
    ],
    "sg:phone":"+1 417 475 3305",
    "sg:postcode":"64854",
    "sg:province":"MO",
    "wof:name":"Charlies Shear Magic",
    "wof:placetype":"venue"
},
  "geometry": {"coordinates":[-94.37552,36.531978],"type":"Point"}
}