{
  "type": "Feature",
  "properties": {
    "iso:country":"US",
    "sg:address":"22874 S State Highway 47",
    "sg:city":"Warrenton",
    "sg:classifiers":[
        {
            "category":"Manufacturing",
            "subcategory":"Wood Products",
            "type":"Manufacturing & Wholesale Goods"
        }
    ],
    "sg:phone":"+1 636 456 5243",
    "sg:postcode":"63383",
    "sg:province":"MO",
    "sg:tags":[
        "woodworking"
    ],
    "wof:name":"O'neil Custom Mill Works",
    "wof:placetype":"venue"
},
  "geometry": {"coordinates":[-91.15187,38.735195],"type":"Point"}
}