{
  "type": "Feature",
  "properties": {
    "iso:country":"US",
    "sg:address":"112 Piper Hills Dr",
    "sg:city":"St Peters",
    "sg:classifiers":[
        {
            "category":"Government",
            "subcategory":"Office",
            "type":"Public Place"
        }
    ],
    "sg:phone":"+1 636 447 3185",
    "sg:postcode":"63376",
    "sg:province":"MO",
    "sg:tags":[
        "federal"
    ],
    "wof:name":"Us Social Security Admin",
    "wof:placetype":"venue"
},
  "geometry": {"coordinates":[-90.588077,38.794348],"type":"Point"}
}