{
  "type": "Feature",
  "properties": {
    "iso:country":"US",
    "sg:address":"5121 S Kingshighway Blvd",
    "sg:city":"Saint Louis",
    "sg:classifiers":[
        {
            "category":"Building & Trades",
            "subcategory":"Construction",
            "type":"Services"
        }
    ],
    "sg:phone":"+1 314 481 1677",
    "sg:postcode":"63109",
    "sg:province":"MO",
    "sg:tags":[
        "house"
    ],
    "wof:name":"Antons Home Remodeling",
    "wof:placetype":"venue"
},
  "geometry": {"coordinates":[-90.277995,38.582631],"type":"Point"}
}