{
  "type": "Feature",
  "properties": {
    "addr:full":"711 Gravois Rd Fenton MO 63026",
    "addr:housenumber":"711",
    "addr:postcode":"63026",
    "addr:street":"Gravois Rd",
    "iso:country":"US",
    "sg:address":"711 Gravois Rd",
    "sg:city":"Fenton",
    "sg:phone":"+1 636 326 4134",
    "sg:postcode":"63026",
    "sg:province":"MO",
    "sg:website":"http://www.chilis.com",
    "wof:name":"Chili's Grill & Bar",
    "wof:placetype":"venue"
},
  "geometry": {"coordinates":[-90.44508399999999,38.51194],"type":"Point"}
}