{
  "type": "Feature",
  "properties": {
    "iso:country":"US",
    "sg:address":"198 Main St",
    "sg:city":"Polo",
    "sg:classifiers":[
        {
            "category":"Restaurant",
            "type":"Food & Drink"
        },
        {
            "category":"Food & Beverages",
            "subcategory":"Groceries & Convenience Stores",
            "type":"Retail Goods"
        }
    ],
    "sg:menulink":"http://www.allmenus.com/mo/grant/225673-caseys-general-store/menu/",
    "sg:phone":"+1 660 354 2210",
    "sg:postcode":"64671",
    "sg:province":"MO",
    "sg:tags":[
        "american",
        "pizza"
    ],
    "wof:name":"Casey's General Store",
    "wof:placetype":"venue"
},
  "geometry": {"coordinates":[-94.03957699999999,39.557436],"type":"Point"}
}