{
  "type": "Feature",
  "properties": {
    "iso:country":"US",
    "sg:address":"636 N Main Ave",
    "sg:city":"Republic",
    "sg:classifiers":[
        {
            "category":"Autos & Motor Vehicles",
            "subcategory":"Automobile Sales",
            "type":"Retail Goods"
        },
        {
            "category":"Retail",
            "subcategory":"Auto Repair",
            "type":"Services"
        }
    ],
    "sg:phone":"+1 417 732 7277",
    "sg:postcode":"65738",
    "sg:province":"MO",
    "sg:tags":[
        "body",
        "used",
        "painting"
    ],
    "wof:name":"Midtown Motors",
    "wof:placetype":"venue"
},
  "geometry": {"coordinates":[-93.48022899999999,37.12647],"type":"Point"}
}