{
  "type": "Feature",
  "properties": {
    "iso:country":"US",
    "sg:address":"100 Osage Hills Rd",
    "sg:city":"Lake Ozark",
    "sg:classifiers":[
        {
            "category":"Travel",
            "subcategory":"Hotels & Motels",
            "type":"Entertainment"
        }
    ],
    "sg:phone":"+1 573 365 1100",
    "sg:postcode":"65049",
    "sg:province":"MO",
    "wof:name":"Osage National Condominiums",
    "wof:placetype":"venue"
},
  "geometry": {"coordinates":[-92.599396,38.207905],"type":"Point"}
}