{
  "type": "Feature",
  "properties": {
    "iso:country":"US",
    "sg:address":"9907 Gravois Rd",
    "sg:city":"St Louis",
    "sg:classifiers":[
        {
            "category":"Personal",
            "type":"Services"
        }
    ],
    "sg:phone":"+1 314 638 6070",
    "sg:postcode":"63123",
    "sg:province":"MO",
    "sg:tags":[
        "control",
        "weight"
    ],
    "sg:website":"www.oaregion4.org",
    "wof:name":"Overeaters Anonymous Oa",
    "wof:placetype":"venue"
},
  "geometry": {"coordinates":[-90.330223,38.550932],"type":"Point"}
}