{
  "type": "Feature",
  "properties": {
    "iso:country":"US",
    "sg:address":"3705 E Battlefield Rd",
    "sg:city":"Springfield",
    "sg:classifiers":[
        {
            "category":"Insurance",
            "subcategory":"Insurance Agent",
            "type":"Services"
        }
    ],
    "sg:phone":"+1 417 883 4828",
    "sg:postcode":"65809",
    "sg:province":"MO",
    "wof:name":"Crowley's Insurance",
    "wof:placetype":"venue"
},
  "geometry": {"coordinates":[-93.217769,37.157661],"type":"Point"}
}