{
  "type": "Feature",
  "properties": {
    "iso:country":"US",
    "sg:address":"915 Mallory St",
    "sg:city":"Dexter",
    "sg:classifiers":[
        {
            "category":"Building & Trades",
            "subcategory":"Equipment Rental",
            "type":"Services"
        }
    ],
    "sg:phone":"+1 573 624 4450",
    "sg:postcode":"63841",
    "sg:province":"MO",
    "sg:tags":[
        "contractor"
    ],
    "wof:name":"Dexter Tool Rental",
    "wof:placetype":"venue"
},
  "geometry": {"coordinates":[-89.973488,36.803871],"type":"Point"}
}