{
  "type": "Feature",
  "properties": {
    "iso:country":"US",
    "sg:address":"14101 E 198th St",
    "sg:city":"Peculiar",
    "sg:classifiers":[
        {
            "category":"Shopping",
            "subcategory":"Stationery & Office Supplies",
            "type":"Retail Goods"
        }
    ],
    "sg:phone":"+1 816 322 2130",
    "sg:postcode":"64078",
    "sg:province":"MO",
    "wof:name":"Takhomasak Inc",
    "wof:placetype":"venue"
},
  "geometry": {"coordinates":[-94.439346,38.761524],"type":"Point"}
}