{
  "type": "Feature",
  "properties": {
    "addr:full":"3625 Broadway St Kansas City MO 64111",
    "addr:housenumber":"3625",
    "addr:postcode":"64111",
    "addr:street":"Broadway St",
    "iso:country":"US",
    "sg:address":"3625 Broadway St",
    "sg:city":"Kansas City",
    "sg:classifiers":[
        {
            "category":"Cinema",
            "subcategory":"Movie Rental",
            "type":"Entertainment"
        }
    ],
    "sg:phone":"+1 816 931 1881",
    "sg:postcode":"64111",
    "sg:province":"MO",
    "sg:tags":[
        "leasing",
        "video",
        "disc",
        "tape"
    ],
    "sg:website":"www.blockbuster.com",
    "wof:name":"Blockbuster Video",
    "wof:placetype":"venue"
},
  "geometry": {"coordinates":[-94.59046499999999,39.062159],"type":"Point"}
}