{
  "type": "Feature",
  "properties": {
    "iso:country":"US",
    "sg:address":"6217 Morganford Rd",
    "sg:city":"Saint Louis",
    "sg:classifiers":[
        {
            "category":"Bars & Pubs",
            "subcategory":"Nightclub",
            "type":"Food & Drink"
        }
    ],
    "sg:phone":"+1 314 352 4465",
    "sg:postcode":"63116",
    "sg:province":"MO",
    "sg:tags":[
        "nightlife"
    ],
    "wof:name":"DOC Haus the",
    "wof:placetype":"venue"
},
  "geometry": {"coordinates":[-90.272797,38.570599],"type":"Point"}
}