{
  "type": "Feature",
  "properties": {
    "iso:country":"US",
    "sg:address":"23351 March Rd",
    "sg:city":"Centralia",
    "sg:phone":"+1 573 682 2829",
    "sg:postcode":"65240",
    "sg:province":"MO",
    "sg:tags":[
        "farm",
        "soybean"
    ],
    "wof:name":"Phillip March",
    "wof:placetype":"venue"
},
  "geometry": {"coordinates":[-92.161281,39.232488],"type":"Point"}
}