{
  "type": "Feature",
  "properties": {
    "iso:country":"US",
    "sg:address":"1609 Ronny Dr",
    "sg:city":"De Soto",
    "sg:classifiers":[
        {
            "category":"Real Estate",
            "subcategory":"Real Estate Operator",
            "type":"Services"
        }
    ],
    "sg:phone":"+1 636 586 2367",
    "sg:postcode":"63020",
    "sg:province":"MO",
    "sg:tags":[
        "building",
        "nonresidential"
    ],
    "wof:name":"Wolf Timber Properties LLC",
    "wof:placetype":"venue"
},
  "geometry": {"coordinates":[-90.574656,38.143751],"type":"Point"}
}