{
  "type": "Feature",
  "properties": {
    "iso:country":"US",
    "sg:address":"707 Hagny St",
    "sg:city":"Lamar",
    "sg:phone":"+1 417 682 5195",
    "sg:postcode":"64759",
    "sg:province":"MO",
    "sg:tags":[
        "farm",
        "wheat"
    ],
    "wof:name":"Ray Little",
    "wof:placetype":"venue"
},
  "geometry": {"coordinates":[-94.261455,37.498648],"type":"Point"}
}