{
  "type": "Feature",
  "properties": {
    "iso:country":"US",
    "sg:address":"507 E Harrison St",
    "sg:city":"Eldon",
    "sg:classifiers":[
        {
            "category":"Social Services",
            "type":"Services"
        }
    ],
    "sg:phone":"+1 573 392 6246",
    "sg:postcode":"65026",
    "sg:province":"MO",
    "sg:tags":[
        "profit",
        "aid"
    ],
    "wof:name":"Miller County Chapter",
    "wof:placetype":"venue"
},
  "geometry": {"coordinates":[-92.57565700000001,38.354783],"type":"Point"}
}