{
  "type": "Feature",
  "properties": {
    "iso:country":"US",
    "sg:address":"312 E Whippoorwill Dr",
    "sg:city":"Strafford",
    "sg:classifiers":[
        {
            "category":"Restaurant",
            "type":"Food & Drink"
        }
    ],
    "sg:phone":"+1 417 736 3355",
    "sg:postcode":"65757",
    "sg:province":"MO",
    "sg:tags":[
        "house",
        "steak",
        "barbecue"
    ],
    "wof:name":"Firehouse Bbq",
    "wof:placetype":"venue"
},
  "geometry": {"coordinates":[-93.110901,37.262192],"type":"Point"}
}