{
  "type": "Feature",
  "properties": {
    "iso:country":"US",
    "sg:address":"9816 E 87 St",
    "sg:city":"Raytown",
    "sg:classifiers":[
        {
            "category":"Real Estate",
            "subcategory":"Real Estate Agent",
            "type":"Services"
        }
    ],
    "sg:phone":"+1 816 358 7667",
    "sg:postcode":"64138",
    "sg:province":"MO",
    "wof:name":"Burton Realty",
    "wof:placetype":"venue"
},
  "geometry": {"coordinates":[-94.466461,38.96528],"type":"Point"}
}