{
  "type": "Feature",
  "properties": {
    "iso:country":"US",
    "sg:address":"2904 Weible Rd",
    "sg:city":"Bonne Terre",
    "sg:classifiers":[
        {
            "category":"Manufacturing",
            "subcategory":"Apparel",
            "type":"Manufacturing & Wholesale Goods"
        }
    ],
    "sg:phone":"+1 573 358 2151",
    "sg:postcode":"63628",
    "sg:province":"MO",
    "wof:name":"Initials & Ideas",
    "wof:placetype":"venue"
},
  "geometry": {"coordinates":[-90.507763,37.896133],"type":"Point"}
}