{
  "type": "Feature",
  "properties": {
    "iso:country":"US",
    "sg:address":"210 W Ohio St",
    "sg:city":"Butler",
    "sg:classifiers":[
        {
            "category":"Insurance",
            "subcategory":"Hazard Insurance",
            "type":"Services"
        },
        {
            "category":"Insurance",
            "subcategory":"Life Insurance",
            "type":"Services"
        }
    ],
    "sg:phone":"+1 660 679 5696",
    "sg:postcode":"64730",
    "sg:province":"MO",
    "wof:name":"Carol Ann Winburn",
    "wof:placetype":"venue"
},
  "geometry": {"coordinates":[-94.334391,38.25853],"type":"Point"}
}