{
  "type": "Feature",
  "properties": {
    "iso:country":"US",
    "sg:address":"381 NW State Hwy 131",
    "sg:city":"Holden",
    "sg:classifiers":[
        {
            "category":"Building & Trades",
            "subcategory":"Construction",
            "type":"Services"
        }
    ],
    "sg:phone":"+1 816 850 4942",
    "sg:postcode":"64040",
    "sg:province":"MO",
    "sg:tags":[
        "family",
        "commercial",
        "general",
        "bu",
        "home",
        "contractor"
    ],
    "wof:name":"Rockwell Construction Inc",
    "wof:placetype":"venue"
},
  "geometry": {"coordinates":[-93.99167199999999,38.83037],"type":"Point"}
}