{
  "type": "Feature",
  "properties": {
    "iso:country":"US",
    "sg:address":"17133 River Aux Vases Church Rd",
    "sg:city":"Sainte Genevieve",
    "sg:classifiers":[
        {
            "category":"Building & Trades",
            "subcategory":"Construction",
            "type":"Services"
        }
    ],
    "sg:phone":"+1 573 883 3210",
    "sg:postcode":"63670",
    "sg:province":"MO",
    "sg:tags":[
        "repair",
        "contractor"
    ],
    "wof:name":"Henderson Motor & Implement",
    "wof:placetype":"venue"
},
  "geometry": {"coordinates":[-90.13560699999999,37.87596],"type":"Point"}
}