{
  "type": "Feature",
  "properties": {
    "iso:country":"US",
    "sg:address":"4801 Woodfield Dr",
    "sg:city":"Saint Joseph",
    "sg:classifiers":[
        {
            "category":"Professional",
            "type":"Services"
        }
    ],
    "sg:phone":"+1 816 364 3963",
    "sg:postcode":"64506",
    "sg:province":"MO",
    "wof:name":"Roberts Professional Services",
    "wof:placetype":"venue"
},
  "geometry": {"coordinates":[-94.784796,39.772152],"type":"Point"}
}