{
  "type": "Feature",
  "properties": {
    "iso:country":"US",
    "sg:address":"706 S 5th St",
    "sg:city":"Clinton",
    "sg:classifiers":[
        {
            "category":"Organizations",
            "subcategory":"Religious Organization",
            "type":"Services"
        }
    ],
    "sg:phone":"+1 660 885 7936",
    "sg:postcode":"64735",
    "sg:province":"MO",
    "sg:tags":[
        "church"
    ],
    "wof:name":"Overcomers In Christ",
    "wof:placetype":"venue"
},
  "geometry": {"coordinates":[-93.768883,38.362969],"type":"Point"}
}