{
  "type": "Feature",
  "properties": {
    "iso:country":"US",
    "sg:address":"919 Oak Haven Dr",
    "sg:city":"Columbia",
    "sg:classifiers":[
        {
            "category":"Organizations",
            "subcategory":"Religious Organization",
            "type":"Services"
        }
    ],
    "sg:phone":"+1 573 449 1003",
    "sg:postcode":"65203",
    "sg:province":"MO",
    "wof:name":"George Floyd Rev",
    "wof:placetype":"venue"
},
  "geometry": {"coordinates":[-92.35301699999999,38.919254],"type":"Point"}
}