{
  "type": "Feature",
  "properties": {
    "iso:country":"US",
    "sg:address":"122 Hout St",
    "sg:city":"Warrensburg",
    "sg:classifiers":[
        {
            "category":"Professional",
            "subcategory":"Lawyer & Legal Services",
            "type":"Services"
        }
    ],
    "sg:phone":"+1 660 747 6335",
    "sg:postcode":"64093",
    "sg:province":"MO",
    "sg:tags":[
        "plan"
    ],
    "wof:name":"Robert L Welling Atty",
    "wof:placetype":"venue"
},
  "geometry": {"coordinates":[-93.740517,38.76476],"type":"Point"}
}