{
  "type": "Feature",
  "properties": {
    "iso:country":"US",
    "sg:address":"5050 Highland Ave",
    "sg:city":"Saint Louis",
    "sg:classifiers":[
        {
            "category":"Real Estate",
            "subcategory":"Real Estate Operator",
            "type":"Services"
        }
    ],
    "sg:phone":"+1 314 367 5050",
    "sg:postcode":"63113",
    "sg:province":"MO",
    "sg:tags":[
        "apartment"
    ],
    "wof:name":"Tower Village Apts",
    "wof:placetype":"venue"
},
  "geometry": {"coordinates":[-90.25900300000001,38.668598],"type":"Point"}
}