{
  "type": "Feature",
  "properties": {
    "iso:country":"US",
    "sg:address":"16541 US Hwy 67",
    "sg:city":"Neelyville",
    "sg:classifiers":[
        {
            "category":"Autos & Motor Vehicles",
            "subcategory":"Automobile Sales",
            "type":"Retail Goods"
        },
        {
            "category":"Autos & Motor Vehicles",
            "subcategory":"Motorcycle Sales",
            "type":"Retail Goods"
        }
    ],
    "sg:phone":"+1 573 989 3342",
    "sg:postcode":"63954",
    "sg:province":"MO",
    "sg:tags":[
        "golf",
        "mfg",
        "car",
        "cart",
        "equipment",
        "transportation"
    ],
    "wof:name":"Creach's Golf Carts",
    "wof:placetype":"venue"
},
  "geometry": {"coordinates":[-90.521201,36.554836],"type":"Point"}
}