{
  "type": "Feature",
  "properties": {
    "iso:country":"US",
    "sg:address":"1443 E Kearney St",
    "sg:city":"Springfield",
    "sg:classifiers":[
        {
            "category":"Home & Garden",
            "subcategory":"Household Appliances",
            "type":"Retail Goods"
        },
        {
            "category":"Building & Trades",
            "subcategory":"Cleaning & Sanitation",
            "type":"Services"
        },
        {
            "category":"Retail",
            "subcategory":"Repair Shop",
            "type":"Services"
        }
    ],
    "sg:phone":"+1 417 831 0013",
    "sg:postcode":"65803",
    "sg:province":"MO",
    "sg:tags":[
        "cleaners-industrial",
        "cleaners-repair",
        "commercial",
        "cleaners-household-dealers",
        "vacuum"
    ],
    "sg:website":"http://www.kearneystreetvacuums.com",
    "wof:name":"Kearney Street Vacuums",
    "wof:placetype":"venue"
},
  "geometry": {"coordinates":[-93.26897,37.240213],"type":"Point"}
}