{
  "type": "Feature",
  "properties": {
    "iso:country":"US",
    "sg:address":"1110 Scoville Place Ct",
    "sg:city":"Florissant",
    "sg:classifiers":[
        {
            "category":"Wholesale",
            "subcategory":"Metals & Minerals",
            "type":"Manufacturing & Wholesale Goods"
        }
    ],
    "sg:phone":"+1 314 831 6057",
    "sg:postcode":"63031",
    "sg:province":"MO",
    "sg:tags":[
        "steel",
        "warehouse",
        "center"
    ],
    "wof:name":"Alladinsteel",
    "wof:placetype":"venue"
},
  "geometry": {"coordinates":[-90.37918500000001,38.799414],"type":"Point"}
}