{
  "type": "Feature",
  "properties": {
    "iso:country":"US",
    "sg:address":"33 Short Rd",
    "sg:city":"Eldon",
    "sg:classifiers":[
        {
            "category":"Building & Trades",
            "subcategory":"Construction",
            "type":"Services"
        }
    ],
    "sg:phone":"+1 573 392 7463",
    "sg:postcode":"65026",
    "sg:province":"MO",
    "sg:tags":[
        "general",
        "contractor"
    ],
    "wof:name":"Ernie's Concrete Construction",
    "wof:placetype":"venue"
},
  "geometry": {"coordinates":[-92.467597,38.370815],"type":"Point"}
}