{
  "type": "Feature",
  "properties": {
    "iso:country":"US",
    "sg:address":"2544 NW Bent Tree Cir",
    "sg:city":"Lees Summit",
    "sg:classifiers":[
        {
            "category":"Retail",
            "subcategory":"Repair Shop",
            "type":"Services"
        },
        {
            "category":"Building & Trades",
            "subcategory":"Construction",
            "type":"Services"
        }
    ],
    "sg:phone":"+1 816 554 8585",
    "sg:postcode":"64081",
    "sg:province":"MO",
    "sg:tags":[
        "roofing",
        "contractor",
        "con",
        "carpentry"
    ],
    "wof:name":"Lee's Summit Roofing",
    "wof:placetype":"venue"
},
  "geometry": {"coordinates":[-94.431974,38.930425],"type":"Point"}
}