{
  "type": "Feature",
  "properties": {
    "iso:country":"US",
    "sg:address":"401 SW 7th St",
    "sg:city":"Concordia",
    "sg:classifiers":[
        {
            "category":"Professional",
            "type":"Services"
        }
    ],
    "sg:phone":"+1 660 463 7742",
    "sg:postcode":"64020",
    "sg:province":"MO",
    "wof:name":"Terry Schnakenberg",
    "wof:placetype":"venue"
},
  "geometry": {"coordinates":[-93.575383,38.983275],"type":"Point"}
}