{
  "type": "Feature",
  "properties": {
    "iso:country":"US",
    "sg:address":"14007 State Highway Ww",
    "sg:city":"Dudley",
    "sg:classifiers":[
        {
            "category":"Home & Garden",
            "subcategory":"Garden Supply",
            "type":"Retail Goods"
        }
    ],
    "sg:phone":"+1 573 624 4848",
    "sg:postcode":"63936",
    "sg:province":"MO",
    "sg:tags":[
        "horticulture",
        "product"
    ],
    "sg:website":"http://www.kevinjohns.net",
    "wof:name":"Kevin Johns",
    "wof:placetype":"venue"
},
  "geometry": {"coordinates":[-90.099189,36.819984],"type":"Point"}
}