{
  "type": "Feature",
  "properties": {
    "iso:country":"US",
    "sg:address":"5494 Brown Rd Suite 117",
    "sg:city":"Hazelwood",
    "sg:classifiers":[
        {
            "category":"Insurance",
            "subcategory":"Hazard Insurance",
            "type":"Services"
        },
        {
            "category":"Insurance",
            "subcategory":"Insurance Agent",
            "type":"Services"
        },
        {
            "category":"Insurance",
            "subcategory":"Life Insurance",
            "type":"Services"
        },
        {
            "category":"Insurance",
            "subcategory":"Title Insurance",
            "type":"Services"
        }
    ],
    "sg:phone":"+1 314 731 0293",
    "sg:postcode":"63042",
    "sg:province":"MO",
    "sg:tags":[
        "auto",
        "renter",
        "homeowner"
    ],
    "sg:website":"http://www.ShelterInsurance.com/CA/agent/RONHAMMONDS",
    "wof:name":"Shelter Insurance - Ron Hammonds",
    "wof:placetype":"venue"
},
  "geometry": {"coordinates":[-90.383402,38.781483],"type":"Point"}
}