{
  "type": "Feature",
  "properties": {
    "iso:country":"US",
    "sg:address":"18445 Edison Ave",
    "sg:city":"Chesterfield",
    "sg:classifiers":[
        {
            "category":"Airport",
            "type":"Transportation"
        }
    ],
    "sg:phone":"+1 636 537 3700",
    "sg:postcode":"63005",
    "sg:province":"MO",
    "sg:tags":[
        "charter",
        "flying",
        "instruction",
        "air"
    ],
    "wof:name":"Weiss Aviation Center",
    "wof:placetype":"venue"
},
  "geometry": {"coordinates":[-90.64526499999999,38.664127],"type":"Point"}
}