{
  "type": "Feature",
  "properties": {
    "iso:country":"US",
    "sg:address":"2710 Belle St",
    "sg:city":"Saint Joseph",
    "sg:classifiers":[
        {
            "category":"Organizations",
            "subcategory":"Religious Organization",
            "type":"Services"
        }
    ],
    "sg:phone":"+1 816 279 2432",
    "sg:postcode":"64503",
    "sg:province":"MO",
    "sg:tags":[
        "child",
        "care"
    ],
    "wof:name":"Mc Carthy Child Care Dev Ctr",
    "wof:placetype":"venue"
},
  "geometry": {"coordinates":[-94.826542,39.740403],"type":"Point"}
}