{
  "type": "Feature",
  "properties": {
    "iso:country":"US",
    "sg:address":"18132 Bent Ridge Dr",
    "sg:city":"Glencoe",
    "sg:classifiers":[
        {
            "category":"Building & Trades",
            "subcategory":"Landscaping Services",
            "type":"Services"
        }
    ],
    "sg:phone":"+1 636 458 1000",
    "sg:postcode":"63038",
    "sg:province":"MO",
    "sg:tags":[
        "lawn",
        "maintenance",
        "grounds"
    ],
    "wof:name":"Mitchell Lawn & Landscpg Inc",
    "wof:placetype":"venue"
},
  "geometry": {"coordinates":[-90.64039699999999,38.603545],"type":"Point"}
}