{
  "type": "Feature",
  "properties": {
    "iso:country":"US",
    "sg:address":"112 S Smith St",
    "sg:city":"Albany",
    "sg:classifiers":[
        {
            "category":"Shopping",
            "type":"Retail Goods"
        }
    ],
    "sg:phone":"+1 660 726 3354",
    "sg:postcode":"64402",
    "sg:province":"MO",
    "sg:tags":[
        "hearing",
        "equipment",
        "supply",
        "merchandise",
        "impaired"
    ],
    "wof:name":"New Concept Hearing Aid Co",
    "wof:placetype":"venue"
},
  "geometry": {"coordinates":[-94.332621,40.247762],"type":"Point"}
}