{
  "type": "Feature",
  "properties": {
    "iso:country":"US",
    "sg:address":"3023 Brentmoor Dr",
    "sg:city":"Saint Charles",
    "sg:classifiers":[
        {
            "category":"Banks & Credit Unions",
            "subcategory":"Financial Services",
            "type":"Services"
        }
    ],
    "sg:phone":"+1 636 926 0904",
    "sg:postcode":"63303",
    "sg:province":"MO",
    "sg:tags":[
        "investor"
    ],
    "wof:name":"Apprill Investments",
    "wof:placetype":"venue"
},
  "geometry": {"coordinates":[-90.562904,38.739744],"type":"Point"}
}