{
  "type": "Feature",
  "properties": {
    "iso:country":"US",
    "sg:address":"229 E Hawk St",
    "sg:city":"Ravenwood",
    "sg:classifiers":[
        {
            "category":"Building & Trades",
            "subcategory":"Construction",
            "type":"Services"
        }
    ],
    "sg:phone":"+1 660 937 3765",
    "sg:postcode":"64479",
    "sg:province":"MO",
    "sg:tags":[
        "downspouts",
        "gutter"
    ],
    "wof:name":"Burch Seamless Guttering",
    "wof:placetype":"venue"
},
  "geometry": {"coordinates":[-94.67133800000001,40.352186],"type":"Point"}
}