{
  "type": "Feature",
  "properties": {
    "iso:country":"US",
    "sg:address":"5364 Golf Course Dr",
    "sg:city":"Shelbina",
    "sg:classifiers":[
        {
            "category":"Sports & Exercise",
            "subcategory":"Golf",
            "type":"Entertainment"
        }
    ],
    "sg:phone":"+1 573 588 4755",
    "sg:postcode":"63468",
    "sg:province":"MO",
    "sg:tags":[
        "course"
    ],
    "wof:name":"Shelbina Lakeside Golf Course",
    "wof:placetype":"venue"
},
  "geometry": {"coordinates":[-92.040573,39.725651],"type":"Point"}
}