{
  "type": "Feature",
  "properties": {
    "iso:country":"US",
    "sg:address":"2188 Highway Jj",
    "sg:city":"Moberly",
    "sg:classifiers":[
        {
            "category":"Professional",
            "subcategory":"Employment Agencies",
            "type":"Services"
        }
    ],
    "sg:phone":"+1 660 263 4299",
    "sg:postcode":"65270",
    "sg:province":"MO",
    "sg:tags":[
        "opportunity",
        "screening"
    ],
    "sg:website":"http://www.realitycheckscreening.com",
    "wof:name":"Reality Check Screening",
    "wof:placetype":"venue"
},
  "geometry": {"coordinates":[-92.478368,39.42787],"type":"Point"}
}