{
  "type": "Feature",
  "properties": {
    "iso:country":"US",
    "sg:address":"39545 Business Highway 10",
    "sg:city":"Richmond",
    "sg:classifiers":[
        {
            "category":"Personal",
            "subcategory":"Beauty Salon",
            "type":"Services"
        }
    ],
    "sg:phone":"+1 816 776 6400",
    "sg:postcode":"64085",
    "sg:province":"MO",
    "wof:name":"Studio 10 Salon",
    "wof:placetype":"venue"
},
  "geometry": {"coordinates":[-94.00609799999999,39.277396],"type":"Point"}
}