{
  "type": "Feature",
  "properties": {
    "iso:country":"US",
    "sg:address":"415 Van Brunt Blvd",
    "sg:city":"Kansas City",
    "sg:classifiers":[
        {
            "category":"Health Services",
            "subcategory":"Doctor",
            "type":"Services"
        }
    ],
    "sg:phone":"+1 816 241 3873",
    "sg:postcode":"64124",
    "sg:province":"MO",
    "sg:tags":[
        "medical"
    ],
    "wof:name":"Quality Care Clinic",
    "wof:placetype":"venue"
},
  "geometry": {"coordinates":[-94.52585999999999,39.107538],"type":"Point"}
}