{
  "type": "Feature",
  "properties": {
    "iso:country":"US",
    "sg:address":"3908 Vogel Rd",
    "sg:city":"Arnold",
    "sg:classifiers":[
        {
            "category":"Retail",
            "subcategory":"Laundry & Dry Cleaning",
            "type":"Services"
        }
    ],
    "sg:phone":"+1 636 282 7266",
    "sg:postcode":"63010",
    "sg:province":"MO",
    "sg:tags":[
        "drycleaning",
        "plant"
    ],
    "wof:name":"Vogel Cleaners",
    "wof:placetype":"venue"
},
  "geometry": {"coordinates":[-90.39126400000001,38.415981],"type":"Point"}
}