{
  "type": "Feature",
  "properties": {
    "iso:country":"US",
    "sg:address":"5203 Chippewa St",
    "sg:city":"Saint Louis",
    "sg:classifiers":[
        {
            "category":"Banks & Credit Unions",
            "subcategory":"Financial Services",
            "type":"Services"
        }
    ],
    "sg:phone":"+1 314 481 5626",
    "sg:postcode":"63109",
    "sg:province":"MO",
    "sg:tags":[
        "broker",
        "mortgage"
    ],
    "sg:website":"www.padda.com",
    "wof:name":"Padda Mortgage",
    "wof:placetype":"venue"
},
  "geometry": {"coordinates":[-90.280643,38.59213],"type":"Point"}
}