{
  "type": "Feature",
  "properties": {
    "iso:country":"US",
    "sg:address":"4300 Tiffany Ln",
    "sg:city":"Joplin",
    "sg:classifiers":[
        {
            "category":"Retail",
            "subcategory":"Auto Rental",
            "type":"Services"
        }
    ],
    "sg:phone":"+1 417 782 2150",
    "sg:postcode":"64801",
    "sg:province":"MO",
    "sg:tags":[
        "mobile",
        "home",
        "leasing"
    ],
    "wof:name":"Tiffany Ter Mobile Home Park",
    "wof:placetype":"venue"
},
  "geometry": {"coordinates":[-94.449229,37.094176],"type":"Point"}
}