{
  "type": "Feature",
  "properties": {
    "iso:country":"US",
    "sg:address":"1306 S Range Line Rd",
    "sg:city":"Joplin",
    "sg:classifiers":[
        {
            "category":"Restaurant",
            "type":"Food & Drink"
        }
    ],
    "sg:phone":"+1 417 624 6984",
    "sg:postcode":"64801",
    "sg:province":"MO",
    "wof:name":"Mythos Euro Greek Kuzina",
    "wof:placetype":"venue"
},
  "geometry": {"coordinates":[-94.47765099999999,37.075233],"type":"Point"}
}