{
  "type": "Feature",
  "properties": {
    "iso:country":"US",
    "sg:address":"3859 Gravois Ave",
    "sg:city":"St Louis",
    "sg:classifiers":[
        {
            "category":"Shopping",
            "subcategory":"Clothing, Apparel, & Fashions",
            "type":"Retail Goods"
        }
    ],
    "sg:phone":"+1 314 664 7772",
    "sg:postcode":"63116",
    "sg:province":"MO",
    "wof:name":"Fashion Cents",
    "wof:placetype":"venue"
},
  "geometry": {"coordinates":[-90.250973,38.591547],"type":"Point"}
}