{
  "type": "Feature",
  "properties": {
    "iso:country":"US",
    "sg:address":"621 Woodbriar Ln",
    "sg:city":"Saint Peters",
    "sg:classifiers":[
        {
            "category":"Building & Trades",
            "subcategory":"Construction",
            "type":"Services"
        }
    ],
    "sg:phone":"+1 636 443 5822",
    "sg:postcode":"63376",
    "sg:province":"MO",
    "sg:tags":[
        "house"
    ],
    "wof:name":"Leaderwood Construction LLC",
    "wof:placetype":"venue"
},
  "geometry": {"coordinates":[-90.55980700000001,38.758427],"type":"Point"}
}