{
  "type": "Feature",
  "properties": {
    "iso:country":"US",
    "sg:address":"6227 Troost Ave",
    "sg:city":"Kansas City",
    "sg:classifiers":[
        {
            "category":"Autos & Motor Vehicles",
            "subcategory":"Auto Supplies",
            "type":"Retail Goods"
        }
    ],
    "sg:phone":"+1 816 361 9017",
    "sg:postcode":"64110",
    "sg:province":"MO",
    "wof:name":"OReilly Auto Parts",
    "wof:placetype":"venue"
},
  "geometry": {"coordinates":[-94.574461,39.013701],"type":"Point"}
}