{
  "type": "Feature",
  "properties": {
    "iso:country":"US",
    "sg:address":"13088 State Hwy 6",
    "sg:city":"Green Castle",
    "sg:classifiers":[
        {
            "category":"Retail",
            "subcategory":"Auto Repair",
            "type":"Services"
        }
    ],
    "sg:phone":"+1 660 488 5288",
    "sg:postcode":"63544",
    "sg:province":"MO",
    "sg:tags":[
        "body"
    ],
    "wof:name":"Tharp Body Shop",
    "wof:placetype":"venue"
},
  "geometry": {"coordinates":[-92.798265,40.246975],"type":"Point"}
}