{
  "type": "Feature",
  "properties": {
    "iso:country":"US",
    "sg:address":"918 Citadel Dr",
    "sg:city":"Weston",
    "sg:classifiers":[
        {
            "category":"Professional",
            "subcategory":"Business Services",
            "type":"Services"
        }
    ],
    "sg:phone":"+1 816 386 5653",
    "sg:postcode":"64098",
    "sg:province":"MO",
    "wof:name":"OMalley & Associates Inc",
    "wof:placetype":"venue"
},
  "geometry": {"coordinates":[-94.88719500000001,39.413096],"type":"Point"}
}