{
  "type": "Feature",
  "properties": {
    "iso:country":"US",
    "sg:address":"1031 Watson Rd",
    "sg:city":"Sullivan",
    "sg:classifiers":[
        {
            "category":"Personal",
            "subcategory":"Beauty Salon",
            "type":"Services"
        }
    ],
    "sg:phone":"+1 573 468 4445",
    "sg:postcode":"63080",
    "sg:province":"MO",
    "wof:name":"Smt Salons",
    "wof:placetype":"venue"
},
  "geometry": {"coordinates":[-91.143958,38.20249],"type":"Point"}
}