{
  "type": "Feature",
  "properties": {
    "addr:full":"97 N Kingshighway St Cape Girardeau MO 63701",
    "addr:housenumber":"97",
    "addr:postcode":"63701",
    "addr:street":"N Kingshighway St",
    "iso:country":"US",
    "sg:address":"97 N Kingshighway St",
    "sg:city":"Cape Girardeau",
    "sg:classifiers":[
        {
            "category":"Restaurant",
            "type":"Food & Drink"
        }
    ],
    "sg:phone":"+1 573 334 8444",
    "sg:postcode":"63701",
    "sg:province":"MO",
    "sg:tags":[
        "pizza"
    ],
    "wof:name":"Little Caesars Pizza",
    "wof:placetype":"venue"
},
  "geometry": {"coordinates":[-89.551799,37.307761],"type":"Point"}
}