{
  "type": "Feature",
  "properties": {
    "iso:country":"US",
    "sg:address":"520 NW Englewood Rd",
    "sg:city":"Kansas City",
    "sg:classifiers":[
        {
            "category":"Professional",
            "subcategory":"Employment Agencies",
            "type":"Services"
        }
    ],
    "sg:phone":"+1 816 453 3660",
    "sg:postcode":"64118",
    "sg:province":"MO",
    "sg:tags":[
        "temporary",
        "help",
        "contractor"
    ],
    "wof:name":"Kelly Services Inc",
    "wof:placetype":"venue"
},
  "geometry": {"coordinates":[-94.588303,39.195614],"type":"Point"}
}