{
  "type": "Feature",
  "properties": {
    "iso:country":"US",
    "sg:address":"12412 Powerscourt Dr",
    "sg:city":"Saint Louis",
    "sg:classifiers":[
        {
            "category":"Health Services",
            "subcategory":"Health Practitioner",
            "type":"Services"
        }
    ],
    "sg:phone":"+1 314 909 1444",
    "sg:postcode":"63131",
    "sg:province":"MO",
    "sg:tags":[
        "medical"
    ],
    "wof:name":"Brad Berger MD",
    "wof:placetype":"venue"
},
  "geometry": {"coordinates":[-90.44958200000001,38.607746],"type":"Point"}
}