{
  "type": "Feature",
  "properties": {
    "iso:country":"US",
    "sg:address":"19504 Lippert Ln",
    "sg:city":"Independence",
    "sg:classifiers":[
        {
            "category":"Professional",
            "type":"Services"
        }
    ],
    "sg:phone":"+1 816 796 5624",
    "sg:postcode":"64056",
    "sg:province":"MO",
    "sg:tags":[
        "establishment"
    ],
    "wof:name":"MRM Tech Inc Of Mo",
    "wof:placetype":"venue"
},
  "geometry": {"coordinates":[-94.343745,39.098531],"type":"Point"}
}