{
  "type": "Feature",
  "properties": {
    "iso:country":"US",
    "sg:address":"777 E Battlefield St",
    "sg:city":"Springfield",
    "sg:classifiers":[
        {
            "category":"Professional",
            "subcategory":"Employment Agencies",
            "type":"Services"
        }
    ],
    "sg:phone":"+1 417 887 5858",
    "sg:postcode":"65807",
    "sg:province":"MO",
    "sg:tags":[
        "temporary",
        "contractor"
    ],
    "sg:website":"http://www.adecco.com",
    "wof:name":"Adecco Employment Services",
    "wof:placetype":"venue"
},
  "geometry": {"coordinates":[-93.285461,37.15979],"type":"Point"}
}