{
  "type": "Feature",
  "properties": {
    "iso:country":"US",
    "sg:address":"6500 Chippewa St Ste 304",
    "sg:city":"Saint Louis",
    "sg:classifiers":[
        {
            "category":"Health Services",
            "subcategory":"Doctor",
            "type":"Services"
        }
    ],
    "sg:phone":"+1 314 352 2711",
    "sg:postcode":"63109",
    "sg:province":"MO",
    "sg:tags":[
        "medicine",
        "podiatrist",
        "sport"
    ],
    "wof:name":"Sollecito Vincent III DPM",
    "wof:placetype":"venue"
},
  "geometry": {"coordinates":[-90.30210099999999,38.5923],"type":"Point"}
}