{
  "type": "Feature",
  "properties": {
    "iso:country":"US",
    "sg:address":"2872 Southgate Loop",
    "sg:city":"Sedalia",
    "sg:classifiers":[
        {
            "category":"Social Services",
            "subcategory":"Adult Care",
            "type":"Services"
        }
    ],
    "sg:phone":"+1 660 827 1419",
    "sg:postcode":"65301",
    "sg:province":"MO",
    "sg:tags":[
        "residential"
    ],
    "wof:name":"V Caslo",
    "wof:placetype":"venue"
},
  "geometry": {"coordinates":[-93.193096,38.675473],"type":"Point"}
}