{
  "type": "Feature",
  "properties": {
    "iso:country":"US",
    "sg:address":"1608 E 63 St",
    "sg:city":"Kansas City",
    "sg:classifiers":[
        {
            "category":"Autos & Motor Vehicles",
            "subcategory":"Auto Supplies",
            "type":"Retail Goods"
        }
    ],
    "sg:phone":"+1 816 523 2121",
    "sg:postcode":"64110",
    "sg:province":"MO",
    "sg:tags":[
        "automobile",
        "stereo",
        "radio"
    ],
    "wof:name":"Mobile Radio",
    "wof:placetype":"venue"
},
  "geometry": {"coordinates":[-94.568197,39.013076],"type":"Point"}
}