{
  "type": "Feature",
  "properties": {
    "iso:country":"US",
    "sg:address":"4922 Macklind Ave",
    "sg:city":"Saint Louis",
    "sg:classifiers":[
        {
            "category":"Retail",
            "subcategory":"Auto Repair",
            "type":"Services"
        }
    ],
    "sg:phone":"+1 314 353 9936",
    "sg:postcode":"63109",
    "sg:province":"MO",
    "sg:tags":[
        "repairing",
        "automobile"
    ],
    "wof:name":"Tom Bess Automotive Inc",
    "wof:placetype":"venue"
},
  "geometry": {"coordinates":[-90.284599,38.585701],"type":"Point"}
}