{
  "type": "Feature",
  "properties": {
    "iso:country":"US",
    "sg:address":"6624 Co Rd 262",
    "sg:city":"Hannibal",
    "sg:classifiers":[
        {
            "category":"Farming",
            "subcategory":"Livestock Farm",
            "type":"Manufacturing & Wholesale Goods"
        }
    ],
    "sg:phone":"+1 573 221 9242",
    "sg:postcode":"63401",
    "sg:province":"MO",
    "sg:tags":[
        "general"
    ],
    "wof:name":"Bar 6 Livestock LLC",
    "wof:placetype":"venue"
},
  "geometry": {"coordinates":[-91.54307799999999,39.706632],"type":"Point"}
}