{
  "type": "Feature",
  "properties": {
    "iso:country":"US",
    "sg:address":"940 S Timbercreek Ave",
    "sg:city":"Springfield",
    "sg:classifiers":[
        {
            "category":"Building & Trades",
            "subcategory":"Construction",
            "type":"Services"
        }
    ],
    "sg:phone":"+1 417 831 5255",
    "sg:postcode":"65802",
    "sg:province":"MO",
    "sg:tags":[
        "masonry",
        "contractor"
    ],
    "wof:name":"Powell Enterprises Constr",
    "wof:placetype":"venue"
},
  "geometry": {"coordinates":[-93.361557,37.198561],"type":"Point"}
}