{
  "type": "Feature",
  "properties": {
    "iso:country":"US",
    "sg:address":"30901 E Stony Point School Rd",
    "sg:city":"Grain Valley",
    "sg:classifiers":[
        {
            "category":"Organizations",
            "subcategory":"Community Association",
            "type":"Services"
        }
    ],
    "sg:phone":"+1 816 228 7266",
    "sg:postcode":"64029",
    "sg:province":"MO",
    "wof:name":"Optimist Club of Grain Valley",
    "wof:placetype":"venue"
},
  "geometry": {"coordinates":[-94.226501,38.987014],"type":"Point"}
}