{
  "type": "Feature",
  "properties": {
    "iso:country":"US",
    "sg:address":"323 Washington St",
    "sg:city":"Jefferson City",
    "sg:classifiers":[
        {
            "category":"Real Estate",
            "subcategory":"Real Estate Operator",
            "type":"Services"
        }
    ],
    "sg:phone":"+1 573 635 7635",
    "sg:postcode":"65101",
    "sg:province":"MO",
    "sg:tags":[
        "building",
        "apartment"
    ],
    "wof:name":"Wymore Apartments",
    "wof:placetype":"venue"
},
  "geometry": {"coordinates":[-92.17392,38.577623],"type":"Point"}
}