{
  "type": "Feature",
  "properties": {
    "iso:country":"US",
    "sg:address":"305 E Walnut St",
    "sg:city":"Springfield",
    "sg:classifiers":[
        {
            "category":"Retail",
            "subcategory":"Portrait Studio",
            "type":"Services"
        }
    ],
    "sg:phone":"+1 417 866 1331",
    "sg:postcode":"65806",
    "sg:province":"MO",
    "sg:tags":[
        "photographer"
    ],
    "wof:name":"Kay Tolliver Whitney Phtgrphy",
    "wof:placetype":"venue"
},
  "geometry": {"coordinates":[-93.28997699999999,37.207055],"type":"Point"}
}