{
  "type": "Feature",
  "properties": {
    "iso:country":"US",
    "sg:address":"5330 Gardner Ave",
    "sg:city":"Kansas City",
    "sg:classifiers":[
        {
            "category":"Railroad",
            "type":"Transportation"
        }
    ],
    "sg:phone":"+1 800 601 7630",
    "sg:postcode":"64120",
    "sg:province":"MO",
    "sg:tags":[
        "operator",
        "line"
    ],
    "wof:name":"CN Intermodal",
    "wof:placetype":"venue"
},
  "geometry": {"coordinates":[-94.514154,39.12634],"type":"Point"}
}