{
  "type": "Feature",
  "properties": {
    "iso:country":"US",
    "sg:address":"1788 US Hwy 61",
    "sg:city":"Festus",
    "sg:classifiers":[
        {
            "category":"Retail",
            "subcategory":"Auto Repair",
            "type":"Services"
        },
        {
            "category":"Autos & Motor Vehicles",
            "subcategory":"Auto Supplies",
            "type":"Retail Goods"
        }
    ],
    "sg:phone":"+1 636 933 2580",
    "sg:postcode":"63028",
    "sg:province":"MO",
    "sg:tags":[
        "repairing",
        "tire"
    ],
    "wof:name":"Mid America Tire & Rubber Co",
    "wof:placetype":"venue"
},
  "geometry": {"coordinates":[-90.392166,38.182391],"type":"Point"}
}