{
  "type": "Feature",
  "properties": {
    "iso:country":"US",
    "sg:address":"21088 US Hwy 59",
    "sg:city":"Tarkio",
    "sg:classifiers":[
        {
            "category":"Real Estate",
            "subcategory":"Real Estate Operator",
            "type":"Services"
        }
    ],
    "sg:phone":"+1 660 736 5202",
    "sg:postcode":"64491",
    "sg:province":"MO",
    "sg:tags":[
        "apartment"
    ],
    "wof:name":"Elray Apartments",
    "wof:placetype":"venue"
},
  "geometry": {"coordinates":[-95.397099,40.420666],"type":"Point"}
}