{
  "type": "Feature",
  "properties": {
    "iso:country":"US",
    "sg:address":"93 State Hwy 7",
    "sg:city":"Clinton",
    "sg:classifiers":[
        {
            "category":"Shopping",
            "subcategory":"Bicycles & Sporting Goods",
            "type":"Retail Goods"
        }
    ],
    "sg:phone":"+1 660 885 4500",
    "sg:postcode":"64735",
    "sg:province":"MO",
    "wof:name":"Thunder Road",
    "wof:placetype":"venue"
},
  "geometry": {"coordinates":[-93.613929,38.348656],"type":"Point"}
}