{
  "type": "Feature",
  "properties": {
    "iso:country":"US",
    "sg:address":"5801 E 113th St",
    "sg:city":"Kansas City",
    "sg:classifiers":[
        {
            "category":"Professional",
            "subcategory":"Management & Consulting",
            "type":"Services"
        }
    ],
    "sg:phone":"+1 816 765 1400",
    "sg:postcode":"64134",
    "sg:province":"MO",
    "sg:tags":[
        "consultant"
    ],
    "wof:name":"Midtown Insurance Conslnt LLC",
    "wof:placetype":"venue"
},
  "geometry": {"coordinates":[-94.521084,38.919616],"type":"Point"}
}