{
  "type": "Feature",
  "properties": {
    "iso:country":"US",
    "sg:address":"1108 S 33rd St",
    "sg:city":"St Joseph",
    "sg:classifiers":[
        {
            "category":"Organizations",
            "subcategory":"Religious Organization",
            "type":"Services"
        }
    ],
    "sg:phone":"+1 816 232 5583",
    "sg:postcode":"64507",
    "sg:province":"MO",
    "sg:tags":[
        "church"
    ],
    "wof:name":"Second Presbyterian Church",
    "wof:placetype":"venue"
},
  "geometry": {"coordinates":[-94.813053,39.756735],"type":"Point"}
}