{
  "type": "Feature",
  "properties": {
    "iso:country":"US",
    "sg:address":"9755 N Farm Rd 81",
    "sg:city":"Walnut Grove",
    "sg:classifiers":[
        {
            "category":"Farming",
            "subcategory":"Livestock Farm",
            "type":"Manufacturing & Wholesale Goods"
        }
    ],
    "sg:phone":"+1 417 742 3414",
    "sg:postcode":"65770",
    "sg:province":"MO",
    "sg:tags":[
        "beef",
        "feedlot",
        "cattle"
    ],
    "wof:name":"Thomas Watts",
    "wof:placetype":"venue"
},
  "geometry": {"coordinates":[-93.46647900000001,37.378161],"type":"Point"}
}