{
  "type": "Feature",
  "properties": {
    "iso:country":"US",
    "sg:address":"2893 County Road 675",
    "sg:city":"Bernie",
    "sg:classifiers":[
        {
            "category":"Manufacturing",
            "subcategory":"Food",
            "type":"Manufacturing & Wholesale Goods"
        },
        {
            "category":"Farming",
            "subcategory":"Farm",
            "type":"Manufacturing & Wholesale Goods"
        }
    ],
    "sg:phone":"+1 573 276 3315",
    "sg:postcode":"63822",
    "sg:province":"MO",
    "sg:tags":[
        "corn",
        "product"
    ],
    "sg:website":"http://www.fancyfarmpopcorn.com",
    "wof:name":"Fancy Farm Popcorn Co., Inc.",
    "wof:placetype":"venue"
},
  "geometry": {"coordinates":[-90.101364,36.659019],"type":"Point"}
}