{
  "type": "Feature",
  "properties": {
    "iso:country":"US",
    "sg:address":"10225 State Highway 96",
    "sg:city":"Carthage",
    "sg:classifiers":[
        {
            "category":"Farming",
            "subcategory":"Livestock Farm",
            "type":"Manufacturing & Wholesale Goods"
        }
    ],
    "sg:phone":"+1 417 359 5172",
    "sg:postcode":"64836",
    "sg:province":"MO",
    "sg:tags":[
        "ranch"
    ],
    "wof:name":"Mark Keenen",
    "wof:placetype":"venue"
},
  "geometry": {"coordinates":[-94.24246,37.198066],"type":"Point"}
}