{
  "type": "Feature",
  "properties": {
    "iso:country":"US",
    "sg:address":"2725 Sutton Blvd",
    "sg:city":"Saint Louis",
    "sg:classifiers":[
        {
            "category":"Bars & Pubs",
            "subcategory":"Dive Bar",
            "type":"Food & Drink"
        },
        {
            "category":"Sports & Exercise",
            "subcategory":"Bowling",
            "type":"Entertainment"
        }
    ],
    "sg:phone":"+1 314 645 5308",
    "sg:postcode":"63143",
    "sg:province":"MO",
    "sg:website":"www.saratogalanes.com/",
    "wof:name":"Saratoga Lanes",
    "wof:placetype":"venue"
},
  "geometry": {"coordinates":[-90.319801,38.611599],"type":"Point"}
}