{
  "type": "Feature",
  "properties": {
    "iso:country":"US",
    "sg:address":"918 S Main St",
    "sg:city":"De Soto",
    "sg:classifiers":[
        {
            "category":"Home & Garden",
            "subcategory":"Building Materials",
            "type":"Retail Goods"
        }
    ],
    "sg:phone":"+1 636 586 3311",
    "sg:postcode":"63020",
    "sg:province":"MO",
    "sg:tags":[
        "lumber"
    ],
    "wof:name":"Hopson Lumber Co",
    "wof:placetype":"venue"
},
  "geometry": {"coordinates":[-90.55676800000001,38.131356],"type":"Point"}
}