{
  "type": "Feature",
  "properties": {
    "iso:country":"US",
    "sg:address":"230 State Hwy 17",
    "sg:city":"Summersville",
    "sg:classifiers":[
        {
            "category":"Retail",
            "subcategory":"Laundry & Dry Cleaning",
            "type":"Services"
        }
    ],
    "sg:phone":"+1 417 932 4246",
    "sg:postcode":"65571",
    "sg:province":"MO",
    "sg:tags":[
        "cleaners",
        "rug",
        "carpet"
    ],
    "wof:name":"L & L Cleaning Svc",
    "wof:placetype":"venue"
},
  "geometry": {"coordinates":[-91.657555,37.172725],"type":"Point"}
}