{
  "type": "Feature",
  "properties": {
    "iso:country":"US",
    "sg:address":"214 S Walnut St",
    "sg:city":"Cameron",
    "sg:phone":"+1 816 632 6300",
    "sg:postcode":"64429",
    "sg:province":"MO",
    "wof:name":"Hunan Chinese Restaurant",
    "wof:placetype":"venue"
},
  "geometry": {"coordinates":[-94.23596999999999,39.738544],"type":"Point"}
}