{
  "type": "Feature",
  "properties": {
    "iso:country":"US",
    "sg:address":"1361 Overland Ln",
    "sg:city":"Moberly",
    "sg:classifiers":[
        {
            "category":"Autos & Motor Vehicles",
            "subcategory":"Automobile Sales",
            "type":"Retail Goods"
        }
    ],
    "sg:phone":"+1 660 263 2357",
    "sg:postcode":"65270",
    "sg:province":"MO",
    "sg:tags":[
        "used"
    ],
    "wof:name":"Maranatha Motors",
    "wof:placetype":"venue"
},
  "geometry": {"coordinates":[-92.447186,39.404293],"type":"Point"}
}