{
  "type": "Feature",
  "properties": {
    "iso:country":"US",
    "sg:address":"1220 Independence Dr",
    "sg:city":"Republic",
    "sg:classifiers":[
        {
            "category":"Building & Trades",
            "subcategory":"Equipment Rental",
            "type":"Services"
        }
    ],
    "sg:phone":"+1 417 732 1616",
    "sg:postcode":"65775",
    "sg:province":"MO",
    "sg:tags":[
        "leasing",
        "furniture"
    ],
    "wof:name":"Tel-A-Rent",
    "wof:placetype":"venue"
},
  "geometry": {"coordinates":[-91.869266,36.744917],"type":"Point"}
}