{
  "type": "Feature",
  "properties": {
    "iso:country":"US",
    "sg:address":"7310 NW Hampton Rd",
    "sg:city":"Kansas City",
    "sg:classifiers":[
        {
            "category":"Organizations",
            "subcategory":"Religious Organization",
            "type":"Services"
        }
    ],
    "sg:phone":"+1 816 891 3463",
    "sg:postcode":"64152",
    "sg:province":"MO",
    "sg:tags":[
        "church"
    ],
    "sg:website":"www.southplattebc.org",
    "wof:name":"South Platte Baptist Church",
    "wof:placetype":"venue"
},
  "geometry": {"coordinates":[-94.733374,39.22892],"type":"Point"}
}