{
  "type": "Feature",
  "properties": {
    "iso:country":"US",
    "sg:address":"2750 E Sunshine St",
    "sg:city":"Springfield",
    "sg:classifiers":[
        {
            "category":"Education",
            "subcategory":"University",
            "type":"Public Place"
        }
    ],
    "sg:phone":"+1 417 881 3818",
    "sg:postcode":"65804",
    "sg:province":"MO",
    "sg:tags":[
        "college"
    ],
    "sg:website":"http://www.acfei.com",
    "wof:name":"American College Of Forensic Examiners Institute Of Forensic Science, Inc.",
    "wof:placetype":"venue"
},
  "geometry": {"coordinates":[-93.24044600000001,37.180726],"type":"Point"}
}