{
  "type": "Feature",
  "properties": {
    "iso:country":"US",
    "sg:address":"415 S Belt Hwy",
    "sg:city":"St Joseph",
    "sg:classifiers":[
        {
            "category":"Wholesale",
            "subcategory":"Machinery & Supplies",
            "type":"Manufacturing & Wholesale Goods"
        }
    ],
    "sg:phone":"+1 816 233 1371",
    "sg:postcode":"64506",
    "sg:province":"MO",
    "sg:tags":[
        "salon",
        "barber",
        "beauty"
    ],
    "wof:name":"State Beauty Supply",
    "wof:placetype":"venue"
},
  "geometry": {"coordinates":[-94.803657,39.763503],"type":"Point"}
}