{
  "type": "Feature",
  "properties": {
    "iso:country":"US",
    "sg:address":"1301 Camillia St",
    "sg:city":"Farmington",
    "sg:classifiers":[
        {
            "category":"Professional",
            "subcategory":"Secretarial Services",
            "type":"Services"
        }
    ],
    "sg:phone":"+1 573 760 1360",
    "sg:postcode":"63640",
    "sg:province":"MO",
    "sg:tags":[
        "convention",
        "court",
        "reporter"
    ],
    "wof:name":"Strother & Smith Court Reprt",
    "wof:placetype":"venue"
},
  "geometry": {"coordinates":[-90.407623,37.792719],"type":"Point"}
}