{
  "type": "Feature",
  "properties": {
    "iso:country":"US",
    "sg:address":"3910 S Old Hwy 94",
    "sg:city":"Saint Charles",
    "sg:classifiers":[
        {
            "category":"Banks & Credit Unions",
            "subcategory":"Bank",
            "type":"Services"
        }
    ],
    "sg:phone":"+1 636 244 0090",
    "sg:postcode":"63304",
    "sg:province":"MO",
    "sg:tags":[
        "broker",
        "mortgage"
    ],
    "wof:name":"Amerigold Mortgage Co",
    "wof:placetype":"venue"
},
  "geometry": {"coordinates":[-90.586924,38.742251],"type":"Point"}
}