{
  "type": "Feature",
  "properties": {
    "iso:country":"US",
    "sg:address":"400 Cedar Ridge Dr",
    "sg:city":"Branson",
    "sg:classifiers":[
        {
            "category":"Education",
            "subcategory":"School",
            "type":"Public Place"
        }
    ],
    "sg:phone":"+1 417 334 6541",
    "sg:postcode":"65616",
    "sg:province":"MO",
    "sg:tags":[
        "k-",
        "private"
    ],
    "sg:website":"http://www.branson.k12.mo.us",
    "wof:name":"Branson Reoganized Schl Dst R-4",
    "wof:placetype":"venue"
},
  "geometry": {"coordinates":[-93.246223,36.65923],"type":"Point"}
}