{
  "type": "Feature",
  "properties": {
    "iso:country":"US",
    "sg:address":"1910 Frederick Ave",
    "sg:city":"St Joseph",
    "sg:classifiers":[
        {
            "category":"Wholesale",
            "subcategory":"Electrical",
            "type":"Manufacturing & Wholesale Goods"
        }
    ],
    "sg:phone":"+1 816 232 0560",
    "sg:postcode":"64501",
    "sg:province":"MO",
    "sg:tags":[
        "alarm",
        "burglar",
        "system"
    ],
    "wof:name":"Midwest Alarm",
    "wof:placetype":"venue"
},
  "geometry": {"coordinates":[-94.837198,39.773861],"type":"Point"}
}