{
  "type": "Feature",
  "properties": {
    "addr:full":"415 Francis St St Joseph MO 64501",
    "addr:housenumber":"415",
    "addr:postcode":"64501",
    "addr:street":"Francis St",
    "iso:country":"US",
    "sg:address":"415 Francis St",
    "sg:city":"St Joseph",
    "sg:classifiers":[
        {
            "category":"Banks & Credit Unions",
            "subcategory":"Bank",
            "type":"Services"
        }
    ],
    "sg:phone":"+1 816 233 2000",
    "sg:postcode":"64501",
    "sg:province":"MO",
    "wof:name":"US Bank",
    "wof:placetype":"venue"
},
  "geometry": {"coordinates":[-94.85430700000001,39.767452],"type":"Point"}
}