{
  "type": "Feature",
  "properties": {
    "iso:country":"US",
    "sg:address":"1047 Tavistock Cir",
    "sg:city":"Saint Louis",
    "sg:classifiers":[
        {
            "category":"Professional",
            "type":"Services"
        }
    ],
    "sg:phone":"+1 314 894 9470",
    "sg:postcode":"63129",
    "sg:province":"MO",
    "wof:name":"Harp Education",
    "wof:placetype":"venue"
},
  "geometry": {"coordinates":[-90.324183,38.498323],"type":"Point"}
}