{
  "type": "Feature",
  "properties": {
    "iso:country":"US",
    "sg:address":"3926 Lindell Blvd",
    "sg:city":"Saint Louis",
    "sg:classifiers":[
        {
            "category":"Restaurant",
            "type":"Food & Drink"
        },
        {
            "category":"Place Of Worship",
            "subcategory":"Temple",
            "type":"Public Place"
        }
    ],
    "sg:phone":"+1 314 535 8085",
    "sg:postcode":"63108",
    "sg:province":"MO",
    "sg:tags":[
        "hindu",
        "vegetarian",
        "indian",
        "pakistani",
        "buffet"
    ],
    "wof:name":"Govinda's",
    "wof:placetype":"venue"
},
  "geometry": {"coordinates":[-90.241402,38.639099],"type":"Point"}
}