{
  "type": "Feature",
  "properties": {
    "iso:country":"US",
    "sg:address":"391 Paul Ave",
    "sg:city":"Saint Louis",
    "sg:classifiers":[
        {
            "category":"Manufacturing",
            "subcategory":"Metals",
            "type":"Manufacturing & Wholesale Goods"
        }
    ],
    "sg:phone":"+1 314 521 1414",
    "sg:postcode":"63135",
    "sg:province":"MO",
    "sg:tags":[
        "steel",
        "product",
        "mfg"
    ],
    "wof:name":"A Finkl & Sons Co",
    "wof:placetype":"venue"
},
  "geometry": {"coordinates":[-90.29569100000001,38.739091],"type":"Point"}
}