{
  "type": "Feature",
  "properties": {
    "iso:country":"US",
    "sg:address":"915 S Baltimore St",
    "sg:city":"Kirksville",
    "sg:classifiers":[
        {
            "category":"Insurance",
            "subcategory":"Insurance Agent",
            "type":"Services"
        }
    ],
    "sg:phone":"+1 660 665 2812",
    "sg:postcode":"63501",
    "sg:province":"MO",
    "wof:name":"Hawkins Insurance Group",
    "wof:placetype":"venue"
},
  "geometry": {"coordinates":[-92.571884,40.18819],"type":"Point"}
}