{
  "type": "Feature",
  "properties": {
    "iso:country":"US",
    "sg:address":"536 Old Smizer Mill Rd",
    "sg:city":"Fenton",
    "sg:classifiers":[
        {
            "category":"Professional",
            "subcategory":"Lawyer & Legal Services",
            "type":"Services"
        }
    ],
    "sg:phone":"+1 636 349 1122",
    "sg:postcode":"63026",
    "sg:province":"MO",
    "sg:tags":[
        "attorney",
        "practice"
    ],
    "wof:name":"Traffic Law Ctr Of Sullivan",
    "wof:placetype":"venue"
},
  "geometry": {"coordinates":[-90.450751,38.515395],"type":"Point"}
}