{
  "type": "Feature",
  "properties": {
    "addr:full":"116 S Kansas Ave Marceline MO 64658",
    "addr:housenumber":"116",
    "addr:postcode":"64658",
    "addr:street":"S Kansas Ave",
    "iso:country":"US",
    "sg:address":"116 S Kansas Ave",
    "sg:city":"Marceline",
    "sg:classifiers":[
        {
            "category":"Restaurant",
            "type":"Food & Drink"
        }
    ],
    "sg:phone":"+1 660 376 2215",
    "sg:postcode":"64658",
    "sg:province":"MO",
    "sg:tags":[
        "eating"
    ],
    "wof:name":"Main Street Cafe",
    "wof:placetype":"venue"
},
  "geometry": {"coordinates":[-92.951318,39.714346],"type":"Point"}
}