{
  "type": "Feature",
  "properties": {
    "iso:country":"US",
    "sg:address":"911 Westwind Dr",
    "sg:city":"Centralia",
    "sg:phone":"+1 573 682 5352",
    "sg:postcode":"65240",
    "sg:province":"MO",
    "sg:tags":[
        "farm",
        "corn",
        "soybean"
    ],
    "wof:name":"Edith Wood",
    "wof:placetype":"venue"
},
  "geometry": {"coordinates":[-92.137811,39.197234],"type":"Point"}
}