{
  "type": "Feature",
  "properties": {
    "iso:country":"US",
    "sg:address":"107 W 11th St",
    "sg:city":"Mountain Grove",
    "sg:classifiers":[
        {
            "category":"Building & Trades",
            "subcategory":"Construction",
            "type":"Services"
        }
    ],
    "sg:phone":"+1 417 926 0522",
    "sg:postcode":"65711",
    "sg:province":"MO",
    "sg:tags":[
        "resurfacing",
        "laying",
        "refinishing",
        "floor"
    ],
    "wof:name":"DIY Outlet",
    "wof:placetype":"venue"
},
  "geometry": {"coordinates":[-92.263533,37.13823],"type":"Point"}
}