{
  "type": "Feature",
  "properties": {
    "iso:country":"US",
    "sg:address":"17401 State Hwy 96",
    "sg:city":"Carthage",
    "sg:classifiers":[
        {
            "category":"Retail",
            "subcategory":"Repair Shop",
            "type":"Services"
        }
    ],
    "sg:phone":"+1 417 358 3384",
    "sg:postcode":"64836",
    "sg:province":"MO",
    "sg:tags":[
        "sporting"
    ],
    "wof:name":"Grip Maker",
    "wof:placetype":"venue"
},
  "geometry": {"coordinates":[-94.37114699999999,37.186438],"type":"Point"}
}