{
  "type": "Feature",
  "properties": {
    "iso:country":"US",
    "sg:address":"12158 Natural Bridge Rd",
    "sg:city":"Bridgeton",
    "sg:classifiers":[
        {
            "category":"Retail",
            "subcategory":"Repair Shop",
            "type":"Services"
        }
    ],
    "sg:phone":"+1 636 227 6762",
    "sg:postcode":"63044",
    "sg:province":"MO",
    "sg:tags":[
        "refrigerating"
    ],
    "wof:name":"American Comfort Plus",
    "wof:placetype":"venue"
},
  "geometry": {"coordinates":[-90.418182,38.755631],"type":"Point"}
}