{
  "type": "Feature",
  "properties": {
    "iso:country":"US",
    "sg:address":"9 W Grant St",
    "sg:city":"Dexter",
    "sg:classifiers":[
        {
            "category":"Social Services",
            "type":"Services"
        }
    ],
    "sg:phone":"+1 573 624 6969",
    "sg:postcode":"63841",
    "sg:province":"MO",
    "sg:tags":[
        "counselor",
        "marriage",
        "family"
    ],
    "wof:name":"Professional Counseling Group",
    "wof:placetype":"venue"
},
  "geometry": {"coordinates":[-89.959458,36.788752],"type":"Point"}
}