{
  "type": "Feature",
  "properties": {
    "iso:country":"US",
    "sg:address":"16696 Anna's Way",
    "sg:city":"Chesterfield",
    "sg:classifiers":[
        {
            "category":"Professional",
            "subcategory":"Management & Consulting",
            "type":"Services"
        }
    ],
    "sg:phone":"+1 314 422 2599",
    "sg:postcode":"63005",
    "sg:province":"MO",
    "wof:name":"Aml Group Inc",
    "wof:placetype":"venue"
},
  "geometry": {"coordinates":[-90.643602,38.63538],"type":"Point"}
}