{
  "type": "Feature",
  "properties": {
    "iso:country":"US",
    "sg:address":"8836 Raleigh Dr",
    "sg:city":"Saint Louis",
    "sg:classifiers":[
        {
            "category":"Wholesale",
            "subcategory":"Metals & Minerals",
            "type":"Manufacturing & Wholesale Goods"
        }
    ],
    "sg:phone":"+1 314 843 3781",
    "sg:postcode":"63123",
    "sg:province":"MO",
    "sg:tags":[
        "pipe",
        "tubing"
    ],
    "wof:name":"Procomm Voice & Data Solutions",
    "wof:placetype":"venue"
},
  "geometry": {"coordinates":[-90.344538,38.556429],"type":"Point"}
}