{
  "type": "Feature",
  "properties": {
    "iso:country":"US",
    "sg:address":"2117 NE 48 St",
    "sg:city":"Kansas City",
    "sg:classifiers":[
        {
            "category":"Education",
            "subcategory":"School",
            "type":"Public Place"
        }
    ],
    "sg:phone":"+1 816 453 9977",
    "sg:postcode":"64118",
    "sg:province":"MO",
    "wof:name":"North Kansas City",
    "wof:placetype":"venue"
},
  "geometry": {"coordinates":[-94.55748699999999,39.180965],"type":"Point"}
}