{
  "type": "Feature",
  "properties": {
    "iso:country":"US",
    "sg:address":"305 Darrel Ct",
    "sg:city":"Liberty",
    "sg:classifiers":[
        {
            "category":"Real Estate",
            "subcategory":"Real Estate Operator",
            "type":"Services"
        }
    ],
    "sg:phone":"+1 816 781 4460",
    "sg:postcode":"64068",
    "sg:province":"MO",
    "sg:tags":[
        "apartment"
    ],
    "wof:name":"Liberty Court Apartments",
    "wof:placetype":"venue"
},
  "geometry": {"coordinates":[-94.411514,39.24106],"type":"Point"}
}