{
  "type": "Feature",
  "properties": {
    "iso:country":"US",
    "sg:address":"25110 E 97 St",
    "sg:city":"Lees Summit",
    "sg:classifiers":[
        {
            "category":"Retail",
            "subcategory":"Auto Repair",
            "type":"Services"
        }
    ],
    "sg:phone":"+1 816 525 5473",
    "sg:postcode":"64086",
    "sg:province":"MO",
    "sg:tags":[
        "body"
    ],
    "wof:name":"R & A Motorsports",
    "wof:placetype":"venue"
},
  "geometry": {"coordinates":[-94.290457,38.940497],"type":"Point"}
}