{
  "type": "Feature",
  "properties": {
    "iso:country":"US",
    "sg:address":"1049 Central St",
    "sg:city":"Kansas City",
    "sg:classifiers":[
        {
            "category":"Communications",
            "subcategory":"Television Station",
            "type":"Services"
        }
    ],
    "sg:phone":"+1 816 221 9999",
    "sg:postcode":"64105",
    "sg:province":"MO",
    "sg:tags":[
        "broadcasting",
        "co"
    ],
    "sg:website":"www.thekansascitychannel.com",
    "wof:name":"KMBC",
    "wof:placetype":"venue"
},
  "geometry": {"coordinates":[-94.586871,39.101638],"type":"Point"}
}