{
  "type": "Feature",
  "properties": {
    "iso:country":"US",
    "sg:address":"3702 Frederick Ave",
    "sg:city":"Saint Joseph",
    "sg:classifiers":[
        {
            "category":"Shopping",
            "subcategory":"Department Store",
            "type":"Retail Goods"
        }
    ],
    "sg:phone":"+1 816 390 9901",
    "sg:postcode":"64506",
    "sg:province":"MO",
    "sg:tags":[
        "dept"
    ],
    "wof:name":"Vanderbilts No 13 Inc",
    "wof:placetype":"venue"
},
  "geometry": {"coordinates":[-94.80159,39.77687],"type":"Point"}
}