{
  "type": "Feature",
  "properties": {
    "iso:country":"US",
    "sg:address":"1 Mayflower Dr",
    "sg:city":"Fenton",
    "sg:classifiers":[
        {
            "category":"Freight",
            "type":"Transportation"
        }
    ],
    "sg:phone":"+1 636 305 4000",
    "sg:postcode":"63026",
    "sg:province":"MO",
    "sg:tags":[
        "mover"
    ],
    "wof:name":"Mayflower Transit LLC",
    "wof:placetype":"venue"
},
  "geometry": {"coordinates":[-90.445387,38.538741],"type":"Point"}
}