{
  "type": "Feature",
  "properties": {
    "iso:country":"US",
    "sg:address":"1236 Jungermann Rd",
    "sg:city":"St Peters",
    "sg:classifiers":[
        {
            "category":"Freight",
            "type":"Transportation"
        }
    ],
    "sg:phone":"+1 636 928 3420",
    "sg:postcode":"63376",
    "sg:province":"MO",
    "wof:name":"Naca Logistics",
    "wof:placetype":"venue"
},
  "geometry": {"coordinates":[-90.57842100000001,38.778372],"type":"Point"}
}