{
  "type": "Feature",
  "properties": {
    "iso:country":"US",
    "sg:address":"3608 Nebraska Ave",
    "sg:city":"Saint Louis",
    "sg:classifiers":[
        {
            "category":"Building & Trades",
            "subcategory":"Plumbing",
            "type":"Services"
        }
    ],
    "sg:phone":"+1 314 776 3434",
    "sg:postcode":"63118",
    "sg:province":"MO",
    "sg:tags":[
        "contractor"
    ],
    "wof:name":"Wolff Plumbing",
    "wof:placetype":"venue"
},
  "geometry": {"coordinates":[-90.23331,38.588888],"type":"Point"}
}