{
  "type": "Feature",
  "properties": {
    "iso:country":"US",
    "sg:address":"6628 NW Dearing Dr",
    "sg:city":"Kansas City",
    "sg:classifiers":[
        {
            "category":"Manufacturing",
            "subcategory":"Tools & Machinery",
            "type":"Manufacturing & Wholesale Goods"
        }
    ],
    "sg:phone":"+1 816 891 0071",
    "sg:postcode":"64152",
    "sg:province":"MO",
    "sg:tags":[
        "devices",
        "mfg"
    ],
    "wof:name":"Lifestyles 21",
    "wof:placetype":"venue"
},
  "geometry": {"coordinates":[-94.726662,39.215724],"type":"Point"}
}