{
  "type": "Feature",
  "properties": {
    "addr:full":"1190 Meramec Station Rd Ballwin MO 63021",
    "addr:housenumber":"1190",
    "addr:postcode":"63021",
    "addr:street":"Meramec Station Rd",
    "iso:country":"US",
    "sg:address":"1190 Meramec Station Rd",
    "sg:city":"Ballwin",
    "sg:classifiers":[
        {
            "category":"Banks & Credit Unions",
            "subcategory":"Bank",
            "type":"Services"
        }
    ],
    "sg:phone":"+1 636 225 9990",
    "sg:postcode":"63021",
    "sg:province":"MO",
    "wof:name":"First Bank",
    "wof:placetype":"venue"
},
  "geometry": {"coordinates":[-90.498137,38.570958],"type":"Point"}
}