{
  "type": "Feature",
  "properties": {
    "iso:country":"US",
    "sg:address":"3406 Main St",
    "sg:city":"Kansas City",
    "sg:classifiers":[
        {
            "category":"Retail",
            "subcategory":"Laundry & Dry Cleaning",
            "type":"Services"
        }
    ],
    "sg:phone":"+1 816 333 3352",
    "sg:postcode":"64111",
    "sg:province":"MO",
    "sg:tags":[
        "cleaners",
        "upholstery"
    ],
    "wof:name":"Dumit Carpet & Upholstery Clng",
    "wof:placetype":"venue"
},
  "geometry": {"coordinates":[-94.585689,39.065187],"type":"Point"}
}