{
  "type": "Feature",
  "properties": {
    "iso:country":"US",
    "sg:address":"3607 N Briarcliff Rd",
    "sg:city":"Kansas City",
    "sg:classifiers":[
        {
            "category":"Retail",
            "subcategory":"Repair Shop",
            "type":"Services"
        }
    ],
    "sg:phone":"+1 816 453 7748",
    "sg:postcode":"64116",
    "sg:province":"MO",
    "wof:name":"Rowzee",
    "wof:placetype":"venue"
},
  "geometry": {"coordinates":[-94.58576600000001,39.160867],"type":"Point"}
}