{
  "type": "Feature",
  "properties": {
    "iso:country":"US",
    "sg:address":"3805 Reavis Barracks Rd",
    "sg:city":"St Louis",
    "sg:classifiers":[
        {
            "category":"Wholesale",
            "subcategory":"Auto Parts",
            "type":"Manufacturing & Wholesale Goods"
        }
    ],
    "sg:phone":"+1 314 892 7602",
    "sg:postcode":"63125",
    "sg:province":"MO",
    "sg:tags":[
        "automobile",
        "rebuilt"
    ],
    "wof:name":"Hill's U-Pull-It",
    "wof:placetype":"venue"
},
  "geometry": {"coordinates":[-90.301675,38.528207],"type":"Point"}
}