{
  "type": "Feature",
  "properties": {
    "iso:country":"US",
    "sg:address":"1305 Locust St",
    "sg:city":"Kansas City",
    "sg:classifiers":[
        {
            "category":"Government",
            "subcategory":"Court House",
            "type":"Public Place"
        }
    ],
    "sg:phone":"+1 816 881 3262",
    "sg:postcode":"64106",
    "sg:province":"MO",
    "wof:name":"Circuit Court of Jackson",
    "wof:placetype":"venue"
},
  "geometry": {"coordinates":[-94.577431,39.097625],"type":"Point"}
}