{
  "type": "Feature",
  "properties": {
    "iso:country":"US",
    "sg:address":"7 Hawks Nest Plz",
    "sg:city":"St Charles",
    "sg:classifiers":[
        {
            "category":"Bars & Pubs",
            "type":"Food & Drink"
        }
    ],
    "sg:phone":"+1 636 947 4747",
    "sg:postcode":"63303",
    "sg:province":"MO",
    "wof:name":"Partners II",
    "wof:placetype":"venue"
},
  "geometry": {"coordinates":[-90.521709,38.77983],"type":"Point"}
}