{
  "type": "Feature",
  "properties": {
    "iso:country":"US",
    "sg:address":"1235 S Truman Blvd",
    "sg:city":"Festus",
    "sg:classifiers":[
        {
            "category":"Retail",
            "subcategory":"Auto Repair",
            "type":"Services"
        }
    ],
    "sg:phone":"+1 636 931 3972",
    "sg:postcode":"63028",
    "sg:province":"MO",
    "sg:tags":[
        "wrecker"
    ],
    "wof:name":"Twin City Tow Co",
    "wof:placetype":"venue"
},
  "geometry": {"coordinates":[-90.395203,38.202292],"type":"Point"}
}