{
  "type": "Feature",
  "properties": {
    "iso:country":"US",
    "sg:address":"1311 S 5th St",
    "sg:city":"St Charles",
    "sg:classifiers":[
        {
            "category":"Banks & Credit Unions",
            "subcategory":"Bank",
            "type":"Services"
        }
    ],
    "sg:phone":"+1 636 946 1933",
    "sg:postcode":"63301",
    "sg:province":"MO",
    "sg:tags":[
        "national"
    ],
    "sg:website":"www.bankofamerica.com",
    "wof:name":"Bank of America",
    "wof:placetype":"venue"
},
  "geometry": {"coordinates":[-90.493414,38.770676],"type":"Point"}
}