{
  "type": "Feature",
  "properties": {
    "iso:country":"US",
    "sg:address":"300 SE 2 St",
    "sg:city":"Lees Summit",
    "sg:classifiers":[
        {
            "category":"Health Services",
            "subcategory":"Health Practitioner",
            "type":"Services"
        }
    ],
    "sg:phone":"+1 816 525 5711",
    "sg:postcode":"64063",
    "sg:province":"MO",
    "sg:tags":[
        "therapist",
        "physical"
    ],
    "wof:name":"Orthopedic & Sports Rehab Ctr",
    "wof:placetype":"venue"
},
  "geometry": {"coordinates":[-94.372728,38.915808],"type":"Point"}
}