{
  "type": "Feature",
  "properties": {
    "iso:country":"US",
    "sg:address":"285 Jamestown Mall",
    "sg:city":"Florissant",
    "sg:classifiers":[
        {
            "category":"Shopping",
            "subcategory":"Clothing, Apparel, & Fashions",
            "type":"Retail Goods"
        }
    ],
    "sg:phone":"+1 314 741 8781",
    "sg:postcode":"63034",
    "sg:province":"MO",
    "wof:name":"Rave Ladies Wear",
    "wof:placetype":"venue"
},
  "geometry": {"coordinates":[-90.24969,38.821033],"type":"Point"}
}