{
  "type": "Feature",
  "properties": {
    "iso:country":"US",
    "sg:address":"4771 Wickerwood Dr",
    "sg:city":"St Louis",
    "sg:classifiers":[
        {
            "category":"Building & Trades",
            "subcategory":"Electrical",
            "type":"Services"
        }
    ],
    "sg:phone":"+1 314 845 9850",
    "sg:postcode":"63129",
    "sg:province":"MO",
    "sg:tags":[
        "booth",
        "equipment",
        "telephone",
        "pay"
    ],
    "wof:name":"Joltran Communications Inc",
    "wof:placetype":"venue"
},
  "geometry": {"coordinates":[-90.325355,38.484957],"type":"Point"}
}