{
  "type": "Feature",
  "properties": {
    "iso:country":"US",
    "sg:address":"101 W 11 St",
    "sg:city":"Kansas City",
    "sg:classifiers":[
        {
            "category":"Professional",
            "subcategory":"Engineering",
            "type":"Services"
        }
    ],
    "sg:phone":"+1 816 421 1042",
    "sg:postcode":"64105",
    "sg:province":"MO",
    "sg:tags":[
        "consulting"
    ],
    "wof:name":"Structural Engineering Assoc",
    "wof:placetype":"venue"
},
  "geometry": {"coordinates":[-94.58553499999999,39.100902],"type":"Point"}
}