{
  "type": "Feature",
  "properties": {
    "iso:country":"US",
    "sg:address":"36576 Hill Valley Rd",
    "sg:city":"California",
    "sg:classifiers":[
        {
            "category":"Farming",
            "subcategory":"Poultry Farm",
            "type":"Manufacturing & Wholesale Goods"
        }
    ],
    "sg:phone":"+1 660 458 6530",
    "sg:postcode":"65018",
    "sg:province":"MO",
    "sg:tags":[
        "egg"
    ],
    "wof:name":"Rex Hill Turkey Farm",
    "wof:placetype":"venue"
},
  "geometry": {"coordinates":[-92.621348,38.552168],"type":"Point"}
}