{
  "type": "Feature",
  "properties": {
    "iso:country":"US",
    "sg:address":"96 N Niangua Ave",
    "sg:city":"Camdenton",
    "sg:classifiers":[
        {
            "category":"Wholesale",
            "subcategory":"Metals & Minerals",
            "type":"Manufacturing & Wholesale Goods"
        }
    ],
    "sg:phone":"+1 573 317 9004",
    "sg:postcode":"65020",
    "sg:province":"MO",
    "sg:tags":[
        "trade",
        "center",
        "ho",
        "contractor"
    ],
    "wof:name":"Isle Pointe Distributing",
    "wof:placetype":"venue"
},
  "geometry": {"coordinates":[-92.745023,38.009593],"type":"Point"}
}