{
  "type": "Feature",
  "properties": {
    "iso:country":"US",
    "sg:address":"12123 Blue Ridge Exd",
    "sg:city":"Grandview",
    "sg:classifiers":[
        {
            "category":"Professional",
            "subcategory":"Advertising",
            "type":"Services"
        }
    ],
    "sg:phone":"+1 816 761 7170",
    "sg:postcode":"64030",
    "sg:province":"MO",
    "sg:tags":[
        "guide"
    ],
    "wof:name":"Fred Arbanas Inc",
    "wof:placetype":"venue"
},
  "geometry": {"coordinates":[-94.526949,38.906119],"type":"Point"}
}