{
  "type": "Feature",
  "properties": {
    "iso:country":"US",
    "sg:address":"310 S Sibley St",
    "sg:city":"Buckner",
    "sg:classifiers":[
        {
            "category":"Retail",
            "subcategory":"Auto Repair",
            "type":"Services"
        }
    ],
    "sg:phone":"+1 816 650 5880",
    "sg:postcode":"64016",
    "sg:province":"MO",
    "sg:tags":[
        "repairing",
        "automobile",
        "general"
    ],
    "wof:name":"D & S Automotive Machine Shop",
    "wof:placetype":"venue"
},
  "geometry": {"coordinates":[-94.197479,39.132978],"type":"Point"}
}