{
  "type": "Feature",
  "properties": {
    "iso:country":"US",
    "sg:address":"7357 SE Haynesville Rd",
    "sg:city":"Holt",
    "sg:classifiers":[
        {
            "category":"Real Estate",
            "subcategory":"Real Estate Agent",
            "type":"Services"
        }
    ],
    "sg:phone":"+1 816 320 3854",
    "sg:postcode":"64048",
    "sg:province":"MO",
    "wof:name":"Holt Realty Dba Realty Exec",
    "wof:placetype":"venue"
},
  "geometry": {"coordinates":[-94.308989,39.465219],"type":"Point"}
}