{
  "type": "Feature",
  "properties": {
    "addr:full":"4300 Morganford Rd Saint Louis MO 63116",
    "addr:postcode":"4300;63116",
    "addr:street":"Morganford Rd",
    "iso:country":"US",
    "sg:address":"4300 Morganford Rd",
    "sg:city":"Saint Louis",
    "sg:classifiers":[
        {
            "category":"Education",
            "subcategory":"School",
            "type":"Public Place"
        }
    ],
    "sg:phone":"+1 314 481 0420",
    "sg:postcode":"63116",
    "sg:province":"MO",
    "sg:tags":[
        "high",
        "middle",
        "elementary"
    ],
    "wof:name":"Schools",
    "wof:placetype":"venue"
},
  "geometry": {"coordinates":[-90.264449,38.588724],"type":"Point"}
}