{
  "type": "Feature",
  "properties": {
    "iso:country":"US",
    "sg:address":"508 Charlotte Pl",
    "sg:city":"O Fallon",
    "sg:classifiers":[
        {
            "category":"Manufacturing",
            "subcategory":"Electronics",
            "type":"Manufacturing & Wholesale Goods"
        }
    ],
    "sg:phone":"+1 636 281 8054",
    "sg:postcode":"63366",
    "sg:province":"MO",
    "sg:tags":[
        "electronic",
        "component",
        "mfg"
    ],
    "wof:name":"Future Home Communications",
    "wof:placetype":"venue"
},
  "geometry": {"coordinates":[-90.742347,38.830498],"type":"Point"}
}