{
  "type": "Feature",
  "properties": {
    "addr:full":"110b Perry Plz Perryville MO 63775",
    "addr:housenumber":"110b",
    "addr:postcode":"63775",
    "addr:street":"Perry Plz",
    "iso:country":"US",
    "sg:address":"110b Perry Plz",
    "sg:city":"Perryville",
    "sg:classifiers":[
        {
            "category":"Restaurant",
            "type":"Food & Drink"
        }
    ],
    "sg:menulink":"http://www.allmenus.com/mo/st-marys/83999-dominos-pizza/menu/",
    "sg:phone":"+1 573 547 3030",
    "sg:postcode":"63775",
    "sg:province":"MO",
    "sg:tags":[
        "american",
        "wing",
        "pizza"
    ],
    "wof:name":"Domino's Pizza",
    "wof:placetype":"venue"
},
  "geometry": {"coordinates":[-90.056014,37.661303],"type":"Point"}
}