{
  "type": "Feature",
  "properties": {
    "iso:country":"US",
    "sg:address":"8007 Chivvis Dr",
    "sg:city":"Saint Louis",
    "sg:classifiers":[
        {
            "category":"Manufacturing",
            "subcategory":"Aerospace",
            "type":"Manufacturing & Wholesale Goods"
        }
    ],
    "sg:phone":"+1 314 832 8077",
    "sg:postcode":"63123",
    "sg:province":"MO",
    "sg:tags":[
        "aircraft",
        "mfg"
    ],
    "wof:name":"Essex Industries Inc",
    "wof:placetype":"venue"
},
  "geometry": {"coordinates":[-90.330429,38.564646],"type":"Point"}
}