{
  "type": "Feature",
  "properties": {
    "iso:country":"US",
    "sg:address":"415 N 2nd St",
    "sg:city":"Saint Charles",
    "sg:classifiers":[
        {
            "category":"Professional",
            "subcategory":"Secretarial Services",
            "type":"Services"
        }
    ],
    "sg:phone":"+1 636 723 0045",
    "sg:postcode":"63301",
    "sg:province":"MO",
    "sg:tags":[
        "reporting"
    ],
    "wof:name":"Taylor & Associates Court Repo",
    "wof:placetype":"venue"
},
  "geometry": {"coordinates":[-90.480766,38.785086],"type":"Point"}
}