{
  "type": "Feature",
  "properties": {
    "iso:country":"US",
    "sg:address":"512 E Cherry St",
    "sg:city":"Troy",
    "sg:classifiers":[
        {
            "category":"Shopping",
            "subcategory":"Clothing, Apparel, & Fashions",
            "type":"Retail Goods"
        }
    ],
    "sg:phone":"+1 636 528 6019",
    "sg:postcode":"63379",
    "sg:province":"MO",
    "sg:tags":[
        "alteration"
    ],
    "wof:name":"Rip & Seam Shop",
    "wof:placetype":"venue"
},
  "geometry": {"coordinates":[-90.97630700000001,38.98106],"type":"Point"}
}