{
  "type": "Feature",
  "properties": {
    "iso:country":"US",
    "sg:address":"1704 Grand Blvd",
    "sg:city":"Kansas City",
    "sg:classifiers":[
        {
            "category":"Food & Beverages",
            "subcategory":"Groceries & Convenience Stores",
            "type":"Retail Goods"
        }
    ],
    "sg:phone":"+1 816 221 9378",
    "sg:postcode":"64108",
    "sg:province":"MO",
    "sg:tags":[
        "station",
        "gasoline"
    ],
    "wof:name":"Total 4399",
    "wof:placetype":"venue"
},
  "geometry": {"coordinates":[-94.581411,39.091779],"type":"Point"}
}