{
  "type": "Feature",
  "properties": {
    "iso:country":"US",
    "sg:address":"8900 US Hwy 24",
    "sg:city":"Independence",
    "sg:classifiers":[
        {
            "category":"Retail",
            "subcategory":"Auto Repair",
            "type":"Services"
        }
    ],
    "sg:phone":"+1 816 461 1138",
    "sg:postcode":"64053",
    "sg:province":"MO",
    "sg:tags":[
        "repairing",
        "automobile"
    ],
    "wof:name":"M & M Auto Svc",
    "wof:placetype":"venue"
},
  "geometry": {"coordinates":[-94.476545,39.108005],"type":"Point"}
}