{
  "type": "Feature",
  "properties": {
    "iso:country":"US",
    "sg:address":"3215 S Main St",
    "sg:city":"Joplin",
    "sg:classifiers":[
        {
            "category":"Bars & Pubs",
            "type":"Food & Drink"
        }
    ],
    "sg:phone":"+1 417 782 4849",
    "sg:postcode":"64804",
    "sg:province":"MO",
    "sg:tags":[
        "drinking"
    ],
    "wof:name":"Tropicana Investments",
    "wof:placetype":"venue"
},
  "geometry": {"coordinates":[-94.514713,37.054951],"type":"Point"}
}