{
  "type": "Feature",
  "properties": {
    "iso:country":"US",
    "sg:address":"511 N Grover St",
    "sg:city":"Liberty",
    "sg:classifiers":[
        {
            "category":"Communications",
            "subcategory":"Film & Video Production",
            "type":"Services"
        }
    ],
    "sg:phone":"+1 816 781 5326",
    "sg:postcode":"64068",
    "sg:province":"MO",
    "sg:tags":[
        "motion"
    ],
    "wof:name":"B B A",
    "wof:placetype":"venue"
},
  "geometry": {"coordinates":[-94.42273400000001,39.25335],"type":"Point"}
}