{
  "type": "Feature",
  "properties": {
    "iso:country":"US",
    "sg:address":"18025 Bonhomme Branch Ct",
    "sg:city":"Chesterfield",
    "sg:classifiers":[
        {
            "category":"Wholesale",
            "subcategory":"Machinery & Supplies",
            "type":"Manufacturing & Wholesale Goods"
        }
    ],
    "sg:phone":"+1 314 469 1100",
    "sg:postcode":"63005",
    "sg:province":"MO",
    "sg:tags":[
        "concrete",
        "equipment"
    ],
    "wof:name":"St Louis Design Svc LLC",
    "wof:placetype":"venue"
},
  "geometry": {"coordinates":[-90.64080199999999,38.64472],"type":"Point"}
}