{
  "type": "Feature",
  "properties": {
    "iso:country":"US",
    "sg:address":"79 Grasso Plz",
    "sg:city":"St Louis",
    "sg:classifiers":[
        {
            "category":"Personal",
            "subcategory":"Beauty Salon",
            "type":"Services"
        }
    ],
    "sg:phone":"+1 314 544 2100",
    "sg:postcode":"63123",
    "sg:province":"MO",
    "wof:name":"Kristopher Paul's Salon",
    "wof:placetype":"venue"
},
  "geometry": {"coordinates":[-90.334284,38.551107],"type":"Point"}
}