{
  "type": "Feature",
  "properties": {
    "iso:country":"US",
    "sg:address":"4455 Chippewa St",
    "sg:city":"St Louis",
    "sg:classifiers":[
        {
            "category":"Personal",
            "subcategory":"Beauty Salon",
            "type":"Services"
        }
    ],
    "sg:phone":"+1 314 865 3357",
    "sg:postcode":"63116",
    "sg:province":"MO",
    "wof:name":"Alex's Hair Design Studio & Sp",
    "wof:placetype":"venue"
},
  "geometry": {"coordinates":[-90.26854,38.590977],"type":"Point"}
}