{
  "type": "Feature",
  "properties": {
    "iso:country":"US",
    "sg:address":"16806 E 252nd St",
    "sg:city":"Harrisonville",
    "sg:classifiers":[
        {
            "category":"Real Estate",
            "subcategory":"Real Estate Operator",
            "type":"Services"
        }
    ],
    "sg:phone":"+1 816 884 4657",
    "sg:postcode":"64701",
    "sg:province":"MO",
    "sg:tags":[
        "property",
        "lessor"
    ],
    "wof:name":"W Miller",
    "wof:placetype":"venue"
},
  "geometry": {"coordinates":[-94.402075,38.661562],"type":"Point"}
}