{
  "type": "Feature",
  "properties": {
    "iso:country":"US",
    "sg:address":"910 Bolger Ct",
    "sg:city":"Fenton",
    "sg:classifiers":[
        {
            "category":"Manufacturing",
            "subcategory":"Tools & Machinery",
            "type":"Manufacturing & Wholesale Goods"
        }
    ],
    "sg:phone":"+1 636 343 0806",
    "sg:postcode":"63026",
    "sg:province":"MO",
    "sg:tags":[
        "mfg",
        "equipment",
        "printing",
        "trade"
    ],
    "sg:website":"www.webtechniquesinc.com",
    "wof:name":"Web Techniques Inc",
    "wof:placetype":"venue"
},
  "geometry": {"coordinates":[-90.459006,38.540662],"type":"Point"}
}