{
  "type": "Feature",
  "properties": {
    "iso:country":"US",
    "sg:address":"1795 N US Hwy 67",
    "sg:city":"Florissant",
    "sg:classifiers":[
        {
            "category":"Freight",
            "type":"Transportation"
        }
    ],
    "sg:phone":"+1 314 638 8828",
    "sg:postcode":"63033",
    "sg:province":"MO",
    "sg:tags":[
        "warehouse",
        "storage"
    ],
    "wof:name":"Public Storage",
    "wof:placetype":"venue"
},
  "geometry": {"coordinates":[-90.317397,38.799298],"type":"Point"}
}