{
  "type": "Feature",
  "properties": {
    "iso:country":"US",
    "sg:address":"1311 Parry St",
    "sg:city":"Lamar",
    "sg:classifiers":[
        {
            "category":"Insurance",
            "subcategory":"Hazard Insurance",
            "type":"Services"
        }
    ],
    "sg:phone":"+1 417 682 3358",
    "sg:postcode":"64759",
    "sg:province":"MO",
    "wof:name":"Belline Bruce",
    "wof:placetype":"venue"
},
  "geometry": {"coordinates":[-94.269978,37.491922],"type":"Point"}
}