{
  "type": "Feature",
  "properties": {
    "iso:country":"US",
    "sg:address":"302 S Washington St",
    "sg:city":"Neosho",
    "sg:classifiers":[
        {
            "category":"Insurance",
            "subcategory":"Hazard Insurance",
            "type":"Services"
        }
    ],
    "sg:phone":"+1 417 451 7362",
    "sg:postcode":"64850",
    "sg:province":"MO",
    "wof:name":"Chalmers Insurance Agency",
    "wof:placetype":"venue"
},
  "geometry": {"coordinates":[-94.36732000000001,36.867495],"type":"Point"}
}