{
  "type": "Feature",
  "properties": {
    "iso:country":"US",
    "sg:address":"1236 Jungermann Rd",
    "sg:city":"St Peters",
    "sg:classifiers":[
        {
            "category":"Wholesale",
            "subcategory":"Office Equipment",
            "type":"Manufacturing & Wholesale Goods"
        }
    ],
    "sg:phone":"+1 636 922 1647",
    "sg:postcode":"63376",
    "sg:province":"MO",
    "sg:tags":[
        "register",
        "cash",
        "supply"
    ],
    "wof:name":"Blue Star",
    "wof:placetype":"venue"
},
  "geometry": {"coordinates":[-90.57842100000001,38.778372],"type":"Point"}
}