{
  "type": "Feature",
  "properties": {
    "addr:full":"6901 Washington Ave Saint Louis MO 63130",
    "addr:housenumber":"6901",
    "addr:postcode":"63130",
    "addr:street":"Washington Ave",
    "iso:country":"US",
    "sg:address":"6901 Washington Ave",
    "sg:city":"Saint Louis",
    "sg:classifiers":[
        {
            "category":"Organizations",
            "subcategory":"Religious Organization",
            "type":"Services"
        }
    ],
    "sg:phone":"+1 314 863 8055",
    "sg:postcode":"63130",
    "sg:province":"MO",
    "sg:website":"www.universityumc.com",
    "wof:name":"University United Methodist Church",
    "wof:placetype":"venue"
},
  "geometry": {"coordinates":[-90.311303,38.655446],"type":"Point"}
}