{
  "type": "Feature",
  "properties": {
    "iso:country":"US",
    "sg:address":"14205 Rainy Lake Dr",
    "sg:city":"Chesterfield",
    "sg:classifiers":[
        {
            "category":"Professional",
            "type":"Services"
        }
    ],
    "sg:phone":"+1 314 453 0159",
    "sg:postcode":"63017",
    "sg:province":"MO",
    "wof:name":"Kawelaske",
    "wof:placetype":"venue"
},
  "geometry": {"coordinates":[-90.51771599999999,38.65671],"type":"Point"}
}