{
  "type": "Feature",
  "properties": {
    "addr:full":"777 Argosy Pkwy Riverside MO 64150",
    "addr:housenumber":"777",
    "addr:postcode":"64150",
    "addr:street":"Argosy Pkwy",
    "iso:country":"US",
    "sg:address":"777 Argosy Pkwy",
    "sg:city":"Riverside",
    "sg:classifiers":[
        {
            "category":"Recreation",
            "subcategory":"Arcade",
            "type":"Entertainment"
        }
    ],
    "sg:phone":"+1 816 746 3100",
    "sg:postcode":"64150",
    "sg:province":"MO",
    "sg:tags":[
        "casino"
    ],
    "sg:website":"www.argosy.com",
    "wof:name":"Argosy Casino",
    "wof:placetype":"venue"
},
  "geometry": {"coordinates":[-94.620606,39.163059],"type":"Point"}
}