{
  "type": "Feature",
  "properties": {
    "iso:country":"US",
    "sg:address":"2000 Meadowtree Ln",
    "sg:city":"Kirkwood",
    "sg:classifiers":[
        {
            "category":"Professional",
            "subcategory":"Business Services",
            "type":"Services"
        }
    ],
    "sg:phone":"+1 314 965 7599",
    "sg:postcode":"63122",
    "sg:province":"MO",
    "sg:tags":[
        "interior",
        "consultant",
        "design",
        "decorator"
    ],
    "wof:name":"Marie Linda Design Co",
    "wof:placetype":"venue"
},
  "geometry": {"coordinates":[-90.44248,38.5912],"type":"Point"}
}