{
  "type": "Feature",
  "properties": {
    "iso:country":"US",
    "sg:address":"12519 Olive Blvd",
    "sg:city":"St Louis",
    "sg:classifiers":[
        {
            "category":"Shopping",
            "subcategory":"Clothing, Apparel, & Fashions",
            "type":"Retail Goods"
        }
    ],
    "sg:phone":"+1 314 205 0319",
    "sg:postcode":"63141",
    "sg:province":"MO",
    "sg:website":"www.oldnavy.com",
    "wof:name":"Old Navy",
    "wof:placetype":"venue"
},
  "geometry": {"coordinates":[-90.462755,38.675652],"type":"Point"}
}