{
  "type": "Feature",
  "properties": {
    "iso:country":"US",
    "sg:address":"4000 E Jackson Blvd",
    "sg:city":"Jackson",
    "sg:classifiers":[
        {
            "category":"Shopping",
            "type":"Retail Goods"
        }
    ],
    "sg:phone":"+1 573 243 4775",
    "sg:postcode":"63755",
    "sg:province":"MO",
    "sg:tags":[
        "merchandise"
    ],
    "wof:name":"Kinder Fireworks",
    "wof:placetype":"venue"
},
  "geometry": {"coordinates":[-89.62119,37.358308],"type":"Point"}
}