{
  "type": "Feature",
  "properties": {
    "iso:country":"US",
    "sg:address":"6369 Olive Blvd",
    "sg:city":"St Louis",
    "sg:classifiers":[
        {
            "category":"Banks & Credit Unions",
            "subcategory":"Bank",
            "type":"Services"
        }
    ],
    "sg:phone":"+1 314 447 0600",
    "sg:postcode":"63130",
    "sg:province":"MO",
    "sg:tags":[
        "loan",
        "real estate"
    ],
    "wof:name":"American Mortgage",
    "wof:placetype":"venue"
},
  "geometry": {"coordinates":[-90.30186399999999,38.662041],"type":"Point"}
}