{
  "type": "Feature",
  "properties": {
    "iso:country":"US",
    "sg:address":"1342 State Hwy 7",
    "sg:city":"Blue Springs",
    "sg:classifiers":[
        {
            "category":"Personal",
            "subcategory":"Beauty Salon",
            "type":"Services"
        }
    ],
    "sg:phone":"+1 816 228 3855",
    "sg:postcode":"64014",
    "sg:province":"MO",
    "sg:tags":[
        "manicuring"
    ],
    "wof:name":"Us Nails",
    "wof:placetype":"venue"
},
  "geometry": {"coordinates":[-94.27280399999999,39.004528],"type":"Point"}
}