{
  "type": "Feature",
  "properties": {
    "iso:country":"US",
    "sg:address":"1417 N Mount Auburn Rd",
    "sg:city":"Cape Girardeau",
    "sg:classifiers":[
        {
            "category":"Health Services",
            "subcategory":"Health Practitioner",
            "type":"Services"
        }
    ],
    "sg:phone":"+1 573 334 9095",
    "sg:postcode":"63701",
    "sg:province":"MO",
    "sg:tags":[
        "psychologist"
    ],
    "wof:name":"Sleep Analysts Inc",
    "wof:placetype":"venue"
},
  "geometry": {"coordinates":[-89.572457,37.326341],"type":"Point"}
}