{
  "type": "Feature",
  "properties": {
    "iso:country":"US",
    "sg:address":"502 W Sturdivant St",
    "sg:city":"Advance",
    "sg:classifiers":[
        {
            "category":"Health Services",
            "subcategory":"Clinic",
            "type":"Services"
        },
        {
            "category":"Community Center",
            "type":"Public Place"
        }
    ],
    "sg:phone":"+1 573 722 9191",
    "sg:postcode":"63730",
    "sg:province":"MO",
    "sg:tags":[
        "medical"
    ],
    "wof:name":"Haven Health Care Medical Clinic",
    "wof:placetype":"venue"
},
  "geometry": {"coordinates":[-89.913117,37.104709],"type":"Point"}
}