{
  "type": "Feature",
  "properties": {
    "iso:country":"US",
    "sg:address":"3525 Watson Rd",
    "sg:city":"St Louis",
    "sg:classifiers":[
        {
            "category":"Professional",
            "subcategory":"Management & Consulting",
            "type":"Services"
        }
    ],
    "sg:phone":"+1 314 781 2781",
    "sg:postcode":"63139",
    "sg:province":"MO",
    "sg:tags":[
        "consultant",
        "business"
    ],
    "wof:name":"Inneval",
    "wof:placetype":"venue"
},
  "geometry": {"coordinates":[-90.30030499999999,38.599155],"type":"Point"}
}