{
  "type": "Feature",
  "properties": {
    "iso:country":"US",
    "sg:address":"1361 W Casco Rd",
    "sg:city":"Leslie",
    "sg:classifiers":[
        {
            "category":"Wholesale",
            "subcategory":"Farm Supplies",
            "type":"Manufacturing & Wholesale Goods"
        },
        {
            "category":"Farming",
            "subcategory":"Farm",
            "type":"Manufacturing & Wholesale Goods"
        }
    ],
    "sg:phone":"+1 573 484 3484",
    "sg:postcode":"63056",
    "sg:province":"MO",
    "sg:tags":[
        "grain"
    ],
    "wof:name":"3 D Farms",
    "wof:placetype":"venue"
},
  "geometry": {"coordinates":[-91.185868,38.471679],"type":"Point"}
}