{
  "type": "Feature",
  "properties": {
    "iso:country":"US",
    "sg:address":"6597 W Independence Dr",
    "sg:city":"Springfield",
    "sg:classifiers":[
        {
            "category":"Wholesale",
            "subcategory":"Toys & Hobbies",
            "type":"Manufacturing & Wholesale Goods"
        }
    ],
    "sg:phone":"+1 417 862 1931",
    "sg:postcode":"65802",
    "sg:province":"MO",
    "sg:tags":[
        "firework"
    ],
    "wof:name":"Fireworks Over America",
    "wof:placetype":"venue"
},
  "geometry": {"coordinates":[-93.42053300000001,37.201548],"type":"Point"}
}