{
  "type": "Feature",
  "properties": {
    "iso:country":"US",
    "sg:address":"26 N Central Ave",
    "sg:city":"St Louis",
    "sg:classifiers":[
        {
            "category":"Restaurant",
            "type":"Food & Drink"
        }
    ],
    "sg:phone":"+1 314 862 1886",
    "sg:postcode":"63105",
    "sg:province":"MO",
    "wof:name":"John P Fields Restaurant",
    "wof:placetype":"venue"
},
  "geometry": {"coordinates":[-90.33805,38.65132],"type":"Point"}
}