{
  "type": "Feature",
  "properties": {
    "iso:country":"US",
    "sg:address":"6424 W Farm Rd 140",
    "sg:city":"Springfield",
    "sg:classifiers":[
        {
            "category":"Building & Trades",
            "subcategory":"Construction",
            "type":"Services"
        }
    ],
    "sg:phone":"+1 417 863 0944",
    "sg:postcode":"65802",
    "sg:province":"MO",
    "sg:tags":[
        "hanging",
        "painter",
        "contractor"
    ],
    "wof:name":"G B's Painting Co",
    "wof:placetype":"venue"
},
  "geometry": {"coordinates":[-93.41608600000001,37.198365],"type":"Point"}
}