{
  "type": "Feature",
  "properties": {
    "iso:country":"US",
    "sg:address":"580 W Hwy 32",
    "sg:city":"Stockton",
    "sg:classifiers":[
        {
            "category":"Shopping",
            "subcategory":"Discount & Variety Stores",
            "type":"Retail Goods"
        }
    ],
    "sg:phone":"+1 417 276 6842",
    "sg:postcode":"65785",
    "sg:province":"MO",
    "wof:name":"Dollar General",
    "wof:placetype":"venue"
},
  "geometry": {"coordinates":[-93.80375600000001,37.7013],"type":"Point"}
}