{
  "type": "Feature",
  "properties": {
    "iso:country":"US",
    "sg:address":"3660 S Geyer Rd",
    "sg:city":"Saint Louis",
    "sg:classifiers":[
        {
            "category":"Retail",
            "subcategory":"Laundry & Dry Cleaning",
            "type":"Services"
        }
    ],
    "sg:phone":"+1 314 909 2300",
    "sg:postcode":"63127",
    "sg:province":"MO",
    "sg:tags":[
        "rental",
        "uniform"
    ],
    "wof:name":"Aramark",
    "wof:placetype":"venue"
},
  "geometry": {"coordinates":[-90.416319,38.553581],"type":"Point"}
}