{
  "type": "Feature",
  "properties": {
    "iso:country":"US",
    "sg:address":"1915 W Sunshine St",
    "sg:city":"Springfield",
    "sg:classifiers":[
        {
            "category":"Wholesale",
            "subcategory":"Machinery & Supplies",
            "type":"Manufacturing & Wholesale Goods"
        }
    ],
    "sg:phone":"+1 417 832 9012",
    "sg:postcode":"65807",
    "sg:province":"MO",
    "sg:tags":[
        "equipment",
        "safety",
        "clothing"
    ],
    "wof:name":"Intellistrobe Safety Syst LLC",
    "wof:placetype":"venue"
},
  "geometry": {"coordinates":[-93.31789999999999,37.182449],"type":"Point"}
}