{
  "type": "Feature",
  "properties": {
    "iso:country":"US",
    "sg:address":"609 W 6th St",
    "sg:city":"Washington",
    "sg:classifiers":[
        {
            "category":"Wholesale",
            "subcategory":"Construction Materials",
            "type":"Manufacturing & Wholesale Goods"
        },
        {
            "category":"Home & Garden",
            "subcategory":"Building Materials",
            "type":"Retail Goods"
        }
    ],
    "sg:phone":"+1 636 239 4207",
    "sg:postcode":"63090",
    "sg:province":"MO",
    "sg:tags":[
        "windows-wholesale",
        "window",
        "manufacturer"
    ],
    "wof:name":"Window Wizard Plus",
    "wof:placetype":"venue"
},
  "geometry": {"coordinates":[-91.01952199999999,38.556],"type":"Point"}
}