{
  "type": "Feature",
  "properties": {
    "iso:country":"US",
    "sg:address":"1449 S Glenstone Ave",
    "sg:city":"Springfield",
    "sg:classifiers":[
        {
            "category":"Personal",
            "subcategory":"Beauty Salon",
            "type":"Services"
        }
    ],
    "sg:phone":"+1 417 889 1318",
    "sg:postcode":"65804",
    "sg:province":"MO",
    "sg:tags":[
        "shop",
        "manicuring"
    ],
    "wof:name":"L A Magic Nails",
    "wof:placetype":"venue"
},
  "geometry": {"coordinates":[-93.262297,37.188852],"type":"Point"}
}