{
  "type": "Feature",
  "properties": {
    "iso:country":"US",
    "sg:address":"1921 S Garrison Ave",
    "sg:city":"Carthage",
    "sg:classifiers":[
        {
            "category":"Insurance",
            "subcategory":"Insurance Agent",
            "type":"Services"
        },
        {
            "category":"Insurance",
            "subcategory":"Hazard Insurance",
            "type":"Services"
        },
        {
            "category":"Insurance",
            "subcategory":"Title Insurance",
            "type":"Services"
        }
    ],
    "sg:phone":"+1 417 358 9715",
    "sg:postcode":"64836",
    "sg:province":"MO",
    "sg:tags":[
        "auto",
        "homeowner"
    ],
    "sg:website":"http://apps.amfam.com/agentlocator/BBROW2?sourceid=yp3",
    "wof:name":"American Family Insurance- Bob Brown Agency Inc",
    "wof:placetype":"venue"
},
  "geometry": {"coordinates":[-94.314577,37.156166],"type":"Point"}
}