{
  "type": "Feature",
  "properties": {
    "iso:country":"US",
    "sg:address":"14754 Manchester Rd",
    "sg:city":"Ballwin",
    "sg:classifiers":[
        {
            "category":"Autos & Motor Vehicles",
            "subcategory":"Automobile Sales",
            "type":"Retail Goods"
        }
    ],
    "sg:phone":"+1 636 227 5810",
    "sg:postcode":"63011",
    "sg:province":"MO",
    "sg:tags":[
        "car",
        "dealer"
    ],
    "sg:website":"www.chryslerwest.com",
    "wof:name":"Chrysler Plymouth West",
    "wof:placetype":"venue"
},
  "geometry": {"coordinates":[-90.53439899999999,38.593004],"type":"Point"}
}