{
  "type": "Feature",
  "properties": {
    "iso:country":"US",
    "sg:address":"1306 Ticonderoga Dr",
    "sg:city":"St Peters",
    "sg:classifiers":[
        {
            "category":"Health Services",
            "subcategory":"Health Practitioner",
            "type":"Services"
        }
    ],
    "sg:phone":"+1 636 441 0320",
    "sg:postcode":"63376",
    "sg:province":"MO",
    "sg:tags":[
        "psychotherapist"
    ],
    "wof:name":"Personal Connection",
    "wof:placetype":"venue"
},
  "geometry": {"coordinates":[-90.570016,38.78767],"type":"Point"}
}