{
  "type": "Feature",
  "properties": {
    "iso:country":"US",
    "sg:address":"1 SE 14th St",
    "sg:city":"Concordia",
    "sg:classifiers":[
        {
            "category":"Travel",
            "subcategory":"Hotels & Motels",
            "type":"Entertainment"
        }
    ],
    "sg:phone":"+1 660 463 2160",
    "sg:postcode":"64020",
    "sg:province":"MO",
    "sg:tags":[
        "breakfast",
        "accommodation",
        "bed",
        "lodging"
    ],
    "wof:name":"Mrs G's B & B",
    "wof:placetype":"venue"
},
  "geometry": {"coordinates":[-93.569092,38.973389],"type":"Point"}
}