{
  "type": "Feature",
  "properties": {
    "iso:country":"US",
    "sg:address":"9 Mustang Dr",
    "sg:city":"Anderson",
    "sg:classifiers":[
        {
            "category":"Utilities",
            "subcategory":"Electric",
            "type":"Services"
        },
        {
            "category":"Manufacturing",
            "subcategory":"Electronics",
            "type":"Manufacturing & Wholesale Goods"
        },
        {
            "category":"Building & Trades",
            "subcategory":"Electrical",
            "type":"Services"
        }
    ],
    "sg:phone":"+1 417 845 7091",
    "sg:postcode":"64831",
    "sg:province":"MO",
    "sg:tags":[
        "industrial",
        "electrician",
        "contractors-commercial",
        "equipment-testing"
    ],
    "wof:name":"New Mac Electric",
    "wof:placetype":"venue"
},
  "geometry": {"coordinates":[-94.431268,36.645592],"type":"Point"}
}