{
  "type": "Feature",
  "properties": {
    "iso:country":"US",
    "sg:address":"732 NE Lyon Dr",
    "sg:city":"Lees Summit",
    "sg:classifiers":[
        {
            "category":"Professional",
            "subcategory":"Lawyer & Legal Services",
            "type":"Services"
        }
    ],
    "sg:phone":"+1 816 347 7400",
    "sg:postcode":"64086",
    "sg:province":"MO",
    "sg:tags":[
        "attorney"
    ],
    "wof:name":"F Patrick Fryer Law Offices",
    "wof:placetype":"venue"
},
  "geometry": {"coordinates":[-94.329365,38.9248],"type":"Point"}
}