{
  "type": "Feature",
  "properties": {
    "iso:country":"US",
    "sg:address":"1925 Washington Ave",
    "sg:city":"Saint Louis",
    "sg:classifiers":[
        {
            "category":"Arts & Performance",
            "subcategory":"Comedy Club",
            "type":"Entertainment"
        }
    ],
    "sg:phone":"+1 314 241 5233",
    "sg:postcode":"63103",
    "sg:province":"MO",
    "sg:website":"www.stlhouseofcomedy.com/",
    "wof:name":"House of Comedy St Louis",
    "wof:placetype":"venue"
},
  "geometry": {"coordinates":[-90.20666199999999,38.633963],"type":"Point"}
}