{
  "type": "Feature",
  "properties": {
    "iso:country":"US",
    "sg:address":"6394 Delmar Blvd",
    "sg:city":"St Louis",
    "sg:classifiers":[
        {
            "category":"Shopping",
            "subcategory":"Shoes",
            "type":"Retail Goods"
        }
    ],
    "sg:phone":"+1 314 721 7007",
    "sg:postcode":"63130",
    "sg:province":"MO",
    "wof:name":"Good Luck Shoes",
    "wof:placetype":"venue"
},
  "geometry": {"coordinates":[-90.304552,38.655853],"type":"Point"}
}