{
  "type": "Feature",
  "properties": {
    "iso:country":"US",
    "sg:address":"1127 N Kingshighway St",
    "sg:city":"Cape Girardeau",
    "sg:classifiers":[
        {
            "category":"Professional",
            "subcategory":"Detective & Security Services",
            "type":"Services"
        }
    ],
    "sg:phone":"+1 573 651 4222",
    "sg:postcode":"63701",
    "sg:province":"MO",
    "sg:tags":[
        "car"
    ],
    "wof:name":"Assoc Investigations",
    "wof:placetype":"venue"
},
  "geometry": {"coordinates":[-89.558058,37.320923],"type":"Point"}
}