{
  "type": "Feature",
  "properties": {
    "iso:country":"US",
    "sg:address":"308 W 8 St",
    "sg:city":"Kansas City",
    "sg:classifiers":[
        {
            "category":"Health Services",
            "subcategory":"Doctor",
            "type":"Services"
        }
    ],
    "sg:phone":"+1 816 229 2557",
    "sg:postcode":"64105",
    "sg:province":"MO",
    "sg:tags":[
        "physician",
        "surgeon"
    ],
    "wof:name":"Duffy Medical Group",
    "wof:placetype":"venue"
},
  "geometry": {"coordinates":[-94.587013,39.104724],"type":"Point"}
}