{
  "type": "Feature",
  "properties": {
    "iso:country":"US",
    "sg:address":"1520 S John Ave",
    "sg:city":"Springfield",
    "sg:classifiers":[
        {
            "category":"Professional",
            "subcategory":"Accounting & Tax Preparation",
            "type":"Services"
        }
    ],
    "sg:phone":"+1 417 883 7031",
    "sg:postcode":"65804",
    "sg:province":"MO",
    "sg:tags":[
        "return"
    ],
    "wof:name":"Accurate Tax Services",
    "wof:placetype":"venue"
},
  "geometry": {"coordinates":[-93.22864800000001,37.186495],"type":"Point"}
}