{
  "type": "Feature",
  "properties": {
    "iso:country":"US",
    "sg:address":"107 Melody Ln",
    "sg:city":"Salisbury",
    "sg:classifiers":[
        {
            "category":"Farming",
            "subcategory":"Livestock Farm",
            "type":"Manufacturing & Wholesale Goods"
        }
    ],
    "sg:phone":"+1 660 388 5700",
    "sg:postcode":"65281",
    "sg:province":"MO",
    "sg:tags":[
        "beef",
        "feedlot",
        "cattle"
    ],
    "wof:name":"Andrew Boss",
    "wof:placetype":"venue"
},
  "geometry": {"coordinates":[-92.802758,39.413543],"type":"Point"}
}