{
  "type": "Feature",
  "properties": {
    "iso:country":"US",
    "sg:address":"17 N Meramec Ave",
    "sg:city":"Saint Louis",
    "sg:classifiers":[
        {
            "category":"Retail",
            "subcategory":"Repair Shop",
            "type":"Services"
        }
    ],
    "sg:phone":"+1 314 721 4548",
    "sg:postcode":"63105",
    "sg:province":"MO",
    "wof:name":"Timekeepers In Clayton",
    "wof:placetype":"venue"
},
  "geometry": {"coordinates":[-90.33954199999999,38.651577],"type":"Point"}
}