{
  "type": "Feature",
  "properties": {
    "iso:country":"US",
    "sg:address":"109 N Main St",
    "sg:city":"Ironton",
    "sg:classifiers":[
        {
            "category":"Health Services",
            "subcategory":"Health Practitioner",
            "type":"Services"
        }
    ],
    "sg:phone":"+1 573 546 7000",
    "sg:postcode":"63650",
    "sg:province":"MO",
    "sg:tags":[
        "nurse"
    ],
    "wof:name":"Kathleen Lubbers",
    "wof:placetype":"venue"
},
  "geometry": {"coordinates":[-90.627937,37.600809],"type":"Point"}
}