{
  "type": "Feature",
  "properties": {
    "iso:country":"US",
    "sg:address":"567 Saint Josephs Ln",
    "sg:city":"Ballwin",
    "sg:classifiers":[
        {
            "category":"Education",
            "subcategory":"School",
            "type":"Public Place"
        }
    ],
    "sg:phone":"+1 636 227 5247",
    "sg:postcode":"63021",
    "sg:province":"MO",
    "sg:tags":[
        "organization",
        "religious"
    ],
    "wof:name":"St Joseph Church & School",
    "wof:placetype":"venue"
},
  "geometry": {"coordinates":[-90.517928,38.586995],"type":"Point"}
}