{
  "type": "Feature",
  "properties": {
    "iso:country":"US",
    "sg:address":"458 State Hwy 291",
    "sg:city":"Lees Summit",
    "sg:classifiers":[
        {
            "category":"Real Estate",
            "subcategory":"Real Estate Services",
            "type":"Services"
        }
    ],
    "sg:phone":"+1 816 525 0050",
    "sg:postcode":"64086",
    "sg:province":"MO",
    "sg:tags":[
        "company",
        "title"
    ],
    "wof:name":"Old Republic Title Co",
    "wof:placetype":"venue"
},
  "geometry": {"coordinates":[-94.36161,38.92004],"type":"Point"}
}