{
  "type": "Feature",
  "properties": {
    "iso:country":"US",
    "sg:address":"11504 Nevill Rd",
    "sg:city":"Mountain Grove",
    "sg:classifiers":[
        {
            "category":"Manufacturing",
            "subcategory":"Lumber",
            "type":"Manufacturing & Wholesale Goods"
        }
    ],
    "sg:phone":"+1 417 962 4987",
    "sg:postcode":"65711",
    "sg:province":"MO",
    "sg:tags":[
        "sawmill"
    ],
    "wof:name":"Reed & Wolfe Lumber Co",
    "wof:placetype":"venue"
},
  "geometry": {"coordinates":[-92.179711,37.139616],"type":"Point"}
}