{
  "type": "Feature",
  "properties": {
    "iso:country":"US",
    "sg:address":"9103 Lawn Ave",
    "sg:city":"Saint Louis",
    "sg:classifiers":[
        {
            "category":"Professional",
            "subcategory":"Research",
            "type":"Services"
        }
    ],
    "sg:phone":"+1 314 977 8476",
    "sg:postcode":"63144",
    "sg:province":"MO",
    "sg:tags":[
        "commercial",
        "physical"
    ],
    "wof:name":"Geneprotech Inc",
    "wof:placetype":"venue"
},
  "geometry": {"coordinates":[-90.355673,38.623751],"type":"Point"}
}