{
  "type": "Feature",
  "properties": {
    "iso:country":"US",
    "sg:address":"1926 Matterhorn Dr",
    "sg:city":"Ballwin",
    "sg:classifiers":[
        {
            "category":"Building & Trades",
            "subcategory":"Plumbing",
            "type":"Services"
        }
    ],
    "sg:phone":"+1 636 405 2979",
    "sg:postcode":"63011",
    "sg:province":"MO",
    "sg:tags":[
        "plumber",
        "industrial",
        "contractors-commercial"
    ],
    "wof:name":"Earl Ey Plumbing",
    "wof:placetype":"venue"
},
  "geometry": {"coordinates":[-90.619264,38.596201],"type":"Point"}
}