{
  "type": "Feature",
  "properties": {
    "iso:country":"US",
    "sg:address":"375 S Main St",
    "sg:city":"Memphis",
    "sg:classifiers":[
        {
            "category":"Retail",
            "subcategory":"Auto Repair",
            "type":"Services"
        }
    ],
    "sg:phone":"+1 660 465 2159",
    "sg:postcode":"63555",
    "sg:province":"MO",
    "sg:tags":[
        "body",
        "automobile",
        "painting",
        "repairing"
    ],
    "wof:name":"Walker Motors Collision Repair Inc",
    "wof:placetype":"venue"
},
  "geometry": {"coordinates":[-92.170475,40.454178],"type":"Point"}
}