{
  "type": "Feature",
  "properties": {
    "iso:country":"US",
    "sg:address":"10569 W Farm Rd 188",
    "sg:city":"Republic",
    "sg:classifiers":[
        {
            "category":"Utilities",
            "subcategory":"Fuel Oil & Lpg",
            "type":"Services"
        }
    ],
    "sg:phone":"+1 417 732 6206",
    "sg:postcode":"65738",
    "sg:province":"MO",
    "sg:tags":[
        "liquefied",
        "gas",
        "petroleum"
    ],
    "wof:name":"Hendrickson Propane Inc",
    "wof:placetype":"venue"
},
  "geometry": {"coordinates":[-93.51638800000001,37.108282],"type":"Point"}
}