{
  "type": "Feature",
  "properties": {
    "addr:full":"2301 Holmes St Kansas City MO 64108",
    "addr:housenumber":"2301",
    "addr:postcode":"64108",
    "addr:street":"Holmes St",
    "iso:country":"US",
    "sg:address":"2301 Holmes St",
    "sg:city":"Kansas City",
    "sg:classifiers":[
        {
            "category":"Shopping",
            "subcategory":"Gifts & Souvenirs",
            "type":"Retail Goods"
        }
    ],
    "sg:phone":"+1 816 404 3300",
    "sg:postcode":"64108",
    "sg:province":"MO",
    "sg:tags":[
        "shop"
    ],
    "wof:name":"Truman Medical Center Gift Sp",
    "wof:placetype":"venue"
},
  "geometry": {"coordinates":[-94.575841,39.083943],"type":"Point"}
}