{
  "type": "Feature",
  "properties": {
    "iso:country":"US",
    "sg:address":"17851 US Hwy 40",
    "sg:city":"Independence",
    "sg:classifiers":[
        {
            "category":"Autos & Motor Vehicles",
            "subcategory":"Motorcycle Sales",
            "type":"Retail Goods"
        }
    ],
    "sg:phone":"+1 816 478 9393",
    "sg:postcode":"64055",
    "sg:province":"MO",
    "sg:tags":[
        "scooter"
    ],
    "wof:name":"Donnell's Motorcycles Inc",
    "wof:placetype":"venue"
},
  "geometry": {"coordinates":[-94.36993699999999,39.033726],"type":"Point"}
}