{
  "type": "Feature",
  "properties": {
    "iso:country":"US",
    "sg:address":"230 Oak Tree Acres Ln",
    "sg:city":"Branson",
    "sg:classifiers":[
        {
            "category":"Professional",
            "subcategory":"Art Services",
            "type":"Services"
        }
    ],
    "sg:phone":"+1 417 334 2977",
    "sg:postcode":"65616",
    "sg:province":"MO",
    "sg:tags":[
        "designer",
        "display",
        "producer"
    ],
    "wof:name":"Basket Creations By Design",
    "wof:placetype":"venue"
},
  "geometry": {"coordinates":[-93.170147,36.655783],"type":"Point"}
}