{
  "type": "Feature",
  "properties": {
    "iso:country":"US",
    "sg:address":"6 Nicolet Dr",
    "sg:city":"Ballwin",
    "sg:classifiers":[
        {
            "category":"Health Services",
            "subcategory":"Doctor",
            "type":"Services"
        }
    ],
    "sg:phone":"+1 314 521 5678",
    "sg:postcode":"63011",
    "sg:province":"MO",
    "sg:tags":[
        "dentist"
    ],
    "wof:name":"Sally Hebert DDS",
    "wof:placetype":"venue"
},
  "geometry": {"coordinates":[-90.515738,38.60194],"type":"Point"}
}