{
  "type": "Feature",
  "properties": {
    "iso:country":"US",
    "sg:address":"11 N 7th St",
    "sg:city":"Columbia",
    "sg:classifiers":[
        {
            "category":"Professional",
            "subcategory":"Lawyer & Legal Services",
            "type":"Services"
        }
    ],
    "sg:phone":"+1 573 449 2451",
    "sg:postcode":"65201",
    "sg:province":"MO",
    "sg:tags":[
        "attorney"
    ],
    "wof:name":"Jones Schneider & Bartlett",
    "wof:placetype":"venue"
},
  "geometry": {"coordinates":[-92.329694,38.95166],"type":"Point"}
}