{
  "type": "Feature",
  "properties": {
    "iso:country":"US",
    "sg:address":"1365 Clarkson Pines Ln",
    "sg:city":"Ellisville",
    "sg:classifiers":[
        {
            "category":"Shopping",
            "subcategory":"Catalog Store",
            "type":"Retail Goods"
        }
    ],
    "sg:phone":"+1 636 527 6623",
    "sg:postcode":"63011",
    "sg:province":"MO",
    "sg:tags":[
        "e"
    ],
    "wof:name":"E-Give",
    "wof:placetype":"venue"
},
  "geometry": {"coordinates":[-90.588067,38.601147],"type":"Point"}
}