{
  "type": "Feature",
  "properties": {
    "iso:country":"US",
    "sg:address":"2670 S Kansas Expy",
    "sg:city":"Springfield",
    "sg:classifiers":[
        {
            "category":"Real Estate",
            "subcategory":"Real Estate Services",
            "type":"Services"
        }
    ],
    "sg:phone":"+1 417 823 0494",
    "sg:postcode":"65807",
    "sg:province":"MO",
    "sg:tags":[
        "company",
        "title"
    ],
    "wof:name":"Guaranty Title Co",
    "wof:placetype":"venue"
},
  "geometry": {"coordinates":[-93.316205,37.166103],"type":"Point"}
}