{
  "type": "Feature",
  "properties": {
    "iso:country":"US",
    "sg:address":"410 SW Ward Rd",
    "sg:city":"Lees Summit",
    "sg:classifiers":[
        {
            "category":"Personal",
            "subcategory":"Beauty Salon",
            "type":"Services"
        }
    ],
    "sg:phone":"+1 816 554 0699",
    "sg:postcode":"64081",
    "sg:province":"MO",
    "sg:tags":[
        "shop"
    ],
    "wof:name":"Nails USA",
    "wof:placetype":"venue"
},
  "geometry": {"coordinates":[-94.39540700000001,38.908173],"type":"Point"}
}