{
  "type": "Feature",
  "properties": {
    "iso:country":"US",
    "sg:address":"1201 Highland Ter",
    "sg:city":"Saint Louis",
    "sg:classifiers":[
        {
            "category":"Professional",
            "subcategory":"Art Services",
            "type":"Services"
        }
    ],
    "sg:phone":"+1 314 646 1576",
    "sg:postcode":"63117",
    "sg:province":"MO",
    "sg:tags":[
        "commercial",
        "design"
    ],
    "wof:name":"Noel Gould",
    "wof:placetype":"venue"
},
  "geometry": {"coordinates":[-90.316205,38.629054],"type":"Point"}
}