{
  "type": "Feature",
  "properties": {
    "iso:country":"US",
    "sg:address":"1517 Grand Blvd",
    "sg:city":"Kansas City",
    "sg:classifiers":[
        {
            "category":"Bars & Pubs",
            "type":"Food & Drink"
        }
    ],
    "sg:phone":"+1 816 421 5632",
    "sg:postcode":"64108",
    "sg:province":"MO",
    "sg:tags":[
        "club",
        "night"
    ],
    "wof:name":"Ziegfield's Inc",
    "wof:placetype":"venue"
},
  "geometry": {"coordinates":[-94.581107,39.09464],"type":"Point"}
}