{
  "type": "Feature",
  "properties": {
    "iso:country":"US",
    "sg:address":"700 E Garfield St",
    "sg:city":"Springfield",
    "sg:phone":"+1 417 869 1919",
    "sg:postcode":"65803",
    "sg:province":"MO",
    "sg:website":"http://www.abcmoving1.com",
    "wof:name":"Abc Moving",
    "wof:placetype":"venue"
},
  "geometry": {"coordinates":[-93.284119,37.233799],"type":"Point"}
}