{
  "type": "Feature",
  "properties": {
    "iso:country":"US",
    "sg:address":"1245 Momarte Ln",
    "sg:city":"Saint Louis",
    "sg:classifiers":[
        {
            "category":"Professional",
            "subcategory":"Computer Services",
            "type":"Services"
        }
    ],
    "sg:phone":"+1 314 482 4141",
    "sg:postcode":"63146",
    "sg:province":"MO",
    "sg:tags":[
        "related"
    ],
    "wof:name":"Microwear Computer Services",
    "wof:placetype":"venue"
},
  "geometry": {"coordinates":[-90.430199,38.678759],"type":"Point"}
}