{
  "type": "Feature",
  "properties": {
    "iso:country":"US",
    "sg:address":"18937 State Hwy 133",
    "sg:city":"Dixon",
    "sg:classifiers":[
        {
            "category":"Personal",
            "subcategory":"Beauty Salon",
            "type":"Services"
        }
    ],
    "sg:phone":"+1 573 759 6099",
    "sg:postcode":"65459",
    "sg:province":"MO",
    "sg:tags":[
        "shop"
    ],
    "wof:name":"Family Hair Center",
    "wof:placetype":"venue"
},
  "geometry": {"coordinates":[-92.11228699999999,38.07411],"type":"Point"}
}