{
  "type": "Feature",
  "properties": {
    "iso:country":"US",
    "sg:address":"1649 S Enterprise Ave",
    "sg:city":"Springfield",
    "sg:classifiers":[
        {
            "category":"Organizations",
            "subcategory":"Religious Organization",
            "type":"Services"
        }
    ],
    "sg:phone":"+1 417 869 7878",
    "sg:postcode":"65804",
    "sg:province":"MO",
    "sg:tags":[
        "church"
    ],
    "wof:name":"United Methodist District Ofc",
    "wof:placetype":"venue"
},
  "geometry": {"coordinates":[-93.249576,37.184522],"type":"Point"}
}