{
  "type": "Feature",
  "properties": {
    "iso:country":"US",
    "sg:address":"9398 Olive Blvd",
    "sg:city":"St Louis",
    "sg:classifiers":[
        {
            "category":"Autos & Motor Vehicles",
            "subcategory":"Fuel & Gas Station",
            "type":"Retail Goods"
        }
    ],
    "sg:phone":"+1 314 997 1126",
    "sg:postcode":"63132",
    "sg:province":"MO",
    "sg:tags":[
        "oil"
    ],
    "wof:name":"Olivette 66 Svc Ctr",
    "wof:placetype":"venue"
},
  "geometry": {"coordinates":[-90.37421999999999,38.674105],"type":"Point"}
}