{
  "type": "Feature",
  "properties": {
    "iso:country":"US",
    "sg:address":"2105 NE Concord Cir",
    "sg:city":"Lees Summit",
    "sg:classifiers":[
        {
            "category":"Professional",
            "subcategory":"Business Services",
            "type":"Services"
        }
    ],
    "sg:phone":"+1 816 524 7976",
    "sg:postcode":"64086",
    "sg:province":"MO",
    "wof:name":"Walking On Water Pool Service",
    "wof:placetype":"venue"
},
  "geometry": {"coordinates":[-94.331559,38.924117],"type":"Point"}
}