{
  "type": "Feature",
  "properties": {
    "iso:country":"US",
    "sg:address":"20209 Icon Rd",
    "sg:city":"Maryville",
    "sg:classifiers":[
        {
            "category":"Building & Trades",
            "subcategory":"Construction",
            "type":"Services"
        }
    ],
    "sg:phone":"+1 660 582 2078",
    "sg:postcode":"64468",
    "sg:province":"MO",
    "sg:tags":[
        "contractor"
    ],
    "wof:name":"Piveral Construction Co",
    "wof:placetype":"venue"
},
  "geometry": {"coordinates":[-94.890974,40.429465],"type":"Point"}
}