{
  "type": "Feature",
  "properties": {
    "iso:country":"US",
    "sg:address":"3107 E Chestnut Expy",
    "sg:city":"Springfield",
    "sg:classifiers":[
        {
            "category":"Home & Garden",
            "subcategory":"Furniture",
            "type":"Retail Goods"
        }
    ],
    "sg:phone":"+1 417 869 0174",
    "sg:postcode":"65802",
    "sg:province":"MO",
    "sg:website":"www.outdoorhome.com",
    "wof:name":"Outdoor Home",
    "wof:placetype":"venue"
},
  "geometry": {"coordinates":[-93.23358399999999,37.209859],"type":"Point"}
}