{
  "type": "Feature",
  "properties": {
    "iso:country":"US",
    "sg:address":"1106 W Beverly Hills Dr",
    "sg:city":"Springfield",
    "sg:classifiers":[
        {
            "category":"Professional",
            "subcategory":"Art Services",
            "type":"Services"
        }
    ],
    "sg:phone":"+1 417 833 0222",
    "sg:postcode":"65803",
    "sg:province":"MO",
    "sg:tags":[
        "management",
        "photography",
        "commercial",
        "real estate"
    ],
    "sg:website":"http://www.aerialphotoinc.com",
    "wof:name":"Aerial Photography",
    "wof:placetype":"venue"
},
  "geometry": {"coordinates":[-93.303541,37.264671],"type":"Point"}
}