{
  "type": "Feature",
  "properties": {
    "iso:country":"US",
    "sg:address":"5237 Genevieve Ave",
    "sg:city":"St Louis",
    "sg:classifiers":[
        {
            "category":"Shopping",
            "subcategory":"Used Merchandise",
            "type":"Retail Goods"
        }
    ],
    "sg:phone":"+1 314 381 9984",
    "sg:postcode":"63120",
    "sg:province":"MO",
    "sg:tags":[
        "antique"
    ],
    "wof:name":"Elmira Antique Odds N Ends",
    "wof:placetype":"venue"
},
  "geometry": {"coordinates":[-90.24835899999999,38.697498],"type":"Point"}
}