{
  "type": "Feature",
  "properties": {
    "iso:country":"US",
    "sg:address":"6 Vicksburg Station",
    "sg:city":"St Charles",
    "sg:classifiers":[
        {
            "category":"Building & Trades",
            "subcategory":"Construction",
            "type":"Services"
        }
    ],
    "sg:phone":"+1 636 936 8100",
    "sg:postcode":"63303",
    "sg:province":"MO",
    "sg:tags":[
        "safety",
        "treatment",
        "floor"
    ],
    "wof:name":"Applied Solutions",
    "wof:placetype":"venue"
},
  "geometry": {"coordinates":[-90.54146900000001,38.74602],"type":"Point"}
}