{
  "type": "Feature",
  "properties": {
    "iso:country":"US",
    "sg:address":"190 Carondelet Plz",
    "sg:city":"St Louis",
    "sg:classifiers":[
        {
            "category":"Real Estate",
            "subcategory":"Developer",
            "type":"Services"
        },
        {
            "category":"Professional",
            "subcategory":"Business Services",
            "type":"Services"
        }
    ],
    "sg:phone":"+1 314 863 0076",
    "sg:postcode":"63105",
    "sg:province":"MO",
    "sg:tags":[
        "development"
    ],
    "wof:name":"Freedom Development Group",
    "wof:placetype":"venue"
},
  "geometry": {"coordinates":[-90.333601,38.648562],"type":"Point"}
}