{
  "type": "Feature",
  "properties": {
    "iso:country":"US",
    "sg:address":"200 Meadowbrook Country Club Est",
    "sg:city":"Ballwin",
    "sg:classifiers":[
        {
            "category":"Shopping",
            "subcategory":"Bicycles & Sporting Goods",
            "type":"Retail Goods"
        },
        {
            "category":"Sports & Exercise",
            "subcategory":"Golf",
            "type":"Entertainment"
        }
    ],
    "sg:phone":"+1 636 227 9962",
    "sg:postcode":"63011",
    "sg:province":"MO",
    "sg:tags":[
        "equipment",
        "course",
        "supply"
    ],
    "wof:name":"Cal Golf Shop, Inc",
    "wof:placetype":"venue"
},
  "geometry": {"coordinates":[-90.56619999999999,38.618],"type":"Point"}
}