{
  "type": "Feature",
  "properties": {
    "iso:country":"US",
    "sg:address":"531 Beechcraft Ave",
    "sg:city":"Chesterfield",
    "sg:classifiers":[
        {
            "category":"Wholesale",
            "subcategory":"Machinery & Supplies",
            "type":"Manufacturing & Wholesale Goods"
        }
    ],
    "sg:phone":"+1 636 532 9357",
    "sg:postcode":"63005",
    "sg:province":"MO",
    "sg:tags":[
        "equipment",
        "establishment",
        "se"
    ],
    "wof:name":"Spirit of St Louis Airport",
    "wof:placetype":"venue"
},
  "geometry": {"coordinates":[-90.651847,38.663526],"type":"Point"}
}