{
  "type": "Feature",
  "properties": {
    "iso:country":"US",
    "sg:address":"12903 US Hwy 71",
    "sg:city":"Grandview",
    "sg:classifiers":[
        {
            "category":"Retail",
            "subcategory":"Portrait Studio",
            "type":"Services"
        }
    ],
    "sg:phone":"+1 816 761 2525",
    "sg:postcode":"64030",
    "sg:province":"MO",
    "sg:tags":[
        "photographer"
    ],
    "wof:name":"Lang Group",
    "wof:placetype":"venue"
},
  "geometry": {"coordinates":[-94.524852,38.890542],"type":"Point"}
}