{
  "type": "Feature",
  "properties": {
    "iso:country":"US",
    "sg:address":"212 Cross Keys Shopping Center",
    "sg:city":"Florissant",
    "sg:classifiers":[
        {
            "category":"Health Services",
            "subcategory":"Chiropractor",
            "type":"Services"
        }
    ],
    "sg:phone":"+1 314 921 1144",
    "sg:postcode":"63033",
    "sg:province":"MO",
    "wof:name":"Cross Keys Chiropractic Ctr",
    "wof:placetype":"venue"
},
  "geometry": {"coordinates":[-90.29855999999999,38.808375],"type":"Point"}
}