{
  "type": "Feature",
  "properties": {
    "iso:country":"US",
    "sg:address":"410 Highland Ave",
    "sg:city":"Caruthersville",
    "sg:classifiers":[
        {
            "category":"Professional",
            "type":"Services"
        }
    ],
    "sg:phone":"+1 573 333 2936",
    "sg:postcode":"63830",
    "sg:province":"MO",
    "wof:name":"Aaron W Gamble Process Service",
    "wof:placetype":"venue"
},
  "geometry": {"coordinates":[-89.657444,36.193027],"type":"Point"}
}