{
  "type": "Feature",
  "properties": {
    "iso:country":"US",
    "sg:address":"310 N Main St",
    "sg:city":"Maryville",
    "sg:classifiers":[
        {
            "category":"Bars & Pubs",
            "type":"Food & Drink"
        }
    ],
    "sg:phone":"+1 660 582 2333",
    "sg:postcode":"64468",
    "sg:province":"MO",
    "wof:name":"Lucky's",
    "wof:placetype":"venue"
},
  "geometry": {"coordinates":[-94.872961,40.34872],"type":"Point"}
}