{
  "type": "Feature",
  "properties": {
    "iso:country":"US",
    "sg:address":"4472 Lindell Blvd",
    "sg:city":"Saint Louis",
    "sg:classifiers":[
        {
            "category":"Professional",
            "subcategory":"Lawyer & Legal Services",
            "type":"Services"
        }
    ],
    "sg:phone":"+1 314 721 4000",
    "sg:postcode":"63108",
    "sg:province":"MO",
    "wof:name":"McCloskey Patricia N Atty",
    "wof:placetype":"venue"
},
  "geometry": {"coordinates":[-90.254949,38.641404],"type":"Point"}
}