{
  "type": "Feature",
  "properties": {
    "iso:country":"US",
    "sg:address":"1102 State Hwy 28",
    "sg:city":"Owensville",
    "sg:classifiers":[
        {
            "category":"Wholesale",
            "subcategory":"Machinery & Supplies",
            "type":"Manufacturing & Wholesale Goods"
        }
    ],
    "sg:phone":"+1 573 437 4421",
    "sg:postcode":"65066",
    "sg:province":"MO",
    "sg:tags":[
        "farm",
        "implement"
    ],
    "wof:name":"Service International",
    "wof:placetype":"venue"
},
  "geometry": {"coordinates":[-91.519403,38.336858],"type":"Point"}
}