{
  "type": "Feature",
  "properties": {
    "iso:country":"US",
    "sg:address":"1560 Woodlake Dr",
    "sg:city":"Chesterfield",
    "sg:classifiers":[
        {
            "category":"Real Estate",
            "subcategory":"Architect",
            "type":"Services"
        }
    ],
    "sg:phone":"+1 314 434 9393",
    "sg:postcode":"63017",
    "sg:province":"MO",
    "sg:tags":[
        "specification",
        "construction",
        "architectural",
        "engineer"
    ],
    "sg:website":"http://www.galehillinc.com",
    "wof:name":"Gale Hill Associates Inc",
    "wof:placetype":"venue"
},
  "geometry": {"coordinates":[-90.517205,38.641758],"type":"Point"}
}