{
  "type": "Feature",
  "properties": {
    "iso:country":"US",
    "sg:address":"2301 S Commercial St",
    "sg:city":"Harrisonville",
    "sg:classifiers":[
        {
            "category":"Shopping",
            "subcategory":"Used Merchandise",
            "type":"Retail Goods"
        }
    ],
    "sg:phone":"+1 816 380 3716",
    "sg:postcode":"64701",
    "sg:province":"MO",
    "wof:name":"Harrisonville Trade Fair Mall",
    "wof:placetype":"venue"
},
  "geometry": {"coordinates":[-94.352208,38.638659],"type":"Point"}
}