{
  "type": "Feature",
  "properties": {
    "iso:country":"US",
    "sg:address":"238 E Washington St",
    "sg:city":"Marshfield",
    "sg:classifiers":[
        {
            "category":"Shopping",
            "subcategory":"Used Merchandise",
            "type":"Retail Goods"
        }
    ],
    "sg:phone":"+1 417 859 4100",
    "sg:postcode":"65706",
    "sg:province":"MO",
    "sg:tags":[
        "pawnbroker"
    ],
    "wof:name":"Redbeards",
    "wof:placetype":"venue"
},
  "geometry": {"coordinates":[-92.904568,37.338566],"type":"Point"}
}