{
  "type": "Feature",
  "properties": {
    "iso:country":"US",
    "sg:address":"2370 S Farm Rd 219",
    "sg:city":"Springfield",
    "sg:classifiers":[
        {
            "category":"Professional",
            "type":"Services"
        }
    ],
    "sg:phone":"+1 417 881 8909",
    "sg:postcode":"65809",
    "sg:province":"MO",
    "wof:name":"Timothy S McKnight",
    "wof:placetype":"venue"
},
  "geometry": {"coordinates":[-93.14619,37.168487],"type":"Point"}
}