{
  "type": "Feature",
  "properties": {
    "iso:country":"US",
    "sg:address":"12640 Derstler Rd",
    "sg:city":"Richmond",
    "sg:phone":"+1 816 776 7668",
    "sg:postcode":"64085",
    "sg:province":"MO",
    "sg:tags":[
        "farm"
    ],
    "wof:name":"David Moyer",
    "wof:placetype":"venue"
},
  "geometry": {"coordinates":[-93.956711,39.326092],"type":"Point"}
}