{
  "type": "Feature",
  "properties": {
    "iso:country":"US",
    "sg:address":"3481 S Parkmont Ct",
    "sg:city":"Springfield",
    "sg:classifiers":[
        {
            "category":"Real Estate",
            "subcategory":"Real Estate Operator",
            "type":"Services"
        }
    ],
    "sg:phone":"+1 417 886 5028",
    "sg:postcode":"65807",
    "sg:province":"MO",
    "sg:tags":[
        "mobile",
        "home",
        "site"
    ],
    "wof:name":"Dees Enterprises LLC",
    "wof:placetype":"venue"
},
  "geometry": {"coordinates":[-93.34442199999999,37.15247],"type":"Point"}
}