{
  "type": "Feature",
  "properties": {
    "addr:full":"101 E Main St Richmond MO 64085",
    "addr:housenumber":"101",
    "addr:postcode":"64085",
    "addr:street":"E Main St",
    "iso:country":"US",
    "sg:address":"101 E Main St",
    "sg:city":"Richmond",
    "sg:classifiers":[
        {
            "category":"Banks & Credit Unions",
            "subcategory":"Bank",
            "type":"Services"
        }
    ],
    "sg:phone":"+1 816 776 5881",
    "sg:postcode":"64085",
    "sg:province":"MO",
    "sg:tags":[
        "national",
        "commercial"
    ],
    "wof:name":"Bank Of America",
    "wof:placetype":"venue"
},
  "geometry": {"coordinates":[-93.97517499999999,39.278435],"type":"Point"}
}