{
  "type": "Feature",
  "properties": {
    "iso:country":"US",
    "sg:address":"700 N Edwards St",
    "sg:city":"Malden",
    "sg:classifiers":[
        {
            "category":"Place Of Worship",
            "subcategory":"Church",
            "type":"Public Place"
        },
        {
            "category":"Place Of Worship",
            "type":"Public Place"
        }
    ],
    "sg:phone":"+1 573 276 5970",
    "sg:postcode":"63863",
    "sg:province":"MO",
    "sg:tags":[
        "churches-baptist-general",
        "churches-baptist"
    ],
    "wof:name":"Macedonia Missionary Baptist Church",
    "wof:placetype":"venue"
},
  "geometry": {"coordinates":[-89.961647,36.565289],"type":"Point"}
}