{
  "type": "Feature",
  "properties": {
    "iso:country":"US",
    "sg:address":"6510 Chippewa St",
    "sg:city":"Saint Louis",
    "sg:classifiers":[
        {
            "category":"Shopping",
            "subcategory":"Comic Books",
            "type":"Retail Goods"
        }
    ],
    "sg:phone":"+1 314 353 9500",
    "sg:postcode":"63109",
    "sg:province":"MO",
    "wof:name":"Mo's Comics & Stories Shop",
    "wof:placetype":"venue"
},
  "geometry": {"coordinates":[-90.30229300000001,38.59208],"type":"Point"}
}