{
  "type": "Feature",
  "properties": {
    "iso:country":"US",
    "sg:address":"5100 Oak St",
    "sg:city":"Kansas City",
    "sg:classifiers":[
        {
            "category":"Education",
            "subcategory":"Special Training",
            "type":"Public Place"
        }
    ],
    "sg:phone":"+1 816 235 1589",
    "sg:postcode":"64112",
    "sg:province":"MO",
    "wof:name":"Generalservice Building",
    "wof:placetype":"venue"
},
  "geometry": {"coordinates":[-94.582813,39.032224],"type":"Point"}
}