{
  "type": "Feature",
  "properties": {
    "iso:country":"US",
    "sg:address":"735 W Stadium Blvd",
    "sg:city":"Jefferson City",
    "sg:classifiers":[
        {
            "category":"Coffee & Tea",
            "type":"Food & Drink"
        }
    ],
    "sg:menulink":"http://www.allmenus.com/mo/jefferson/115384-starbucks-coffee/menu/",
    "sg:phone":"+1 573 635 8401",
    "sg:postcode":"65109",
    "sg:province":"MO",
    "sg:tags":[
        "american"
    ],
    "wof:name":"Starbucks Coffee",
    "wof:placetype":"venue"
},
  "geometry": {"coordinates":[-92.21581999999999,38.58108],"type":"Point"}
}