{
  "type": "Feature",
  "properties": {
    "iso:country":"US",
    "sg:address":"48816 Vista Rd",
    "sg:city":"Browning",
    "sg:classifiers":[
        {
            "category":"Real Estate",
            "subcategory":"Real Estate Agent",
            "type":"Services"
        }
    ],
    "sg:phone":"+1 660 946 4475",
    "sg:postcode":"64630",
    "sg:province":"MO",
    "wof:name":"Browning Housing Corp",
    "wof:placetype":"venue"
},
  "geometry": {"coordinates":[-93.198977,40.065145],"type":"Point"}
}