{
  "type": "Feature",
  "properties": {
    "iso:country":"US",
    "sg:address":"129 N Massey Blvd",
    "sg:city":"Nixa",
    "sg:classifiers":[
        {
            "category":"Restaurant",
            "type":"Food & Drink"
        }
    ],
    "sg:menulink":"http://www.allmenus.com/mo/union-chapel/60380-papa-johns-pizza/menu/",
    "sg:phone":"+1 417 725 7676",
    "sg:postcode":"65714",
    "sg:province":"MO",
    "sg:tags":[
        "american",
        "pizza"
    ],
    "wof:name":"Papa John's Pizza",
    "wof:placetype":"venue"
},
  "geometry": {"coordinates":[-93.303112,37.046498],"type":"Point"}
}