{
  "type": "Feature",
  "properties": {
    "iso:country":"US",
    "sg:address":"123 E Colorado Ave",
    "sg:city":"Bland",
    "sg:classifiers":[
        {
            "category":"Personal",
            "subcategory":"Beauty Salon",
            "type":"Services"
        }
    ],
    "sg:phone":"+1 573 646 3310",
    "sg:postcode":"65014",
    "sg:province":"MO",
    "wof:name":"Delight Shear Beauty Shop",
    "wof:placetype":"venue"
},
  "geometry": {"coordinates":[-91.628792,38.302349],"type":"Point"}
}