{
  "type": "Feature",
  "properties": {
    "iso:country":"US",
    "sg:address":"1006 W Harmony St",
    "sg:city":"Neosho",
    "sg:classifiers":[
        {
            "category":"Communications",
            "subcategory":"Newspaper",
            "type":"Services"
        }
    ],
    "sg:phone":"+1 417 451 0747",
    "sg:postcode":"64850",
    "sg:province":"MO",
    "sg:website":"http://www.gatehousemedia.com",
    "wof:name":"Gatehouse Media",
    "wof:placetype":"venue"
},
  "geometry": {"coordinates":[-94.382166,36.869011],"type":"Point"}
}