{
  "type": "Feature",
  "properties": {
    "iso:country":"US",
    "sg:address":"615 S Washington St",
    "sg:city":"Chillicothe",
    "sg:classifiers":[
        {
            "category":"Wholesale",
            "subcategory":"Farm Supplies",
            "type":"Manufacturing & Wholesale Goods"
        }
    ],
    "sg:phone":"+1 660 646 5454",
    "sg:postcode":"64601",
    "sg:province":"MO",
    "wof:name":"Orscheln Farm & Home",
    "wof:placetype":"venue"
},
  "geometry": {"coordinates":[-93.55276499999999,39.781181],"type":"Point"}
}