{
  "type": "Feature",
  "properties": {
    "iso:country":"US",
    "sg:address":"117 Front St",
    "sg:city":"Labadie",
    "sg:classifiers":[
        {
            "category":"Restaurant",
            "type":"Food & Drink"
        }
    ],
    "sg:phone":"+1 636 451 0100",
    "sg:postcode":"63055",
    "sg:province":"MO",
    "sg:website":"http://www.3brothersrestaurantandbar.com/",
    "wof:name":"3 Brothers",
    "wof:placetype":"venue"
},
  "geometry": {"coordinates":[-90.84811000000001,38.528683],"type":"Point"}
}