{
  "type": "Feature",
  "properties": {
    "iso:country":"US",
    "sg:address":"6920 NW 79 Ter",
    "sg:city":"Kansas City",
    "sg:classifiers":[
        {
            "category":"Insurance",
            "subcategory":"Insurance Agent",
            "type":"Services"
        }
    ],
    "sg:phone":"+1 816 505 3735",
    "sg:postcode":"64152",
    "sg:province":"MO",
    "sg:tags":[
        "processing"
    ],
    "wof:name":"Electronic Health Claim Svc",
    "wof:placetype":"venue"
},
  "geometry": {"coordinates":[-94.662164,39.238962],"type":"Point"}
}