{
  "type": "Feature",
  "properties": {
    "iso:country":"US",
    "sg:address":"200 Wilshire Blvd",
    "sg:city":"Liberty",
    "sg:classifiers":[
        {
            "category":"Building & Trades",
            "subcategory":"Construction",
            "type":"Services"
        }
    ],
    "sg:phone":"+1 816 804 0673",
    "sg:postcode":"64068",
    "sg:province":"MO",
    "sg:tags":[
        "carpentry",
        "contractor"
    ],
    "wof:name":"L R S Construction",
    "wof:placetype":"venue"
},
  "geometry": {"coordinates":[-94.45635900000001,39.233115],"type":"Point"}
}