{
  "type": "Feature",
  "properties": {
    "iso:country":"US",
    "sg:address":"4600 State Hwy Y",
    "sg:city":"Cleveland",
    "sg:classifiers":[
        {
            "category":"Mining & Drilling",
            "type":"Manufacturing & Wholesale Goods"
        }
    ],
    "sg:phone":"+1 816 618 7625",
    "sg:postcode":"64734",
    "sg:province":"MO",
    "sg:tags":[
        "quarry"
    ],
    "wof:name":"Beyer Crushed Rock",
    "wof:placetype":"venue"
},
  "geometry": {"coordinates":[-94.55096500000001,38.684531],"type":"Point"}
}