{
  "type": "Feature",
  "properties": {
    "iso:country":"US",
    "sg:address":"1008 W Mill St",
    "sg:city":"Butler",
    "sg:classifiers":[
        {
            "category":"Farming",
            "subcategory":"Livestock Farm",
            "type":"Manufacturing & Wholesale Goods"
        }
    ],
    "sg:phone":"+1 660 679 4494",
    "sg:postcode":"64730",
    "sg:province":"MO",
    "sg:tags":[
        "ranch",
        "feedlot",
        "beef",
        "cattle"
    ],
    "wof:name":"Herman Shubert",
    "wof:placetype":"venue"
},
  "geometry": {"coordinates":[-94.349647,38.264225],"type":"Point"}
}