{
  "type": "Feature",
  "properties": {
    "addr:full":"76 State Hwy 13 Reeds Spring MO 65737",
    "addr:housenumber":"76",
    "addr:postcode":"65737",
    "addr:street":"State Hwy 13 Reeds",
    "iso:country":"US",
    "sg:address":"76 State Hwy 13",
    "sg:city":"Reeds Spring",
    "sg:classifiers":[
        {
            "category":"Professional",
            "subcategory":"Accounting & Tax Preparation",
            "type":"Services"
        }
    ],
    "sg:phone":"+1 417 272 8998",
    "sg:postcode":"65737",
    "sg:province":"MO",
    "wof:name":"H & R Block",
    "wof:placetype":"venue"
},
  "geometry": {"coordinates":[-93.383115,36.754658],"type":"Point"}
}