{
  "type": "Feature",
  "properties": {
    "iso:country":"US",
    "sg:address":"720 Oak St",
    "sg:city":"Kansas City",
    "sg:classifiers":[
        {
            "category":"Professional",
            "subcategory":"Employment Agencies",
            "type":"Services"
        },
        {
            "category":"Social Services",
            "type":"Services"
        }
    ],
    "sg:phone":"+1 816 822 8083",
    "sg:postcode":"64106",
    "sg:province":"MO",
    "sg:tags":[
        "training",
        "woman",
        "for",
        "low",
        "welfare",
        "organization"
    ],
    "wof:name":"Women's Employment Network",
    "wof:placetype":"venue"
},
  "geometry": {"coordinates":[-94.578053,39.104881],"type":"Point"}
}