{
  "type": "Feature",
  "properties": {
    "iso:country":"US",
    "sg:address":"111 W Dakota St",
    "sg:city":"Butler",
    "sg:classifiers":[
        {
            "category":"Banks & Credit Unions",
            "subcategory":"Investment Brokerage",
            "type":"Services"
        },
        {
            "category":"Insurance",
            "subcategory":"Hazard Insurance",
            "type":"Services"
        }
    ],
    "sg:phone":"+1 660 679 6186",
    "sg:postcode":"64730",
    "sg:province":"MO",
    "sg:tags":[
        "agent",
        "resume"
    ],
    "wof:name":"F R M S",
    "wof:placetype":"venue"
},
  "geometry": {"coordinates":[-94.333248,38.257464],"type":"Point"}
}