{
  "type": "Feature",
  "properties": {
    "iso:country":"US",
    "sg:address":"455 E Elliott Ave",
    "sg:city":"St Louis",
    "sg:classifiers":[
        {
            "category":"Wholesale",
            "subcategory":"Machinery & Supplies",
            "type":"Manufacturing & Wholesale Goods"
        }
    ],
    "sg:phone":"+1 314 965 6500",
    "sg:postcode":"63122",
    "sg:province":"MO",
    "sg:tags":[
        "steel",
        "shop",
        "handling",
        "shelving",
        "material",
        "metal",
        "equipment"
    ],
    "sg:website":"www.industrialshelving.com",
    "wof:name":"Industrial Shelving Systems",
    "wof:placetype":"venue"
},
  "geometry": {"coordinates":[-90.396974,38.57398],"type":"Point"}
}