{
  "type": "Feature",
  "properties": {
    "iso:country":"US",
    "sg:address":"107 Tori Pines Dr",
    "sg:city":"Saint Louis",
    "sg:classifiers":[
        {
            "category":"Real Estate",
            "subcategory":"Real Estate Operator",
            "type":"Services"
        }
    ],
    "sg:phone":"+1 314 293 0676",
    "sg:postcode":"63129",
    "sg:province":"MO",
    "sg:tags":[
        "building",
        "builder",
        "apartment",
        "operative"
    ],
    "wof:name":"Tori Pines Villas",
    "wof:placetype":"venue"
},
  "geometry": {"coordinates":[-90.30620999999999,38.457439],"type":"Point"}
}