{
  "type": "Feature",
  "properties": {
    "iso:country":"US",
    "sg:address":"16105 Spring Valley Rd",
    "sg:city":"Belton",
    "sg:classifiers":[
        {
            "category":"Restaurant",
            "type":"Food & Drink"
        }
    ],
    "sg:phone":"+1 816 318 1891",
    "sg:postcode":"64012",
    "sg:province":"MO",
    "sg:tags":[
        "caterer",
        "catering"
    ],
    "wof:name":"Silber Spoons Catering Inc",
    "wof:placetype":"venue"
},
  "geometry": {"coordinates":[-94.496461,38.828182],"type":"Point"}
}