{
  "type": "Feature",
  "properties": {
    "iso:country":"US",
    "sg:address":"1315 S Landrum St",
    "sg:city":"Mount Vernon",
    "sg:classifiers":[
        {
            "category":"Local Transit",
            "type":"Transportation"
        }
    ],
    "sg:phone":"+1 417 466 3280",
    "sg:postcode":"65712",
    "sg:province":"MO",
    "sg:tags":[
        "passenger"
    ],
    "wof:name":"Saint Jhns Paramedic Ambulance",
    "wof:placetype":"venue"
},
  "geometry": {"coordinates":[-93.823189,37.092839],"type":"Point"}
}