{
  "type": "Feature",
  "properties": {
    "iso:country":"US",
    "sg:address":"810 Southwest Blvd",
    "sg:city":"Kansas City",
    "sg:classifiers":[
        {
            "category":"Restaurant",
            "type":"Food & Drink"
        }
    ],
    "sg:phone":"+1 816 471 5442",
    "sg:postcode":"64108",
    "sg:province":"MO",
    "wof:name":"El Pueblito",
    "wof:placetype":"venue"
},
  "geometry": {"coordinates":[-94.59470399999999,39.084354],"type":"Point"}
}