{
  "type": "Feature",
  "properties": {
    "iso:country":"US",
    "sg:address":"279 US Hwy 50",
    "sg:city":"Warrensburg",
    "sg:classifiers":[
        {
            "category":"Home & Garden",
            "subcategory":"Carpets & Floor Coverings",
            "type":"Retail Goods"
        }
    ],
    "sg:phone":"+1 660 429 3833",
    "sg:postcode":"64093",
    "sg:province":"MO",
    "wof:name":"Integrity Interiors",
    "wof:placetype":"venue"
},
  "geometry": {"coordinates":[-93.664489,38.772799],"type":"Point"}
}