{
  "type": "Feature",
  "properties": {
    "iso:country":"US",
    "sg:address":"1320 Rolling Fields Dr",
    "sg:city":"Jackson",
    "sg:classifiers":[
        {
            "category":"Real Estate",
            "subcategory":"Developer",
            "type":"Services"
        }
    ],
    "sg:phone":"+1 573 243 5882",
    "sg:postcode":"63755",
    "sg:province":"MO",
    "sg:tags":[
        "cemetery"
    ],
    "wof:name":"German Evangelical Church",
    "wof:placetype":"venue"
},
  "geometry": {"coordinates":[-89.68628200000001,37.38469],"type":"Point"}
}