{
  "type": "Feature",
  "properties": {
    "iso:country":"US",
    "sg:address":"21 W 53 St",
    "sg:city":"Kansas City",
    "sg:classifiers":[
        {
            "category":"Building & Trades",
            "subcategory":"Construction",
            "type":"Services"
        }
    ],
    "sg:phone":"+1 816 361 6894",
    "sg:postcode":"64112",
    "sg:province":"MO",
    "sg:tags":[
        "house"
    ],
    "wof:name":"Pete-Douglas Construction",
    "wof:placetype":"venue"
},
  "geometry": {"coordinates":[-94.58989800000001,39.030928],"type":"Point"}
}