{
  "type": "Feature",
  "properties": {
    "iso:country":"US",
    "sg:address":"531 George St",
    "sg:city":"Marshfield",
    "sg:classifiers":[
        {
            "category":"Manufacturing",
            "subcategory":"Wood Products",
            "type":"Manufacturing & Wholesale Goods"
        }
    ],
    "sg:phone":"+1 417 234 1232",
    "sg:postcode":"65706",
    "sg:province":"MO",
    "sg:tags":[
        "millwork"
    ],
    "wof:name":"Masters Millwork Co",
    "wof:placetype":"venue"
},
  "geometry": {"coordinates":[-92.923452,37.332121],"type":"Point"}
}