{
  "type": "Feature",
  "properties": {
    "iso:country":"US",
    "sg:address":"4675 N Gretna Rd",
    "sg:city":"Branson",
    "sg:classifiers":[
        {
            "category":"Banks & Credit Unions",
            "subcategory":"Bank",
            "type":"Services"
        }
    ],
    "sg:phone":"+1 417 334 6474",
    "sg:postcode":"65616",
    "sg:province":"MO",
    "wof:name":"Hawthorn Bank",
    "wof:placetype":"venue"
},
  "geometry": {"coordinates":[-93.256726,36.66161],"type":"Point"}
}