{
  "type": "Feature",
  "properties": {
    "iso:country":"US",
    "sg:address":"390 S Woods Mill Rd",
    "sg:city":"Chesterfield",
    "sg:classifiers":[
        {
            "category":"Real Estate",
            "subcategory":"Real Estate Agent",
            "type":"Services"
        }
    ],
    "sg:phone":"+1 314 205 1335",
    "sg:postcode":"63017",
    "sg:province":"MO",
    "wof:name":"Fairfield IV",
    "wof:placetype":"venue"
},
  "geometry": {"coordinates":[-90.508492,38.651542],"type":"Point"}
}