{
  "type": "Feature",
  "properties": {
    "iso:country":"US",
    "sg:address":"7211 Olive Blvd",
    "sg:city":"St Louis",
    "sg:classifiers":[
        {
            "category":"Professional",
            "subcategory":"Advertising",
            "type":"Services"
        }
    ],
    "sg:phone":"+1 314 721 1401",
    "sg:postcode":"63130",
    "sg:province":"MO",
    "wof:name":"St Louis Promotions",
    "wof:placetype":"venue"
},
  "geometry": {"coordinates":[-90.32160399999999,38.669706],"type":"Point"}
}