{
  "type": "Feature",
  "properties": {
    "iso:country":"US",
    "sg:address":"704 S Franklin St",
    "sg:city":"Cuba",
    "sg:classifiers":[
        {
            "category":"Autos & Motor Vehicles",
            "subcategory":"Automobile Sales",
            "type":"Retail Goods"
        },
        {
            "category":"Retail",
            "subcategory":"Auto Repair",
            "type":"Services"
        }
    ],
    "sg:phone":"+1 573 885 2886",
    "sg:postcode":"65453",
    "sg:province":"MO",
    "sg:tags":[
        "car",
        "used"
    ],
    "sg:website":"http://qualitypreownedautomotive.com",
    "wof:name":"Quality Preowned Automotive",
    "wof:placetype":"venue"
},
  "geometry": {"coordinates":[-91.402086,38.059161],"type":"Point"}
}