{
  "type": "Feature",
  "properties": {
    "iso:country":"US",
    "sg:address":"5410 Co Rd 302",
    "sg:city":"Maywood",
    "sg:classifiers":[
        {
            "category":"Shopping",
            "subcategory":"Bicycles & Sporting Goods",
            "type":"Retail Goods"
        }
    ],
    "sg:phone":"+1 573 478 3396",
    "sg:postcode":"63454",
    "sg:province":"MO",
    "wof:name":"Stones Sportsman Inc",
    "wof:placetype":"venue"
},
  "geometry": {"coordinates":[-91.584543,39.939916],"type":"Point"}
}