{
  "type": "Feature",
  "properties": {
    "iso:country":"US",
    "sg:address":"10406 Ladue Rd",
    "sg:city":"St Louis",
    "sg:classifiers":[
        {
            "category":"Professional",
            "subcategory":"Management & Consulting",
            "type":"Services"
        }
    ],
    "sg:phone":"+1 314 997 8801",
    "sg:postcode":"63141",
    "sg:province":"MO",
    "sg:tags":[
        "consultant",
        "business"
    ],
    "wof:name":"Susan Cejka",
    "wof:placetype":"venue"
},
  "geometry": {"coordinates":[-90.40631399999999,38.654974],"type":"Point"}
}