{
  "type": "Feature",
  "properties": {
    "iso:country":"US",
    "sg:address":"1599 State Hwy 72",
    "sg:city":"Rolla",
    "sg:classifiers":[
        {
            "category":"Building & Trades",
            "subcategory":"Construction",
            "type":"Services"
        }
    ],
    "sg:phone":"+1 573 364 6830",
    "sg:postcode":"65401",
    "sg:province":"MO",
    "sg:tags":[
        "insulation",
        "contractor"
    ],
    "wof:name":"H & H Insulation Service",
    "wof:placetype":"venue"
},
  "geometry": {"coordinates":[-91.744615,37.933667],"type":"Point"}
}