{
  "type": "Feature",
  "properties": {
    "addr:full":"6071 Telegraph Rd St Louis MO 63129",
    "addr:housenumber":"6071",
    "addr:postcode":"63129",
    "addr:street":"Telegraph Rd",
    "iso:country":"US",
    "sg:address":"6071 Telegraph Rd",
    "sg:city":"St Louis",
    "sg:classifiers":[
        {
            "category":"Shopping",
            "subcategory":"Pharmacy",
            "type":"Retail Goods"
        }
    ],
    "sg:phone":"+1 314 846 9264",
    "sg:postcode":"63129",
    "sg:province":"MO",
    "wof:name":"Walgreens",
    "wof:placetype":"venue"
},
  "geometry": {"coordinates":[-90.30628299999999,38.453372],"type":"Point"}
}