{
  "type": "Feature",
  "properties": {
    "iso:country":"US",
    "sg:address":"101 Jefferson St",
    "sg:city":"Jefferson City",
    "sg:classifiers":[
        {
            "category":"Local Transit",
            "type":"Transportation"
        }
    ],
    "sg:phone":"+1 573 636 8414",
    "sg:postcode":"65101",
    "sg:province":"MO",
    "sg:tags":[
        "passenger"
    ],
    "wof:name":"Amtrak",
    "wof:placetype":"venue"
},
  "geometry": {"coordinates":[-92.170101,38.578991],"type":"Point"}
}