{
  "type": "Feature",
  "properties": {
    "iso:country":"US",
    "sg:address":"1500 Santa Anna St",
    "sg:city":"St Charles",
    "sg:classifiers":[
        {
            "category":"Shopping",
            "subcategory":"Florist",
            "type":"Retail Goods"
        }
    ],
    "sg:phone":"+1 636 946 4725",
    "sg:postcode":"63303",
    "sg:province":"MO",
    "wof:name":"Flowers & Dreams",
    "wof:placetype":"venue"
},
  "geometry": {"coordinates":[-90.52966000000001,38.76809],"type":"Point"}
}