{
  "type": "Feature",
  "properties": {
    "iso:country":"US",
    "sg:address":"16026 Pine Terrace Dr",
    "sg:city":"Ballwin",
    "sg:classifiers":[
        {
            "category":"Professional",
            "type":"Services"
        }
    ],
    "sg:phone":"+1 636 527 0267",
    "sg:postcode":"63021",
    "sg:province":"MO",
    "wof:name":"Thunderbolt Idea Development",
    "wof:placetype":"venue"
},
  "geometry": {"coordinates":[-90.570638,38.566821],"type":"Point"}
}