{
  "type": "Feature",
  "properties": {
    "iso:country":"US",
    "sg:address":"1383 US Hwy 63 Bus",
    "sg:city":"West Plains",
    "sg:classifiers":[
        {
            "category":"Wholesale",
            "subcategory":"Home Furnishings",
            "type":"Manufacturing & Wholesale Goods"
        }
    ],
    "sg:phone":"+1 417 256 6559",
    "sg:postcode":"65775",
    "sg:province":"MO",
    "sg:tags":[
        "hardwood",
        "flooring"
    ],
    "wof:name":"Masters Craft Corporation",
    "wof:placetype":"venue"
},
  "geometry": {"coordinates":[-91.871055,36.740588],"type":"Point"}
}