{
  "type": "Feature",
  "properties": {
    "iso:country":"US",
    "sg:address":"741 Hardwood Rd",
    "sg:city":"Marshfield",
    "sg:classifiers":[
        {
            "category":"Real Estate",
            "subcategory":"Real Estate Agent",
            "type":"Services"
        }
    ],
    "sg:phone":"+1 417 859 2553",
    "sg:postcode":"65706",
    "sg:province":"MO",
    "wof:name":"Quinterra",
    "wof:placetype":"venue"
},
  "geometry": {"coordinates":[-92.88037799999999,37.273458],"type":"Point"}
}