{
  "type": "Feature",
  "properties": {
    "iso:country":"US",
    "sg:address":"9805 Air Cargo Rd",
    "sg:city":"St Louis",
    "sg:classifiers":[
        {
            "category":"Airline",
            "type":"Transportation"
        }
    ],
    "sg:phone":"+1 314 592 6352",
    "sg:postcode":"63134",
    "sg:province":"MO",
    "sg:tags":[
        "scheduled",
        "cargo",
        "air"
    ],
    "wof:name":"Southwest Airlines Cargo",
    "wof:placetype":"venue"
},
  "geometry": {"coordinates":[-90.35296099999999,38.735589],"type":"Point"}
}