{
  "type": "Feature",
  "properties": {
    "iso:country":"US",
    "sg:address":"500 State Hwy 7",
    "sg:city":"Blue Springs",
    "sg:classifiers":[
        {
            "category":"Shopping",
            "subcategory":"Hobbies, Toys, & Games",
            "type":"Retail Goods"
        }
    ],
    "sg:phone":"+1 816 228 2356",
    "sg:postcode":"64014",
    "sg:province":"MO",
    "sg:tags":[
        "sewing",
        "merchandise"
    ],
    "wof:name":"Hobby Lobby 29",
    "wof:placetype":"venue"
},
  "geometry": {"coordinates":[-94.27241100000001,39.014416],"type":"Point"}
}