{
  "type": "Feature",
  "properties": {
    "iso:country":"US",
    "sg:address":"6906 Olive Blvd",
    "sg:city":"Saint Louis",
    "sg:classifiers":[
        {
            "category":"Shopping",
            "subcategory":"Beauty & Cosmetics",
            "type":"Retail Goods"
        }
    ],
    "sg:phone":"+1 314 862 0054",
    "sg:postcode":"63130",
    "sg:province":"MO",
    "sg:tags":[
        "supply"
    ],
    "wof:name":"Coco Beauty Supply",
    "wof:placetype":"venue"
},
  "geometry": {"coordinates":[-90.314499,38.665001],"type":"Point"}
}