{
  "type": "Feature",
  "properties": {
    "iso:country":"US",
    "sg:address":"5165 Highway D",
    "sg:city":"Farmington",
    "sg:classifiers":[
        {
            "category":"Place Of Worship",
            "subcategory":"Church",
            "type":"Public Place"
        },
        {
            "category":"Place Of Worship",
            "type":"Public Place"
        }
    ],
    "sg:phone":"+1 573 747 0001",
    "sg:postcode":"63640",
    "sg:province":"MO",
    "sg:tags":[
        "churches-evangelical",
        "free"
    ],
    "sg:website":"http://www.cbcparkland.org",
    "wof:name":"Covenant Bible Church",
    "wof:placetype":"venue"
},
  "geometry": {"coordinates":[-90.42067,37.825615],"type":"Point"}
}