{
  "type": "Feature",
  "properties": {
    "iso:country":"US",
    "sg:address":"25882 Apple Dr",
    "sg:city":"Wheeling",
    "sg:phone":"+1 660 659 2219",
    "sg:postcode":"64688",
    "sg:province":"MO",
    "sg:tags":[
        "wheat",
        "beef",
        "farm",
        "corn",
        "soybean",
        "cattle",
        "feedlot"
    ],
    "wof:name":"Lloyd Howe",
    "wof:placetype":"venue"
},
  "geometry": {"coordinates":[-93.363704,39.807332],"type":"Point"}
}