{
  "type": "Feature",
  "properties": {
    "iso:country":"US",
    "sg:address":"11726 Saint Charles Rock Rd",
    "sg:city":"Bridgeton",
    "sg:classifiers":[
        {
            "category":"Manufacturing",
            "subcategory":"Jewelry",
            "type":"Manufacturing & Wholesale Goods"
        }
    ],
    "sg:phone":"+1 314 291 4653",
    "sg:postcode":"63044",
    "sg:province":"MO",
    "sg:tags":[
        "platinum",
        "buyer",
        "silver",
        "gold"
    ],
    "wof:name":"Missouri Gold Buyers",
    "wof:placetype":"venue"
},
  "geometry": {"coordinates":[-90.415268,38.744888],"type":"Point"}
}