{
  "type": "Feature",
  "properties": {
    "iso:country":"US",
    "sg:address":"6209 NW Karen Rd",
    "sg:city":"Kansas City",
    "sg:classifiers":[
        {
            "category":"Building & Trades",
            "subcategory":"Electrical",
            "type":"Services"
        }
    ],
    "sg:phone":"+1 816 741 3745",
    "sg:postcode":"64151",
    "sg:province":"MO",
    "sg:tags":[
        "electrical",
        "contractor"
    ],
    "wof:name":"Day Enterprises",
    "wof:placetype":"venue"
},
  "geometry": {"coordinates":[-94.61798899999999,39.206596],"type":"Point"}
}