{
  "type": "Feature",
  "properties": {
    "iso:country":"US",
    "sg:address":"7552 Watson Rd",
    "sg:city":"Shrewsbury",
    "sg:classifiers":[
        {
            "category":"Building & Trades",
            "subcategory":"Construction",
            "type":"Services"
        }
    ],
    "sg:phone":"+1 314 962 3248",
    "sg:postcode":"63119",
    "sg:province":"MO",
    "sg:tags":[
        "installation",
        "solar"
    ],
    "sg:website":"energysavers-teamusa.com",
    "wof:name":"Energy Savers - Team USA",
    "wof:placetype":"venue"
},
  "geometry": {"coordinates":[-90.32804899999999,38.57826],"type":"Point"}
}