{
  "type": "Feature",
  "properties": {
    "iso:country":"US",
    "sg:address":"701 S Massachusetts",
    "sg:city":"Sedalia",
    "sg:classifiers":[
        {
            "category":"Education",
            "subcategory":"School",
            "type":"Public Place"
        }
    ],
    "sg:phone":"+1 660 826 1925",
    "sg:postcode":"65301",
    "sg:province":"MO",
    "sg:website":"www.sedaliastpauls.org",
    "wof:name":"St Paul's Lutheran School",
    "wof:placetype":"venue"
},
  "geometry": {"coordinates":[-93.22602500000001,38.705058],"type":"Point"}
}