{
  "type": "Feature",
  "properties": {
    "iso:country":"US",
    "sg:address":"3305 Bristol Ave",
    "sg:city":"Kansas City",
    "sg:classifiers":[
        {
            "category":"Building & Trades",
            "subcategory":"Construction",
            "type":"Services"
        }
    ],
    "sg:phone":"+1 816 924 7184",
    "sg:postcode":"64129",
    "sg:province":"MO",
    "sg:tags":[
        "home",
        "improvement"
    ],
    "wof:name":"Father & Sons Home Improvement",
    "wof:placetype":"venue"
},
  "geometry": {"coordinates":[-94.499447,39.06487],"type":"Point"}
}