{
  "type": "Feature",
  "properties": {
    "iso:country":"US",
    "sg:address":"2847 Co Rd 651",
    "sg:city":"Bernie",
    "sg:classifiers":[
        {
            "category":"Farming",
            "subcategory":"Farm",
            "type":"Manufacturing & Wholesale Goods"
        }
    ],
    "sg:phone":"+1 573 276 3536",
    "sg:postcode":"63822",
    "sg:province":"MO",
    "sg:tags":[
        "crop",
        "general"
    ],
    "wof:name":"Randall V Harris",
    "wof:placetype":"venue"
},
  "geometry": {"coordinates":[-90.05538900000001,36.658412],"type":"Point"}
}