{
  "type": "Feature",
  "properties": {
    "iso:country":"US",
    "sg:address":"16804 E 49 Ter S",
    "sg:city":"Independence",
    "sg:classifiers":[
        {
            "category":"Building & Trades",
            "subcategory":"Construction",
            "type":"Services"
        }
    ],
    "sg:phone":"+1 816 373 7137",
    "sg:postcode":"64055",
    "sg:province":"MO",
    "sg:tags":[
        "contractor"
    ],
    "wof:name":"Specialty Concepts",
    "wof:placetype":"venue"
},
  "geometry": {"coordinates":[-94.382987,39.029377],"type":"Point"}
}