{
  "type": "Feature",
  "properties": {
    "iso:country":"US",
    "sg:address":"112 E Goetz Ave",
    "sg:city":"Saint Louis",
    "sg:classifiers":[
        {
            "category":"Shopping",
            "subcategory":"Hobbies, Toys, & Games",
            "type":"Retail Goods"
        }
    ],
    "sg:phone":"+1 314 631 5941",
    "sg:postcode":"63125",
    "sg:province":"MO",
    "wof:name":"On Go Pet Sitting & Parrot Toy",
    "wof:placetype":"venue"
},
  "geometry": {"coordinates":[-90.275351,38.531979],"type":"Point"}
}