{
  "type": "Feature",
  "properties": {
    "iso:country":"US",
    "sg:address":"13157 Highway 52",
    "sg:city":"Versailles",
    "sg:classifiers":[
        {
            "category":"Manufacturing",
            "subcategory":"Paper Products",
            "type":"Manufacturing & Wholesale Goods"
        }
    ],
    "sg:phone":"+1 573 378 6769",
    "sg:postcode":"65084",
    "sg:province":"MO",
    "sg:tags":[
        "bamboo"
    ],
    "wof:name":"Camp's Greenhouse",
    "wof:placetype":"venue"
},
  "geometry": {"coordinates":[-92.82087900000001,38.445098],"type":"Point"}
}