{
  "type": "Feature",
  "properties": {
    "iso:country":"US",
    "sg:address":"4784 Oak St",
    "sg:city":"Kansas City",
    "sg:classifiers":[
        {
            "category":"Professional",
            "subcategory":"Art Services",
            "type":"Services"
        }
    ],
    "sg:phone":"+1 816 753 4176",
    "sg:postcode":"64112",
    "sg:province":"MO",
    "sg:tags":[
        "design",
        "arts",
        "graphic",
        "commercial",
        "artist"
    ],
    "wof:name":"Chick Studios",
    "wof:placetype":"venue"
},
  "geometry": {"coordinates":[-94.582407,39.041709],"type":"Point"}
}