{
  "type": "Feature",
  "properties": {
    "iso:country":"US",
    "sg:address":"201 Pecan St",
    "sg:city":"Hornersville",
    "sg:classifiers":[
        {
            "category":"Retail",
            "subcategory":"Funeral Services",
            "type":"Services"
        }
    ],
    "sg:phone":"+1 573 737 2447",
    "sg:postcode":"63855",
    "sg:province":"MO",
    "wof:name":"Bradshaw & Emmerson Fnrl Homes",
    "wof:placetype":"venue"
},
  "geometry": {"coordinates":[-90.110074,36.039796],"type":"Point"}
}