{
  "type": "Feature",
  "properties": {
    "iso:country":"US",
    "sg:address":"2019 NE Avanti Ct",
    "sg:city":"Grain Valley",
    "sg:classifiers":[
        {
            "category":"Organizations",
            "subcategory":"Membership Organization",
            "type":"Services"
        }
    ],
    "sg:phone":"+1 816 847 7249",
    "sg:postcode":"64029",
    "sg:province":"MO",
    "wof:name":"Conference of Grand Masters MA",
    "wof:placetype":"venue"
},
  "geometry": {"coordinates":[-94.23441800000001,39.039871],"type":"Point"}
}