{
  "type": "Feature",
  "properties": {
    "addr:full":"2414 N Minnesota Ave Joplin MO 64801",
    "addr:housenumber":"2414",
    "addr:postcode":"64801",
    "addr:street":"N Minnesota Ave",
    "iso:country":"US",
    "sg:address":"2414 N Minnesota Ave",
    "sg:city":"Joplin",
    "sg:classifiers":[
        {
            "category":"Real Estate",
            "subcategory":"Real Estate Agent",
            "type":"Services"
        }
    ],
    "sg:phone":"+1 417 782 5724",
    "sg:postcode":"64801",
    "sg:province":"MO",
    "wof:name":"Adamson Real Estate Inves",
    "wof:placetype":"venue"
},
  "geometry": {"coordinates":[-94.504848,37.112715],"type":"Point"}
}