{
  "type": "Feature",
  "properties": {
    "addr:full":"232 W Main St West Plains MO 65775",
    "addr:housenumber":"232",
    "addr:postcode":"65775",
    "addr:street":"W Main St",
    "iso:country":"US",
    "sg:address":"232 W Main St",
    "sg:city":"West Plains",
    "sg:classifiers":[
        {
            "category":"Government",
            "subcategory":"Office",
            "type":"Public Place"
        }
    ],
    "sg:phone":"+1 417 256 7553",
    "sg:postcode":"65775",
    "sg:province":"MO",
    "sg:tags":[
        "armed",
        "force",
        "recruiting"
    ],
    "wof:name":"US Army Recruiting",
    "wof:placetype":"venue"
},
  "geometry": {"coordinates":[-91.85428,36.728121],"type":"Point"}
}