{
  "type": "Feature",
  "properties": {
    "iso:country":"US",
    "sg:address":"200 NW 72 St",
    "sg:city":"Kansas City",
    "sg:classifiers":[
        {
            "category":"Real Estate",
            "subcategory":"Real Estate Agent",
            "type":"Services"
        }
    ],
    "sg:phone":"+1 816 468 9997",
    "sg:postcode":"64118",
    "sg:province":"MO",
    "wof:name":"Homes 4 Less",
    "wof:placetype":"venue"
},
  "geometry": {"coordinates":[-94.585393,39.224643],"type":"Point"}
}