{
  "type": "Feature",
  "properties": {
    "iso:country":"US",
    "sg:address":"31683 Pistol Pt Lp",
    "sg:city":"Gravois Mills",
    "sg:classifiers":[
        {
            "category":"Real Estate",
            "subcategory":"Real Estate Agent",
            "type":"Services"
        }
    ],
    "sg:phone":"+1 573 372 3555",
    "sg:postcode":"65037",
    "sg:province":"MO",
    "sg:tags":[
        "rental",
        "vacation"
    ],
    "sg:website":"www.crystalwatervillas.com",
    "wof:name":"Crystal Water Villas",
    "wof:placetype":"venue"
},
  "geometry": {"coordinates":[-92.74100300000001,38.22357],"type":"Point"}
}