{
  "type": "Feature",
  "properties": {
    "iso:country":"US",
    "sg:address":"805 SE 3 St",
    "sg:city":"Lees Summit",
    "sg:classifiers":[
        {
            "category":"Shopping",
            "subcategory":"Bicycles & Sporting Goods",
            "type":"Retail Goods"
        }
    ],
    "sg:phone":"+1 816 525 1460",
    "sg:postcode":"64063",
    "sg:province":"MO",
    "sg:tags":[
        "gun",
        "gunsmith"
    ],
    "wof:name":"Bob's Gun Rack",
    "wof:placetype":"venue"
},
  "geometry": {"coordinates":[-94.36262499999999,38.914799],"type":"Point"}
}