{
  "type": "Feature",
  "properties": {
    "iso:country":"US",
    "sg:address":"4420 Madison Ave",
    "sg:city":"Kansas City",
    "sg:classifiers":[
        {
            "category":"Wholesale",
            "subcategory":"Drugs",
            "type":"Manufacturing & Wholesale Goods"
        },
        {
            "category":"Professional",
            "subcategory":"Research",
            "type":"Services"
        }
    ],
    "sg:phone":"+1 816 523 0920",
    "sg:postcode":"64111",
    "sg:province":"MO",
    "sg:tags":[
        "medical"
    ],
    "wof:name":"Proteon Therapeutics LLC",
    "wof:placetype":"venue"
},
  "geometry": {"coordinates":[-94.597236,39.046491],"type":"Point"}
}