{
  "type": "Feature",
  "properties": {
    "iso:country":"US",
    "sg:address":"608 16th Ave N",
    "sg:city":"Greenwood",
    "sg:classifiers":[
        {
            "category":"Building & Trades",
            "subcategory":"Construction",
            "type":"Services"
        }
    ],
    "sg:phone":"+1 816 537 5969",
    "sg:postcode":"64034",
    "sg:province":"MO",
    "sg:tags":[
        "wallcoverings-installation",
        "wallpaper",
        "painting",
        "contractor"
    ],
    "wof:name":"Louie N Sons Painting",
    "wof:placetype":"venue"
},
  "geometry": {"coordinates":[-94.352784,38.85729],"type":"Point"}
}