{
  "type": "Feature",
  "properties": {
    "iso:country":"US",
    "sg:address":"34364 Maries Road 211",
    "sg:city":"Meta",
    "sg:phone":"+1 573 728 6439",
    "sg:postcode":"65058",
    "sg:province":"MO",
    "sg:tags":[
        "farm",
        "field",
        "corn",
        "wheat",
        "crop"
    ],
    "wof:name":"Deeken Farms",
    "wof:placetype":"venue"
},
  "geometry": {"coordinates":[-92.009845,38.245138],"type":"Point"}
}