{
  "type": "Feature",
  "properties": {
    "iso:country":"US",
    "sg:address":"18591 Miller Cir",
    "sg:city":"Rocky Mount",
    "sg:classifiers":[
        {
            "category":"Travel",
            "subcategory":"Campground",
            "type":"Entertainment"
        }
    ],
    "sg:phone":"+1 573 392 1000",
    "sg:postcode":"65072",
    "sg:province":"MO",
    "sg:tags":[
        "camp"
    ],
    "sg:website":"www.wonderlandcamp.org",
    "wof:name":"Wonderland Camp",
    "wof:placetype":"venue"
},
  "geometry": {"coordinates":[-92.74346799999999,38.273633],"type":"Point"}
}