{
  "type": "Feature",
  "properties": {
    "iso:country":"US",
    "sg:address":"27943 State Hwy Y E",
    "sg:city":"Bell City",
    "sg:classifiers":[
        {
            "category":"Farming",
            "subcategory":"Farm",
            "type":"Manufacturing & Wholesale Goods"
        }
    ],
    "sg:phone":"+1 573 733 4366",
    "sg:postcode":"63735",
    "sg:province":"MO",
    "wof:name":"Hunter Gin Inc",
    "wof:placetype":"venue"
},
  "geometry": {"coordinates":[-89.762737,36.963007],"type":"Point"}
}