{
  "type": "Feature",
  "properties": {
    "iso:country":"US",
    "sg:address":"2233 McCausland Ave",
    "sg:city":"Saint Louis",
    "sg:classifiers":[
        {
            "category":"Retail",
            "subcategory":"Auto Repair",
            "type":"Services"
        }
    ],
    "sg:phone":"+1 314 645 3881",
    "sg:postcode":"63143",
    "sg:province":"MO",
    "wof:name":"Waters Auto Centers Inc",
    "wof:placetype":"venue"
},
  "geometry": {"coordinates":[-90.30880000000001,38.616798],"type":"Point"}
}