{
  "type": "Feature",
  "properties": {
    "iso:country":"US",
    "sg:address":"5 Birdie Ct",
    "sg:city":"Saint Peters",
    "sg:classifiers":[
        {
            "category":"Manufacturing",
            "subcategory":"Tools & Machinery",
            "type":"Manufacturing & Wholesale Goods"
        }
    ],
    "sg:phone":"+1 636 397 2332",
    "sg:postcode":"63376",
    "sg:province":"MO",
    "sg:tags":[
        "devices",
        "mfg"
    ],
    "wof:name":"Honeywell",
    "wof:placetype":"venue"
},
  "geometry": {"coordinates":[-90.609211,38.769963],"type":"Point"}
}