{
  "type": "Feature",
  "properties": {
    "iso:country":"US",
    "sg:address":"3833 Vaile Ave",
    "sg:city":"Florissant",
    "sg:classifiers":[
        {
            "category":"Sports & Exercise",
            "subcategory":"Gym",
            "type":"Entertainment"
        }
    ],
    "sg:phone":"+1 314 837 1103",
    "sg:postcode":"63034",
    "sg:province":"MO",
    "sg:tags":[
        "fitness",
        "physical",
        "facility"
    ],
    "wof:name":"Curves For Women",
    "wof:placetype":"venue"
},
  "geometry": {"coordinates":[-90.308176,38.826353],"type":"Point"}
}