{
  "type": "Feature",
  "properties": {
    "iso:country":"US",
    "sg:address":"1123 Washington Ave",
    "sg:city":"Saint Louis",
    "sg:classifiers":[
        {
            "category":"Personal",
            "subcategory":"Beauty Salon",
            "type":"Services"
        },
        {
            "category":"Personal",
            "subcategory":"Barber",
            "type":"Services"
        }
    ],
    "sg:phone":"+1 314 335 7030",
    "sg:postcode":"63101",
    "sg:province":"MO",
    "sg:tags":[
        "hair"
    ],
    "sg:website":"www.BladesOnWashington.com",
    "wof:name":"Blades On Washington",
    "wof:placetype":"venue"
},
  "geometry": {"coordinates":[-90.195356,38.631494],"type":"Point"}
}