{
  "type": "Feature",
  "properties": {
    "iso:country":"US",
    "sg:address":"615 S Bishop Ave",
    "sg:city":"Rolla",
    "sg:classifiers":[
        {
            "category":"Personal",
            "subcategory":"Nail Salon",
            "type":"Services"
        }
    ],
    "sg:phone":"+1 573 426 5055",
    "sg:postcode":"65401",
    "sg:province":"MO",
    "wof:name":"L T Nails",
    "wof:placetype":"venue"
},
  "geometry": {"coordinates":[-91.777383,37.948562],"type":"Point"}
}