{
  "type": "Feature",
  "properties": {
    "iso:country":"US",
    "sg:address":"1931 Washington St",
    "sg:city":"Florissant",
    "sg:classifiers":[
        {
            "category":"Personal",
            "subcategory":"Beauty Salon",
            "type":"Services"
        }
    ],
    "sg:phone":"+1 314 837 8003",
    "sg:postcode":"63033",
    "sg:province":"MO",
    "sg:tags":[
        "hair",
        "stylist"
    ],
    "wof:name":"Hair On Washington",
    "wof:placetype":"venue"
},
  "geometry": {"coordinates":[-90.314393,38.780555],"type":"Point"}
}