{
  "type": "Feature",
  "properties": {
    "iso:country":"US",
    "sg:address":"218 W Mill St",
    "sg:city":"Liberty",
    "sg:classifiers":[
        {
            "category":"Personal",
            "subcategory":"Barber",
            "type":"Services"
        }
    ],
    "sg:phone":"+1 816 781 6900",
    "sg:postcode":"64068",
    "sg:province":"MO",
    "wof:name":"Mill Street Barber & Style Shop",
    "wof:placetype":"venue"
},
  "geometry": {"coordinates":[-94.42266499999999,39.244723],"type":"Point"}
}