{
  "type": "Feature",
  "properties": {
    "iso:country":"US",
    "sg:address":"7132 Groveland Dr",
    "sg:city":"Saint Louis",
    "sg:classifiers":[
        {
            "category":"Professional",
            "type":"Services"
        }
    ],
    "sg:phone":"+1 314 389 4386",
    "sg:postcode":"63121",
    "sg:province":"MO",
    "wof:name":"Monty Carr",
    "wof:placetype":"venue"
},
  "geometry": {"coordinates":[-90.286529,38.708431],"type":"Point"}
}