{
  "type": "Feature",
  "properties": {
    "iso:country":"US",
    "sg:address":"804 W Rollotrend Ln",
    "sg:city":"Eldon",
    "sg:classifiers":[
        {
            "category":"Professional",
            "subcategory":"Business Services",
            "type":"Services"
        }
    ],
    "sg:phone":"+1 573 392 1089",
    "sg:postcode":"65026",
    "sg:province":"MO",
    "wof:name":"Kirchner Enterprises",
    "wof:placetype":"venue"
},
  "geometry": {"coordinates":[-92.59318399999999,38.35772],"type":"Point"}
}