{
  "type": "Feature",
  "properties": {
    "iso:country":"US",
    "sg:address":"10895 Natural Bridge Rd",
    "sg:city":"Bridgeton",
    "sg:classifiers":[
        {
            "category":"Banks & Credit Unions",
            "subcategory":"Bank",
            "type":"Services"
        }
    ],
    "sg:phone":"+1 314 429 0018",
    "sg:postcode":"63044",
    "sg:province":"MO",
    "sg:tags":[
        "state"
    ],
    "wof:name":"Communityamerica Credit Union",
    "wof:placetype":"venue"
},
  "geometry": {"coordinates":[-90.367352,38.741156],"type":"Point"}
}