{
  "type": "Feature",
  "properties": {
    "addr:full":"319 E Main St Fredericktown MO 63645",
    "addr:housenumber":"319",
    "addr:postcode":"63645",
    "addr:street":"E Main St",
    "iso:country":"US",
    "sg:address":"319 E Main St",
    "sg:city":"Fredericktown",
    "sg:classifiers":[
        {
            "category":"Food & Beverages",
            "subcategory":"Groceries & Convenience Stores",
            "type":"Retail Goods"
        }
    ],
    "sg:phone":"+1 573 783 7788",
    "sg:postcode":"63645",
    "sg:province":"MO",
    "sg:tags":[
        "be",
        "station",
        "gasoline",
        "alcoholic"
    ],
    "wof:name":"Short Stop",
    "wof:placetype":"venue"
},
  "geometry": {"coordinates":[-90.29065900000001,37.559575],"type":"Point"}
}