{
  "type": "Feature",
  "properties": {
    "iso:country":"US",
    "sg:address":"2508 Shepard Blvd",
    "sg:city":"Columbia",
    "sg:classifiers":[
        {
            "category":"Professional",
            "subcategory":"Business Services",
            "type":"Services"
        }
    ],
    "sg:phone":"+1 573 449 1761",
    "sg:postcode":"65201",
    "sg:province":"MO",
    "wof:name":"Dakin Rentals",
    "wof:placetype":"venue"
},
  "geometry": {"coordinates":[-92.29816700000001,38.937564],"type":"Point"}
}