{
  "type": "Feature",
  "properties": {
    "iso:country":"US",
    "sg:address":"1425 Hodiamont Ave",
    "sg:city":"Saint Louis",
    "sg:classifiers":[
        {
            "category":"Social Services",
            "subcategory":"Child Care",
            "type":"Services"
        }
    ],
    "sg:phone":"+1 314 261 9727",
    "sg:postcode":"63112",
    "sg:province":"MO",
    "sg:tags":[
        "day"
    ],
    "wof:name":"A Childs World",
    "wof:placetype":"venue"
},
  "geometry": {"coordinates":[-90.286827,38.673266],"type":"Point"}
}