{
  "type": "Feature",
  "properties": {
    "iso:country":"US",
    "sg:address":"17 Arundel Pl",
    "sg:city":"Saint Louis",
    "sg:classifiers":[
        {
            "category":"Restaurant",
            "type":"Food & Drink"
        }
    ],
    "sg:phone":"+1 314 725 3822",
    "sg:postcode":"63105",
    "sg:province":"MO",
    "wof:name":"Claunett Co The",
    "wof:placetype":"venue"
},
  "geometry": {"coordinates":[-90.303827,38.639532],"type":"Point"}
}