{
  "type": "Feature",
  "properties": {
    "iso:country":"US",
    "sg:address":"743 Spirit 40 Park Dr",
    "sg:city":"Chesterfield",
    "sg:classifiers":[
        {
            "category":"Wholesale",
            "subcategory":"Medical Equipment & Supplies",
            "type":"Manufacturing & Wholesale Goods"
        }
    ],
    "sg:phone":"+1 636 519 4833",
    "sg:postcode":"63005",
    "sg:province":"MO",
    "wof:name":"Paradigm Systems LLC",
    "wof:placetype":"venue"
},
  "geometry": {"coordinates":[-90.64052599999999,38.671417],"type":"Point"}
}