{
  "type": "Feature",
  "properties": {
    "iso:country":"US",
    "sg:address":"1645 W Republic Rd",
    "sg:city":"Springfield",
    "sg:classifiers":[
        {
            "category":"Food & Beverages",
            "subcategory":"Bakery",
            "type":"Retail Goods"
        }
    ],
    "sg:phone":"+1 417 866 5533",
    "sg:postcode":"65807",
    "sg:province":"MO",
    "sg:tags":[
        "baker"
    ],
    "sg:website":"www.bethsbakeshoppe.com",
    "wof:name":"Beth's Bake Shoppe & Tea Room",
    "wof:placetype":"venue"
},
  "geometry": {"coordinates":[-93.315741,37.138369],"type":"Point"}
}