{
  "type": "Feature",
  "properties": {
    "iso:country":"US",
    "sg:address":"57635 Cumberland Trl",
    "sg:city":"New London",
    "sg:classifiers":[
        {
            "category":"Farming",
            "subcategory":"Livestock Farm",
            "type":"Manufacturing & Wholesale Goods"
        }
    ],
    "sg:phone":"+1 573 985 4771",
    "sg:postcode":"63459",
    "sg:province":"MO",
    "sg:tags":[
        "beef",
        "feedlot",
        "cattle"
    ],
    "wof:name":"Brown Hurley",
    "wof:placetype":"venue"
},
  "geometry": {"coordinates":[-91.38408699999999,39.518848],"type":"Point"}
}