{
  "type": "Feature",
  "properties": {
    "iso:country":"US",
    "sg:address":"200 E Main St",
    "sg:city":"California",
    "sg:classifiers":[
        {
            "category":"Government",
            "subcategory":"Office",
            "type":"Public Place"
        }
    ],
    "sg:phone":"+1 573 796 4671",
    "sg:postcode":"65018",
    "sg:province":"MO",
    "wof:name":"Moniteau County Probate",
    "wof:placetype":"venue"
},
  "geometry": {"coordinates":[-92.56532199999999,38.636153],"type":"Point"}
}