{
  "type": "Feature",
  "properties": {
    "iso:country":"US",
    "sg:address":"502 N Main St",
    "sg:city":"Salem",
    "sg:classifiers":[
        {
            "category":"Professional",
            "subcategory":"Accounting & Tax Preparation",
            "type":"Services"
        }
    ],
    "sg:phone":"+1 573 739 4536",
    "sg:postcode":"65560",
    "sg:province":"MO",
    "sg:tags":[
        "accountant"
    ],
    "wof:name":"Thomas Russell CPA",
    "wof:placetype":"venue"
},
  "geometry": {"coordinates":[-91.536196,37.646704],"type":"Point"}
}