{
  "type": "Feature",
  "properties": {
    "iso:country":"US",
    "sg:address":"3828 Independence Ave",
    "sg:city":"Kansas City",
    "sg:classifiers":[
        {
            "category":"Retail",
            "subcategory":"Repair Shop",
            "type":"Services"
        }
    ],
    "sg:phone":"+1 816 231 0332",
    "sg:postcode":"64124",
    "sg:province":"MO",
    "wof:name":"Northeast Key Service",
    "wof:placetype":"venue"
},
  "geometry": {"coordinates":[-94.535749,39.105871],"type":"Point"}
}