{
  "type": "Feature",
  "properties": {
    "iso:country":"US",
    "sg:address":"4633 Maryland Ave",
    "sg:city":"Saint Louis",
    "sg:classifiers":[
        {
            "category":"Professional",
            "subcategory":"Lawyer & Legal Services",
            "type":"Services"
        }
    ],
    "sg:phone":"+1 314 361 2000",
    "sg:postcode":"63108",
    "sg:province":"MO",
    "wof:name":"Kramer Joyce Attorney-Legal Servcs & Sttlmnt Ngttn",
    "wof:placetype":"venue"
},
  "geometry": {"coordinates":[-90.259102,38.6441],"type":"Point"}
}