{
  "type": "Feature",
  "properties": {
    "iso:country":"US",
    "sg:address":"205 N Thompson Ave",
    "sg:city":"Excelsior Spgs",
    "sg:classifiers":[
        {
            "category":"Organizations",
            "subcategory":"Non-profit Organization",
            "type":"Services"
        }
    ],
    "sg:phone":"+1 816 630 5036",
    "sg:postcode":"64024",
    "sg:province":"MO",
    "sg:tags":[
        "info",
        "addiction",
        "abuse",
        "treatment",
        "drug"
    ],
    "wof:name":"Changing Lives Treatment",
    "wof:placetype":"venue"
},
  "geometry": {"coordinates":[-94.224819,39.342376],"type":"Point"}
}