{
  "type": "Feature",
  "properties": {
    "iso:country":"US",
    "sg:address":"394 US Hwy 54",
    "sg:city":"Camdenton",
    "sg:classifiers":[
        {
            "category":"Building & Trades",
            "subcategory":"Construction",
            "type":"Services"
        }
    ],
    "sg:phone":"+1 573 317 1020",
    "sg:postcode":"65020",
    "sg:province":"MO",
    "sg:tags":[
        "general",
        "contractor"
    ],
    "wof:name":"Laughlin Construction",
    "wof:placetype":"venue"
},
  "geometry": {"coordinates":[-92.751475,38.004211],"type":"Point"}
}