{
  "type": "Feature",
  "properties": {
    "iso:country":"US",
    "sg:address":"10 Merri Ln",
    "sg:city":"Florissant",
    "sg:classifiers":[
        {
            "category":"Education",
            "subcategory":"Dance Studio",
            "type":"Public Place"
        }
    ],
    "sg:phone":"+1 314 837 0542",
    "sg:postcode":"63031",
    "sg:province":"MO",
    "wof:name":"Creative Dance Academy",
    "wof:placetype":"venue"
},
  "geometry": {"coordinates":[-90.338398,38.799881],"type":"Point"}
}