{
  "type": "Feature",
  "properties": {
    "iso:country":"US",
    "sg:address":"4735 N Brighton Ave",
    "sg:city":"Kansas City",
    "sg:classifiers":[
        {
            "category":"Organizations",
            "subcategory":"Religious Organization",
            "type":"Services"
        }
    ],
    "sg:phone":"+1 816 453 5400",
    "sg:postcode":"64117",
    "sg:province":"MO",
    "sg:tags":[
        "child",
        "day",
        "care"
    ],
    "wof:name":"Sunshine Day School",
    "wof:placetype":"venue"
},
  "geometry": {"coordinates":[-94.521227,39.180673],"type":"Point"}
}