{
  "type": "Feature",
  "properties": {
    "iso:country":"US",
    "sg:address":"500 Chesterfield Center",
    "sg:city":"Chesterfield",
    "sg:classifiers":[
        {
            "category":"Professional",
            "subcategory":"Computer Services",
            "type":"Services"
        }
    ],
    "sg:phone":"+1 636 237 1000",
    "sg:postcode":"63017",
    "sg:province":"MO",
    "sg:tags":[
        "consultant",
        "designer"
    ],
    "sg:website":"www.neteffects.com",
    "wof:name":"Neteffects",
    "wof:placetype":"venue"
},
  "geometry": {"coordinates":[-90.567729,38.649901],"type":"Point"}
}