{
  "type": "Feature",
  "properties": {
    "iso:country":"US",
    "sg:address":"1554 E County Highway 450",
    "sg:city":"Sikeston",
    "sg:classifiers":[
        {
            "category":"Manufacturing",
            "subcategory":"Buildings",
            "type":"Manufacturing & Wholesale Goods"
        },
        {
            "category":"Building & Trades",
            "subcategory":"Construction",
            "type":"Services"
        }
    ],
    "sg:phone":"+1 573 471 4634",
    "sg:postcode":"63801",
    "sg:province":"MO",
    "sg:tags":[
        "home",
        "builder",
        "contractor"
    ],
    "wof:name":"Baker Construction",
    "wof:placetype":"venue"
},
  "geometry": {"coordinates":[-89.551631,36.950278],"type":"Point"}
}