{
  "type": "Feature",
  "properties": {
    "iso:country":"US",
    "sg:address":"15121 Manchester Rd",
    "sg:city":"Ballwin",
    "sg:classifiers":[
        {
            "category":"Autos & Motor Vehicles",
            "subcategory":"Automobile Sales",
            "type":"Retail Goods"
        }
    ],
    "sg:phone":"+1 314 388 3880",
    "sg:postcode":"63011",
    "sg:province":"MO",
    "sg:tags":[
        "used"
    ],
    "wof:name":"Dean Team of Dellwood Inc",
    "wof:placetype":"venue"
},
  "geometry": {"coordinates":[-90.551222,38.592954],"type":"Point"}
}