{
  "type": "Feature",
  "properties": {
    "iso:country":"US",
    "sg:address":"9515 Manchester Rd",
    "sg:city":"Webster Groves",
    "sg:classifiers":[
        {
            "category":"Banks & Credit Unions",
            "subcategory":"Bank",
            "type":"Services"
        }
    ],
    "sg:phone":"+1 314 962 2800",
    "sg:postcode":"63119",
    "sg:province":"MO",
    "sg:tags":[
        "loan"
    ],
    "wof:name":"Missouri Payday",
    "wof:placetype":"venue"
},
  "geometry": {"coordinates":[-90.36388700000001,38.609371],"type":"Point"}
}