{
  "type": "Feature",
  "properties": {
    "iso:country":"US",
    "sg:address":"22 S Hillview Dr",
    "sg:city":"Saint Peters",
    "sg:classifiers":[
        {
            "category":"Restaurant",
            "type":"Food & Drink"
        }
    ],
    "sg:phone":"+1 636 970 6546",
    "sg:postcode":"63376",
    "sg:province":"MO",
    "sg:tags":[
        "eating"
    ],
    "wof:name":"Tjs Catering",
    "wof:placetype":"venue"
},
  "geometry": {"coordinates":[-90.62702,38.77494],"type":"Point"}
}