{
  "type": "Feature",
  "properties": {
    "iso:country":"US",
    "sg:address":"5243 Baumgartner Rd",
    "sg:city":"Saint Louis",
    "sg:classifiers":[
        {
            "category":"Shopping",
            "subcategory":"Computers & Home Electronics",
            "type":"Retail Goods"
        }
    ],
    "sg:phone":"+1 314 892 9883",
    "sg:postcode":"63129",
    "sg:province":"MO",
    "wof:name":"Autco Distributing Inc",
    "wof:placetype":"venue"
},
  "geometry": {"coordinates":[-90.350956,38.462327],"type":"Point"}
}