{
  "type": "Feature",
  "properties": {
    "iso:country":"US",
    "sg:address":"401 N Jefferson St",
    "sg:city":"Oregon",
    "sg:classifiers":[
        {
            "category":"Real Estate",
            "subcategory":"Real Estate Operator",
            "type":"Services"
        }
    ],
    "sg:phone":"+1 660 446 2516",
    "sg:postcode":"64473",
    "sg:province":"MO",
    "sg:tags":[
        "apartment"
    ],
    "wof:name":"Jefferson Heights Apartments",
    "wof:placetype":"venue"
},
  "geometry": {"coordinates":[-95.14199600000001,39.990027],"type":"Point"}
}