{
  "type": "Feature",
  "properties": {
    "iso:country":"US",
    "sg:address":"8201 Idaho Ave",
    "sg:city":"St Louis",
    "sg:classifiers":[
        {
            "category":"Manufacturing",
            "subcategory":"Chemicals & Compounds",
            "type":"Manufacturing & Wholesale Goods"
        }
    ],
    "sg:phone":"+1 314 577 1600",
    "sg:postcode":"63111",
    "sg:province":"MO",
    "sg:tags":[
        "inorganic",
        "industrial",
        "mfg"
    ],
    "sg:website":"www.astaris.com",
    "wof:name":"Astaris LLC",
    "wof:placetype":"venue"
},
  "geometry": {"coordinates":[-90.269824,38.547278],"type":"Point"}
}