{
  "type": "Feature",
  "properties": {
    "iso:country":"US",
    "sg:address":"2443 Gothland Ave",
    "sg:city":"Saint Louis",
    "sg:classifiers":[
        {
            "category":"Building & Trades",
            "subcategory":"Landscaping Services",
            "type":"Services"
        }
    ],
    "sg:phone":"+1 314 423 9166",
    "sg:postcode":"63114",
    "sg:province":"MO",
    "sg:tags":[
        "landscape"
    ],
    "wof:name":"Bales Lawn Care",
    "wof:placetype":"venue"
},
  "geometry": {"coordinates":[-90.353542,38.702193],"type":"Point"}
}