{
  "type": "Feature",
  "properties": {
    "iso:country":"US",
    "sg:address":"9359 Watson Industrial Park",
    "sg:city":"Saint Louis",
    "sg:classifiers":[
        {
            "category":"Organizations",
            "subcategory":"Religious Organization",
            "type":"Services"
        }
    ],
    "sg:phone":"+1 314 963 9450",
    "sg:postcode":"63126",
    "sg:province":"MO",
    "wof:name":"Unitd Cerebral Plsy",
    "wof:placetype":"venue"
},
  "geometry": {"coordinates":[-90.37339,38.561559],"type":"Point"}
}