{
  "type": "Feature",
  "properties": {
    "iso:country":"US",
    "sg:address":"413 Summit Tree Ct",
    "sg:city":"Fenton",
    "sg:classifiers":[
        {
            "category":"Building & Trades",
            "subcategory":"Construction",
            "type":"Services"
        }
    ],
    "sg:phone":"+1 636 349 7708",
    "sg:postcode":"63026",
    "sg:province":"MO",
    "sg:tags":[
        "home",
        "builder"
    ],
    "wof:name":"Jones Co",
    "wof:placetype":"venue"
},
  "geometry": {"coordinates":[-90.45312,38.512689],"type":"Point"}
}