{
  "type": "Feature",
  "properties": {
    "iso:country":"US",
    "sg:address":"701 Perry Ave",
    "sg:city":"Cape Girardeau",
    "sg:classifiers":[
        {
            "category":"Building & Trades",
            "subcategory":"Construction",
            "type":"Services"
        }
    ],
    "sg:phone":"+1 573 334 9167",
    "sg:postcode":"63701",
    "sg:province":"MO",
    "wof:name":"Brian Weiss Construction",
    "wof:placetype":"venue"
},
  "geometry": {"coordinates":[-89.53919399999999,37.314512],"type":"Point"}
}