{
  "type": "Feature",
  "properties": {
    "iso:country":"US",
    "sg:address":"30 Anchor Dr",
    "sg:city":"Blue Springs",
    "sg:classifiers":[
        {
            "category":"Real Estate",
            "subcategory":"Real Estate Agent",
            "type":"Services"
        }
    ],
    "sg:phone":"+1 816 229 2884",
    "sg:postcode":"64015",
    "sg:province":"MO",
    "wof:name":"P A S",
    "wof:placetype":"venue"
},
  "geometry": {"coordinates":[-94.314243,39.016185],"type":"Point"}
}