{
  "type": "Feature",
  "properties": {
    "iso:country":"US",
    "sg:address":"902 Custer St",
    "sg:city":"Trenton",
    "sg:classifiers":[
        {
            "category":"Health Services",
            "subcategory":"Doctor",
            "type":"Services"
        }
    ],
    "sg:phone":"+1 660 359 4317",
    "sg:postcode":"64683",
    "sg:province":"MO",
    "sg:tags":[
        "medical"
    ],
    "wof:name":"David L Ryan MD",
    "wof:placetype":"venue"
},
  "geometry": {"coordinates":[-93.615422,40.074281],"type":"Point"}
}