{
  "type": "Feature",
  "properties": {
    "iso:country":"US",
    "sg:address":"506 Pin Oak Dr",
    "sg:city":"Adrian",
    "sg:classifiers":[
        {
            "category":"Shopping",
            "subcategory":"Hobbies, Toys, & Games",
            "type":"Retail Goods"
        }
    ],
    "sg:phone":"+1 816 297 2650",
    "sg:postcode":"64720",
    "sg:province":"MO",
    "wof:name":"Raybourn Creative Arts",
    "wof:placetype":"venue"
},
  "geometry": {"coordinates":[-94.34604400000001,38.402603],"type":"Point"}
}