{
  "type": "Feature",
  "properties": {
    "iso:country":"US",
    "sg:address":"208 Dejournet Dr",
    "sg:city":"Chesterfield",
    "sg:classifiers":[
        {
            "category":"Professional",
            "subcategory":"Business Services",
            "type":"Services"
        }
    ],
    "sg:phone":"+1 636 532 5449",
    "sg:postcode":"63005",
    "sg:province":"MO",
    "sg:tags":[
        "investigation",
        "background"
    ],
    "wof:name":"Lilly J Johnson",
    "wof:placetype":"venue"
},
  "geometry": {"coordinates":[-90.59304400000001,38.660685],"type":"Point"}
}