{
  "type": "Feature",
  "properties": {
    "iso:country":"US",
    "sg:address":"2400 Dennis Rd",
    "sg:city":"Sedalia",
    "sg:classifiers":[
        {
            "category":"Personal",
            "type":"Services"
        }
    ],
    "sg:phone":"+1 660 826 1731",
    "sg:postcode":"65301",
    "sg:province":"MO",
    "sg:tags":[
        "control",
        "weight"
    ],
    "wof:name":"Herbalife Distributor",
    "wof:placetype":"venue"
},
  "geometry": {"coordinates":[-93.259108,38.703372],"type":"Point"}
}