{
  "type": "Feature",
  "properties": {
    "iso:country":"US",
    "sg:address":"18179 Dairy Way",
    "sg:city":"Kirksville",
    "sg:classifiers":[
        {
            "category":"Personal",
            "subcategory":"Beauty Salon",
            "type":"Services"
        }
    ],
    "sg:phone":"+1 660 665 6647",
    "sg:postcode":"63501",
    "sg:province":"MO",
    "wof:name":"Millennium Hair Salon",
    "wof:placetype":"venue"
},
  "geometry": {"coordinates":[-92.535257,40.221687],"type":"Point"}
}