{
  "type": "Feature",
  "properties": {
    "iso:country":"US",
    "sg:address":"258 Lamp and Lantern Village",
    "sg:city":"Chesterfield",
    "sg:classifiers":[
        {
            "category":"Real Estate",
            "subcategory":"Real Estate Agent",
            "type":"Services"
        }
    ],
    "sg:phone":"+1 636 256 2400",
    "sg:postcode":"63017",
    "sg:province":"MO",
    "wof:name":"Coldwell Banker",
    "wof:placetype":"venue"
},
  "geometry": {"coordinates":[-90.516366,38.62499],"type":"Point"}
}