{
  "type": "Feature",
  "properties": {
    "iso:country":"US",
    "sg:address":"1701 S Florissant Rd",
    "sg:city":"Saint Louis",
    "sg:classifiers":[
        {
            "category":"Health Services",
            "subcategory":"Chiropractor",
            "type":"Services"
        }
    ],
    "sg:phone":"+1 314 522 0042",
    "sg:postcode":"63121",
    "sg:province":"MO",
    "wof:name":"Sclortino David J",
    "wof:placetype":"venue"
},
  "geometry": {"coordinates":[-90.304906,38.723656],"type":"Point"}
}