{
  "type": "Feature",
  "properties": {
    "iso:country":"US",
    "sg:address":"14394 Shafer Rd",
    "sg:city":"Licking",
    "sg:classifiers":[
        {
            "category":"Wholesale",
            "subcategory":"Machinery & Supplies",
            "type":"Manufacturing & Wholesale Goods"
        }
    ],
    "sg:phone":"+1 573 674 9019",
    "sg:postcode":"65542",
    "sg:province":"MO",
    "sg:tags":[
        "tank"
    ],
    "wof:name":"We-Mac Mfg",
    "wof:placetype":"venue"
},
  "geometry": {"coordinates":[-91.88584299999999,37.569703],"type":"Point"}
}