{
  "type": "Feature",
  "properties": {
    "iso:country":"US",
    "sg:address":"13101 Bennington Ave",
    "sg:city":"Grandview",
    "sg:classifiers":[
        {
            "category":"Organizations",
            "subcategory":"Non-profit Organization",
            "type":"Services"
        }
    ],
    "sg:phone":"+1 816 765 1034",
    "sg:postcode":"64030",
    "sg:province":"MO",
    "wof:name":"Ruskin Hills Home Assoc",
    "wof:placetype":"venue"
},
  "geometry": {"coordinates":[-94.51667999999999,38.885677],"type":"Point"}
}