{
  "type": "Feature",
  "properties": {
    "iso:country":"US",
    "sg:address":"625 S Old Orchard Ave",
    "sg:city":"Springfield",
    "sg:classifiers":[
        {
            "category":"Retail",
            "subcategory":"Repair Shop",
            "type":"Services"
        }
    ],
    "sg:phone":"+1 417 862 5027",
    "sg:postcode":"65802",
    "sg:province":"MO",
    "wof:name":"Clean It All",
    "wof:placetype":"venue"
},
  "geometry": {"coordinates":[-93.240172,37.199973],"type":"Point"}
}