{
  "type": "Feature",
  "properties": {
    "iso:country":"US",
    "sg:address":"2908 Maywood Ave",
    "sg:city":"Saint Louis",
    "sg:classifiers":[
        {
            "category":"Social Services",
            "subcategory":"Child Care",
            "type":"Services"
        }
    ],
    "sg:phone":"+1 314 383 2070",
    "sg:postcode":"63121",
    "sg:province":"MO",
    "sg:tags":[
        "day"
    ],
    "wof:name":"Bishops Day Care",
    "wof:placetype":"venue"
},
  "geometry": {"coordinates":[-90.29128799999999,38.692146],"type":"Point"}
}