{
  "type": "Feature",
  "properties": {
    "iso:country":"US",
    "sg:address":"101 S High St",
    "sg:city":"Stockton",
    "sg:classifiers":[
        {
            "category":"Building & Trades",
            "subcategory":"Plumbing",
            "type":"Services"
        }
    ],
    "sg:phone":"+1 417 276 3899",
    "sg:postcode":"65785",
    "sg:province":"MO",
    "sg:tags":[
        "conditioning",
        "air",
        "system",
        "contractor"
    ],
    "wof:name":"Smith Heating & Cooling",
    "wof:placetype":"venue"
},
  "geometry": {"coordinates":[-93.797511,37.698387],"type":"Point"}
}