{
  "type": "Feature",
  "properties": {
    "iso:country":"US",
    "sg:address":"3721 State Hwy 125",
    "sg:city":"Sparta",
    "sg:classifiers":[
        {
            "category":"Building & Trades",
            "subcategory":"Construction",
            "type":"Services"
        }
    ],
    "sg:phone":"+1 417 581 4691",
    "sg:postcode":"65753",
    "sg:province":"MO",
    "sg:tags":[
        "house"
    ],
    "wof:name":"Braden Brothers Construct",
    "wof:placetype":"venue"
},
  "geometry": {"coordinates":[-93.118583,37.040112],"type":"Point"}
}