{
  "type": "Feature",
  "properties": {
    "iso:country":"US",
    "sg:address":"35 San Aymores Ct",
    "sg:city":"Fenton",
    "sg:classifiers":[
        {
            "category":"Real Estate",
            "subcategory":"Real Estate Operator",
            "type":"Services"
        }
    ],
    "sg:phone":"+1 636 343 4250",
    "sg:postcode":"63026",
    "sg:province":"MO",
    "sg:tags":[
        "mobile",
        "home",
        "community"
    ],
    "wof:name":"Siesta Manor Mobile Home Park",
    "wof:placetype":"venue"
},
  "geometry": {"coordinates":[-90.466757,38.495318],"type":"Point"}
}