{
  "type": "Feature",
  "properties": {
    "iso:country":"US",
    "sg:address":"19526 Highway J",
    "sg:city":"Conway",
    "sg:classifiers":[
        {
            "category":"Autos & Motor Vehicles",
            "subcategory":"Fuel & Gas Station",
            "type":"Retail Goods"
        },
        {
            "category":"Food & Beverages",
            "subcategory":"Groceries & Convenience Stores",
            "type":"Retail Goods"
        }
    ],
    "sg:phone":"+1 417 589 9942",
    "sg:postcode":"65632",
    "sg:province":"MO",
    "wof:name":"Morgan Store",
    "wof:placetype":"venue"
},
  "geometry": {"coordinates":[-92.696378,37.51079],"type":"Point"}
}