{
  "type": "Feature",
  "properties": {
    "iso:country":"US",
    "sg:address":"17984 Jersey Ln",
    "sg:city":"Carthage",
    "sg:classifiers":[
        {
            "category":"Building & Trades",
            "subcategory":"Construction",
            "type":"Services"
        }
    ],
    "sg:phone":"+1 417 358 7129",
    "sg:postcode":"64836",
    "sg:province":"MO",
    "sg:tags":[
        "maker",
        "cabinet"
    ],
    "wof:name":"Randy's Custom Woodworking",
    "wof:placetype":"venue"
},
  "geometry": {"coordinates":[-94.382942,37.188365],"type":"Point"}
}