{
  "type": "Feature",
  "properties": {
    "iso:country":"US",
    "sg:address":"1540 S Svc Rd Highway 70 W",
    "sg:city":"Wentzville",
    "sg:classifiers":[
        {
            "category":"Building & Trades",
            "subcategory":"Pest Control",
            "type":"Services"
        }
    ],
    "sg:phone":"+1 636 332 6510",
    "sg:postcode":"63385",
    "sg:province":"MO",
    "wof:name":"Rottler Pest Control Company",
    "wof:placetype":"venue"
},
  "geometry": {"coordinates":[-90.88381800000001,38.80696],"type":"Point"}
}