{
  "type": "Feature",
  "properties": {
    "iso:country":"US",
    "sg:address":"4558 Dakota Trl",
    "sg:city":"St Charles",
    "sg:classifiers":[
        {
            "category":"Manufacturing",
            "subcategory":"Printing",
            "type":"Manufacturing & Wholesale Goods"
        }
    ],
    "sg:phone":"+1 636 926 8500",
    "sg:postcode":"63304",
    "sg:province":"MO",
    "sg:tags":[
        "printer"
    ],
    "wof:name":"T C Custom Printing",
    "wof:placetype":"venue"
},
  "geometry": {"coordinates":[-90.612979,38.73257],"type":"Point"}
}