{
  "type": "Feature",
  "properties": {
    "addr:full":"201 Independence St Kennett MO 63857",
    "addr:housenumber":"201",
    "addr:postcode":"63857",
    "addr:street":"Independence St",
    "iso:country":"US",
    "sg:address":"201 Independence St",
    "sg:city":"Kennett",
    "sg:classifiers":[
        {
            "category":"Insurance",
            "subcategory":"Insurance Agent",
            "type":"Services"
        }
    ],
    "sg:phone":"+1 573 888 3828",
    "sg:postcode":"63857",
    "sg:province":"MO",
    "wof:name":"Farm Bureau Insurance",
    "wof:placetype":"venue"
},
  "geometry": {"coordinates":[-90.03345299999999,36.237643],"type":"Point"}
}