{
  "type": "Feature",
  "properties": {
    "iso:country":"US",
    "sg:address":"707 NE Hunter's Rd",
    "sg:city":"Blue Springs",
    "sg:classifiers":[
        {
            "category":"Communications",
            "subcategory":"Radio Station",
            "type":"Services"
        }
    ],
    "sg:phone":"+1 816 228 5726",
    "sg:postcode":"64014",
    "sg:province":"MO",
    "sg:tags":[
        "broadcast"
    ],
    "wof:name":"Greg Echlin Sports Services",
    "wof:placetype":"venue"
},
  "geometry": {"coordinates":[-94.251462,39.045673],"type":"Point"}
}