{
  "type": "Feature",
  "properties": {
    "iso:country":"US",
    "sg:address":"524 Court St",
    "sg:city":"Fulton",
    "sg:classifiers":[
        {
            "category":"Insurance",
            "subcategory":"Hazard Insurance",
            "type":"Services"
        }
    ],
    "sg:phone":"+1 573 642 5221",
    "sg:postcode":"65251",
    "sg:province":"MO",
    "wof:name":"Hayes, Mary",
    "wof:placetype":"venue"
},
  "geometry": {"coordinates":[-91.947924,38.847708],"type":"Point"}
}