{
  "type": "Feature",
  "properties": {
    "iso:country":"US",
    "sg:address":"519 E Oak St",
    "sg:city":"Warrenton",
    "sg:classifiers":[
        {
            "category":"Real Estate",
            "subcategory":"Real Estate Agent",
            "type":"Services"
        }
    ],
    "sg:phone":"+1 636 456 7565",
    "sg:postcode":"63383",
    "sg:province":"MO",
    "wof:name":"Remax Westgate",
    "wof:placetype":"venue"
},
  "geometry": {"coordinates":[-91.14166400000001,38.812283],"type":"Point"}
}