{
  "type": "Feature",
  "properties": {
    "iso:country":"US",
    "sg:address":"12 Crabtree Ln",
    "sg:city":"Pacific",
    "sg:classifiers":[
        {
            "category":"Professional",
            "subcategory":"Management & Consulting",
            "type":"Services"
        }
    ],
    "sg:phone":"+1 636 938 5005",
    "sg:postcode":"63069",
    "sg:province":"MO",
    "wof:name":"Vogt Consultants Inc",
    "wof:placetype":"venue"
},
  "geometry": {"coordinates":[-90.69379600000001,38.427026],"type":"Point"}
}