{
  "type": "Feature",
  "properties": {
    "iso:country":"US",
    "sg:address":"2646 Hwy 109",
    "sg:city":"Grover",
    "sg:classifiers":[
        {
            "category":"Professional",
            "subcategory":"Business Services",
            "type":"Services"
        }
    ],
    "sg:phone":"+1 636 273 0100",
    "sg:postcode":"63040",
    "sg:province":"MO",
    "wof:name":"Beilman Group",
    "wof:placetype":"venue"
},
  "geometry": {"coordinates":[-90.64494500000001,38.57483],"type":"Point"}
}