{
  "type": "Feature",
  "properties": {
    "iso:country":"US",
    "sg:address":"6609 N Oak Fwy",
    "sg:city":"Kansas City",
    "sg:classifiers":[
        {
            "category":"Autos & Motor Vehicles",
            "subcategory":"Motorcycle Sales",
            "type":"Retail Goods"
        }
    ],
    "sg:phone":"+1 816 420 9000",
    "sg:postcode":"64118",
    "sg:province":"MO",
    "sg:tags":[
        "scooter"
    ],
    "sg:website":"www.worthharley-davidson.com",
    "wof:name":"Worth Harley-Davidson",
    "wof:placetype":"venue"
},
  "geometry": {"coordinates":[-94.57608,39.213409],"type":"Point"}
}