{
  "type": "Feature",
  "properties": {
    "iso:country":"US",
    "sg:address":"312 Valle St",
    "sg:city":"Pilot Knob",
    "sg:classifiers":[
        {
            "category":"Retail",
            "subcategory":"Funeral Services",
            "type":"Services"
        }
    ],
    "sg:phone":"+1 573 546 6103",
    "sg:postcode":"63663",
    "sg:province":"MO",
    "sg:tags":[
        "director"
    ],
    "wof:name":"Bryson Funeral Home",
    "wof:placetype":"venue"
},
  "geometry": {"coordinates":[-90.643693,37.626228],"type":"Point"}
}