{
  "type": "Feature",
  "properties": {
    "iso:country":"US",
    "sg:address":"975 Plateau Dr",
    "sg:city":"Fenton",
    "sg:classifiers":[
        {
            "category":"Home & Garden",
            "subcategory":"Home Furnishings",
            "type":"Retail Goods"
        }
    ],
    "sg:phone":"+1 636 529 0632",
    "sg:postcode":"63026",
    "sg:province":"MO",
    "sg:tags":[
        "venetian",
        "blind"
    ],
    "wof:name":"Budget Blinds",
    "wof:placetype":"venue"
},
  "geometry": {"coordinates":[-90.478393,38.503879],"type":"Point"}
}