{
  "type": "Feature",
  "properties": {
    "iso:country":"US",
    "sg:address":"1576 Fencorp Ct",
    "sg:city":"Fenton",
    "sg:classifiers":[
        {
            "category":"Professional",
            "subcategory":"Computer Services",
            "type":"Services"
        }
    ],
    "sg:phone":"+1 636 305 9669",
    "sg:postcode":"63026",
    "sg:province":"MO",
    "sg:tags":[
        "repair"
    ],
    "wof:name":"CHE Consulting Inc",
    "wof:placetype":"venue"
},
  "geometry": {"coordinates":[-90.44694200000001,38.536149],"type":"Point"}
}