{
  "type": "Feature",
  "properties": {
    "iso:country":"US",
    "sg:address":"9618 Old Bonhomme Rd",
    "sg:city":"St Louis",
    "sg:classifiers":[
        {
            "category":"Insurance",
            "subcategory":"Insurance Agent",
            "type":"Services"
        }
    ],
    "sg:phone":"+1 314 997 7735",
    "sg:postcode":"63132",
    "sg:province":"MO",
    "wof:name":"J Tom Miles Jr",
    "wof:placetype":"venue"
},
  "geometry": {"coordinates":[-90.388132,38.668054],"type":"Point"}
}