{
  "type": "Feature",
  "properties": {
    "iso:country":"US",
    "sg:address":"3800 S Elizabeth St",
    "sg:city":"Independence",
    "sg:classifiers":[
        {
            "category":"Personal",
            "subcategory":"Beauty Salon",
            "type":"Services"
        }
    ],
    "sg:phone":"+1 816 795 9710",
    "sg:postcode":"64057",
    "sg:province":"MO",
    "sg:tags":[
        "shop",
        "manicuring"
    ],
    "wof:name":"Tammy's Nails",
    "wof:placetype":"venue"
},
  "geometry": {"coordinates":[-94.360924,39.048929],"type":"Point"}
}