{
  "type": "Feature",
  "properties": {
    "iso:country":"US",
    "sg:address":"821 W Sherwood Dr",
    "sg:city":"Springfield",
    "sg:classifiers":[
        {
            "category":"Travel",
            "subcategory":"Bed & Breakfast",
            "type":"Entertainment"
        }
    ],
    "sg:phone":"+1 417 883 0941",
    "sg:postcode":"65810",
    "sg:province":"MO",
    "sg:tags":[
        "inn"
    ],
    "wof:name":"Seldom Inn",
    "wof:placetype":"venue"
},
  "geometry": {"coordinates":[-93.30258,37.126618],"type":"Point"}
}