{
  "type": "Feature",
  "properties": {
    "iso:country":"US",
    "sg:address":"8965 US Hwy 36",
    "sg:city":"Hannibal",
    "sg:classifiers":[
        {
            "category":"Building & Trades",
            "subcategory":"Construction",
            "type":"Services"
        }
    ],
    "sg:phone":"+1 573 221 5958",
    "sg:postcode":"63401",
    "sg:province":"MO",
    "sg:tags":[
        "paving",
        "contractor"
    ],
    "wof:name":"Chester Bross Construction",
    "wof:placetype":"venue"
},
  "geometry": {"coordinates":[-91.427166,39.713765],"type":"Point"}
}