{
  "type": "Feature",
  "properties": {
    "iso:country":"US",
    "sg:address":"218 S Wood St",
    "sg:city":"Neosho",
    "sg:classifiers":[
        {
            "category":"Personal",
            "subcategory":"Beauty Salon",
            "type":"Services"
        }
    ],
    "sg:phone":"+1 417 451 4006",
    "sg:postcode":"64850",
    "sg:province":"MO",
    "sg:tags":[
        "shop"
    ],
    "wof:name":"Perfect Nails",
    "wof:placetype":"venue"
},
  "geometry": {"coordinates":[-94.36863,36.868469],"type":"Point"}
}