{
  "type": "Feature",
  "properties": {
    "iso:country":"US",
    "sg:address":"33184 Wieneke Branch Rd",
    "sg:city":"California",
    "sg:classifiers":[
        {
            "category":"Freight",
            "type":"Transportation"
        }
    ],
    "sg:phone":"+1 573 796 4484",
    "sg:postcode":"65018",
    "sg:province":"MO",
    "sg:tags":[
        "hauling",
        "trucking"
    ],
    "wof:name":"Douglas Enterprises Inc",
    "wof:placetype":"venue"
},
  "geometry": {"coordinates":[-92.48787,38.581179],"type":"Point"}
}