{
  "type": "Feature",
  "properties": {
    "iso:country":"US",
    "sg:address":"2902 McClelland Blvd",
    "sg:city":"Joplin",
    "sg:classifiers":[
        {
            "category":"Health Services",
            "subcategory":"Doctor",
            "type":"Services"
        }
    ],
    "sg:phone":"+1 417 623 2440",
    "sg:postcode":"64804",
    "sg:province":"MO",
    "sg:tags":[
        "dentist"
    ],
    "wof:name":"Richard J Reed DDS",
    "wof:placetype":"venue"
},
  "geometry": {"coordinates":[-94.532426,37.056649],"type":"Point"}
}