{
  "type": "Feature",
  "properties": {
    "iso:country":"US",
    "sg:address":"814 S Main St",
    "sg:city":"Joplin",
    "sg:classifiers":[
        {
            "category":"Home & Garden",
            "subcategory":"Carpets & Floor Coverings",
            "type":"Retail Goods"
        }
    ],
    "sg:phone":"+1 417 623 1991",
    "sg:postcode":"64801",
    "sg:province":"MO",
    "sg:tags":[
        "material"
    ],
    "wof:name":"Smith's Floor Store",
    "wof:placetype":"venue"
},
  "geometry": {"coordinates":[-94.51367500000001,37.081716],"type":"Point"}
}