{
  "type": "Feature",
  "properties": {
    "iso:country":"US",
    "sg:address":"145 S Mount Auburn Rd",
    "sg:city":"Cape Girardeau",
    "sg:classifiers":[
        {
            "category":"Health Services",
            "subcategory":"Clinic",
            "type":"Services"
        }
    ],
    "sg:phone":"+1 573 334 7014",
    "sg:postcode":"63703",
    "sg:province":"MO",
    "sg:tags":[
        "home",
        "care",
        "help",
        "supply"
    ],
    "wof:name":"V N A Community Services",
    "wof:placetype":"venue"
},
  "geometry": {"coordinates":[-89.57441900000001,37.303314],"type":"Point"}
}