{
  "type": "Feature",
  "properties": {
    "iso:country":"US",
    "sg:address":"941 Charter Commons St",
    "sg:city":"Chesterfield",
    "sg:classifiers":[
        {
            "category":"Building & Trades",
            "subcategory":"Locksmith",
            "type":"Services"
        }
    ],
    "sg:phone":"+1 636 394 0662",
    "sg:postcode":"63017",
    "sg:province":"MO",
    "sg:tags":[
        "lock"
    ],
    "wof:name":"Abbot Lock & Key Co",
    "wof:placetype":"venue"
},
  "geometry": {"coordinates":[-90.518029,38.626457],"type":"Point"}
}