{
  "type": "Feature",
  "properties": {
    "iso:country":"US",
    "sg:address":"650 Gaylord Dr",
    "sg:city":"Fulton",
    "sg:classifiers":[
        {
            "category":"Retail",
            "subcategory":"Auto Repair",
            "type":"Services"
        }
    ],
    "sg:phone":"+1 573 642 1988",
    "sg:postcode":"65251",
    "sg:province":"MO",
    "sg:tags":[
        "body"
    ],
    "wof:name":"Pauls Auto Body",
    "wof:placetype":"venue"
},
  "geometry": {"coordinates":[-91.96991199999999,38.851616],"type":"Point"}
}