{
  "type": "Feature",
  "properties": {
    "iso:country":"US",
    "sg:address":"3516 Pcr 206",
    "sg:city":"Perryville",
    "sg:classifiers":[
        {
            "category":"Building & Trades",
            "subcategory":"Electrical",
            "type":"Services"
        }
    ],
    "sg:phone":"+1 573 547 8665",
    "sg:postcode":"63775",
    "sg:province":"MO",
    "sg:tags":[
        "industrial",
        "electrician",
        "contractors-commercial",
        "electric"
    ],
    "wof:name":"Tom 'S Electric Wiring",
    "wof:placetype":"venue"
},
  "geometry": {"coordinates":[-89.847211,37.790891],"type":"Point"}
}