{
  "type": "Feature",
  "properties": {
    "iso:country":"US",
    "sg:address":"227 S Central Ave",
    "sg:city":"Clayton",
    "sg:classifiers":[
        {
            "category":"Government",
            "subcategory":"Office",
            "type":"Public Place"
        }
    ],
    "sg:phone":"+1 314 290 8440",
    "sg:postcode":"63105",
    "sg:province":"MO",
    "sg:tags":[
        "village"
    ],
    "wof:name":"Clayton Parking Tickets",
    "wof:placetype":"venue"
},
  "geometry": {"coordinates":[-90.338893,38.646311],"type":"Point"}
}