{
  "type": "Feature",
  "properties": {
    "iso:country":"US",
    "sg:address":"217 Market St",
    "sg:city":"Kimmswick",
    "sg:classifiers":[
        {
            "category":"Shopping",
            "type":"Retail Goods"
        },
        {
            "category":"Shopping",
            "subcategory":"Gifts & Souvenirs",
            "type":"Retail Goods"
        }
    ],
    "sg:phone":"+1 636 464 3472",
    "sg:postcode":"63053",
    "sg:province":"MO",
    "sg:tags":[
        "craft",
        "gallery",
        "dealer"
    ],
    "wof:name":"Bunny Patch",
    "wof:placetype":"venue"
},
  "geometry": {"coordinates":[-90.364018,38.365377],"type":"Point"}
}