{
  "type": "Feature",
  "properties": {
    "iso:country":"US",
    "sg:address":"3533 Dunn Rd",
    "sg:city":"Florissant",
    "sg:classifiers":[
        {
            "category":"Insurance",
            "subcategory":"Hazard Insurance",
            "type":"Services"
        },
        {
            "category":"Insurance",
            "subcategory":"Insurance Agent",
            "type":"Services"
        },
        {
            "category":"Insurance",
            "subcategory":"Life Insurance",
            "type":"Services"
        }
    ],
    "sg:phone":"+1 314 266 3312",
    "sg:postcode":"63033",
    "sg:province":"MO",
    "sg:tags":[
        "auto"
    ],
    "sg:website":"http://statefarm.mqgroup.com/url.asp?usr=253638",
    "wof:name":"Owens, Dimitri - State Farm Insurance Agent",
    "wof:placetype":"venue"
},
  "geometry": {"coordinates":[-90.27121,38.77145],"type":"Point"}
}