{
  "type": "Feature",
  "properties": {
    "iso:country":"US",
    "sg:address":"53 Wampler Dr",
    "sg:city":"Arnold",
    "sg:classifiers":[
        {
            "category":"Professional",
            "subcategory":"Management & Consulting",
            "type":"Services"
        }
    ],
    "sg:phone":"+1 636 282 9284",
    "sg:postcode":"63010",
    "sg:province":"MO",
    "wof:name":"Dgt Midwest LLC",
    "wof:placetype":"venue"
},
  "geometry": {"coordinates":[-90.401464,38.413246],"type":"Point"}
}