{
  "type": "Feature",
  "properties": {
    "iso:country":"US",
    "sg:address":"1107 S Main St",
    "sg:city":"Charleston",
    "sg:classifiers":[
        {
            "category":"Autos & Motor Vehicles",
            "subcategory":"Automobile Sales",
            "type":"Retail Goods"
        }
    ],
    "sg:phone":"+1 573 683 3055",
    "sg:postcode":"63834",
    "sg:province":"MO",
    "sg:tags":[
        "used"
    ],
    "wof:name":"George Kenny Enterprises",
    "wof:placetype":"venue"
},
  "geometry": {"coordinates":[-89.35005200000001,36.913267],"type":"Point"}
}