{
  "type": "Feature",
  "properties": {
    "iso:country":"US",
    "sg:address":"311 S Union Ave",
    "sg:city":"Springfield",
    "sg:classifiers":[
        {
            "category":"Autos & Motor Vehicles",
            "subcategory":"Auto Supplies",
            "type":"Retail Goods"
        }
    ],
    "sg:phone":"+1 417 883 1515",
    "sg:postcode":"65802",
    "sg:province":"MO",
    "sg:tags":[
        "automobile",
        "part",
        "accessory"
    ],
    "wof:name":"Mighty Auto Parts of Springfield",
    "wof:placetype":"venue"
},
  "geometry": {"coordinates":[-93.23340899999999,37.206827],"type":"Point"}
}