{
  "type": "Feature",
  "properties": {
    "iso:country":"US",
    "sg:address":"969 Anglum Rd",
    "sg:city":"Hazelwood",
    "sg:phone":"+1 314 824 1148",
    "sg:postcode":"63042",
    "sg:province":"MO",
    "sg:website":"http://www.aaronsofficeinfo.com",
    "wof:name":"Aaron's Office Furniture",
    "wof:placetype":"venue"
},
  "geometry": {"coordinates":[-90.393863,38.774053],"type":"Point"}
}