{
  "type": "Feature",
  "properties": {
    "iso:country":"US",
    "sg:address":"1000 E 24 Ave",
    "sg:city":"Kansas City",
    "sg:classifiers":[
        {
            "category":"Freight",
            "type":"Transportation"
        }
    ],
    "sg:phone":"+1 816 836 1983",
    "sg:postcode":"64116",
    "sg:province":"MO",
    "sg:tags":[
        "operator",
        "local",
        "trucking"
    ],
    "wof:name":"Discount Piano Outlet",
    "wof:placetype":"venue"
},
  "geometry": {"coordinates":[-94.567706,39.146865],"type":"Point"}
}