{
  "type": "Feature",
  "properties": {
    "iso:country":"US",
    "sg:address":"3733 N Hanley Rd",
    "sg:city":"St Louis",
    "sg:classifiers":[
        {
            "category":"Professional",
            "type":"Services"
        }
    ],
    "sg:phone":"+1 314 423 5433",
    "sg:postcode":"63121",
    "sg:province":"MO",
    "sg:tags":[
        "establishment"
    ],
    "wof:name":"Unavailable",
    "wof:placetype":"venue"
},
  "geometry": {"coordinates":[-90.319442,38.712459],"type":"Point"}
}