{
  "type": "Feature",
  "properties": {
    "iso:country":"US",
    "sg:address":"370 US Hwy 54",
    "sg:city":"Camdenton",
    "sg:classifiers":[
        {
            "category":"Wholesale",
            "subcategory":"Durable Goods & Equipment",
            "type":"Manufacturing & Wholesale Goods"
        }
    ],
    "sg:phone":"+1 573 317 0480",
    "sg:postcode":"65020",
    "sg:province":"MO",
    "sg:tags":[
        "representative",
        "manufacturer"
    ],
    "wof:name":"Dolphin International Ent",
    "wof:placetype":"venue"
},
  "geometry": {"coordinates":[-92.749741,38.004667],"type":"Point"}
}