{
  "type": "Feature",
  "properties": {
    "iso:country":"US",
    "sg:address":"25 Schlesinger Rd",
    "sg:city":"Tuscumbia",
    "sg:classifiers":[
        {
            "category":"Place Of Worship",
            "type":"Public Place"
        }
    ],
    "sg:phone":"+1 573 736 5559",
    "sg:postcode":"65082",
    "sg:province":"MO",
    "sg:tags":[
        "church"
    ],
    "wof:name":"Mount Zion Christian Church",
    "wof:placetype":"venue"
},
  "geometry": {"coordinates":[-92.422627,38.212772],"type":"Point"}
}