{
  "type": "Feature",
  "properties": {
    "iso:country":"US",
    "sg:address":"1024 S Big Bend Blvd",
    "sg:city":"Saint Louis",
    "sg:classifiers":[
        {
            "category":"Shopping",
            "subcategory":"Stationery & Office Supplies",
            "type":"Retail Goods"
        },
        {
            "category":"Wholesale",
            "subcategory":"Computers",
            "type":"Manufacturing & Wholesale Goods"
        }
    ],
    "sg:phone":"+1 314 646 8100",
    "sg:postcode":"63117",
    "sg:province":"MO",
    "sg:tags":[
        "equipment"
    ],
    "wof:name":"Office Depot",
    "wof:placetype":"venue"
},
  "geometry": {"coordinates":[-90.318901,38.633801],"type":"Point"}
}