{
  "type": "Feature",
  "properties": {
    "iso:country":"US",
    "sg:address":"7115 Page Ave",
    "sg:city":"Saint Louis",
    "sg:classifiers":[
        {
            "category":"Restaurant",
            "type":"Food & Drink"
        }
    ],
    "sg:phone":"+1 314 862 4111",
    "sg:postcode":"63133",
    "sg:province":"MO",
    "sg:website":"www.popeyes.com",
    "wof:name":"Popeye's Famous Fried Chicken & Biscuits",
    "wof:placetype":"venue"
},
  "geometry": {"coordinates":[-90.313904,38.676498],"type":"Point"}
}