{
  "type": "Feature",
  "properties": {
    "addr:full":"297 SW State Hwy U Holden MO 64040",
    "addr:housenumber":"297",
    "addr:postcode":"64040",
    "addr:street":"Sw State Hwy U Holden",
    "iso:country":"US",
    "sg:address":"297 SW State Hwy U",
    "sg:city":"Holden",
    "sg:classifiers":[
        {
            "category":"Retail",
            "subcategory":"Auto Repair",
            "type":"Services"
        }
    ],
    "sg:phone":"+1 816 850 5677",
    "sg:postcode":"64040",
    "sg:province":"MO",
    "sg:tags":[
        "automotive",
        "wrecker"
    ],
    "wof:name":"Joe's Tows",
    "wof:placetype":"venue"
},
  "geometry": {"coordinates":[-93.946471,38.725699],"type":"Point"}
}