{
  "type": "Feature",
  "properties": {
    "iso:country":"US",
    "sg:address":"4620 J C Nichols Pkwy",
    "sg:city":"Kansas City",
    "sg:classifiers":[
        {
            "category":"Health Services",
            "subcategory":"Medical Lab",
            "type":"Services"
        }
    ],
    "sg:phone":"+1 816 753 7543",
    "sg:postcode":"64112",
    "sg:province":"MO",
    "sg:tags":[
        "laboratory",
        "dental"
    ],
    "wof:name":"Plaza Dental Lab Inc",
    "wof:placetype":"venue"
},
  "geometry": {"coordinates":[-94.588453,39.043883],"type":"Point"}
}