{
  "type": "Feature",
  "properties": {
    "iso:country":"US",
    "sg:address":"312 S 4th St",
    "sg:city":"Hayti",
    "sg:classifiers":[
        {
            "category":"Shopping",
            "subcategory":"Discount & Variety Stores",
            "type":"Retail Goods"
        }
    ],
    "sg:phone":"+1 573 359 6358",
    "sg:postcode":"63851",
    "sg:province":"MO",
    "wof:name":"Dollar & More Thrift Store",
    "wof:placetype":"venue"
},
  "geometry": {"coordinates":[-89.747883,36.231933],"type":"Point"}
}