{
  "type": "Feature",
  "properties": {
    "iso:country":"US",
    "sg:address":"4911 Barnes Hospital Plz",
    "sg:city":"Saint Louis",
    "sg:classifiers":[
        {
            "category":"Health Services",
            "subcategory":"Doctor",
            "type":"Services"
        }
    ],
    "sg:phone":"+1 314 362 3181",
    "sg:postcode":"63101",
    "sg:province":"MO",
    "sg:tags":[
        "obstetrician",
        "gynecologist"
    ],
    "wof:name":"Mutch David G MD",
    "wof:placetype":"venue"
},
  "geometry": {"coordinates":[-90.264793,38.634954],"type":"Point"}
}