{
  "type": "Feature",
  "properties": {
    "iso:country":"US",
    "sg:address":"1101 Missouri Ave",
    "sg:city":"Saint Louis",
    "sg:classifiers":[
        {
            "category":"Wholesale",
            "subcategory":"Apparel",
            "type":"Manufacturing & Wholesale Goods"
        }
    ],
    "sg:phone":"+1 314 997 1877",
    "sg:postcode":"63104",
    "sg:province":"MO",
    "sg:tags":[
        "clothing"
    ],
    "wof:name":"Broder Brothers",
    "wof:placetype":"venue"
},
  "geometry": {"coordinates":[-90.217027,38.620354],"type":"Point"}
}