{
  "type": "Feature",
  "properties": {
    "iso:country":"US",
    "sg:address":"700 E Liberty St",
    "sg:city":"Mexico",
    "sg:classifiers":[
        {
            "category":"Retail",
            "subcategory":"Car Wash",
            "type":"Services"
        }
    ],
    "sg:phone":"+1 573 581 9494",
    "sg:postcode":"65265",
    "sg:province":"MO",
    "sg:tags":[
        "carwash"
    ],
    "wof:name":"Auto Spa & Detailing",
    "wof:placetype":"venue"
},
  "geometry": {"coordinates":[-91.876778,39.170373],"type":"Point"}
}