{
  "type": "Feature",
  "properties": {
    "iso:country":"US",
    "sg:address":"2701 W Clay St",
    "sg:city":"St Charles",
    "sg:classifiers":[
        {
            "category":"Home & Garden",
            "subcategory":"Building Materials",
            "type":"Retail Goods"
        },
        {
            "category":"Home & Garden",
            "subcategory":"Home Furnishings",
            "type":"Retail Goods"
        }
    ],
    "sg:phone":"+1 636 946 5622",
    "sg:postcode":"63301",
    "sg:province":"MO",
    "sg:tags":[
        "shower",
        "door",
        "enclosure",
        "accessory"
    ],
    "wof:name":"Total Glass & Shelving Inc",
    "wof:placetype":"venue"
},
  "geometry": {"coordinates":[-90.520961,38.784648],"type":"Point"}
}