{
  "type": "Feature",
  "properties": {
    "iso:country":"US",
    "sg:address":"6126 Independence Ave",
    "sg:city":"Kansas City",
    "sg:classifiers":[
        {
            "category":"Restaurant",
            "type":"Food & Drink"
        }
    ],
    "sg:phone":"+1 816 483 5600",
    "sg:postcode":"64125",
    "sg:province":"MO",
    "wof:name":"Paso Del Norte",
    "wof:placetype":"venue"
},
  "geometry": {"coordinates":[-94.510124,39.104971],"type":"Point"}
}