{
  "type": "Feature",
  "properties": {
    "iso:country":"US",
    "sg:address":"5029 Bancroft Ave",
    "sg:city":"Saint Louis",
    "sg:classifiers":[
        {
            "category":"Professional",
            "subcategory":"Management & Consulting",
            "type":"Services"
        }
    ],
    "sg:phone":"+1 314 302 3693",
    "sg:postcode":"63109",
    "sg:province":"MO",
    "sg:tags":[
        "security",
        "social",
        "administration",
        "monitor",
        "hearing"
    ],
    "wof:name":"Ian T Murphy",
    "wof:placetype":"venue"
},
  "geometry": {"coordinates":[-90.278914,38.589989],"type":"Point"}
}