{
  "type": "Feature",
  "properties": {
    "iso:country":"US",
    "sg:address":"18 Highway K",
    "sg:city":"Hermann",
    "sg:classifiers":[
        {
            "category":"Building & Trades",
            "subcategory":"Construction",
            "type":"Services"
        }
    ],
    "sg:phone":"+1 573 252 4560",
    "sg:postcode":"65041",
    "sg:province":"MO",
    "sg:tags":[
        "wallcoverings-installation",
        "wallpaper",
        "painting",
        "contractor"
    ],
    "wof:name":"Ruth Hauser Wlpr Intr Paintin",
    "wof:placetype":"venue"
},
  "geometry": {"coordinates":[-91.483063,38.802788],"type":"Point"}
}