{
  "type": "Feature",
  "properties": {
    "iso:country":"US",
    "sg:address":"7778 Folk Ave",
    "sg:city":"Saint Louis",
    "sg:classifiers":[
        {
            "category":"Building & Trades",
            "subcategory":"Landscaping Services",
            "type":"Services"
        }
    ],
    "sg:phone":"+1 314 781 0946",
    "sg:postcode":"63143",
    "sg:province":"MO",
    "wof:name":"Easy Mow",
    "wof:placetype":"venue"
},
  "geometry": {"coordinates":[-90.32716000000001,38.619446],"type":"Point"}
}