{
  "type": "Feature",
  "properties": {
    "iso:country":"US",
    "sg:address":"714 State Hwy Ab",
    "sg:city":"Willard",
    "sg:classifiers":[
        {
            "category":"Professional",
            "subcategory":"Business Services",
            "type":"Services"
        }
    ],
    "sg:phone":"+1 417 742 3581",
    "sg:postcode":"65781",
    "sg:province":"MO",
    "sg:tags":[
        "embroidery"
    ],
    "wof:name":"Tech Threads",
    "wof:placetype":"venue"
},
  "geometry": {"coordinates":[-93.433215,37.292388],"type":"Point"}
}