{
  "type": "Feature",
  "properties": {
    "iso:country":"US",
    "sg:address":"1035 Bellevue Ave Ste 110",
    "sg:city":"Saint Louis",
    "sg:classifiers":[
        {
            "category":"Health Services",
            "subcategory":"Doctor",
            "type":"Services"
        }
    ],
    "sg:phone":"+1 314 647 0180",
    "sg:postcode":"63117",
    "sg:province":"MO",
    "wof:name":"Abbott David MD",
    "wof:placetype":"venue"
},
  "geometry": {"coordinates":[-90.312202,38.632401],"type":"Point"}
}