{
  "type": "Feature",
  "properties": {
    "iso:country":"US",
    "sg:address":"1044 NW 25th Rd",
    "sg:city":"Holden",
    "sg:classifiers":[
        {
            "category":"Building & Trades",
            "subcategory":"Construction",
            "type":"Services"
        }
    ],
    "sg:phone":"+1 816 564 0789",
    "sg:postcode":"64040",
    "sg:province":"MO",
    "sg:tags":[
        "contractor",
        "mason"
    ],
    "sg:website":"http://www.blackwaterbrickandstone.com",
    "wof:name":"Blackwater Stone",
    "wof:placetype":"venue"
},
  "geometry": {"coordinates":[-93.940088,38.771674],"type":"Point"}
}