{
  "type": "Feature",
  "properties": {
    "iso:country":"US",
    "sg:address":"2145 N Ballas Rd",
    "sg:city":"St Louis",
    "sg:classifiers":[
        {
            "category":"Education",
            "subcategory":"School",
            "type":"Public Place"
        }
    ],
    "sg:phone":"+1 314 787 1036",
    "sg:postcode":"63131",
    "sg:province":"MO",
    "sg:website":"www.covenantstlouis.org",
    "wof:name":"Covenant Christian School",
    "wof:placetype":"venue"
},
  "geometry": {"coordinates":[-90.44380200000001,38.62128],"type":"Point"}
}