{
  "type": "Feature",
  "properties": {
    "iso:country":"US",
    "sg:address":"2286 Rose Ln",
    "sg:city":"Pacific",
    "sg:classifiers":[
        {
            "category":"Freight",
            "type":"Transportation"
        }
    ],
    "sg:phone":"+1 636 271 5959",
    "sg:postcode":"63069",
    "sg:province":"MO",
    "sg:tags":[
        "hauling",
        "trucking"
    ],
    "wof:name":"Midwest Hauling Inc",
    "wof:placetype":"venue"
},
  "geometry": {"coordinates":[-90.771766,38.481546],"type":"Point"}
}