{
  "type": "Feature",
  "properties": {
    "iso:country":"US",
    "sg:address":"12864 Pennridge Dr",
    "sg:city":"Bridgeton",
    "sg:classifiers":[
        {
            "category":"Utilities",
            "subcategory":"Refuse",
            "type":"Services"
        },
        {
            "category":"Utilities",
            "subcategory":"Recycling",
            "type":"Services"
        },
        {
            "category":"Utilities",
            "type":"Services"
        }
    ],
    "sg:phone":"+1 314 291 3131",
    "sg:postcode":"63044",
    "sg:province":"MO",
    "sg:tags":[
        "rubbish",
        "collection",
        "garbage",
        "removal"
    ],
    "sg:website":"http://www.meridianwastestl.com",
    "wof:name":"Meridian Waste Services",
    "wof:placetype":"venue"
},
  "geometry": {"coordinates":[-90.431633,38.765532],"type":"Point"}
}