{
  "type": "Feature",
  "properties": {
    "iso:country":"US",
    "sg:address":"197 Leonard Dr",
    "sg:city":"Ft Leonard Wood",
    "sg:classifiers":[
        {
            "category":"Professional",
            "type":"Services"
        }
    ],
    "sg:phone":"+1 573 329 8528",
    "sg:postcode":"65401",
    "sg:province":"MO",
    "sg:tags":[
        "establishment"
    ],
    "wof:name":"Trimble",
    "wof:placetype":"venue"
},
  "geometry": {"coordinates":[-91.753185,37.941803],"type":"Point"}
}