{
  "type": "Feature",
  "properties": {
    "iso:country":"US",
    "sg:address":"1120 Graham St",
    "sg:city":"Saint Louis",
    "sg:classifiers":[
        {
            "category":"Personal",
            "type":"Services"
        }
    ],
    "sg:phone":"+1 314 831 2464",
    "sg:postcode":"63139",
    "sg:province":"MO",
    "wof:name":"North County Dermatology",
    "wof:placetype":"venue"
},
  "geometry": {"coordinates":[-90.291185,38.628779],"type":"Point"}
}