{
  "type": "Feature",
  "properties": {
    "iso:country":"US",
    "sg:address":"10442 Liv 229",
    "sg:city":"Chillicothe",
    "sg:classifiers":[
        {
            "category":"Retail",
            "subcategory":"Repair Shop",
            "type":"Services"
        },
        {
            "category":"Building & Trades",
            "subcategory":"Plumbing",
            "type":"Services"
        }
    ],
    "sg:phone":"+1 660 646 3320",
    "sg:postcode":"64601",
    "sg:province":"MO",
    "sg:tags":[
        "septic"
    ],
    "wof:name":"Knouse Septic Tank & Line Clng",
    "wof:placetype":"venue"
},
  "geometry": {"coordinates":[-93.602429,39.826059],"type":"Point"}
}