{
  "type": "Feature",
  "properties": {
    "iso:country":"US",
    "sg:address":"911 Kensington Rd",
    "sg:city":"Joplin",
    "sg:classifiers":[
        {
            "category":"Shopping",
            "subcategory":"Gifts & Souvenirs",
            "type":"Retail Goods"
        }
    ],
    "sg:phone":"+1 417 781 5750",
    "sg:postcode":"64801",
    "sg:province":"MO",
    "wof:name":"Belsnickle",
    "wof:placetype":"venue"
},
  "geometry": {"coordinates":[-94.523099,37.103701],"type":"Point"}
}