{
  "type": "Feature",
  "properties": {
    "iso:country":"US",
    "sg:address":"1705 Christy Dr",
    "sg:city":"Jefferson City",
    "sg:classifiers":[
        {
            "category":"Health Services",
            "subcategory":"Podiatrist",
            "type":"Services"
        }
    ],
    "sg:phone":"+1 573 634 3338",
    "sg:postcode":"65101",
    "sg:province":"MO",
    "wof:name":"Advanced Foot Care Ctr",
    "wof:placetype":"venue"
},
  "geometry": {"coordinates":[-92.193071,38.556782],"type":"Point"}
}