{
  "type": "Feature",
  "properties": {
    "iso:country":"US",
    "sg:address":"510 Broadway St",
    "sg:city":"Elsberry",
    "sg:phone":"+1 573 898 2161",
    "sg:postcode":"63343",
    "sg:province":"MO",
    "sg:tags":[
        "corn",
        "farming",
        "soybean"
    ],
    "wof:name":"Welch Long Farms Inc",
    "wof:placetype":"venue"
},
  "geometry": {"coordinates":[-90.78469,39.164823],"type":"Point"}
}