{
  "type": "Feature",
  "properties": {
    "iso:country":"US",
    "sg:address":"621 E 23rd St S",
    "sg:city":"Independence",
    "sg:classifiers":[
        {
            "category":"Organizations",
            "subcategory":"Professional Association",
            "type":"Services"
        }
    ],
    "sg:phone":"+1 816 836 4700",
    "sg:postcode":"64055",
    "sg:province":"MO",
    "wof:name":"Financial Independence",
    "wof:placetype":"venue"
},
  "geometry": {"coordinates":[-94.407093,39.078837],"type":"Point"}
}