{
  "type": "Feature",
  "properties": {
    "iso:country":"US",
    "sg:address":"7130 State Highway 14 E",
    "sg:city":"Sparta",
    "sg:classifiers":[
        {
            "category":"Restaurant",
            "type":"Food & Drink"
        }
    ],
    "sg:phone":"+1 417 634 2227",
    "sg:postcode":"65753",
    "sg:province":"MO",
    "sg:tags":[
        "pizza"
    ],
    "wof:name":"A J's Pizza",
    "wof:placetype":"venue"
},
  "geometry": {"coordinates":[-93.090118,37.001221],"type":"Point"}
}