{
  "type": "Feature",
  "properties": {
    "addr:full":"8195 State Hwy Zz West Plains MO 65775",
    "addr:housenumber":"8195",
    "addr:postcode":"65775",
    "addr:street":"State Hwy Zz",
    "iso:country":"US",
    "sg:address":"8195 State Hwy Zz",
    "sg:city":"West Plains",
    "sg:classifiers":[
        {
            "category":"Retail",
            "subcategory":"Laundry & Dry Cleaning",
            "type":"Services"
        }
    ],
    "sg:phone":"+1 417 257 7727",
    "sg:postcode":"65775",
    "sg:province":"MO",
    "sg:tags":[
        "cleaners",
        "rug",
        "carpet"
    ],
    "wof:name":"Best Carpet & Upholstery Clng",
    "wof:placetype":"venue"
},
  "geometry": {"coordinates":[-91.75559699999999,36.713758],"type":"Point"}
}