{
  "type": "Feature",
  "properties": {
    "iso:country":"US",
    "sg:address":"5889 Dr Martin Luther King Dr",
    "sg:city":"Saint Louis",
    "sg:classifiers":[
        {
            "category":"Organizations",
            "subcategory":"Membership Organization",
            "type":"Services"
        }
    ],
    "sg:phone":"+1 314 385 4262",
    "sg:postcode":"63112",
    "sg:province":"MO",
    "wof:name":"Eugene A Fowler Rev",
    "wof:placetype":"venue"
},
  "geometry": {"coordinates":[-90.282062,38.67358],"type":"Point"}
}