{
  "type": "Feature",
  "properties": {
    "iso:country":"US",
    "sg:address":"615 S 13th St",
    "sg:city":"St Joseph",
    "sg:classifiers":[
        {
            "category":"Retail",
            "subcategory":"Repair Shop",
            "type":"Services"
        }
    ],
    "sg:phone":"+1 816 279 1833",
    "sg:postcode":"64501",
    "sg:province":"MO",
    "sg:tags":[
        "sharpening"
    ],
    "wof:name":"Perfect Edge",
    "wof:placetype":"venue"
},
  "geometry": {"coordinates":[-94.844712,39.759113],"type":"Point"}
}