{
  "type": "Feature",
  "properties": {
    "iso:country":"US",
    "sg:address":"515 S Ohio Ave",
    "sg:city":"Sedalia",
    "sg:classifiers":[
        {
            "category":"Home & Garden",
            "subcategory":"Furniture",
            "type":"Retail Goods"
        }
    ],
    "sg:phone":"+1 660 826 1818",
    "sg:postcode":"65301",
    "sg:province":"MO",
    "sg:tags":[
        "store"
    ],
    "wof:name":"McLaughlin Bros Furniture Company",
    "wof:placetype":"venue"
},
  "geometry": {"coordinates":[-93.228249,38.706877],"type":"Point"}
}