{
  "type": "Feature",
  "properties": {
    "addr:full":"6700 Olive Boulevard St Louis MO 63130",
    "addr:housenumber":"6700",
    "addr:postcode":"63130",
    "addr:street":"Olive Boulevard",
    "iso:country":"US",
    "sg:address":"6700 Olive Boulevard",
    "sg:city":"St Louis",
    "sg:classifiers":[
        {
            "category":"Autos & Motor Vehicles",
            "subcategory":"Fuel & Gas Station",
            "type":"Retail Goods"
        }
    ],
    "sg:phone":"+1 314 863 0425",
    "sg:postcode":"63130",
    "sg:province":"MO",
    "wof:name":"BP/Amoco",
    "wof:placetype":"venue"
},
  "geometry": {"coordinates":[-90.307987,38.662815],"type":"Point"}
}