{
  "type": "Feature",
  "properties": {
    "iso:country":"US",
    "sg:address":"16568 Manchester Rd",
    "sg:city":"Grover",
    "sg:classifiers":[
        {
            "category":"Retail",
            "subcategory":"Laundry & Dry Cleaning",
            "type":"Services"
        }
    ],
    "sg:phone":"+1 636 458 8828",
    "sg:postcode":"63040",
    "sg:province":"MO",
    "sg:tags":[
        "drycleaning",
        "plant"
    ],
    "wof:name":"Wildwood Cleaners",
    "wof:placetype":"venue"
},
  "geometry": {"coordinates":[-90.621894,38.579616],"type":"Point"}
}