{
  "type": "Feature",
  "properties": {
    "iso:country":"US",
    "sg:address":"1530 US Hwy 60",
    "sg:city":"Republic",
    "sg:classifiers":[
        {
            "category":"Home & Garden",
            "subcategory":"Building Materials",
            "type":"Retail Goods"
        }
    ],
    "sg:phone":"+1 417 732 7619",
    "sg:postcode":"65738",
    "sg:province":"MO",
    "wof:name":"Republic Ornamental Concrete",
    "wof:placetype":"venue"
},
  "geometry": {"coordinates":[-93.455417,37.134006],"type":"Point"}
}