{
  "type": "Feature",
  "properties": {
    "iso:country":"US",
    "sg:address":"6 S Courtney Dr",
    "sg:city":"Butler",
    "sg:classifiers":[
        {
            "category":"Autos & Motor Vehicles",
            "subcategory":"Automobile Sales",
            "type":"Retail Goods"
        }
    ],
    "sg:phone":"+1 660 679 4626",
    "sg:postcode":"64730",
    "sg:province":"MO",
    "sg:tags":[
        "dealers-used",
        "used",
        "cars-wholesale",
        "car"
    ],
    "wof:name":"Berry Sales",
    "wof:placetype":"venue"
},
  "geometry": {"coordinates":[-94.335998,38.248655],"type":"Point"}
}