{
  "type": "Feature",
  "properties": {
    "iso:country":"US",
    "sg:address":"3150 S National Ave",
    "sg:city":"Springfield",
    "sg:classifiers":[
        {
            "category":"Health Services",
            "subcategory":"Doctor",
            "type":"Services"
        }
    ],
    "sg:phone":"+1 417 881 5529",
    "sg:postcode":"65807",
    "sg:province":"MO",
    "sg:tags":[
        "physician",
        "surgeon"
    ],
    "wof:name":"Clarke Orthopedic Clinic",
    "wof:placetype":"venue"
},
  "geometry": {"coordinates":[-93.27736299999999,37.157147],"type":"Point"}
}