{
  "type": "Feature",
  "properties": {
    "iso:country":"US",
    "sg:address":"306 E Washington Ave",
    "sg:city":"Ava",
    "sg:classifiers":[
        {
            "category":"Shopping",
            "subcategory":"Musical Instruments",
            "type":"Retail Goods"
        }
    ],
    "sg:phone":"+1 417 683 1996",
    "sg:postcode":"65608",
    "sg:province":"MO",
    "wof:name":"Music Room",
    "wof:placetype":"venue"
},
  "geometry": {"coordinates":[-92.658643,36.952072],"type":"Point"}
}