{
  "type": "Feature",
  "properties": {
    "iso:country":"US",
    "sg:address":"725 State Hwy 248",
    "sg:city":"Reeds Spring",
    "sg:classifiers":[
        {
            "category":"Restaurant",
            "type":"Food & Drink"
        }
    ],
    "sg:phone":"+1 417 272 8243",
    "sg:postcode":"65737",
    "sg:province":"MO",
    "wof:name":"Papouli's",
    "wof:placetype":"venue"
},
  "geometry": {"coordinates":[-93.36791599999999,36.758995],"type":"Point"}
}