{
  "type": "Feature",
  "properties": {
    "iso:country":"US",
    "sg:address":"9468 Glen Hollow Ln",
    "sg:city":"Carthage",
    "sg:classifiers":[
        {
            "category":"Wholesale",
            "subcategory":"Metals & Minerals",
            "type":"Manufacturing & Wholesale Goods"
        }
    ],
    "sg:phone":"+1 417 358 2178",
    "sg:postcode":"64836",
    "sg:province":"MO",
    "sg:tags":[
        "copper"
    ],
    "wof:name":"Morton's Copper Co",
    "wof:placetype":"venue"
},
  "geometry": {"coordinates":[-94.23190200000001,37.148531],"type":"Point"}
}