{
  "type": "Feature",
  "properties": {
    "iso:country":"US",
    "sg:address":"320 N Main St",
    "sg:city":"Fredericktown",
    "sg:classifiers":[
        {
            "category":"Place Of Worship",
            "subcategory":"Church",
            "type":"Public Place"
        },
        {
            "category":"Place Of Worship",
            "type":"Public Place"
        }
    ],
    "sg:phone":"+1 573 783 3502",
    "sg:postcode":"63645",
    "sg:province":"MO",
    "sg:tags":[
        "churches-baptist-general",
        "churches-baptist"
    ],
    "wof:name":"First Freewill Baptist",
    "wof:placetype":"venue"
},
  "geometry": {"coordinates":[-90.29424400000001,37.563746],"type":"Point"}
}