{
  "type": "Feature",
  "properties": {
    "iso:country":"US",
    "sg:address":"4940 Childrens Pl",
    "sg:city":"Saint Louis",
    "sg:classifiers":[
        {
            "category":"Education",
            "subcategory":"College",
            "type":"Public Place"
        }
    ],
    "sg:phone":"+1 314 362 7002",
    "sg:postcode":"63110",
    "sg:province":"MO",
    "sg:tags":[
        "hospital",
        "psychiatric"
    ],
    "wof:name":"Department of Psychiatry",
    "wof:placetype":"venue"
},
  "geometry": {"coordinates":[-90.26473900000001,38.637246],"type":"Point"}
}