{
  "type": "Feature",
  "properties": {
    "iso:country":"US",
    "sg:address":"12714 Highway T",
    "sg:city":"Marionville",
    "sg:classifiers":[
        {
            "category":"Farming",
            "subcategory":"Livestock Farm",
            "type":"Manufacturing & Wholesale Goods"
        }
    ],
    "sg:phone":"+1 417 744 2086",
    "sg:postcode":"65705",
    "sg:province":"MO",
    "sg:tags":[
        "ranch"
    ],
    "wof:name":"Charles Wells",
    "wof:placetype":"venue"
},
  "geometry": {"coordinates":[-93.627686,37.083832],"type":"Point"}
}