{
  "type": "Feature",
  "properties": {
    "iso:country":"US",
    "sg:address":"212 Osage Ave",
    "sg:city":"Camdenton",
    "sg:classifiers":[
        {
            "category":"Marine",
            "type":"Transportation"
        }
    ],
    "sg:phone":"+1 573 873 3666",
    "sg:postcode":"65020",
    "sg:province":"MO",
    "sg:tags":[
        "towing"
    ],
    "wof:name":"C's Marine Svc",
    "wof:placetype":"venue"
},
  "geometry": {"coordinates":[-92.7424,38.009467],"type":"Point"}
}