{
  "type": "Feature",
  "properties": {
    "iso:country":"US",
    "sg:address":"140 Cliff Cave Rd",
    "sg:city":"St Louis",
    "sg:classifiers":[
        {
            "category":"Manufacturing",
            "subcategory":"Jewelry",
            "type":"Manufacturing & Wholesale Goods"
        },
        {
            "category":"Wholesale",
            "subcategory":"Jewelry",
            "type":"Manufacturing & Wholesale Goods"
        }
    ],
    "sg:phone":"+1 314 846 8440",
    "sg:postcode":"63129",
    "sg:province":"MO",
    "sg:tags":[
        "stone"
    ],
    "wof:name":"Palecek Diamond Setting Co",
    "wof:placetype":"venue"
},
  "geometry": {"coordinates":[-90.303252,38.470033],"type":"Point"}
}