{
  "type": "Feature",
  "properties": {
    "iso:country":"US",
    "sg:address":"3637 Taylor Ave",
    "sg:city":"Bridgeton",
    "sg:classifiers":[
        {
            "category":"Retail",
            "subcategory":"Portrait Studio",
            "type":"Services"
        }
    ],
    "sg:phone":"+1 314 291 4343",
    "sg:postcode":"63044",
    "sg:province":"MO",
    "sg:tags":[
        "photo"
    ],
    "wof:name":"Bella Photo",
    "wof:placetype":"venue"
},
  "geometry": {"coordinates":[-90.41629500000001,38.740114],"type":"Point"}
}