{
  "type": "Feature",
  "properties": {
    "iso:country":"US",
    "sg:address":"6291 Arsenal St",
    "sg:city":"St Louis",
    "sg:classifiers":[
        {
            "category":"Health Services",
            "subcategory":"Health Practitioner",
            "type":"Services"
        }
    ],
    "sg:phone":"+1 314 968 6868",
    "sg:postcode":"63139",
    "sg:province":"MO",
    "sg:tags":[
        "psychotherapist"
    ],
    "wof:name":"Art Therapy Ctr",
    "wof:placetype":"venue"
},
  "geometry": {"coordinates":[-90.296222,38.607696],"type":"Point"}
}