{
  "type": "Feature",
  "properties": {
    "iso:country":"US",
    "sg:address":"234 S Neosho Blvd",
    "sg:city":"Neosho",
    "sg:classifiers":[
        {
            "category":"Personal",
            "subcategory":"Massage",
            "type":"Services"
        },
        {
            "category":"Wholesale",
            "subcategory":"Non-durable Goods",
            "type":"Manufacturing & Wholesale Goods"
        },
        {
            "category":"Personal",
            "subcategory":"Barber",
            "type":"Services"
        },
        {
            "category":"Personal",
            "subcategory":"Beauty Salon",
            "type":"Services"
        }
    ],
    "sg:phone":"+1 417 451 4477",
    "sg:postcode":"64850",
    "sg:province":"MO",
    "sg:tags":[
        "equipment",
        "manufacturer",
        "supplies-wholesale",
        "salons-equipment",
        "supply"
    ],
    "wof:name":"About Style",
    "wof:placetype":"venue"
},
  "geometry": {"coordinates":[-94.380973,36.868565],"type":"Point"}
}