{
  "type": "Feature",
  "properties": {
    "iso:country":"US",
    "sg:address":"333 W 46 Ter",
    "sg:city":"Kansas City",
    "sg:classifiers":[
        {
            "category":"Real Estate",
            "subcategory":"Real Estate Operator",
            "type":"Services"
        }
    ],
    "sg:phone":"+1 816 531 8699",
    "sg:postcode":"64112",
    "sg:province":"MO",
    "sg:tags":[
        "building",
        "apartment",
        "nonresidential"
    ],
    "wof:name":"Neptune Apartments",
    "wof:placetype":"venue"
},
  "geometry": {"coordinates":[-94.589997,39.043154],"type":"Point"}
}