{
  "type": "Feature",
  "properties": {
    "iso:country":"US",
    "sg:address":"13665 E 42 Ter S",
    "sg:city":"Independence",
    "sg:classifiers":[
        {
            "category":"Wholesale",
            "subcategory":"Books, Periodicals, & Newspapers",
            "type":"Manufacturing & Wholesale Goods"
        }
    ],
    "sg:phone":"+1 816 350 8554",
    "sg:postcode":"64055",
    "sg:province":"MO",
    "sg:tags":[
        "distributor"
    ],
    "wof:name":"USA Today",
    "wof:placetype":"venue"
},
  "geometry": {"coordinates":[-94.417658,39.044097],"type":"Point"}
}