{
  "type": "Feature",
  "properties": {
    "iso:country":"US",
    "sg:address":"16111 Manchester Rd",
    "sg:city":"Ballwin",
    "sg:classifiers":[
        {
            "category":"Health Services",
            "subcategory":"Doctor",
            "type":"Services"
        }
    ],
    "sg:phone":"+1 636 391 6030",
    "sg:postcode":"63011",
    "sg:province":"MO",
    "wof:name":"Zieba Family Dentistry",
    "wof:placetype":"venue"
},
  "geometry": {"coordinates":[-90.595354,38.590573],"type":"Point"}
}