{
  "type": "Feature",
  "properties": {
    "iso:country":"US",
    "sg:address":"1994 S White Oak Ave",
    "sg:city":"Springfield",
    "sg:classifiers":[
        {
            "category":"Shopping",
            "subcategory":"Bicycles & Sporting Goods",
            "type":"Retail Goods"
        }
    ],
    "sg:phone":"+1 417 886 4399",
    "sg:postcode":"65809",
    "sg:province":"MO",
    "sg:tags":[
        "equipment",
        "golf",
        "supply"
    ],
    "wof:name":"Chase Enterprises",
    "wof:placetype":"venue"
},
  "geometry": {"coordinates":[-93.20875100000001,37.177078],"type":"Point"}
}