{
  "type": "Feature",
  "properties": {
    "iso:country":"US",
    "sg:address":"330 W Park Mall",
    "sg:city":"Cape Girardeau",
    "sg:classifiers":[
        {
            "category":"Shopping",
            "subcategory":"Gifts & Souvenirs",
            "type":"Retail Goods"
        }
    ],
    "sg:phone":"+1 573 339 1789",
    "sg:postcode":"63703",
    "sg:province":"MO",
    "wof:name":"Things Remembered Inc",
    "wof:placetype":"venue"
},
  "geometry": {"coordinates":[-89.573804,37.299022],"type":"Point"}
}