{
  "type": "Feature",
  "properties": {
    "iso:country":"US",
    "sg:address":"8240 Local Hillsboro Rd",
    "sg:city":"Cedar Hill",
    "sg:classifiers":[
        {
            "category":"Retail",
            "subcategory":"Auto Repair",
            "type":"Services"
        }
    ],
    "sg:phone":"+1 636 274 0466",
    "sg:postcode":"63016",
    "sg:province":"MO",
    "sg:tags":[
        "body"
    ],
    "wof:name":"KV Auto Body Unlimited",
    "wof:placetype":"venue"
},
  "geometry": {"coordinates":[-90.629147,38.368579],"type":"Point"}
}