{
  "type": "Feature",
  "properties": {
    "iso:country":"US",
    "sg:address":"3648 Hebert St",
    "sg:city":"Saint Louis",
    "sg:classifiers":[
        {
            "category":"Bars & Pubs",
            "type":"Food & Drink"
        }
    ],
    "sg:phone":"+1 314 535 0669",
    "sg:postcode":"63107",
    "sg:province":"MO",
    "sg:tags":[
        "tavern",
        "lounge",
        "nightlife",
        "cocktail"
    ],
    "wof:name":"Hurns Cocktail Lounge",
    "wof:placetype":"venue"
},
  "geometry": {"coordinates":[-90.219498,38.66],"type":"Point"}
}