{
  "type": "Feature",
  "properties": {
    "iso:country":"US",
    "sg:address":"16140 Westwoods Business Park",
    "sg:city":"Ellisville",
    "sg:classifiers":[
        {
            "category":"Social Services",
            "type":"Services"
        }
    ],
    "sg:phone":"+1 636 530 0800",
    "sg:postcode":"63021",
    "sg:province":"MO",
    "sg:tags":[
        "instruction",
        "health",
        "care"
    ],
    "sg:website":"www.inpatient.com",
    "wof:name":"Inpatient Management Inc",
    "wof:placetype":"venue"
},
  "geometry": {"coordinates":[-90.600566,38.585566],"type":"Point"}
}