{
  "type": "Feature",
  "properties": {
    "iso:country":"US",
    "sg:address":"2910 California Ave",
    "sg:city":"St Louis",
    "sg:classifiers":[
        {
            "category":"Real Estate",
            "subcategory":"Real Estate Operator",
            "type":"Services"
        }
    ],
    "sg:phone":"+1 314 772 3577",
    "sg:postcode":"63118",
    "sg:province":"MO",
    "sg:tags":[
        "apartment"
    ],
    "wof:name":"Lafayette Elderly Property",
    "wof:placetype":"venue"
},
  "geometry": {"coordinates":[-90.228301,38.601646],"type":"Point"}
}