{
  "type": "Feature",
  "properties": {
    "iso:country":"US",
    "sg:address":"553 State Rte B",
    "sg:city":"St James",
    "sg:classifiers":[
        {
            "category":"Wholesale",
            "subcategory":"Meat",
            "type":"Manufacturing & Wholesale Goods"
        }
    ],
    "sg:phone":"+1 573 265 7674",
    "sg:postcode":"65559",
    "sg:province":"MO",
    "sg:tags":[
        "packer"
    ],
    "wof:name":"Forest City Packing Co",
    "wof:placetype":"venue"
},
  "geometry": {"coordinates":[-91.60558399999999,38.010174],"type":"Point"}
}