{
  "type": "Feature",
  "properties": {
    "iso:country":"US",
    "sg:address":"2688 Tyrell Dr",
    "sg:city":"Saint Louis",
    "sg:classifiers":[
        {
            "category":"Professional",
            "type":"Services"
        }
    ],
    "sg:phone":"+1 314 867 6143",
    "sg:postcode":"63136",
    "sg:province":"MO",
    "wof:name":"Tricias Care",
    "wof:placetype":"venue"
},
  "geometry": {"coordinates":[-90.262879,38.735763],"type":"Point"}
}