{
  "type": "Feature",
  "properties": {
    "iso:country":"US",
    "sg:address":"1112 E Stadium Blvd",
    "sg:city":"Columbia",
    "sg:classifiers":[
        {
            "category":"Travel",
            "subcategory":"Hotels & Motels",
            "type":"Entertainment"
        }
    ],
    "sg:phone":"+1 573 449 2731",
    "sg:postcode":"65201",
    "sg:province":"MO",
    "sg:tags":[
        "operation"
    ],
    "wof:name":"Campus Inn Inc",
    "wof:placetype":"venue"
},
  "geometry": {"coordinates":[-92.32619699999999,38.935019],"type":"Point"}
}