{
  "type": "Feature",
  "properties": {
    "iso:country":"US",
    "sg:address":"300 N Osage St",
    "sg:city":"Independence",
    "sg:classifiers":[
        {
            "category":"Shopping",
            "subcategory":"Computers & Home Electronics",
            "type":"Retail Goods"
        }
    ],
    "sg:phone":"+1 816 836 2000",
    "sg:postcode":"64050",
    "sg:province":"MO",
    "sg:tags":[
        "software"
    ],
    "sg:website":"www.optimation.com",
    "wof:name":"Optimation Sofeware Products",
    "wof:placetype":"venue"
},
  "geometry": {"coordinates":[-94.41839299999999,39.094592],"type":"Point"}
}