{
  "type": "Feature",
  "properties": {
    "iso:country":"US",
    "sg:address":"1047 E Karsch Blvd",
    "sg:city":"Farmington",
    "sg:classifiers":[
        {
            "category":"Personal",
            "subcategory":"Barber",
            "type":"Services"
        }
    ],
    "sg:phone":"+1 573 756 9566",
    "sg:postcode":"63640",
    "sg:province":"MO",
    "sg:tags":[
        "shop"
    ],
    "wof:name":"Sportsman's Barber Shop",
    "wof:placetype":"venue"
},
  "geometry": {"coordinates":[-90.40638800000001,37.781319],"type":"Point"}
}