{
  "type": "Feature",
  "properties": {
    "iso:country":"US",
    "sg:address":"13416 Garden Circle Ct",
    "sg:city":"Saint Louis",
    "sg:classifiers":[
        {
            "category":"Wholesale",
            "subcategory":"Furniture",
            "type":"Manufacturing & Wholesale Goods"
        }
    ],
    "sg:phone":"+1 314 843 8868",
    "sg:postcode":"63128",
    "sg:province":"MO",
    "wof:name":"Phan Anthony & Vanessa Nguyen",
    "wof:placetype":"venue"
},
  "geometry": {"coordinates":[-90.391631,38.481673],"type":"Point"}
}