{
  "type": "Feature",
  "properties": {
    "iso:country":"US",
    "sg:address":"1019 N Vandeventer St",
    "sg:city":"Kennett",
    "sg:classifiers":[
        {
            "category":"Education",
            "subcategory":"School",
            "type":"Public Place"
        }
    ],
    "sg:phone":"+1 573 717 1145",
    "sg:postcode":"63857",
    "sg:province":"MO",
    "wof:name":"Kennett Early Childhood School",
    "wof:placetype":"venue"
},
  "geometry": {"coordinates":[-90.060248,36.246916],"type":"Point"}
}