{
  "type": "Feature",
  "properties": {
    "iso:country":"US",
    "sg:address":"1 Insurance Center Plz",
    "sg:city":"Saint Louis",
    "sg:classifiers":[
        {
            "category":"Insurance",
            "subcategory":"Insurance Agent",
            "type":"Services"
        }
    ],
    "sg:phone":"+1 314 434 5663",
    "sg:postcode":"63141",
    "sg:province":"MO",
    "sg:tags":[
        "broker"
    ],
    "wof:name":"Advantage Insur Manager Lic",
    "wof:placetype":"venue"
},
  "geometry": {"coordinates":[-90.45376,38.671513],"type":"Point"}
}