{
  "type": "Feature",
  "properties": {
    "iso:country":"US",
    "sg:address":"11818 Borman Dr",
    "sg:city":"Saint Louis",
    "sg:classifiers":[
        {
            "category":"Wholesale",
            "subcategory":"Medical Equipment & Supplies",
            "type":"Manufacturing & Wholesale Goods"
        }
    ],
    "sg:phone":"+1 314 994 3020",
    "sg:postcode":"63146",
    "sg:province":"MO",
    "sg:tags":[
        "security"
    ],
    "wof:name":"Siemens",
    "wof:placetype":"venue"
},
  "geometry": {"coordinates":[-90.438081,38.693425],"type":"Point"}
}