{
  "type": "Feature",
  "properties": {
    "iso:country":"US",
    "sg:address":"2376 Cassens Dr",
    "sg:city":"Fenton",
    "sg:classifiers":[
        {
            "category":"Building & Trades",
            "subcategory":"Construction",
            "type":"Services"
        }
    ],
    "sg:phone":"+1 636 343 7000",
    "sg:postcode":"63026",
    "sg:province":"MO",
    "sg:tags":[
        "general",
        "contractor"
    ],
    "wof:name":"Eurostyle Inc",
    "wof:placetype":"venue"
},
  "geometry": {"coordinates":[-90.446894,38.554425],"type":"Point"}
}