{
  "type": "Feature",
  "properties": {
    "iso:country":"US",
    "sg:address":"6665 Olive Blvd",
    "sg:city":"Saint Louis",
    "sg:classifiers":[
        {
            "category":"Restaurant",
            "type":"Food & Drink"
        }
    ],
    "sg:phone":"+1 314 727 7057",
    "sg:postcode":"63130",
    "sg:province":"MO",
    "wof:name":"Queen of Sheba",
    "wof:placetype":"venue"
},
  "geometry": {"coordinates":[-90.306044,38.662884],"type":"Point"}
}