{
  "type": "Feature",
  "properties": {
    "iso:country":"US",
    "sg:address":"6555 Chippewa St Ste 200",
    "sg:city":"Saint Louis",
    "sg:classifiers":[
        {
            "category":"Health Services",
            "subcategory":"Doctor",
            "type":"Services"
        }
    ],
    "sg:phone":"+1 314 647 2555",
    "sg:postcode":"63109",
    "sg:province":"MO",
    "sg:tags":[
        "medicine",
        "internal"
    ],
    "wof:name":"Prager Simeon MD",
    "wof:placetype":"venue"
},
  "geometry": {"coordinates":[-90.303299,38.591801],"type":"Point"}
}