{
  "type": "Feature",
  "properties": {
    "iso:country":"US",
    "sg:address":"7 Arnold Mall",
    "sg:city":"Arnold",
    "sg:classifiers":[
        {
            "category":"Personal",
            "type":"Services"
        }
    ],
    "sg:phone":"+1 636 282 1211",
    "sg:postcode":"63010",
    "sg:province":"MO",
    "sg:tags":[
        "consulting",
        "management"
    ],
    "wof:name":"L A Weight Loss Centers",
    "wof:placetype":"venue"
},
  "geometry": {"coordinates":[-90.373491,38.444019],"type":"Point"}
}