{
  "type": "Feature",
  "properties": {
    "iso:country":"US",
    "sg:address":"400 S Madison St",
    "sg:city":"Strafford",
    "sg:classifiers":[
        {
            "category":"Organizations",
            "subcategory":"Religious Organization",
            "type":"Services"
        }
    ],
    "sg:phone":"+1 417 736 4448",
    "sg:postcode":"65757",
    "sg:province":"MO",
    "sg:tags":[
        "church"
    ],
    "wof:name":"First Baptist Church-Strafford",
    "wof:placetype":"venue"
},
  "geometry": {"coordinates":[-93.1169,37.2675],"type":"Point"}
}