{
  "type": "Feature",
  "properties": {
    "iso:country":"US",
    "sg:address":"2396 Highway A",
    "sg:city":"Washington",
    "sg:classifiers":[
        {
            "category":"Place Of Worship",
            "type":"Public Place"
        }
    ],
    "sg:phone":"+1 636 239 0021",
    "sg:postcode":"63090",
    "sg:province":"MO",
    "sg:tags":[
        "church"
    ],
    "wof:name":"Wellspring Wesleyan Church",
    "wof:placetype":"venue"
},
  "geometry": {"coordinates":[-91.020838,38.532622],"type":"Point"}
}