{
  "type": "Feature",
  "properties": {
    "iso:country":"US",
    "sg:address":"8006 Windsor Rd",
    "sg:city":"Kansas City",
    "sg:classifiers":[
        {
            "category":"Real Estate",
            "subcategory":"Real Estate Agent",
            "type":"Services"
        }
    ],
    "sg:phone":"+1 816 781 3668",
    "sg:postcode":"64167",
    "sg:province":"MO",
    "sg:tags":[
        "appraisal"
    ],
    "wof:name":"Professional Appraisals",
    "wof:placetype":"venue"
},
  "geometry": {"coordinates":[-94.48681000000001,39.32596],"type":"Point"}
}