{
  "type": "Feature",
  "properties": {
    "iso:country":"US",
    "sg:address":"8400 Pershall Rd",
    "sg:city":"Hazelwood",
    "sg:classifiers":[
        {
            "category":"Home & Garden",
            "subcategory":"Hardware",
            "type":"Retail Goods"
        }
    ],
    "sg:phone":"+1 314 524 8665",
    "sg:postcode":"63042",
    "sg:province":"MO",
    "sg:tags":[
        "tool",
        "used"
    ],
    "wof:name":"PSI Tools",
    "wof:placetype":"venue"
},
  "geometry": {"coordinates":[-90.33074499999999,38.774758],"type":"Point"}
}