{
  "type": "Feature",
  "properties": {
    "iso:country":"US",
    "sg:address":"11844 Tesson Ferry Rd",
    "sg:city":"Saint Louis",
    "sg:classifiers":[
        {
            "category":"Autos & Motor Vehicles",
            "subcategory":"Auto Supplies",
            "type":"Retail Goods"
        }
    ],
    "sg:phone":"+1 314 842 3566",
    "sg:postcode":"63128",
    "sg:province":"MO",
    "wof:name":"Dobbs Tire Center",
    "wof:placetype":"venue"
},
  "geometry": {"coordinates":[-90.362753,38.519842],"type":"Point"}
}