{
  "type": "Feature",
  "properties": {
    "iso:country":"US",
    "sg:address":"200 W Lone Jack Lees Summit Rd",
    "sg:city":"Lone Jack",
    "sg:classifiers":[
        {
            "category":"Organizations",
            "subcategory":"Religious Organization",
            "type":"Services"
        }
    ],
    "sg:phone":"+1 816 697 2370",
    "sg:postcode":"64070",
    "sg:province":"MO",
    "sg:tags":[
        "church"
    ],
    "wof:name":"Christian Church",
    "wof:placetype":"venue"
},
  "geometry": {"coordinates":[-94.174971,38.87225],"type":"Point"}
}