{
  "type": "Feature",
  "properties": {
    "iso:country":"US",
    "sg:address":"14190 Keepsake Rd",
    "sg:city":"Gravois Mills",
    "sg:classifiers":[
        {
            "category":"Retail",
            "subcategory":"Repair Shop",
            "type":"Services"
        }
    ],
    "sg:phone":"+1 573 372 2592",
    "sg:postcode":"65037",
    "sg:province":"MO",
    "wof:name":"Saw Doctor",
    "wof:placetype":"venue"
},
  "geometry": {"coordinates":[-92.816345,38.276161],"type":"Point"}
}