{
  "type": "Feature",
  "properties": {
    "iso:country":"US",
    "sg:address":"928 S Glenstone Ave",
    "sg:city":"Springfield",
    "sg:classifiers":[
        {
            "category":"Manufacturing",
            "subcategory":"Glass & Minerals",
            "type":"Manufacturing & Wholesale Goods"
        }
    ],
    "sg:phone":"+1 417 869 1501",
    "sg:postcode":"65804",
    "sg:province":"MO",
    "sg:tags":[
        "concrete",
        "brick"
    ],
    "wof:name":"Glenstone Block Co",
    "wof:placetype":"venue"
},
  "geometry": {"coordinates":[-93.261966,37.198175],"type":"Point"}
}