{
  "type": "Feature",
  "properties": {
    "iso:country":"US",
    "sg:address":"811 NW Cedar Creek Ln",
    "sg:city":"Lees Summit",
    "sg:classifiers":[
        {
            "category":"Building & Trades",
            "subcategory":"Construction",
            "type":"Services"
        }
    ],
    "sg:phone":"+1 816 765 8765",
    "sg:postcode":"64081",
    "sg:province":"MO",
    "sg:tags":[
        "contractor"
    ],
    "wof:name":"Hotle Drywall",
    "wof:placetype":"venue"
},
  "geometry": {"coordinates":[-94.441892,38.931593],"type":"Point"}
}