{
  "type": "Feature",
  "properties": {
    "iso:country":"US",
    "sg:address":"12977 N 40 Dr",
    "sg:city":"Saint Louis",
    "sg:classifiers":[
        {
            "category":"Insurance",
            "subcategory":"Insurance Agent",
            "type":"Services"
        }
    ],
    "sg:phone":"+1 314 542 0076",
    "sg:postcode":"63141",
    "sg:province":"MO",
    "sg:tags":[
        "agency",
        "general"
    ],
    "wof:name":"Heritage Financial Group Inc",
    "wof:placetype":"venue"
},
  "geometry": {"coordinates":[-90.47568800000001,38.638949],"type":"Point"}
}