{
  "type": "Feature",
  "properties": {
    "iso:country":"US",
    "sg:address":"12814 Strathearn Dr",
    "sg:city":"Saint Louis",
    "sg:classifiers":[
        {
            "category":"Professional",
            "type":"Services"
        }
    ],
    "sg:phone":"+1 314 576 6464",
    "sg:postcode":"63146",
    "sg:province":"MO",
    "wof:name":"Double Take Displays Inc",
    "wof:placetype":"venue"
},
  "geometry": {"coordinates":[-90.470761,38.695525],"type":"Point"}
}