{
  "type": "Feature",
  "properties": {
    "iso:country":"US",
    "sg:address":"528 E Main St",
    "sg:city":"Jackson",
    "sg:classifiers":[
        {
            "category":"Restaurant",
            "type":"Food & Drink"
        }
    ],
    "sg:phone":"+1 573 243 7740",
    "sg:postcode":"63755",
    "sg:province":"MO",
    "wof:name":"Delmonicos",
    "wof:placetype":"venue"
},
  "geometry": {"coordinates":[-89.662475,37.382056],"type":"Point"}
}