{
  "type": "Feature",
  "properties": {
    "iso:country":"US",
    "sg:address":"8714 Gravois Rd",
    "sg:city":"Saint Louis",
    "sg:classifiers":[
        {
            "category":"Insurance",
            "subcategory":"Insurance Agent",
            "type":"Services"
        }
    ],
    "sg:phone":"+1 314 631 6311",
    "sg:postcode":"63123",
    "sg:province":"MO",
    "wof:name":"Independent Brokers Agency",
    "wof:placetype":"venue"
},
  "geometry": {"coordinates":[-90.309877,38.556256],"type":"Point"}
}