{
  "type": "Feature",
  "properties": {
    "iso:country":"US",
    "sg:address":"1201 N Highway Dr",
    "sg:city":"Fenton",
    "sg:classifiers":[
        {
            "category":"Professional",
            "type":"Services"
        },
        {
            "category":"Manufacturing",
            "subcategory":"Wood Products",
            "type":"Manufacturing & Wholesale Goods"
        },
        {
            "category":"Manufacturing",
            "subcategory":"Paper Products",
            "type":"Manufacturing & Wholesale Goods"
        }
    ],
    "sg:phone":"+1 636 861 5400",
    "sg:postcode":"63026",
    "sg:province":"MO",
    "sg:tags":[
        "fiber-wholesale",
        "fiber",
        "materials-wholesale",
        "packaging",
        "boxes-corrugated",
        "boxes-folding-manufacturers",
        "manufacturer"
    ],
    "sg:website":"http://www.crockettcontainer.com",
    "wof:name":"Tin Inc.",
    "wof:placetype":"venue"
},
  "geometry": {"coordinates":[-90.469521,38.543301],"type":"Point"}
}