{
  "type": "Feature",
  "properties": {
    "iso:country":"US",
    "sg:address":"7025 St Charles Rock Rd",
    "sg:city":"Saint Louis",
    "sg:classifiers":[
        {
            "category":"Shopping",
            "subcategory":"Department Store",
            "type":"Retail Goods"
        }
    ],
    "sg:phone":"+1 314 727 0460",
    "sg:postcode":"63133",
    "sg:province":"MO",
    "wof:name":"Frison Flea Market Inc",
    "wof:placetype":"venue"
},
  "geometry": {"coordinates":[-90.302831,38.684546],"type":"Point"}
}