{
  "type": "Feature",
  "properties": {
    "iso:country":"US",
    "sg:address":"3125 E Jackson Blvd",
    "sg:city":"Jackson",
    "sg:classifiers":[
        {
            "category":"Fast Food",
            "type":"Food & Drink"
        },
        {
            "category":"Restaurant",
            "type":"Food & Drink"
        }
    ],
    "sg:phone":"+1 573 243 4400",
    "sg:postcode":"63755",
    "sg:province":"MO",
    "sg:tags":[
        "hot",
        "hamburger",
        "dog",
        "take"
    ],
    "sg:website":"http://www.huddlehouse.com/",
    "wof:name":"Huddle House",
    "wof:placetype":"venue"
},
  "geometry": {"coordinates":[-89.637253,37.366195],"type":"Point"}
}