{
  "type": "Feature",
  "properties": {
    "iso:country":"US",
    "sg:address":"130 Cedar Oak Dr",
    "sg:city":"Gainesville",
    "sg:classifiers":[
        {
            "category":"Home & Garden",
            "subcategory":"Building Materials",
            "type":"Retail Goods"
        }
    ],
    "sg:phone":"+1 417 679 3256",
    "sg:postcode":"65655",
    "sg:province":"MO",
    "wof:name":"Ozarks Vintage Timbers",
    "wof:placetype":"venue"
},
  "geometry": {"coordinates":[-92.42498500000001,36.610711],"type":"Point"}
}