{
  "type": "Feature",
  "properties": {
    "iso:country":"US",
    "sg:address":"110 N Jefferson St",
    "sg:city":"Mexico",
    "sg:classifiers":[
        {
            "category":"Shopping",
            "subcategory":"Hobbies, Toys, & Games",
            "type":"Retail Goods"
        }
    ],
    "sg:phone":"+1 573 581 6262",
    "sg:postcode":"65265",
    "sg:province":"MO",
    "sg:website":"www.stickywicketquilt.com",
    "wof:name":"Sticky Wicket",
    "wof:placetype":"venue"
},
  "geometry": {"coordinates":[-91.882493,39.172908],"type":"Point"}
}