{
  "type": "Feature",
  "properties": {
    "iso:country":"US",
    "sg:address":"3709 S Providence Rd C",
    "sg:city":"Columbia",
    "sg:classifiers":[
        {
            "category":"Restaurant",
            "type":"Food & Drink"
        }
    ],
    "sg:phone":"+1 573 256 8888",
    "sg:postcode":"65203",
    "sg:province":"MO",
    "sg:tags":[
        "style",
        "family"
    ],
    "wof:name":"Okii Mamas Inc",
    "wof:placetype":"venue"
},
  "geometry": {"coordinates":[-92.335391,38.910132],"type":"Point"}
}