{
  "type": "Feature",
  "properties": {
    "iso:country":"US",
    "sg:address":"201 E 21 Ave",
    "sg:city":"Kansas City",
    "sg:classifiers":[
        {
            "category":"Health Services",
            "subcategory":"Doctor",
            "type":"Services"
        }
    ],
    "sg:phone":"+1 816 842 2235",
    "sg:postcode":"64116",
    "sg:province":"MO",
    "wof:name":"McConnell JAS L",
    "wof:placetype":"venue"
},
  "geometry": {"coordinates":[-94.577275,39.143842],"type":"Point"}
}