{
  "type": "Feature",
  "properties": {
    "iso:country":"US",
    "sg:address":"4800 S Limit Ave",
    "sg:city":"Sedalia",
    "sg:classifiers":[
        {
            "category":"Autos & Motor Vehicles",
            "subcategory":"Automobile Sales",
            "type":"Retail Goods"
        }
    ],
    "sg:phone":"+1 660 827 6760",
    "sg:postcode":"65301",
    "sg:province":"MO",
    "sg:tags":[
        "dealers-used",
        "used",
        "cars-wholesale",
        "car"
    ],
    "wof:name":"Taylor Car Connection",
    "wof:placetype":"venue"
},
  "geometry": {"coordinates":[-93.251856,38.669346],"type":"Point"}
}