{
  "type": "Feature",
  "properties": {
    "iso:country":"US",
    "sg:address":"148 Tulip Tree Dr",
    "sg:city":"Saint Charles",
    "sg:classifiers":[
        {
            "category":"Building & Trades",
            "subcategory":"Landscaping Services",
            "type":"Services"
        }
    ],
    "sg:phone":"+1 636 936 8874",
    "sg:postcode":"63304",
    "sg:province":"MO",
    "wof:name":"1st Choice Lawn Service Inc",
    "wof:placetype":"venue"
},
  "geometry": {"coordinates":[-90.610141,38.753199],"type":"Point"}
}