{
  "type": "Feature",
  "properties": {
    "iso:country":"US",
    "sg:address":"650 W Arrow St",
    "sg:city":"Marshall",
    "sg:classifiers":[
        {
            "category":"Organizations",
            "subcategory":"Religious Organization",
            "type":"Services"
        }
    ],
    "sg:phone":"+1 660 886 2695",
    "sg:postcode":"65340",
    "sg:province":"MO",
    "wof:name":"Seventh Day Adventist Church",
    "wof:placetype":"venue"
},
  "geometry": {"coordinates":[-93.204836,39.12037],"type":"Point"}
}