{
  "type": "Feature",
  "properties": {
    "iso:country":"US",
    "sg:address":"126 S County Center Way",
    "sg:city":"St Louis",
    "sg:classifiers":[
        {
            "category":"Shopping",
            "subcategory":"Bicycles & Sporting Goods",
            "type":"Retail Goods"
        }
    ],
    "sg:phone":"+1 314 892 5885",
    "sg:postcode":"63129",
    "sg:province":"MO",
    "sg:tags":[
        "equipment",
        "golf",
        "supply"
    ],
    "wof:name":"Golf Discount of St Louis Inc",
    "wof:placetype":"venue"
},
  "geometry": {"coordinates":[-90.328912,38.504495],"type":"Point"}
}