{
  "type": "Feature",
  "properties": {
    "iso:country":"US",
    "sg:address":"94 S Madison Ave",
    "sg:city":"Aurora",
    "sg:classifiers":[
        {
            "category":"Farming",
            "subcategory":"Farm",
            "type":"Manufacturing & Wholesale Goods"
        }
    ],
    "sg:phone":"+1 417 847 6872",
    "sg:postcode":"65605",
    "sg:province":"MO",
    "wof:name":"Triple D Farm",
    "wof:placetype":"venue"
},
  "geometry": {"coordinates":[-93.720898,36.974773],"type":"Point"}
}