{
  "type": "Feature",
  "properties": {
    "iso:country":"US",
    "sg:address":"930 S Campbell Ave",
    "sg:city":"Springfield",
    "sg:classifiers":[
        {
            "category":"Real Estate",
            "subcategory":"Real Estate Operator",
            "type":"Services"
        }
    ],
    "sg:phone":"+1 417 864 6455",
    "sg:postcode":"65806",
    "sg:province":"MO",
    "sg:tags":[
        "building",
        "apartment"
    ],
    "wof:name":"Windsor Court",
    "wof:placetype":"venue"
},
  "geometry": {"coordinates":[-93.294467,37.19741],"type":"Point"}
}