{
  "type": "Feature",
  "properties": {
    "iso:country":"US",
    "sg:address":"500 W Main St",
    "sg:city":"Wentzville",
    "sg:classifiers":[
        {
            "category":"Organizations",
            "subcategory":"Non-profit Organization",
            "type":"Services"
        }
    ],
    "sg:phone":"+1 636 327 6358",
    "sg:postcode":"63385",
    "sg:province":"MO",
    "sg:tags":[
        "development",
        "neighborhood",
        "group"
    ],
    "wof:name":"Wentzville Community Club",
    "wof:placetype":"venue"
},
  "geometry": {"coordinates":[-90.861789,38.809221],"type":"Point"}
}