{
  "type": "Feature",
  "properties": {
    "iso:country":"US",
    "sg:address":"706 N Ault St",
    "sg:city":"Moberly",
    "sg:classifiers":[
        {
            "category":"Building & Trades",
            "subcategory":"Construction",
            "type":"Services"
        }
    ],
    "sg:phone":"+1 660 263 1968",
    "sg:postcode":"65270",
    "sg:province":"MO",
    "sg:tags":[
        "nonresidential"
    ],
    "wof:name":"Rays Custom Service",
    "wof:placetype":"venue"
},
  "geometry": {"coordinates":[-92.43450900000001,39.426795],"type":"Point"}
}