{
  "type": "Feature",
  "properties": {
    "iso:country":"US",
    "sg:address":"711 E Walnut St",
    "sg:city":"Raymore",
    "sg:classifiers":[
        {
            "category":"Real Estate",
            "subcategory":"Real Estate Services",
            "type":"Services"
        },
        {
            "category":"Real Estate",
            "subcategory":"Real Estate Agent",
            "type":"Services"
        }
    ],
    "sg:phone":"+1 816 331 4500",
    "sg:postcode":"64083",
    "sg:province":"MO",
    "sg:tags":[
        "buyer",
        "broker"
    ],
    "wof:name":"Grace Land Realty Co",
    "wof:placetype":"venue"
},
  "geometry": {"coordinates":[-94.456352,38.804119],"type":"Point"}
}