{
  "type": "Feature",
  "properties": {
    "iso:country":"US",
    "sg:address":"627 Butler Dr",
    "sg:city":"Eureka",
    "sg:classifiers":[
        {
            "category":"Banks & Credit Unions",
            "subcategory":"Financial Services",
            "type":"Services"
        }
    ],
    "sg:phone":"+1 636 938 6693",
    "sg:postcode":"63025",
    "sg:province":"MO",
    "sg:tags":[
        "investor"
    ],
    "wof:name":"Eureka Investment Club",
    "wof:placetype":"venue"
},
  "geometry": {"coordinates":[-90.638767,38.497132],"type":"Point"}
}