{
  "type": "Feature",
  "properties": {
    "iso:country":"US",
    "sg:address":"12882 Manchester Rd",
    "sg:city":"St Louis",
    "sg:classifiers":[
        {
            "category":"Professional",
            "subcategory":"Computer Services",
            "type":"Services"
        }
    ],
    "sg:phone":"+1 314 984 9511",
    "sg:postcode":"63131",
    "sg:province":"MO",
    "sg:tags":[
        "consultant",
        "designer",
        "programing",
        "custom"
    ],
    "sg:website":"www.lawrenceinc.com",
    "wof:name":"Lawrence & Associates Inc",
    "wof:placetype":"venue"
},
  "geometry": {"coordinates":[-90.45781599999999,38.602056],"type":"Point"}
}