{
  "type": "Feature",
  "properties": {
    "iso:country":"US",
    "sg:address":"23015 Range Ln",
    "sg:city":"Richland",
    "sg:classifiers":[
        {
            "category":"Farming",
            "subcategory":"Farm",
            "type":"Manufacturing & Wholesale Goods"
        }
    ],
    "sg:phone":"+1 573 765 3897",
    "sg:postcode":"65556",
    "sg:province":"MO",
    "sg:tags":[
        "crop",
        "general"
    ],
    "wof:name":"Dennis Kays",
    "wof:placetype":"venue"
},
  "geometry": {"coordinates":[-92.385644,37.830673],"type":"Point"}
}