{
  "type": "Feature",
  "properties": {
    "iso:country":"US",
    "sg:address":"522 Locust Ln",
    "sg:city":"Kansas City",
    "sg:classifiers":[
        {
            "category":"Recreation",
            "type":"Entertainment"
        }
    ],
    "sg:phone":"+1 816 221 3399",
    "sg:postcode":"64106",
    "sg:province":"MO",
    "sg:tags":[
        "tours",
        "sightseeing"
    ],
    "wof:name":"Kansas City Trolley Corp",
    "wof:placetype":"venue"
},
  "geometry": {"coordinates":[-94.57781,39.108433],"type":"Point"}
}