{
  "type": "Feature",
  "properties": {
    "iso:country":"US",
    "sg:address":"4833 Sunrise Dr",
    "sg:city":"Jefferson City",
    "sg:classifiers":[
        {
            "category":"Social Services",
            "subcategory":"Job Training",
            "type":"Services"
        }
    ],
    "sg:phone":"+1 573 526 9132",
    "sg:postcode":"65101",
    "sg:province":"MO",
    "wof:name":"Gliniecki Dante",
    "wof:placetype":"venue"
},
  "geometry": {"coordinates":[-92.058273,38.511577],"type":"Point"}
}