{
  "type": "Feature",
  "properties": {
    "iso:country":"US",
    "sg:address":"1819 SW Market St",
    "sg:city":"Lees Summit",
    "sg:classifiers":[
        {
            "category":"Building & Trades",
            "subcategory":"Construction",
            "type":"Services"
        }
    ],
    "sg:phone":"+1 816 000 1111",
    "sg:postcode":"64082",
    "sg:province":"MO",
    "sg:tags":[
        "fire",
        "restoration",
        "damage"
    ],
    "wof:name":"Munters Moisture Control Svc",
    "wof:placetype":"venue"
},
  "geometry": {"coordinates":[-94.374509,38.886904],"type":"Point"}
}