{
  "type": "Feature",
  "properties": {
    "iso:country":"US",
    "sg:address":"119 N Sycamore St",
    "sg:city":"Branson",
    "sg:classifiers":[
        {
            "category":"Building & Trades",
            "subcategory":"Plumbing",
            "type":"Services"
        }
    ],
    "sg:phone":"+1 417 334 1277",
    "sg:postcode":"65616",
    "sg:province":"MO",
    "sg:tags":[
        "plumber"
    ],
    "wof:name":"A -Rite Plumbing",
    "wof:placetype":"venue"
},
  "geometry": {"coordinates":[-93.21578,36.644152],"type":"Point"}
}