{
  "type": "Feature",
  "properties": {
    "iso:country":"US",
    "sg:address":"382 Festus Centre Dr",
    "sg:city":"Festus",
    "sg:classifiers":[
        {
            "category":"Personal",
            "subcategory":"Beauty Salon",
            "type":"Services"
        }
    ],
    "sg:phone":"+1 636 933 0730",
    "sg:postcode":"63028",
    "sg:province":"MO",
    "sg:tags":[
        "shop",
        "manicuring"
    ],
    "wof:name":"Jimmy's Nails",
    "wof:placetype":"venue"
},
  "geometry": {"coordinates":[-90.39542400000001,38.212777],"type":"Point"}
}