{
  "type": "Feature",
  "properties": {
    "iso:country":"US",
    "sg:address":"4271 Glendale Rd",
    "sg:city":"House Springs",
    "sg:classifiers":[
        {
            "category":"Professional",
            "type":"Services"
        }
    ],
    "sg:phone":"+1 636 671 1102",
    "sg:postcode":"63051",
    "sg:province":"MO",
    "wof:name":"Dragonfly Kiln Works",
    "wof:placetype":"venue"
},
  "geometry": {"coordinates":[-90.56366300000001,38.42541],"type":"Point"}
}