{
  "type": "Feature",
  "properties": {
    "iso:country":"US",
    "sg:address":"144 Parrish",
    "sg:city":"Fort Leonard Wood",
    "sg:classifiers":[
        {
            "category":"Social Services",
            "subcategory":"Child Care",
            "type":"Services"
        }
    ],
    "sg:phone":"+1 573 329 5486",
    "sg:postcode":"65473",
    "sg:province":"MO",
    "wof:name":"Pass-Gaither Tabatha",
    "wof:placetype":"venue"
},
  "geometry": {"coordinates":[-92.128638,37.773426],"type":"Point"}
}