{
  "type": "Feature",
  "properties": {
    "iso:country":"US",
    "sg:address":"1165 E Cherry St",
    "sg:city":"Troy",
    "sg:classifiers":[
        {
            "category":"Social Services",
            "subcategory":"Child Care",
            "type":"Services"
        }
    ],
    "sg:phone":"+1 636 528 2900",
    "sg:postcode":"63379",
    "sg:province":"MO",
    "wof:name":"Precious Memories 24 Hr Lrnng",
    "wof:placetype":"venue"
},
  "geometry": {"coordinates":[-90.956588,38.985096],"type":"Point"}
}