{
  "type": "Feature",
  "properties": {
    "iso:country":"US",
    "sg:address":"104 Old US Hwy 40",
    "sg:city":"O Fallon",
    "sg:classifiers":[
        {
            "category":"Shopping",
            "type":"Retail Goods"
        }
    ],
    "sg:phone":"+1 636 272 4847",
    "sg:postcode":"63366",
    "sg:province":"MO",
    "sg:tags":[
        "bird"
    ],
    "wof:name":"Jungleland Pets",
    "wof:placetype":"venue"
},
  "geometry": {"coordinates":[-90.69991899999999,38.80026],"type":"Point"}
}