{
  "type": "Feature",
  "properties": {
    "iso:country":"US",
    "sg:address":"1052 Cassens Industrial Ct",
    "sg:city":"Fenton",
    "sg:classifiers":[
        {
            "category":"Wholesale",
            "subcategory":"Medical Equipment & Supplies",
            "type":"Manufacturing & Wholesale Goods"
        }
    ],
    "sg:phone":"+1 636 305 2779",
    "sg:postcode":"63026",
    "sg:province":"MO",
    "sg:tags":[
        "hospital"
    ],
    "wof:name":"Mediq PRN",
    "wof:placetype":"venue"
},
  "geometry": {"coordinates":[-90.44855,38.555591],"type":"Point"}
}