{
  "type": "Feature",
  "properties": {
    "iso:country":"US",
    "sg:address":"15575 S Hwy 39",
    "sg:city":"Stockton",
    "sg:classifiers":[
        {
            "category":"Manufacturing",
            "subcategory":"Retail Goods",
            "type":"Manufacturing & Wholesale Goods"
        }
    ],
    "sg:phone":"+1 417 276 4116",
    "sg:postcode":"65785",
    "sg:province":"MO",
    "sg:tags":[
        "broom",
        "brush"
    ],
    "sg:website":"www.joycebrush.com",
    "wof:name":"Joyce Brush Co",
    "wof:placetype":"venue"
},
  "geometry": {"coordinates":[-93.812326,37.671397],"type":"Point"}
}