{
  "type": "Feature",
  "properties": {
    "iso:country":"US",
    "sg:address":"58948 Molly Branch Rd",
    "sg:city":"Russellville",
    "sg:classifiers":[
        {
            "category":"Building & Trades",
            "subcategory":"Construction",
            "type":"Services"
        }
    ],
    "sg:phone":"+1 660 489 2205",
    "sg:postcode":"65074",
    "sg:province":"MO",
    "sg:tags":[
        "precast",
        "concrete",
        "park",
        "furniture"
    ],
    "wof:name":"American Park & Recrtl Lsg",
    "wof:placetype":"venue"
},
  "geometry": {"coordinates":[-92.550957,38.516991],"type":"Point"}
}