{
  "type": "Feature",
  "properties": {
    "iso:country":"US",
    "sg:address":"6824 E County Line Rd",
    "sg:city":"Rogersville",
    "sg:classifiers":[
        {
            "category":"Building & Trades",
            "subcategory":"Landscaping Services",
            "type":"Services"
        }
    ],
    "sg:phone":"+1 417 753 7594",
    "sg:postcode":"65742",
    "sg:province":"MO",
    "sg:tags":[
        "tree"
    ],
    "wof:name":"Phelps Robert G Jr Abc Tree & Crane Service",
    "wof:placetype":"venue"
},
  "geometry": {"coordinates":[-93.109425,37.089545],"type":"Point"}
}