{
  "type": "Feature",
  "properties": {
    "iso:country":"US",
    "sg:address":"4357 W William St",
    "sg:city":"Battlefield",
    "sg:classifiers":[
        {
            "category":"Building & Trades",
            "subcategory":"Construction",
            "type":"Services"
        }
    ],
    "sg:phone":"+1 417 883 3241",
    "sg:postcode":"65619",
    "sg:province":"MO",
    "sg:tags":[
        "wallcoverings-installation",
        "wallpaper",
        "painting",
        "contractor"
    ],
    "wof:name":"Hamilton Painting",
    "wof:placetype":"venue"
},
  "geometry": {"coordinates":[-93.371592,37.126695],"type":"Point"}
}