{
  "type": "Feature",
  "properties": {
    "iso:country":"US",
    "sg:address":"2210 State Hwy 291",
    "sg:city":"Independence",
    "sg:classifiers":[
        {
            "category":"Wholesale",
            "subcategory":"Farm Supplies",
            "type":"Manufacturing & Wholesale Goods"
        },
        {
            "category":"Home & Garden",
            "subcategory":"Garden Supply",
            "type":"Retail Goods"
        }
    ],
    "sg:phone":"+1 816 461 7333",
    "sg:postcode":"64057",
    "sg:province":"MO",
    "sg:website":"www.mytscstore.com",
    "wof:name":"Tractor Supply Co",
    "wof:placetype":"venue"
},
  "geometry": {"coordinates":[-94.37926400000001,39.078797],"type":"Point"}
}