{
  "type": "Feature",
  "properties": {
    "iso:country":"US",
    "sg:address":"6411 Evanston Ave",
    "sg:city":"Raytown",
    "sg:classifiers":[
        {
            "category":"Building & Trades",
            "subcategory":"Landscaping Services",
            "type":"Services"
        }
    ],
    "sg:phone":"+1 816 353 3950",
    "sg:postcode":"64133",
    "sg:province":"MO",
    "sg:tags":[
        "tree"
    ],
    "wof:name":"Ray Town Tree Service",
    "wof:placetype":"venue"
},
  "geometry": {"coordinates":[-94.46769,39.007271],"type":"Point"}
}