{
  "type": "Feature",
  "properties": {
    "iso:country":"US",
    "sg:address":"5425 S Grand Blvd",
    "sg:city":"Saint Louis",
    "sg:classifiers":[
        {
            "category":"Restaurant",
            "type":"Food & Drink"
        }
    ],
    "sg:phone":"+1 314 352 0202",
    "sg:postcode":"63111",
    "sg:province":"MO",
    "sg:tags":[
        "mexican"
    ],
    "wof:name":"Chimichanga's Mexican Restaurant",
    "wof:placetype":"venue"
},
  "geometry": {"coordinates":[-90.25309799999999,38.569901],"type":"Point"}
}