{
  "type": "Feature",
  "properties": {
    "iso:country":"US",
    "sg:address":"7700 N Broadway",
    "sg:city":"St Louis",
    "sg:classifiers":[
        {
            "category":"Autos & Motor Vehicles",
            "subcategory":"Automobile Sales",
            "type":"Retail Goods"
        }
    ],
    "sg:phone":"+1 314 381 6268",
    "sg:postcode":"63147",
    "sg:province":"MO",
    "sg:tags":[
        "car",
        "used",
        "dealer"
    ],
    "wof:name":"G & M Motors",
    "wof:placetype":"venue"
},
  "geometry": {"coordinates":[-90.23012,38.705301],"type":"Point"}
}