{
  "type": "Feature",
  "properties": {
    "iso:country":"US",
    "sg:address":"7304 Sni A Bar Rd",
    "sg:city":"Kansas City",
    "sg:classifiers":[
        {
            "category":"Organizations",
            "subcategory":"Religious Organization",
            "type":"Services"
        }
    ],
    "sg:phone":"+1 816 921 2235",
    "sg:postcode":"64129",
    "sg:province":"MO",
    "sg:tags":[
        "church"
    ],
    "wof:name":"Full Face Christian Ctr",
    "wof:placetype":"venue"
},
  "geometry": {"coordinates":[-94.499042,39.036213],"type":"Point"}
}