{
  "type": "Feature",
  "properties": {
    "iso:country":"US",
    "sg:address":"2123 E 16 St",
    "sg:city":"Kansas City",
    "sg:classifiers":[
        {
            "category":"Shopping",
            "subcategory":"Clothing, Apparel, & Fashions",
            "type":"Retail Goods"
        }
    ],
    "sg:phone":"+1 816 474 4161",
    "sg:postcode":"64127",
    "sg:province":"MO",
    "wof:name":"Cultural Beauty & Bridal Bouti",
    "wof:placetype":"venue"
},
  "geometry": {"coordinates":[-94.556546,39.092872],"type":"Point"}
}