{
  "type": "Feature",
  "properties": {
    "iso:country":"US",
    "sg:address":"3423 Montana St",
    "sg:city":"Saint Louis",
    "sg:classifiers":[
        {
            "category":"Manufacturing",
            "subcategory":"Glass & Minerals",
            "type":"Manufacturing & Wholesale Goods"
        }
    ],
    "sg:phone":"+1 314 678 0856",
    "sg:postcode":"63118",
    "sg:province":"MO",
    "sg:tags":[
        "product",
        "mfg"
    ],
    "wof:name":"Creative Glass Ltd",
    "wof:placetype":"venue"
},
  "geometry": {"coordinates":[-90.243807,38.583697],"type":"Point"}
}