{
  "type": "Feature",
  "properties": {
    "iso:country":"US",
    "sg:address":"11710 W 23rd St S",
    "sg:city":"Independence",
    "sg:classifiers":[
        {
            "category":"Autos & Motor Vehicles",
            "subcategory":"Auto Supplies",
            "type":"Retail Goods"
        }
    ],
    "sg:phone":"+1 816 836 3363",
    "sg:postcode":"64050",
    "sg:province":"MO",
    "wof:name":"Advance Stores Company Inc",
    "wof:placetype":"venue"
},
  "geometry": {"coordinates":[-94.437392,39.08008],"type":"Point"}
}