{
  "type": "Feature",
  "properties": {
    "iso:country":"US",
    "sg:address":"1749 Independence St",
    "sg:city":"Cape Girardeau",
    "sg:classifiers":[
        {
            "category":"Health Services",
            "subcategory":"Doctor",
            "type":"Services"
        }
    ],
    "sg:phone":"+1 573 335 6854",
    "sg:postcode":"63703",
    "sg:province":"MO",
    "wof:name":"Hall Diane",
    "wof:placetype":"venue"
},
  "geometry": {"coordinates":[-89.54329199999999,37.305923],"type":"Point"}
}