{
  "type": "Feature",
  "properties": {
    "iso:country":"US",
    "sg:address":"6403 Clemens Ave",
    "sg:city":"St Louis",
    "sg:classifiers":[
        {
            "category":"Health Services",
            "subcategory":"Clinic",
            "type":"Services"
        }
    ],
    "sg:phone":"+1 314 721 7557",
    "sg:postcode":"63130",
    "sg:province":"MO",
    "wof:name":"Center For Immigrant Health",
    "wof:placetype":"venue"
},
  "geometry": {"coordinates":[-90.303513,38.658945],"type":"Point"}
}