{
  "type": "Feature",
  "properties": {
    "iso:country":"US",
    "sg:address":"7 Golden Wheat Ct",
    "sg:city":"Saint Charles",
    "sg:classifiers":[
        {
            "category":"Manufacturing",
            "subcategory":"Tools & Machinery",
            "type":"Manufacturing & Wholesale Goods"
        }
    ],
    "sg:phone":"+1 636 928 9493",
    "sg:postcode":"63304",
    "sg:province":"MO",
    "sg:tags":[
        "mfg",
        "ophthalmic"
    ],
    "wof:name":"Wesley-Jessen Inc",
    "wof:placetype":"venue"
},
  "geometry": {"coordinates":[-90.606646,38.7224],"type":"Point"}
}