{
  "type": "Feature",
  "properties": {
    "iso:country":"US",
    "sg:address":"215 US Highway 60 W",
    "sg:city":"Republic",
    "sg:classifiers":[
        {
            "category":"Insurance",
            "subcategory":"Insurance Agent",
            "type":"Services"
        },
        {
            "category":"Insurance",
            "subcategory":"Hazard Insurance",
            "type":"Services"
        },
        {
            "category":"Insurance",
            "subcategory":"Title Insurance",
            "type":"Services"
        },
        {
            "category":"Insurance",
            "subcategory":"Life Insurance",
            "type":"Services"
        }
    ],
    "sg:phone":"+1 417 732 1491",
    "sg:postcode":"65738",
    "sg:province":"MO",
    "sg:tags":[
        "business",
        "auto",
        "commercial",
        "homeowner",
        "motorcycle",
        "renter"
    ],
    "wof:name":"Allstate Insurance Company - Mark Mccully",
    "wof:placetype":"venue"
},
  "geometry": {"coordinates":[-93.447304,37.13773],"type":"Point"}
}