{
  "type": "Feature",
  "properties": {
    "iso:country":"US",
    "sg:address":"2314 NW Vivion Rd",
    "sg:city":"Northmoor",
    "sg:classifiers":[
        {
            "category":"Shopping",
            "subcategory":"Clothing, Apparel, & Fashions",
            "type":"Retail Goods"
        }
    ],
    "sg:phone":"+1 816 505 1615",
    "sg:postcode":"64150",
    "sg:province":"MO",
    "sg:tags":[
        "clothing",
        "boys'"
    ],
    "wof:name":"The Chess Club",
    "wof:placetype":"venue"
},
  "geometry": {"coordinates":[-94.605845,39.180365],"type":"Point"}
}