{
  "type": "Feature",
  "properties": {
    "iso:country":"US",
    "sg:address":"10019 Watson Rd",
    "sg:city":"Saint Louis",
    "sg:classifiers":[
        {
            "category":"Health Services",
            "subcategory":"Chiropractor",
            "type":"Services"
        }
    ],
    "sg:phone":"+1 314 835 1234",
    "sg:postcode":"63126",
    "sg:province":"MO",
    "wof:name":"David Lask DC",
    "wof:placetype":"venue"
},
  "geometry": {"coordinates":[-90.397415,38.556221],"type":"Point"}
}