{
  "type": "Feature",
  "properties": {
    "iso:country":"US",
    "sg:address":"179 Glossip Ave",
    "sg:city":"Highlandville",
    "sg:classifiers":[
        {
            "category":"Food & Beverages",
            "subcategory":"Groceries & Convenience Stores",
            "type":"Retail Goods"
        }
    ],
    "sg:phone":"+1 417 443 3848",
    "sg:postcode":"65669",
    "sg:province":"MO",
    "wof:name":"Underwoods Store 3",
    "wof:placetype":"venue"
},
  "geometry": {"coordinates":[-93.284499,36.9273],"type":"Point"}
}