{
  "type": "Feature",
  "properties": {
    "iso:country":"US",
    "sg:address":"224 E Chestnut St",
    "sg:city":"Springfield",
    "sg:classifiers":[
        {
            "category":"Professional",
            "subcategory":"Testing Lab",
            "type":"Services"
        }
    ],
    "sg:phone":"+1 417 831 1340",
    "sg:postcode":"65806",
    "sg:province":"MO",
    "sg:tags":[
        "laboratory"
    ],
    "wof:name":"Nicholas Seed Testing",
    "wof:placetype":"venue"
},
  "geometry": {"coordinates":[-93.29142400000001,37.214969],"type":"Point"}
}