{
  "type": "Feature",
  "properties": {
    "iso:country":"US",
    "sg:address":"1138 W Division St",
    "sg:city":"Springfield",
    "sg:classifiers":[
        {
            "category":"Shopping",
            "subcategory":"Clothing, Apparel, & Fashions",
            "type":"Retail Goods"
        }
    ],
    "sg:phone":"+1 417 866 9300",
    "sg:postcode":"65803",
    "sg:province":"MO",
    "wof:name":"Joans Bridal Shoppe",
    "wof:placetype":"venue"
},
  "geometry": {"coordinates":[-93.30531499999999,37.226181],"type":"Point"}
}