{
  "type": "Feature",
  "properties": {
    "iso:country":"US",
    "sg:address":"9633 SW Gridley Rd",
    "sg:city":"Clarksdale",
    "sg:classifiers":[
        {
            "category":"Farming",
            "subcategory":"Farm",
            "type":"Manufacturing & Wholesale Goods"
        }
    ],
    "sg:phone":"+1 816 393 5507",
    "sg:postcode":"64430",
    "sg:province":"MO",
    "wof:name":"Ishmael Farms",
    "wof:placetype":"venue"
},
  "geometry": {"coordinates":[-94.53719700000001,39.805755],"type":"Point"}
}