{
  "type": "Feature",
  "properties": {
    "iso:country":"US",
    "sg:address":"414 E 12th St",
    "sg:city":"Kansas City",
    "sg:classifiers":[
        {
            "category":"Government",
            "subcategory":"Office",
            "type":"Public Place"
        }
    ],
    "sg:phone":"+1 816 513 3300",
    "sg:postcode":"64106",
    "sg:province":"MO",
    "sg:tags":[
        "policy"
    ],
    "wof:name":"Auditor Office of",
    "wof:placetype":"venue"
},
  "geometry": {"coordinates":[-94.577527,39.099804],"type":"Point"}
}