{
  "type": "Feature",
  "properties": {
    "addr:full":"4185 Crescent Dr St Louis MO 63129",
    "addr:housenumber":"4185",
    "addr:postcode":"63129",
    "addr:street":"Crescent Dr",
    "iso:country":"US",
    "sg:address":"4185 Crescent Dr",
    "sg:city":"St Louis",
    "sg:classifiers":[
        {
            "category":"Insurance",
            "subcategory":"Insurance Agent",
            "type":"Services"
        }
    ],
    "sg:phone":"+1 314 487 6508",
    "sg:postcode":"63129",
    "sg:province":"MO",
    "wof:name":"Thrivent Financial-Lutherans",
    "wof:placetype":"venue"
},
  "geometry": {"coordinates":[-90.333859,38.509852],"type":"Point"}
}