{
  "type": "Feature",
  "properties": {
    "iso:country":"US",
    "sg:address":"1306 Hathman Pl",
    "sg:city":"Columbia",
    "sg:classifiers":[
        {
            "category":"Wholesale",
            "subcategory":"Beer",
            "type":"Manufacturing & Wholesale Goods"
        }
    ],
    "sg:phone":"+1 573 874 4100",
    "sg:postcode":"65201",
    "sg:province":"MO",
    "wof:name":"N H Scheppers Distributing Co",
    "wof:placetype":"venue"
},
  "geometry": {"coordinates":[-92.308881,38.966439],"type":"Point"}
}