{
  "type": "Feature",
  "properties": {
    "iso:country":"US",
    "sg:address":"314 N 5th St",
    "sg:city":"Moberly",
    "sg:classifiers":[
        {
            "category":"Place Of Worship",
            "subcategory":"Church",
            "type":"Public Place"
        },
        {
            "category":"Place Of Worship",
            "type":"Public Place"
        },
        {
            "category":"Organizations",
            "subcategory":"Religious Organization",
            "type":"Services"
        }
    ],
    "sg:phone":"+1 660 263 6160",
    "sg:postcode":"65270",
    "sg:province":"MO",
    "sg:tags":[
        "churches-baptist-general",
        "churches-baptist"
    ],
    "wof:name":"Second Baptist Church",
    "wof:placetype":"venue"
},
  "geometry": {"coordinates":[-92.44140299999999,39.420963],"type":"Point"}
}