{
  "type": "Feature",
  "properties": {
    "iso:country":"US",
    "sg:address":"2625 S Belt Hwy",
    "sg:city":"St Joseph",
    "sg:classifiers":[
        {
            "category":"Food & Beverages",
            "subcategory":"Groceries & Convenience Stores",
            "type":"Retail Goods"
        }
    ],
    "sg:phone":"+1 816 232 4828",
    "sg:postcode":"64503",
    "sg:province":"MO",
    "wof:name":"Fastgas Co",
    "wof:placetype":"venue"
},
  "geometry": {"coordinates":[-94.801321,39.7436],"type":"Point"}
}