{
  "type": "Feature",
  "properties": {
    "iso:country":"US",
    "sg:address":"2132 N Broadway Ave",
    "sg:city":"Springfield",
    "sg:classifiers":[
        {
            "category":"Retail",
            "subcategory":"Auto Repair",
            "type":"Services"
        }
    ],
    "sg:phone":"+1 417 832 1346",
    "sg:postcode":"65803",
    "sg:province":"MO",
    "sg:tags":[
        "general"
    ],
    "wof:name":"Christian Dreams Inc",
    "wof:placetype":"venue"
},
  "geometry": {"coordinates":[-93.302165,37.236499],"type":"Point"}
}