{
  "type": "Feature",
  "properties": {
    "iso:country":"US",
    "sg:address":"2208 W Main St",
    "sg:city":"Sedalia",
    "sg:classifiers":[
        {
            "category":"Building & Trades",
            "subcategory":"Construction",
            "type":"Services"
        }
    ],
    "sg:phone":"+1 660 826 7187",
    "sg:postcode":"65301",
    "sg:province":"MO",
    "wof:name":"Highway Dept",
    "wof:placetype":"venue"
},
  "geometry": {"coordinates":[-93.253156,38.71387],"type":"Point"}
}