{
  "type": "Feature",
  "properties": {
    "iso:country":"US",
    "sg:address":"328 Memory Ln",
    "sg:city":"Seymour",
    "sg:classifiers":[
        {
            "category":"Autos & Motor Vehicles",
            "subcategory":"Automobile Sales",
            "type":"Retail Goods"
        }
    ],
    "sg:phone":"+1 417 935 4999",
    "sg:postcode":"65746",
    "sg:province":"MO",
    "sg:tags":[
        "car",
        "used",
        "dealer"
    ],
    "sg:website":"www.drivindreams.com",
    "wof:name":"Drivin' Dreams",
    "wof:placetype":"venue"
},
  "geometry": {"coordinates":[-92.710249,37.127845],"type":"Point"}
}