{
  "type": "Feature",
  "properties": {
    "iso:country":"US",
    "sg:address":"3176 Hampton Ave",
    "sg:city":"St Louis",
    "sg:classifiers":[
        {
            "category":"Professional",
            "subcategory":"Lawyer & Legal Services",
            "type":"Services"
        }
    ],
    "sg:phone":"+1 314 481 2886",
    "sg:postcode":"63139",
    "sg:province":"MO",
    "sg:tags":[
        "attorney"
    ],
    "wof:name":"Thomas E Bauer Law Office",
    "wof:placetype":"venue"
},
  "geometry": {"coordinates":[-90.29065300000001,38.604824],"type":"Point"}
}