{
  "type": "Feature",
  "properties": {
    "iso:country":"US",
    "sg:address":"3812 S Cox Rd",
    "sg:city":"Springfield",
    "sg:classifiers":[
        {
            "category":"Banks & Credit Unions",
            "subcategory":"Investment Brokerage",
            "type":"Services"
        }
    ],
    "sg:phone":"+1 417 889 5170",
    "sg:postcode":"65807",
    "sg:province":"MO",
    "sg:tags":[
        "security"
    ],
    "wof:name":"Edward Jones 02633",
    "wof:placetype":"venue"
},
  "geometry": {"coordinates":[-93.322817,37.14558],"type":"Point"}
}