{
  "type": "Feature",
  "properties": {
    "iso:country":"US",
    "sg:address":"2617 Olive St",
    "sg:city":"Saint Louis",
    "sg:classifiers":[
        {
            "category":"Professional",
            "subcategory":"Printing & Photocopies",
            "type":"Services"
        }
    ],
    "sg:phone":"+1 314 533 5151",
    "sg:postcode":"63103",
    "sg:province":"MO",
    "wof:name":"Romac Printing",
    "wof:placetype":"venue"
},
  "geometry": {"coordinates":[-90.21472,38.63355],"type":"Point"}
}