{
  "type": "Feature",
  "properties": {
    "iso:country":"US",
    "sg:address":"202 N Main St",
    "sg:city":"Concordia",
    "sg:classifiers":[
        {
            "category":"Fast Food",
            "type":"Food & Drink"
        },
        {
            "category":"Restaurant",
            "type":"Food & Drink"
        }
    ],
    "sg:phone":"+1 660 463 7779",
    "sg:postcode":"64020",
    "sg:province":"MO",
    "sg:tags":[
        "hamburger",
        "hot",
        "dog",
        "american",
        "take"
    ],
    "sg:website":"http://www.hardees.com",
    "wof:name":"Hardee's",
    "wof:placetype":"venue"
},
  "geometry": {"coordinates":[-93.567848,38.990282],"type":"Point"}
}