{
  "type": "Feature",
  "properties": {
    "iso:country":"US",
    "sg:address":"15261 Golden Rain Dr",
    "sg:city":"Chesterfield",
    "sg:classifiers":[
        {
            "category":"Arena",
            "subcategory":"Sports Club",
            "type":"Entertainment"
        }
    ],
    "sg:phone":"+1 636 536 0997",
    "sg:postcode":"63017",
    "sg:province":"MO",
    "sg:tags":[
        "health"
    ],
    "wof:name":"Fitness Experts Inc",
    "wof:placetype":"venue"
},
  "geometry": {"coordinates":[-90.55525900000001,38.628764],"type":"Point"}
}