{
  "type": "Feature",
  "properties": {
    "iso:country":"US",
    "sg:address":"305 N Grand Ave",
    "sg:city":"Jasper",
    "sg:classifiers":[
        {
            "category":"Farming",
            "subcategory":"Farm & Veterinary Services",
            "type":"Manufacturing & Wholesale Goods"
        }
    ],
    "sg:phone":"+1 417 394 2032",
    "sg:postcode":"64755",
    "sg:province":"MO",
    "sg:tags":[
        "crop"
    ],
    "wof:name":"Kelly Neil Flying Svc At Lamar",
    "wof:placetype":"venue"
},
  "geometry": {"coordinates":[-94.444391,37.257015],"type":"Point"}
}