{
  "type": "Feature",
  "properties": {
    "iso:country":"US",
    "sg:address":"1200 E Woodhurst Dr",
    "sg:city":"Springfield",
    "sg:phone":"+1 417 877 4677",
    "sg:postcode":"65804",
    "sg:province":"MO",
    "wof:name":"Southwest Builders Incorporated",
    "wof:placetype":"venue"
},
  "geometry": {"coordinates":[-93.27626,37.157761],"type":"Point"}
}