{
  "type": "Feature",
  "properties": {
    "iso:country":"US",
    "sg:address":"3512 Gravois Rd",
    "sg:city":"House Springs",
    "sg:classifiers":[
        {
            "category":"Organizations",
            "subcategory":"Religious Organization",
            "type":"Services"
        }
    ],
    "sg:phone":"+1 636 677 3489",
    "sg:postcode":"63051",
    "sg:province":"MO",
    "sg:tags":[
        "church"
    ],
    "wof:name":"High Ridge Church Of Christ",
    "wof:placetype":"venue"
},
  "geometry": {"coordinates":[-90.549626,38.447783],"type":"Point"}
}