{
  "type": "Feature",
  "properties": {
    "iso:country":"US",
    "sg:address":"620 Morgan Rd",
    "sg:city":"Bolivar",
    "sg:classifiers":[
        {
            "category":"Freight",
            "type":"Transportation"
        }
    ],
    "sg:phone":"+1 417 777 3965",
    "sg:postcode":"65653",
    "sg:province":"MO",
    "sg:tags":[
        "trucking"
    ],
    "wof:name":"Black Watch Logistics Inc",
    "wof:placetype":"venue"
},
  "geometry": {"coordinates":[-93.119725,36.839422],"type":"Point"}
}