{
  "type": "Feature",
  "properties": {
    "iso:country":"US",
    "sg:address":"1207 SW Westminister Rd",
    "sg:city":"Blue Springs",
    "sg:classifiers":[
        {
            "category":"Professional",
            "subcategory":"Computer Services",
            "type":"Services"
        }
    ],
    "sg:phone":"+1 816 220 1471",
    "sg:postcode":"64014",
    "sg:province":"MO",
    "sg:tags":[
        "programing",
        "custom"
    ],
    "wof:name":"Heather L Hassler",
    "wof:placetype":"venue"
},
  "geometry": {"coordinates":[-94.27153,39.003406],"type":"Point"}
}