{
  "type": "Feature",
  "properties": {
    "iso:country":"US",
    "sg:address":"2808 Pembroke Ln",
    "sg:city":"Saint Joseph",
    "sg:classifiers":[
        {
            "category":"Sports & Exercise",
            "subcategory":"Gym",
            "type":"Entertainment"
        }
    ],
    "sg:phone":"+1 816 364 5311",
    "sg:postcode":"64506",
    "sg:province":"MO",
    "sg:tags":[
        "fitness",
        "physical",
        "facility"
    ],
    "wof:name":"Alices Energy Connection",
    "wof:placetype":"venue"
},
  "geometry": {"coordinates":[-94.809899,39.793049],"type":"Point"}
}