{
  "type": "Feature",
  "properties": {
    "iso:country":"US",
    "sg:address":"836 W Washington St",
    "sg:city":"Marshfield",
    "sg:classifiers":[
        {
            "category":"Home & Garden",
            "subcategory":"Carpets & Floor Coverings",
            "type":"Retail Goods"
        }
    ],
    "sg:phone":"+1 417 859 6620",
    "sg:postcode":"65706",
    "sg:province":"MO",
    "sg:tags":[
        "dealer",
        "rug"
    ],
    "wof:name":"Day's Floor Co",
    "wof:placetype":"venue"
},
  "geometry": {"coordinates":[-92.919076,37.337146],"type":"Point"}
}