{
  "type": "Feature",
  "properties": {
    "iso:country":"US",
    "sg:address":"15900 Sewell Ct",
    "sg:city":"Chesterfield",
    "sg:classifiers":[
        {
            "category":"Building & Trades",
            "subcategory":"Construction",
            "type":"Services"
        }
    ],
    "sg:phone":"+1 636 519 0948",
    "sg:postcode":"63005",
    "sg:province":"MO",
    "sg:tags":[
        "roofing",
        "contractor"
    ],
    "wof:name":"Dave Harting Roofing",
    "wof:placetype":"venue"
},
  "geometry": {"coordinates":[-90.578791,38.637419],"type":"Point"}
}