{
  "type": "Feature",
  "properties": {
    "iso:country":"US",
    "sg:address":"2700 Telegraph Rd",
    "sg:city":"St Louis",
    "sg:classifiers":[
        {
            "category":"Shopping",
            "subcategory":"Pharmacy",
            "type":"Retail Goods"
        }
    ],
    "sg:phone":"+1 314 416 0361",
    "sg:postcode":"63125",
    "sg:province":"MO",
    "sg:website":"www.walgreens.com",
    "wof:name":"Walgreens",
    "wof:placetype":"venue"
},
  "geometry": {"coordinates":[-90.293398,38.509443],"type":"Point"}
}