{
  "type": "Feature",
  "properties": {
    "iso:country":"US",
    "sg:address":"1822 Cherry Ave",
    "sg:city":"Saint Louis",
    "sg:classifiers":[
        {
            "category":"Retail",
            "subcategory":"Repair Shop",
            "type":"Services"
        }
    ],
    "sg:phone":"+1 314 822 4445",
    "sg:postcode":"63121",
    "sg:province":"MO",
    "wof:name":"Wescor",
    "wof:placetype":"venue"
},
  "geometry": {"coordinates":[-90.28867700000001,38.683794],"type":"Point"}
}