{
  "type": "Feature",
  "properties": {
    "iso:country":"US",
    "sg:address":"601 N Washington St",
    "sg:city":"Farmington",
    "sg:classifiers":[
        {
            "category":"Professional",
            "subcategory":"Lawyer & Legal Services",
            "type":"Services"
        }
    ],
    "sg:phone":"+1 573 756 5400",
    "sg:postcode":"63640",
    "sg:province":"MO",
    "sg:tags":[
        "attorney",
        "criminal",
        "duo",
        "personal",
        "divorce",
        "assistance",
        "injury",
        "dwi",
        "law"
    ],
    "sg:website":"http://www.farmingtoncriminallawyer.com",
    "wof:name":"Murphy, Renee",
    "wof:placetype":"venue"
},
  "geometry": {"coordinates":[-90.419811,37.785992],"type":"Point"}
}