{
  "type": "Feature",
  "properties": {
    "iso:country":"US",
    "sg:address":"505 Highway 63 S",
    "sg:city":"Vienna",
    "sg:classifiers":[
        {
            "category":"Autos & Motor Vehicles",
            "subcategory":"Auto Supplies",
            "type":"Retail Goods"
        }
    ],
    "sg:phone":"+1 573 422 3414",
    "sg:postcode":"65582",
    "sg:province":"MO",
    "sg:tags":[
        "tire"
    ],
    "wof:name":"Miller's Tire Service",
    "wof:placetype":"venue"
},
  "geometry": {"coordinates":[-91.88948499999999,38.148964],"type":"Point"}
}