{
  "type": "Feature",
  "properties": {
    "addr:full":"920 E 15th St Joplin MO 64804",
    "addr:housenumber":"920",
    "addr:postcode":"64804",
    "addr:street":"E 15Th St",
    "iso:country":"US",
    "sg:address":"920 E 15th St",
    "sg:city":"Joplin",
    "sg:classifiers":[
        {
            "category":"Shopping",
            "subcategory":"Books",
            "type":"Retail Goods"
        }
    ],
    "sg:phone":"+1 417 206 7800",
    "sg:postcode":"64804",
    "sg:province":"MO",
    "sg:website":"www.expectonline.com",
    "wof:name":"Great Expectations",
    "wof:placetype":"venue"
},
  "geometry": {"coordinates":[-94.50420800000001,37.074719],"type":"Point"}
}