{
  "type": "Feature",
  "properties": {
    "iso:country":"US",
    "sg:address":"15224 Manchester Rd",
    "sg:city":"Ballwin",
    "sg:classifiers":[
        {
            "category":"Personal",
            "subcategory":"Beauty Salon",
            "type":"Services"
        }
    ],
    "sg:phone":"+1 636 527 5007",
    "sg:postcode":"63011",
    "sg:province":"MO",
    "sg:tags":[
        "shop"
    ],
    "wof:name":"Manicura Nail Salon & Spa",
    "wof:placetype":"venue"
},
  "geometry": {"coordinates":[-90.55354,38.592786],"type":"Point"}
}