{
  "type": "Feature",
  "properties": {
    "iso:country":"US",
    "sg:address":"553 Purdue Ave",
    "sg:city":"St Louis",
    "sg:classifiers":[
        {
            "category":"Home & Garden",
            "subcategory":"Garden Supply",
            "type":"Retail Goods"
        }
    ],
    "sg:phone":"+1 314 862 2960",
    "sg:postcode":"63130",
    "sg:province":"MO",
    "sg:tags":[
        "lawn"
    ],
    "wof:name":"Special Gardens Inc",
    "wof:placetype":"venue"
},
  "geometry": {"coordinates":[-90.32764,38.65516],"type":"Point"}
}