{
  "type": "Feature",
  "properties": {
    "iso:country":"US",
    "sg:address":"214 S Bemiston Ave",
    "sg:city":"St Louis",
    "sg:classifiers":[
        {
            "category":"Organizations",
            "subcategory":"Community Association",
            "type":"Services"
        }
    ],
    "sg:phone":"+1 314 863 3310",
    "sg:postcode":"63105",
    "sg:province":"MO",
    "sg:tags":[
        "educational"
    ],
    "wof:name":"St Louis Co Parent Edu Prgm",
    "wof:placetype":"venue"
},
  "geometry": {"coordinates":[-90.33733100000001,38.646325],"type":"Point"}
}