{
  "type": "Feature",
  "properties": {
    "iso:country":"US",
    "sg:address":"3051 Becker Crossing Dr",
    "sg:city":"Saint Louis",
    "sg:classifiers":[
        {
            "category":"Building & Trades",
            "subcategory":"Cleaning & Sanitation",
            "type":"Services"
        }
    ],
    "sg:phone":"+1 314 293 0549",
    "sg:postcode":"63129",
    "sg:province":"MO",
    "sg:tags":[
        "maintenance"
    ],
    "wof:name":"Modern Cleaning Services",
    "wof:placetype":"venue"
},
  "geometry": {"coordinates":[-90.32939,38.42715],"type":"Point"}
}