{
  "type": "Feature",
  "properties": {
    "iso:country":"US",
    "sg:address":"5946 Troost Ave",
    "sg:city":"Kansas City",
    "sg:classifiers":[
        {
            "category":"Restaurant",
            "type":"Food & Drink"
        }
    ],
    "sg:phone":"+1 816 523 4740",
    "sg:postcode":"64110",
    "sg:province":"MO",
    "wof:name":"Texas Tom's Restaurant",
    "wof:placetype":"venue"
},
  "geometry": {"coordinates":[-94.574337,39.019082],"type":"Point"}
}