{
  "type": "Feature",
  "properties": {
    "addr:full":"13127 New Halls Ferry Rd Florissant MO 63033",
    "addr:housenumber":"13127",
    "addr:postcode":"63033",
    "addr:street":"New Halls Ferry Rd",
    "iso:country":"US",
    "sg:address":"13127 New Halls Ferry Rd",
    "sg:city":"Florissant",
    "sg:classifiers":[
        {
            "category":"Government",
            "subcategory":"Office",
            "type":"Public Place"
        }
    ],
    "sg:phone":"+1 314 921 2133",
    "sg:postcode":"63033",
    "sg:province":"MO",
    "sg:tags":[
        "federal",
        "security"
    ],
    "wof:name":"Army National Guard",
    "wof:placetype":"venue"
},
  "geometry": {"coordinates":[-90.290852,38.796806],"type":"Point"}
}