{
  "type": "Feature",
  "properties": {
    "iso:country":"US",
    "sg:address":"189 Otto Ln",
    "sg:city":"Cape Girardeau",
    "sg:classifiers":[
        {
            "category":"Building & Trades",
            "subcategory":"Landscaping Services",
            "type":"Services"
        }
    ],
    "sg:phone":"+1 573 243 4934",
    "sg:postcode":"63701",
    "sg:province":"MO",
    "sg:tags":[
        "landscape",
        "contractor"
    ],
    "wof:name":"Greenfield Tuf Farm",
    "wof:placetype":"venue"
},
  "geometry": {"coordinates":[-89.678648,37.306351],"type":"Point"}
}