{
  "type": "Feature",
  "properties": {
    "iso:country":"US",
    "sg:address":"110 W 14th Ave",
    "sg:city":"Kansas City",
    "sg:classifiers":[
        {
            "category":"Manufacturing",
            "subcategory":"Printing",
            "type":"Manufacturing & Wholesale Goods"
        }
    ],
    "sg:phone":"+1 816 842 1151",
    "sg:postcode":"64116",
    "sg:province":"MO",
    "sg:tags":[
        "print",
        "lithographic",
        "typesetting"
    ],
    "wof:name":"J-2 Printing Inc",
    "wof:placetype":"venue"
},
  "geometry": {"coordinates":[-94.584315,39.134311],"type":"Point"}
}