{
  "type": "Feature",
  "properties": {
    "iso:country":"US",
    "sg:address":"1742 S 20th St",
    "sg:city":"Ozark",
    "sg:classifiers":[
        {
            "category":"Personal",
            "subcategory":"Nail Salon",
            "type":"Services"
        }
    ],
    "sg:phone":"+1 417 485 4456",
    "sg:postcode":"65721",
    "sg:province":"MO",
    "wof:name":"Crystal Nails",
    "wof:placetype":"venue"
},
  "geometry": {"coordinates":[-93.227175,37.010046],"type":"Point"}
}