{
  "type": "Feature",
  "properties": {
    "iso:country":"US",
    "sg:address":"13215 Timber Park Dr",
    "sg:city":"Platte City",
    "sg:classifiers":[
        {
            "category":"Building & Trades",
            "subcategory":"Plumbing",
            "type":"Services"
        }
    ],
    "sg:phone":"+1 816 858 2078",
    "sg:postcode":"64079",
    "sg:province":"MO",
    "sg:tags":[
        "plumbing",
        "contractor"
    ],
    "wof:name":"Certified Backflow Inc",
    "wof:placetype":"venue"
},
  "geometry": {"coordinates":[-94.76706299999999,39.334307],"type":"Point"}
}