{
  "type": "Feature",
  "properties": {
    "iso:country":"US",
    "sg:address":"916 W South St",
    "sg:city":"Neosho",
    "sg:classifiers":[
        {
            "category":"Health Services",
            "subcategory":"Doctor",
            "type":"Services"
        }
    ],
    "sg:phone":"+1 417 451 3307",
    "sg:postcode":"64850",
    "sg:province":"MO",
    "wof:name":"Norman L Smith DDS",
    "wof:placetype":"venue"
},
  "geometry": {"coordinates":[-94.38248299999999,36.858238],"type":"Point"}
}