{
  "type": "Feature",
  "properties": {
    "iso:country":"US",
    "sg:address":"7001 Hunter St",
    "sg:city":"Raytown",
    "sg:classifiers":[
        {
            "category":"Personal",
            "subcategory":"Beauty Salon",
            "type":"Services"
        }
    ],
    "sg:phone":"+1 816 356 7376",
    "sg:postcode":"64133",
    "sg:province":"MO",
    "wof:name":"Avante Beauty Care",
    "wof:placetype":"venue"
},
  "geometry": {"coordinates":[-94.479207,38.996189],"type":"Point"}
}