{
  "type": "Feature",
  "properties": {
    "iso:country":"US",
    "sg:address":"3150 Hwy Jj",
    "sg:city":"Palmyra",
    "sg:classifiers":[
        {
            "category":"Wholesale",
            "subcategory":"Farm Supplies",
            "type":"Manufacturing & Wholesale Goods"
        }
    ],
    "sg:phone":"+1 573 769 2635",
    "sg:postcode":"63461",
    "sg:province":"MO",
    "wof:name":"Roche Vitamin & Fine Chemicals",
    "wof:placetype":"venue"
},
  "geometry": {"coordinates":[-91.436697,39.834486],"type":"Point"}
}