{
  "type": "Feature",
  "properties": {
    "iso:country":"US",
    "sg:address":"115 S Main St",
    "sg:city":"Piedmont",
    "sg:classifiers":[
        {
            "category":"Shopping",
            "subcategory":"Used Merchandise",
            "type":"Retail Goods"
        }
    ],
    "sg:phone":"+1 573 223 3543",
    "sg:postcode":"63957",
    "sg:province":"MO",
    "wof:name":"Cinnamon Bear & Friends",
    "wof:placetype":"venue"
},
  "geometry": {"coordinates":[-90.695956,37.154569],"type":"Point"}
}