{
  "type": "Feature",
  "properties": {
    "addr:full":"429 Lafayette Ctr Ballwin MO 63011",
    "addr:housenumber":"429",
    "addr:postcode":"63011",
    "addr:street":"Lafayette Ctr",
    "iso:country":"US",
    "sg:address":"429 Lafayette Ctr",
    "sg:city":"Ballwin",
    "sg:classifiers":[
        {
            "category":"Retail",
            "subcategory":"Laundry & Dry Cleaning",
            "type":"Services"
        }
    ],
    "sg:phone":"+1 636 527 8009",
    "sg:postcode":"63011",
    "sg:province":"MO",
    "sg:tags":[
        "cleaner",
        "commercial"
    ],
    "wof:name":"American Cleaners",
    "wof:placetype":"venue"
},
  "geometry": {"coordinates":[-90.522232,38.595557],"type":"Point"}
}