{
  "type": "Feature",
  "properties": {
    "iso:country":"US",
    "sg:address":"26807 NE 150th St",
    "sg:city":"Excelsior Springs",
    "sg:classifiers":[
        {
            "category":"Building & Trades",
            "subcategory":"Cleaning & Sanitation",
            "type":"Services"
        }
    ],
    "sg:phone":"+1 816 630 0402",
    "sg:postcode":"64024",
    "sg:province":"MO",
    "sg:tags":[
        "maintenance"
    ],
    "wof:name":"Make Ready Cleaning",
    "wof:placetype":"venue"
},
  "geometry": {"coordinates":[-94.268798,39.364089],"type":"Point"}
}