{
  "type": "Feature",
  "properties": {
    "iso:country":"US",
    "sg:address":"6130 Cherry St",
    "sg:city":"Kansas City",
    "sg:classifiers":[
        {
            "category":"Professional",
            "subcategory":"Secretarial Services",
            "type":"Services"
        }
    ],
    "sg:phone":"+1 816 523 8977",
    "sg:postcode":"64110",
    "sg:province":"MO",
    "sg:tags":[
        "reporting"
    ],
    "wof:name":"Twp Services",
    "wof:placetype":"venue"
},
  "geometry": {"coordinates":[-94.581504,39.014692],"type":"Point"}
}