{
  "type": "Feature",
  "properties": {
    "iso:country":"US",
    "sg:address":"9860 Watson Rd",
    "sg:city":"Saint Louis",
    "sg:classifiers":[
        {
            "category":"Personal",
            "type":"Services"
        }
    ],
    "sg:phone":"+1 314 821 3900",
    "sg:postcode":"63126",
    "sg:province":"MO",
    "wof:name":"Turning Point Weight Loss Cntr",
    "wof:placetype":"venue"
},
  "geometry": {"coordinates":[-90.38938,38.556626],"type":"Point"}
}