{
  "type": "Feature",
  "properties": {
    "iso:country":"US",
    "sg:address":"13580 State Hwy 43",
    "sg:city":"Seneca",
    "sg:classifiers":[
        {
            "category":"Building & Trades",
            "subcategory":"Construction",
            "type":"Services"
        }
    ],
    "sg:phone":"+1 417 776 4900",
    "sg:postcode":"64865",
    "sg:province":"MO",
    "sg:tags":[
        "house",
        "mater",
        "contractor",
        "concrete"
    ],
    "wof:name":"K G Concrete Construction",
    "wof:placetype":"venue"
},
  "geometry": {"coordinates":[-94.59267800000001,36.882596],"type":"Point"}
}