{
  "type": "Feature",
  "properties": {
    "iso:country":"US",
    "sg:address":"116 E White Oak St",
    "sg:city":"Independence",
    "sg:classifiers":[
        {
            "category":"Organizations",
            "subcategory":"Religious Organization",
            "type":"Services"
        }
    ],
    "sg:phone":"+1 816 461 6020",
    "sg:postcode":"64050",
    "sg:province":"MO",
    "wof:name":"Second Baptist Church",
    "wof:placetype":"venue"
},
  "geometry": {"coordinates":[-94.415454,39.094568],"type":"Point"}
}