{
  "type": "Feature",
  "properties": {
    "iso:country":"US",
    "sg:address":"1021 W Main St",
    "sg:city":"Imperial",
    "sg:classifiers":[
        {
            "category":"Insurance",
            "subcategory":"Insurance Agent",
            "type":"Services"
        }
    ],
    "sg:phone":"+1 636 464 0665",
    "sg:postcode":"63052",
    "sg:province":"MO",
    "wof:name":"American Family Insurance",
    "wof:placetype":"venue"
},
  "geometry": {"coordinates":[-90.376668,38.368998],"type":"Point"}
}