{
  "type": "Feature",
  "properties": {
    "iso:country":"US",
    "sg:address":"204 Poplar St",
    "sg:city":"Advance",
    "sg:classifiers":[
        {
            "category":"Building & Trades",
            "subcategory":"Plumbing",
            "type":"Services"
        }
    ],
    "sg:phone":"+1 573 722 5777",
    "sg:postcode":"63730",
    "sg:province":"MO",
    "sg:tags":[
        "contractor"
    ],
    "wof:name":"K&K Construction & Mechanical",
    "wof:placetype":"venue"
},
  "geometry": {"coordinates":[-89.913017,37.106125],"type":"Point"}
}