{
  "type": "Feature",
  "properties": {
    "iso:country":"US",
    "sg:address":"11325 Saint Charles Rock Rd",
    "sg:city":"Bridgeton",
    "sg:classifiers":[
        {
            "category":"Health Services",
            "subcategory":"Nursing And Care Facility",
            "type":"Services"
        }
    ],
    "sg:phone":"+1 314 209 1177",
    "sg:postcode":"63044",
    "sg:province":"MO",
    "sg:tags":[
        "skilled"
    ],
    "wof:name":"Mizpah Manor",
    "wof:placetype":"venue"
},
  "geometry": {"coordinates":[-90.403335,38.740252],"type":"Point"}
}