{
  "type": "Feature",
  "properties": {
    "iso:country":"US",
    "sg:address":"9200 Green Park Rd",
    "sg:city":"St Louis",
    "sg:classifiers":[
        {
            "category":"Building & Trades",
            "subcategory":"Construction",
            "type":"Services"
        }
    ],
    "sg:phone":"+1 314 894 9500",
    "sg:postcode":"63123",
    "sg:province":"MO",
    "sg:tags":[
        "masonry",
        "contractor"
    ],
    "wof:name":"John J Smith Masonry Co",
    "wof:placetype":"venue"
},
  "geometry": {"coordinates":[-90.330809,38.52307],"type":"Point"}
}