{
  "type": "Feature",
  "properties": {
    "iso:country":"US",
    "sg:address":"14522 S Outer 40 Rd",
    "sg:city":"Chesterfield",
    "sg:classifiers":[
        {
            "category":"Building & Trades",
            "subcategory":"Construction",
            "type":"Services"
        }
    ],
    "sg:phone":"+1 314 275 5700",
    "sg:postcode":"63017",
    "sg:province":"MO",
    "sg:tags":[
        "industrial",
        "contractors-commercial"
    ],
    "wof:name":"Horizon Global Technology, Inc.",
    "wof:placetype":"venue"
},
  "geometry": {"coordinates":[-90.52054,38.644376],"type":"Point"}
}