{
  "type": "Feature",
  "properties": {
    "iso:country":"US",
    "sg:address":"1134 Co Rd 442",
    "sg:city":"New Franklin",
    "sg:classifiers":[
        {
            "category":"Building & Trades",
            "subcategory":"Construction",
            "type":"Services"
        }
    ],
    "sg:phone":"+1 660 848 2872",
    "sg:postcode":"65274",
    "sg:province":"MO",
    "sg:tags":[
        "contractor"
    ],
    "wof:name":"John Jones Drywall Compan",
    "wof:placetype":"venue"
},
  "geometry": {"coordinates":[-92.62466499999999,39.01217],"type":"Point"}
}