{
  "type": "Feature",
  "properties": {
    "iso:country":"US",
    "sg:address":"908 W 11th St",
    "sg:city":"Rolla",
    "sg:classifiers":[
        {
            "category":"Building & Trades",
            "subcategory":"Landscaping Services",
            "type":"Services"
        }
    ],
    "sg:phone":"+1 573 578 9066",
    "sg:postcode":"65401",
    "sg:province":"MO",
    "sg:tags":[
        "lawn",
        "maintenance",
        "grounds"
    ],
    "wof:name":"Josh Caron's Yard Care",
    "wof:placetype":"venue"
},
  "geometry": {"coordinates":[-91.781689,37.952375],"type":"Point"}
}