{
  "type": "Feature",
  "properties": {
    "iso:country":"US",
    "sg:address":"6454 Alamo Ave",
    "sg:city":"Saint Louis",
    "sg:classifiers":[
        {
            "category":"Health Services",
            "subcategory":"Clinic",
            "type":"Services"
        }
    ],
    "sg:phone":"+1 314 863 2363",
    "sg:postcode":"63105",
    "sg:province":"MO",
    "sg:tags":[
        "counseling",
        "mental"
    ],
    "wof:name":"Robinson Mark Lee Dmin",
    "wof:placetype":"venue"
},
  "geometry": {"coordinates":[-90.31089799999999,38.634998],"type":"Point"}
}