{
  "type": "Feature",
  "properties": {
    "iso:country":"US",
    "sg:address":"4601 Stilwell Ave",
    "sg:city":"Kansas City",
    "sg:classifiers":[
        {
            "category":"Wholesale",
            "subcategory":"Machinery & Supplies",
            "type":"Manufacturing & Wholesale Goods"
        }
    ],
    "sg:phone":"+1 816 471 5115",
    "sg:postcode":"64120",
    "sg:province":"MO",
    "sg:tags":[
        "packer",
        "equipment",
        "meat"
    ],
    "wof:name":"Talleyrand Industries",
    "wof:placetype":"venue"
},
  "geometry": {"coordinates":[-94.522128,39.140969],"type":"Point"}
}