{
  "type": "Feature",
  "properties": {
    "iso:country":"US",
    "sg:address":"196 NW Oldham Pkwy",
    "sg:city":"Lees Summit",
    "sg:classifiers":[
        {
            "category":"Professional",
            "subcategory":"Advertising",
            "type":"Services"
        }
    ],
    "sg:phone":"+1 816 246 5940",
    "sg:postcode":"64081",
    "sg:province":"MO",
    "sg:tags":[
        "mailing",
        "shipping"
    ],
    "wof:name":"Shipping Ctr",
    "wof:placetype":"venue"
},
  "geometry": {"coordinates":[-94.40126100000001,38.917416],"type":"Point"}
}