{
  "type": "Feature",
  "properties": {
    "iso:country":"US",
    "sg:address":"2159 Welsch Industrial Ct",
    "sg:city":"St Louis",
    "sg:classifiers":[
        {
            "category":"Wholesale",
            "subcategory":"Chemicals & Plastics",
            "type":"Manufacturing & Wholesale Goods"
        }
    ],
    "sg:phone":"+1 314 994 0022",
    "sg:postcode":"63146",
    "sg:province":"MO",
    "sg:tags":[
        "deodorant"
    ],
    "wof:name":"Guardian Environmental Systems",
    "wof:placetype":"venue"
},
  "geometry": {"coordinates":[-90.43318499999999,38.699024],"type":"Point"}
}