{
  "type": "Feature",
  "properties": {
    "iso:country":"US",
    "sg:address":"3838 S Broadway",
    "sg:city":"Saint Louis",
    "sg:classifiers":[
        {
            "category":"Building & Trades",
            "subcategory":"Electrical",
            "type":"Services"
        }
    ],
    "sg:phone":"+1 314 776 5252",
    "sg:postcode":"63118",
    "sg:province":"MO",
    "sg:tags":[
        "electrician",
        "electric",
        "contractor"
    ],
    "wof:name":"Southwestern Electric Co",
    "wof:placetype":"venue"
},
  "geometry": {"coordinates":[-90.227402,38.584702],"type":"Point"}
}