{
  "type": "Feature",
  "properties": {
    "iso:country":"US",
    "sg:address":"409 Outback Ln",
    "sg:city":"Reeds Spring",
    "sg:classifiers":[
        {
            "category":"Building & Trades",
            "subcategory":"Construction",
            "type":"Services"
        }
    ],
    "sg:phone":"+1 417 272 8561",
    "sg:postcode":"65737",
    "sg:province":"MO",
    "sg:tags":[
        "contractor"
    ],
    "wof:name":"Montes Mobile Home Mover",
    "wof:placetype":"venue"
},
  "geometry": {"coordinates":[-93.367225,36.784594],"type":"Point"}
}