{
  "type": "Feature",
  "properties": {
    "iso:country":"US",
    "sg:address":"313 N Davis St",
    "sg:city":"Hamilton",
    "sg:classifiers":[
        {
            "category":"Wholesale",
            "subcategory":"Farm Supplies",
            "type":"Manufacturing & Wholesale Goods"
        }
    ],
    "sg:phone":"+1 816 583 2128",
    "sg:postcode":"64644",
    "sg:province":"MO",
    "wof:name":"Mfa Exchange",
    "wof:placetype":"venue"
},
  "geometry": {"coordinates":[-93.998182,39.745082],"type":"Point"}
}