{
  "type": "Feature",
  "properties": {
    "iso:country":"US",
    "sg:address":"10686 Highway V",
    "sg:city":"Vienna",
    "sg:classifiers":[
        {
            "category":"Education",
            "subcategory":"College",
            "type":"Public Place"
        },
        {
            "category":"Organizations",
            "subcategory":"Membership Organization",
            "type":"Services"
        }
    ],
    "sg:phone":"+1 573 422 3820",
    "sg:postcode":"65582",
    "sg:province":"MO",
    "sg:tags":[
        "fraternal",
        "sorority",
        "housing",
        "student",
        "fraternity"
    ],
    "wof:name":"Vienna-Bassett Eagles",
    "wof:placetype":"venue"
},
  "geometry": {"coordinates":[-91.955959,38.174349],"type":"Point"}
}