{
  "type": "Feature",
  "properties": {
    "iso:country":"US",
    "sg:address":"338 Willie Oaks Rd",
    "sg:city":"Forsyth",
    "sg:classifiers":[
        {
            "category":"Building & Trades",
            "subcategory":"Plumbing",
            "type":"Services"
        },
        {
            "category":"Building & Trades",
            "subcategory":"Construction",
            "type":"Services"
        }
    ],
    "sg:phone":"+1 417 546 4854",
    "sg:postcode":"65653",
    "sg:province":"MO",
    "sg:tags":[
        "plumber",
        "industrial",
        "system",
        "specialty",
        "heating",
        "contractors-commercial",
        "contractor",
        "air conditioning"
    ],
    "wof:name":"Todd Plumbing Heating",
    "wof:placetype":"venue"
},
  "geometry": {"coordinates":[-93.138925,36.662185],"type":"Point"}
}