{
  "type": "Feature",
  "properties": {
    "iso:country":"US",
    "sg:address":"870 State Hwy 291",
    "sg:city":"Liberty",
    "sg:classifiers":[
        {
            "category":"Personal",
            "subcategory":"Beauty Salon",
            "type":"Services"
        }
    ],
    "sg:phone":"+1 816 407 9800",
    "sg:postcode":"64068",
    "sg:province":"MO",
    "sg:tags":[
        "manicuring"
    ],
    "wof:name":"Miss Nails",
    "wof:placetype":"venue"
},
  "geometry": {"coordinates":[-94.43521800000001,39.238073],"type":"Point"}
}