{
  "type": "Feature",
  "properties": {
    "iso:country":"US",
    "sg:address":"201 S Moniteau Ave",
    "sg:city":"Sedalia",
    "sg:classifiers":[
        {
            "category":"Manufacturing",
            "subcategory":"Tools & Machinery",
            "type":"Manufacturing & Wholesale Goods"
        }
    ],
    "sg:phone":"+1 660 829 4600",
    "sg:postcode":"65301",
    "sg:province":"MO",
    "sg:tags":[
        "machine",
        "repair",
        "shop",
        "machinery-rebuild"
    ],
    "wof:name":"Sedalia Machine Works",
    "wof:placetype":"venue"
},
  "geometry": {"coordinates":[-93.230919,38.710331],"type":"Point"}
}