{
  "type": "Feature",
  "properties": {
    "addr:full":"1213 State Hwy 92 Platte City MO 64079",
    "addr:housenumber":"1213",
    "addr:postcode":"64079",
    "addr:street":"State Hwy 92",
    "iso:country":"US",
    "sg:address":"1213 State Hwy 92",
    "sg:city":"Platte City",
    "sg:classifiers":[
        {
            "category":"Banks & Credit Unions",
            "subcategory":"Bank",
            "type":"Services"
        }
    ],
    "sg:phone":"+1 816 858 4005",
    "sg:postcode":"64079",
    "sg:province":"MO",
    "sg:tags":[
        "loan"
    ],
    "wof:name":"Security Finance Corp",
    "wof:placetype":"venue"
},
  "geometry": {"coordinates":[-94.770887,39.362999],"type":"Point"}
}