{
  "type": "Feature",
  "properties": {
    "iso:country":"US",
    "sg:address":"2030 S National Ave",
    "sg:city":"Springfield",
    "sg:classifiers":[
        {
            "category":"Health Services",
            "subcategory":"Health Practitioner",
            "type":"Services"
        }
    ],
    "sg:phone":"+1 417 883 3911",
    "sg:postcode":"65804",
    "sg:province":"MO",
    "sg:tags":[
        "psychologist"
    ],
    "wof:name":"St John's Clinic-Psychology",
    "wof:placetype":"venue"
},
  "geometry": {"coordinates":[-93.27668199999999,37.177582],"type":"Point"}
}