{
  "type": "Feature",
  "properties": {
    "iso:country":"US",
    "sg:address":"3990 Co Rd 2150",
    "sg:city":"Pomona",
    "sg:phone":"+1 417 256 0178",
    "sg:postcode":"65789",
    "sg:province":"MO",
    "sg:tags":[
        "farm",
        "soybean"
    ],
    "wof:name":"Gene Morgan",
    "wof:placetype":"venue"
},
  "geometry": {"coordinates":[-91.857057,36.906062],"type":"Point"}
}