{
  "type": "Feature",
  "properties": {
    "iso:country":"US",
    "sg:address":"307 E 55 St",
    "sg:city":"Kansas City",
    "sg:classifiers":[
        {
            "category":"Shopping",
            "subcategory":"Gifts & Souvenirs",
            "type":"Retail Goods"
        }
    ],
    "sg:phone":"+1 816 822 2627",
    "sg:postcode":"64113",
    "sg:province":"MO",
    "wof:name":"Windermere & Bergamont LTD",
    "wof:placetype":"venue"
},
  "geometry": {"coordinates":[-94.583146,39.027436],"type":"Point"}
}