{
  "type": "Feature",
  "properties": {
    "iso:country":"US",
    "sg:address":"812 Moore St",
    "sg:city":"Dexter",
    "sg:classifiers":[
        {
            "category":"Wholesale",
            "subcategory":"Durable Goods & Equipment",
            "type":"Manufacturing & Wholesale Goods"
        }
    ],
    "sg:phone":"+1 573 624 4663",
    "sg:postcode":"63841",
    "sg:province":"MO",
    "wof:name":"Ayers Supply",
    "wof:placetype":"venue"
},
  "geometry": {"coordinates":[-89.97076300000001,36.786231],"type":"Point"}
}