{
  "type": "Feature",
  "properties": {
    "iso:country":"US",
    "sg:address":"79 Cherokee Ln",
    "sg:city":"Winfield",
    "sg:classifiers":[
        {
            "category":"Autos & Motor Vehicles",
            "subcategory":"Auto Supplies",
            "type":"Retail Goods"
        }
    ],
    "sg:phone":"+1 636 462 6032",
    "sg:postcode":"63389",
    "sg:province":"MO",
    "wof:name":"K & D Mobile Tool Sales",
    "wof:placetype":"venue"
},
  "geometry": {"coordinates":[-90.848195,39.002023],"type":"Point"}
}