{
  "type": "Feature",
  "properties": {
    "iso:country":"US",
    "sg:address":"6062 Front St",
    "sg:city":"Kimmswick",
    "sg:classifiers":[
        {
            "category":"Shopping",
            "subcategory":"Gifts & Souvenirs",
            "type":"Retail Goods"
        }
    ],
    "sg:phone":"+1 636 464 9339",
    "sg:postcode":"63053",
    "sg:province":"MO",
    "sg:tags":[
        "shop"
    ],
    "wof:name":"Dough Depot",
    "wof:placetype":"venue"
},
  "geometry": {"coordinates":[-90.362942,38.365179],"type":"Point"}
}