{
  "type": "Feature",
  "properties": {
    "iso:country":"US",
    "sg:address":"8120 E 133rd Ter",
    "sg:city":"Grandview",
    "sg:classifiers":[
        {
            "category":"Shopping",
            "subcategory":"Music",
            "type":"Retail Goods"
        }
    ],
    "sg:phone":"+1 816 761 8738",
    "sg:postcode":"64030",
    "sg:province":"MO",
    "wof:name":"Thru Roof Records",
    "wof:placetype":"venue"
},
  "geometry": {"coordinates":[-94.498386,38.881124],"type":"Point"}
}