{
  "type": "Feature",
  "properties": {
    "iso:country":"US",
    "sg:address":"304 N Main St",
    "sg:city":"Gallatin",
    "sg:classifiers":[
        {
            "category":"Restaurant",
            "type":"Food & Drink"
        }
    ],
    "sg:phone":"+1 660 663 3913",
    "sg:postcode":"64640",
    "sg:province":"MO",
    "sg:tags":[
        "pizza"
    ],
    "sg:website":"http://www.caseys.com",
    "wof:name":"Casey's Carry Out Pizza",
    "wof:placetype":"venue"
},
  "geometry": {"coordinates":[-93.96141900000001,39.916463],"type":"Point"}
}