{
  "type": "Feature",
  "properties": {
    "iso:country":"US",
    "sg:address":"210 S Belt Hwy",
    "sg:city":"St Joseph",
    "sg:classifiers":[
        {
            "category":"Shopping",
            "type":"Retail Goods"
        },
        {
            "category":"Recreation",
            "type":"Entertainment"
        }
    ],
    "sg:phone":"+1 816 279 3313",
    "sg:postcode":"64506",
    "sg:province":"MO",
    "sg:tags":[
        "repair",
        "art",
        "gallery",
        "dealer"
    ],
    "sg:website":"www.jfranklingallery.com",
    "wof:name":"J Franklin Gallery",
    "wof:placetype":"venue"
},
  "geometry": {"coordinates":[-94.803785,39.766173],"type":"Point"}
}