{
  "type": "Feature",
  "properties": {
    "addr:full":"1138 Vine St Poplar Bluff MO 63901",
    "addr:housenumber":"1138",
    "addr:postcode":"63901",
    "addr:street":"Vine St",
    "iso:country":"US",
    "sg:address":"1138 Vine St",
    "sg:city":"Poplar Bluff",
    "sg:classifiers":[
        {
            "category":"Professional",
            "subcategory":"Accounting & Tax Preparation",
            "type":"Services"
        }
    ],
    "sg:phone":"+1 573 686 8800",
    "sg:postcode":"63901",
    "sg:province":"MO",
    "sg:tags":[
        "return"
    ],
    "wof:name":"Express Personnel Services",
    "wof:placetype":"venue"
},
  "geometry": {"coordinates":[-90.407032,36.757376],"type":"Point"}
}