{
  "type": "Feature",
  "properties": {
    "iso:country":"US",
    "sg:address":"9915 E 63rd St",
    "sg:city":"Raytown",
    "sg:classifiers":[
        {
            "category":"Professional",
            "subcategory":"Engineering",
            "type":"Services"
        },
        {
            "category":"Real Estate",
            "subcategory":"Architect",
            "type":"Services"
        }
    ],
    "sg:phone":"+1 816 353 1288",
    "sg:postcode":"64133",
    "sg:province":"MO",
    "sg:tags":[
        "consulting",
        "construction",
        "specification",
        "architectural",
        "engineer"
    ],
    "wof:name":"Little, Corliss V & Co",
    "wof:placetype":"venue"
},
  "geometry": {"coordinates":[-94.464308,39.008546],"type":"Point"}
}