{
  "type": "Feature",
  "properties": {
    "iso:country":"US",
    "sg:address":"2800 Maguire Blvd",
    "sg:city":"Columbia",
    "sg:classifiers":[
        {
            "category":"Manufacturing",
            "subcategory":"Printing",
            "type":"Manufacturing & Wholesale Goods"
        }
    ],
    "sg:phone":"+1 573 882 7801",
    "sg:postcode":"65201",
    "sg:province":"MO",
    "sg:tags":[
        "lithographic",
        "commercial"
    ],
    "wof:name":"University of Missouri",
    "wof:placetype":"venue"
},
  "geometry": {"coordinates":[-92.287735,38.920536],"type":"Point"}
}