{
  "type": "Feature",
  "properties": {
    "iso:country":"US",
    "sg:address":"7 N Elm St",
    "sg:city":"Dexter",
    "sg:classifiers":[
        {
            "category":"Professional",
            "subcategory":"Lawyer & Legal Services",
            "type":"Services"
        }
    ],
    "sg:phone":"+1 573 624 5901",
    "sg:postcode":"63841",
    "sg:province":"MO",
    "sg:tags":[
        "attorney"
    ],
    "wof:name":"Parsons Law Firm",
    "wof:placetype":"venue"
},
  "geometry": {"coordinates":[-89.95502999999999,36.793077],"type":"Point"}
}