{
  "type": "Feature",
  "properties": {
    "iso:country":"US",
    "sg:address":"207 Sunset Dr",
    "sg:city":"Doniphan",
    "sg:classifiers":[
        {
            "category":"Building & Trades",
            "subcategory":"Construction",
            "type":"Services"
        }
    ],
    "sg:phone":"+1 573 996 4120",
    "sg:postcode":"63935",
    "sg:province":"MO",
    "sg:tags":[
        "insulation",
        "heat",
        "contractor"
    ],
    "wof:name":"Air Tight Insulation",
    "wof:placetype":"venue"
},
  "geometry": {"coordinates":[-90.808384,36.619146],"type":"Point"}
}