{
  "type": "Feature",
  "properties": {
    "iso:country":"US",
    "sg:address":"1612 Westport Rd",
    "sg:city":"Kansas City",
    "sg:classifiers":[
        {
            "category":"Personal",
            "subcategory":"Beauty Salon",
            "type":"Services"
        }
    ],
    "sg:phone":"+1 816 756 5756",
    "sg:postcode":"64111",
    "sg:province":"MO",
    "sg:tags":[
        "shop"
    ],
    "wof:name":"West 47th Street Salon",
    "wof:placetype":"venue"
},
  "geometry": {"coordinates":[-94.604936,39.050221],"type":"Point"}
}