{
  "type": "Feature",
  "properties": {
    "iso:country":"US",
    "sg:address":"2906 Breckenridge Dr",
    "sg:city":"Cape Girardeau",
    "sg:classifiers":[
        {
            "category":"Health Services",
            "subcategory":"Doctor",
            "type":"Services"
        }
    ],
    "sg:phone":"+1 573 334 8798",
    "sg:postcode":"63701",
    "sg:province":"MO",
    "wof:name":"Jeffrey Patton D",
    "wof:placetype":"venue"
},
  "geometry": {"coordinates":[-89.573553,37.3262],"type":"Point"}
}