{
  "type": "Feature",
  "properties": {
    "iso:country":"US",
    "sg:address":"524 S Joplin Ave",
    "sg:city":"Joplin",
    "sg:classifiers":[
        {
            "category":"Restaurant",
            "type":"Food & Drink"
        }
    ],
    "sg:phone":"+1 417 659 4641",
    "sg:postcode":"64801",
    "sg:province":"MO",
    "sg:tags":[
        "eating"
    ],
    "wof:name":"Joplin Street Diner",
    "wof:placetype":"venue"
},
  "geometry": {"coordinates":[-94.51459199999999,37.085818],"type":"Point"}
}