{
  "type": "Feature",
  "properties": {
    "iso:country":"US",
    "sg:address":"105 W Main St",
    "sg:city":"Linn",
    "sg:classifiers":[
        {
            "category":"Insurance",
            "subcategory":"Insurance Agent",
            "type":"Services"
        },
        {
            "category":"Insurance",
            "subcategory":"Hazard Insurance",
            "type":"Services"
        },
        {
            "category":"Insurance",
            "subcategory":"Title Insurance",
            "type":"Services"
        },
        {
            "category":"Insurance",
            "subcategory":"Life Insurance",
            "type":"Services"
        }
    ],
    "sg:phone":"+1 573 897 4897",
    "sg:postcode":"65051",
    "sg:province":"MO",
    "sg:tags":[
        "business",
        "auto",
        "commercial",
        "homeowner",
        "motorcycle",
        "renter"
    ],
    "wof:name":"Allstate Insurance Company - Glenn Muenks",
    "wof:placetype":"venue"
},
  "geometry": {"coordinates":[-91.853508,38.48711],"type":"Point"}
}