{
  "type": "Feature",
  "properties": {
    "iso:country":"US",
    "sg:address":"1104 Platte Falls Rd",
    "sg:city":"Platte City",
    "sg:classifiers":[
        {
            "category":"Real Estate",
            "subcategory":"Real Estate Services",
            "type":"Services"
        }
    ],
    "sg:phone":"+1 816 858 5498",
    "sg:postcode":"64079",
    "sg:province":"MO",
    "sg:tags":[
        "company",
        "title"
    ],
    "wof:name":"Platte County Title & Abstract",
    "wof:placetype":"venue"
},
  "geometry": {"coordinates":[-94.76845299999999,39.353563],"type":"Point"}
}