{
  "type": "Feature",
  "properties": {
    "iso:country":"US",
    "sg:address":"1632 NW Chipman Rd",
    "sg:city":"Lees Summit",
    "sg:classifiers":[
        {
            "category":"Shopping",
            "subcategory":"Shoes",
            "type":"Retail Goods"
        }
    ],
    "sg:phone":"+1 816 525 6600",
    "sg:postcode":"64081",
    "sg:province":"MO",
    "wof:name":"Famous Footwear",
    "wof:placetype":"venue"
},
  "geometry": {"coordinates":[-94.407132,38.926131],"type":"Point"}
}