{
  "type": "Feature",
  "properties": {
    "iso:country":"US",
    "sg:address":"725 2nd St",
    "sg:city":"Osceola",
    "sg:classifiers":[
        {
            "category":"Personal",
            "subcategory":"Beauty Salon",
            "type":"Services"
        }
    ],
    "sg:phone":"+1 417 646 5521",
    "sg:postcode":"64776",
    "sg:province":"MO",
    "sg:tags":[
        "shop"
    ],
    "wof:name":"Super Scissors Clip N Curl",
    "wof:placetype":"venue"
},
  "geometry": {"coordinates":[-93.702815,38.047961],"type":"Point"}
}