{
  "type": "Feature",
  "properties": {
    "iso:country":"US",
    "sg:address":"12244 County Road 442",
    "sg:city":"Dudley",
    "sg:classifiers":[
        {
            "category":"Manufacturing",
            "subcategory":"Food",
            "type":"Manufacturing & Wholesale Goods"
        },
        {
            "category":"Farming",
            "subcategory":"Farm",
            "type":"Manufacturing & Wholesale Goods"
        }
    ],
    "sg:phone":"+1 573 624 3870",
    "sg:postcode":"63936",
    "sg:province":"MO",
    "sg:tags":[
        "corn",
        "product"
    ],
    "wof:name":"Wendell Pfeffer",
    "wof:placetype":"venue"
},
  "geometry": {"coordinates":[-90.05149,36.847771],"type":"Point"}
}