{
  "type": "Feature",
  "properties": {
    "iso:country":"US",
    "sg:address":"6714 Olive Blvd",
    "sg:city":"Saint Louis",
    "sg:classifiers":[
        {
            "category":"Bars & Pubs",
            "subcategory":"Dive Bar",
            "type":"Food & Drink"
        }
    ],
    "sg:phone":"+1 314 725 7375",
    "sg:postcode":"63130",
    "sg:province":"MO",
    "wof:name":"3rd Generation Bar",
    "wof:placetype":"venue"
},
  "geometry": {"coordinates":[-90.30830899999999,38.663114],"type":"Point"}
}