{
  "type": "Feature",
  "properties": {
    "iso:country":"US",
    "sg:address":"1 Industrial Dr",
    "sg:city":"Cuba",
    "sg:classifiers":[
        {
            "category":"Utilities",
            "subcategory":"Electric",
            "type":"Services"
        }
    ],
    "sg:phone":"+1 573 885 2521",
    "sg:postcode":"65453",
    "sg:province":"MO",
    "sg:tags":[
        "transformer"
    ],
    "sg:website":"http://www.meramec-electrical.com",
    "wof:name":"Meramec Electrical Products Inc",
    "wof:placetype":"venue"
},
  "geometry": {"coordinates":[-91.39823199999999,38.06023],"type":"Point"}
}