{
  "type": "Feature",
  "properties": {
    "iso:country":"US",
    "sg:address":"200 N Grant Ave",
    "sg:city":"Springfield",
    "sg:classifiers":[
        {
            "category":"Food & Beverages",
            "subcategory":"Liquor & Beverages",
            "type":"Retail Goods"
        }
    ],
    "sg:phone":"+1 417 874 7018",
    "sg:postcode":"65806",
    "sg:province":"MO",
    "wof:name":"Brown Derby Liquor Stores",
    "wof:placetype":"venue"
},
  "geometry": {"coordinates":[-93.29871,37.20899],"type":"Point"}
}