{
  "type": "Feature",
  "properties": {
    "iso:country":"US",
    "sg:address":"1813 SW Market St",
    "sg:city":"Lees Summit",
    "sg:classifiers":[
        {
            "category":"Retail",
            "subcategory":"Auto Repair",
            "type":"Services"
        }
    ],
    "sg:phone":"+1 816 525 8266",
    "sg:postcode":"64082",
    "sg:province":"MO",
    "sg:tags":[
        "repairing",
        "automobile"
    ],
    "wof:name":"ASR Automotive Ctr",
    "wof:placetype":"venue"
},
  "geometry": {"coordinates":[-94.37582399999999,38.887103],"type":"Point"}
}