{
  "type": "Feature",
  "properties": {
    "iso:country":"US",
    "sg:address":"8000 Bonhomme Ave",
    "sg:city":"St Louis",
    "sg:classifiers":[
        {
            "category":"Insurance",
            "subcategory":"Insurance Agent",
            "type":"Services"
        }
    ],
    "sg:phone":"+1 314 725 4250",
    "sg:postcode":"63105",
    "sg:province":"MO",
    "wof:name":"Denny M Black",
    "wof:placetype":"venue"
},
  "geometry": {"coordinates":[-90.34179399999999,38.647888],"type":"Point"}
}