{
  "type": "Feature",
  "properties": {
    "iso:country":"US",
    "sg:address":"25206 Walnut St",
    "sg:city":"Bell City",
    "sg:classifiers":[
        {
            "category":"Wholesale",
            "subcategory":"Vending Machines",
            "type":"Manufacturing & Wholesale Goods"
        }
    ],
    "sg:phone":"+1 573 733 8494",
    "sg:postcode":"63735",
    "sg:province":"MO",
    "sg:tags":[
        "operator"
    ],
    "wof:name":"Loose Change",
    "wof:placetype":"venue"
},
  "geometry": {"coordinates":[-89.823065,37.021934],"type":"Point"}
}