{
  "type": "Feature",
  "properties": {
    "iso:country":"US",
    "sg:address":"317 E Broadway St",
    "sg:city":"Monett",
    "sg:classifiers":[
        {
            "category":"Government",
            "subcategory":"Department Of Motor Vehicles",
            "type":"Public Place"
        }
    ],
    "sg:phone":"+1 417 235 3033",
    "sg:postcode":"65708",
    "sg:province":"MO",
    "sg:tags":[
        "refrigeration",
        "truck",
        "equipment"
    ],
    "wof:name":"Northern Refrigerated Express",
    "wof:placetype":"venue"
},
  "geometry": {"coordinates":[-93.924457,36.920543],"type":"Point"}
}