{
  "type": "Feature",
  "properties": {
    "iso:country":"US",
    "sg:address":"126 W Pine St",
    "sg:city":"Farmington",
    "sg:classifiers":[
        {
            "category":"Personal",
            "subcategory":"Beauty Salon",
            "type":"Services"
        }
    ],
    "sg:phone":"+1 573 747 1923",
    "sg:postcode":"63640",
    "sg:province":"MO",
    "wof:name":"Shear Designs",
    "wof:placetype":"venue"
},
  "geometry": {"coordinates":[-90.41706600000001,37.789471],"type":"Point"}
}