{
  "type": "Feature",
  "properties": {
    "iso:country":"US",
    "sg:address":"1120 E 16th St",
    "sg:city":"Sedalia",
    "sg:classifiers":[
        {
            "category":"Wholesale",
            "subcategory":"Groceries",
            "type":"Manufacturing & Wholesale Goods"
        }
    ],
    "sg:phone":"+1 660 827 2038",
    "sg:postcode":"65301",
    "sg:province":"MO",
    "sg:tags":[
        "confectionery"
    ],
    "wof:name":"Geotz Snack Sales",
    "wof:placetype":"venue"
},
  "geometry": {"coordinates":[-93.21467,38.696719],"type":"Point"}
}