{
  "type": "Feature",
  "properties": {
    "iso:country":"US",
    "sg:address":"600 Broadway St",
    "sg:city":"Kansas City",
    "sg:classifiers":[
        {
            "category":"Building & Trades",
            "subcategory":"Construction",
            "type":"Services"
        }
    ],
    "sg:phone":"+1 816 221 3500",
    "sg:postcode":"64105",
    "sg:province":"MO",
    "sg:tags":[
        "general",
        "contractor"
    ],
    "wof:name":"ESS Construction",
    "wof:placetype":"venue"
},
  "geometry": {"coordinates":[-94.58808399999999,39.106482],"type":"Point"}
}