{
  "type": "Feature",
  "properties": {
    "iso:country":"US",
    "sg:address":"2239 E 70 St",
    "sg:city":"Kansas City",
    "sg:classifiers":[
        {
            "category":"Building & Trades",
            "subcategory":"Electrical",
            "type":"Services"
        }
    ],
    "sg:phone":"+1 816 361 3113",
    "sg:postcode":"64132",
    "sg:province":"MO",
    "sg:tags":[
        "electrical",
        "contractor"
    ],
    "wof:name":"Custom Electric",
    "wof:placetype":"venue"
},
  "geometry": {"coordinates":[-94.559802,38.999912],"type":"Point"}
}