{
  "type": "Feature",
  "properties": {
    "iso:country":"US",
    "sg:address":"5538 Telegraph Rd",
    "sg:city":"St Louis",
    "sg:classifiers":[
        {
            "category":"Real Estate",
            "subcategory":"Real Estate Agent",
            "type":"Services"
        }
    ],
    "sg:phone":"+1 314 487 0050",
    "sg:postcode":"63129",
    "sg:province":"MO",
    "sg:website":"www.cbgundaker.com",
    "wof:name":"Coldwell Banker Gundaker",
    "wof:placetype":"venue"
},
  "geometry": {"coordinates":[-90.304503,38.471682],"type":"Point"}
}