{
  "type": "Feature",
  "properties": {
    "iso:country":"US",
    "sg:address":"14 Westport Rd",
    "sg:city":"Kansas City",
    "sg:classifiers":[
        {
            "category":"Retail",
            "subcategory":"Funeral Services",
            "type":"Services"
        }
    ],
    "sg:phone":"+1 816 561 8181",
    "sg:postcode":"64111",
    "sg:province":"MO",
    "sg:tags":[
        "business"
    ],
    "wof:name":"Marts Memorial Services",
    "wof:placetype":"venue"
},
  "geometry": {"coordinates":[-94.58731400000001,39.054915],"type":"Point"}
}