{
  "type": "Feature",
  "properties": {
    "iso:country":"US",
    "sg:address":"7015 N Oak Fwy",
    "sg:city":"Kansas City",
    "sg:classifiers":[
        {
            "category":"Shopping",
            "subcategory":"Used Merchandise",
            "type":"Retail Goods"
        }
    ],
    "sg:phone":"+1 816 436 5518",
    "sg:postcode":"64118",
    "sg:province":"MO",
    "wof:name":"Cash America",
    "wof:placetype":"venue"
},
  "geometry": {"coordinates":[-94.57602199999999,39.221378],"type":"Point"}
}