{
  "type": "Feature",
  "properties": {
    "iso:country":"US",
    "sg:address":"7409 E 227th St",
    "sg:city":"Peculiar",
    "sg:classifiers":[
        {
            "category":"Building & Trades",
            "subcategory":"Plumbing",
            "type":"Services"
        }
    ],
    "sg:phone":"+1 816 779 5501",
    "sg:postcode":"64078",
    "sg:province":"MO",
    "sg:tags":[
        "plumbing",
        "contractor"
    ],
    "wof:name":"Professional Plumbing Svc Inc",
    "wof:placetype":"venue"
},
  "geometry": {"coordinates":[-94.516587,38.712134],"type":"Point"}
}