{
  "type": "Feature",
  "properties": {
    "iso:country":"US",
    "sg:address":"4206 S Grand Blvd",
    "sg:city":"Saint Louis",
    "sg:classifiers":[
        {
            "category":"Food & Beverages",
            "subcategory":"Groceries & Convenience Stores",
            "type":"Retail Goods"
        }
    ],
    "sg:phone":"+1 314 752 2828",
    "sg:postcode":"63111",
    "sg:province":"MO",
    "wof:name":"Speedy Gas",
    "wof:placetype":"venue"
},
  "geometry": {"coordinates":[-90.2444,38.580799],"type":"Point"}
}