{
  "type": "Feature",
  "properties": {
    "addr:full":"13999 Manchester Rd Ballwin MO 63011",
    "addr:housenumber":"13999",
    "addr:postcode":"63011",
    "addr:street":"Manchester Rd",
    "iso:country":"US",
    "sg:address":"13999 Manchester Rd",
    "sg:city":"Ballwin",
    "sg:classifiers":[
        {
            "category":"Banks & Credit Unions",
            "subcategory":"Bank",
            "type":"Services"
        }
    ],
    "sg:phone":"+1 636 394 9808",
    "sg:postcode":"63011",
    "sg:province":"MO",
    "sg:tags":[
        "national",
        "commercial"
    ],
    "wof:name":"Bank Of America",
    "wof:placetype":"venue"
},
  "geometry": {"coordinates":[-90.48985399999999,38.595866],"type":"Point"}
}