{
  "type": "Feature",
  "properties": {
    "iso:country":"US",
    "sg:address":"7615 N Platte Purchase Dr",
    "sg:city":"Kansas City",
    "sg:classifiers":[
        {
            "category":"Social Services",
            "subcategory":"Child Care",
            "type":"Services"
        }
    ],
    "sg:phone":"+1 816 436 9990",
    "sg:postcode":"64118",
    "sg:province":"MO",
    "sg:tags":[
        "kindergarten",
        "academic",
        "school"
    ],
    "wof:name":"Children's Montessori Ctr",
    "wof:placetype":"venue"
},
  "geometry": {"coordinates":[-94.600835,39.236072],"type":"Point"}
}