{
  "type": "Feature",
  "properties": {
    "iso:country":"US",
    "sg:address":"101 E Benton St",
    "sg:city":"Carrollton",
    "sg:classifiers":[
        {
            "category":"Personal",
            "subcategory":"Beauty Salon",
            "type":"Services"
        }
    ],
    "sg:phone":"+1 660 542 0101",
    "sg:postcode":"64633",
    "sg:province":"MO",
    "wof:name":"Salon 101",
    "wof:placetype":"venue"
},
  "geometry": {"coordinates":[-93.495079,39.358521],"type":"Point"}
}