{
  "type": "Feature",
  "properties": {
    "iso:country":"US",
    "sg:address":"3 Donna Dr",
    "sg:city":"Saint Peters",
    "sg:classifiers":[
        {
            "category":"Professional",
            "subcategory":"Business Services",
            "type":"Services"
        }
    ],
    "sg:phone":"+1 636 379 0528",
    "sg:postcode":"63376",
    "sg:province":"MO",
    "wof:name":"Kiethline Enterprises LLC",
    "wof:placetype":"venue"
},
  "geometry": {"coordinates":[-90.663904,38.780869],"type":"Point"}
}