{
  "type": "Feature",
  "properties": {
    "iso:country":"US",
    "sg:address":"3153 Morgan Ford Rd",
    "sg:city":"Saint Louis",
    "sg:classifiers":[
        {
            "category":"Restaurant",
            "type":"Food & Drink"
        }
    ],
    "sg:phone":"+1 314 772 9800",
    "sg:postcode":"63116",
    "sg:province":"MO",
    "sg:tags":[
        "traditional",
        "american",
        "pizza"
    ],
    "sg:website":"www.3monkeysstl.com",
    "wof:name":"3 Monkeys",
    "wof:placetype":"venue"
},
  "geometry": {"coordinates":[-90.262087,38.602889],"type":"Point"}
}