{
  "type": "Feature",
  "properties": {
    "iso:country":"US",
    "sg:address":"14528 N Outer Rd",
    "sg:city":"Chesterfield",
    "sg:classifiers":[
        {
            "category":"Professional",
            "subcategory":"Management & Consulting",
            "type":"Services"
        }
    ],
    "sg:phone":"+1 314 628 3400",
    "sg:postcode":"63017",
    "sg:province":"MO",
    "sg:tags":[
        "chain",
        "supply"
    ],
    "wof:name":"Roi",
    "wof:placetype":"venue"
},
  "geometry": {"coordinates":[-90.550127,38.65189],"type":"Point"}
}