{
  "type": "Feature",
  "properties": {
    "iso:country":"US",
    "sg:address":"1050 E Walnut St",
    "sg:city":"Springfield",
    "sg:classifiers":[
        {
            "category":"Professional",
            "subcategory":"Lawyer & Legal Services",
            "type":"Services"
        }
    ],
    "sg:phone":"+1 417 863 9460",
    "sg:postcode":"65806",
    "sg:province":"MO",
    "wof:name":"Steven Senner Atty",
    "wof:placetype":"venue"
},
  "geometry": {"coordinates":[-93.281137,37.206584],"type":"Point"}
}