{
  "type": "Feature",
  "properties": {
    "iso:country":"US",
    "sg:address":"256 E Hadley St",
    "sg:city":"Republic",
    "sg:classifiers":[
        {
            "category":"Farming",
            "subcategory":"Livestock Farm",
            "type":"Manufacturing & Wholesale Goods"
        }
    ],
    "sg:phone":"+1 417 732 5353",
    "sg:postcode":"65738",
    "sg:province":"MO",
    "sg:tags":[
        "ranch"
    ],
    "wof:name":"Turnback Cattle Company",
    "wof:placetype":"venue"
},
  "geometry": {"coordinates":[-93.478179,37.106107],"type":"Point"}
}