{
  "type": "Feature",
  "properties": {
    "iso:country":"US",
    "sg:address":"1401 Harris Ave",
    "sg:city":"Trenton",
    "sg:classifiers":[
        {
            "category":"Wholesale",
            "subcategory":"Meat",
            "type":"Manufacturing & Wholesale Goods"
        }
    ],
    "sg:phone":"+1 660 359 3913",
    "sg:postcode":"64683",
    "sg:province":"MO",
    "sg:tags":[
        "prod",
        "prepared"
    ],
    "sg:website":"www.conagrafoods.com",
    "wof:name":"Trenton Home Foods Inc",
    "wof:placetype":"venue"
},
  "geometry": {"coordinates":[-93.609084,40.081036],"type":"Point"}
}