{
  "type": "Feature",
  "properties": {
    "iso:country":"US",
    "sg:address":"1314 E 33 St",
    "sg:city":"Kansas City",
    "sg:classifiers":[
        {
            "category":"Real Estate",
            "subcategory":"Real Estate Operator",
            "type":"Services"
        }
    ],
    "sg:phone":"+1 816 931 2617",
    "sg:postcode":"64109",
    "sg:province":"MO",
    "sg:tags":[
        "building",
        "apartment"
    ],
    "wof:name":"Paradise Properties",
    "wof:placetype":"venue"
},
  "geometry": {"coordinates":[-94.568652,39.066855],"type":"Point"}
}