{
  "type": "Feature",
  "properties": {
    "iso:country":"US",
    "sg:address":"2438 McNair",
    "sg:city":"Saint Louis",
    "sg:classifiers":[
        {
            "category":"Deli",
            "type":"Food & Drink"
        }
    ],
    "sg:phone":"+1 314 773 8225",
    "sg:postcode":"63118",
    "sg:province":"MO",
    "sg:website":"www.bluescitydeli.com/",
    "wof:name":"Blues City Deli",
    "wof:placetype":"venue"
},
  "geometry": {"coordinates":[-90.21801,38.60569],"type":"Point"}
}