{
  "type": "Feature",
  "properties": {
    "iso:country":"US",
    "sg:address":"862 Hyde Park Dr",
    "sg:city":"Arnold",
    "sg:classifiers":[
        {
            "category":"Wholesale",
            "subcategory":"Non-durable Goods",
            "type":"Manufacturing & Wholesale Goods"
        }
    ],
    "sg:phone":"+1 636 282 2855",
    "sg:postcode":"63010",
    "sg:province":"MO",
    "wof:name":"Knittery",
    "wof:placetype":"venue"
},
  "geometry": {"coordinates":[-90.36672900000001,38.442831],"type":"Point"}
}