{
  "type": "Feature",
  "properties": {
    "iso:country":"US",
    "sg:address":"165 US Hwy 24",
    "sg:city":"Independence",
    "sg:classifiers":[
        {
            "category":"Banks & Credit Unions",
            "subcategory":"Bank",
            "type":"Services"
        }
    ],
    "sg:phone":"+1 816 254 2288",
    "sg:postcode":"64050",
    "sg:province":"MO",
    "sg:tags":[
        "loan",
        "broker"
    ],
    "wof:name":"Just Say Cash",
    "wof:placetype":"venue"
},
  "geometry": {"coordinates":[-94.413084,39.101198],"type":"Point"}
}