{
  "type": "Feature",
  "properties": {
    "iso:country":"US",
    "sg:address":"6557 Manchester Ave",
    "sg:city":"St Louis",
    "sg:classifiers":[
        {
            "category":"Freight",
            "type":"Transportation"
        }
    ],
    "sg:phone":"+1 314 646 7867",
    "sg:postcode":"63139",
    "sg:province":"MO",
    "sg:tags":[
        "commercial",
        "storage"
    ],
    "wof:name":"Cornerstone Self Storage",
    "wof:placetype":"venue"
},
  "geometry": {"coordinates":[-90.301934,38.618836],"type":"Point"}
}