{
  "type": "Feature",
  "properties": {
    "iso:country":"US",
    "sg:address":"8455 Gravois Rd",
    "sg:city":"St Louis",
    "sg:classifiers":[
        {
            "category":"Shopping",
            "subcategory":"Tobacco",
            "type":"Retail Goods"
        }
    ],
    "sg:phone":"+1 314 351 7714",
    "sg:postcode":"63123",
    "sg:province":"MO",
    "sg:tags":[
        "cigarette",
        "product",
        "cigar",
        "dealer",
        "merchandise"
    ],
    "wof:name":"Dirt Cheap Cigarettes & Beer",
    "wof:placetype":"venue"
},
  "geometry": {"coordinates":[-90.305393,38.557713],"type":"Point"}
}