{
  "type": "Feature",
  "properties": {
    "iso:country":"US",
    "sg:address":"1145 Belgrove Dr",
    "sg:city":"St Louis",
    "sg:classifiers":[
        {
            "category":"Building & Trades",
            "subcategory":"Construction",
            "type":"Services"
        }
    ],
    "sg:phone":"+1 314 867 5222",
    "sg:postcode":"63137",
    "sg:province":"MO",
    "sg:tags":[
        "general",
        "work",
        "commercial",
        "contractor"
    ],
    "wof:name":"Duggan F Construction Co",
    "wof:placetype":"venue"
},
  "geometry": {"coordinates":[-90.205715,38.764495],"type":"Point"}
}