{
  "type": "Feature",
  "properties": {
    "iso:country":"US",
    "sg:address":"845 US Hwy 60",
    "sg:city":"Monett",
    "sg:classifiers":[
        {
            "category":"Utilities",
            "subcategory":"Mobile Phone",
            "type":"Services"
        }
    ],
    "sg:phone":"+1 417 235 3862",
    "sg:postcode":"65708",
    "sg:province":"MO",
    "sg:tags":[
        "communication",
        "telephone",
        "cellular",
        "radiotelephone"
    ],
    "wof:name":"Russell Cellular",
    "wof:placetype":"venue"
},
  "geometry": {"coordinates":[-93.947633,36.915929],"type":"Point"}
}