{
  "type": "Feature",
  "properties": {
    "iso:country":"US",
    "sg:address":"1000 N Main St",
    "sg:city":"Sainte Genevieve",
    "sg:classifiers":[
        {
            "category":"Manufacturing",
            "subcategory":"Toys & Sporting Goods",
            "type":"Manufacturing & Wholesale Goods"
        }
    ],
    "sg:phone":"+1 573 883 5777",
    "sg:postcode":"63670",
    "sg:province":"MO",
    "sg:tags":[
        "mfg"
    ],
    "wof:name":"Lipp Plastics Manufacturing Co",
    "wof:placetype":"venue"
},
  "geometry": {"coordinates":[-90.047017,37.988667],"type":"Point"}
}