{
  "type": "Feature",
  "properties": {
    "iso:country":"US",
    "sg:address":"220 S Main St",
    "sg:city":"Joplin",
    "sg:classifiers":[
        {
            "category":"Shopping",
            "subcategory":"Stationery & Office Supplies",
            "type":"Retail Goods"
        },
        {
            "category":"Wholesale",
            "subcategory":"Office Equipment",
            "type":"Manufacturing & Wholesale Goods"
        },
        {
            "category":"Manufacturing",
            "subcategory":"Electronics",
            "type":"Manufacturing & Wholesale Goods"
        },
        {
            "category":"Professional",
            "subcategory":"Printing & Photocopies",
            "type":"Services"
        }
    ],
    "sg:phone":"+1 417 624 7447",
    "sg:postcode":"64801",
    "sg:province":"MO",
    "sg:tags":[
        "equipment-wholesale",
        "duplicating",
        "machine",
        "copying",
        "printers-equipment",
        "copy",
        "manufacturer",
        "furniture"
    ],
    "sg:website":"http://www.ambussys.com",
    "wof:name":"American Business Systems Co",
    "wof:placetype":"venue"
},
  "geometry": {"coordinates":[-94.513237,37.089582],"type":"Point"}
}