{
  "type": "Feature",
  "properties": {
    "iso:country":"US",
    "sg:address":"722 S Caneer St",
    "sg:city":"Senath",
    "sg:classifiers":[
        {
            "category":"Government",
            "subcategory":"Office",
            "type":"Public Place"
        }
    ],
    "sg:phone":"+1 573 738 2209",
    "sg:postcode":"63876",
    "sg:province":"MO",
    "sg:tags":[
        "government-united",
        "state"
    ],
    "wof:name":"Senath Housing Authority",
    "wof:placetype":"venue"
},
  "geometry": {"coordinates":[-90.16385,36.123479],"type":"Point"}
}