{
  "type": "Feature",
  "properties": {
    "iso:country":"US",
    "sg:address":"3131 E Division St",
    "sg:city":"Springfield",
    "sg:classifiers":[
        {
            "category":"Professional",
            "type":"Services"
        }
    ],
    "sg:phone":"+1 417 831 1862",
    "sg:postcode":"65802",
    "sg:province":"MO",
    "sg:tags":[
        "establishment"
    ],
    "wof:name":"Unimark Warehouse",
    "wof:placetype":"venue"
},
  "geometry": {"coordinates":[-93.2306,37.224463],"type":"Point"}
}