{
  "type": "Feature",
  "properties": {
    "iso:country":"US",
    "sg:address":"90 Smith St",
    "sg:city":"Gower",
    "sg:classifiers":[
        {
            "category":"Building & Trades",
            "subcategory":"Electrical",
            "type":"Services"
        }
    ],
    "sg:phone":"+1 816 424 6810",
    "sg:postcode":"64454",
    "sg:province":"MO",
    "wof:name":"Falcon Cable",
    "wof:placetype":"venue"
},
  "geometry": {"coordinates":[-94.598782,39.609],"type":"Point"}
}