{
  "type": "Feature",
  "properties": {
    "iso:country":"US",
    "sg:address":"108 Frizzell St",
    "sg:city":"Potosi",
    "sg:classifiers":[
        {
            "category":"Health Services",
            "subcategory":"Nursing And Care Facility",
            "type":"Services"
        }
    ],
    "sg:phone":"+1 573 438 8500",
    "sg:postcode":"63664",
    "sg:province":"MO",
    "sg:tags":[
        "nurse",
        "practice-arnp",
        "nurses-advanced"
    ],
    "wof:name":"Young Constance RN BC Fnp",
    "wof:placetype":"venue"
},
  "geometry": {"coordinates":[-90.780474,37.932124],"type":"Point"}
}