{
  "type": "Feature",
  "properties": {
    "iso:country":"US",
    "sg:address":"4282 County Road 637",
    "sg:city":"Arbyrd",
    "sg:classifiers":[
        {
            "category":"Manufacturing",
            "subcategory":"Food",
            "type":"Manufacturing & Wholesale Goods"
        },
        {
            "category":"Farming",
            "subcategory":"Farm",
            "type":"Manufacturing & Wholesale Goods"
        }
    ],
    "sg:phone":"+1 573 654 2119",
    "sg:postcode":"63821",
    "sg:province":"MO",
    "sg:tags":[
        "corn",
        "product"
    ],
    "wof:name":"Denny Haddock",
    "wof:placetype":"venue"
},
  "geometry": {"coordinates":[-90.195178,36.051254],"type":"Point"}
}