{
  "type": "Feature",
  "properties": {
    "iso:country":"US",
    "sg:address":"1010 S Bishop Ave",
    "sg:city":"Rolla",
    "sg:classifiers":[
        {
            "category":"Home & Garden",
            "subcategory":"Furniture",
            "type":"Retail Goods"
        }
    ],
    "sg:phone":"+1 573 426 4790",
    "sg:postcode":"65401",
    "sg:province":"MO",
    "wof:name":"Miss Charlotte's Used Furnitur",
    "wof:placetype":"venue"
},
  "geometry": {"coordinates":[-91.779197,37.928806],"type":"Point"}
}