{
  "type": "Feature",
  "properties": {
    "iso:country":"US",
    "sg:address":"1992 State Hwy 7",
    "sg:city":"Blue Springs",
    "sg:classifiers":[
        {
            "category":"Restaurant",
            "type":"Food & Drink"
        }
    ],
    "sg:phone":"+1 816 224 3126",
    "sg:postcode":"64014",
    "sg:province":"MO",
    "wof:name":"Quiznos Sub",
    "wof:placetype":"venue"
},
  "geometry": {"coordinates":[-94.273205,38.997144],"type":"Point"}
}