{
  "type": "Feature",
  "properties": {
    "iso:country":"US",
    "sg:address":"201 Johnson Cir",
    "sg:city":"Carrollton",
    "sg:classifiers":[
        {
            "category":"Real Estate",
            "subcategory":"Real Estate Operator",
            "type":"Services"
        }
    ],
    "sg:phone":"+1 660 542 2134",
    "sg:postcode":"64633",
    "sg:province":"MO",
    "sg:tags":[
        "property",
        "lessor"
    ],
    "wof:name":"Jane Freeman",
    "wof:placetype":"venue"
},
  "geometry": {"coordinates":[-93.492785,39.37072],"type":"Point"}
}