{
  "type": "Feature",
  "properties": {
    "iso:country":"US",
    "sg:address":"11120 US Hwy 24",
    "sg:city":"Independence",
    "sg:classifiers":[
        {
            "category":"Cinema",
            "subcategory":"Movie Rental",
            "type":"Entertainment"
        }
    ],
    "sg:phone":"+1 816 252 8188",
    "sg:postcode":"64054",
    "sg:province":"MO",
    "sg:tags":[
        "leasing",
        "video",
        "disc",
        "tape"
    ],
    "wof:name":"Blockbuster Video",
    "wof:placetype":"venue"
},
  "geometry": {"coordinates":[-94.445238,39.102546],"type":"Point"}
}