{
  "type": "Feature",
  "properties": {
    "iso:country":"US",
    "sg:address":"601 E Smith St",
    "sg:city":"California",
    "sg:classifiers":[
        {
            "category":"Health Services",
            "subcategory":"Chiropractor",
            "type":"Services"
        }
    ],
    "sg:phone":"+1 573 796 4651",
    "sg:postcode":"65018",
    "sg:province":"MO",
    "wof:name":"Hug Chiropractic",
    "wof:placetype":"venue"
},
  "geometry": {"coordinates":[-92.559639,38.629453],"type":"Point"}
}