{
  "type": "Feature",
  "properties": {
    "iso:country":"US",
    "sg:address":"7290 Manchester Rd",
    "sg:city":"Maplewood",
    "sg:classifiers":[
        {
            "category":"Shopping",
            "subcategory":"Jewelry",
            "type":"Retail Goods"
        },
        {
            "category":"Home & Garden",
            "subcategory":"Home Furnishings",
            "type":"Retail Goods"
        }
    ],
    "sg:phone":"+1 314 645 1155",
    "sg:postcode":"63143",
    "sg:province":"MO",
    "sg:tags":[
        "decor"
    ],
    "sg:website":"mavenstl.com",
    "wof:name":"Maven",
    "wof:placetype":"venue"
},
  "geometry": {"coordinates":[-90.316769,38.613389],"type":"Point"}
}