{
  "type": "Feature",
  "properties": {
    "iso:country":"US",
    "sg:address":"3809 S Kingshighway Blvd",
    "sg:city":"Saint Louis",
    "sg:classifiers":[
        {
            "category":"Shopping",
            "subcategory":"Jewelry",
            "type":"Retail Goods"
        }
    ],
    "sg:phone":"+1 314 351 8388",
    "sg:postcode":"63109",
    "sg:province":"MO",
    "wof:name":"Queens Jewelry",
    "wof:placetype":"venue"
},
  "geometry": {"coordinates":[-90.273279,38.591493],"type":"Point"}
}