{
  "type": "Feature",
  "properties": {
    "iso:country":"US",
    "sg:address":"9990 Crabapple Rd SE",
    "sg:city":"Agency",
    "sg:classifiers":[
        {
            "category":"Manufacturing",
            "subcategory":"Food",
            "type":"Manufacturing & Wholesale Goods"
        }
    ],
    "sg:phone":"+1 816 253 9502",
    "sg:postcode":"64401",
    "sg:province":"MO",
    "sg:tags":[
        "product"
    ],
    "wof:name":"David Kelsey",
    "wof:placetype":"venue"
},
  "geometry": {"coordinates":[-94.69449,39.60855],"type":"Point"}
}