{
  "type": "Feature",
  "properties": {
    "iso:country":"US",
    "sg:address":"709 Monroe St",
    "sg:city":"Desloge",
    "sg:classifiers":[
        {
            "category":"Shopping",
            "type":"Retail Goods"
        }
    ],
    "sg:phone":"+1 573 431 8958",
    "sg:postcode":"63601",
    "sg:province":"MO",
    "sg:tags":[
        "merchandise"
    ],
    "wof:name":"Cemetery Lettering",
    "wof:placetype":"venue"
},
  "geometry": {"coordinates":[-90.525593,37.86431],"type":"Point"}
}