{
  "type": "Feature",
  "properties": {
    "iso:country":"US",
    "sg:address":"6204 Dr Martin Luther King Dr",
    "sg:city":"St Louis",
    "sg:classifiers":[
        {
            "category":"Home & Garden",
            "subcategory":"Furniture",
            "type":"Retail Goods"
        }
    ],
    "sg:phone":"+1 314 385 2081",
    "sg:postcode":"63133",
    "sg:province":"MO",
    "wof:name":"Arvin's Appliance Furniture/AC",
    "wof:placetype":"venue"
},
  "geometry": {"coordinates":[-90.286917,38.676047],"type":"Point"}
}