{
  "type": "Feature",
  "properties": {
    "iso:country":"US",
    "sg:address":"2015 Hwy K",
    "sg:city":"O Fallon",
    "sg:classifiers":[
        {
            "category":"Personal",
            "subcategory":"Beauty Salon",
            "type":"Services"
        }
    ],
    "sg:phone":"+1 636 281 9598",
    "sg:postcode":"63366",
    "sg:province":"MO",
    "sg:tags":[
        "shop"
    ],
    "wof:name":"Hair Happening",
    "wof:placetype":"venue"
},
  "geometry": {"coordinates":[-90.69980700000001,38.78234],"type":"Point"}
}