{
  "type": "Feature",
  "properties": {
    "iso:country":"US",
    "sg:address":"195 Co Rd 435",
    "sg:city":"New Franklin",
    "sg:classifiers":[
        {
            "category":"Building & Trades",
            "subcategory":"Construction",
            "type":"Services"
        }
    ],
    "sg:phone":"+1 573 698 3004",
    "sg:postcode":"65274",
    "sg:province":"MO",
    "sg:tags":[
        "contractor"
    ],
    "wof:name":"De Felice Construction",
    "wof:placetype":"venue"
},
  "geometry": {"coordinates":[-92.591961,38.997675],"type":"Point"}
}