{
  "type": "Feature",
  "properties": {
    "iso:country":"US",
    "sg:address":"400 NW Barry Rd",
    "sg:city":"Kansas City",
    "sg:classifiers":[
        {
            "category":"Shopping",
            "subcategory":"Gifts & Souvenirs",
            "type":"Retail Goods"
        }
    ],
    "sg:phone":"+1 816 436 1012",
    "sg:postcode":"64155",
    "sg:province":"MO",
    "sg:tags":[
        "engraving",
        "custom"
    ],
    "wof:name":"Things Remembered",
    "wof:placetype":"venue"
},
  "geometry": {"coordinates":[-94.589716,39.246488],"type":"Point"}
}