{
  "type": "Feature",
  "properties": {
    "iso:country":"US",
    "sg:address":"617 Barbara Pl",
    "sg:city":"Festus",
    "sg:classifiers":[
        {
            "category":"Professional",
            "subcategory":"Accounting & Tax Preparation",
            "type":"Services"
        },
        {
            "category":"Professional",
            "subcategory":"Management & Consulting",
            "type":"Services"
        },
        {
            "category":"Banks & Credit Unions",
            "subcategory":"Financial Services",
            "type":"Services"
        }
    ],
    "sg:phone":"+1 636 931 2000",
    "sg:postcode":"63028",
    "sg:province":"MO",
    "sg:tags":[
        "financing",
        "return",
        "preparation-business",
        "consultant",
        "loan",
        "planning"
    ],
    "wof:name":"Computax Inc",
    "wof:placetype":"venue"
},
  "geometry": {"coordinates":[-90.389354,38.214383],"type":"Point"}
}