{
  "type": "Feature",
  "properties": {
    "iso:country":"US",
    "sg:address":"1204 Live Oak Ln",
    "sg:city":"Warrensburg",
    "sg:classifiers":[
        {
            "category":"Building & Trades",
            "subcategory":"Construction",
            "type":"Services"
        }
    ],
    "sg:phone":"+1 660 429 3440",
    "sg:postcode":"64093",
    "sg:province":"MO",
    "sg:tags":[
        "excavating",
        "contractor"
    ],
    "wof:name":"Fretco Inc",
    "wof:placetype":"venue"
},
  "geometry": {"coordinates":[-93.75567100000001,38.744839],"type":"Point"}
}