{
  "type": "Feature",
  "properties": {
    "iso:country":"US",
    "sg:address":"22775 Audrain Road 812",
    "sg:city":"Mexico",
    "sg:classifiers":[
        {
            "category":"Banks & Credit Unions",
            "subcategory":"Bank",
            "type":"Services"
        },
        {
            "category":"Shopping",
            "subcategory":"Used Merchandise",
            "type":"Retail Goods"
        }
    ],
    "sg:phone":"+1 573 581 4213",
    "sg:postcode":"65265",
    "sg:province":"MO",
    "sg:tags":[
        "shop",
        "second",
        "resale",
        "hand"
    ],
    "wof:name":"Simple Tymes",
    "wof:placetype":"venue"
},
  "geometry": {"coordinates":[-91.879017,39.137007],"type":"Point"}
}