{
  "type": "Feature",
  "properties": {
    "iso:country":"US",
    "sg:address":"3675 S Noland Rd",
    "sg:city":"Independence",
    "sg:classifiers":[
        {
            "category":"Real Estate",
            "subcategory":"Real Estate Agent",
            "type":"Services"
        }
    ],
    "sg:phone":"+1 816 833 1488",
    "sg:postcode":"64055",
    "sg:province":"MO",
    "wof:name":"Mike's Farm",
    "wof:placetype":"venue"
},
  "geometry": {"coordinates":[-94.414776,39.057113],"type":"Point"}
}