{
  "type": "Feature",
  "properties": {
    "iso:country":"US",
    "sg:address":"1111 E Republic Rd",
    "sg:city":"Springfield",
    "sg:classifiers":[
        {
            "category":"Personal",
            "subcategory":"Nail Salon",
            "type":"Services"
        }
    ],
    "sg:phone":"+1 417 881 5553",
    "sg:postcode":"65807",
    "sg:province":"MO",
    "wof:name":"Rainbow Nails",
    "wof:placetype":"venue"
},
  "geometry": {"coordinates":[-93.27983500000001,37.138248],"type":"Point"}
}