{
  "type": "Feature",
  "properties": {
    "iso:country":"US",
    "sg:address":"10875 Indian Head Industrl Blvd",
    "sg:city":"Olivette",
    "sg:classifiers":[
        {
            "category":"Manufacturing",
            "subcategory":"Food",
            "type":"Manufacturing & Wholesale Goods"
        }
    ],
    "sg:phone":"+1 314 426 7273",
    "sg:postcode":"63132",
    "sg:province":"MO",
    "sg:tags":[
        "product",
        "chinese"
    ],
    "wof:name":"Deli Food Mfg Inc",
    "wof:placetype":"venue"
},
  "geometry": {"coordinates":[-90.396867,38.689553],"type":"Point"}
}