{
  "type": "Feature",
  "properties": {
    "iso:country":"US",
    "sg:address":"210 SE Douglas St",
    "sg:city":"Lees Summit",
    "sg:classifiers":[
        {
            "category":"Personal",
            "subcategory":"Beauty Salon",
            "type":"Services"
        }
    ],
    "sg:phone":"+1 816 347 1501",
    "sg:postcode":"64063",
    "sg:province":"MO",
    "sg:tags":[
        "shop"
    ],
    "wof:name":"Salon 210",
    "wof:placetype":"venue"
},
  "geometry": {"coordinates":[-94.376852,38.913397],"type":"Point"}
}