{
  "type": "Feature",
  "properties": {
    "iso:country":"US",
    "sg:address":"9330 Manchester Rd",
    "sg:city":"Webster Groves",
    "sg:classifiers":[
        {
            "category":"Autos & Motor Vehicles",
            "subcategory":"Auto Supplies",
            "type":"Retail Goods"
        }
    ],
    "sg:phone":"+1 314 961 6603",
    "sg:postcode":"63119",
    "sg:province":"MO",
    "sg:tags":[
        "automobile",
        "parts"
    ],
    "wof:name":"NAPA Auto Parts",
    "wof:placetype":"venue"
},
  "geometry": {"coordinates":[-90.360816,38.610451],"type":"Point"}
}