{
  "type": "Feature",
  "properties": {
    "iso:country":"US",
    "sg:address":"8111 Maryland Ave",
    "sg:city":"St Louis",
    "sg:classifiers":[
        {
            "category":"Personal",
            "subcategory":"Beauty Salon",
            "type":"Services"
        }
    ],
    "sg:phone":"+1 314 725 6179",
    "sg:postcode":"63105",
    "sg:province":"MO",
    "sg:tags":[
        "shop"
    ],
    "wof:name":"Salon Blanca",
    "wof:placetype":"venue"
},
  "geometry": {"coordinates":[-90.343143,38.652322],"type":"Point"}
}