{
  "type": "Feature",
  "properties": {
    "iso:country":"US",
    "sg:address":"1749 Gilsinn Ln",
    "sg:city":"Fenton",
    "sg:classifiers":[
        {
            "category":"Health Services",
            "subcategory":"Nursing And Care Facility",
            "type":"Services"
        },
        {
            "category":"Health Services",
            "subcategory":"Health Practitioner",
            "type":"Services"
        }
    ],
    "sg:phone":"+1 636 343 3803",
    "sg:postcode":"63026",
    "sg:province":"MO",
    "sg:tags":[
        "home",
        "eldercare-home"
    ],
    "wof:name":"Catalano Home Health Care",
    "wof:placetype":"venue"
},
  "geometry": {"coordinates":[-90.464314,38.540373],"type":"Point"}
}