{
  "type": "Feature",
  "properties": {
    "iso:country":"US",
    "sg:address":"402 Country Oak Dr",
    "sg:city":"Chesterfield",
    "sg:classifiers":[
        {
            "category":"Shopping",
            "subcategory":"Catalog Store",
            "type":"Retail Goods"
        }
    ],
    "sg:phone":"+1 314 542 2540",
    "sg:postcode":"63017",
    "sg:province":"MO",
    "wof:name":"Nouveau Technologies",
    "wof:placetype":"venue"
},
  "geometry": {"coordinates":[-90.52034399999999,38.672859],"type":"Point"}
}