{
  "type": "Feature",
  "properties": {
    "iso:country":"US",
    "sg:address":"4290 State Rte P",
    "sg:city":"Pomona",
    "sg:classifiers":[
        {
            "category":"Food & Beverages",
            "subcategory":"Groceries & Convenience Stores",
            "type":"Retail Goods"
        },
        {
            "category":"Autos & Motor Vehicles",
            "subcategory":"Fuel & Gas Station",
            "type":"Retail Goods"
        }
    ],
    "sg:phone":"+1 417 469 1483",
    "sg:postcode":"65789",
    "sg:province":"MO",
    "sg:tags":[
        "station",
        "gasoline"
    ],
    "wof:name":"Fas-Serv Market 3",
    "wof:placetype":"venue"
},
  "geometry": {"coordinates":[-91.919684,36.866767],"type":"Point"}
}