{
  "type": "Feature",
  "properties": {
    "iso:country":"US",
    "sg:address":"905 W Exchange St",
    "sg:city":"Kahoka",
    "sg:classifiers":[
        {
            "category":"Building & Trades",
            "subcategory":"Construction",
            "type":"Services"
        }
    ],
    "sg:phone":"+1 660 727 8023",
    "sg:postcode":"63445",
    "sg:province":"MO",
    "sg:tags":[
        "house"
    ],
    "wof:name":"Spriggs Home Repair",
    "wof:placetype":"venue"
},
  "geometry": {"coordinates":[-91.72962800000001,40.419608],"type":"Point"}
}