{
  "type": "Feature",
  "properties": {
    "iso:country":"US",
    "sg:address":"4160 Old Mill Pkwy",
    "sg:city":"St Peters",
    "sg:classifiers":[
        {
            "category":"Communications",
            "subcategory":"Film & Video Production",
            "type":"Services"
        }
    ],
    "sg:phone":"+1 636 279 1222",
    "sg:postcode":"63376",
    "sg:province":"MO",
    "sg:tags":[
        "taping"
    ],
    "wof:name":"TCI Cablevision Of Missouri",
    "wof:placetype":"venue"
},
  "geometry": {"coordinates":[-90.57463,38.790192],"type":"Point"}
}