{
  "type": "Feature",
  "properties": {
    "iso:country":"US",
    "sg:address":"1011 E Montclair St",
    "sg:city":"Springfield",
    "sg:classifiers":[
        {
            "category":"Professional",
            "type":"Services"
        },
        {
            "category":"Health Services",
            "subcategory":"Doctor",
            "type":"Services"
        }
    ],
    "sg:phone":"+1 417 890 8877",
    "sg:postcode":"65807",
    "sg:province":"MO",
    "sg:tags":[
        "physician",
        "surgeon"
    ],
    "wof:name":"Arnold Vision LLC",
    "wof:placetype":"venue"
},
  "geometry": {"coordinates":[-93.28110599999999,37.157817],"type":"Point"}
}