{
  "type": "Feature",
  "properties": {
    "iso:country":"US",
    "sg:address":"610 S Main St",
    "sg:city":"Saint Charles",
    "sg:classifiers":[
        {
            "category":"Shopping",
            "subcategory":"Gifts & Souvenirs",
            "type":"Retail Goods"
        }
    ],
    "sg:phone":"+1 636 947 6672",
    "sg:postcode":"63301",
    "sg:province":"MO",
    "wof:name":"Little Hills Emporium",
    "wof:placetype":"venue"
},
  "geometry": {"coordinates":[-90.483735,38.776475],"type":"Point"}
}