{
  "type": "Feature",
  "properties": {
    "iso:country":"US",
    "sg:address":"27143 Prairie Rd",
    "sg:city":"Sedalia",
    "sg:classifiers":[
        {
            "category":"Farming",
            "subcategory":"Farm",
            "type":"Manufacturing & Wholesale Goods"
        }
    ],
    "sg:phone":"+1 660 827 1795",
    "sg:postcode":"65301",
    "sg:province":"MO",
    "sg:tags":[
        "crop",
        "general"
    ],
    "wof:name":"Larry D Wilson Farms Inc",
    "wof:placetype":"venue"
},
  "geometry": {"coordinates":[-93.326144,38.683179],"type":"Point"}
}