{
  "type": "Feature",
  "properties": {
    "iso:country":"US",
    "sg:address":"2812 Hazel St",
    "sg:city":"Carthage",
    "sg:classifiers":[
        {
            "category":"Fast Food",
            "type":"Food & Drink"
        },
        {
            "category":"Restaurant",
            "type":"Food & Drink"
        }
    ],
    "sg:phone":"+1 417 358 4602",
    "sg:postcode":"64836",
    "sg:province":"MO",
    "sg:tags":[
        "shop",
        "hamburger",
        "dog",
        "hot",
        "fountain",
        "soda",
        "american"
    ],
    "sg:website":"http://www.awrestaurants.com",
    "wof:name":"A & W Restaurants",
    "wof:placetype":"venue"
},
  "geometry": {"coordinates":[-94.319603,37.139326],"type":"Point"}
}