{
  "type": "Feature",
  "properties": {
    "iso:country":"US",
    "sg:address":"268 S Jefferson Ave",
    "sg:city":"Marshall",
    "sg:classifiers":[
        {
            "category":"Health Services",
            "subcategory":"Doctor",
            "type":"Services"
        }
    ],
    "sg:phone":"+1 660 886 2842",
    "sg:postcode":"65340",
    "sg:province":"MO",
    "sg:tags":[
        "physician",
        "family",
        "gynecology",
        "practice",
        "surgeons",
        "obstetrics",
        "medicine"
    ],
    "sg:website":"http://www.centralmissouriwomenshealthcare.com",
    "wof:name":"Central Missouri Women's Healthcare",
    "wof:placetype":"venue"
},
  "geometry": {"coordinates":[-93.19600199999999,39.118872],"type":"Point"}
}