{
  "type": "Feature",
  "properties": {
    "iso:country":"US",
    "sg:address":"303 Jefferson St",
    "sg:city":"Spickard",
    "sg:classifiers":[
        {
            "category":"Government",
            "subcategory":"Office",
            "type":"Public Place"
        }
    ],
    "sg:phone":"+1 660 485 6106",
    "sg:postcode":"64679",
    "sg:province":"MO",
    "sg:tags":[
        "executive"
    ],
    "wof:name":"City Of Spickard",
    "wof:placetype":"venue"
},
  "geometry": {"coordinates":[-93.594801,40.244545],"type":"Point"}
}