{
  "type": "Feature",
  "properties": {
    "iso:country":"US",
    "sg:address":"3002 Kaiser Hill Rd",
    "sg:city":"New Haven",
    "sg:classifiers":[
        {
            "category":"Freight",
            "type":"Transportation"
        }
    ],
    "sg:phone":"+1 573 237 3628",
    "sg:postcode":"63068",
    "sg:province":"MO",
    "sg:tags":[
        "operator",
        "trucking"
    ],
    "wof:name":"CRST",
    "wof:placetype":"venue"
},
  "geometry": {"coordinates":[-91.26231900000001,38.603473],"type":"Point"}
}