{
  "type": "Feature",
  "properties": {
    "iso:country":"US",
    "sg:address":"1209 Hickory Run Ln",
    "sg:city":"Chesterfield",
    "sg:classifiers":[
        {
            "category":"Communications",
            "subcategory":"Film & Video Production",
            "type":"Services"
        }
    ],
    "sg:phone":"+1 636 458 1564",
    "sg:postcode":"63005",
    "sg:province":"MO",
    "sg:tags":[
        "taping"
    ],
    "wof:name":"Digital Mediamark LLC",
    "wof:placetype":"venue"
},
  "geometry": {"coordinates":[-90.72709399999999,38.605605],"type":"Point"}
}