{
  "type": "Feature",
  "properties": {
    "iso:country":"US",
    "sg:address":"1163 E Karsch Blvd",
    "sg:city":"Farmington",
    "sg:classifiers":[
        {
            "category":"Freight",
            "type":"Transportation"
        }
    ],
    "sg:phone":"+1 573 756 3228",
    "sg:postcode":"63640",
    "sg:province":"MO",
    "sg:tags":[
        "commercial",
        "storage",
        "special"
    ],
    "wof:name":"M & M Self Storage",
    "wof:placetype":"venue"
},
  "geometry": {"coordinates":[-90.40505,37.779634],"type":"Point"}
}