{
  "type": "Feature",
  "properties": {
    "iso:country":"US",
    "sg:address":"1600 Genessee St",
    "sg:city":"Kansas City",
    "sg:classifiers":[
        {
            "category":"Manufacturing",
            "subcategory":"Printing",
            "type":"Manufacturing & Wholesale Goods"
        }
    ],
    "sg:phone":"+1 816 471 0200",
    "sg:postcode":"64102",
    "sg:province":"MO",
    "sg:tags":[
        "publisher"
    ],
    "wof:name":"Missouri Beef Cattlemen",
    "wof:placetype":"venue"
},
  "geometry": {"coordinates":[-94.605063,39.093409],"type":"Point"}
}