{
  "type": "Feature",
  "properties": {
    "iso:country":"US",
    "sg:address":"242 Chesterfield Mall",
    "sg:city":"Chesterfield",
    "sg:classifiers":[
        {
            "category":"Shopping",
            "type":"Retail Goods"
        }
    ],
    "sg:phone":"+1 636 537 1341",
    "sg:postcode":"63017",
    "sg:province":"MO",
    "sg:tags":[
        "sunglasses",
        "accessory"
    ],
    "wof:name":"Sunglass Hut 181",
    "wof:placetype":"venue"
},
  "geometry": {"coordinates":[-90.562242,38.649829],"type":"Point"}
}