{
  "type": "Feature",
  "properties": {
    "addr:full":"2503 River Winds Ct St Louis MO 63129",
    "addr:housenumber":"2503",
    "addr:postcode":"63129",
    "addr:street":"River Winds Ct",
    "iso:country":"US",
    "sg:address":"2503 River Winds Ct",
    "sg:city":"St Louis",
    "sg:classifiers":[
        {
            "category":"Shopping",
            "type":"Retail Goods"
        }
    ],
    "sg:phone":"+1 314 846 0893",
    "sg:postcode":"63129",
    "sg:province":"MO",
    "sg:tags":[
        "chemical"
    ],
    "wof:name":"Naquest Chemical Co",
    "wof:placetype":"venue"
},
  "geometry": {"coordinates":[-90.313875,38.42537],"type":"Point"}
}