{
  "type": "Feature",
  "properties": {
    "iso:country":"US",
    "sg:address":"785 Brownell Ave",
    "sg:city":"St Louis",
    "sg:classifiers":[
        {
            "category":"Building & Trades",
            "subcategory":"Construction",
            "type":"Services"
        }
    ],
    "sg:phone":"+1 314 965 0995",
    "sg:postcode":"63122",
    "sg:province":"MO",
    "sg:tags":[
        "repairing",
        "remodeling",
        "contractor"
    ],
    "wof:name":"Rosenberg Inc",
    "wof:placetype":"venue"
},
  "geometry": {"coordinates":[-90.39091000000001,38.593757],"type":"Point"}
}