{
  "type": "Feature",
  "properties": {
    "iso:country":"US",
    "sg:address":"319 N Main St",
    "sg:city":"St Charles",
    "sg:classifiers":[
        {
            "category":"Shopping",
            "subcategory":"Used Merchandise",
            "type":"Retail Goods"
        }
    ],
    "sg:phone":"+1 636 946 1898",
    "sg:postcode":"63301",
    "sg:province":"MO",
    "sg:tags":[
        "antique",
        "repair"
    ],
    "wof:name":"Antiques & Oak",
    "wof:placetype":"venue"
},
  "geometry": {"coordinates":[-90.480119,38.783728],"type":"Point"}
}