{
  "type": "Feature",
  "properties": {
    "iso:country":"US",
    "sg:address":"316 Kirk Dr",
    "sg:city":"Ferguson",
    "sg:classifiers":[
        {
            "category":"Education",
            "subcategory":"Special Training",
            "type":"Public Place"
        }
    ],
    "sg:phone":"+1 314 521 2980",
    "sg:postcode":"63135",
    "sg:province":"MO",
    "sg:tags":[
        "tutoring"
    ],
    "wof:name":"Be Smart Tutorial Svc",
    "wof:placetype":"venue"
},
  "geometry": {"coordinates":[-90.28335300000001,38.741067],"type":"Point"}
}