{
  "type": "Feature",
  "properties": {
    "iso:country":"US",
    "sg:address":"3801 Eminence Ave",
    "sg:city":"Saint Louis",
    "sg:classifiers":[
        {
            "category":"Shopping",
            "subcategory":"Bicycles & Sporting Goods",
            "type":"Retail Goods"
        }
    ],
    "sg:phone":"+1 314 423 7554",
    "sg:postcode":"63134",
    "sg:province":"MO",
    "wof:name":"Dixie Little Flies",
    "wof:placetype":"venue"
},
  "geometry": {"coordinates":[-90.350191,38.723901],"type":"Point"}
}