{
  "type": "Feature",
  "properties": {
    "iso:country":"US",
    "sg:address":"2507 SE Outer Rd",
    "sg:city":"Harrisonville",
    "sg:classifiers":[
        {
            "category":"Government",
            "subcategory":"Fire Station",
            "type":"Public Place"
        }
    ],
    "sg:phone":"+1 816 884 3366",
    "sg:postcode":"64701",
    "sg:province":"MO",
    "sg:tags":[
        "department"
    ],
    "wof:name":"Fire Department",
    "wof:placetype":"venue"
},
  "geometry": {"coordinates":[-94.352655,38.638045],"type":"Point"}
}