{
  "type": "Feature",
  "properties": {
    "iso:country":"US",
    "sg:address":"527 Huntridge Dr",
    "sg:city":"Columbia",
    "sg:classifiers":[
        {
            "category":"Communications",
            "subcategory":"Film & Video Production",
            "type":"Services"
        }
    ],
    "sg:phone":"+1 573 441 1648",
    "sg:postcode":"65201",
    "sg:province":"MO",
    "sg:tags":[
        "motion"
    ],
    "wof:name":"Corkery Dan",
    "wof:placetype":"venue"
},
  "geometry": {"coordinates":[-92.332007,38.918173],"type":"Point"}
}