{
  "type": "Feature",
  "properties": {
    "iso:country":"US",
    "sg:address":"684 Country Club Dr",
    "sg:city":"Lake Ozark",
    "sg:classifiers":[
        {
            "category":"Shopping",
            "subcategory":"Computers & Home Electronics",
            "type":"Retail Goods"
        }
    ],
    "sg:phone":"+1 573 964 5767",
    "sg:postcode":"65049",
    "sg:province":"MO",
    "sg:tags":[
        "software"
    ],
    "wof:name":"Specialized Disaster Systems",
    "wof:placetype":"venue"
},
  "geometry": {"coordinates":[-92.694884,38.195015],"type":"Point"}
}