{
  "type": "Feature",
  "properties": {
    "iso:country":"US",
    "sg:address":"3109 Cedar Crest Ln",
    "sg:city":"Chillicothe",
    "sg:classifiers":[
        {
            "category":"Organizations",
            "subcategory":"Non-profit Organization",
            "type":"Services"
        }
    ],
    "sg:phone":"+1 660 646 5330",
    "sg:postcode":"64601",
    "sg:province":"MO",
    "sg:tags":[
        "community",
        "social"
    ],
    "wof:name":"Rural Development Consultants",
    "wof:placetype":"venue"
},
  "geometry": {"coordinates":[-93.559415,39.814463],"type":"Point"}
}