{
  "type": "Feature",
  "properties": {
    "iso:country":"US",
    "sg:address":"2208 S Jefferson Ave",
    "sg:city":"Saint Louis",
    "sg:classifiers":[
        {
            "category":"Restaurant",
            "type":"Food & Drink"
        }
    ],
    "sg:phone":"+1 314 664 7777",
    "sg:postcode":"63118",
    "sg:province":"MO",
    "sg:tags":[
        "american",
        "latin"
    ],
    "sg:website":"www.fritangastl.net",
    "wof:name":"Fritanga",
    "wof:placetype":"venue"
},
  "geometry": {"coordinates":[-90.221801,38.609624],"type":"Point"}
}