{
  "type": "Feature",
  "properties": {
    "iso:country":"US",
    "sg:address":"2313 State Hwy 173",
    "sg:city":"Galena",
    "sg:classifiers":[
        {
            "category":"Retail",
            "subcategory":"Auto Repair",
            "type":"Services"
        }
    ],
    "sg:phone":"+1 417 357 0041",
    "sg:postcode":"65656",
    "sg:province":"MO",
    "sg:tags":[
        "repairing",
        "automobile"
    ],
    "wof:name":"Crossroads Automotive",
    "wof:placetype":"venue"
},
  "geometry": {"coordinates":[-93.533344,36.82275],"type":"Point"}
}