{
  "type": "Feature",
  "properties": {
    "iso:country":"US",
    "sg:address":"7711 Elm Ave",
    "sg:city":"Kansas City",
    "sg:classifiers":[
        {
            "category":"Professional",
            "type":"Services"
        }
    ],
    "sg:phone":"+1 816 313 1962",
    "sg:postcode":"64138",
    "sg:province":"MO",
    "wof:name":"Harry Renne",
    "wof:placetype":"venue"
},
  "geometry": {"coordinates":[-94.472801,38.980322],"type":"Point"}
}