{
  "type": "Feature",
  "properties": {
    "iso:country":"US",
    "sg:address":"120 E 4th St",
    "sg:city":"Winfield",
    "sg:classifiers":[
        {
            "category":"Professional",
            "subcategory":"Computer Services",
            "type":"Services"
        }
    ],
    "sg:phone":"+1 636 566 8358",
    "sg:postcode":"63382",
    "sg:province":"MO",
    "wof:name":"Specialty Computers",
    "wof:placetype":"venue"
},
  "geometry": {"coordinates":[-91.481471,39.302397],"type":"Point"}
}