{
  "type": "Feature",
  "properties": {
    "iso:country":"US",
    "sg:address":"502 S Hughes St",
    "sg:city":"Hamilton",
    "sg:classifiers":[
        {
            "category":"Farming",
            "subcategory":"Farm",
            "type":"Manufacturing & Wholesale Goods"
        }
    ],
    "sg:phone":"+1 816 583 2279",
    "sg:postcode":"64644",
    "sg:province":"MO",
    "sg:tags":[
        "crop",
        "general"
    ],
    "wof:name":"C Palmer",
    "wof:placetype":"venue"
},
  "geometry": {"coordinates":[-94.00061599999999,39.736652],"type":"Point"}
}