{
  "type": "Feature",
  "properties": {
    "iso:country":"US",
    "sg:address":"107 Clover Rd",
    "sg:city":"Hannibal",
    "sg:classifiers":[
        {
            "category":"Shopping",
            "subcategory":"Florist",
            "type":"Retail Goods"
        }
    ],
    "sg:phone":"+1 573 221 2209",
    "sg:postcode":"63401",
    "sg:province":"MO",
    "wof:name":"Flowers & Gifts From Heart",
    "wof:placetype":"venue"
},
  "geometry": {"coordinates":[-91.414368,39.727962],"type":"Point"}
}