{
  "type": "Feature",
  "properties": {
    "iso:country":"US",
    "sg:address":"585 State Road M",
    "sg:city":"Auxvasse",
    "sg:classifiers":[
        {
            "category":"Retail",
            "subcategory":"Auto Repair",
            "type":"Services"
        }
    ],
    "sg:phone":"+1 573 387 4892",
    "sg:postcode":"65231",
    "sg:province":"MO",
    "sg:tags":[
        "body",
        "painting",
        "repairing",
        "automobile"
    ],
    "wof:name":"M&M Auto Body & Sales",
    "wof:placetype":"venue"
},
  "geometry": {"coordinates":[-92.033728,39.043123],"type":"Point"}
}