{
  "type": "Feature",
  "properties": {
    "iso:country":"US",
    "sg:address":"1404 E Jefferson St",
    "sg:city":"Kirksville",
    "sg:classifiers":[
        {
            "category":"Organizations",
            "subcategory":"Community Association",
            "type":"Services"
        }
    ],
    "sg:phone":"+1 660 665 3449",
    "sg:postcode":"63501",
    "sg:province":"MO",
    "wof:name":"Optimist International",
    "wof:placetype":"venue"
},
  "geometry": {"coordinates":[-92.569076,40.192988],"type":"Point"}
}