{
  "type": "Feature",
  "properties": {
    "iso:country":"US",
    "sg:address":"144 NW 361st Rd",
    "sg:city":"Warrensburg",
    "sg:classifiers":[
        {
            "category":"Recreation",
            "type":"Entertainment"
        }
    ],
    "sg:phone":"+1 660 747 1811",
    "sg:postcode":"64019",
    "sg:province":"MO",
    "sg:tags":[
        "fairground"
    ],
    "wof:name":"Johnson County Fair Assoc",
    "wof:placetype":"venue"
},
  "geometry": {"coordinates":[-93.809997,38.786774],"type":"Point"}
}