{
  "type": "Feature",
  "properties": {
    "iso:country":"US",
    "sg:address":"917 Miller St",
    "sg:city":"New Haven",
    "sg:classifiers":[
        {
            "category":"Building & Trades",
            "subcategory":"Plumbing",
            "type":"Services"
        }
    ],
    "sg:phone":"+1 573 237 3022",
    "sg:postcode":"63068",
    "sg:province":"MO",
    "sg:tags":[
        "plumbing",
        "contractor"
    ],
    "wof:name":"Gerald D Pinnell LLC",
    "wof:placetype":"venue"
},
  "geometry": {"coordinates":[-91.21474000000001,38.611355],"type":"Point"}
}