{
  "type": "Feature",
  "properties": {
    "iso:country":"US",
    "sg:address":"1104 S Walnut St",
    "sg:city":"Cameron",
    "sg:classifiers":[
        {
            "category":"Autos & Motor Vehicles",
            "subcategory":"Auto Supplies",
            "type":"Retail Goods"
        }
    ],
    "sg:phone":"+1 816 632 3790",
    "sg:postcode":"64429",
    "sg:province":"MO",
    "sg:tags":[
        "stereo",
        "shell",
        "automobile",
        "system",
        "caps",
        "truck",
        "radio",
        "liner"
    ],
    "sg:website":"http://www.visionaudioinc.com",
    "wof:name":"Vision Audio Inc",
    "wof:placetype":"venue"
},
  "geometry": {"coordinates":[-94.236925,39.729422],"type":"Point"}
}