{
  "type": "Feature",
  "properties": {
    "iso:country":"US",
    "sg:address":"107 S Main St",
    "sg:city":"Fayette",
    "sg:classifiers":[
        {
            "category":"Personal",
            "subcategory":"Beauty Salon",
            "type":"Services"
        }
    ],
    "sg:phone":"+1 660 248 2777",
    "sg:postcode":"65248",
    "sg:province":"MO",
    "sg:tags":[
        "hair",
        "shop",
        "stylist"
    ],
    "wof:name":"Carol's Hair Styling",
    "wof:placetype":"venue"
},
  "geometry": {"coordinates":[-92.682597,39.146143],"type":"Point"}
}