{
  "type": "Feature",
  "properties": {
    "iso:country":"US",
    "sg:address":"101 State Dr",
    "sg:city":"Hollister",
    "sg:classifiers":[
        {
            "category":"Structure",
            "subcategory":"Office Building",
            "type":"Public Place"
        }
    ],
    "sg:phone":"+1 417 334 6627",
    "sg:postcode":"65672",
    "sg:province":"MO",
    "sg:tags":[
        "park"
    ],
    "sg:website":"http://www.bransonsreview.com",
    "wof:name":"Tri Sons Properties",
    "wof:placetype":"venue"
},
  "geometry": {"coordinates":[-93.24284400000001,36.600101],"type":"Point"}
}