{
  "type": "Feature",
  "properties": {
    "iso:country":"US",
    "sg:address":"809 S Logan St",
    "sg:city":"Independence",
    "sg:classifiers":[
        {
            "category":"Building & Trades",
            "subcategory":"Construction",
            "type":"Services"
        }
    ],
    "sg:phone":"+1 816 716 1866",
    "sg:postcode":"64050",
    "sg:province":"MO",
    "sg:tags":[
        "contractor"
    ],
    "wof:name":"Roof Masters",
    "wof:placetype":"venue"
},
  "geometry": {"coordinates":[-94.40434399999999,39.083084],"type":"Point"}
}