{
  "type": "Feature",
  "properties": {
    "iso:country":"US",
    "sg:address":"5301 Arsenal St",
    "sg:city":"St Louis",
    "sg:classifiers":[
        {
            "category":"Autos & Motor Vehicles",
            "subcategory":"Automobile Sales",
            "type":"Retail Goods"
        }
    ],
    "sg:phone":"+1 314 664 8889",
    "sg:postcode":"63139",
    "sg:province":"MO",
    "sg:tags":[
        "car",
        "used",
        "dealer"
    ],
    "wof:name":"All Auto Sales",
    "wof:placetype":"venue"
},
  "geometry": {"coordinates":[-90.27857899999999,38.605934],"type":"Point"}
}