{
  "type": "Feature",
  "properties": {
    "iso:country":"US",
    "sg:address":"3680 N Farm Rd 129",
    "sg:city":"Springfield",
    "sg:classifiers":[
        {
            "category":"Building & Trades",
            "subcategory":"Construction",
            "type":"Services"
        }
    ],
    "sg:phone":"+1 417 833 0966",
    "sg:postcode":"65803",
    "sg:province":"MO",
    "sg:tags":[
        "house"
    ],
    "wof:name":"Mitchells Construction",
    "wof:placetype":"venue"
},
  "geometry": {"coordinates":[-93.34822,37.26304],"type":"Point"}
}