{
  "type": "Feature",
  "properties": {
    "iso:country":"US",
    "sg:address":"15620 Manchester Rd",
    "sg:city":"Ellisville",
    "sg:classifiers":[
        {
            "category":"Insurance",
            "subcategory":"Hazard Insurance",
            "type":"Services"
        }
    ],
    "sg:phone":"+1 636 227 9900",
    "sg:postcode":"63011",
    "sg:province":"MO",
    "sg:tags":[
        "commercial",
        "business"
    ],
    "wof:name":"Health Insurance",
    "wof:placetype":"venue"
},
  "geometry": {"coordinates":[-90.573822,38.592709],"type":"Point"}
}