{
  "type": "Feature",
  "properties": {
    "iso:country":"US",
    "sg:address":"10274 Page Ave",
    "sg:city":"Saint Louis",
    "sg:classifiers":[
        {
            "category":"Retail",
            "subcategory":"Repair Shop",
            "type":"Services"
        }
    ],
    "sg:phone":"+1 636 394 4613",
    "sg:postcode":"63132",
    "sg:province":"MO",
    "wof:name":"AAA Key & Lock Service",
    "wof:placetype":"venue"
},
  "geometry": {"coordinates":[-90.386374,38.690951],"type":"Point"}
}