{
  "type": "Feature",
  "properties": {
    "iso:country":"US",
    "sg:address":"8476 N State Hwy 125",
    "sg:city":"Strafford",
    "sg:classifiers":[
        {
            "category":"Professional",
            "subcategory":"Business Services",
            "type":"Services"
        }
    ],
    "sg:phone":"+1 417 759 2347",
    "sg:postcode":"65757",
    "sg:province":"MO",
    "sg:tags":[
        "auctioneer"
    ],
    "wof:name":"Easterly Auction Svc",
    "wof:placetype":"venue"
},
  "geometry": {"coordinates":[-93.13360299999999,37.346549],"type":"Point"}
}