{
  "type": "Feature",
  "properties": {
    "iso:country":"US",
    "sg:address":"504 Townsend St",
    "sg:city":"Cassville",
    "sg:classifiers":[
        {
            "category":"Manufacturing",
            "subcategory":"Buildings",
            "type":"Manufacturing & Wholesale Goods"
        },
        {
            "category":"Building & Trades",
            "subcategory":"Construction",
            "type":"Services"
        }
    ],
    "sg:phone":"+1 417 847 0594",
    "sg:postcode":"65625",
    "sg:province":"MO",
    "sg:tags":[
        "home",
        "builder",
        "contractor"
    ],
    "wof:name":"Sloan Custom Homes Inc",
    "wof:placetype":"venue"
},
  "geometry": {"coordinates":[-93.870232,36.678093],"type":"Point"}
}