{
  "type": "Feature",
  "properties": {
    "iso:country":"US",
    "sg:address":"1732 W Adams Ave",
    "sg:city":"Saint Louis",
    "sg:classifiers":[
        {
            "category":"Real Estate",
            "subcategory":"Architect",
            "type":"Services"
        }
    ],
    "sg:phone":"+1 314 965 8624",
    "sg:postcode":"63122",
    "sg:province":"MO",
    "sg:tags":[
        "architectural"
    ],
    "wof:name":"Thomas Teasdale",
    "wof:placetype":"venue"
},
  "geometry": {"coordinates":[-90.43495799999999,38.58161],"type":"Point"}
}