{
  "type": "Feature",
  "properties": {
    "iso:country":"US",
    "sg:address":"9905 Walnut Dr",
    "sg:city":"Kansas City",
    "sg:classifiers":[
        {
            "category":"Insurance",
            "subcategory":"Insurance Agent",
            "type":"Services"
        }
    ],
    "sg:phone":"+1 816 761 3300",
    "sg:postcode":"64114",
    "sg:province":"MO",
    "wof:name":"Group Concepts Inc",
    "wof:placetype":"venue"
},
  "geometry": {"coordinates":[-94.591431,38.947827],"type":"Point"}
}