{
  "type": "Feature",
  "properties": {
    "iso:country":"US",
    "sg:address":"208 E 2nd St",
    "sg:city":"Fulton",
    "sg:classifiers":[
        {
            "category":"Shopping",
            "subcategory":"Gifts & Souvenirs",
            "type":"Retail Goods"
        }
    ],
    "sg:phone":"+1 573 642 6711",
    "sg:postcode":"65251",
    "sg:province":"MO",
    "sg:tags":[
        "cards",
        "greeting"
    ],
    "wof:name":"Westlake's Hallmark Shop",
    "wof:placetype":"venue"
},
  "geometry": {"coordinates":[-91.946214,38.844377],"type":"Point"}
}