{
  "type": "Feature",
  "properties": {
    "iso:country":"US",
    "sg:address":"1200 Briarbrook Dr",
    "sg:city":"Carl Junction",
    "sg:classifiers":[
        {
            "category":"Shopping",
            "subcategory":"Bicycles & Sporting Goods",
            "type":"Retail Goods"
        }
    ],
    "sg:phone":"+1 417 782 4477",
    "sg:postcode":"64834",
    "sg:province":"MO",
    "sg:tags":[
        "equipment",
        "golf",
        "supply"
    ],
    "wof:name":"Golf Hut",
    "wof:placetype":"venue"
},
  "geometry": {"coordinates":[-94.53762399999999,37.145508],"type":"Point"}
}