{
  "type": "Feature",
  "properties": {
    "iso:country":"US",
    "sg:address":"4446 Parktowne Dr",
    "sg:city":"Saint Charles",
    "sg:classifiers":[
        {
            "category":"Shopping",
            "subcategory":"Discount & Variety Stores",
            "type":"Retail Goods"
        }
    ],
    "sg:phone":"+1 636 477 8800",
    "sg:postcode":"63304",
    "sg:province":"MO",
    "sg:tags":[
        "military",
        "gear"
    ],
    "wof:name":"Highway 94 Boot Camp Hdqtr",
    "wof:placetype":"venue"
},
  "geometry": {"coordinates":[-90.607218,38.741925],"type":"Point"}
}