{
  "type": "Feature",
  "properties": {
    "iso:country":"US",
    "sg:address":"615 Cherokee Dr Ste 4B",
    "sg:city":"Marshall",
    "sg:classifiers":[
        {
            "category":"Government",
            "subcategory":"Office",
            "type":"Public Place"
        }
    ],
    "sg:phone":"+1 660 886 5549",
    "sg:postcode":"65340",
    "sg:province":"MO",
    "sg:tags":[
        "government-state"
    ],
    "sg:website":"http://www.stateparks.com",
    "wof:name":"Missouri Department Of Agriculture",
    "wof:placetype":"venue"
},
  "geometry": {"coordinates":[-93.213342,39.112714],"type":"Point"}
}