{
  "type": "Feature",
  "properties": {
    "iso:country":"US",
    "sg:address":"1273 Doctors Dr",
    "sg:city":"Farmington",
    "sg:classifiers":[
        {
            "category":"Health Services",
            "subcategory":"Dentist",
            "type":"Services"
        }
    ],
    "sg:phone":"+1 573 760 0440",
    "sg:postcode":"63640",
    "sg:province":"MO",
    "sg:tags":[
        "product",
        "dentists-cosmetic",
        "dental",
        "dentistry",
        "whitening",
        "hygienist",
        "teeth"
    ],
    "sg:website":"http://www.westmountdentalarts.com",
    "wof:name":"Westmount Dental Arts",
    "wof:placetype":"venue"
},
  "geometry": {"coordinates":[-90.44135799999999,37.778262],"type":"Point"}
}