{
  "type": "Feature",
  "properties": {
    "iso:country":"US",
    "sg:address":"3102 Erika Ave",
    "sg:city":"Sedalia",
    "sg:classifiers":[
        {
            "category":"Insurance",
            "subcategory":"Insurance Agent",
            "type":"Services"
        }
    ],
    "sg:phone":"+1 660 827 0492",
    "sg:postcode":"65301",
    "sg:province":"MO",
    "sg:tags":[
        "processing"
    ],
    "wof:name":"Medical Billing Assoc",
    "wof:placetype":"venue"
},
  "geometry": {"coordinates":[-93.24733999999999,38.68511],"type":"Point"}
}