{
  "type": "Feature",
  "properties": {
    "iso:country":"US",
    "sg:address":"5863 Suemandy Rd",
    "sg:city":"Saint Peters",
    "sg:classifiers":[
        {
            "category":"Health Services",
            "subcategory":"Doctor",
            "type":"Services"
        }
    ],
    "sg:phone":"+1 636 970 4700",
    "sg:postcode":"63376",
    "sg:province":"MO",
    "wof:name":"Bhatia Orthodontics",
    "wof:placetype":"venue"
},
  "geometry": {"coordinates":[-90.622373,38.796372],"type":"Point"}
}