{
  "type": "Feature",
  "properties": {
    "iso:country":"US",
    "sg:address":"11640 Gravois Rd",
    "sg:city":"Sappington",
    "sg:classifiers":[
        {
            "category":"Retail",
            "subcategory":"Auto Rental",
            "type":"Services"
        }
    ],
    "sg:phone":"+1 314 849 4800",
    "sg:postcode":"63126",
    "sg:province":"MO",
    "sg:tags":[
        "automobile",
        "leasing"
    ],
    "wof:name":"Enterprise Rent-A-Car",
    "wof:placetype":"venue"
},
  "geometry": {"coordinates":[-90.384568,38.533009],"type":"Point"}
}