{
  "type": "Feature",
  "properties": {
    "iso:country":"US",
    "sg:address":"3721 Washington Blvd",
    "sg:city":"St Louis",
    "sg:classifiers":[
        {
            "category":"Arts & Performance",
            "subcategory":"Art Gallery",
            "type":"Entertainment"
        }
    ],
    "sg:phone":"+1 314 531 3030",
    "sg:postcode":"63108",
    "sg:province":"MO",
    "sg:website":"www.brunodavidgallery.com",
    "wof:name":"Bruno David Gallery",
    "wof:placetype":"venue"
},
  "geometry": {"coordinates":[-90.234203,38.640675],"type":"Point"}
}