{
  "type": "Feature",
  "properties": {
    "iso:country":"US",
    "sg:address":"4014 Union Blvd",
    "sg:city":"St Louis",
    "sg:classifiers":[
        {
            "category":"Government",
            "subcategory":"Police Station",
            "type":"Public Place"
        }
    ],
    "sg:phone":"+1 314 444 0001",
    "sg:postcode":"63115",
    "sg:province":"MO",
    "sg:tags":[
        "department"
    ],
    "wof:name":"St Louis Police Dept",
    "wof:placetype":"venue"
},
  "geometry": {"coordinates":[-90.25617,38.682037],"type":"Point"}
}