{
  "type": "Feature",
  "properties": {
    "iso:country":"US",
    "sg:address":"3785 Huster Rd",
    "sg:city":"Saint Charles",
    "sg:classifiers":[
        {
            "category":"Building & Trades",
            "subcategory":"Landscaping Services",
            "type":"Services"
        }
    ],
    "sg:phone":"+1 636 723 0200",
    "sg:postcode":"63301",
    "sg:province":"MO",
    "wof:name":"Landscape Maintenance Inc",
    "wof:placetype":"venue"
},
  "geometry": {"coordinates":[-90.53055500000001,38.817741],"type":"Point"}
}