{
  "type": "Feature",
  "properties": {
    "iso:country":"US",
    "sg:address":"1699 S Hanley Rd",
    "sg:city":"St Louis",
    "sg:classifiers":[
        {
            "category":"Professional",
            "subcategory":"Computer Services",
            "type":"Services"
        }
    ],
    "sg:phone":"+1 314 647 1099",
    "sg:postcode":"63144",
    "sg:province":"MO",
    "sg:tags":[
        "chemical",
        "licensing",
        "library",
        "software"
    ],
    "sg:website":"www.tripos.com",
    "wof:name":"Tripos Inc",
    "wof:placetype":"venue"
},
  "geometry": {"coordinates":[-90.33506800000001,38.625319],"type":"Point"}
}