{
  "type": "Feature",
  "properties": {
    "iso:country":"US",
    "sg:address":"1299 W 5th St",
    "sg:city":"Eureka",
    "sg:classifiers":[
        {
            "category":"Wholesale",
            "subcategory":"Auto Parts",
            "type":"Manufacturing & Wholesale Goods"
        }
    ],
    "sg:phone":"+1 636 938 5165",
    "sg:postcode":"63025",
    "sg:province":"MO",
    "wof:name":"NAPA Auto Parts",
    "wof:placetype":"venue"
},
  "geometry": {"coordinates":[-90.65251600000001,38.504351],"type":"Point"}
}