{
  "type": "Feature",
  "properties": {
    "iso:country":"US",
    "sg:address":"765 S Odell Ave",
    "sg:city":"Marshall",
    "sg:classifiers":[
        {
            "category":"Retail",
            "subcategory":"Auto Repair",
            "type":"Services"
        }
    ],
    "sg:phone":"+1 660 831 5126",
    "sg:postcode":"65340",
    "sg:province":"MO",
    "sg:tags":[
        "repairing",
        "automobile"
    ],
    "wof:name":"Eastwood Automotive",
    "wof:placetype":"venue"
},
  "geometry": {"coordinates":[-93.195026,39.114058],"type":"Point"}
}