{
  "type": "Feature",
  "properties": {
    "iso:country":"US",
    "sg:address":"110 Washington St",
    "sg:city":"Doniphan",
    "sg:classifiers":[
        {
            "category":"Communications",
            "subcategory":"Newspaper",
            "type":"Services"
        }
    ],
    "sg:phone":"+1 573 996 2103",
    "sg:postcode":"63935",
    "sg:province":"MO",
    "wof:name":"Butler County Publishing",
    "wof:placetype":"venue"
},
  "geometry": {"coordinates":[-90.826365,36.61755],"type":"Point"}
}