{
  "type": "Feature",
  "properties": {
    "iso:country":"US",
    "sg:address":"1002 E Hubach Hill Rd",
    "sg:city":"Raymore",
    "sg:classifiers":[
        {
            "category":"Wholesale",
            "subcategory":"Machinery & Supplies",
            "type":"Manufacturing & Wholesale Goods"
        }
    ],
    "sg:phone":"+1 816 322 8242",
    "sg:postcode":"64083",
    "sg:province":"MO",
    "sg:tags":[
        "barbecue",
        "equipment"
    ],
    "wof:name":"Bubba D Enterprises Inc",
    "wof:placetype":"venue"
},
  "geometry": {"coordinates":[-94.439651,38.78178],"type":"Point"}
}