{
  "type": "Feature",
  "properties": {
    "iso:country":"US",
    "sg:address":"4140 Old Homestead Dr",
    "sg:city":"Imperial",
    "sg:classifiers":[
        {
            "category":"Building & Trades",
            "subcategory":"Construction",
            "type":"Services"
        }
    ],
    "sg:phone":"+1 636 287 5060",
    "sg:postcode":"63052",
    "sg:province":"MO",
    "sg:tags":[
        "house"
    ],
    "wof:name":"Boyster Home Improvement",
    "wof:placetype":"venue"
},
  "geometry": {"coordinates":[-90.48543600000001,38.438513],"type":"Point"}
}