{
  "type": "Feature",
  "properties": {
    "iso:country":"US",
    "sg:address":"605 N Sherman Pkwy",
    "sg:city":"Springfield",
    "sg:classifiers":[
        {
            "category":"Utilities",
            "subcategory":"Telephone",
            "type":"Services"
        }
    ],
    "sg:phone":"+1 417 865 8392",
    "sg:postcode":"65802",
    "sg:province":"MO",
    "sg:tags":[
        "telecommunication"
    ],
    "wof:name":"C B Management Co Inc",
    "wof:placetype":"venue"
},
  "geometry": {"coordinates":[-93.281283,37.213535],"type":"Point"}
}