{
  "type": "Feature",
  "properties": {
    "iso:country":"US",
    "sg:address":"1562 N Marjorie Ln",
    "sg:city":"Springfield",
    "sg:classifiers":[
        {
            "category":"Wholesale",
            "subcategory":"Machinery & Supplies",
            "type":"Manufacturing & Wholesale Goods"
        }
    ],
    "sg:phone":"+1 417 864 8556",
    "sg:postcode":"65803",
    "sg:province":"MO",
    "sg:tags":[
        "plumbing",
        "repair",
        "indus"
    ],
    "wof:name":"Richards Pump Service",
    "wof:placetype":"venue"
},
  "geometry": {"coordinates":[-93.358912,37.22755],"type":"Point"}
}