{
  "type": "Feature",
  "properties": {
    "addr:full":"11245 Saint Charles Rock Rd Bridgeton MO 63044",
    "addr:housenumber":"11245",
    "addr:postcode":"63044",
    "addr:street":"Saint Charles Rock Rd",
    "iso:country":"US",
    "sg:address":"11245 Saint Charles Rock Rd",
    "sg:city":"Bridgeton",
    "sg:classifiers":[
        {
            "category":"Home & Garden",
            "subcategory":"Building Materials",
            "type":"Retail Goods"
        }
    ],
    "sg:phone":"+1 314 291 5288",
    "sg:postcode":"63044",
    "sg:province":"MO",
    "sg:tags":[
        "center"
    ],
    "wof:name":"Home Depot",
    "wof:placetype":"venue"
},
  "geometry": {"coordinates":[-90.40135600000001,38.739085],"type":"Point"}
}