{
  "type": "Feature",
  "properties": {
    "iso:country":"US",
    "sg:address":"7000 NW Prairie View Rd",
    "sg:city":"Kansas City",
    "sg:classifiers":[
        {
            "category":"Insurance",
            "subcategory":"Insurance Agent",
            "type":"Services"
        }
    ],
    "sg:phone":"+1 816 587 5200",
    "sg:postcode":"64151",
    "sg:province":"MO",
    "wof:name":"Allstate",
    "wof:placetype":"venue"
},
  "geometry": {"coordinates":[-94.648714,39.220797],"type":"Point"}
}