{
  "type": "Feature",
  "properties": {
    "iso:country":"US",
    "sg:address":"16300 Justus Post Rd",
    "sg:city":"Chesterfield",
    "sg:classifiers":[
        {
            "category":"Building & Trades",
            "subcategory":"Electrical",
            "type":"Services"
        }
    ],
    "sg:phone":"+1 636 532 2000",
    "sg:postcode":"63017",
    "sg:province":"MO",
    "sg:tags":[
        "electric",
        "contractor"
    ],
    "wof:name":"S C Sachs Co Inc",
    "wof:placetype":"venue"
},
  "geometry": {"coordinates":[-90.5681,38.646541],"type":"Point"}
}