{
  "type": "Feature",
  "properties": {
    "iso:country":"US",
    "sg:address":"2706 Alhambra Ct",
    "sg:city":"Saint Louis",
    "sg:classifiers":[
        {
            "category":"Professional",
            "type":"Services"
        }
    ],
    "sg:phone":"+1 314 772 7535",
    "sg:postcode":"63118",
    "sg:province":"MO",
    "wof:name":"Metro St Louis Notary Services",
    "wof:placetype":"venue"
},
  "geometry": {"coordinates":[-90.240075,38.607077],"type":"Point"}
}