{
  "type": "Feature",
  "properties": {
    "iso:country":"US",
    "sg:address":"16 Mohawk Dr",
    "sg:city":"Kirksville",
    "sg:classifiers":[
        {
            "category":"Professional",
            "subcategory":"Employment Agencies",
            "type":"Services"
        }
    ],
    "sg:phone":"+1 660 665 9507",
    "sg:postcode":"63501",
    "sg:province":"MO",
    "sg:tags":[
        "help",
        "supply"
    ],
    "wof:name":"Debalina Modeling",
    "wof:placetype":"venue"
},
  "geometry": {"coordinates":[-92.57708599999999,40.200739],"type":"Point"}
}