{
  "type": "Feature",
  "properties": {
    "iso:country":"US",
    "sg:address":"55 Hwy Y",
    "sg:city":"Eldon",
    "sg:classifiers":[
        {
            "category":"Retail",
            "subcategory":"Auto Repair",
            "type":"Services"
        }
    ],
    "sg:phone":"+1 573 392 7501",
    "sg:postcode":"65026",
    "sg:province":"MO",
    "sg:tags":[
        "repairing",
        "automobile"
    ],
    "wof:name":"Xcc",
    "wof:placetype":"venue"
},
  "geometry": {"coordinates":[-92.60003399999999,38.347384],"type":"Point"}
}