{
  "type": "Feature",
  "properties": {
    "iso:country":"US",
    "sg:address":"621 W 16th St",
    "sg:city":"Sedalia",
    "sg:classifiers":[
        {
            "category":"Personal",
            "subcategory":"Beauty Salon",
            "type":"Services"
        }
    ],
    "sg:phone":"+1 660 826 4250",
    "sg:postcode":"65301",
    "sg:province":"MO",
    "sg:tags":[
        "shop"
    ],
    "wof:name":"Fashion Flair Stylon",
    "wof:placetype":"venue"
},
  "geometry": {"coordinates":[-93.23539599999999,38.697704],"type":"Point"}
}