{
  "type": "Feature",
  "properties": {
    "iso:country":"US",
    "sg:address":"542 Lering Ct",
    "sg:city":"Ballwin",
    "sg:classifiers":[
        {
            "category":"Real Estate",
            "subcategory":"Real Estate Agent",
            "type":"Services"
        }
    ],
    "sg:phone":"+1 636 230 9250",
    "sg:postcode":"63011",
    "sg:province":"MO",
    "wof:name":"Prudential Alliance",
    "wof:placetype":"venue"
},
  "geometry": {"coordinates":[-90.58036199999999,38.607458],"type":"Point"}
}