{
  "type": "Feature",
  "properties": {
    "iso:country":"US",
    "sg:address":"232 Old Sulphur Springs Rd",
    "sg:city":"Ballwin",
    "sg:classifiers":[
        {
            "category":"Shopping",
            "subcategory":"Clothing, Apparel, & Fashions",
            "type":"Retail Goods"
        }
    ],
    "sg:phone":"+1 636 391 3551",
    "sg:postcode":"63021",
    "sg:province":"MO",
    "sg:tags":[
        "uniform"
    ],
    "sg:website":"www.justmeapparel.com",
    "wof:name":"Just Me Apparel",
    "wof:placetype":"venue"
},
  "geometry": {"coordinates":[-90.515517,38.589846],"type":"Point"}
}