{
  "type": "Feature",
  "properties": {
    "iso:country":"US",
    "sg:address":"272 Co Rd K",
    "sg:city":"Glasgow",
    "sg:classifiers":[
        {
            "category":"Manufacturing",
            "subcategory":"Jewelry",
            "type":"Manufacturing & Wholesale Goods"
        }
    ],
    "sg:phone":"+1 660 338 2503",
    "sg:postcode":"65254",
    "sg:province":"MO",
    "sg:tags":[
        "ware",
        "mfg"
    ],
    "wof:name":"Village Pewter",
    "wof:placetype":"venue"
},
  "geometry": {"coordinates":[-92.85533599999999,39.122114],"type":"Point"}
}