{
  "type": "Feature",
  "properties": {
    "iso:country":"US",
    "sg:address":"131 Blue Ridge Trce",
    "sg:city":"Festus",
    "sg:classifiers":[
        {
            "category":"Communications",
            "subcategory":"Film & Video Production",
            "type":"Services"
        }
    ],
    "sg:phone":"+1 636 931 6382",
    "sg:postcode":"63028",
    "sg:province":"MO",
    "sg:tags":[
        "motion",
        "picture",
        "distribution"
    ],
    "wof:name":"Drf Distribution Ltd",
    "wof:placetype":"venue"
},
  "geometry": {"coordinates":[-90.432856,38.239584],"type":"Point"}
}