{
  "type": "Feature",
  "properties": {
    "iso:country":"US",
    "sg:address":"3450 Bridgeland Dr",
    "sg:city":"Bridgeton",
    "sg:classifiers":[
        {
            "category":"Health Services",
            "subcategory":"Dentist",
            "type":"Services"
        }
    ],
    "sg:phone":"+1 314 770 0400",
    "sg:postcode":"63044",
    "sg:province":"MO",
    "sg:tags":[
        "dentists-cosmetic",
        "dentistry"
    ],
    "sg:website":"http://www.rechtindental.com",
    "wof:name":"Rechtin Family & Cosmetic Dental Care",
    "wof:placetype":"venue"
},
  "geometry": {"coordinates":[-90.429039,38.74844],"type":"Point"}
}