{
  "type": "Feature",
  "properties": {
    "iso:country":"US",
    "sg:address":"6600 E 124th St",
    "sg:city":"Grandview",
    "sg:classifiers":[
        {
            "category":"Social Services",
            "subcategory":"Child Care",
            "type":"Services"
        }
    ],
    "sg:phone":"+1 816 966 1868",
    "sg:postcode":"64030",
    "sg:province":"MO",
    "sg:tags":[
        "day"
    ],
    "wof:name":"Mothers Love Child Care",
    "wof:placetype":"venue"
},
  "geometry": {"coordinates":[-94.51299899999999,38.898792],"type":"Point"}
}