{
  "type": "Feature",
  "properties": {
    "iso:country":"US",
    "sg:address":"3429 E Trafficway St",
    "sg:city":"Springfield",
    "sg:classifiers":[
        {
            "category":"Education",
            "subcategory":"School",
            "type":"Public Place"
        }
    ],
    "sg:phone":"+1 417 523 7100",
    "sg:postcode":"65802",
    "sg:province":"MO",
    "sg:website":"http://www.phsband.com",
    "wof:name":"Hickory Hills Elem School",
    "wof:placetype":"venue"
},
  "geometry": {"coordinates":[-93.253738,37.210812],"type":"Point"}
}