{
  "type": "Feature",
  "properties": {
    "iso:country":"US",
    "sg:address":"2007 Broadway St",
    "sg:city":"Kansas City",
    "sg:classifiers":[
        {
            "category":"Organizations",
            "subcategory":"Non-profit Organization",
            "type":"Services"
        }
    ],
    "sg:phone":"+1 816 842 5242",
    "sg:postcode":"64108",
    "sg:province":"MO",
    "sg:tags":[
        "social"
    ],
    "wof:name":"American Lung Assn Wstn MO",
    "wof:placetype":"venue"
},
  "geometry": {"coordinates":[-94.588944,39.087843],"type":"Point"}
}