{
  "type": "Feature",
  "properties": {
    "iso:country":"US",
    "sg:address":"7829 S Broadway",
    "sg:city":"St Louis",
    "sg:classifiers":[
        {
            "category":"Freight",
            "type":"Transportation"
        },
        {
            "category":"Building & Trades",
            "subcategory":"Construction",
            "type":"Services"
        }
    ],
    "sg:phone":"+1 314 631 6808",
    "sg:postcode":"63111",
    "sg:province":"MO",
    "sg:tags":[
        "installation",
        "trucking",
        "equipment",
        "erectors",
        "machinery",
        "operator",
        "local"
    ],
    "wof:name":"Bosko Machinery",
    "wof:placetype":"venue"
},
  "geometry": {"coordinates":[-90.260186,38.545534],"type":"Point"}
}