{
  "type": "Feature",
  "properties": {
    "iso:country":"US",
    "sg:address":"35 Marshall Rd",
    "sg:city":"Valley Park",
    "sg:classifiers":[
        {
            "category":"Banks & Credit Unions",
            "subcategory":"Financial Services",
            "type":"Services"
        }
    ],
    "sg:phone":"+1 636 230 3500",
    "sg:postcode":"63088",
    "sg:province":"MO",
    "sg:tags":[
        "company",
        "holding"
    ],
    "sg:website":"www.meramecvalleybank.com",
    "wof:name":"Valley Bancshares Inc",
    "wof:placetype":"venue"
},
  "geometry": {"coordinates":[-90.492783,38.548815],"type":"Point"}
}