{
  "type": "Feature",
  "properties": {
    "iso:country":"US",
    "sg:address":"325 W Cardinal St",
    "sg:city":"Springfield",
    "sg:classifiers":[
        {
            "category":"Food & Beverages",
            "subcategory":"Groceries & Convenience Stores",
            "type":"Retail Goods"
        }
    ],
    "sg:phone":"+1 417 890 1171",
    "sg:postcode":"65810",
    "sg:province":"MO",
    "wof:name":"Quik Trip",
    "wof:placetype":"venue"
},
  "geometry": {"coordinates":[-93.295422,37.134664],"type":"Point"}
}