{
  "type": "Feature",
  "properties": {
    "iso:country":"US",
    "sg:address":"324 N G St",
    "sg:city":"Poplar Bluff",
    "sg:classifiers":[
        {
            "category":"Social Services",
            "subcategory":"Child Care",
            "type":"Services"
        }
    ],
    "sg:phone":"+1 573 727 9904",
    "sg:postcode":"63901",
    "sg:province":"MO",
    "sg:tags":[
        "day"
    ],
    "wof:name":"Joannas Tot Care",
    "wof:placetype":"venue"
},
  "geometry": {"coordinates":[-90.38218000000001,36.756659],"type":"Point"}
}