{
  "type": "Feature",
  "properties": {
    "iso:country":"US",
    "sg:address":"14721 Greenleaf Valley Dr",
    "sg:city":"Chesterfield",
    "sg:classifiers":[
        {
            "category":"Wholesale",
            "subcategory":"Stationery",
            "type":"Manufacturing & Wholesale Goods"
        }
    ],
    "sg:phone":"+1 636 537 0974",
    "sg:postcode":"63017",
    "sg:province":"MO",
    "sg:tags":[
        "marking",
        "price",
        "labeling",
        "equipment",
        "mail",
        "order"
    ],
    "wof:name":"American Pricemark Co",
    "wof:placetype":"venue"
},
  "geometry": {"coordinates":[-90.533958,38.64191],"type":"Point"}
}