{
  "type": "Feature",
  "properties": {
    "iso:country":"US",
    "sg:address":"107 Broadway St",
    "sg:city":"Camdenton",
    "sg:classifiers":[
        {
            "category":"Retail",
            "subcategory":"Auto Repair",
            "type":"Services"
        }
    ],
    "sg:phone":"+1 573 346 3636",
    "sg:postcode":"65020",
    "sg:province":"MO",
    "sg:tags":[
        "repairing",
        "automobile"
    ],
    "wof:name":"Fewell's Automotive Inc",
    "wof:placetype":"venue"
},
  "geometry": {"coordinates":[-92.73627500000001,38.003126],"type":"Point"}
}