{
  "type": "Feature",
  "properties": {
    "addr:full":"15920 US Hwy 160 Forsyth MO 65653",
    "addr:postcode":"15920;65653",
    "addr:street":"Us Hwy 160",
    "iso:country":"US",
    "sg:address":"15920 US Hwy 160",
    "sg:city":"Forsyth",
    "sg:classifiers":[
        {
            "category":"Food & Beverages",
            "subcategory":"Groceries & Convenience Stores",
            "type":"Retail Goods"
        }
    ],
    "sg:phone":"+1 417 546 2400",
    "sg:postcode":"65653",
    "sg:province":"MO",
    "wof:name":"Blimpie",
    "wof:placetype":"venue"
},
  "geometry": {"coordinates":[-93.11993200000001,36.687895],"type":"Point"}
}