{
  "type": "Feature",
  "properties": {
    "iso:country":"US",
    "sg:address":"13732 Olive Blvd",
    "sg:city":"Chesterfield",
    "sg:classifiers":[
        {
            "category":"Shopping",
            "subcategory":"Gifts & Souvenirs",
            "type":"Retail Goods"
        }
    ],
    "sg:phone":"+1 314 628 9555",
    "sg:postcode":"63017",
    "sg:province":"MO",
    "sg:tags":[
        "cards",
        "greeting"
    ],
    "wof:name":"Froehlichs Inc",
    "wof:placetype":"venue"
},
  "geometry": {"coordinates":[-90.509401,38.680728],"type":"Point"}
}