{
  "type": "Feature",
  "properties": {
    "iso:country":"US",
    "sg:address":"1318 Clarkson Clayton Ctr",
    "sg:city":"Ellisville",
    "sg:classifiers":[
        {
            "category":"Real Estate",
            "subcategory":"Real Estate Services",
            "type":"Services"
        },
        {
            "category":"Real Estate",
            "subcategory":"Real Estate Agent",
            "type":"Services"
        }
    ],
    "sg:phone":"+1 314 308 2941",
    "sg:postcode":"63011",
    "sg:province":"MO",
    "sg:tags":[
        "buyer",
        "broker"
    ],
    "wof:name":"Joni Antweil Independant Realtor",
    "wof:placetype":"venue"
},
  "geometry": {"coordinates":[-90.587612,38.60318],"type":"Point"}
}