{
  "type": "Feature",
  "properties": {
    "iso:country":"US",
    "sg:address":"1005 Gulf St",
    "sg:city":"Lamar",
    "sg:classifiers":[
        {
            "category":"Professional",
            "subcategory":"Business Services",
            "type":"Services"
        }
    ],
    "sg:phone":"+1 417 682 3362",
    "sg:postcode":"64759",
    "sg:province":"MO",
    "sg:tags":[
        "interior",
        "consultant",
        "design",
        "decorator"
    ],
    "wof:name":"Dandb Shoff Enterprises",
    "wof:placetype":"venue"
},
  "geometry": {"coordinates":[-94.277716,37.495704],"type":"Point"}
}