{
  "type": "Feature",
  "properties": {
    "iso:country":"US",
    "sg:address":"303 N Darrowby Dr",
    "sg:city":"Raymore",
    "sg:classifiers":[
        {
            "category":"Building & Trades",
            "subcategory":"Construction",
            "type":"Services"
        }
    ],
    "sg:phone":"+1 816 322 3563",
    "sg:postcode":"64083",
    "sg:province":"MO",
    "sg:tags":[
        "hanging",
        "contractor"
    ],
    "wof:name":"Olson Painting",
    "wof:placetype":"venue"
},
  "geometry": {"coordinates":[-94.48827799999999,38.811203],"type":"Point"}
}