{
  "type": "Feature",
  "properties": {
    "iso:country":"US",
    "sg:address":"306 US Hwy 24",
    "sg:city":"Salisbury",
    "sg:classifiers":[
        {
            "category":"Restaurant",
            "type":"Food & Drink"
        }
    ],
    "sg:phone":"+1 660 388 6098",
    "sg:postcode":"65281",
    "sg:province":"MO",
    "wof:name":"Salisbury Diner",
    "wof:placetype":"venue"
},
  "geometry": {"coordinates":[-92.79772199999999,39.43006],"type":"Point"}
}