{
  "type": "Feature",
  "properties": {
    "iso:country":"US",
    "sg:address":"402 N Elizabeth Ave",
    "sg:city":"Saint Louis",
    "sg:classifiers":[
        {
            "category":"Building & Trades",
            "subcategory":"Construction",
            "type":"Services"
        }
    ],
    "sg:phone":"+1 314 522 2360",
    "sg:postcode":"63135",
    "sg:province":"MO",
    "sg:tags":[
        "contractor"
    ],
    "wof:name":"Geoffrion Construction",
    "wof:placetype":"venue"
},
  "geometry": {"coordinates":[-90.300087,38.75142],"type":"Point"}
}