{
  "type": "Feature",
  "properties": {
    "iso:country":"US",
    "sg:address":"13003 13th St",
    "sg:city":"Grandview",
    "sg:classifiers":[
        {
            "category":"Shopping",
            "subcategory":"Jewelry",
            "type":"Retail Goods"
        },
        {
            "category":"Manufacturing",
            "subcategory":"Jewelry",
            "type":"Manufacturing & Wholesale Goods"
        },
        {
            "category":"Retail",
            "subcategory":"Repair Shop",
            "type":"Services"
        }
    ],
    "sg:phone":"+1 816 763 9415",
    "sg:postcode":"64030",
    "sg:province":"MO",
    "sg:tags":[
        "repairing",
        "diamond",
        "designer",
        "watch",
        "jeweler"
    ],
    "sg:website":"http://www.crewsjewelry.com",
    "wof:name":"Crews Fine Jewelry",
    "wof:placetype":"venue"
},
  "geometry": {"coordinates":[-94.530291,38.889081],"type":"Point"}
}