{
  "type": "Feature",
  "properties": {
    "iso:country":"US",
    "sg:address":"305 N Cherry St",
    "sg:city":"Cameron",
    "sg:classifiers":[
        {
            "category":"Insurance",
            "subcategory":"Insurance Agent",
            "type":"Services"
        },
        {
            "category":"Insurance",
            "subcategory":"Hazard Insurance",
            "type":"Services"
        }
    ],
    "sg:phone":"+1 816 632 7225",
    "sg:postcode":"64429",
    "sg:province":"MO",
    "sg:tags":[
        "consultant",
        "analyst"
    ],
    "wof:name":"Ocker Insurance",
    "wof:placetype":"venue"
},
  "geometry": {"coordinates":[-94.239767,39.741402],"type":"Point"}
}