{
  "type": "Feature",
  "properties": {
    "iso:country":"US",
    "sg:address":"2519 Missouri Blvd",
    "sg:city":"Jefferson City",
    "sg:classifiers":[
        {
            "category":"Ice Cream",
            "type":"Food & Drink"
        }
    ],
    "sg:menulink":"http://www.allmenus.com/mo/jefferson/92623-steak-n-shake/menu/",
    "sg:phone":"+1 573 636 9553",
    "sg:postcode":"65109",
    "sg:province":"MO",
    "sg:tags":[
        "american"
    ],
    "wof:name":"Steak 'n Shake",
    "wof:placetype":"venue"
},
  "geometry": {"coordinates":[-92.2165,38.581947],"type":"Point"}
}