{
  "type": "Feature",
  "properties": {
    "iso:country":"US",
    "sg:address":"6109 Courtney Way",
    "sg:city":"Imperial",
    "sg:classifiers":[
        {
            "category":"Manufacturing",
            "subcategory":"Buildings",
            "type":"Manufacturing & Wholesale Goods"
        },
        {
            "category":"Building & Trades",
            "subcategory":"Construction",
            "type":"Services"
        }
    ],
    "sg:phone":"+1 636 942 7447",
    "sg:postcode":"63052",
    "sg:province":"MO",
    "sg:tags":[
        "home",
        "builder",
        "contractor"
    ],
    "wof:name":"D C Construction",
    "wof:placetype":"venue"
},
  "geometry": {"coordinates":[-90.460081,38.372935],"type":"Point"}
}