{
  "type": "Feature",
  "properties": {
    "iso:country":"US",
    "sg:address":"6140 Raytown Rd",
    "sg:city":"Raytown",
    "sg:classifiers":[
        {
            "category":"Real Estate",
            "subcategory":"Real Estate Services",
            "type":"Services"
        },
        {
            "category":"Real Estate",
            "subcategory":"Real Estate Operator",
            "type":"Services"
        }
    ],
    "sg:phone":"+1 816 353 5678",
    "sg:postcode":"64133",
    "sg:province":"MO",
    "sg:tags":[
        "vacancy",
        "apartment",
        "rental",
        "listing"
    ],
    "sg:website":"http://www.bowenapartments.com",
    "wof:name":"Bowen Apartments",
    "wof:placetype":"venue"
},
  "geometry": {"coordinates":[-94.46325299999999,39.011601],"type":"Point"}
}