{
  "type": "Feature",
  "properties": {
    "iso:country":"US",
    "sg:address":"1812 NW Willowbrook Dr",
    "sg:city":"Blue Springs",
    "sg:classifiers":[
        {
            "category":"Professional",
            "subcategory":"Management & Consulting",
            "type":"Services"
        }
    ],
    "sg:phone":"+1 816 229 0811",
    "sg:postcode":"64015",
    "sg:province":"MO",
    "sg:tags":[
        "business"
    ],
    "wof:name":"Dmk",
    "wof:placetype":"venue"
},
  "geometry": {"coordinates":[-94.283659,39.025354],"type":"Point"}
}