{
  "type": "Feature",
  "properties": {
    "addr:full":"7667 NW Prairie View Rd Kansas City MO 64151",
    "addr:housenumber":"7667",
    "addr:postcode":"64151",
    "addr:street":"Nw Prairie View Rd",
    "iso:country":"US",
    "sg:address":"7667 NW Prairie View Rd",
    "sg:city":"Kansas City",
    "sg:classifiers":[
        {
            "category":"Insurance",
            "subcategory":"Insurance Agent",
            "type":"Services"
        }
    ],
    "sg:phone":"+1 816 584 1520",
    "sg:postcode":"64151",
    "sg:province":"MO",
    "wof:name":"MetLife",
    "wof:placetype":"venue"
},
  "geometry": {"coordinates":[-94.65845299999999,39.233216],"type":"Point"}
}