{
  "type": "Feature",
  "properties": {
    "iso:country":"US",
    "sg:address":"402 Recovery Rd",
    "sg:city":"Kennett",
    "sg:classifiers":[
        {
            "category":"Health Services",
            "subcategory":"Hospital",
            "type":"Services"
        }
    ],
    "sg:phone":"+1 573 888 0274",
    "sg:postcode":"63857",
    "sg:province":"MO",
    "wof:name":"Twin Rivers Occupational Medicine",
    "wof:placetype":"venue"
},
  "geometry": {"coordinates":[-90.040812,36.234032],"type":"Point"}
}