{
  "type": "Feature",
  "properties": {
    "iso:country":"US",
    "sg:address":"212 W Mill St",
    "sg:city":"Liberty",
    "sg:classifiers":[
        {
            "category":"Retail",
            "subcategory":"Animal Services",
            "type":"Services"
        }
    ],
    "sg:phone":"+1 816 781 8232",
    "sg:postcode":"64068",
    "sg:province":"MO",
    "sg:tags":[
        "merchandise"
    ],
    "wof:name":"Pet-Cetra Boutique & Clippery",
    "wof:placetype":"venue"
},
  "geometry": {"coordinates":[-94.4246,39.244826],"type":"Point"}
}