{
  "type": "Feature",
  "properties": {
    "iso:country":"US",
    "sg:address":"303 State Hwy 8",
    "sg:city":"Steelville",
    "sg:classifiers":[
        {
            "category":"Building & Trades",
            "subcategory":"Construction",
            "type":"Services"
        }
    ],
    "sg:phone":"+1 573 775 3562",
    "sg:postcode":"65565",
    "sg:province":"MO",
    "sg:tags":[
        "maker",
        "cabinet"
    ],
    "wof:name":"Snodgrass Cabinets",
    "wof:placetype":"venue"
},
  "geometry": {"coordinates":[-91.35852199999999,37.967227],"type":"Point"}
}