{
  "type": "Feature",
  "properties": {
    "iso:country":"US",
    "sg:address":"101 W Stoddard St",
    "sg:city":"Dexter",
    "sg:classifiers":[
        {
            "category":"Autos & Motor Vehicles",
            "subcategory":"Fuel & Gas Station",
            "type":"Retail Goods"
        }
    ],
    "sg:phone":"+1 573 624 4723",
    "sg:postcode":"63841",
    "sg:province":"MO",
    "sg:tags":[
        "oil"
    ],
    "wof:name":"Cleo's 66",
    "wof:placetype":"venue"
},
  "geometry": {"coordinates":[-89.960746,36.793188],"type":"Point"}
}