{
  "type": "Feature",
  "properties": {
    "iso:country":"US",
    "sg:address":"310 SE Brentwood Dr",
    "sg:city":"Lees Summit",
    "sg:classifiers":[
        {
            "category":"Building & Trades",
            "subcategory":"Construction",
            "type":"Services"
        }
    ],
    "sg:phone":"+1 816 524 6774",
    "sg:postcode":"64063",
    "sg:province":"MO",
    "sg:tags":[
        "residential"
    ],
    "wof:name":"Miller Construction",
    "wof:placetype":"venue"
},
  "geometry": {"coordinates":[-94.353793,38.912822],"type":"Point"}
}