{
  "type": "Feature",
  "properties": {
    "iso:country":"US",
    "sg:address":"6515 Natural Bridge Rd",
    "sg:city":"Saint Louis",
    "sg:classifiers":[
        {
            "category":"Social Services",
            "subcategory":"Child Care",
            "type":"Services"
        }
    ],
    "sg:phone":"+1 314 382 5333",
    "sg:postcode":"63121",
    "sg:province":"MO",
    "sg:tags":[
        "day"
    ],
    "wof:name":"Sunshine Child Development Center",
    "wof:placetype":"venue"
},
  "geometry": {"coordinates":[-90.283589,38.694903],"type":"Point"}
}