{
  "type": "Feature",
  "properties": {
    "iso:country":"US",
    "sg:address":"406 W 6th St",
    "sg:city":"Lawson",
    "sg:classifiers":[
        {
            "category":"Recreation",
            "type":"Entertainment"
        }
    ],
    "sg:phone":"+1 816 580 7440",
    "sg:postcode":"64062",
    "sg:province":"MO",
    "sg:tags":[
        "instruction",
        "gymnastic"
    ],
    "wof:name":"Northwest Gymnastics",
    "wof:placetype":"venue"
},
  "geometry": {"coordinates":[-94.210106,39.440418],"type":"Point"}
}