{
  "type": "Feature",
  "properties": {
    "iso:country":"US",
    "sg:address":"147 E Marseille Dr",
    "sg:city":"St Louis",
    "sg:classifiers":[
        {
            "category":"Wholesale",
            "subcategory":"Construction Materials",
            "type":"Manufacturing & Wholesale Goods"
        }
    ],
    "sg:phone":"+1 314 487 1899",
    "sg:postcode":"63129",
    "sg:province":"MO",
    "sg:tags":[
        "pallet",
        "skid"
    ],
    "wof:name":"PCF Products",
    "wof:placetype":"venue"
},
  "geometry": {"coordinates":[-90.29073,38.489192],"type":"Point"}
}