{
  "type": "Feature",
  "properties": {
    "iso:country":"US",
    "sg:address":"2130 Schuetz Rd",
    "sg:city":"Saint Louis",
    "sg:classifiers":[
        {
            "category":"Insurance",
            "subcategory":"Insurance Agent",
            "type":"Services"
        }
    ],
    "sg:phone":"+1 314 432 1991",
    "sg:postcode":"63146",
    "sg:province":"MO",
    "wof:name":"Young Paul F",
    "wof:placetype":"venue"
},
  "geometry": {"coordinates":[-90.42925700000001,38.69765],"type":"Point"}
}