{
  "type": "Feature",
  "properties": {
    "iso:country":"US",
    "sg:address":"2401 Bernadette Dr",
    "sg:city":"Columbia",
    "sg:classifiers":[
        {
            "category":"Home & Garden",
            "subcategory":"Building Materials",
            "type":"Retail Goods"
        }
    ],
    "sg:phone":"+1 573 446 5800",
    "sg:postcode":"65203",
    "sg:province":"MO",
    "sg:tags":[
        "paint"
    ],
    "wof:name":"Sherwin-Williams Paints",
    "wof:placetype":"venue"
},
  "geometry": {"coordinates":[-92.375884,38.965939],"type":"Point"}
}