{
  "type": "Feature",
  "properties": {
    "iso:country":"US",
    "sg:address":"7358 Lawrence 1222",
    "sg:city":"Ash Grove",
    "sg:classifiers":[
        {
            "category":"Professional",
            "subcategory":"Business Services",
            "type":"Services"
        }
    ],
    "sg:phone":"+1 417 491 4852",
    "sg:postcode":"65604",
    "sg:province":"MO",
    "wof:name":"Dam It Enterprises",
    "wof:placetype":"venue"
},
  "geometry": {"coordinates":[-93.653789,37.166212],"type":"Point"}
}