{
  "type": "Feature",
  "properties": {
    "iso:country":"US",
    "sg:address":"1664 State Hwy Jj",
    "sg:city":"Sparta",
    "sg:classifiers":[
        {
            "category":"Building & Trades",
            "subcategory":"Electrical",
            "type":"Services"
        }
    ],
    "sg:phone":"+1 417 818 5368",
    "sg:postcode":"65753",
    "sg:province":"MO",
    "sg:tags":[
        "electrical",
        "contractor"
    ],
    "wof:name":"Sorenson Electric",
    "wof:placetype":"venue"
},
  "geometry": {"coordinates":[-93.146193,37.017258],"type":"Point"}
}