{
  "type": "Feature",
  "properties": {
    "iso:country":"US",
    "sg:address":"7234 Stone Pointe Ct",
    "sg:city":"St Louis",
    "sg:classifiers":[
        {
            "category":"Banks & Credit Unions",
            "subcategory":"Investment Brokerage",
            "type":"Services"
        },
        {
            "category":"Banks & Credit Unions",
            "subcategory":"Bank",
            "type":"Services"
        }
    ],
    "sg:phone":"+1 314 846 8300",
    "sg:postcode":"63129",
    "sg:province":"MO",
    "sg:tags":[
        "advisory",
        "loan",
        "financial"
    ],
    "wof:name":"Mortgage Vestors",
    "wof:placetype":"venue"
},
  "geometry": {"coordinates":[-90.335257,38.432853],"type":"Point"}
}