{
  "type": "Feature",
  "properties": {
    "iso:country":"US",
    "sg:address":"34250 Ringen School Rd",
    "sg:city":"Mora",
    "sg:classifiers":[
        {
            "category":"Insurance",
            "subcategory":"Hazard Insurance",
            "type":"Services"
        }
    ],
    "sg:phone":"+1 660 368 2232",
    "sg:postcode":"65345",
    "sg:province":"MO",
    "wof:name":"Allen Zimmerschied",
    "wof:placetype":"venue"
},
  "geometry": {"coordinates":[-93.097864,38.589718],"type":"Point"}
}