{
  "type": "Feature",
  "properties": {
    "iso:country":"US",
    "sg:address":"6862 County Road 333",
    "sg:city":"Neelyville",
    "sg:classifiers":[
        {
            "category":"Professional",
            "subcategory":"Lawyer & Legal Services",
            "type":"Services"
        }
    ],
    "sg:phone":"+1 573 300 7934",
    "sg:postcode":"63954",
    "sg:province":"MO",
    "sg:tags":[
        "attorney"
    ],
    "wof:name":"Susan L Luttrull",
    "wof:placetype":"venue"
},
  "geometry": {"coordinates":[-90.389444,36.563682],"type":"Point"}
}