{
  "type": "Feature",
  "properties": {
    "iso:country":"US",
    "sg:address":"100 S Crittenden St",
    "sg:city":"Marshfield",
    "sg:classifiers":[
        {
            "category":"Shopping",
            "subcategory":"Gifts & Souvenirs",
            "type":"Retail Goods"
        }
    ],
    "sg:phone":"+1 417 468 2046",
    "sg:postcode":"65706",
    "sg:province":"MO",
    "sg:tags":[
        "shop"
    ],
    "wof:name":"Beverley's Hallmark Shop",
    "wof:placetype":"venue"
},
  "geometry": {"coordinates":[-92.90631399999999,37.338598],"type":"Point"}
}