{
  "type": "Feature",
  "properties": {
    "iso:country":"US",
    "sg:address":"5485 State Hwy Jj",
    "sg:city":"Walnut Grove",
    "sg:classifiers":[
        {
            "category":"Retail",
            "subcategory":"Portrait Studio",
            "type":"Services"
        }
    ],
    "sg:phone":"+1 417 376 3131",
    "sg:postcode":"65770",
    "sg:province":"MO",
    "sg:tags":[
        "photographer",
        "photo"
    ],
    "wof:name":"Christy's Custom Photography",
    "wof:placetype":"venue"
},
  "geometry": {"coordinates":[-93.490421,37.469441],"type":"Point"}
}