{
  "type": "Feature",
  "properties": {
    "iso:country":"US",
    "sg:address":"3434 Terrace St",
    "sg:city":"Kansas City",
    "sg:classifiers":[
        {
            "category":"Manufacturing",
            "subcategory":"Tools & Machinery",
            "type":"Manufacturing & Wholesale Goods"
        }
    ],
    "sg:phone":"+1 816 931 6001",
    "sg:postcode":"64111",
    "sg:province":"MO",
    "sg:tags":[
        "box",
        "gear",
        "power",
        "mfg",
        "transmission",
        "reducer",
        "mechanical"
    ],
    "wof:name":"Blue Chip Machine Co",
    "wof:placetype":"venue"
},
  "geometry": {"coordinates":[-94.601174,39.067337],"type":"Point"}
}