{
  "type": "Feature",
  "properties": {
    "iso:country":"US",
    "sg:address":"200 S Washington St",
    "sg:city":"Chillicothe",
    "sg:classifiers":[
        {
            "category":"Shopping",
            "subcategory":"Hobbies, Toys, & Games",
            "type":"Retail Goods"
        }
    ],
    "sg:phone":"+1 660 646 1120",
    "sg:postcode":"64601",
    "sg:province":"MO",
    "sg:tags":[
        "track",
        "race"
    ],
    "wof:name":"North Mo R/C Raceway",
    "wof:placetype":"venue"
},
  "geometry": {"coordinates":[-93.55294000000001,39.785091],"type":"Point"}
}