{
  "type": "Feature",
  "properties": {
    "iso:country":"US",
    "sg:address":"228 Schabbing Ln",
    "sg:city":"Cape Girardeau",
    "sg:classifiers":[
        {
            "category":"Farming",
            "subcategory":"Dairy Farm",
            "type":"Manufacturing & Wholesale Goods"
        }
    ],
    "sg:phone":"+1 573 335 0492",
    "sg:postcode":"63701",
    "sg:province":"MO",
    "wof:name":"Ramsey Creek Farm",
    "wof:placetype":"venue"
},
  "geometry": {"coordinates":[-89.601778,37.31085],"type":"Point"}
}