{
  "type": "Feature",
  "properties": {
    "iso:country":"US",
    "sg:address":"8101 NW Belvedere Pkwy",
    "sg:city":"Kansas City",
    "sg:classifiers":[
        {
            "category":"Education",
            "subcategory":"School",
            "type":"Public Place"
        }
    ],
    "sg:phone":"+1 816 741 3656",
    "sg:postcode":"64152",
    "sg:province":"MO",
    "wof:name":"Prairie Point Elem School",
    "wof:placetype":"venue"
},
  "geometry": {"coordinates":[-94.67196800000001,39.232473],"type":"Point"}
}