{
  "type": "Feature",
  "properties": {
    "iso:country":"US",
    "sg:address":"614 N Walnut St",
    "sg:city":"Cameron",
    "sg:classifiers":[
        {
            "category":"Food & Beverages",
            "subcategory":"Groceries & Convenience Stores",
            "type":"Retail Goods"
        }
    ],
    "sg:phone":"+1 816 632 6152",
    "sg:postcode":"64429",
    "sg:province":"MO",
    "wof:name":"My Store Markets",
    "wof:placetype":"venue"
},
  "geometry": {"coordinates":[-94.23553200000001,39.745262],"type":"Point"}
}