{
  "type": "Feature",
  "properties": {
    "iso:country":"US",
    "sg:address":"201 W 2nd St",
    "sg:city":"Sedalia",
    "sg:classifiers":[
        {
            "category":"Government",
            "subcategory":"Police Station",
            "type":"Public Place"
        }
    ],
    "sg:phone":"+1 660 826 2590",
    "sg:postcode":"65301",
    "sg:province":"MO",
    "sg:tags":[
        "department"
    ],
    "wof:name":"Sedalia Police Dept Detective",
    "wof:placetype":"venue"
},
  "geometry": {"coordinates":[-93.229828,38.710114],"type":"Point"}
}