{
  "type": "Feature",
  "properties": {
    "iso:country":"US",
    "sg:address":"600 E Battlefield Rd",
    "sg:city":"Springfield",
    "sg:classifiers":[
        {
            "category":"Restaurant",
            "type":"Food & Drink"
        }
    ],
    "sg:phone":"+1 417 881 5700",
    "sg:postcode":"65807",
    "sg:province":"MO",
    "sg:tags":[
        "drinking",
        "eating"
    ],
    "wof:name":"Tony Roma's",
    "wof:placetype":"venue"
},
  "geometry": {"coordinates":[-93.28916599999999,37.159926],"type":"Point"}
}