{
  "type": "Feature",
  "properties": {
    "iso:country":"US",
    "sg:address":"12518 Lusher Rd",
    "sg:city":"Saint Louis",
    "sg:classifiers":[
        {
            "category":"Shopping",
            "type":"Retail Goods"
        }
    ],
    "sg:phone":"+1 314 438 0003",
    "sg:postcode":"63138",
    "sg:province":"MO",
    "sg:tags":[
        "merchandise"
    ],
    "wof:name":"Midwest Aquatics",
    "wof:placetype":"venue"
},
  "geometry": {"coordinates":[-90.227721,38.808729],"type":"Point"}
}