{
  "type": "Feature",
  "properties": {
    "iso:country":"US",
    "sg:address":"5725 Dale Ave",
    "sg:city":"Saint Louis",
    "sg:classifiers":[
        {
            "category":"Restaurant",
            "type":"Food & Drink"
        }
    ],
    "sg:phone":"+1 314 647 5572",
    "sg:postcode":"63110",
    "sg:province":"MO",
    "wof:name":"Guardian Environmental",
    "wof:placetype":"venue"
},
  "geometry": {"coordinates":[-90.28270000000001,38.624298],"type":"Point"}
}