{
  "type": "Feature",
  "properties": {
    "iso:country":"US",
    "sg:address":"1304 Parkade Blvd",
    "sg:city":"Columbia",
    "sg:classifiers":[
        {
            "category":"Social Services",
            "type":"Services"
        }
    ],
    "sg:phone":"+1 573 449 5202",
    "sg:postcode":"65203",
    "sg:province":"MO",
    "sg:tags":[
        "organization",
        "welfare"
    ],
    "wof:name":"Salvation Army Red Shield Str",
    "wof:placetype":"venue"
},
  "geometry": {"coordinates":[-92.34369,38.965749],"type":"Point"}
}