{
  "type": "Feature",
  "properties": {
    "iso:country":"US",
    "sg:address":"646 Country Lake Dr",
    "sg:city":"Saint Peters",
    "sg:classifiers":[
        {
            "category":"Building & Trades",
            "subcategory":"Cleaning & Sanitation",
            "type":"Services"
        }
    ],
    "sg:phone":"+1 636 447 7935",
    "sg:postcode":"63376",
    "sg:province":"MO",
    "sg:tags":[
        "maintenance"
    ],
    "wof:name":"Carlas Cleaning Service",
    "wof:placetype":"venue"
},
  "geometry": {"coordinates":[-90.581613,38.759315],"type":"Point"}
}