{
  "type": "Feature",
  "properties": {
    "iso:country":"US",
    "sg:address":"1605 Lincoln Ln",
    "sg:city":"Rolla",
    "sg:classifiers":[
        {
            "category":"Professional",
            "type":"Services"
        }
    ],
    "sg:phone":"+1 573 364 0379",
    "sg:postcode":"65401",
    "sg:province":"MO",
    "wof:name":"Immi Consulting",
    "wof:placetype":"venue"
},
  "geometry": {"coordinates":[-91.74390699999999,37.958564],"type":"Point"}
}