{
  "type": "Feature",
  "properties": {
    "iso:country":"US",
    "sg:address":"1700 S 9th St",
    "sg:city":"Saint Louis",
    "sg:classifiers":[
        {
            "category":"Home & Garden",
            "subcategory":"Home Furnishings",
            "type":"Retail Goods"
        },
        {
            "category":"Food & Beverages",
            "subcategory":"Liquor & Beverages",
            "type":"Retail Goods"
        }
    ],
    "sg:phone":"+1 314 436 0282",
    "sg:postcode":"63104",
    "sg:province":"MO",
    "sg:tags":[
        "decor",
        "wine",
        "beer",
        "spirit"
    ],
    "sg:website":"www.soulardporch.com/",
    "wof:name":"The Porch",
    "wof:placetype":"venue"
},
  "geometry": {"coordinates":[-90.202608,38.610549],"type":"Point"}
}