{
  "type": "Feature",
  "properties": {
    "iso:country":"US",
    "sg:address":"1227 Garden Village Dr",
    "sg:city":"Florissant",
    "sg:classifiers":[
        {
            "category":"Health Services",
            "subcategory":"Doctor",
            "type":"Services"
        }
    ],
    "sg:phone":"+1 314 503 7608",
    "sg:postcode":"63031",
    "sg:province":"MO",
    "sg:tags":[
        "medical"
    ],
    "wof:name":"Infinite Possibilities Inc",
    "wof:placetype":"venue"
},
  "geometry": {"coordinates":[-90.32853900000001,38.824701],"type":"Point"}
}