{
  "type": "Feature",
  "properties": {
    "iso:country":"US",
    "sg:address":"351 N Chamber Dr",
    "sg:city":"Fredericktown",
    "sg:classifiers":[
        {
            "category":"Personal",
            "subcategory":"Beauty Salon",
            "type":"Services"
        }
    ],
    "sg:phone":"+1 573 783 2650",
    "sg:postcode":"63645",
    "sg:province":"MO",
    "wof:name":"Bobbie's Styling Salon",
    "wof:placetype":"venue"
},
  "geometry": {"coordinates":[-90.28078600000001,37.566712],"type":"Point"}
}