{
  "type": "Feature",
  "properties": {
    "iso:country":"US",
    "sg:address":"6918 S Benton Ave",
    "sg:city":"Kansas City",
    "sg:classifiers":[
        {
            "category":"Banks & Credit Unions",
            "subcategory":"Bank",
            "type":"Services"
        }
    ],
    "sg:phone":"+1 816 444 0555",
    "sg:postcode":"64132",
    "sg:province":"MO",
    "sg:tags":[
        "loan",
        "real estate"
    ],
    "wof:name":"Clarion Mortgage Capital Corp",
    "wof:placetype":"venue"
},
  "geometry": {"coordinates":[-94.55339499999999,39.000038],"type":"Point"}
}