{
  "type": "Feature",
  "properties": {
    "iso:country":"US",
    "sg:address":"1202 Oakvale Dr",
    "sg:city":"Harrisonville",
    "sg:classifiers":[
        {
            "category":"Building & Trades",
            "subcategory":"Construction",
            "type":"Services"
        }
    ],
    "sg:phone":"+1 816 380 1910",
    "sg:postcode":"64701",
    "sg:province":"MO",
    "sg:tags":[
        "contractor"
    ],
    "wof:name":"Bob Eisel Dry Wall & Texture",
    "wof:placetype":"venue"
},
  "geometry": {"coordinates":[-94.34070199999999,38.648985],"type":"Point"}
}