{
  "type": "Feature",
  "properties": {
    "iso:country":"US",
    "sg:address":"4141 Co Rd 227",
    "sg:city":"Fulton",
    "sg:classifiers":[
        {
            "category":"Farming",
            "subcategory":"Livestock Farm",
            "type":"Manufacturing & Wholesale Goods"
        }
    ],
    "sg:phone":"+1 573 642 5426",
    "sg:postcode":"65251",
    "sg:province":"MO",
    "sg:tags":[
        "beef",
        "feedlot",
        "cattle"
    ],
    "wof:name":"Forrest Backer",
    "wof:placetype":"venue"
},
  "geometry": {"coordinates":[-92.041985,38.908994],"type":"Point"}
}