{
  "type": "Feature",
  "properties": {
    "iso:country":"US",
    "sg:address":"19 S County Centerway",
    "sg:city":"St Louis",
    "sg:classifiers":[
        {
            "category":"Personal",
            "type":"Services"
        }
    ],
    "sg:phone":"+1 314 821 0070",
    "sg:postcode":"63129",
    "sg:province":"MO",
    "sg:tags":[
        "wear",
        "formal"
    ],
    "wof:name":"Gingiss Formalwear",
    "wof:placetype":"venue"
},
  "geometry": {"coordinates":[-90.329525,38.505355],"type":"Point"}
}