{
  "type": "Feature",
  "properties": {
    "iso:country":"US",
    "sg:address":"128 W 10th St",
    "sg:city":"Lamar",
    "sg:classifiers":[
        {
            "category":"Insurance",
            "subcategory":"Insurance Agent",
            "type":"Services"
        }
    ],
    "sg:phone":"+1 417 682 3131",
    "sg:postcode":"64759",
    "sg:province":"MO",
    "wof:name":"McManis Insurance Assoc LLC",
    "wof:placetype":"venue"
},
  "geometry": {"coordinates":[-94.27727400000001,37.495806],"type":"Point"}
}