{
  "type": "Feature",
  "properties": {
    "iso:country":"US",
    "sg:address":"500 NW R D Mize Rd",
    "sg:city":"Blue Springs",
    "sg:classifiers":[
        {
            "category":"Manufacturing",
            "subcategory":"Printing",
            "type":"Manufacturing & Wholesale Goods"
        }
    ],
    "sg:phone":"+1 816 229 9161",
    "sg:postcode":"64014",
    "sg:province":"MO",
    "sg:tags":[
        "newspaper"
    ],
    "sg:website":"www.examiner.net",
    "wof:name":"Blue Springs Examiner",
    "wof:placetype":"venue"
},
  "geometry": {"coordinates":[-94.269232,39.023725],"type":"Point"}
}