{
  "type": "Feature",
  "properties": {
    "iso:country":"US",
    "sg:address":"725 W Battlefield Rd",
    "sg:city":"Springfield",
    "sg:classifiers":[
        {
            "category":"Health Services",
            "subcategory":"Clinic",
            "type":"Services"
        }
    ],
    "sg:phone":"+1 417 889 7444",
    "sg:postcode":"65807",
    "sg:province":"MO",
    "wof:name":"Horizon Medical Center",
    "wof:placetype":"venue"
},
  "geometry": {"coordinates":[-93.30038500000001,37.160056],"type":"Point"}
}