{
  "type": "Feature",
  "properties": {
    "iso:country":"US",
    "sg:address":"5916 Marwinette Ave",
    "sg:city":"Saint Louis",
    "sg:classifiers":[
        {
            "category":"Building & Trades",
            "subcategory":"Landscaping Services",
            "type":"Services"
        }
    ],
    "sg:phone":"+1 314 352 1113",
    "sg:postcode":"63116",
    "sg:province":"MO",
    "sg:tags":[
        "landscape"
    ],
    "wof:name":"Shaw Lawn & Landscaping",
    "wof:placetype":"venue"
},
  "geometry": {"coordinates":[-90.266222,38.569227],"type":"Point"}
}