{
  "type": "Feature",
  "properties": {
    "iso:country":"US",
    "sg:address":"115 E College Ave",
    "sg:city":"Fredericktown",
    "sg:classifiers":[
        {
            "category":"Place Of Worship",
            "subcategory":"Church",
            "type":"Public Place"
        },
        {
            "category":"Place Of Worship",
            "type":"Public Place"
        }
    ],
    "sg:phone":"+1 573 783 6322",
    "sg:postcode":"63645",
    "sg:province":"MO",
    "sg:tags":[
        "churches-baptist-general",
        "churches-baptist"
    ],
    "wof:name":"Southern Baptist Convention",
    "wof:placetype":"venue"
},
  "geometry": {"coordinates":[-90.29428,37.557778],"type":"Point"}
}