{
  "type": "Feature",
  "properties": {
    "iso:country":"US",
    "sg:address":"3070 Mercantile Industrial Dr",
    "sg:city":"St Charles",
    "sg:classifiers":[
        {
            "category":"Manufacturing",
            "subcategory":"Building Materials",
            "type":"Manufacturing & Wholesale Goods"
        }
    ],
    "sg:phone":"+1 636 947 7277",
    "sg:postcode":"63301",
    "sg:province":"MO",
    "sg:tags":[
        "member",
        "wood",
        "structural"
    ],
    "wof:name":"Beilsmith Brothers Inc",
    "wof:placetype":"venue"
},
  "geometry": {"coordinates":[-90.478724,38.816485],"type":"Point"}
}