{
  "type": "Feature",
  "properties": {
    "iso:country":"US",
    "sg:address":"4127 Old Homestead Dr",
    "sg:city":"Imperial",
    "sg:classifiers":[
        {
            "category":"Professional",
            "subcategory":"Art Services",
            "type":"Services"
        }
    ],
    "sg:phone":"+1 636 296 5950",
    "sg:postcode":"63052",
    "sg:province":"MO",
    "sg:tags":[
        "interior",
        "designer",
        "decorator"
    ],
    "wof:name":"Interior Details",
    "wof:placetype":"venue"
},
  "geometry": {"coordinates":[-90.483626,38.440128],"type":"Point"}
}