{
  "type": "Feature",
  "properties": {
    "iso:country":"US",
    "sg:address":"153 S Odell Ave",
    "sg:city":"Marshall",
    "sg:classifiers":[
        {
            "category":"Government",
            "subcategory":"Office",
            "type":"Public Place"
        }
    ],
    "sg:phone":"+1 660 886 6908",
    "sg:postcode":"65340",
    "sg:province":"MO",
    "wof:name":"Saline County University Ext",
    "wof:placetype":"venue"
},
  "geometry": {"coordinates":[-93.194968,39.119807],"type":"Point"}
}