{
  "type": "Feature",
  "properties": {
    "iso:country":"US",
    "sg:address":"203 State Hwy 5",
    "sg:city":"Fayette",
    "sg:classifiers":[
        {
            "category":"Utilities",
            "subcategory":"Cable",
            "type":"Services"
        }
    ],
    "sg:phone":"+1 660 248 2058",
    "sg:postcode":"65248",
    "sg:province":"MO",
    "sg:tags":[
        "television"
    ],
    "wof:name":"Comcast Cable",
    "wof:placetype":"venue"
},
  "geometry": {"coordinates":[-92.69644599999999,39.162437],"type":"Point"}
}