{
  "type": "Feature",
  "properties": {
    "iso:country":"US",
    "sg:address":"454 Nature Trail Rd",
    "sg:city":"Blue Eye",
    "sg:classifiers":[
        {
            "category":"Organizations",
            "subcategory":"Professional Association",
            "type":"Services"
        }
    ],
    "sg:phone":"+1 417 779 2177",
    "sg:postcode":"65611",
    "sg:province":"AR",
    "sg:tags":[
        "business"
    ],
    "wof:name":"S C O R E 0237",
    "wof:placetype":"venue"
},
  "geometry": {"coordinates":[-93.393136,36.549175],"type":"Point"}
}