{
  "type": "Feature",
  "properties": {
    "iso:country":"US",
    "sg:address":"117 W 2nd St",
    "sg:city":"Holden",
    "sg:classifiers":[
        {
            "category":"Banks & Credit Unions",
            "subcategory":"Bank",
            "type":"Services"
        },
        {
            "category":"Shopping",
            "subcategory":"Used Merchandise",
            "type":"Retail Goods"
        }
    ],
    "sg:phone":"+1 816 732 4026",
    "sg:postcode":"64040",
    "sg:province":"MO",
    "sg:tags":[
        "resale",
        "shop",
        "second",
        "hand"
    ],
    "wof:name":"Hope Thrift Center",
    "wof:placetype":"venue"
},
  "geometry": {"coordinates":[-93.989953,38.717944],"type":"Point"}
}