{
  "type": "Feature",
  "properties": {
    "iso:country":"US",
    "sg:address":"164 Aldersgate Dr",
    "sg:city":"Nixa",
    "sg:classifiers":[
        {
            "category":"Food & Beverages",
            "subcategory":"Specialty",
            "type":"Retail Goods"
        }
    ],
    "sg:phone":"+1 417 724 0900",
    "sg:postcode":"65714",
    "sg:province":"MO",
    "wof:name":"Einsteins Nutrition",
    "wof:placetype":"venue"
},
  "geometry": {"coordinates":[-93.295518,37.060003],"type":"Point"}
}