{
  "type": "Feature",
  "properties": {
    "iso:country":"US",
    "sg:address":"13012 Manchester Rd",
    "sg:city":"St Louis",
    "sg:classifiers":[
        {
            "category":"Shopping",
            "subcategory":"Clothing, Apparel, & Fashions",
            "type":"Retail Goods"
        }
    ],
    "sg:phone":"+1 314 822 0504",
    "sg:postcode":"63131",
    "sg:province":"MO",
    "sg:tags":[
        "tailor"
    ],
    "wof:name":"Tailor Made Alterations",
    "wof:placetype":"venue"
},
  "geometry": {"coordinates":[-90.4618,38.602408],"type":"Point"}
}