{
  "type": "Feature",
  "properties": {
    "iso:country":"US",
    "sg:address":"4107 N Cherry St",
    "sg:city":"Kansas City",
    "sg:classifiers":[
        {
            "category":"Personal",
            "subcategory":"Beauty Salon",
            "type":"Services"
        }
    ],
    "sg:phone":"+1 816 455 7206",
    "sg:postcode":"64116",
    "sg:province":"MO",
    "wof:name":"Salon Safari",
    "wof:placetype":"venue"
},
  "geometry": {"coordinates":[-94.576683,39.168522],"type":"Point"}
}