{
  "type": "Feature",
  "properties": {
    "iso:country":"US",
    "sg:address":"103 Washington St",
    "sg:city":"Mount Vernon",
    "sg:classifiers":[
        {
            "category":"Retail",
            "subcategory":"Auto Repair",
            "type":"Services"
        }
    ],
    "sg:phone":"+1 417 466 2622",
    "sg:postcode":"65712",
    "sg:province":"MO",
    "sg:tags":[
        "automotive"
    ],
    "wof:name":"I 44 Truck Interiors",
    "wof:placetype":"venue"
},
  "geometry": {"coordinates":[-93.809257,37.101564],"type":"Point"}
}