{
  "type": "Feature",
  "properties": {
    "iso:country":"US",
    "sg:address":"1150 Grand Blvd",
    "sg:city":"Kansas City",
    "sg:classifiers":[
        {
            "category":"Professional",
            "subcategory":"Lawyer & Legal Services",
            "type":"Services"
        }
    ],
    "sg:phone":"+1 816 842 3030",
    "sg:postcode":"64106",
    "sg:province":"MO",
    "wof:name":"Shirkey Robt L",
    "wof:placetype":"venue"
},
  "geometry": {"coordinates":[-94.580972,39.10045],"type":"Point"}
}