{
  "type": "Feature",
  "properties": {
    "iso:country":"US",
    "sg:address":"731 E Yerby St",
    "sg:city":"Marshall",
    "sg:classifiers":[
        {
            "category":"Shopping",
            "subcategory":"Gifts & Souvenirs",
            "type":"Retail Goods"
        }
    ],
    "sg:phone":"+1 660 886 7679",
    "sg:postcode":"65340",
    "sg:province":"MO",
    "wof:name":"Balloons Unlimited",
    "wof:placetype":"venue"
},
  "geometry": {"coordinates":[-93.18228000000001,39.114176],"type":"Point"}
}