{
  "type": "Feature",
  "properties": {
    "iso:country":"US",
    "sg:address":"201 W Columbia St",
    "sg:city":"Farmington",
    "sg:classifiers":[
        {
            "category":"Organizations",
            "subcategory":"Religious Organization",
            "type":"Services"
        }
    ],
    "sg:phone":"+1 573 756 5314",
    "sg:postcode":"63640",
    "sg:province":"MO",
    "sg:tags":[
        "church"
    ],
    "wof:name":"Christian Church Farmington",
    "wof:placetype":"venue"
},
  "geometry": {"coordinates":[-90.42438199999999,37.780819],"type":"Point"}
}