{
  "type": "Feature",
  "properties": {
    "iso:country":"US",
    "sg:address":"31034 Pleasant Hill Rd",
    "sg:city":"Sedalia",
    "sg:classifiers":[
        {
            "category":"Autos & Motor Vehicles",
            "subcategory":"Automobile Sales",
            "type":"Retail Goods"
        }
    ],
    "sg:phone":"+1 660 826 3204",
    "sg:postcode":"65301",
    "sg:province":"MO",
    "sg:tags":[
        "car",
        "used",
        "dealer"
    ],
    "wof:name":"Z's Auto Sales",
    "wof:placetype":"venue"
},
  "geometry": {"coordinates":[-93.17937999999999,38.621933],"type":"Point"}
}