{
  "type": "Feature",
  "properties": {
    "iso:country":"US",
    "sg:address":"18 S Jefferson Ave",
    "sg:city":"Marshall",
    "sg:classifiers":[
        {
            "category":"Shopping",
            "subcategory":"Jewelry",
            "type":"Retail Goods"
        }
    ],
    "sg:phone":"+1 660 886 2251",
    "sg:postcode":"65340",
    "sg:province":"MO",
    "sg:tags":[
        "jeweler"
    ],
    "wof:name":"Sturhahn Jewelers",
    "wof:placetype":"venue"
},
  "geometry": {"coordinates":[-93.195849,39.120638],"type":"Point"}
}