{
  "type": "Feature",
  "properties": {
    "addr:full":"829 Jansen St Chillicothe MO 64601",
    "addr:housenumber":"829",
    "addr:postcode":"64601",
    "addr:street":"Jansen St",
    "iso:country":"US",
    "sg:address":"829 Jansen St",
    "sg:city":"Chillicothe",
    "sg:classifiers":[
        {
            "category":"Organizations",
            "subcategory":"Community Association",
            "type":"Services"
        }
    ],
    "sg:phone":"+1 660 646 6921",
    "sg:postcode":"64601",
    "sg:province":"MO",
    "wof:name":"Delta Kappa Gamma Society",
    "wof:placetype":"venue"
},
  "geometry": {"coordinates":[-93.573075,39.79523],"type":"Point"}
}