{
  "type": "Feature",
  "properties": {
    "iso:country":"US",
    "sg:address":"65 NE 500th Rd",
    "sg:city":"Warrensburg",
    "sg:classifiers":[
        {
            "category":"Building & Trades",
            "subcategory":"Landscaping Services",
            "type":"Services"
        }
    ],
    "sg:phone":"+1 660 747 5364",
    "sg:postcode":"64093",
    "sg:province":"MO",
    "wof:name":"Dan E Deevers",
    "wof:placetype":"venue"
},
  "geometry": {"coordinates":[-93.729586,38.833894],"type":"Point"}
}