{
  "type": "Feature",
  "properties": {
    "iso:country":"US",
    "sg:address":"412 W 11 St",
    "sg:city":"Kansas City",
    "sg:classifiers":[
        {
            "category":"Real Estate",
            "subcategory":"Real Estate Agent",
            "type":"Services"
        }
    ],
    "sg:phone":"+1 816 472 1220",
    "sg:postcode":"64105",
    "sg:province":"MO",
    "wof:name":"MBA Realty",
    "wof:placetype":"venue"
},
  "geometry": {"coordinates":[-94.58983499999999,39.101136],"type":"Point"}
}