{
  "type": "Feature",
  "properties": {
    "iso:country":"US",
    "sg:address":"11909 Madison Ave",
    "sg:city":"Kansas City",
    "sg:classifiers":[
        {
            "category":"Wholesale",
            "subcategory":"Non-durable Goods",
            "type":"Manufacturing & Wholesale Goods"
        }
    ],
    "sg:phone":"+1 816 941 4406",
    "sg:postcode":"64145",
    "sg:province":"MO",
    "sg:tags":[
        "gift"
    ],
    "wof:name":"Mid States Gift Sales",
    "wof:placetype":"venue"
},
  "geometry": {"coordinates":[-94.605465,38.912582],"type":"Point"}
}