{
  "type": "Feature",
  "properties": {
    "iso:country":"US",
    "sg:address":"551 SE Melody Ln",
    "sg:city":"Lees Summit",
    "sg:classifiers":[
        {
            "category":"Insurance",
            "subcategory":"Insurance Agent",
            "type":"Services"
        }
    ],
    "sg:phone":"+1 816 554 0533",
    "sg:postcode":"64063",
    "sg:province":"MO",
    "wof:name":"Direct General Ins Agency",
    "wof:placetype":"venue"
},
  "geometry": {"coordinates":[-94.362353,38.907563],"type":"Point"}
}