{
  "type": "Feature",
  "properties": {
    "iso:country":"US",
    "sg:address":"8015 Monroe Ave",
    "sg:city":"Saint Louis",
    "sg:classifiers":[
        {
            "category":"Organizations",
            "subcategory":"Religious Organization",
            "type":"Services"
        }
    ],
    "sg:phone":"+1 314 423 1075",
    "sg:postcode":"63114",
    "sg:province":"MO",
    "wof:name":"Marian Centre of St Louis",
    "wof:placetype":"venue"
},
  "geometry": {"coordinates":[-90.33081199999999,38.68683],"type":"Point"}
}