{
  "type": "Feature",
  "properties": {
    "iso:country":"US",
    "sg:address":"1402 Gettysburg Lndg",
    "sg:city":"St Charles",
    "sg:classifiers":[
        {
            "category":"Social Services",
            "subcategory":"Child Care",
            "type":"Services"
        }
    ],
    "sg:phone":"+1 636 447 8003",
    "sg:postcode":"63303",
    "sg:province":"MO",
    "sg:tags":[
        "kindergarten",
        "academic",
        "school"
    ],
    "wof:name":"Goddard School",
    "wof:placetype":"venue"
},
  "geometry": {"coordinates":[-90.551253,38.751505],"type":"Point"}
}