{
  "type": "Feature",
  "properties": {
    "iso:country":"US",
    "sg:address":"6859 Audrain Rd 132",
    "sg:city":"Centralia",
    "sg:classifiers":[
        {
            "category":"Professional",
            "subcategory":"Business Services",
            "type":"Services"
        }
    ],
    "sg:phone":"+1 573 682 2128",
    "sg:postcode":"65240",
    "sg:province":"MO",
    "sg:tags":[
        "mfg",
        "assembly",
        "contract",
        "oxygen",
        "tent"
    ],
    "wof:name":"Sunnydale / Goss",
    "wof:placetype":"venue"
},
  "geometry": {"coordinates":[-92.179975,39.299863],"type":"Point"}
}