{
  "type": "Feature",
  "properties": {
    "iso:country":"US",
    "sg:address":"5145 US Hwy 67",
    "sg:city":"Florissant",
    "sg:classifiers":[
        {
            "category":"Organizations",
            "subcategory":"Religious Organization",
            "type":"Services"
        }
    ],
    "sg:phone":"+1 314 355 7800",
    "sg:postcode":"63034",
    "sg:province":"MO",
    "wof:name":"Day Star Church",
    "wof:placetype":"venue"
},
  "geometry": {"coordinates":[-90.262272,38.822114],"type":"Point"}
}