{
  "type": "Feature",
  "properties": {
    "iso:country":"US",
    "sg:address":"1 N Delaware St",
    "sg:city":"Butler",
    "sg:classifiers":[
        {
            "category":"Government",
            "subcategory":"Court House",
            "type":"Public Place"
        }
    ],
    "sg:phone":"+1 660 679 4030",
    "sg:postcode":"64730",
    "sg:province":"MO",
    "sg:tags":[
        "county",
        "counsel"
    ],
    "wof:name":"Bates County Attorney",
    "wof:placetype":"venue"
},
  "geometry": {"coordinates":[-94.33311999999999,38.258516],"type":"Point"}
}