{
  "type": "Feature",
  "properties": {
    "iso:country":"US",
    "sg:address":"135 S Walnut St",
    "sg:city":"Steele",
    "sg:classifiers":[
        {
            "category":"Structure",
            "subcategory":"Warehouse",
            "type":"Public Place"
        },
        {
            "category":"Retail",
            "subcategory":"Storage",
            "type":"Services"
        }
    ],
    "sg:phone":"+1 573 695 7288",
    "sg:postcode":"63877",
    "sg:province":"MO",
    "sg:tags":[
        "self",
        "warehouses-public-commercial"
    ],
    "wof:name":"Pemco Storage, Inc.",
    "wof:placetype":"venue"
},
  "geometry": {"coordinates":[-89.831057,36.082847],"type":"Point"}
}