{
  "type": "Feature",
  "properties": {
    "iso:country":"US",
    "sg:address":"905 State Hwy 92",
    "sg:city":"Kearney",
    "sg:classifiers":[
        {
            "category":"Utilities",
            "subcategory":"Fuel Oil & Lpg",
            "type":"Services"
        }
    ],
    "sg:phone":"+1 816 628 5669",
    "sg:postcode":"64060",
    "sg:province":"MO",
    "sg:tags":[
        "propane",
        "gas"
    ],
    "sg:website":"www.ferrellgas.com",
    "wof:name":"Ferrellgas",
    "wof:placetype":"venue"
},
  "geometry": {"coordinates":[-94.376426,39.367841],"type":"Point"}
}