{
  "type": "Feature",
  "properties": {
    "iso:country":"US",
    "sg:address":"401 N Osage Blvd",
    "sg:city":"Nevada",
    "sg:classifiers":[
        {
            "category":"Food & Beverages",
            "subcategory":"Groceries & Convenience Stores",
            "type":"Retail Goods"
        }
    ],
    "sg:phone":"+1 417 667 8427",
    "sg:postcode":"64772",
    "sg:province":"MO",
    "wof:name":"Cash N'Dash",
    "wof:placetype":"venue"
},
  "geometry": {"coordinates":[-94.34939799999999,37.842524],"type":"Point"}
}