{
  "type": "Feature",
  "properties": {
    "iso:country":"US",
    "sg:address":"1510 S Main St",
    "sg:city":"Joplin",
    "sg:classifiers":[
        {
            "category":"Shopping",
            "subcategory":"Clothing, Apparel, & Fashions",
            "type":"Retail Goods"
        },
        {
            "category":"Banks & Credit Unions",
            "subcategory":"Bank",
            "type":"Services"
        },
        {
            "category":"Shopping",
            "subcategory":"Used Merchandise",
            "type":"Retail Goods"
        }
    ],
    "sg:phone":"+1 417 781 6311",
    "sg:postcode":"64804",
    "sg:province":"MO",
    "sg:tags":[
        "shop",
        "resale",
        "second",
        "consignment",
        "hand"
    ],
    "wof:name":"My Sister's Closet",
    "wof:placetype":"venue"
},
  "geometry": {"coordinates":[-94.51387800000001,37.074989],"type":"Point"}
}