{
  "type": "Feature",
  "properties": {
    "addr:full":"32152 Hwy 135 Gravois Mills MO 65037",
    "addr:housenumber":"32152",
    "addr:postcode":"65037",
    "addr:street":"Hwy 135 Gravois Mills",
    "iso:country":"US",
    "sg:address":"32152 Hwy 135",
    "sg:city":"Gravois Mills",
    "sg:classifiers":[
        {
            "category":"Professional",
            "subcategory":"Employment Agencies",
            "type":"Services"
        }
    ],
    "sg:phone":"+1 573 374 5388",
    "sg:postcode":"65037",
    "sg:province":"MO",
    "wof:name":"Management Recruiters Intl",
    "wof:placetype":"venue"
},
  "geometry": {"coordinates":[-92.85127900000001,38.219359],"type":"Point"}
}