{
  "type": "Feature",
  "properties": {
    "iso:country":"US",
    "sg:address":"32294 Maries Road 213",
    "sg:city":"Vienna",
    "sg:classifiers":[
        {
            "category":"Farming",
            "subcategory":"Livestock Farm",
            "type":"Manufacturing & Wholesale Goods"
        }
    ],
    "sg:phone":"+1 573 422 3070",
    "sg:postcode":"65582",
    "sg:province":"MO",
    "sg:tags":[
        "beef",
        "feedlot",
        "cattle"
    ],
    "wof:name":"Maries Valley Veiw Farms",
    "wof:placetype":"venue"
},
  "geometry": {"coordinates":[-91.985584,38.204446],"type":"Point"}
}