{
  "type": "Feature",
  "properties": {
    "iso:country":"US",
    "sg:address":"103 Cypress St",
    "sg:city":"Kennett",
    "sg:phone":"+1 573 888 3408",
    "sg:postcode":"63857",
    "sg:province":"MO",
    "sg:tags":[
        "equipment",
        "commercial"
    ],
    "wof:name":"Farrell Equipment Co",
    "wof:placetype":"venue"
},
  "geometry": {"coordinates":[-90.045875,36.236631],"type":"Point"}
}