{
  "type": "Feature",
  "properties": {
    "iso:country":"US",
    "sg:address":"1500 Arapaho",
    "sg:city":"Blue Springs",
    "sg:classifiers":[
        {
            "category":"Shopping",
            "subcategory":"Computers & Home Electronics",
            "type":"Retail Goods"
        }
    ],
    "sg:phone":"+1 816 903 3474",
    "sg:postcode":"64015",
    "sg:province":"MO",
    "sg:tags":[
        "equipment",
        "satellite",
        "system"
    ],
    "wof:name":"Dish Installer",
    "wof:placetype":"venue"
},
  "geometry": {"coordinates":[-94.2837,39.001072],"type":"Point"}
}