{
  "type": "Feature",
  "properties": {
    "iso:country":"US",
    "sg:address":"48 Main St",
    "sg:city":"Cassville",
    "sg:classifiers":[
        {
            "category":"Personal",
            "type":"Services"
        }
    ],
    "sg:phone":"+1 417 847 5340",
    "sg:postcode":"65625",
    "sg:province":"MO",
    "wof:name":"Electric Beach Tanning Salon",
    "wof:placetype":"venue"
},
  "geometry": {"coordinates":[-93.873215,36.673337],"type":"Point"}
}