{
  "type": "Feature",
  "properties": {
    "iso:country":"US",
    "sg:address":"600 Aspen Ridge Ct",
    "sg:city":"Chesterfield",
    "sg:classifiers":[
        {
            "category":"Professional",
            "subcategory":"Management & Consulting",
            "type":"Services"
        }
    ],
    "sg:phone":"+1 636 207 1985",
    "sg:postcode":"63017",
    "sg:province":"MO",
    "sg:tags":[
        "business"
    ],
    "wof:name":"Reinholz Consulting Inc",
    "wof:placetype":"venue"
},
  "geometry": {"coordinates":[-90.519167,38.637715],"type":"Point"}
}