{
  "type": "Feature",
  "properties": {
    "iso:country":"US",
    "sg:address":"1359 Green Elm Dr",
    "sg:city":"Fenton",
    "sg:classifiers":[
        {
            "category":"Building & Trades",
            "subcategory":"Construction",
            "type":"Services"
        }
    ],
    "sg:phone":"+1 314 952 1377",
    "sg:postcode":"63026",
    "sg:province":"MO",
    "sg:tags":[
        "roofing",
        "contractor"
    ],
    "wof:name":"Domian Roofing LLC",
    "wof:placetype":"venue"
},
  "geometry": {"coordinates":[-90.47831100000001,38.517246],"type":"Point"}
}