{
  "type": "Feature",
  "properties": {
    "iso:country":"US",
    "sg:address":"15592 Private Drive 3442",
    "sg:city":"Savannah",
    "sg:classifiers":[
        {
            "category":"Shopping",
            "subcategory":"Gifts & Souvenirs",
            "type":"Retail Goods"
        }
    ],
    "sg:phone":"+1 816 324 5574",
    "sg:postcode":"64485",
    "sg:province":"MO",
    "sg:tags":[
        "shop"
    ],
    "wof:name":"Waterwheel Crafters Mall & Esp",
    "wof:placetype":"venue"
},
  "geometry": {"coordinates":[-94.807166,39.900524],"type":"Point"}
}