{
  "type": "Feature",
  "properties": {
    "iso:country":"US",
    "sg:address":"1421 E North Ave",
    "sg:city":"Belton",
    "sg:classifiers":[
        {
            "category":"Autos & Motor Vehicles",
            "subcategory":"Automobile Sales",
            "type":"Retail Goods"
        }
    ],
    "sg:phone":"+1 816 322 4443",
    "sg:postcode":"64012",
    "sg:province":"MO",
    "sg:tags":[
        "car",
        "used",
        "dealer"
    ],
    "wof:name":"Thompson Sackman Motors Inc",
    "wof:placetype":"venue"
},
  "geometry": {"coordinates":[-94.52184,38.814018],"type":"Point"}
}