{
  "type": "Feature",
  "properties": {
    "iso:country":"US",
    "sg:address":"231 State Hwy A",
    "sg:city":"Lamar",
    "sg:classifiers":[
        {
            "category":"Farming",
            "subcategory":"Farm",
            "type":"Manufacturing & Wholesale Goods"
        }
    ],
    "sg:phone":"+1 417 682 2538",
    "sg:postcode":"64759",
    "sg:province":"MO",
    "sg:tags":[
        "crop",
        "general"
    ],
    "wof:name":"Linderhof Farms Inc",
    "wof:placetype":"venue"
},
  "geometry": {"coordinates":[-94.186626,37.531955],"type":"Point"}
}