{
  "type": "Feature",
  "properties": {
    "iso:country":"US",
    "sg:address":"411 E Cherry St",
    "sg:city":"Troy",
    "sg:classifiers":[
        {
            "category":"Health Services",
            "subcategory":"Doctor",
            "type":"Services"
        }
    ],
    "sg:phone":"+1 636 528 6820",
    "sg:postcode":"63379",
    "sg:province":"MO",
    "sg:tags":[
        "dentist"
    ],
    "wof:name":"C Kevin Harrell DDS",
    "wof:placetype":"venue"
},
  "geometry": {"coordinates":[-90.97702099999999,38.980987],"type":"Point"}
}