{
  "type": "Feature",
  "properties": {
    "iso:country":"US",
    "sg:address":"11 Peterson Ln",
    "sg:city":"Silex",
    "sg:phone":"+1 573 656 3490",
    "sg:postcode":"63377",
    "sg:province":"MO",
    "sg:tags":[
        "farm",
        "field",
        "crop"
    ],
    "wof:name":"Craig Aubuchon",
    "wof:placetype":"venue"
},
  "geometry": {"coordinates":[-91.154196,39.059293],"type":"Point"}
}