{
  "type": "Feature",
  "properties": {
    "iso:country":"US",
    "sg:address":"201 N Dodgion St",
    "sg:city":"Independence",
    "sg:classifiers":[
        {
            "category":"Government",
            "subcategory":"Office",
            "type":"Public Place"
        }
    ],
    "sg:phone":"+1 816 325 7370",
    "sg:postcode":"64050",
    "sg:province":"MO",
    "sg:tags":[
        "village"
    ],
    "sg:website":"www.independencemo.org",
    "wof:name":"Roger T Sermon Community Ctr",
    "wof:placetype":"venue"
},
  "geometry": {"coordinates":[-94.41092399999999,39.09544],"type":"Point"}
}