{
  "type": "Feature",
  "properties": {
    "iso:country":"US",
    "sg:address":"20 Corporate Hills Dr",
    "sg:city":"Saint Charles",
    "sg:classifiers":[
        {
            "category":"Banks & Credit Unions",
            "subcategory":"Bank",
            "type":"Services"
        }
    ],
    "sg:phone":"+1 636 916 8500",
    "sg:postcode":"63301",
    "sg:province":"MO",
    "sg:tags":[
        "depository",
        "banking"
    ],
    "wof:name":"Western Union Fincl Svcs Inc",
    "wof:placetype":"venue"
},
  "geometry": {"coordinates":[-90.485013,38.81193],"type":"Point"}
}