{
  "type": "Feature",
  "properties": {
    "iso:country":"US",
    "sg:address":"315 S 3rd St",
    "sg:city":"Hannibal",
    "sg:classifiers":[
        {
            "category":"Shopping",
            "subcategory":"Used Merchandise",
            "type":"Retail Goods"
        }
    ],
    "sg:phone":"+1 573 248 2955",
    "sg:postcode":"63401",
    "sg:province":"MO",
    "wof:name":"Smiths Treasure Chest LLC",
    "wof:placetype":"venue"
},
  "geometry": {"coordinates":[-91.355762,39.707457],"type":"Point"}
}