{
  "type": "Feature",
  "properties": {
    "iso:country":"US",
    "sg:address":"9400 Sears Ln",
    "sg:city":"Poplar Bluff",
    "sg:classifiers":[
        {
            "category":"Organizations",
            "subcategory":"Religious Organization",
            "type":"Services"
        }
    ],
    "sg:phone":"+1 573 785 5622",
    "sg:postcode":"63901",
    "sg:province":"MO",
    "wof:name":"Morning Star Mssn Baptst Chrch",
    "wof:placetype":"venue"
},
  "geometry": {"coordinates":[-90.508735,36.861399],"type":"Point"}
}