{
  "type": "Feature",
  "properties": {
    "iso:country":"US",
    "sg:address":"215 S Kirkwood Rd",
    "sg:city":"Saint Louis",
    "sg:classifiers":[
        {
            "category":"Restaurant",
            "type":"Food & Drink"
        }
    ],
    "sg:phone":"+1 314 966 3666",
    "sg:postcode":"63122",
    "sg:province":"MO",
    "sg:tags":[
        "pizza"
    ],
    "wof:name":"Imos of Kirkwood",
    "wof:placetype":"venue"
},
  "geometry": {"coordinates":[-90.40649000000001,38.578995],"type":"Point"}
}