{
  "type": "Feature",
  "properties": {
    "iso:country":"US",
    "sg:address":"11424 US Hwy 24",
    "sg:city":"Independence",
    "sg:classifiers":[
        {
            "category":"Organizations",
            "subcategory":"Community Association",
            "type":"Services"
        }
    ],
    "sg:phone":"+1 816 461 1755",
    "sg:postcode":"64054",
    "sg:province":"MO",
    "sg:tags":[
        "fraternal"
    ],
    "wof:name":"Fraternal Order Of Eagles",
    "wof:placetype":"venue"
},
  "geometry": {"coordinates":[-94.44201099999999,39.102453],"type":"Point"}
}