{
  "type": "Feature",
  "properties": {
    "iso:country":"US",
    "sg:address":"134 61st St",
    "sg:city":"Trenton",
    "sg:phone":"+1 660 359 6403",
    "sg:postcode":"64683",
    "sg:province":"MO",
    "sg:tags":[
        "farm",
        "grain",
        "cash"
    ],
    "wof:name":"Meservey Farms Inc",
    "wof:placetype":"venue"
},
  "geometry": {"coordinates":[-93.57795400000001,39.992892],"type":"Point"}
}