{
  "type": "Feature",
  "properties": {
    "iso:country":"US",
    "sg:address":"900 Madison St",
    "sg:city":"Jefferson City",
    "sg:classifiers":[
        {
            "category":"Health Services",
            "subcategory":"Doctor",
            "type":"Services"
        }
    ],
    "sg:phone":"+1 573 634 2575",
    "sg:postcode":"65101",
    "sg:province":"MO",
    "wof:name":"Robert L Johnston DDS",
    "wof:placetype":"venue"
},
  "geometry": {"coordinates":[-92.17817599999999,38.57],"type":"Point"}
}