{
  "type": "Feature",
  "properties": {
    "iso:country":"US",
    "sg:address":"320 S Baltimore St",
    "sg:city":"Kirksville",
    "sg:classifiers":[
        {
            "category":"Autos & Motor Vehicles",
            "subcategory":"Auto Supplies",
            "type":"Retail Goods"
        }
    ],
    "sg:phone":"+1 660 665 5648",
    "sg:postcode":"63501",
    "sg:province":"MO",
    "wof:name":"Hunters Banner Tire Service",
    "wof:placetype":"venue"
},
  "geometry": {"coordinates":[-92.572036,40.192895],"type":"Point"}
}