{
  "type": "Feature",
  "properties": {
    "iso:country":"US",
    "sg:address":"30352 State Hwy 5",
    "sg:city":"Tipton",
    "sg:classifiers":[
        {
            "category":"Insurance",
            "subcategory":"Hazard Insurance",
            "type":"Services"
        }
    ],
    "sg:phone":"+1 660 433 5500",
    "sg:postcode":"65081",
    "sg:province":"MO",
    "sg:tags":[
        "bond"
    ],
    "wof:name":"Viking Bail Bonds",
    "wof:placetype":"venue"
},
  "geometry": {"coordinates":[-92.798131,38.654149],"type":"Point"}
}