{
  "type": "Feature",
  "properties": {
    "iso:country":"US",
    "sg:address":"635 Francis St",
    "sg:city":"St Joseph",
    "sg:classifiers":[
        {
            "category":"Organizations",
            "subcategory":"Community Association",
            "type":"Services"
        }
    ],
    "sg:phone":"+1 816 232 0050",
    "sg:postcode":"64501",
    "sg:province":"MO",
    "sg:website":"www.youth-alliance.org",
    "wof:name":"St Joseph Youth Alliance",
    "wof:placetype":"venue"
},
  "geometry": {"coordinates":[-94.85222,39.767476],"type":"Point"}
}