{
  "type": "Feature",
  "properties": {
    "iso:country":"US",
    "sg:address":"18921 E Valley View Pkwy",
    "sg:city":"Independence",
    "sg:classifiers":[
        {
            "category":"Fast Food",
            "type":"Food & Drink"
        },
        {
            "category":"Restaurant",
            "type":"Food & Drink"
        },
        {
            "category":"Food & Beverages",
            "subcategory":"Groceries & Convenience Stores",
            "type":"Retail Goods"
        }
    ],
    "sg:phone":"+1 816 795 8037",
    "sg:postcode":"64055",
    "sg:province":"MO",
    "sg:tags":[
        "shop",
        "american",
        "sandwich",
        "take"
    ],
    "sg:website":"http://www.subway.com",
    "wof:name":"SUBWAY",
    "wof:placetype":"venue"
},
  "geometry": {"coordinates":[-94.356286,39.034002],"type":"Point"}
}