{
  "type": "Feature",
  "properties": {
    "iso:country":"US",
    "sg:address":"837 Carrolton Ln",
    "sg:city":"Poplar Bluff",
    "sg:classifiers":[
        {
            "category":"Restaurant",
            "type":"Food & Drink"
        }
    ],
    "sg:phone":"+1 573 785 8328",
    "sg:postcode":"63901",
    "sg:province":"MO",
    "sg:tags":[
        "caterer"
    ],
    "wof:name":"Mike's Barbeque",
    "wof:placetype":"venue"
},
  "geometry": {"coordinates":[-90.400009,36.782075],"type":"Point"}
}