{
  "type": "Feature",
  "properties": {
    "iso:country":"US",
    "sg:address":"208 E 18th Ave",
    "sg:city":"Kansas City",
    "sg:classifiers":[
        {
            "category":"Professional",
            "subcategory":"Business Services",
            "type":"Services"
        }
    ],
    "sg:phone":"+1 816 471 4200",
    "sg:postcode":"64116",
    "sg:province":"MO",
    "wof:name":"Pete Walton Agency Inc",
    "wof:placetype":"venue"
},
  "geometry": {"coordinates":[-94.578681,39.140322],"type":"Point"}
}