{
  "type": "Feature",
  "properties": {
    "iso:country":"US",
    "sg:address":"4845 Co Rte 202",
    "sg:city":"Fulton",
    "sg:classifiers":[
        {
            "category":"Building & Trades",
            "subcategory":"Equipment Rental",
            "type":"Services"
        }
    ],
    "sg:phone":"+1 573 642 4397",
    "sg:postcode":"65251",
    "sg:province":"MO",
    "wof:name":"Wk Rentals",
    "wof:placetype":"venue"
},
  "geometry": {"coordinates":[-91.982967,38.879749],"type":"Point"}
}