{
  "type": "Feature",
  "properties": {
    "iso:country":"US",
    "sg:address":"1808 Interstate 70 Dr SW",
    "sg:city":"Columbia",
    "sg:classifiers":[
        {
            "category":"Professional",
            "subcategory":"Printing & Photocopies",
            "type":"Services"
        }
    ],
    "sg:phone":"+1 573 445 4185",
    "sg:postcode":"65203",
    "sg:province":"MO",
    "sg:tags":[
        "duplicating",
        "copying"
    ],
    "wof:name":"Lanier Worldwide Inc",
    "wof:placetype":"venue"
},
  "geometry": {"coordinates":[-92.36668899999999,38.966311],"type":"Point"}
}