{
  "type": "Feature",
  "properties": {
    "iso:country":"US",
    "sg:address":"7222 SW Arnold Rd",
    "sg:city":"Plattsburg",
    "sg:classifiers":[
        {
            "category":"Wholesale",
            "subcategory":"Machinery & Supplies",
            "type":"Manufacturing & Wholesale Goods"
        }
    ],
    "sg:phone":"+1 816 930 3085",
    "sg:postcode":"64477",
    "sg:province":"MO",
    "sg:tags":[
        "equipment",
        "establishment"
    ],
    "wof:name":"Anner Inc",
    "wof:placetype":"venue"
},
  "geometry": {"coordinates":[-94.491348,39.470055],"type":"Point"}
}