{
  "type": "Feature",
  "properties": {
    "iso:country":"US",
    "sg:address":"807 Hazelwest Dr",
    "sg:city":"Hazelwood",
    "sg:classifiers":[
        {
            "category":"Health Services",
            "subcategory":"Doctor",
            "type":"Services"
        }
    ],
    "sg:phone":"+1 314 731 5464",
    "sg:postcode":"63042",
    "sg:province":"MO",
    "sg:tags":[
        "dentist"
    ],
    "wof:name":"E Eugene King IV DDS",
    "wof:placetype":"venue"
},
  "geometry": {"coordinates":[-90.377166,38.783328],"type":"Point"}
}