{
  "type": "Feature",
  "properties": {
    "iso:country":"US",
    "sg:address":"3310 W College St",
    "sg:city":"Springfield",
    "sg:classifiers":[
        {
            "category":"Wholesale",
            "subcategory":"Painting Supplies",
            "type":"Manufacturing & Wholesale Goods"
        },
        {
            "category":"Retail",
            "subcategory":"Repair Shop",
            "type":"Services"
        },
        {
            "category":"Home & Garden",
            "subcategory":"Hardware",
            "type":"Retail Goods"
        },
        {
            "category":"Home & Garden",
            "subcategory":"Building Materials",
            "type":"Retail Goods"
        },
        {
            "category":"Wholesale",
            "subcategory":"Hardware",
            "type":"Manufacturing & Wholesale Goods"
        },
        {
            "category":"Home & Garden",
            "subcategory":"Garden Supply",
            "type":"Retail Goods"
        }
    ],
    "sg:phone":"+1 417 869 2912",
    "sg:postcode":"65802",
    "sg:province":"MO",
    "sg:tags":[
        "renting",
        "lawn",
        "outdoor",
        "power",
        "equipment",
        "equipment-sales",
        "landscaping",
        "saw",
        "paint",
        "store"
    ],
    "sg:website":"http://www.stihldealer.net/default-dealer-042833.aspx",
    "wof:name":"Cowan's Ace Hardware, Store 14352",
    "wof:placetype":"venue"
},
  "geometry": {"coordinates":[-93.345286,37.20917],"type":"Point"}
}