{
  "type": "Feature",
  "properties": {
    "iso:country":"US",
    "sg:address":"13843 Apache Way",
    "sg:city":"Greentop",
    "sg:classifiers":[
        {
            "category":"Shopping",
            "subcategory":"Computers & Home Electronics",
            "type":"Retail Goods"
        }
    ],
    "sg:phone":"+1 660 665 4136",
    "sg:postcode":"63546",
    "sg:province":"MO",
    "wof:name":"Sandefur Electronics",
    "wof:placetype":"venue"
},
  "geometry": {"coordinates":[-92.450828,40.291278],"type":"Point"}
}