{
  "type": "Feature",
  "properties": {
    "iso:country":"US",
    "sg:address":"905 Holiday Ave",
    "sg:city":"Hazelwood",
    "sg:classifiers":[
        {
            "category":"Professional",
            "subcategory":"Management & Consulting",
            "type":"Services"
        }
    ],
    "sg:phone":"+1 314 895 3657",
    "sg:postcode":"63042",
    "sg:province":"MO",
    "sg:tags":[
        "retail",
        "direct",
        "sales"
    ],
    "wof:name":"Karens Cakes",
    "wof:placetype":"venue"
},
  "geometry": {"coordinates":[-90.371756,38.789907],"type":"Point"}
}