{
  "type": "Feature",
  "properties": {
    "iso:country":"US",
    "sg:address":"109 Apple Valley Pkwy",
    "sg:city":"Belton",
    "sg:classifiers":[
        {
            "category":"Health Services",
            "subcategory":"Doctor",
            "type":"Services"
        }
    ],
    "sg:phone":"+1 816 331 4200",
    "sg:postcode":"64012",
    "sg:province":"MO",
    "sg:tags":[
        "dentist"
    ],
    "wof:name":"Keystone Dental",
    "wof:placetype":"venue"
},
  "geometry": {"coordinates":[-94.51950100000001,38.81281],"type":"Point"}
}