{
  "type": "Feature",
  "properties": {
    "iso:country":"US",
    "sg:address":"6410 N Oak Fwy",
    "sg:city":"Kansas City",
    "sg:classifiers":[
        {
            "category":"Retail",
            "subcategory":"Laundry & Dry Cleaning",
            "type":"Services"
        }
    ],
    "sg:phone":"+1 816 436 6488",
    "sg:postcode":"64118",
    "sg:province":"MO",
    "sg:tags":[
        "cleaners"
    ],
    "wof:name":"Sheila's Dry Cleaners",
    "wof:placetype":"venue"
},
  "geometry": {"coordinates":[-94.576313,39.210442],"type":"Point"}
}