{
  "type": "Feature",
  "properties": {
    "iso:country":"US",
    "sg:address":"1002 Linn St",
    "sg:city":"Sikeston",
    "sg:classifiers":[
        {
            "category":"Health Services",
            "subcategory":"Nursing And Care Facility",
            "type":"Services"
        },
        {
            "category":"Health Services",
            "subcategory":"Health Practitioner",
            "type":"Services"
        }
    ],
    "sg:phone":"+1 573 481 0800",
    "sg:postcode":"63801",
    "sg:province":"MO",
    "sg:tags":[
        "home",
        "eldercare-home"
    ],
    "wof:name":"White & Associates Home Assistance Inc",
    "wof:placetype":"venue"
},
  "geometry": {"coordinates":[-89.57448,36.880921],"type":"Point"}
}