{
  "type": "Feature",
  "properties": {
    "iso:country":"US",
    "sg:address":"10742 Sunset Hills Plz",
    "sg:city":"St Louis",
    "sg:classifiers":[
        {
            "category":"Banks & Credit Unions",
            "subcategory":"Bank",
            "type":"Services"
        }
    ],
    "sg:phone":"+1 314 909 8588",
    "sg:postcode":"63127",
    "sg:province":"MO",
    "sg:tags":[
        "loan",
        "real estate"
    ],
    "wof:name":"Plaza Mortgage",
    "wof:placetype":"venue"
},
  "geometry": {"coordinates":[-90.407478,38.554405],"type":"Point"}
}