{
  "type": "Feature",
  "properties": {
    "iso:country":"US",
    "sg:address":"5625 E Farm Rd 174",
    "sg:city":"Rogersville",
    "sg:classifiers":[
        {
            "category":"Wholesale",
            "subcategory":"Motor Vehicles",
            "type":"Manufacturing & Wholesale Goods"
        }
    ],
    "sg:phone":"+1 417 881 7319",
    "sg:postcode":"65742",
    "sg:province":"MO",
    "wof:name":"Bradley K Welch",
    "wof:placetype":"venue"
},
  "geometry": {"coordinates":[-93.18074799999999,37.127678],"type":"Point"}
}