{
  "type": "Feature",
  "properties": {
    "iso:country":"US",
    "sg:address":"4011 E 25th St",
    "sg:city":"Joplin",
    "sg:classifiers":[
        {
            "category":"Social Services",
            "subcategory":"Child Care",
            "type":"Services"
        }
    ],
    "sg:phone":"+1 417 624 8061",
    "sg:postcode":"64804",
    "sg:province":"MO",
    "sg:tags":[
        "day"
    ],
    "wof:name":"Grow and Learn Preschool",
    "wof:placetype":"venue"
},
  "geometry": {"coordinates":[-94.45615599999999,37.064219],"type":"Point"}
}