{
  "type": "Feature",
  "properties": {
    "iso:country":"US",
    "sg:address":"675 Jeffco Blvd",
    "sg:city":"Arnold",
    "sg:classifiers":[
        {
            "category":"Bars & Pubs",
            "type":"Food & Drink"
        }
    ],
    "sg:phone":"+1 636 296 3831",
    "sg:postcode":"63010",
    "sg:province":"MO",
    "sg:tags":[
        "restaurant"
    ],
    "sg:website":"http://dylanssportsbar.com",
    "wof:name":"Dylan's Sports Bar & Grill",
    "wof:placetype":"venue"
},
  "geometry": {"coordinates":[-90.36638600000001,38.450344],"type":"Point"}
}