{
  "type": "Feature",
  "properties": {
    "iso:country":"US",
    "sg:address":"395 N Mary Lynn Ln",
    "sg:city":"Nixa",
    "sg:classifiers":[
        {
            "category":"Professional",
            "subcategory":"Business Services",
            "type":"Services"
        }
    ],
    "sg:phone":"+1 417 725 9216",
    "sg:postcode":"65714",
    "sg:province":"MO",
    "sg:tags":[
        "organizing",
        "services-household"
    ],
    "wof:name":"Logan, Inc.",
    "wof:placetype":"venue"
},
  "geometry": {"coordinates":[-93.369423,37.049789],"type":"Point"}
}