{
  "type": "Feature",
  "properties": {
    "iso:country":"US",
    "sg:address":"725 Lincoln Dr",
    "sg:city":"Imperial",
    "sg:classifiers":[
        {
            "category":"Building & Trades",
            "subcategory":"Landscaping Services",
            "type":"Services"
        }
    ],
    "sg:phone":"+1 636 464 6737",
    "sg:postcode":"63052",
    "sg:province":"MO",
    "sg:tags":[
        "lawn"
    ],
    "wof:name":"Outside Guys",
    "wof:placetype":"venue"
},
  "geometry": {"coordinates":[-90.361757,38.382993],"type":"Point"}
}