{
  "type": "Feature",
  "properties": {
    "iso:country":"US",
    "sg:address":"4408 Arsenal St",
    "sg:city":"St Louis",
    "sg:classifiers":[
        {
            "category":"Professional",
            "subcategory":"Computer Services",
            "type":"Services"
        }
    ],
    "sg:phone":"+1 314 776 7470",
    "sg:postcode":"63116",
    "sg:province":"MO",
    "sg:tags":[
        "website",
        "design"
    ],
    "wof:name":"Websanity Inc",
    "wof:placetype":"venue"
},
  "geometry": {"coordinates":[-90.26440100000001,38.604814],"type":"Point"}
}