{
  "type": "Feature",
  "properties": {
    "iso:country":"US",
    "sg:address":"400 W Young Ave Ste A",
    "sg:city":"Warrensburg",
    "sg:classifiers":[
        {
            "category":"Insurance",
            "subcategory":"Hazard Insurance",
            "type":"Services"
        }
    ],
    "sg:phone":"+1 660 747 5160",
    "sg:postcode":"64093",
    "sg:province":"MO",
    "wof:name":"Pete Wittman",
    "wof:placetype":"venue"
},
  "geometry": {"coordinates":[-93.731795,38.770821],"type":"Point"}
}