{
  "type": "Feature",
  "properties": {
    "iso:country":"US",
    "sg:address":"367 Buckhurst Dr",
    "sg:city":"Ballwin",
    "sg:classifiers":[
        {
            "category":"Travel",
            "subcategory":"Travel Agent",
            "type":"Entertainment"
        }
    ],
    "sg:phone":"+1 636 227 9356",
    "sg:postcode":"63021",
    "sg:province":"MO",
    "sg:tags":[
        "agency"
    ],
    "wof:name":"Sixth Star Travel",
    "wof:placetype":"venue"
},
  "geometry": {"coordinates":[-90.579908,38.577633],"type":"Point"}
}