{
  "type": "Feature",
  "properties": {
    "iso:country":"US",
    "sg:address":"5106 Miller Rd",
    "sg:city":"Saint Joseph",
    "sg:classifiers":[
        {
            "category":"Organizations",
            "subcategory":"Religious Organization",
            "type":"Services"
        }
    ],
    "sg:phone":"+1 816 233 2280",
    "sg:postcode":"64505",
    "sg:province":"MO",
    "wof:name":"Saint Johns Charsmtc Episcpl",
    "wof:placetype":"venue"
},
  "geometry": {"coordinates":[-94.824803,39.812169],"type":"Point"}
}