{
  "type": "Feature",
  "properties": {
    "iso:country":"US",
    "sg:address":"419 Kayla Ct",
    "sg:city":"Washington",
    "sg:classifiers":[
        {
            "category":"Building & Trades",
            "subcategory":"Construction",
            "type":"Services"
        }
    ],
    "sg:phone":"+1 636 390 2391",
    "sg:postcode":"63090",
    "sg:province":"MO",
    "sg:tags":[
        "contractor",
        "mechanical"
    ],
    "wof:name":"Weiss Mechanical",
    "wof:placetype":"venue"
},
  "geometry": {"coordinates":[-91.01490699999999,38.536337],"type":"Point"}
}