{
  "type": "Feature",
  "properties": {
    "iso:country":"US",
    "sg:address":"608 Forest St",
    "sg:city":"Cuba",
    "sg:classifiers":[
        {
            "category":"Real Estate",
            "subcategory":"Real Estate Operator",
            "type":"Services"
        }
    ],
    "sg:phone":"+1 573 885 1128",
    "sg:postcode":"65453",
    "sg:province":"MO",
    "sg:tags":[
        "building",
        "apartment"
    ],
    "wof:name":"Highley Heights Apartments",
    "wof:placetype":"venue"
},
  "geometry": {"coordinates":[-91.408171,38.066877],"type":"Point"}
}