{
  "type": "Feature",
  "properties": {
    "iso:country":"US",
    "sg:address":"115 John St",
    "sg:city":"Campbell",
    "sg:classifiers":[
        {
            "category":"Retail",
            "subcategory":"Car Wash",
            "type":"Services"
        }
    ],
    "sg:phone":"+1 573 246 3454",
    "sg:postcode":"63933",
    "sg:province":"MO",
    "sg:tags":[
        "automobile",
        "detail",
        "clean"
    ],
    "wof:name":"Becky's Auto Detail",
    "wof:placetype":"venue"
},
  "geometry": {"coordinates":[-90.072401,36.492308],"type":"Point"}
}