{
  "type": "Feature",
  "properties": {
    "iso:country":"US",
    "sg:address":"8637 Olive Blvd",
    "sg:city":"St Louis",
    "sg:classifiers":[
        {
            "category":"Retail",
            "subcategory":"Laundry & Dry Cleaning",
            "type":"Services"
        }
    ],
    "sg:phone":"+1 314 567 6680",
    "sg:postcode":"63132",
    "sg:province":"MO",
    "sg:tags":[
        "cleaners"
    ],
    "wof:name":"American Cleaners",
    "wof:placetype":"venue"
},
  "geometry": {"coordinates":[-90.35758,38.674167],"type":"Point"}
}