{
  "type": "Feature",
  "properties": {
    "iso:country":"US",
    "sg:address":"11802 E 23rd St S",
    "sg:city":"Independence",
    "sg:classifiers":[
        {
            "category":"Shopping",
            "subcategory":"Department Store",
            "type":"Retail Goods"
        },
        {
            "category":"Shopping",
            "subcategory":"Discount & Variety Stores",
            "type":"Retail Goods"
        }
    ],
    "sg:phone":"+1 816 461 3281",
    "sg:postcode":"64050",
    "sg:province":"MO",
    "wof:name":"Bargains Galore Discount Store",
    "wof:placetype":"venue"
},
  "geometry": {"coordinates":[-94.436785,39.079999],"type":"Point"}
}