{
  "type": "Feature",
  "properties": {
    "iso:country":"US",
    "sg:address":"105 E 3rd St",
    "sg:city":"West Plains",
    "sg:classifiers":[
        {
            "category":"Home & Garden",
            "subcategory":"Garden Supply",
            "type":"Retail Goods"
        }
    ],
    "sg:phone":"+1 417 256 4465",
    "sg:postcode":"65775",
    "sg:province":"MO",
    "sg:tags":[
        "engine"
    ],
    "wof:name":"RTN Small Engines",
    "wof:placetype":"venue"
},
  "geometry": {"coordinates":[-91.852386,36.733939],"type":"Point"}
}