{
  "type": "Feature",
  "properties": {
    "iso:country":"US",
    "sg:address":"9401 N Oak Trfy",
    "sg:city":"Kansas City",
    "sg:classifiers":[
        {
            "category":"Health Services",
            "subcategory":"Doctor",
            "type":"Services"
        }
    ],
    "sg:phone":"+1 816 478 1230",
    "sg:postcode":"64155",
    "sg:province":"MO",
    "sg:tags":[
        "physician",
        "surgeon"
    ],
    "wof:name":"Discover Vision Ctr",
    "wof:placetype":"venue"
},
  "geometry": {"coordinates":[-94.57564600000001,39.264953],"type":"Point"}
}