{
  "type": "Feature",
  "properties": {
    "iso:country":"US",
    "sg:address":"5510 E Truman Rd",
    "sg:city":"Kansas City",
    "sg:classifiers":[
        {
            "category":"Restaurant",
            "type":"Food & Drink"
        }
    ],
    "sg:phone":"+1 816 231 4848",
    "sg:postcode":"64127",
    "sg:province":"MO",
    "wof:name":"El Molina Restaurant",
    "wof:placetype":"venue"
},
  "geometry": {"coordinates":[-94.51884099999999,39.094222],"type":"Point"}
}