{
  "type": "Feature",
  "properties": {
    "iso:country":"US",
    "sg:address":"204 S Washington St",
    "sg:city":"Nevada",
    "sg:classifiers":[
        {
            "category":"Organizations",
            "subcategory":"Religious Organization",
            "type":"Services"
        }
    ],
    "sg:phone":"+1 417 667 3540",
    "sg:postcode":"64772",
    "sg:province":"MO",
    "sg:tags":[
        "church"
    ],
    "sg:website":"www.fccnevada.org",
    "wof:name":"First Christian Church",
    "wof:placetype":"venue"
},
  "geometry": {"coordinates":[-94.355447,37.837071],"type":"Point"}
}