{
  "type": "Feature",
  "properties": {
    "iso:country":"US",
    "sg:address":"525 Jules St",
    "sg:city":"St Joseph",
    "sg:classifiers":[
        {
            "category":"Government",
            "subcategory":"Office",
            "type":"Public Place"
        }
    ],
    "sg:phone":"+1 816 387 2226",
    "sg:postcode":"64501",
    "sg:province":"MO",
    "sg:tags":[
        "state",
        "program"
    ],
    "wof:name":"Driver's License Office",
    "wof:placetype":"venue"
},
  "geometry": {"coordinates":[-94.853241,39.768274],"type":"Point"}
}