{
  "type": "Feature",
  "properties": {
    "iso:country":"US",
    "sg:address":"1415 Madison 517",
    "sg:city":"Fredericktown",
    "sg:classifiers":[
        {
            "category":"Education",
            "subcategory":"College",
            "type":"Public Place"
        }
    ],
    "sg:phone":"+1 573 783 7932",
    "sg:postcode":"63645",
    "sg:province":"MO",
    "sg:tags":[
        "academic",
        "school"
    ],
    "sg:website":"www.mineralarea.edu",
    "wof:name":"Mineral Area College",
    "wof:placetype":"venue"
},
  "geometry": {"coordinates":[-90.324257,37.573562],"type":"Point"}
}