{
  "type": "Feature",
  "properties": {
    "iso:country":"US",
    "sg:address":"41179 State Hwy K",
    "sg:city":"Richmond",
    "sg:classifiers":[
        {
            "category":"Freight",
            "type":"Transportation"
        }
    ],
    "sg:phone":"+1 816 776 3680",
    "sg:postcode":"64085",
    "sg:province":"MO",
    "sg:tags":[
        "special"
    ],
    "wof:name":"Premiere Barns",
    "wof:placetype":"venue"
},
  "geometry": {"coordinates":[-93.961839,39.401415],"type":"Point"}
}