{
  "type": "Feature",
  "properties": {
    "iso:country":"US",
    "sg:address":"705 N Main St",
    "sg:city":"Clarkton",
    "sg:phone":"+1 573 448 3770",
    "sg:postcode":"63837",
    "sg:province":"MO",
    "sg:tags":[
        "distributor",
        "oil",
        "marketer"
    ],
    "wof:name":"MFA Oil Co",
    "wof:placetype":"venue"
},
  "geometry": {"coordinates":[-89.968237,36.457839],"type":"Point"}
}