{
  "type": "Feature",
  "properties": {
    "iso:country":"US",
    "sg:address":"4221 S Campbell Ave",
    "sg:city":"Springfield",
    "sg:classifiers":[
        {
            "category":"Banks & Credit Unions",
            "subcategory":"Bank",
            "type":"Services"
        }
    ],
    "sg:phone":"+1 417 887 6025",
    "sg:postcode":"65810",
    "sg:province":"MO",
    "sg:website":"http://www.cnbnetbank.com",
    "wof:name":"Citizens National Bank Of Springfield (Inc)",
    "wof:placetype":"venue"
},
  "geometry": {"coordinates":[-93.29640000000001,37.137541],"type":"Point"}
}