{
  "type": "Feature",
  "properties": {
    "iso:country":"US",
    "sg:address":"11470 State Hwy C",
    "sg:city":"Hillsboro",
    "sg:classifiers":[
        {
            "category":"Education",
            "subcategory":"School",
            "type":"Public Place"
        }
    ],
    "sg:phone":"+1 636 944 3931",
    "sg:postcode":"63050",
    "sg:province":"MO",
    "wof:name":"Grandview Middle School",
    "wof:placetype":"venue"
},
  "geometry": {"coordinates":[-90.663009,38.214647],"type":"Point"}
}