{
  "type": "Feature",
  "properties": {
    "iso:country":"US",
    "sg:address":"1096 Care Ave",
    "sg:city":"Nixa",
    "sg:classifiers":[
        {
            "category":"Real Estate",
            "subcategory":"Real Estate Operator",
            "type":"Services"
        }
    ],
    "sg:phone":"+1 417 725 4443",
    "sg:postcode":"65714",
    "sg:province":"MO",
    "sg:tags":[
        "building",
        "apartment"
    ],
    "wof:name":"Crowhaven Apartments",
    "wof:placetype":"venue"
},
  "geometry": {"coordinates":[-93.317865,37.038634],"type":"Point"}
}