{
  "type": "Feature",
  "properties": {
    "iso:country":"US",
    "sg:address":"28517 Possum Trot Rd",
    "sg:city":"Stover",
    "sg:classifiers":[
        {
            "category":"Recreation",
            "subcategory":"Marina",
            "type":"Entertainment"
        }
    ],
    "sg:phone":"+1 573 377 4666",
    "sg:postcode":"65078",
    "sg:province":"MO",
    "sg:tags":[
        "operation"
    ],
    "wof:name":"Buffalo Cove Bar & Grill",
    "wof:placetype":"venue"
},
  "geometry": {"coordinates":[-93.047404,38.292899],"type":"Point"}
}