{
  "type": "Feature",
  "properties": {
    "iso:country":"US",
    "sg:address":"600 W Republic Rd",
    "sg:city":"Springfield",
    "sg:classifiers":[
        {
            "category":"Banks & Credit Unions",
            "subcategory":"Investment Brokerage",
            "type":"Services"
        },
        {
            "category":"Banks & Credit Unions",
            "subcategory":"Financial Services",
            "type":"Services"
        }
    ],
    "sg:phone":"+1 417 890 1995",
    "sg:postcode":"65807",
    "sg:province":"MO",
    "sg:tags":[
        "fund",
        "security",
        "management",
        "mutual"
    ],
    "wof:name":"Calton & Associates",
    "wof:placetype":"venue"
},
  "geometry": {"coordinates":[-93.298241,37.138199],"type":"Point"}
}