{
  "type": "Feature",
  "properties": {
    "iso:country":"US",
    "sg:address":"12 S 9th St",
    "sg:city":"Columbia",
    "sg:classifiers":[
        {
            "category":"Shopping",
            "subcategory":"Clothing, Apparel, & Fashions",
            "type":"Retail Goods"
        }
    ],
    "sg:phone":"+1 573 499 1313",
    "sg:postcode":"65201",
    "sg:province":"MO",
    "sg:tags":[
        "body",
        "shop",
        "piercing"
    ],
    "wof:name":"Dream Catcher Studio",
    "wof:placetype":"venue"
},
  "geometry": {"coordinates":[-92.32746299999999,38.950588],"type":"Point"}
}