{
  "type": "Feature",
  "properties": {
    "iso:country":"US",
    "sg:address":"2631 Cherokee St",
    "sg:city":"Saint Louis",
    "sg:classifiers":[
        {
            "category":"Shopping",
            "subcategory":"Books",
            "type":"Retail Goods"
        }
    ],
    "sg:phone":"+1 314 664 6575",
    "sg:postcode":"63118",
    "sg:province":"MO",
    "sg:tags":[
        "mags",
        "video",
        "books",
        "music"
    ],
    "sg:website":"apoprecords.com",
    "wof:name":"Apop Records",
    "wof:placetype":"venue"
},
  "geometry": {"coordinates":[-90.226764,38.593468],"type":"Point"}
}