{
  "type": "Feature",
  "properties": {
    "iso:country":"US",
    "sg:address":"2618 NE Vivion Rd",
    "sg:city":"Kansas City",
    "sg:classifiers":[
        {
            "category":"Cinema",
            "subcategory":"Movie Rental",
            "type":"Entertainment"
        }
    ],
    "sg:phone":"+1 816 452 6150",
    "sg:postcode":"64119",
    "sg:province":"MO",
    "sg:tags":[
        "leasing",
        "video",
        "disc",
        "tape"
    ],
    "sg:website":"www.blockbuster.com",
    "wof:name":"Blockbuster Video",
    "wof:placetype":"venue"
},
  "geometry": {"coordinates":[-94.548596,39.186438],"type":"Point"}
}