{
  "type": "Feature",
  "properties": {
    "iso:country":"US",
    "sg:address":"6668 Flowerfield Ln",
    "sg:city":"Florissant",
    "sg:classifiers":[
        {
            "category":"Real Estate",
            "subcategory":"Real Estate Operator",
            "type":"Services"
        }
    ],
    "sg:phone":"+1 314 741 8211",
    "sg:postcode":"63033",
    "sg:province":"MO",
    "sg:tags":[
        "condominium"
    ],
    "wof:name":"Paddock Forest Condominiums",
    "wof:placetype":"venue"
},
  "geometry": {"coordinates":[-90.235097,38.796683],"type":"Point"}
}