{
  "type": "Feature",
  "properties": {
    "iso:country":"US",
    "sg:address":"10028 State Highway V",
    "sg:city":"Galena",
    "sg:classifiers":[
        {
            "category":"Home & Garden",
            "subcategory":"Building Materials",
            "type":"Retail Goods"
        }
    ],
    "sg:phone":"+1 417 357 6494",
    "sg:postcode":"65656",
    "sg:province":"MO",
    "sg:tags":[
        "downspouts",
        "gutter"
    ],
    "wof:name":"Rain Drains",
    "wof:placetype":"venue"
},
  "geometry": {"coordinates":[-93.39572200000001,36.8326],"type":"Point"}
}