{
  "type": "Feature",
  "properties": {
    "iso:country":"US",
    "sg:address":"1225 N Kingshighway St",
    "sg:city":"Cape Girardeau",
    "sg:classifiers":[
        {
            "category":"Professional",
            "subcategory":"Lawyer & Legal Services",
            "type":"Services"
        }
    ],
    "sg:phone":"+1 573 651 4806",
    "sg:postcode":"63701",
    "sg:province":"MO",
    "sg:tags":[
        "attorney"
    ],
    "wof:name":"Legal Svc Of Southern Missouri",
    "wof:placetype":"venue"
},
  "geometry": {"coordinates":[-89.55945800000001,37.322575],"type":"Point"}
}