{
  "type": "Feature",
  "properties": {
    "iso:country":"US",
    "sg:address":"15185 Olive Blvd",
    "sg:city":"Chesterfield",
    "sg:classifiers":[
        {
            "category":"Government",
            "subcategory":"Office",
            "type":"Public Place"
        }
    ],
    "sg:phone":"+1 636 532 7298",
    "sg:postcode":"63017",
    "sg:province":"MO",
    "sg:tags":[
        "executive",
        "gallery"
    ],
    "wof:name":"Faust Pk Thrnhill Historic Vlg",
    "wof:placetype":"venue"
},
  "geometry": {"coordinates":[-90.54258900000001,38.662882],"type":"Point"}
}