{
  "type": "Feature",
  "properties": {
    "iso:country":"US",
    "sg:address":"1603 E Ohio St",
    "sg:city":"Clinton",
    "sg:classifiers":[
        {
            "category":"Banks & Credit Unions",
            "subcategory":"Investment Brokerage",
            "type":"Services"
        }
    ],
    "sg:phone":"+1 660 885 3671",
    "sg:postcode":"64735",
    "sg:province":"MO",
    "sg:tags":[
        "security"
    ],
    "wof:name":"Investment Centers of America",
    "wof:placetype":"venue"
},
  "geometry": {"coordinates":[-93.75063299999999,38.366283],"type":"Point"}
}