{
  "type": "Feature",
  "properties": {
    "iso:country":"US",
    "sg:address":"6316 US Hwy 54",
    "sg:city":"Osage Beach",
    "sg:classifiers":[
        {
            "category":"Freight",
            "type":"Transportation"
        }
    ],
    "sg:phone":"+1 573 348 5725",
    "sg:postcode":"65065",
    "sg:province":"MO",
    "sg:tags":[
        "commercial",
        "storage"
    ],
    "wof:name":"54 Mini Storage",
    "wof:placetype":"venue"
},
  "geometry": {"coordinates":[-92.66637900000001,38.126844],"type":"Point"}
}