{
  "type": "Feature",
  "properties": {
    "iso:country":"US",
    "sg:address":"12485 Limestone Spr",
    "sg:city":"Saint Louis",
    "sg:classifiers":[
        {
            "category":"Shopping",
            "subcategory":"Catalog Store",
            "type":"Retail Goods"
        }
    ],
    "sg:phone":"+1 314 842 3020",
    "sg:postcode":"63127",
    "sg:province":"MO",
    "sg:tags":[
        "product",
        "hy",
        "marketing",
        "vitamin",
        "direct",
        "skin",
        "home",
        "care"
    ],
    "wof:name":"Bodywise Indep Consulate",
    "wof:placetype":"venue"
},
  "geometry": {"coordinates":[-90.404956,38.534743],"type":"Point"}
}