{
  "type": "Feature",
  "properties": {
    "iso:country":"US",
    "sg:address":"1381 High St Ste 211",
    "sg:city":"Washington",
    "sg:classifiers":[
        {
            "category":"Health Services",
            "subcategory":"Chiropractor",
            "type":"Services"
        }
    ],
    "sg:phone":"+1 636 390 9990",
    "sg:postcode":"63090",
    "sg:province":"MO",
    "sg:tags":[
        "chiropractic"
    ],
    "wof:name":"Spilker Chiropractic",
    "wof:placetype":"venue"
},
  "geometry": {"coordinates":[-91.025032,38.545261],"type":"Point"}
}