{
  "type": "Feature",
  "properties": {
    "iso:country":"US",
    "sg:address":"1940 Windmoor Pl",
    "sg:city":"Saint Louis",
    "sg:classifiers":[
        {
            "category":"Banks & Credit Unions",
            "subcategory":"Financial Services",
            "type":"Services"
        }
    ],
    "sg:phone":"+1 314 822 4849",
    "sg:postcode":"63131",
    "sg:province":"MO",
    "sg:tags":[
        "trust",
        "management"
    ],
    "wof:name":"Ottenad Profit Sharing Trust",
    "wof:placetype":"venue"
},
  "geometry": {"coordinates":[-90.449364,38.614401],"type":"Point"}
}