{
  "type": "Feature",
  "properties": {
    "iso:country":"US",
    "sg:address":"104 Coppersmith Ct",
    "sg:city":"Saint Charles",
    "sg:classifiers":[
        {
            "category":"Professional",
            "subcategory":"Computer Services",
            "type":"Services"
        }
    ],
    "sg:phone":"+1 636 947 3044",
    "sg:postcode":"63301",
    "sg:province":"MO",
    "sg:tags":[
        "datum"
    ],
    "wof:name":"1 Step Network",
    "wof:placetype":"venue"
},
  "geometry": {"coordinates":[-90.54998999999999,38.800081],"type":"Point"}
}