{
  "type": "Feature",
  "properties": {
    "iso:country":"US",
    "sg:address":"1144 Old Cadet Rd",
    "sg:city":"Bonne Terre",
    "sg:classifiers":[
        {
            "category":"Building & Trades",
            "subcategory":"Construction",
            "type":"Services"
        }
    ],
    "sg:phone":"+1 573 358 7472",
    "sg:postcode":"63628",
    "sg:province":"MO",
    "sg:tags":[
        "contractor"
    ],
    "wof:name":"Harris Construction",
    "wof:placetype":"venue"
},
  "geometry": {"coordinates":[-90.58988600000001,37.946318],"type":"Point"}
}