{
  "type": "Feature",
  "properties": {
    "iso:country":"US",
    "sg:address":"901 Lake Maurer Rd",
    "sg:city":"Excelsior Spgs",
    "sg:classifiers":[
        {
            "category":"Organizations",
            "subcategory":"Religious Organization",
            "type":"Services"
        }
    ],
    "sg:phone":"+1 816 637 2701",
    "sg:postcode":"64024",
    "sg:province":"MO",
    "sg:tags":[
        "church"
    ],
    "wof:name":"Northern Missouri District",
    "wof:placetype":"venue"
},
  "geometry": {"coordinates":[-94.228101,39.325652],"type":"Point"}
}