{
  "type": "Feature",
  "properties": {
    "iso:country":"US",
    "sg:address":"1206 S Main St",
    "sg:city":"Maryville",
    "sg:classifiers":[
        {
            "category":"Personal",
            "subcategory":"Beauty Salon",
            "type":"Services"
        }
    ],
    "sg:phone":"+1 660 582 5958",
    "sg:postcode":"64468",
    "sg:province":"MO",
    "wof:name":"A Polished Image",
    "wof:placetype":"venue"
},
  "geometry": {"coordinates":[-94.87389899999999,40.333791],"type":"Point"}
}