{
  "type": "Feature",
  "properties": {
    "iso:country":"US",
    "sg:address":"1926 Allen Ave",
    "sg:city":"St Louis",
    "sg:classifiers":[
        {
            "category":"Organizations",
            "subcategory":"Religious Organization",
            "type":"Services"
        }
    ],
    "sg:phone":"+1 314 436 9392",
    "sg:postcode":"63104",
    "sg:province":"MO",
    "sg:tags":[
        "church"
    ],
    "sg:website":"www.freedomchristiancenter.com",
    "wof:name":"Freedom Christian Ctr",
    "wof:placetype":"venue"
},
  "geometry": {"coordinates":[-90.213621,38.609802],"type":"Point"}
}