{
  "type": "Feature",
  "properties": {
    "iso:country":"US",
    "sg:address":"201 NE Victoria Dr",
    "sg:city":"Lees Summit",
    "sg:classifiers":[
        {
            "category":"Manufacturing",
            "subcategory":"Motor Vehicles & Parts",
            "type":"Manufacturing & Wholesale Goods"
        }
    ],
    "sg:phone":"+1 816 525 6766",
    "sg:postcode":"64086",
    "sg:province":"MO",
    "sg:tags":[
        "automobile",
        "supply"
    ],
    "wof:name":"Automotive Parts Professionals",
    "wof:placetype":"venue"
},
  "geometry": {"coordinates":[-94.37500300000001,38.936654],"type":"Point"}
}