{
  "type": "Feature",
  "properties": {
    "iso:country":"US",
    "sg:address":"36 E Cline St",
    "sg:city":"Aurora",
    "sg:classifiers":[
        {
            "category":"Organizations",
            "subcategory":"Religious Organization",
            "type":"Services"
        }
    ],
    "sg:phone":"+1 417 678 3306",
    "sg:postcode":"65605",
    "sg:province":"MO",
    "wof:name":"Faith Full Gospel",
    "wof:placetype":"venue"
},
  "geometry": {"coordinates":[-93.71901099999999,36.98595],"type":"Point"}
}