{
  "type": "Feature",
  "properties": {
    "iso:country":"US",
    "sg:address":"801 E Main St",
    "sg:city":"Warsaw",
    "sg:phone":"+1 660 438 6118",
    "sg:postcode":"65355",
    "sg:province":"MO",
    "sg:tags":[
        "product",
        "petroleum"
    ],
    "wof:name":"All Star Gas Corporation",
    "wof:placetype":"venue"
},
  "geometry": {"coordinates":[-93.369224,38.24022],"type":"Point"}
}