{
  "type": "Feature",
  "properties": {
    "iso:country":"US",
    "sg:address":"8811 Ladue Rd",
    "sg:city":"St Louis",
    "sg:classifiers":[
        {
            "category":"Manufacturing",
            "subcategory":"Printing",
            "type":"Manufacturing & Wholesale Goods"
        }
    ],
    "sg:phone":"+1 314 863 3737",
    "sg:postcode":"63124",
    "sg:province":"MO",
    "sg:tags":[
        "newspaper"
    ],
    "wof:name":"Ladue News",
    "wof:placetype":"venue"
},
  "geometry": {"coordinates":[-90.350247,38.65341],"type":"Point"}
}