{
  "type": "Feature",
  "properties": {
    "iso:country":"US",
    "sg:address":"4597 Co Rd 112",
    "sg:city":"Maywood",
    "sg:classifiers":[
        {
            "category":"Social Services",
            "subcategory":"Child Care",
            "type":"Services"
        }
    ],
    "sg:phone":"+1 573 478 3620",
    "sg:postcode":"63454",
    "sg:province":"MO",
    "sg:tags":[
        "day"
    ],
    "wof:name":"Shirleys Daycare",
    "wof:placetype":"venue"
},
  "geometry": {"coordinates":[-91.629661,39.939589],"type":"Point"}
}