{
  "type": "Feature",
  "properties": {
    "iso:country":"US",
    "sg:address":"13730 Mount Zion Rd",
    "sg:city":"Versailles",
    "sg:classifiers":[
        {
            "category":"Farming",
            "subcategory":"Livestock Farm",
            "type":"Manufacturing & Wholesale Goods"
        },
        {
            "category":"Farming",
            "subcategory":"Farm",
            "type":"Manufacturing & Wholesale Goods"
        }
    ],
    "sg:phone":"+1 573 378 5031",
    "sg:postcode":"65084",
    "sg:province":"MO",
    "wof:name":"Menno Kilmer",
    "wof:placetype":"venue"
},
  "geometry": {"coordinates":[-92.790411,38.476529],"type":"Point"}
}