{
  "type": "Feature",
  "properties": {
    "iso:country":"US",
    "sg:address":"390 Brown Rd",
    "sg:city":"St Peters",
    "sg:classifiers":[
        {
            "category":"Building & Trades",
            "subcategory":"Plumbing",
            "type":"Services"
        }
    ],
    "sg:phone":"+1 636 970 4400",
    "sg:postcode":"63376",
    "sg:province":"MO",
    "sg:tags":[
        "conditioning",
        "air",
        "system",
        "contractor"
    ],
    "wof:name":"Kappa Heating & Air Cond Inc",
    "wof:placetype":"venue"
},
  "geometry": {"coordinates":[-90.644537,38.803579],"type":"Point"}
}