{
  "type": "Feature",
  "properties": {
    "iso:country":"US",
    "sg:address":"1501 N Duquesne Rd",
    "sg:city":"Joplin",
    "sg:classifiers":[
        {
            "category":"Government",
            "subcategory":"Court House",
            "type":"Public Place"
        }
    ],
    "sg:phone":"+1 417 781 5085",
    "sg:postcode":"64801",
    "sg:province":"MO",
    "wof:name":"City of Duquesne",
    "wof:placetype":"venue"
},
  "geometry": {"coordinates":[-94.458327,37.098064],"type":"Point"}
}