{
  "type": "Feature",
  "properties": {
    "iso:country":"US",
    "sg:address":"706 E 29 St",
    "sg:city":"Kansas City",
    "sg:classifiers":[
        {
            "category":"Professional",
            "subcategory":"Business Services",
            "type":"Services"
        }
    ],
    "sg:phone":"+1 816 561 5661",
    "sg:postcode":"64109",
    "sg:province":"MO",
    "sg:tags":[
        "interior",
        "design"
    ],
    "wof:name":"Scot Stockton",
    "wof:placetype":"venue"
},
  "geometry": {"coordinates":[-94.575271,39.074353],"type":"Point"}
}