{
  "type": "Feature",
  "properties": {
    "iso:country":"US",
    "sg:address":"20521 S School Rd",
    "sg:city":"Peculiar",
    "sg:classifiers":[
        {
            "category":"Organizations",
            "subcategory":"Religious Organization",
            "type":"Services"
        }
    ],
    "sg:phone":"+1 816 758 4477",
    "sg:postcode":"64078",
    "sg:province":"MO",
    "sg:tags":[
        "church"
    ],
    "wof:name":"United Methodist Chr Family Lf",
    "wof:placetype":"venue"
},
  "geometry": {"coordinates":[-94.459553,38.752115],"type":"Point"}
}