{
  "type": "Feature",
  "properties": {
    "iso:country":"US",
    "sg:address":"1015 Ave Cesar E Chavez",
    "sg:city":"Kansas City",
    "sg:classifiers":[
        {
            "category":"Organizations",
            "subcategory":"Religious Organization",
            "type":"Services"
        }
    ],
    "sg:phone":"+1 816 421 1015",
    "sg:postcode":"64108",
    "sg:province":"MO",
    "sg:tags":[
        "church"
    ],
    "wof:name":"GCI",
    "wof:placetype":"venue"
},
  "geometry": {"coordinates":[-94.597116,39.085888],"type":"Point"}
}