{
  "type": "Feature",
  "properties": {
    "addr:full":"124 N Folger St Carrollton MO 64633",
    "addr:housenumber":"124",
    "addr:postcode":"64633",
    "addr:street":"N Folger St",
    "iso:country":"US",
    "sg:address":"124 N Folger St",
    "sg:city":"Carrollton",
    "sg:classifiers":[
        {
            "category":"Organizations",
            "subcategory":"Religious Organization",
            "type":"Services"
        }
    ],
    "sg:phone":"+1 660 542 3006",
    "sg:postcode":"64633",
    "sg:province":"MO",
    "wof:name":"First Baptist Church",
    "wof:placetype":"venue"
},
  "geometry": {"coordinates":[-93.496938,39.360156],"type":"Point"}
}