{
  "type": "Feature",
  "properties": {
    "iso:country":"US",
    "sg:address":"4018 Duncan Ave",
    "sg:city":"St Louis",
    "sg:classifiers":[
        {
            "category":"Wholesale",
            "subcategory":"Machinery & Supplies",
            "type":"Manufacturing & Wholesale Goods"
        },
        {
            "category":"Wholesale",
            "subcategory":"Chemicals & Plastics",
            "type":"Manufacturing & Wholesale Goods"
        }
    ],
    "sg:phone":"+1 314 371 4053",
    "sg:postcode":"63110",
    "sg:province":"MO",
    "sg:tags":[
        "equipment",
        "industrial",
        "merchandise",
        "che",
        "nitrogen"
    ],
    "wof:name":"Praxair",
    "wof:placetype":"venue"
},
  "geometry": {"coordinates":[-90.244749,38.633674],"type":"Point"}
}