{
  "type": "Feature",
  "properties": {
    "iso:country":"US",
    "sg:address":"230 E North Ave",
    "sg:city":"Belton",
    "sg:classifiers":[
        {
            "category":"Retail",
            "subcategory":"Car Wash",
            "type":"Services"
        },
        {
            "category":"Manufacturing",
            "subcategory":"Glass & Minerals",
            "type":"Manufacturing & Wholesale Goods"
        },
        {
            "category":"Retail",
            "subcategory":"Auto Repair",
            "type":"Services"
        }
    ],
    "sg:phone":"+1 816 331 1965",
    "sg:postcode":"64012",
    "sg:province":"MO",
    "sg:tags":[
        "body",
        "plate",
        "automobile",
        "detailing",
        "window",
        "removal",
        "glass-auto",
        "dent",
        "painting",
        "repairing"
    ],
    "sg:website":"http://www.zspaintlessdentrepair.com",
    "wof:name":"Z's Paintless Dent Repair",
    "wof:placetype":"venue"
},
  "geometry": {"coordinates":[-94.530142,38.814475],"type":"Point"}
}