{
  "type": "Feature",
  "properties": {
    "iso:country":"US",
    "sg:address":"2072 E Bennett St",
    "sg:city":"Springfield",
    "sg:classifiers":[
        {
            "category":"Recreation",
            "type":"Entertainment"
        }
    ],
    "sg:phone":"+1 417 881 5611",
    "sg:postcode":"65804",
    "sg:province":"MO",
    "wof:name":"Diva Vocal",
    "wof:placetype":"venue"
},
  "geometry": {"coordinates":[-93.255016,37.188592],"type":"Point"}
}