{
  "type": "Feature",
  "properties": {
    "iso:country":"US",
    "sg:address":"940 N Boonville Ave",
    "sg:city":"Springfield",
    "sg:classifiers":[
        {
            "category":"Government",
            "subcategory":"Office",
            "type":"Public Place"
        }
    ],
    "sg:phone":"+1 417 868 4000",
    "sg:postcode":"65802",
    "sg:province":"MO",
    "wof:name":"Greene County Courthouse",
    "wof:placetype":"venue"
},
  "geometry": {"coordinates":[-93.292269,37.218217],"type":"Point"}
}