{
  "type": "Feature",
  "properties": {
    "iso:country":"US",
    "sg:address":"3824 SW Harbor Dr",
    "sg:city":"Lees Summit",
    "sg:classifiers":[
        {
            "category":"Building & Trades",
            "subcategory":"Landscaping Services",
            "type":"Services"
        }
    ],
    "sg:phone":"+1 816 525 0542",
    "sg:postcode":"64082",
    "sg:province":"MO",
    "wof:name":"Turf Master",
    "wof:placetype":"venue"
},
  "geometry": {"coordinates":[-94.39143,38.852301],"type":"Point"}
}