{
  "type": "Feature",
  "properties": {
    "iso:country":"US",
    "sg:address":"3315 N Belt Hwy",
    "sg:city":"St Joseph",
    "sg:classifiers":[
        {
            "category":"Retail",
            "subcategory":"Portrait Studio",
            "type":"Services"
        }
    ],
    "sg:phone":"+1 816 364 6454",
    "sg:postcode":"64506",
    "sg:province":"MO",
    "sg:tags":[
        "photographer"
    ],
    "sg:website":"www.jmcbee.com",
    "wof:name":"JMCB Studios",
    "wof:placetype":"venue"
},
  "geometry": {"coordinates":[-94.814701,39.799766],"type":"Point"}
}