{
  "type": "Feature",
  "properties": {
    "iso:country":"US",
    "sg:address":"5620 Grand Drive",
    "sg:city":"Saint Louis",
    "sg:classifiers":[
        {
            "category":"Sports & Exercise",
            "subcategory":"Tennis Court",
            "type":"Entertainment"
        }
    ],
    "sg:phone":"+1 314 361 0177",
    "sg:postcode":"63112",
    "sg:province":"MO",
    "sg:website":"www.dwightdavistennis.com",
    "wof:name":"Dwight Davis Tennis Center",
    "wof:placetype":"venue"
},
  "geometry": {"coordinates":[-90.283642,38.643461],"type":"Point"}
}