{
  "type": "Feature",
  "properties": {
    "iso:country":"US",
    "sg:address":"5431 Janet Ave",
    "sg:city":"Saint Louis",
    "sg:classifiers":[
        {
            "category":"Local Transit",
            "type":"Transportation"
        }
    ],
    "sg:phone":"+1 314 381 1047",
    "sg:postcode":"63136",
    "sg:province":"MO",
    "sg:tags":[
        "taxicab"
    ],
    "wof:name":"Suburban Transportation",
    "wof:placetype":"venue"
},
  "geometry": {"coordinates":[-90.265574,38.710004],"type":"Point"}
}