{
  "type": "Feature",
  "properties": {
    "iso:country":"US",
    "sg:address":"1111 Lacy",
    "sg:city":"Thayer",
    "sg:classifiers":[
        {
            "category":"Professional",
            "subcategory":"Detective & Security Services",
            "type":"Services"
        }
    ],
    "sg:phone":"+1 417 264 2274",
    "sg:postcode":"65791",
    "sg:province":"MO",
    "sg:tags":[
        "information",
        "bureau"
    ],
    "wof:name":"Allen Appraisal Svc.",
    "wof:placetype":"venue"
},
  "geometry": {"coordinates":[-91.541096,36.534895],"type":"Point"}
}