{
  "type": "Feature",
  "properties": {
    "iso:country":"US",
    "sg:address":"2625 Breezy Point Ln",
    "sg:city":"O Fallon",
    "sg:classifiers":[
        {
            "category":"Personal",
            "subcategory":"Beauty Salon",
            "type":"Services"
        }
    ],
    "sg:phone":"+1 636 978 0921",
    "sg:postcode":"63368",
    "sg:province":"MO",
    "sg:tags":[
        "shop"
    ],
    "wof:name":"Professional Hair Technique",
    "wof:placetype":"venue"
},
  "geometry": {"coordinates":[-90.70743,38.772207],"type":"Point"}
}