{
  "type": "Feature",
  "properties": {
    "iso:country":"US",
    "sg:address":"10669 State Hwy 21",
    "sg:city":"Hillsboro",
    "sg:classifiers":[
        {
            "category":"Real Estate",
            "subcategory":"Real Estate Services",
            "type":"Services"
        }
    ],
    "sg:phone":"+1 636 797 2780",
    "sg:postcode":"63050",
    "sg:province":"MO",
    "sg:tags":[
        "company",
        "title"
    ],
    "wof:name":"Land America Commonwealth",
    "wof:placetype":"venue"
},
  "geometry": {"coordinates":[-90.56325200000001,38.22859],"type":"Point"}
}