{
  "type": "Feature",
  "properties": {
    "iso:country":"US",
    "sg:address":"1101 W Main St",
    "sg:city":"Greenwood",
    "sg:classifiers":[
        {
            "category":"Shopping",
            "subcategory":"Department Store",
            "type":"Retail Goods"
        }
    ],
    "sg:phone":"+1 816 623 4489",
    "sg:postcode":"64034",
    "sg:province":"MO",
    "wof:name":"Casey's General Store",
    "wof:placetype":"venue"
},
  "geometry": {"coordinates":[-94.34729799999999,38.851601],"type":"Point"}
}