{
  "type": "Feature",
  "properties": {
    "iso:country":"US",
    "sg:address":"316 E 51 St",
    "sg:city":"Kansas City",
    "sg:classifiers":[
        {
            "category":"Personal",
            "subcategory":"Barber",
            "type":"Services"
        }
    ],
    "sg:phone":"+1 816 753 9745",
    "sg:postcode":"64112",
    "sg:province":"MO",
    "sg:tags":[
        "shop"
    ],
    "wof:name":"Colonial Barber Shop",
    "wof:placetype":"venue"
},
  "geometry": {"coordinates":[-94.582843,39.034795],"type":"Point"}
}