{
  "type": "Feature",
  "properties": {
    "iso:country":"US",
    "sg:address":"2670 Spring Forest Dr",
    "sg:city":"Imperial",
    "sg:classifiers":[
        {
            "category":"Building & Trades",
            "subcategory":"Construction",
            "type":"Services"
        }
    ],
    "sg:phone":"+1 636 296 4615",
    "sg:postcode":"63052",
    "sg:province":"MO",
    "sg:tags":[
        "general",
        "contractor"
    ],
    "wof:name":"4-Way Snow Removal",
    "wof:placetype":"venue"
},
  "geometry": {"coordinates":[-90.41413,38.404976],"type":"Point"}
}