{
  "type": "Feature",
  "properties": {
    "iso:country":"US",
    "sg:address":"17019 NE 170th St",
    "sg:city":"Holt",
    "sg:classifiers":[
        {
            "category":"Farming",
            "subcategory":"Farm",
            "type":"Manufacturing & Wholesale Goods"
        }
    ],
    "sg:phone":"+1 816 628 5832",
    "sg:postcode":"64048",
    "sg:province":"MO",
    "wof:name":"Circle Jt Ranch",
    "wof:placetype":"venue"
},
  "geometry": {"coordinates":[-94.371643,39.401192],"type":"Point"}
}