{
  "type": "Feature",
  "properties": {
    "iso:country":"US",
    "sg:address":"5117 Virginia Ave",
    "sg:city":"Saint Louis",
    "sg:classifiers":[
        {
            "category":"Organizations",
            "subcategory":"Religious Organization",
            "type":"Services"
        }
    ],
    "sg:phone":"+1 314 351 3426",
    "sg:postcode":"63111",
    "sg:province":"MO",
    "wof:name":"Victory Independent Baptist",
    "wof:placetype":"venue"
},
  "geometry": {"coordinates":[-90.244963,38.568242],"type":"Point"}
}