{
  "type": "Feature",
  "properties": {
    "iso:country":"US",
    "sg:address":"17117 Westridge Meadows Dr",
    "sg:city":"Chesterfield",
    "sg:classifiers":[
        {
            "category":"Professional",
            "subcategory":"Management & Consulting",
            "type":"Services"
        }
    ],
    "sg:phone":"+1 636 537 8445",
    "sg:postcode":"63005",
    "sg:province":"MO",
    "wof:name":"Sales Obsession",
    "wof:placetype":"venue"
},
  "geometry": {"coordinates":[-90.608672,38.657316],"type":"Point"}
}