{
  "type": "Feature",
  "properties": {
    "iso:country":"US",
    "sg:address":"14162 Kafir Rd",
    "sg:city":"Carthage",
    "sg:classifiers":[
        {
            "category":"Wholesale",
            "subcategory":"Non-durable Goods",
            "type":"Manufacturing & Wholesale Goods"
        }
    ],
    "sg:phone":"+1 417 359 9588",
    "sg:postcode":"64836",
    "sg:province":"MO",
    "wof:name":"A & R Feather Co",
    "wof:placetype":"venue"
},
  "geometry": {"coordinates":[-94.32055800000001,37.212948],"type":"Point"}
}