{
  "type": "Feature",
  "properties": {
    "iso:country":"US",
    "sg:address":"3805 Vaile Ave",
    "sg:city":"Florissant",
    "sg:classifiers":[
        {
            "category":"Restaurant",
            "type":"Food & Drink"
        }
    ],
    "sg:phone":"+1 314 831 8810",
    "sg:postcode":"63034",
    "sg:province":"MO",
    "sg:tags":[
        "eating"
    ],
    "wof:name":"NOrleans Cafe",
    "wof:placetype":"venue"
},
  "geometry": {"coordinates":[-90.30714999999999,38.826656],"type":"Point"}
}