{
  "type": "Feature",
  "properties": {
    "iso:country":"US",
    "sg:address":"5437 Southwest Ave",
    "sg:city":"Saint Louis",
    "sg:classifiers":[
        {
            "category":"Food & Beverages",
            "subcategory":"Groceries & Convenience Stores",
            "type":"Retail Goods"
        }
    ],
    "sg:phone":"+1 314 646 8469",
    "sg:postcode":"63139",
    "sg:province":"MO",
    "sg:website":"www.save-a-lot.com",
    "wof:name":"Save A-Lot Southwest",
    "wof:placetype":"venue"
},
  "geometry": {"coordinates":[-90.279694,38.610181],"type":"Point"}
}