{
  "type": "Feature",
  "properties": {
    "iso:country":"US",
    "sg:address":"14 W 62 Ter",
    "sg:city":"Kansas City",
    "sg:classifiers":[
        {
            "category":"Food & Beverages",
            "subcategory":"Groceries & Convenience Stores",
            "type":"Retail Goods"
        }
    ],
    "sg:phone":"+1 816 523 3700",
    "sg:postcode":"64113",
    "sg:province":"MO",
    "sg:tags":[
        "grocer"
    ],
    "wof:name":"Cosentino's Market In Brooksid",
    "wof:placetype":"venue"
},
  "geometry": {"coordinates":[-94.58999300000001,39.014952],"type":"Point"}
}