{
  "type": "Feature",
  "properties": {
    "iso:country":"US",
    "sg:address":"104 N Public Ave",
    "sg:city":"Ava",
    "sg:classifiers":[
        {
            "category":"Personal",
            "subcategory":"Barber",
            "type":"Services"
        }
    ],
    "sg:phone":"+1 417 683 4702",
    "sg:postcode":"65631",
    "sg:province":"MO",
    "wof:name":"Duck-In Barber Shop",
    "wof:placetype":"venue"
},
  "geometry": {"coordinates":[-93.473083,37.030966],"type":"Point"}
}