{
  "type": "Feature",
  "properties": {
    "iso:country":"US",
    "sg:address":"1900 E 16th St",
    "sg:city":"Trenton",
    "sg:classifiers":[
        {
            "category":"Government",
            "subcategory":"Office",
            "type":"Public Place"
        }
    ],
    "sg:phone":"+1 660 359 6323",
    "sg:postcode":"64683",
    "sg:province":"MO",
    "sg:tags":[
        "village"
    ],
    "wof:name":"Street Maintenance Garage",
    "wof:placetype":"venue"
},
  "geometry": {"coordinates":[-93.59832900000001,40.080476],"type":"Point"}
}