{
  "type": "Feature",
  "properties": {
    "iso:country":"US",
    "sg:address":"218 Delaware St",
    "sg:city":"Kansas City",
    "sg:classifiers":[
        {
            "category":"Professional",
            "subcategory":"Engineering",
            "type":"Services"
        }
    ],
    "sg:phone":"+1 816 471 2225",
    "sg:postcode":"64105",
    "sg:province":"MO",
    "sg:tags":[
        "mechanical",
        "design",
        "engineer"
    ],
    "wof:name":"Jay Consulting Engineers Inc",
    "wof:placetype":"venue"
},
  "geometry": {"coordinates":[-94.585379,39.111994],"type":"Point"}
}