{
  "type": "Feature",
  "properties": {
    "iso:country":"US",
    "sg:address":"10 S Rangeline Rd",
    "sg:city":"Columbia",
    "sg:classifiers":[
        {
            "category":"Freight",
            "type":"Transportation"
        }
    ],
    "sg:phone":"+1 573 214 0992",
    "sg:postcode":"65201",
    "sg:province":"MO",
    "sg:tags":[
        "general"
    ],
    "wof:name":"Route Z Storage Units",
    "wof:placetype":"venue"
},
  "geometry": {"coordinates":[-92.199108,38.949375],"type":"Point"}
}