{
  "type": "Feature",
  "properties": {
    "iso:country":"US",
    "sg:address":"8206 Gravois Rd",
    "sg:city":"St Louis",
    "sg:classifiers":[
        {
            "category":"Recreation",
            "type":"Entertainment"
        }
    ],
    "sg:phone":"+1 314 351 6303",
    "sg:postcode":"63123",
    "sg:province":"MO",
    "sg:tags":[
        "martial",
        "arts",
        "instruction"
    ],
    "wof:name":"Shaolin Black Dragon Kung Fu",
    "wof:placetype":"venue"
},
  "geometry": {"coordinates":[-90.30230400000001,38.55891],"type":"Point"}
}