{
  "type": "Feature",
  "properties": {
    "iso:country":"US",
    "sg:address":"811 S Neosho Blvd",
    "sg:city":"Neosho",
    "sg:classifiers":[
        {
            "category":"Professional",
            "subcategory":"Accounting & Tax Preparation",
            "type":"Services"
        }
    ],
    "sg:phone":"+1 417 451 0079",
    "sg:postcode":"64850",
    "sg:province":"MO",
    "sg:tags":[
        "return",
        "preparation-business"
    ],
    "wof:name":"Robertson Tax Service",
    "wof:placetype":"venue"
},
  "geometry": {"coordinates":[-94.383013,36.859425],"type":"Point"}
}