{
  "type": "Feature",
  "properties": {
    "iso:country":"US",
    "sg:address":"1416 Gentry St",
    "sg:city":"Kansas City",
    "sg:classifiers":[
        {
            "category":"Wholesale",
            "subcategory":"Electrical",
            "type":"Manufacturing & Wholesale Goods"
        }
    ],
    "sg:phone":"+1 816 842 9283",
    "sg:postcode":"64116",
    "sg:province":"MO",
    "sg:tags":[
        "equipment",
        "electric",
        "supply"
    ],
    "sg:website":"www.mweinc.com",
    "wof:name":"MWE Inc",
    "wof:placetype":"venue"
},
  "geometry": {"coordinates":[-94.57391800000001,39.135665],"type":"Point"}
}