{
  "type": "Feature",
  "properties": {
    "iso:country":"US",
    "sg:address":"100 S Jefferson St",
    "sg:city":"Kearney",
    "sg:classifiers":[
        {
            "category":"Personal",
            "subcategory":"Beauty Salon",
            "type":"Services"
        }
    ],
    "sg:phone":"+1 816 635 6039",
    "sg:postcode":"64060",
    "sg:province":"MO",
    "wof:name":"Leesa's Hair Care",
    "wof:placetype":"venue"
},
  "geometry": {"coordinates":[-94.36232699999999,39.372128],"type":"Point"}
}