{
  "type": "Feature",
  "properties": {
    "iso:country":"US",
    "sg:address":"274 Westwind Rd",
    "sg:city":"Elkland",
    "sg:classifiers":[
        {
            "category":"Manufacturing",
            "subcategory":"Pet Food",
            "type":"Manufacturing & Wholesale Goods"
        },
        {
            "category":"Farming",
            "subcategory":"Farm",
            "type":"Manufacturing & Wholesale Goods"
        }
    ],
    "sg:phone":"+1 417 345 8380",
    "sg:postcode":"65644",
    "sg:province":"MO",
    "sg:tags":[
        "hay"
    ],
    "wof:name":"Bill Nimmo",
    "wof:placetype":"venue"
},
  "geometry": {"coordinates":[-93.028477,37.55185],"type":"Point"}
}