{
  "type": "Feature",
  "properties": {
    "iso:country":"US",
    "sg:address":"5583 Chapel Hill Rd",
    "sg:city":"Sullivan",
    "sg:classifiers":[
        {
            "category":"Organizations",
            "subcategory":"Religious Organization",
            "type":"Services"
        }
    ],
    "sg:phone":"+1 636 629 0701",
    "sg:postcode":"63080",
    "sg:province":"MO",
    "sg:tags":[
        "church"
    ],
    "wof:name":"New Chapel Hill",
    "wof:placetype":"venue"
},
  "geometry": {"coordinates":[-90.975503,38.22198],"type":"Point"}
}