{
  "type": "Feature",
  "properties": {
    "iso:country":"US",
    "sg:address":"51 Elaine Dr",
    "sg:city":"O Fallon",
    "sg:classifiers":[
        {
            "category":"Wholesale",
            "subcategory":"Photographic Equipment",
            "type":"Manufacturing & Wholesale Goods"
        }
    ],
    "sg:phone":"+1 636 240 4815",
    "sg:postcode":"63366",
    "sg:province":"MO",
    "sg:tags":[
        "camera"
    ],
    "sg:website":"www.cwejrs.com",
    "wof:name":"CWE/Jrs",
    "wof:placetype":"venue"
},
  "geometry": {"coordinates":[-90.723984,38.808358],"type":"Point"}
}