{
  "type": "Feature",
  "properties": {
    "iso:country":"US",
    "sg:address":"522 S Main St",
    "sg:city":"Grain Valley",
    "sg:classifiers":[
        {
            "category":"Restaurant",
            "type":"Food & Drink"
        }
    ],
    "sg:phone":"+1 816 847 7990",
    "sg:postcode":"64029",
    "sg:province":"MO",
    "wof:name":"Russo's Pizza",
    "wof:placetype":"venue"
},
  "geometry": {"coordinates":[-94.198528,39.008312],"type":"Point"}
}