{
  "type": "Feature",
  "properties": {
    "iso:country":"US",
    "sg:address":"3221 Lemay Ferry Rd",
    "sg:city":"St Louis",
    "sg:classifiers":[
        {
            "category":"Personal",
            "subcategory":"Beauty Salon",
            "type":"Services"
        }
    ],
    "sg:phone":"+1 314 487 3405",
    "sg:postcode":"63125",
    "sg:province":"MO",
    "wof:name":"Kelly's Salon",
    "wof:placetype":"venue"
},
  "geometry": {"coordinates":[-90.31700600000001,38.512878],"type":"Point"}
}