{
  "type": "Feature",
  "properties": {
    "iso:country":"US",
    "sg:address":"5384 Elm Rd",
    "sg:city":"Reeds",
    "sg:classifiers":[
        {
            "category":"Retail",
            "subcategory":"Auto Repair",
            "type":"Services"
        }
    ],
    "sg:phone":"+1 417 673 9396",
    "sg:postcode":"64859",
    "sg:province":"MO",
    "sg:tags":[
        "injection",
        "part",
        "engines-diesel-fuel"
    ],
    "wof:name":"All Care Diesel",
    "wof:placetype":"venue"
},
  "geometry": {"coordinates":[-94.15550399999999,37.1234],"type":"Point"}
}