{
  "type": "Feature",
  "properties": {
    "iso:country":"US",
    "sg:address":"129 W 4th St",
    "sg:city":"Appleton City",
    "sg:classifiers":[
        {
            "category":"Insurance",
            "subcategory":"Insurance Agent",
            "type":"Services"
        }
    ],
    "sg:phone":"+1 660 476 2543",
    "sg:postcode":"64724",
    "sg:province":"MO",
    "wof:name":"Shelter Insurance",
    "wof:placetype":"venue"
},
  "geometry": {"coordinates":[-94.028419,38.190591],"type":"Point"}
}