{
  "type": "Feature",
  "properties": {
    "iso:country":"US",
    "sg:address":"924 W Morrow St",
    "sg:city":"Marshall",
    "sg:classifiers":[
        {
            "category":"Place Of Worship",
            "subcategory":"Church",
            "type":"Public Place"
        },
        {
            "category":"Place Of Worship",
            "type":"Public Place"
        }
    ],
    "sg:phone":"+1 660 886 9580",
    "sg:postcode":"65340",
    "sg:province":"MO",
    "sg:tags":[
        "christ",
        "churches-community"
    ],
    "sg:website":"http://www.cofchrist.org",
    "wof:name":"Community Of Christ",
    "wof:placetype":"venue"
},
  "geometry": {"coordinates":[-93.21167800000001,39.104582],"type":"Point"}
}