{
  "type": "Feature",
  "properties": {
    "iso:country":"US",
    "sg:address":"317 Broadway St",
    "sg:city":"Elsberry",
    "sg:classifiers":[
        {
            "category":"Real Estate",
            "subcategory":"Real Estate Services",
            "type":"Services"
        }
    ],
    "sg:phone":"+1 573 898 5530",
    "sg:postcode":"63343",
    "sg:province":"MO",
    "sg:tags":[
        "company",
        "title"
    ],
    "wof:name":"Lin-Pike Land Title Co",
    "wof:placetype":"venue"
},
  "geometry": {"coordinates":[-90.782982,39.165709],"type":"Point"}
}