{
  "type": "Feature",
  "properties": {
    "iso:country":"US",
    "sg:address":"3760 S Grand Blvd",
    "sg:city":"Saint Louis",
    "sg:classifiers":[
        {
            "category":"Banks & Credit Unions",
            "subcategory":"Bank",
            "type":"Services"
        }
    ],
    "sg:phone":"+1 314 771 6750",
    "sg:postcode":"63118",
    "sg:province":"MO",
    "sg:website":"www.pulasklbankstl.com",
    "wof:name":"Pulaski Bank",
    "wof:placetype":"venue"
},
  "geometry": {"coordinates":[-90.244598,38.588699],"type":"Point"}
}