{
  "type": "Feature",
  "properties": {
    "iso:country":"US",
    "sg:address":"15660 Boiling Springs Rd",
    "sg:city":"Licking",
    "sg:classifiers":[
        {
            "category":"Farming",
            "subcategory":"Farm",
            "type":"Manufacturing & Wholesale Goods"
        }
    ],
    "sg:phone":"+1 573 674 2508",
    "sg:postcode":"65542",
    "sg:province":"MO",
    "sg:tags":[
        "crop",
        "general"
    ],
    "wof:name":"Eugene Peyton Farm",
    "wof:placetype":"venue"
},
  "geometry": {"coordinates":[-91.993441,37.45662],"type":"Point"}
}