{
  "type": "Feature",
  "properties": {
    "iso:country":"US",
    "sg:address":"511 Delaware St",
    "sg:city":"Kansas City",
    "sg:classifiers":[
        {
            "category":"Banks & Credit Unions",
            "subcategory":"Financial Services",
            "type":"Services"
        }
    ],
    "sg:phone":"+1 816 474 6333",
    "sg:postcode":"64105",
    "sg:province":"MO",
    "sg:tags":[
        "company",
        "holding"
    ],
    "wof:name":"P3 Holdings",
    "wof:placetype":"venue"
},
  "geometry": {"coordinates":[-94.583809,39.107507],"type":"Point"}
}