{
  "type": "Feature",
  "properties": {
    "iso:country":"US",
    "sg:address":"10500 State Hwy 350",
    "sg:city":"Raytown",
    "sg:classifiers":[
        {
            "category":"Organizations",
            "subcategory":"Religious Organization",
            "type":"Services"
        }
    ],
    "sg:phone":"+1 816 353 1994",
    "sg:postcode":"64138",
    "sg:province":"MO",
    "sg:tags":[
        "church"
    ],
    "sg:website":"www.firstbaptistraytown.com",
    "wof:name":"First Baptist Church",
    "wof:placetype":"venue"
},
  "geometry": {"coordinates":[-94.45946600000001,38.985792],"type":"Point"}
}