{
  "type": "Feature",
  "properties": {
    "iso:country":"US",
    "sg:address":"1208 S Boundary St",
    "sg:city":"Kirksville",
    "sg:classifiers":[
        {
            "category":"Insurance",
            "subcategory":"Insurance Agent",
            "type":"Services"
        }
    ],
    "sg:phone":"+1 660 665 6868",
    "sg:postcode":"63501",
    "sg:province":"MO",
    "sg:tags":[
        "processing"
    ],
    "wof:name":"Professional Claims Assistance",
    "wof:placetype":"venue"
},
  "geometry": {"coordinates":[-92.595578,40.186471],"type":"Point"}
}