{
  "type": "Feature",
  "properties": {
    "iso:country":"US",
    "sg:address":"1342 E Kingsley St",
    "sg:city":"Springfield",
    "sg:classifiers":[
        {
            "category":"Health Services",
            "subcategory":"Health Practitioner",
            "type":"Services"
        }
    ],
    "sg:phone":"+1 417 269 0390",
    "sg:postcode":"65804",
    "sg:province":"MO",
    "sg:tags":[
        "psychologist"
    ],
    "wof:name":"Kingsley Psychological Assoc",
    "wof:placetype":"venue"
},
  "geometry": {"coordinates":[-93.27382900000001,37.1403],"type":"Point"}
}