{
  "type": "Feature",
  "properties": {
    "iso:country":"US",
    "sg:address":"3905 SW 14 St Ct",
    "sg:city":"Blue Springs",
    "sg:classifiers":[
        {
            "category":"Restaurant",
            "type":"Food & Drink"
        }
    ],
    "sg:phone":"+1 816 224 0071",
    "sg:postcode":"64015",
    "sg:province":"MO",
    "sg:tags":[
        "eating"
    ],
    "wof:name":"Ridgewood Detectable Treats",
    "wof:placetype":"venue"
},
  "geometry": {"coordinates":[-94.28330699999999,38.982645],"type":"Point"}
}