{
  "type": "Feature",
  "properties": {
    "iso:country":"US",
    "sg:address":"1216 W C St",
    "sg:city":"Joplin",
    "sg:classifiers":[
        {
            "category":"Manufacturing",
            "subcategory":"Tools & Machinery",
            "type":"Manufacturing & Wholesale Goods"
        }
    ],
    "sg:phone":"+1 417 623 8000",
    "sg:postcode":"64801",
    "sg:province":"MO",
    "sg:tags":[
        "storage"
    ],
    "sg:website":"www.eaglepicher.com",
    "wof:name":"Eagle-Picher Technologies Div",
    "wof:placetype":"venue"
},
  "geometry": {"coordinates":[-94.52620899999999,37.094284],"type":"Point"}
}