{
  "type": "Feature",
  "properties": {
    "iso:country":"US",
    "sg:address":"13761 Saint Charles Rock Rd",
    "sg:city":"Bridgeton",
    "sg:classifiers":[
        {
            "category":"Wholesale",
            "subcategory":"Hardware",
            "type":"Manufacturing & Wholesale Goods"
        },
        {
            "category":"Professional",
            "subcategory":"Business Services",
            "type":"Services"
        }
    ],
    "sg:phone":"+1 314 770 2915",
    "sg:postcode":"63044",
    "sg:province":"MO",
    "sg:tags":[
        "nut",
        "bolt"
    ],
    "wof:name":"Michael Hose Sales",
    "wof:placetype":"venue"
},
  "geometry": {"coordinates":[-90.465754,38.781029],"type":"Point"}
}