{
  "type": "Feature",
  "properties": {
    "iso:country":"US",
    "sg:address":"7521 N Oak Fwy",
    "sg:city":"Kansas City",
    "sg:classifiers":[
        {
            "category":"Retail",
            "subcategory":"Laundry & Dry Cleaning",
            "type":"Services"
        }
    ],
    "sg:phone":"+1 816 436 6648",
    "sg:postcode":"64118",
    "sg:province":"MO",
    "sg:tags":[
        "cleaners"
    ],
    "wof:name":"Ida's Daisy Fresh Cleaners",
    "wof:placetype":"venue"
},
  "geometry": {"coordinates":[-94.576009,39.229613],"type":"Point"}
}