{
  "type": "Feature",
  "properties": {
    "iso:country":"US",
    "sg:address":"210 Monroe St",
    "sg:city":"Jefferson City",
    "sg:classifiers":[
        {
            "category":"Manufacturing",
            "subcategory":"Printing",
            "type":"Manufacturing & Wholesale Goods"
        }
    ],
    "sg:phone":"+1 573 636 3131",
    "sg:postcode":"65101",
    "sg:province":"MO",
    "sg:tags":[
        "newspaper"
    ],
    "sg:website":"www.newstribune.com",
    "wof:name":"News Tribune Co",
    "wof:placetype":"venue"
},
  "geometry": {"coordinates":[-92.168819,38.576128],"type":"Point"}
}