{
  "type": "Feature",
  "properties": {
    "iso:country":"US",
    "sg:address":"1202 Forum Dr",
    "sg:city":"Rolla",
    "sg:classifiers":[
        {
            "category":"Professional",
            "subcategory":"Management & Consulting",
            "type":"Services"
        }
    ],
    "sg:phone":"+1 573 341 8121",
    "sg:postcode":"65401",
    "sg:province":"MO",
    "wof:name":"Universal Challenge Center",
    "wof:placetype":"venue"
},
  "geometry": {"coordinates":[-91.75219199999999,37.952643],"type":"Point"}
}