{
  "type": "Feature",
  "properties": {
    "iso:country":"US",
    "sg:address":"2539 Woodson Rd",
    "sg:city":"Saint Louis",
    "sg:classifiers":[
        {
            "category":"Restaurant",
            "type":"Food & Drink"
        }
    ],
    "sg:phone":"+1 314 428 1143",
    "sg:postcode":"63114",
    "sg:province":"MO",
    "sg:tags":[
        "eating"
    ],
    "wof:name":"Diner George Rivolo",
    "wof:placetype":"venue"
},
  "geometry": {"coordinates":[-90.361589,38.705007],"type":"Point"}
}