{
  "type": "Feature",
  "properties": {
    "iso:country":"US",
    "sg:address":"3449 S Kingshighway Blvd",
    "sg:city":"Saint Louis",
    "sg:classifiers":[
        {
            "category":"Restaurant",
            "type":"Food & Drink"
        }
    ],
    "sg:phone":"+1 314 481 7802",
    "sg:postcode":"63139",
    "sg:province":"MO",
    "sg:tags":[
        "eating"
    ],
    "wof:name":"Lee's Famous Recipe",
    "wof:placetype":"venue"
},
  "geometry": {"coordinates":[-90.270798,38.5961],"type":"Point"}
}