{
  "type": "Feature",
  "properties": {
    "iso:country":"US",
    "sg:address":"103 W 3rd St",
    "sg:city":"Rolla",
    "sg:classifiers":[
        {
            "category":"Building & Trades",
            "subcategory":"Electrical",
            "type":"Services"
        }
    ],
    "sg:phone":"+1 573 364 6125",
    "sg:postcode":"65401",
    "sg:province":"MO",
    "sg:tags":[
        "industrial",
        "electrician",
        "contractors-commercial",
        "electric"
    ],
    "wof:name":"Martin Electric",
    "wof:placetype":"venue"
},
  "geometry": {"coordinates":[-91.77059800000001,37.946171],"type":"Point"}
}