{
  "type": "Feature",
  "properties": {
    "iso:country":"US",
    "sg:address":"2 Chilton Ln",
    "sg:city":"Saint Louis",
    "sg:classifiers":[
        {
            "category":"Manufacturing",
            "subcategory":"Furniture",
            "type":"Manufacturing & Wholesale Goods"
        }
    ],
    "sg:phone":"+1 314 997 3311",
    "sg:postcode":"63141",
    "sg:province":"MO",
    "sg:tags":[
        "decorative",
        "lighting",
        "accessory"
    ],
    "wof:name":"Bottle Bay Birch",
    "wof:placetype":"venue"
},
  "geometry": {"coordinates":[-90.415148,38.65779],"type":"Point"}
}