{
  "type": "Feature",
  "properties": {
    "iso:country":"US",
    "sg:address":"7089 W Junge Blvd",
    "sg:city":"Joplin",
    "sg:classifiers":[
        {
            "category":"Building & Trades",
            "subcategory":"Construction",
            "type":"Services"
        }
    ],
    "sg:phone":"+1 417 781 2806",
    "sg:postcode":"64804",
    "sg:province":"MO",
    "sg:tags":[
        "dry wall",
        "contractor"
    ],
    "wof:name":"Ron Watson Drywall",
    "wof:placetype":"venue"
},
  "geometry": {"coordinates":[-94.60598899999999,37.078535],"type":"Point"}
}