{
  "type": "Feature",
  "properties": {
    "iso:country":"US",
    "sg:address":"570 NW 1601st Rd",
    "sg:city":"Kingsville",
    "sg:classifiers":[
        {
            "category":"Organizations",
            "subcategory":"Religious Organization",
            "type":"Services"
        }
    ],
    "sg:phone":"+1 816 697 2698",
    "sg:postcode":"64061",
    "sg:province":"MO",
    "sg:tags":[
        "church"
    ],
    "wof:name":"Elm Spring Baptist Church",
    "wof:placetype":"venue"
},
  "geometry": {"coordinates":[-94.042733,38.848278],"type":"Point"}
}