{
  "type": "Feature",
  "properties": {
    "iso:country":"US",
    "sg:address":"4980 Parker Rd",
    "sg:city":"Florissant",
    "sg:classifiers":[
        {
            "category":"Social Services",
            "type":"Services"
        }
    ],
    "sg:phone":"+1 314 741 6691",
    "sg:postcode":"63033",
    "sg:province":"MO",
    "wof:name":"Access 2 Ross",
    "wof:placetype":"venue"
},
  "geometry": {"coordinates":[-90.264385,38.793339],"type":"Point"}
}