{
  "type": "Feature",
  "properties": {
    "iso:country":"US",
    "sg:address":"317 State Hwy 291",
    "sg:city":"Liberty",
    "sg:classifiers":[
        {
            "category":"Freight",
            "type":"Transportation"
        }
    ],
    "sg:phone":"+1 816 781 0606",
    "sg:postcode":"64068",
    "sg:province":"MO",
    "sg:tags":[
        "commercial",
        "storage"
    ],
    "wof:name":"Attic Storage",
    "wof:placetype":"venue"
},
  "geometry": {"coordinates":[-94.441557,39.242458],"type":"Point"}
}