{
  "type": "Feature",
  "properties": {
    "iso:country":"US",
    "sg:address":"22 Country Breeze Cir",
    "sg:city":"Eldon",
    "sg:classifiers":[
        {
            "category":"Manufacturing",
            "subcategory":"Tools & Machinery",
            "type":"Manufacturing & Wholesale Goods"
        }
    ],
    "sg:phone":"+1 573 392 5717",
    "sg:postcode":"65026",
    "sg:province":"MO",
    "sg:tags":[
        "building",
        "equipment",
        "construction"
    ],
    "wof:name":"Djs Construction",
    "wof:placetype":"venue"
},
  "geometry": {"coordinates":[-92.547913,38.34856],"type":"Point"}
}