{
  "type": "Feature",
  "properties": {
    "iso:country":"US",
    "sg:address":"12300 Pleasant Prairie Rd",
    "sg:city":"Napoleon",
    "sg:classifiers":[
        {
            "category":"Building & Trades",
            "subcategory":"Construction",
            "type":"Services"
        }
    ],
    "sg:phone":"+1 816 240 8570",
    "sg:postcode":"64074",
    "sg:province":"MO",
    "sg:tags":[
        "concrete",
        "contractor"
    ],
    "wof:name":"Turner & Michael Construction",
    "wof:placetype":"venue"
},
  "geometry": {"coordinates":[-94.09218799999999,39.109595],"type":"Point"}
}