{
  "type": "Feature",
  "properties": {
    "iso:country":"US",
    "sg:address":"700 E 16th Ave",
    "sg:city":"Kansas City",
    "sg:classifiers":[
        {
            "category":"Wholesale",
            "subcategory":"Durable Goods & Equipment",
            "type":"Manufacturing & Wholesale Goods"
        }
    ],
    "sg:phone":"+1 816 421 4500",
    "sg:postcode":"64116",
    "sg:province":"MO",
    "sg:tags":[
        "maker",
        "monument"
    ],
    "sg:website":"www.johnsongranite.com",
    "wof:name":"Johnson Granite Supply Co",
    "wof:placetype":"venue"
},
  "geometry": {"coordinates":[-94.572124,39.137769],"type":"Point"}
}