{
  "type": "Feature",
  "properties": {
    "iso:country":"US",
    "sg:address":"1023 NW 63 St",
    "sg:city":"Kansas City",
    "sg:classifiers":[
        {
            "category":"Shopping",
            "type":"Retail Goods"
        }
    ],
    "sg:phone":"+1 816 505 4301",
    "sg:postcode":"64118",
    "sg:province":"MO",
    "sg:tags":[
        "merchandise"
    ],
    "wof:name":"Aesthetic Essentials",
    "wof:placetype":"venue"
},
  "geometry": {"coordinates":[-94.59303,39.209646],"type":"Point"}
}