{
  "type": "Feature",
  "properties": {
    "iso:country":"US",
    "sg:address":"217 N 7th St",
    "sg:city":"St Louis",
    "sg:classifiers":[
        {
            "category":"Restaurant",
            "type":"Food & Drink"
        }
    ],
    "sg:phone":"+1 314 241 9898",
    "sg:postcode":"63101",
    "sg:province":"MO",
    "wof:name":"Zuzu",
    "wof:placetype":"venue"
},
  "geometry": {"coordinates":[-90.19141999999999,38.628176],"type":"Point"}
}