{
  "type": "Feature",
  "properties": {
    "iso:country":"US",
    "sg:address":"6006 Pershing Ave",
    "sg:city":"Saint Louis",
    "sg:classifiers":[
        {
            "category":"Arena",
            "subcategory":"Sports Club",
            "type":"Entertainment"
        }
    ],
    "sg:phone":"+1 314 726 5070",
    "sg:postcode":"63112",
    "sg:province":"MO",
    "sg:tags":[
        "martial art"
    ],
    "wof:name":"St Louis Ki Society",
    "wof:placetype":"venue"
},
  "geometry": {"coordinates":[-90.294998,38.649502],"type":"Point"}
}