{
  "type": "Feature",
  "properties": {
    "iso:country":"US",
    "sg:address":"6150 Oakland Ave",
    "sg:city":"Saint Louis",
    "sg:classifiers":[
        {
            "category":"Health Services",
            "subcategory":"Doctor",
            "type":"Services"
        },
        {
            "category":"Health Services",
            "subcategory":"Hospital",
            "type":"Services"
        },
        {
            "category":"Education",
            "subcategory":"University",
            "type":"Public Place"
        }
    ],
    "sg:phone":"+1 314 577 8000",
    "sg:postcode":"63139",
    "sg:province":"MO",
    "sg:tags":[
        "college"
    ],
    "wof:name":"Ritter Paul J MD",
    "wof:placetype":"venue"
},
  "geometry": {"coordinates":[-90.287903,38.6311],"type":"Point"}
}