{
  "type": "Feature",
  "properties": {
    "addr:full":"4191 S Scenic Ave Springfield MO 65807",
    "addr:housenumber":"4191",
    "addr:postcode":"65807",
    "addr:street":"S Scenic Ave",
    "iso:country":"US",
    "sg:address":"4191 S Scenic Ave",
    "sg:city":"Springfield",
    "sg:classifiers":[
        {
            "category":"Food & Beverages",
            "subcategory":"Groceries & Convenience Stores",
            "type":"Retail Goods"
        }
    ],
    "sg:phone":"+1 417 882 0292",
    "sg:postcode":"65807",
    "sg:province":"MO",
    "wof:name":"Convenient Food Mart",
    "wof:placetype":"venue"
},
  "geometry": {"coordinates":[-93.33268099999999,37.138945],"type":"Point"}
}