{
  "type": "Feature",
  "properties": {
    "iso:country":"US",
    "sg:address":"10620 SW Willard Rd",
    "sg:city":"Stewartsville",
    "sg:classifiers":[
        {
            "category":"Building & Trades",
            "subcategory":"Construction",
            "type":"Services"
        }
    ],
    "sg:phone":"+1 816 667 5255",
    "sg:postcode":"64490",
    "sg:province":"MO",
    "sg:tags":[
        "concrete",
        "work"
    ],
    "wof:name":"C Sutton Historical Bldg Mvg",
    "wof:placetype":"venue"
},
  "geometry": {"coordinates":[-94.602079,39.753935],"type":"Point"}
}