{
  "type": "Feature",
  "properties": {
    "iso:country":"US",
    "sg:address":"915 W Grant St",
    "sg:city":"Dexter",
    "sg:classifiers":[
        {
            "category":"Education",
            "subcategory":"School",
            "type":"Public Place"
        }
    ],
    "sg:phone":"+1 573 614 1015",
    "sg:postcode":"63841",
    "sg:province":"MO",
    "wof:name":"Southwest Elementary School",
    "wof:placetype":"venue"
},
  "geometry": {"coordinates":[-89.971187,36.788973],"type":"Point"}
}