{
  "type": "Feature",
  "properties": {
    "iso:country":"US",
    "sg:address":"425 N Highway Dr",
    "sg:city":"Fenton",
    "sg:classifiers":[
        {
            "category":"Home & Garden",
            "subcategory":"Building Materials",
            "type":"Retail Goods"
        }
    ],
    "sg:phone":"+1 636 343 6522",
    "sg:postcode":"63026",
    "sg:province":"MO",
    "sg:tags":[
        "roofing"
    ],
    "wof:name":"Tamko Roofing Products Inc",
    "wof:placetype":"venue"
},
  "geometry": {"coordinates":[-90.44983000000001,38.543236],"type":"Point"}
}