{
  "type": "Feature",
  "properties": {
    "iso:country":"US",
    "sg:address":"6778 Robbins Ave",
    "sg:city":"Saint Louis",
    "sg:classifiers":[
        {
            "category":"Wholesale",
            "subcategory":"Durable Goods & Equipment",
            "type":"Manufacturing & Wholesale Goods"
        }
    ],
    "sg:phone":"+1 314 406 1712",
    "sg:postcode":"63133",
    "sg:province":"MO",
    "wof:name":"Treasure Supply Inc",
    "wof:placetype":"venue"
},
  "geometry": {"coordinates":[-90.30815,38.677381],"type":"Point"}
}