{
  "type": "Feature",
  "properties": {
    "iso:country":"US",
    "sg:address":"2222 Aileswood Ct",
    "sg:city":"Saint Louis",
    "sg:classifiers":[
        {
            "category":"Health Services",
            "subcategory":"Clinic",
            "type":"Services"
        }
    ],
    "sg:phone":"+1 314 845 0500",
    "sg:postcode":"63129",
    "sg:province":"MO",
    "sg:tags":[
        "transcription",
        "medical"
    ],
    "wof:name":"Nem Processing Service",
    "wof:placetype":"venue"
},
  "geometry": {"coordinates":[-90.297944,38.475579],"type":"Point"}
}