{
  "type": "Feature",
  "properties": {
    "iso:country":"US",
    "sg:address":"1318 Grant St",
    "sg:city":"Unionville",
    "sg:classifiers":[
        {
            "category":"Organizations",
            "subcategory":"Religious Organization",
            "type":"Services"
        }
    ],
    "sg:phone":"+1 660 947 3318",
    "sg:postcode":"63565",
    "sg:province":"MO",
    "wof:name":"Church Of Christ",
    "wof:placetype":"venue"
},
  "geometry": {"coordinates":[-92.998631,40.476194],"type":"Point"}
}