{
  "type": "Feature",
  "properties": {
    "iso:country":"US",
    "sg:address":"2720 Cherokee St 2nd Fl",
    "sg:city":"St Louis",
    "sg:classifiers":[
        {
            "category":"Arts & Performance",
            "subcategory":"Arts Center",
            "type":"Entertainment"
        }
    ],
    "sg:postcode":"63118",
    "sg:province":"MO",
    "sg:website":"www.artdimensions.org/",
    "wof:name":"Art Dimensions",
    "wof:placetype":"venue"
},
  "geometry": {"coordinates":[-90.228494,38.593606],"type":"Point"}
}