{
  "type": "Feature",
  "properties": {
    "iso:country":"US",
    "sg:address":"103 S Locust St",
    "sg:city":"Eldon",
    "sg:classifiers":[
        {
            "category":"Professional",
            "type":"Services"
        }
    ],
    "sg:phone":"+1 573 392 5248",
    "sg:postcode":"65026",
    "sg:province":"MO",
    "sg:tags":[
        "establishment"
    ],
    "wof:name":"M W Inc",
    "wof:placetype":"venue"
},
  "geometry": {"coordinates":[-92.585227,38.349723],"type":"Point"}
}