{
  "type": "Feature",
  "properties": {
    "iso:country":"US",
    "sg:address":"17 Mullanphy Ct",
    "sg:city":"Florissant",
    "sg:classifiers":[
        {
            "category":"Retail",
            "subcategory":"Animal Services",
            "type":"Services"
        }
    ],
    "sg:phone":"+1 314 831 7387",
    "sg:postcode":"63031",
    "sg:province":"MO",
    "sg:tags":[
        "pet",
        "grooming",
        "washing"
    ],
    "wof:name":"Dogs N Style",
    "wof:placetype":"venue"
},
  "geometry": {"coordinates":[-90.331684,38.805418],"type":"Point"}
}