{
  "type": "Feature",
  "properties": {
    "iso:country":"US",
    "sg:address":"307 S Kyler St",
    "sg:city":"Monett",
    "sg:classifiers":[
        {
            "category":"Restaurant",
            "type":"Food & Drink"
        }
    ],
    "sg:phone":"+1 417 236 0201",
    "sg:postcode":"65708",
    "sg:province":"MO",
    "sg:tags":[
        "pizza",
        "italian"
    ],
    "wof:name":"Gambino's Pizza",
    "wof:placetype":"venue"
},
  "geometry": {"coordinates":[-93.914326,36.913647],"type":"Point"}
}