{
  "type": "Feature",
  "properties": {
    "iso:country":"US",
    "sg:address":"204 North St",
    "sg:city":"Martinsburg",
    "sg:classifiers":[
        {
            "category":"Building & Trades",
            "subcategory":"Electrical",
            "type":"Services"
        }
    ],
    "sg:phone":"+1 573 492 6514",
    "sg:postcode":"65264",
    "sg:province":"MO",
    "sg:tags":[
        "electric",
        "contractor"
    ],
    "wof:name":"Cope & Wright Electric LLC",
    "wof:placetype":"venue"
},
  "geometry": {"coordinates":[-91.64836099999999,39.103144],"type":"Point"}
}