{
  "type": "Feature",
  "properties": {
    "iso:country":"US",
    "sg:address":"5209 NW Crooked Rd",
    "sg:city":"Kansas City",
    "sg:classifiers":[
        {
            "category":"Banks & Credit Unions",
            "subcategory":"Bank",
            "type":"Services"
        }
    ],
    "sg:phone":"+1 816 587 5600",
    "sg:postcode":"64152",
    "sg:province":"MO",
    "sg:tags":[
        "mortgage"
    ],
    "wof:name":"Apex Mortgage",
    "wof:placetype":"venue"
},
  "geometry": {"coordinates":[-94.68778399999999,39.190287],"type":"Point"}
}