{
  "type": "Feature",
  "properties": {
    "iso:country":"US",
    "sg:address":"1279 Madison 201",
    "sg:city":"Fredericktown",
    "sg:classifiers":[
        {
            "category":"School Buses",
            "type":"Transportation"
        }
    ],
    "sg:phone":"+1 573 783 6198",
    "sg:postcode":"63645",
    "sg:province":"MO",
    "wof:name":"R H Thompson & Sons Inc",
    "wof:placetype":"venue"
},
  "geometry": {"coordinates":[-90.309268,37.545223],"type":"Point"}
}