{
  "type": "Feature",
  "properties": {
    "iso:country":"US",
    "sg:address":"114 N Main St",
    "sg:city":"Webb City",
    "sg:classifiers":[
        {
            "category":"Shopping",
            "subcategory":"Gifts & Souvenirs",
            "type":"Retail Goods"
        }
    ],
    "sg:phone":"+1 417 673 8872",
    "sg:postcode":"64870",
    "sg:province":"MO",
    "sg:tags":[
        "shop"
    ],
    "wof:name":"Hunter's Lane",
    "wof:placetype":"venue"
},
  "geometry": {"coordinates":[-94.463112,37.147182],"type":"Point"}
}