{
  "type": "Feature",
  "properties": {
    "iso:country":"US",
    "sg:address":"31943 Ladder St",
    "sg:city":"Atlanta",
    "sg:classifiers":[
        {
            "category":"Farming",
            "subcategory":"Livestock Farm",
            "type":"Manufacturing & Wholesale Goods"
        },
        {
            "category":"Farming",
            "subcategory":"Farm & Veterinary Services",
            "type":"Manufacturing & Wholesale Goods"
        }
    ],
    "sg:phone":"+1 660 239 4451",
    "sg:postcode":"63530",
    "sg:province":"MO",
    "sg:tags":[
        "breeder"
    ],
    "wof:name":"Scott Miller",
    "wof:placetype":"venue"
},
  "geometry": {"coordinates":[-92.433745,39.925446],"type":"Point"}
}