{
  "type": "Feature",
  "properties": {
    "iso:country":"US",
    "sg:address":"427 W Coler St",
    "sg:city":"Neosho",
    "sg:classifiers":[
        {
            "category":"Professional",
            "subcategory":"Employment Agencies",
            "type":"Services"
        }
    ],
    "sg:phone":"+1 417 451 1330",
    "sg:postcode":"64850",
    "sg:province":"MO",
    "sg:tags":[
        "opportunity"
    ],
    "wof:name":"Adecco",
    "wof:placetype":"venue"
},
  "geometry": {"coordinates":[-94.37496299999999,36.872913],"type":"Point"}
}