{
  "type": "Feature",
  "properties": {
    "iso:country":"US",
    "sg:address":"13932 New Offenburg Rd",
    "sg:city":"Sainte Genevieve",
    "sg:classifiers":[
        {
            "category":"Professional",
            "subcategory":"Management & Consulting",
            "type":"Services"
        }
    ],
    "sg:phone":"+1 573 883 3421",
    "sg:postcode":"63670",
    "sg:province":"MO",
    "wof:name":"Bieser Construction",
    "wof:placetype":"venue"
},
  "geometry": {"coordinates":[-90.198303,37.9082],"type":"Point"}
}