{
  "type": "Feature",
  "properties": {
    "iso:country":"US",
    "sg:address":"39 Ronnies Plz",
    "sg:city":"St Louis",
    "sg:classifiers":[
        {
            "category":"Banks & Credit Unions",
            "subcategory":"Bank",
            "type":"Services"
        }
    ],
    "sg:phone":"+1 314 842 3979",
    "sg:postcode":"63126",
    "sg:province":"MO",
    "wof:name":"Reliance Bank",
    "wof:placetype":"venue"
},
  "geometry": {"coordinates":[-90.36085300000001,38.526913],"type":"Point"}
}