{
  "type": "Feature",
  "properties": {
    "iso:country":"US",
    "sg:address":"605 Agean Way",
    "sg:city":"Ballwin",
    "sg:classifiers":[
        {
            "category":"Building & Trades",
            "subcategory":"Construction",
            "type":"Services"
        }
    ],
    "sg:phone":"+1 636 230 5906",
    "sg:postcode":"63011",
    "sg:province":"MO",
    "sg:tags":[
        "insulation",
        "heat",
        "contractor"
    ],
    "wof:name":"Premier Insulation LLC",
    "wof:placetype":"venue"
},
  "geometry": {"coordinates":[-90.52104799999999,38.615688],"type":"Point"}
}