{
  "type": "Feature",
  "properties": {
    "addr:full":"1321 Preacher Roe Blvd West Plains MO 65775",
    "addr:housenumber":"1321",
    "addr:postcode":"65775",
    "addr:street":"Preacher Roe Blvd",
    "iso:country":"US",
    "sg:address":"1321 Preacher Roe Blvd",
    "sg:city":"West Plains",
    "sg:classifiers":[
        {
            "category":"Restaurant",
            "type":"Food & Drink"
        }
    ],
    "sg:menulink":"http://www.allmenus.com/mo/howell/105262-ryans/menu/",
    "sg:phone":"+1 417 257 3050",
    "sg:postcode":"65775",
    "sg:province":"MO",
    "sg:tags":[
        "american"
    ],
    "wof:name":"Ryan's",
    "wof:placetype":"venue"
},
  "geometry": {"coordinates":[-91.870981,36.721354],"type":"Point"}
}