{
  "type": "Feature",
  "properties": {
    "iso:country":"US",
    "sg:address":"515 N Two Mile Rd",
    "sg:city":"Dexter",
    "sg:classifiers":[
        {
            "category":"Sports & Exercise",
            "subcategory":"Bowling",
            "type":"Entertainment"
        }
    ],
    "sg:phone":"+1 573 624 1731",
    "sg:postcode":"63841",
    "sg:province":"MO",
    "sg:tags":[
        "center"
    ],
    "wof:name":"Womens International Bowl",
    "wof:placetype":"venue"
},
  "geometry": {"coordinates":[-89.98880200000001,36.797009],"type":"Point"}
}