{
  "type": "Feature",
  "properties": {
    "iso:country":"US",
    "sg:address":"306 NW 11 St",
    "sg:city":"Blue Springs",
    "sg:classifiers":[
        {
            "category":"Retail",
            "subcategory":"Auto Repair",
            "type":"Services"
        }
    ],
    "sg:phone":"+1 816 229 0018",
    "sg:postcode":"64015",
    "sg:province":"MO",
    "sg:tags":[
        "body",
        "automobile",
        "painting"
    ],
    "wof:name":"Charlie's Auto Collision Rpr",
    "wof:placetype":"venue"
},
  "geometry": {"coordinates":[-94.277664,39.019802],"type":"Point"}
}