{
  "type": "Feature",
  "properties": {
    "iso:country":"US",
    "sg:address":"1059 Oak Ridge Rd",
    "sg:city":"Robertsville",
    "sg:classifiers":[
        {
            "category":"Building & Trades",
            "subcategory":"Construction",
            "type":"Services"
        }
    ],
    "sg:phone":"+1 636 271 6041",
    "sg:postcode":"63072",
    "sg:province":"MO",
    "sg:tags":[
        "nonresidential"
    ],
    "wof:name":"Reed Construction Inc",
    "wof:placetype":"venue"
},
  "geometry": {"coordinates":[-90.777976,38.394945],"type":"Point"}
}