{
  "type": "Feature",
  "properties": {
    "iso:country":"US",
    "sg:address":"2401 Neier Rd",
    "sg:city":"Union",
    "sg:classifiers":[
        {
            "category":"Place Of Worship",
            "subcategory":"Church",
            "type":"Public Place"
        },
        {
            "category":"Place Of Worship",
            "type":"Public Place"
        }
    ],
    "sg:phone":"+1 636 583 2806",
    "sg:postcode":"63084",
    "sg:province":"MO",
    "sg:tags":[
        "churches-interdenominational",
        "churches-various",
        "denomination"
    ],
    "wof:name":"St. Joseph's Church",
    "wof:placetype":"venue"
},
  "geometry": {"coordinates":[-91.107452,38.389561],"type":"Point"}
}