{
  "type": "Feature",
  "properties": {
    "iso:country":"US",
    "sg:address":"2019 W Kansas St",
    "sg:city":"Liberty",
    "sg:classifiers":[
        {
            "category":"Personal",
            "subcategory":"Beauty Salon",
            "type":"Services"
        },
        {
            "category":"Personal",
            "subcategory":"Barber",
            "type":"Services"
        }
    ],
    "sg:phone":"+1 816 781 8727",
    "sg:postcode":"64068",
    "sg:province":"MO",
    "wof:name":"Snip & Clip Beauty Salon",
    "wof:placetype":"venue"
},
  "geometry": {"coordinates":[-94.452293,39.244665],"type":"Point"}
}