{
  "type": "Feature",
  "properties": {
    "iso:country":"US",
    "sg:address":"803 Galaxie Ave",
    "sg:city":"Harrisonville",
    "sg:classifiers":[
        {
            "category":"Professional",
            "subcategory":"Business Services",
            "type":"Services"
        }
    ],
    "sg:phone":"+1 816 380 5597",
    "sg:postcode":"64701",
    "sg:province":"MO",
    "sg:tags":[
        "packaging"
    ],
    "wof:name":"Grafco Pet",
    "wof:placetype":"venue"
},
  "geometry": {"coordinates":[-94.33129599999999,38.657844],"type":"Point"}
}