{
  "type": "Feature",
  "properties": {
    "iso:country":"US",
    "sg:address":"4235 S Charleston Ave",
    "sg:city":"Springfield",
    "sg:classifiers":[
        {
            "category":"Professional",
            "subcategory":"Business Services",
            "type":"Services"
        }
    ],
    "sg:phone":"+1 417 887 9558",
    "sg:postcode":"65804",
    "sg:province":"MO",
    "wof:name":"Springfield Central Systems",
    "wof:placetype":"venue"
},
  "geometry": {"coordinates":[-93.263063,37.136435],"type":"Point"}
}