{
  "type": "Feature",
  "properties": {
    "addr:full":"7777 Bonhomme Ave Saint Louis MO 63105",
    "addr:housenumber":"7777",
    "addr:postcode":"63105",
    "addr:street":"Bonhomme Ave",
    "iso:country":"US",
    "sg:address":"7777 Bonhomme Ave",
    "sg:city":"Saint Louis",
    "sg:classifiers":[
        {
            "category":"Professional",
            "subcategory":"Lawyer & Legal Services",
            "type":"Services"
        }
    ],
    "sg:phone":"+1 314 725 0606",
    "sg:postcode":"63105",
    "sg:province":"MO",
    "wof:name":"William F White",
    "wof:placetype":"venue"
},
  "geometry": {"coordinates":[-90.335427,38.647405],"type":"Point"}
}