{
  "type": "Feature",
  "properties": {
    "iso:country":"US",
    "sg:address":"4024 S Broadway",
    "sg:city":"Saint Louis",
    "sg:classifiers":[
        {
            "category":"Organizations",
            "subcategory":"Religious Organization",
            "type":"Services"
        }
    ],
    "sg:phone":"+1 314 752 7900",
    "sg:postcode":"63118",
    "sg:province":"MO",
    "sg:tags":[
        "church"
    ],
    "wof:name":"Christian Faith House Church",
    "wof:placetype":"venue"
},
  "geometry": {"coordinates":[-90.227997,38.581902],"type":"Point"}
}