{
  "type": "Feature",
  "properties": {
    "iso:country":"US",
    "sg:address":"107 N Main St",
    "sg:city":"Nevada",
    "sg:classifiers":[
        {
            "category":"Professional",
            "subcategory":"Lawyer & Legal Services",
            "type":"Services"
        }
    ],
    "sg:phone":"+1 417 667 2735",
    "sg:postcode":"64772",
    "sg:province":"MO",
    "sg:tags":[
        "attorney"
    ],
    "wof:name":"Neal Quitno",
    "wof:placetype":"venue"
},
  "geometry": {"coordinates":[-94.357978,37.839179],"type":"Point"}
}