{
  "type": "Feature",
  "properties": {
    "iso:country":"US",
    "sg:address":"15630 Co Rd 614",
    "sg:city":"Dexter",
    "sg:classifiers":[
        {
            "category":"Shopping",
            "subcategory":"Computers & Home Electronics",
            "type":"Retail Goods"
        }
    ],
    "sg:phone":"+1 573 624 6619",
    "sg:postcode":"63841",
    "sg:province":"MO",
    "sg:tags":[
        "equipment",
        "dealer"
    ],
    "wof:name":"Computer Setup",
    "wof:placetype":"venue"
},
  "geometry": {"coordinates":[-89.995926,36.785619],"type":"Point"}
}