{
  "type": "Feature",
  "properties": {
    "iso:country":"US",
    "sg:address":"5001 Mardel Ave",
    "sg:city":"Saint Louis",
    "sg:classifiers":[
        {
            "category":"Restaurant",
            "type":"Food & Drink"
        }
    ],
    "sg:phone":"+1 314 752 2739",
    "sg:postcode":"63109",
    "sg:province":"MO",
    "sg:website":"www.theworldcafestl.com/",
    "wof:name":"The World Cafe",
    "wof:placetype":"venue"
},
  "geometry": {"coordinates":[-90.276685,38.593532],"type":"Point"}
}