{
  "type": "Feature",
  "properties": {
    "iso:country":"US",
    "sg:address":"16987 Smith Ln",
    "sg:city":"Lexington",
    "sg:classifiers":[
        {
            "category":"Farming",
            "subcategory":"Livestock Farm",
            "type":"Manufacturing & Wholesale Goods"
        },
        {
            "category":"Farming",
            "subcategory":"Farm",
            "type":"Manufacturing & Wholesale Goods"
        }
    ],
    "sg:phone":"+1 660 259 2370",
    "sg:postcode":"64067",
    "sg:province":"MO",
    "sg:website":"http://www.marksmithagent.com",
    "wof:name":"Circle S Farm",
    "wof:placetype":"venue"
},
  "geometry": {"coordinates":[-93.905002,39.154762],"type":"Point"}
}