{
  "type": "Feature",
  "properties": {
    "iso:country":"US",
    "sg:address":"1340 S Kingshighway Blvd",
    "sg:city":"St Louis",
    "sg:classifiers":[
        {
            "category":"Building & Trades",
            "subcategory":"Construction",
            "type":"Services"
        },
        {
            "category":"Home & Garden",
            "subcategory":"Carpets & Floor Coverings",
            "type":"Retail Goods"
        }
    ],
    "sg:phone":"+1 314 371 3410",
    "sg:postcode":"63110",
    "sg:province":"MO",
    "sg:tags":[
        "material",
        "laying",
        "contractor"
    ],
    "wof:name":"Nanette Distributors",
    "wof:placetype":"venue"
},
  "geometry": {"coordinates":[-90.265934,38.620676],"type":"Point"}
}