{
  "type": "Feature",
  "properties": {
    "iso:country":"US",
    "sg:address":"9528 Echo Ln",
    "sg:city":"Overland",
    "sg:classifiers":[
        {
            "category":"Building & Trades",
            "subcategory":"Landscaping Services",
            "type":"Services"
        }
    ],
    "sg:phone":"+1 314 276 3881",
    "sg:postcode":"63114",
    "sg:province":"MO",
    "sg:tags":[
        "landscape",
        "contractor"
    ],
    "wof:name":"Buzzers Lawn Svc",
    "wof:placetype":"venue"
},
  "geometry": {"coordinates":[-90.370215,38.692135],"type":"Point"}
}