{
  "type": "Feature",
  "properties": {
    "iso:country":"US",
    "sg:address":"201 12th St W",
    "sg:city":"Lamar",
    "sg:classifiers":[
        {
            "category":"Arts & Performance",
            "subcategory":"Theater",
            "type":"Entertainment"
        }
    ],
    "sg:phone":"+1 417 682 2111",
    "sg:postcode":"64759",
    "sg:province":"MO",
    "sg:tags":[
        "live",
        "music"
    ],
    "wof:name":"Good Times Entertainment",
    "wof:placetype":"venue"
},
  "geometry": {"coordinates":[-94.279162,37.493386],"type":"Point"}
}