{
  "type": "Feature",
  "properties": {
    "iso:country":"US",
    "sg:address":"17601 E 231st St",
    "sg:city":"Harrisonville",
    "sg:classifiers":[
        {
            "category":"Utilities",
            "subcategory":"Electric",
            "type":"Services"
        }
    ],
    "sg:phone":"+1 816 758 4998",
    "sg:postcode":"64701",
    "sg:province":"MO",
    "sg:tags":[
        "company"
    ],
    "wof:name":"Kansas City Power & Light Co",
    "wof:placetype":"venue"
},
  "geometry": {"coordinates":[-94.390919,38.700302],"type":"Point"}
}