{
  "type": "Feature",
  "properties": {
    "iso:country":"US",
    "sg:address":"3164 N Glenstone Ave",
    "sg:city":"Springfield",
    "sg:classifiers":[
        {
            "category":"Retail",
            "subcategory":"Auto Repair",
            "type":"Services"
        }
    ],
    "sg:phone":"+1 417 833 6711",
    "sg:postcode":"65803",
    "sg:province":"MO",
    "sg:tags":[
        "repairing",
        "automobile"
    ],
    "wof:name":"D D Mobile Auto Svc",
    "wof:placetype":"venue"
},
  "geometry": {"coordinates":[-93.264912,37.257009],"type":"Point"}
}