{
  "type": "Feature",
  "properties": {
    "iso:country":"US",
    "sg:address":"113 W Main St",
    "sg:city":"Jackson",
    "sg:classifiers":[
        {
            "category":"Professional",
            "subcategory":"Engineering",
            "type":"Services"
        }
    ],
    "sg:phone":"+1 573 243 4080",
    "sg:postcode":"63755",
    "sg:province":"MO",
    "sg:tags":[
        "engineer"
    ],
    "sg:website":"www.stricklandengineering.com",
    "wof:name":"Strickland Engineering",
    "wof:placetype":"venue"
},
  "geometry": {"coordinates":[-89.668054,37.382511],"type":"Point"}
}