{
  "type": "Feature",
  "properties": {
    "iso:country":"US",
    "sg:address":"4800 NE 46 Ter",
    "sg:city":"Kansas City",
    "sg:classifiers":[
        {
            "category":"Retail",
            "subcategory":"Repair Shop",
            "type":"Services"
        }
    ],
    "sg:phone":"+1 816 792 5955",
    "sg:postcode":"64117",
    "sg:province":"MO",
    "sg:tags":[
        "lock",
        "locksmith"
    ],
    "wof:name":"Lamb Locksmith Co",
    "wof:placetype":"venue"
},
  "geometry": {"coordinates":[-94.521333,39.178155],"type":"Point"}
}