{
  "type": "Feature",
  "properties": {
    "iso:country":"US",
    "sg:address":"508 E Liberty St",
    "sg:city":"Mexico",
    "sg:classifiers":[
        {
            "category":"Shopping",
            "subcategory":"Used Merchandise",
            "type":"Retail Goods"
        }
    ],
    "sg:phone":"+1 573 581 1971",
    "sg:postcode":"65265",
    "sg:province":"MO",
    "sg:tags":[
        "shop",
        "consignment"
    ],
    "wof:name":"Seconds To Go",
    "wof:placetype":"venue"
},
  "geometry": {"coordinates":[-91.878536,39.170338],"type":"Point"}
}