{
  "type": "Feature",
  "properties": {
    "iso:country":"US",
    "sg:address":"103 W Karnes St",
    "sg:city":"Senath",
    "sg:classifiers":[
        {
            "category":"Insurance",
            "subcategory":"Hazard Insurance",
            "type":"Services"
        }
    ],
    "sg:phone":"+1 573 738 2391",
    "sg:postcode":"63876",
    "sg:province":"MO",
    "wof:name":"Steven D Morgan",
    "wof:placetype":"venue"
},
  "geometry": {"coordinates":[-90.158179,36.127637],"type":"Point"}
}