{
  "type": "Feature",
  "properties": {
    "iso:country":"US",
    "sg:address":"700 Brierwood Dr",
    "sg:city":"Moberly",
    "sg:classifiers":[
        {
            "category":"Freight",
            "type":"Transportation"
        }
    ],
    "sg:phone":"+1 660 263 7783",
    "sg:postcode":"65270",
    "sg:province":"MO",
    "sg:tags":[
        "trucking"
    ],
    "wof:name":"K P's Trucking Inc",
    "wof:placetype":"venue"
},
  "geometry": {"coordinates":[-92.464455,39.409579],"type":"Point"}
}