{
  "type": "Feature",
  "properties": {
    "iso:country":"US",
    "sg:address":"3 W 63 St",
    "sg:city":"Kansas City",
    "sg:classifiers":[
        {
            "category":"Professional",
            "subcategory":"Printing & Photocopies",
            "type":"Services"
        }
    ],
    "sg:phone":"+1 816 333 2322",
    "sg:postcode":"64113",
    "sg:province":"MO",
    "sg:tags":[
        "stationery",
        "photocopying",
        "telegraph"
    ],
    "wof:name":"Brookside Neighborhood Office",
    "wof:placetype":"venue"
},
  "geometry": {"coordinates":[-94.58944700000001,39.013846],"type":"Point"}
}