{
  "type": "Feature",
  "properties": {
    "iso:country":"US",
    "sg:address":"1210 Washington Ave",
    "sg:city":"St Louis",
    "sg:classifiers":[
        {
            "category":"Sports & Exercise",
            "subcategory":"Gym",
            "type":"Entertainment"
        }
    ],
    "sg:phone":"+1 314 621 9530",
    "sg:postcode":"63103",
    "sg:province":"MO",
    "sg:tags":[
        "personal",
        "trainer"
    ],
    "wof:name":"Elite Fitness Studio",
    "wof:placetype":"venue"
},
  "geometry": {"coordinates":[-90.19812400000001,38.631977],"type":"Point"}
}