{
  "type": "Feature",
  "properties": {
    "iso:country":"US",
    "sg:address":"32580 Walnut School Rd",
    "sg:city":"Sedalia",
    "sg:classifiers":[
        {
            "category":"Home & Garden",
            "subcategory":"Household Appliances",
            "type":"Retail Goods"
        },
        {
            "category":"Building & Trades",
            "subcategory":"Construction",
            "type":"Services"
        }
    ],
    "sg:phone":"+1 660 826 5506",
    "sg:postcode":"65301",
    "sg:province":"MO",
    "sg:tags":[
        "systems-repairing",
        "major",
        "system",
        "specialty",
        "appliances-small",
        "equipment",
        "heating",
        "contractor",
        "air conditioning"
    ],
    "wof:name":"Around The Clock Heating & Air Conditioning",
    "wof:placetype":"venue"
},
  "geometry": {"coordinates":[-93.175859,38.599953],"type":"Point"}
}