{
  "type": "Feature",
  "properties": {
    "iso:country":"US",
    "sg:address":"5205 E 23 St",
    "sg:city":"Kansas City",
    "sg:classifiers":[
        {
            "category":"Organizations",
            "subcategory":"Religious Organization",
            "type":"Services"
        }
    ],
    "sg:phone":"+1 816 241 9197",
    "sg:postcode":"64127",
    "sg:province":"MO",
    "wof:name":"Freedom Temple Ministries",
    "wof:placetype":"venue"
},
  "geometry": {"coordinates":[-94.521126,39.083226],"type":"Point"}
}