{
  "type": "Feature",
  "properties": {
    "iso:country":"US",
    "sg:address":"12411 Wornall Rd",
    "sg:city":"Kansas City",
    "sg:classifiers":[
        {
            "category":"Education",
            "subcategory":"College",
            "type":"Public Place"
        }
    ],
    "sg:phone":"+1 816 214 4922",
    "sg:postcode":"64145",
    "sg:province":"MO",
    "sg:tags":[
        "school",
        "theological"
    ],
    "sg:website":"www.metroallnations.com",
    "wof:name":"All Nations Training Ctr",
    "wof:placetype":"venue"
},
  "geometry": {"coordinates":[-94.59426499999999,38.902847],"type":"Point"}
}