{
  "type": "Feature",
  "properties": {
    "iso:country":"US",
    "sg:address":"15110 Manchester Rd",
    "sg:city":"Ballwin",
    "sg:classifiers":[
        {
            "category":"Autos & Motor Vehicles",
            "subcategory":"Automobile Sales",
            "type":"Retail Goods"
        }
    ],
    "sg:phone":"+1 636 227 5333",
    "sg:postcode":"63011",
    "sg:province":"MO",
    "sg:tags":[
        "car",
        "dealer"
    ],
    "sg:website":"www.elcochevy.com",
    "wof:name":"Elco Chevrolet Inc",
    "wof:placetype":"venue"
},
  "geometry": {"coordinates":[-90.551569,38.592802],"type":"Point"}
}