{
  "type": "Feature",
  "properties": {
    "iso:country":"US",
    "sg:address":"612 Garfield Ave",
    "sg:city":"Kansas City",
    "sg:classifiers":[
        {
            "category":"Real Estate",
            "subcategory":"Real Estate Operator",
            "type":"Services"
        }
    ],
    "sg:phone":"+1 816 221 5222",
    "sg:postcode":"64124",
    "sg:province":"MO",
    "sg:tags":[
        "building",
        "apartment"
    ],
    "wof:name":"Century Towers",
    "wof:placetype":"venue"
},
  "geometry": {"coordinates":[-94.55726300000001,39.105984],"type":"Point"}
}