{
  "type": "Feature",
  "properties": {
    "iso:country":"US",
    "sg:address":"1136 Washington Ave",
    "sg:city":"St Louis",
    "sg:classifiers":[
        {
            "category":"Shopping",
            "subcategory":"Used Merchandise",
            "type":"Retail Goods"
        }
    ],
    "sg:phone":"+1 314 540 8953",
    "sg:postcode":"63101",
    "sg:province":"MO",
    "sg:tags":[
        "vintage",
        "consignment"
    ],
    "sg:website":"evesapplevintage.com",
    "wof:name":"Eve's Apple Vintage",
    "wof:placetype":"venue"
},
  "geometry": {"coordinates":[-90.196453,38.631723],"type":"Point"}
}