{
  "type": "Feature",
  "properties": {
    "iso:country":"US",
    "sg:address":"3101 Droste Rd",
    "sg:city":"St Charles",
    "sg:classifiers":[
        {
            "category":"Health Services",
            "subcategory":"Doctor",
            "type":"Services"
        }
    ],
    "sg:phone":"+1 636 946 9009",
    "sg:postcode":"63301",
    "sg:province":"MO",
    "sg:tags":[
        "dentist"
    ],
    "wof:name":"Parkside Dentistry",
    "wof:placetype":"venue"
},
  "geometry": {"coordinates":[-90.52628,38.797889],"type":"Point"}
}