{
  "type": "Feature",
  "properties": {
    "iso:country":"US",
    "sg:address":"8417 New Hampshire Ave",
    "sg:city":"Saint Louis",
    "sg:classifiers":[
        {
            "category":"Manufacturing",
            "subcategory":"Tools & Machinery",
            "type":"Manufacturing & Wholesale Goods"
        }
    ],
    "sg:phone":"+1 314 631 9200",
    "sg:postcode":"63123",
    "sg:province":"MO",
    "sg:tags":[
        "water",
        "pump",
        "domestic",
        "mfg"
    ],
    "wof:name":"Weber Walter L Machine & Tl Co",
    "wof:placetype":"venue"
},
  "geometry": {"coordinates":[-90.328293,38.559953],"type":"Point"}
}