{
  "type": "Feature",
  "properties": {
    "iso:country":"US",
    "sg:address":"8907 Natural Bridge Rd",
    "sg:city":"Saint Louis",
    "sg:classifiers":[
        {
            "category":"Retail",
            "subcategory":"Auto Repair",
            "type":"Services"
        }
    ],
    "sg:phone":"+1 314 428 6300",
    "sg:postcode":"63121",
    "sg:province":"MO",
    "sg:tags":[
        "automotive"
    ],
    "wof:name":"Brake Headquarters",
    "wof:placetype":"venue"
},
  "geometry": {"coordinates":[-90.327519,38.716485],"type":"Point"}
}