{
  "type": "Feature",
  "properties": {
    "iso:country":"US",
    "sg:address":"1526 E Anderson St",
    "sg:city":"Mexico",
    "sg:classifiers":[
        {
            "category":"Building & Trades",
            "subcategory":"Construction",
            "type":"Services"
        }
    ],
    "sg:phone":"+1 573 581 9311",
    "sg:postcode":"65265",
    "sg:province":"MO",
    "sg:tags":[
        "contractor"
    ],
    "wof:name":"Schulte Seamless Gutters",
    "wof:placetype":"venue"
},
  "geometry": {"coordinates":[-91.867968,39.17439],"type":"Point"}
}