{
  "type": "Feature",
  "properties": {
    "iso:country":"US",
    "sg:address":"227 Main St",
    "sg:city":"Pevely",
    "sg:classifiers":[
        {
            "category":"Bars & Pubs",
            "type":"Food & Drink"
        },
        {
            "category":"Restaurant",
            "type":"Food & Drink"
        }
    ],
    "sg:phone":"+1 636 479 9749",
    "sg:postcode":"63070",
    "sg:province":"MO",
    "sg:tags":[
        "tavern",
        "grill",
        "brew"
    ],
    "wof:name":"Main Street Pub",
    "wof:placetype":"venue"
},
  "geometry": {"coordinates":[-90.39555,38.283911],"type":"Point"}
}