{
  "type": "Feature",
  "properties": {
    "iso:country":"US",
    "sg:address":"11202 Putnam St",
    "sg:city":"Independence",
    "sg:classifiers":[
        {
            "category":"Building & Trades",
            "subcategory":"Construction",
            "type":"Services"
        }
    ],
    "sg:phone":"+1 816 836 3568",
    "sg:postcode":"64054",
    "sg:province":"MO",
    "sg:tags":[
        "hanging",
        "contractor"
    ],
    "wof:name":"K M Onka Painting",
    "wof:placetype":"venue"
},
  "geometry": {"coordinates":[-94.443192,39.118756],"type":"Point"}
}