{
  "type": "Feature",
  "properties": {
    "addr:full":"1319 Caulks Hill Rd St Charles MO 63304",
    "addr:housenumber":"1319",
    "addr:postcode":"63304",
    "addr:street":"Caulks Hill Rd St Charles",
    "iso:country":"US",
    "sg:address":"1319 Caulks Hill Rd",
    "sg:city":"St Charles",
    "sg:classifiers":[
        {
            "category":"Health Services",
            "subcategory":"Doctor",
            "type":"Services"
        }
    ],
    "sg:phone":"+1 636 441 3430",
    "sg:postcode":"63304",
    "sg:province":"MO",
    "sg:tags":[
        "dentist"
    ],
    "wof:name":"Caulks Hill Dental Inc",
    "wof:placetype":"venue"
},
  "geometry": {"coordinates":[-90.579054,38.736489],"type":"Point"}
}