{
  "type": "Feature",
  "properties": {
    "iso:country":"US",
    "sg:address":"302 W 13th St",
    "sg:city":"Sedalia",
    "sg:classifiers":[
        {
            "category":"Freight",
            "type":"Transportation"
        }
    ],
    "sg:phone":"+1 660 829 1269",
    "sg:postcode":"65301",
    "sg:province":"MO",
    "sg:tags":[
        "mobile",
        "home"
    ],
    "wof:name":"Spencer's Transport",
    "wof:placetype":"venue"
},
  "geometry": {"coordinates":[-93.231426,38.700404],"type":"Point"}
}