{
  "type": "Feature",
  "properties": {
    "iso:country":"US",
    "sg:address":"5400 Knollwood Pkwy Ct",
    "sg:city":"Hazelwood",
    "sg:classifiers":[
        {
            "category":"Professional",
            "subcategory":"Computer Services",
            "type":"Services"
        }
    ],
    "sg:phone":"+1 314 731 7748",
    "sg:postcode":"63042",
    "sg:province":"MO",
    "sg:tags":[
        "related"
    ],
    "wof:name":"REB Enterprises",
    "wof:placetype":"venue"
},
  "geometry": {"coordinates":[-90.39112799999999,38.782136],"type":"Point"}
}