{
  "type": "Feature",
  "properties": {
    "iso:country":"US",
    "sg:address":"1405 E Hines St",
    "sg:city":"Republic",
    "sg:classifiers":[
        {
            "category":"Real Estate",
            "subcategory":"Real Estate Operator",
            "type":"Services"
        }
    ],
    "sg:phone":"+1 417 732 5606",
    "sg:postcode":"65738",
    "sg:province":"MO",
    "sg:tags":[
        "apartment"
    ],
    "wof:name":"Republic III Apartments",
    "wof:placetype":"venue"
},
  "geometry": {"coordinates":[-93.459265,37.125544],"type":"Point"}
}