{
  "type": "Feature",
  "properties": {
    "iso:country":"US",
    "sg:address":"16150 SE 95th Rd",
    "sg:city":"Gower",
    "sg:classifiers":[
        {
            "category":"Farming",
            "subcategory":"Livestock Farm",
            "type":"Manufacturing & Wholesale Goods"
        }
    ],
    "sg:phone":"+1 816 424 6629",
    "sg:postcode":"64454",
    "sg:province":"MO",
    "sg:tags":[
        "feeding"
    ],
    "wof:name":"Terry Batchelder",
    "wof:placetype":"venue"
},
  "geometry": {"coordinates":[-94.69441,39.572274],"type":"Point"}
}