{
  "type": "Feature",
  "properties": {
    "iso:country":"US",
    "sg:address":"3330 S Lakeside Ave",
    "sg:city":"Springfield",
    "sg:classifiers":[
        {
            "category":"Building & Trades",
            "subcategory":"Construction",
            "type":"Services"
        }
    ],
    "sg:phone":"+1 417 890 6047",
    "sg:postcode":"65804",
    "sg:province":"MO",
    "sg:tags":[
        "contractor",
        "painting",
        "hanging"
    ],
    "wof:name":"Young Painting Co Inc",
    "wof:placetype":"venue"
},
  "geometry": {"coordinates":[-93.23706,37.152216],"type":"Point"}
}