{
  "type": "Feature",
  "properties": {
    "iso:country":"US",
    "sg:address":"6157 Minerva Ave",
    "sg:city":"St Louis",
    "sg:classifiers":[
        {
            "category":"Organizations",
            "subcategory":"Religious Organization",
            "type":"Services"
        }
    ],
    "sg:phone":"+1 314 383 7977",
    "sg:postcode":"63133",
    "sg:province":"MO",
    "sg:tags":[
        "church"
    ],
    "wof:name":"Ebenezer Baptist Church",
    "wof:placetype":"venue"
},
  "geometry": {"coordinates":[-90.290463,38.673019],"type":"Point"}
}