{
  "type": "Feature",
  "properties": {
    "iso:country":"US",
    "sg:address":"343 S Kirkwood Rd",
    "sg:city":"St Louis",
    "sg:classifiers":[
        {
            "category":"Restaurant",
            "type":"Food & Drink"
        }
    ],
    "sg:phone":"+1 314 822 8070",
    "sg:postcode":"63122",
    "sg:province":"MO",
    "sg:tags":[
        "eating"
    ],
    "wof:name":"Quiznos Subs",
    "wof:placetype":"venue"
},
  "geometry": {"coordinates":[-90.40654000000001,38.57652],"type":"Point"}
}