{
  "type": "Feature",
  "properties": {
    "iso:country":"US",
    "sg:address":"23 Surrey Dr",
    "sg:city":"Camdenton",
    "sg:classifiers":[
        {
            "category":"Real Estate",
            "subcategory":"Surveying",
            "type":"Services"
        }
    ],
    "sg:phone":"+1 573 346 2557",
    "sg:postcode":"65020",
    "sg:province":"MO",
    "sg:tags":[
        "surveyor"
    ],
    "wof:name":"Snelling Whitworth & Hasty Inc",
    "wof:placetype":"venue"
},
  "geometry": {"coordinates":[-92.766445,38.065792],"type":"Point"}
}