{
  "type": "Feature",
  "properties": {
    "iso:country":"US",
    "sg:address":"945 E Hwy 22",
    "sg:city":"Centralia",
    "sg:classifiers":[
        {
            "category":"Sports & Exercise",
            "subcategory":"Gym",
            "type":"Entertainment"
        }
    ],
    "sg:phone":"+1 573 682 9810",
    "sg:postcode":"65240",
    "sg:province":"MO",
    "sg:tags":[
        "fitness",
        "physical",
        "facility"
    ],
    "wof:name":"Apex Fitness Inc",
    "wof:placetype":"venue"
},
  "geometry": {"coordinates":[-92.128052,39.217277],"type":"Point"}
}