{
  "type": "Feature",
  "properties": {
    "iso:country":"US",
    "sg:address":"39 Fox Valley Center",
    "sg:city":"Arnold",
    "sg:classifiers":[
        {
            "category":"Government",
            "subcategory":"Office",
            "type":"Public Place"
        }
    ],
    "sg:phone":"+1 636 287 1083",
    "sg:postcode":"63010",
    "sg:province":"MO",
    "sg:tags":[
        "federal",
        "security"
    ],
    "wof:name":"US Govt Us Army Arnold Sta",
    "wof:placetype":"venue"
},
  "geometry": {"coordinates":[-90.37011699999999,38.447046],"type":"Point"}
}