{
  "type": "Feature",
  "properties": {
    "addr:full":"2304 W Broadway Blvd Sedalia MO 65301",
    "addr:housenumber":"2304",
    "addr:postcode":"65301",
    "addr:street":"W Broadway Blvd",
    "iso:country":"US",
    "sg:address":"2304 W Broadway Blvd",
    "sg:city":"Sedalia",
    "sg:classifiers":[
        {
            "category":"Professional",
            "subcategory":"Advertising",
            "type":"Services"
        }
    ],
    "sg:phone":"+1 660 826 0700",
    "sg:postcode":"65301",
    "sg:province":"MO",
    "sg:tags":[
        "mailing",
        "shipping"
    ],
    "wof:name":"UPS Store",
    "wof:placetype":"venue"
},
  "geometry": {"coordinates":[-93.25530000000001,38.705259],"type":"Point"}
}