{
  "type": "Feature",
  "properties": {
    "iso:country":"US",
    "sg:address":"18118 Chesterfield Airport Rd",
    "sg:city":"Chesterfield",
    "sg:classifiers":[
        {
            "category":"Airline",
            "type":"Transportation"
        }
    ],
    "sg:phone":"+1 636 733 3393",
    "sg:postcode":"63005",
    "sg:province":"MO",
    "sg:tags":[
        "air",
        "ambulance"
    ],
    "wof:name":"Lifenet",
    "wof:placetype":"venue"
},
  "geometry": {"coordinates":[-90.640017,38.669822],"type":"Point"}
}