{
  "type": "Feature",
  "properties": {
    "iso:country":"US",
    "sg:address":"34 N Brentwood Blvd",
    "sg:city":"St Louis",
    "sg:classifiers":[
        {
            "category":"Professional",
            "subcategory":"Lawyer & Legal Services",
            "type":"Services"
        }
    ],
    "sg:phone":"+1 314 721 5211",
    "sg:postcode":"63105",
    "sg:province":"MO",
    "sg:tags":[
        "attorney"
    ],
    "wof:name":"Kwadwo Armano",
    "wof:placetype":"venue"
},
  "geometry": {"coordinates":[-90.341204,38.651401],"type":"Point"}
}