{
  "type": "Feature",
  "properties": {
    "iso:country":"US",
    "sg:address":"1600 Bird Rd Apt 112",
    "sg:city":"Branson",
    "sg:classifiers":[
        {
            "category":"Shopping",
            "subcategory":"Jewelry",
            "type":"Retail Goods"
        }
    ],
    "sg:phone":"+1 417 334 6364",
    "sg:postcode":"65616",
    "sg:province":"MO",
    "sg:tags":[
        "precious",
        "semi-precious",
        "stone"
    ],
    "wof:name":"The Jewelry Studio",
    "wof:placetype":"venue"
},
  "geometry": {"coordinates":[-93.243557,36.671882],"type":"Point"}
}