{
  "type": "Feature",
  "properties": {
    "iso:country":"US",
    "sg:address":"131 E Washington St",
    "sg:city":"Kearney",
    "sg:classifiers":[
        {
            "category":"Restaurant",
            "type":"Food & Drink"
        }
    ],
    "sg:phone":"+1 816 903 5521",
    "sg:postcode":"64060",
    "sg:province":"MO",
    "sg:tags":[
        "management",
        "eating"
    ],
    "wof:name":"Integrity Management Company",
    "wof:placetype":"venue"
},
  "geometry": {"coordinates":[-94.361876,39.372944],"type":"Point"}
}