{
  "type": "Feature",
  "properties": {
    "iso:country":"US",
    "sg:address":"12519 Co Rd 637",
    "sg:city":"Dexter",
    "sg:phone":"+1 573 624 7001",
    "sg:postcode":"63841",
    "sg:province":"MO",
    "sg:tags":[
        "farm",
        "corn"
    ],
    "wof:name":"Boyers Farm",
    "wof:placetype":"venue"
},
  "geometry": {"coordinates":[-90.00251799999999,36.79342],"type":"Point"}
}