{
  "type": "Feature",
  "properties": {
    "iso:country":"US",
    "sg:address":"174 Tandy Rd",
    "sg:city":"Seymour",
    "sg:classifiers":[
        {
            "category":"Farming",
            "subcategory":"Livestock Farm",
            "type":"Manufacturing & Wholesale Goods"
        }
    ],
    "sg:phone":"+1 417 767 4367",
    "sg:postcode":"65746",
    "sg:province":"MO",
    "sg:tags":[
        "beef",
        "equine",
        "feedlot",
        "cattle"
    ],
    "wof:name":"Pat Henry",
    "wof:placetype":"venue"
},
  "geometry": {"coordinates":[-92.888739,37.115551],"type":"Point"}
}