{
  "type": "Feature",
  "properties": {
    "iso:country":"US",
    "sg:address":"707 W Martha St",
    "sg:city":"Kirksville",
    "sg:classifiers":[
        {
            "category":"Social Services",
            "subcategory":"Child Care",
            "type":"Services"
        }
    ],
    "sg:phone":"+1 660 665 5747",
    "sg:postcode":"63501",
    "sg:province":"MO",
    "sg:tags":[
        "day"
    ],
    "wof:name":"Maizes Family Day Care Home",
    "wof:placetype":"venue"
},
  "geometry": {"coordinates":[-92.590794,40.200198],"type":"Point"}
}