{
  "type": "Feature",
  "properties": {
    "iso:country":"US",
    "sg:address":"10920 Old US Hwy 54",
    "sg:city":"Holts Summit",
    "sg:classifiers":[
        {
            "category":"Retail",
            "subcategory":"Funeral Services",
            "type":"Services"
        }
    ],
    "sg:phone":"+1 573 896 5572",
    "sg:postcode":"65043",
    "sg:province":"MO",
    "sg:tags":[
        "director"
    ],
    "wof:name":"Debo Funeral Home",
    "wof:placetype":"venue"
},
  "geometry": {"coordinates":[-92.109465,38.664961],"type":"Point"}
}