{
  "type": "Feature",
  "properties": {
    "iso:country":"US",
    "sg:address":"16 Lockwood Rd",
    "sg:city":"Eldon",
    "sg:classifiers":[
        {
            "category":"Professional",
            "subcategory":"Art Services",
            "type":"Services"
        }
    ],
    "sg:phone":"+1 636 462 5547",
    "sg:postcode":"65026",
    "sg:province":"MO",
    "sg:tags":[
        "photographer"
    ],
    "wof:name":"Fague Photography & Glamour",
    "wof:placetype":"venue"
},
  "geometry": {"coordinates":[-92.68472300000001,38.227943],"type":"Point"}
}