{
  "type": "Feature",
  "properties": {
    "iso:country":"US",
    "sg:address":"4444 Belleview Ave",
    "sg:city":"Kansas City",
    "sg:classifiers":[
        {
            "category":"Wholesale",
            "subcategory":"Home Furnishings",
            "type":"Manufacturing & Wholesale Goods"
        }
    ],
    "sg:phone":"+1 816 756 0007",
    "sg:postcode":"64111",
    "sg:province":"MO",
    "sg:tags":[
        "fabric"
    ],
    "wof:name":"J H S Associates",
    "wof:placetype":"venue"
},
  "geometry": {"coordinates":[-94.59836799999999,39.046993],"type":"Point"}
}