{
  "type": "Feature",
  "properties": {
    "iso:country":"US",
    "sg:address":"101 E Main St",
    "sg:city":"Willow Springs",
    "sg:classifiers":[
        {
            "category":"Shopping",
            "subcategory":"Pharmacy",
            "type":"Retail Goods"
        }
    ],
    "sg:phone":"+1 417 469 3005",
    "sg:postcode":"65793",
    "sg:province":"MO",
    "sg:website":"www.fergusondrug.com",
    "wof:name":"Ferguson Drug Co",
    "wof:placetype":"venue"
},
  "geometry": {"coordinates":[-91.96984500000001,36.992297],"type":"Point"}
}