{
  "type": "Feature",
  "properties": {
    "iso:country":"US",
    "sg:address":"801 S Florissant Rd",
    "sg:city":"St Louis",
    "sg:classifiers":[
        {
            "category":"Organizations",
            "subcategory":"Religious Organization",
            "type":"Services"
        }
    ],
    "sg:phone":"+1 314 521 4723",
    "sg:postcode":"63135",
    "sg:province":"MO",
    "sg:tags":[
        "church"
    ],
    "wof:name":"Abundant Life Fellowship Inc",
    "wof:placetype":"venue"
},
  "geometry": {"coordinates":[-90.301682,38.734645],"type":"Point"}
}