{
  "type": "Feature",
  "properties": {
    "iso:country":"US",
    "sg:address":"300 S Jefferson Ave Suite 301",
    "sg:city":"Springfield",
    "sg:classifiers":[
        {
            "category":"Professional",
            "subcategory":"Engineering",
            "type":"Services"
        },
        {
            "category":"Real Estate",
            "subcategory":"Architect",
            "type":"Services"
        }
    ],
    "sg:phone":"+1 417 869 0719",
    "sg:postcode":"65806",
    "sg:province":"MO",
    "sg:tags":[
        "engineer"
    ],
    "sg:website":"http://www.ghnae.com",
    "wof:name":"GHN-Gaskin Hill Norcross",
    "wof:placetype":"venue"
},
  "geometry": {"coordinates":[-93.28993199999999,37.208141],"type":"Point"}
}