{
  "type": "Feature",
  "properties": {
    "iso:country":"US",
    "sg:address":"8411 State Rd CC",
    "sg:city":"Steedman",
    "sg:classifiers":[
        {
            "category":"Building & Trades",
            "subcategory":"Construction",
            "type":"Services"
        }
    ],
    "sg:phone":"+1 573 676 5773",
    "sg:postcode":"65077",
    "sg:province":"MO",
    "sg:tags":[
        "contractor"
    ],
    "wof:name":"Powers Construction",
    "wof:placetype":"venue"
},
  "geometry": {"coordinates":[-91.816816,38.751664],"type":"Point"}
}