{
  "type": "Feature",
  "properties": {
    "iso:country":"US",
    "sg:address":"16452 Laurel Rd",
    "sg:city":"Eldridge",
    "sg:classifiers":[
        {
            "category":"Freight",
            "type":"Transportation"
        }
    ],
    "sg:phone":"+1 417 426 5248",
    "sg:postcode":"65463",
    "sg:province":"MO",
    "sg:tags":[
        "operator",
        "local",
        "trucking"
    ],
    "wof:name":"Shawn Ripley",
    "wof:placetype":"venue"
},
  "geometry": {"coordinates":[-92.737714,37.861428],"type":"Point"}
}