{
  "type": "Feature",
  "properties": {
    "iso:country":"US",
    "sg:address":"4610 Yeager Rd",
    "sg:city":"Hillsboro",
    "sg:classifiers":[
        {
            "category":"Retail",
            "subcategory":"Repair Shop",
            "type":"Services"
        }
    ],
    "sg:phone":"+1 636 797 4300",
    "sg:postcode":"63050",
    "sg:province":"MO",
    "sg:tags":[
        "equipment",
        "hydraulic"
    ],
    "wof:name":"Don's Diesel Svc",
    "wof:placetype":"venue"
},
  "geometry": {"coordinates":[-90.56423700000001,38.226873],"type":"Point"}
}