{
  "type": "Feature",
  "properties": {
    "iso:country":"US",
    "sg:address":"300 Barbs Ln",
    "sg:city":"Forsyth",
    "sg:classifiers":[
        {
            "category":"Building & Trades",
            "subcategory":"Construction",
            "type":"Services"
        }
    ],
    "sg:phone":"+1 417 546 2785",
    "sg:postcode":"65653",
    "sg:province":"MO",
    "sg:tags":[
        "contractor"
    ],
    "wof:name":"Bull Shoals Drywall & Plasteri",
    "wof:placetype":"venue"
},
  "geometry": {"coordinates":[-93.08474,36.687156],"type":"Point"}
}