{
  "type": "Feature",
  "properties": {
    "iso:country":"US",
    "sg:address":"415 N Rollins St",
    "sg:city":"Centralia",
    "sg:classifiers":[
        {
            "category":"Autos & Motor Vehicles",
            "subcategory":"Auto Supplies",
            "type":"Retail Goods"
        },
        {
            "category":"Retail",
            "subcategory":"Auto Repair",
            "type":"Services"
        }
    ],
    "sg:phone":"+1 573 682 5891",
    "sg:postcode":"65240",
    "sg:province":"MO",
    "sg:tags":[
        "tire"
    ],
    "sg:website":"http://www.denniswhitaker.com",
    "wof:name":"D & D Tire & Auto",
    "wof:placetype":"venue"
},
  "geometry": {"coordinates":[-92.136715,39.215008],"type":"Point"}
}