{
  "type": "Feature",
  "properties": {
    "iso:country":"US",
    "sg:address":"239 Chasselle Ln",
    "sg:city":"Saint Louis",
    "sg:classifiers":[
        {
            "category":"Banks & Credit Unions",
            "subcategory":"Financial Services",
            "type":"Services"
        }
    ],
    "sg:phone":"+1 314 434 5595",
    "sg:postcode":"63141",
    "sg:province":"MO",
    "sg:tags":[
        "trust",
        "nonprofit",
        "management"
    ],
    "wof:name":"Hergert Gospel Trust",
    "wof:placetype":"venue"
},
  "geometry": {"coordinates":[-90.474917,38.66154],"type":"Point"}
}