{
  "type": "Feature",
  "properties": {
    "iso:country":"US",
    "sg:address":"111 N Main St",
    "sg:city":"Poplar Bluff",
    "sg:classifiers":[
        {
            "category":"Real Estate",
            "subcategory":"Real Estate Services",
            "type":"Services"
        }
    ],
    "sg:phone":"+1 573 686 1495",
    "sg:postcode":"63901",
    "sg:province":"MO",
    "sg:tags":[
        "company",
        "title"
    ],
    "wof:name":"Butler County Abstract Title",
    "wof:placetype":"venue"
},
  "geometry": {"coordinates":[-90.392883,36.756885],"type":"Point"}
}