{
  "type": "Feature",
  "properties": {
    "iso:country":"US",
    "sg:address":"1623 Ville Maura Ln",
    "sg:city":"Hazelwood",
    "sg:classifiers":[
        {
            "category":"Building & Trades",
            "subcategory":"Cleaning & Sanitation",
            "type":"Services"
        }
    ],
    "sg:phone":"+1 314 291 7139",
    "sg:postcode":"63042",
    "sg:province":"MO",
    "sg:tags":[
        "maintenance"
    ],
    "wof:name":"Bobs Cleaning",
    "wof:placetype":"venue"
},
  "geometry": {"coordinates":[-90.39872200000001,38.782977],"type":"Point"}
}