{
  "type": "Feature",
  "properties": {
    "iso:country":"US",
    "sg:address":"201 E Main St",
    "sg:city":"Union",
    "sg:classifiers":[
        {
            "category":"Restaurant",
            "type":"Food & Drink"
        }
    ],
    "sg:phone":"+1 636 584 7832",
    "sg:postcode":"63084",
    "sg:province":"MO",
    "sg:tags":[
        "grill",
        "style",
        "bar",
        "family",
        "house",
        "steak"
    ],
    "sg:website":"http://www.bugsyaonmainst.com",
    "wof:name":"Bugsy's Restaurant & Bar",
    "wof:placetype":"venue"
},
  "geometry": {"coordinates":[-91.007347,38.445492],"type":"Point"}
}