{
  "type": "Feature",
  "properties": {
    "addr:full":"11806 W Florissant Ave Florissant MO 63033",
    "addr:housenumber":"11806",
    "addr:postcode":"63033",
    "addr:street":"W Florissant Ave",
    "iso:country":"US",
    "sg:address":"11806 W Florissant Ave",
    "sg:city":"Florissant",
    "sg:classifiers":[
        {
            "category":"Insurance",
            "subcategory":"Insurance Agent",
            "type":"Services"
        }
    ],
    "sg:phone":"+1 314 921 0300",
    "sg:postcode":"63033",
    "sg:province":"MO",
    "wof:name":"Farmers Insurance",
    "wof:placetype":"venue"
},
  "geometry": {"coordinates":[-90.280907,38.77878],"type":"Point"}
}