{
  "type": "Feature",
  "properties": {
    "iso:country":"US",
    "sg:address":"909 Cherry St",
    "sg:city":"Columbia",
    "sg:classifiers":[
        {
            "category":"Shopping",
            "subcategory":"Used Merchandise",
            "type":"Retail Goods"
        }
    ],
    "sg:phone":"+1 573 443 5263",
    "sg:postcode":"65201",
    "sg:province":"MO",
    "wof:name":"Zixen Enterprises",
    "wof:placetype":"venue"
},
  "geometry": {"coordinates":[-92.326526,38.950536],"type":"Point"}
}