{
  "type": "Feature",
  "properties": {
    "iso:country":"US",
    "sg:address":"6501 Wydown Blvd",
    "sg:city":"Saint Louis",
    "sg:classifiers":[
        {
            "category":"Education",
            "subcategory":"Preschool",
            "type":"Public Place"
        },
        {
            "category":"Education",
            "subcategory":"School",
            "type":"Public Place"
        }
    ],
    "sg:phone":"+1 314 721 5060",
    "sg:postcode":"63105",
    "sg:province":"MO",
    "sg:tags":[
        "elementary"
    ],
    "sg:website":"www.firstcongregational.org",
    "wof:name":"First Congregational Church of St Louis UCC",
    "wof:placetype":"venue"
},
  "geometry": {"coordinates":[-90.311302,38.642799],"type":"Point"}
}