{
  "type": "Feature",
  "properties": {
    "iso:country":"US",
    "sg:address":"400 NW Barry Rd",
    "sg:city":"Kansas City",
    "sg:classifiers":[
        {
            "category":"Health Services",
            "subcategory":"Optometrist",
            "type":"Services"
        }
    ],
    "sg:phone":"+1 816 468 7733",
    "sg:postcode":"64155",
    "sg:province":"MO",
    "wof:name":"Dr Drake and Associates",
    "wof:placetype":"venue"
},
  "geometry": {"coordinates":[-94.589716,39.246488],"type":"Point"}
}