{
  "type": "Feature",
  "properties": {
    "iso:country":"US",
    "sg:address":"394 Glaize Holler Rd",
    "sg:city":"Brumley",
    "sg:classifiers":[
        {
            "category":"Retail",
            "subcategory":"Repair Shop",
            "type":"Services"
        }
    ],
    "sg:phone":"+1 573 369 2610",
    "sg:postcode":"65017",
    "sg:province":"MO",
    "sg:tags":[
        "farm",
        "corn",
        "taxidermist"
    ],
    "wof:name":"Jim's Taxidermy",
    "wof:placetype":"venue"
},
  "geometry": {"coordinates":[-92.524108,38.074415],"type":"Point"}
}