{
  "type": "Feature",
  "properties": {
    "iso:country":"US",
    "sg:address":"209 S Main St",
    "sg:city":"Liberal",
    "sg:classifiers":[
        {
            "category":"Government",
            "subcategory":"Office",
            "type":"Public Place"
        }
    ],
    "sg:phone":"+1 417 843 2135",
    "sg:postcode":"64762",
    "sg:province":"MO",
    "sg:tags":[
        "township",
        "government-city",
        "village"
    ],
    "wof:name":"City Of Liberal",
    "wof:placetype":"venue"
},
  "geometry": {"coordinates":[-94.520199,37.556014],"type":"Point"}
}