{
  "type": "Feature",
  "properties": {
    "iso:country":"US",
    "sg:address":"5621 Delmar Blvd",
    "sg:city":"Saint Louis",
    "sg:classifiers":[
        {
            "category":"Social Services",
            "subcategory":"Job Training",
            "type":"Services"
        }
    ],
    "sg:phone":"+1 314 383 1733",
    "sg:postcode":"63112",
    "sg:province":"MO",
    "sg:tags":[
        "care",
        "center",
        "day"
    ],
    "wof:name":"The Unted Chrch Nghbrhood Hses",
    "wof:placetype":"venue"
},
  "geometry": {"coordinates":[-90.284161,38.653923],"type":"Point"}
}