{
  "type": "Feature",
  "properties": {
    "iso:country":"US",
    "sg:address":"5049 Wornall Rd",
    "sg:city":"Kansas City",
    "sg:classifiers":[
        {
            "category":"Organizations",
            "subcategory":"Community Association",
            "type":"Services"
        }
    ],
    "sg:phone":"+1 816 931 8430",
    "sg:postcode":"64112",
    "sg:province":"MO",
    "sg:tags":[
        "owner",
        "condominium"
    ],
    "wof:name":"Walnuts",
    "wof:placetype":"venue"
},
  "geometry": {"coordinates":[-94.59183400000001,39.036034],"type":"Point"}
}