{
  "type": "Feature",
  "properties": {
    "iso:country":"US",
    "sg:address":"558 State Hwy 224",
    "sg:city":"Wellington",
    "sg:classifiers":[
        {
            "category":"Banks & Credit Unions",
            "subcategory":"Bank",
            "type":"Services"
        }
    ],
    "sg:phone":"+1 816 934 2641",
    "sg:postcode":"64097",
    "sg:province":"MO",
    "wof:name":"B & L Bank",
    "wof:placetype":"venue"
},
  "geometry": {"coordinates":[-94.028114,39.131768],"type":"Point"}
}