{
  "type": "Feature",
  "properties": {
    "iso:country":"US",
    "sg:address":"15566 Manchester Rd",
    "sg:city":"Ballwin",
    "sg:classifiers":[
        {
            "category":"Shopping",
            "type":"Retail Goods"
        }
    ],
    "sg:phone":"+1 636 227 3944",
    "sg:postcode":"63011",
    "sg:province":"MO",
    "sg:tags":[
        "chemical",
        "equipment",
        "swimming",
        "pool",
        "supply"
    ],
    "wof:name":"Sunset Aquatech Pools",
    "wof:placetype":"venue"
},
  "geometry": {"coordinates":[-90.567621,38.592836],"type":"Point"}
}