{
  "type": "Feature",
  "properties": {
    "iso:country":"US",
    "sg:address":"9440 County Road 410",
    "sg:city":"Ellsinore",
    "sg:classifiers":[
        {
            "category":"Shopping",
            "subcategory":"Gifts & Souvenirs",
            "type":"Retail Goods"
        }
    ],
    "sg:phone":"+1 573 998 2066",
    "sg:postcode":"63937",
    "sg:province":"MO",
    "sg:tags":[
        "shop"
    ],
    "wof:name":"Country Charm Gifts",
    "wof:placetype":"venue"
},
  "geometry": {"coordinates":[-90.63964,36.910009],"type":"Point"}
}