{
  "type": "Feature",
  "properties": {
    "iso:country":"US",
    "sg:address":"6201 Main St",
    "sg:city":"Grandview",
    "sg:classifiers":[
        {
            "category":"Personal",
            "subcategory":"Beauty Salon",
            "type":"Services"
        }
    ],
    "sg:phone":"+1 816 761 1115",
    "sg:postcode":"64030",
    "sg:province":"MO",
    "sg:tags":[
        "shop"
    ],
    "wof:name":"All About Braids & Weeves",
    "wof:placetype":"venue"
},
  "geometry": {"coordinates":[-94.519745,38.888414],"type":"Point"}
}