{
  "type": "Feature",
  "properties": {
    "iso:country":"US",
    "sg:address":"5500 Woodland Ave",
    "sg:city":"Kansas City",
    "sg:classifiers":[
        {
            "category":"Social Services",
            "subcategory":"Child Care",
            "type":"Services"
        }
    ],
    "sg:phone":"+1 816 363 0536",
    "sg:postcode":"64110",
    "sg:province":"MO",
    "sg:tags":[
        "day"
    ],
    "wof:name":"Luv Does Matter Resource",
    "wof:placetype":"venue"
},
  "geometry": {"coordinates":[-94.564607,39.025044],"type":"Point"}
}