{
  "type": "Feature",
  "properties": {
    "iso:country":"US",
    "sg:address":"3222 Oklahoma Ave",
    "sg:city":"Trenton",
    "sg:classifiers":[
        {
            "category":"Social Services",
            "subcategory":"Child Care",
            "type":"Services"
        }
    ],
    "sg:phone":"+1 660 359 5778",
    "sg:postcode":"64683",
    "sg:province":"MO",
    "sg:tags":[
        "state",
        "day",
        "licensed"
    ],
    "wof:name":"Pamela Norris",
    "wof:placetype":"venue"
},
  "geometry": {"coordinates":[-93.60415,40.100959],"type":"Point"}
}