{
  "type": "Feature",
  "properties": {
    "iso:country":"US",
    "sg:address":"5960 US Hwy 60",
    "sg:city":"Fordland",
    "sg:classifiers":[
        {
            "category":"Organizations",
            "subcategory":"Religious Organization",
            "type":"Services"
        }
    ],
    "sg:phone":"+1 417 767 4456",
    "sg:postcode":"65652",
    "sg:province":"MO",
    "wof:name":"Morning Star Assmbly God Chrch",
    "wof:placetype":"venue"
},
  "geometry": {"coordinates":[-92.964862,37.137914],"type":"Point"}
}