{
  "type": "Feature",
  "properties": {
    "iso:country":"US",
    "sg:address":"424 NW 1601 Rd",
    "sg:city":"Urich",
    "sg:classifiers":[
        {
            "category":"Farming",
            "subcategory":"Livestock Farm",
            "type":"Manufacturing & Wholesale Goods"
        }
    ],
    "sg:phone":"+1 660 638 4559",
    "sg:postcode":"64788",
    "sg:province":"MO",
    "sg:tags":[
        "beef",
        "feedlot",
        "cattle"
    ],
    "wof:name":"Ron Nadler",
    "wof:placetype":"venue"
},
  "geometry": {"coordinates":[-94.04635500000001,38.434709],"type":"Point"}
}