{
  "type": "Feature",
  "properties": {
    "iso:country":"US",
    "sg:address":"1402 S Elliott Ave",
    "sg:city":"Aurora",
    "sg:classifiers":[
        {
            "category":"Professional",
            "subcategory":"Business Services",
            "type":"Services"
        }
    ],
    "sg:phone":"+1 417 678 7751",
    "sg:postcode":"65605",
    "sg:province":"MO",
    "wof:name":"Aurora Closing Company",
    "wof:placetype":"venue"
},
  "geometry": {"coordinates":[-93.718146,36.960586],"type":"Point"}
}