{
  "type": "Feature",
  "properties": {
    "iso:country":"US",
    "sg:address":"19318 Iris Rd",
    "sg:city":"Neosho",
    "sg:classifiers":[
        {
            "category":"Building & Trades",
            "subcategory":"Construction",
            "type":"Services"
        }
    ],
    "sg:phone":"+1 417 472 3072",
    "sg:postcode":"64850",
    "sg:province":"MO",
    "sg:tags":[
        "house"
    ],
    "wof:name":"Home-Co Improvements",
    "wof:placetype":"venue"
},
  "geometry": {"coordinates":[-94.30036800000001,36.926838],"type":"Point"}
}