{
  "type": "Feature",
  "properties": {
    "iso:country":"US",
    "sg:address":"2019 N Commercial St",
    "sg:city":"Harrisonville",
    "sg:classifiers":[
        {
            "category":"Shopping",
            "subcategory":"Florist",
            "type":"Retail Goods"
        }
    ],
    "sg:phone":"+1 816 380 2522",
    "sg:postcode":"64701",
    "sg:province":"MO",
    "wof:name":"Garden Gate Floral & Gift",
    "wof:placetype":"venue"
},
  "geometry": {"coordinates":[-94.36572099999999,38.663134],"type":"Point"}
}