{
  "type": "Feature",
  "properties": {
    "iso:country":"US",
    "sg:address":"505 Blue Ave",
    "sg:city":"Belton",
    "sg:classifiers":[
        {
            "category":"Organizations",
            "subcategory":"Community Association",
            "type":"Services"
        }
    ],
    "sg:phone":"+1 816 331 1936",
    "sg:postcode":"64012",
    "sg:province":"MO",
    "wof:name":"Belton Mt Pleasant Emergency",
    "wof:placetype":"venue"
},
  "geometry": {"coordinates":[-94.52528599999999,38.810035],"type":"Point"}
}