{
  "type": "Feature",
  "properties": {
    "iso:country":"US",
    "sg:address":"50 Hoelting Farm Ln",
    "sg:city":"Old Monroe",
    "sg:phone":"+1 636 665 5478",
    "sg:postcode":"63369",
    "sg:province":"MO",
    "sg:tags":[
        "farm",
        "corn"
    ],
    "wof:name":"Ralph Vogelcesang",
    "wof:placetype":"venue"
},
  "geometry": {"coordinates":[-90.79348400000001,38.929875],"type":"Point"}
}