{
  "type": "Feature",
  "properties": {
    "iso:country":"US",
    "sg:address":"18 Southmoor Dr",
    "sg:city":"Clayton",
    "sg:classifiers":[
        {
            "category":"Health Services",
            "subcategory":"Doctor",
            "type":"Services"
        }
    ],
    "sg:phone":"+1 314 862 0210",
    "sg:postcode":"63105",
    "sg:province":"MO",
    "wof:name":"Patterson G Alexander MD",
    "wof:placetype":"venue"
},
  "geometry": {"coordinates":[-90.318001,38.640598],"type":"Point"}
}