{
  "type": "Feature",
  "properties": {
    "iso:country":"US",
    "sg:address":"552 E Hackberry Blvd",
    "sg:city":"Columbia",
    "sg:classifiers":[
        {
            "category":"Insurance",
            "subcategory":"Hazard Insurance",
            "type":"Services"
        },
        {
            "category":"Retail",
            "subcategory":"Repair Shop",
            "type":"Services"
        },
        {
            "category":"Professional",
            "subcategory":"Detective & Security Services",
            "type":"Services"
        }
    ],
    "sg:phone":"+1 573 449 0560",
    "sg:postcode":"65202",
    "sg:province":"MO",
    "sg:tags":[
        "business",
        "skip",
        "commercial",
        "tracing",
        "bail",
        "bond"
    ],
    "wof:name":"Prathersville Bail Bonds",
    "wof:placetype":"venue"
},
  "geometry": {"coordinates":[-92.33331,39.011301],"type":"Point"}
}