{
  "type": "Feature",
  "properties": {
    "iso:country":"US",
    "sg:address":"6303 King Hill Ave",
    "sg:city":"St Joseph",
    "sg:classifiers":[
        {
            "category":"Restaurant",
            "type":"Food & Drink"
        }
    ],
    "sg:phone":"+1 816 364 5136",
    "sg:postcode":"64504",
    "sg:province":"MO",
    "wof:name":"Taco Bandito",
    "wof:placetype":"venue"
},
  "geometry": {"coordinates":[-94.86214200000001,39.710639],"type":"Point"}
}