{
  "type": "Feature",
  "properties": {
    "addr:full":"64 S County Center Way Des Peres MO 63129",
    "addr:housenumber":"64",
    "addr:postcode":"63129",
    "addr:street":"S County Center Way",
    "iso:country":"US",
    "sg:address":"64 S County Center Way",
    "sg:city":"Des Peres",
    "sg:classifiers":[
        {
            "category":"Utilities",
            "subcategory":"Telephone",
            "type":"Services"
        }
    ],
    "sg:phone":"+1 314 966 0313",
    "sg:postcode":"63129",
    "sg:province":"MO",
    "sg:tags":[
        "company"
    ],
    "wof:name":"Dakota Watch Co",
    "wof:placetype":"venue"
},
  "geometry": {"coordinates":[-90.32929300000001,38.504938],"type":"Point"}
}