{
  "type": "Feature",
  "properties": {
    "iso:country":"US",
    "sg:address":"410 Burris St",
    "sg:city":"Fredericktown",
    "sg:classifiers":[
        {
            "category":"Restaurant",
            "type":"Food & Drink"
        }
    ],
    "sg:phone":"+1 573 783 8858",
    "sg:postcode":"63645",
    "sg:province":"MO",
    "sg:tags":[
        "style",
        "family"
    ],
    "wof:name":"A & M Restaurant",
    "wof:placetype":"venue"
},
  "geometry": {"coordinates":[-90.289131,37.570288],"type":"Point"}
}