{
  "type": "Feature",
  "properties": {
    "iso:country":"US",
    "sg:address":"12808 15 St",
    "sg:city":"Grandview",
    "sg:classifiers":[
        {
            "category":"Real Estate",
            "subcategory":"Real Estate Agent",
            "type":"Services"
        }
    ],
    "sg:phone":"+1 816 761 5864",
    "sg:postcode":"64030",
    "sg:province":"MO",
    "sg:tags":[
        "development"
    ],
    "wof:name":"Wb Enterprises Inc",
    "wof:placetype":"venue"
},
  "geometry": {"coordinates":[-94.527045,38.897286],"type":"Point"}
}