{
  "type": "Feature",
  "properties": {
    "iso:country":"US",
    "sg:address":"11241 Saint Charles Rock Rd",
    "sg:city":"Bridgeton",
    "sg:classifiers":[
        {
            "category":"Personal",
            "subcategory":"Nail Salon",
            "type":"Services"
        }
    ],
    "sg:phone":"+1 314 739 0858",
    "sg:postcode":"63044",
    "sg:province":"MO",
    "wof:name":"LG Nails",
    "wof:placetype":"venue"
},
  "geometry": {"coordinates":[-90.40116,38.738922],"type":"Point"}
}