{
  "type": "Feature",
  "properties": {
    "iso:country":"US",
    "sg:address":"9714 Middleton Rd",
    "sg:city":"Lees Summit",
    "sg:classifiers":[
        {
            "category":"Organizations",
            "subcategory":"Community Association",
            "type":"Services"
        }
    ],
    "sg:phone":"+1 816 525 2219",
    "sg:postcode":"64086",
    "sg:province":"MO",
    "wof:name":"Ancient Free & Accepted M",
    "wof:placetype":"venue"
},
  "geometry": {"coordinates":[-94.29266800000001,38.940188],"type":"Point"}
}