{
  "type": "Feature",
  "properties": {
    "iso:country":"US",
    "sg:address":"506 Main St",
    "sg:city":"Noel",
    "sg:classifiers":[
        {
            "category":"Insurance",
            "subcategory":"Title Insurance",
            "type":"Services"
        }
    ],
    "sg:phone":"+1 417 223 5159",
    "sg:postcode":"64854",
    "sg:province":"MO",
    "sg:tags":[
        "mortgage"
    ],
    "wof:name":"Mcdonald Cty Title Escrow Inc",
    "wof:placetype":"venue"
},
  "geometry": {"coordinates":[-94.484465,36.544981],"type":"Point"}
}