{
  "type": "Feature",
  "properties": {
    "iso:country":"US",
    "sg:address":"102 N Mine St",
    "sg:city":"Potosi",
    "sg:classifiers":[
        {
            "category":"Insurance",
            "subcategory":"Insurance Agent",
            "type":"Services"
        }
    ],
    "sg:phone":"+1 573 438 5300",
    "sg:postcode":"63664",
    "sg:province":"MO",
    "wof:name":"Craig Portell Insurance",
    "wof:placetype":"venue"
},
  "geometry": {"coordinates":[-90.78801199999999,37.937647],"type":"Point"}
}