{
  "type": "Feature",
  "properties": {
    "iso:country":"US",
    "sg:address":"15323 Lawrence 2077",
    "sg:city":"Mount Vernon",
    "sg:classifiers":[
        {
            "category":"Real Estate",
            "subcategory":"Surveying",
            "type":"Services"
        }
    ],
    "sg:phone":"+1 417 471 1628",
    "sg:postcode":"65712",
    "sg:province":"MO",
    "wof:name":"Austin Land Surveying",
    "wof:placetype":"venue"
},
  "geometry": {"coordinates":[-93.781291,37.163027],"type":"Point"}
}