{
  "type": "Feature",
  "properties": {
    "iso:country":"US",
    "sg:address":"1004 Carondelet Dr W",
    "sg:city":"Kansas City",
    "sg:classifiers":[
        {
            "category":"Health Services",
            "subcategory":"Doctor",
            "type":"Services"
        }
    ],
    "sg:phone":"+1 816 942 3060",
    "sg:postcode":"64114",
    "sg:province":"MO",
    "sg:tags":[
        "medical",
        "clinic"
    ],
    "wof:name":"Complete Healthcare For Women",
    "wof:placetype":"venue"
},
  "geometry": {"coordinates":[-94.604381,38.935319],"type":"Point"}
}