{
  "type": "Feature",
  "properties": {
    "iso:country":"US",
    "sg:address":"26 Robert Dr",
    "sg:city":"St Charles",
    "sg:phone":"+1 636 272 1811",
    "sg:postcode":"63304",
    "sg:province":"MO",
    "sg:tags":[
        "lubricant"
    ],
    "wof:name":"R-Bet Sales",
    "wof:placetype":"venue"
},
  "geometry": {"coordinates":[-90.577894,38.731015],"type":"Point"}
}