{
  "type": "Feature",
  "properties": {
    "iso:country":"US",
    "sg:address":"8141 Manchester Rd",
    "sg:city":"St Louis",
    "sg:classifiers":[
        {
            "category":"Health Services",
            "subcategory":"Medical Lab",
            "type":"Services"
        }
    ],
    "sg:phone":"+1 314 646 0404",
    "sg:postcode":"63144",
    "sg:province":"MO",
    "sg:tags":[
        "laboratory",
        "dental"
    ],
    "wof:name":"Modern Dental Arts Inc",
    "wof:placetype":"venue"
},
  "geometry": {"coordinates":[-90.33914300000001,38.611859],"type":"Point"}
}