{
  "type": "Feature",
  "properties": {
    "iso:country":"US",
    "sg:address":"505 Ash St",
    "sg:city":"Buffalo",
    "sg:classifiers":[
        {
            "category":"Wholesale",
            "subcategory":"Medical Equipment & Supplies",
            "type":"Manufacturing & Wholesale Goods"
        }
    ],
    "sg:phone":"+1 417 345 2244",
    "sg:postcode":"65622",
    "sg:province":"MO",
    "sg:tags":[
        "physician",
        "surgeon"
    ],
    "wof:name":"Citizens Memorial Home Medical",
    "wof:placetype":"venue"
},
  "geometry": {"coordinates":[-93.10391799999999,37.652727],"type":"Point"}
}