{
  "type": "Feature",
  "properties": {
    "iso:country":"US",
    "sg:address":"2625 NE Vivion Rd",
    "sg:city":"Kansas City",
    "sg:classifiers":[
        {
            "category":"Retail",
            "subcategory":"Auto Repair",
            "type":"Services"
        }
    ],
    "sg:phone":"+1 816 452 4435",
    "sg:postcode":"64119",
    "sg:province":"MO",
    "sg:tags":[
        "muffler",
        "exhaust",
        "system"
    ],
    "wof:name":"Meineke Car Care Ctr",
    "wof:placetype":"venue"
},
  "geometry": {"coordinates":[-94.548565,39.186272],"type":"Point"}
}