{
  "type": "Feature",
  "properties": {
    "iso:country":"US",
    "sg:address":"12561 State Rte A",
    "sg:city":"Ste Genevieve",
    "sg:classifiers":[
        {
            "category":"Utilities",
            "subcategory":"Refuse",
            "type":"Services"
        }
    ],
    "sg:phone":"+1 573 438 8824",
    "sg:postcode":"63670",
    "sg:province":"MO",
    "sg:tags":[
        "sanitation"
    ],
    "wof:name":"Continental Waste Industries",
    "wof:placetype":"venue"
},
  "geometry": {"coordinates":[-90.120412,37.936788],"type":"Point"}
}