{
  "type": "Feature",
  "properties": {
    "iso:country":"US",
    "sg:address":"8243 Lackland Rd",
    "sg:city":"Saint Louis",
    "sg:classifiers":[
        {
            "category":"Manufacturing",
            "subcategory":"Food",
            "type":"Manufacturing & Wholesale Goods"
        }
    ],
    "sg:phone":"+1 314 428 5266",
    "sg:postcode":"63114",
    "sg:province":"MO",
    "sg:tags":[
        "product",
        "mfg"
    ],
    "wof:name":"George Weston Bakeries  Inc",
    "wof:placetype":"venue"
},
  "geometry": {"coordinates":[-90.335194,38.703285],"type":"Point"}
}