{
  "type": "Feature",
  "properties": {
    "iso:country":"US",
    "sg:address":"13479 Olive Blvd",
    "sg:city":"Chesterfield",
    "sg:classifiers":[
        {
            "category":"Personal",
            "type":"Services"
        }
    ],
    "sg:phone":"+1 314 434 8422",
    "sg:postcode":"63017",
    "sg:province":"MO",
    "sg:website":"www.sunstudiotans.com",
    "wof:name":"Sun Studio Tanning Salon",
    "wof:placetype":"venue"
},
  "geometry": {"coordinates":[-90.496617,38.680358],"type":"Point"}
}