{
  "type": "Feature",
  "properties": {
    "iso:country":"US",
    "sg:address":"129 Double Eagle Dr",
    "sg:city":"Saint Charles",
    "sg:classifiers":[
        {
            "category":"Banks & Credit Unions",
            "subcategory":"Financial Services",
            "type":"Services"
        }
    ],
    "sg:phone":"+1 636 949 0627",
    "sg:postcode":"63303",
    "sg:province":"MO",
    "sg:tags":[
        "trust",
        "investment",
        "real estate"
    ],
    "wof:name":"Diversified Investments LLC",
    "wof:placetype":"venue"
},
  "geometry": {"coordinates":[-90.54454,38.772069],"type":"Point"}
}