{
  "type": "Feature",
  "properties": {
    "iso:country":"US",
    "sg:address":"118 W Jackson St",
    "sg:city":"Mexico",
    "sg:classifiers":[
        {
            "category":"Banks & Credit Unions",
            "subcategory":"Bank",
            "type":"Services"
        }
    ],
    "sg:phone":"+1 573 581 9300",
    "sg:postcode":"65265",
    "sg:province":"MO",
    "sg:tags":[
        "loan",
        "real estate"
    ],
    "wof:name":"Countrywide Home Loans",
    "wof:placetype":"venue"
},
  "geometry": {"coordinates":[-91.88346300000001,39.17212],"type":"Point"}
}