{
  "type": "Feature",
  "properties": {
    "iso:country":"US",
    "sg:address":"120 S 15th St",
    "sg:city":"Saint Joseph",
    "sg:classifiers":[
        {
            "category":"Professional",
            "type":"Services"
        }
    ],
    "sg:phone":"+1 816 387 8488",
    "sg:postcode":"64501",
    "sg:province":"MO",
    "wof:name":"Kress & Sons LLC",
    "wof:placetype":"venue"
},
  "geometry": {"coordinates":[-94.842499,39.766022],"type":"Point"}
}