{
  "type": "Feature",
  "properties": {
    "iso:country":"US",
    "sg:address":"4900 S Farm Rd 189",
    "sg:city":"Rogersville",
    "sg:classifiers":[
        {
            "category":"Organizations",
            "subcategory":"Religious Organization",
            "type":"Services"
        }
    ],
    "sg:phone":"+1 417 881 2409",
    "sg:postcode":"65742",
    "sg:province":"MO",
    "sg:tags":[
        "church"
    ],
    "wof:name":"River Of Life Lutheran Church",
    "wof:placetype":"venue"
},
  "geometry": {"coordinates":[-93.208777,37.124095],"type":"Point"}
}