{
  "type": "Feature",
  "properties": {
    "iso:country":"US",
    "sg:address":"15063 Isleview Ct",
    "sg:city":"Chesterfield",
    "sg:classifiers":[
        {
            "category":"Professional",
            "subcategory":"Computer Services",
            "type":"Services"
        }
    ],
    "sg:phone":"+1 636 519 8608",
    "sg:postcode":"63017",
    "sg:province":"MO",
    "sg:tags":[
        "consulting",
        "software"
    ],
    "wof:name":"CTS Incorporated",
    "wof:placetype":"venue"
},
  "geometry": {"coordinates":[-90.549149,38.629553],"type":"Point"}
}