{
  "type": "Feature",
  "properties": {
    "addr:full":"1210 Lemay Ferry Rd Saint Louis MO 63125",
    "addr:housenumber":"1210",
    "addr:postcode":"63125",
    "addr:street":"Lemay Ferry Rd",
    "iso:country":"US",
    "sg:address":"1210 Lemay Ferry Rd",
    "sg:city":"Saint Louis",
    "sg:classifiers":[
        {
            "category":"Wholesale",
            "subcategory":"Petroleum",
            "type":"Manufacturing & Wholesale Goods"
        }
    ],
    "sg:phone":"+1 314 544 0540",
    "sg:postcode":"63125",
    "sg:province":"MO",
    "sg:tags":[
        "bulk",
        "convenience",
        "store"
    ],
    "wof:name":"Express Mart",
    "wof:placetype":"venue"
},
  "geometry": {"coordinates":[-90.287498,38.532972],"type":"Point"}
}