{
  "type": "Feature",
  "properties": {
    "iso:country":"US",
    "sg:address":"102 W Saint Francis St",
    "sg:city":"Kennett",
    "sg:classifiers":[
        {
            "category":"Wholesale",
            "subcategory":"Medical Equipment & Supplies",
            "type":"Manufacturing & Wholesale Goods"
        }
    ],
    "sg:phone":"+1 573 888 1773",
    "sg:postcode":"63841",
    "sg:province":"MO",
    "sg:tags":[
        "physician",
        "surgeon"
    ],
    "wof:name":"Mitchell Home Medical Equip",
    "wof:placetype":"venue"
},
  "geometry": {"coordinates":[-89.960505,36.798255],"type":"Point"}
}