{
  "type": "Feature",
  "properties": {
    "iso:country":"US",
    "sg:address":"4478 S Noland Rd",
    "sg:city":"Independence",
    "sg:classifiers":[
        {
            "category":"Personal",
            "type":"Services"
        }
    ],
    "sg:phone":"+1 816 478 9889",
    "sg:postcode":"64055",
    "sg:province":"MO",
    "sg:tags":[
        "salon",
        "tanning"
    ],
    "wof:name":"Celsius Tannery",
    "wof:placetype":"venue"
},
  "geometry": {"coordinates":[-94.41550599999999,39.040495],"type":"Point"}
}