{
  "type": "Feature",
  "properties": {
    "iso:country":"US",
    "sg:address":"3604 Fremont Ave",
    "sg:city":"Kansas City",
    "sg:classifiers":[
        {
            "category":"Professional",
            "subcategory":"Management & Consulting",
            "type":"Services"
        }
    ],
    "sg:phone":"+1 816 861 4090",
    "sg:postcode":"64129",
    "sg:province":"MO",
    "wof:name":"Stevens & Associates Inc",
    "wof:placetype":"venue"
},
  "geometry": {"coordinates":[-94.509743,39.057773],"type":"Point"}
}