{
  "type": "Feature",
  "properties": {
    "iso:country":"US",
    "sg:address":"16604 Benton Taylor Dr",
    "sg:city":"Chesterfield",
    "sg:classifiers":[
        {
            "category":"Building & Trades",
            "subcategory":"Construction",
            "type":"Services"
        }
    ],
    "sg:phone":"+1 636 537 2924",
    "sg:postcode":"63005",
    "sg:province":"MO",
    "sg:tags":[
        "new",
        "home"
    ],
    "wof:name":"Affinity Communities Inc",
    "wof:placetype":"venue"
},
  "geometry": {"coordinates":[-90.580654,38.653425],"type":"Point"}
}