{
  "type": "Feature",
  "properties": {
    "iso:country":"US",
    "sg:address":"502 Briarbrook Dr",
    "sg:city":"Carl Junction",
    "sg:classifiers":[
        {
            "category":"Sports & Exercise",
            "subcategory":"Golf",
            "type":"Entertainment"
        }
    ],
    "sg:phone":"+1 417 649 6936",
    "sg:postcode":"64834",
    "sg:province":"MO",
    "sg:tags":[
        "course",
        "public"
    ],
    "wof:name":"Huffman Golf Enterprises Inc",
    "wof:placetype":"venue"
},
  "geometry": {"coordinates":[-94.539998,37.160353],"type":"Point"}
}