{
  "type": "Feature",
  "properties": {
    "iso:country":"US",
    "sg:address":"2131 Hickory St",
    "sg:city":"Saint Louis",
    "sg:classifiers":[
        {
            "category":"Manufacturing",
            "subcategory":"Chemicals & Compounds",
            "type":"Manufacturing & Wholesale Goods"
        }
    ],
    "sg:phone":"+1 314 621 4200",
    "sg:postcode":"63104",
    "sg:province":"MO",
    "sg:tags":[
        "mfg",
        "plastic"
    ],
    "wof:name":"Marchem Corporation",
    "wof:placetype":"venue"
},
  "geometry": {"coordinates":[-90.215402,38.61989],"type":"Point"}
}