{
  "type": "Feature",
  "properties": {
    "iso:country":"US",
    "sg:address":"30017 Overstreet Rd",
    "sg:city":"Sedalia",
    "sg:classifiers":[
        {
            "category":"Wholesale",
            "subcategory":"Farm Supplies",
            "type":"Manufacturing & Wholesale Goods"
        }
    ],
    "sg:phone":"+1 660 827 2354",
    "sg:postcode":"65301",
    "sg:province":"MO",
    "sg:tags":[
        "feed"
    ],
    "wof:name":"Hostetler Poultry & Feed Supl",
    "wof:placetype":"venue"
},
  "geometry": {"coordinates":[-93.134173,38.692617],"type":"Point"}
}