{
  "type": "Feature",
  "properties": {
    "iso:country":"US",
    "sg:address":"7608 S Raytown Rd",
    "sg:city":"Raytown",
    "sg:classifiers":[
        {
            "category":"Professional",
            "subcategory":"Lawyer & Legal Services",
            "type":"Services"
        }
    ],
    "sg:phone":"+1 816 353 8787",
    "sg:postcode":"64138",
    "sg:province":"MO",
    "sg:tags":[
        "attorney"
    ],
    "wof:name":"Wiley W Morrison",
    "wof:placetype":"venue"
},
  "geometry": {"coordinates":[-94.464583,38.985449],"type":"Point"}
}