{
  "type": "Feature",
  "properties": {
    "iso:country":"US",
    "sg:address":"200 S Church St",
    "sg:city":"Fayette",
    "sg:classifiers":[
        {
            "category":"Food & Beverages",
            "subcategory":"Groceries & Convenience Stores",
            "type":"Retail Goods"
        }
    ],
    "sg:phone":"+1 660 248 1382",
    "sg:postcode":"65248",
    "sg:province":"MO",
    "wof:name":"Fayette Fast Lane",
    "wof:placetype":"venue"
},
  "geometry": {"coordinates":[-92.683048,39.145004],"type":"Point"}
}