{
  "type": "Feature",
  "properties": {
    "iso:country":"US",
    "sg:address":"3303 Miller St",
    "sg:city":"Bethany",
    "sg:classifiers":[
        {
            "category":"Insurance",
            "subcategory":"Hazard Insurance",
            "type":"Services"
        }
    ],
    "sg:phone":"+1 660 425 7677",
    "sg:postcode":"64424",
    "sg:province":"MO",
    "sg:tags":[
        "commercial",
        "business"
    ],
    "wof:name":"Ross Insurance Agency",
    "wof:placetype":"venue"
},
  "geometry": {"coordinates":[-94.019875,40.265274],"type":"Point"}
}