{
  "type": "Feature",
  "properties": {
    "iso:country":"US",
    "sg:address":"2330 Madison 417",
    "sg:city":"Fredericktown",
    "sg:classifiers":[
        {
            "category":"Wholesale",
            "subcategory":"Petroleum",
            "type":"Manufacturing & Wholesale Goods"
        }
    ],
    "sg:phone":"+1 573 783 3928",
    "sg:postcode":"63645",
    "sg:province":"MO",
    "sg:tags":[
        "pipe",
        "line",
        "company"
    ],
    "wof:name":"Centerpoint Energy-Ms River",
    "wof:placetype":"venue"
},
  "geometry": {"coordinates":[-90.300668,37.438368],"type":"Point"}
}