{
  "type": "Feature",
  "properties": {
    "iso:country":"US",
    "sg:address":"2600 N Westwood Blvd",
    "sg:city":"Poplar Bluff",
    "sg:classifiers":[
        {
            "category":"Home & Garden",
            "subcategory":"Furniture",
            "type":"Retail Goods"
        }
    ],
    "sg:phone":"+1 573 776 1003",
    "sg:postcode":"63901",
    "sg:province":"MO",
    "wof:name":"Sluggo's Warehouse Outlet",
    "wof:placetype":"venue"
},
  "geometry": {"coordinates":[-90.42868199999999,36.784859],"type":"Point"}
}