{
  "type": "Feature",
  "properties": {
    "iso:country":"US",
    "sg:address":"4008 E Truman Rd",
    "sg:city":"Kansas City",
    "sg:classifiers":[
        {
            "category":"Insurance",
            "subcategory":"Hazard Insurance",
            "type":"Services"
        }
    ],
    "sg:phone":"+1 816 842 1717",
    "sg:postcode":"64127",
    "sg:province":"MO",
    "sg:tags":[
        "bond"
    ],
    "wof:name":"Liberty Bonding Co",
    "wof:placetype":"venue"
},
  "geometry": {"coordinates":[-94.53321099999999,39.094089],"type":"Point"}
}