{
  "type": "Feature",
  "properties": {
    "iso:country":"US",
    "sg:address":"2955 S Old Hwy 94",
    "sg:city":"Saint Peters",
    "sg:classifiers":[
        {
            "category":"Restaurant",
            "type":"Food & Drink"
        }
    ],
    "sg:phone":"+1 636 926 3782",
    "sg:postcode":"63376",
    "sg:province":"MO",
    "sg:tags":[
        "eating"
    ],
    "wof:name":"Subway",
    "wof:placetype":"venue"
},
  "geometry": {"coordinates":[-90.55686300000001,38.752791],"type":"Point"}
}