{
  "type": "Feature",
  "properties": {
    "iso:country":"US",
    "sg:address":"50 Westmoreland Pl",
    "sg:city":"Saint Louis",
    "sg:classifiers":[
        {
            "category":"Professional",
            "subcategory":"Lawyer & Legal Services",
            "type":"Services"
        }
    ],
    "sg:phone":"+1 314 367 4333",
    "sg:postcode":"63108",
    "sg:province":"MO",
    "wof:name":"Valier Charles E Atty",
    "wof:placetype":"venue"
},
  "geometry": {"coordinates":[-90.273409,38.646057],"type":"Point"}
}