{
  "type": "Feature",
  "properties": {
    "iso:country":"US",
    "sg:address":"2711 Clay Edwards Dr",
    "sg:city":"Kansas City",
    "sg:classifiers":[
        {
            "category":"Education",
            "subcategory":"Vocational School",
            "type":"Public Place"
        }
    ],
    "sg:phone":"+1 816 421 5323",
    "sg:postcode":"64116",
    "sg:province":"MO",
    "wof:name":"Cntrl MO State Univ Dept Nurs",
    "wof:placetype":"venue"
},
  "geometry": {"coordinates":[-94.55025000000001,39.150381],"type":"Point"}
}