{
  "type": "Feature",
  "properties": {
    "iso:country":"US",
    "sg:address":"715 N Holden St",
    "sg:city":"Warrensburg",
    "sg:classifiers":[
        {
            "category":"Professional",
            "subcategory":"Business Services",
            "type":"Services"
        }
    ],
    "sg:phone":"+1 660 422 6820",
    "sg:postcode":"64093",
    "sg:province":"MO",
    "wof:name":"Allison Bail Bonds",
    "wof:placetype":"venue"
},
  "geometry": {"coordinates":[-93.73979300000001,38.772654],"type":"Point"}
}