{
  "type": "Feature",
  "properties": {
    "iso:country":"US",
    "sg:address":"6861 Bonnie Ave",
    "sg:city":"Saint Louis",
    "sg:classifiers":[
        {
            "category":"Building & Trades",
            "subcategory":"Construction",
            "type":"Services"
        }
    ],
    "sg:phone":"+1 314 631 9191",
    "sg:postcode":"63123",
    "sg:province":"MO",
    "sg:tags":[
        "contractor"
    ],
    "wof:name":"Nahn Tile Co",
    "wof:placetype":"venue"
},
  "geometry": {"coordinates":[-90.333817,38.554025],"type":"Point"}
}