{
  "type": "Feature",
  "properties": {
    "iso:country":"US",
    "sg:address":"3212 Holmes St",
    "sg:city":"Kansas City",
    "sg:classifiers":[
        {
            "category":"Retail",
            "subcategory":"Auto Repair",
            "type":"Services"
        }
    ],
    "sg:phone":"+1 816 561 0096",
    "sg:postcode":"64109",
    "sg:province":"MO",
    "sg:tags":[
        "body",
        "automobile",
        "painting"
    ],
    "wof:name":"Wild Child's Custom Shop",
    "wof:placetype":"venue"
},
  "geometry": {"coordinates":[-94.57679400000001,39.067549],"type":"Point"}
}