{
  "type": "Feature",
  "properties": {
    "iso:country":"US",
    "sg:address":"1064 Big Sky Dr",
    "sg:city":"Fenton",
    "sg:classifiers":[
        {
            "category":"Professional",
            "type":"Services"
        }
    ],
    "sg:phone":"+1 636 326 4466",
    "sg:postcode":"63026",
    "sg:province":"MO",
    "wof:name":"Cogent Innovators LLC",
    "wof:placetype":"venue"
},
  "geometry": {"coordinates":[-90.439311,38.492258],"type":"Point"}
}