{
  "type": "Feature",
  "properties": {
    "iso:country":"US",
    "sg:address":"469 Normandy Rd",
    "sg:city":"Fordland",
    "sg:classifiers":[
        {
            "category":"Building & Trades",
            "subcategory":"Construction",
            "type":"Services"
        }
    ],
    "sg:phone":"+1 417 767 2380",
    "sg:postcode":"65652",
    "sg:province":"MO",
    "sg:tags":[
        "contractor"
    ],
    "wof:name":"Mitco Drywall",
    "wof:placetype":"venue"
},
  "geometry": {"coordinates":[-92.91874900000001,37.180734],"type":"Point"}
}