{
  "type": "Feature",
  "properties": {
    "iso:country":"US",
    "sg:address":"231 S Kent St",
    "sg:city":"Excelsior Spgs",
    "sg:classifiers":[
        {
            "category":"Building & Trades",
            "subcategory":"Landscaping Services",
            "type":"Services"
        }
    ],
    "sg:phone":"+1 816 630 5574",
    "sg:postcode":"64024",
    "sg:province":"MO",
    "sg:tags":[
        "lawn",
        "maintenance",
        "grounds"
    ],
    "wof:name":"D & N Lawn Care & Landscaping",
    "wof:placetype":"venue"
},
  "geometry": {"coordinates":[-94.221329,39.333001],"type":"Point"}
}