{
  "type": "Feature",
  "properties": {
    "iso:country":"US",
    "sg:address":"8920 Wornall Rd",
    "sg:city":"Kansas City",
    "sg:classifiers":[
        {
            "category":"Restaurant",
            "type":"Food & Drink"
        }
    ],
    "sg:phone":"+1 816 444 5542",
    "sg:postcode":"64114",
    "sg:province":"MO",
    "sg:tags":[
        "barbecue",
        "eating"
    ],
    "wof:name":"Smoke Stack Bar-B-Que 3",
    "wof:placetype":"venue"
},
  "geometry": {"coordinates":[-94.595569,38.965372],"type":"Point"}
}