{
  "type": "Feature",
  "properties": {
    "iso:country":"US",
    "sg:address":"3101 Woodkirk Ln",
    "sg:city":"Columbia",
    "sg:classifiers":[
        {
            "category":"Arts & Performance",
            "subcategory":"Music",
            "type":"Entertainment"
        }
    ],
    "sg:phone":"+1 573 449 0609",
    "sg:postcode":"65203",
    "sg:province":"MO",
    "sg:tags":[
        "musician"
    ],
    "wof:name":"The Musician Network",
    "wof:placetype":"venue"
},
  "geometry": {"coordinates":[-92.35985700000001,38.918221],"type":"Point"}
}