{
  "type": "Feature",
  "properties": {
    "iso:country":"US",
    "sg:address":"1278 US Hwy 60",
    "sg:city":"Republic",
    "sg:classifiers":[
        {
            "category":"Food & Beverages",
            "subcategory":"Groceries & Convenience Stores",
            "type":"Retail Goods"
        }
    ],
    "sg:phone":"+1 417 732 9226",
    "sg:postcode":"65738",
    "sg:province":"MO",
    "wof:name":"Rapid Roberts",
    "wof:placetype":"venue"
},
  "geometry": {"coordinates":[-93.45716899999999,37.13245],"type":"Point"}
}