{
  "type": "Feature",
  "properties": {
    "iso:country":"US",
    "sg:address":"10306 Yarwood Ct",
    "sg:city":"St Louis",
    "sg:classifiers":[
        {
            "category":"Building & Trades",
            "subcategory":"Construction",
            "type":"Services"
        }
    ],
    "sg:phone":"+1 314 374 6555",
    "sg:postcode":"63136",
    "sg:province":"MO",
    "sg:tags":[
        "concrete",
        "contractor"
    ],
    "wof:name":"Ready To Roll Concrete",
    "wof:placetype":"venue"
},
  "geometry": {"coordinates":[-90.27932199999999,38.758113],"type":"Point"}
}