{
  "type": "Feature",
  "properties": {
    "iso:country":"US",
    "sg:address":"3654 W Madison St",
    "sg:city":"Springfield",
    "sg:classifiers":[
        {
            "category":"Professional",
            "type":"Services"
        }
    ],
    "sg:phone":"+1 417 864 8261",
    "sg:postcode":"65802",
    "sg:province":"MO",
    "wof:name":"National Society of Sons",
    "wof:placetype":"venue"
},
  "geometry": {"coordinates":[-93.354101,37.201652],"type":"Point"}
}