{
  "type": "Feature",
  "properties": {
    "iso:country":"US",
    "sg:address":"1695 Clarkson Rd",
    "sg:city":"Chesterfield",
    "sg:classifiers":[
        {
            "category":"Real Estate",
            "subcategory":"Real Estate Agent",
            "type":"Services"
        }
    ],
    "sg:phone":"+1 636 530 1743",
    "sg:postcode":"63017",
    "sg:province":"MO",
    "wof:name":"Lorraine Hadley",
    "wof:placetype":"venue"
},
  "geometry": {"coordinates":[-90.565691,38.644916],"type":"Point"}
}