{
  "type": "Feature",
  "properties": {
    "iso:country":"US",
    "sg:address":"33534 State Hwy Ac",
    "sg:city":"Richland",
    "sg:classifiers":[
        {
            "category":"Building & Trades",
            "subcategory":"Pest Control",
            "type":"Services"
        }
    ],
    "sg:phone":"+1 573 480 0180",
    "sg:postcode":"65556",
    "sg:province":"MO",
    "wof:name":"Cansler Pest Control",
    "wof:placetype":"venue"
},
  "geometry": {"coordinates":[-92.42052,37.662728],"type":"Point"}
}