{
  "type": "Feature",
  "properties": {
    "iso:country":"US",
    "sg:address":"6560 Satke Dr",
    "sg:city":"House Springs",
    "sg:classifiers":[
        {
            "category":"Professional",
            "type":"Services"
        }
    ],
    "sg:phone":"+1 636 671 6262",
    "sg:postcode":"63051",
    "sg:province":"MO",
    "wof:name":"Jeffco Soho Inc",
    "wof:placetype":"venue"
},
  "geometry": {"coordinates":[-90.571185,38.405354],"type":"Point"}
}