{
  "type": "Feature",
  "properties": {
    "iso:country":"US",
    "sg:address":"1278 Jungermann Rd",
    "sg:city":"St Peters",
    "sg:classifiers":[
        {
            "category":"Sports & Exercise",
            "subcategory":"Gym",
            "type":"Entertainment"
        }
    ],
    "sg:phone":"+1 636 922 7200",
    "sg:postcode":"63376",
    "sg:province":"MO",
    "sg:tags":[
        "facility",
        "club",
        "gymnasium",
        "health",
        "fitness",
        "studio",
        "physical"
    ],
    "wof:name":"One Body Fitness",
    "wof:placetype":"venue"
},
  "geometry": {"coordinates":[-90.578413,38.778448],"type":"Point"}
}