{
  "type": "Feature",
  "properties": {
    "iso:country":"US",
    "sg:address":"159 State Rte B",
    "sg:city":"Raymondville",
    "sg:classifiers":[
        {
            "category":"Food & Beverages",
            "subcategory":"Groceries & Convenience Stores",
            "type":"Retail Goods"
        }
    ],
    "sg:phone":"+1 417 457 6400",
    "sg:postcode":"65555",
    "sg:province":"MO",
    "sg:tags":[
        "grocer"
    ],
    "wof:name":"Raymondville Grocery & Market",
    "wof:placetype":"venue"
},
  "geometry": {"coordinates":[-91.83760100000001,37.33934],"type":"Point"}
}