{
  "type": "Feature",
  "properties": {
    "iso:country":"US",
    "sg:address":"44 N Central Ave",
    "sg:city":"St Louis",
    "sg:classifiers":[
        {
            "category":"Retail",
            "subcategory":"Photofinishing",
            "type":"Services"
        }
    ],
    "sg:phone":"+1 314 721 1799",
    "sg:postcode":"63105",
    "sg:province":"MO",
    "sg:tags":[
        "photo",
        "laboratory"
    ],
    "wof:name":"Rainbo Color Inc",
    "wof:placetype":"venue"
},
  "geometry": {"coordinates":[-90.338078,38.651052],"type":"Point"}
}