{
  "type": "Feature",
  "properties": {
    "iso:country":"US",
    "sg:address":"614 W Jonathan Dr",
    "sg:city":"Marionville",
    "sg:classifiers":[
        {
            "category":"Building & Trades",
            "subcategory":"Construction",
            "type":"Services"
        }
    ],
    "sg:phone":"+1 417 258 2584",
    "sg:postcode":"65705",
    "sg:province":"MO",
    "sg:tags":[
        "maker",
        "cabinet"
    ],
    "sg:website":"www.alpinewood.com",
    "wof:name":"Alpine Wood Products Co Inc",
    "wof:placetype":"venue"
},
  "geometry": {"coordinates":[-93.64539499999999,36.987734],"type":"Point"}
}