{
  "type": "Feature",
  "properties": {
    "iso:country":"US",
    "sg:address":"6547 W State Highway 162",
    "sg:city":"Gideon",
    "sg:classifiers":[
        {
            "category":"Farming",
            "subcategory":"Farm",
            "type":"Manufacturing & Wholesale Goods"
        }
    ],
    "sg:phone":"+1 573 448 3546",
    "sg:postcode":"63848",
    "sg:province":"MO",
    "wof:name":"Larry Woolverton Farms",
    "wof:placetype":"venue"
},
  "geometry": {"coordinates":[-89.912279,36.451923],"type":"Point"}
}