{
  "type": "Feature",
  "properties": {
    "iso:country":"US",
    "sg:address":"8523 Sterling Ave",
    "sg:city":"Kansas City",
    "sg:classifiers":[
        {
            "category":"Professional",
            "subcategory":"Engineering",
            "type":"Services"
        }
    ],
    "sg:phone":"+1 816 313 7430",
    "sg:postcode":"64138",
    "sg:province":"MO",
    "wof:name":"Advanced Technical Services",
    "wof:placetype":"venue"
},
  "geometry": {"coordinates":[-94.451363,38.967188],"type":"Point"}
}