{
  "type": "Feature",
  "properties": {
    "iso:country":"US",
    "sg:address":"4060 Coyote Dr",
    "sg:city":"Joplin",
    "sg:classifiers":[
        {
            "category":"Wholesale",
            "subcategory":"Hardware",
            "type":"Manufacturing & Wholesale Goods"
        },
        {
            "category":"Home & Garden",
            "subcategory":"Garden Supply",
            "type":"Retail Goods"
        },
        {
            "category":"Retail",
            "subcategory":"Repair Shop",
            "type":"Services"
        }
    ],
    "sg:phone":"+1 877 659 8334",
    "sg:postcode":"64804",
    "sg:province":"MO",
    "sg:tags":[
        "renting",
        "lawn",
        "outdoor",
        "power",
        "landscaping",
        "equipment-sales",
        "equipment",
        "saw"
    ],
    "sg:website":"http://www.stihlusa.com/",
    "wof:name":"S & H Farm Supply, Inc.",
    "wof:placetype":"venue"
},
  "geometry": {"coordinates":[-94.54594400000001,37.012107],"type":"Point"}
}