{
  "type": "Feature",
  "properties": {
    "iso:country":"US",
    "sg:address":"32937 State Hwy 25",
    "sg:city":"Advance",
    "sg:classifiers":[
        {
            "category":"Utilities",
            "subcategory":"Fuel Oil & Lpg",
            "type":"Services"
        }
    ],
    "sg:phone":"+1 573 722 3455",
    "sg:postcode":"63730",
    "sg:province":"MO",
    "wof:name":"MFA Oil Co",
    "wof:placetype":"venue"
},
  "geometry": {"coordinates":[-89.904709,37.094246],"type":"Point"}
}