{
  "type": "Feature",
  "properties": {
    "iso:country":"US",
    "sg:address":"1435 Thompson Blvd",
    "sg:city":"Sedalia",
    "sg:classifiers":[
        {
            "category":"Restaurant",
            "type":"Food & Drink"
        }
    ],
    "sg:phone":"+1 660 829 4888",
    "sg:postcode":"65301",
    "sg:province":"MO",
    "sg:tags":[
        "eating"
    ],
    "wof:name":"Paula Jean's Cafe",
    "wof:placetype":"venue"
},
  "geometry": {"coordinates":[-93.265084,38.700688],"type":"Point"}
}