{
  "type": "Feature",
  "properties": {
    "iso:country":"US",
    "sg:address":"715 E 5th St",
    "sg:city":"Carterville",
    "sg:classifiers":[
        {
            "category":"Manufacturing",
            "subcategory":"Metals",
            "type":"Manufacturing & Wholesale Goods"
        }
    ],
    "sg:phone":"+1 417 673 3319",
    "sg:postcode":"64835",
    "sg:province":"MO",
    "sg:tags":[
        "steel",
        "manufacture",
        "equipment"
    ],
    "wof:name":"Red's Welding",
    "wof:placetype":"venue"
},
  "geometry": {"coordinates":[-94.4332,37.14116],"type":"Point"}
}