{
  "type": "Feature",
  "properties": {
    "addr:full":"1701 Highway Z Pevely MO 63070",
    "addr:housenumber":"1701",
    "addr:postcode":"63070",
    "addr:street":"Highway",
    "iso:country":"US",
    "sg:address":"1701 Highway Z",
    "sg:city":"Pevely",
    "sg:classifiers":[
        {
            "category":"Restaurant",
            "type":"Food & Drink"
        }
    ],
    "sg:menulink":"http://www.allmenus.com/mo/joachim/194272-mcdonalds/menu/",
    "sg:postcode":"63070",
    "sg:province":"MO",
    "sg:tags":[
        "burger",
        "american"
    ],
    "wof:name":"McDonald's",
    "wof:placetype":"venue"
},
  "geometry": {"coordinates":[-90.404843,38.286828],"type":"Point"}
}