{
  "type": "Feature",
  "properties": {
    "iso:country":"US",
    "sg:address":"112 W Railroad St",
    "sg:city":"Gideon",
    "sg:classifiers":[
        {
            "category":"Restaurant",
            "type":"Food & Drink"
        }
    ],
    "sg:phone":"+1 573 448 3458",
    "sg:postcode":"63848",
    "sg:province":"MO",
    "sg:tags":[
        "house",
        "steak",
        "barbecue"
    ],
    "wof:name":"Berry Barn",
    "wof:placetype":"venue"
},
  "geometry": {"coordinates":[-89.919336,36.457044],"type":"Point"}
}