{
  "type": "Feature",
  "properties": {
    "iso:country":"US",
    "sg:address":"19165 Lawrence 1240",
    "sg:city":"Marionville",
    "sg:classifiers":[
        {
            "category":"Social Services",
            "subcategory":"Child Care",
            "type":"Services"
        }
    ],
    "sg:phone":"+1 417 258 7406",
    "sg:postcode":"65705",
    "sg:province":"MO",
    "sg:tags":[
        "day"
    ],
    "wof:name":"Mamma Bear Daycare",
    "wof:placetype":"venue"
},
  "geometry": {"coordinates":[-93.62836799999999,36.993036],"type":"Point"}
}