{
  "type": "Feature",
  "properties": {
    "iso:country":"US",
    "sg:address":"200 N Main St",
    "sg:city":"Plattsburg",
    "sg:classifiers":[
        {
            "category":"Insurance",
            "subcategory":"Insurance Agent",
            "type":"Services"
        }
    ],
    "sg:phone":"+1 816 539 2181",
    "sg:postcode":"64477",
    "sg:province":"MO",
    "wof:name":"Mericle Insurance",
    "wof:placetype":"venue"
},
  "geometry": {"coordinates":[-94.44717900000001,39.566424],"type":"Point"}
}