{
  "type": "Feature",
  "properties": {
    "iso:country":"US",
    "sg:address":"3107 Beavercreek Dr",
    "sg:city":"Cape Girardeau",
    "sg:classifiers":[
        {
            "category":"Building & Trades",
            "subcategory":"Construction",
            "type":"Services"
        }
    ],
    "sg:phone":"+1 573 334 3456",
    "sg:postcode":"63701",
    "sg:province":"MO",
    "sg:tags":[
        "house"
    ],
    "wof:name":"D J Roth Construction Inc",
    "wof:placetype":"venue"
},
  "geometry": {"coordinates":[-89.577788,37.327861],"type":"Point"}
}