{
  "type": "Feature",
  "properties": {
    "iso:country":"US",
    "sg:address":"8619 E 61 Ter",
    "sg:city":"Kansas City",
    "sg:classifiers":[
        {
            "category":"Real Estate",
            "subcategory":"Real Estate Agent",
            "type":"Services"
        }
    ],
    "sg:phone":"+1 816 353 6060",
    "sg:postcode":"64129",
    "sg:province":"MO",
    "wof:name":"Garden Pointe Apartments",
    "wof:placetype":"venue"
},
  "geometry": {"coordinates":[-94.482643,39.012235],"type":"Point"}
}