{
  "type": "Feature",
  "properties": {
    "iso:country":"US",
    "sg:address":"2125 Hwy K",
    "sg:city":"O Fallon",
    "sg:classifiers":[
        {
            "category":"Retail",
            "subcategory":"Auto Repair",
            "type":"Services"
        }
    ],
    "sg:phone":"+1 636 272 8200",
    "sg:postcode":"63368",
    "sg:province":"MO",
    "sg:tags":[
        "shop",
        "automotive"
    ],
    "wof:name":"Rjm Enterprises",
    "wof:placetype":"venue"
},
  "geometry": {"coordinates":[-90.69982899999999,38.78102],"type":"Point"}
}