{
  "type": "Feature",
  "properties": {
    "iso:country":"US",
    "sg:address":"8867 Ladue Rd",
    "sg:city":"St Louis",
    "sg:classifiers":[
        {
            "category":"Food & Beverages",
            "subcategory":"Groceries & Convenience Stores",
            "type":"Retail Goods"
        }
    ],
    "sg:phone":"+1 314 725 7574",
    "sg:postcode":"63124",
    "sg:province":"MO",
    "sg:tags":[
        "eating",
        "grocer",
        "video",
        "tape",
        "rental",
        "floris"
    ],
    "wof:name":"Schnucks",
    "wof:placetype":"venue"
},
  "geometry": {"coordinates":[-90.350734,38.65341],"type":"Point"}
}