{
  "type": "Feature",
  "properties": {
    "iso:country":"US",
    "sg:address":"6720 N Garfield Ave",
    "sg:city":"Kansas City",
    "sg:classifiers":[
        {
            "category":"Professional",
            "type":"Services"
        }
    ],
    "sg:phone":"+1 816 459 7994",
    "sg:postcode":"64118",
    "sg:province":"MO",
    "wof:name":"Raylene Pineiro",
    "wof:placetype":"venue"
},
  "geometry": {"coordinates":[-94.553811,39.216363],"type":"Point"}
}