{
  "type": "Feature",
  "properties": {
    "iso:country":"US",
    "sg:address":"508 N Main St",
    "sg:city":"Kirksville",
    "sg:classifiers":[
        {
            "category":"Real Estate",
            "subcategory":"Real Estate Operator",
            "type":"Services"
        }
    ],
    "sg:phone":"+1 660 665 0106",
    "sg:postcode":"63501",
    "sg:province":"MO",
    "sg:tags":[
        "building",
        "apartment"
    ],
    "wof:name":"Mills APT Rentals",
    "wof:placetype":"venue"
},
  "geometry": {"coordinates":[-92.585306,40.198737],"type":"Point"}
}