{
  "type": "Feature",
  "properties": {
    "iso:country":"US",
    "sg:address":"1936 Linn St",
    "sg:city":"Kansas City",
    "sg:classifiers":[
        {
            "category":"Manufacturing",
            "subcategory":"Printing",
            "type":"Manufacturing & Wholesale Goods"
        }
    ],
    "sg:phone":"+1 816 842 9500",
    "sg:postcode":"64116",
    "sg:province":"MO",
    "sg:tags":[
        "publisher"
    ],
    "wof:name":"Needle Love Co Inc",
    "wof:placetype":"venue"
},
  "geometry": {"coordinates":[-94.568049,39.14277],"type":"Point"}
}