{
  "type": "Feature",
  "properties": {
    "iso:country":"US",
    "sg:address":"711 Old Ballas Rd",
    "sg:city":"St Louis",
    "sg:classifiers":[
        {
            "category":"Communications",
            "subcategory":"Film & Video Production",
            "type":"Services"
        },
        {
            "category":"Shopping",
            "type":"Retail Goods"
        }
    ],
    "sg:phone":"+1 314 997 4599",
    "sg:postcode":"63141",
    "sg:province":"MO",
    "sg:tags":[
        "motion",
        "wedding",
        "supply"
    ],
    "wof:name":"Copy Cat Video",
    "wof:placetype":"venue"
},
  "geometry": {"coordinates":[-90.438613,38.670715],"type":"Point"}
}