{
  "type": "Feature",
  "properties": {
    "iso:country":"US",
    "sg:address":"2610 Telegraph Rd",
    "sg:city":"Saint Louis",
    "sg:classifiers":[
        {
            "category":"Retail",
            "subcategory":"Repair Shop",
            "type":"Services"
        }
    ],
    "sg:phone":"+1 314 892 1812",
    "sg:postcode":"63125",
    "sg:province":"MO",
    "wof:name":"Bahr TV and Vcr Service",
    "wof:placetype":"venue"
},
  "geometry": {"coordinates":[-90.29096800000001,38.511773],"type":"Point"}
}