{
  "type": "Feature",
  "properties": {
    "iso:country":"US",
    "sg:address":"304 S Elm Ave",
    "sg:city":"Clever",
    "sg:classifiers":[
        {
            "category":"Manufacturing",
            "subcategory":"Rubber & Plastics",
            "type":"Manufacturing & Wholesale Goods"
        },
        {
            "category":"Autos & Motor Vehicles",
            "subcategory":"Auto Supplies",
            "type":"Retail Goods"
        },
        {
            "category":"Retail",
            "subcategory":"Auto Repair",
            "type":"Services"
        }
    ],
    "sg:phone":"+1 417 743 2543",
    "sg:postcode":"65631",
    "sg:province":"MO",
    "sg:tags":[
        "recap",
        "retread",
        "tires-wholesale",
        "tire",
        "manufacturer"
    ],
    "sg:website":"http://www.coopertire.com/html/",
    "wof:name":"Rick's Tire Shop",
    "wof:placetype":"venue"
},
  "geometry": {"coordinates":[-93.468548,37.032195],"type":"Point"}
}