{
  "type": "Feature",
  "properties": {
    "iso:country":"US",
    "sg:address":"440 S Cavalier Ave",
    "sg:city":"Springfield",
    "sg:classifiers":[
        {
            "category":"Professional",
            "subcategory":"Detective & Security Services",
            "type":"Services"
        }
    ],
    "sg:phone":"+1 417 883 6254",
    "sg:postcode":"65802",
    "sg:province":"MO",
    "sg:tags":[
        "electrical",
        "system",
        "contractor"
    ],
    "wof:name":"American Dtection Specialtists",
    "wof:placetype":"venue"
},
  "geometry": {"coordinates":[-93.231359,37.202891],"type":"Point"}
}