{
  "type": "Feature",
  "properties": {
    "iso:country":"US",
    "sg:address":"1501 Kansas Ave",
    "sg:city":"Joplin",
    "sg:classifiers":[
        {
            "category":"Place Of Worship",
            "subcategory":"Church",
            "type":"Public Place"
        },
        {
            "category":"Place Of Worship",
            "type":"Public Place"
        }
    ],
    "sg:phone":"+1 417 624 0857",
    "sg:postcode":"64804",
    "sg:province":"MO",
    "sg:tags":[
        "churches-seventh-day",
        "adventist",
        "christian",
        "churches-advent"
    ],
    "sg:website":"http://www.adventist.org",
    "wof:name":"Church-Seventh Day",
    "wof:placetype":"venue"
},
  "geometry": {"coordinates":[-94.499634,37.074669],"type":"Point"}
}