{
  "type": "Feature",
  "properties": {
    "iso:country":"US",
    "sg:address":"21092 Ladle Ln",
    "sg:city":"Waynesville",
    "sg:classifiers":[
        {
            "category":"Building & Trades",
            "subcategory":"Construction",
            "type":"Services"
        }
    ],
    "sg:phone":"+1 573 336 4483",
    "sg:postcode":"65583",
    "sg:province":"MO",
    "sg:tags":[
        "house"
    ],
    "wof:name":"Happy Home Improvement",
    "wof:placetype":"venue"
},
  "geometry": {"coordinates":[-92.176202,37.853618],"type":"Point"}
}