{
  "type": "Feature",
  "properties": {
    "iso:country":"US",
    "sg:address":"1323 S Elliott Ave",
    "sg:city":"Aurora",
    "sg:classifiers":[
        {
            "category":"Restaurant",
            "type":"Food & Drink"
        }
    ],
    "sg:phone":"+1 417 678 0211",
    "sg:postcode":"65605",
    "sg:province":"MO",
    "sg:tags":[
        "eating"
    ],
    "wof:name":"Pao's Chinese Restaurant",
    "wof:placetype":"venue"
},
  "geometry": {"coordinates":[-93.718277,36.961419],"type":"Point"}
}