{
  "type": "Feature",
  "properties": {
    "iso:country":"US",
    "sg:address":"1516 Edgemont Blvd",
    "sg:city":"Perryville",
    "sg:phone":"+1 573 547 4506",
    "sg:postcode":"63775",
    "sg:province":"MO",
    "wof:name":"Hoeckele Bakery & Deli",
    "wof:placetype":"venue"
},
  "geometry": {"coordinates":[-89.886967,37.72238],"type":"Point"}
}