{
  "type": "Feature",
  "properties": {
    "iso:country":"US",
    "sg:address":"902 Dogwood Dr",
    "sg:city":"Warrensburg",
    "sg:classifiers":[
        {
            "category":"Real Estate",
            "subcategory":"Real Estate Services",
            "type":"Services"
        },
        {
            "category":"Real Estate",
            "subcategory":"Real Estate Agent",
            "type":"Services"
        }
    ],
    "sg:phone":"+1 660 238 1566",
    "sg:postcode":"64093",
    "sg:province":"MO",
    "sg:tags":[
        "buyer",
        "broker"
    ],
    "wof:name":"Banner Realty",
    "wof:placetype":"venue"
},
  "geometry": {"coordinates":[-93.718896,38.760719],"type":"Point"}
}