{
  "type": "Feature",
  "properties": {
    "iso:country":"US",
    "sg:address":"635 E Elliott Ave",
    "sg:city":"Kirkwood",
    "sg:classifiers":[
        {
            "category":"Building & Trades",
            "subcategory":"Construction",
            "type":"Services"
        }
    ],
    "sg:phone":"+1 314 965 4745",
    "sg:postcode":"63122",
    "sg:province":"MO",
    "sg:tags":[
        "paving",
        "contractor"
    ],
    "wof:name":"Fontana Asphalt Contracting",
    "wof:placetype":"venue"
},
  "geometry": {"coordinates":[-90.392118,38.573985],"type":"Point"}
}