{
  "type": "Feature",
  "properties": {
    "iso:country":"US",
    "sg:address":"107 W Broadway",
    "sg:city":"Columbia",
    "sg:classifiers":[
        {
            "category":"Retail",
            "subcategory":"Portrait Studio",
            "type":"Services"
        }
    ],
    "sg:phone":"+1 573 874 1722",
    "sg:postcode":"65203",
    "sg:province":"MO",
    "sg:tags":[
        "photographer"
    ],
    "wof:name":"Michael Long Photography",
    "wof:placetype":"venue"
},
  "geometry": {"coordinates":[-92.341837,38.951476],"type":"Point"}
}