{
  "type": "Feature",
  "properties": {
    "iso:country":"US",
    "sg:address":"525 Walnut St",
    "sg:city":"Kansas City",
    "sg:classifiers":[
        {
            "category":"Home & Garden",
            "subcategory":"Home Furnishings",
            "type":"Retail Goods"
        }
    ],
    "sg:phone":"+1 816 842 4201",
    "sg:postcode":"64106",
    "sg:province":"MO",
    "sg:tags":[
        "lighting",
        "fixture"
    ],
    "wof:name":"Kclf",
    "wof:placetype":"venue"
},
  "geometry": {"coordinates":[-94.581485,39.108428],"type":"Point"}
}