{
  "type": "Feature",
  "properties": {
    "iso:country":"US",
    "sg:address":"7730 Carondelet Ave",
    "sg:city":"Saint Louis",
    "sg:classifiers":[
        {
            "category":"Professional",
            "subcategory":"Management & Consulting",
            "type":"Services"
        }
    ],
    "sg:phone":"+1 314 727 9394",
    "sg:postcode":"63105",
    "sg:province":"MO",
    "sg:tags":[
        "consultant",
        "health",
        "care"
    ],
    "wof:name":"Pohle Hal Managed Care Cons",
    "wof:placetype":"venue"
},
  "geometry": {"coordinates":[-90.336281,38.648662],"type":"Point"}
}