{
  "type": "Feature",
  "properties": {
    "iso:country":"US",
    "sg:address":"8607 Longview Rd",
    "sg:city":"Kansas City",
    "sg:classifiers":[
        {
            "category":"Organizations",
            "subcategory":"Religious Organization",
            "type":"Services"
        }
    ],
    "sg:phone":"+1 816 761 4989",
    "sg:postcode":"64134",
    "sg:province":"MO",
    "sg:tags":[
        "church"
    ],
    "wof:name":"Christ Our Redeemer AME Chr",
    "wof:placetype":"venue"
},
  "geometry": {"coordinates":[-94.48908299999999,38.914536],"type":"Point"}
}