{
  "type": "Feature",
  "properties": {
    "iso:country":"US",
    "sg:address":"27499 Farm View Ave",
    "sg:city":"Salisbury",
    "sg:classifiers":[
        {
            "category":"Manufacturing",
            "subcategory":"Food",
            "type":"Manufacturing & Wholesale Goods"
        },
        {
            "category":"Farming",
            "subcategory":"Farm",
            "type":"Manufacturing & Wholesale Goods"
        }
    ],
    "sg:phone":"+1 660 388 6293",
    "sg:postcode":"65281",
    "sg:province":"MO",
    "sg:tags":[
        "corn",
        "product"
    ],
    "wof:name":"Gerald Fessler",
    "wof:placetype":"venue"
},
  "geometry": {"coordinates":[-92.81486099999999,39.431598],"type":"Point"}
}