{
  "type": "Feature",
  "properties": {
    "iso:country":"US",
    "sg:address":"1701 Hwy 42",
    "sg:city":"Brumley",
    "sg:classifiers":[
        {
            "category":"Building & Trades",
            "subcategory":"Plumbing",
            "type":"Services"
        }
    ],
    "sg:phone":"+1 573 369 0066",
    "sg:postcode":"65017",
    "sg:province":"MO",
    "sg:tags":[
        "contractor"
    ],
    "wof:name":"Lb Heating and Cooling Brumley",
    "wof:placetype":"venue"
},
  "geometry": {"coordinates":[-92.457043,38.097163],"type":"Point"}
}