{
  "type": "Feature",
  "properties": {
    "iso:country":"US",
    "sg:address":"1414 Mansfield Rd",
    "sg:city":"Saint Joseph",
    "sg:classifiers":[
        {
            "category":"Organizations",
            "subcategory":"Non-profit Organization",
            "type":"Services"
        }
    ],
    "sg:phone":"+1 816 238 8707",
    "sg:postcode":"64504",
    "sg:province":"MO",
    "sg:tags":[
        "social"
    ],
    "wof:name":"March Dmes Brth Dfcts Fndation",
    "wof:placetype":"venue"
},
  "geometry": {"coordinates":[-94.841471,39.719104],"type":"Point"}
}