{
  "type": "Feature",
  "properties": {
    "iso:country":"US",
    "sg:address":"1012 N Main St",
    "sg:city":"Sikeston",
    "sg:classifiers":[
        {
            "category":"Wholesale",
            "subcategory":"Medical Equipment & Supplies",
            "type":"Manufacturing & Wholesale Goods"
        },
        {
            "category":"Shopping",
            "subcategory":"Pharmacy",
            "type":"Retail Goods"
        }
    ],
    "sg:phone":"+1 573 471 0285",
    "sg:postcode":"63801",
    "sg:province":"MO",
    "sg:tags":[
        "home",
        "health",
        "care"
    ],
    "sg:website":"http://www.randysrx.com",
    "wof:name":"Randy's Rx",
    "wof:placetype":"venue"
},
  "geometry": {"coordinates":[-89.58445,36.889112],"type":"Point"}
}