{
  "type": "Feature",
  "properties": {
    "iso:country":"US",
    "sg:address":"309 Cherry Ave",
    "sg:city":"Owensville",
    "sg:classifiers":[
        {
            "category":"Social Services",
            "subcategory":"Child Care",
            "type":"Services"
        }
    ],
    "sg:phone":"+1 573 437 3470",
    "sg:postcode":"65066",
    "sg:province":"MO",
    "sg:tags":[
        "day"
    ],
    "wof:name":"TLC Childcare",
    "wof:placetype":"venue"
},
  "geometry": {"coordinates":[-91.497259,38.355814],"type":"Point"}
}