{
  "type": "Feature",
  "properties": {
    "iso:country":"US",
    "sg:address":"516 W Main Ave",
    "sg:city":"Bernie",
    "sg:classifiers":[
        {
            "category":"Education",
            "subcategory":"School",
            "type":"Public Place"
        }
    ],
    "sg:phone":"+1 573 293 5334",
    "sg:postcode":"63822",
    "sg:province":"MO",
    "wof:name":"Bernie High School",
    "wof:placetype":"venue"
},
  "geometry": {"coordinates":[-89.97463999999999,36.669271],"type":"Point"}
}