{
  "type": "Feature",
  "properties": {
    "iso:country":"US",
    "sg:address":"1950 E Webb Rd",
    "sg:city":"Ozark",
    "sg:classifiers":[
        {
            "category":"Wholesale",
            "subcategory":"Vending Machines",
            "type":"Manufacturing & Wholesale Goods"
        }
    ],
    "sg:phone":"+1 417 581 1011",
    "sg:postcode":"65721",
    "sg:province":"MO",
    "wof:name":"Jenks Enterprises Inc",
    "wof:placetype":"venue"
},
  "geometry": {"coordinates":[-93.186831,37.052981],"type":"Point"}
}