{
  "type": "Feature",
  "properties": {
    "iso:country":"US",
    "sg:address":"4101 Chippewa St",
    "sg:city":"Saint Louis",
    "sg:classifiers":[
        {
            "category":"Autos & Motor Vehicles",
            "subcategory":"Automobile Sales",
            "type":"Retail Goods"
        }
    ],
    "sg:phone":"+1 314 773 8866",
    "sg:postcode":"63116",
    "sg:province":"MO",
    "sg:tags":[
        "used"
    ],
    "wof:name":"JD Byrider",
    "wof:placetype":"venue"
},
  "geometry": {"coordinates":[-90.256396,38.58961],"type":"Point"}
}