{
  "type": "Feature",
  "properties": {
    "iso:country":"US",
    "sg:address":"509 E Hillcrest St",
    "sg:city":"Stockton",
    "sg:classifiers":[
        {
            "category":"Communications",
            "subcategory":"Film & Video Production",
            "type":"Services"
        }
    ],
    "sg:phone":"+1 417 276 3058",
    "sg:postcode":"65785",
    "sg:province":"MO",
    "sg:tags":[
        "taping"
    ],
    "wof:name":"Captured Memories",
    "wof:placetype":"venue"
},
  "geometry": {"coordinates":[-93.790102,37.68791],"type":"Point"}
}