{
  "type": "Feature",
  "properties": {
    "iso:country":"US",
    "sg:address":"1041 E 18th St",
    "sg:city":"Rolla",
    "sg:classifiers":[
        {
            "category":"Building & Trades",
            "subcategory":"Construction",
            "type":"Services"
        }
    ],
    "sg:phone":"+1 573 364 8149",
    "sg:postcode":"65401",
    "sg:province":"MO",
    "sg:tags":[
        "excavation",
        "home",
        "builder",
        "contractor"
    ],
    "sg:website":"http://www.blex.com",
    "wof:name":"Bloomsdale Excvtg Field Off",
    "wof:placetype":"venue"
},
  "geometry": {"coordinates":[-91.756905,37.957987],"type":"Point"}
}