{
  "type": "Feature",
  "properties": {
    "iso:country":"US",
    "sg:address":"4020 Page Blvd",
    "sg:city":"St Louis",
    "sg:classifiers":[
        {
            "category":"Organizations",
            "subcategory":"Religious Organization",
            "type":"Services"
        }
    ],
    "sg:phone":"+1 314 531 0122",
    "sg:postcode":"63113",
    "sg:province":"MO",
    "sg:tags":[
        "church"
    ],
    "wof:name":"Elbethel Church God and Christ",
    "wof:placetype":"venue"
},
  "geometry": {"coordinates":[-90.23683800000001,38.649851],"type":"Point"}
}