{
  "type": "Feature",
  "properties": {
    "iso:country":"US",
    "sg:address":"118 E School St",
    "sg:city":"Bonne Terre",
    "sg:classifiers":[
        {
            "category":"Real Estate",
            "subcategory":"Real Estate Operator",
            "type":"Services"
        }
    ],
    "sg:phone":"+1 573 358 3355",
    "sg:postcode":"63628",
    "sg:province":"MO",
    "sg:tags":[
        "building",
        "nonresidential"
    ],
    "wof:name":"Heritage Hall",
    "wof:placetype":"venue"
},
  "geometry": {"coordinates":[-90.55235999999999,37.922282],"type":"Point"}
}