{
  "type": "Feature",
  "properties": {
    "iso:country":"US",
    "sg:address":"1805 Veterans Memorial Pkwy",
    "sg:city":"St Charles",
    "sg:classifiers":[
        {
            "category":"Restaurant",
            "type":"Food & Drink"
        }
    ],
    "sg:phone":"+1 636 978 7755",
    "sg:postcode":"63385",
    "sg:province":"MO",
    "wof:name":"Ethyl's Wildwood",
    "wof:placetype":"venue"
},
  "geometry": {"coordinates":[-90.819681,38.805792],"type":"Point"}
}