{
  "type": "Feature",
  "properties": {
    "iso:country":"US",
    "sg:address":"214 Morgan St",
    "sg:city":"St Louis",
    "sg:classifiers":[
        {
            "category":"Manufacturing",
            "subcategory":"Food",
            "type":"Manufacturing & Wholesale Goods"
        }
    ],
    "sg:phone":"+1 314 231 9976",
    "sg:postcode":"63102",
    "sg:province":"MO",
    "sg:tags":[
        "brewer"
    ],
    "wof:name":"Morgan Street Brewery",
    "wof:placetype":"venue"
},
  "geometry": {"coordinates":[-90.1825,38.630659],"type":"Point"}
}