{
  "type": "Feature",
  "properties": {
    "iso:country":"US",
    "sg:address":"8463 NW Ridgeline Rd",
    "sg:city":"King City",
    "sg:phone":"+1 660 535 6202",
    "sg:postcode":"64463",
    "sg:province":"MO",
    "sg:tags":[
        "beef",
        "farm",
        "corn",
        "soybean",
        "cattle",
        "feedlot"
    ],
    "wof:name":"Jimmy Hunter",
    "wof:placetype":"venue"
},
  "geometry": {"coordinates":[-94.433747,40.03739],"type":"Point"}
}