{
  "type": "Feature",
  "properties": {
    "iso:country":"US",
    "sg:address":"2106 Oaklawn Dr",
    "sg:city":"Chillicothe",
    "sg:classifiers":[
        {
            "category":"Farming",
            "subcategory":"Farm",
            "type":"Manufacturing & Wholesale Goods"
        }
    ],
    "sg:phone":"+1 660 646 5367",
    "sg:postcode":"64601",
    "sg:province":"MO",
    "sg:tags":[
        "crop",
        "general"
    ],
    "wof:name":"Feeney Farms Inc",
    "wof:placetype":"venue"
},
  "geometry": {"coordinates":[-93.56008199999999,39.811077],"type":"Point"}
}