{
  "type": "Feature",
  "properties": {
    "iso:country":"US",
    "sg:address":"1247 Park Meadow Dr",
    "sg:city":"Fenton",
    "sg:classifiers":[
        {
            "category":"Professional",
            "subcategory":"Computer Services",
            "type":"Services"
        }
    ],
    "sg:phone":"+1 636 343 0002",
    "sg:postcode":"63026",
    "sg:province":"MO",
    "sg:tags":[
        "programing",
        "custom"
    ],
    "wof:name":"Aser Inc",
    "wof:placetype":"venue"
},
  "geometry": {"coordinates":[-90.451369,38.528329],"type":"Point"}
}