{
  "type": "Feature",
  "properties": {
    "iso:country":"US",
    "sg:address":"313 Cherokee St",
    "sg:city":"St Joseph",
    "sg:classifiers":[
        {
            "category":"Retail",
            "subcategory":"Auto Repair",
            "type":"Services"
        }
    ],
    "sg:phone":"+1 816 238 8400",
    "sg:postcode":"64504",
    "sg:province":"MO",
    "sg:tags":[
        "body",
        "automobile",
        "painting"
    ],
    "wof:name":"Pop's Rod Shop",
    "wof:placetype":"venue"
},
  "geometry": {"coordinates":[-94.862616,39.71952],"type":"Point"}
}