{
  "type": "Feature",
  "properties": {
    "iso:country":"US",
    "sg:address":"18720 Stovall Ln",
    "sg:city":"Pacific",
    "sg:classifiers":[
        {
            "category":"Restaurant",
            "type":"Food & Drink"
        },
        {
            "category":"Bars & Pubs",
            "subcategory":"Nightclub",
            "type":"Food & Drink"
        }
    ],
    "sg:phone":"+1 636 405 3024",
    "sg:postcode":"63069",
    "sg:province":"MO",
    "sg:tags":[
        "club",
        "night"
    ],
    "wof:name":"Stovall's Grove Rocl Horse Saloon",
    "wof:placetype":"venue"
},
  "geometry": {"coordinates":[-90.70698299999999,38.549668],"type":"Point"}
}