{
  "type": "Feature",
  "properties": {
    "iso:country":"US",
    "sg:address":"2820 Market St",
    "sg:city":"Saint Louis",
    "sg:classifiers":[
        {
            "category":"Food & Beverages",
            "subcategory":"Groceries & Convenience Stores",
            "type":"Retail Goods"
        }
    ],
    "sg:phone":"+1 314 533 4250",
    "sg:postcode":"63103",
    "sg:province":"MO",
    "wof:name":"Westinghouse Elec Market",
    "wof:placetype":"venue"
},
  "geometry": {"coordinates":[-90.21844400000001,38.631102],"type":"Point"}
}