{
  "type": "Feature",
  "properties": {
    "iso:country":"US",
    "sg:address":"1401 Pine St",
    "sg:city":"Saint Louis",
    "sg:classifiers":[
        {
            "category":"Restaurant",
            "type":"Food & Drink"
        }
    ],
    "sg:phone":"+1 314 621 6698",
    "sg:postcode":"63103",
    "sg:province":"MO",
    "sg:tags":[
        "drinking",
        "eating"
    ],
    "wof:name":"Kellie OTooles",
    "wof:placetype":"venue"
},
  "geometry": {"coordinates":[-90.20188,38.629826],"type":"Point"}
}