{
  "type": "Feature",
  "properties": {
    "iso:country":"US",
    "sg:address":"548 E 395th Rd",
    "sg:city":"Dunnegan",
    "sg:classifiers":[
        {
            "category":"Professional",
            "type":"Services"
        }
    ],
    "sg:phone":"+1 417 654 3515",
    "sg:postcode":"65640",
    "sg:province":"MO",
    "sg:tags":[
        "establishment"
    ],
    "wof:name":"Chickamauga Cherokee",
    "wof:placetype":"venue"
},
  "geometry": {"coordinates":[-93.536193,37.676401],"type":"Point"}
}