{
  "type": "Feature",
  "properties": {
    "iso:country":"US",
    "sg:address":"13208 US Hwy 40",
    "sg:city":"Independence",
    "sg:classifiers":[
        {
            "category":"Retail",
            "subcategory":"Auto Repair",
            "type":"Services"
        }
    ],
    "sg:phone":"+1 816 373 3100",
    "sg:postcode":"64055",
    "sg:province":"MO",
    "sg:tags":[
        "repairing",
        "automobile"
    ],
    "wof:name":"Hurst Imported Car Svc",
    "wof:placetype":"venue"
},
  "geometry": {"coordinates":[-94.422692,39.035986],"type":"Point"}
}