{
  "type": "Feature",
  "properties": {
    "iso:country":"US",
    "sg:address":"15770 N Amity Ct",
    "sg:city":"Platte City",
    "sg:classifiers":[
        {
            "category":"Retail",
            "subcategory":"Portrait Studio",
            "type":"Services"
        }
    ],
    "sg:phone":"+1 816 532 4858",
    "sg:postcode":"64079",
    "sg:province":"MO",
    "sg:tags":[
        "photographer"
    ],
    "sg:website":"www.rudysphotography.com",
    "wof:name":"Rudy's Photography",
    "wof:placetype":"venue"
},
  "geometry": {"coordinates":[-94.68842600000001,39.379868],"type":"Point"}
}