{
  "type": "Feature",
  "properties": {
    "iso:country":"US",
    "sg:address":"620 6th St",
    "sg:city":"Bunker",
    "sg:classifiers":[
        {
            "category":"Government",
            "subcategory":"Office",
            "type":"Public Place"
        }
    ],
    "sg:phone":"+1 573 689 2444",
    "sg:postcode":"63629",
    "sg:province":"MO",
    "sg:tags":[
        "city"
    ],
    "wof:name":"Bunker City Hall",
    "wof:placetype":"venue"
},
  "geometry": {"coordinates":[-91.210055,37.452166],"type":"Point"}
}