{
  "type": "Feature",
  "properties": {
    "iso:country":"US",
    "sg:address":"600 Dairy St",
    "sg:city":"Monett",
    "sg:classifiers":[
        {
            "category":"Professional",
            "type":"Services"
        }
    ],
    "sg:phone":"+1 417 235 5088",
    "sg:postcode":"65708",
    "sg:province":"MO",
    "wof:name":"Lovin Oven",
    "wof:placetype":"venue"
},
  "geometry": {"coordinates":[-93.916884,36.915914],"type":"Point"}
}