{
  "type": "Feature",
  "properties": {
    "iso:country":"US",
    "sg:address":"604 Missouri Ave",
    "sg:city":"West Plains",
    "sg:classifiers":[
        {
            "category":"Retail",
            "subcategory":"Laundry & Dry Cleaning",
            "type":"Services"
        }
    ],
    "sg:phone":"+1 417 256 2003",
    "sg:postcode":"65775",
    "sg:province":"MO",
    "sg:tags":[
        "drycleaning",
        "plant",
        "linen",
        "supply"
    ],
    "wof:name":"Lunas Imperial Dry Cleaners",
    "wof:placetype":"venue"
},
  "geometry": {"coordinates":[-91.85744699999999,36.733587],"type":"Point"}
}