{
  "type": "Feature",
  "properties": {
    "iso:country":"US",
    "sg:address":"601 Co Rd 226",
    "sg:city":"Cape Girardeau",
    "sg:phone":"+1 573 243 4325",
    "sg:postcode":"63701",
    "sg:province":"MO",
    "sg:tags":[
        "farm",
        "corn",
        "soybean"
    ],
    "wof:name":"David Nussbaum",
    "wof:placetype":"venue"
},
  "geometry": {"coordinates":[-89.67241199999999,37.288654],"type":"Point"}
}