{
  "type": "Feature",
  "properties": {
    "iso:country":"US",
    "sg:address":"10812 Arnett Dr",
    "sg:city":"Saint Louis",
    "sg:classifiers":[
        {
            "category":"Professional",
            "type":"Services"
        }
    ],
    "sg:phone":"+1 314 729 7475",
    "sg:postcode":"63123",
    "sg:province":"MO",
    "wof:name":"A M Media Duplication",
    "wof:placetype":"venue"
},
  "geometry": {"coordinates":[-90.339101,38.523249],"type":"Point"}
}