{
  "type": "Feature",
  "properties": {
    "iso:country":"US",
    "sg:address":"3251 Main St",
    "sg:city":"Grandview",
    "sg:classifiers":[
        {
            "category":"Shopping",
            "type":"Retail Goods"
        }
    ],
    "sg:phone":"+1 816 765 2444",
    "sg:postcode":"64030",
    "sg:province":"MO",
    "sg:tags":[
        "merchandise"
    ],
    "wof:name":"Graniteworks",
    "wof:placetype":"venue"
},
  "geometry": {"coordinates":[-94.550191,38.890954],"type":"Point"}
}