{
  "type": "Feature",
  "properties": {
    "iso:country":"US",
    "sg:address":"721 SE 201st Rd",
    "sg:city":"Warrensburg",
    "sg:classifiers":[
        {
            "category":"Manufacturing",
            "subcategory":"Food",
            "type":"Manufacturing & Wholesale Goods"
        },
        {
            "category":"Farming",
            "subcategory":"Farm",
            "type":"Manufacturing & Wholesale Goods"
        }
    ],
    "sg:phone":"+1 660 747 6297",
    "sg:postcode":"64093",
    "sg:province":"MO",
    "sg:tags":[
        "corn",
        "product"
    ],
    "wof:name":"James Wilson",
    "wof:placetype":"venue"
},
  "geometry": {"coordinates":[-93.713329,38.65193],"type":"Point"}
}