{
  "type": "Feature",
  "properties": {
    "iso:country":"US",
    "sg:address":"522 S Prairie St",
    "sg:city":"Maryville",
    "sg:classifiers":[
        {
            "category":"Taxi",
            "type":"Transportation"
        }
    ],
    "sg:phone":"+1 660 582 5680",
    "sg:postcode":"64468",
    "sg:province":"MO",
    "sg:tags":[
        "taxicab"
    ],
    "wof:name":"Cab Co Of Maryville",
    "wof:placetype":"venue"
},
  "geometry": {"coordinates":[-94.868341,40.341864],"type":"Point"}
}