{
  "type": "Feature",
  "properties": {
    "iso:country":"US",
    "sg:address":"555 Beechcraft Ave",
    "sg:city":"Chesterfield",
    "sg:classifiers":[
        {
            "category":"Autos & Motor Vehicles",
            "subcategory":"Automobile Sales",
            "type":"Retail Goods"
        }
    ],
    "sg:phone":"+1 636 536 3811",
    "sg:postcode":"63005",
    "sg:province":"MO",
    "sg:tags":[
        "aircraft"
    ],
    "wof:name":"Federal Aviation Adm Airways",
    "wof:placetype":"venue"
},
  "geometry": {"coordinates":[-90.65178899999999,38.663338],"type":"Point"}
}