{
  "type": "Feature",
  "properties": {
    "addr:full":"1010 N Main St Piedmont MO 63957",
    "addr:housenumber":"1010",
    "addr:postcode":"63957",
    "addr:street":"N Main St",
    "iso:country":"US",
    "sg:address":"1010 N Main St",
    "sg:city":"Piedmont",
    "sg:classifiers":[
        {
            "category":"Autos & Motor Vehicles",
            "subcategory":"Automobile Sales",
            "type":"Retail Goods"
        }
    ],
    "sg:phone":"+1 573 223 4225",
    "sg:postcode":"63957",
    "sg:province":"MO",
    "wof:name":"Ross Ford",
    "wof:placetype":"venue"
},
  "geometry": {"coordinates":[-90.68828999999999,37.163482],"type":"Point"}
}