{
  "type": "Feature",
  "properties": {
    "iso:country":"US",
    "sg:address":"1301 Shamrock Ct",
    "sg:city":"Warrensburg",
    "sg:classifiers":[
        {
            "category":"Health Services",
            "subcategory":"Doctor",
            "type":"Services"
        }
    ],
    "sg:phone":"+1 660 747 6206",
    "sg:postcode":"64093",
    "sg:province":"MO",
    "sg:tags":[
        "dentist",
        "general"
    ],
    "wof:name":"Heath  Chad DDS",
    "wof:placetype":"venue"
},
  "geometry": {"coordinates":[-93.715538,38.749928],"type":"Point"}
}