{
  "type": "Feature",
  "properties": {
    "iso:country":"US",
    "sg:address":"519 Southwest Blvd",
    "sg:city":"Kansas City",
    "sg:classifiers":[
        {
            "category":"Communications",
            "subcategory":"Film & Video Production",
            "type":"Services"
        }
    ],
    "sg:phone":"+1 816 283 3365",
    "sg:postcode":"64108",
    "sg:province":"MO",
    "sg:tags":[
        "picture",
        "industrial",
        "producer",
        "tv",
        "commercial",
        "motion",
        "studio"
    ],
    "wof:name":"Jones Bob Film Production",
    "wof:placetype":"venue"
},
  "geometry": {"coordinates":[-94.591257,39.086268],"type":"Point"}
}