{
  "type": "Feature",
  "properties": {
    "iso:country":"US",
    "sg:address":"1905 Winged Foot Dr",
    "sg:city":"Nixa",
    "sg:classifiers":[
        {
            "category":"Retail",
            "subcategory":"Repair Shop",
            "type":"Services"
        }
    ],
    "sg:phone":"+1 417 485 4334",
    "sg:postcode":"65714",
    "sg:province":"MO",
    "sg:tags":[
        "equipment",
        "dental",
        "refinishing"
    ],
    "wof:name":"Midwest Dental",
    "wof:placetype":"venue"
},
  "geometry": {"coordinates":[-93.24740300000001,37.066868],"type":"Point"}
}