{
  "type": "Feature",
  "properties": {
    "iso:country":"US",
    "sg:address":"1127 Main St",
    "sg:city":"Blue Springs",
    "sg:classifiers":[
        {
            "category":"Health Services",
            "subcategory":"Doctor",
            "type":"Services"
        }
    ],
    "sg:phone":"+1 816 229 1941",
    "sg:postcode":"64015",
    "sg:province":"MO",
    "sg:tags":[
        "medical"
    ],
    "wof:name":"Blue Sprng Chrpractic Hlth Ctr",
    "wof:placetype":"venue"
},
  "geometry": {"coordinates":[-94.278813,39.018482],"type":"Point"}
}