{
  "type": "Feature",
  "properties": {
    "iso:country":"US",
    "sg:address":"6191 Co Rd 290",
    "sg:city":"Carl Junction",
    "sg:classifiers":[
        {
            "category":"Autos & Motor Vehicles",
            "subcategory":"Boat Sales",
            "type":"Retail Goods"
        }
    ],
    "sg:phone":"+1 417 627 9276",
    "sg:postcode":"64834",
    "sg:province":"MO",
    "sg:tags":[
        "top",
        "upholstery",
        "cover"
    ],
    "wof:name":"J & D Custom Covers",
    "wof:placetype":"venue"
},
  "geometry": {"coordinates":[-94.581186,37.147034],"type":"Point"}
}