{
  "type": "Feature",
  "properties": {
    "iso:country":"US",
    "sg:address":"7369 Amherst Ave",
    "sg:city":"St Louis",
    "sg:classifiers":[
        {
            "category":"Health Services",
            "subcategory":"Clinic",
            "type":"Services"
        }
    ],
    "sg:phone":"+1 314 727 5646",
    "sg:postcode":"63130",
    "sg:province":"MO",
    "sg:tags":[
        "home",
        "care"
    ],
    "wof:name":"Exquisite Home Care Svc",
    "wof:placetype":"venue"
},
  "geometry": {"coordinates":[-90.327938,38.662014],"type":"Point"}
}