{
  "type": "Feature",
  "properties": {
    "iso:country":"US",
    "sg:address":"740 S Westwood Blvd",
    "sg:city":"Poplar Bluff",
    "sg:classifiers":[
        {
            "category":"Home & Garden",
            "subcategory":"Furniture",
            "type":"Retail Goods"
        }
    ],
    "sg:phone":"+1 573 686 2733",
    "sg:postcode":"63901",
    "sg:province":"MO",
    "wof:name":"Oak Store",
    "wof:placetype":"venue"
},
  "geometry": {"coordinates":[-90.40941599999999,36.751664],"type":"Point"}
}