{
  "type": "Feature",
  "properties": {
    "iso:country":"US",
    "sg:address":"2716 Church Rd",
    "sg:city":"Saint Charles",
    "sg:phone":"+1 636 258 3634",
    "sg:postcode":"63301",
    "sg:province":"MO",
    "sg:tags":[
        "farm",
        "corn"
    ],
    "wof:name":"Steve Boerding",
    "wof:placetype":"venue"
},
  "geometry": {"coordinates":[-90.47772999999999,38.86839],"type":"Point"}
}