{
  "type": "Feature",
  "properties": {
    "iso:country":"US",
    "sg:address":"2538 Alleghany Rd",
    "sg:city":"Cuba",
    "sg:classifiers":[
        {
            "category":"Utilities",
            "subcategory":"Water",
            "type":"Services"
        }
    ],
    "sg:phone":"+1 573 885 3320",
    "sg:postcode":"65453",
    "sg:province":"MO",
    "sg:tags":[
        "supply"
    ],
    "wof:name":"Indian Hills Utilities",
    "wof:placetype":"venue"
},
  "geometry": {"coordinates":[-91.443399,38.086168],"type":"Point"}
}