{
  "type": "Feature",
  "properties": {
    "iso:country":"US",
    "sg:address":"17877 State Hwy 32",
    "sg:city":"Sainte Genevieve",
    "sg:classifiers":[
        {
            "category":"Wholesale",
            "subcategory":"Apparel",
            "type":"Manufacturing & Wholesale Goods"
        }
    ],
    "sg:phone":"+1 573 883 7477",
    "sg:postcode":"63670",
    "sg:province":"MO",
    "sg:tags":[
        "operator",
        "piece",
        "local",
        "trucking"
    ],
    "wof:name":"Beelman Truck Co",
    "wof:placetype":"venue"
},
  "geometry": {"coordinates":[-90.13059,37.936852],"type":"Point"}
}