{
  "type": "Feature",
  "properties": {
    "iso:country":"US",
    "sg:address":"506 Cool Dell Ct",
    "sg:city":"Ballwin",
    "sg:classifiers":[
        {
            "category":"Banks & Credit Unions",
            "subcategory":"Investment Brokerage",
            "type":"Services"
        }
    ],
    "sg:phone":"+1 636 527 3299",
    "sg:postcode":"63021",
    "sg:province":"MO",
    "sg:tags":[
        "security"
    ],
    "wof:name":"Design Funding Group",
    "wof:placetype":"venue"
},
  "geometry": {"coordinates":[-90.480825,38.585422],"type":"Point"}
}