{
  "type": "Feature",
  "properties": {
    "iso:country":"US",
    "sg:address":"3350 Greenwood Blvd",
    "sg:city":"Saint Louis",
    "sg:classifiers":[
        {
            "category":"Professional",
            "subcategory":"Lawyer & Legal Services",
            "type":"Services"
        }
    ],
    "sg:phone":"+1 314 645 5900",
    "sg:postcode":"63143",
    "sg:province":"MO",
    "sg:website":"www.commonsenselaw.net",
    "wof:name":"O'gorman & Sandroni Attorney of Law",
    "wof:placetype":"venue"
},
  "geometry": {"coordinates":[-90.31744500000001,38.607341],"type":"Point"}
}