{
  "type": "Feature",
  "properties": {
    "iso:country":"US",
    "sg:address":"17 S Mount Auburn Rd",
    "sg:city":"Cape Girardeau",
    "sg:classifiers":[
        {
            "category":"Banks & Credit Unions",
            "subcategory":"Bank",
            "type":"Services"
        }
    ],
    "sg:phone":"+1 573 335 9755",
    "sg:postcode":"63703",
    "sg:province":"MO",
    "sg:website":"www.1stcombank.com",
    "wof:name":"First Community Bank",
    "wof:placetype":"venue"
},
  "geometry": {"coordinates":[-89.57405900000001,37.306648],"type":"Point"}
}