{
  "type": "Feature",
  "properties": {
    "iso:country":"US",
    "sg:address":"76 Lake Forest Dr",
    "sg:city":"St Louis",
    "sg:classifiers":[
        {
            "category":"Banks & Credit Unions",
            "subcategory":"Investment Brokerage",
            "type":"Services"
        }
    ],
    "sg:phone":"+1 314 645 6010",
    "sg:postcode":"63117",
    "sg:province":"MO",
    "sg:tags":[
        "consultant",
        "financing"
    ],
    "wof:name":"Sterling Resources",
    "wof:placetype":"venue"
},
  "geometry": {"coordinates":[-90.33838799999999,38.632933],"type":"Point"}
}