{
  "type": "Feature",
  "properties": {
    "iso:country":"US",
    "sg:address":"17601 US Hwy 40",
    "sg:city":"Independence",
    "sg:classifiers":[
        {
            "category":"Health Services",
            "subcategory":"Doctor",
            "type":"Services"
        }
    ],
    "sg:phone":"+1 816 836 8130",
    "sg:postcode":"64055",
    "sg:province":"MO",
    "sg:tags":[
        "dr"
    ],
    "wof:name":"Gillbanks Marjon Inc",
    "wof:placetype":"venue"
},
  "geometry": {"coordinates":[-94.370323,39.033809],"type":"Point"}
}