{
  "type": "Feature",
  "properties": {
    "iso:country":"US",
    "sg:address":"601 State Rd Aa",
    "sg:city":"Roach",
    "sg:classifiers":[
        {
            "category":"Retail",
            "subcategory":"Repair Shop",
            "type":"Services"
        }
    ],
    "sg:phone":"+1 573 346 3815",
    "sg:postcode":"65787",
    "sg:province":"MO",
    "sg:tags":[
        "welding"
    ],
    "wof:name":"Central Metal Products",
    "wof:placetype":"venue"
},
  "geometry": {"coordinates":[-92.835459,37.993116],"type":"Point"}
}