{
  "type": "Feature",
  "properties": {
    "iso:country":"US",
    "sg:address":"4800 Carter Ave",
    "sg:city":"Saint Louis",
    "sg:classifiers":[
        {
            "category":"Personal",
            "subcategory":"Barber",
            "type":"Services"
        }
    ],
    "sg:phone":"+1 314 381 0025",
    "sg:postcode":"63115",
    "sg:province":"MO",
    "wof:name":"Moe's Barbershop",
    "wof:placetype":"venue"
},
  "geometry": {"coordinates":[-90.239921,38.681915],"type":"Point"}
}