{
  "type": "Feature",
  "properties": {
    "iso:country":"US",
    "sg:address":"144 7th St",
    "sg:city":"Hillsboro",
    "sg:classifiers":[
        {
            "category":"Home & Garden",
            "subcategory":"Hardware",
            "type":"Retail Goods"
        }
    ],
    "sg:phone":"+1 636 797 2034",
    "sg:postcode":"63050",
    "sg:province":"MO",
    "wof:name":"Hillsboro City Hardware",
    "wof:placetype":"venue"
},
  "geometry": {"coordinates":[-90.561226,38.236199],"type":"Point"}
}