{
  "type": "Feature",
  "properties": {
    "addr:full":"3271 E Battlefield Rd Springfield MO 65804",
    "addr:housenumber":"3271",
    "addr:postcode":"65804",
    "addr:street":"E Battlefield Rd",
    "iso:country":"US",
    "sg:address":"3271 E Battlefield Rd",
    "sg:city":"Springfield",
    "sg:classifiers":[
        {
            "category":"Banks & Credit Unions",
            "subcategory":"Bank",
            "type":"Services"
        }
    ],
    "sg:phone":"+1 417 882 2222",
    "sg:postcode":"65804",
    "sg:province":"MO",
    "wof:name":"Union Planters Bank",
    "wof:placetype":"venue"
},
  "geometry": {"coordinates":[-93.229223,37.15828],"type":"Point"}
}