{
  "type": "Feature",
  "properties": {
    "iso:country":"US",
    "sg:address":"12847 W Hwy Bb",
    "sg:city":"Rocheport",
    "sg:classifiers":[
        {
            "category":"Restaurant",
            "type":"Food & Drink"
        }
    ],
    "sg:menulink":"http://www.allmenus.com/mo/katy/185259-les-bourgeois-vineyards-blufftop-bistro/menu/",
    "sg:phone":"+1 573 698 2300",
    "sg:postcode":"65279",
    "sg:province":"MO",
    "sg:tags":[
        "american"
    ],
    "wof:name":"Les Bourgeois Vineyards Blufftop Bistro",
    "wof:placetype":"venue"
},
  "geometry": {"coordinates":[-92.534057,38.968208],"type":"Point"}
}