{
  "type": "Feature",
  "properties": {
    "iso:country":"US",
    "sg:address":"300 W Saint Francis St",
    "sg:city":"Kennett",
    "sg:classifiers":[
        {
            "category":"Organizations",
            "subcategory":"Religious Organization",
            "type":"Services"
        }
    ],
    "sg:phone":"+1 573 888 4689",
    "sg:postcode":"63841",
    "sg:province":"MO",
    "sg:tags":[
        "church"
    ],
    "sg:website":"www.fbckenn.com",
    "wof:name":"First Baptist Church Prayer",
    "wof:placetype":"venue"
},
  "geometry": {"coordinates":[-89.96238099999999,36.798243],"type":"Point"}
}