{
  "type": "Feature",
  "properties": {
    "iso:country":"US",
    "sg:address":"702 S Commercial St",
    "sg:city":"Branson",
    "sg:classifiers":[
        {
            "category":"Travel",
            "subcategory":"Hotels & Motels",
            "type":"Entertainment"
        },
        {
            "category":"Travel",
            "subcategory":"Resort",
            "type":"Entertainment"
        }
    ],
    "sg:phone":"+1 417 334 3372",
    "sg:postcode":"65616",
    "sg:province":"MO",
    "wof:name":"Rain's Motel",
    "wof:placetype":"venue"
},
  "geometry": {"coordinates":[-93.217094,36.638557],"type":"Point"}
}