{
  "type": "Feature",
  "properties": {
    "iso:country":"US",
    "sg:address":"6207 NW Bell Rd",
    "sg:city":"Kansas City",
    "sg:classifiers":[
        {
            "category":"School Buses",
            "type":"Transportation"
        }
    ],
    "sg:phone":"+1 816 741 4023",
    "sg:postcode":"64152",
    "sg:province":"MO",
    "wof:name":"Laidlaw Educational",
    "wof:placetype":"venue"
},
  "geometry": {"coordinates":[-94.68709699999999,39.208487],"type":"Point"}
}