{
  "type": "Feature",
  "properties": {
    "iso:country":"US",
    "sg:address":"2101 SE Hamblen Rd",
    "sg:city":"Lees Summit",
    "sg:classifiers":[
        {
            "category":"Building & Trades",
            "subcategory":"Construction",
            "type":"Services"
        }
    ],
    "sg:phone":"+1 816 969 7710",
    "sg:postcode":"64082",
    "sg:province":"MO",
    "sg:tags":[
        "marking",
        "maintenance",
        "parking"
    ],
    "wof:name":"Lees Summit Public Works Dept",
    "wof:placetype":"venue"
},
  "geometry": {"coordinates":[-94.35648500000001,38.875359],"type":"Point"}
}