{
  "type": "Feature",
  "properties": {
    "iso:country":"US",
    "sg:address":"340 W 5 St",
    "sg:city":"Kansas City",
    "sg:classifiers":[
        {
            "category":"Manufacturing",
            "subcategory":"Chemicals & Compounds",
            "type":"Manufacturing & Wholesale Goods"
        }
    ],
    "sg:phone":"+1 816 471 3313",
    "sg:postcode":"64105",
    "sg:province":"MO",
    "sg:tags":[
        "paint",
        "varnish",
        "allied",
        "product"
    ],
    "sg:website":"www.colonialpatterns.com",
    "wof:name":"Colonial Patterns Inc",
    "wof:placetype":"venue"
},
  "geometry": {"coordinates":[-94.588155,39.107622],"type":"Point"}
}