{
  "type": "Feature",
  "properties": {
    "iso:country":"US",
    "sg:address":"201 W Capitol Ave",
    "sg:city":"Jefferson City",
    "sg:classifiers":[
        {
            "category":"Communications",
            "subcategory":"News Services",
            "type":"Services"
        }
    ],
    "sg:phone":"+1 573 634 3565",
    "sg:postcode":"65101",
    "sg:province":"MO",
    "sg:tags":[
        "syndicate"
    ],
    "wof:name":"Kansas City Star Company",
    "wof:placetype":"venue"
},
  "geometry": {"coordinates":[-92.17397699999999,38.579969],"type":"Point"}
}