{
  "type": "Feature",
  "properties": {
    "iso:country":"US",
    "sg:address":"11311 E 13 St S",
    "sg:city":"Independence",
    "sg:classifiers":[
        {
            "category":"Professional",
            "type":"Services"
        }
    ],
    "sg:phone":"+1 816 461 2119",
    "sg:postcode":"64052",
    "sg:province":"MO",
    "wof:name":"Marlin J Cullens",
    "wof:placetype":"venue"
},
  "geometry": {"coordinates":[-94.443375,39.092968],"type":"Point"}
}