{
  "type": "Feature",
  "properties": {
    "addr:full":"11977 Old St Charles Rd Bridgeton MO 63044",
    "addr:housenumber":"11977",
    "addr:postcode":"63044",
    "addr:street":"Old St Charles Rd",
    "iso:country":"US",
    "sg:address":"11977 Old St Charles Rd",
    "sg:city":"Bridgeton",
    "sg:classifiers":[
        {
            "category":"Manufacturing",
            "subcategory":"Signs",
            "type":"Manufacturing & Wholesale Goods"
        }
    ],
    "sg:phone":"+1 314 344 4400",
    "sg:postcode":"63044",
    "sg:province":"MO",
    "sg:website":"www.fastsigns.com",
    "wof:name":"Fastsigns",
    "wof:placetype":"venue"
},
  "geometry": {"coordinates":[-90.42913299999999,38.73923],"type":"Point"}
}