{
  "type": "Feature",
  "properties": {
    "iso:country":"US",
    "sg:address":"1913 E 20th St",
    "sg:city":"Joplin",
    "sg:classifiers":[
        {
            "category":"Professional",
            "subcategory":"Accounting & Tax Preparation",
            "type":"Services"
        }
    ],
    "sg:phone":"+1 417 623 6900",
    "sg:postcode":"64804",
    "sg:province":"MO",
    "wof:name":"Koller Judy",
    "wof:placetype":"venue"
},
  "geometry": {"coordinates":[-94.49347299999999,37.069347],"type":"Point"}
}