{
  "type": "Feature",
  "properties": {
    "iso:country":"US",
    "sg:address":"5992 Howdershell Rd",
    "sg:city":"Hazelwood",
    "sg:classifiers":[
        {
            "category":"Professional",
            "type":"Services"
        }
    ],
    "sg:phone":"+1 314 895 4005",
    "sg:postcode":"63042",
    "sg:province":"MO",
    "sg:tags":[
        "establishment"
    ],
    "wof:name":"Midwest Interstate Railhead",
    "wof:placetype":"venue"
},
  "geometry": {"coordinates":[-90.380616,38.782864],"type":"Point"}
}