{
  "type": "Feature",
  "properties": {
    "iso:country":"US",
    "sg:address":"106 W 7th St",
    "sg:city":"Sedalia",
    "sg:classifiers":[
        {
            "category":"Professional",
            "subcategory":"Lawyer & Legal Services",
            "type":"Services"
        }
    ],
    "sg:phone":"+1 660 826 9200",
    "sg:postcode":"65301",
    "sg:province":"MO",
    "wof:name":"Smith Carmen L LLC",
    "wof:placetype":"venue"
},
  "geometry": {"coordinates":[-93.229311,38.70527],"type":"Point"}
}