{
  "type": "Feature",
  "properties": {
    "iso:country":"US",
    "sg:address":"3556 S Culpepper Cir",
    "sg:city":"Springfield",
    "sg:classifiers":[
        {
            "category":"Real Estate",
            "subcategory":"Real Estate Services",
            "type":"Services"
        },
        {
            "category":"Real Estate",
            "subcategory":"Real Estate Operator",
            "type":"Services"
        }
    ],
    "sg:phone":"+1 417 883 7887",
    "sg:postcode":"65804",
    "sg:province":"MO",
    "sg:tags":[
        "vacancy",
        "apartment",
        "rental",
        "listing"
    ],
    "wof:name":"Hamilton Corporation",
    "wof:placetype":"venue"
},
  "geometry": {"coordinates":[-93.27611,37.148929],"type":"Point"}
}