{
  "type": "Feature",
  "properties": {
    "iso:country":"US",
    "sg:address":"13852 US Hwy 160",
    "sg:city":"Forsyth",
    "sg:classifiers":[
        {
            "category":"Health Services",
            "subcategory":"Doctor",
            "type":"Services"
        }
    ],
    "sg:phone":"+1 417 546 3500",
    "sg:postcode":"65653",
    "sg:province":"MO",
    "sg:tags":[
        "physician",
        "surgeon"
    ],
    "wof:name":"Forsyth Medical Care",
    "wof:placetype":"venue"
},
  "geometry": {"coordinates":[-93.127803,36.726531],"type":"Point"}
}