{
  "type": "Feature",
  "properties": {
    "iso:country":"US",
    "sg:address":"1603 McCausland Ave",
    "sg:city":"St Louis",
    "sg:classifiers":[
        {
            "category":"Restaurant",
            "type":"Food & Drink"
        }
    ],
    "sg:phone":"+1 314 333 3301",
    "sg:postcode":"63117",
    "sg:province":"MO",
    "wof:name":"Mihalis Chop House",
    "wof:placetype":"venue"
},
  "geometry": {"coordinates":[-90.307998,38.622891],"type":"Point"}
}