{
  "type": "Feature",
  "properties": {
    "iso:country":"US",
    "sg:address":"18207 Edison Ave",
    "sg:city":"Chesterfield",
    "sg:classifiers":[
        {
            "category":"Professional",
            "subcategory":"Engineering",
            "type":"Services"
        }
    ],
    "sg:phone":"+1 636 532 1003",
    "sg:postcode":"63005",
    "sg:province":"MO",
    "sg:tags":[
        "engineer",
        "integration",
        "system"
    ],
    "sg:website":"http://www.respmech.com",
    "wof:name":"Response Mechanics Inc",
    "wof:placetype":"venue"
},
  "geometry": {"coordinates":[-90.644519,38.66415],"type":"Point"}
}