{
  "type": "Feature",
  "properties": {
    "iso:country":"US",
    "sg:address":"20896 US Hwy 160",
    "sg:city":"Forsyth",
    "sg:classifiers":[
        {
            "category":"Organizations",
            "subcategory":"Religious Organization",
            "type":"Services"
        }
    ],
    "sg:phone":"+1 417 546 3650",
    "sg:postcode":"65653",
    "sg:province":"MO",
    "wof:name":"Forythe Trnty Chrch of Nzerene",
    "wof:placetype":"venue"
},
  "geometry": {"coordinates":[-93.051343,36.694831],"type":"Point"}
}