{
  "type": "Feature",
  "properties": {
    "iso:country":"US",
    "sg:address":"217 Lark Hill Ln",
    "sg:city":"Ballwin",
    "sg:classifiers":[
        {
            "category":"Building & Trades",
            "subcategory":"Plumbing",
            "type":"Services"
        }
    ],
    "sg:phone":"+1 314 869 1550",
    "sg:postcode":"63021",
    "sg:province":"MO",
    "sg:tags":[
        "plumber",
        "industrial",
        "contractors-commercial"
    ],
    "wof:name":"Joseph P Grimes Plumbing Repairs",
    "wof:placetype":"venue"
},
  "geometry": {"coordinates":[-90.536231,38.588576],"type":"Point"}
}