{
  "type": "Feature",
  "properties": {
    "iso:country":"US",
    "sg:address":"5661 Telegraph Rd",
    "sg:city":"St Louis",
    "sg:classifiers":[
        {
            "category":"Health Services",
            "subcategory":"Podiatrist",
            "type":"Services"
        }
    ],
    "sg:phone":"+1 314 846 6030",
    "sg:postcode":"63129",
    "sg:province":"MO",
    "wof:name":"Oakville Podiatric Center",
    "wof:placetype":"venue"
},
  "geometry": {"coordinates":[-90.305539,38.4687],"type":"Point"}
}