{
  "type": "Feature",
  "properties": {
    "iso:country":"US",
    "sg:address":"318 W Meramec St",
    "sg:city":"Pacific",
    "sg:classifiers":[
        {
            "category":"Organizations",
            "subcategory":"Community Association",
            "type":"Services"
        }
    ],
    "sg:phone":"+1 636 257 3298",
    "sg:postcode":"63069",
    "sg:province":"MO",
    "sg:tags":[
        "fraternal"
    ],
    "wof:name":"Pacific American Legion",
    "wof:placetype":"venue"
},
  "geometry": {"coordinates":[-90.74502699999999,38.477112],"type":"Point"}
}