{
  "type": "Feature",
  "properties": {
    "iso:country":"US",
    "sg:address":"2136 William St",
    "sg:city":"Cape Girardeau",
    "sg:classifiers":[
        {
            "category":"Cinema",
            "subcategory":"Movie Rental",
            "type":"Entertainment"
        }
    ],
    "sg:phone":"+1 573 339 0778",
    "sg:postcode":"63703",
    "sg:province":"MO",
    "sg:tags":[
        "leasing",
        "video",
        "disc",
        "tape"
    ],
    "sg:website":"www.gohastings.com",
    "wof:name":"Hastings Books Music Video",
    "wof:placetype":"venue"
},
  "geometry": {"coordinates":[-89.547331,37.302991],"type":"Point"}
}