{
  "type": "Feature",
  "properties": {
    "iso:country":"US",
    "sg:address":"182 Starling Rd",
    "sg:city":"Olean",
    "sg:classifiers":[
        {
            "category":"Manufacturing",
            "subcategory":"Signs",
            "type":"Manufacturing & Wholesale Goods"
        }
    ],
    "sg:phone":"+1 573 392 7020",
    "sg:postcode":"65064",
    "sg:province":"MO",
    "sg:tags":[
        "specialty",
        "mfg"
    ],
    "wof:name":"Sign Decor By Richard Rose",
    "wof:placetype":"venue"
},
  "geometry": {"coordinates":[-92.468468,38.41102],"type":"Point"}
}