{
  "type": "Feature",
  "properties": {
    "iso:country":"US",
    "sg:address":"603 Walnut St",
    "sg:city":"Barnett",
    "sg:classifiers":[
        {
            "category":"Building & Trades",
            "subcategory":"Landscaping Services",
            "type":"Services"
        }
    ],
    "sg:phone":"+1 573 392 4185",
    "sg:postcode":"65075",
    "sg:province":"MO",
    "sg:tags":[
        "tree"
    ],
    "wof:name":"Edgar & Sons Tree Svc",
    "wof:placetype":"venue"
},
  "geometry": {"coordinates":[-92.26750699999999,38.253954],"type":"Point"}
}