{
  "type": "Feature",
  "properties": {
    "iso:country":"US",
    "sg:address":"11039 N Harrison St",
    "sg:city":"Kansas City",
    "sg:classifiers":[
        {
            "category":"Education",
            "subcategory":"Special Training",
            "type":"Public Place"
        }
    ],
    "sg:phone":"+1 816 734 4606",
    "sg:postcode":"64155",
    "sg:province":"MO",
    "wof:name":"Voice To Hands Interpreting",
    "wof:placetype":"venue"
},
  "geometry": {"coordinates":[-94.56662300000001,39.294027],"type":"Point"}
}