{
  "type": "Feature",
  "properties": {
    "iso:country":"US",
    "sg:address":"2527 State Highway 248",
    "sg:city":"Branson",
    "sg:classifiers":[
        {
            "category":"Place Of Worship",
            "subcategory":"Church",
            "type":"Public Place"
        },
        {
            "category":"Place Of Worship",
            "type":"Public Place"
        },
        {
            "category":"Organizations",
            "subcategory":"Religious Organization",
            "type":"Services"
        }
    ],
    "sg:phone":"+1 417 339 4041",
    "sg:postcode":"65616",
    "sg:province":"MO",
    "sg:tags":[
        "god",
        "god-independent",
        "churches-assemblies"
    ],
    "sg:website":"http://www.trilakescenter.com",
    "wof:name":"Trike Lake Church",
    "wof:placetype":"venue"
},
  "geometry": {"coordinates":[-93.251721,36.675862],"type":"Point"}
}