{
  "type": "Feature",
  "properties": {
    "iso:country":"US",
    "sg:address":"1360 S 5th St",
    "sg:city":"Saint Charles",
    "sg:classifiers":[
        {
            "category":"Insurance",
            "subcategory":"Insurance Agent",
            "type":"Services"
        }
    ],
    "sg:phone":"+1 636 947 9555",
    "sg:postcode":"63301",
    "sg:province":"MO",
    "wof:name":"Hunter Insurance Services",
    "wof:placetype":"venue"
},
  "geometry": {"coordinates":[-90.493611,38.770026],"type":"Point"}
}