{
  "type": "Feature",
  "properties": {
    "iso:country":"US",
    "sg:address":"1613 S Madison St",
    "sg:city":"Webb City",
    "sg:classifiers":[
        {
            "category":"Restaurant",
            "type":"Food & Drink"
        }
    ],
    "sg:menulink":"http://www.allmenus.com/mo/joplin/201691-sonic/menu/",
    "sg:phone":"+1 417 673 3033",
    "sg:postcode":"64870",
    "sg:province":"MO",
    "sg:tags":[
        "burger",
        "american"
    ],
    "wof:name":"Sonic",
    "wof:placetype":"venue"
},
  "geometry": {"coordinates":[-94.47538,37.12881],"type":"Point"}
}