{
  "type": "Feature",
  "properties": {
    "iso:country":"US",
    "sg:address":"5902 E Red Bridge Rd",
    "sg:city":"Kansas City",
    "sg:classifiers":[
        {
            "category":"Restaurant",
            "type":"Food & Drink"
        }
    ],
    "sg:phone":"+1 816 931 3463",
    "sg:postcode":"64134",
    "sg:province":"MO",
    "wof:name":"Kansas City Ind Restaurant",
    "wof:placetype":"venue"
},
  "geometry": {"coordinates":[-94.52000200000001,38.923951],"type":"Point"}
}