{
  "type": "Feature",
  "properties": {
    "iso:country":"US",
    "sg:address":"670 W Village St",
    "sg:city":"Springfield",
    "sg:classifiers":[
        {
            "category":"Organizations",
            "subcategory":"Community Association",
            "type":"Services"
        }
    ],
    "sg:phone":"+1 417 883 3263",
    "sg:postcode":"65807",
    "sg:province":"MO",
    "wof:name":"Past Dst 26h Governors Lions",
    "wof:placetype":"venue"
},
  "geometry": {"coordinates":[-93.303805,37.150784],"type":"Point"}
}