{
  "type": "Feature",
  "properties": {
    "iso:country":"US",
    "sg:address":"605 Old Ballas Rd",
    "sg:city":"St Louis",
    "sg:classifiers":[
        {
            "category":"Health Services",
            "subcategory":"Health Practitioner",
            "type":"Services"
        }
    ],
    "sg:phone":"+1 314 432 1500",
    "sg:postcode":"63141",
    "sg:province":"MO",
    "sg:tags":[
        "therapist",
        "physical"
    ],
    "wof:name":"Town & Country Physical Thrpy",
    "wof:placetype":"venue"
},
  "geometry": {"coordinates":[-90.43863,38.668237],"type":"Point"}
}