{
  "type": "Feature",
  "properties": {
    "iso:country":"US",
    "sg:address":"1237 S Range Line Rd",
    "sg:city":"Joplin",
    "sg:classifiers":[
        {
            "category":"Banks & Credit Unions",
            "subcategory":"Bank",
            "type":"Services"
        }
    ],
    "sg:phone":"+1 417 782 2274",
    "sg:postcode":"64801",
    "sg:province":"MO",
    "sg:tags":[
        "depository",
        "banking"
    ],
    "wof:name":"Check Cashers",
    "wof:placetype":"venue"
},
  "geometry": {"coordinates":[-94.477509,37.076971],"type":"Point"}
}