{
  "type": "Feature",
  "properties": {
    "iso:country":"US",
    "sg:address":"101 Cedar Ln",
    "sg:city":"Steelville",
    "sg:classifiers":[
        {
            "category":"Organizations",
            "subcategory":"Community Association",
            "type":"Services"
        }
    ],
    "sg:phone":"+1 573 775 2515",
    "sg:postcode":"65565",
    "sg:province":"MO",
    "sg:tags":[
        "club"
    ],
    "wof:name":"Veterans Of Foreign Wars",
    "wof:placetype":"venue"
},
  "geometry": {"coordinates":[-91.377657,37.952454],"type":"Point"}
}