{
  "type": "Feature",
  "properties": {
    "iso:country":"US",
    "sg:address":"800 W 87 St",
    "sg:city":"Kansas City",
    "sg:classifiers":[
        {
            "category":"Manufacturing",
            "subcategory":"Printing",
            "type":"Manufacturing & Wholesale Goods"
        }
    ],
    "sg:phone":"+1 816 444 2735",
    "sg:postcode":"64114",
    "sg:province":"MO",
    "sg:tags":[
        "periodical"
    ],
    "wof:name":"Mothership",
    "wof:placetype":"venue"
},
  "geometry": {"coordinates":[-94.59851,38.970876],"type":"Point"}
}