{
  "type": "Feature",
  "properties": {
    "iso:country":"US",
    "sg:address":"1325 Queens Ct",
    "sg:city":"Saint Peters",
    "sg:classifiers":[
        {
            "category":"Health Services",
            "subcategory":"Doctor",
            "type":"Services"
        }
    ],
    "sg:phone":"+1 636 970 1500",
    "sg:postcode":"63376",
    "sg:province":"MO",
    "wof:name":"Saint Peters Square Fmly Dntl",
    "wof:placetype":"venue"
},
  "geometry": {"coordinates":[-90.58615399999999,38.755875],"type":"Point"}
}