{
  "type": "Feature",
  "properties": {
    "iso:country":"US",
    "sg:address":"12401 E 43rd St S",
    "sg:city":"Independence",
    "sg:classifiers":[
        {
            "category":"Insurance",
            "subcategory":"Hazard Insurance",
            "type":"Services"
        }
    ],
    "sg:phone":"+1 816 886 0013",
    "sg:postcode":"64055",
    "sg:province":"MO",
    "sg:tags":[
        "commercial",
        "business"
    ],
    "wof:name":"Dorland Insurance",
    "wof:placetype":"venue"
},
  "geometry": {"coordinates":[-94.433823,39.04356],"type":"Point"}
}