{
  "type": "Feature",
  "properties": {
    "iso:country":"US",
    "sg:address":"285 Pear Tree Rd",
    "sg:city":"Troy",
    "sg:classifiers":[
        {
            "category":"Building & Trades",
            "subcategory":"Construction",
            "type":"Services"
        }
    ],
    "sg:phone":"+1 866 372 0365",
    "sg:postcode":"63379",
    "sg:province":"MO",
    "sg:tags":[
        "insulation",
        "contractor"
    ],
    "wof:name":"Inspection Pros",
    "wof:placetype":"venue"
},
  "geometry": {"coordinates":[-91.014988,38.938849],"type":"Point"}
}