{
  "type": "Feature",
  "properties": {
    "iso:country":"US",
    "sg:address":"8953 Windom Ave",
    "sg:city":"Saint Louis",
    "sg:classifiers":[
        {
            "category":"Building & Trades",
            "subcategory":"Construction",
            "type":"Services"
        }
    ],
    "sg:phone":"+1 314 428 4548",
    "sg:postcode":"63114",
    "sg:province":"MO",
    "sg:tags":[
        "hanging",
        "contractor"
    ],
    "wof:name":"Martin Allen Painting",
    "wof:placetype":"venue"
},
  "geometry": {"coordinates":[-90.35260599999999,38.708419],"type":"Point"}
}