{
  "type": "Feature",
  "properties": {
    "iso:country":"US",
    "sg:address":"1491 Arlington Ave",
    "sg:city":"Saint Louis",
    "sg:classifiers":[
        {
            "category":"Professional",
            "type":"Services"
        }
    ],
    "sg:phone":"+1 314 367 0175",
    "sg:postcode":"63112",
    "sg:province":"MO",
    "wof:name":"Administrative Loan Services",
    "wof:placetype":"venue"
},
  "geometry": {"coordinates":[-90.271432,38.666299],"type":"Point"}
}