{
  "type": "Feature",
  "properties": {
    "iso:country":"US",
    "sg:address":"700 N 2nd St",
    "sg:city":"Saint Louis",
    "sg:classifiers":[
        {
            "category":"Bars & Pubs",
            "type":"Food & Drink"
        }
    ],
    "sg:phone":"+1 314 241 1720",
    "sg:postcode":"63102",
    "sg:province":"MO",
    "wof:name":"Saint Louis Heart Breakers",
    "wof:placetype":"venue"
},
  "geometry": {"coordinates":[-90.184389,38.630089],"type":"Point"}
}