{
  "type": "Feature",
  "properties": {
    "iso:country":"US",
    "sg:address":"6520 Clayton Rd",
    "sg:city":"Saint Louis",
    "sg:classifiers":[
        {
            "category":"Health Services",
            "subcategory":"Health Practitioner",
            "type":"Services"
        }
    ],
    "sg:phone":"+1 314 645 4499",
    "sg:postcode":"63117",
    "sg:province":"MO",
    "wof:name":"Hillel Abramson",
    "wof:placetype":"venue"
},
  "geometry": {"coordinates":[-90.313745,38.634227],"type":"Point"}
}