{
  "type": "Feature",
  "properties": {
    "iso:country":"US",
    "sg:address":"2300 State Hwy 291",
    "sg:city":"Independence",
    "sg:classifiers":[
        {
            "category":"Food & Beverages",
            "subcategory":"Groceries & Convenience Stores",
            "type":"Retail Goods"
        }
    ],
    "sg:phone":"+1 816 252 1972",
    "sg:postcode":"64057",
    "sg:province":"MO",
    "sg:tags":[
        "market"
    ],
    "wof:name":"Joe's Market",
    "wof:placetype":"venue"
},
  "geometry": {"coordinates":[-94.379093,39.074318],"type":"Point"}
}