{
  "type": "Feature",
  "properties": {
    "iso:country":"US",
    "sg:address":"5109 NW Ridgewood Dr",
    "sg:city":"Kansas City",
    "sg:classifiers":[
        {
            "category":"Building & Trades",
            "subcategory":"Construction",
            "type":"Services"
        }
    ],
    "sg:phone":"+1 816 741 8211",
    "sg:postcode":"64151",
    "sg:province":"MO",
    "sg:tags":[
        "contractor"
    ],
    "wof:name":"Boots Ronald E Drywall Company",
    "wof:placetype":"venue"
},
  "geometry": {"coordinates":[-94.632233,39.186784],"type":"Point"}
}