{
  "type": "Feature",
  "properties": {
    "iso:country":"US",
    "sg:address":"14500 E 42 St S",
    "sg:city":"Independence",
    "sg:classifiers":[
        {
            "category":"Wholesale",
            "subcategory":"Medical Equipment & Supplies",
            "type":"Manufacturing & Wholesale Goods"
        }
    ],
    "sg:phone":"+1 816 373 4009",
    "sg:postcode":"64055",
    "sg:province":"MO",
    "wof:name":"Baxter Health Systems",
    "wof:placetype":"venue"
},
  "geometry": {"coordinates":[-94.404934,39.043775],"type":"Point"}
}