{
  "type": "Feature",
  "properties": {
    "iso:country":"US",
    "sg:address":"4112 Manchester Ave",
    "sg:city":"Saint Louis",
    "sg:classifiers":[
        {
            "category":"Bars & Pubs",
            "subcategory":"Lounge",
            "type":"Food & Drink"
        },
        {
            "category":"Bars & Pubs",
            "subcategory":"Gay Bar",
            "type":"Food & Drink"
        },
        {
            "category":"Recreation",
            "subcategory":"Dance Hall",
            "type":"Entertainment"
        }
    ],
    "sg:phone":"+1 314 371 1333",
    "sg:postcode":"63110",
    "sg:province":"MO",
    "sg:tags":[
        "club",
        "karaoke"
    ],
    "sg:website":"www.justjohnsclub.com",
    "wof:name":"Just John's Club",
    "wof:placetype":"venue"
},
  "geometry": {"coordinates":[-90.250647,38.627694],"type":"Point"}
}