{
  "type": "Feature",
  "properties": {
    "addr:full":"100 Plaza Sq Park Hills MO 63601",
    "addr:housenumber":"100",
    "addr:postcode":"63601",
    "addr:street":"Plaza Sq",
    "iso:country":"US",
    "sg:address":"100 Plaza Sq",
    "sg:city":"Park Hills",
    "sg:classifiers":[
        {
            "category":"Restaurant",
            "type":"Food & Drink"
        }
    ],
    "sg:menulink":"http://www.allmenus.com/mo/st-francois/156040-hardees/menu/",
    "sg:phone":"+1 573 431 5988",
    "sg:postcode":"63601",
    "sg:province":"MO",
    "sg:tags":[
        "burger",
        "american"
    ],
    "wof:name":"Hardee's",
    "wof:placetype":"venue"
},
  "geometry": {"coordinates":[-90.487971,37.838741],"type":"Point"}
}