{
  "type": "Feature",
  "properties": {
    "iso:country":"US",
    "sg:address":"91 Edward Dr",
    "sg:city":"Eureka",
    "sg:classifiers":[
        {
            "category":"Professional",
            "subcategory":"Lawyer & Legal Services",
            "type":"Services"
        }
    ],
    "sg:phone":"+1 636 938 3351",
    "sg:postcode":"63025",
    "sg:province":"MO",
    "sg:tags":[
        "attorney",
        "practice"
    ],
    "wof:name":"George J Miller",
    "wof:placetype":"venue"
},
  "geometry": {"coordinates":[-90.63718299999999,38.511288],"type":"Point"}
}