{
  "type": "Feature",
  "properties": {
    "iso:country":"US",
    "sg:address":"2023 Cherokee St",
    "sg:city":"Saint Louis",
    "sg:classifiers":[
        {
            "category":"Wholesale",
            "subcategory":"Dairy",
            "type":"Manufacturing & Wholesale Goods"
        }
    ],
    "sg:phone":"+1 314 773 2393",
    "sg:postcode":"63118",
    "sg:province":"MO",
    "sg:tags":[
        "product"
    ],
    "wof:name":"Berlinger Dairy Center",
    "wof:placetype":"venue"
},
  "geometry": {"coordinates":[-90.221778,38.592882],"type":"Point"}
}