{
  "type": "Feature",
  "properties": {
    "iso:country":"US",
    "sg:address":"600 W Morrison St",
    "sg:city":"Fayette",
    "sg:classifiers":[
        {
            "category":"Education",
            "subcategory":"College",
            "type":"Public Place"
        },
        {
            "category":"Communications",
            "type":"Services"
        }
    ],
    "sg:phone":"+1 660 248 1148",
    "sg:postcode":"65248",
    "sg:province":"MO",
    "wof:name":"Mite Network",
    "wof:placetype":"venue"
},
  "geometry": {"coordinates":[-92.69064299999999,39.143536],"type":"Point"}
}