{
  "type": "Feature",
  "properties": {
    "iso:country":"US",
    "sg:address":"448 W Little Oaks Rd",
    "sg:city":"Rolla",
    "sg:classifiers":[
        {
            "category":"Autos & Motor Vehicles",
            "subcategory":"Automobile Sales",
            "type":"Retail Goods"
        },
        {
            "category":"Autos & Motor Vehicles",
            "subcategory":"Auto Supplies",
            "type":"Retail Goods"
        },
        {
            "category":"Retail",
            "subcategory":"Auto Repair",
            "type":"Services"
        }
    ],
    "sg:phone":"+1 573 364 3322",
    "sg:postcode":"65401",
    "sg:province":"MO",
    "sg:tags":[
        "tire",
        "car",
        "part",
        "brake",
        "new"
    ],
    "wof:name":"Taylor Used Cars & Salvage",
    "wof:placetype":"venue"
},
  "geometry": {"coordinates":[-91.77347,37.915094],"type":"Point"}
}