{
  "type": "Feature",
  "properties": {
    "iso:country":"US",
    "sg:address":"5682 Alona Pt",
    "sg:city":"Osage Beach",
    "sg:classifiers":[
        {
            "category":"Restaurant",
            "type":"Food & Drink"
        }
    ],
    "sg:phone":"+1 573 348 0486",
    "sg:postcode":"65065",
    "sg:province":"MO",
    "sg:tags":[
        "eating"
    ],
    "wof:name":"T Bones Bar & Grill",
    "wof:placetype":"venue"
},
  "geometry": {"coordinates":[-92.681358,38.143649],"type":"Point"}
}