{
  "type": "Feature",
  "properties": {
    "iso:country":"US",
    "sg:address":"110 E Dakota St",
    "sg:city":"Butler",
    "sg:classifiers":[
        {
            "category":"Professional",
            "subcategory":"Accounting & Tax Preparation",
            "type":"Services"
        }
    ],
    "sg:phone":"+1 660 679 3101",
    "sg:postcode":"64730",
    "sg:province":"MO",
    "sg:tags":[
        "return"
    ],
    "wof:name":"H & R Block",
    "wof:placetype":"venue"
},
  "geometry": {"coordinates":[-94.33108799999999,38.257496],"type":"Point"}
}