{
  "type": "Feature",
  "properties": {
    "iso:country":"US",
    "sg:address":"4949 Caribee Dr",
    "sg:city":"St Louis",
    "sg:classifiers":[
        {
            "category":"Shopping",
            "subcategory":"Bicycles & Sporting Goods",
            "type":"Retail Goods"
        }
    ],
    "sg:phone":"+1 314 416 7529",
    "sg:postcode":"63128",
    "sg:province":"MO",
    "sg:tags":[
        "equipment",
        "playground"
    ],
    "wof:name":"Gateway Recreational Products",
    "wof:placetype":"venue"
},
  "geometry": {"coordinates":[-90.370524,38.497591],"type":"Point"}
}