{
  "type": "Feature",
  "properties": {
    "iso:country":"US",
    "sg:address":"2800 S Range Line Rd",
    "sg:city":"Joplin",
    "sg:classifiers":[
        {
            "category":"Bars & Pubs",
            "type":"Food & Drink"
        }
    ],
    "sg:phone":"+1 417 623 1117",
    "sg:postcode":"64804",
    "sg:province":"MO",
    "sg:tags":[
        "club",
        "night"
    ],
    "wof:name":"Hidden Acres Supper Club",
    "wof:placetype":"venue"
},
  "geometry": {"coordinates":[-94.478217,37.062034],"type":"Point"}
}