{
  "type": "Feature",
  "properties": {
    "iso:country":"US",
    "sg:address":"202 N 39th St",
    "sg:city":"Bethany",
    "sg:classifiers":[
        {
            "category":"Professional",
            "type":"Services"
        }
    ],
    "sg:phone":"+1 660 425 6094",
    "sg:postcode":"64424",
    "sg:province":"MO",
    "wof:name":"John Whitt",
    "wof:placetype":"venue"
},
  "geometry": {"coordinates":[-94.014567,40.269432],"type":"Point"}
}