{
  "type": "Feature",
  "properties": {
    "iso:country":"US",
    "sg:address":"708 N Charles St",
    "sg:city":"Warrensburg",
    "sg:phone":"+1 660 747 8805",
    "sg:postcode":"64093",
    "sg:province":"MO",
    "wof:name":"El Vaquero Mexican Restaurant",
    "wof:placetype":"venue"
},
  "geometry": {"coordinates":[-93.734543,38.771186],"type":"Point"}
}