{
  "type": "Feature",
  "properties": {
    "iso:country":"US",
    "sg:address":"1223 W Central Ave",
    "sg:city":"Carthage",
    "sg:classifiers":[
        {
            "category":"Food & Beverages",
            "subcategory":"Groceries & Convenience Stores",
            "type":"Retail Goods"
        }
    ],
    "sg:phone":"+1 417 358 2624",
    "sg:postcode":"64836",
    "sg:province":"MO",
    "sg:tags":[
        "grocer"
    ],
    "wof:name":"Ramey Super Markets",
    "wof:placetype":"venue"
},
  "geometry": {"coordinates":[-94.327124,37.178979],"type":"Point"}
}