{
  "type": "Feature",
  "properties": {
    "iso:country":"US",
    "sg:address":"305 Arrowhead Dr",
    "sg:city":"Ozark",
    "sg:classifiers":[
        {
            "category":"Health Services",
            "subcategory":"Dentist",
            "type":"Services"
        }
    ],
    "sg:phone":"+1 417 725 2401",
    "sg:postcode":"65721",
    "sg:province":"MO",
    "wof:name":"Michael K Butterfield",
    "wof:placetype":"venue"
},
  "geometry": {"coordinates":[-93.297788,36.982333],"type":"Point"}
}