{
  "type": "Feature",
  "properties": {
    "addr:full":"2039 E Independence St Springfield MO 65804",
    "addr:housenumber":"2039",
    "addr:postcode":"65804",
    "addr:street":"E Independence St",
    "iso:country":"US",
    "sg:address":"2039 E Independence St",
    "sg:city":"Springfield",
    "sg:classifiers":[
        {
            "category":"Professional",
            "subcategory":"Business Services",
            "type":"Services"
        }
    ],
    "sg:phone":"+1 417 890 0030",
    "sg:postcode":"65804",
    "sg:province":"MO",
    "wof:name":"Postnet",
    "wof:placetype":"venue"
},
  "geometry": {"coordinates":[-93.258117,37.141463],"type":"Point"}
}