{
  "type": "Feature",
  "properties": {
    "iso:country":"US",
    "sg:address":"4650 Deer Valley Ln",
    "sg:city":"Springfield",
    "sg:classifiers":[
        {
            "category":"Shopping",
            "subcategory":"Crafts & Fabrics",
            "type":"Retail Goods"
        }
    ],
    "sg:phone":"+1 417 869 2931",
    "sg:postcode":"65802",
    "sg:province":"MO",
    "sg:tags":[
        "sewing"
    ],
    "wof:name":"Brook Grant Sewing",
    "wof:placetype":"venue"
},
  "geometry": {"coordinates":[-93.19543899999999,37.219616],"type":"Point"}
}