{
  "type": "Feature",
  "properties": {
    "iso:country":"US",
    "sg:address":"1554 Mississippi Ave",
    "sg:city":"St Louis",
    "sg:classifiers":[
        {
            "category":"Real Estate",
            "subcategory":"Real Estate Agent",
            "type":"Services"
        }
    ],
    "sg:phone":"+1 314 776 2489",
    "sg:postcode":"63104",
    "sg:province":"MO",
    "sg:tags":[
        "inspection"
    ],
    "wof:name":"Preferred Building Inspections",
    "wof:placetype":"venue"
},
  "geometry": {"coordinates":[-90.213572,38.616849],"type":"Point"}
}