{
  "type": "Feature",
  "properties": {
    "iso:country":"US",
    "sg:address":"1161 Butler St",
    "sg:city":"Poplar Bluff",
    "sg:classifiers":[
        {
            "category":"Wholesale",
            "subcategory":"Furniture",
            "type":"Manufacturing & Wholesale Goods"
        }
    ],
    "sg:phone":"+1 573 785 3060",
    "sg:postcode":"63901",
    "sg:province":"MO",
    "wof:name":"Scheffer's Office Furniture",
    "wof:placetype":"venue"
},
  "geometry": {"coordinates":[-90.409633,36.751313],"type":"Point"}
}