{
  "type": "Feature",
  "properties": {
    "iso:country":"US",
    "sg:address":"211 N 7th St",
    "sg:city":"Saint Louis",
    "sg:classifiers":[
        {
            "category":"Professional",
            "type":"Services"
        }
    ],
    "sg:phone":"+1 314 621 9710",
    "sg:postcode":"63101",
    "sg:province":"MO",
    "wof:name":"Jf Services",
    "wof:placetype":"venue"
},
  "geometry": {"coordinates":[-90.191408,38.628216],"type":"Point"}
}