{
  "type": "Feature",
  "properties": {
    "iso:country":"US",
    "sg:address":"160 Saylesville Dr",
    "sg:city":"Chesterfield",
    "sg:classifiers":[
        {
            "category":"Real Estate",
            "subcategory":"Real Estate Agent",
            "type":"Services"
        }
    ],
    "sg:phone":"+1 314 291 0048",
    "sg:postcode":"63017",
    "sg:province":"MO",
    "wof:name":"Romantique Plaza LLC",
    "wof:placetype":"venue"
},
  "geometry": {"coordinates":[-90.51102299999999,38.659224],"type":"Point"}
}