{
  "type": "Feature",
  "properties": {
    "iso:country":"US",
    "sg:address":"3829 Bellevue St",
    "sg:city":"Hannibal",
    "sg:classifiers":[
        {
            "category":"Autos & Motor Vehicles",
            "subcategory":"Automobile Sales",
            "type":"Retail Goods"
        }
    ],
    "sg:phone":"+1 573 221 0700",
    "sg:postcode":"63401",
    "sg:province":"MO",
    "sg:tags":[
        "car",
        "dealer"
    ],
    "wof:name":"Express Rent A Car & Auto Sale",
    "wof:placetype":"venue"
},
  "geometry": {"coordinates":[-91.399812,39.689441],"type":"Point"}
}