{
  "type": "Feature",
  "properties": {
    "iso:country":"US",
    "sg:address":"101 Timber Ridge Dr",
    "sg:city":"Hillsboro",
    "sg:classifiers":[
        {
            "category":"Real Estate",
            "subcategory":"Real Estate Operator",
            "type":"Services"
        }
    ],
    "sg:phone":"+1 636 797 4682",
    "sg:postcode":"63050",
    "sg:province":"MO",
    "sg:tags":[
        "apartment"
    ],
    "wof:name":"Timber Ridge Apartments",
    "wof:placetype":"venue"
},
  "geometry": {"coordinates":[-90.55865,38.24198],"type":"Point"}
}