{
  "type": "Feature",
  "properties": {
    "iso:country":"US",
    "sg:address":"111 Dublin Ln",
    "sg:city":"Festus",
    "sg:classifiers":[
        {
            "category":"Professional",
            "subcategory":"Business Services",
            "type":"Services"
        }
    ],
    "sg:phone":"+1 636 937 3794",
    "sg:postcode":"63028",
    "sg:province":"MO",
    "wof:name":"Bisch Enterprise",
    "wof:placetype":"venue"
},
  "geometry": {"coordinates":[-90.40935399999999,38.217985],"type":"Point"}
}