{
  "type": "Feature",
  "properties": {
    "iso:country":"US",
    "sg:address":"12931 Olive Blvd",
    "sg:city":"St Louis",
    "sg:classifiers":[
        {
            "category":"Personal",
            "subcategory":"Beauty Salon",
            "type":"Services"
        }
    ],
    "sg:phone":"+1 314 434 4622",
    "sg:postcode":"63141",
    "sg:province":"MO",
    "sg:tags":[
        "shop",
        "manicuring"
    ],
    "wof:name":"Fingerpaints At Michael's West",
    "wof:placetype":"venue"
},
  "geometry": {"coordinates":[-90.48034199999999,38.682572],"type":"Point"}
}