{
  "type": "Feature",
  "properties": {
    "iso:country":"US",
    "sg:address":"7345 S Lindbergh Blvd",
    "sg:city":"St Louis",
    "sg:classifiers":[
        {
            "category":"Utilities",
            "subcategory":"Mobile Phone",
            "type":"Services"
        }
    ],
    "sg:phone":"+1 314 487 7010",
    "sg:postcode":"63125",
    "sg:province":"MO",
    "sg:tags":[
        "telephone",
        "cellular"
    ],
    "wof:name":"Cingular Wireless",
    "wof:placetype":"venue"
},
  "geometry": {"coordinates":[-90.327574,38.507167],"type":"Point"}
}