{
  "type": "Feature",
  "properties": {
    "iso:country":"US",
    "sg:address":"3199 Mercier St",
    "sg:city":"Kansas City",
    "sg:classifiers":[
        {
            "category":"Manufacturing",
            "subcategory":"Printing",
            "type":"Manufacturing & Wholesale Goods"
        }
    ],
    "sg:phone":"+1 816 231 4844",
    "sg:postcode":"64111",
    "sg:province":"MO",
    "sg:tags":[
        "binding"
    ],
    "wof:name":"Heartland Binding Inc",
    "wof:placetype":"venue"
},
  "geometry": {"coordinates":[-94.599993,39.071571],"type":"Point"}
}