{
  "type": "Feature",
  "properties": {
    "iso:country":"US",
    "sg:address":"602 S Washington St",
    "sg:city":"Paris",
    "sg:classifiers":[
        {
            "category":"Professional",
            "subcategory":"Business Services",
            "type":"Services"
        }
    ],
    "sg:phone":"+1 660 327 5645",
    "sg:postcode":"65275",
    "sg:province":"MO",
    "wof:name":"Darlenes Upholstery",
    "wof:placetype":"venue"
},
  "geometry": {"coordinates":[-92.001594,39.475574],"type":"Point"}
}