{
  "type": "Feature",
  "properties": {
    "iso:country":"US",
    "sg:address":"33502 James Rd",
    "sg:city":"Richland",
    "sg:classifiers":[
        {
            "category":"Farming",
            "subcategory":"Farm",
            "type":"Manufacturing & Wholesale Goods"
        }
    ],
    "sg:phone":"+1 573 765 4183",
    "sg:postcode":"65556",
    "sg:province":"MO",
    "sg:tags":[
        "crop",
        "general"
    ],
    "wof:name":"Steve Maddux",
    "wof:placetype":"venue"
},
  "geometry": {"coordinates":[-92.42886,37.797385],"type":"Point"}
}