{
  "type": "Feature",
  "properties": {
    "iso:country":"US",
    "sg:address":"405 Main St",
    "sg:city":"Leonard",
    "sg:classifiers":[
        {
            "category":"Farming",
            "subcategory":"Farm",
            "type":"Manufacturing & Wholesale Goods"
        }
    ],
    "sg:phone":"+1 660 762 4668",
    "sg:postcode":"63451",
    "sg:province":"MO",
    "sg:tags":[
        "crop",
        "general"
    ],
    "wof:name":"David Echternacht",
    "wof:placetype":"venue"
},
  "geometry": {"coordinates":[-92.183328,39.892107],"type":"Point"}
}