{
  "type": "Feature",
  "properties": {
    "iso:country":"US",
    "sg:address":"5514 Gaston Rd",
    "sg:city":"Eunice",
    "sg:classifiers":[
        {
            "category":"Freight",
            "type":"Transportation"
        }
    ],
    "sg:phone":"+1 417 932 4964",
    "sg:postcode":"65468",
    "sg:province":"MO",
    "sg:tags":[
        "trucking"
    ],
    "sg:website":"www.dandgauto.com",
    "wof:name":"D & G Auto Transport Inc",
    "wof:placetype":"venue"
},
  "geometry": {"coordinates":[-91.77986300000001,37.245714],"type":"Point"}
}