{
  "type": "Feature",
  "properties": {
    "iso:country":"US",
    "sg:address":"2251 W Outer 61",
    "sg:city":"Troy",
    "sg:classifiers":[
        {
            "category":"Home & Garden",
            "subcategory":"Building Materials",
            "type":"Retail Goods"
        },
        {
            "category":"Manufacturing",
            "subcategory":"Glass & Minerals",
            "type":"Manufacturing & Wholesale Goods"
        }
    ],
    "sg:phone":"+1 636 528 5196",
    "sg:postcode":"63379",
    "sg:province":"MO",
    "sg:tags":[
        "ready",
        "concrete",
        "mfg",
        "mix",
        "construction",
        "mixed"
    ],
    "wof:name":"Troy Ready Mix & Material Co",
    "wof:placetype":"venue"
},
  "geometry": {"coordinates":[-90.974001,39.071602],"type":"Point"}
}