{
  "type": "Feature",
  "properties": {
    "iso:country":"US",
    "sg:address":"201 Enchanted Pkwy",
    "sg:city":"Manchester",
    "sg:classifiers":[
        {
            "category":"Health Services",
            "subcategory":"Chiropractor",
            "type":"Services"
        }
    ],
    "sg:phone":"+1 314 918 7241",
    "sg:postcode":"63021",
    "sg:province":"MO",
    "wof:name":"West County Physical Medicine",
    "wof:placetype":"venue"
},
  "geometry": {"coordinates":[-90.501935,38.590422],"type":"Point"}
}