{
  "type": "Feature",
  "properties": {
    "iso:country":"US",
    "sg:address":"171 S County Centerway",
    "sg:city":"Saint Louis",
    "sg:classifiers":[
        {
            "category":"Cinema",
            "subcategory":"Movie Rental",
            "type":"Entertainment"
        }
    ],
    "sg:phone":"+1 314 835 1353",
    "sg:postcode":"63129",
    "sg:province":"MO",
    "sg:tags":[
        "video",
        "tape"
    ],
    "wof:name":"Suncoast Mpc 3459",
    "wof:placetype":"venue"
},
  "geometry": {"coordinates":[-90.328515,38.504264],"type":"Point"}
}