{
  "type": "Feature",
  "properties": {
    "iso:country":"US",
    "sg:address":"4121 Roanoke Rd",
    "sg:city":"Kansas City",
    "sg:classifiers":[
        {
            "category":"Social Services",
            "subcategory":"Child Care",
            "type":"Services"
        }
    ],
    "sg:phone":"+1 816 756 0134",
    "sg:postcode":"64111",
    "sg:province":"MO",
    "sg:tags":[
        "day"
    ],
    "wof:name":"Nylas Childcare",
    "wof:placetype":"venue"
},
  "geometry": {"coordinates":[-94.597936,39.053473],"type":"Point"}
}