{
  "type": "Feature",
  "properties": {
    "iso:country":"US",
    "sg:address":"310 E 4th St",
    "sg:city":"Sedalia",
    "sg:classifiers":[
        {
            "category":"Personal",
            "subcategory":"Beauty Salon",
            "type":"Services"
        }
    ],
    "sg:phone":"+1 660 826 6759",
    "sg:postcode":"65301",
    "sg:province":"MO",
    "wof:name":"Pearl's Beauty Shop",
    "wof:placetype":"venue"
},
  "geometry": {"coordinates":[-93.225721,38.707687],"type":"Point"}
}