{
  "type": "Feature",
  "properties": {
    "iso:country":"US",
    "sg:address":"3304 W Broadway",
    "sg:city":"Columbia",
    "sg:classifiers":[
        {
            "category":"Professional",
            "subcategory":"Business Services",
            "type":"Services"
        }
    ],
    "sg:phone":"+1 573 445 4566",
    "sg:postcode":"65203",
    "sg:province":"MO",
    "sg:tags":[
        "embroidery"
    ],
    "wof:name":"Embroid Me",
    "wof:placetype":"venue"
},
  "geometry": {"coordinates":[-92.384989,38.954979],"type":"Point"}
}