{
  "type": "Feature",
  "properties": {
    "iso:country":"US",
    "sg:address":"5945 W Florissant Ave",
    "sg:city":"St Louis",
    "sg:classifiers":[
        {
            "category":"Organizations",
            "subcategory":"Religious Organization",
            "type":"Services"
        }
    ],
    "sg:phone":"+1 314 385 1258",
    "sg:postcode":"63136",
    "sg:province":"MO",
    "sg:tags":[
        "church"
    ],
    "wof:name":"St Douglas P Baptist Church",
    "wof:placetype":"venue"
},
  "geometry": {"coordinates":[-90.250299,38.707837],"type":"Point"}
}