{
  "type": "Feature",
  "properties": {
    "iso:country":"US",
    "sg:address":"2795 Hwy 52",
    "sg:city":"Eldon",
    "sg:classifiers":[
        {
            "category":"Social Services",
            "subcategory":"Child Care",
            "type":"Services"
        }
    ],
    "sg:phone":"+1 573 392 2933",
    "sg:postcode":"65026",
    "sg:province":"MO",
    "sg:tags":[
        "day"
    ],
    "wof:name":"Teddybear Daycare",
    "wof:placetype":"venue"
},
  "geometry": {"coordinates":[-92.565866,38.300926],"type":"Point"}
}