{
  "type": "Feature",
  "properties": {
    "iso:country":"US",
    "sg:address":"293 NE Co Rd H",
    "sg:city":"Warrensburg",
    "sg:phone":"+1 660 747 8780",
    "sg:postcode":"64093",
    "sg:province":"MO",
    "sg:tags":[
        "farm",
        "soybean"
    ],
    "wof:name":"Harold Wissman",
    "wof:placetype":"venue"
},
  "geometry": {"coordinates":[-93.796593,38.902492],"type":"Point"}
}