{
  "type": "Feature",
  "properties": {
    "iso:country":"US",
    "sg:address":"3640 N Grand Ave",
    "sg:city":"Kansas City",
    "sg:classifiers":[
        {
            "category":"Social Services",
            "subcategory":"Child Care",
            "type":"Services"
        }
    ],
    "sg:phone":"+1 816 454 3453",
    "sg:postcode":"64116",
    "sg:province":"MO",
    "sg:tags":[
        "day"
    ],
    "wof:name":"Tranquility Day Spa Inc",
    "wof:placetype":"venue"
},
  "geometry": {"coordinates":[-94.578596,39.161568],"type":"Point"}
}