{
  "type": "Feature",
  "properties": {
    "iso:country":"US",
    "sg:address":"19040 E Valley View Pkwy",
    "sg:city":"Independence",
    "sg:classifiers":[
        {
            "category":"Shopping",
            "subcategory":"Discount & Variety Stores",
            "type":"Retail Goods"
        }
    ],
    "sg:phone":"+1 816 200 2003",
    "sg:postcode":"64055",
    "sg:province":"MO",
    "sg:tags":[
        "merchandise",
        "general"
    ],
    "wof:name":"Costco Wholesale Corporation",
    "wof:placetype":"venue"
},
  "geometry": {"coordinates":[-94.349114,39.038333],"type":"Point"}
}