{
  "type": "Feature",
  "properties": {
    "iso:country":"US",
    "sg:address":"1011 County Highway 419",
    "sg:city":"Portageville",
    "sg:classifiers":[
        {
            "category":"Professional",
            "subcategory":"Management & Consulting",
            "type":"Services"
        }
    ],
    "sg:phone":"+1 573 379 3232",
    "sg:postcode":"63873",
    "sg:province":"MO",
    "sg:tags":[
        "farm"
    ],
    "wof:name":"Francis Hulshof",
    "wof:placetype":"venue"
},
  "geometry": {"coordinates":[-89.662403,36.446677],"type":"Point"}
}