{
  "type": "Feature",
  "properties": {
    "iso:country":"US",
    "sg:address":"3101 Lusk Dr",
    "sg:city":"Neosho",
    "sg:classifiers":[
        {
            "category":"Banks & Credit Unions",
            "subcategory":"Financial Services",
            "type":"Services"
        }
    ],
    "sg:phone":"+1 417 451 9955",
    "sg:postcode":"64850",
    "sg:province":"MO",
    "sg:tags":[
        "cashing",
        "financing",
        "loan",
        "check",
        "payday"
    ],
    "sg:website":"http://www.advanceamerica.com",
    "wof:name":"Advance America",
    "wof:placetype":"venue"
},
  "geometry": {"coordinates":[-94.394633,36.839117],"type":"Point"}
}