{
  "type": "Feature",
  "properties": {
    "iso:country":"US",
    "sg:address":"105 West Ave",
    "sg:city":"Eureka",
    "sg:classifiers":[
        {
            "category":"Professional",
            "subcategory":"Advertising",
            "type":"Services"
        }
    ],
    "sg:phone":"+1 636 938 5502",
    "sg:postcode":"63025",
    "sg:province":"MO",
    "sg:tags":[
        "advertising-promotional",
        "product"
    ],
    "sg:website":"http://www.lizmark.com",
    "wof:name":"Lizmark",
    "wof:placetype":"venue"
},
  "geometry": {"coordinates":[-90.630463,38.502571],"type":"Point"}
}