{
  "type": "Feature",
  "properties": {
    "iso:country":"US",
    "sg:address":"1756 N New Florissant Rd",
    "sg:city":"Florissant",
    "sg:classifiers":[
        {
            "category":"Shopping",
            "type":"Retail Goods"
        }
    ],
    "sg:phone":"+1 314 921 4331",
    "sg:postcode":"63033",
    "sg:province":"MO",
    "sg:tags":[
        "merchandise"
    ],
    "wof:name":"Count Your Blessings",
    "wof:placetype":"venue"
},
  "geometry": {"coordinates":[-90.316013,38.802156],"type":"Point"}
}