{
  "type": "Feature",
  "properties": {
    "iso:country":"US",
    "sg:address":"6511 Marmaduke Ave",
    "sg:city":"St Louis",
    "sg:classifiers":[
        {
            "category":"Building & Trades",
            "subcategory":"Construction",
            "type":"Services"
        }
    ],
    "sg:phone":"+1 314 832 8020",
    "sg:postcode":"63139",
    "sg:province":"MO",
    "sg:tags":[
        "downspouts",
        "gutter"
    ],
    "wof:name":"C & T Aluminum Inc",
    "wof:placetype":"venue"
},
  "geometry": {"coordinates":[-90.30244500000001,38.6113],"type":"Point"}
}