{
  "type": "Feature",
  "properties": {
    "iso:country":"US",
    "sg:address":"800 SW Blue Pkwy",
    "sg:city":"Lees Summit",
    "sg:classifiers":[
        {
            "category":"Restaurant",
            "type":"Food & Drink"
        }
    ],
    "sg:phone":"+1 816 524 1910",
    "sg:postcode":"64063",
    "sg:province":"MO",
    "sg:tags":[
        "eating"
    ],
    "wof:name":"Johnny Ray's Drive In",
    "wof:placetype":"venue"
},
  "geometry": {"coordinates":[-94.392026,38.910975],"type":"Point"}
}