{
  "type": "Feature",
  "properties": {
    "iso:country":"US",
    "sg:address":"4615 S Lindbergh Blvd",
    "sg:city":"Saint Louis",
    "sg:classifiers":[
        {
            "category":"Building & Trades",
            "subcategory":"Construction",
            "type":"Services"
        }
    ],
    "sg:phone":"+1 314 842 0695",
    "sg:postcode":"63127",
    "sg:province":"MO",
    "sg:tags":[
        "contractor"
    ],
    "wof:name":"Quality Seamless Guttering",
    "wof:placetype":"venue"
},
  "geometry": {"coordinates":[-90.381005,38.529437],"type":"Point"}
}