{
  "type": "Feature",
  "properties": {
    "iso:country":"US",
    "sg:address":"1220 Big Bill Rd",
    "sg:city":"Arnold",
    "sg:classifiers":[
        {
            "category":"Restaurant",
            "type":"Food & Drink"
        }
    ],
    "sg:menulink":"http://www.allmenus.com/mo/arnold/217535-bandanas-bbq/menu/",
    "sg:phone":"+1 636 282 3328",
    "sg:postcode":"63010",
    "sg:province":"MO",
    "sg:tags":[
        "barbecue",
        "american"
    ],
    "wof:name":"Bandana's BBQ",
    "wof:placetype":"venue"
},
  "geometry": {"coordinates":[-90.378018,38.442543],"type":"Point"}
}