{
  "type": "Feature",
  "properties": {
    "iso:country":"US",
    "sg:address":"735 Marshall Ave",
    "sg:city":"Webster Groves",
    "sg:classifiers":[
        {
            "category":"Building & Trades",
            "subcategory":"Construction",
            "type":"Services"
        }
    ],
    "sg:phone":"+1 314 962 7300",
    "sg:postcode":"63119",
    "sg:province":"MO",
    "sg:tags":[
        "window",
        "replacement"
    ],
    "wof:name":"J P Window & Door Svc",
    "wof:placetype":"venue"
},
  "geometry": {"coordinates":[-90.33833799999999,38.604218],"type":"Point"}
}