{
  "type": "Feature",
  "properties": {
    "iso:country":"US",
    "sg:address":"2015 Mullanphy Ln",
    "sg:city":"Florissant",
    "sg:classifiers":[
        {
            "category":"Education",
            "subcategory":"School",
            "type":"Public Place"
        }
    ],
    "sg:phone":"+1 314 953 4600",
    "sg:postcode":"63031",
    "sg:province":"MO",
    "sg:tags":[
        "elementary"
    ],
    "sg:website":"www.hazelwood.org",
    "wof:name":"Lusher Elementary School",
    "wof:placetype":"venue"
},
  "geometry": {"coordinates":[-90.349903,38.81609],"type":"Point"}
}