{
  "type": "Feature",
  "properties": {
    "iso:country":"US",
    "sg:address":"358 E Springfield Rd",
    "sg:city":"Sullivan",
    "sg:classifiers":[
        {
            "category":"Organizations",
            "subcategory":"Professional Association",
            "type":"Services"
        }
    ],
    "sg:phone":"+1 573 860 7138",
    "sg:postcode":"63080",
    "sg:province":"MO",
    "sg:tags":[
        "business",
        "trade"
    ],
    "wof:name":"Mid America Regional Informati",
    "wof:placetype":"venue"
},
  "geometry": {"coordinates":[-91.15321,38.220129],"type":"Point"}
}