{
  "type": "Feature",
  "properties": {
    "iso:country":"US",
    "sg:address":"8117 State Hwy 13",
    "sg:city":"Polo",
    "sg:classifiers":[
        {
            "category":"Freight",
            "type":"Transportation"
        }
    ],
    "sg:phone":"+1 660 354 2117",
    "sg:postcode":"64671",
    "sg:province":"MO",
    "sg:tags":[
        "special"
    ],
    "wof:name":"Polo Storage Rental",
    "wof:placetype":"venue"
},
  "geometry": {"coordinates":[-94.040159,39.537928],"type":"Point"}
}