{
  "type": "Feature",
  "properties": {
    "iso:country":"US",
    "sg:address":"5727 Manchester Ave",
    "sg:city":"Saint Louis",
    "sg:classifiers":[
        {
            "category":"Building & Trades",
            "subcategory":"Construction",
            "type":"Services"
        }
    ],
    "sg:phone":"+1 314 647 7070",
    "sg:postcode":"63110",
    "sg:province":"MO",
    "sg:tags":[
        "contractor"
    ],
    "wof:name":"Strassner Tennis Court Bldrs",
    "wof:placetype":"venue"
},
  "geometry": {"coordinates":[-90.282997,38.622898],"type":"Point"}
}