{
  "type": "Feature",
  "properties": {
    "iso:country":"US",
    "sg:address":"4175 Crescent Dr",
    "sg:city":"St Louis",
    "sg:classifiers":[
        {
            "category":"Professional",
            "subcategory":"Business Services",
            "type":"Services"
        },
        {
            "category":"Professional",
            "subcategory":"Management & Consulting",
            "type":"Services"
        }
    ],
    "sg:phone":"+1 314 416 7509",
    "sg:postcode":"63129",
    "sg:province":"MO",
    "sg:tags":[
        "consultant"
    ],
    "wof:name":"Labor Solutions International",
    "wof:placetype":"venue"
},
  "geometry": {"coordinates":[-90.334104,38.509558],"type":"Point"}
}