{
  "type": "Feature",
  "properties": {
    "iso:country":"US",
    "sg:address":"73 Highway Hh",
    "sg:city":"Cherryville",
    "sg:classifiers":[
        {
            "category":"Autos & Motor Vehicles",
            "subcategory":"Auto Supplies",
            "type":"Retail Goods"
        }
    ],
    "sg:phone":"+1 573 743 3796",
    "sg:postcode":"65446",
    "sg:province":"MO",
    "sg:tags":[
        "tire"
    ],
    "wof:name":"Joe's Tire & Auto",
    "wof:placetype":"venue"
},
  "geometry": {"coordinates":[-91.270203,37.840187],"type":"Point"}
}