{
  "type": "Feature",
  "properties": {
    "iso:country":"US",
    "sg:address":"105 Plum Tree Dr",
    "sg:city":"Saint Peters",
    "sg:classifiers":[
        {
            "category":"Building & Trades",
            "subcategory":"Cleaning & Sanitation",
            "type":"Services"
        }
    ],
    "sg:phone":"+1 636 928 7462",
    "sg:postcode":"63376",
    "sg:province":"MO",
    "sg:tags":[
        "maintenance"
    ],
    "wof:name":"Window Washing",
    "wof:placetype":"venue"
},
  "geometry": {"coordinates":[-90.58644,38.78299],"type":"Point"}
}