{
  "type": "Feature",
  "properties": {
    "iso:country":"US",
    "sg:address":"8401 Midland Blvd",
    "sg:city":"Saint Louis",
    "sg:classifiers":[
        {
            "category":"Government",
            "subcategory":"Office",
            "type":"Public Place"
        }
    ],
    "sg:phone":"+1 314 427 4715",
    "sg:postcode":"63114",
    "sg:province":"MO",
    "sg:tags":[
        "executive",
        "police",
        "protection"
    ],
    "wof:name":"City of Charlack",
    "wof:placetype":"venue"
},
  "geometry": {"coordinates":[-90.341536,38.697178],"type":"Point"}
}