{
  "type": "Feature",
  "properties": {
    "iso:country":"US",
    "sg:address":"304 8th Ave",
    "sg:city":"Crystal City",
    "sg:classifiers":[
        {
            "category":"Building & Trades",
            "subcategory":"Landscaping Services",
            "type":"Services"
        }
    ],
    "sg:phone":"+1 636 931 5973",
    "sg:postcode":"63019",
    "sg:province":"MO",
    "sg:tags":[
        "landscape"
    ],
    "wof:name":"Gardens By Design",
    "wof:placetype":"venue"
},
  "geometry": {"coordinates":[-90.38162800000001,38.2274],"type":"Point"}
}