{
  "type": "Feature",
  "properties": {
    "iso:country":"US",
    "sg:address":"349 S Main St",
    "sg:city":"Carthage",
    "sg:classifiers":[
        {
            "category":"Real Estate",
            "subcategory":"Real Estate Services",
            "type":"Services"
        }
    ],
    "sg:phone":"+1 417 358 8083",
    "sg:postcode":"64836",
    "sg:province":"MO",
    "sg:tags":[
        "company",
        "abstract",
        "title"
    ],
    "wof:name":"Hawkins Title Co",
    "wof:placetype":"venue"
},
  "geometry": {"coordinates":[-94.311018,37.176606],"type":"Point"}
}