{
  "type": "Feature",
  "properties": {
    "iso:country":"US",
    "sg:address":"2055 N Bluff St",
    "sg:city":"Fulton",
    "sg:classifiers":[
        {
            "category":"Restaurant",
            "type":"Food & Drink"
        }
    ],
    "sg:menulink":"http://www.allmenus.com/mo/west-fulton/65694-pizza-hut/menu/",
    "sg:phone":"+1 573 642 2875",
    "sg:postcode":"65251",
    "sg:province":"MO",
    "sg:tags":[
        "american",
        "pizza"
    ],
    "wof:name":"Pizza Hut",
    "wof:placetype":"venue"
},
  "geometry": {"coordinates":[-91.944007,38.867274],"type":"Point"}
}