{
  "type": "Feature",
  "properties": {
    "addr:full":"701 Emerson Rd Saint Louis MO 63141",
    "addr:housenumber":"701",
    "addr:postcode":"63141",
    "addr:street":"Emerson Rd",
    "iso:country":"US",
    "sg:address":"701 Emerson Rd",
    "sg:city":"Saint Louis",
    "sg:classifiers":[
        {
            "category":"Banks & Credit Unions",
            "subcategory":"Investment Brokerage",
            "type":"Services"
        }
    ],
    "sg:phone":"+1 314 993 4455",
    "sg:postcode":"63141",
    "sg:province":"MO",
    "sg:tags":[
        "security"
    ],
    "wof:name":"Phoenix Home Lf Mutl Insur Co",
    "wof:placetype":"venue"
},
  "geometry": {"coordinates":[-90.447311,38.669829],"type":"Point"}
}