{
  "type": "Feature",
  "properties": {
    "iso:country":"US",
    "sg:address":"13355 State Hwy D",
    "sg:city":"Oak Ridge",
    "sg:phone":"+1 573 266 3648",
    "sg:postcode":"63769",
    "sg:province":"MO",
    "sg:tags":[
        "farm",
        "corn",
        "soybean"
    ],
    "wof:name":"Wayne Hoffmann",
    "wof:placetype":"venue"
},
  "geometry": {"coordinates":[-89.738618,37.534576],"type":"Point"}
}