{
  "type": "Feature",
  "properties": {
    "iso:country":"US",
    "sg:address":"2653 E Elm St",
    "sg:city":"Springfield",
    "sg:classifiers":[
        {
            "category":"Retail",
            "subcategory":"Repair Shop",
            "type":"Services"
        }
    ],
    "sg:phone":"+1 417 865 9887",
    "sg:postcode":"65802",
    "sg:province":"MO",
    "sg:tags":[
        "refrigeration"
    ],
    "wof:name":"A One Refrigeration",
    "wof:placetype":"venue"
},
  "geometry": {"coordinates":[-93.24245500000001,37.204368],"type":"Point"}
}