{
  "type": "Feature",
  "properties": {
    "iso:country":"US",
    "sg:address":"609 W Versailles Ave",
    "sg:city":"California",
    "sg:classifiers":[
        {
            "category":"Organizations",
            "subcategory":"Community Association",
            "type":"Services"
        }
    ],
    "sg:phone":"+1 573 796 3754",
    "sg:postcode":"65018",
    "sg:province":"MO",
    "wof:name":"Delta Kappa Gamma Society",
    "wof:placetype":"venue"
},
  "geometry": {"coordinates":[-92.574888,38.628802],"type":"Point"}
}