{
  "type": "Feature",
  "properties": {
    "iso:country":"US",
    "sg:address":"8927 Lackland Rd",
    "sg:city":"Saint Louis",
    "sg:classifiers":[
        {
            "category":"Building & Trades",
            "subcategory":"Cleaning & Sanitation",
            "type":"Services"
        }
    ],
    "sg:phone":"+1 314 426 6659",
    "sg:postcode":"63114",
    "sg:province":"MO",
    "sg:tags":[
        "maintenance"
    ],
    "wof:name":"Xtra Kleen Inc",
    "wof:placetype":"venue"
},
  "geometry": {"coordinates":[-90.35539199999999,38.699559],"type":"Point"}
}