{
  "type": "Feature",
  "properties": {
    "iso:country":"US",
    "sg:address":"4207 Veterans Memorial Pkwy",
    "sg:city":"St Peters",
    "sg:classifiers":[
        {
            "category":"Restaurant",
            "type":"Food & Drink"
        }
    ],
    "sg:phone":"+1 636 928 4360",
    "sg:postcode":"63376",
    "sg:province":"MO",
    "sg:tags":[
        "mexican"
    ],
    "wof:name":"El Mezcal",
    "wof:placetype":"venue"
},
  "geometry": {"coordinates":[-90.57607400000001,38.796148],"type":"Point"}
}