{
  "type": "Feature",
  "properties": {
    "iso:country":"US",
    "sg:address":"1571 Bunker Hill Dr",
    "sg:city":"Cape Girardeau",
    "sg:classifiers":[
        {
            "category":"Shopping",
            "subcategory":"Clothing, Apparel, & Fashions",
            "type":"Retail Goods"
        }
    ],
    "sg:phone":"+1 573 651 0269",
    "sg:postcode":"63701",
    "sg:province":"MO",
    "wof:name":"Carol-Cyns Dress Shop",
    "wof:placetype":"venue"
},
  "geometry": {"coordinates":[-89.54378,37.339272],"type":"Point"}
}