{
  "type": "Feature",
  "properties": {
    "iso:country":"US",
    "sg:address":"1019 W Main St",
    "sg:city":"Branson",
    "sg:classifiers":[
        {
            "category":"Real Estate",
            "subcategory":"Real Estate Agent",
            "type":"Services"
        }
    ],
    "sg:phone":"+1 417 334 1346",
    "sg:postcode":"65616",
    "sg:province":"MO",
    "wof:name":"A Blue Ribbon Realty",
    "wof:placetype":"venue"
},
  "geometry": {"coordinates":[-93.23277299999999,36.644482],"type":"Point"}
}