{
  "type": "Feature",
  "properties": {
    "iso:country":"US",
    "sg:address":"1210 W Sunshine St",
    "sg:city":"Springfield",
    "sg:classifiers":[
        {
            "category":"Retail",
            "subcategory":"Auto Rental",
            "type":"Services"
        }
    ],
    "sg:phone":"+1 417 864 4466",
    "sg:postcode":"65807",
    "sg:province":"MO",
    "sg:tags":[
        "renting",
        "automobile"
    ],
    "wof:name":"Avis Rent A Car",
    "wof:placetype":"venue"
},
  "geometry": {"coordinates":[-93.308656,37.182302],"type":"Point"}
}