{
  "type": "Feature",
  "properties": {
    "iso:country":"US",
    "sg:address":"4403 Cloverbrook Dr",
    "sg:city":"Florissant",
    "sg:classifiers":[
        {
            "category":"Wholesale",
            "subcategory":"Non-durable Goods",
            "type":"Manufacturing & Wholesale Goods"
        }
    ],
    "sg:phone":"+1 314 741 6065",
    "sg:postcode":"63033",
    "sg:province":"MO",
    "wof:name":"Buck Pack Inc",
    "wof:placetype":"venue"
},
  "geometry": {"coordinates":[-90.271591,38.799291],"type":"Point"}
}