{
  "type": "Feature",
  "properties": {
    "iso:country":"US",
    "sg:address":"2101 Schotthill Woods Dr",
    "sg:city":"Jefferson City",
    "sg:classifiers":[
        {
            "category":"Food & Beverages",
            "subcategory":"Groceries & Convenience Stores",
            "type":"Retail Goods"
        }
    ],
    "sg:phone":"+1 573 659 3600",
    "sg:postcode":"65101",
    "sg:province":"MO",
    "sg:tags":[
        "grocer"
    ],
    "wof:name":"Gerbes Supermarket 118",
    "wof:placetype":"venue"
},
  "geometry": {"coordinates":[-92.149857,38.547968],"type":"Point"}
}