{
  "type": "Feature",
  "properties": {
    "iso:country":"US",
    "sg:address":"4516 NE 44 Ter",
    "sg:city":"Kansas City",
    "sg:classifiers":[
        {
            "category":"Social Services",
            "subcategory":"Child Care",
            "type":"Services"
        }
    ],
    "sg:phone":"+1 816 454 9259",
    "sg:postcode":"64117",
    "sg:province":"MO",
    "sg:tags":[
        "day"
    ],
    "wof:name":"Amelungs Day Care",
    "wof:placetype":"venue"
},
  "geometry": {"coordinates":[-94.525087,39.174559],"type":"Point"}
}