{
  "type": "Feature",
  "properties": {
    "iso:country":"US",
    "sg:address":"116 N Smith St",
    "sg:city":"Cuba",
    "sg:classifiers":[
        {
            "category":"Personal",
            "subcategory":"Beauty Salon",
            "type":"Services"
        }
    ],
    "sg:phone":"+1 573 885 0808",
    "sg:postcode":"65453",
    "sg:province":"MO",
    "wof:name":"E-Z Kuts",
    "wof:placetype":"venue"
},
  "geometry": {"coordinates":[-91.40743399999999,38.062519],"type":"Point"}
}