{
  "type": "Feature",
  "properties": {
    "iso:country":"US",
    "sg:address":"49 State Hwy B",
    "sg:city":"Leonard",
    "sg:classifiers":[
        {
            "category":"Farming",
            "subcategory":"Livestock Farm",
            "type":"Manufacturing & Wholesale Goods"
        }
    ],
    "sg:phone":"+1 660 762 4297",
    "sg:postcode":"63451",
    "sg:province":"MO",
    "sg:tags":[
        "feedlot",
        "hog",
        "or",
        "beef",
        "cattle"
    ],
    "wof:name":"Otto Farms",
    "wof:placetype":"venue"
},
  "geometry": {"coordinates":[-92.23512100000001,39.917351],"type":"Point"}
}