{
  "type": "Feature",
  "properties": {
    "iso:country":"US",
    "sg:address":"1920 SW 5 St",
    "sg:city":"Blue Springs",
    "sg:classifiers":[
        {
            "category":"Insurance",
            "subcategory":"Insurance Agent",
            "type":"Services"
        }
    ],
    "sg:phone":"+1 816 228 3051",
    "sg:postcode":"64014",
    "sg:province":"MO",
    "wof:name":"Hoskins Innovative Servic",
    "wof:placetype":"venue"
},
  "geometry": {"coordinates":[-94.27051,38.999205],"type":"Point"}
}