{
  "type": "Feature",
  "properties": {
    "iso:country":"US",
    "sg:address":"662 Palisades View Dr",
    "sg:city":"Eureka",
    "sg:classifiers":[
        {
            "category":"Professional",
            "subcategory":"Engineering",
            "type":"Services"
        }
    ],
    "sg:phone":"+1 314 541 1115",
    "sg:postcode":"63025",
    "sg:province":"MO",
    "sg:tags":[
        "consulting",
        "engineer"
    ],
    "wof:name":"Brncic Engineering, Inc.",
    "wof:placetype":"venue"
},
  "geometry": {"coordinates":[-90.636819,38.491553],"type":"Point"}
}