{
  "type": "Feature",
  "properties": {
    "iso:country":"US",
    "sg:address":"505 E Main St",
    "sg:city":"Richland",
    "sg:classifiers":[
        {
            "category":"Professional",
            "subcategory":"Art Services",
            "type":"Services"
        }
    ],
    "sg:phone":"+1 573 765 3934",
    "sg:postcode":"65556",
    "sg:province":"MO",
    "sg:tags":[
        "commercial",
        "design"
    ],
    "wof:name":"Lownsberry Illustration & Dsgn",
    "wof:placetype":"venue"
},
  "geometry": {"coordinates":[-92.397521,37.854043],"type":"Point"}
}