{
  "type": "Feature",
  "properties": {
    "iso:country":"US",
    "sg:address":"708 Whitney St",
    "sg:city":"Kennett",
    "sg:classifiers":[
        {
            "category":"Manufacturing",
            "subcategory":"Tools & Machinery",
            "type":"Manufacturing & Wholesale Goods"
        }
    ],
    "sg:phone":"+1 573 888 4080",
    "sg:postcode":"63857",
    "sg:province":"MO",
    "sg:tags":[
        "machine",
        "shop",
        "mfg"
    ],
    "wof:name":"Webco Machine & Tool Co",
    "wof:placetype":"venue"
},
  "geometry": {"coordinates":[-90.04769,36.237505],"type":"Point"}
}