{
  "type": "Feature",
  "properties": {
    "iso:country":"US",
    "sg:address":"1803 Oak Ridge Cir",
    "sg:city":"St Joseph",
    "sg:classifiers":[
        {
            "category":"Personal",
            "subcategory":"Beauty Salon",
            "type":"Services"
        }
    ],
    "sg:phone":"+1 816 676 0622",
    "sg:postcode":"64506",
    "sg:province":"MO",
    "sg:tags":[
        "shop"
    ],
    "wof:name":"Panache Full Service Salon",
    "wof:placetype":"venue"
},
  "geometry": {"coordinates":[-94.79832399999999,39.784193],"type":"Point"}
}