{
  "type": "Feature",
  "properties": {
    "iso:country":"US",
    "sg:address":"2049 Southern Expy",
    "sg:city":"Cape Girardeau",
    "sg:classifiers":[
        {
            "category":"Building & Trades",
            "subcategory":"Electrical",
            "type":"Services"
        }
    ],
    "sg:phone":"+1 573 335 8110",
    "sg:postcode":"63703",
    "sg:province":"MO",
    "sg:tags":[
        "electrical",
        "contractor"
    ],
    "wof:name":"Cotner Electric Co",
    "wof:placetype":"venue"
},
  "geometry": {"coordinates":[-89.54950100000001,37.281394],"type":"Point"}
}