{
  "type": "Feature",
  "properties": {
    "iso:country":"US",
    "sg:address":"1105 Walnut St",
    "sg:city":"Doniphan",
    "sg:classifiers":[
        {
            "category":"Social Services",
            "type":"Services"
        },
        {
            "category":"Social Services",
            "subcategory":"Child Care",
            "type":"Services"
        }
    ],
    "sg:phone":"+1 573 996 2648",
    "sg:postcode":"63935",
    "sg:province":"MO",
    "sg:tags":[
        "nursery",
        "day"
    ],
    "wof:name":"Ozark Foothills Child Advocacy",
    "wof:placetype":"venue"
},
  "geometry": {"coordinates":[-90.844307,36.613789],"type":"Point"}
}