{
  "type": "Feature",
  "properties": {
    "iso:country":"US",
    "sg:address":"5901 Troost Ave",
    "sg:city":"Kansas City",
    "sg:classifiers":[
        {
            "category":"Professional",
            "subcategory":"Accounting & Tax Preparation",
            "type":"Services"
        }
    ],
    "sg:phone":"+1 816 363 8500",
    "sg:postcode":"64110",
    "sg:province":"MO",
    "sg:tags":[
        "bookkeeping",
        "general"
    ],
    "wof:name":"J E Harshaw & Assoc Accounting",
    "wof:placetype":"venue"
},
  "geometry": {"coordinates":[-94.574297,39.018294],"type":"Point"}
}