{
  "type": "Feature",
  "properties": {
    "iso:country":"US",
    "sg:address":"706 De Mun Ave",
    "sg:city":"Saint Louis",
    "sg:classifiers":[
        {
            "category":"Professional",
            "subcategory":"Employment Agencies",
            "type":"Services"
        }
    ],
    "sg:phone":"+1 314 725 3488",
    "sg:postcode":"63105",
    "sg:province":"MO",
    "wof:name":"Employer Resources",
    "wof:placetype":"venue"
},
  "geometry": {"coordinates":[-90.30789900000001,38.6385],"type":"Point"}
}