{
  "type": "Feature",
  "properties": {
    "iso:country":"US",
    "sg:address":"611 Main St",
    "sg:city":"Trenton",
    "sg:classifiers":[
        {
            "category":"Autos & Motor Vehicles",
            "subcategory":"Automobile Sales",
            "type":"Retail Goods"
        }
    ],
    "sg:phone":"+1 660 359 0080",
    "sg:postcode":"64683",
    "sg:province":"MO",
    "sg:tags":[
        "car",
        "dealer"
    ],
    "wof:name":"Auto-Matic Financing & Sales",
    "wof:placetype":"venue"
},
  "geometry": {"coordinates":[-93.61946500000001,40.073601],"type":"Point"}
}