{
  "type": "Feature",
  "properties": {
    "iso:country":"US",
    "sg:address":"31 Homestead Ln",
    "sg:city":"Troy",
    "sg:classifiers":[
        {
            "category":"Wholesale",
            "subcategory":"Machinery & Supplies",
            "type":"Manufacturing & Wholesale Goods"
        }
    ],
    "sg:phone":"+1 636 462 2850",
    "sg:postcode":"63379",
    "sg:province":"MO",
    "sg:tags":[
        "distributor",
        "maintenance"
    ],
    "wof:name":"J J Enterprises",
    "wof:placetype":"venue"
},
  "geometry": {"coordinates":[-90.907963,39.03984],"type":"Point"}
}