{
  "type": "Feature",
  "properties": {
    "iso:country":"US",
    "sg:address":"6212 NW Barry Rd",
    "sg:city":"Kansas City",
    "sg:classifiers":[
        {
            "category":"Wholesale",
            "subcategory":"Non-durable Goods",
            "type":"Manufacturing & Wholesale Goods"
        },
        {
            "category":"Home & Garden",
            "subcategory":"Garden Supply",
            "type":"Retail Goods"
        }
    ],
    "sg:phone":"+1 816 746 1113",
    "sg:postcode":"64154",
    "sg:province":"MO",
    "sg:tags":[
        "house",
        "bird",
        "feeder"
    ],
    "wof:name":"Backyard Bird Center",
    "wof:placetype":"venue"
},
  "geometry": {"coordinates":[-94.647969,39.246966],"type":"Point"}
}