{
  "type": "Feature",
  "properties": {
    "iso:country":"US",
    "sg:address":"3607 Lafayette St",
    "sg:city":"St Joseph",
    "sg:classifiers":[
        {
            "category":"Retail",
            "subcategory":"Auto Repair",
            "type":"Services"
        }
    ],
    "sg:phone":"+1 816 232 1764",
    "sg:postcode":"64507",
    "sg:province":"MO",
    "sg:tags":[
        "repairing",
        "transmission",
        "general",
        "automobile",
        "automotive"
    ],
    "wof:name":"J & M Auto Repair",
    "wof:placetype":"venue"
},
  "geometry": {"coordinates":[-94.803794,39.758062],"type":"Point"}
}