{
  "type": "Feature",
  "properties": {
    "iso:country":"US",
    "sg:address":"126 Tulip Tree Dr",
    "sg:city":"St Charles",
    "sg:classifiers":[
        {
            "category":"Wholesale",
            "subcategory":"Machinery & Supplies",
            "type":"Manufacturing & Wholesale Goods"
        }
    ],
    "sg:phone":"+1 636 248 5251",
    "sg:postcode":"63304",
    "sg:province":"MO",
    "sg:tags":[
        "pressure",
        "washing",
        "equipment"
    ],
    "wof:name":"Quality Power Wash",
    "wof:placetype":"venue"
},
  "geometry": {"coordinates":[-90.61019400000001,38.753204],"type":"Point"}
}