{
  "type": "Feature",
  "properties": {
    "iso:country":"US",
    "sg:address":"122 Manlyn Dr",
    "sg:city":"Saint Louis",
    "sg:classifiers":[
        {
            "category":"Restaurant",
            "type":"Food & Drink"
        }
    ],
    "sg:phone":"+1 314 822 3098",
    "sg:postcode":"63122",
    "sg:province":"MO",
    "sg:tags":[
        "eating"
    ],
    "wof:name":"Brunch By Design",
    "wof:placetype":"venue"
},
  "geometry": {"coordinates":[-90.40447899999999,38.59666],"type":"Point"}
}