{
  "type": "Feature",
  "properties": {
    "iso:country":"US",
    "sg:address":"1020 W Buchanan St",
    "sg:city":"California",
    "sg:classifiers":[
        {
            "category":"Retail",
            "subcategory":"Car Wash",
            "type":"Services"
        }
    ],
    "sg:phone":"+1 573 796 5646",
    "sg:postcode":"65018",
    "sg:province":"MO",
    "sg:tags":[
        "automobile",
        "detail",
        "clean"
    ],
    "wof:name":"Hampton Auto Sales & Car Care",
    "wof:placetype":"venue"
},
  "geometry": {"coordinates":[-92.58102,38.631102],"type":"Point"}
}