{
  "type": "Feature",
  "properties": {
    "iso:country":"US",
    "sg:address":"6363 Bartmer Industrial Dr",
    "sg:city":"St Louis",
    "sg:classifiers":[
        {
            "category":"Wholesale",
            "subcategory":"Construction Materials",
            "type":"Manufacturing & Wholesale Goods"
        },
        {
            "category":"Home & Garden",
            "subcategory":"Building Materials",
            "type":"Retail Goods"
        }
    ],
    "sg:phone":"+1 314 726 2225",
    "sg:postcode":"63130",
    "sg:province":"MO",
    "sg:tags":[
        "roofing"
    ],
    "sg:website":"www.warriorbp.com",
    "wof:name":"Warrior Building Products Inc",
    "wof:placetype":"venue"
},
  "geometry": {"coordinates":[-90.29924099999999,38.663766],"type":"Point"}
}