{
  "type": "Feature",
  "properties": {
    "iso:country":"US",
    "sg:address":"7801 NW Hwy M",
    "sg:city":"Appleton City",
    "sg:phone":"+1 660 476 5696",
    "sg:postcode":"64724",
    "sg:province":"MO",
    "sg:tags":[
        "farm",
        "corn",
        "wheat",
        "soybean"
    ],
    "wof:name":"Claude Bock",
    "wof:placetype":"venue"
},
  "geometry": {"coordinates":[-93.92556999999999,38.140815],"type":"Point"}
}