{
  "type": "Feature",
  "properties": {
    "iso:country":"US",
    "sg:address":"300 E 9th St",
    "sg:city":"Carrollton",
    "sg:classifiers":[
        {
            "category":"Government",
            "subcategory":"Office",
            "type":"Public Place"
        },
        {
            "category":"Education",
            "subcategory":"School",
            "type":"Public Place"
        }
    ],
    "sg:phone":"+1 660 542 1276",
    "sg:postcode":"64633",
    "sg:province":"MO",
    "sg:tags":[
        "educational",
        "program",
        "administrative"
    ],
    "wof:name":"Carrollton Senior High School",
    "wof:placetype":"venue"
},
  "geometry": {"coordinates":[-93.491067,39.368266],"type":"Point"}
}