{
  "type": "Feature",
  "properties": {
    "iso:country":"US",
    "sg:address":"9828 S Broadway",
    "sg:city":"Saint Louis",
    "sg:classifiers":[
        {
            "category":"Social Services",
            "subcategory":"Child Care",
            "type":"Services"
        }
    ],
    "sg:phone":"+1 314 544 3338",
    "sg:postcode":"63125",
    "sg:province":"MO",
    "sg:tags":[
        "center",
        "day"
    ],
    "wof:name":"Lemay Child & Famly Center",
    "wof:placetype":"venue"
},
  "geometry": {"coordinates":[-90.277185,38.526613],"type":"Point"}
}