{
  "type": "Feature",
  "properties": {
    "iso:country":"US",
    "sg:address":"2201 N Westwood Blvd",
    "sg:city":"Poplar Bluff",
    "sg:classifiers":[
        {
            "category":"Banks & Credit Unions",
            "subcategory":"Bank",
            "type":"Services"
        }
    ],
    "sg:phone":"+1 573 776 1999",
    "sg:postcode":"63901",
    "sg:province":"MO",
    "sg:tags":[
        "loan",
        "institution",
        "business"
    ],
    "wof:name":"Bluff Fast Cash",
    "wof:placetype":"venue"
},
  "geometry": {"coordinates":[-90.424299,36.779179],"type":"Point"}
}