{
  "type": "Feature",
  "properties": {
    "iso:country":"US",
    "sg:address":"1911 US Hwy 40",
    "sg:city":"Blue Springs",
    "sg:classifiers":[
        {
            "category":"Manufacturing",
            "subcategory":"Signs",
            "type":"Manufacturing & Wholesale Goods"
        }
    ],
    "sg:phone":"+1 816 229 1234",
    "sg:postcode":"64015",
    "sg:province":"MO",
    "sg:tags":[
        "specialty",
        "mfg"
    ],
    "wof:name":"Vital Signs",
    "wof:placetype":"venue"
},
  "geometry": {"coordinates":[-94.287363,39.00935],"type":"Point"}
}