{
  "type": "Feature",
  "properties": {
    "iso:country":"US",
    "sg:address":"9225 Ward Pkwy N",
    "sg:city":"Kansas City",
    "sg:classifiers":[
        {
            "category":"Health Services",
            "subcategory":"Doctor",
            "type":"Services"
        }
    ],
    "sg:phone":"+1 816 333 3337",
    "sg:postcode":"64114",
    "sg:province":"MO",
    "sg:tags":[
        "dentist"
    ],
    "wof:name":"T L C Dental Care",
    "wof:placetype":"venue"
},
  "geometry": {"coordinates":[-94.597911,38.959778],"type":"Point"}
}