{
  "type": "Feature",
  "properties": {
    "addr:full":"882 State Hwy 291 Liberty MO 64068",
    "addr:housenumber":"882",
    "addr:postcode":"64068",
    "addr:street":"State Hwy 291",
    "iso:country":"US",
    "sg:address":"882 State Hwy 291",
    "sg:city":"Liberty",
    "sg:classifiers":[
        {
            "category":"Retail",
            "subcategory":"Laundry & Dry Cleaning",
            "type":"Services"
        }
    ],
    "sg:phone":"+1 816 792 9916",
    "sg:postcode":"64068",
    "sg:province":"MO",
    "sg:tags":[
        "cleaners"
    ],
    "wof:name":"Pride Stanley & Executive",
    "wof:placetype":"venue"
},
  "geometry": {"coordinates":[-94.435351,39.238146],"type":"Point"}
}