{
  "type": "Feature",
  "properties": {
    "iso:country":"US",
    "sg:address":"5200 Oak St",
    "sg:city":"Kansas City",
    "sg:classifiers":[
        {
            "category":"Social Services",
            "type":"Services"
        }
    ],
    "sg:phone":"+1 816 444 1142",
    "sg:postcode":"64112",
    "sg:province":"MO",
    "sg:tags":[
        "senior",
        "citizen"
    ],
    "wof:name":"Shepherd's Connection",
    "wof:placetype":"venue"
},
  "geometry": {"coordinates":[-94.582978,39.029142],"type":"Point"}
}