{
  "type": "Feature",
  "properties": {
    "iso:country":"US",
    "sg:address":"101 Ladue Aire Dr",
    "sg:city":"Creve Coeur",
    "sg:classifiers":[
        {
            "category":"Building & Trades",
            "subcategory":"Plumbing",
            "type":"Services"
        }
    ],
    "sg:phone":"+1 314 434 5551",
    "sg:postcode":"63141",
    "sg:province":"MO",
    "sg:tags":[
        "plumbing",
        "sub",
        "contractor"
    ],
    "wof:name":"De Luca Plumbing LLC",
    "wof:placetype":"venue"
},
  "geometry": {"coordinates":[-90.47593500000001,38.652711],"type":"Point"}
}