{
  "type": "Feature",
  "properties": {
    "iso:country":"US",
    "sg:address":"3101 Main St",
    "sg:city":"Kansas City",
    "sg:classifiers":[
        {
            "category":"Education",
            "subcategory":"School",
            "type":"Public Place"
        }
    ],
    "sg:phone":"+1 816 841 2284",
    "sg:postcode":"64111",
    "sg:province":"MO",
    "sg:tags":[
        "academic",
        "special"
    ],
    "sg:website":"www.ccvi.org",
    "wof:name":"Children's Center",
    "wof:placetype":"venue"
},
  "geometry": {"coordinates":[-94.585364,39.070051],"type":"Point"}
}