{
  "type": "Feature",
  "properties": {
    "iso:country":"US",
    "sg:address":"8396 Simpson Hill",
    "sg:city":"Cedar Hill",
    "sg:classifiers":[
        {
            "category":"Professional",
            "subcategory":"Art Services",
            "type":"Services"
        }
    ],
    "sg:phone":"+1 636 274 0919",
    "sg:postcode":"63016",
    "sg:province":"MO",
    "sg:tags":[
        "graphic",
        "designer"
    ],
    "wof:name":"ZEC",
    "wof:placetype":"venue"
},
  "geometry": {"coordinates":[-90.64821999999999,38.327459],"type":"Point"}
}