{
  "type": "Feature",
  "properties": {
    "iso:country":"US",
    "sg:address":"3774 Gumtree Ln",
    "sg:city":"Saint Louis",
    "sg:classifiers":[
        {
            "category":"Professional",
            "subcategory":"Detective & Security Services",
            "type":"Services"
        }
    ],
    "sg:phone":"+1 314 487 9137",
    "sg:postcode":"63129",
    "sg:province":"MO",
    "sg:tags":[
        "contract",
        "investigator"
    ],
    "wof:name":"James Stabile",
    "wof:placetype":"venue"
},
  "geometry": {"coordinates":[-90.347819,38.472963],"type":"Point"}
}