{
  "type": "Feature",
  "properties": {
    "iso:country":"US",
    "sg:address":"7359 Hazelwood Ave",
    "sg:city":"Hazelwood",
    "sg:classifiers":[
        {
            "category":"Manufacturing",
            "subcategory":"Food",
            "type":"Manufacturing & Wholesale Goods"
        }
    ],
    "sg:phone":"+1 314 524 6320",
    "sg:postcode":"63042",
    "sg:province":"MO",
    "sg:tags":[
        "canned",
        "dr",
        "soft",
        "mfg"
    ],
    "wof:name":"Rainbow Fruit Juice",
    "wof:placetype":"venue"
},
  "geometry": {"coordinates":[-90.343795,38.774524],"type":"Point"}
}