{
  "type": "Feature",
  "properties": {
    "iso:country":"US",
    "sg:address":"3296 Rider Trl S",
    "sg:city":"Earth City",
    "sg:classifiers":[
        {
            "category":"Restaurant",
            "type":"Food & Drink"
        }
    ],
    "sg:menulink":"http://www.allmenus.com/mo/northwest/194132-mcdonalds/menu/",
    "sg:postcode":"63045",
    "sg:province":"MO",
    "sg:tags":[
        "burger",
        "american"
    ],
    "wof:name":"McDonald's",
    "wof:placetype":"venue"
},
  "geometry": {"coordinates":[-90.45479,38.761602],"type":"Point"}
}