{
  "type": "Feature",
  "properties": {
    "iso:country":"US",
    "sg:address":"727 S 15th St",
    "sg:city":"St Joseph",
    "sg:classifiers":[
        {
            "category":"Government",
            "subcategory":"Office",
            "type":"Public Place"
        }
    ],
    "sg:phone":"+1 816 271 4664",
    "sg:postcode":"64501",
    "sg:province":"MO",
    "sg:tags":[
        "village"
    ],
    "wof:name":"St Joseph City Neighborhood",
    "wof:placetype":"venue"
},
  "geometry": {"coordinates":[-94.842253,39.760396],"type":"Point"}
}