{
  "type": "Feature",
  "properties": {
    "iso:country":"US",
    "sg:address":"203 E 10th St",
    "sg:city":"Eldon",
    "sg:classifiers":[
        {
            "category":"Real Estate",
            "subcategory":"Real Estate Agent",
            "type":"Services"
        }
    ],
    "sg:phone":"+1 573 392 9900",
    "sg:postcode":"65026",
    "sg:province":"MO",
    "wof:name":"B & L Veatch Realty",
    "wof:placetype":"venue"
},
  "geometry": {"coordinates":[-92.580866,38.34197],"type":"Point"}
}