{
  "type": "Feature",
  "properties": {
    "iso:country":"US",
    "sg:address":"2101 W Chestnut Expy",
    "sg:city":"Springfield",
    "sg:classifiers":[
        {
            "category":"Organizations",
            "subcategory":"Religious Organization",
            "type":"Services"
        }
    ],
    "sg:phone":"+1 417 865 4338",
    "sg:postcode":"65802",
    "sg:province":"MO",
    "sg:tags":[
        "church"
    ],
    "wof:name":"Deliverance Temple Church",
    "wof:placetype":"venue"
},
  "geometry": {"coordinates":[-93.31976899999999,37.214503],"type":"Point"}
}