{
  "type": "Feature",
  "properties": {
    "iso:country":"US",
    "sg:address":"18850 N Jay Jay",
    "sg:city":"Centralia",
    "sg:classifiers":[
        {
            "category":"Retail",
            "subcategory":"Animal Services",
            "type":"Services"
        }
    ],
    "sg:phone":"+1 573 682 2597",
    "sg:postcode":"65240",
    "sg:province":"MO",
    "sg:tags":[
        "pet"
    ],
    "wof:name":"Slip Check Co",
    "wof:placetype":"venue"
},
  "geometry": {"coordinates":[-92.167044,39.172248],"type":"Point"}
}