{
  "type": "Feature",
  "properties": {
    "iso:country":"US",
    "sg:address":"5734 S Main St",
    "sg:city":"Joplin",
    "sg:classifiers":[
        {
            "category":"Organizations",
            "subcategory":"Religious Organization",
            "type":"Services"
        }
    ],
    "sg:phone":"+1 417 781 7501",
    "sg:postcode":"64804",
    "sg:province":"MO",
    "sg:tags":[
        "church"
    ],
    "wof:name":"Peace Tabernacles",
    "wof:placetype":"venue"
},
  "geometry": {"coordinates":[-94.51542499999999,37.027235],"type":"Point"}
}