{
  "type": "Feature",
  "properties": {
    "iso:country":"US",
    "sg:address":"19 Gravois Bluffs Plaza Dr",
    "sg:city":"Fenton",
    "sg:classifiers":[
        {
            "category":"Building & Trades",
            "subcategory":"Equipment Rental",
            "type":"Services"
        }
    ],
    "sg:phone":"+1 636 349 0008",
    "sg:postcode":"63026",
    "sg:province":"MO",
    "sg:tags":[
        "leasing",
        "furniture"
    ],
    "wof:name":"Rent-A-Center",
    "wof:placetype":"venue"
},
  "geometry": {"coordinates":[-90.44729100000001,38.508903],"type":"Point"}
}