{
  "type": "Feature",
  "properties": {
    "iso:country":"US",
    "sg:address":"113 S Prairie St",
    "sg:city":"Bloomfield",
    "sg:classifiers":[
        {
            "category":"Professional",
            "subcategory":"Lawyer & Legal Services",
            "type":"Services"
        }
    ],
    "sg:phone":"+1 573 568 4518",
    "sg:postcode":"63825",
    "sg:province":"MO",
    "sg:tags":[
        "attorney",
        "practice"
    ],
    "wof:name":"Briney And Welborn Law Office",
    "wof:placetype":"venue"
},
  "geometry": {"coordinates":[-89.929205,36.884353],"type":"Point"}
}