{
  "type": "Feature",
  "properties": {
    "iso:country":"US",
    "sg:address":"8108 Co Rd 166",
    "sg:city":"Carthage",
    "sg:classifiers":[
        {
            "category":"Manufacturing",
            "subcategory":"Metals",
            "type":"Manufacturing & Wholesale Goods"
        }
    ],
    "sg:phone":"+1 417 359 4272",
    "sg:postcode":"64836",
    "sg:province":"MO",
    "sg:tags":[
        "ornamental",
        "work"
    ],
    "wof:name":"Ozark Iron Works",
    "wof:placetype":"venue"
},
  "geometry": {"coordinates":[-94.357947,37.173304],"type":"Point"}
}