{
  "type": "Feature",
  "properties": {
    "iso:country":"US",
    "sg:address":"27 Seven Oaks Dr",
    "sg:city":"Chesterfield",
    "sg:classifiers":[
        {
            "category":"Manufacturing",
            "subcategory":"Watercraft",
            "type":"Manufacturing & Wholesale Goods"
        }
    ],
    "sg:phone":"+1 636 386 1100",
    "sg:postcode":"63005",
    "sg:province":"MO",
    "sg:tags":[
        "barge"
    ],
    "wof:name":"Barge Management Inc",
    "wof:placetype":"venue"
},
  "geometry": {"coordinates":[-90.594416,38.62114],"type":"Point"}
}