{
  "type": "Feature",
  "properties": {
    "iso:country":"US",
    "sg:address":"508 Walnut St",
    "sg:city":"Richmond",
    "sg:classifiers":[
        {
            "category":"Professional",
            "subcategory":"Detective & Security Services",
            "type":"Services"
        }
    ],
    "sg:phone":"+1 816 776 3882",
    "sg:postcode":"64085",
    "sg:province":"MO",
    "sg:tags":[
        "car"
    ],
    "wof:name":"Dar Shan Investigations",
    "wof:placetype":"venue"
},
  "geometry": {"coordinates":[-93.966765,39.289121],"type":"Point"}
}