{
  "type": "Feature",
  "properties": {
    "iso:country":"US",
    "sg:address":"1807 Chestnut St",
    "sg:city":"Trenton",
    "sg:classifiers":[
        {
            "category":"Social Services",
            "subcategory":"Child Care",
            "type":"Services"
        }
    ],
    "sg:phone":"+1 660 359 2662",
    "sg:postcode":"64683",
    "sg:province":"MO",
    "sg:tags":[
        "kindergarten",
        "academic",
        "school"
    ],
    "wof:name":"Head Start School",
    "wof:placetype":"venue"
},
  "geometry": {"coordinates":[-93.618548,40.083867],"type":"Point"}
}