{
  "type": "Feature",
  "properties": {
    "iso:country":"US",
    "sg:address":"4313 SW Sapelo Dr",
    "sg:city":"Lees Summit",
    "sg:classifiers":[
        {
            "category":"Travel",
            "subcategory":"Travel Agent",
            "type":"Entertainment"
        }
    ],
    "sg:phone":"+1 816 537 4533",
    "sg:postcode":"64082",
    "sg:province":"MO",
    "sg:tags":[
        "agency"
    ],
    "sg:website":"www.cruzdreams.com",
    "wof:name":"Cruise Dreams",
    "wof:placetype":"venue"
},
  "geometry": {"coordinates":[-94.38141899999999,38.840692],"type":"Point"}
}