{
  "type": "Feature",
  "properties": {
    "iso:country":"US",
    "sg:address":"1717 Fenpark Dr",
    "sg:city":"Fenton",
    "sg:classifiers":[
        {
            "category":"Manufacturing",
            "subcategory":"Signs",
            "type":"Manufacturing & Wholesale Goods"
        }
    ],
    "sg:phone":"+1 636 343 9400",
    "sg:postcode":"63026",
    "sg:province":"MO",
    "sg:tags":[
        "surgical",
        "specialty",
        "mfg"
    ],
    "sg:website":"www.quickpoint.com",
    "wof:name":"Quick Point Inc",
    "wof:placetype":"venue"
},
  "geometry": {"coordinates":[-90.448995,38.540549],"type":"Point"}
}