{
  "type": "Feature",
  "properties": {
    "iso:country":"US",
    "sg:address":"3120 Gillham Plz",
    "sg:city":"Kansas City",
    "sg:classifiers":[
        {
            "category":"Food & Beverages",
            "subcategory":"Liquor & Beverages",
            "type":"Retail Goods"
        }
    ],
    "sg:phone":"+1 816 753 4135",
    "sg:postcode":"64109",
    "sg:province":"MO",
    "wof:name":"Berbiglia Wines & Spirits",
    "wof:placetype":"venue"
},
  "geometry": {"coordinates":[-94.57909100000001,39.068809],"type":"Point"}
}