{
  "type": "Feature",
  "properties": {
    "iso:country":"US",
    "sg:address":"895 Bolger Ct",
    "sg:city":"Fenton",
    "sg:classifiers":[
        {
            "category":"Autos & Motor Vehicles",
            "subcategory":"Fuel & Gas Station",
            "type":"Retail Goods"
        }
    ],
    "sg:phone":"+1 636 343 9770",
    "sg:postcode":"63026",
    "sg:province":"MO",
    "sg:tags":[
        "convenience",
        "station",
        "store"
    ],
    "wof:name":"U-Gas Inc",
    "wof:placetype":"venue"
},
  "geometry": {"coordinates":[-90.459142,38.540813],"type":"Point"}
}