{
  "type": "Feature",
  "properties": {
    "iso:country":"US",
    "sg:address":"4915 Emerson Ave",
    "sg:city":"Saint Louis",
    "sg:classifiers":[
        {
            "category":"Building & Trades",
            "subcategory":"Construction",
            "type":"Services"
        }
    ],
    "sg:phone":"+1 314 385 3270",
    "sg:postcode":"63120",
    "sg:province":"MO",
    "sg:tags":[
        "house"
    ],
    "wof:name":"J&J Home Remodelers",
    "wof:placetype":"venue"
},
  "geometry": {"coordinates":[-90.252396,38.690994],"type":"Point"}
}