{
  "type": "Feature",
  "properties": {
    "iso:country":"US",
    "sg:address":"135 W Rose Ave",
    "sg:city":"Saint Louis",
    "sg:classifiers":[
        {
            "category":"Manufacturing",
            "subcategory":"Printing",
            "type":"Manufacturing & Wholesale Goods"
        }
    ],
    "sg:phone":"+1 314 971 7530",
    "sg:postcode":"63119",
    "sg:province":"MO",
    "sg:tags":[
        "periodical"
    ],
    "wof:name":"Intermission Magazine",
    "wof:placetype":"venue"
},
  "geometry": {"coordinates":[-90.361262,38.570567],"type":"Point"}
}