{
  "type": "Feature",
  "properties": {
    "iso:country":"US",
    "sg:address":"1225 N Warson Rd",
    "sg:city":"St Louis",
    "sg:classifiers":[
        {
            "category":"Manufacturing",
            "subcategory":"Chemicals & Compounds",
            "type":"Manufacturing & Wholesale Goods"
        }
    ],
    "sg:phone":"+1 314 835 1317",
    "sg:postcode":"63132",
    "sg:province":"MO",
    "sg:tags":[
        "paint",
        "varnish",
        "allied",
        "product"
    ],
    "wof:name":"Vanex Color Inc",
    "wof:placetype":"venue"
},
  "geometry": {"coordinates":[-90.394656,38.682716],"type":"Point"}
}