{
  "type": "Feature",
  "properties": {
    "iso:country":"US",
    "sg:address":"21307 Hwy D",
    "sg:city":"Eolia",
    "sg:classifiers":[
        {
            "category":"Professional",
            "subcategory":"Lawyer & Legal Services",
            "type":"Services"
        }
    ],
    "sg:phone":"+1 573 485 6122",
    "sg:postcode":"63344",
    "sg:province":"MO",
    "sg:tags":[
        "attorney"
    ],
    "wof:name":"John Bruere",
    "wof:placetype":"venue"
},
  "geometry": {"coordinates":[-90.99790299999999,39.278468],"type":"Point"}
}