{
  "type": "Feature",
  "properties": {
    "iso:country":"US",
    "sg:address":"1807 Sherwood Dr",
    "sg:city":"Cape Girardeau",
    "sg:classifiers":[
        {
            "category":"Manufacturing",
            "subcategory":"Chemicals & Compounds",
            "type":"Manufacturing & Wholesale Goods"
        }
    ],
    "sg:phone":"+1 573 335 4758",
    "sg:postcode":"63701",
    "sg:province":"MO",
    "sg:tags":[
        "plastic"
    ],
    "wof:name":"Cape Polymers Inc",
    "wof:placetype":"venue"
},
  "geometry": {"coordinates":[-89.548209,37.341517],"type":"Point"}
}