{
  "type": "Feature",
  "properties": {
    "iso:country":"US",
    "sg:address":"498 Lake Center",
    "sg:city":"St Charles",
    "sg:classifiers":[
        {
            "category":"Recreation",
            "subcategory":"Marina",
            "type":"Entertainment"
        }
    ],
    "sg:phone":"+1 636 250 7500",
    "sg:postcode":"63301",
    "sg:province":"MO",
    "sg:website":"www.lakecentermarina.com",
    "wof:name":"Lake Center Marina",
    "wof:placetype":"venue"
},
  "geometry": {"coordinates":[-90.495187,38.900733],"type":"Point"}
}