{
  "type": "Feature",
  "properties": {
    "iso:country":"US",
    "sg:address":"96 Worth Rd",
    "sg:city":"Saint Louis",
    "sg:classifiers":[
        {
            "category":"Shopping",
            "subcategory":"Discount & Variety Stores",
            "type":"Retail Goods"
        }
    ],
    "sg:phone":"+1 314 845 2467",
    "sg:postcode":"63125",
    "sg:province":"MO",
    "wof:name":"US Coast Guard Exchange Svc",
    "wof:placetype":"venue"
},
  "geometry": {"coordinates":[-90.28412400000001,38.505004],"type":"Point"}
}