{
  "type": "Feature",
  "properties": {
    "iso:country":"US",
    "sg:address":"2358 Lackland Rd",
    "sg:city":"Saint Louis",
    "sg:classifiers":[
        {
            "category":"Real Estate",
            "subcategory":"Real Estate Operator",
            "type":"Services"
        }
    ],
    "sg:phone":"+1 314 429 2870",
    "sg:postcode":"63114",
    "sg:province":"MO",
    "sg:tags":[
        "building",
        "nonresidential"
    ],
    "wof:name":"Overland Lions Home Assn",
    "wof:placetype":"venue"
},
  "geometry": {"coordinates":[-90.377888,38.699513],"type":"Point"}
}