{
  "type": "Feature",
  "properties": {
    "iso:country":"US",
    "sg:address":"3118 N River Blvd",
    "sg:city":"Independence",
    "sg:classifiers":[
        {
            "category":"Shopping",
            "subcategory":"Catalog Store",
            "type":"Retail Goods"
        }
    ],
    "sg:phone":"+1 816 833 3636",
    "sg:postcode":"64050",
    "sg:province":"MO",
    "sg:tags":[
        "mail",
        "order",
        "online"
    ],
    "wof:name":"Matts Rx",
    "wof:placetype":"venue"
},
  "geometry": {"coordinates":[-94.425014,39.121898],"type":"Point"}
}