{
  "type": "Feature",
  "properties": {
    "iso:country":"US",
    "sg:address":"325 S 5th St",
    "sg:city":"Saint Charles",
    "sg:classifiers":[
        {
            "category":"Shopping",
            "subcategory":"Stationery & Office Supplies",
            "type":"Retail Goods"
        }
    ],
    "sg:phone":"+1 636 946 6655",
    "sg:postcode":"63301",
    "sg:province":"MO",
    "sg:tags":[
        "photocopying",
        "du",
        "printing",
        "offset"
    ],
    "wof:name":"Wilcoxen Office Supply",
    "wof:placetype":"venue"
},
  "geometry": {"coordinates":[-90.487167,38.780929],"type":"Point"}
}