{
  "type": "Feature",
  "properties": {
    "iso:country":"US",
    "sg:address":"1235 N Main St",
    "sg:city":"Poplar Bluff",
    "sg:classifiers":[
        {
            "category":"Education",
            "subcategory":"School",
            "type":"Public Place"
        }
    ],
    "sg:phone":"+1 573 785 4905",
    "sg:postcode":"63901",
    "sg:province":"MO",
    "wof:name":"New Mark Twain Elementary Schl",
    "wof:placetype":"venue"
},
  "geometry": {"coordinates":[-90.40168,36.768091],"type":"Point"}
}