{
  "type": "Feature",
  "properties": {
    "iso:country":"US",
    "sg:address":"18600 E 37 Ter S",
    "sg:city":"Independence",
    "sg:classifiers":[
        {
            "category":"Professional",
            "subcategory":"Accounting & Tax Preparation",
            "type":"Services"
        }
    ],
    "sg:phone":"+1 816 461 8288",
    "sg:postcode":"64057",
    "sg:province":"MO",
    "sg:tags":[
        "billing"
    ],
    "wof:name":"Midland Group",
    "wof:placetype":"venue"
},
  "geometry": {"coordinates":[-94.36171299999999,39.0505],"type":"Point"}
}