{
  "type": "Feature",
  "properties": {
    "iso:country":"US",
    "sg:address":"1244 E Lark St",
    "sg:city":"Springfield",
    "sg:classifiers":[
        {
            "category":"Health Services",
            "subcategory":"Dentist",
            "type":"Services"
        }
    ],
    "sg:phone":"+1 417 881 1388",
    "sg:postcode":"65804",
    "sg:province":"MO",
    "sg:tags":[
        "dental",
        "clinic"
    ],
    "sg:website":"http://www.buzbeedental.com",
    "wof:name":"Buzbee Dental Clinic",
    "wof:placetype":"venue"
},
  "geometry": {"coordinates":[-93.27798300000001,37.135043],"type":"Point"}
}