{
  "type": "Feature",
  "properties": {
    "iso:country":"US",
    "sg:address":"217 Main St",
    "sg:city":"Mc Fall",
    "sg:classifiers":[
        {
            "category":"Bars & Pubs",
            "type":"Food & Drink"
        }
    ],
    "sg:phone":"+1 660 439 5452",
    "sg:postcode":"64643",
    "sg:province":"MO",
    "sg:tags":[
        "lounge",
        "cocktail"
    ],
    "wof:name":"Short Stop Lounge",
    "wof:placetype":"venue"
},
  "geometry": {"coordinates":[-93.342654,39.604513],"type":"Point"}
}