{
  "type": "Feature",
  "properties": {
    "iso:country":"US",
    "sg:address":"1803 Allison St",
    "sg:city":"Kennett",
    "sg:classifiers":[
        {
            "category":"Professional",
            "subcategory":"Lawyer & Legal Services",
            "type":"Services"
        }
    ],
    "sg:phone":"+1 573 888 1887",
    "sg:postcode":"63857",
    "sg:province":"MO",
    "sg:tags":[
        "attorney",
        "practice"
    ],
    "wof:name":"Edgington, Richard P",
    "wof:placetype":"venue"
},
  "geometry": {"coordinates":[-90.023453,36.256419],"type":"Point"}
}