{
  "type": "Feature",
  "properties": {
    "iso:country":"US",
    "sg:address":"1214 E 3rd St",
    "sg:city":"Maryville",
    "sg:classifiers":[
        {
            "category":"Professional",
            "subcategory":"Business Services",
            "type":"Services"
        }
    ],
    "sg:phone":"+1 660 582 7164",
    "sg:postcode":"64468",
    "sg:province":"MO",
    "sg:tags":[
        "appraiser"
    ],
    "wof:name":"Jim Merrigan Auctioneer",
    "wof:placetype":"venue"
},
  "geometry": {"coordinates":[-94.859669,40.347579],"type":"Point"}
}