{
  "type": "Feature",
  "properties": {
    "iso:country":"US",
    "sg:address":"2123 W Republic Rd",
    "sg:city":"Springfield",
    "sg:classifiers":[
        {
            "category":"Restaurant",
            "type":"Food & Drink"
        }
    ],
    "sg:phone":"+1 417 890 8788",
    "sg:postcode":"65807",
    "sg:province":"MO",
    "sg:tags":[
        "eating"
    ],
    "wof:name":"China King",
    "wof:placetype":"venue"
},
  "geometry": {"coordinates":[-93.321158,37.138451],"type":"Point"}
}