{
  "type": "Feature",
  "properties": {
    "iso:country":"US",
    "sg:address":"304 W Bridge St",
    "sg:city":"Keytesville",
    "sg:classifiers":[
        {
            "category":"Bars & Pubs",
            "type":"Food & Drink"
        }
    ],
    "sg:phone":"+1 660 288 3149",
    "sg:postcode":"65261",
    "sg:province":"MO",
    "sg:tags":[
        "drinking"
    ],
    "wof:name":"Sherry's Place",
    "wof:placetype":"venue"
},
  "geometry": {"coordinates":[-92.938844,39.434617],"type":"Point"}
}