{
  "type": "Feature",
  "properties": {
    "iso:country":"US",
    "sg:address":"12324 Betsy Ross Ln",
    "sg:city":"Saint Louis",
    "sg:classifiers":[
        {
            "category":"Insurance",
            "subcategory":"Insurance Agent",
            "type":"Services"
        }
    ],
    "sg:phone":"+1 314 434 4668",
    "sg:postcode":"63146",
    "sg:province":"MO",
    "wof:name":"Woodruff Insurance",
    "wof:placetype":"venue"
},
  "geometry": {"coordinates":[-90.453975,38.679236],"type":"Point"}
}