{
  "type": "Feature",
  "properties": {
    "iso:country":"US",
    "sg:address":"204 Driftwood Dr",
    "sg:city":"Sedalia",
    "sg:classifiers":[
        {
            "category":"Professional",
            "type":"Services"
        }
    ],
    "sg:phone":"+1 660 826 7749",
    "sg:postcode":"65301",
    "sg:province":"MO",
    "wof:name":"Cerebral Palsy of Mid Mis",
    "wof:placetype":"venue"
},
  "geometry": {"coordinates":[-93.249616,38.688986],"type":"Point"}
}