{
  "type": "Feature",
  "properties": {
    "iso:country":"US",
    "sg:address":"11430 Gravois Rd",
    "sg:city":"Sappington",
    "sg:classifiers":[
        {
            "category":"Insurance",
            "subcategory":"Insurance Agent",
            "type":"Services"
        }
    ],
    "sg:phone":"+1 314 843 4001",
    "sg:postcode":"63126",
    "sg:province":"MO",
    "wof:name":"National Council-Compensation",
    "wof:placetype":"venue"
},
  "geometry": {"coordinates":[-90.376245,38.538164],"type":"Point"}
}