{
  "type": "Feature",
  "properties": {
    "iso:country":"US",
    "sg:address":"4151 Benne Rd",
    "sg:city":"Defiance",
    "sg:classifiers":[
        {
            "category":"Recreation",
            "type":"Entertainment"
        }
    ],
    "sg:phone":"+1 636 828 5711",
    "sg:postcode":"63341",
    "sg:province":"MO",
    "sg:tags":[
        "club",
        "membership"
    ],
    "wof:name":"Bridle Spur Hunt Club",
    "wof:placetype":"venue"
},
  "geometry": {"coordinates":[-90.82611199999999,38.708012],"type":"Point"}
}