{
  "type": "Feature",
  "properties": {
    "iso:country":"US",
    "sg:address":"221 N Chapman Ave",
    "sg:city":"Mountain Grove",
    "sg:classifiers":[
        {
            "category":"Autos & Motor Vehicles",
            "subcategory":"Automobile Sales",
            "type":"Retail Goods"
        }
    ],
    "sg:phone":"+1 417 926 5143",
    "sg:postcode":"65711",
    "sg:province":"MO",
    "sg:tags":[
        "car",
        "dealer"
    ],
    "wof:name":"Morris Motors",
    "wof:placetype":"venue"
},
  "geometry": {"coordinates":[-92.26964,37.129926],"type":"Point"}
}