{
  "type": "Feature",
  "properties": {
    "iso:country":"US",
    "sg:address":"11268 Olive Blvd",
    "sg:city":"St Louis",
    "sg:classifiers":[
        {
            "category":"Retail",
            "subcategory":"Laundry & Dry Cleaning",
            "type":"Services"
        }
    ],
    "sg:phone":"+1 314 872 8098",
    "sg:postcode":"63141",
    "sg:province":"MO",
    "sg:tags":[
        "cleaners"
    ],
    "wof:name":"Henry Cleaners & Shirt Laundry",
    "wof:placetype":"venue"
},
  "geometry": {"coordinates":[-90.42951600000001,38.671507],"type":"Point"}
}