{
  "type": "Feature",
  "properties": {
    "iso:country":"US",
    "sg:address":"6124 E Connecticut Ave",
    "sg:city":"Kansas City",
    "sg:classifiers":[
        {
            "category":"Building & Trades",
            "subcategory":"Construction",
            "type":"Services"
        }
    ],
    "sg:phone":"+1 816 231 2281",
    "sg:postcode":"64120",
    "sg:province":"MO",
    "sg:tags":[
        "interior",
        "industrial",
        "design",
        "contractor"
    ],
    "wof:name":"Chief Industries Inc",
    "wof:placetype":"venue"
},
  "geometry": {"coordinates":[-94.510419,39.132819],"type":"Point"}
}