{
  "type": "Feature",
  "properties": {
    "iso:country":"US",
    "sg:address":"160 S County Centerway",
    "sg:city":"St Louis",
    "sg:classifiers":[
        {
            "category":"Food & Beverages",
            "subcategory":"Specialty",
            "type":"Retail Goods"
        }
    ],
    "sg:phone":"+1 314 909 9057",
    "sg:postcode":"63129",
    "sg:province":"MO",
    "sg:tags":[
        "tea",
        "coffee"
    ],
    "wof:name":"Sho Me Bubble Tea",
    "wof:placetype":"venue"
},
  "geometry": {"coordinates":[-90.328703,38.504252],"type":"Point"}
}