{
  "type": "Feature",
  "properties": {
    "iso:country":"US",
    "sg:address":"3815 Seneca St",
    "sg:city":"Saint Joseph",
    "sg:classifiers":[
        {
            "category":"Manufacturing",
            "subcategory":"Tools & Machinery",
            "type":"Manufacturing & Wholesale Goods"
        }
    ],
    "sg:phone":"+1 816 901 0338",
    "sg:postcode":"64507",
    "sg:province":"MO",
    "sg:tags":[
        "industrial",
        "mfg"
    ],
    "wof:name":"B W Carousels",
    "wof:placetype":"venue"
},
  "geometry": {"coordinates":[-94.79924699999999,39.757106],"type":"Point"}
}