{
  "type": "Feature",
  "properties": {
    "iso:country":"US",
    "sg:address":"110 State Rte H",
    "sg:city":"Edgar Springs",
    "sg:classifiers":[
        {
            "category":"Retail",
            "subcategory":"Animal Services",
            "type":"Services"
        }
    ],
    "sg:phone":"+1 573 435 9259",
    "sg:postcode":"65462",
    "sg:province":"MO",
    "wof:name":"Puppy Trax Kennels",
    "wof:placetype":"venue"
},
  "geometry": {"coordinates":[-91.86608099999999,37.697764],"type":"Point"}
}