{
  "type": "Feature",
  "properties": {
    "iso:country":"US",
    "sg:address":"4141 Ponotoc Ln",
    "sg:city":"House Springs",
    "sg:classifiers":[
        {
            "category":"Communications",
            "subcategory":"Radio Station",
            "type":"Services"
        }
    ],
    "sg:phone":"+1 636 677 6680",
    "sg:postcode":"63051",
    "sg:province":"MO",
    "sg:tags":[
        "broadcast"
    ],
    "wof:name":"Mary G Beckmann President",
    "wof:placetype":"venue"
},
  "geometry": {"coordinates":[-90.53685900000001,38.427635],"type":"Point"}
}