{
  "type": "Feature",
  "properties": {
    "iso:country":"US",
    "sg:address":"278 Jefferson Rd",
    "sg:city":"Branson",
    "sg:phone":"+1 417 239 1372",
    "sg:postcode":"65616",
    "sg:province":"MO",
    "wof:name":"Crossland Boat & Self Storage",
    "wof:placetype":"venue"
},
  "geometry": {"coordinates":[-93.217466,36.707804],"type":"Point"}
}