{
  "type": "Feature",
  "properties": {
    "iso:country":"US",
    "sg:address":"2302 S 11th St",
    "sg:city":"St Joseph",
    "sg:classifiers":[
        {
            "category":"Bars & Pubs",
            "type":"Food & Drink"
        }
    ],
    "sg:phone":"+1 816 233 6960",
    "sg:postcode":"64503",
    "sg:province":"MO",
    "sg:tags":[
        "drinking"
    ],
    "wof:name":"Hickory Tavern",
    "wof:placetype":"venue"
},
  "geometry": {"coordinates":[-94.84671899999999,39.742362],"type":"Point"}
}