{
  "type": "Feature",
  "properties": {
    "iso:country":"US",
    "sg:address":"6570 Impala Dr",
    "sg:city":"Joplin",
    "sg:classifiers":[
        {
            "category":"Building & Trades",
            "subcategory":"Plumbing",
            "type":"Services"
        }
    ],
    "sg:phone":"+1 417 623 1223",
    "sg:postcode":"64804",
    "sg:province":"MO",
    "sg:tags":[
        "contractor"
    ],
    "wof:name":"Lyerla Sheet Metal",
    "wof:placetype":"venue"
},
  "geometry": {"coordinates":[-94.444312,36.977546],"type":"Point"}
}