{
  "type": "Feature",
  "properties": {
    "iso:country":"US",
    "sg:address":"101 E Weeks St",
    "sg:city":"Elmer",
    "sg:classifiers":[
        {
            "category":"Professional",
            "type":"Services"
        }
    ],
    "sg:phone":"+1 660 825 4212",
    "sg:postcode":"63538",
    "sg:province":"MO",
    "sg:tags":[
        "establishment"
    ],
    "wof:name":"Elmer Garage & Repair",
    "wof:placetype":"venue"
},
  "geometry": {"coordinates":[-92.650386,39.955558],"type":"Point"}
}