{
  "type": "Feature",
  "properties": {
    "iso:country":"US",
    "sg:address":"3900 Vogel Rd",
    "sg:city":"Arnold",
    "sg:classifiers":[
        {
            "category":"Food & Beverages",
            "subcategory":"Groceries & Convenience Stores",
            "type":"Retail Goods"
        }
    ],
    "sg:phone":"+1 636 282 3377",
    "sg:postcode":"63010",
    "sg:province":"MO",
    "sg:tags":[
        "grocer"
    ],
    "wof:name":"Schnucks",
    "wof:placetype":"venue"
},
  "geometry": {"coordinates":[-90.391188,38.41604],"type":"Point"}
}