{
  "type": "Feature",
  "properties": {
    "iso:country":"US",
    "sg:address":"1119 Hillside Dr",
    "sg:city":"Chillicothe",
    "sg:classifiers":[
        {
            "category":"Organizations",
            "subcategory":"Membership Organization",
            "type":"Services"
        }
    ],
    "sg:phone":"+1 660 646 1943",
    "sg:postcode":"64601",
    "sg:province":"MO",
    "wof:name":"Uct",
    "wof:placetype":"venue"
},
  "geometry": {"coordinates":[-93.566523,39.798534],"type":"Point"}
}