{
  "type": "Feature",
  "properties": {
    "iso:country":"US",
    "sg:address":"3235 E Jackson Blvd",
    "sg:city":"Jackson",
    "sg:classifiers":[
        {
            "category":"Shopping",
            "subcategory":"Jewelry",
            "type":"Retail Goods"
        }
    ],
    "sg:phone":"+1 573 204 7875",
    "sg:postcode":"63755",
    "sg:province":"MO",
    "wof:name":"Creative Bead Workshop",
    "wof:placetype":"venue"
},
  "geometry": {"coordinates":[-89.630957,37.362927],"type":"Point"}
}