{
  "type": "Feature",
  "properties": {
    "iso:country":"US",
    "sg:address":"5100 NW Gateway Ave",
    "sg:city":"Kansas City",
    "sg:classifiers":[
        {
            "category":"Shopping",
            "subcategory":"Jewelry",
            "type":"Retail Goods"
        }
    ],
    "sg:phone":"+1 816 587 6200",
    "sg:postcode":"64150",
    "sg:province":"MO",
    "sg:tags":[
        "stone",
        "op"
    ],
    "wof:name":"Skyline Inn",
    "wof:placetype":"venue"
},
  "geometry": {"coordinates":[-94.613314,39.187364],"type":"Point"}
}