{
  "type": "Feature",
  "properties": {
    "iso:country":"US",
    "sg:address":"4400 N Wyatt Ln",
    "sg:city":"Columbia",
    "sg:classifiers":[
        {
            "category":"Building & Trades",
            "subcategory":"Plumbing",
            "type":"Services"
        }
    ],
    "sg:phone":"+1 573 474 1510",
    "sg:postcode":"65202",
    "sg:province":"MO",
    "sg:tags":[
        "plumber",
        "industrial",
        "contractors-commercial"
    ],
    "wof:name":"Titus Plumbing",
    "wof:placetype":"venue"
},
  "geometry": {"coordinates":[-92.25507500000001,38.997943],"type":"Point"}
}