{
  "type": "Feature",
  "properties": {
    "iso:country":"US",
    "sg:address":"1820 Market St",
    "sg:city":"St Louis",
    "sg:classifiers":[
        {
            "category":"Shopping",
            "subcategory":"Jewelry",
            "type":"Retail Goods"
        }
    ],
    "sg:phone":"+1 314 621 7188",
    "sg:postcode":"63103",
    "sg:province":"MO",
    "sg:tags":[
        "jeweler"
    ],
    "wof:name":"I Love Rice",
    "wof:placetype":"venue"
},
  "geometry": {"coordinates":[-90.208922,38.629748],"type":"Point"}
}