{
  "type": "Feature",
  "properties": {
    "iso:country":"US",
    "sg:address":"8665 Kingsbridge Ln",
    "sg:city":"St Louis",
    "sg:classifiers":[
        {
            "category":"Personal",
            "type":"Services"
        }
    ],
    "sg:phone":"+1 314 989 9400",
    "sg:postcode":"63132",
    "sg:province":"MO",
    "sg:tags":[
        "house",
        "sitter"
    ],
    "wof:name":"St Louis Housesitters",
    "wof:placetype":"venue"
},
  "geometry": {"coordinates":[-90.35968,38.663986],"type":"Point"}
}