{
  "type": "Feature",
  "properties": {
    "iso:country":"US",
    "sg:address":"202 SE 3 St",
    "sg:city":"Lees Summit",
    "sg:classifiers":[
        {
            "category":"Building & Trades",
            "subcategory":"Landscaping Services",
            "type":"Services"
        }
    ],
    "sg:phone":"+1 816 525 1984",
    "sg:postcode":"64063",
    "sg:province":"MO",
    "sg:tags":[
        "lawn",
        "maintenance",
        "grounds"
    ],
    "wof:name":"Paragon Lawns",
    "wof:placetype":"venue"
},
  "geometry": {"coordinates":[-94.37330900000001,38.913904],"type":"Point"}
}