{
  "type": "Feature",
  "properties": {
    "iso:country":"US",
    "sg:address":"916 W Atlantic St",
    "sg:city":"Springfield",
    "sg:classifiers":[
        {
            "category":"Retail",
            "subcategory":"Laundry & Dry Cleaning",
            "type":"Services"
        }
    ],
    "sg:phone":"+1 417 869 6533",
    "sg:postcode":"65803",
    "sg:province":"MO",
    "sg:tags":[
        "cleaners"
    ],
    "wof:name":"Glo Dry Cleaning Specialists",
    "wof:placetype":"venue"
},
  "geometry": {"coordinates":[-93.30190399999999,37.233378],"type":"Point"}
}