{
  "type": "Feature",
  "properties": {
    "iso:country":"US",
    "sg:address":"4600 Co Rd 257",
    "sg:city":"Fulton",
    "sg:classifiers":[
        {
            "category":"Farming",
            "subcategory":"Livestock Farm",
            "type":"Manufacturing & Wholesale Goods"
        }
    ],
    "sg:phone":"+1 573 642 4912",
    "sg:postcode":"65251",
    "sg:province":"MO",
    "sg:tags":[
        "beef",
        "feedlot",
        "cattle"
    ],
    "wof:name":"Danny Rose",
    "wof:placetype":"venue"
},
  "geometry": {"coordinates":[-92.097735,38.893969],"type":"Point"}
}