{
  "type": "Feature",
  "properties": {
    "iso:country":"US",
    "sg:address":"100 S Maple St",
    "sg:city":"Cole Camp",
    "sg:classifiers":[
        {
            "category":"Restaurant",
            "type":"Food & Drink"
        }
    ],
    "sg:phone":"+1 660 668 2333",
    "sg:postcode":"65325",
    "sg:province":"MO",
    "wof:name":"Der Essenn Platz",
    "wof:placetype":"venue"
},
  "geometry": {"coordinates":[-93.202556,38.460214],"type":"Point"}
}