{
  "type": "Feature",
  "properties": {
    "iso:country":"US",
    "sg:address":"2036 N National Ave",
    "sg:city":"Springfield",
    "sg:classifiers":[
        {
            "category":"Building & Trades",
            "subcategory":"Plumbing",
            "type":"Services"
        }
    ],
    "sg:phone":"+1 417 863 6840",
    "sg:postcode":"65803",
    "sg:province":"MO",
    "sg:tags":[
        "plumbing",
        "contractor"
    ],
    "wof:name":"Drussa Plumbing",
    "wof:placetype":"venue"
},
  "geometry": {"coordinates":[-93.274947,37.234447],"type":"Point"}
}