{
  "type": "Feature",
  "properties": {
    "iso:country":"US",
    "sg:address":"1005 Fair St",
    "sg:city":"Chillicothe",
    "sg:classifiers":[
        {
            "category":"Retail",
            "subcategory":"Auto Rental",
            "type":"Services"
        },
        {
            "category":"Local Transit",
            "type":"Transportation"
        }
    ],
    "sg:phone":"+1 660 646 2585",
    "sg:postcode":"64601",
    "sg:province":"MO",
    "sg:tags":[
        "shuttle",
        "limousine"
    ],
    "wof:name":"Sweet Ride Limousine Service",
    "wof:placetype":"venue"
},
  "geometry": {"coordinates":[-93.559174,39.796862],"type":"Point"}
}