{
  "type": "Feature",
  "properties": {
    "iso:country":"US",
    "sg:address":"203 Railroad St",
    "sg:city":"Steele",
    "sg:classifiers":[
        {
            "category":"Manufacturing",
            "subcategory":"Tools & Machinery",
            "type":"Manufacturing & Wholesale Goods"
        }
    ],
    "sg:phone":"+1 573 695 3755",
    "sg:postcode":"63877",
    "sg:province":"MO",
    "sg:tags":[
        "die",
        "maker"
    ],
    "wof:name":"Steele Tool & Mfg",
    "wof:placetype":"venue"
},
  "geometry": {"coordinates":[-89.808882,36.047734],"type":"Point"}
}