{
  "type": "Feature",
  "properties": {
    "iso:country":"US",
    "sg:address":"11100 N Congress Ave",
    "sg:city":"Kansas City",
    "sg:classifiers":[
        {
            "category":"Manufacturing",
            "subcategory":"Chemicals & Compounds",
            "type":"Manufacturing & Wholesale Goods"
        }
    ],
    "sg:phone":"+1 816 891 1600",
    "sg:postcode":"64153",
    "sg:province":"MO",
    "sg:tags":[
        "agricultural",
        "mfg"
    ],
    "wof:name":"West Agro Inc",
    "wof:placetype":"venue"
},
  "geometry": {"coordinates":[-94.667969,39.289596],"type":"Point"}
}