{
  "type": "Feature",
  "properties": {
    "iso:country":"US",
    "sg:address":"354 State Hwy Hh",
    "sg:city":"Piedmont",
    "sg:classifiers":[
        {
            "category":"Retail",
            "subcategory":"Auto Repair",
            "type":"Services"
        }
    ],
    "sg:phone":"+1 573 223 3654",
    "sg:postcode":"63957",
    "sg:province":"MO",
    "sg:tags":[
        "general"
    ],
    "wof:name":"Jackson Automotive",
    "wof:placetype":"venue"
},
  "geometry": {"coordinates":[-90.702381,37.138007],"type":"Point"}
}