{
  "type": "Feature",
  "properties": {
    "iso:country":"US",
    "sg:address":"526 Muirfield Dr",
    "sg:city":"Saint Charles",
    "sg:classifiers":[
        {
            "category":"Organizations",
            "subcategory":"Religious Organization",
            "type":"Services"
        }
    ],
    "sg:phone":"+1 636 926 2701",
    "sg:postcode":"63304",
    "sg:province":"MO",
    "wof:name":"North County Community Church",
    "wof:placetype":"venue"
},
  "geometry": {"coordinates":[-90.61189299999999,38.71475],"type":"Point"}
}