{
  "type": "Feature",
  "properties": {
    "iso:country":"US",
    "sg:address":"725 Industrial Rd",
    "sg:city":"Chillicothe",
    "sg:classifiers":[
        {
            "category":"Wholesale",
            "subcategory":"Groceries",
            "type":"Manufacturing & Wholesale Goods"
        }
    ],
    "sg:phone":"+1 660 646 6918",
    "sg:postcode":"64601",
    "sg:province":"MO",
    "sg:tags":[
        "food",
        "broker"
    ],
    "wof:name":"John Graves Food Svc",
    "wof:placetype":"venue"
},
  "geometry": {"coordinates":[-93.54337599999999,39.779577],"type":"Point"}
}