{
  "type": "Feature",
  "properties": {
    "iso:country":"US",
    "sg:address":"11430 Saint Charles Rock Rd",
    "sg:city":"Bridgeton",
    "sg:classifiers":[
        {
            "category":"Insurance",
            "subcategory":"Insurance Agent",
            "type":"Services"
        }
    ],
    "sg:phone":"+1 314 298 3445",
    "sg:postcode":"63044",
    "sg:province":"MO",
    "wof:name":"Shelter Insurance",
    "wof:placetype":"venue"
},
  "geometry": {"coordinates":[-90.406853,38.7418],"type":"Point"}
}