{
  "type": "Feature",
  "properties": {
    "iso:country":"US",
    "sg:address":"13714 E 42nd Ter S",
    "sg:city":"Independence",
    "sg:phone":"+1 816 737 2700",
    "sg:postcode":"64055",
    "sg:province":"MO",
    "sg:website":"http://www.smartsiding.com",
    "wof:name":"Continental Siding Supply",
    "wof:placetype":"venue"
},
  "geometry": {"coordinates":[-94.418785,39.044083],"type":"Point"}
}