{
  "type": "Feature",
  "properties": {
    "iso:country":"US",
    "sg:address":"5135 Lemay Ferry Rd",
    "sg:city":"Saint Louis",
    "sg:classifiers":[
        {
            "category":"Real Estate",
            "subcategory":"Real Estate Operator",
            "type":"Services"
        }
    ],
    "sg:phone":"+1 314 487 0150",
    "sg:postcode":"63129",
    "sg:province":"MO",
    "sg:tags":[
        "building",
        "commercial"
    ],
    "wof:name":"Butler Hill Plaza Shopping Ctr",
    "wof:placetype":"venue"
},
  "geometry": {"coordinates":[-90.349304,38.484828],"type":"Point"}
}