{
  "type": "Feature",
  "properties": {
    "iso:country":"US",
    "sg:address":"11150 N Rte Z",
    "sg:city":"Hallsville",
    "sg:classifiers":[
        {
            "category":"Professional",
            "subcategory":"Business Services",
            "type":"Services"
        }
    ],
    "sg:phone":"+1 573 696 0030",
    "sg:postcode":"65255",
    "sg:province":"MO",
    "sg:tags":[
        "auctioneer"
    ],
    "wof:name":"Conklin's Auction Svc",
    "wof:placetype":"venue"
},
  "geometry": {"coordinates":[-92.16146500000001,39.079711],"type":"Point"}
}