{
  "type": "Feature",
  "properties": {
    "iso:country":"US",
    "sg:address":"1335 Lakemont Dr",
    "sg:city":"Arnold",
    "sg:classifiers":[
        {
            "category":"Building & Trades",
            "subcategory":"Construction",
            "type":"Services"
        }
    ],
    "sg:phone":"+1 636 282 0020",
    "sg:postcode":"63010",
    "sg:province":"MO",
    "sg:tags":[
        "wallcoverings-installation",
        "wallpaper",
        "painting",
        "contractor"
    ],
    "wof:name":"James Mier Painting",
    "wof:placetype":"venue"
},
  "geometry": {"coordinates":[-90.417824,38.449532],"type":"Point"}
}