{
  "type": "Feature",
  "properties": {
    "iso:country":"US",
    "sg:address":"1223 N Glenn Ave",
    "sg:city":"Springfield",
    "sg:classifiers":[
        {
            "category":"Shopping",
            "subcategory":"Gifts & Souvenirs",
            "type":"Retail Goods"
        }
    ],
    "sg:phone":"+1 417 864 6196",
    "sg:postcode":"65802",
    "sg:province":"MO",
    "wof:name":"Crazy Beads & Gifts",
    "wof:placetype":"venue"
},
  "geometry": {"coordinates":[-93.334367,37.221798],"type":"Point"}
}