{
  "type": "Feature",
  "properties": {
    "iso:country":"US",
    "sg:address":"18018 State Hwy J",
    "sg:city":"Monroe City",
    "sg:classifiers":[
        {
            "category":"Food & Beverages",
            "subcategory":"Groceries & Convenience Stores",
            "type":"Retail Goods"
        }
    ],
    "sg:phone":"+1 573 735 4436",
    "sg:postcode":"63456",
    "sg:province":"MO",
    "wof:name":"Russells One Stop",
    "wof:placetype":"venue"
},
  "geometry": {"coordinates":[-91.655175,39.573976],"type":"Point"}
}