{
  "type": "Feature",
  "properties": {
    "iso:country":"US",
    "sg:address":"4430 Woodson Rd",
    "sg:city":"St Louis",
    "sg:classifiers":[
        {
            "category":"Retail",
            "subcategory":"Repair Shop",
            "type":"Services"
        },
        {
            "category":"Building & Trades",
            "subcategory":"Plumbing",
            "type":"Services"
        }
    ],
    "sg:phone":"+1 314 733 1776",
    "sg:postcode":"63134",
    "sg:province":"MO",
    "sg:tags":[
        "air",
        "equipment",
        "mechanical",
        "conditioning",
        "contractor"
    ],
    "wof:name":"American Services St Louis LLC",
    "wof:placetype":"venue"
},
  "geometry": {"coordinates":[-90.357354,38.730666],"type":"Point"}
}