{
  "type": "Feature",
  "properties": {
    "iso:country":"US",
    "sg:address":"12804 Partridge Run Dr",
    "sg:city":"Florissant",
    "sg:classifiers":[
        {
            "category":"Professional",
            "subcategory":"Management & Consulting",
            "type":"Services"
        }
    ],
    "sg:phone":"+1 314 355 0586",
    "sg:postcode":"63033",
    "sg:province":"MO",
    "sg:tags":[
        "telecommunication"
    ],
    "wof:name":"Eagle Communications & Conslt",
    "wof:placetype":"venue"
},
  "geometry": {"coordinates":[-90.241355,38.810113],"type":"Point"}
}