{
  "type": "Feature",
  "properties": {
    "iso:country":"US",
    "sg:address":"3815 Magnolia Ave",
    "sg:city":"St Louis",
    "sg:classifiers":[
        {
            "category":"Education",
            "subcategory":"Library",
            "type":"Public Place"
        }
    ],
    "sg:phone":"+1 314 776 4320",
    "sg:postcode":"63110",
    "sg:province":"MO",
    "sg:tags":[
        "special",
        "interest"
    ],
    "sg:website":"www.msb.k12.mo.us",
    "wof:name":"Missouri School-The Blind Libr",
    "wof:placetype":"venue"
},
  "geometry": {"coordinates":[-90.245206,38.60763],"type":"Point"}
}