{
  "type": "Feature",
  "properties": {
    "iso:country":"US",
    "sg:address":"200 W 1st St",
    "sg:city":"Farmington",
    "sg:classifiers":[
        {
            "category":"Retail",
            "subcategory":"Event Space",
            "type":"Services"
        }
    ],
    "sg:phone":"+1 573 366 4628",
    "sg:postcode":"63640",
    "sg:province":"MO",
    "sg:tags":[
        "facility",
        "hall",
        "reception",
        "banquet"
    ],
    "wof:name":"Alexander's",
    "wof:placetype":"venue"
},
  "geometry": {"coordinates":[-90.42305,37.779308],"type":"Point"}
}