{
  "type": "Feature",
  "properties": {
    "iso:country":"US",
    "sg:address":"3944 Vogel Rd",
    "sg:city":"Arnold",
    "sg:classifiers":[
        {
            "category":"Banks & Credit Unions",
            "subcategory":"Bank",
            "type":"Services"
        }
    ],
    "sg:phone":"+1 636 282 9000",
    "sg:postcode":"63010",
    "sg:province":"MO",
    "sg:tags":[
        "mortgage"
    ],
    "sg:website":"www.eaglebankandtrust.com",
    "wof:name":"Eagle Bank & Trust Co",
    "wof:placetype":"venue"
},
  "geometry": {"coordinates":[-90.391836,38.415716],"type":"Point"}
}