{
  "type": "Feature",
  "properties": {
    "iso:country":"US",
    "sg:address":"317 N Broadview St",
    "sg:city":"Cape Girardeau",
    "sg:classifiers":[
        {
            "category":"Retail",
            "subcategory":"Auto Repair",
            "type":"Services"
        }
    ],
    "sg:phone":"+1 573 335 5052",
    "sg:postcode":"63701",
    "sg:province":"MO",
    "sg:tags":[
        "towing",
        "wrecker"
    ],
    "wof:name":"Sperling Garage & Wrecker Svc",
    "wof:placetype":"venue"
},
  "geometry": {"coordinates":[-89.553961,37.312556],"type":"Point"}
}