{
  "type": "Feature",
  "properties": {
    "iso:country":"US",
    "sg:address":"141 Sherman Ridge",
    "sg:city":"Gravois Mills",
    "sg:classifiers":[
        {
            "category":"Autos & Motor Vehicles",
            "subcategory":"Boat Sales",
            "type":"Retail Goods"
        }
    ],
    "sg:phone":"+1 573 374 1796",
    "sg:postcode":"65037",
    "sg:province":"MO",
    "sg:tags":[
        "top",
        "upholstery",
        "cover"
    ],
    "wof:name":"Advanced Custom Canvas",
    "wof:placetype":"venue"
},
  "geometry": {"coordinates":[-92.81965,38.193439],"type":"Point"}
}