{
  "type": "Feature",
  "properties": {
    "iso:country":"US",
    "sg:address":"59 Turner St",
    "sg:city":"Fort Leonard Wood",
    "sg:classifiers":[
        {
            "category":"Social Services",
            "subcategory":"Child Care",
            "type":"Services"
        }
    ],
    "sg:phone":"+1 573 329 5247",
    "sg:postcode":"65473",
    "sg:province":"MO",
    "wof:name":"Erah Ford",
    "wof:placetype":"venue"
},
  "geometry": {"coordinates":[-92.13381699999999,37.775725],"type":"Point"}
}