{
  "type": "Feature",
  "properties": {
    "iso:country":"US",
    "sg:address":"6020 Old Antonia Rd",
    "sg:city":"Imperial",
    "sg:classifiers":[
        {
            "category":"Organizations",
            "subcategory":"Religious Organization",
            "type":"Services"
        }
    ],
    "sg:phone":"+1 636 464 1013",
    "sg:postcode":"63052",
    "sg:province":"MO",
    "sg:tags":[
        "catholic",
        "church"
    ],
    "wof:name":"Saint Jsphs Rman Cthlic Church",
    "wof:placetype":"venue"
},
  "geometry": {"coordinates":[-90.410877,38.358463],"type":"Point"}
}