{
  "type": "Feature",
  "properties": {
    "iso:country":"US",
    "sg:address":"6761 SW Thornton Rd",
    "sg:city":"Clarksdale",
    "sg:classifiers":[
        {
            "category":"Farming",
            "subcategory":"Farm",
            "type":"Manufacturing & Wholesale Goods"
        }
    ],
    "sg:phone":"+1 816 261 9037",
    "sg:postcode":"64430",
    "sg:province":"MO",
    "wof:name":"Howard Weisenburger Farms",
    "wof:placetype":"venue"
},
  "geometry": {"coordinates":[-94.592608,39.807124],"type":"Point"}
}