{
  "type": "Feature",
  "properties": {
    "iso:country":"US",
    "sg:address":"900 Airport Rd",
    "sg:city":"Festus",
    "sg:classifiers":[
        {
            "category":"Airport",
            "type":"Transportation"
        }
    ],
    "sg:phone":"+1 636 937 2228",
    "sg:postcode":"63028",
    "sg:province":"MO",
    "wof:name":"Festus City Airport",
    "wof:placetype":"venue"
},
  "geometry": {"coordinates":[-90.38718,38.195399],"type":"Point"}
}