{
  "type": "Feature",
  "properties": {
    "addr:full":"1350 W College St Marshall MO 65340",
    "addr:housenumber":"1350",
    "addr:postcode":"65340",
    "addr:street":"W College St",
    "iso:country":"US",
    "sg:address":"1350 W College St",
    "sg:city":"Marshall",
    "sg:classifiers":[
        {
            "category":"Restaurant",
            "type":"Food & Drink"
        }
    ],
    "sg:phone":"+1 660 886 6565",
    "sg:postcode":"65340",
    "sg:province":"MO",
    "sg:tags":[
        "eating"
    ],
    "wof:name":"Domino's Pizza",
    "wof:placetype":"venue"
},
  "geometry": {"coordinates":[-93.215267,39.108261],"type":"Point"}
}