{
  "type": "Feature",
  "properties": {
    "iso:country":"US",
    "sg:address":"1005 Eastridge Dr",
    "sg:city":"Pacific",
    "sg:classifiers":[
        {
            "category":"Retail",
            "subcategory":"Repair Shop",
            "type":"Services"
        }
    ],
    "sg:phone":"+1 636 742 2850",
    "sg:postcode":"63069",
    "sg:province":"MO",
    "sg:tags":[
        "equipment",
        "industrial",
        "equipment-repairing",
        "welding"
    ],
    "wof:name":"Bucher & Sons",
    "wof:placetype":"venue"
},
  "geometry": {"coordinates":[-90.791921,38.491843],"type":"Point"}
}