{
  "type": "Feature",
  "properties": {
    "iso:country":"US",
    "sg:address":"2600 Virginia Ave",
    "sg:city":"Saint Louis",
    "sg:classifiers":[
        {
            "category":"Food & Beverages",
            "subcategory":"Groceries & Convenience Stores",
            "type":"Retail Goods"
        }
    ],
    "sg:phone":"+1 314 776 4350",
    "sg:postcode":"63118",
    "sg:province":"MO",
    "wof:name":"Barnett's Market",
    "wof:placetype":"venue"
},
  "geometry": {"coordinates":[-90.235603,38.6073],"type":"Point"}
}