{
  "type": "Feature",
  "properties": {
    "iso:country":"US",
    "sg:address":"311 2nd St",
    "sg:city":"Monett",
    "sg:classifiers":[
        {
            "category":"Building & Trades",
            "subcategory":"Construction",
            "type":"Services"
        }
    ],
    "sg:phone":"+1 417 236 0535",
    "sg:postcode":"65708",
    "sg:province":"MO",
    "sg:tags":[
        "general",
        "contractor"
    ],
    "wof:name":"B H Construction",
    "wof:placetype":"venue"
},
  "geometry": {"coordinates":[-93.926317,36.922094],"type":"Point"}
}