{
  "type": "Feature",
  "properties": {
    "iso:country":"US",
    "sg:address":"1802 W Vine St",
    "sg:city":"Harrisonville",
    "sg:classifiers":[
        {
            "category":"Professional",
            "subcategory":"Art Services",
            "type":"Services"
        }
    ],
    "sg:phone":"+1 816 380 4747",
    "sg:postcode":"64701",
    "sg:province":"MO",
    "sg:tags":[
        "designer",
        "display",
        "producer"
    ],
    "wof:name":"Western Materials & Design",
    "wof:placetype":"venue"
},
  "geometry": {"coordinates":[-94.363477,38.659932],"type":"Point"}
}