{
  "type": "Feature",
  "properties": {
    "iso:country":"US",
    "sg:address":"17286 Hilltop Ridge Dr",
    "sg:city":"Eureka",
    "sg:classifiers":[
        {
            "category":"Health Services",
            "subcategory":"Clinic",
            "type":"Services"
        }
    ],
    "sg:phone":"+1 636 938 1380",
    "sg:postcode":"63025",
    "sg:province":"MO",
    "sg:tags":[
        "welfare"
    ],
    "wof:name":"Asahi Kasei Medical America Inc",
    "wof:placetype":"venue"
},
  "geometry": {"coordinates":[-90.65114800000001,38.514769],"type":"Point"}
}