{
  "type": "Feature",
  "properties": {
    "iso:country":"US",
    "sg:address":"3926 N Grand Blvd",
    "sg:city":"St Louis",
    "sg:classifiers":[
        {
            "category":"Restaurant",
            "type":"Food & Drink"
        }
    ],
    "sg:phone":"+1 314 371 7777",
    "sg:postcode":"63107",
    "sg:province":"MO",
    "sg:tags":[
        "eating"
    ],
    "wof:name":"Grand Chop Suey",
    "wof:placetype":"venue"
},
  "geometry": {"coordinates":[-90.215227,38.663153],"type":"Point"}
}