{
  "type": "Feature",
  "properties": {
    "iso:country":"US",
    "sg:address":"44 County Road 512",
    "sg:city":"Wappapello",
    "sg:classifiers":[
        {
            "category":"Autos & Motor Vehicles",
            "subcategory":"Automobile Sales",
            "type":"Retail Goods"
        }
    ],
    "sg:phone":"+1 573 222 9800",
    "sg:postcode":"63966",
    "sg:province":"MO",
    "sg:tags":[
        "dealers-used",
        "car",
        "used",
        "cars-wholesale"
    ],
    "wof:name":"Miller Motor Company",
    "wof:placetype":"venue"
},
  "geometry": {"coordinates":[-90.29008899999999,36.905721],"type":"Point"}
}