{
  "type": "Feature",
  "properties": {
    "iso:country":"US",
    "sg:address":"3110 NE Vivion Rd",
    "sg:city":"Kansas City",
    "sg:classifiers":[
        {
            "category":"Wholesale",
            "subcategory":"Medical Equipment & Supplies",
            "type":"Manufacturing & Wholesale Goods"
        }
    ],
    "sg:phone":"+1 816 522 3052",
    "sg:postcode":"64119",
    "sg:province":"MO",
    "sg:tags":[
        "to",
        "surgical",
        "hospital",
        "sales",
        "surgery"
    ],
    "wof:name":"MGT Medical Distributor  LLC",
    "wof:placetype":"venue"
},
  "geometry": {"coordinates":[-94.541586,39.188173],"type":"Point"}
}