{
  "type": "Feature",
  "properties": {
    "iso:country":"US",
    "sg:address":"3904 Delmar Blvd",
    "sg:city":"Saint Louis",
    "sg:classifiers":[
        {
            "category":"Social Services",
            "subcategory":"Child Care",
            "type":"Services"
        }
    ],
    "sg:phone":"+1 314 371 9999",
    "sg:postcode":"63108",
    "sg:province":"MO",
    "sg:tags":[
        "day"
    ],
    "wof:name":"Happy Spirit Daycare",
    "wof:placetype":"venue"
},
  "geometry": {"coordinates":[-90.238401,38.642929],"type":"Point"}
}