{
  "type": "Feature",
  "properties": {
    "iso:country":"US",
    "sg:address":"6305 Garfield Ave",
    "sg:city":"St Louis",
    "sg:classifiers":[
        {
            "category":"Organizations",
            "subcategory":"Religious Organization",
            "type":"Services"
        }
    ],
    "sg:phone":"+1 314 521 0900",
    "sg:postcode":"63134",
    "sg:province":"MO",
    "sg:tags":[
        "church"
    ],
    "wof:name":"Harvest Church Of St Louis",
    "wof:placetype":"venue"
},
  "geometry": {"coordinates":[-90.333607,38.754566],"type":"Point"}
}