{
  "type": "Feature",
  "properties": {
    "iso:country":"US",
    "sg:address":"2344 N Lindbergh Blvd",
    "sg:city":"St Louis",
    "sg:classifiers":[
        {
            "category":"Professional",
            "subcategory":"Advertising",
            "type":"Services"
        }
    ],
    "sg:phone":"+1 314 426 5270",
    "sg:postcode":"63114",
    "sg:province":"MO",
    "sg:tags":[
        "publishing"
    ],
    "wof:name":"C T M Brochure Display Inc",
    "wof:placetype":"venue"
},
  "geometry": {"coordinates":[-90.408885,38.704902],"type":"Point"}
}