{
  "type": "Feature",
  "properties": {
    "iso:country":"US",
    "sg:address":"78 Davis St",
    "sg:city":"Saint Louis",
    "sg:classifiers":[
        {
            "category":"Government",
            "subcategory":"Office",
            "type":"Public Place"
        }
    ],
    "sg:phone":"+1 314 416 9315",
    "sg:postcode":"63125",
    "sg:province":"MO",
    "sg:tags":[
        "national",
        "security"
    ],
    "wof:name":"MO Natnal Gard Military Police",
    "wof:placetype":"venue"
},
  "geometry": {"coordinates":[-90.280681,38.503218],"type":"Point"}
}