{
  "type": "Feature",
  "properties": {
    "iso:country":"US",
    "sg:address":"38415 W 112th St",
    "sg:city":"Richmond",
    "sg:classifiers":[
        {
            "category":"Farming",
            "subcategory":"Farm",
            "type":"Manufacturing & Wholesale Goods"
        }
    ],
    "sg:phone":"+1 816 776 3054",
    "sg:postcode":"64085",
    "sg:province":"MO",
    "wof:name":"Harold Douglas Farms",
    "wof:placetype":"venue"
},
  "geometry": {"coordinates":[-94.038391,39.292372],"type":"Point"}
}