{
  "type": "Feature",
  "properties": {
    "iso:country":"US",
    "sg:address":"429 Central Ave",
    "sg:city":"Pattonsburg",
    "sg:classifiers":[
        {
            "category":"Retail",
            "subcategory":"Auto Repair",
            "type":"Services"
        }
    ],
    "sg:phone":"+1 660 367 4380",
    "sg:postcode":"64670",
    "sg:province":"MO",
    "sg:tags":[
        "general"
    ],
    "wof:name":"Hartley Service",
    "wof:placetype":"venue"
},
  "geometry": {"coordinates":[-94.10207,40.072211],"type":"Point"}
}