{
  "type": "Feature",
  "properties": {
    "iso:country":"US",
    "sg:address":"4732 McPherson Ave",
    "sg:city":"Saint Louis",
    "sg:classifiers":[
        {
            "category":"Shopping",
            "subcategory":"Antiques",
            "type":"Retail Goods"
        }
    ],
    "sg:phone":"+1 314 367 0588",
    "sg:postcode":"63108",
    "sg:province":"MO",
    "sg:website":"www.antiquecenterofstlouis.com",
    "wof:name":"Antique Center of St Louis",
    "wof:placetype":"venue"
},
  "geometry": {"coordinates":[-90.258904,38.647701],"type":"Point"}
}