{
  "type": "Feature",
  "properties": {
    "iso:country":"US",
    "sg:address":"507 Jordan Rd",
    "sg:city":"Old Monroe",
    "sg:classifiers":[
        {
            "category":"Organizations",
            "subcategory":"Membership Organization",
            "type":"Services"
        }
    ],
    "sg:phone":"+1 636 661 5372",
    "sg:postcode":"63369",
    "sg:province":"MO",
    "wof:name":"Chain of Rocks Gun Club Inc",
    "wof:placetype":"venue"
},
  "geometry": {"coordinates":[-90.79765399999999,38.917462],"type":"Point"}
}