{
  "type": "Feature",
  "properties": {
    "iso:country":"US",
    "sg:address":"60 S Kingshighway",
    "sg:city":"Cape Girardeau",
    "sg:classifiers":[
        {
            "category":"Retail",
            "subcategory":"Auto Rental",
            "type":"Services"
        }
    ],
    "sg:phone":"+1 573 339 7981",
    "sg:postcode":"63703",
    "sg:province":"MO",
    "sg:tags":[
        "renting",
        "truck",
        "leasing"
    ],
    "wof:name":"U-Haul Co",
    "wof:placetype":"venue"
},
  "geometry": {"coordinates":[-89.55181399999999,37.30562],"type":"Point"}
}