{
  "type": "Feature",
  "properties": {
    "iso:country":"US",
    "sg:address":"1415 Village Dr",
    "sg:city":"St Joseph",
    "sg:classifiers":[
        {
            "category":"Shopping",
            "subcategory":"Pharmacy",
            "type":"Retail Goods"
        }
    ],
    "sg:phone":"+1 816 279 6700",
    "sg:postcode":"64506",
    "sg:province":"MO",
    "wof:name":"R X Alternatives",
    "wof:placetype":"venue"
},
  "geometry": {"coordinates":[-94.79997,39.776956],"type":"Point"}
}