{
  "type": "Feature",
  "properties": {
    "iso:country":"US",
    "sg:address":"205 W Cleveland St",
    "sg:city":"West Plains",
    "sg:classifiers":[
        {
            "category":"Retail",
            "subcategory":"Repair Shop",
            "type":"Services"
        }
    ],
    "sg:phone":"+1 417 256 2060",
    "sg:postcode":"65775",
    "sg:province":"MO",
    "sg:tags":[
        "related"
    ],
    "wof:name":"Best Auto Repair",
    "wof:placetype":"venue"
},
  "geometry": {"coordinates":[-91.854383,36.729736],"type":"Point"}
}