{
  "type": "Feature",
  "properties": {
    "iso:country":"US",
    "sg:address":"9811 Clayton Rd",
    "sg:city":"St Louis",
    "sg:classifiers":[
        {
            "category":"Shopping",
            "subcategory":"Clothing, Apparel, & Fashions",
            "type":"Retail Goods"
        }
    ],
    "sg:phone":"+1 314 567 0778",
    "sg:postcode":"63124",
    "sg:province":"MO",
    "sg:tags":[
        "furnishing"
    ],
    "wof:name":"Kim Kuehner Men's Sportswear",
    "wof:placetype":"venue"
},
  "geometry": {"coordinates":[-90.39356600000001,38.636943],"type":"Point"}
}