{
  "type": "Feature",
  "properties": {
    "iso:country":"US",
    "sg:address":"17765 S Hwy 97",
    "sg:city":"Jerico Springs",
    "sg:classifiers":[
        {
            "category":"Farming",
            "subcategory":"Livestock Farm",
            "type":"Manufacturing & Wholesale Goods"
        },
        {
            "category":"Farming",
            "subcategory":"Farm",
            "type":"Manufacturing & Wholesale Goods"
        }
    ],
    "sg:phone":"+1 417 398 2430",
    "sg:postcode":"64756",
    "sg:province":"MO",
    "sg:tags":[
        "hog",
        "or",
        "feedlot"
    ],
    "wof:name":"Rocky Meadow Pig Nursery",
    "wof:placetype":"venue"
},
  "geometry": {"coordinates":[-94.031824,37.642036],"type":"Point"}
}