{
  "type": "Feature",
  "properties": {
    "iso:country":"US",
    "sg:address":"884 SW 1200th Rd",
    "sg:city":"Chilhowee",
    "sg:classifiers":[
        {
            "category":"Building & Trades",
            "subcategory":"Construction",
            "type":"Services"
        }
    ],
    "sg:phone":"+1 660 678 5891",
    "sg:postcode":"64733",
    "sg:province":"MO",
    "sg:tags":[
        "excavation",
        "contractor"
    ],
    "wof:name":"Furrey Excavating",
    "wof:placetype":"venue"
},
  "geometry": {"coordinates":[-93.91539,38.578576],"type":"Point"}
}