{
  "type": "Feature",
  "properties": {
    "iso:country":"US",
    "sg:address":"100 E US Hwy 60",
    "sg:city":"Mountain View",
    "sg:classifiers":[
        {
            "category":"Health Services",
            "subcategory":"Hospital",
            "type":"Services"
        }
    ],
    "sg:phone":"+1 417 934 7000",
    "sg:postcode":"65548",
    "sg:province":"MO",
    "wof:name":"St Francis Hospital",
    "wof:placetype":"venue"
},
  "geometry": {"coordinates":[-91.70239100000001,37.00161],"type":"Point"}
}