{
  "type": "Feature",
  "properties": {
    "iso:country":"US",
    "sg:address":"904 N Rosewood Dr",
    "sg:city":"Monett",
    "sg:classifiers":[
        {
            "category":"Professional",
            "type":"Services"
        }
    ],
    "sg:phone":"+1 417 235 6404",
    "sg:postcode":"65708",
    "sg:province":"MO",
    "wof:name":"Kenneth Campbell",
    "wof:placetype":"venue"
},
  "geometry": {"coordinates":[-93.91824699999999,36.933711],"type":"Point"}
}