{
  "type": "Feature",
  "properties": {
    "iso:country":"US",
    "sg:address":"1308 S Hedges St",
    "sg:city":"Independence",
    "sg:classifiers":[
        {
            "category":"Building & Trades",
            "subcategory":"Equipment Rental",
            "type":"Services"
        }
    ],
    "sg:phone":"+1 816 833 1840",
    "sg:postcode":"64052",
    "sg:province":"MO",
    "wof:name":"A1 Promotions",
    "wof:placetype":"venue"
},
  "geometry": {"coordinates":[-94.451622,39.093364],"type":"Point"}
}