{
  "type": "Feature",
  "properties": {
    "iso:country":"US",
    "sg:address":"18 Fortune Ln",
    "sg:city":"Saint Louis",
    "sg:classifiers":[
        {
            "category":"Professional",
            "subcategory":"Management & Consulting",
            "type":"Services"
        }
    ],
    "sg:phone":"+1 314 965 5051",
    "sg:postcode":"63122",
    "sg:province":"MO",
    "sg:tags":[
        "business"
    ],
    "wof:name":"Willa Inc",
    "wof:placetype":"venue"
},
  "geometry": {"coordinates":[-90.390232,38.574376],"type":"Point"}
}