{
  "type": "Feature",
  "properties": {
    "iso:country":"US",
    "sg:address":"15096 Malberg Rd",
    "sg:city":"Elk Creek",
    "sg:classifiers":[
        {
            "category":"Wholesale",
            "subcategory":"Meat",
            "type":"Manufacturing & Wholesale Goods"
        }
    ],
    "sg:phone":"+1 417 934 6466",
    "sg:postcode":"65464",
    "sg:province":"MO",
    "sg:tags":[
        "plant",
        "packing"
    ],
    "wof:name":"R & DS",
    "wof:placetype":"venue"
},
  "geometry": {"coordinates":[-92.008528,37.16587],"type":"Point"}
}