{
  "type": "Feature",
  "properties": {
    "iso:country":"US",
    "sg:address":"315 N US Hwy 169",
    "sg:city":"Gower",
    "sg:classifiers":[
        {
            "category":"Real Estate",
            "subcategory":"Real Estate Agent",
            "type":"Services"
        }
    ],
    "sg:phone":"+1 816 424 3120",
    "sg:postcode":"64454",
    "sg:province":"MO",
    "wof:name":"Gregory Realty",
    "wof:placetype":"venue"
},
  "geometry": {"coordinates":[-94.59611099999999,39.613749],"type":"Point"}
}