{
  "type": "Feature",
  "properties": {
    "iso:country":"US",
    "sg:address":"2401 US Hwy 40",
    "sg:city":"Blue Springs",
    "sg:classifiers":[
        {
            "category":"Professional",
            "subcategory":"Art Services",
            "type":"Services"
        },
        {
            "category":"Manufacturing",
            "subcategory":"Printing",
            "type":"Manufacturing & Wholesale Goods"
        }
    ],
    "sg:phone":"+1 816 228 3445",
    "sg:postcode":"64015",
    "sg:province":"MO",
    "sg:tags":[
        "graphic",
        "printer",
        "offset"
    ],
    "wof:name":"Rainbow Graphics",
    "wof:placetype":"venue"
},
  "geometry": {"coordinates":[-94.29235300000001,39.009857],"type":"Point"}
}