{
  "type": "Feature",
  "properties": {
    "addr:full":"323 Locust St Chillicothe MO 64601",
    "addr:housenumber":"323",
    "addr:postcode":"64601",
    "addr:street":"Locust St",
    "iso:country":"US",
    "sg:address":"323 Locust St",
    "sg:city":"Chillicothe",
    "sg:classifiers":[
        {
            "category":"Personal",
            "subcategory":"Beauty Salon",
            "type":"Services"
        }
    ],
    "sg:phone":"+1 660 646 6005",
    "sg:postcode":"64601",
    "sg:province":"MO",
    "sg:tags":[
        "shop"
    ],
    "wof:name":"Hair Port",
    "wof:placetype":"venue"
},
  "geometry": {"coordinates":[-93.552385,39.790515],"type":"Point"}
}