{
  "type": "Feature",
  "properties": {
    "iso:country":"US",
    "sg:address":"803 Main St",
    "sg:city":"Blue Springs",
    "sg:classifiers":[
        {
            "category":"Shopping",
            "subcategory":"Jewelry",
            "type":"Retail Goods"
        }
    ],
    "sg:phone":"+1 816 806 2333",
    "sg:postcode":"64015",
    "sg:province":"MO",
    "sg:tags":[
        "designer"
    ],
    "wof:name":"Cristal Dreams",
    "wof:placetype":"venue"
},
  "geometry": {"coordinates":[-94.27499899999999,39.018367],"type":"Point"}
}