{
  "type": "Feature",
  "properties": {
    "iso:country":"US",
    "sg:address":"7841 N Anita Ave",
    "sg:city":"Kansas City",
    "sg:classifiers":[
        {
            "category":"Real Estate",
            "subcategory":"Real Estate Operator",
            "type":"Services"
        }
    ],
    "sg:phone":"+1 816 741 4100",
    "sg:postcode":"64151",
    "sg:province":"MO",
    "sg:tags":[
        "building",
        "apartment"
    ],
    "wof:name":"Apples Apartments",
    "wof:placetype":"venue"
},
  "geometry": {"coordinates":[-94.632745,39.236732],"type":"Point"}
}