{
  "type": "Feature",
  "properties": {
    "iso:country":"US",
    "sg:address":"222 Main St",
    "sg:city":"Noel",
    "sg:classifiers":[
        {
            "category":"Shopping",
            "subcategory":"Pharmacy",
            "type":"Retail Goods"
        }
    ],
    "sg:phone":"+1 417 475 3292",
    "sg:postcode":"64854",
    "sg:province":"MO",
    "wof:name":"Noel Pharmacy",
    "wof:placetype":"venue"
},
  "geometry": {"coordinates":[-94.487408,36.545562],"type":"Point"}
}