{
  "type": "Feature",
  "properties": {
    "iso:country":"US",
    "sg:address":"2513 S Trl Ridge",
    "sg:city":"Independence",
    "sg:classifiers":[
        {
            "category":"Professional",
            "subcategory":"Advertising",
            "type":"Services"
        }
    ],
    "sg:phone":"+1 816 210 7109",
    "sg:postcode":"64055",
    "sg:province":"MO",
    "wof:name":"KANSASCITY1.COM",
    "wof:placetype":"venue"
},
  "geometry": {"coordinates":[-94.386644,39.07401],"type":"Point"}
}