{
  "type": "Feature",
  "properties": {
    "iso:country":"US",
    "sg:address":"1491 E 10th St",
    "sg:city":"Rolla",
    "sg:classifiers":[
        {
            "category":"Health Services",
            "subcategory":"Dentist",
            "type":"Services"
        }
    ],
    "sg:phone":"+1 573 364 2868",
    "sg:postcode":"65401",
    "sg:province":"MO",
    "sg:website":"http://www.atkinsondental.com",
    "wof:name":"Atkinson Dental Clinic PC",
    "wof:placetype":"venue"
},
  "geometry": {"coordinates":[-91.770538,37.951488],"type":"Point"}
}