{
  "type": "Feature",
  "properties": {
    "iso:country":"US",
    "sg:address":"14 Jefferson Sq",
    "sg:city":"De Soto",
    "sg:classifiers":[
        {
            "category":"Health Services",
            "subcategory":"Clinic",
            "type":"Services"
        }
    ],
    "sg:phone":"+1 636 586 9114",
    "sg:postcode":"63020",
    "sg:province":"MO",
    "sg:tags":[
        "home"
    ],
    "wof:name":"JMH Home Health Care",
    "wof:placetype":"venue"
},
  "geometry": {"coordinates":[-90.57906699999999,38.145543],"type":"Point"}
}