{
  "type": "Feature",
  "properties": {
    "iso:country":"US",
    "sg:address":"6405 Arsenal St",
    "sg:city":"Saint Louis",
    "sg:classifiers":[
        {
            "category":"Building & Trades",
            "subcategory":"Electrical",
            "type":"Services"
        }
    ],
    "sg:phone":"+1 314 644 3614",
    "sg:postcode":"63139",
    "sg:province":"MO",
    "sg:tags":[
        "electrician"
    ],
    "wof:name":"Casey Electric",
    "wof:placetype":"venue"
},
  "geometry": {"coordinates":[-90.296402,38.607601],"type":"Point"}
}