{
  "type": "Feature",
  "properties": {
    "iso:country":"US",
    "sg:address":"416 Main St",
    "sg:city":"Kansas City",
    "sg:classifiers":[
        {
            "category":"Health Services",
            "subcategory":"Doctor",
            "type":"Services"
        }
    ],
    "sg:phone":"+1 816 363 2202",
    "sg:postcode":"64105",
    "sg:province":"MO",
    "sg:tags":[
        "medical"
    ],
    "wof:name":"Ben Z Abella MD PC",
    "wof:placetype":"venue"
},
  "geometry": {"coordinates":[-94.58298000000001,39.108442],"type":"Point"}
}