{
  "type": "Feature",
  "properties": {
    "iso:country":"US",
    "sg:address":"207 N Maple St",
    "sg:city":"Eldon",
    "sg:classifiers":[
        {
            "category":"Building & Trades",
            "subcategory":"Construction",
            "type":"Services"
        }
    ],
    "sg:phone":"+1 573 392 3648",
    "sg:postcode":"65026",
    "sg:province":"MO",
    "sg:tags":[
        "hanging",
        "contractor"
    ],
    "wof:name":"Sutton Painting",
    "wof:placetype":"venue"
},
  "geometry": {"coordinates":[-92.57917399999999,38.35274],"type":"Point"}
}