{
  "type": "Feature",
  "properties": {
    "iso:country":"US",
    "sg:address":"114 Westwoods Dr",
    "sg:city":"Liberty",
    "sg:classifiers":[
        {
            "category":"Professional",
            "subcategory":"Lawyer & Legal Services",
            "type":"Services"
        }
    ],
    "sg:phone":"+1 816 792 2020",
    "sg:postcode":"64068",
    "sg:province":"MO",
    "sg:tags":[
        "attorney"
    ],
    "wof:name":"Patton & Chamberlain",
    "wof:placetype":"venue"
},
  "geometry": {"coordinates":[-94.43659700000001,39.248066],"type":"Point"}
}