{
  "type": "Feature",
  "properties": {
    "iso:country":"US",
    "sg:address":"10 S Folger St",
    "sg:city":"Carrollton",
    "sg:classifiers":[
        {
            "category":"Personal",
            "subcategory":"Barber",
            "type":"Services"
        }
    ],
    "sg:phone":"+1 660 542 3354",
    "sg:postcode":"64633",
    "sg:province":"MO",
    "sg:tags":[
        "shop"
    ],
    "wof:name":"Westside Barber Shop",
    "wof:placetype":"venue"
},
  "geometry": {"coordinates":[-93.497045,39.358446],"type":"Point"}
}