{
  "type": "Feature",
  "properties": {
    "iso:country":"US",
    "sg:address":"4371 Cook Ave",
    "sg:city":"St Louis",
    "sg:classifiers":[
        {
            "category":"Organizations",
            "subcategory":"Religious Organization",
            "type":"Services"
        }
    ],
    "sg:phone":"+1 314 652 2160",
    "sg:postcode":"63113",
    "sg:province":"MO",
    "sg:tags":[
        "church"
    ],
    "wof:name":"New Christian Light Church",
    "wof:placetype":"venue"
},
  "geometry": {"coordinates":[-90.245749,38.652548],"type":"Point"}
}