{
  "type": "Feature",
  "properties": {
    "iso:country":"US",
    "sg:address":"3808 W Florissant Ave",
    "sg:city":"St Louis",
    "sg:classifiers":[
        {
            "category":"Organizations",
            "subcategory":"Community Association",
            "type":"Services"
        }
    ],
    "sg:phone":"+1 314 533 2030",
    "sg:postcode":"63107",
    "sg:province":"MO",
    "sg:tags":[
        "civic"
    ],
    "wof:name":"Third Ward Neighborhood Cncl",
    "wof:placetype":"venue"
},
  "geometry": {"coordinates":[-90.214568,38.671622],"type":"Point"}
}