{
  "type": "Feature",
  "properties": {
    "iso:country":"US",
    "sg:address":"5390 E 23rd St",
    "sg:city":"Joplin",
    "sg:classifiers":[
        {
            "category":"Building & Trades",
            "subcategory":"Construction",
            "type":"Services"
        }
    ],
    "sg:phone":"+1 417 206 2000",
    "sg:postcode":"64801",
    "sg:province":"MO",
    "sg:tags":[
        "residential",
        "siding",
        "contractor"
    ],
    "wof:name":"Home Town Siding Co Inc",
    "wof:placetype":"venue"
},
  "geometry": {"coordinates":[-94.434184,37.065768],"type":"Point"}
}