{
  "type": "Feature",
  "properties": {
    "iso:country":"US",
    "sg:address":"1909 Sir Lancelot Ln",
    "sg:city":"Saint Louis",
    "sg:classifiers":[
        {
            "category":"Personal",
            "type":"Services"
        }
    ],
    "sg:phone":"+1 314 469 1479",
    "sg:postcode":"63146",
    "sg:province":"MO",
    "sg:tags":[
        "computer",
        "programing",
        "custom"
    ],
    "wof:name":"Triton Digital Inc",
    "wof:placetype":"venue"
},
  "geometry": {"coordinates":[-90.47886699999999,38.695543],"type":"Point"}
}