{
  "type": "Feature",
  "properties": {
    "addr:full":"7733 Forsyth Blvd Saint Louis MO 63105",
    "addr:housenumber":"7733",
    "addr:postcode":"63105",
    "addr:street":"Forsyth Blvd",
    "iso:country":"US",
    "sg:address":"7733 Forsyth Blvd",
    "sg:city":"Saint Louis",
    "sg:classifiers":[
        {
            "category":"Banks & Credit Unions",
            "subcategory":"Investment Brokerage",
            "type":"Services"
        }
    ],
    "sg:phone":"+1 314 725 1255",
    "sg:postcode":"63105",
    "sg:province":"MO",
    "sg:tags":[
        "firm",
        "brokerage"
    ],
    "wof:name":"Wachovia Securities LLC",
    "wof:placetype":"venue"
},
  "geometry": {"coordinates":[-90.33599599999999,38.650135],"type":"Point"}
}