{
  "type": "Feature",
  "properties": {
    "iso:country":"US",
    "sg:address":"3120 N Juanita Dr",
    "sg:city":"Buckner",
    "sg:classifiers":[
        {
            "category":"Structure",
            "subcategory":"Office Building",
            "type":"Public Place"
        }
    ],
    "sg:phone":"+1 816 985 3822",
    "sg:postcode":"64016",
    "sg:province":"MO",
    "sg:tags":[
        "park"
    ],
    "wof:name":"Mcbee Properties",
    "wof:placetype":"venue"
},
  "geometry": {"coordinates":[-94.262514,39.1569],"type":"Point"}
}