{
  "type": "Feature",
  "properties": {
    "iso:country":"US",
    "sg:address":"20 Villawood Ln",
    "sg:city":"Saint Louis",
    "sg:classifiers":[
        {
            "category":"Manufacturing",
            "subcategory":"Metals",
            "type":"Manufacturing & Wholesale Goods"
        }
    ],
    "sg:phone":"+1 314 968 5754",
    "sg:postcode":"63119",
    "sg:province":"MO",
    "sg:tags":[
        "machine",
        "screw",
        "product",
        "mfg"
    ],
    "wof:name":"Mae Engineered Products",
    "wof:placetype":"venue"
},
  "geometry": {"coordinates":[-90.344624,38.573831],"type":"Point"}
}