{
  "type": "Feature",
  "properties": {
    "iso:country":"US",
    "sg:address":"120 E Broadway St",
    "sg:city":"Brunswick",
    "sg:classifiers":[
        {
            "category":"Health Services",
            "subcategory":"Doctor",
            "type":"Services"
        }
    ],
    "sg:phone":"+1 660 548 3161",
    "sg:postcode":"65236",
    "sg:province":"MO",
    "sg:tags":[
        "medical"
    ],
    "wof:name":"Grand River Medical Center",
    "wof:placetype":"venue"
},
  "geometry": {"coordinates":[-93.12957900000001,39.423151],"type":"Point"}
}