{
  "type": "Feature",
  "properties": {
    "iso:country":"US",
    "sg:address":"13341 Co Rd 2030",
    "sg:city":"Rolla",
    "sg:classifiers":[
        {
            "category":"Building & Trades",
            "subcategory":"Plumbing",
            "type":"Services"
        }
    ],
    "sg:phone":"+1 573 364 6047",
    "sg:postcode":"65401",
    "sg:province":"MO",
    "sg:tags":[
        "septic"
    ],
    "wof:name":"Taylor's Septic Tank Cleaning",
    "wof:placetype":"venue"
},
  "geometry": {"coordinates":[-91.743809,37.99928],"type":"Point"}
}