{
  "type": "Feature",
  "properties": {
    "iso:country":"US",
    "sg:address":"2602 S Picher Ave",
    "sg:city":"Joplin",
    "sg:classifiers":[
        {
            "category":"Health Services",
            "subcategory":"Doctor",
            "type":"Services"
        }
    ],
    "sg:phone":"+1 417 781 2220",
    "sg:postcode":"64804",
    "sg:province":"MO",
    "sg:tags":[
        "dentist"
    ],
    "wof:name":"Benjamin D Rosenberg DDS Inc",
    "wof:placetype":"venue"
},
  "geometry": {"coordinates":[-94.527044,37.06125],"type":"Point"}
}