{
  "type": "Feature",
  "properties": {
    "iso:country":"US",
    "sg:address":"321 E North St",
    "sg:city":"Warrensburg",
    "sg:classifiers":[
        {
            "category":"Real Estate",
            "subcategory":"Real Estate Operator",
            "type":"Services"
        }
    ],
    "sg:phone":"+1 660 429 2933",
    "sg:postcode":"64093",
    "sg:province":"MO",
    "sg:tags":[
        "apartment"
    ],
    "wof:name":"Kansas Rural Housing Svc LLC",
    "wof:placetype":"venue"
},
  "geometry": {"coordinates":[-93.734886,38.767518],"type":"Point"}
}