{
  "type": "Feature",
  "properties": {
    "iso:country":"US",
    "sg:address":"409 E Lincoln Ave",
    "sg:city":"Owensville",
    "sg:classifiers":[
        {
            "category":"Shopping",
            "subcategory":"Used Merchandise",
            "type":"Retail Goods"
        }
    ],
    "sg:phone":"+1 573 437 3435",
    "sg:postcode":"65066",
    "sg:province":"MO",
    "sg:tags":[
        "store"
    ],
    "wof:name":"Owensville Antique Mall",
    "wof:placetype":"venue"
},
  "geometry": {"coordinates":[-91.49626499999999,38.345109],"type":"Point"}
}