{
  "type": "Feature",
  "properties": {
    "iso:country":"US",
    "sg:address":"13712 E 42nd Ter S",
    "sg:city":"Independence",
    "sg:classifiers":[
        {
            "category":"Travel",
            "subcategory":"Hotels & Motels",
            "type":"Entertainment"
        },
        {
            "category":"Travel",
            "subcategory":"Bed & Breakfast",
            "type":"Entertainment"
        }
    ],
    "sg:phone":"+1 816 373 2800",
    "sg:postcode":"64055",
    "sg:province":"MO",
    "sg:tags":[
        "inn",
        "lodging"
    ],
    "sg:website":"http://www.redroof.com",
    "wof:name":"Red Roof Inn",
    "wof:placetype":"venue"
},
  "geometry": {"coordinates":[-94.41880999999999,39.044084],"type":"Point"}
}