{
  "type": "Feature",
  "properties": {
    "iso:country":"US",
    "sg:address":"2800 Rockcreek Parkway",
    "sg:city":"Kansas City",
    "sg:classifiers":[
        {
            "category":"Professional",
            "subcategory":"Computer Services",
            "type":"Services"
        }
    ],
    "sg:postcode":"64117",
    "sg:province":"MO",
    "sg:website":"http://www.cerner.com",
    "wof:name":"Cerner",
    "wof:placetype":"venue"
},
  "geometry": {"coordinates":[-94.54660699999999,39.148522],"type":"Point"}
}