{
  "type": "Feature",
  "properties": {
    "iso:country":"US",
    "sg:address":"8320 Westridge Rd",
    "sg:city":"Kansas City",
    "sg:classifiers":[
        {
            "category":"Building & Trades",
            "subcategory":"Construction",
            "type":"Services"
        }
    ],
    "sg:phone":"+1 816 690 6700",
    "sg:postcode":"64138",
    "sg:province":"MO",
    "wof:name":"Jakes Crossing LLC",
    "wof:placetype":"venue"
},
  "geometry": {"coordinates":[-94.44202,38.968646],"type":"Point"}
}