{
  "type": "Feature",
  "properties": {
    "iso:country":"US",
    "sg:address":"26108 E 267th St",
    "sg:city":"Harrisonville",
    "sg:classifiers":[
        {
            "category":"Professional",
            "subcategory":"Engineering",
            "type":"Services"
        },
        {
            "category":"Building & Trades",
            "subcategory":"Cleaning & Sanitation",
            "type":"Services"
        },
        {
            "category":"Wholesale",
            "subcategory":"Construction Materials",
            "type":"Manufacturing & Wholesale Goods"
        },
        {
            "category":"Building & Trades",
            "subcategory":"Construction",
            "type":"Services"
        }
    ],
    "sg:phone":"+1 816 380 4867",
    "sg:postcode":"64701",
    "sg:province":"MO",
    "sg:tags":[
        "industrial",
        "elevator-consultants",
        "elevators-repairing",
        "elevator",
        "passenger-commercial",
        "cars-refinishing",
        "elevators-freight",
        "inspector"
    ],
    "wof:name":"Eagle Elevator Corp",
    "wof:placetype":"venue"
},
  "geometry": {"coordinates":[-94.29142899999999,38.630926],"type":"Point"}
}