{
  "type": "Feature",
  "properties": {
    "iso:country":"US",
    "sg:address":"817 S Main St",
    "sg:city":"Jasper",
    "sg:classifiers":[
        {
            "category":"Retail",
            "subcategory":"Veterinary Services",
            "type":"Services"
        }
    ],
    "sg:phone":"+1 417 394 2626",
    "sg:postcode":"64755",
    "sg:province":"MO",
    "sg:tags":[
        "veterinarian"
    ],
    "wof:name":"Jasper Veterinary Svc",
    "wof:placetype":"venue"
},
  "geometry": {"coordinates":[-94.302648,37.325829],"type":"Point"}
}