{
  "type": "Feature",
  "properties": {
    "iso:country":"US",
    "sg:address":"106 N Massey Blvd",
    "sg:city":"Nixa",
    "sg:classifiers":[
        {
            "category":"Shopping",
            "subcategory":"Pharmacy",
            "type":"Retail Goods"
        }
    ],
    "sg:phone":"+1 417 724 9345",
    "sg:postcode":"65714",
    "sg:province":"MO",
    "wof:name":"Walgreens",
    "wof:placetype":"venue"
},
  "geometry": {"coordinates":[-93.302603,37.043723],"type":"Point"}
}