{
  "type": "Feature",
  "properties": {
    "iso:country":"US",
    "sg:address":"7852 State Hwy 176",
    "sg:city":"Walnut Shade",
    "sg:classifiers":[
        {
            "category":"Manufacturing",
            "subcategory":"Metals",
            "type":"Manufacturing & Wholesale Goods"
        }
    ],
    "sg:phone":"+1 417 336 4737",
    "sg:postcode":"65771",
    "sg:province":"MO",
    "sg:tags":[
        "product",
        "wire",
        "fabricated",
        "mfg"
    ],
    "wof:name":"Storage Solutions",
    "wof:placetype":"venue"
},
  "geometry": {"coordinates":[-93.197293,36.759983],"type":"Point"}
}