{
  "type": "Feature",
  "properties": {
    "iso:country":"US",
    "sg:address":"207 S Cedar Ave",
    "sg:city":"Independence",
    "sg:classifiers":[
        {
            "category":"Building & Trades",
            "subcategory":"Cleaning & Sanitation",
            "type":"Services"
        }
    ],
    "sg:phone":"+1 816 356 0007",
    "sg:postcode":"64053",
    "sg:province":"MO",
    "sg:tags":[
        "maintenance"
    ],
    "wof:name":"Raytown Chimney Cleaning",
    "wof:placetype":"venue"
},
  "geometry": {"coordinates":[-94.4577,39.108427],"type":"Point"}
}