{
  "type": "Feature",
  "properties": {
    "iso:country":"US",
    "sg:address":"2024 Lobo Dr",
    "sg:city":"Festus",
    "sg:classifiers":[
        {
            "category":"Arts & Performance",
            "subcategory":"Theater",
            "type":"Entertainment"
        }
    ],
    "sg:phone":"+1 636 937 4089",
    "sg:postcode":"63028",
    "sg:province":"MO",
    "sg:tags":[
        "live",
        "music"
    ],
    "wof:name":"Sounds Unlimited DJ & Karaoke",
    "wof:placetype":"venue"
},
  "geometry": {"coordinates":[-90.346909,38.106087],"type":"Point"}
}