{
  "type": "Feature",
  "properties": {
    "iso:country":"US",
    "sg:address":"2824 Guinotte Ave",
    "sg:city":"Kansas City",
    "sg:classifiers":[
        {
            "category":"Retail",
            "subcategory":"Repair Shop",
            "type":"Services"
        }
    ],
    "sg:phone":"+1 816 241 5151",
    "sg:postcode":"64120",
    "sg:province":"MO",
    "sg:tags":[
        "elevator"
    ],
    "wof:name":"Independent Elevator Corp",
    "wof:placetype":"venue"
},
  "geometry": {"coordinates":[-94.54640000000001,39.118865],"type":"Point"}
}