{
  "type": "Feature",
  "properties": {
    "iso:country":"US",
    "sg:address":"1618 Porter Ave",
    "sg:city":"Aurora",
    "sg:classifiers":[
        {
            "category":"Farming",
            "subcategory":"Farm",
            "type":"Manufacturing & Wholesale Goods"
        }
    ],
    "sg:phone":"+1 417 678 2067",
    "sg:postcode":"65605",
    "sg:province":"MO",
    "wof:name":"Shelton Farms",
    "wof:placetype":"venue"
},
  "geometry": {"coordinates":[-93.71208,36.957782],"type":"Point"}
}