{
  "type": "Feature",
  "properties": {
    "iso:country":"US",
    "sg:address":"3005 Locust St",
    "sg:city":"St Louis",
    "sg:classifiers":[
        {
            "category":"Professional",
            "subcategory":"Art Services",
            "type":"Services"
        }
    ],
    "sg:phone":"+1 314 652 9797",
    "sg:postcode":"63103",
    "sg:province":"MO",
    "sg:tags":[
        "photographer",
        "photography",
        "commercial"
    ],
    "sg:website":"www.rggphoto.com",
    "wof:name":"Robert G Grimm Photography I",
    "wof:placetype":"venue"
},
  "geometry": {"coordinates":[-90.22335099999999,38.636178],"type":"Point"}
}