{
  "type": "Feature",
  "properties": {
    "iso:country":"US",
    "sg:address":"1516 Jade Rd",
    "sg:city":"Columbia",
    "sg:classifiers":[
        {
            "category":"Autos & Motor Vehicles",
            "subcategory":"Automobile Sales",
            "type":"Retail Goods"
        }
    ],
    "sg:phone":"+1 573 814 1250",
    "sg:postcode":"65201",
    "sg:province":"MO",
    "sg:tags":[
        "new",
        "car"
    ],
    "wof:name":"K & W Auto Sales",
    "wof:placetype":"venue"
},
  "geometry": {"coordinates":[-92.129341,38.952544],"type":"Point"}
}