{
  "type": "Feature",
  "properties": {
    "iso:country":"US",
    "sg:address":"108 S Main St",
    "sg:city":"Maryville",
    "sg:classifiers":[
        {
            "category":"Shopping",
            "subcategory":"Musical Instruments",
            "type":"Retail Goods"
        }
    ],
    "sg:phone":"+1 660 582 2128",
    "sg:postcode":"64468",
    "sg:province":"MO",
    "sg:tags":[
        "repair"
    ],
    "wof:name":"1-2-4 Music",
    "wof:placetype":"venue"
},
  "geometry": {"coordinates":[-94.873043,40.345945],"type":"Point"}
}