{
  "type": "Feature",
  "properties": {
    "iso:country":"US",
    "sg:address":"1017 Franklin Ave",
    "sg:city":"Lexington",
    "sg:classifiers":[
        {
            "category":"Professional",
            "subcategory":"Accounting & Tax Preparation",
            "type":"Services"
        }
    ],
    "sg:phone":"+1 660 259 6363",
    "sg:postcode":"64067",
    "sg:province":"MO",
    "wof:name":"H & R Block",
    "wof:placetype":"venue"
},
  "geometry": {"coordinates":[-93.882409,39.184366],"type":"Point"}
}