{
  "type": "Feature",
  "properties": {
    "iso:country":"US",
    "sg:address":"3575 Parker Spr",
    "sg:city":"Florissant",
    "sg:classifiers":[
        {
            "category":"Autos & Motor Vehicles",
            "subcategory":"Fuel & Gas Station",
            "type":"Retail Goods"
        }
    ],
    "sg:phone":"+1 314 837 6257",
    "sg:postcode":"63033",
    "sg:province":"MO",
    "sg:tags":[
        "automotive",
        "station",
        "gasoline"
    ],
    "wof:name":"Mobil Halls Ferry Service",
    "wof:placetype":"venue"
},
  "geometry": {"coordinates":[-90.292569,38.795372],"type":"Point"}
}