{
  "type": "Feature",
  "properties": {
    "iso:country":"US",
    "sg:address":"5100 Oakland Ave",
    "sg:city":"St Louis",
    "sg:classifiers":[
        {
            "category":"Wholesale",
            "subcategory":"Electrical",
            "type":"Manufacturing & Wholesale Goods"
        }
    ],
    "sg:phone":"+1 314 531 9719",
    "sg:postcode":"63110",
    "sg:province":"MO",
    "sg:tags":[
        "light",
        "tube",
        "bulb"
    ],
    "wof:name":"Hytron Electric Products",
    "wof:placetype":"venue"
},
  "geometry": {"coordinates":[-90.268979,38.629092],"type":"Point"}
}