{
  "type": "Feature",
  "properties": {
    "iso:country":"US",
    "sg:address":"5638 Sky Hill Dr",
    "sg:city":"St Louis",
    "sg:classifiers":[
        {
            "category":"Professional",
            "subcategory":"Management & Consulting",
            "type":"Services"
        },
        {
            "category":"Wholesale",
            "subcategory":"Groceries",
            "type":"Manufacturing & Wholesale Goods"
        }
    ],
    "sg:phone":"+1 314 846 0557",
    "sg:postcode":"63129",
    "sg:province":"MO",
    "sg:tags":[
        "manufacture",
        "group",
        "for",
        "marketing",
        "rep",
        "consultant"
    ],
    "wof:name":"Anchor Marketing Group Inc",
    "wof:placetype":"venue"
},
  "geometry": {"coordinates":[-90.311238,38.467622],"type":"Point"}
}