{
  "type": "Feature",
  "properties": {
    "iso:country":"US",
    "sg:address":"35462 State Hwy Zz",
    "sg:city":"Graham",
    "sg:classifiers":[
        {
            "category":"Farming",
            "subcategory":"Livestock Farm",
            "type":"Manufacturing & Wholesale Goods"
        }
    ],
    "sg:phone":"+1 660 939 2502",
    "sg:postcode":"64455",
    "sg:province":"MO",
    "sg:tags":[
        "feedlot",
        "corn",
        "soybean",
        "beef",
        "cattle"
    ],
    "wof:name":"Rodney Lewis",
    "wof:placetype":"venue"
},
  "geometry": {"coordinates":[-95.037087,40.211121],"type":"Point"}
}