{
  "type": "Feature",
  "properties": {
    "iso:country":"US",
    "sg:address":"412 N Frederick St",
    "sg:city":"Cape Girardeau",
    "sg:classifiers":[
        {
            "category":"Professional",
            "subcategory":"Business Services",
            "type":"Services"
        }
    ],
    "sg:phone":"+1 573 335 4446",
    "sg:postcode":"63701",
    "sg:province":"MO",
    "sg:tags":[
        "inspection"
    ],
    "wof:name":"Home Buyers Inspection Inc",
    "wof:placetype":"venue"
},
  "geometry": {"coordinates":[-89.52449900000001,37.310718],"type":"Point"}
}