{
  "type": "Feature",
  "properties": {
    "iso:country":"US",
    "sg:address":"1901 Angelrodt St",
    "sg:city":"St Louis",
    "sg:classifiers":[
        {
            "category":"Real Estate",
            "subcategory":"Real Estate Agent",
            "type":"Services"
        }
    ],
    "sg:phone":"+1 314 588 8074",
    "sg:postcode":"63107",
    "sg:province":"MO",
    "wof:name":"Magnus Group LLC",
    "wof:placetype":"venue"
},
  "geometry": {"coordinates":[-90.201095,38.657137],"type":"Point"}
}