{
  "type": "Feature",
  "properties": {
    "iso:country":"US",
    "sg:address":"5586 Camp Woodland Ln",
    "sg:city":"Albany",
    "sg:classifiers":[
        {
            "category":"Travel",
            "subcategory":"Campground",
            "type":"Entertainment"
        }
    ],
    "sg:phone":"+1 660 726 3869",
    "sg:postcode":"64402",
    "sg:province":"MO",
    "sg:tags":[
        "camp"
    ],
    "wof:name":"Girl Scouts Camp",
    "wof:placetype":"venue"
},
  "geometry": {"coordinates":[-94.334581,40.18776],"type":"Point"}
}