{
  "type": "Feature",
  "properties": {
    "iso:country":"US",
    "sg:address":"1120 W Pearce Blvd",
    "sg:city":"Wentzville",
    "sg:classifiers":[
        {
            "category":"Retail",
            "subcategory":"Veterinary Services",
            "type":"Services"
        }
    ],
    "sg:phone":"+1 636 332 4411",
    "sg:postcode":"63385",
    "sg:province":"MO",
    "sg:tags":[
        "veterinarian"
    ],
    "wof:name":"Animal Docs Inc",
    "wof:placetype":"venue"
},
  "geometry": {"coordinates":[-90.865949,38.810184],"type":"Point"}
}