{
  "type": "Feature",
  "properties": {
    "iso:country":"US",
    "sg:address":"801 N Oates Dr",
    "sg:city":"Hayti",
    "sg:classifiers":[
        {
            "category":"Real Estate",
            "subcategory":"Real Estate Operator",
            "type":"Services"
        }
    ],
    "sg:phone":"+1 573 359 2634",
    "sg:postcode":"63851",
    "sg:province":"MO",
    "sg:tags":[
        "apartment"
    ],
    "wof:name":"Cleveland Apartments",
    "wof:placetype":"venue"
},
  "geometry": {"coordinates":[-89.753742,36.24698],"type":"Point"}
}