{
  "type": "Feature",
  "properties": {
    "iso:country":"US",
    "sg:address":"2913 Oak Lawn Dr",
    "sg:city":"Columbia",
    "sg:classifiers":[
        {
            "category":"Professional",
            "subcategory":"Secretarial Services",
            "type":"Services"
        }
    ],
    "sg:phone":"+1 573 449 5778",
    "sg:postcode":"65203",
    "sg:province":"MO",
    "sg:tags":[
        "resume"
    ],
    "wof:name":"A Plus Professional Typing Svc",
    "wof:placetype":"venue"
},
  "geometry": {"coordinates":[-92.353278,38.919356],"type":"Point"}
}