{
  "type": "Feature",
  "properties": {
    "iso:country":"US",
    "sg:address":"2240 S Campbell Ave",
    "sg:city":"Springfield",
    "sg:classifiers":[
        {
            "category":"Personal",
            "subcategory":"Beauty Salon",
            "type":"Services"
        }
    ],
    "sg:phone":"+1 417 823 7080",
    "sg:postcode":"65807",
    "sg:province":"MO",
    "sg:tags":[
        "shop"
    ],
    "wof:name":"Nails II",
    "wof:placetype":"venue"
},
  "geometry": {"coordinates":[-93.295203,37.174122],"type":"Point"}
}