{
  "type": "Feature",
  "properties": {
    "iso:country":"US",
    "sg:address":"1568 Fencorp Dr",
    "sg:city":"Fenton",
    "sg:classifiers":[
        {
            "category":"Wholesale",
            "subcategory":"Office Equipment",
            "type":"Manufacturing & Wholesale Goods"
        },
        {
            "category":"Professional",
            "subcategory":"Art Services",
            "type":"Services"
        },
        {
            "category":"Professional",
            "subcategory":"Printing & Photocopies",
            "type":"Services"
        },
        {
            "category":"Shopping",
            "subcategory":"Computers & Home Electronics",
            "type":"Retail Goods"
        }
    ],
    "sg:phone":"+1 636 326 2040",
    "sg:postcode":"63026",
    "sg:province":"MO",
    "sg:tags":[
        "scanning",
        "graphic",
        "supply",
        "services-commercial",
        "duplicating",
        "designer",
        "copying",
        "plotting",
        "printer"
    ],
    "wof:name":"Lake Printing",
    "wof:placetype":"venue"
},
  "geometry": {"coordinates":[-90.447005,38.535902],"type":"Point"}
}