{
  "type": "Feature",
  "properties": {
    "iso:country":"US",
    "sg:address":"14748 Manchester Rd",
    "sg:city":"Ballwin",
    "sg:classifiers":[
        {
            "category":"Health Services",
            "subcategory":"Doctor",
            "type":"Services"
        }
    ],
    "sg:phone":"+1 636 256 3636",
    "sg:postcode":"63011",
    "sg:province":"MO",
    "sg:tags":[
        "physician",
        "surgeon",
        "medical"
    ],
    "wof:name":"Mark A Lichtenfeld MD",
    "wof:placetype":"venue"
},
  "geometry": {"coordinates":[-90.531158,38.592912],"type":"Point"}
}