{
  "type": "Feature",
  "properties": {
    "iso:country":"US",
    "sg:address":"54998 Cedar Ridge",
    "sg:city":"California",
    "sg:classifiers":[
        {
            "category":"Shopping",
            "type":"Retail Goods"
        }
    ],
    "sg:phone":"+1 573 584 3511",
    "sg:postcode":"65018",
    "sg:province":"MO",
    "sg:tags":[
        "product",
        "wood"
    ],
    "wof:name":"Cedar Ridge Wood Products",
    "wof:placetype":"venue"
},
  "geometry": {"coordinates":[-92.469669,38.65212],"type":"Point"}
}