{
  "type": "Feature",
  "properties": {
    "iso:country":"US",
    "sg:address":"3940 Troost Ave",
    "sg:city":"Kansas City",
    "sg:classifiers":[
        {
            "category":"Personal",
            "subcategory":"Beauty Salon",
            "type":"Services"
        }
    ],
    "sg:phone":"+1 816 561 8428",
    "sg:postcode":"64110",
    "sg:province":"MO",
    "sg:tags":[
        "shop"
    ],
    "wof:name":"Fancy Nails Salon",
    "wof:placetype":"venue"
},
  "geometry": {"coordinates":[-94.57226900000001,39.055043],"type":"Point"}
}