{
  "type": "Feature",
  "properties": {
    "iso:country":"US",
    "sg:address":"2831 N Kingshighway Blvd",
    "sg:city":"St Louis",
    "sg:classifiers":[
        {
            "category":"Organizations",
            "subcategory":"Religious Organization",
            "type":"Services"
        }
    ],
    "sg:phone":"+1 314 367 2314",
    "sg:postcode":"63115",
    "sg:province":"MO",
    "sg:tags":[
        "church"
    ],
    "sg:website":"www.allsaintsepiscopal.net",
    "wof:name":"All Saints Episcopal Church",
    "wof:placetype":"venue"
},
  "geometry": {"coordinates":[-90.255999,38.670326],"type":"Point"}
}