{
  "type": "Feature",
  "properties": {
    "iso:country":"US",
    "sg:address":"1020 Madison 529",
    "sg:city":"Fredericktown",
    "sg:classifiers":[
        {
            "category":"Building & Trades",
            "subcategory":"Electrical",
            "type":"Services"
        }
    ],
    "sg:phone":"+1 573 783 2158",
    "sg:postcode":"63645",
    "sg:province":"MO",
    "sg:tags":[
        "industrial",
        "electrician",
        "electric",
        "contractors-commercial"
    ],
    "wof:name":"Fox Electrical Contractors",
    "wof:placetype":"venue"
},
  "geometry": {"coordinates":[-90.41416599999999,37.579985],"type":"Point"}
}