{
  "type": "Feature",
  "properties": {
    "iso:country":"US",
    "sg:address":"2725 N Westwood Blvd",
    "sg:city":"Poplar Bluff",
    "sg:classifiers":[
        {
            "category":"Health Services",
            "subcategory":"Doctor",
            "type":"Services"
        }
    ],
    "sg:phone":"+1 573 776 7129",
    "sg:postcode":"63901",
    "sg:province":"MO",
    "sg:tags":[
        "clinic"
    ],
    "wof:name":"Kneibert Clinic",
    "wof:placetype":"venue"
},
  "geometry": {"coordinates":[-90.429965,36.786207],"type":"Point"}
}