{
  "type": "Feature",
  "properties": {
    "iso:country":"US",
    "sg:address":"400 Friedens Rd",
    "sg:city":"St Charles",
    "sg:classifiers":[
        {
            "category":"Sports & Exercise",
            "subcategory":"Golf",
            "type":"Entertainment"
        }
    ],
    "sg:phone":"+1 636 946 9945",
    "sg:postcode":"63303",
    "sg:province":"MO",
    "sg:tags":[
        "course"
    ],
    "wof:name":"St Charles Golf Course Mntnc",
    "wof:placetype":"venue"
},
  "geometry": {"coordinates":[-90.506716,38.755962],"type":"Point"}
}