{
  "type": "Feature",
  "properties": {
    "iso:country":"US",
    "sg:address":"1117 N Washington St",
    "sg:city":"Nevada",
    "sg:classifiers":[
        {
            "category":"Professional",
            "subcategory":"Computer Services",
            "type":"Services"
        }
    ],
    "sg:phone":"+1 417 667 4140",
    "sg:postcode":"64772",
    "sg:province":"MO",
    "sg:tags":[
        "datum",
        "advertising",
        "representative"
    ],
    "wof:name":"Jones Microcomputer Solutions",
    "wof:placetype":"venue"
},
  "geometry": {"coordinates":[-94.35467199999999,37.850743],"type":"Point"}
}