{
  "type": "Feature",
  "properties": {
    "iso:country":"US",
    "sg:address":"107 S Linn Ave",
    "sg:city":"Wentzville",
    "sg:classifiers":[
        {
            "category":"Bars & Pubs",
            "type":"Food & Drink"
        },
        {
            "category":"Restaurant",
            "type":"Food & Drink"
        }
    ],
    "sg:phone":"+1 636 639 2337",
    "sg:postcode":"63385",
    "sg:province":"MO",
    "sg:tags":[
        "tavern",
        "grill",
        "brew"
    ],
    "wof:name":"Olde Towne Pub",
    "wof:placetype":"venue"
},
  "geometry": {"coordinates":[-90.852763,38.810542],"type":"Point"}
}