{
  "type": "Feature",
  "properties": {
    "iso:country":"US",
    "sg:address":"701 Grand Canyon Dr",
    "sg:city":"Farmington",
    "sg:classifiers":[
        {
            "category":"Professional",
            "subcategory":"Computer Services",
            "type":"Services"
        }
    ],
    "sg:phone":"+1 573 760 1798",
    "sg:postcode":"63640",
    "sg:province":"MO",
    "sg:tags":[
        "cd-rom",
        "software"
    ],
    "wof:name":"Mitware",
    "wof:placetype":"venue"
},
  "geometry": {"coordinates":[-90.430428,37.793129],"type":"Point"}
}