{
  "type": "Feature",
  "properties": {
    "iso:country":"US",
    "sg:address":"2331 Hampton Ave",
    "sg:city":"Saint Louis",
    "sg:classifiers":[
        {
            "category":"Health Services",
            "subcategory":"Doctor",
            "type":"Services"
        },
        {
            "category":"Shopping",
            "subcategory":"Pharmacy",
            "type":"Retail Goods"
        }
    ],
    "sg:phone":"+1 314 772 5000",
    "sg:postcode":"63139",
    "sg:province":"MO",
    "sg:tags":[
        "drugstore"
    ],
    "wof:name":"Dng Pharmacy",
    "wof:placetype":"venue"
},
  "geometry": {"coordinates":[-90.287695,38.614954],"type":"Point"}
}