{
  "type": "Feature",
  "properties": {
    "iso:country":"US",
    "sg:address":"22935 Harlan Ln",
    "sg:city":"Waynesville",
    "sg:classifiers":[
        {
            "category":"Building & Trades",
            "subcategory":"Cleaning & Sanitation",
            "type":"Services"
        }
    ],
    "sg:phone":"+1 573 336 3210",
    "sg:postcode":"65584",
    "sg:province":"MO",
    "sg:tags":[
        "maintenance"
    ],
    "wof:name":"Rah ink Cleaning & Maint",
    "wof:placetype":"venue"
},
  "geometry": {"coordinates":[-92.132893,37.828057],"type":"Point"}
}