{
  "type": "Feature",
  "properties": {
    "iso:country":"US",
    "sg:address":"3101 Caroline St",
    "sg:city":"Saint Louis",
    "sg:classifiers":[
        {
            "category":"Organizations",
            "subcategory":"Religious Organization",
            "type":"Services"
        }
    ],
    "sg:phone":"+1 314 772 6086",
    "sg:postcode":"63104",
    "sg:province":"MO",
    "wof:name":"Rock Chapel AME Church",
    "wof:placetype":"venue"
},
  "geometry": {"coordinates":[-90.22930100000001,38.6208],"type":"Point"}
}