{
  "type": "Feature",
  "properties": {
    "iso:country":"US",
    "sg:address":"6001 S Broadway",
    "sg:city":"Saint Louis",
    "sg:classifiers":[
        {
            "category":"Wholesale",
            "subcategory":"Construction Materials",
            "type":"Manufacturing & Wholesale Goods"
        }
    ],
    "sg:phone":"+1 314 457 0300",
    "sg:postcode":"63111",
    "sg:province":"MO",
    "wof:name":"Shed City",
    "wof:placetype":"venue"
},
  "geometry": {"coordinates":[-90.24628,38.55757],"type":"Point"}
}