{
  "type": "Feature",
  "properties": {
    "iso:country":"US",
    "sg:address":"8442 Apple Rd",
    "sg:city":"Sarcoxie",
    "sg:classifiers":[
        {
            "category":"Social Services",
            "subcategory":"Child Care",
            "type":"Services"
        }
    ],
    "sg:phone":"+1 417 548 6403",
    "sg:postcode":"64862",
    "sg:province":"MO",
    "sg:tags":[
        "day"
    ],
    "wof:name":"Kathys Krtters Prschool Dycare",
    "wof:placetype":"venue"
},
  "geometry": {"coordinates":[-94.22199500000001,37.066581],"type":"Point"}
}