{
  "type": "Feature",
  "properties": {
    "iso:country":"US",
    "sg:address":"724 Union Blvd",
    "sg:city":"Saint Louis",
    "sg:classifiers":[
        {
            "category":"Education",
            "subcategory":"University",
            "type":"Public Place"
        }
    ],
    "sg:phone":"+1 314 367 2585",
    "sg:postcode":"63108",
    "sg:province":"MO",
    "sg:tags":[
        "college"
    ],
    "wof:name":"University Otrch and Extnsn-U of Mo/Lncln U Cprtve",
    "wof:placetype":"venue"
},
  "geometry": {"coordinates":[-90.27310199999999,38.653301],"type":"Point"}
}