{
  "type": "Feature",
  "properties": {
    "iso:country":"US",
    "sg:address":"721 Olive St",
    "sg:city":"Saint Louis",
    "sg:classifiers":[
        {
            "category":"Wholesale",
            "subcategory":"Jewelry",
            "type":"Manufacturing & Wholesale Goods"
        }
    ],
    "sg:phone":"+1 314 421 5339",
    "sg:postcode":"63101",
    "sg:province":"MO",
    "sg:tags":[
        "stone"
    ],
    "wof:name":"Dia-Jewels Inc",
    "wof:placetype":"venue"
},
  "geometry": {"coordinates":[-90.191669,38.628395],"type":"Point"}
}