{
  "type": "Feature",
  "properties": {
    "iso:country":"US",
    "sg:address":"1 N Washington St",
    "sg:city":"Farmington",
    "sg:classifiers":[
        {
            "category":"Government",
            "subcategory":"Court House",
            "type":"Public Place"
        }
    ],
    "sg:phone":"+1 573 756 5144",
    "sg:postcode":"63640",
    "sg:province":"MO",
    "wof:name":"Pratte Kenneth W Circuit Judge",
    "wof:placetype":"venue"
},
  "geometry": {"coordinates":[-90.42088699999999,37.781152],"type":"Point"}
}