{
  "type": "Feature",
  "properties": {
    "iso:country":"US",
    "sg:address":"1409 S Commercial St",
    "sg:city":"Harrisonville",
    "sg:classifiers":[
        {
            "category":"Travel",
            "subcategory":"Hotels & Motels",
            "type":"Entertainment"
        }
    ],
    "sg:phone":"+1 816 380 3326",
    "sg:postcode":"64701",
    "sg:province":"MO",
    "wof:name":"Payless Motel",
    "wof:placetype":"venue"
},
  "geometry": {"coordinates":[-94.35528499999999,38.645983],"type":"Point"}
}