{
  "type": "Feature",
  "properties": {
    "iso:country":"US",
    "sg:address":"1810 E 28th St",
    "sg:city":"Trenton",
    "sg:classifiers":[
        {
            "category":"Personal",
            "subcategory":"Beauty Salon",
            "type":"Services"
        }
    ],
    "sg:phone":"+1 660 359 5959",
    "sg:postcode":"64683",
    "sg:province":"MO",
    "sg:tags":[
        "shop"
    ],
    "wof:name":"Magnolias",
    "wof:placetype":"venue"
},
  "geometry": {"coordinates":[-93.601383,40.090062],"type":"Point"}
}