{
  "type": "Feature",
  "properties": {
    "iso:country":"US",
    "sg:address":"8433 Goldenrod",
    "sg:city":"Cedar Hill",
    "sg:classifiers":[
        {
            "category":"Manufacturing",
            "subcategory":"Retail Goods",
            "type":"Manufacturing & Wholesale Goods"
        }
    ],
    "sg:phone":"+1 636 274 8890",
    "sg:postcode":"63016",
    "sg:province":"MO",
    "sg:tags":[
        "product",
        "mfg"
    ],
    "wof:name":"Simply Stitches",
    "wof:placetype":"venue"
},
  "geometry": {"coordinates":[-90.64201,38.368568],"type":"Point"}
}