{
  "type": "Feature",
  "properties": {
    "iso:country":"US",
    "sg:address":"1038 S Delaware Ave",
    "sg:city":"Springfield",
    "sg:classifiers":[
        {
            "category":"Manufacturing",
            "subcategory":"Printing",
            "type":"Manufacturing & Wholesale Goods"
        }
    ],
    "sg:phone":"+1 417 862 5363",
    "sg:postcode":"65804",
    "sg:province":"MO",
    "sg:tags":[
        "publishing"
    ],
    "wof:name":"Forbes Mill Press",
    "wof:placetype":"venue"
},
  "geometry": {"coordinates":[-93.26661300000001,37.195259],"type":"Point"}
}