{
  "type": "Feature",
  "properties": {
    "iso:country":"US",
    "sg:address":"502 W Main St",
    "sg:city":"Jackson",
    "sg:classifiers":[
        {
            "category":"Wholesale",
            "subcategory":"Medical Equipment & Supplies",
            "type":"Manufacturing & Wholesale Goods"
        }
    ],
    "sg:phone":"+1 573 243 6226",
    "sg:postcode":"63755",
    "sg:province":"MO",
    "wof:name":"Banner Medical Equipment Inc",
    "wof:placetype":"venue"
},
  "geometry": {"coordinates":[-89.673131,37.383217],"type":"Point"}
}