{
  "type": "Feature",
  "properties": {
    "iso:country":"US",
    "sg:address":"6620 Stephens Station Rd",
    "sg:city":"Columbia",
    "sg:classifiers":[
        {
            "category":"Building & Trades",
            "subcategory":"Construction",
            "type":"Services"
        }
    ],
    "sg:phone":"+1 573 474 3814",
    "sg:postcode":"65202",
    "sg:province":"MO",
    "sg:tags":[
        "equipment",
        "supply",
        "drywall",
        "contractor"
    ],
    "wof:name":"Jc Drywall Inc",
    "wof:placetype":"venue"
},
  "geometry": {"coordinates":[-92.265247,39.021218],"type":"Point"}
}