{
  "type": "Feature",
  "properties": {
    "iso:country":"US",
    "sg:address":"2004 Lee Ave",
    "sg:city":"Jackson",
    "sg:classifiers":[
        {
            "category":"Utilities",
            "subcategory":"Refuse",
            "type":"Services"
        }
    ],
    "sg:phone":"+1 573 243 6223",
    "sg:postcode":"63755",
    "sg:province":"MO",
    "sg:tags":[
        "system"
    ],
    "wof:name":"Site U29",
    "wof:placetype":"venue"
},
  "geometry": {"coordinates":[-89.678405,37.364757],"type":"Point"}
}