{
  "type": "Feature",
  "properties": {
    "iso:country":"US",
    "sg:address":"9201 Saint Charles Rock Rd",
    "sg:city":"St Louis",
    "sg:classifiers":[
        {
            "category":"Autos & Motor Vehicles",
            "subcategory":"Automobile Sales",
            "type":"Retail Goods"
        }
    ],
    "sg:phone":"+1 314 427 4400",
    "sg:postcode":"63114",
    "sg:province":"MO",
    "sg:tags":[
        "car",
        "dealer"
    ],
    "wof:name":"Regency Motors II",
    "wof:placetype":"venue"
},
  "geometry": {"coordinates":[-90.358225,38.715138],"type":"Point"}
}