{
  "type": "Feature",
  "properties": {
    "iso:country":"US",
    "sg:address":"3317 N Euclid Ave",
    "sg:city":"St Louis",
    "sg:classifiers":[
        {
            "category":"Social Services",
            "subcategory":"Child Care",
            "type":"Services"
        }
    ],
    "sg:phone":"+1 314 389 2713",
    "sg:postcode":"63115",
    "sg:province":"MO",
    "wof:name":"Spirit Of The Child Day Care",
    "wof:placetype":"venue"
},
  "geometry": {"coordinates":[-90.250355,38.673581],"type":"Point"}
}