{
  "type": "Feature",
  "properties": {
    "iso:country":"US",
    "sg:address":"37589 Co Rd 680",
    "sg:city":"Perry",
    "sg:classifiers":[
        {
            "category":"Wholesale",
            "subcategory":"Machinery & Supplies",
            "type":"Manufacturing & Wholesale Goods"
        },
        {
            "category":"Retail",
            "subcategory":"Auto Repair",
            "type":"Services"
        }
    ],
    "sg:phone":"+1 573 565 2856",
    "sg:postcode":"63462",
    "sg:province":"MO",
    "sg:tags":[
        "engine",
        "general"
    ],
    "wof:name":"Sharp's Diesel Repair",
    "wof:placetype":"venue"
},
  "geometry": {"coordinates":[-91.78539499999999,39.440306],"type":"Point"}
}