{
  "type": "Feature",
  "properties": {
    "iso:country":"US",
    "sg:address":"727 Ridge Ave",
    "sg:city":"Poplar Bluff",
    "sg:classifiers":[
        {
            "category":"Organizations",
            "subcategory":"Religious Organization",
            "type":"Services"
        }
    ],
    "sg:phone":"+1 573 776 6200",
    "sg:postcode":"63901",
    "sg:province":"MO",
    "sg:tags":[
        "church"
    ],
    "wof:name":"Christian Family Fellowship",
    "wof:placetype":"venue"
},
  "geometry": {"coordinates":[-90.415865,36.762408],"type":"Point"}
}