{
  "type": "Feature",
  "properties": {
    "iso:country":"US",
    "sg:address":"207 W Caldwell St",
    "sg:city":"Paris",
    "sg:classifiers":[
        {
            "category":"Organizations",
            "subcategory":"Religious Organization",
            "type":"Services"
        }
    ],
    "sg:phone":"+1 660 327 4326",
    "sg:postcode":"65275",
    "sg:province":"MO",
    "sg:tags":[
        "church"
    ],
    "wof:name":"Methodist Church Study",
    "wof:placetype":"venue"
},
  "geometry": {"coordinates":[-92.002133,39.481602],"type":"Point"}
}