{
  "type": "Feature",
  "properties": {
    "iso:country":"US",
    "sg:address":"101 S Allen St",
    "sg:city":"Centralia",
    "sg:classifiers":[
        {
            "category":"Professional",
            "subcategory":"Lawyer & Legal Services",
            "type":"Services"
        }
    ],
    "sg:phone":"+1 573 682 3933",
    "sg:postcode":"65240",
    "sg:province":"MO",
    "sg:tags":[
        "attorney"
    ],
    "wof:name":"Grimes Fay & Gaeth LLC",
    "wof:placetype":"venue"
},
  "geometry": {"coordinates":[-92.13888,39.21156],"type":"Point"}
}