{
  "type": "Feature",
  "properties": {
    "iso:country":"US",
    "sg:address":"456 W Little Oaks Rd",
    "sg:city":"Rolla",
    "sg:classifiers":[
        {
            "category":"Personal",
            "type":"Services"
        }
    ],
    "sg:phone":"+1 573 426 4435",
    "sg:postcode":"65401",
    "sg:province":"MO",
    "sg:tags":[
        "towing"
    ],
    "wof:name":"Central Missouri Towing & Recovery",
    "wof:placetype":"venue"
},
  "geometry": {"coordinates":[-91.77315,37.915095],"type":"Point"}
}