{
  "type": "Feature",
  "properties": {
    "iso:country":"US",
    "sg:address":"1106 Crosswinds Ct",
    "sg:city":"Wentzville",
    "sg:classifiers":[
        {
            "category":"Food & Beverages",
            "subcategory":"Groceries & Convenience Stores",
            "type":"Retail Goods"
        }
    ],
    "sg:phone":"+1 636 639 6804",
    "sg:postcode":"63385",
    "sg:province":"MO",
    "sg:tags":[
        "product"
    ],
    "wof:name":"Buddeez Inc",
    "wof:placetype":"venue"
},
  "geometry": {"coordinates":[-90.817649,38.801536],"type":"Point"}
}