{
  "type": "Feature",
  "properties": {
    "iso:country":"US",
    "sg:address":"159 Endeavor Dr",
    "sg:city":"Rogersville",
    "sg:classifiers":[
        {
            "category":"Manufacturing",
            "subcategory":"Metals",
            "type":"Manufacturing & Wholesale Goods"
        }
    ],
    "sg:phone":"+1 417 753 2888",
    "sg:postcode":"65742",
    "sg:province":"MO",
    "sg:tags":[
        "forming"
    ],
    "wof:name":"Mid-AM Metal Forming",
    "wof:placetype":"venue"
},
  "geometry": {"coordinates":[-93.036146,37.114921],"type":"Point"}
}