{
  "type": "Feature",
  "properties": {
    "iso:country":"US",
    "sg:address":"10426 Lackland Rd",
    "sg:city":"Saint Louis",
    "sg:classifiers":[
        {
            "category":"Professional",
            "subcategory":"Business Services",
            "type":"Services"
        }
    ],
    "sg:phone":"+1 314 423 8472",
    "sg:postcode":"63114",
    "sg:province":"MO",
    "wof:name":"Lunn Appraisal Service",
    "wof:placetype":"venue"
},
  "geometry": {"coordinates":[-90.39109500000001,38.696596],"type":"Point"}
}