{
  "type": "Feature",
  "properties": {
    "iso:country":"US",
    "sg:address":"821 S Sparks Ave",
    "sg:city":"Springfield",
    "sg:classifiers":[
        {
            "category":"Organizations",
            "subcategory":"Religious Organization",
            "type":"Services"
        }
    ],
    "sg:phone":"+1 417 832 8546",
    "sg:postcode":"65802",
    "sg:province":"MO",
    "wof:name":"Central Arkansas Univ Ministry",
    "wof:placetype":"venue"
},
  "geometry": {"coordinates":[-93.25046399999999,37.198777],"type":"Point"}
}