{
  "type": "Feature",
  "properties": {
    "iso:country":"US",
    "sg:address":"211 Hillsdale Dr",
    "sg:city":"Ballwin",
    "sg:classifiers":[
        {
            "category":"Professional",
            "subcategory":"Business Services",
            "type":"Services"
        }
    ],
    "sg:phone":"+1 636 527 0013",
    "sg:postcode":"63011",
    "sg:province":"MO",
    "wof:name":"Adrian Enterprises",
    "wof:placetype":"venue"
},
  "geometry": {"coordinates":[-90.567961,38.59774],"type":"Point"}
}