{
  "type": "Feature",
  "properties": {
    "iso:country":"US",
    "sg:address":"3024 S 29th St",
    "sg:city":"Saint Joseph",
    "sg:classifiers":[
        {
            "category":"Building & Trades",
            "subcategory":"Construction",
            "type":"Services"
        }
    ],
    "sg:phone":"+1 816 279 6673",
    "sg:postcode":"64503",
    "sg:province":"MO",
    "sg:tags":[
        "contractor"
    ],
    "wof:name":"Dale Frankum Masonry",
    "wof:placetype":"venue"
},
  "geometry": {"coordinates":[-94.822326,39.737116],"type":"Point"}
}