{
  "type": "Feature",
  "properties": {
    "iso:country":"US",
    "sg:address":"501 N Maguire St",
    "sg:city":"Warrensburg",
    "sg:classifiers":[
        {
            "category":"Professional",
            "subcategory":"Advertising",
            "type":"Services"
        }
    ],
    "sg:phone":"+1 660 747 2799",
    "sg:postcode":"64093",
    "sg:province":"MO",
    "sg:tags":[
        "mailing",
        "shipping"
    ],
    "wof:name":"Pack 'N' Mail",
    "wof:placetype":"venue"
},
  "geometry": {"coordinates":[-93.735478,38.768355],"type":"Point"}
}