{
  "type": "Feature",
  "properties": {
    "iso:country":"US",
    "sg:address":"5223 N 20th St",
    "sg:city":"St Louis",
    "sg:classifiers":[
        {
            "category":"Education",
            "subcategory":"School",
            "type":"Public Place"
        }
    ],
    "sg:phone":"+1 314 534 9628",
    "sg:postcode":"63107",
    "sg:province":"MO",
    "wof:name":"St Louis Academies",
    "wof:placetype":"venue"
},
  "geometry": {"coordinates":[-90.21335500000001,38.67548],"type":"Point"}
}