{
  "type": "Feature",
  "properties": {
    "iso:country":"US",
    "sg:address":"4607 Beck Ave",
    "sg:city":"St Louis",
    "sg:classifiers":[
        {
            "category":"Building & Trades",
            "subcategory":"Construction",
            "type":"Services"
        }
    ],
    "sg:phone":"+1 314 772 9696",
    "sg:postcode":"63116",
    "sg:province":"MO",
    "sg:tags":[
        "builder",
        "specialty",
        "repairer",
        "chimney",
        "contractor"
    ],
    "sg:website":"www.gerardchimney.com",
    "wof:name":"Gerard Chimney Co",
    "wof:placetype":"venue"
},
  "geometry": {"coordinates":[-90.271563,38.592685],"type":"Point"}
}