{
  "type": "Feature",
  "properties": {
    "iso:country":"US",
    "sg:address":"310 E Washington St",
    "sg:city":"East Prairie",
    "sg:classifiers":[
        {
            "category":"Autos & Motor Vehicles",
            "subcategory":"Auto Supplies",
            "type":"Retail Goods"
        }
    ],
    "sg:phone":"+1 573 649 5550",
    "sg:postcode":"63845",
    "sg:province":"MO",
    "sg:tags":[
        "automotive",
        "repair"
    ],
    "wof:name":"Auto Tire and Parts Company",
    "wof:placetype":"venue"
},
  "geometry": {"coordinates":[-89.380348,36.777412],"type":"Point"}
}