{
  "type": "Feature",
  "properties": {
    "iso:country":"US",
    "sg:address":"802 N 6th St",
    "sg:city":"Tarkio",
    "sg:classifiers":[
        {
            "category":"Transit Center",
            "subcategory":"Freight",
            "type":"Transportation"
        },
        {
            "category":"Freight",
            "type":"Transportation"
        }
    ],
    "sg:phone":"+1 660 736 5872",
    "sg:postcode":"64491",
    "sg:province":"MO",
    "sg:tags":[
        "local",
        "trucking-motor",
        "trucking"
    ],
    "wof:name":"Bill Smith Trucking",
    "wof:placetype":"venue"
},
  "geometry": {"coordinates":[-95.382279,40.446417],"type":"Point"}
}