{
  "type": "Feature",
  "properties": {
    "iso:country":"US",
    "sg:address":"2810 N Belt Hwy",
    "sg:city":"St Joseph",
    "sg:classifiers":[
        {
            "category":"Wholesale",
            "subcategory":"Auto Parts",
            "type":"Manufacturing & Wholesale Goods"
        }
    ],
    "sg:phone":"+1 816 232 4048",
    "sg:postcode":"64506",
    "sg:province":"MO",
    "sg:tags":[
        "truck",
        "accessory"
    ],
    "wof:name":"Line X Of St Joseph",
    "wof:placetype":"venue"
},
  "geometry": {"coordinates":[-94.809404,39.790811],"type":"Point"}
}