{
  "type": "Feature",
  "properties": {
    "iso:country":"US",
    "sg:address":"3101 Industrial Park Pl W",
    "sg:city":"Saint Peters",
    "sg:classifiers":[
        {
            "category":"Building & Trades",
            "subcategory":"Construction",
            "type":"Services"
        }
    ],
    "sg:phone":"+1 636 928 9966",
    "sg:postcode":"63376",
    "sg:province":"MO",
    "sg:tags":[
        "concrete",
        "contractor"
    ],
    "wof:name":"M & H Concrete Contractors",
    "wof:placetype":"venue"
},
  "geometry": {"coordinates":[-90.66913599999999,38.800773],"type":"Point"}
}