{
  "type": "Feature",
  "properties": {
    "iso:country":"US",
    "sg:address":"202 E 1st St",
    "sg:city":"West Plains",
    "sg:classifiers":[
        {
            "category":"Home & Garden",
            "subcategory":"Building Materials",
            "type":"Retail Goods"
        }
    ],
    "sg:phone":"+1 417 255 8303",
    "sg:postcode":"65775",
    "sg:province":"MO",
    "sg:tags":[
        "glass",
        "window",
        "plate"
    ],
    "wof:name":"Phil's Glass & Screen Repair",
    "wof:placetype":"venue"
},
  "geometry": {"coordinates":[-91.851382,36.731965],"type":"Point"}
}