{
  "type": "Feature",
  "properties": {
    "iso:country":"US",
    "sg:address":"8178 State Rd Nn",
    "sg:city":"Fulton",
    "sg:classifiers":[
        {
            "category":"Building & Trades",
            "subcategory":"Construction",
            "type":"Services"
        }
    ],
    "sg:phone":"+1 573 642 1828",
    "sg:postcode":"65251",
    "sg:province":"MO",
    "sg:tags":[
        "paving",
        "contractor"
    ],
    "wof:name":"Christensen Construction Co",
    "wof:placetype":"venue"
},
  "geometry": {"coordinates":[-91.979249,38.762927],"type":"Point"}
}