{
  "type": "Feature",
  "properties": {
    "iso:country":"US",
    "sg:address":"311 N Walnut St",
    "sg:city":"Cameron",
    "sg:classifiers":[
        {
            "category":"Banks & Credit Unions",
            "subcategory":"Investment Brokerage",
            "type":"Services"
        }
    ],
    "sg:phone":"+1 816 632 7111",
    "sg:postcode":"64429",
    "sg:province":"MO",
    "sg:tags":[
        "security"
    ],
    "wof:name":"A G Edwards & Sons Inc",
    "wof:placetype":"venue"
},
  "geometry": {"coordinates":[-94.235854,39.742163],"type":"Point"}
}