{
  "type": "Feature",
  "properties": {
    "iso:country":"US",
    "sg:address":"309 SW Seagull St",
    "sg:city":"Lees Summit",
    "sg:classifiers":[
        {
            "category":"Professional",
            "subcategory":"Business Services",
            "type":"Services"
        }
    ],
    "sg:phone":"+1 816 537 4099",
    "sg:postcode":"64082",
    "sg:province":"MO",
    "wof:name":"Bullocks Rcwear Safety Eqp LLC",
    "wof:placetype":"venue"
},
  "geometry": {"coordinates":[-94.38504,38.82718],"type":"Point"}
}