{
  "type": "Feature",
  "properties": {
    "iso:country":"US",
    "sg:address":"21301 E 175th St",
    "sg:city":"Pleasant Hill",
    "sg:classifiers":[
        {
            "category":"Building & Trades",
            "subcategory":"Plumbing",
            "type":"Services"
        }
    ],
    "sg:phone":"+1 816 540 3795",
    "sg:postcode":"64080",
    "sg:province":"MO",
    "sg:tags":[
        "contractor"
    ],
    "wof:name":"Glenn Sivils",
    "wof:placetype":"venue"
},
  "geometry": {"coordinates":[-94.336702,38.800392],"type":"Point"}
}