{
  "type": "Feature",
  "properties": {
    "iso:country":"US",
    "sg:address":"624 NE English Manor Dr",
    "sg:city":"Lees Summit",
    "sg:classifiers":[
        {
            "category":"Retail",
            "subcategory":"Portrait Studio",
            "type":"Services"
        }
    ],
    "sg:phone":"+1 816 554 6210",
    "sg:postcode":"64086",
    "sg:province":"MO",
    "sg:tags":[
        "photographer"
    ],
    "wof:name":"Lakelight Photography",
    "wof:placetype":"venue"
},
  "geometry": {"coordinates":[-94.36618900000001,38.926585],"type":"Point"}
}