{
  "type": "Feature",
  "properties": {
    "iso:country":"US",
    "sg:address":"121 W 2nd St",
    "sg:city":"Mountain Grove",
    "sg:classifiers":[
        {
            "category":"Shopping",
            "subcategory":"Computers & Home Electronics",
            "type":"Retail Goods"
        }
    ],
    "sg:phone":"+1 417 926 6248",
    "sg:postcode":"65711",
    "sg:province":"MO",
    "wof:name":"Radio Shack",
    "wof:placetype":"venue"
},
  "geometry": {"coordinates":[-92.26351200000001,37.129913],"type":"Point"}
}