{
  "type": "Feature",
  "properties": {
    "iso:country":"US",
    "sg:address":"1814 Main St",
    "sg:city":"Kansas City",
    "sg:classifiers":[
        {
            "category":"Manufacturing",
            "subcategory":"Printing",
            "type":"Manufacturing & Wholesale Goods"
        }
    ],
    "sg:phone":"+1 816 842 7881",
    "sg:postcode":"64108",
    "sg:province":"MO",
    "sg:tags":[
        "print",
        "shop",
        "specialty"
    ],
    "wof:name":"American Reprographics",
    "wof:placetype":"venue"
},
  "geometry": {"coordinates":[-94.58370600000001,39.090616],"type":"Point"}
}