{
  "type": "Feature",
  "properties": {
    "iso:country":"US",
    "sg:address":"1808 Horseshoe Ridge Rd",
    "sg:city":"Chesterfield",
    "sg:classifiers":[
        {
            "category":"Professional",
            "subcategory":"Business Services",
            "type":"Services"
        }
    ],
    "sg:phone":"+1 636 530 0440",
    "sg:postcode":"63005",
    "sg:province":"MO",
    "wof:name":"Lindell Enterprises",
    "wof:placetype":"venue"
},
  "geometry": {"coordinates":[-90.597842,38.639655],"type":"Point"}
}