{
  "type": "Feature",
  "properties": {
    "iso:country":"US",
    "sg:address":"21519 S Cleveland Ave",
    "sg:city":"Belton",
    "sg:classifiers":[
        {
            "category":"Building & Trades",
            "subcategory":"Construction",
            "type":"Services"
        }
    ],
    "sg:phone":"+1 816 618 3588",
    "sg:postcode":"64012",
    "sg:province":"MO",
    "sg:tags":[
        "dry wall",
        "contractor"
    ],
    "wof:name":"Big T Dry Wall",
    "wof:placetype":"venue"
},
  "geometry": {"coordinates":[-94.55324,38.735435],"type":"Point"}
}