{
  "type": "Feature",
  "properties": {
    "iso:country":"US",
    "sg:address":"996 Chesterfield Pkwy E",
    "sg:city":"Chesterfield",
    "sg:classifiers":[
        {
            "category":"Professional",
            "subcategory":"Lawyer & Legal Services",
            "type":"Services"
        }
    ],
    "sg:phone":"+1 636 530 9110",
    "sg:postcode":"63017",
    "sg:province":"MO",
    "sg:tags":[
        "consulting",
        "management"
    ],
    "sg:website":"www.hirsch-co.com",
    "wof:name":"Hirsch & Co",
    "wof:placetype":"venue"
},
  "geometry": {"coordinates":[-90.55383399999999,38.656936],"type":"Point"}
}