{
  "type": "Feature",
  "properties": {
    "iso:country":"US",
    "sg:address":"26 N Central Ave",
    "sg:city":"St Louis",
    "sg:classifiers":[
        {
            "category":"Wholesale",
            "subcategory":"Apparel",
            "type":"Manufacturing & Wholesale Goods"
        }
    ],
    "sg:phone":"+1 314 421 6328",
    "sg:postcode":"63105",
    "sg:province":"MO",
    "sg:tags":[
        "shoes"
    ],
    "wof:name":"Alpers' Jobbing Co",
    "wof:placetype":"venue"
},
  "geometry": {"coordinates":[-90.33805,38.65132],"type":"Point"}
}