{
  "type": "Feature",
  "properties": {
    "iso:country":"US",
    "sg:address":"8015 NW Potomac Ave",
    "sg:city":"Kansas City",
    "sg:classifiers":[
        {
            "category":"Building & Trades",
            "subcategory":"Construction",
            "type":"Services"
        }
    ],
    "sg:phone":"+1 816 587 2255",
    "sg:postcode":"64152",
    "sg:province":"MO",
    "sg:tags":[
        "contractor"
    ],
    "wof:name":"Cunningham & Assoc",
    "wof:placetype":"venue"
},
  "geometry": {"coordinates":[-94.695014,39.239297],"type":"Point"}
}