{
  "type": "Feature",
  "properties": {
    "iso:country":"US",
    "sg:address":"2007 S Halliburton St",
    "sg:city":"Kirksville",
    "sg:classifiers":[
        {
            "category":"Personal",
            "subcategory":"Beauty Salon",
            "type":"Services"
        }
    ],
    "sg:phone":"+1 660 665 5065",
    "sg:postcode":"63501",
    "sg:province":"MO",
    "sg:tags":[
        "shop"
    ],
    "wof:name":"Carolyn's New Image Hair Care",
    "wof:placetype":"venue"
},
  "geometry": {"coordinates":[-92.576576,40.178924],"type":"Point"}
}