{
  "type": "Feature",
  "properties": {
    "iso:country":"US",
    "sg:address":"7066 Pershing Ave",
    "sg:city":"Saint Louis",
    "sg:classifiers":[
        {
            "category":"Professional",
            "subcategory":"Art Services",
            "type":"Services"
        }
    ],
    "sg:phone":"+1 314 862 5994",
    "sg:postcode":"63130",
    "sg:province":"MO",
    "sg:tags":[
        "commercial",
        "design"
    ],
    "wof:name":"Whitney Design Works LLC",
    "wof:placetype":"venue"
},
  "geometry": {"coordinates":[-90.31619000000001,38.652199],"type":"Point"}
}