{
  "type": "Feature",
  "properties": {
    "iso:country":"US",
    "sg:address":"707 N State St",
    "sg:city":"Rolla",
    "sg:classifiers":[
        {
            "category":"Organizations",
            "subcategory":"Community Association",
            "type":"Services"
        }
    ],
    "sg:phone":"+1 573 364 6434",
    "sg:postcode":"65401",
    "sg:province":"MO",
    "sg:tags":[
        "sorority",
        "fraternity"
    ],
    "wof:name":"Phi Kappa Theta",
    "wof:placetype":"venue"
},
  "geometry": {"coordinates":[-91.775216,37.949916],"type":"Point"}
}