{
  "type": "Feature",
  "properties": {
    "iso:country":"US",
    "sg:address":"101 Champagne Blvd",
    "sg:city":"Branson",
    "sg:classifiers":[
        {
            "category":"Real Estate",
            "subcategory":"Real Estate Services",
            "type":"Services"
        },
        {
            "category":"Personal",
            "type":"Services"
        },
        {
            "category":"Building & Trades",
            "subcategory":"Cleaning & Sanitation",
            "type":"Services"
        }
    ],
    "sg:phone":"+1 417 336 0246",
    "sg:postcode":"65616",
    "sg:province":"MO",
    "sg:tags":[
        "butlers'",
        "maids'",
        "maintenance",
        "cleaners-interior"
    ],
    "wof:name":"Master Corp Inc",
    "wof:placetype":"venue"
},
  "geometry": {"coordinates":[-93.287132,36.606449],"type":"Point"}
}