{
  "type": "Feature",
  "properties": {
    "iso:country":"US",
    "sg:address":"2717 Winnebago St",
    "sg:city":"Saint Louis",
    "sg:classifiers":[
        {
            "category":"Building & Trades",
            "subcategory":"Construction",
            "type":"Services"
        }
    ],
    "sg:phone":"+1 314 776 1941",
    "sg:postcode":"63118",
    "sg:province":"MO",
    "sg:tags":[
        "excavation",
        "contractor"
    ],
    "wof:name":"M W D Trucking",
    "wof:placetype":"venue"
},
  "geometry": {"coordinates":[-90.22944200000001,38.588323],"type":"Point"}
}