{
  "type": "Feature",
  "properties": {
    "iso:country":"US",
    "sg:address":"2916 E 33 St",
    "sg:city":"Kansas City",
    "sg:classifiers":[
        {
            "category":"Professional",
            "subcategory":"Research",
            "type":"Services"
        }
    ],
    "sg:phone":"+1 816 923 0390",
    "sg:postcode":"64128",
    "sg:province":"MO",
    "sg:tags":[
        "new",
        "product",
        "innovation"
    ],
    "wof:name":"Belco Investments Inc",
    "wof:placetype":"venue"
},
  "geometry": {"coordinates":[-94.548547,39.06617],"type":"Point"}
}