{
  "type": "Feature",
  "properties": {
    "iso:country":"US",
    "sg:address":"786 Merus Ct",
    "sg:city":"Fenton",
    "sg:classifiers":[
        {
            "category":"Wholesale",
            "subcategory":"Furniture",
            "type":"Manufacturing & Wholesale Goods"
        }
    ],
    "sg:phone":"+1 636 349 3383",
    "sg:postcode":"63026",
    "sg:province":"MO",
    "sg:website":"www.chesterharvey.net",
    "wof:name":"Chester L Harvey",
    "wof:placetype":"venue"
},
  "geometry": {"coordinates":[-90.455791,38.539963],"type":"Point"}
}