{
  "type": "Feature",
  "properties": {
    "iso:country":"US",
    "sg:address":"1722 Commercial St",
    "sg:city":"St Joseph",
    "sg:classifiers":[
        {
            "category":"Manufacturing",
            "subcategory":"Glass & Minerals",
            "type":"Manufacturing & Wholesale Goods"
        },
        {
            "category":"Building & Trades",
            "subcategory":"Construction",
            "type":"Services"
        }
    ],
    "sg:phone":"+1 816 390 9927",
    "sg:postcode":"64503",
    "sg:province":"MO",
    "sg:tags":[
        "nonresidential",
        "contractor",
        "concrete",
        "brick",
        "prod",
        "block"
    ],
    "wof:name":"Talbot & Sons Construction",
    "wof:placetype":"venue"
},
  "geometry": {"coordinates":[-94.838329,39.738241],"type":"Point"}
}