{
  "type": "Feature",
  "properties": {
    "iso:country":"US",
    "sg:address":"7068 Maryland Ave",
    "sg:city":"Saint Louis",
    "sg:classifiers":[
        {
            "category":"Professional",
            "subcategory":"Lawyer & Legal Services",
            "type":"Services"
        }
    ],
    "sg:phone":"+1 314 863 0466",
    "sg:postcode":"63130",
    "sg:province":"MO",
    "wof:name":"Sewell Larry M Atty",
    "wof:placetype":"venue"
},
  "geometry": {"coordinates":[-90.318298,38.649799],"type":"Point"}
}