{
  "type": "Feature",
  "properties": {
    "iso:country":"US",
    "sg:address":"7309 Brunswick Ave",
    "sg:city":"St Louis",
    "sg:classifiers":[
        {
            "category":"Organizations",
            "subcategory":"Professional Association",
            "type":"Services"
        }
    ],
    "sg:phone":"+1 314 645 2224",
    "sg:postcode":"63119",
    "sg:province":"MO",
    "wof:name":"Royal Alliance Assoc Inc",
    "wof:placetype":"venue"
},
  "geometry": {"coordinates":[-90.32488600000001,38.58908],"type":"Point"}
}