{
  "type": "Feature",
  "properties": {
    "iso:country":"US",
    "sg:address":"1674 Gravois Rd",
    "sg:city":"High Ridge",
    "sg:classifiers":[
        {
            "category":"Organizations",
            "subcategory":"Community Association",
            "type":"Services"
        }
    ],
    "sg:phone":"+1 636 376 0471",
    "sg:postcode":"63049",
    "sg:province":"MO",
    "sg:tags":[
        "fraternal"
    ],
    "wof:name":"Grand Chapter Of Mo Des",
    "wof:placetype":"venue"
},
  "geometry": {"coordinates":[-90.49502,38.485527],"type":"Point"}
}