{
  "type": "Feature",
  "properties": {
    "iso:country":"US",
    "sg:address":"5334 NE 43 Ter",
    "sg:city":"Kansas City",
    "sg:phone":"+1 816 455 6924",
    "sg:postcode":"64117",
    "sg:province":"MO",
    "sg:tags":[
        "farm",
        "corn",
        "soybean"
    ],
    "wof:name":"Colby Kruse",
    "wof:placetype":"venue"
},
  "geometry": {"coordinates":[-94.51696,39.172612],"type":"Point"}
}