{
  "type": "Feature",
  "properties": {
    "iso:country":"US",
    "sg:address":"107 N Washington St",
    "sg:city":"Nevada",
    "sg:classifiers":[
        {
            "category":"Personal",
            "subcategory":"Beauty Salon",
            "type":"Services"
        }
    ],
    "sg:phone":"+1 417 667 3807",
    "sg:postcode":"64772",
    "sg:province":"MO",
    "wof:name":"Nile's Hairstyling Salon",
    "wof:placetype":"venue"
},
  "geometry": {"coordinates":[-94.355298,37.838233],"type":"Point"}
}