{
  "type": "Feature",
  "properties": {
    "iso:country":"US",
    "sg:address":"1165 W Chestnut St",
    "sg:city":"Kahoka",
    "sg:classifiers":[
        {
            "category":"Personal",
            "subcategory":"Beauty Salon",
            "type":"Services"
        }
    ],
    "sg:phone":"+1 660 727 2168",
    "sg:postcode":"63445",
    "sg:province":"MO",
    "sg:tags":[
        "shop"
    ],
    "wof:name":"Beauty Barn Salon",
    "wof:placetype":"venue"
},
  "geometry": {"coordinates":[-91.732308,40.422601],"type":"Point"}
}