{
  "type": "Feature",
  "properties": {
    "iso:country":"US",
    "sg:address":"53 Fenwick Dr",
    "sg:city":"Saint Louis",
    "sg:classifiers":[
        {
            "category":"Building & Trades",
            "subcategory":"Construction",
            "type":"Services"
        }
    ],
    "sg:phone":"+1 314 522 6147",
    "sg:postcode":"63135",
    "sg:province":"MO",
    "sg:tags":[
        "house"
    ],
    "wof:name":"Joe Finazzos Home Works",
    "wof:placetype":"venue"
},
  "geometry": {"coordinates":[-90.289177,38.746522],"type":"Point"}
}