{
  "type": "Feature",
  "properties": {
    "iso:country":"US",
    "sg:address":"13223 US Hwy 71",
    "sg:city":"Grandview",
    "sg:classifiers":[
        {
            "category":"Building & Trades",
            "subcategory":"Construction",
            "type":"Services"
        }
    ],
    "sg:phone":"+1 816 767 1300",
    "sg:postcode":"64030",
    "sg:province":"MO",
    "sg:tags":[
        "spa",
        "designer",
        "dealer",
        "pool",
        "swimming"
    ],
    "wof:name":"Blue Haven Pools of Kc",
    "wof:placetype":"venue"
},
  "geometry": {"coordinates":[-94.525233,38.88538],"type":"Point"}
}