{
  "type": "Feature",
  "properties": {
    "iso:country":"US",
    "sg:address":"14061 Burr Oak Rd",
    "sg:city":"Mayview",
    "sg:phone":"+1 660 237 4303",
    "sg:postcode":"64071",
    "sg:province":"MO",
    "sg:tags":[
        "farm",
        "corn",
        "soybean"
    ],
    "wof:name":"David Mittelhauser",
    "wof:placetype":"venue"
},
  "geometry": {"coordinates":[-93.85002799999999,38.992828],"type":"Point"}
}