{
  "type": "Feature",
  "properties": {
    "iso:country":"US",
    "sg:address":"745 Craig Rd",
    "sg:city":"St Louis",
    "sg:classifiers":[
        {
            "category":"Professional",
            "subcategory":"Accounting & Tax Preparation",
            "type":"Services"
        }
    ],
    "sg:phone":"+1 314 567 7878",
    "sg:postcode":"63141",
    "sg:province":"MO",
    "sg:tags":[
        "accountant"
    ],
    "wof:name":"Samuel Goldstein CPA",
    "wof:placetype":"venue"
},
  "geometry": {"coordinates":[-90.436746,38.666897],"type":"Point"}
}