{
  "type": "Feature",
  "properties": {
    "iso:country":"US",
    "sg:address":"115 S Clayton Ave",
    "sg:city":"Maryville",
    "sg:classifiers":[
        {
            "category":"Building & Trades",
            "subcategory":"Equipment Rental",
            "type":"Services"
        }
    ],
    "sg:phone":"+1 660 582 4373",
    "sg:postcode":"64468",
    "sg:province":"MO",
    "sg:tags":[
        "yard",
        "leasing",
        "store"
    ],
    "wof:name":"Whan Rentals",
    "wof:placetype":"venue"
},
  "geometry": {"coordinates":[-94.884033,40.363066],"type":"Point"}
}