{
  "type": "Feature",
  "properties": {
    "iso:country":"US",
    "sg:address":"3442 State Rd H",
    "sg:city":"Fulton",
    "sg:classifiers":[
        {
            "category":"Building & Trades",
            "subcategory":"Construction",
            "type":"Services"
        }
    ],
    "sg:phone":"+1 573 642 1020",
    "sg:postcode":"65251",
    "sg:province":"MO",
    "sg:tags":[
        "dry wall",
        "contractor"
    ],
    "wof:name":"RLM Plaster & Drywall",
    "wof:placetype":"venue"
},
  "geometry": {"coordinates":[-92.048795,38.81119],"type":"Point"}
}