{
  "type": "Feature",
  "properties": {
    "iso:country":"US",
    "sg:address":"28263 Co Rd W",
    "sg:city":"Meadville",
    "sg:classifiers":[
        {
            "category":"Organizations",
            "subcategory":"Religious Organization",
            "type":"Services"
        }
    ],
    "sg:phone":"+1 660 938 4445",
    "sg:postcode":"64659",
    "sg:province":"MO",
    "wof:name":"Parsonage",
    "wof:placetype":"venue"
},
  "geometry": {"coordinates":[-93.03156300000001,39.955315],"type":"Point"}
}