{
  "type": "Feature",
  "properties": {
    "iso:country":"US",
    "sg:address":"3501 SW Lakefront Ln W",
    "sg:city":"St Joseph",
    "sg:classifiers":[
        {
            "category":"Autos & Motor Vehicles",
            "subcategory":"Boat Sales",
            "type":"Retail Goods"
        }
    ],
    "sg:phone":"+1 816 238 5142",
    "sg:postcode":"64504",
    "sg:province":"MO",
    "sg:tags":[
        "outboard"
    ],
    "wof:name":"St Joseph Outboard Motor",
    "wof:placetype":"venue"
},
  "geometry": {"coordinates":[-94.94577099999999,39.722749],"type":"Point"}
}