{
  "type": "Feature",
  "properties": {
    "iso:country":"US",
    "sg:address":"859 Wellesley Terrace Ln",
    "sg:city":"Chesterfield",
    "sg:classifiers":[
        {
            "category":"Real Estate",
            "subcategory":"Real Estate Agent",
            "type":"Services"
        }
    ],
    "sg:phone":"+1 636 537 3060",
    "sg:postcode":"63017",
    "sg:province":"MO",
    "wof:name":"David Batty",
    "wof:placetype":"venue"
},
  "geometry": {"coordinates":[-90.550611,38.662149],"type":"Point"}
}