{
  "type": "Feature",
  "properties": {
    "iso:country":"US",
    "sg:address":"4859 S Franwood Pl",
    "sg:city":"Springfield",
    "sg:classifiers":[
        {
            "category":"Manufacturing",
            "subcategory":"Buildings",
            "type":"Manufacturing & Wholesale Goods"
        },
        {
            "category":"Building & Trades",
            "subcategory":"Construction",
            "type":"Services"
        }
    ],
    "sg:phone":"+1 417 883 8642",
    "sg:postcode":"65810",
    "sg:province":"MO",
    "sg:tags":[
        "home",
        "builder",
        "contractor"
    ],
    "wof:name":"Boyd Building Company",
    "wof:placetype":"venue"
},
  "geometry": {"coordinates":[-93.354238,37.125997],"type":"Point"}
}