{
  "type": "Feature",
  "properties": {
    "addr:full":"3447 Bright Hope Ln Auxvasse MO 65231",
    "addr:housenumber":"3447",
    "addr:postcode":"65231",
    "addr:street":"Bright Hope Ln",
    "iso:country":"US",
    "sg:address":"3447 Bright Hope Ln",
    "sg:city":"Auxvasse",
    "sg:classifiers":[
        {
            "category":"Building & Trades",
            "subcategory":"Construction",
            "type":"Services"
        }
    ],
    "sg:phone":"+1 573 387 4652",
    "sg:postcode":"65231",
    "sg:province":"MO",
    "sg:tags":[
        "general",
        "contractor"
    ],
    "wof:name":"Cornerstone Construction",
    "wof:placetype":"venue"
},
  "geometry": {"coordinates":[-92.04199,39.031569],"type":"Point"}
}