{
  "type": "Feature",
  "properties": {
    "iso:country":"US",
    "sg:address":"6104 E 150th Ter",
    "sg:city":"Grandview",
    "sg:classifiers":[
        {
            "category":"Building & Trades",
            "subcategory":"Construction",
            "type":"Services"
        }
    ],
    "sg:phone":"+1 816 509 3357",
    "sg:postcode":"64030",
    "sg:province":"MO",
    "sg:tags":[
        "house"
    ],
    "wof:name":"American Decor",
    "wof:placetype":"venue"
},
  "geometry": {"coordinates":[-94.521506,38.85195],"type":"Point"}
}