{
  "type": "Feature",
  "properties": {
    "iso:country":"US",
    "sg:address":"1310 Castle Dr",
    "sg:city":"Kirksville",
    "sg:classifiers":[
        {
            "category":"Building & Trades",
            "subcategory":"Plumbing",
            "type":"Services"
        }
    ],
    "sg:phone":"+1 660 665 1061",
    "sg:postcode":"63501",
    "sg:province":"MO",
    "sg:tags":[
        "contractor"
    ],
    "wof:name":"C & I Home Service LLC",
    "wof:placetype":"venue"
},
  "geometry": {"coordinates":[-92.566506,40.207512],"type":"Point"}
}