{
  "type": "Feature",
  "properties": {
    "iso:country":"US",
    "sg:address":"207 S Broadway St",
    "sg:city":"Poplar Bluff",
    "sg:classifiers":[
        {
            "category":"Health Services",
            "subcategory":"Hospital",
            "type":"Services"
        }
    ],
    "sg:phone":"+1 573 785 4176",
    "sg:postcode":"63901",
    "sg:province":"MO",
    "sg:tags":[
        "specialty"
    ],
    "wof:name":"Correctional Counseling Inc",
    "wof:placetype":"venue"
},
  "geometry": {"coordinates":[-90.39415700000001,36.755664],"type":"Point"}
}