{
  "type": "Feature",
  "properties": {
    "iso:country":"US",
    "sg:address":"7712 E 233rd St",
    "sg:city":"Peculiar",
    "sg:classifiers":[
        {
            "category":"Building & Trades",
            "subcategory":"Landscaping Services",
            "type":"Services"
        }
    ],
    "sg:phone":"+1 816 885 2669",
    "sg:postcode":"64078",
    "sg:province":"MO",
    "sg:tags":[
        "landscape",
        "contractor"
    ],
    "wof:name":"Avenue Lawn Care",
    "wof:placetype":"venue"
},
  "geometry": {"coordinates":[-94.51246,38.70117],"type":"Point"}
}