{
  "type": "Feature",
  "properties": {
    "iso:country":"US",
    "sg:address":"10303 E 87 St",
    "sg:city":"Kansas City",
    "sg:classifiers":[
        {
            "category":"Building & Trades",
            "subcategory":"Construction",
            "type":"Services"
        }
    ],
    "sg:phone":"+1 816 356 4081",
    "sg:postcode":"64138",
    "sg:province":"MO",
    "sg:tags":[
        "box",
        "contractor",
        "concrete",
        "sewer",
        "storm",
        "catch",
        "basin",
        "culvert"
    ],
    "wof:name":"Corlew Construction Co Inc",
    "wof:placetype":"venue"
},
  "geometry": {"coordinates":[-94.463729,38.965007],"type":"Point"}
}