{
  "type": "Feature",
  "properties": {
    "iso:country":"US",
    "sg:address":"905 Main St",
    "sg:city":"Trenton",
    "sg:classifiers":[
        {
            "category":"Shopping",
            "subcategory":"Used Merchandise",
            "type":"Retail Goods"
        }
    ],
    "sg:phone":"+1 660 359 3441",
    "sg:postcode":"64683",
    "sg:province":"MO",
    "sg:tags":[
        "shop",
        "thrift"
    ],
    "wof:name":"Salvation Army Thrift Store",
    "wof:placetype":"venue"
},
  "geometry": {"coordinates":[-93.61751099999999,40.075458],"type":"Point"}
}