{
  "type": "Feature",
  "properties": {
    "iso:country":"US",
    "sg:address":"7014 E Truman Rd",
    "sg:city":"Kansas City",
    "sg:classifiers":[
        {
            "category":"Building & Trades",
            "subcategory":"Landscaping Services",
            "type":"Services"
        }
    ],
    "sg:phone":"+1 816 241 7766",
    "sg:postcode":"64126",
    "sg:province":"MO",
    "wof:name":"S & S Lawn Service Inc",
    "wof:placetype":"venue"
},
  "geometry": {"coordinates":[-94.497422,39.093596],"type":"Point"}
}