{
  "type": "Feature",
  "properties": {
    "iso:country":"US",
    "sg:address":"203 N Walnut St",
    "sg:city":"Willow Springs",
    "sg:classifiers":[
        {
            "category":"Professional",
            "subcategory":"Accounting & Tax Preparation",
            "type":"Services"
        }
    ],
    "sg:phone":"+1 417 469 3636",
    "sg:postcode":"65793",
    "sg:province":"MO",
    "wof:name":"Matthew L James CPA",
    "wof:placetype":"venue"
},
  "geometry": {"coordinates":[-91.968076,36.99161],"type":"Point"}
}