{
  "type": "Feature",
  "properties": {
    "iso:country":"US",
    "sg:address":"203 Chesterfield Industrial Blvd",
    "sg:city":"Chesterfield",
    "sg:classifiers":[
        {
            "category":"Professional",
            "subcategory":"Management & Consulting",
            "type":"Services"
        },
        {
            "category":"Manufacturing",
            "subcategory":"Tools & Machinery",
            "type":"Manufacturing & Wholesale Goods"
        }
    ],
    "sg:phone":"+1 636 536 0282",
    "sg:postcode":"63005",
    "sg:province":"MO",
    "sg:tags":[
        "machine",
        "marketing",
        "mfg",
        "consultant"
    ],
    "wof:name":"R L Marketing",
    "wof:placetype":"venue"
},
  "geometry": {"coordinates":[-90.62214400000001,38.666062],"type":"Point"}
}