{
  "type": "Feature",
  "properties": {
    "iso:country":"US",
    "sg:address":"12884 Tammy Kay Dr",
    "sg:city":"Sappington",
    "sg:classifiers":[
        {
            "category":"Social Services",
            "subcategory":"Child Care",
            "type":"Services"
        }
    ],
    "sg:phone":"+1 314 849 0207",
    "sg:postcode":"63128",
    "sg:province":"MO",
    "wof:name":"Get Well Ctr",
    "wof:placetype":"venue"
},
  "geometry": {"coordinates":[-90.383366,38.498861],"type":"Point"}
}