{
  "type": "Feature",
  "properties": {
    "iso:country":"US",
    "sg:address":"12082 Ladue Rd",
    "sg:city":"Saint Louis",
    "sg:classifiers":[
        {
            "category":"Real Estate",
            "subcategory":"Real Estate Agent",
            "type":"Services"
        }
    ],
    "sg:phone":"+1 314 576 5228",
    "sg:postcode":"63141",
    "sg:province":"MO",
    "wof:name":"William L Watts Realtor",
    "wof:placetype":"venue"
},
  "geometry": {"coordinates":[-90.449208,38.655418],"type":"Point"}
}