{
  "type": "Feature",
  "properties": {
    "iso:country":"US",
    "sg:address":"17692 Woods Dr",
    "sg:city":"Boonville",
    "sg:classifiers":[
        {
            "category":"Personal",
            "subcategory":"Barber",
            "type":"Services"
        }
    ],
    "sg:phone":"+1 660 882 7389",
    "sg:postcode":"65233",
    "sg:province":"MO",
    "sg:tags":[
        "shop"
    ],
    "wof:name":"Spring Street Barbershop",
    "wof:placetype":"venue"
},
  "geometry": {"coordinates":[-92.763098,38.947173],"type":"Point"}
}