{
  "type": "Feature",
  "properties": {
    "iso:country":"US",
    "sg:address":"1026 Euclid Blvd",
    "sg:city":"Carthage",
    "sg:classifiers":[
        {
            "category":"Personal",
            "subcategory":"Beauty Salon",
            "type":"Services"
        }
    ],
    "sg:phone":"+1 417 358 7780",
    "sg:postcode":"64836",
    "sg:province":"MO",
    "sg:tags":[
        "shop"
    ],
    "wof:name":"Judy's Beauty Shop",
    "wof:placetype":"venue"
},
  "geometry": {"coordinates":[-94.29894400000001,37.160556],"type":"Point"}
}