{
  "type": "Feature",
  "properties": {
    "iso:country":"US",
    "sg:address":"500 Medical Dr",
    "sg:city":"Wentzville",
    "sg:classifiers":[
        {
            "category":"Professional",
            "type":"Services"
        }
    ],
    "sg:phone":"+1 636 639 9885",
    "sg:postcode":"63385",
    "sg:province":"MO",
    "sg:tags":[
        "establishment"
    ],
    "wof:name":"Lca",
    "wof:placetype":"venue"
},
  "geometry": {"coordinates":[-90.881158,38.823315],"type":"Point"}
}