{
  "type": "Feature",
  "properties": {
    "iso:country":"US",
    "sg:address":"301 Murphy Dr",
    "sg:city":"Pacific",
    "sg:classifiers":[
        {
            "category":"Building & Trades",
            "subcategory":"Electrical",
            "type":"Services"
        }
    ],
    "sg:phone":"+1 636 257 2845",
    "sg:postcode":"63069",
    "sg:province":"MO",
    "sg:tags":[
        "electrician"
    ],
    "wof:name":"Pacific Electrical Contractors, Inc",
    "wof:placetype":"venue"
},
  "geometry": {"coordinates":[-90.795273,38.443901],"type":"Point"}
}