{
  "type": "Feature",
  "properties": {
    "iso:country":"US",
    "sg:address":"1 Summit Ct",
    "sg:city":"Fenton",
    "sg:classifiers":[
        {
            "category":"Retail",
            "subcategory":"Laundry & Dry Cleaning",
            "type":"Services"
        }
    ],
    "sg:phone":"+1 636 343 1620",
    "sg:postcode":"63026",
    "sg:province":"MO",
    "wof:name":"Worley Rug & Upholstery",
    "wof:placetype":"venue"
},
  "geometry": {"coordinates":[-90.47770800000001,38.510388],"type":"Point"}
}