{
  "type": "Feature",
  "properties": {
    "iso:country":"US",
    "sg:address":"9423 Sappington Rd",
    "sg:city":"Sappington",
    "sg:classifiers":[
        {
            "category":"Wholesale",
            "subcategory":"Stationery",
            "type":"Manufacturing & Wholesale Goods"
        }
    ],
    "sg:phone":"+1 314 843 6800",
    "sg:postcode":"63126",
    "sg:province":"MO",
    "sg:tags":[
        "business",
        "form",
        "system"
    ],
    "wof:name":"CMF Business Forms & Systems",
    "wof:placetype":"venue"
},
  "geometry": {"coordinates":[-90.38011400000001,38.535736],"type":"Point"}
}