{
  "type": "Feature",
  "properties": {
    "iso:country":"US",
    "sg:address":"14280 State Hwy 96",
    "sg:city":"Miller",
    "sg:classifiers":[
        {
            "category":"Manufacturing",
            "subcategory":"Petroleum Products",
            "type":"Manufacturing & Wholesale Goods"
        }
    ],
    "sg:phone":"+1 417 452 3229",
    "sg:postcode":"65707",
    "sg:province":"MO",
    "sg:tags":[
        "asphalt",
        "mfg"
    ],
    "wof:name":"Coastal Emulsions",
    "wof:placetype":"venue"
},
  "geometry": {"coordinates":[-93.795956,37.188779],"type":"Point"}
}