{
  "type": "Feature",
  "properties": {
    "iso:country":"US",
    "sg:address":"1203 Forum Dr",
    "sg:city":"Rolla",
    "sg:classifiers":[
        {
            "category":"Social Services",
            "type":"Services"
        }
    ],
    "sg:phone":"+1 573 368 5770",
    "sg:postcode":"65401",
    "sg:province":"MO",
    "sg:tags":[
        "counseling"
    ],
    "wof:name":"Ann Clark Counseling Service",
    "wof:placetype":"venue"
},
  "geometry": {"coordinates":[-91.752341,37.952627],"type":"Point"}
}