{
  "type": "Feature",
  "properties": {
    "iso:country":"US",
    "sg:address":"1809 E Sadie Ln",
    "sg:city":"Joplin",
    "sg:classifiers":[
        {
            "category":"Professional",
            "type":"Services"
        }
    ],
    "sg:phone":"+1 417 624 8800",
    "sg:postcode":"64801",
    "sg:province":"MO",
    "sg:tags":[
        "transportation"
    ],
    "wof:name":"Cw Freight Brokerage Inc",
    "wof:placetype":"venue"
},
  "geometry": {"coordinates":[-94.493765,37.117062],"type":"Point"}
}