{
  "type": "Feature",
  "properties": {
    "iso:country":"US",
    "sg:address":"2619 Cherokee St",
    "sg:city":"St Louis",
    "sg:classifiers":[
        {
            "category":"Personal",
            "subcategory":"Beauty Salon",
            "type":"Services"
        }
    ],
    "sg:phone":"+1 314 664 6606",
    "sg:postcode":"63118",
    "sg:province":"MO",
    "wof:name":"Milo Hair Braiding",
    "wof:placetype":"venue"
},
  "geometry": {"coordinates":[-90.226463,38.593459],"type":"Point"}
}