{
  "type": "Feature",
  "properties": {
    "iso:country":"US",
    "sg:address":"4537 Liberty St",
    "sg:city":"Kansas City",
    "sg:classifiers":[
        {
            "category":"Professional",
            "type":"Services"
        }
    ],
    "sg:phone":"+1 816 561 9665",
    "sg:postcode":"64111",
    "sg:province":"MO",
    "wof:name":"Brostoski Roseann Lamartina",
    "wof:placetype":"venue"
},
  "geometry": {"coordinates":[-94.603255,39.045162],"type":"Point"}
}