{
  "type": "Feature",
  "properties": {
    "iso:country":"US",
    "sg:address":"1006 Westport Rd",
    "sg:city":"Kansas City",
    "sg:classifiers":[
        {
            "category":"Professional",
            "subcategory":"Secretarial Services",
            "type":"Services"
        }
    ],
    "sg:phone":"+1 816 931 2276",
    "sg:postcode":"64111",
    "sg:province":"MO",
    "sg:tags":[
        "reporting",
        "court"
    ],
    "wof:name":"Final Draft Secretarial Svc",
    "wof:placetype":"venue"
},
  "geometry": {"coordinates":[-94.598263,39.050101],"type":"Point"}
}