{
  "type": "Feature",
  "properties": {
    "iso:country":"US",
    "sg:address":"9420 Lackland Rd",
    "sg:city":"St Louis",
    "sg:classifiers":[
        {
            "category":"Building & Trades",
            "subcategory":"Landscaping Services",
            "type":"Services"
        }
    ],
    "sg:phone":"+1 314 429 4829",
    "sg:postcode":"63114",
    "sg:province":"MO",
    "sg:tags":[
        "landscape",
        "contractor"
    ],
    "wof:name":"Perales Land Maintenance Inc",
    "wof:placetype":"venue"
},
  "geometry": {"coordinates":[-90.362926,38.70052],"type":"Point"}
}