{
  "type": "Feature",
  "properties": {
    "iso:country":"US",
    "sg:address":"2917 S Main St",
    "sg:city":"Joplin",
    "sg:classifiers":[
        {
            "category":"Personal",
            "subcategory":"Beauty Salon",
            "type":"Services"
        }
    ],
    "sg:phone":"+1 417 782 7447",
    "sg:postcode":"64804",
    "sg:province":"MO",
    "wof:name":"Spalon Japho",
    "wof:placetype":"venue"
},
  "geometry": {"coordinates":[-94.514644,37.057577],"type":"Point"}
}