{
  "type": "Feature",
  "properties": {
    "iso:country":"US",
    "sg:address":"3909 E 20th St",
    "sg:city":"Joplin",
    "sg:classifiers":[
        {
            "category":"Wholesale",
            "subcategory":"Machinery & Supplies",
            "type":"Manufacturing & Wholesale Goods"
        }
    ],
    "sg:phone":"+1 417 623 2877",
    "sg:postcode":"64801",
    "sg:province":"MO",
    "sg:tags":[
        "thrust",
        "bearing",
        "ball",
        "linear",
        "roller"
    ],
    "wof:name":"Applied Industrial Tech Inc",
    "wof:placetype":"venue"
},
  "geometry": {"coordinates":[-94.46126099999999,37.069415],"type":"Point"}
}