{
  "type": "Feature",
  "properties": {
    "iso:country":"US",
    "sg:address":"317 Ozark Ave",
    "sg:city":"Cabool",
    "sg:classifiers":[
        {
            "category":"Autos & Motor Vehicles",
            "subcategory":"Fuel & Gas Station",
            "type":"Retail Goods"
        },
        {
            "category":"Food & Beverages",
            "subcategory":"Groceries & Convenience Stores",
            "type":"Retail Goods"
        }
    ],
    "sg:phone":"+1 417 962 4393",
    "sg:postcode":"65689",
    "sg:province":"MO",
    "sg:website":"http://www.texaco.com/",
    "wof:name":"Texaco",
    "wof:placetype":"venue"
},
  "geometry": {"coordinates":[-92.097174,37.123748],"type":"Point"}
}