{
  "type": "Feature",
  "properties": {
    "iso:country":"US",
    "sg:address":"1420 S Glenstone Ave",
    "sg:city":"Springfield",
    "sg:classifiers":[
        {
            "category":"Shopping",
            "subcategory":"Tobacco",
            "type":"Retail Goods"
        }
    ],
    "sg:phone":"+1 417 890 1978",
    "sg:postcode":"65804",
    "sg:province":"MO",
    "sg:tags":[
        "product"
    ],
    "wof:name":"Tobacco World",
    "wof:placetype":"venue"
},
  "geometry": {"coordinates":[-93.262156,37.188377],"type":"Point"}
}