{
  "type": "Feature",
  "properties": {
    "iso:country":"US",
    "sg:address":"2822 Gladwood Dr",
    "sg:city":"St Louis",
    "sg:classifiers":[
        {
            "category":"Personal",
            "type":"Services"
        }
    ],
    "sg:phone":"+1 314 221 0047",
    "sg:postcode":"63129",
    "sg:province":"MO",
    "sg:tags":[
        "wedding",
        "chapel"
    ],
    "wof:name":"Anyplace Wedding Svc",
    "wof:placetype":"venue"
},
  "geometry": {"coordinates":[-90.31778,38.481001],"type":"Point"}
}