{
  "type": "Feature",
  "properties": {
    "iso:country":"US",
    "sg:address":"5443 E Bennett St",
    "sg:city":"Springfield",
    "sg:classifiers":[
        {
            "category":"Professional",
            "subcategory":"Management & Consulting",
            "type":"Services"
        }
    ],
    "sg:phone":"+1 417 875 1015",
    "sg:postcode":"65809",
    "sg:province":"MO",
    "sg:tags":[
        "consultant",
        "telecommunication"
    ],
    "wof:name":"Five Hills Co",
    "wof:placetype":"venue"
},
  "geometry": {"coordinates":[-93.179113,37.186136],"type":"Point"}
}