{
  "type": "Feature",
  "properties": {
    "iso:country":"US",
    "sg:address":"3305 Shady Bend Dr",
    "sg:city":"Independence",
    "sg:classifiers":[
        {
            "category":"Professional",
            "subcategory":"Advertising",
            "type":"Services"
        }
    ],
    "sg:phone":"+1 816 836 8890",
    "sg:postcode":"64052",
    "sg:province":"MO",
    "sg:tags":[
        "station",
        "radio",
        "representative"
    ],
    "wof:name":"Jch Inc-WLVJ",
    "wof:placetype":"venue"
},
  "geometry": {"coordinates":[-94.434704,39.059806],"type":"Point"}
}