{
  "type": "Feature",
  "properties": {
    "iso:country":"US",
    "sg:address":"1422 Delmar Blvd",
    "sg:city":"Saint Louis",
    "sg:classifiers":[
        {
            "category":"Retail",
            "subcategory":"Auto Repair",
            "type":"Services"
        }
    ],
    "sg:phone":"+1 314 436 2788",
    "sg:postcode":"63103",
    "sg:province":"MO",
    "sg:tags":[
        "repairing",
        "automobile"
    ],
    "wof:name":"St Louis Auto & Truck Repair",
    "wof:placetype":"venue"
},
  "geometry": {"coordinates":[-90.199303,38.634102],"type":"Point"}
}