{
  "type": "Feature",
  "properties": {
    "iso:country":"US",
    "sg:address":"415 N High St",
    "sg:city":"Neosho",
    "sg:classifiers":[
        {
            "category":"Social Services",
            "type":"Services"
        }
    ],
    "sg:phone":"+1 417 455 9393",
    "sg:postcode":"64850",
    "sg:province":"MO",
    "sg:tags":[
        "shelter",
        "homeless"
    ],
    "wof:name":"Neosho Area Compassionate",
    "wof:placetype":"venue"
},
  "geometry": {"coordinates":[-94.37306,36.873782],"type":"Point"}
}