{
  "type": "Feature",
  "properties": {
    "iso:country":"US",
    "sg:address":"205 N 5th St",
    "sg:city":"St Charles",
    "sg:classifiers":[
        {
            "category":"Personal",
            "type":"Services"
        }
    ],
    "sg:phone":"+1 636 946 1030",
    "sg:postcode":"63301",
    "sg:province":"MO",
    "sg:tags":[
        "control",
        "health",
        "weight"
    ],
    "wof:name":"Hypnotic Solutions",
    "wof:placetype":"venue"
},
  "geometry": {"coordinates":[-90.485281,38.784468],"type":"Point"}
}