{
  "type": "Feature",
  "properties": {
    "iso:country":"US",
    "sg:address":"23701 Dresden Rd",
    "sg:city":"La Monte",
    "sg:classifiers":[
        {
            "category":"Professional",
            "type":"Services"
        }
    ],
    "sg:phone":"+1 660 829 1915",
    "sg:postcode":"65337",
    "sg:province":"MO",
    "wof:name":"Cindy D Peck",
    "wof:placetype":"venue"
},
  "geometry": {"coordinates":[-93.34596999999999,38.728391],"type":"Point"}
}