{
  "type": "Feature",
  "properties": {
    "iso:country":"US",
    "sg:address":"2125 Cherokee St",
    "sg:city":"Saint Louis",
    "sg:classifiers":[
        {
            "category":"Shopping",
            "subcategory":"Antiques",
            "type":"Retail Goods"
        }
    ],
    "sg:phone":"+1 314 776 5900",
    "sg:postcode":"63118",
    "sg:province":"MO",
    "wof:name":"China Finders",
    "wof:placetype":"venue"
},
  "geometry": {"coordinates":[-90.222307,38.593048],"type":"Point"}
}