{
  "type": "Feature",
  "properties": {
    "iso:country":"US",
    "sg:address":"16227 Westwoods Business Park",
    "sg:city":"Ellisville",
    "sg:classifiers":[
        {
            "category":"Wholesale",
            "subcategory":"Stationery",
            "type":"Manufacturing & Wholesale Goods"
        }
    ],
    "sg:phone":"+1 636 591 0003",
    "sg:postcode":"63021",
    "sg:province":"MO",
    "sg:tags":[
        "business",
        "form",
        "system"
    ],
    "wof:name":"Home & Business Systems Inc",
    "wof:placetype":"venue"
},
  "geometry": {"coordinates":[-90.59913899999999,38.584769],"type":"Point"}
}