{
  "type": "Feature",
  "properties": {
    "iso:country":"US",
    "sg:address":"37 Produce Row",
    "sg:city":"Saint Louis",
    "sg:classifiers":[
        {
            "category":"Social Services",
            "type":"Services"
        }
    ],
    "sg:phone":"+1 314 231 7482",
    "sg:postcode":"63102",
    "sg:province":"MO",
    "wof:name":"Santas Helpers",
    "wof:placetype":"venue"
},
  "geometry": {"coordinates":[-90.189026,38.652938],"type":"Point"}
}