{
  "type": "Feature",
  "properties": {
    "iso:country":"US",
    "sg:address":"23979 US Hwy 136",
    "sg:city":"Tarkio",
    "sg:classifiers":[
        {
            "category":"Communications",
            "subcategory":"Radio Station",
            "type":"Services"
        }
    ],
    "sg:phone":"+1 660 736 4321",
    "sg:postcode":"64491",
    "sg:province":"MO",
    "sg:tags":[
        "company",
        "broadcasting"
    ],
    "wof:name":"KRSS",
    "wof:placetype":"venue"
},
  "geometry": {"coordinates":[-95.40084899999999,40.423142],"type":"Point"}
}