{
  "type": "Feature",
  "properties": {
    "iso:country":"US",
    "sg:address":"116 E Jefferson St",
    "sg:city":"Kirksville",
    "sg:classifiers":[
        {
            "category":"Professional",
            "subcategory":"Computer Services",
            "type":"Services"
        }
    ],
    "sg:phone":"+1 660 627 7455",
    "sg:postcode":"63501",
    "sg:province":"MO",
    "sg:tags":[
        "repair"
    ],
    "wof:name":"Xtreme Technologies & Comm",
    "wof:placetype":"venue"
},
  "geometry": {"coordinates":[-92.583027,40.192948],"type":"Point"}
}