{
  "type": "Feature",
  "properties": {
    "iso:country":"US",
    "sg:address":"306 Sherman St",
    "sg:city":"Green City",
    "sg:classifiers":[
        {
            "category":"Recreation",
            "type":"Entertainment"
        }
    ],
    "sg:phone":"+1 660 874 4380",
    "sg:postcode":"63545",
    "sg:province":"MO",
    "sg:tags":[
        "membership"
    ],
    "wof:name":"Green City Pool Club",
    "wof:placetype":"venue"
},
  "geometry": {"coordinates":[-92.952656,40.27078],"type":"Point"}
}