{
  "type": "Feature",
  "properties": {
    "iso:country":"US",
    "sg:address":"3815 Lemay Ferry Rd",
    "sg:city":"St Louis",
    "sg:classifiers":[
        {
            "category":"Autos & Motor Vehicles",
            "subcategory":"Automobile Sales",
            "type":"Retail Goods"
        }
    ],
    "sg:phone":"+1 314 894 2311",
    "sg:postcode":"63125",
    "sg:province":"MO",
    "sg:tags":[
        "car",
        "dealer"
    ],
    "wof:name":"Dave Sinclair Oldsmobile-KIA",
    "wof:placetype":"venue"
},
  "geometry": {"coordinates":[-90.324224,38.507629],"type":"Point"}
}