{
  "type": "Feature",
  "properties": {
    "iso:country":"US",
    "sg:address":"206 N Garth Ave",
    "sg:city":"Columbia",
    "sg:classifiers":[
        {
            "category":"Social Services",
            "type":"Services"
        }
    ],
    "sg:phone":"+1 573 268 8577",
    "sg:postcode":"65203",
    "sg:province":"MO",
    "wof:name":"The Cross Roads",
    "wof:placetype":"venue"
},
  "geometry": {"coordinates":[-92.338911,38.954426],"type":"Point"}
}