{
  "type": "Feature",
  "properties": {
    "iso:country":"US",
    "sg:address":"591 W State Highway 164",
    "sg:city":"Steele",
    "sg:classifiers":[
        {
            "category":"Farming",
            "subcategory":"Farm",
            "type":"Manufacturing & Wholesale Goods"
        }
    ],
    "sg:phone":"+1 573 695 3159",
    "sg:postcode":"63877",
    "sg:province":"MO",
    "wof:name":"Southern Farm Co Inc",
    "wof:placetype":"venue"
},
  "geometry": {"coordinates":[-89.857762,36.084966],"type":"Point"}
}