{
  "type": "Feature",
  "properties": {
    "addr:full":"417 E Spring St Boonville MO 65233",
    "addr:housenumber":"417",
    "addr:postcode":"65233",
    "addr:street":"E Spring St",
    "iso:country":"US",
    "sg:address":"417 E Spring St",
    "sg:city":"Boonville",
    "sg:classifiers":[
        {
            "category":"Fast Food",
            "type":"Food & Drink"
        },
        {
            "category":"Restaurant",
            "type":"Food & Drink"
        },
        {
            "category":"Professional",
            "type":"Services"
        }
    ],
    "sg:phone":"+1 660 882 2001",
    "sg:postcode":"65233",
    "sg:province":"MO",
    "sg:tags":[
        "delivery",
        "take",
        "pizza"
    ],
    "sg:website":"http://www.dominospizza.com",
    "wof:name":"Domino's Pizza",
    "wof:placetype":"venue"
},
  "geometry": {"coordinates":[-92.745097,38.975251],"type":"Point"}
}