{
  "type": "Feature",
  "properties": {
    "iso:country":"US",
    "sg:address":"1515 S Morley St",
    "sg:city":"Moberly",
    "sg:classifiers":[
        {
            "category":"Home & Garden",
            "subcategory":"Building Materials",
            "type":"Retail Goods"
        }
    ],
    "sg:phone":"+1 660 263 4527",
    "sg:postcode":"65270",
    "sg:province":"MO",
    "wof:name":"Dragonfyre Art Glass",
    "wof:placetype":"venue"
},
  "geometry": {"coordinates":[-92.43440699999999,39.399167],"type":"Point"}
}