{
  "type": "Feature",
  "properties": {
    "iso:country":"US",
    "sg:address":"1120 Olivette Executive Pkwy",
    "sg:city":"St Louis",
    "sg:classifiers":[
        {
            "category":"Professional",
            "subcategory":"Lawyer & Legal Services",
            "type":"Services"
        }
    ],
    "sg:phone":"+1 314 997 7733",
    "sg:postcode":"63132",
    "sg:province":"MO",
    "sg:tags":[
        "attorney"
    ],
    "sg:website":"www.tlflaw.com",
    "wof:name":"Thomeczek Law Firm",
    "wof:placetype":"venue"
},
  "geometry": {"coordinates":[-90.37229499999999,38.675727],"type":"Point"}
}