{
  "type": "Feature",
  "properties": {
    "iso:country":"US",
    "sg:address":"415 N Main St",
    "sg:city":"Chaffee",
    "sg:classifiers":[
        {
            "category":"Wholesale",
            "subcategory":"Auto Parts",
            "type":"Manufacturing & Wholesale Goods"
        }
    ],
    "sg:phone":"+1 573 887 3526",
    "sg:postcode":"63740",
    "sg:province":"MO",
    "sg:tags":[
        "automobile",
        "supply"
    ],
    "wof:name":"Auto Tire & Parts Co",
    "wof:placetype":"venue"
},
  "geometry": {"coordinates":[-89.653396,37.183511],"type":"Point"}
}