{
  "type": "Feature",
  "properties": {
    "iso:country":"US",
    "sg:address":"1400 S Outer Rd E",
    "sg:city":"Eureka",
    "sg:classifiers":[
        {
            "category":"Freight",
            "type":"Transportation"
        }
    ],
    "sg:phone":"+1 636 938 5777",
    "sg:postcode":"63025",
    "sg:province":"MO",
    "sg:tags":[
        "operator",
        "automobile",
        "used",
        "trucking"
    ],
    "wof:name":"Kociela Enterprises Inc",
    "wof:placetype":"venue"
},
  "geometry": {"coordinates":[-90.611408,38.502479],"type":"Point"}
}