{
  "type": "Feature",
  "properties": {
    "iso:country":"US",
    "sg:address":"275 Grail Castle Ct",
    "sg:city":"St Charles",
    "sg:classifiers":[
        {
            "category":"Building & Trades",
            "subcategory":"Construction",
            "type":"Services"
        }
    ],
    "sg:phone":"+1 636 926 9938",
    "sg:postcode":"63304",
    "sg:province":"MO",
    "sg:tags":[
        "home",
        "builder"
    ],
    "wof:name":"Camelot Subdivision",
    "wof:placetype":"venue"
},
  "geometry": {"coordinates":[-90.653081,38.713278],"type":"Point"}
}