{
  "type": "Feature",
  "properties": {
    "iso:country":"US",
    "sg:address":"9415 Co Rd 7670",
    "sg:city":"Pottersville",
    "sg:classifiers":[
        {
            "category":"Organizations",
            "subcategory":"Religious Organization",
            "type":"Services"
        }
    ],
    "sg:phone":"+1 417 257 7200",
    "sg:postcode":"65790",
    "sg:province":"MO",
    "sg:tags":[
        "church"
    ],
    "wof:name":"Trinity Missionary Baptist Ch",
    "wof:placetype":"venue"
},
  "geometry": {"coordinates":[-92.092142,36.709254],"type":"Point"}
}