{
  "type": "Feature",
  "properties": {
    "iso:country":"US",
    "sg:address":"587 Spragues Mill Dr",
    "sg:city":"Ballwin",
    "sg:classifiers":[
        {
            "category":"Building & Trades",
            "subcategory":"Landscaping Services",
            "type":"Services"
        }
    ],
    "sg:phone":"+1 636 256 9735",
    "sg:postcode":"63011",
    "sg:province":"MO",
    "sg:tags":[
        "landscape"
    ],
    "wof:name":"Distinqt Land Maintenance",
    "wof:placetype":"venue"
},
  "geometry": {"coordinates":[-90.54751400000001,38.597844],"type":"Point"}
}