{
  "type": "Feature",
  "properties": {
    "iso:country":"US",
    "sg:address":"5051 W Four Ridge Rd",
    "sg:city":"House Springs",
    "sg:classifiers":[
        {
            "category":"Food & Beverages",
            "subcategory":"Groceries & Convenience Stores",
            "type":"Retail Goods"
        }
    ],
    "sg:phone":"+1 636 948 3111",
    "sg:postcode":"63051",
    "sg:province":"MO",
    "wof:name":"Carrows Market",
    "wof:placetype":"venue"
},
  "geometry": {"coordinates":[-90.500167,38.393717],"type":"Point"}
}