{
  "type": "Feature",
  "properties": {
    "iso:country":"US",
    "sg:address":"10110 E 63rd St",
    "sg:city":"Raytown",
    "sg:classifiers":[
        {
            "category":"Insurance",
            "subcategory":"Insurance Agent",
            "type":"Services"
        },
        {
            "category":"Insurance",
            "subcategory":"Hazard Insurance",
            "type":"Services"
        },
        {
            "category":"Insurance",
            "subcategory":"Title Insurance",
            "type":"Services"
        },
        {
            "category":"Insurance",
            "subcategory":"Life Insurance",
            "type":"Services"
        }
    ],
    "sg:phone":"+1 816 356 2223",
    "sg:postcode":"64133",
    "sg:province":"MO",
    "sg:tags":[
        "business",
        "auto",
        "commercial",
        "homeowner",
        "property",
        "casualty"
    ],
    "sg:website":"http://www.farmersagent.com/trigot/",
    "wof:name":"Thomas Rigot - Farmers Insurance",
    "wof:placetype":"venue"
},
  "geometry": {"coordinates":[-94.461512,39.008714],"type":"Point"}
}