{
  "type": "Feature",
  "properties": {
    "iso:country":"US",
    "sg:address":"911 Washington Ave",
    "sg:city":"St Louis",
    "sg:classifiers":[
        {
            "category":"Government",
            "subcategory":"Office",
            "type":"Public Place"
        }
    ],
    "sg:phone":"+1 314 425 4249",
    "sg:postcode":"63101",
    "sg:province":"MO",
    "sg:tags":[
        "federal"
    ],
    "sg:website":"www.osha.gov",
    "wof:name":"US Occupation Safety & Health",
    "wof:placetype":"venue"
},
  "geometry": {"coordinates":[-90.193636,38.631195],"type":"Point"}
}