{
  "type": "Feature",
  "properties": {
    "iso:country":"US",
    "sg:address":"18235 Co Rd 491",
    "sg:city":"Puxico",
    "sg:classifiers":[
        {
            "category":"Shopping",
            "subcategory":"Bicycles & Sporting Goods",
            "type":"Retail Goods"
        }
    ],
    "sg:phone":"+1 573 222 3735",
    "sg:postcode":"63960",
    "sg:province":"MO",
    "sg:tags":[
        "repair",
        "used",
        "merchandise"
    ],
    "wof:name":"Kents Guns and Reloading",
    "wof:placetype":"venue"
},
  "geometry": {"coordinates":[-90.17041999999999,36.884557],"type":"Point"}
}