{
  "type": "Feature",
  "properties": {
    "iso:country":"US",
    "sg:address":"5800 Phantom Dr",
    "sg:city":"Hazelwood",
    "sg:classifiers":[
        {
            "category":"Banks & Credit Unions",
            "subcategory":"Bank",
            "type":"Services"
        },
        {
            "category":"Banks & Credit Unions",
            "subcategory":"Financial Services",
            "type":"Services"
        }
    ],
    "sg:phone":"+1 314 731 2552",
    "sg:postcode":"63042",
    "sg:province":"MO",
    "sg:tags":[
        "loan"
    ],
    "sg:website":"http://www.neighborscu.org",
    "wof:name":"Neighbors Credit Union",
    "wof:placetype":"venue"
},
  "geometry": {"coordinates":[-90.384761,38.771276],"type":"Point"}
}