{
  "type": "Feature",
  "properties": {
    "iso:country":"US",
    "sg:address":"1 S Memorial Dr",
    "sg:city":"Saint Louis",
    "sg:classifiers":[
        {
            "category":"Professional",
            "subcategory":"Advertising",
            "type":"Services"
        }
    ],
    "sg:phone":"+1 314 342 8600",
    "sg:postcode":"63102",
    "sg:province":"MO",
    "sg:tags":[
        "agency"
    ],
    "wof:name":"DArcy Msius Benton Bowles Inc",
    "wof:placetype":"venue"
},
  "geometry": {"coordinates":[-90.187726,38.623926],"type":"Point"}
}