{
  "type": "Feature",
  "properties": {
    "iso:country":"US",
    "sg:address":"331 Blanche Dr",
    "sg:city":"Saint Charles",
    "sg:classifiers":[
        {
            "category":"Restaurant",
            "type":"Food & Drink"
        }
    ],
    "sg:phone":"+1 636 946 0745",
    "sg:postcode":"63303",
    "sg:province":"MO",
    "sg:tags":[
        "pasta",
        "delivery",
        "pizza"
    ],
    "wof:name":"Pizza Pasta Express",
    "wof:placetype":"venue"
},
  "geometry": {"coordinates":[-90.51944899999999,38.74603],"type":"Point"}
}