{
  "type": "Feature",
  "properties": {
    "iso:country":"US",
    "sg:address":"600 W Linden Ave",
    "sg:city":"Independence",
    "sg:classifiers":[
        {
            "category":"Manufacturing",
            "subcategory":"Printing",
            "type":"Manufacturing & Wholesale Goods"
        }
    ],
    "sg:phone":"+1 816 252 3322",
    "sg:postcode":"64050",
    "sg:province":"MO",
    "sg:tags":[
        "printer"
    ],
    "wof:name":"W W Phelps Printing Co",
    "wof:placetype":"venue"
},
  "geometry": {"coordinates":[-94.422397,39.083997],"type":"Point"}
}