{
  "type": "Feature",
  "properties": {
    "iso:country":"US",
    "sg:address":"1012 Industrial Park Dr",
    "sg:city":"Montgomery City",
    "sg:classifiers":[
        {
            "category":"Manufacturing",
            "subcategory":"Building Materials",
            "type":"Manufacturing & Wholesale Goods"
        },
        {
            "category":"Home & Garden",
            "subcategory":"Furniture",
            "type":"Retail Goods"
        }
    ],
    "sg:phone":"+1 573 564 2628",
    "sg:postcode":"63361",
    "sg:province":"MO",
    "sg:tags":[
        "cabinet",
        "wood",
        "kitchen",
        "mfg"
    ],
    "wof:name":"Brandkamp Industries Inc",
    "wof:placetype":"venue"
},
  "geometry": {"coordinates":[-91.497691,38.956074],"type":"Point"}
}