{
  "type": "Feature",
  "properties": {
    "iso:country":"US",
    "sg:address":"111 N Newstead Ave",
    "sg:city":"Saint Louis",
    "sg:classifiers":[
        {
            "category":"Deli",
            "type":"Food & Drink"
        },
        {
            "category":"Food & Beverages",
            "subcategory":"Groceries & Convenience Stores",
            "type":"Retail Goods"
        }
    ],
    "sg:phone":"+1 314 531 5704",
    "sg:postcode":"63108",
    "sg:province":"MO",
    "wof:name":"Shapiro's Market",
    "wof:placetype":"venue"
},
  "geometry": {"coordinates":[-90.254501,38.641399],"type":"Point"}
}