{
  "type": "Feature",
  "properties": {
    "iso:country":"US",
    "sg:address":"5479 Pike 454",
    "sg:city":"Curryville",
    "sg:classifiers":[
        {
            "category":"Manufacturing",
            "subcategory":"Food",
            "type":"Manufacturing & Wholesale Goods"
        },
        {
            "category":"Farming",
            "subcategory":"Farm",
            "type":"Manufacturing & Wholesale Goods"
        }
    ],
    "sg:phone":"+1 573 324 2792",
    "sg:postcode":"63339",
    "sg:province":"MO",
    "sg:tags":[
        "corn",
        "product"
    ],
    "wof:name":"Floyd Dameron",
    "wof:placetype":"venue"
},
  "geometry": {"coordinates":[-91.374211,39.295209],"type":"Point"}
}