{
  "type": "Feature",
  "properties": {
    "iso:country":"US",
    "sg:address":"2764 Barron Rd",
    "sg:city":"Poplar Bluff",
    "sg:classifiers":[
        {
            "category":"Health Services",
            "subcategory":"Optometrist",
            "type":"Services"
        }
    ],
    "sg:phone":"+1 573 785 2987",
    "sg:postcode":"63901",
    "sg:province":"MO",
    "wof:name":"Knights Templar of US",
    "wof:placetype":"venue"
},
  "geometry": {"coordinates":[-90.431855,36.792021],"type":"Point"}
}