{
  "type": "Feature",
  "properties": {
    "iso:country":"US",
    "sg:address":"311 W 3rd St",
    "sg:city":"Sedalia",
    "sg:classifiers":[
        {
            "category":"Education",
            "subcategory":"Library",
            "type":"Public Place"
        }
    ],
    "sg:phone":"+1 660 826 1314",
    "sg:postcode":"65301",
    "sg:province":"MO",
    "wof:name":"Sedalia Public Library",
    "wof:placetype":"venue"
},
  "geometry": {"coordinates":[-93.231273,38.708666],"type":"Point"}
}