{
  "type": "Feature",
  "properties": {
    "iso:country":"US",
    "sg:address":"1715 Deer Tracks Trl",
    "sg:city":"St Louis",
    "sg:classifiers":[
        {
            "category":"Wholesale",
            "subcategory":"Computers",
            "type":"Manufacturing & Wholesale Goods"
        },
        {
            "category":"Shopping",
            "subcategory":"Computers & Home Electronics",
            "type":"Retail Goods"
        }
    ],
    "sg:phone":"+1 314 965 7750",
    "sg:postcode":"63131",
    "sg:province":"MO",
    "sg:tags":[
        "equipment",
        "dealer"
    ],
    "wof:name":"Datalink Corp",
    "wof:placetype":"venue"
},
  "geometry": {"coordinates":[-90.45320100000001,38.608814],"type":"Point"}
}