{
  "type": "Feature",
  "properties": {
    "iso:country":"US",
    "sg:address":"314 N Walnut St",
    "sg:city":"Willow Springs",
    "sg:classifiers":[
        {
            "category":"Organizations",
            "subcategory":"Religious Organization",
            "type":"Services"
        }
    ],
    "sg:phone":"+1 417 469 2090",
    "sg:postcode":"65793",
    "sg:province":"MO",
    "sg:tags":[
        "church"
    ],
    "wof:name":"Seventh Day Adventist Church",
    "wof:placetype":"venue"
},
  "geometry": {"coordinates":[-91.966871,36.99251],"type":"Point"}
}