{
  "type": "Feature",
  "properties": {
    "iso:country":"US",
    "sg:address":"8720 US Hwy 24",
    "sg:city":"Independence",
    "sg:classifiers":[
        {
            "category":"Professional",
            "subcategory":"Accounting & Tax Preparation",
            "type":"Services"
        }
    ],
    "sg:phone":"+1 816 254 2300",
    "sg:postcode":"64053",
    "sg:province":"MO",
    "wof:name":"Quality Tax & Accounting",
    "wof:placetype":"venue"
},
  "geometry": {"coordinates":[-94.478238,39.108068],"type":"Point"}
}