{
  "type": "Feature",
  "properties": {
    "iso:country":"US",
    "sg:address":"2311 State Hwy 173",
    "sg:city":"Galena",
    "sg:classifiers":[
        {
            "category":"Food & Beverages",
            "subcategory":"Groceries & Convenience Stores",
            "type":"Retail Goods"
        },
        {
            "category":"Autos & Motor Vehicles",
            "subcategory":"Fuel & Gas Station",
            "type":"Retail Goods"
        }
    ],
    "sg:phone":"+1 417 357 6210",
    "sg:postcode":"65656",
    "sg:province":"MO",
    "sg:tags":[
        "station",
        "gasoline"
    ],
    "wof:name":"Cross Roads Store",
    "wof:placetype":"venue"
},
  "geometry": {"coordinates":[-93.53334,36.822782],"type":"Point"}
}