{
  "type": "Feature",
  "properties": {
    "iso:country":"US",
    "sg:address":"1200 Swift Ave",
    "sg:city":"Kansas City",
    "sg:classifiers":[
        {
            "category":"Retail",
            "subcategory":"Repair Shop",
            "type":"Services"
        }
    ],
    "sg:phone":"+1 816 842 3047",
    "sg:postcode":"64116",
    "sg:province":"MO",
    "sg:tags":[
        "repairing",
        "saw"
    ],
    "wof:name":"PDQ Sales & Svc",
    "wof:placetype":"venue"
},
  "geometry": {"coordinates":[-94.577405,39.132338],"type":"Point"}
}