{
  "type": "Feature",
  "properties": {
    "iso:country":"US",
    "sg:address":"8 S Jackson St",
    "sg:city":"Perryville",
    "sg:classifiers":[
        {
            "category":"Personal",
            "subcategory":"Beauty Salon",
            "type":"Services"
        }
    ],
    "sg:phone":"+1 573 547 3003",
    "sg:postcode":"63775",
    "sg:province":"MO",
    "wof:name":"Reflections",
    "wof:placetype":"venue"
},
  "geometry": {"coordinates":[-89.86358799999999,37.724806],"type":"Point"}
}