{
  "type": "Feature",
  "properties": {
    "iso:country":"US",
    "sg:address":"461 W Aldersgate Dr",
    "sg:city":"Nixa",
    "sg:classifiers":[
        {
            "category":"Restaurant",
            "type":"Food & Drink"
        }
    ],
    "sg:phone":"+1 417 724 1016",
    "sg:postcode":"65714",
    "sg:province":"MO",
    "sg:tags":[
        "style",
        "family"
    ],
    "wof:name":"Patrick's Family Restaurant",
    "wof:placetype":"venue"
},
  "geometry": {"coordinates":[-93.303218,37.06011],"type":"Point"}
}