{
  "type": "Feature",
  "properties": {
    "iso:country":"US",
    "sg:address":"708 E Kingsbury St",
    "sg:city":"Springfield",
    "sg:classifiers":[
        {
            "category":"Real Estate",
            "subcategory":"Real Estate Agent",
            "type":"Services"
        }
    ],
    "sg:phone":"+1 417 890 0423",
    "sg:postcode":"65807",
    "sg:province":"MO",
    "wof:name":"Homes Magazine",
    "wof:placetype":"venue"
},
  "geometry": {"coordinates":[-93.283604,37.184786],"type":"Point"}
}