{
  "type": "Feature",
  "properties": {
    "iso:country":"US",
    "sg:address":"1401 Rowan Ave",
    "sg:city":"St Louis",
    "sg:classifiers":[
        {
            "category":"Organizations",
            "subcategory":"Community Association",
            "type":"Services"
        }
    ],
    "sg:phone":"+1 314 367 5959",
    "sg:postcode":"63112",
    "sg:province":"MO",
    "sg:tags":[
        "civic"
    ],
    "wof:name":"Organization-Black Struggle",
    "wof:placetype":"venue"
},
  "geometry": {"coordinates":[-90.282279,38.671817],"type":"Point"}
}