{
  "type": "Feature",
  "properties": {
    "iso:country":"US",
    "sg:address":"215 Cedar St",
    "sg:city":"Pleasant Hill",
    "sg:classifiers":[
        {
            "category":"Retail",
            "subcategory":"Auto Repair",
            "type":"Services"
        }
    ],
    "sg:phone":"+1 816 987 2984",
    "sg:postcode":"64080",
    "sg:province":"MO",
    "sg:tags":[
        "repairing",
        "automobile"
    ],
    "wof:name":"TLC Automotive Repair",
    "wof:placetype":"venue"
},
  "geometry": {"coordinates":[-94.273453,38.786644],"type":"Point"}
}