{
  "type": "Feature",
  "properties": {
    "iso:country":"US",
    "sg:address":"15098 Hwy D",
    "sg:city":"Mexico",
    "sg:classifiers":[
        {
            "category":"Retail",
            "subcategory":"Repair Shop",
            "type":"Services"
        }
    ],
    "sg:phone":"+1 573 581 0909",
    "sg:postcode":"65265",
    "sg:province":"MO",
    "sg:tags":[
        "tractor"
    ],
    "wof:name":"Norfleet Ag Svc LLC",
    "wof:placetype":"venue"
},
  "geometry": {"coordinates":[-92.02588799999999,39.121281],"type":"Point"}
}