{
  "type": "Feature",
  "properties": {
    "iso:country":"US",
    "sg:address":"5617 S 20th Rd",
    "sg:city":"Walnut Grove",
    "sg:classifiers":[
        {
            "category":"Freight",
            "type":"Transportation"
        }
    ],
    "sg:phone":"+1 417 788 2772",
    "sg:postcode":"65770",
    "sg:province":"MO",
    "sg:tags":[
        "truck",
        "dump"
    ],
    "wof:name":"Chism Trucking",
    "wof:placetype":"venue"
},
  "geometry": {"coordinates":[-93.602565,37.434252],"type":"Point"}
}