{
  "type": "Feature",
  "properties": {
    "iso:country":"US",
    "sg:address":"21346 Swope Rd",
    "sg:city":"Sedalia",
    "sg:classifiers":[
        {
            "category":"Real Estate",
            "subcategory":"Real Estate Agent",
            "type":"Services"
        }
    ],
    "sg:phone":"+1 660 826 3880",
    "sg:postcode":"65301",
    "sg:province":"MO",
    "wof:name":"Audrey Bigelow",
    "wof:placetype":"venue"
},
  "geometry": {"coordinates":[-93.224435,38.766623],"type":"Point"}
}