{
  "type": "Feature",
  "properties": {
    "iso:country":"US",
    "sg:address":"2230 E Fritts Ln",
    "sg:city":"Springfield",
    "sg:classifiers":[
        {
            "category":"Professional",
            "subcategory":"Management & Consulting",
            "type":"Services"
        }
    ],
    "sg:phone":"+1 417 881 5655",
    "sg:postcode":"65804",
    "sg:province":"MO",
    "sg:tags":[
        "public",
        "relations"
    ],
    "wof:name":"Jerry E Clark",
    "wof:placetype":"venue"
},
  "geometry": {"coordinates":[-93.25236099999999,37.170146],"type":"Point"}
}