{
  "type": "Feature",
  "properties": {
    "iso:country":"US",
    "sg:address":"24 S Allen St",
    "sg:city":"Bonne Terre",
    "sg:classifiers":[
        {
            "category":"Personal",
            "subcategory":"Beauty Salon",
            "type":"Services"
        }
    ],
    "sg:phone":"+1 573 358 1588",
    "sg:postcode":"63628",
    "sg:province":"MO",
    "sg:tags":[
        "shop"
    ],
    "wof:name":"A Permanent Place",
    "wof:placetype":"venue"
},
  "geometry": {"coordinates":[-90.54955,37.921643],"type":"Point"}
}