{
  "type": "Feature",
  "properties": {
    "iso:country":"US",
    "sg:address":"727 N Main St",
    "sg:city":"Independence",
    "sg:classifiers":[
        {
            "category":"Organizations",
            "subcategory":"Religious Organization",
            "type":"Services"
        }
    ],
    "sg:phone":"+1 816 461 0302",
    "sg:postcode":"64050",
    "sg:province":"MO",
    "sg:tags":[
        "churches-united",
        "christ",
        "church"
    ],
    "sg:website":"http://www.stlukesuccindep.org",
    "wof:name":"St Luke's United Church-Christ",
    "wof:placetype":"venue"
},
  "geometry": {"coordinates":[-94.415435,39.097863],"type":"Point"}
}