{
  "type": "Feature",
  "properties": {
    "iso:country":"US",
    "sg:address":"176 SE State Hwy Y",
    "sg:city":"Warrensburg",
    "sg:classifiers":[
        {
            "category":"Real Estate",
            "subcategory":"Real Estate Operator",
            "type":"Services"
        }
    ],
    "sg:phone":"+1 660 747 9680",
    "sg:postcode":"64093",
    "sg:province":"MO",
    "sg:tags":[
        "mobile",
        "home",
        "community"
    ],
    "wof:name":"Country Aire Mobile Estates",
    "wof:placetype":"venue"
},
  "geometry": {"coordinates":[-93.715042,38.696636],"type":"Point"}
}