{
  "type": "Feature",
  "properties": {
    "iso:country":"US",
    "sg:address":"115 Dairy St",
    "sg:city":"Monett",
    "sg:classifiers":[
        {
            "category":"Manufacturing",
            "subcategory":"Aerospace",
            "type":"Manufacturing & Wholesale Goods"
        }
    ],
    "sg:phone":"+1 417 235 7801",
    "sg:postcode":"65708",
    "sg:province":"MO",
    "sg:tags":[
        "aircraft",
        "component"
    ],
    "sg:website":"www.roderickarms.com",
    "wof:name":"Roderick Arms",
    "wof:placetype":"venue"
},
  "geometry": {"coordinates":[-93.923225,36.915971],"type":"Point"}
}