{
  "type": "Feature",
  "properties": {
    "iso:country":"US",
    "sg:address":"101 E 9th Ave",
    "sg:city":"Kansas City",
    "sg:classifiers":[
        {
            "category":"Wholesale",
            "subcategory":"Metals & Minerals",
            "type":"Manufacturing & Wholesale Goods"
        }
    ],
    "sg:phone":"+1 816 471 3500",
    "sg:postcode":"64116",
    "sg:province":"MO",
    "sg:tags":[
        "aluminum"
    ],
    "sg:website":"www.ryersontull.com",
    "wof:name":"Ryerson Tull",
    "wof:placetype":"venue"
},
  "geometry": {"coordinates":[-94.57984500000001,39.125983],"type":"Point"}
}