{
  "type": "Feature",
  "properties": {
    "iso:country":"US",
    "sg:address":"8219 Hwy 50 W",
    "sg:city":"Centertown",
    "sg:classifiers":[
        {
            "category":"Retail",
            "subcategory":"Auto Repair",
            "type":"Services"
        }
    ],
    "sg:phone":"+1 573 893 6718",
    "sg:postcode":"65023",
    "sg:province":"MO",
    "sg:tags":[
        "exhaust"
    ],
    "wof:name":"After Hours Welding & Muffler",
    "wof:placetype":"venue"
},
  "geometry": {"coordinates":[-92.35701899999999,38.607412],"type":"Point"}
}