{
  "type": "Feature",
  "properties": {
    "iso:country":"US",
    "sg:address":"7500 Prospect Ave",
    "sg:city":"Kansas City",
    "sg:classifiers":[
        {
            "category":"Autos & Motor Vehicles",
            "subcategory":"Automobile Sales",
            "type":"Retail Goods"
        }
    ],
    "sg:phone":"+1 816 333 5757",
    "sg:postcode":"64132",
    "sg:province":"MO",
    "sg:tags":[
        "car",
        "dealer"
    ],
    "wof:name":"T K Auto Sales",
    "wof:placetype":"venue"
},
  "geometry": {"coordinates":[-94.557456,38.987181],"type":"Point"}
}