{
  "type": "Feature",
  "properties": {
    "iso:country":"US",
    "sg:address":"700 East St",
    "sg:city":"Lathrop",
    "sg:classifiers":[
        {
            "category":"Education",
            "subcategory":"School",
            "type":"Public Place"
        }
    ],
    "sg:phone":"+1 816 528 7500",
    "sg:postcode":"64465",
    "sg:province":"MO",
    "sg:tags":[
        "district"
    ],
    "wof:name":"Lathrop R-2 School District",
    "wof:placetype":"venue"
},
  "geometry": {"coordinates":[-94.330472,39.544273],"type":"Point"}
}