{
  "type": "Feature",
  "properties": {
    "iso:country":"US",
    "sg:address":"55 Aspen St",
    "sg:city":"Belton",
    "sg:classifiers":[
        {
            "category":"Building & Trades",
            "subcategory":"Cleaning & Sanitation",
            "type":"Services"
        }
    ],
    "sg:phone":"+1 816 322 9968",
    "sg:postcode":"64012",
    "sg:province":"MO",
    "sg:tags":[
        "janitor"
    ],
    "wof:name":"Extra Hands",
    "wof:placetype":"venue"
},
  "geometry": {"coordinates":[-94.529388,38.819161],"type":"Point"}
}