{
  "type": "Feature",
  "properties": {
    "iso:country":"US",
    "sg:address":"1165 Cherry St",
    "sg:city":"Poplar Bluff",
    "sg:classifiers":[
        {
            "category":"Professional",
            "subcategory":"Lawyer & Legal Services",
            "type":"Services"
        }
    ],
    "sg:phone":"+1 573 686 2459",
    "sg:postcode":"63901",
    "sg:province":"MO",
    "sg:tags":[
        "attorney"
    ],
    "wof:name":"Kennedy Kennedy & Robbins",
    "wof:placetype":"venue"
},
  "geometry": {"coordinates":[-90.407414,36.754827],"type":"Point"}
}