{
  "type": "Feature",
  "properties": {
    "iso:country":"US",
    "sg:address":"8030 N Oak Fwy",
    "sg:city":"Kansas City",
    "sg:classifiers":[
        {
            "category":"Cinema",
            "subcategory":"Movie Rental",
            "type":"Entertainment"
        }
    ],
    "sg:phone":"+1 816 468 6950",
    "sg:postcode":"64118",
    "sg:province":"MO",
    "sg:tags":[
        "leasing",
        "video",
        "disc",
        "tape"
    ],
    "sg:website":"www.blockbuster.com",
    "wof:name":"Blockbuster Video",
    "wof:placetype":"venue"
},
  "geometry": {"coordinates":[-94.576066,39.239787],"type":"Point"}
}