{
  "type": "Feature",
  "properties": {
    "iso:country":"US",
    "sg:address":"614 1st St",
    "sg:city":"Glasgow",
    "sg:classifiers":[
        {
            "category":"Insurance",
            "subcategory":"Insurance Agent",
            "type":"Services"
        }
    ],
    "sg:phone":"+1 660 338 2240",
    "sg:postcode":"65254",
    "sg:province":"MO",
    "wof:name":"AFLAC",
    "wof:placetype":"venue"
},
  "geometry": {"coordinates":[-92.846785,39.227255],"type":"Point"}
}