{
  "type": "Feature",
  "properties": {
    "iso:country":"US",
    "sg:address":"615 E 5th St",
    "sg:city":"Joplin",
    "sg:classifiers":[
        {
            "category":"Landmark",
            "subcategory":"Tourist Information",
            "type":"Public Place"
        }
    ],
    "sg:phone":"+1 417 624 8383",
    "sg:postcode":"64801",
    "sg:province":"MO",
    "sg:tags":[
        "attraction"
    ],
    "wof:name":"Joplin In Line Hockey",
    "wof:placetype":"venue"
},
  "geometry": {"coordinates":[-94.507406,37.086526],"type":"Point"}
}