{
  "type": "Feature",
  "properties": {
    "iso:country":"US",
    "sg:address":"2413 E Chestnut Expy",
    "sg:city":"Springfield",
    "sg:classifiers":[
        {
            "category":"Manufacturing",
            "subcategory":"Retail Goods",
            "type":"Manufacturing & Wholesale Goods"
        }
    ],
    "sg:phone":"+1 417 869 6655",
    "sg:postcode":"65802",
    "sg:province":"MO",
    "sg:tags":[
        "product",
        "mfg"
    ],
    "wof:name":"Rijack Manufacturing LLC",
    "wof:placetype":"venue"
},
  "geometry": {"coordinates":[-93.246787,37.210217],"type":"Point"}
}