{
  "type": "Feature",
  "properties": {
    "iso:country":"US",
    "sg:address":"4016 Washington St",
    "sg:city":"Kansas City",
    "sg:classifiers":[
        {
            "category":"Real Estate",
            "subcategory":"Architect",
            "type":"Services"
        }
    ],
    "sg:phone":"+1 816 931 5600",
    "sg:postcode":"64111",
    "sg:province":"MO",
    "sg:tags":[
        "architectural"
    ],
    "wof:name":"Mantel & Teter Architects Inc",
    "wof:placetype":"venue"
},
  "geometry": {"coordinates":[-94.591426,39.054569],"type":"Point"}
}