{
  "type": "Feature",
  "properties": {
    "iso:country":"US",
    "sg:address":"1450 S Timber Ridge Ln",
    "sg:city":"Rogersville",
    "sg:classifiers":[
        {
            "category":"Cinema",
            "subcategory":"Movie Rental",
            "type":"Entertainment"
        }
    ],
    "sg:phone":"+1 417 759 6888",
    "sg:postcode":"65742",
    "sg:province":"MO",
    "sg:tags":[
        "video",
        "tape"
    ],
    "wof:name":"Front Row Video",
    "wof:placetype":"venue"
},
  "geometry": {"coordinates":[-93.13032800000001,37.184168],"type":"Point"}
}