{
  "type": "Feature",
  "properties": {
    "addr:full":"2122 Saint Louis Galleria St Louis MO 63117",
    "addr:housenumber":"2122",
    "addr:postcode":"63117",
    "addr:street":"Saint Louis Galleria",
    "iso:country":"US",
    "sg:address":"2122 Saint Louis Galleria",
    "sg:city":"St Louis",
    "sg:classifiers":[
        {
            "category":"Shopping",
            "subcategory":"Gifts & Souvenirs",
            "type":"Retail Goods"
        }
    ],
    "sg:phone":"+1 314 863 5558",
    "sg:postcode":"63117",
    "sg:province":"MO",
    "sg:tags":[
        "shop"
    ],
    "wof:name":"Disney Store",
    "wof:placetype":"venue"
},
  "geometry": {"coordinates":[-90.346339,38.637733],"type":"Point"}
}