{
  "type": "Feature",
  "properties": {
    "iso:country":"US",
    "sg:address":"2705 E Linwood Blvd",
    "sg:city":"Kansas City",
    "sg:classifiers":[
        {
            "category":"Professional",
            "type":"Services"
        }
    ],
    "sg:phone":"+1 816 753 2363",
    "sg:postcode":"64128",
    "sg:province":"MO",
    "wof:name":"Linwood Community Dev Ctr",
    "wof:placetype":"venue"
},
  "geometry": {"coordinates":[-94.550664,39.067902],"type":"Point"}
}