{
  "type": "Feature",
  "properties": {
    "iso:country":"US",
    "sg:address":"1984 Parker Rd",
    "sg:city":"St Louis",
    "sg:classifiers":[
        {
            "category":"Organizations",
            "subcategory":"Religious Organization",
            "type":"Services"
        }
    ],
    "sg:phone":"+1 314 741 2510",
    "sg:postcode":"63138",
    "sg:province":"MO",
    "sg:tags":[
        "church"
    ],
    "wof:name":"Friendly Missionary Baptist",
    "wof:placetype":"venue"
},
  "geometry": {"coordinates":[-90.227428,38.795179],"type":"Point"}
}