{
  "type": "Feature",
  "properties": {
    "iso:country":"US",
    "sg:address":"700 W Nodaway St",
    "sg:city":"Oregon",
    "sg:classifiers":[
        {
            "category":"Retail",
            "subcategory":"Storage",
            "type":"Services"
        }
    ],
    "sg:phone":"+1 660 446 2924",
    "sg:postcode":"64473",
    "sg:province":"MO",
    "sg:tags":[
        "container"
    ],
    "wof:name":"Mike Sipes Shop",
    "wof:placetype":"venue"
},
  "geometry": {"coordinates":[-95.151433,39.987323],"type":"Point"}
}