{
  "type": "Feature",
  "properties": {
    "iso:country":"US",
    "sg:address":"4969 St. Louis Ave",
    "sg:city":"St Louis",
    "sg:classifiers":[
        {
            "category":"Arts & Performance",
            "subcategory":"Arts Center",
            "type":"Entertainment"
        },
        {
            "category":"Personal",
            "type":"Services"
        }
    ],
    "sg:phone":"+1 888 643 2583",
    "sg:postcode":"63115",
    "sg:province":"MO",
    "sg:tags":[
        "planning",
        "party",
        "performing",
        "event"
    ],
    "sg:website":"www.grimprov.com",
    "wof:name":"The Murder Mystery Company",
    "wof:placetype":"venue"
},
  "geometry": {"coordinates":[-90.254946,38.671318],"type":"Point"}
}