{
  "type": "Feature",
  "properties": {
    "addr:full":"38 N Main St Cape Girardeau MO 63701",
    "addr:housenumber":"38",
    "addr:postcode":"63701",
    "addr:street":"N Main St",
    "iso:country":"US",
    "sg:address":"38 N Main St",
    "sg:city":"Cape Girardeau",
    "sg:classifiers":[
        {
            "category":"Personal",
            "subcategory":"Beauty Salon",
            "type":"Services"
        }
    ],
    "sg:phone":"+1 573 335 8585",
    "sg:postcode":"63701",
    "sg:province":"MO",
    "sg:tags":[
        "shop"
    ],
    "wof:name":"Attitudes",
    "wof:placetype":"venue"
},
  "geometry": {"coordinates":[-89.51838499999999,37.304247],"type":"Point"}
}