{
  "type": "Feature",
  "properties": {
    "iso:country":"US",
    "sg:address":"3510 Gravois Ave",
    "sg:city":"St Louis",
    "sg:classifiers":[
        {
            "category":"Autos & Motor Vehicles",
            "subcategory":"Auto Supplies",
            "type":"Retail Goods"
        }
    ],
    "sg:phone":"+1 314 772 7666",
    "sg:postcode":"63118",
    "sg:province":"MO",
    "sg:tags":[
        "automobile",
        "parts"
    ],
    "wof:name":"Advance Auto Parts Inc",
    "wof:placetype":"venue"
},
  "geometry": {"coordinates":[-90.24365899999999,38.592496],"type":"Point"}
}