{
  "type": "Feature",
  "properties": {
    "iso:country":"US",
    "sg:address":"21009 Lawrence 1160",
    "sg:city":"Verona",
    "sg:classifiers":[
        {
            "category":"Building & Trades",
            "subcategory":"Construction",
            "type":"Services"
        }
    ],
    "sg:phone":"+1 417 498 6548",
    "sg:postcode":"65769",
    "sg:province":"MO",
    "sg:tags":[
        "excavating",
        "contractor"
    ],
    "wof:name":"Hillhouse Services",
    "wof:placetype":"venue"
},
  "geometry": {"coordinates":[-93.77287800000001,36.968051],"type":"Point"}
}