{
  "type": "Feature",
  "properties": {
    "iso:country":"US",
    "sg:address":"8340 E Bannister Rd",
    "sg:city":"Kansas City",
    "sg:classifiers":[
        {
            "category":"Banks & Credit Unions",
            "subcategory":"Bank",
            "type":"Services"
        }
    ],
    "sg:phone":"+1 816 763 3222",
    "sg:postcode":"64134",
    "sg:province":"MO",
    "sg:tags":[
        "loan",
        "institution",
        "business"
    ],
    "wof:name":"Tracy's Loan Co",
    "wof:placetype":"venue"
},
  "geometry": {"coordinates":[-94.491373,38.951771],"type":"Point"}
}