{
  "type": "Feature",
  "properties": {
    "iso:country":"US",
    "sg:address":"2244 S Kingshighway Blvd",
    "sg:city":"Saint Louis",
    "sg:classifiers":[
        {
            "category":"Retail",
            "subcategory":"Auto Rental",
            "type":"Services"
        },
        {
            "category":"Retail",
            "subcategory":"Auto Repair",
            "type":"Services"
        }
    ],
    "sg:phone":"+1 314 772 1400",
    "sg:postcode":"63110",
    "sg:province":"MO",
    "sg:tags":[
        "body",
        "shop",
        "car"
    ],
    "wof:name":"Brown Don Chevrolet Inc",
    "wof:placetype":"venue"
},
  "geometry": {"coordinates":[-90.26750199999999,38.613998],"type":"Point"}
}