{
  "type": "Feature",
  "properties": {
    "iso:country":"US",
    "sg:address":"6214 Delmar Blvd",
    "sg:city":"Saint Louis",
    "sg:classifiers":[
        {
            "category":"Professional",
            "subcategory":"Lawyer & Legal Services",
            "type":"Services"
        }
    ],
    "sg:phone":"+1 314 721 7117",
    "sg:postcode":"63130",
    "sg:province":"MO",
    "wof:name":"Frenkel & Frenkel PC",
    "wof:placetype":"venue"
},
  "geometry": {"coordinates":[-90.300102,38.655602],"type":"Point"}
}