{
  "type": "Feature",
  "properties": {
    "iso:country":"US",
    "sg:address":"113 W Booneslick Rd",
    "sg:city":"Warrenton",
    "sg:classifiers":[
        {
            "category":"Professional",
            "subcategory":"Lawyer & Legal Services",
            "type":"Services"
        }
    ],
    "sg:phone":"+1 636 456 7261",
    "sg:postcode":"63383",
    "sg:province":"MO",
    "sg:tags":[
        "attorney",
        "practice",
        "plan"
    ],
    "sg:website":"http://www.jarobertsonlawfirm.com",
    "wof:name":"Jeffrey A Robertson, Pc",
    "wof:placetype":"venue"
},
  "geometry": {"coordinates":[-91.14766899999999,38.81115],"type":"Point"}
}