{
  "type": "Feature",
  "properties": {
    "iso:country":"US",
    "sg:address":"402 Ryan Ln",
    "sg:city":"Chillicothe",
    "sg:classifiers":[
        {
            "category":"Home & Garden",
            "subcategory":"Building Materials",
            "type":"Retail Goods"
        }
    ],
    "sg:phone":"+1 660 646 2000",
    "sg:postcode":"64601",
    "sg:province":"MO",
    "sg:tags":[
        "lumber",
        "other"
    ],
    "wof:name":"Pat Thorne Lumber Co",
    "wof:placetype":"venue"
},
  "geometry": {"coordinates":[-93.545855,39.782327],"type":"Point"}
}