{
  "type": "Feature",
  "properties": {
    "iso:country":"US",
    "sg:address":"2002 S Wall Ave",
    "sg:city":"Joplin",
    "sg:classifiers":[
        {
            "category":"Insurance",
            "subcategory":"Hazard Insurance",
            "type":"Services"
        }
    ],
    "sg:phone":"+1 417 626 8332",
    "sg:postcode":"64804",
    "sg:province":"MO",
    "wof:name":"Williams, Bill",
    "wof:placetype":"venue"
},
  "geometry": {"coordinates":[-94.51635899999999,37.069565],"type":"Point"}
}