{
  "type": "Feature",
  "properties": {
    "iso:country":"US",
    "sg:address":"100 W Walnut St",
    "sg:city":"Nevada",
    "sg:classifiers":[
        {
            "category":"Banks & Credit Unions",
            "subcategory":"Bank",
            "type":"Services"
        }
    ],
    "sg:phone":"+1 417 667 3057",
    "sg:postcode":"64772",
    "sg:province":"MO",
    "sg:website":"www.fnbnevada.com",
    "wof:name":"First National Bank",
    "wof:placetype":"venue"
},
  "geometry": {"coordinates":[-94.3579,37.839238],"type":"Point"}
}