{
  "type": "Feature",
  "properties": {
    "iso:country":"US",
    "sg:address":"3616 Humphrey St",
    "sg:city":"Saint Louis",
    "sg:classifiers":[
        {
            "category":"Shopping",
            "subcategory":"Gifts & Souvenirs",
            "type":"Retail Goods"
        }
    ],
    "sg:phone":"+1 314 776 4448",
    "sg:postcode":"63116",
    "sg:province":"MO",
    "wof:name":"Grand Things LLC",
    "wof:placetype":"venue"
},
  "geometry": {"coordinates":[-90.246469,38.598943],"type":"Point"}
}