{
  "type": "Feature",
  "properties": {
    "iso:country":"US",
    "sg:address":"4532 E Truman Rd",
    "sg:city":"Kansas City",
    "sg:classifiers":[
        {
            "category":"Retail",
            "subcategory":"Auto Repair",
            "type":"Services"
        }
    ],
    "sg:phone":"+1 816 231 0972",
    "sg:postcode":"64127",
    "sg:province":"MO",
    "sg:tags":[
        "shop",
        "truck",
        "general"
    ],
    "wof:name":"Falco's Service",
    "wof:placetype":"venue"
},
  "geometry": {"coordinates":[-94.529163,39.09424],"type":"Point"}
}