{
  "type": "Feature",
  "properties": {
    "iso:country":"US",
    "sg:address":"302 N Connor Ave",
    "sg:city":"Joplin",
    "sg:classifiers":[
        {
            "category":"Building & Trades",
            "subcategory":"Construction",
            "type":"Services"
        }
    ],
    "sg:phone":"+1 417 782 5531",
    "sg:postcode":"64801",
    "sg:province":"MO",
    "sg:tags":[
        "house"
    ],
    "wof:name":"Landmark Builders",
    "wof:placetype":"venue"
},
  "geometry": {"coordinates":[-94.52239,37.09423],"type":"Point"}
}