{
  "type": "Feature",
  "properties": {
    "iso:country":"US",
    "sg:address":"5445 Telegraph Rd",
    "sg:city":"St Louis",
    "sg:classifiers":[
        {
            "category":"Personal",
            "subcategory":"Beauty Salon",
            "type":"Services"
        }
    ],
    "sg:phone":"+1 314 487 3601",
    "sg:postcode":"63129",
    "sg:province":"MO",
    "sg:tags":[
        "shop"
    ],
    "wof:name":"Cuttery Limited",
    "wof:placetype":"venue"
},
  "geometry": {"coordinates":[-90.304378,38.475238],"type":"Point"}
}