{
  "type": "Feature",
  "properties": {
    "iso:country":"US",
    "sg:address":"1784 Doll Rd",
    "sg:city":"Hermann",
    "sg:phone":"+1 573 486 5281",
    "sg:postcode":"65041",
    "sg:province":"MO",
    "sg:tags":[
        "farm",
        "soybean"
    ],
    "wof:name":"Jon Schneider",
    "wof:placetype":"venue"
},
  "geometry": {"coordinates":[-91.421767,38.588213],"type":"Point"}
}