{
  "type": "Feature",
  "properties": {
    "iso:country":"US",
    "sg:address":"1549 N College St",
    "sg:city":"Neosho",
    "sg:classifiers":[
        {
            "category":"Food & Beverages",
            "subcategory":"Liquor & Beverages",
            "type":"Retail Goods"
        }
    ],
    "sg:phone":"+1 417 451 0979",
    "sg:postcode":"64850",
    "sg:province":"MO",
    "wof:name":"Hickory Creek Corner",
    "wof:placetype":"venue"
},
  "geometry": {"coordinates":[-94.37031500000001,36.887789],"type":"Point"}
}