{
  "type": "Feature",
  "properties": {
    "iso:country":"US",
    "sg:address":"553 Commercial Dr",
    "sg:city":"Union",
    "sg:classifiers":[
        {
            "category":"Manufacturing",
            "subcategory":"Tools & Machinery",
            "type":"Manufacturing & Wholesale Goods"
        }
    ],
    "sg:phone":"+1 636 583 8984",
    "sg:postcode":"63084",
    "sg:province":"MO",
    "sg:tags":[
        "machine",
        "shop"
    ],
    "sg:website":"www.linmarkmachine.com",
    "wof:name":"Linmark Machine Products Inc",
    "wof:placetype":"venue"
},
  "geometry": {"coordinates":[-91.00543,38.489904],"type":"Point"}
}