{
  "type": "Feature",
  "properties": {
    "iso:country":"US",
    "sg:address":"2103 Forum Dr",
    "sg:city":"Rolla",
    "sg:classifiers":[
        {
            "category":"Retail",
            "subcategory":"Auto Repair",
            "type":"Services"
        }
    ],
    "sg:phone":"+1 573 341 5757",
    "sg:postcode":"65401",
    "sg:province":"MO",
    "sg:tags":[
        "body",
        "painting",
        "repairing",
        "automobile"
    ],
    "wof:name":"Gary's Auto Body Inc",
    "wof:placetype":"venue"
},
  "geometry": {"coordinates":[-91.75174699999999,37.965191],"type":"Point"}
}