{
  "type": "Feature",
  "properties": {
    "iso:country":"US",
    "sg:address":"406 S 1st St",
    "sg:city":"King City",
    "sg:classifiers":[
        {
            "category":"Retail",
            "subcategory":"Repair Shop",
            "type":"Services"
        }
    ],
    "sg:phone":"+1 660 535 4930",
    "sg:postcode":"64463",
    "sg:province":"MO",
    "sg:tags":[
        "repairing",
        "lawn",
        "mower"
    ],
    "wof:name":"A-1 Atv & Lawn Equipment Rpr",
    "wof:placetype":"venue"
},
  "geometry": {"coordinates":[-94.519724,40.0478],"type":"Point"}
}