{
  "type": "Feature",
  "properties": {
    "iso:country":"US",
    "sg:address":"7877 Costa Pl",
    "sg:city":"Saint Louis",
    "sg:classifiers":[
        {
            "category":"Professional",
            "type":"Services"
        }
    ],
    "sg:phone":"+1 314 544 5211",
    "sg:postcode":"63111",
    "sg:province":"MO",
    "wof:name":"It Athena LLC",
    "wof:placetype":"venue"
},
  "geometry": {"coordinates":[-90.26849,38.55096],"type":"Point"}
}