{
  "type": "Feature",
  "properties": {
    "iso:country":"US",
    "sg:address":"531 Old Rte 66",
    "sg:city":"St Robert",
    "sg:classifiers":[
        {
            "category":"Wholesale",
            "subcategory":"Electrical",
            "type":"Manufacturing & Wholesale Goods"
        }
    ],
    "sg:phone":"+1 573 336 0144",
    "sg:postcode":"65584",
    "sg:province":"MO",
    "sg:tags":[
        "equipment",
        "electric",
        "supply"
    ],
    "wof:name":"Butler Supply",
    "wof:placetype":"venue"
},
  "geometry": {"coordinates":[-92.160741,37.821851],"type":"Point"}
}