{
  "type": "Feature",
  "properties": {
    "iso:country":"US",
    "sg:address":"1510 Denmark Rd",
    "sg:city":"Union",
    "sg:classifiers":[
        {
            "category":"Real Estate",
            "subcategory":"Real Estate Agent",
            "type":"Services"
        }
    ],
    "sg:phone":"+1 636 583 5124",
    "sg:postcode":"63084",
    "sg:province":"MO",
    "wof:name":"Re/Max Central",
    "wof:placetype":"venue"
},
  "geometry": {"coordinates":[-90.96402,38.431551],"type":"Point"}
}