{
  "type": "Feature",
  "properties": {
    "iso:country":"US",
    "sg:address":"1600 Bird Rd",
    "sg:city":"Branson",
    "sg:classifiers":[
        {
            "category":"Real Estate",
            "subcategory":"Real Estate Services",
            "type":"Services"
        },
        {
            "category":"Real Estate",
            "subcategory":"Real Estate Operator",
            "type":"Services"
        }
    ],
    "sg:phone":"+1 417 337 5803",
    "sg:postcode":"65616",
    "sg:province":"MO",
    "sg:tags":[
        "vacancy",
        "apartment",
        "rental",
        "finder",
        "listing"
    ],
    "wof:name":"Best Western",
    "wof:placetype":"venue"
},
  "geometry": {"coordinates":[-93.243557,36.671882],"type":"Point"}
}