{
  "type": "Feature",
  "properties": {
    "iso:country":"US",
    "sg:address":"30 Maryland Plaza Suite 200",
    "sg:city":"St Louis",
    "sg:classifiers":[
        {
            "category":"Personal",
            "subcategory":"Beauty Salon",
            "type":"Services"
        }
    ],
    "sg:phone":"+1 314 361 8200",
    "sg:postcode":"63108",
    "sg:province":"MO",
    "sg:tags":[
        "hair"
    ],
    "sg:website":"www.stlacademy.net",
    "wof:name":"St. Louis Academy",
    "wof:placetype":"venue"
},
  "geometry": {"coordinates":[-90.262833,38.645001],"type":"Point"}
}