{
  "type": "Feature",
  "properties": {
    "iso:country":"US",
    "sg:address":"224 E Washington St",
    "sg:city":"East Prairie",
    "sg:classifiers":[
        {
            "category":"Autos & Motor Vehicles",
            "subcategory":"Automobile Sales",
            "type":"Retail Goods"
        }
    ],
    "sg:phone":"+1 573 649 3777",
    "sg:postcode":"63845",
    "sg:province":"MO",
    "sg:tags":[
        "used"
    ],
    "wof:name":"Bain Auto Sales",
    "wof:placetype":"venue"
},
  "geometry": {"coordinates":[-89.381702,36.777482],"type":"Point"}
}