{
  "type": "Feature",
  "properties": {
    "iso:country":"US",
    "sg:address":"128 Center St",
    "sg:city":"Phillipsburg",
    "sg:classifiers":[
        {
            "category":"Organizations",
            "subcategory":"Religious Organization",
            "type":"Services"
        }
    ],
    "sg:phone":"+1 417 589 6074",
    "sg:postcode":"65722",
    "sg:province":"MO",
    "wof:name":"Phillipsburg Baptist Church",
    "wof:placetype":"venue"
},
  "geometry": {"coordinates":[-92.786919,37.553924],"type":"Point"}
}