{
  "type": "Feature",
  "properties": {
    "iso:country":"US",
    "sg:address":"2100 Bellevue Ave",
    "sg:city":"St Louis",
    "sg:classifiers":[
        {
            "category":"Recreation",
            "type":"Entertainment"
        }
    ],
    "sg:phone":"+1 314 645 5333",
    "sg:postcode":"63143",
    "sg:province":"MO",
    "sg:tags":[
        "martial",
        "arts",
        "instruction"
    ],
    "wof:name":"Iron Dragon Classical Kung Fu",
    "wof:placetype":"venue"
},
  "geometry": {"coordinates":[-90.31336899999999,38.62037],"type":"Point"}
}