{
  "type": "Feature",
  "properties": {
    "iso:country":"US",
    "sg:address":"330 Hawthorn Rd",
    "sg:city":"Seymour",
    "sg:classifiers":[
        {
            "category":"Building & Trades",
            "subcategory":"Construction",
            "type":"Services"
        }
    ],
    "sg:phone":"+1 417 935 9360",
    "sg:postcode":"65746",
    "sg:province":"MO",
    "sg:tags":[
        "house"
    ],
    "wof:name":"SHC Inc",
    "wof:placetype":"venue"
},
  "geometry": {"coordinates":[-92.808251,37.097589],"type":"Point"}
}