{
  "type": "Feature",
  "properties": {
    "iso:country":"US",
    "sg:address":"2500 E Kearney St",
    "sg:city":"Springfield",
    "sg:classifiers":[
        {
            "category":"Autos & Motor Vehicles",
            "subcategory":"Boat Sales",
            "type":"Retail Goods"
        }
    ],
    "sg:phone":"+1 417 873 5900",
    "sg:postcode":"65803",
    "sg:province":"MO",
    "sg:tags":[
        "repair",
        "maintenance"
    ],
    "wof:name":"Tracker Marine Boat Company",
    "wof:placetype":"venue"
},
  "geometry": {"coordinates":[-93.325543,37.241251],"type":"Point"}
}