{
  "type": "Feature",
  "properties": {
    "iso:country":"US",
    "sg:address":"101 Farrar Dr",
    "sg:city":"Cape Girardeau",
    "sg:classifiers":[
        {
            "category":"Real Estate",
            "subcategory":"Architect",
            "type":"Services"
        }
    ],
    "sg:phone":"+1 573 651 9001",
    "sg:postcode":"63701",
    "sg:province":"MO",
    "sg:tags":[
        "architectural"
    ],
    "wof:name":"Phillip B Smith Architect",
    "wof:placetype":"venue"
},
  "geometry": {"coordinates":[-89.576955,37.303357],"type":"Point"}
}