{
  "type": "Feature",
  "properties": {
    "iso:country":"US",
    "sg:address":"7085 Madrid Ln",
    "sg:city":"Neosho",
    "sg:classifiers":[
        {
            "category":"Wholesale",
            "subcategory":"Machinery & Supplies",
            "type":"Manufacturing & Wholesale Goods"
        }
    ],
    "sg:phone":"+1 417 437 6445",
    "sg:postcode":"64850",
    "sg:province":"MO",
    "sg:tags":[
        "equipment",
        "industrial"
    ],
    "wof:name":"American Cargo Equipment Inc",
    "wof:placetype":"venue"
},
  "geometry": {"coordinates":[-94.349673,36.963696],"type":"Point"}
}