{
  "type": "Feature",
  "properties": {
    "iso:country":"US",
    "sg:address":"801 E 18th St",
    "sg:city":"Rolla",
    "sg:classifiers":[
        {
            "category":"Freight",
            "type":"Transportation"
        }
    ],
    "sg:phone":"+1 573 341 8588",
    "sg:postcode":"65401",
    "sg:province":"MO",
    "sg:tags":[
        "operator",
        "local",
        "trucking"
    ],
    "wof:name":"Yoakum Dump Trucking",
    "wof:placetype":"venue"
},
  "geometry": {"coordinates":[-91.762889,37.957961],"type":"Point"}
}