{
  "type": "Feature",
  "properties": {
    "iso:country":"US",
    "sg:address":"1846 W Pearce Blvd",
    "sg:city":"Wentzville",
    "sg:classifiers":[
        {
            "category":"Health Services",
            "subcategory":"Clinic",
            "type":"Services"
        }
    ],
    "sg:phone":"+1 636 332 5724",
    "sg:postcode":"63385",
    "sg:province":"MO",
    "sg:tags":[
        "home",
        "care"
    ],
    "wof:name":"House Calls Home Health Care",
    "wof:placetype":"venue"
},
  "geometry": {"coordinates":[-90.889225,38.805509],"type":"Point"}
}