{
  "type": "Feature",
  "properties": {
    "iso:country":"US",
    "sg:address":"620 N Prospect Ave",
    "sg:city":"Kansas City",
    "sg:classifiers":[
        {
            "category":"Autos & Motor Vehicles",
            "subcategory":"Automobile Sales",
            "type":"Retail Goods"
        }
    ],
    "sg:phone":"+1 816 231 6655",
    "sg:postcode":"64120",
    "sg:province":"MO",
    "sg:tags":[
        "used"
    ],
    "wof:name":"Sam Davis Auto Sales",
    "wof:placetype":"venue"
},
  "geometry": {"coordinates":[-94.550329,39.120656],"type":"Point"}
}