{
  "type": "Feature",
  "properties": {
    "iso:country":"US",
    "sg:address":"344 Festus Centre Dr",
    "sg:city":"Festus",
    "sg:classifiers":[
        {
            "category":"Real Estate",
            "subcategory":"Real Estate Services",
            "type":"Services"
        },
        {
            "category":"Real Estate",
            "subcategory":"Real Estate Agent",
            "type":"Services"
        }
    ],
    "sg:phone":"+1 636 931 9800",
    "sg:postcode":"63028",
    "sg:province":"MO",
    "sg:tags":[
        "buyer",
        "broker"
    ],
    "wof:name":"Callahan Five Star Realty",
    "wof:placetype":"venue"
},
  "geometry": {"coordinates":[-90.39494500000001,38.212722],"type":"Point"}
}