{
  "type": "Feature",
  "properties": {
    "iso:country":"US",
    "sg:address":"2448 E Wildwood Rd",
    "sg:city":"Springfield",
    "sg:classifiers":[
        {
            "category":"Real Estate",
            "subcategory":"Real Estate Agent",
            "type":"Services"
        }
    ],
    "sg:phone":"+1 417 886 2552",
    "sg:postcode":"65804",
    "sg:province":"MO",
    "sg:tags":[
        "inspection"
    ],
    "wof:name":"ARIS Home Inspections",
    "wof:placetype":"venue"
},
  "geometry": {"coordinates":[-93.24927599999999,37.108323],"type":"Point"}
}