{
  "type": "Feature",
  "properties": {
    "iso:country":"US",
    "sg:address":"6745 Bartmer Ave",
    "sg:city":"Saint Louis",
    "sg:classifiers":[
        {
            "category":"Building & Trades",
            "subcategory":"Construction",
            "type":"Services"
        }
    ],
    "sg:phone":"+1 314 721 7827",
    "sg:postcode":"63130",
    "sg:province":"MO",
    "sg:tags":[
        "hanging",
        "contractor"
    ],
    "wof:name":"Ambience Painting",
    "wof:placetype":"venue"
},
  "geometry": {"coordinates":[-90.30777500000001,38.66507],"type":"Point"}
}