{
  "type": "Feature",
  "properties": {
    "iso:country":"US",
    "sg:address":"119 N 3rd St",
    "sg:city":"Hannibal",
    "sg:classifiers":[
        {
            "category":"Communications",
            "subcategory":"Radio Station",
            "type":"Services"
        }
    ],
    "sg:phone":"+1 573 221 3450",
    "sg:postcode":"63401",
    "sg:province":"MO",
    "sg:tags":[
        "company",
        "broadcasting"
    ],
    "wof:name":"KHMO",
    "wof:placetype":"venue"
},
  "geometry": {"coordinates":[-91.35748700000001,39.709844],"type":"Point"}
}