{
  "type": "Feature",
  "properties": {
    "iso:country":"US",
    "sg:address":"15300 State Hwy 133",
    "sg:city":"Dixon",
    "sg:classifiers":[
        {
            "category":"Building & Trades",
            "subcategory":"Construction",
            "type":"Services"
        }
    ],
    "sg:phone":"+1 573 759 6799",
    "sg:postcode":"65459",
    "sg:province":"MO",
    "sg:tags":[
        "excavating",
        "contractor"
    ],
    "wof:name":"Arthur Bassett Excavating",
    "wof:placetype":"venue"
},
  "geometry": {"coordinates":[-92.12151,38.004563],"type":"Point"}
}