{
  "type": "Feature",
  "properties": {
    "iso:country":"US",
    "sg:address":"714 Spirit 40 Park Dr",
    "sg:city":"Chesterfield",
    "sg:classifiers":[
        {
            "category":"Utilities",
            "subcategory":"Telephone",
            "type":"Services"
        },
        {
            "category":"Communications",
            "type":"Services"
        }
    ],
    "sg:phone":"+1 636 736 4000",
    "sg:postcode":"63005",
    "sg:province":"MO",
    "sg:tags":[
        "data"
    ],
    "sg:website":"http://www.customerdirect.com",
    "wof:name":"Customer Direct",
    "wof:placetype":"venue"
},
  "geometry": {"coordinates":[-90.638476,38.670904],"type":"Point"}
}