{
  "type": "Feature",
  "properties": {
    "iso:country":"US",
    "sg:address":"1610 Angelique St",
    "sg:city":"St Joseph",
    "sg:classifiers":[
        {
            "category":"Organizations",
            "subcategory":"Religious Organization",
            "type":"Services"
        }
    ],
    "sg:phone":"+1 816 232 7355",
    "sg:postcode":"64501",
    "sg:province":"MO",
    "sg:tags":[
        "church"
    ],
    "wof:name":"St Francis Baptist Temple",
    "wof:placetype":"venue"
},
  "geometry": {"coordinates":[-94.84059999999999,39.763363],"type":"Point"}
}