{
  "type": "Feature",
  "properties": {
    "iso:country":"US",
    "sg:address":"21371 McCurdy Ln",
    "sg:city":"Hughesville",
    "sg:classifiers":[
        {
            "category":"Professional",
            "type":"Services"
        }
    ],
    "sg:phone":"+1 660 829 4844",
    "sg:postcode":"65301",
    "sg:province":"MO",
    "wof:name":"Pete Phillips",
    "wof:placetype":"venue"
},
  "geometry": {"coordinates":[-93.243942,38.766293],"type":"Point"}
}