{
  "type": "Feature",
  "properties": {
    "iso:country":"US",
    "sg:address":"8260 NE Underground Dr",
    "sg:city":"Kansas City",
    "sg:classifiers":[
        {
            "category":"Building & Trades",
            "subcategory":"Electrical",
            "type":"Services"
        }
    ],
    "sg:phone":"+1 816 308 0059",
    "sg:postcode":"64161",
    "sg:province":"MO",
    "sg:tags":[
        "electric",
        "contractor"
    ],
    "wof:name":"Epic Electric Mine Shop",
    "wof:placetype":"venue"
},
  "geometry": {"coordinates":[-94.48478799999999,39.156264],"type":"Point"}
}