{
  "type": "Feature",
  "properties": {
    "iso:country":"US",
    "sg:address":"12182 Belle Meade Rd",
    "sg:city":"Saint Louis",
    "sg:classifiers":[
        {
            "category":"Professional",
            "subcategory":"Lawyer & Legal Services",
            "type":"Services"
        }
    ],
    "sg:phone":"+1 314 822 9386",
    "sg:postcode":"63131",
    "sg:province":"MO",
    "wof:name":"Gregory P White Atty",
    "wof:placetype":"venue"
},
  "geometry": {"coordinates":[-90.440077,38.617105],"type":"Point"}
}