{
  "type": "Feature",
  "properties": {
    "iso:country":"US",
    "sg:address":"424 NW State Hwy M",
    "sg:city":"Centerview",
    "sg:phone":"+1 660 747 9300",
    "sg:postcode":"64019",
    "sg:province":"MO",
    "sg:tags":[
        "farm",
        "soybean"
    ],
    "wof:name":"Richard Feldman",
    "wof:placetype":"venue"
},
  "geometry": {"coordinates":[-93.907105,38.825871],"type":"Point"}
}