{
  "type": "Feature",
  "properties": {
    "iso:country":"US",
    "sg:address":"5502 Natural Bridge Ave",
    "sg:city":"St Louis",
    "sg:classifiers":[
        {
            "category":"Personal",
            "subcategory":"Beauty Salon",
            "type":"Services"
        }
    ],
    "sg:phone":"+1 314 381 8482",
    "sg:postcode":"63120",
    "sg:province":"MO",
    "wof:name":"Babi Doll Hair Studio",
    "wof:placetype":"venue"
},
  "geometry": {"coordinates":[-90.26516599999999,38.682173],"type":"Point"}
}