{
  "type": "Feature",
  "properties": {
    "iso:country":"US",
    "sg:address":"213 S Metzletein Rd",
    "sg:city":"Clever",
    "sg:classifiers":[
        {
            "category":"Home & Garden",
            "subcategory":"Building Materials",
            "type":"Retail Goods"
        },
        {
            "category":"Manufacturing",
            "subcategory":"Lumber",
            "type":"Manufacturing & Wholesale Goods"
        }
    ],
    "sg:phone":"+1 417 743 2838",
    "sg:postcode":"65631",
    "sg:province":"MO",
    "sg:tags":[
        "lumber-wholesale"
    ],
    "wof:name":"Monger Construction, Inc.",
    "wof:placetype":"venue"
},
  "geometry": {"coordinates":[-93.500356,37.037695],"type":"Point"}
}