{
  "type": "Feature",
  "properties": {
    "iso:country":"US",
    "sg:address":"1798 State Hwy Bb",
    "sg:city":"Hollister",
    "sg:classifiers":[
        {
            "category":"Organizations",
            "subcategory":"Community Association",
            "type":"Services"
        }
    ],
    "sg:phone":"+1 417 334 6482",
    "sg:postcode":"65630",
    "sg:province":"MO",
    "sg:tags":[
        "child",
        "day",
        "care"
    ],
    "wof:name":"Parents As Teachers",
    "wof:placetype":"venue"
},
  "geometry": {"coordinates":[-93.244558,36.83866],"type":"Point"}
}