{
  "type": "Feature",
  "properties": {
    "iso:country":"US",
    "sg:address":"501 N Clayview Dr",
    "sg:city":"Liberty",
    "sg:phone":"+1 816 792 1696",
    "sg:postcode":"64068",
    "sg:province":"MO",
    "sg:tags":[
        "farm",
        "corn",
        "soybean"
    ],
    "wof:name":"Darrell Godfrey",
    "wof:placetype":"venue"
},
  "geometry": {"coordinates":[-94.438519,39.254615],"type":"Point"}
}