{
  "type": "Feature",
  "properties": {
    "iso:country":"US",
    "sg:address":"5918 Maple Ave",
    "sg:city":"Saint Louis",
    "sg:classifiers":[
        {
            "category":"Banks & Credit Unions",
            "subcategory":"Financial Services",
            "type":"Services"
        }
    ],
    "sg:phone":"+1 314 862 0729",
    "sg:postcode":"63112",
    "sg:province":"MO",
    "sg:tags":[
        "investor"
    ],
    "wof:name":"Brick & Mortar Investments",
    "wof:placetype":"venue"
},
  "geometry": {"coordinates":[-90.290207,38.661253],"type":"Point"}
}