{
  "type": "Feature",
  "properties": {
    "iso:country":"US",
    "sg:address":"7004 Monticello",
    "sg:city":"Barnhart",
    "sg:classifiers":[
        {
            "category":"Insurance",
            "subcategory":"Insurance Agent",
            "type":"Services"
        },
        {
            "category":"Insurance",
            "subcategory":"Hazard Insurance",
            "type":"Services"
        },
        {
            "category":"Insurance",
            "subcategory":"Title Insurance",
            "type":"Services"
        }
    ],
    "sg:phone":"+1 636 464 1221",
    "sg:postcode":"63012",
    "sg:province":"MO",
    "sg:tags":[
        "auto",
        "homeowner"
    ],
    "sg:website":"http://apps.amfam.com/agentlocator/RKRAEMER?sourceid=yp3",
    "wof:name":"American Family Insurance- Randolph J Kraemer",
    "wof:placetype":"venue"
},
  "geometry": {"coordinates":[-90.399655,38.34063],"type":"Point"}
}