{
  "type": "Feature",
  "properties": {
    "addr:full":"435 SW Ward Rd Lees Summit MO 64081",
    "addr:housenumber":"435",
    "addr:postcode":"64081",
    "addr:street":"Sw Ward Rd",
    "iso:country":"US",
    "sg:address":"435 SW Ward Rd",
    "sg:city":"Lees Summit",
    "sg:classifiers":[
        {
            "category":"Professional",
            "subcategory":"Accounting & Tax Preparation",
            "type":"Services"
        }
    ],
    "sg:phone":"+1 816 525 8162",
    "sg:postcode":"64081",
    "sg:province":"MO",
    "sg:tags":[
        "return",
        "filing"
    ],
    "wof:name":"H & R Block Tax Svc",
    "wof:placetype":"venue"
},
  "geometry": {"coordinates":[-94.395229,38.90879],"type":"Point"}
}