{
  "type": "Feature",
  "properties": {
    "iso:country":"US",
    "sg:address":"500 Jungermann Rd",
    "sg:city":"St Peters",
    "sg:classifiers":[
        {
            "category":"Building & Trades",
            "subcategory":"Cleaning & Sanitation",
            "type":"Services"
        }
    ],
    "sg:phone":"+1 636 928 7771",
    "sg:postcode":"63376",
    "sg:province":"MO",
    "sg:tags":[
        "polishing",
        "waxing",
        "maintenance",
        "floor"
    ],
    "wof:name":"Integrity Cleaning System LLC",
    "wof:placetype":"venue"
},
  "geometry": {"coordinates":[-90.57708100000001,38.782058],"type":"Point"}
}