{
  "type": "Feature",
  "properties": {
    "iso:country":"US",
    "sg:address":"15800 Elmwood Ave",
    "sg:city":"Kansas City",
    "sg:classifiers":[
        {
            "category":"Bars & Pubs",
            "type":"Food & Drink"
        }
    ],
    "sg:phone":"+1 816 318 8130",
    "sg:postcode":"64147",
    "sg:province":"MO",
    "sg:tags":[
        "drinking"
    ],
    "wof:name":"Rg Casual Bar",
    "wof:placetype":"venue"
},
  "geometry": {"coordinates":[-94.543387,38.83981],"type":"Point"}
}