{
  "type": "Feature",
  "properties": {
    "iso:country":"US",
    "sg:address":"4650 Lansdowne Ave",
    "sg:city":"Saint Louis",
    "sg:classifiers":[
        {
            "category":"Home & Garden",
            "subcategory":"Furniture",
            "type":"Retail Goods"
        }
    ],
    "sg:phone":"+1 314 832 5300",
    "sg:postcode":"63116",
    "sg:province":"MO",
    "sg:tags":[
        "store"
    ],
    "sg:website":"www.hdlfurnitureandflooring.com",
    "wof:name":"Home Decor Liquidators",
    "wof:placetype":"venue"
},
  "geometry": {"coordinates":[-90.27357600000001,38.587285],"type":"Point"}
}