{
  "type": "Feature",
  "properties": {
    "iso:country":"US",
    "sg:address":"500 S 4th St",
    "sg:city":"Canton",
    "sg:classifiers":[
        {
            "category":"Retail",
            "subcategory":"Animal Services",
            "type":"Services"
        }
    ],
    "sg:phone":"+1 573 288 8983",
    "sg:postcode":"63435",
    "sg:province":"MO",
    "wof:name":"Marshas Grooming Salon",
    "wof:placetype":"venue"
},
  "geometry": {"coordinates":[-91.51850399999999,40.126577],"type":"Point"}
}