{
  "type": "Feature",
  "properties": {
    "iso:country":"US",
    "sg:address":"600 State Hwy 291",
    "sg:city":"Lees Summit",
    "sg:classifiers":[
        {
            "category":"Real Estate",
            "subcategory":"Real Estate Operator",
            "type":"Services"
        }
    ],
    "sg:phone":"+1 816 524 2441",
    "sg:postcode":"64063",
    "sg:province":"MO",
    "sg:tags":[
        "apartment"
    ],
    "wof:name":"Lodge Apartments",
    "wof:placetype":"venue"
},
  "geometry": {"coordinates":[-94.36322800000001,38.907216],"type":"Point"}
}