{
  "type": "Feature",
  "properties": {
    "iso:country":"US",
    "sg:address":"1003 E Main St",
    "sg:city":"Richmond",
    "sg:classifiers":[
        {
            "category":"Restaurant",
            "type":"Food & Drink"
        }
    ],
    "sg:phone":"+1 816 470 3200",
    "sg:postcode":"64085",
    "sg:province":"MO",
    "wof:name":"Susie's 10-13 Restaurant",
    "wof:placetype":"venue"
},
  "geometry": {"coordinates":[-93.958697,39.278223],"type":"Point"}
}