{
  "type": "Feature",
  "properties": {
    "iso:country":"US",
    "sg:address":"2942 US Hwy 61",
    "sg:city":"Bloomsdale",
    "sg:classifiers":[
        {
            "category":"Wholesale",
            "subcategory":"Construction Materials",
            "type":"Manufacturing & Wholesale Goods"
        }
    ],
    "sg:phone":"+1 573 483 8170",
    "sg:postcode":"63627",
    "sg:province":"MO",
    "sg:tags":[
        "cement"
    ],
    "wof:name":"Holcim Us Inc",
    "wof:placetype":"venue"
},
  "geometry": {"coordinates":[-90.28911600000001,38.084594],"type":"Point"}
}