{
  "type": "Feature",
  "properties": {
    "iso:country":"US",
    "sg:address":"12119 Saint Charles Rock Rd",
    "sg:city":"Bridgeton",
    "sg:classifiers":[
        {
            "category":"Professional",
            "subcategory":"Lawyer & Legal Services",
            "type":"Services"
        }
    ],
    "sg:phone":"+1 314 739 0500",
    "sg:postcode":"63044",
    "sg:province":"MO",
    "wof:name":"Traffic Law Center",
    "wof:placetype":"venue"
},
  "geometry": {"coordinates":[-90.423648,38.748868],"type":"Point"}
}