{
  "type": "Feature",
  "properties": {
    "iso:country":"US",
    "sg:address":"6205 Oak St",
    "sg:city":"Kansas City",
    "sg:classifiers":[
        {
            "category":"Home & Garden",
            "subcategory":"Furniture",
            "type":"Retail Goods"
        }
    ],
    "sg:phone":"+1 816 333 7373",
    "sg:postcode":"64113",
    "sg:province":"MO",
    "sg:tags":[
        "interior",
        "design",
        "provides"
    ],
    "wof:name":"Daltons",
    "wof:placetype":"venue"
},
  "geometry": {"coordinates":[-94.583718,39.013701],"type":"Point"}
}