{
  "type": "Feature",
  "properties": {
    "iso:country":"US",
    "sg:address":"5147 Auriesville Ln",
    "sg:city":"Hazelwood",
    "sg:classifiers":[
        {
            "category":"Building & Trades",
            "subcategory":"Construction",
            "type":"Services"
        }
    ],
    "sg:phone":"+1 314 291 0830",
    "sg:postcode":"63042",
    "sg:province":"MO",
    "sg:tags":[
        "excavation",
        "contractor"
    ],
    "wof:name":"Don Rush Contracting Inc",
    "wof:placetype":"venue"
},
  "geometry": {"coordinates":[-90.40000999999999,38.777314],"type":"Point"}
}