{
  "type": "Feature",
  "properties": {
    "iso:country":"US",
    "sg:address":"5661 Telegraph Rd",
    "sg:city":"Saint Louis",
    "sg:classifiers":[
        {
            "category":"Restaurant",
            "type":"Food & Drink"
        }
    ],
    "sg:menulink":"http://www.allmenus.com/mo/oakville/83944-dominos-pizza/menu/",
    "sg:phone":"+1 314 846 6600",
    "sg:postcode":"63129",
    "sg:province":"MO",
    "sg:tags":[
        "american",
        "wing",
        "pizza"
    ],
    "wof:name":"Domino's Pizza",
    "wof:placetype":"venue"
},
  "geometry": {"coordinates":[-90.306307,38.466527],"type":"Point"}
}