{
  "type": "Feature",
  "properties": {
    "addr:full":"7259 Manchester Rd Saint Louis MO 63143",
    "addr:housenumber":"7259",
    "addr:postcode":"63143",
    "addr:street":"Manchester Rd",
    "iso:country":"US",
    "sg:address":"7259 Manchester Rd",
    "sg:city":"Saint Louis",
    "sg:classifiers":[
        {
            "category":"Building & Trades",
            "subcategory":"Locksmith",
            "type":"Services"
        }
    ],
    "sg:phone":"+1 314 667 4344",
    "sg:postcode":"63143",
    "sg:province":"MO",
    "sg:tags":[
        "key"
    ],
    "wof:name":"24 Hour Emergency Locksmith",
    "wof:placetype":"venue"
},
  "geometry": {"coordinates":[-90.316349,38.613693],"type":"Point"}
}