{
  "type": "Feature",
  "properties": {
    "iso:country":"US",
    "sg:address":"526 Saint Josephs Ln",
    "sg:city":"Ballwin",
    "sg:classifiers":[
        {
            "category":"Organizations",
            "subcategory":"Religious Organization",
            "type":"Services"
        }
    ],
    "sg:phone":"+1 636 227 9833",
    "sg:postcode":"63021",
    "sg:province":"MO",
    "sg:tags":[
        "church"
    ],
    "wof:name":"St Joseph's Church",
    "wof:placetype":"venue"
},
  "geometry": {"coordinates":[-90.51732800000001,38.586837],"type":"Point"}
}