{
  "type": "Feature",
  "properties": {
    "iso:country":"US",
    "sg:address":"26860 Stillings Rd",
    "sg:city":"Platte City",
    "sg:classifiers":[
        {
            "category":"Government",
            "subcategory":"Office",
            "type":"Public Place"
        }
    ],
    "sg:phone":"+1 816 546 3312",
    "sg:postcode":"64079",
    "sg:province":"MO",
    "sg:tags":[
        "transportation"
    ],
    "wof:name":"Farley Special Road District",
    "wof:placetype":"venue"
},
  "geometry": {"coordinates":[-94.888254,39.319687],"type":"Point"}
}