{
  "type": "Feature",
  "properties": {
    "iso:country":"US",
    "sg:address":"1080 Kimberly Ln",
    "sg:city":"Saint Peters",
    "sg:classifiers":[
        {
            "category":"Shopping",
            "subcategory":"Bicycles & Sporting Goods",
            "type":"Retail Goods"
        }
    ],
    "sg:phone":"+1 636 441 9200",
    "sg:postcode":"63376",
    "sg:province":"MO",
    "wof:name":"Murphys Sporting Goods",
    "wof:placetype":"venue"
},
  "geometry": {"coordinates":[-90.61547899999999,38.78853],"type":"Point"}
}