{
  "type": "Feature",
  "properties": {
    "iso:country":"US",
    "sg:address":"3627 Bates St",
    "sg:city":"St Louis",
    "sg:classifiers":[
        {
            "category":"Shopping",
            "subcategory":"Computers & Home Electronics",
            "type":"Retail Goods"
        }
    ],
    "sg:phone":"+1 314 351 9955",
    "sg:postcode":"63116",
    "sg:province":"MO",
    "sg:tags":[
        "television",
        "radio"
    ],
    "wof:name":"Carl Will TV Inc",
    "wof:placetype":"venue"
},
  "geometry": {"coordinates":[-90.254953,38.568844],"type":"Point"}
}