{
  "type": "Feature",
  "properties": {
    "iso:country":"US",
    "sg:address":"1831 Chestnut St",
    "sg:city":"St Louis",
    "sg:classifiers":[
        {
            "category":"Insurance",
            "subcategory":"Insurance Agent",
            "type":"Services"
        }
    ],
    "sg:phone":"+1 314 923 4444",
    "sg:postcode":"63103",
    "sg:province":"MO",
    "wof:name":"Blue Cross & Blue Shield Of MO",
    "wof:placetype":"venue"
},
  "geometry": {"coordinates":[-90.20716899999999,38.630158],"type":"Point"}
}