{
  "type": "Feature",
  "properties": {
    "iso:country":"US",
    "sg:address":"714 N State Hwy 47",
    "sg:city":"Warrenton",
    "sg:classifiers":[
        {
            "category":"Autos & Motor Vehicles",
            "subcategory":"Fuel & Gas Station",
            "type":"Retail Goods"
        }
    ],
    "sg:phone":"+1 636 456 4182",
    "sg:postcode":"63383",
    "sg:province":"MO",
    "sg:tags":[
        "convenience",
        "station",
        "store"
    ],
    "wof:name":"KWIK Store",
    "wof:placetype":"venue"
},
  "geometry": {"coordinates":[-91.141182,38.819129],"type":"Point"}
}