{
  "type": "Feature",
  "properties": {
    "iso:country":"US",
    "sg:address":"14107 Denver Rd",
    "sg:city":"Grandview",
    "sg:classifiers":[
        {
            "category":"Building & Trades",
            "subcategory":"Construction",
            "type":"Services"
        }
    ],
    "sg:phone":"+1 816 763 3501",
    "sg:postcode":"64030",
    "sg:province":"MO",
    "sg:tags":[
        "acoustical",
        "drywall",
        "contractor"
    ],
    "wof:name":"Kerr Systems Inc",
    "wof:placetype":"venue"
},
  "geometry": {"coordinates":[-94.534217,38.865956],"type":"Point"}
}