{
  "type": "Feature",
  "properties": {
    "iso:country":"US",
    "sg:address":"1066 Prince Albert Ct",
    "sg:city":"O Fallon",
    "sg:classifiers":[
        {
            "category":"Building & Trades",
            "subcategory":"Construction",
            "type":"Services"
        }
    ],
    "sg:phone":"+1 636 300 4487",
    "sg:postcode":"63366",
    "sg:province":"MO",
    "sg:tags":[
        "contractor"
    ],
    "wof:name":"Maine Bros Fencing",
    "wof:placetype":"venue"
},
  "geometry": {"coordinates":[-90.677002,38.815821],"type":"Point"}
}