{
  "type": "Feature",
  "properties": {
    "iso:country":"US",
    "sg:address":"3545 Evergreen Ln",
    "sg:city":"St Louis",
    "sg:classifiers":[
        {
            "category":"Retail",
            "subcategory":"Auto Repair",
            "type":"Services"
        },
        {
            "category":"Retail",
            "subcategory":"Auto Rental",
            "type":"Services"
        }
    ],
    "sg:phone":"+1 314 845 9098",
    "sg:postcode":"63125",
    "sg:province":"MO",
    "sg:tags":[
        "automobile",
        "leasing",
        "general"
    ],
    "wof:name":"Auto Connection Sales & Lsng",
    "wof:placetype":"venue"
},
  "geometry": {"coordinates":[-90.322433,38.50798],"type":"Point"}
}