{
  "type": "Feature",
  "properties": {
    "iso:country":"US",
    "sg:address":"36 Country Fair Ln",
    "sg:city":"Saint Louis",
    "sg:classifiers":[
        {
            "category":"Shopping",
            "type":"Retail Goods"
        }
    ],
    "sg:phone":"+1 314 994 9776",
    "sg:postcode":"63141",
    "sg:province":"MO",
    "sg:tags":[
        "equipment",
        "medical"
    ],
    "wof:name":"Stat Technologies Inc",
    "wof:placetype":"venue"
},
  "geometry": {"coordinates":[-90.408714,38.659586],"type":"Point"}
}