{
  "type": "Feature",
  "properties": {
    "iso:country":"US",
    "sg:address":"650 E Cherry St",
    "sg:city":"Troy",
    "sg:classifiers":[
        {
            "category":"Shopping",
            "subcategory":"Florist",
            "type":"Retail Goods"
        }
    ],
    "sg:phone":"+1 636 528 8528",
    "sg:postcode":"63379",
    "sg:province":"MO",
    "wof:name":"Troy Flower & Gift Shop",
    "wof:placetype":"venue"
},
  "geometry": {"coordinates":[-90.97536599999999,38.981354],"type":"Point"}
}