{
  "type": "Feature",
  "properties": {
    "iso:country":"US",
    "sg:address":"14195 Clayton Rd",
    "sg:city":"Chesterfield",
    "sg:classifiers":[
        {
            "category":"Retail",
            "subcategory":"Auto Rental",
            "type":"Services"
        }
    ],
    "sg:phone":"+1 636 227 5261",
    "sg:postcode":"63017",
    "sg:province":"MO",
    "sg:tags":[
        "truck"
    ],
    "wof:name":"Ryder Truck Rental One Way Inc",
    "wof:placetype":"venue"
},
  "geometry": {"coordinates":[-90.52323699999999,38.621992],"type":"Point"}
}