{
  "type": "Feature",
  "properties": {
    "addr:full":"3601 Faraon St St Joseph MO 64506",
    "addr:housenumber":"3601",
    "addr:postcode":"64506",
    "addr:street":"Faraon St",
    "iso:country":"US",
    "sg:address":"3601 Faraon St",
    "sg:city":"St Joseph",
    "sg:classifiers":[
        {
            "category":"Shopping",
            "subcategory":"Pharmacy",
            "type":"Retail Goods"
        }
    ],
    "sg:phone":"+1 816 233 9963",
    "sg:postcode":"64506",
    "sg:province":"MO",
    "wof:name":"Medicine Shoppe Pharmacy",
    "wof:placetype":"venue"
},
  "geometry": {"coordinates":[-94.80356999999999,39.769731],"type":"Point"}
}