{
  "type": "Feature",
  "properties": {
    "iso:country":"US",
    "sg:address":"1202 Market St",
    "sg:city":"Hermann",
    "sg:classifiers":[
        {
            "category":"Social Services",
            "type":"Services"
        }
    ],
    "sg:phone":"+1 573 486 0136",
    "sg:postcode":"65041",
    "sg:province":"MO",
    "wof:name":"Gasconade County Counseling SE",
    "wof:placetype":"venue"
},
  "geometry": {"coordinates":[-91.438682,38.696887],"type":"Point"}
}