{
  "type": "Feature",
  "properties": {
    "iso:country":"US",
    "sg:address":"1103 S Mitchell Ave",
    "sg:city":"Chillicothe",
    "sg:classifiers":[
        {
            "category":"Home & Garden",
            "subcategory":"Garden Supply",
            "type":"Retail Goods"
        }
    ],
    "sg:phone":"+1 660 646 4644",
    "sg:postcode":"64601",
    "sg:province":"MO",
    "wof:name":"Kille Kubota",
    "wof:placetype":"venue"
},
  "geometry": {"coordinates":[-93.53939200000001,39.776598],"type":"Point"}
}