{
  "type": "Feature",
  "properties": {
    "iso:country":"US",
    "sg:address":"1214 Washington Ave",
    "sg:city":"St Louis",
    "sg:classifiers":[
        {
            "category":"Building & Trades",
            "subcategory":"Construction",
            "type":"Services"
        }
    ],
    "sg:phone":"+1 314 241 1010",
    "sg:postcode":"63103",
    "sg:province":"MO",
    "sg:tags":[
        "resurfacing",
        "laying",
        "refinishing",
        "floor"
    ],
    "wof:name":"Third Floor Gallery On Wshngtn",
    "wof:placetype":"venue"
},
  "geometry": {"coordinates":[-90.198075,38.631963],"type":"Point"}
}