{
  "type": "Feature",
  "properties": {
    "iso:country":"US",
    "sg:address":"6972 N Broadway Ave",
    "sg:city":"Kansas City",
    "sg:classifiers":[
        {
            "category":"Recreation",
            "type":"Entertainment"
        }
    ],
    "sg:phone":"+1 816 436 9556",
    "sg:postcode":"64118",
    "sg:province":"MO",
    "wof:name":"Arrowhead Realty",
    "wof:placetype":"venue"
},
  "geometry": {"coordinates":[-94.585438,39.219822],"type":"Point"}
}