{
  "type": "Feature",
  "properties": {
    "iso:country":"US",
    "sg:address":"16982 Manchester Rd",
    "sg:city":"Grover",
    "sg:classifiers":[
        {
            "category":"Government",
            "subcategory":"Post Office",
            "type":"Public Place"
        }
    ],
    "sg:phone":"+1 636 000 1111",
    "sg:postcode":"63040",
    "sg:province":"MO",
    "wof:name":"US Post Office",
    "wof:placetype":"venue"
},
  "geometry": {"coordinates":[-90.64148400000001,38.576051],"type":"Point"}
}