{
  "type": "Feature",
  "properties": {
    "iso:country":"US",
    "sg:address":"1005 Waterford Dr",
    "sg:city":"Florissant",
    "sg:classifiers":[
        {
            "category":"Education",
            "subcategory":"School",
            "type":"Public Place"
        }
    ],
    "sg:phone":"+1 314 506 9029",
    "sg:postcode":"63033",
    "sg:province":"MO",
    "sg:tags":[
        "k-",
        "private"
    ],
    "sg:website":"http://www.fergflor.k12.mo.us",
    "wof:name":"Duchesne School Ferguson",
    "wof:placetype":"venue"
},
  "geometry": {"coordinates":[-90.300842,38.792845],"type":"Point"}
}