{
  "type": "Feature",
  "properties": {
    "iso:country":"US",
    "sg:address":"2037 S River St",
    "sg:city":"Carthage",
    "sg:classifiers":[
        {
            "category":"Building & Trades",
            "subcategory":"Construction",
            "type":"Services"
        }
    ],
    "sg:phone":"+1 417 358 8894",
    "sg:postcode":"64836",
    "sg:province":"MO",
    "sg:tags":[
        "concrete",
        "contractor"
    ],
    "wof:name":"Decorative Concrete Specialist",
    "wof:placetype":"venue"
},
  "geometry": {"coordinates":[-94.301153,37.153724],"type":"Point"}
}