{
  "type": "Feature",
  "properties": {
    "iso:country":"US",
    "sg:address":"513 W Atlantic St",
    "sg:city":"Springfield",
    "sg:classifiers":[
        {
            "category":"Retail",
            "subcategory":"Auto Repair",
            "type":"Services"
        }
    ],
    "sg:phone":"+1 417 831 6580",
    "sg:postcode":"65803",
    "sg:province":"MO",
    "sg:tags":[
        "body"
    ],
    "wof:name":"Quality Auto Works",
    "wof:placetype":"venue"
},
  "geometry": {"coordinates":[-93.29548699999999,37.233439],"type":"Point"}
}