{
  "type": "Feature",
  "properties": {
    "iso:country":"US",
    "sg:address":"205 E Pine St",
    "sg:city":"Strafford",
    "sg:classifiers":[
        {
            "category":"Cinema",
            "subcategory":"Movie Rental",
            "type":"Entertainment"
        }
    ],
    "sg:phone":"+1 417 736 3026",
    "sg:postcode":"65757",
    "sg:province":"MO",
    "sg:tags":[
        "video",
        "tape"
    ],
    "wof:name":"S & S Video",
    "wof:placetype":"venue"
},
  "geometry": {"coordinates":[-93.115497,37.269226],"type":"Point"}
}