{
  "type": "Feature",
  "properties": {
    "iso:country":"US",
    "sg:address":"275 S New Florissant Rd",
    "sg:city":"Florissant",
    "sg:classifiers":[
        {
            "category":"Recreation",
            "type":"Entertainment"
        }
    ],
    "sg:phone":"+1 314 839 7673",
    "sg:postcode":"63031",
    "sg:province":"MO",
    "sg:tags":[
        "pool",
        "swimming"
    ],
    "wof:name":"Bangert Swimming Pool",
    "wof:placetype":"venue"
},
  "geometry": {"coordinates":[-90.32538599999999,38.784103],"type":"Point"}
}