{
  "type": "Feature",
  "properties": {
    "iso:country":"US",
    "sg:address":"6591 Scanlan Ave",
    "sg:city":"Saint Louis",
    "sg:classifiers":[
        {
            "category":"Professional",
            "type":"Services"
        }
    ],
    "sg:phone":"+1 314 781 8561",
    "sg:postcode":"63139",
    "sg:province":"MO",
    "wof:name":"Yates & Sons Inc",
    "wof:placetype":"venue"
},
  "geometry": {"coordinates":[-90.30247300000001,38.605735],"type":"Point"}
}