{
  "type": "Feature",
  "properties": {
    "iso:country":"US",
    "sg:address":"3501 E Meyer Blvd",
    "sg:city":"Kansas City",
    "sg:classifiers":[
        {
            "category":"Organizations",
            "subcategory":"Religious Organization",
            "type":"Services"
        }
    ],
    "sg:phone":"+1 816 361 0852",
    "sg:postcode":"64132",
    "sg:province":"MO",
    "sg:tags":[
        "church"
    ],
    "wof:name":"Saint John AME Church",
    "wof:placetype":"venue"
},
  "geometry": {"coordinates":[-94.54479499999999,39.007352],"type":"Point"}
}