{
  "type": "Feature",
  "properties": {
    "iso:country":"US",
    "sg:address":"218 E High St",
    "sg:city":"Jefferson City",
    "sg:classifiers":[
        {
            "category":"Professional",
            "subcategory":"Art Services",
            "type":"Services"
        }
    ],
    "sg:phone":"+1 573 635 0250",
    "sg:postcode":"65101",
    "sg:province":"MO",
    "sg:tags":[
        "photographer"
    ],
    "wof:name":"Full Spectrum Photo",
    "wof:placetype":"venue"
},
  "geometry": {"coordinates":[-92.17101700000001,38.575842],"type":"Point"}
}