{
  "type": "Feature",
  "properties": {
    "iso:country":"US",
    "sg:address":"2020 Princeton Rd",
    "sg:city":"Trenton",
    "sg:classifiers":[
        {
            "category":"Home & Garden",
            "subcategory":"Furniture",
            "type":"Retail Goods"
        }
    ],
    "sg:phone":"+1 660 359 6128",
    "sg:postcode":"64683",
    "sg:province":"MO",
    "sg:tags":[
        "store"
    ],
    "wof:name":"A&A Termite Control",
    "wof:placetype":"venue"
},
  "geometry": {"coordinates":[-93.610707,40.084351],"type":"Point"}
}