{
  "type": "Feature",
  "properties": {
    "iso:country":"US",
    "sg:address":"10803 Olive Blvd",
    "sg:city":"St Louis",
    "sg:classifiers":[
        {
            "category":"Health Services",
            "subcategory":"Doctor",
            "type":"Services"
        }
    ],
    "sg:phone":"+1 314 432 4335",
    "sg:postcode":"63141",
    "sg:province":"MO",
    "sg:tags":[
        "physician",
        "surgeon"
    ],
    "wof:name":"Kathy C Maupin MD",
    "wof:placetype":"venue"
},
  "geometry": {"coordinates":[-90.415802,38.673286],"type":"Point"}
}