{
  "type": "Feature",
  "properties": {
    "iso:country":"US",
    "sg:address":"15691 State Highway 164",
    "sg:city":"Hornersville",
    "sg:classifiers":[
        {
            "category":"Restaurant",
            "type":"Food & Drink"
        }
    ],
    "sg:phone":"+1 573 737 2130",
    "sg:postcode":"63855",
    "sg:province":"MO",
    "wof:name":"Moore Max And Marty",
    "wof:placetype":"venue"
},
  "geometry": {"coordinates":[-90.096854,36.078224],"type":"Point"}
}