{
  "type": "Feature",
  "properties": {
    "iso:country":"US",
    "sg:address":"131 W Argonne Dr",
    "sg:city":"Kirkwood",
    "sg:classifiers":[
        {
            "category":"Restaurant",
            "type":"Food & Drink"
        }
    ],
    "sg:phone":"+1 314 965 8050",
    "sg:postcode":"63122",
    "sg:province":"MO",
    "wof:name":"Massa's Of Kirkwood Inc",
    "wof:placetype":"venue"
},
  "geometry": {"coordinates":[-90.408016,38.581319],"type":"Point"}
}