{
  "type": "Feature",
  "properties": {
    "iso:country":"US",
    "sg:address":"522 Locust Ln",
    "sg:city":"Kansas City",
    "sg:classifiers":[
        {
            "category":"Local Transit",
            "type":"Transportation"
        }
    ],
    "sg:phone":"+1 816 471 1234",
    "sg:postcode":"64106",
    "sg:province":"MO",
    "sg:tags":[
        "passenger"
    ],
    "wof:name":"Crystal Limousine Service",
    "wof:placetype":"venue"
},
  "geometry": {"coordinates":[-94.57781,39.108433],"type":"Point"}
}