{
  "type": "Feature",
  "properties": {
    "iso:country":"US",
    "sg:address":"305 Richmond Dr",
    "sg:city":"Warrenton",
    "sg:classifiers":[
        {
            "category":"Personal",
            "subcategory":"Barber",
            "type":"Services"
        }
    ],
    "sg:phone":"+1 636 456 3881",
    "sg:postcode":"63383",
    "sg:province":"MO",
    "sg:tags":[
        "shop"
    ],
    "wof:name":"Hair Station 66",
    "wof:placetype":"venue"
},
  "geometry": {"coordinates":[-91.130999,38.820908],"type":"Point"}
}