{
  "type": "Feature",
  "properties": {
    "iso:country":"US",
    "sg:address":"36 Barkley Dr",
    "sg:city":"Waynesville",
    "sg:classifiers":[
        {
            "category":"Insurance",
            "subcategory":"Insurance Agent",
            "type":"Services"
        }
    ],
    "sg:phone":"+1 573 774 2233",
    "sg:postcode":"65583",
    "sg:province":"MO",
    "wof:name":"INA Fernandez Insurance",
    "wof:placetype":"venue"
},
  "geometry": {"coordinates":[-92.238669,37.800059],"type":"Point"}
}