{
  "type": "Feature",
  "properties": {
    "iso:country":"US",
    "sg:address":"150 SE 25th Ln",
    "sg:city":"Lamar",
    "sg:classifiers":[
        {
            "category":"Farming",
            "subcategory":"Farm",
            "type":"Manufacturing & Wholesale Goods"
        }
    ],
    "sg:phone":"+1 417 682 6266",
    "sg:postcode":"64759",
    "sg:province":"MO",
    "sg:tags":[
        "crop",
        "general"
    ],
    "wof:name":"Forst Farms Inc",
    "wof:placetype":"venue"
},
  "geometry": {"coordinates":[-94.25340799999999,37.474275],"type":"Point"}
}