{
  "type": "Feature",
  "properties": {
    "iso:country":"US",
    "sg:address":"504 E Bond St",
    "sg:city":"Monett",
    "sg:classifiers":[
        {
            "category":"Retail",
            "subcategory":"Laundry & Dry Cleaning",
            "type":"Services"
        }
    ],
    "sg:phone":"+1 417 235 7724",
    "sg:postcode":"65708",
    "sg:province":"MO",
    "sg:tags":[
        "cleaners"
    ],
    "wof:name":"Fulp Cleaners",
    "wof:placetype":"venue"
},
  "geometry": {"coordinates":[-93.92141599999999,36.922485],"type":"Point"}
}