{
  "type": "Feature",
  "properties": {
    "iso:country":"US",
    "sg:address":"12980 Diver Dr",
    "sg:city":"Racine",
    "sg:classifiers":[
        {
            "category":"Organizations",
            "subcategory":"Religious Organization",
            "type":"Services"
        }
    ],
    "sg:phone":"+1 417 776 2214",
    "sg:postcode":"64850",
    "sg:province":"MO",
    "sg:tags":[
        "church"
    ],
    "wof:name":"Racine Apostolic Church",
    "wof:placetype":"venue"
},
  "geometry": {"coordinates":[-94.553296,36.881407],"type":"Point"}
}