{
  "type": "Feature",
  "properties": {
    "iso:country":"US",
    "sg:address":"8247 NW Birch Ln",
    "sg:city":"Kansas City",
    "sg:classifiers":[
        {
            "category":"Sports & Exercise",
            "subcategory":"Gym",
            "type":"Entertainment"
        }
    ],
    "sg:phone":"+1 816 587 2130",
    "sg:postcode":"64151",
    "sg:province":"MO",
    "sg:tags":[
        "fitness",
        "physical",
        "facility"
    ],
    "wof:name":"Marantha of Brookfield",
    "wof:placetype":"venue"
},
  "geometry": {"coordinates":[-94.643777,39.246197],"type":"Point"}
}