{
  "type": "Feature",
  "properties": {
    "addr:full":"505 Allen Rd Campbell MO 63933",
    "addr:housenumber":"505",
    "addr:postcode":"63933",
    "addr:street":"Allen Rd",
    "iso:country":"US",
    "sg:address":"505 Allen Rd",
    "sg:city":"Campbell",
    "sg:classifiers":[
        {
            "category":"Place Of Worship",
            "type":"Public Place"
        }
    ],
    "sg:phone":"+1 573 246 2503",
    "sg:postcode":"63933",
    "sg:province":"MO",
    "sg:tags":[
        "church"
    ],
    "wof:name":"Assembly First",
    "wof:placetype":"venue"
},
  "geometry": {"coordinates":[-90.07122,36.499489],"type":"Point"}
}