{
  "type": "Feature",
  "properties": {
    "iso:country":"US",
    "sg:address":"18407 Old Lexington Rd",
    "sg:city":"Independence",
    "sg:classifiers":[
        {
            "category":"Freight",
            "type":"Transportation"
        }
    ],
    "sg:phone":"+1 816 796 9833",
    "sg:postcode":"64058",
    "sg:province":"MO",
    "sg:tags":[
        "operator",
        "trucking"
    ],
    "wof:name":"Herb Merritt Distributors",
    "wof:placetype":"venue"
},
  "geometry": {"coordinates":[-94.35906300000001,39.132433],"type":"Point"}
}