{
  "type": "Feature",
  "properties": {
    "addr:full":"5524 Riverview Blvd St Louis MO 63120",
    "addr:housenumber":"5524",
    "addr:postcode":"63120",
    "addr:street":"Riverview Blvd",
    "iso:country":"US",
    "sg:address":"5524 Riverview Blvd",
    "sg:city":"St Louis",
    "sg:classifiers":[
        {
            "category":"Retail",
            "subcategory":"Auto Repair",
            "type":"Services"
        }
    ],
    "sg:phone":"+1 314 383 2019",
    "sg:postcode":"63120",
    "sg:province":"MO",
    "sg:tags":[
        "transmission"
    ],
    "wof:name":"Roy's Transmission",
    "wof:placetype":"venue"
},
  "geometry": {"coordinates":[-90.251182,38.704983],"type":"Point"}
}