{
  "type": "Feature",
  "properties": {
    "iso:country":"US",
    "sg:address":"6289 N Oak Fwy",
    "sg:city":"Kansas City",
    "sg:classifiers":[
        {
            "category":"Home & Garden",
            "subcategory":"Carpets & Floor Coverings",
            "type":"Retail Goods"
        }
    ],
    "sg:phone":"+1 816 452 8109",
    "sg:postcode":"64118",
    "sg:province":"MO",
    "sg:tags":[
        "dealer",
        "rug"
    ],
    "wof:name":"Weber Carpet",
    "wof:placetype":"venue"
},
  "geometry": {"coordinates":[-94.576196,39.207396],"type":"Point"}
}