{
  "type": "Feature",
  "properties": {
    "iso:country":"US",
    "sg:address":"7925 Clayton Rd",
    "sg:city":"Saint Louis",
    "sg:classifiers":[
        {
            "category":"Professional",
            "subcategory":"Business Services",
            "type":"Services"
        }
    ],
    "sg:phone":"+1 314 862 6049",
    "sg:postcode":"63117",
    "sg:province":"MO",
    "sg:tags":[
        "support",
        "legal"
    ],
    "wof:name":"Master File Inc",
    "wof:placetype":"venue"
},
  "geometry": {"coordinates":[-90.341516,38.637783],"type":"Point"}
}