{
  "type": "Feature",
  "properties": {
    "iso:country":"US",
    "sg:address":"1491 W 52nd St",
    "sg:city":"Carthage",
    "sg:classifiers":[
        {
            "category":"Building & Trades",
            "subcategory":"Construction",
            "type":"Services"
        }
    ],
    "sg:phone":"+1 417 358 2799",
    "sg:postcode":"64836",
    "sg:province":"MO",
    "sg:tags":[
        "millwright"
    ],
    "wof:name":"Headys Millwright",
    "wof:placetype":"venue"
},
  "geometry": {"coordinates":[-94.33098200000001,37.096916],"type":"Point"}
}