{
  "type": "Feature",
  "properties": {
    "iso:country":"US",
    "sg:address":"258 Maple Grove Way",
    "sg:city":"Columbia",
    "sg:classifiers":[
        {
            "category":"Retail",
            "subcategory":"Repair Shop",
            "type":"Services"
        }
    ],
    "sg:phone":"+1 573 442 8107",
    "sg:postcode":"65203",
    "sg:province":"MO",
    "sg:tags":[
        "welding"
    ],
    "wof:name":"Wegener Welding",
    "wof:placetype":"venue"
},
  "geometry": {"coordinates":[-92.348274,38.898369],"type":"Point"}
}