{
  "type": "Feature",
  "properties": {
    "iso:country":"US",
    "sg:address":"950 S Washington St",
    "sg:city":"Chillicothe",
    "sg:classifiers":[
        {
            "category":"Autos & Motor Vehicles",
            "subcategory":"Auto Supplies",
            "type":"Retail Goods"
        }
    ],
    "sg:phone":"+1 660 646 2985",
    "sg:postcode":"64601",
    "sg:province":"MO",
    "sg:tags":[
        "automobile",
        "parts"
    ],
    "wof:name":"Carquest-Chillicothe",
    "wof:placetype":"venue"
},
  "geometry": {"coordinates":[-93.552842,39.777821],"type":"Point"}
}