{
  "type": "Feature",
  "properties": {
    "iso:country":"US",
    "sg:address":"8031 SW State Hwy 116",
    "sg:city":"Rushville",
    "sg:phone":"+1 816 688 7809",
    "sg:postcode":"64484",
    "sg:province":"MO",
    "sg:tags":[
        "farm",
        "corn",
        "grain",
        "cash",
        "tobacco"
    ],
    "wof:name":"Daniel Berry",
    "wof:placetype":"venue"
},
  "geometry": {"coordinates":[-95.00310399999999,39.56758],"type":"Point"}
}