{
  "type": "Feature",
  "properties": {
    "iso:country":"US",
    "sg:address":"1200 E Broadway Blvd",
    "sg:city":"Sedalia",
    "sg:classifiers":[
        {
            "category":"Organizations",
            "subcategory":"Religious Organization",
            "type":"Services"
        }
    ],
    "sg:phone":"+1 660 826 1525",
    "sg:postcode":"65301",
    "sg:province":"MO",
    "sg:tags":[
        "church"
    ],
    "wof:name":"Salvation Army",
    "wof:placetype":"venue"
},
  "geometry": {"coordinates":[-93.213498,38.703621],"type":"Point"}
}