{
  "type": "Feature",
  "properties": {
    "iso:country":"US",
    "sg:address":"8400 Natural Bridge Rd",
    "sg:city":"St Louis",
    "sg:classifiers":[
        {
            "category":"Insurance",
            "subcategory":"Insurance Agent",
            "type":"Services"
        }
    ],
    "sg:phone":"+1 314 389 4027",
    "sg:postcode":"63121",
    "sg:province":"MO",
    "wof:name":"American Family Insurance",
    "wof:placetype":"venue"
},
  "geometry": {"coordinates":[-90.31718600000001,38.708532],"type":"Point"}
}