{
  "type": "Feature",
  "properties": {
    "iso:country":"US",
    "sg:address":"4032 Butler Hill Rd",
    "sg:city":"Saint Louis",
    "sg:classifiers":[
        {
            "category":"Personal",
            "type":"Services"
        }
    ],
    "sg:phone":"+1 314 845 2826",
    "sg:postcode":"63129",
    "sg:province":"MO",
    "sg:tags":[
        "parlor",
        "tanning"
    ],
    "wof:name":"Cindees Electric Beach",
    "wof:placetype":"venue"
},
  "geometry": {"coordinates":[-90.350212,38.485743],"type":"Point"}
}