{
  "type": "Feature",
  "properties": {
    "iso:country":"US",
    "sg:address":"2083 US Hwy 67",
    "sg:city":"Festus",
    "sg:classifiers":[
        {
            "category":"Autos & Motor Vehicles",
            "subcategory":"Auto Supplies",
            "type":"Retail Goods"
        },
        {
            "category":"Wholesale",
            "subcategory":"Auto Parts",
            "type":"Manufacturing & Wholesale Goods"
        }
    ],
    "sg:phone":"+1 636 931 4640",
    "sg:postcode":"63028",
    "sg:province":"MO",
    "sg:tags":[
        "bo",
        "truck",
        "accessory"
    ],
    "sg:website":"www.bufftruck.com",
    "wof:name":"Buff Truck Outfitters",
    "wof:placetype":"venue"
},
  "geometry": {"coordinates":[-90.436667,38.187928],"type":"Point"}
}