{
  "type": "Feature",
  "properties": {
    "iso:country":"US",
    "sg:address":"144 S Highway J Kk",
    "sg:city":"Lamar",
    "sg:classifiers":[
        {
            "category":"Professional",
            "type":"Services"
        }
    ],
    "sg:phone":"+1 417 682 2690",
    "sg:postcode":"64759",
    "sg:province":"MO",
    "sg:tags":[
        "caterer"
    ],
    "wof:name":"The Honey Pot",
    "wof:placetype":"venue"
},
  "geometry": {"coordinates":[-94.354365,37.454691],"type":"Point"}
}