{
  "type": "Feature",
  "properties": {
    "iso:country":"US",
    "sg:address":"17972 Argonne Estates Dr",
    "sg:city":"Florissant",
    "sg:classifiers":[
        {
            "category":"Shopping",
            "subcategory":"Gifts & Souvenirs",
            "type":"Retail Goods"
        }
    ],
    "sg:phone":"+1 314 837 4411",
    "sg:postcode":"63034",
    "sg:province":"MO",
    "wof:name":"Eye Impressive Gift Shop",
    "wof:placetype":"venue"
},
  "geometry": {"coordinates":[-90.280046,38.850482],"type":"Point"}
}