{
  "type": "Feature",
  "properties": {
    "iso:country":"US",
    "sg:address":"450 Cumberland Way",
    "sg:city":"Sullivan",
    "sg:classifiers":[
        {
            "category":"Restaurant",
            "type":"Food & Drink"
        }
    ],
    "sg:phone":"+1 573 860 8812",
    "sg:postcode":"63080",
    "sg:province":"MO",
    "wof:name":"China King Sullivan",
    "wof:placetype":"venue"
},
  "geometry": {"coordinates":[-91.156739,38.217865],"type":"Point"}
}