{
  "type": "Feature",
  "properties": {
    "iso:country":"US",
    "sg:address":"213 Stewart St",
    "sg:city":"Bernie",
    "sg:classifiers":[
        {
            "category":"Organizations",
            "subcategory":"Religious Organization",
            "type":"Services"
        }
    ],
    "sg:phone":"+1 573 293 5627",
    "sg:postcode":"63822",
    "sg:province":"MO",
    "sg:tags":[
        "church"
    ],
    "wof:name":"Bernie Christian Church",
    "wof:placetype":"venue"
},
  "geometry": {"coordinates":[-89.968154,36.670678],"type":"Point"}
}