{
  "type": "Feature",
  "properties": {
    "iso:country":"US",
    "sg:address":"6321 W Florissant Ave",
    "sg:city":"Saint Louis",
    "sg:classifiers":[
        {
            "category":"Home & Garden",
            "subcategory":"Furniture",
            "type":"Retail Goods"
        }
    ],
    "sg:phone":"+1 314 383 8111",
    "sg:postcode":"63136",
    "sg:province":"MO",
    "sg:tags":[
        "store"
    ],
    "wof:name":"Dynasty Discount & More",
    "wof:placetype":"venue"
},
  "geometry": {"coordinates":[-90.254998,38.713379],"type":"Point"}
}