{
  "type": "Feature",
  "properties": {
    "iso:country":"US",
    "sg:address":"201 NE Sunnyside School Rd",
    "sg:city":"Blue Springs",
    "sg:classifiers":[
        {
            "category":"Education",
            "subcategory":"School",
            "type":"Public Place"
        }
    ],
    "sg:phone":"+1 816 224 1380",
    "sg:postcode":"64014",
    "sg:province":"MO",
    "wof:name":"James Walker Elementary School",
    "wof:placetype":"venue"
},
  "geometry": {"coordinates":[-94.25851400000001,39.017558],"type":"Point"}
}