{
  "type": "Feature",
  "properties": {
    "iso:country":"US",
    "sg:address":"255 N Main Cross St",
    "sg:city":"Bowling Green",
    "sg:classifiers":[
        {
            "category":"Retail",
            "subcategory":"Auto Repair",
            "type":"Services"
        }
    ],
    "sg:phone":"+1 573 324 2440",
    "sg:postcode":"63334",
    "sg:province":"MO",
    "sg:tags":[
        "general"
    ],
    "wof:name":"Glens Auto Repair",
    "wof:placetype":"venue"
},
  "geometry": {"coordinates":[-91.194147,39.343949],"type":"Point"}
}