{
  "type": "Feature",
  "properties": {
    "iso:country":"US",
    "sg:address":"3000 S Hanley Rd",
    "sg:city":"St Louis",
    "sg:classifiers":[
        {
            "category":"Shopping",
            "subcategory":"Bicycles & Sporting Goods",
            "type":"Retail Goods"
        }
    ],
    "sg:phone":"+1 314 647 8054",
    "sg:postcode":"63144",
    "sg:province":"MO",
    "sg:website":"www.proamgolfctr.com",
    "wof:name":"Pro AM Golf",
    "wof:placetype":"venue"
},
  "geometry": {"coordinates":[-90.332815,38.607652],"type":"Point"}
}