{
  "type": "Feature",
  "properties": {
    "iso:country":"US",
    "sg:address":"400 First Capitol Dr",
    "sg:city":"St Charles",
    "sg:classifiers":[
        {
            "category":"Health Services",
            "subcategory":"Doctor",
            "type":"Services"
        }
    ],
    "sg:phone":"+1 636 916 0633",
    "sg:postcode":"63301",
    "sg:province":"MO",
    "sg:tags":[
        "physician",
        "surgeon"
    ],
    "wof:name":"Esse Health",
    "wof:placetype":"venue"
},
  "geometry": {"coordinates":[-90.48693900000001,38.78114],"type":"Point"}
}