{
  "type": "Feature",
  "properties": {
    "iso:country":"US",
    "sg:address":"2111 Plattin Rd",
    "sg:city":"Festus",
    "sg:classifiers":[
        {
            "category":"Professional",
            "type":"Services"
        }
    ],
    "sg:phone":"+1 636 937 6998",
    "sg:postcode":"63028",
    "sg:province":"MO",
    "sg:tags":[
        "establishment"
    ],
    "wof:name":"Berwyn Enterprises",
    "wof:placetype":"venue"
},
  "geometry": {"coordinates":[-90.402218,38.173124],"type":"Point"}
}