{
  "type": "Feature",
  "properties": {
    "iso:country":"US",
    "sg:address":"950 Providence Ave",
    "sg:city":"St Louis",
    "sg:classifiers":[
        {
            "category":"Retail",
            "subcategory":"Portrait Studio",
            "type":"Services"
        }
    ],
    "sg:phone":"+1 314 401 8089",
    "sg:postcode":"63119",
    "sg:province":"MO",
    "sg:tags":[
        "photographer"
    ],
    "wof:name":"Sarah Carmody Photography",
    "wof:placetype":"venue"
},
  "geometry": {"coordinates":[-90.332995,38.598618],"type":"Point"}
}