{
  "type": "Feature",
  "properties": {
    "iso:country":"US",
    "sg:address":"21995 State Hwy 32",
    "sg:city":"Ste Genevieve",
    "sg:classifiers":[
        {
            "category":"Health Services",
            "subcategory":"Chiropractor",
            "type":"Services"
        },
        {
            "category":"Health Services",
            "subcategory":"Clinic",
            "type":"Services"
        }
    ],
    "sg:phone":"+1 573 883 2442",
    "sg:postcode":"63670",
    "sg:province":"MO",
    "sg:tags":[
        "home",
        "care"
    ],
    "wof:name":"Physicians Health & Rehab",
    "wof:placetype":"venue"
},
  "geometry": {"coordinates":[-90.05662100000001,37.967695],"type":"Point"}
}