{
  "type": "Feature",
  "properties": {
    "iso:country":"US",
    "sg:address":"101 W 21st St",
    "sg:city":"Higginsville",
    "sg:classifiers":[
        {
            "category":"Social Services",
            "subcategory":"Adult Care",
            "type":"Services"
        },
        {
            "category":"Social Services",
            "type":"Services"
        }
    ],
    "sg:phone":"+1 660 584 7040",
    "sg:postcode":"64037",
    "sg:province":"MO",
    "sg:tags":[
        "organization",
        "senior",
        "citizen"
    ],
    "wof:name":"Higginsville Senior Center",
    "wof:placetype":"venue"
},
  "geometry": {"coordinates":[-93.720001,39.074103],"type":"Point"}
}