{
  "type": "Feature",
  "properties": {
    "iso:country":"US",
    "sg:address":"2246 N Roosevelt Ave",
    "sg:city":"Springfield",
    "sg:classifiers":[
        {
            "category":"Social Services",
            "subcategory":"Child Care",
            "type":"Services"
        }
    ],
    "sg:phone":"+1 417 865 4341",
    "sg:postcode":"65803",
    "sg:province":"MO",
    "sg:tags":[
        "state",
        "licensed",
        "day",
        "provider"
    ],
    "wof:name":"Victoria Taylor",
    "wof:placetype":"venue"
},
  "geometry": {"coordinates":[-93.321281,37.239652],"type":"Point"}
}