{
  "type": "Feature",
  "properties": {
    "iso:country":"US",
    "sg:address":"141 Lawson Ave",
    "sg:city":"Lebanon",
    "sg:classifiers":[
        {
            "category":"Organizations",
            "subcategory":"Community Association",
            "type":"Services"
        }
    ],
    "sg:phone":"+1 417 588 2620",
    "sg:postcode":"65536",
    "sg:province":"MO",
    "sg:website":"http://www.communityactionpartnership.com",
    "wof:name":"Missouri Ozarks Community Action, Inc.",
    "wof:placetype":"venue"
},
  "geometry": {"coordinates":[-92.650019,37.659837],"type":"Point"}
}