{
  "type": "Feature",
  "properties": {
    "iso:country":"US",
    "sg:address":"2209 N Belt Hwy",
    "sg:city":"St Joseph",
    "sg:classifiers":[
        {
            "category":"Restaurant",
            "type":"Food & Drink"
        }
    ],
    "sg:phone":"+1 816 671 9090",
    "sg:postcode":"64506",
    "sg:province":"MO",
    "sg:tags":[
        "eating"
    ],
    "wof:name":"China One Intl Buffett",
    "wof:placetype":"venue"
},
  "geometry": {"coordinates":[-94.80385,39.785524],"type":"Point"}
}