{
  "type": "Feature",
  "properties": {
    "iso:country":"US",
    "sg:address":"8050 Watson Rd",
    "sg:city":"Saint Louis",
    "sg:classifiers":[
        {
            "category":"Professional",
            "subcategory":"Lawyer & Legal Services",
            "type":"Services"
        }
    ],
    "sg:phone":"+1 314 842 1650",
    "sg:postcode":"63119",
    "sg:province":"MO",
    "wof:name":"Berry Lbrecht LLC Attys At Law",
    "wof:placetype":"venue"
},
  "geometry": {"coordinates":[-90.34364100000001,38.567289],"type":"Point"}
}