{
  "type": "Feature",
  "properties": {
    "iso:country":"US",
    "sg:address":"508 NW Little Ave",
    "sg:city":"Lees Summit",
    "sg:classifiers":[
        {
            "category":"Building & Trades",
            "subcategory":"Plumbing",
            "type":"Services"
        }
    ],
    "sg:phone":"+1 816 524 9338",
    "sg:postcode":"64063",
    "sg:province":"MO",
    "sg:tags":[
        "plumbing",
        "contractor"
    ],
    "wof:name":"Gene's Plumbing & Sewer Svc",
    "wof:placetype":"venue"
},
  "geometry": {"coordinates":[-94.384531,38.915669],"type":"Point"}
}