{
  "type": "Feature",
  "properties": {
    "iso:country":"US",
    "sg:address":"4094 Farm Road 2155",
    "sg:city":"Exeter",
    "sg:classifiers":[
        {
            "category":"Personal",
            "subcategory":"Beauty Salon",
            "type":"Services"
        }
    ],
    "sg:phone":"+1 417 652 3144",
    "sg:postcode":"65647",
    "sg:province":"MO",
    "sg:tags":[
        "hair",
        "stylist"
    ],
    "wof:name":"Hair It Is",
    "wof:placetype":"venue"
},
  "geometry": {"coordinates":[-94.033485,36.71249],"type":"Point"}
}