{
  "type": "Feature",
  "properties": {
    "iso:country":"US",
    "sg:address":"11013 E 83 Ter",
    "sg:city":"Kansas City",
    "sg:classifiers":[
        {
            "category":"Professional",
            "subcategory":"Business Services",
            "type":"Services"
        }
    ],
    "sg:phone":"+1 816 353 6754",
    "sg:postcode":"64138",
    "sg:province":"MO",
    "wof:name":"Frances E Johnson",
    "wof:placetype":"venue"
},
  "geometry": {"coordinates":[-94.452668,38.970806],"type":"Point"}
}