{
  "type": "Feature",
  "properties": {
    "iso:country":"US",
    "sg:address":"302 N Marr St",
    "sg:city":"Mountain View",
    "sg:classifiers":[
        {
            "category":"Organizations",
            "subcategory":"Religious Organization",
            "type":"Services"
        }
    ],
    "sg:phone":"+1 417 934 6475",
    "sg:postcode":"65548",
    "sg:province":"MO",
    "sg:tags":[
        "church"
    ],
    "wof:name":"Pentecostal Church Of God",
    "wof:placetype":"venue"
},
  "geometry": {"coordinates":[-91.695572,36.997653],"type":"Point"}
}