{
  "type": "Feature",
  "properties": {
    "iso:country":"US",
    "sg:address":"899 SW 30th Rd",
    "sg:city":"Liberal",
    "sg:classifiers":[
        {
            "category":"Manufacturing",
            "subcategory":"Food",
            "type":"Manufacturing & Wholesale Goods"
        },
        {
            "category":"Farming",
            "subcategory":"Livestock Farm",
            "type":"Manufacturing & Wholesale Goods"
        },
        {
            "category":"Farming",
            "subcategory":"Farm",
            "type":"Manufacturing & Wholesale Goods"
        }
    ],
    "sg:phone":"+1 417 843 5327",
    "sg:postcode":"64762",
    "sg:province":"MO",
    "sg:tags":[
        "corn",
        "ranch",
        "product"
    ],
    "wof:name":"Overman Farms",
    "wof:placetype":"venue"
},
  "geometry": {"coordinates":[-94.463943,37.461109],"type":"Point"}
}