{
  "type": "Feature",
  "properties": {
    "iso:country":"US",
    "sg:address":"704 N Kingshighway St",
    "sg:city":"Perryville",
    "sg:classifiers":[
        {
            "category":"Autos & Motor Vehicles",
            "subcategory":"Auto Supplies",
            "type":"Retail Goods"
        },
        {
            "category":"Retail",
            "subcategory":"Auto Repair",
            "type":"Services"
        }
    ],
    "sg:phone":"+1 573 547 2568",
    "sg:postcode":"63775",
    "sg:province":"MO",
    "sg:tags":[
        "wheel",
        "lettering",
        "automobile",
        "body",
        "dent",
        "servicing-automotive",
        "truck",
        "axle",
        "wheels-aligning",
        "alignment-frame",
        "balancing",
        "removal",
        "painting",
        "repairing"
    ],
    "wof:name":"Werner Auto Body Repair",
    "wof:placetype":"venue"
},
  "geometry": {"coordinates":[-89.86806799999999,37.736078],"type":"Point"}
}