{
  "type": "Feature",
  "properties": {
    "iso:country":"US",
    "sg:address":"8773 Old Hwy 60",
    "sg:city":"Mountain Grove",
    "sg:classifiers":[
        {
            "category":"Restaurant",
            "type":"Food & Drink"
        }
    ],
    "sg:phone":"+1 417 926 9954",
    "sg:postcode":"65711",
    "sg:province":"MO",
    "wof:name":"Club 60 Steak House",
    "wof:placetype":"venue"
},
  "geometry": {"coordinates":[-92.31189500000001,37.130525],"type":"Point"}
}