{
  "type": "Feature",
  "properties": {
    "iso:country":"US",
    "sg:address":"400 Barnes Rd",
    "sg:city":"St Louis",
    "sg:classifiers":[
        {
            "category":"Recreation",
            "type":"Entertainment"
        },
        {
            "category":"Shopping",
            "subcategory":"Bicycles & Sporting Goods",
            "type":"Retail Goods"
        },
        {
            "category":"Organizations",
            "subcategory":"Community Association",
            "type":"Services"
        }
    ],
    "sg:phone":"+1 314 994 0011",
    "sg:postcode":"63124",
    "sg:province":"MO",
    "sg:tags":[
        "golf",
        "supply",
        "club",
        "country",
        "cart",
        "membership",
        "rent",
        "lesson"
    ],
    "wof:name":"Saint Louis Country Club",
    "wof:placetype":"venue"
},
  "geometry": {"coordinates":[-90.380836,38.648272],"type":"Point"}
}