{
  "type": "Feature",
  "properties": {
    "iso:country":"US",
    "sg:address":"252 State Hwy 7",
    "sg:city":"Clinton",
    "sg:classifiers":[
        {
            "category":"Retail",
            "subcategory":"Auto Repair",
            "type":"Services"
        }
    ],
    "sg:phone":"+1 660 477 9222",
    "sg:postcode":"64735",
    "sg:province":"MO",
    "sg:tags":[
        "wrecker"
    ],
    "wof:name":"Auto Pro Tire & Tow",
    "wof:placetype":"venue"
},
  "geometry": {"coordinates":[-93.61497300000001,38.325638],"type":"Point"}
}