{
  "type": "Feature",
  "properties": {
    "iso:country":"US",
    "sg:address":"9 Apple Ct A",
    "sg:city":"Dexter",
    "sg:classifiers":[
        {
            "category":"Real Estate",
            "subcategory":"Real Estate Operator",
            "type":"Services"
        }
    ],
    "sg:phone":"+1 573 624 7451",
    "sg:postcode":"63841",
    "sg:province":"MO",
    "sg:tags":[
        "apartment"
    ],
    "wof:name":"Dexter Apts.",
    "wof:placetype":"venue"
},
  "geometry": {"coordinates":[-89.95706199999999,36.807803],"type":"Point"}
}