{
  "type": "Feature",
  "properties": {
    "iso:country":"US",
    "sg:address":"4588 Little Rock Rd",
    "sg:city":"St Louis",
    "sg:classifiers":[
        {
            "category":"Building & Trades",
            "subcategory":"Landscaping Services",
            "type":"Services"
        }
    ],
    "sg:phone":"+1 314 892 7374",
    "sg:postcode":"63128",
    "sg:province":"MO",
    "sg:tags":[
        "home",
        "lawn",
        "landscape",
        "maintenance",
        "contractor"
    ],
    "wof:name":"Better Home & Lawn Service",
    "wof:placetype":"venue"
},
  "geometry": {"coordinates":[-90.34221100000001,38.501056],"type":"Point"}
}