{
  "type": "Feature",
  "properties": {
    "iso:country":"US",
    "sg:address":"407 Washington St",
    "sg:city":"Weston",
    "sg:classifiers":[
        {
            "category":"Travel",
            "subcategory":"Hotels & Motels",
            "type":"Entertainment"
        }
    ],
    "sg:phone":"+1 816 386 5367",
    "sg:postcode":"64098",
    "sg:province":"MO",
    "sg:tags":[
        "breakfast",
        "bed"
    ],
    "wof:name":"Lemon Tree",
    "wof:placetype":"venue"
},
  "geometry": {"coordinates":[-94.90448499999999,39.411704],"type":"Point"}
}