{
  "type": "Feature",
  "properties": {
    "iso:country":"US",
    "sg:address":"105 S Hope St",
    "sg:city":"Jackson",
    "sg:classifiers":[
        {
            "category":"Professional",
            "subcategory":"Accounting & Tax Preparation",
            "type":"Services"
        }
    ],
    "sg:phone":"+1 573 243 3991",
    "sg:postcode":"63755",
    "sg:province":"MO",
    "sg:tags":[
        "accountant"
    ],
    "wof:name":"Beussink Hey & Roe",
    "wof:placetype":"venue"
},
  "geometry": {"coordinates":[-89.66653700000001,37.382391],"type":"Point"}
}