{
  "type": "Feature",
  "properties": {
    "iso:country":"US",
    "sg:address":"1689 NW 650th Rd",
    "sg:city":"Kingsville",
    "sg:classifiers":[
        {
            "category":"Retail",
            "subcategory":"Auto Repair",
            "type":"Services"
        }
    ],
    "sg:phone":"+1 816 697 2849",
    "sg:postcode":"64061",
    "sg:province":"MO",
    "sg:tags":[
        "automotive"
    ],
    "wof:name":"Penns Tow Service Inc",
    "wof:placetype":"venue"
},
  "geometry": {"coordinates":[-94.05875899999999,38.868444],"type":"Point"}
}