{
  "type": "Feature",
  "properties": {
    "addr:full":"9911 Kennerly Rd Saint Louis MO 63128",
    "addr:housenumber":"9911",
    "addr:postcode":"63128",
    "addr:street":"Kennerly Rd",
    "iso:country":"US",
    "sg:address":"9911 Kennerly Rd",
    "sg:city":"Saint Louis",
    "sg:classifiers":[
        {
            "category":"Health Services",
            "subcategory":"Doctor",
            "type":"Services"
        }
    ],
    "sg:phone":"+1 314 842 4699",
    "sg:postcode":"63128",
    "sg:province":"MO",
    "wof:name":"Saint Luis S Oral Mxllfacial S",
    "wof:placetype":"venue"
},
  "geometry": {"coordinates":[-90.37584699999999,38.507817],"type":"Point"}
}