{
  "type": "Feature",
  "properties": {
    "iso:country":"US",
    "sg:address":"1008 Holloway St",
    "sg:city":"Rolla",
    "sg:classifiers":[
        {
            "category":"Professional",
            "type":"Services"
        }
    ],
    "sg:phone":"+1 573 364 5539",
    "sg:postcode":"65401",
    "sg:province":"MO",
    "sg:tags":[
        "arts",
        "artist"
    ],
    "wof:name":"Arts Rolla",
    "wof:placetype":"venue"
},
  "geometry": {"coordinates":[-91.76186,37.952235],"type":"Point"}
}