{
  "type": "Feature",
  "properties": {
    "iso:country":"US",
    "sg:address":"110 E Middle St",
    "sg:city":"Leonard",
    "sg:classifiers":[
        {
            "category":"Government",
            "subcategory":"Office",
            "type":"Public Place"
        }
    ],
    "sg:phone":"+1 660 762 4210",
    "sg:postcode":"63451",
    "sg:province":"MO",
    "wof:name":"Village Of Leonard",
    "wof:placetype":"venue"
},
  "geometry": {"coordinates":[-92.182727,39.894477],"type":"Point"}
}