{
  "type": "Feature",
  "properties": {
    "addr:full":"300 W 4th St Mountain View MO 65548",
    "addr:housenumber":"300",
    "addr:postcode":"65548",
    "addr:street":"W 4Th St",
    "iso:country":"US",
    "sg:address":"300 W 4th St",
    "sg:city":"Mountain View",
    "sg:classifiers":[
        {
            "category":"Organizations",
            "subcategory":"Religious Organization",
            "type":"Services"
        }
    ],
    "sg:phone":"+1 417 934 2391",
    "sg:postcode":"65548",
    "sg:province":"MO",
    "sg:tags":[
        "church"
    ],
    "wof:name":"Nazarene Church",
    "wof:placetype":"venue"
},
  "geometry": {"coordinates":[-91.705365,36.99778],"type":"Point"}
}