{
  "type": "Feature",
  "properties": {
    "iso:country":"US",
    "sg:address":"129 E 3rd St",
    "sg:city":"Hermann",
    "sg:classifiers":[
        {
            "category":"Retail",
            "subcategory":"Repair Shop",
            "type":"Services"
        }
    ],
    "sg:phone":"+1 573 486 2096",
    "sg:postcode":"65041",
    "sg:province":"MO",
    "sg:tags":[
        "sporting"
    ],
    "wof:name":"Klott Gun Repair",
    "wof:placetype":"venue"
},
  "geometry": {"coordinates":[-91.437207,38.705253],"type":"Point"}
}