{
  "type": "Feature",
  "properties": {
    "iso:country":"US",
    "sg:address":"18990 N Locust Grove Rd",
    "sg:city":"Sturgeon",
    "sg:classifiers":[
        {
            "category":"Building & Trades",
            "subcategory":"Construction",
            "type":"Services"
        }
    ],
    "sg:phone":"+1 573 687 3373",
    "sg:postcode":"65284",
    "sg:province":"MO",
    "sg:tags":[
        "contractor"
    ],
    "wof:name":"Bailey Service Co",
    "wof:placetype":"venue"
},
  "geometry": {"coordinates":[-92.31185499999999,39.178988],"type":"Point"}
}