{
  "type": "Feature",
  "properties": {
    "iso:country":"US",
    "sg:address":"630 Jeffco Blvd",
    "sg:city":"Arnold",
    "sg:classifiers":[
        {
            "category":"Building & Trades",
            "subcategory":"Electrical",
            "type":"Services"
        }
    ],
    "sg:phone":"+1 636 296 8600",
    "sg:postcode":"63010",
    "sg:province":"MO",
    "sg:tags":[
        "engineering"
    ],
    "wof:name":"B H M G Service Corp",
    "wof:placetype":"venue"
},
  "geometry": {"coordinates":[-90.363215,38.452149],"type":"Point"}
}