{
  "type": "Feature",
  "properties": {
    "addr:full":"5790 Campus Pkwy Hazelwood MO 63042",
    "addr:housenumber":"5790",
    "addr:postcode":"63042",
    "addr:street":"Campus Pkwy",
    "iso:country":"US",
    "sg:address":"5790 Campus Pkwy",
    "sg:city":"Hazelwood",
    "sg:classifiers":[
        {
            "category":"Retail",
            "subcategory":"Auto Rental",
            "type":"Services"
        }
    ],
    "sg:phone":"+1 314 731 7690",
    "sg:postcode":"63042",
    "sg:province":"MO",
    "sg:tags":[
        "truck"
    ],
    "wof:name":"Ryder",
    "wof:placetype":"venue"
},
  "geometry": {"coordinates":[-90.386545,38.774587],"type":"Point"}
}