{
  "type": "Feature",
  "properties": {
    "iso:country":"US",
    "sg:address":"1711 Willoughby St",
    "sg:city":"Kennett",
    "sg:classifiers":[
        {
            "category":"Shopping",
            "subcategory":"Gifts & Souvenirs",
            "type":"Retail Goods"
        }
    ],
    "sg:phone":"+1 573 888 1889",
    "sg:postcode":"63857",
    "sg:province":"MO",
    "sg:tags":[
        "collectible"
    ],
    "wof:name":"Ramie Rhamy's",
    "wof:placetype":"venue"
},
  "geometry": {"coordinates":[-90.035614,36.247198],"type":"Point"}
}