{
  "type": "Feature",
  "properties": {
    "iso:country":"US",
    "sg:address":"13514 State Hwy N",
    "sg:city":"Mound City",
    "sg:phone":"+1 660 442 5778",
    "sg:postcode":"64470",
    "sg:province":"MO",
    "sg:tags":[
        "farm",
        "corn"
    ],
    "wof:name":"Duane Nauman",
    "wof:placetype":"venue"
},
  "geometry": {"coordinates":[-95.23921799999999,40.142733],"type":"Point"}
}