{
  "type": "Feature",
  "properties": {
    "iso:country":"US",
    "sg:address":"11155 Dunn Rd",
    "sg:city":"St Louis",
    "sg:classifiers":[
        {
            "category":"Health Services",
            "subcategory":"Podiatrist",
            "type":"Services"
        }
    ],
    "sg:phone":"+1 314 355 0074",
    "sg:postcode":"63136",
    "sg:province":"MO",
    "wof:name":"Shari Kaminsky MD",
    "wof:placetype":"venue"
},
  "geometry": {"coordinates":[-90.239058,38.775789],"type":"Point"}
}