{
  "type": "Feature",
  "properties": {
    "iso:country":"US",
    "sg:address":"17388 Highway 22",
    "sg:city":"Thompson",
    "sg:classifiers":[
        {
            "category":"Wholesale",
            "subcategory":"Farm Supplies",
            "type":"Manufacturing & Wholesale Goods"
        },
        {
            "category":"Home & Garden",
            "subcategory":"Garden Supply",
            "type":"Retail Goods"
        },
        {
            "category":"Wholesale",
            "subcategory":"Machinery & Supplies",
            "type":"Manufacturing & Wholesale Goods"
        },
        {
            "category":"Shopping",
            "subcategory":"Pets & Pet Supplies",
            "type":"Retail Goods"
        }
    ],
    "sg:phone":"+1 573 581 5180",
    "sg:postcode":"65285",
    "sg:province":"MO",
    "sg:tags":[
        "feed",
        "equipment",
        "fertilizer",
        "baling"
    ],
    "sg:website":"http://www.mfa-inc.com",
    "wof:name":"Mfa Agri Services",
    "wof:placetype":"venue"
},
  "geometry": {"coordinates":[-91.981763,39.189954],"type":"Point"}
}