{
  "type": "Feature",
  "properties": {
    "iso:country":"US",
    "sg:address":"527 Trade Center Blvd",
    "sg:city":"Chesterfield",
    "sg:classifiers":[
        {
            "category":"Manufacturing",
            "subcategory":"Tools & Machinery",
            "type":"Manufacturing & Wholesale Goods"
        },
        {
            "category":"Retail",
            "subcategory":"Repair Shop",
            "type":"Services"
        },
        {
            "category":"Retail",
            "subcategory":"Auto Repair",
            "type":"Services"
        }
    ],
    "sg:phone":"+1 636 449 0133",
    "sg:postcode":"63005",
    "sg:province":"MO",
    "sg:tags":[
        "machine",
        "automobile",
        "machinery-rebuild"
    ],
    "wof:name":"Fab Lab Inc",
    "wof:placetype":"venue"
},
  "geometry": {"coordinates":[-90.624399,38.662904],"type":"Point"}
}