{
  "type": "Feature",
  "properties": {
    "iso:country":"US",
    "sg:address":"4401 Oak Dr",
    "sg:city":"Joplin",
    "sg:classifiers":[
        {
            "category":"Travel",
            "subcategory":"Hotels & Motels",
            "type":"Entertainment"
        }
    ],
    "sg:phone":"+1 417 624 6493",
    "sg:postcode":"64804",
    "sg:province":"MO",
    "wof:name":"Ko Ko Motel",
    "wof:placetype":"venue"
},
  "geometry": {"coordinates":[-94.49247800000001,37.039147],"type":"Point"}
}