{
  "type": "Feature",
  "properties": {
    "iso:country":"US",
    "sg:address":"9440 Big Bend Blvd",
    "sg:city":"Saint Louis",
    "sg:classifiers":[
        {
            "category":"Social Services",
            "subcategory":"Child Care",
            "type":"Services"
        }
    ],
    "sg:phone":"+1 314 961 0456",
    "sg:postcode":"63119",
    "sg:province":"MO",
    "sg:tags":[
        "organization",
        "religious",
        "day"
    ],
    "wof:name":"Church of Open Door",
    "wof:placetype":"venue"
},
  "geometry": {"coordinates":[-90.37689,38.573568],"type":"Point"}
}