{
  "type": "Feature",
  "properties": {
    "iso:country":"US",
    "sg:address":"133 S Walnut St",
    "sg:city":"Dexter",
    "sg:classifiers":[
        {
            "category":"Manufacturing",
            "subcategory":"Printing",
            "type":"Manufacturing & Wholesale Goods"
        }
    ],
    "sg:phone":"+1 573 624 4545",
    "sg:postcode":"63841",
    "sg:province":"MO",
    "sg:tags":[
        "newspaper"
    ],
    "sg:website":"www.dailystatesman.com",
    "wof:name":"Daily Statesman",
    "wof:placetype":"venue"
},
  "geometry": {"coordinates":[-89.95790700000001,36.791409],"type":"Point"}
}