{
  "type": "Feature",
  "properties": {
    "iso:country":"US",
    "sg:address":"225 E 3rd St",
    "sg:city":"Cameron",
    "sg:classifiers":[
        {
            "category":"Restaurant",
            "type":"Food & Drink"
        }
    ],
    "sg:menulink":"http://www.allmenus.com/mo/shoal/68975-breadeaux-pizza/menu/",
    "sg:phone":"+1 816 632 7472",
    "sg:postcode":"64429",
    "sg:province":"MO",
    "sg:tags":[
        "american",
        "pizza"
    ],
    "wof:name":"Breadeaux Pizza",
    "wof:placetype":"venue"
},
  "geometry": {"coordinates":[-94.23684799999999,39.741249],"type":"Point"}
}