{
  "type": "Feature",
  "properties": {
    "iso:country":"US",
    "sg:address":"4400 NW Barry Rd",
    "sg:city":"Kansas City",
    "sg:classifiers":[
        {
            "category":"Shopping",
            "subcategory":"Pharmacy",
            "type":"Retail Goods"
        }
    ],
    "sg:phone":"+1 816 587 8018",
    "sg:postcode":"64154",
    "sg:province":"MO",
    "sg:website":"www.albertsons.com",
    "wof:name":"Osco Drug",
    "wof:placetype":"venue"
},
  "geometry": {"coordinates":[-94.634019,39.246658],"type":"Point"}
}