{
  "type": "Feature",
  "properties": {
    "iso:country":"US",
    "sg:address":"2043 W Kansas St",
    "sg:city":"Liberty",
    "sg:classifiers":[
        {
            "category":"Health Services",
            "subcategory":"Doctor",
            "type":"Services"
        }
    ],
    "sg:phone":"+1 816 632 1242",
    "sg:postcode":"64068",
    "sg:province":"MO",
    "wof:name":"Thomas J Kennedy DDS",
    "wof:placetype":"venue"
},
  "geometry": {"coordinates":[-94.45272300000001,39.244554],"type":"Point"}
}