{
  "type": "Feature",
  "properties": {
    "iso:country":"US",
    "sg:address":"1706 N 9th St",
    "sg:city":"Monett",
    "sg:classifiers":[
        {
            "category":"Organizations",
            "subcategory":"Religious Organization",
            "type":"Services"
        }
    ],
    "sg:phone":"+1 417 235 3416",
    "sg:postcode":"65708",
    "sg:province":"MO",
    "sg:tags":[
        "church"
    ],
    "wof:name":"St John's Ev Lutheran Church",
    "wof:placetype":"venue"
},
  "geometry": {"coordinates":[-93.91818000000001,36.939875],"type":"Point"}
}