{
  "type": "Feature",
  "properties": {
    "iso:country":"US",
    "sg:address":"111 Stewart St",
    "sg:city":"Bernie",
    "sg:classifiers":[
        {
            "category":"Autos & Motor Vehicles",
            "subcategory":"Auto Supplies",
            "type":"Retail Goods"
        },
        {
            "category":"Retail",
            "subcategory":"Repair Shop",
            "type":"Services"
        }
    ],
    "sg:phone":"+1 573 293 4806",
    "sg:postcode":"63822",
    "sg:province":"MO",
    "sg:tags":[
        "upholstery",
        "upholsterer",
        "automobile",
        "top",
        "covers",
        "seat"
    ],
    "wof:name":"Bootheel Auto Upholstery",
    "wof:placetype":"venue"
},
  "geometry": {"coordinates":[-89.968318,36.669378],"type":"Point"}
}