{
  "type": "Feature",
  "properties": {
    "iso:country":"US",
    "sg:address":"112 W Maple St",
    "sg:city":"Shelbina",
    "sg:classifiers":[
        {
            "category":"Food & Beverages",
            "subcategory":"Groceries & Convenience Stores",
            "type":"Retail Goods"
        }
    ],
    "sg:phone":"+1 573 588 4413",
    "sg:postcode":"63468",
    "sg:province":"MO",
    "sg:tags":[
        "grocer"
    ],
    "wof:name":"Dobyns Market/Laura's Deli",
    "wof:placetype":"venue"
},
  "geometry": {"coordinates":[-92.041577,39.69439],"type":"Point"}
}