{
  "type": "Feature",
  "properties": {
    "iso:country":"US",
    "sg:address":"311 N 5th St",
    "sg:city":"Saint Charles",
    "sg:classifiers":[
        {
            "category":"Professional",
            "subcategory":"Employment Agencies",
            "type":"Services"
        }
    ],
    "sg:phone":"+1 636 949 5607",
    "sg:postcode":"63301",
    "sg:province":"MO",
    "wof:name":"Absolute Outsourcing Inc",
    "wof:placetype":"venue"
},
  "geometry": {"coordinates":[-90.484827,38.785307],"type":"Point"}
}