{
  "type": "Feature",
  "properties": {
    "iso:country":"US",
    "sg:address":"1012 High St",
    "sg:city":"Fredericktown",
    "sg:classifiers":[
        {
            "category":"Food & Beverages",
            "subcategory":"Groceries & Convenience Stores",
            "type":"Retail Goods"
        }
    ],
    "sg:phone":"+1 573 783 7008",
    "sg:postcode":"63645",
    "sg:province":"MO",
    "wof:name":"Village Store The",
    "wof:placetype":"venue"
},
  "geometry": {"coordinates":[-90.28773,37.547232],"type":"Point"}
}