{
  "type": "Feature",
  "properties": {
    "iso:country":"US",
    "sg:address":"2500 Bluff Blvd",
    "sg:city":"Columbia",
    "sg:classifiers":[
        {
            "category":"Building & Trades",
            "subcategory":"Equipment Rental",
            "type":"Services"
        }
    ],
    "sg:phone":"+1 573 442 3898",
    "sg:postcode":"65201",
    "sg:province":"MO",
    "sg:tags":[
        "yard",
        "leasing",
        "store"
    ],
    "wof:name":"Powell Rentals Raymond",
    "wof:placetype":"venue"
},
  "geometry": {"coordinates":[-92.300346,38.93856],"type":"Point"}
}