{
  "type": "Feature",
  "properties": {
    "iso:country":"US",
    "sg:address":"8008 Carondelet Ave",
    "sg:city":"St Louis",
    "sg:classifiers":[
        {
            "category":"Real Estate",
            "subcategory":"Architect",
            "type":"Services"
        }
    ],
    "sg:phone":"+1 314 721 0167",
    "sg:postcode":"63105",
    "sg:province":"MO",
    "sg:tags":[
        "architectural"
    ],
    "wof:name":"Charles E Bell Architects Inc",
    "wof:placetype":"venue"
},
  "geometry": {"coordinates":[-90.3415,38.649117],"type":"Point"}
}