{
  "type": "Feature",
  "properties": {
    "addr:full":"7261 Watson Rd Saint Louis MO 63119",
    "addr:housenumber":"7261",
    "addr:postcode":"63119",
    "addr:street":"Watson Rd",
    "iso:country":"US",
    "sg:address":"7261 Watson Rd",
    "sg:city":"Saint Louis",
    "sg:classifiers":[
        {
            "category":"Shopping",
            "subcategory":"Mobile Phones",
            "type":"Retail Goods"
        },
        {
            "category":"Shopping",
            "subcategory":"Computers & Home Electronics",
            "type":"Retail Goods"
        }
    ],
    "sg:phone":"+1 314 481 7096",
    "sg:postcode":"63119",
    "sg:province":"MO",
    "sg:website":"www.radioshack.com",
    "wof:name":"Radio Shack",
    "wof:placetype":"venue"
},
  "geometry": {"coordinates":[-90.319298,38.582401],"type":"Point"}
}