{
  "type": "Feature",
  "properties": {
    "iso:country":"US",
    "sg:address":"195 State Hwy 7",
    "sg:city":"Clinton",
    "sg:classifiers":[
        {
            "category":"Manufacturing",
            "subcategory":"Glass & Minerals",
            "type":"Manufacturing & Wholesale Goods"
        }
    ],
    "sg:phone":"+1 660 885 6364",
    "sg:postcode":"64735",
    "sg:province":"MO",
    "sg:tags":[
        "ready",
        "concrete",
        "mfg"
    ],
    "wof:name":"Fischer Concrete Inc",
    "wof:placetype":"venue"
},
  "geometry": {"coordinates":[-93.614684,38.333778],"type":"Point"}
}