{
  "type": "Feature",
  "properties": {
    "iso:country":"US",
    "sg:address":"908 Paradise Ln",
    "sg:city":"Smithville",
    "sg:classifiers":[
        {
            "category":"Retail",
            "subcategory":"Laundry & Dry Cleaning",
            "type":"Services"
        }
    ],
    "sg:phone":"+1 816 532 3575",
    "sg:postcode":"64089",
    "sg:province":"MO",
    "wof:name":"Doubletime Carpet Maintenance",
    "wof:placetype":"venue"
},
  "geometry": {"coordinates":[-94.564421,39.446145],"type":"Point"}
}