{
  "type": "Feature",
  "properties": {
    "iso:country":"US",
    "sg:address":"4540 S Noland Rd",
    "sg:city":"Independence",
    "sg:classifiers":[
        {
            "category":"Shopping",
            "subcategory":"Florist",
            "type":"Retail Goods"
        }
    ],
    "sg:phone":"+1 816 373 5532",
    "sg:postcode":"64055",
    "sg:province":"MO",
    "wof:name":"Kansas City Rose Co",
    "wof:placetype":"venue"
},
  "geometry": {"coordinates":[-94.41564700000001,39.037391],"type":"Point"}
}