{
  "type": "Feature",
  "properties": {
    "iso:country":"US",
    "sg:address":"19300 S School Rd",
    "sg:city":"Raymore",
    "sg:classifiers":[
        {
            "category":"Shopping",
            "subcategory":"Bicycles & Sporting Goods",
            "type":"Retail Goods"
        }
    ],
    "sg:phone":"+1 816 331 4491",
    "sg:postcode":"64083",
    "sg:province":"MO",
    "sg:tags":[
        "cutlery",
        "mfg"
    ],
    "wof:name":"W C Davis Custom Knives",
    "wof:placetype":"venue"
},
  "geometry": {"coordinates":[-94.458592,38.775151],"type":"Point"}
}