{
  "type": "Feature",
  "properties": {
    "iso:country":"US",
    "sg:address":"307 Tennis Ct",
    "sg:city":"Kansas City",
    "sg:classifiers":[
        {
            "category":"Retail",
            "subcategory":"Auto Repair",
            "type":"Services"
        }
    ],
    "sg:phone":"+1 816 474 5800",
    "sg:postcode":"64116",
    "sg:province":"MO",
    "sg:tags":[
        "body",
        "automobile",
        "painting"
    ],
    "wof:name":"Jack Miller Body Works",
    "wof:placetype":"venue"
},
  "geometry": {"coordinates":[-94.58438200000001,39.151732],"type":"Point"}
}