{
  "type": "Feature",
  "properties": {
    "iso:country":"US",
    "sg:address":"17131 Bel Ray Pl",
    "sg:city":"Belton",
    "sg:classifiers":[
        {
            "category":"Arts & Performance",
            "subcategory":"Dance",
            "type":"Entertainment"
        }
    ],
    "sg:phone":"+1 816 331 0013",
    "sg:postcode":"64012",
    "sg:province":"MO",
    "sg:tags":[
        "instruction",
        "dancing"
    ],
    "wof:name":"Bel Ray Center",
    "wof:placetype":"venue"
},
  "geometry": {"coordinates":[-94.49955,38.812658],"type":"Point"}
}