{
  "type": "Feature",
  "properties": {
    "iso:country":"US",
    "sg:address":"17145 US Hwy 63",
    "sg:city":"Rolla",
    "sg:classifiers":[
        {
            "category":"Autos & Motor Vehicles",
            "subcategory":"Motorcycle Sales",
            "type":"Retail Goods"
        }
    ],
    "sg:phone":"+1 573 364 1107",
    "sg:postcode":"65401",
    "sg:province":"MO",
    "wof:name":"Ace Cycle Supply",
    "wof:placetype":"venue"
},
  "geometry": {"coordinates":[-91.79886999999999,37.845631],"type":"Point"}
}