{
  "type": "Feature",
  "properties": {
    "iso:country":"US",
    "sg:address":"3108 Olive St",
    "sg:city":"Saint Louis",
    "sg:classifiers":[
        {
            "category":"Restaurant",
            "type":"Food & Drink"
        }
    ],
    "sg:phone":"+1 314 225 2555",
    "sg:postcode":"63103",
    "sg:province":"MO",
    "sg:tags":[
        "chinese"
    ],
    "sg:website":"www.santobento.com",
    "wof:name":"Santo Bento",
    "wof:placetype":"venue"
},
  "geometry": {"coordinates":[-90.224322,38.635425],"type":"Point"}
}