{
  "type": "Feature",
  "properties": {
    "iso:country":"US",
    "sg:address":"3306 Market St",
    "sg:city":"Hannibal",
    "sg:classifiers":[
        {
            "category":"Professional",
            "type":"Services"
        }
    ],
    "sg:phone":"+1 573 406 0192",
    "sg:postcode":"63401",
    "sg:province":"MO",
    "wof:name":"Ginger Demic",
    "wof:placetype":"venue"
},
  "geometry": {"coordinates":[-91.392954,39.686863],"type":"Point"}
}