{
  "type": "Feature",
  "properties": {
    "iso:country":"US",
    "sg:address":"863 Blattner Rd",
    "sg:city":"Wright City",
    "sg:classifiers":[
        {
            "category":"Professional",
            "subcategory":"Art Services",
            "type":"Services"
        }
    ],
    "sg:phone":"+1 636 745 2617",
    "sg:postcode":"63390",
    "sg:province":"MO",
    "sg:tags":[
        "graphic",
        "designer"
    ],
    "wof:name":"Custom Graphics Signs",
    "wof:placetype":"venue"
},
  "geometry": {"coordinates":[-90.98110699999999,38.797267],"type":"Point"}
}