{
  "type": "Feature",
  "properties": {
    "iso:country":"US",
    "sg:address":"220 W Lockwood Ave",
    "sg:city":"Saint Louis",
    "sg:classifiers":[
        {
            "category":"Restaurant",
            "type":"Food & Drink"
        }
    ],
    "sg:phone":"+1 314 962 5508",
    "sg:postcode":"63119",
    "sg:province":"MO",
    "sg:tags":[
        "eating",
        "product",
        "dairy"
    ],
    "wof:name":"Cool Beans Cafe",
    "wof:placetype":"venue"
},
  "geometry": {"coordinates":[-90.36303100000001,38.593358],"type":"Point"}
}