{
  "type": "Feature",
  "properties": {
    "iso:country":"US",
    "sg:address":"1427 S Barnes Ave",
    "sg:city":"Springfield",
    "sg:classifiers":[
        {
            "category":"Building & Trades",
            "subcategory":"Cleaning & Sanitation",
            "type":"Services"
        }
    ],
    "sg:phone":"+1 417 877 8022",
    "sg:postcode":"65804",
    "sg:province":"MO",
    "sg:tags":[
        "maintenance"
    ],
    "wof:name":"Midnight Madness Janitorial",
    "wof:placetype":"venue"
},
  "geometry": {"coordinates":[-93.252684,37.185896],"type":"Point"}
}