{
  "type": "Feature",
  "properties": {
    "iso:country":"US",
    "sg:address":"23 SE 3 St",
    "sg:city":"Lees Summit",
    "sg:classifiers":[
        {
            "category":"Professional",
            "subcategory":"Lawyer & Legal Services",
            "type":"Services"
        }
    ],
    "sg:phone":"+1 816 525 9000",
    "sg:postcode":"64063",
    "sg:province":"MO",
    "sg:tags":[
        "attorney"
    ],
    "wof:name":"O'Brien Law Office",
    "wof:placetype":"venue"
},
  "geometry": {"coordinates":[-94.37691100000001,38.912161],"type":"Point"}
}