{
  "type": "Feature",
  "properties": {
    "iso:country":"US",
    "sg:address":"2088 Co Ln 172",
    "sg:city":"Carthage",
    "sg:classifiers":[
        {
            "category":"Organizations",
            "subcategory":"Religious Organization",
            "type":"Services"
        }
    ],
    "sg:phone":"+1 417 623 2160",
    "sg:postcode":"64836",
    "sg:province":"MO",
    "sg:tags":[
        "church"
    ],
    "wof:name":"Scotland Church Of God",
    "wof:placetype":"venue"
},
  "geometry": {"coordinates":[-94.372462,37.082719],"type":"Point"}
}