{
  "type": "Feature",
  "properties": {
    "iso:country":"US",
    "sg:address":"401 N Allison St",
    "sg:city":"Lawson",
    "sg:classifiers":[
        {
            "category":"Education",
            "subcategory":"School",
            "type":"Public Place"
        }
    ],
    "sg:phone":"+1 816 580 7277",
    "sg:postcode":"64062",
    "sg:province":"MO",
    "wof:name":"Lawson School District R14",
    "wof:placetype":"venue"
},
  "geometry": {"coordinates":[-94.199242,39.438221],"type":"Point"}
}