{
  "type": "Feature",
  "properties": {
    "iso:country":"US",
    "sg:address":"1420 Highway M",
    "sg:city":"Sedalia",
    "sg:classifiers":[
        {
            "category":"Professional",
            "subcategory":"Management & Consulting",
            "type":"Services"
        },
        {
            "category":"Landmark",
            "subcategory":"Monument",
            "type":"Public Place"
        },
        {
            "category":"Retail",
            "subcategory":"Funeral Services",
            "type":"Services"
        }
    ],
    "sg:phone":"+1 660 826 2207",
    "sg:postcode":"65301",
    "sg:province":"MO",
    "sg:tags":[
        "consultant",
        "plans-pre-arranged"
    ],
    "sg:website":"http://kidwellgranite.com",
    "wof:name":"Sedalia Monument Co",
    "wof:placetype":"venue"
},
  "geometry": {"coordinates":[-93.190386,38.699581],"type":"Point"}
}