{
  "type": "Feature",
  "properties": {
    "iso:country":"US",
    "sg:address":"929 Summit Oaks Dr",
    "sg:city":"Eureka",
    "sg:classifiers":[
        {
            "category":"Shopping",
            "subcategory":"Gifts & Souvenirs",
            "type":"Retail Goods"
        }
    ],
    "sg:phone":"+1 636 390 4700",
    "sg:postcode":"63025",
    "sg:province":"MO",
    "sg:tags":[
        "shop"
    ],
    "wof:name":"Pizzazz",
    "wof:placetype":"venue"
},
  "geometry": {"coordinates":[-90.666061,38.501508],"type":"Point"}
}