{
  "type": "Feature",
  "properties": {
    "iso:country":"US",
    "sg:address":"8327 S Broadway",
    "sg:city":"St Louis",
    "sg:classifiers":[
        {
            "category":"Social Services",
            "type":"Services"
        }
    ],
    "sg:phone":"+1 314 631 4299",
    "sg:postcode":"63111",
    "sg:province":"MO",
    "sg:tags":[
        "organization",
        "welfare"
    ],
    "sg:website":"www.harrishouse.org",
    "wof:name":"Harris House",
    "wof:placetype":"venue"
},
  "geometry": {"coordinates":[-90.26421499999999,38.541965],"type":"Point"}
}