{
  "type": "Feature",
  "properties": {
    "iso:country":"US",
    "sg:address":"525 Zigler St",
    "sg:city":"Webb City",
    "sg:classifiers":[
        {
            "category":"Retail",
            "subcategory":"Repair Shop",
            "type":"Services"
        }
    ],
    "sg:phone":"+1 417 673 1816",
    "sg:postcode":"64870",
    "sg:province":"MO",
    "wof:name":"United Scale Service",
    "wof:placetype":"venue"
},
  "geometry": {"coordinates":[-94.48151,37.139625],"type":"Point"}
}