{
  "type": "Feature",
  "properties": {
    "iso:country":"US",
    "sg:address":"3518 E Catalpa St",
    "sg:city":"Springfield",
    "sg:classifiers":[
        {
            "category":"Real Estate",
            "subcategory":"Real Estate Agent",
            "type":"Services"
        }
    ],
    "sg:phone":"+1 417 833 6402",
    "sg:postcode":"65809",
    "sg:province":"MO",
    "sg:tags":[
        "appraiser",
        "business"
    ],
    "wof:name":"Glor Jerry Appraisal",
    "wof:placetype":"venue"
},
  "geometry": {"coordinates":[-93.22458899999999,37.191234],"type":"Point"}
}