{
  "type": "Feature",
  "properties": {
    "addr:full":"2045 N MO-125 Strafford MO 65757",
    "addr:housenumber":"2045",
    "addr:postcode":"mo-125;65757",
    "addr:street":"N",
    "iso:country":"US",
    "sg:address":"2045 N MO-125",
    "sg:city":"Strafford",
    "sg:classifiers":[
        {
            "category":"Restaurant",
            "type":"Food & Drink"
        }
    ],
    "sg:menulink":"http://www.allmenus.com/mo/taylor/67828-foxs-pizza-den/menu/",
    "sg:phone":"+1 417 736 2004",
    "sg:postcode":"65757",
    "sg:province":"MO",
    "sg:tags":[
        "american",
        "pizza"
    ],
    "wof:name":"Fox's Pizza Den",
    "wof:placetype":"venue"
},
  "geometry": {"coordinates":[-93.1357,37.231377],"type":"Point"}
}