{
  "type": "Feature",
  "properties": {
    "iso:country":"US",
    "sg:address":"600 W Washington Blvd",
    "sg:city":"Cuba",
    "sg:classifiers":[
        {
            "category":"Real Estate",
            "subcategory":"Real Estate Services",
            "type":"Services"
        }
    ],
    "sg:phone":"+1 573 885 6470",
    "sg:postcode":"65453",
    "sg:province":"MO",
    "sg:tags":[
        "abstract",
        "title"
    ],
    "wof:name":"Crawford County Title Co",
    "wof:placetype":"venue"
},
  "geometry": {"coordinates":[-91.40706,38.061849],"type":"Point"}
}