{
  "type": "Feature",
  "properties": {
    "iso:country":"US",
    "sg:address":"1406 Neffwold Ln",
    "sg:city":"St Louis",
    "sg:classifiers":[
        {
            "category":"Manufacturing",
            "subcategory":"Paper Products",
            "type":"Manufacturing & Wholesale Goods"
        }
    ],
    "sg:phone":"+1 314 909 7588",
    "sg:postcode":"63122",
    "sg:province":"MO",
    "sg:tags":[
        "bag"
    ],
    "wof:name":"Bancroft Bag Inc",
    "wof:placetype":"venue"
},
  "geometry": {"coordinates":[-90.433789,38.559418],"type":"Point"}
}