{
  "type": "Feature",
  "properties": {
    "iso:country":"US",
    "sg:address":"1618 US Hwy 160",
    "sg:city":"Caulfield",
    "sg:classifiers":[
        {
            "category":"Retail",
            "subcategory":"Auto Repair",
            "type":"Services"
        }
    ],
    "sg:phone":"+1 417 284 8084",
    "sg:postcode":"65626",
    "sg:province":"AR",
    "sg:tags":[
        "transmission"
    ],
    "wof:name":"Tranny Shop",
    "wof:placetype":"venue"
},
  "geometry": {"coordinates":[-92.04591600000001,36.61513],"type":"Point"}
}