{
  "type": "Feature",
  "properties": {
    "iso:country":"US",
    "sg:address":"1970 Craig Rd",
    "sg:city":"St Louis",
    "sg:classifiers":[
        {
            "category":"Travel",
            "subcategory":"Hotels & Motels",
            "type":"Entertainment"
        }
    ],
    "sg:phone":"+1 314 205 8000",
    "sg:postcode":"63146",
    "sg:province":"MO",
    "sg:tags":[
        "operation"
    ],
    "wof:name":"Club House Inn & Suites",
    "wof:placetype":"venue"
},
  "geometry": {"coordinates":[-90.442065,38.696776],"type":"Point"}
}