{
  "type": "Feature",
  "properties": {
    "iso:country":"US",
    "sg:address":"1625 Larkin Williams Rd",
    "sg:city":"Fenton",
    "sg:classifiers":[
        {
            "category":"Shopping",
            "type":"Retail Goods"
        }
    ],
    "sg:phone":"+1 636 305 3100",
    "sg:postcode":"63026",
    "sg:province":"MO",
    "sg:tags":[
        "religious"
    ],
    "sg:website":"www.ctainc.com",
    "wof:name":"Christian Teachers Aid",
    "wof:placetype":"venue"
},
  "geometry": {"coordinates":[-90.45314399999999,38.53553],"type":"Point"}
}