{
  "type": "Feature",
  "properties": {
    "iso:country":"US",
    "sg:address":"337 Nelda Ave",
    "sg:city":"Saint Louis",
    "sg:classifiers":[
        {
            "category":"Professional",
            "subcategory":"Management & Consulting",
            "type":"Services"
        }
    ],
    "sg:phone":"+1 314 965 1776",
    "sg:postcode":"63122",
    "sg:province":"MO",
    "sg:tags":[
        "communication",
        "public",
        "relations"
    ],
    "wof:name":"Eicher Communications Inc",
    "wof:placetype":"venue"
},
  "geometry": {"coordinates":[-90.429089,38.576051],"type":"Point"}
}