{
  "type": "Feature",
  "properties": {
    "iso:country":"US",
    "sg:address":"11 N Water St",
    "sg:city":"Liberty",
    "sg:phone":"+1 816 781 4922",
    "sg:postcode":"64068",
    "sg:province":"MO",
    "sg:website":"http://www.gmpeters.com",
    "wof:name":"GM Peters Insurance Agency Inc.",
    "wof:placetype":"venue"
},
  "geometry": {"coordinates":[-94.41943999999999,39.246164],"type":"Point"}
}