{
  "type": "Feature",
  "properties": {
    "iso:country":"US",
    "sg:address":"1734 Warmington Ct",
    "sg:city":"Ballwin",
    "sg:classifiers":[
        {
            "category":"Restaurant",
            "type":"Food & Drink"
        }
    ],
    "sg:phone":"+1 636 394 6196",
    "sg:postcode":"63021",
    "sg:province":"MO",
    "sg:tags":[
        "eating"
    ],
    "wof:name":"Palermos Pizza Champion Pizza",
    "wof:placetype":"venue"
},
  "geometry": {"coordinates":[-90.47469100000001,38.585739],"type":"Point"}
}