{
  "type": "Feature",
  "properties": {
    "iso:country":"US",
    "sg:address":"53553 Swift Ln",
    "sg:city":"Vandalia",
    "sg:classifiers":[
        {
            "category":"Manufacturing",
            "subcategory":"Food",
            "type":"Manufacturing & Wholesale Goods"
        }
    ],
    "sg:phone":"+1 573 594 2657",
    "sg:postcode":"63382",
    "sg:province":"MO",
    "sg:tags":[
        "product"
    ],
    "wof:name":"Malcom Coose",
    "wof:placetype":"venue"
},
  "geometry": {"coordinates":[-91.47028899999999,39.334339],"type":"Point"}
}