{
  "type": "Feature",
  "properties": {
    "iso:country":"US",
    "sg:address":"134 E Velma Ave",
    "sg:city":"St Louis",
    "sg:classifiers":[
        {
            "category":"Home & Garden",
            "subcategory":"Building Materials",
            "type":"Retail Goods"
        }
    ],
    "sg:phone":"+1 314 544 3010",
    "sg:postcode":"63125",
    "sg:province":"MO",
    "sg:tags":[
        "door"
    ],
    "wof:name":"Parkton Innovations Inc",
    "wof:placetype":"venue"
},
  "geometry": {"coordinates":[-90.275492,38.52958],"type":"Point"}
}