{
  "type": "Feature",
  "properties": {
    "iso:country":"US",
    "sg:address":"2008 Kratky Rd",
    "sg:city":"Saint Louis",
    "sg:classifiers":[
        {
            "category":"Building & Trades",
            "subcategory":"Construction",
            "type":"Services"
        }
    ],
    "sg:phone":"+1 314 872 3326",
    "sg:postcode":"63114",
    "sg:province":"MO",
    "sg:tags":[
        "contractor"
    ],
    "wof:name":"Invisible Fence of St Louis",
    "wof:placetype":"venue"
},
  "geometry": {"coordinates":[-90.40719,38.699837],"type":"Point"}
}