{
  "type": "Feature",
  "properties": {
    "iso:country":"US",
    "sg:address":"1200 SW Madison St",
    "sg:city":"Lees Summit",
    "sg:classifiers":[
        {
            "category":"Professional",
            "subcategory":"Business Services",
            "type":"Services"
        }
    ],
    "sg:phone":"+1 816 524 0535",
    "sg:postcode":"64081",
    "sg:province":"MO",
    "sg:tags":[
        "transcribing",
        "disc"
    ],
    "wof:name":"Professional Medical Trnscrptn",
    "wof:placetype":"venue"
},
  "geometry": {"coordinates":[-94.383788,38.897199],"type":"Point"}
}