{
  "type": "Feature",
  "properties": {
    "iso:country":"US",
    "sg:address":"2358 S 13th St",
    "sg:city":"St Louis",
    "sg:classifiers":[
        {
            "category":"Professional",
            "subcategory":"Management & Consulting",
            "type":"Services"
        },
        {
            "category":"Professional",
            "subcategory":"Employment Agencies",
            "type":"Services"
        }
    ],
    "sg:phone":"+1 314 771 2662",
    "sg:postcode":"63104",
    "sg:province":"MO",
    "sg:tags":[
        "personnel",
        "supply",
        "help",
        "consultant"
    ],
    "wof:name":"Landmark Staffing",
    "wof:placetype":"venue"
},
  "geometry": {"coordinates":[-90.212324,38.604684],"type":"Point"}
}