{
  "type": "Feature",
  "properties": {
    "iso:country":"US",
    "sg:address":"16752 Wild Horse Creek Rd",
    "sg:city":"Chesterfield",
    "sg:classifiers":[
        {
            "category":"Wholesale",
            "subcategory":"Sporting Goods",
            "type":"Manufacturing & Wholesale Goods"
        }
    ],
    "sg:phone":"+1 636 537 9200",
    "sg:postcode":"63005",
    "sg:province":"MO",
    "sg:tags":[
        "equipment",
        "billiard",
        "supply"
    ],
    "wof:name":"Amini's Galleria",
    "wof:placetype":"venue"
},
  "geometry": {"coordinates":[-90.588499,38.655702],"type":"Point"}
}