{
  "type": "Feature",
  "properties": {
    "addr:full":"717 Branson Landing Blvd Branson MO 65616",
    "addr:housenumber":"717",
    "addr:postcode":"65616",
    "addr:street":"Branson Landing Blvd",
    "iso:country":"US",
    "sg:address":"717 Branson Landing Blvd",
    "sg:city":"Branson",
    "sg:classifiers":[
        {
            "category":"Restaurant",
            "type":"Food & Drink"
        }
    ],
    "sg:phone":"+1 417 337 7373",
    "sg:postcode":"65616",
    "sg:province":"MO",
    "sg:tags":[
        "seafood",
        "style",
        "american",
        "family"
    ],
    "sg:website":"http://www.joescrabshack.com",
    "wof:name":"Joe's Crab Shack",
    "wof:placetype":"venue"
},
  "geometry": {"coordinates":[-93.21389000000001,36.640382],"type":"Point"}
}