{
  "type": "Feature",
  "properties": {
    "addr:full":"126 Cunningham Pkwy Belton MO 64012",
    "addr:housenumber":"126",
    "addr:postcode":"64012",
    "addr:street":"Cunningham Pkwy",
    "iso:country":"US",
    "sg:address":"126 Cunningham Pkwy",
    "sg:city":"Belton",
    "sg:classifiers":[
        {
            "category":"Insurance",
            "subcategory":"Insurance Agent",
            "type":"Services"
        }
    ],
    "sg:phone":"+1 816 322 1622",
    "sg:postcode":"64012",
    "sg:province":"MO",
    "wof:name":"Farmers Insurance",
    "wof:placetype":"venue"
},
  "geometry": {"coordinates":[-94.506957,38.810173],"type":"Point"}
}