{
  "type": "Feature",
  "properties": {
    "iso:country":"US",
    "sg:address":"134 N Kingshighway St",
    "sg:city":"St Charles",
    "sg:classifiers":[
        {
            "category":"Personal",
            "subcategory":"Barber",
            "type":"Services"
        }
    ],
    "sg:phone":"+1 636 946 0700",
    "sg:postcode":"63301",
    "sg:province":"MO",
    "wof:name":"Tony's Barbershop",
    "wof:placetype":"venue"
},
  "geometry": {"coordinates":[-90.494748,38.786268],"type":"Point"}
}