{
  "type": "Feature",
  "properties": {
    "iso:country":"US",
    "sg:address":"5015 Cabanne Ave",
    "sg:city":"St Louis",
    "sg:classifiers":[
        {
            "category":"Real Estate",
            "subcategory":"Real Estate Agent",
            "type":"Services"
        }
    ],
    "sg:phone":"+1 314 454 9757",
    "sg:postcode":"63113",
    "sg:province":"MO",
    "wof:name":"Property Concepts",
    "wof:placetype":"venue"
},
  "geometry": {"coordinates":[-90.265851,38.656513],"type":"Point"}
}