{
  "type": "Feature",
  "properties": {
    "addr:full":"13526 Heritage Dr St Joseph MO 64505",
    "addr:housenumber":"13526",
    "addr:postcode":"64505",
    "addr:street":"Heritage Dr",
    "iso:country":"US",
    "sg:address":"13526 Heritage Dr",
    "sg:city":"St Joseph",
    "sg:classifiers":[
        {
            "category":"Shopping",
            "subcategory":"Pharmacy",
            "type":"Retail Goods"
        }
    ],
    "sg:phone":"+1 816 279 2632",
    "sg:postcode":"64505",
    "sg:province":"MO",
    "sg:tags":[
        "product",
        "health",
        "care"
    ],
    "wof:name":"Herbalife Distributor",
    "wof:placetype":"venue"
},
  "geometry": {"coordinates":[-94.800725,39.829081],"type":"Point"}
}