{
  "type": "Feature",
  "properties": {
    "iso:country":"US",
    "sg:address":"1807 W 7th St",
    "sg:city":"Joplin",
    "sg:classifiers":[
        {
            "category":"Autos & Motor Vehicles",
            "subcategory":"Automobile Sales",
            "type":"Retail Goods"
        }
    ],
    "sg:phone":"+1 417 625 5595",
    "sg:postcode":"64801",
    "sg:province":"MO",
    "sg:tags":[
        "new",
        "car"
    ],
    "wof:name":"Roper's West",
    "wof:placetype":"venue"
},
  "geometry": {"coordinates":[-94.536393,37.084692],"type":"Point"}
}