{
  "type": "Feature",
  "properties": {
    "iso:country":"US",
    "sg:address":"1400 State Hwy F",
    "sg:city":"Waynesville",
    "sg:classifiers":[
        {
            "category":"Social Services",
            "type":"Services"
        }
    ],
    "sg:phone":"+1 573 774 0097",
    "sg:postcode":"65583",
    "sg:province":"MO",
    "sg:tags":[
        "counseling"
    ],
    "wof:name":"Susan A Marino",
    "wof:placetype":"venue"
},
  "geometry": {"coordinates":[-92.180004,37.828379],"type":"Point"}
}