{
  "type": "Feature",
  "properties": {
    "iso:country":"US",
    "sg:address":"610 S Church St",
    "sg:city":"Fayette",
    "sg:classifiers":[
        {
            "category":"Building & Trades",
            "subcategory":"Construction",
            "type":"Services"
        }
    ],
    "sg:phone":"+1 660 248 2385",
    "sg:postcode":"65248",
    "sg:province":"MO",
    "sg:tags":[
        "marking",
        "maintenance",
        "parking"
    ],
    "wof:name":"Fayette City Street Dept",
    "wof:placetype":"venue"
},
  "geometry": {"coordinates":[-92.68067000000001,39.141802],"type":"Point"}
}