{
  "type": "Feature",
  "properties": {
    "iso:country":"US",
    "sg:address":"2414 Taylor Rd",
    "sg:city":"Grover",
    "sg:classifiers":[
        {
            "category":"Shopping",
            "subcategory":"Pets & Pet Supplies",
            "type":"Retail Goods"
        },
        {
            "category":"Retail",
            "subcategory":"Animal Services",
            "type":"Services"
        }
    ],
    "sg:phone":"+1 636 458 8838",
    "sg:postcode":"63040",
    "sg:province":"MO",
    "sg:tags":[
        "specialty",
        "food",
        "dog",
        "cat",
        "furnishing",
        "store"
    ],
    "sg:website":"http://www.oneluckymutt.com",
    "wof:name":"One Lucky Mutt",
    "wof:placetype":"venue"
},
  "geometry": {"coordinates":[-90.627426,38.582069],"type":"Point"}
}