{
  "type": "Feature",
  "properties": {
    "iso:country":"US",
    "sg:address":"2138 Ridge Dr",
    "sg:city":"Arnold",
    "sg:classifiers":[
        {
            "category":"Place Of Worship",
            "subcategory":"Church",
            "type":"Public Place"
        },
        {
            "category":"Place Of Worship",
            "type":"Public Place"
        }
    ],
    "sg:phone":"+1 636 287 3010",
    "sg:postcode":"63010",
    "sg:province":"MO",
    "sg:tags":[
        "churches-non-denominational"
    ],
    "wof:name":"Church In Action",
    "wof:placetype":"venue"
},
  "geometry": {"coordinates":[-90.37621,38.442489],"type":"Point"}
}