{
  "type": "Feature",
  "properties": {
    "iso:country":"US",
    "sg:address":"3676 Eagles Hill Ridge",
    "sg:city":"Saint Charles",
    "sg:classifiers":[
        {
            "category":"Professional",
            "subcategory":"Management & Consulting",
            "type":"Services"
        }
    ],
    "sg:phone":"+1 314 210 0214",
    "sg:postcode":"63303",
    "sg:province":"MO",
    "wof:name":"Trichotomy LLC",
    "wof:placetype":"venue"
},
  "geometry": {"coordinates":[-90.576004,38.736631],"type":"Point"}
}