{
  "type": "Feature",
  "properties": {
    "iso:country":"US",
    "sg:address":"116 Chiefs Ct",
    "sg:city":"Branson",
    "sg:classifiers":[
        {
            "category":"Shopping",
            "subcategory":"Florist",
            "type":"Retail Goods"
        }
    ],
    "sg:phone":"+1 417 335 2203",
    "sg:postcode":"65616",
    "sg:province":"MO",
    "wof:name":"Accents Flower Shop",
    "wof:placetype":"venue"
},
  "geometry": {"coordinates":[-93.251254,36.672395],"type":"Point"}
}