{
  "type": "Feature",
  "properties": {
    "iso:country":"US",
    "sg:address":"3201 Highway 61",
    "sg:city":"Hannibal",
    "sg:classifiers":[
        {
            "category":"Health Services",
            "subcategory":"Doctor",
            "type":"Services"
        },
        {
            "category":"Health Services",
            "subcategory":"Clinic",
            "type":"Services"
        }
    ],
    "sg:phone":"+1 573 248 0008",
    "sg:postcode":"63401",
    "sg:province":"MO",
    "sg:tags":[
        "physician",
        "medical",
        "surgeons",
        "surgery-general",
        "welfare"
    ],
    "wof:name":"Quincy Medical Group",
    "wof:placetype":"venue"
},
  "geometry": {"coordinates":[-91.39052700000001,39.708204],"type":"Point"}
}