{
  "type": "Feature",
  "properties": {
    "iso:country":"US",
    "sg:address":"309 Smoky Mountain Ct",
    "sg:city":"Columbia",
    "sg:classifiers":[
        {
            "category":"Health Services",
            "subcategory":"Clinic",
            "type":"Services"
        }
    ],
    "sg:phone":"+1 573 446 1929",
    "sg:postcode":"65203",
    "sg:province":"MO",
    "sg:tags":[
        "welfare"
    ],
    "wof:name":"Ashkey Mbnor Care Center Ashle",
    "wof:placetype":"venue"
},
  "geometry": {"coordinates":[-92.388876,38.951613],"type":"Point"}
}