{
  "type": "Feature",
  "properties": {
    "iso:country":"US",
    "sg:address":"1212 S Main St",
    "sg:city":"Maryville",
    "sg:classifiers":[
        {
            "category":"Education",
            "subcategory":"School",
            "type":"Public Place"
        }
    ],
    "sg:phone":"+1 660 562 2036",
    "sg:postcode":"64468",
    "sg:province":"MO",
    "wof:name":"Missouri Pre School Project",
    "wof:placetype":"venue"
},
  "geometry": {"coordinates":[-94.873898,40.333739],"type":"Point"}
}