{
  "type": "Feature",
  "properties": {
    "iso:country":"US",
    "sg:address":"204 Johnson Cir",
    "sg:city":"Carrollton",
    "sg:classifiers":[
        {
            "category":"Health Services",
            "subcategory":"Doctor",
            "type":"Services"
        }
    ],
    "sg:phone":"+1 660 542 3418",
    "sg:postcode":"64633",
    "sg:province":"MO",
    "sg:tags":[
        "medical"
    ],
    "wof:name":"Donald L Kampschmidt MD",
    "wof:placetype":"venue"
},
  "geometry": {"coordinates":[-93.492744,39.370795],"type":"Point"}
}