{
  "type": "Feature",
  "properties": {
    "iso:country":"US",
    "sg:address":"138 E Torrance St",
    "sg:city":"Maryville",
    "sg:classifiers":[
        {
            "category":"Social Services",
            "subcategory":"Child Care",
            "type":"Services"
        }
    ],
    "sg:phone":"+1 660 582 8054",
    "sg:postcode":"64468",
    "sg:province":"MO",
    "sg:tags":[
        "day"
    ],
    "wof:name":"Farnans Day Care",
    "wof:placetype":"venue"
},
  "geometry": {"coordinates":[-94.872699,40.340268],"type":"Point"}
}