{
  "type": "Feature",
  "properties": {
    "iso:country":"US",
    "sg:address":"14974 State Hwy 164",
    "sg:city":"Hornersville",
    "sg:classifiers":[
        {
            "category":"Freight",
            "type":"Transportation"
        }
    ],
    "sg:phone":"+1 573 737 2428",
    "sg:postcode":"63855",
    "sg:province":"MO",
    "sg:tags":[
        "trucking"
    ],
    "wof:name":"Harold Bibbs & Sons Trucking",
    "wof:placetype":"venue"
},
  "geometry": {"coordinates":[-90.12508,36.046594],"type":"Point"}
}