{
  "type": "Feature",
  "properties": {
    "addr:full":"7194 Page Ave Saint Louis MO 63133",
    "addr:housenumber":"7194",
    "addr:postcode":"63133",
    "addr:street":"Page Ave",
    "iso:country":"US",
    "sg:address":"7194 Page Ave",
    "sg:city":"Saint Louis",
    "sg:classifiers":[
        {
            "category":"Restaurant",
            "type":"Food & Drink"
        }
    ],
    "sg:phone":"+1 314 721 2450",
    "sg:postcode":"63133",
    "sg:province":"MO",
    "sg:tags":[
        "eating"
    ],
    "wof:name":"Chung's Chop Suey",
    "wof:placetype":"venue"
},
  "geometry": {"coordinates":[-90.314796,38.677101],"type":"Point"}
}