{
  "type": "Feature",
  "properties": {
    "iso:country":"US",
    "sg:address":"5620 Kerth Rd",
    "sg:city":"Saint Louis",
    "sg:classifiers":[
        {
            "category":"Shopping",
            "subcategory":"Books",
            "type":"Retail Goods"
        }
    ],
    "sg:phone":"+1 314 845 3264",
    "sg:postcode":"63128",
    "sg:province":"MO",
    "wof:name":"Booksmart Inc",
    "wof:placetype":"venue"
},
  "geometry": {"coordinates":[-90.371835,38.47532],"type":"Point"}
}