{
  "type": "Feature",
  "properties": {
    "iso:country":"US",
    "sg:address":"540 US Hwy 50 W",
    "sg:city":"Union",
    "sg:classifiers":[
        {
            "category":"Retail",
            "subcategory":"Animal Services",
            "type":"Services"
        }
    ],
    "sg:phone":"+1 636 583 0770",
    "sg:postcode":"63084",
    "sg:province":"MO",
    "wof:name":"Pampered Pets Grooming",
    "wof:placetype":"venue"
},
  "geometry": {"coordinates":[-91.015023,38.439204],"type":"Point"}
}