{
  "type": "Feature",
  "properties": {
    "iso:country":"US",
    "sg:address":"1279 SW 90th Rd",
    "sg:city":"Asbury",
    "sg:classifiers":[
        {
            "category":"Building & Trades",
            "subcategory":"Landscaping Services",
            "type":"Services"
        }
    ],
    "sg:phone":"+1 417 842 3305",
    "sg:postcode":"64832",
    "sg:province":"MO",
    "sg:tags":[
        "landscape"
    ],
    "wof:name":"Hinrichs Maintenance",
    "wof:placetype":"venue"
},
  "geometry": {"coordinates":[-94.53183300000001,37.376269],"type":"Point"}
}