{
  "type": "Feature",
  "properties": {
    "iso:country":"US",
    "sg:address":"9925 Liv 2302",
    "sg:city":"Chillicothe",
    "sg:classifiers":[
        {
            "category":"Farming",
            "subcategory":"Farm & Veterinary Services",
            "type":"Manufacturing & Wholesale Goods"
        }
    ],
    "sg:phone":"+1 660 646 5310",
    "sg:postcode":"64601",
    "sg:province":"MO",
    "sg:tags":[
        "preparation",
        "crop",
        "for",
        "market"
    ],
    "wof:name":"Kimmis Williams",
    "wof:placetype":"venue"
},
  "geometry": {"coordinates":[-93.597673,39.815739],"type":"Point"}
}