{
  "type": "Feature",
  "properties": {
    "iso:country":"US",
    "sg:address":"935 Markey Dr",
    "sg:city":"Belton",
    "sg:classifiers":[
        {
            "category":"Professional",
            "type":"Services"
        }
    ],
    "sg:phone":"+1 816 318 9200",
    "sg:postcode":"64012",
    "sg:province":"MO",
    "sg:tags":[
        "establishment"
    ],
    "wof:name":"Moneymatters Network Inc",
    "wof:placetype":"venue"
},
  "geometry": {"coordinates":[-94.54114800000001,38.829899],"type":"Point"}
}