{
  "type": "Feature",
  "properties": {
    "iso:country":"US",
    "sg:address":"11906 Manchester Rd",
    "sg:city":"Saint Louis",
    "sg:classifiers":[
        {
            "category":"Real Estate",
            "subcategory":"Real Estate Agent",
            "type":"Services"
        }
    ],
    "sg:phone":"+1 314 822 7478",
    "sg:postcode":"63131",
    "sg:province":"MO",
    "wof:name":"Roth David A & Assoc Inc",
    "wof:placetype":"venue"
},
  "geometry": {"coordinates":[-90.432006,38.601047],"type":"Point"}
}