{
  "type": "Feature",
  "properties": {
    "iso:country":"US",
    "sg:address":"923 S Main St",
    "sg:city":"Fredericktown",
    "sg:classifiers":[
        {
            "category":"Building & Trades",
            "subcategory":"Construction",
            "type":"Services"
        }
    ],
    "sg:phone":"+1 573 783 3205",
    "sg:postcode":"63645",
    "sg:province":"MO",
    "sg:tags":[
        "marking",
        "maintenance",
        "parking"
    ],
    "wof:name":"Fredericktown Street Dept",
    "wof:placetype":"venue"
},
  "geometry": {"coordinates":[-90.294895,37.548015],"type":"Point"}
}