{
  "type": "Feature",
  "properties": {
    "iso:country":"US",
    "sg:address":"145 Main Street",
    "sg:city":"Newburg",
    "sg:phone":"+1 573 762 2915",
    "sg:postcode":"65550",
    "sg:province":"MO",
    "wof:name":"Blue's Market",
    "wof:placetype":"venue"
},
  "geometry": {"coordinates":[-91.898853,37.922041],"type":"Point"}
}