{
  "type": "Feature",
  "properties": {
    "iso:country":"US",
    "sg:address":"4997 Co Rd 290",
    "sg:city":"Puxico",
    "sg:classifiers":[
        {
            "category":"Farming",
            "subcategory":"Livestock Farm",
            "type":"Manufacturing & Wholesale Goods"
        }
    ],
    "sg:phone":"+1 573 222 3229",
    "sg:postcode":"63960",
    "sg:province":"MO",
    "sg:tags":[
        "beef",
        "feedlot",
        "cattle"
    ],
    "wof:name":"Claude Lowe",
    "wof:placetype":"venue"
},
  "geometry": {"coordinates":[-90.205252,36.914614],"type":"Point"}
}