{
  "type": "Feature",
  "properties": {
    "iso:country":"US",
    "sg:address":"1239 Belmont Ave",
    "sg:city":"Kansas City",
    "sg:classifiers":[
        {
            "category":"Personal",
            "subcategory":"Beauty Salon",
            "type":"Services"
        }
    ],
    "sg:phone":"+1 816 231 6130",
    "sg:postcode":"64126",
    "sg:province":"MO",
    "sg:tags":[
        "shop"
    ],
    "wof:name":"Js Hair Care",
    "wof:placetype":"venue"
},
  "geometry": {"coordinates":[-94.510014,39.095749],"type":"Point"}
}