{
  "type": "Feature",
  "properties": {
    "iso:country":"US",
    "sg:address":"413 E Walnut St",
    "sg:city":"Springfield",
    "sg:classifiers":[
        {
            "category":"Organizations",
            "subcategory":"Religious Organization",
            "type":"Services"
        }
    ],
    "sg:phone":"+1 417 866 4326",
    "sg:postcode":"65806",
    "sg:province":"MO",
    "wof:name":"Saint Paul Untd Methdst Church",
    "wof:placetype":"venue"
},
  "geometry": {"coordinates":[-93.288524,37.206978],"type":"Point"}
}