{
  "type": "Feature",
  "properties": {
    "iso:country":"US",
    "sg:address":"5434 Tracy Ave",
    "sg:city":"Kansas City",
    "sg:classifiers":[
        {
            "category":"Freight",
            "type":"Transportation"
        }
    ],
    "sg:phone":"+1 816 822 4042",
    "sg:postcode":"64110",
    "sg:province":"MO",
    "sg:tags":[
        "operator",
        "local",
        "trucking"
    ],
    "wof:name":"Ricketts Trucking",
    "wof:placetype":"venue"
},
  "geometry": {"coordinates":[-94.57153099999999,39.027736],"type":"Point"}
}