{
  "type": "Feature",
  "properties": {
    "iso:country":"US",
    "sg:address":"1310 Lockett Ln",
    "sg:city":"Saint Louis",
    "sg:classifiers":[
        {
            "category":"Banks & Credit Unions",
            "subcategory":"Investment Brokerage",
            "type":"Services"
        }
    ],
    "sg:phone":"+1 314 966 6706",
    "sg:postcode":"63122",
    "sg:province":"MO",
    "sg:tags":[
        "advisory"
    ],
    "wof:name":"Egc Financial Inc",
    "wof:placetype":"venue"
},
  "geometry": {"coordinates":[-90.43077099999999,38.594768],"type":"Point"}
}