{
  "type": "Feature",
  "properties": {
    "iso:country":"US",
    "sg:address":"1898 Wentzville Pkwy",
    "sg:city":"Wentzville",
    "sg:classifiers":[
        {
            "category":"Ice Cream",
            "type":"Food & Drink"
        }
    ],
    "sg:menulink":"http://www.allmenus.com/mo/wentzville/182880-culvers/menu/",
    "sg:phone":"+1 636 327 7537",
    "sg:postcode":"63385",
    "sg:province":"MO",
    "sg:tags":[
        "burger",
        "american"
    ],
    "wof:name":"Culver's",
    "wof:placetype":"venue"
},
  "geometry": {"coordinates":[-90.853071,38.822064],"type":"Point"}
}