{
  "type": "Feature",
  "properties": {
    "iso:country":"US",
    "sg:address":"4100 SW Ward Rd",
    "sg:city":"Lees Summit",
    "sg:classifiers":[
        {
            "category":"Retail",
            "subcategory":"Laundry & Dry Cleaning",
            "type":"Services"
        }
    ],
    "sg:phone":"+1 816 524 3007",
    "sg:postcode":"64082",
    "sg:province":"MO",
    "wof:name":"Design For Dancers",
    "wof:placetype":"venue"
},
  "geometry": {"coordinates":[-94.398791,38.851636],"type":"Point"}
}