{
  "type": "Feature",
  "properties": {
    "iso:country":"US",
    "sg:address":"12350 S 1325 Rd",
    "sg:city":"Stockton",
    "sg:classifiers":[
        {
            "category":"Building & Trades",
            "subcategory":"Construction",
            "type":"Services"
        }
    ],
    "sg:phone":"+1 417 276 3235",
    "sg:postcode":"65785",
    "sg:province":"MO",
    "sg:tags":[
        "repair",
        "remodeling",
        "home"
    ],
    "wof:name":"Contractors Unlimited",
    "wof:placetype":"venue"
},
  "geometry": {"coordinates":[-93.83144900000001,37.719626],"type":"Point"}
}