{
  "type": "Feature",
  "properties": {
    "iso:country":"US",
    "sg:address":"2438 Taylor Rd",
    "sg:city":"Grover",
    "sg:classifiers":[
        {
            "category":"Personal",
            "subcategory":"Nail Salon",
            "type":"Services"
        }
    ],
    "sg:phone":"+1 636 405 1190",
    "sg:postcode":"63040",
    "sg:province":"MO",
    "wof:name":"Wildwood Nail Spa",
    "wof:placetype":"venue"
},
  "geometry": {"coordinates":[-90.62746300000001,38.581651],"type":"Point"}
}