{
  "type": "Feature",
  "properties": {
    "iso:country":"US",
    "sg:address":"612 Selma Ave",
    "sg:city":"Webster Groves",
    "sg:classifiers":[
        {
            "category":"Building & Trades",
            "subcategory":"Construction",
            "type":"Services"
        }
    ],
    "sg:phone":"+1 314 968 3246",
    "sg:postcode":"63119",
    "sg:province":"MO",
    "sg:tags":[
        "repairing",
        "remodeling",
        "contractor"
    ],
    "wof:name":"Tri-Square Construction",
    "wof:placetype":"venue"
},
  "geometry": {"coordinates":[-90.350425,38.580167],"type":"Point"}
}