{
  "type": "Feature",
  "properties": {
    "iso:country":"US",
    "sg:address":"615 E 23rd St S",
    "sg:city":"Independence",
    "sg:classifiers":[
        {
            "category":"Insurance",
            "subcategory":"Insurance Agent",
            "type":"Services"
        },
        {
            "category":"Insurance",
            "subcategory":"Hazard Insurance",
            "type":"Services"
        },
        {
            "category":"Insurance",
            "subcategory":"Title Insurance",
            "type":"Services"
        }
    ],
    "sg:phone":"+1 816 254 6800",
    "sg:postcode":"64055",
    "sg:province":"MO",
    "sg:tags":[
        "auto",
        "homeowner"
    ],
    "sg:website":"http://apps.amfam.com/agentlocator/TMILLER?sourceid=yp3",
    "wof:name":"American Family Insurance- Ted Miller Agency Inc",
    "wof:placetype":"venue"
},
  "geometry": {"coordinates":[-94.407891,39.078935],"type":"Point"}
}