{
  "type": "Feature",
  "properties": {
    "iso:country":"US",
    "sg:address":"7100 W Elizabeth St",
    "sg:city":"Columbia",
    "sg:classifiers":[
        {
            "category":"Wholesale",
            "subcategory":"Computers",
            "type":"Manufacturing & Wholesale Goods"
        }
    ],
    "sg:phone":"+1 573 445 4920",
    "sg:postcode":"65202",
    "sg:province":"MO",
    "sg:tags":[
        "equipment"
    ],
    "wof:name":"Spellman Computer Services",
    "wof:placetype":"venue"
},
  "geometry": {"coordinates":[-92.441811,38.994175],"type":"Point"}
}