{
  "type": "Feature",
  "properties": {
    "iso:country":"US",
    "sg:address":"2809 Highway A Ste C",
    "sg:city":"Washington",
    "sg:classifiers":[
        {
            "category":"Building & Trades",
            "subcategory":"Equipment Rental",
            "type":"Services"
        }
    ],
    "sg:phone":"+1 636 239 4762",
    "sg:postcode":"63090",
    "sg:province":"MO",
    "sg:tags":[
        "yard",
        "leasing",
        "store"
    ],
    "wof:name":"Conerco Inc",
    "wof:placetype":"venue"
},
  "geometry": {"coordinates":[-91.024494,38.52615],"type":"Point"}
}