{
  "type": "Feature",
  "properties": {
    "addr:full":"820 Armour Rd Kansas City MO 64116",
    "addr:housenumber":"820",
    "addr:postcode":"64116",
    "addr:street":"Armour Rd",
    "iso:country":"US",
    "sg:address":"820 Armour Rd",
    "sg:city":"Kansas City",
    "sg:classifiers":[
        {
            "category":"Government",
            "subcategory":"Post Office",
            "type":"Public Place"
        }
    ],
    "sg:phone":"+1 816 221 6716",
    "sg:postcode":"64116",
    "sg:province":"MO",
    "wof:name":"US Post Office",
    "wof:placetype":"venue"
},
  "geometry": {"coordinates":[-94.569265,39.143388],"type":"Point"}
}