{
  "type": "Feature",
  "properties": {
    "iso:country":"US",
    "sg:address":"1358 S 5th St",
    "sg:city":"St Charles",
    "sg:classifiers":[
        {
            "category":"Personal",
            "subcategory":"Beauty Salon",
            "type":"Services"
        }
    ],
    "sg:phone":"+1 636 947 4840",
    "sg:postcode":"63301",
    "sg:province":"MO",
    "sg:tags":[
        "manicuring"
    ],
    "wof:name":"Le's Nails",
    "wof:placetype":"venue"
},
  "geometry": {"coordinates":[-90.493627,38.769994],"type":"Point"}
}