{
  "type": "Feature",
  "properties": {
    "iso:country":"US",
    "sg:address":"410 S Oak St",
    "sg:city":"Union",
    "sg:classifiers":[
        {
            "category":"Social Services",
            "type":"Services"
        }
    ],
    "sg:phone":"+1 636 583 2000",
    "sg:postcode":"63084",
    "sg:province":"MO",
    "sg:tags":[
        "mission"
    ],
    "sg:website":"www.ninosdemexico.org",
    "wof:name":"Ninos De Mexico",
    "wof:placetype":"venue"
},
  "geometry": {"coordinates":[-91.00654,38.442334],"type":"Point"}
}