{
  "type": "Feature",
  "properties": {
    "iso:country":"US",
    "sg:address":"1231 E Republic Rd",
    "sg:city":"Springfield",
    "sg:classifiers":[
        {
            "category":"Personal",
            "subcategory":"Tattoo Parlor",
            "type":"Services"
        }
    ],
    "sg:phone":"+1 417 889 9130",
    "sg:postcode":"65804",
    "sg:province":"MO",
    "sg:tags":[
        "tattooing"
    ],
    "wof:name":"Eyewitness Tattoo Studio",
    "wof:placetype":"venue"
},
  "geometry": {"coordinates":[-93.27764999999999,37.137908],"type":"Point"}
}