{
  "type": "Feature",
  "properties": {
    "iso:country":"US",
    "sg:address":"17327 US Hwy 71",
    "sg:city":"Belton",
    "sg:classifiers":[
        {
            "category":"Professional",
            "type":"Services"
        }
    ],
    "sg:phone":"+1 816 322 2350",
    "sg:postcode":"64012",
    "sg:province":"MO",
    "sg:tags":[
        "establishment"
    ],
    "wof:name":"Crabtree Harmon Corp",
    "wof:placetype":"venue"
},
  "geometry": {"coordinates":[-94.501868,38.81052],"type":"Point"}
}