{
  "type": "Feature",
  "properties": {
    "iso:country":"US",
    "sg:address":"660 N Hawkins Ave",
    "sg:city":"Hannibal",
    "sg:classifiers":[
        {
            "category":"Building & Trades",
            "subcategory":"Landscaping Services",
            "type":"Services"
        }
    ],
    "sg:phone":"+1 573 221 5474",
    "sg:postcode":"63401",
    "sg:province":"MO",
    "sg:tags":[
        "lawn",
        "care"
    ],
    "wof:name":"Ryan Lawn Care",
    "wof:placetype":"venue"
},
  "geometry": {"coordinates":[-91.38532499999999,39.710204],"type":"Point"}
}