{
  "type": "Feature",
  "properties": {
    "addr:full":"64 N Clark St Sullivan MO 63080",
    "addr:housenumber":"64",
    "addr:postcode":"63080",
    "addr:street":"N Clark St",
    "iso:country":"US",
    "sg:address":"64 N Clark St",
    "sg:city":"Sullivan",
    "sg:classifiers":[
        {
            "category":"Home & Garden",
            "subcategory":"Building Materials",
            "type":"Retail Goods"
        }
    ],
    "sg:phone":"+1 573 860 2400",
    "sg:postcode":"63080",
    "sg:province":"MO",
    "wof:name":"Windshields & More",
    "wof:placetype":"venue"
},
  "geometry": {"coordinates":[-91.160922,38.210642],"type":"Point"}
}