{
  "type": "Feature",
  "properties": {
    "iso:country":"US",
    "sg:address":"1907 S Business 54",
    "sg:city":"Eldon",
    "sg:classifiers":[
        {
            "category":"Food & Beverages",
            "subcategory":"Groceries & Convenience Stores",
            "type":"Retail Goods"
        }
    ],
    "sg:phone":"+1 573 392 2059",
    "sg:postcode":"65026",
    "sg:province":"MO",
    "wof:name":"Nolt's Country Market",
    "wof:placetype":"venue"
},
  "geometry": {"coordinates":[-92.586001,38.334751],"type":"Point"}
}