{
  "type": "Feature",
  "properties": {
    "iso:country":"US",
    "sg:address":"8201 NE 53 St",
    "sg:city":"Kansas City",
    "sg:classifiers":[
        {
            "category":"Wholesale",
            "subcategory":"Non-durable Goods",
            "type":"Manufacturing & Wholesale Goods"
        }
    ],
    "sg:phone":"+1 816 805 6725",
    "sg:postcode":"64119",
    "sg:province":"MO",
    "wof:name":"Burkhart Distributors",
    "wof:placetype":"venue"
},
  "geometry": {"coordinates":[-94.479782,39.189979],"type":"Point"}
}