{
  "type": "Feature",
  "properties": {
    "iso:country":"US",
    "sg:address":"9478 E State Hwy 76",
    "sg:city":"Kirbyville",
    "sg:classifiers":[
        {
            "category":"Home & Garden",
            "subcategory":"Building Materials",
            "type":"Retail Goods"
        }
    ],
    "sg:phone":"+1 417 546 4712",
    "sg:postcode":"65679",
    "sg:province":"MO",
    "sg:tags":[
        "lumber"
    ],
    "wof:name":"Starrett Lumber",
    "wof:placetype":"venue"
},
  "geometry": {"coordinates":[-93.101969,36.655467],"type":"Point"}
}