{
  "type": "Feature",
  "properties": {
    "iso:country":"US",
    "sg:address":"56539 Little Moniteau Rd",
    "sg:city":"California",
    "sg:classifiers":[
        {
            "category":"Building & Trades",
            "subcategory":"Construction",
            "type":"Services"
        }
    ],
    "sg:phone":"+1 573 796 5606",
    "sg:postcode":"65018",
    "sg:province":"MO",
    "sg:tags":[
        "contractor"
    ],
    "wof:name":"D & D Installers Inc",
    "wof:placetype":"venue"
},
  "geometry": {"coordinates":[-92.519074,38.649657],"type":"Point"}
}