{
  "type": "Feature",
  "properties": {
    "iso:country":"US",
    "sg:address":"915 N Grand Blvd",
    "sg:city":"Saint Louis",
    "sg:classifiers":[
        {
            "category":"Professional",
            "subcategory":"Research",
            "type":"Services"
        }
    ],
    "sg:phone":"+1 314 289 6333",
    "sg:postcode":"63103",
    "sg:province":"MO",
    "sg:tags":[
        "support",
        "education",
        "activity"
    ],
    "wof:name":"Vandeventer Pl Res Foundation",
    "wof:placetype":"venue"
},
  "geometry": {"coordinates":[-90.229617,38.641967],"type":"Point"}
}