{
  "type": "Feature",
  "properties": {
    "iso:country":"US",
    "sg:address":"6130 Southwest Ave",
    "sg:city":"St Louis",
    "sg:classifiers":[
        {
            "category":"Wholesale",
            "subcategory":"Hardware",
            "type":"Manufacturing & Wholesale Goods"
        },
        {
            "category":"Manufacturing",
            "subcategory":"Metals",
            "type":"Manufacturing & Wholesale Goods"
        }
    ],
    "sg:phone":"+1 314 644 5988",
    "sg:postcode":"63139",
    "sg:province":"MO",
    "sg:tags":[
        "valve",
        "mfg",
        "industrial",
        "trap",
        "steam"
    ],
    "wof:name":"Steam Management Systems Inc",
    "wof:placetype":"venue"
},
  "geometry": {"coordinates":[-90.29143500000001,38.611051],"type":"Point"}
}