{
  "type": "Feature",
  "properties": {
    "iso:country":"US",
    "sg:address":"2715 Lemay Ferry Rd",
    "sg:city":"Saint Louis",
    "sg:classifiers":[
        {
            "category":"Retail",
            "subcategory":"Auto Repair",
            "type":"Services"
        }
    ],
    "sg:phone":"+1 314 487 1300",
    "sg:postcode":"63125",
    "sg:province":"MO",
    "sg:tags":[
        "transmission"
    ],
    "wof:name":"Austins Transmission Inc",
    "wof:placetype":"venue"
},
  "geometry": {"coordinates":[-90.306797,38.519175],"type":"Point"}
}