{
  "type": "Feature",
  "properties": {
    "iso:country":"US",
    "sg:address":"6317 Martin Luther King Dr",
    "sg:city":"St Louis",
    "sg:classifiers":[
        {
            "category":"Professional",
            "type":"Services"
        }
    ],
    "sg:phone":"+1 314 389 7475",
    "sg:postcode":"63133",
    "sg:province":"MO",
    "sg:tags":[
        "establishment"
    ],
    "wof:name":"Wellston Community Support",
    "wof:placetype":"venue"
},
  "geometry": {"coordinates":[-90.289126,38.677368],"type":"Point"}
}