{
  "type": "Feature",
  "properties": {
    "iso:country":"US",
    "sg:address":"110 W 29th St",
    "sg:city":"Higginsville",
    "sg:classifiers":[
        {
            "category":"Building & Trades",
            "subcategory":"Electrical",
            "type":"Services"
        }
    ],
    "sg:phone":"+1 660 584 5088",
    "sg:postcode":"64037",
    "sg:province":"MO",
    "sg:tags":[
        "electric",
        "industrial",
        "contractors-commercial",
        "contractor"
    ],
    "wof:name":"Hulett Electric",
    "wof:placetype":"venue"
},
  "geometry": {"coordinates":[-93.716803,39.06623],"type":"Point"}
}