{
  "type": "Feature",
  "properties": {
    "iso:country":"US",
    "sg:address":"1701 E Broadway",
    "sg:city":"Columbia",
    "sg:classifiers":[
        {
            "category":"Health Services",
            "subcategory":"Doctor",
            "type":"Services"
        },
        {
            "category":"Health Services",
            "subcategory":"Hospital",
            "type":"Services"
        }
    ],
    "sg:phone":"+1 573 815 3870",
    "sg:postcode":"65201",
    "sg:province":"MO",
    "sg:tags":[
        "physician",
        "educational",
        "endocrinology",
        "support",
        "surgeons",
        "surgeon",
        "referral",
        "metabolism",
        "diabetes"
    ],
    "wof:name":"Diabetes Self Management Program",
    "wof:placetype":"venue"
},
  "geometry": {"coordinates":[-92.314362,38.950161],"type":"Point"}
}