{
  "type": "Feature",
  "properties": {
    "iso:country":"US",
    "sg:address":"1770 Sportsman Rd",
    "sg:city":"Boonville",
    "sg:classifiers":[
        {
            "category":"Building & Trades",
            "subcategory":"Landscaping Services",
            "type":"Services"
        }
    ],
    "sg:phone":"+1 660 882 6139",
    "sg:postcode":"65233",
    "sg:province":"MO",
    "wof:name":"Dirtworks Landscaping",
    "wof:placetype":"venue"
},
  "geometry": {"coordinates":[-92.77972,38.947628],"type":"Point"}
}