{
  "type": "Feature",
  "properties": {
    "iso:country":"US",
    "sg:address":"2588 N Westwood Blvd",
    "sg:city":"Poplar Bluff",
    "sg:classifiers":[
        {
            "category":"Health Services",
            "subcategory":"Doctor",
            "type":"Services"
        }
    ],
    "sg:phone":"+1 573 785 5909",
    "sg:postcode":"63901",
    "sg:province":"MO",
    "sg:tags":[
        "practice",
        "family"
    ],
    "wof:name":"Poplar Bluff Family Medicine",
    "wof:placetype":"venue"
},
  "geometry": {"coordinates":[-90.428887,36.785022],"type":"Point"}
}