{
  "type": "Feature",
  "properties": {
    "iso:country":"US",
    "sg:address":"953 W Liberty Dr",
    "sg:city":"Liberty",
    "sg:classifiers":[
        {
            "category":"Health Services",
            "subcategory":"Doctor",
            "type":"Services"
        }
    ],
    "sg:phone":"+1 816 415 4255",
    "sg:postcode":"64068",
    "sg:province":"MO",
    "sg:tags":[
        "physician",
        "surgeon"
    ],
    "wof:name":"Imaan Ali Iii Enterprises, Inc.",
    "wof:placetype":"venue"
},
  "geometry": {"coordinates":[-94.435737,39.2396],"type":"Point"}
}