{
  "type": "Feature",
  "properties": {
    "iso:country":"US",
    "sg:address":"1415 W 23rd St S",
    "sg:city":"Independence",
    "sg:classifiers":[
        {
            "category":"Restaurant",
            "type":"Food & Drink"
        }
    ],
    "sg:menulink":"http://www.allmenus.com/mo/blue/148946-subway/menu/",
    "sg:phone":"+1 816 254 6680",
    "sg:postcode":"64050",
    "sg:province":"MO",
    "sg:tags":[
        "american",
        "sandwich"
    ],
    "wof:name":"Subway",
    "wof:placetype":"venue"
},
  "geometry": {"coordinates":[-94.434623,39.079681],"type":"Point"}
}