{
  "type": "Feature",
  "properties": {
    "addr:full":"3800 NE 80th St Kansas City MO 64119",
    "addr:housenumber":"3800",
    "addr:postcode":"64119",
    "addr:street":"Ne 80Th St",
    "iso:country":"US",
    "sg:address":"3800 NE 80th St",
    "sg:city":"Kansas City",
    "sg:classifiers":[
        {
            "category":"Organizations",
            "subcategory":"Religious Organization",
            "type":"Services"
        }
    ],
    "sg:phone":"+1 816 436 2530",
    "sg:postcode":"64119",
    "sg:province":"MO",
    "sg:tags":[
        "church"
    ],
    "wof:name":"Seventh-Day Adventist Church",
    "wof:placetype":"venue"
},
  "geometry": {"coordinates":[-94.52924400000001,39.238473],"type":"Point"}
}