{
  "type": "Feature",
  "properties": {
    "iso:country":"US",
    "sg:address":"3001 Nicholson Ave",
    "sg:city":"Kansas City",
    "sg:classifiers":[
        {
            "category":"Wholesale",
            "subcategory":"Machinery & Supplies",
            "type":"Manufacturing & Wholesale Goods"
        }
    ],
    "sg:phone":"+1 816 483 5343",
    "sg:postcode":"64120",
    "sg:province":"MO",
    "sg:tags":[
        "gage"
    ],
    "sg:website":"www.ociinstruments.com",
    "wof:name":"OCI Instruments",
    "wof:placetype":"venue"
},
  "geometry": {"coordinates":[-94.54482899999999,39.124159],"type":"Point"}
}