{
  "type": "Feature",
  "properties": {
    "iso:country":"US",
    "sg:address":"17408 E 203rd St",
    "sg:city":"Pleasant Hill",
    "sg:classifiers":[
        {
            "category":"Building & Trades",
            "subcategory":"Construction",
            "type":"Services"
        }
    ],
    "sg:phone":"+1 816 779 4818",
    "sg:postcode":"64080",
    "sg:province":"MO",
    "sg:tags":[
        "house"
    ],
    "wof:name":"Charles Oquin",
    "wof:placetype":"venue"
},
  "geometry": {"coordinates":[-94.39291299999999,38.751487],"type":"Point"}
}