{
  "type": "Feature",
  "properties": {
    "iso:country":"US",
    "sg:address":"714 Mexico City Ave",
    "sg:city":"Kansas City",
    "sg:classifiers":[
        {
            "category":"Airport",
            "type":"Transportation"
        }
    ],
    "sg:phone":"+1 816 243 2460",
    "sg:postcode":"64153",
    "sg:province":"MO",
    "sg:tags":[
        "aircraft",
        "support",
        "ground"
    ],
    "wof:name":"Tug TECHNOLOGIES",
    "wof:placetype":"venue"
},
  "geometry": {"coordinates":[-94.718965,39.303402],"type":"Point"}
}