{
  "type": "Feature",
  "properties": {
    "iso:country":"US",
    "sg:address":"10000 Watson Rd",
    "sg:city":"Saint Louis",
    "sg:classifiers":[
        {
            "category":"Banks & Credit Unions",
            "subcategory":"Bank",
            "type":"Services"
        }
    ],
    "sg:phone":"+1 314 835 1195",
    "sg:postcode":"63126",
    "sg:province":"MO",
    "sg:tags":[
        "loan",
        "broker",
        "mortgage"
    ],
    "wof:name":"Alternative Mortgage Solutions",
    "wof:placetype":"venue"
},
  "geometry": {"coordinates":[-90.395079,38.556304],"type":"Point"}
}