{
  "type": "Feature",
  "properties": {
    "iso:country":"US",
    "sg:address":"522 N New Ballas Rd",
    "sg:city":"Creve Coeur",
    "sg:classifiers":[
        {
            "category":"Health Services",
            "subcategory":"Doctor",
            "type":"Services"
        }
    ],
    "sg:phone":"+1 314 567 5873",
    "sg:postcode":"63141",
    "sg:province":"MO",
    "sg:tags":[
        "physician",
        "medical",
        "surgeon"
    ],
    "wof:name":"Lester Reese MD",
    "wof:placetype":"venue"
},
  "geometry": {"coordinates":[-90.44324,38.665904],"type":"Point"}
}