{
  "type": "Feature",
  "properties": {
    "iso:country":"US",
    "sg:address":"200 NE Mulberry St",
    "sg:city":"Lees Summit",
    "sg:classifiers":[
        {
            "category":"Professional",
            "subcategory":"Management & Consulting",
            "type":"Services"
        }
    ],
    "sg:phone":"+1 816 508 2000",
    "sg:postcode":"64086",
    "sg:province":"MO",
    "wof:name":"Patriot Financial Group",
    "wof:placetype":"venue"
},
  "geometry": {"coordinates":[-94.37317299999999,38.941571],"type":"Point"}
}