{
  "type": "Feature",
  "properties": {
    "iso:country":"US",
    "sg:address":"1101 McGee St",
    "sg:city":"Kansas City",
    "sg:classifiers":[
        {
            "category":"Communications",
            "type":"Services"
        }
    ],
    "sg:phone":"+1 816 936 1076",
    "sg:postcode":"64106",
    "sg:province":"MO",
    "sg:tags":[
        "carrier"
    ],
    "wof:name":"Qwest Communications",
    "wof:placetype":"venue"
},
  "geometry": {"coordinates":[-94.57973699999999,39.09981],"type":"Point"}
}