{
  "type": "Feature",
  "properties": {
    "iso:country":"US",
    "sg:address":"1935 S Campbell Ave",
    "sg:city":"Springfield",
    "sg:classifiers":[
        {
            "category":"Cafe",
            "type":"Food & Drink"
        }
    ],
    "sg:menulink":"http://www.allmenus.com/mo/springfield/55005-hemingways-blue-water-cafe/menu/",
    "sg:phone":"+1 417 891 5100",
    "sg:postcode":"65807",
    "sg:province":"MO",
    "sg:tags":[
        "seafood",
        "american"
    ],
    "wof:name":"Hemingway's Blue Water Cafe",
    "wof:placetype":"venue"
},
  "geometry": {"coordinates":[-93.29510399999999,37.179447],"type":"Point"}
}