{
  "type": "Feature",
  "properties": {
    "iso:country":"US",
    "sg:address":"320 Kennett St",
    "sg:city":"Kennett",
    "sg:classifiers":[
        {
            "category":"Social Services",
            "subcategory":"Job Training",
            "type":"Services"
        }
    ],
    "sg:phone":"+1 573 888 1727",
    "sg:postcode":"63857",
    "sg:province":"MO",
    "sg:tags":[
        "workshop",
        "sheltered"
    ],
    "wof:name":"Dunklin Day Activity Center",
    "wof:placetype":"venue"
},
  "geometry": {"coordinates":[-90.055477,36.234107],"type":"Point"}
}