{
  "type": "Feature",
  "properties": {
    "iso:country":"US",
    "sg:address":"2560 Independence St",
    "sg:city":"Cape Girardeau",
    "sg:classifiers":[
        {
            "category":"Health Services",
            "subcategory":"Doctor",
            "type":"Services"
        }
    ],
    "sg:phone":"+1 573 334 0778",
    "sg:postcode":"63703",
    "sg:province":"MO",
    "sg:tags":[
        "medical"
    ],
    "wof:name":"Cape County Health",
    "wof:placetype":"venue"
},
  "geometry": {"coordinates":[-89.55813499999999,37.307535],"type":"Point"}
}