{
  "type": "Feature",
  "properties": {
    "iso:country":"US",
    "sg:address":"527 W 39 St",
    "sg:city":"Kansas City",
    "sg:classifiers":[
        {
            "category":"Banks & Credit Unions",
            "subcategory":"Bank",
            "type":"Services"
        }
    ],
    "sg:phone":"+1 816 861 2505",
    "sg:postcode":"64111",
    "sg:province":"MO",
    "sg:tags":[
        "mortgage"
    ],
    "wof:name":"A E G Mortgage",
    "wof:placetype":"venue"
},
  "geometry": {"coordinates":[-94.592748,39.056732],"type":"Point"}
}