{
  "type": "Feature",
  "properties": {
    "iso:country":"US",
    "sg:address":"18950 US Hwy 59",
    "sg:city":"Saint Joseph",
    "sg:classifiers":[
        {
            "category":"Recreation",
            "type":"Entertainment"
        }
    ],
    "sg:phone":"+1 816 232 7502",
    "sg:postcode":"64505",
    "sg:province":"MO",
    "sg:tags":[
        "dance"
    ],
    "wof:name":"Arising Gymnastics Center",
    "wof:placetype":"venue"
},
  "geometry": {"coordinates":[-94.81425299999999,39.851688],"type":"Point"}
}