{
  "type": "Feature",
  "properties": {
    "iso:country":"US",
    "sg:address":"12820 Gammon Rd",
    "sg:city":"Lees Summit",
    "sg:classifiers":[
        {
            "category":"Building & Trades",
            "subcategory":"Landscaping Services",
            "type":"Services"
        }
    ],
    "sg:phone":"+1 816 525 1157",
    "sg:postcode":"64086",
    "sg:province":"MO",
    "wof:name":"Countryside Lawn Service Inc",
    "wof:placetype":"venue"
},
  "geometry": {"coordinates":[-94.237747,38.8804],"type":"Point"}
}