{
  "type": "Feature",
  "properties": {
    "iso:country":"US",
    "sg:address":"221 W Lexington Ave",
    "sg:city":"Independence",
    "sg:classifiers":[
        {
            "category":"Place Of Worship",
            "subcategory":"Church",
            "type":"Public Place"
        },
        {
            "category":"Place Of Worship",
            "type":"Public Place"
        }
    ],
    "sg:phone":"+1 816 833 0640",
    "sg:postcode":"64050",
    "sg:province":"MO",
    "sg:tags":[
        "testament",
        "christ-new",
        "churches-church",
        "christ"
    ],
    "wof:name":"Church Of Christ With The Elijah Message",
    "wof:placetype":"venue"
},
  "geometry": {"coordinates":[-94.417337,39.092148],"type":"Point"}
}