{
  "type": "Feature",
  "properties": {
    "iso:country":"US",
    "sg:address":"7716 Forsyth Blvd",
    "sg:city":"St Louis",
    "sg:classifiers":[
        {
            "category":"Retail",
            "subcategory":"Laundry & Dry Cleaning",
            "type":"Services"
        },
        {
            "category":"Shopping",
            "subcategory":"Clothing, Apparel, & Fashions",
            "type":"Retail Goods"
        }
    ],
    "sg:phone":"+1 314 721 7043",
    "sg:postcode":"63105",
    "sg:province":"MO",
    "sg:tags":[
        "alteration"
    ],
    "wof:name":"Decker Tailoring",
    "wof:placetype":"venue"
},
  "geometry": {"coordinates":[-90.336507,38.650025],"type":"Point"}
}