{
  "type": "Feature",
  "properties": {
    "iso:country":"US",
    "sg:address":"14335 State Hwy Y",
    "sg:city":"Excelsior Spgs",
    "sg:classifiers":[
        {
            "category":"Autos & Motor Vehicles",
            "subcategory":"Automobile Sales",
            "type":"Retail Goods"
        }
    ],
    "sg:phone":"+1 816 630 0635",
    "sg:postcode":"64024",
    "sg:province":"MO",
    "sg:tags":[
        "used",
        "truck"
    ],
    "wof:name":"David's Used Cars",
    "wof:placetype":"venue"
},
  "geometry": {"coordinates":[-94.21109,39.347138],"type":"Point"}
}