{
  "type": "Feature",
  "properties": {
    "iso:country":"US",
    "sg:address":"12715 State Hwy M",
    "sg:city":"Ste Genevieve",
    "sg:classifiers":[
        {
            "category":"Professional",
            "type":"Services"
        }
    ],
    "sg:phone":"+1 573 883 9282",
    "sg:postcode":"63670",
    "sg:province":"MO",
    "sg:tags":[
        "establishment"
    ],
    "wof:name":"Ringwald Brothers",
    "wof:placetype":"venue"
},
  "geometry": {"coordinates":[-90.053248,37.937498],"type":"Point"}
}