{
  "type": "Feature",
  "properties": {
    "iso:country":"US",
    "sg:address":"224 E 1st St",
    "sg:city":"Hermann",
    "sg:classifiers":[
        {
            "category":"Personal",
            "subcategory":"Beauty Salon",
            "type":"Services"
        }
    ],
    "sg:phone":"+1 573 486 3797",
    "sg:postcode":"65041",
    "sg:province":"MO",
    "sg:tags":[
        "shop"
    ],
    "wof:name":"Impressions Salon & Tanning",
    "wof:placetype":"venue"
},
  "geometry": {"coordinates":[-91.434729,38.706757],"type":"Point"}
}