{
  "type": "Feature",
  "properties": {
    "iso:country":"US",
    "sg:address":"236 E Emma St",
    "sg:city":"Slater",
    "sg:classifiers":[
        {
            "category":"Building & Trades",
            "subcategory":"Construction",
            "type":"Services"
        }
    ],
    "sg:phone":"+1 660 529 3122",
    "sg:postcode":"65349",
    "sg:province":"MO",
    "sg:tags":[
        "hanging",
        "contractor"
    ],
    "wof:name":"Mitch Hager Painting",
    "wof:placetype":"venue"
},
  "geometry": {"coordinates":[-93.05945199999999,39.221976],"type":"Point"}
}