{
  "type": "Feature",
  "properties": {
    "iso:country":"US",
    "sg:address":"507 E Nifong Blvd",
    "sg:city":"Columbia",
    "sg:classifiers":[
        {
            "category":"Social Services",
            "type":"Services"
        },
        {
            "category":"Shopping",
            "subcategory":"Used Merchandise",
            "type":"Retail Goods"
        },
        {
            "category":"Banks & Credit Unions",
            "subcategory":"Bank",
            "type":"Services"
        },
        {
            "category":"Shopping",
            "subcategory":"Thrift Store",
            "type":"Retail Goods"
        },
        {
            "category":"Organizations",
            "subcategory":"Non-profit Organization",
            "type":"Services"
        }
    ],
    "sg:phone":"+1 573 442 8527",
    "sg:postcode":"65201",
    "sg:province":"MO",
    "sg:tags":[
        "shop",
        "foundations-educational",
        "philanthropic",
        "research",
        "resale",
        "second",
        "hand",
        "furniture",
        "charity"
    ],
    "sg:website":"http://www.goodwill.org",
    "wof:name":"Goodwill Stores",
    "wof:placetype":"venue"
},
  "geometry": {"coordinates":[-92.334109,38.910194],"type":"Point"}
}