{
  "type": "Feature",
  "properties": {
    "iso:country":"US",
    "sg:address":"816 Wagon Knob Rd",
    "sg:city":"Odessa",
    "sg:classifiers":[
        {
            "category":"Real Estate",
            "subcategory":"Real Estate Services",
            "type":"Services"
        },
        {
            "category":"Real Estate",
            "subcategory":"Real Estate Agent",
            "type":"Services"
        }
    ],
    "sg:phone":"+1 816 230 4699",
    "sg:postcode":"64076",
    "sg:province":"MO",
    "sg:tags":[
        "buyer",
        "broker"
    ],
    "wof:name":"Business Realty Inc",
    "wof:placetype":"venue"
},
  "geometry": {"coordinates":[-93.970361,38.922684],"type":"Point"}
}