{
  "type": "Feature",
  "properties": {
    "iso:country":"US",
    "sg:address":"28702 Highway A",
    "sg:city":"Fairview",
    "sg:classifiers":[
        {
            "category":"Farming",
            "subcategory":"Farm",
            "type":"Manufacturing & Wholesale Goods"
        }
    ],
    "sg:phone":"+1 417 652 7177",
    "sg:postcode":"64842",
    "sg:province":"MO",
    "wof:name":"Evans Farms",
    "wof:placetype":"venue"
},
  "geometry": {"coordinates":[-94.13817400000001,36.764357],"type":"Point"}
}