{
  "type": "Feature",
  "properties": {
    "iso:country":"US",
    "sg:address":"1133 E State Highway 76",
    "sg:city":"Branson",
    "sg:classifiers":[
        {
            "category":"Personal",
            "subcategory":"Beauty Salon",
            "type":"Services"
        }
    ],
    "sg:phone":"+1 417 334 2184",
    "sg:postcode":"65616",
    "sg:province":"MO",
    "wof:name":"Gary's Coiffures",
    "wof:placetype":"venue"
},
  "geometry": {"coordinates":[-93.28476000000001,36.638245],"type":"Point"}
}