{
  "type": "Feature",
  "properties": {
    "iso:country":"US",
    "sg:address":"4910 E River Walk Ln",
    "sg:city":"Springfield",
    "sg:classifiers":[
        {
            "category":"Real Estate",
            "subcategory":"Real Estate Agent",
            "type":"Services"
        }
    ],
    "sg:phone":"+1 417 883 3000",
    "sg:postcode":"65809",
    "sg:province":"MO",
    "sg:website":"www.jhopkins.com",
    "wof:name":"J Hopkins & Assoc Inc",
    "wof:placetype":"venue"
},
  "geometry": {"coordinates":[-93.192278,37.167377],"type":"Point"}
}