{
  "type": "Feature",
  "properties": {
    "iso:country":"US",
    "sg:address":"13124 US Hwy 71",
    "sg:city":"Grandview",
    "sg:classifiers":[
        {
            "category":"Professional",
            "subcategory":"Business Services",
            "type":"Services"
        }
    ],
    "sg:phone":"+1 816 761 2083",
    "sg:postcode":"64030",
    "sg:province":"MO",
    "sg:tags":[
        "personal"
    ],
    "wof:name":"Cowboys Tattoo",
    "wof:placetype":"venue"
},
  "geometry": {"coordinates":[-94.525728,38.883593],"type":"Point"}
}