{
  "type": "Feature",
  "properties": {
    "iso:country":"US",
    "sg:address":"210 W Stoddard St",
    "sg:city":"Dexter",
    "sg:classifiers":[
        {
            "category":"Personal",
            "subcategory":"Tanning Parlor",
            "type":"Services"
        }
    ],
    "sg:phone":"+1 573 624 6668",
    "sg:postcode":"63841",
    "sg:province":"MO",
    "sg:tags":[
        "salon"
    ],
    "wof:name":"Always Tan",
    "wof:placetype":"venue"
},
  "geometry": {"coordinates":[-89.962047,36.793301],"type":"Point"}
}