{
  "type": "Feature",
  "properties": {
    "iso:country":"US",
    "sg:address":"2901 University Meadows Dr",
    "sg:city":"Saint Louis",
    "sg:classifiers":[
        {
            "category":"Banks & Credit Unions",
            "subcategory":"Financial Services",
            "type":"Services"
        }
    ],
    "sg:phone":"+1 314 383 8553",
    "sg:postcode":"63121",
    "sg:province":"MO",
    "sg:tags":[
        "real",
        "business",
        "f",
        "company",
        "operating",
        "property",
        "buying"
    ],
    "wof:name":"S J Holding Corp",
    "wof:placetype":"venue"
},
  "geometry": {"coordinates":[-90.308758,38.703658],"type":"Point"}
}