{
  "type": "Feature",
  "properties": {
    "iso:country":"US",
    "sg:address":"1500 S Outer Rd E",
    "sg:city":"Eureka",
    "sg:classifiers":[
        {
            "category":"Retail",
            "subcategory":"Storage",
            "type":"Services"
        }
    ],
    "sg:phone":"+1 636 938 4970",
    "sg:postcode":"63025",
    "sg:province":"MO",
    "sg:tags":[
        "recreational",
        "boat",
        "campers-storage",
        "vehicle"
    ],
    "sg:website":"http://www.lighthousestoragestl.com",
    "wof:name":"Lighthouse Storage",
    "wof:placetype":"venue"
},
  "geometry": {"coordinates":[-90.608525,38.503319],"type":"Point"}
}