{
  "type": "Feature",
  "properties": {
    "iso:country":"US",
    "sg:address":"2700 Rochester St",
    "sg:city":"Kansas City",
    "sg:classifiers":[
        {
            "category":"Retail",
            "subcategory":"Auto Repair",
            "type":"Services"
        }
    ],
    "sg:phone":"+1 816 483 6300",
    "sg:postcode":"64120",
    "sg:province":"MO",
    "sg:tags":[
        "recreational",
        "vehicle"
    ],
    "sg:website":"www.fogcycle.com",
    "wof:name":"Mid-City Collision Repair Inc",
    "wof:placetype":"venue"
},
  "geometry": {"coordinates":[-94.548287,39.120644],"type":"Point"}
}