{
  "type": "Feature",
  "properties": {
    "iso:country":"US",
    "sg:address":"2320 Schuetz Rd",
    "sg:city":"St Louis",
    "sg:classifiers":[
        {
            "category":"Health Services",
            "subcategory":"Doctor",
            "type":"Services"
        }
    ],
    "sg:phone":"+1 314 991 4363",
    "sg:postcode":"63146",
    "sg:province":"MO",
    "sg:tags":[
        "physician",
        "surgeon"
    ],
    "wof:name":"Wcp Laboratories",
    "wof:placetype":"venue"
},
  "geometry": {"coordinates":[-90.431901,38.704529],"type":"Point"}
}