{
  "type": "Feature",
  "properties": {
    "iso:country":"US",
    "sg:address":"6649 Romiss Ct",
    "sg:city":"St Louis",
    "sg:classifiers":[
        {
            "category":"Building & Trades",
            "subcategory":"Construction",
            "type":"Services"
        }
    ],
    "sg:phone":"+1 314 524 6111",
    "sg:postcode":"63134",
    "sg:province":"MO",
    "sg:tags":[
        "general",
        "special",
        "contractor"
    ],
    "wof:name":"B & P Construction Inc",
    "wof:placetype":"venue"
},
  "geometry": {"coordinates":[-90.34184,38.762282],"type":"Point"}
}