{
  "type": "Feature",
  "properties": {
    "iso:country":"US",
    "sg:address":"525 Hawkins Rd",
    "sg:city":"Fenton",
    "sg:classifiers":[
        {
            "category":"Building & Trades",
            "subcategory":"Construction",
            "type":"Services"
        }
    ],
    "sg:phone":"+1 636 343 8530",
    "sg:postcode":"63026",
    "sg:province":"MO",
    "sg:tags":[
        "repair",
        "handyman",
        "maintenance",
        "home"
    ],
    "wof:name":"David Bufka Handyman",
    "wof:placetype":"venue"
},
  "geometry": {"coordinates":[-90.469946,38.500092],"type":"Point"}
}