{
  "type": "Feature",
  "properties": {
    "iso:country":"US",
    "sg:address":"6165 S Hwy 94",
    "sg:city":"Augusta",
    "sg:classifiers":[
        {
            "category":"Real Estate",
            "subcategory":"Surveying",
            "type":"Services"
        }
    ],
    "sg:phone":"+1 636 228 4902",
    "sg:postcode":"63332",
    "sg:province":"MO",
    "sg:tags":[
        "engineering"
    ],
    "wof:name":"Ditch Engineering Inc",
    "wof:placetype":"venue"
},
  "geometry": {"coordinates":[-90.91574,38.58892],"type":"Point"}
}