{
  "type": "Feature",
  "properties": {
    "iso:country":"US",
    "sg:address":"321 E Truman St",
    "sg:city":"Marceline",
    "sg:classifiers":[
        {
            "category":"Personal",
            "subcategory":"Beauty Salon",
            "type":"Services"
        }
    ],
    "sg:phone":"+1 660 376 2197",
    "sg:postcode":"64658",
    "sg:province":"MO",
    "wof:name":"Joy S Beauty Shop",
    "wof:placetype":"venue"
},
  "geometry": {"coordinates":[-92.942977,39.717796],"type":"Point"}
}