{
  "type": "Feature",
  "properties": {
    "iso:country":"US",
    "sg:address":"680 Craig Rd",
    "sg:city":"Saint Louis",
    "sg:classifiers":[
        {
            "category":"Professional",
            "subcategory":"Computer Services",
            "type":"Services"
        }
    ],
    "sg:phone":"+1 314 567 6737",
    "sg:postcode":"63146",
    "sg:province":"MO",
    "sg:tags":[
        "datum",
        "related"
    ],
    "wof:name":"SEI",
    "wof:placetype":"venue"
},
  "geometry": {"coordinates":[-90.43674900000001,38.668884],"type":"Point"}
}