{
  "type": "Feature",
  "properties": {
    "iso:country":"US",
    "sg:address":"12467 Matthews Ln",
    "sg:city":"Saint Louis",
    "sg:classifiers":[
        {
            "category":"Professional",
            "subcategory":"Management & Consulting",
            "type":"Services"
        }
    ],
    "sg:phone":"+1 314 842 3943",
    "sg:postcode":"63127",
    "sg:province":"MO",
    "wof:name":"Diehlhart",
    "wof:placetype":"venue"
},
  "geometry": {"coordinates":[-90.402148,38.542947],"type":"Point"}
}