{
  "type": "Feature",
  "properties": {
    "iso:country":"US",
    "sg:address":"1108 Olive St Ste 200",
    "sg:city":"Saint Louis",
    "sg:classifiers":[
        {
            "category":"Professional",
            "subcategory":"Lawyer & Legal Services",
            "type":"Services"
        }
    ],
    "sg:phone":"+1 314 721 1100",
    "sg:postcode":"63101",
    "sg:province":"MO",
    "wof:name":"Henshaw Molly Atty",
    "wof:placetype":"venue"
},
  "geometry": {"coordinates":[-90.195823,38.629266],"type":"Point"}
}