{
  "type": "Feature",
  "properties": {
    "iso:country":"US",
    "sg:address":"123 N Ranney St",
    "sg:city":"Sikeston",
    "sg:classifiers":[
        {
            "category":"Manufacturing",
            "subcategory":"Chemicals & Compounds",
            "type":"Manufacturing & Wholesale Goods"
        },
        {
            "category":"Professional",
            "subcategory":"Business Services",
            "type":"Services"
        },
        {
            "category":"Building & Trades",
            "subcategory":"Pest Control",
            "type":"Services"
        }
    ],
    "sg:phone":"+1 573 475 4655",
    "sg:postcode":"63801",
    "sg:province":"MO",
    "sg:tags":[
        "industrial",
        "supply",
        "services-commercial",
        "termite",
        "bee",
        "equipment",
        "repellent",
        "mothproofing",
        "barriers",
        "removal",
        "inspection",
        "bird"
    ],
    "wof:name":"Terminix",
    "wof:placetype":"venue"
},
  "geometry": {"coordinates":[-89.586185,36.877625],"type":"Point"}
}