{
  "type": "Feature",
  "properties": {
    "iso:country":"US",
    "sg:address":"4134 Crescent Dr",
    "sg:city":"Saint Louis",
    "sg:classifiers":[
        {
            "category":"Wholesale",
            "subcategory":"Electrical",
            "type":"Manufacturing & Wholesale Goods"
        }
    ],
    "sg:phone":"+1 314 892 4646",
    "sg:postcode":"63129",
    "sg:province":"MO",
    "sg:tags":[
        "outdoor",
        "for",
        "mfg",
        "pro",
        "lighting",
        "representative"
    ],
    "wof:name":"Peiker & Piatchek Associates",
    "wof:placetype":"venue"
},
  "geometry": {"coordinates":[-90.33490999999999,38.508297],"type":"Point"}
}