{
  "type": "Feature",
  "properties": {
    "iso:country":"US",
    "sg:address":"909 E Karsch Blvd",
    "sg:city":"Farmington",
    "sg:classifiers":[
        {
            "category":"Shopping",
            "type":"Retail Goods"
        }
    ],
    "sg:phone":"+1 573 756 4121",
    "sg:postcode":"63640",
    "sg:province":"MO",
    "sg:tags":[
        "farm",
        "equipment"
    ],
    "wof:name":"Farm Equipment Sales Inc",
    "wof:placetype":"venue"
},
  "geometry": {"coordinates":[-90.407921,37.782898],"type":"Point"}
}