{
  "type": "Feature",
  "properties": {
    "iso:country":"US",
    "sg:address":"5 W 57 Ter",
    "sg:city":"Kansas City",
    "sg:classifiers":[
        {
            "category":"Building & Trades",
            "subcategory":"Construction",
            "type":"Services"
        }
    ],
    "sg:phone":"+1 913 488 5062",
    "sg:postcode":"64113",
    "sg:province":"MO",
    "sg:tags":[
        "floor",
        "laying",
        "contractor"
    ],
    "wof:name":"Griffard Hardwoods",
    "wof:placetype":"venue"
},
  "geometry": {"coordinates":[-94.59023000000001,39.023222],"type":"Point"}
}