{
  "type": "Feature",
  "properties": {
    "iso:country":"US",
    "sg:address":"1031 SE 3 Ter",
    "sg:city":"Lees Summit",
    "sg:classifiers":[
        {
            "category":"Professional",
            "subcategory":"Detective & Security Services",
            "type":"Services"
        }
    ],
    "sg:phone":"+1 816 246 0945",
    "sg:postcode":"64063",
    "sg:province":"MO",
    "sg:tags":[
        "guard",
        "patrol"
    ],
    "wof:name":"K-9 School Security Svc",
    "wof:placetype":"venue"
},
  "geometry": {"coordinates":[-94.355422,38.913203],"type":"Point"}
}