{
  "type": "Feature",
  "properties": {
    "iso:country":"US",
    "sg:address":"1460 78th St",
    "sg:city":"Saint Louis",
    "sg:classifiers":[
        {
            "category":"Arts & Performance",
            "subcategory":"Theater",
            "type":"Entertainment"
        }
    ],
    "sg:phone":"+1 314 863 3286",
    "sg:postcode":"63130",
    "sg:province":"MO",
    "sg:tags":[
        "group"
    ],
    "wof:name":"Street Nasty Entertainment",
    "wof:placetype":"venue"
},
  "geometry": {"coordinates":[-90.33759000000001,38.678306],"type":"Point"}
}