{
  "type": "Feature",
  "properties": {
    "addr:full":"1616 State Hwy 7 Blue Springs MO 64014",
    "addr:housenumber":"1616",
    "addr:postcode":"64014",
    "addr:street":"State Hwy 7",
    "iso:country":"US",
    "sg:address":"1616 State Hwy 7",
    "sg:city":"Blue Springs",
    "sg:classifiers":[
        {
            "category":"Shopping",
            "subcategory":"Pharmacy",
            "type":"Retail Goods"
        }
    ],
    "sg:phone":"+1 816 228 1994",
    "sg:postcode":"64014",
    "sg:province":"MO",
    "wof:name":"Osco Drug",
    "wof:placetype":"venue"
},
  "geometry": {"coordinates":[-94.27310799999999,38.999354],"type":"Point"}
}