{
  "type": "Feature",
  "properties": {
    "iso:country":"US",
    "sg:address":"95 Weatherby Dr",
    "sg:city":"Wright City",
    "sg:classifiers":[
        {
            "category":"Manufacturing",
            "subcategory":"Building Materials",
            "type":"Manufacturing & Wholesale Goods"
        }
    ],
    "sg:phone":"+1 636 745 9154",
    "sg:postcode":"63390",
    "sg:province":"MO",
    "sg:tags":[
        "mfg"
    ],
    "wof:name":"JMJ Building Supply",
    "wof:placetype":"venue"
},
  "geometry": {"coordinates":[-91.03948,38.835235],"type":"Point"}
}