{
  "type": "Feature",
  "properties": {
    "iso:country":"US",
    "sg:address":"539 NE Noeleen Ln",
    "sg:city":"Lees Summit",
    "sg:classifiers":[
        {
            "category":"Retail",
            "subcategory":"Animal Services",
            "type":"Services"
        }
    ],
    "sg:phone":"+1 816 525 1421",
    "sg:postcode":"64086",
    "sg:province":"MO",
    "wof:name":"Mountainalre Farms",
    "wof:placetype":"venue"
},
  "geometry": {"coordinates":[-94.35234199999999,38.922936],"type":"Point"}
}