{
  "type": "Feature",
  "properties": {
    "iso:country":"US",
    "sg:address":"712 Jefferson St",
    "sg:city":"Jefferson City",
    "sg:classifiers":[
        {
            "category":"Banks & Credit Unions",
            "subcategory":"Bank",
            "type":"Services"
        }
    ],
    "sg:phone":"+1 573 636 6767",
    "sg:postcode":"65101",
    "sg:province":"MO",
    "sg:tags":[
        "loan",
        "real estate"
    ],
    "wof:name":"Central Missouri Mortgage",
    "wof:placetype":"venue"
},
  "geometry": {"coordinates":[-92.177322,38.572881],"type":"Point"}
}