{
  "type": "Feature",
  "properties": {
    "iso:country":"US",
    "sg:address":"320 N Jefferson Ave",
    "sg:city":"Springfield",
    "sg:classifiers":[
        {
            "category":"Social Services",
            "type":"Services"
        }
    ],
    "sg:phone":"+1 417 863 7700",
    "sg:postcode":"65806",
    "sg:province":"MO",
    "sg:tags":[
        "organization",
        "welfare"
    ],
    "sg:website":"www.uwozarks.com",
    "wof:name":"United Way",
    "wof:placetype":"venue"
},
  "geometry": {"coordinates":[-93.289697,37.21052],"type":"Point"}
}