{
  "type": "Feature",
  "properties": {
    "iso:country":"US",
    "sg:address":"145 US Hwy 24",
    "sg:city":"Independence",
    "sg:classifiers":[
        {
            "category":"Autos & Motor Vehicles",
            "subcategory":"Automobile Sales",
            "type":"Retail Goods"
        }
    ],
    "sg:phone":"+1 816 254 9887",
    "sg:postcode":"64050",
    "sg:province":"MO",
    "sg:tags":[
        "car",
        "used",
        "dealer"
    ],
    "wof:name":"A & A Auto Sales",
    "wof:placetype":"venue"
},
  "geometry": {"coordinates":[-94.414906,39.101289],"type":"Point"}
}