{
  "type": "Feature",
  "properties": {
    "iso:country":"US",
    "sg:address":"2440 S Brentwood Blvd",
    "sg:city":"St Louis",
    "sg:classifiers":[
        {
            "category":"Health Services",
            "subcategory":"Doctor",
            "type":"Services"
        }
    ],
    "sg:phone":"+1 314 962 6643",
    "sg:postcode":"63144",
    "sg:province":"MO",
    "sg:tags":[
        "dentist"
    ],
    "wof:name":"Dann Dental Associates Inc",
    "wof:placetype":"venue"
},
  "geometry": {"coordinates":[-90.34893,38.614159],"type":"Point"}
}