{
  "type": "Feature",
  "properties": {
    "iso:country":"US",
    "sg:address":"3935 N Bales Ave",
    "sg:city":"Kansas City",
    "sg:classifiers":[
        {
            "category":"Professional",
            "subcategory":"Detective & Security Services",
            "type":"Services"
        }
    ],
    "sg:phone":"+1 816 455 4949",
    "sg:postcode":"64117",
    "sg:province":"MO",
    "sg:tags":[
        "system"
    ],
    "wof:name":"Alarm Service Co",
    "wof:placetype":"venue"
},
  "geometry": {"coordinates":[-94.539008,39.16602],"type":"Point"}
}