{
  "type": "Feature",
  "properties": {
    "iso:country":"US",
    "sg:address":"10430 Page Ave",
    "sg:city":"Saint Louis",
    "sg:classifiers":[
        {
            "category":"Health Services",
            "subcategory":"Podiatrist",
            "type":"Services"
        }
    ],
    "sg:phone":"+1 314 423 8811",
    "sg:postcode":"63132",
    "sg:province":"MO",
    "wof:name":"John J Holtzman",
    "wof:placetype":"venue"
},
  "geometry": {"coordinates":[-90.391925,38.691673],"type":"Point"}
}