{
  "type": "Feature",
  "properties": {
    "iso:country":"US",
    "sg:address":"1600 Genessee St",
    "sg:city":"Kansas City",
    "sg:classifiers":[
        {
            "category":"Freight",
            "type":"Transportation"
        }
    ],
    "sg:phone":"+1 816 221 7354",
    "sg:postcode":"64102",
    "sg:province":"MO",
    "wof:name":"Fritz Companies",
    "wof:placetype":"venue"
},
  "geometry": {"coordinates":[-94.605063,39.093409],"type":"Point"}
}