{
  "type": "Feature",
  "properties": {
    "iso:country":"US",
    "sg:address":"435 Westport Rd",
    "sg:city":"Kansas City",
    "sg:classifiers":[
        {
            "category":"Organizations",
            "subcategory":"Non-profit Organization",
            "type":"Services"
        }
    ],
    "sg:phone":"+1 816 561 1061",
    "sg:postcode":"64111",
    "sg:province":"MO",
    "sg:website":"www.bridgingthegap.org",
    "wof:name":"Keep Kansas City Beautiful",
    "wof:placetype":"venue"
},
  "geometry": {"coordinates":[-94.591172,39.052944],"type":"Point"}
}