{
  "type": "Feature",
  "properties": {
    "addr:full":"301 Main St Monett MO 65708",
    "addr:housenumber":"301",
    "addr:postcode":"65708",
    "addr:street":"Main St",
    "iso:country":"US",
    "sg:address":"301 Main St",
    "sg:city":"Monett",
    "sg:classifiers":[
        {
            "category":"Banks & Credit Unions",
            "subcategory":"Investment Brokerage",
            "type":"Services"
        }
    ],
    "sg:phone":"+1 417 236 9981",
    "sg:postcode":"65708",
    "sg:province":"MO",
    "sg:tags":[
        "advisory",
        "financial"
    ],
    "wof:name":"Thrivent Financial-Lutherans",
    "wof:placetype":"venue"
},
  "geometry": {"coordinates":[-93.93116999999999,36.918167],"type":"Point"}
}