{
  "type": "Feature",
  "properties": {
    "iso:country":"US",
    "sg:address":"13 Green Meadows Dr",
    "sg:city":"Doniphan",
    "sg:classifiers":[
        {
            "category":"Building & Trades",
            "subcategory":"Construction",
            "type":"Services"
        }
    ],
    "sg:phone":"+1 573 996 9709",
    "sg:postcode":"63935",
    "sg:province":"MO",
    "sg:tags":[
        "system",
        "specialty",
        "heating",
        "contractor",
        "air conditioning"
    ],
    "wof:name":"Bc Affordable Energy Systems",
    "wof:placetype":"venue"
},
  "geometry": {"coordinates":[-90.820406,36.627887],"type":"Point"}
}