{
  "type": "Feature",
  "properties": {
    "iso:country":"US",
    "sg:address":"1206 W 39 St",
    "sg:city":"Kansas City",
    "sg:classifiers":[
        {
            "category":"Professional",
            "subcategory":"Lawyer & Legal Services",
            "type":"Services"
        }
    ],
    "sg:phone":"+1 816 753 5556",
    "sg:postcode":"64111",
    "sg:province":"MO",
    "sg:tags":[
        "attorney"
    ],
    "wof:name":"Corley Law Firm",
    "wof:placetype":"venue"
},
  "geometry": {"coordinates":[-94.601378,39.057203],"type":"Point"}
}