{
  "type": "Feature",
  "properties": {
    "iso:country":"US",
    "sg:address":"450 Main St",
    "sg:city":"New Madrid",
    "sg:classifiers":[
        {
            "category":"Government",
            "subcategory":"Office",
            "type":"Public Place"
        }
    ],
    "sg:phone":"+1 573 748 2228",
    "sg:postcode":"63869",
    "sg:province":"MO",
    "wof:name":"New Madrid Circuit Clerk",
    "wof:placetype":"venue"
},
  "geometry": {"coordinates":[-89.52717,36.5878],"type":"Point"}
}