{
  "type": "Feature",
  "properties": {
    "iso:country":"US",
    "sg:address":"4228 Windsor Ave",
    "sg:city":"Kansas City",
    "sg:classifiers":[
        {
            "category":"Wholesale",
            "subcategory":"Machinery & Supplies",
            "type":"Manufacturing & Wholesale Goods"
        }
    ],
    "sg:phone":"+1 816 231 0660",
    "sg:postcode":"64123",
    "sg:province":"MO",
    "sg:tags":[
        "equipment",
        "printing"
    ],
    "wof:name":"Smith Printers Service Co",
    "wof:placetype":"venue"
},
  "geometry": {"coordinates":[-94.530507,39.113965],"type":"Point"}
}