{
  "type": "Feature",
  "properties": {
    "iso:country":"US",
    "sg:address":"1816 Walnut St",
    "sg:city":"Kansas City",
    "sg:classifiers":[
        {
            "category":"Manufacturing",
            "subcategory":"Printing",
            "type":"Manufacturing & Wholesale Goods"
        }
    ],
    "sg:phone":"+1 816 421 0013",
    "sg:postcode":"64108",
    "sg:province":"MO",
    "sg:tags":[
        "typesetting"
    ],
    "wof:name":"Echo Graphics",
    "wof:placetype":"venue"
},
  "geometry": {"coordinates":[-94.582596,39.091162],"type":"Point"}
}