{
  "type": "Feature",
  "properties": {
    "iso:country":"US",
    "sg:address":"103 N Church St",
    "sg:city":"Union",
    "sg:classifiers":[
        {
            "category":"Retail",
            "subcategory":"Funeral Services",
            "type":"Services"
        }
    ],
    "sg:phone":"+1 636 583 2525",
    "sg:postcode":"63084",
    "sg:province":"MO",
    "sg:tags":[
        "director"
    ],
    "wof:name":"Oltmann Funeral Homes Inc",
    "wof:placetype":"venue"
},
  "geometry": {"coordinates":[-91.00564199999999,38.447141],"type":"Point"}
}