{
  "type": "Feature",
  "properties": {
    "iso:country":"US",
    "sg:address":"5005 NW Nantucket Dr",
    "sg:city":"Blue Springs",
    "sg:classifiers":[
        {
            "category":"Freight",
            "type":"Transportation"
        }
    ],
    "sg:phone":"+1 816 365 7245",
    "sg:postcode":"64015",
    "sg:province":"MO",
    "sg:tags":[
        "operator",
        "local",
        "trucking"
    ],
    "wof:name":"Precision Piano Moving",
    "wof:placetype":"venue"
},
  "geometry": {"coordinates":[-94.320015,39.035193],"type":"Point"}
}