{
  "type": "Feature",
  "properties": {
    "iso:country":"US",
    "sg:address":"8025 Cler Ave",
    "sg:city":"Overland",
    "sg:classifiers":[
        {
            "category":"Building & Trades",
            "subcategory":"Landscaping Services",
            "type":"Services"
        }
    ],
    "sg:phone":"+1 314 427 1812",
    "sg:postcode":"63114",
    "sg:province":"MO",
    "sg:tags":[
        "spraying",
        "surgery",
        "tree",
        "pruning"
    ],
    "wof:name":"Petrov Brothers Tree Service",
    "wof:placetype":"venue"
},
  "geometry": {"coordinates":[-90.329189,38.705407],"type":"Point"}
}