{
  "type": "Feature",
  "properties": {
    "iso:country":"US",
    "sg:address":"3706 W 76 Country Blvd",
    "sg:city":"Branson",
    "sg:classifiers":[
        {
            "category":"Personal",
            "subcategory":"Beauty Salon",
            "type":"Services"
        }
    ],
    "sg:phone":"+1 417 334 6759",
    "sg:postcode":"65616",
    "sg:province":"MO",
    "wof:name":"French Quarters",
    "wof:placetype":"venue"
},
  "geometry": {"coordinates":[-93.28830000000001,36.647062],"type":"Point"}
}