{
  "type": "Feature",
  "properties": {
    "iso:country":"US",
    "sg:address":"2511 S Jefferson Ave",
    "sg:city":"Saint Louis",
    "sg:classifiers":[
        {
            "category":"Autos & Motor Vehicles",
            "subcategory":"Auto Supplies",
            "type":"Retail Goods"
        },
        {
            "category":"Retail",
            "subcategory":"Auto Repair",
            "type":"Services"
        }
    ],
    "sg:phone":"+1 314 773 0781",
    "sg:postcode":"63104",
    "sg:province":"MO",
    "sg:tags":[
        "tire"
    ],
    "sg:website":"www.itdroll.com",
    "wof:name":"Jefferson-Gravois Tire Co Inc",
    "wof:placetype":"venue"
},
  "geometry": {"coordinates":[-90.222702,38.605999],"type":"Point"}
}