{
  "type": "Feature",
  "properties": {
    "iso:country":"US",
    "sg:address":"4528 Main St",
    "sg:city":"Kansas City",
    "sg:classifiers":[
        {
            "category":"Social Services",
            "type":"Services"
        }
    ],
    "sg:phone":"+1 816 531 1230",
    "sg:postcode":"64111",
    "sg:province":"MO",
    "wof:name":"Abloff & Sanders MD",
    "wof:placetype":"venue"
},
  "geometry": {"coordinates":[-94.586868,39.044602],"type":"Point"}
}