{
  "type": "Feature",
  "properties": {
    "iso:country":"US",
    "sg:address":"1620 N Jefferson Ave",
    "sg:city":"St Louis",
    "sg:classifiers":[
        {
            "category":"Manufacturing",
            "subcategory":"Paper Products",
            "type":"Manufacturing & Wholesale Goods"
        }
    ],
    "sg:phone":"+1 314 241 0990",
    "sg:postcode":"63106",
    "sg:province":"MO",
    "sg:tags":[
        "box"
    ],
    "wof:name":"St Louis Carton Co",
    "wof:placetype":"venue"
},
  "geometry": {"coordinates":[-90.212818,38.646371],"type":"Point"}
}