{
  "type": "Feature",
  "properties": {
    "iso:country":"US",
    "sg:address":"1136 Columbus Cir",
    "sg:city":"Warrenton",
    "sg:classifiers":[
        {
            "category":"Travel",
            "subcategory":"Travel Agent",
            "type":"Entertainment"
        }
    ],
    "sg:phone":"+1 636 456 1270",
    "sg:postcode":"63383",
    "sg:province":"MO",
    "sg:tags":[
        "agency",
        "services-commercial"
    ],
    "wof:name":"Siesta Travel",
    "wof:placetype":"venue"
},
  "geometry": {"coordinates":[-91.13428,38.848687],"type":"Point"}
}