{
  "type": "Feature",
  "properties": {
    "iso:country":"US",
    "sg:address":"30 Mockingbird Ln",
    "sg:city":"Montgomery City",
    "sg:classifiers":[
        {
            "category":"Real Estate",
            "subcategory":"Developer",
            "type":"Services"
        }
    ],
    "sg:phone":"+1 573 564 2519",
    "sg:postcode":"63361",
    "sg:province":"MO",
    "sg:tags":[
        "cemetery"
    ],
    "wof:name":"New Providence Cemetery A",
    "wof:placetype":"venue"
},
  "geometry": {"coordinates":[-91.607463,38.921191],"type":"Point"}
}