{
  "type": "Feature",
  "properties": {
    "iso:country":"US",
    "sg:address":"2200 Cassens Dr",
    "sg:city":"Fenton",
    "sg:classifiers":[
        {
            "category":"Manufacturing",
            "subcategory":"Chemicals & Compounds",
            "type":"Manufacturing & Wholesale Goods"
        }
    ],
    "sg:phone":"+1 636 349 1233",
    "sg:postcode":"63026",
    "sg:province":"MO",
    "sg:tags":[
        "inorganic",
        "industrial",
        "mfg"
    ],
    "wof:name":"Nu Chem Inc",
    "wof:placetype":"venue"
},
  "geometry": {"coordinates":[-90.442609,38.546342],"type":"Point"}
}