{
  "type": "Feature",
  "properties": {
    "iso:country":"US",
    "sg:address":"8460 Watson Rd",
    "sg:city":"St Louis",
    "sg:classifiers":[
        {
            "category":"Travel",
            "subcategory":"Travel Agent",
            "type":"Entertainment"
        }
    ],
    "sg:phone":"+1 314 842 8422",
    "sg:postcode":"63119",
    "sg:province":"MO",
    "sg:tags":[
        "operator",
        "tour",
        "agency",
        "bureau"
    ],
    "wof:name":"Unlimited Tours & Travel Inc",
    "wof:placetype":"venue"
},
  "geometry": {"coordinates":[-90.35386699999999,38.565656],"type":"Point"}
}