{
  "type": "Feature",
  "properties": {
    "iso:country":"US",
    "sg:address":"865 N Kingshighway St",
    "sg:city":"Cape Girardeau",
    "sg:classifiers":[
        {
            "category":"Autos & Motor Vehicles",
            "subcategory":"Fuel & Gas Station",
            "type":"Retail Goods"
        }
    ],
    "sg:phone":"+1 573 334 0062",
    "sg:postcode":"63701",
    "sg:province":"MO",
    "sg:tags":[
        "station",
        "gasoline"
    ],
    "wof:name":"Amerimart",
    "wof:placetype":"venue"
},
  "geometry": {"coordinates":[-89.555908,37.318657],"type":"Point"}
}