{
  "type": "Feature",
  "properties": {
    "iso:country":"US",
    "sg:address":"1841 Dogwood Dr",
    "sg:city":"Joplin",
    "sg:classifiers":[
        {
            "category":"Freight",
            "type":"Transportation"
        }
    ],
    "sg:phone":"+1 417 625 1381",
    "sg:postcode":"64801",
    "sg:province":"MO",
    "sg:tags":[
        "operator",
        "local",
        "trucking"
    ],
    "wof:name":"JC Transport",
    "wof:placetype":"venue"
},
  "geometry": {"coordinates":[-94.537716,37.122357],"type":"Point"}
}