{
  "type": "Feature",
  "properties": {
    "iso:country":"US",
    "sg:address":"182 Southpoint Dr",
    "sg:city":"Camdenton",
    "sg:classifiers":[
        {
            "category":"Building & Trades",
            "subcategory":"Cleaning & Sanitation",
            "type":"Services"
        },
        {
            "category":"Home & Garden",
            "subcategory":"Carpets & Floor Coverings",
            "type":"Retail Goods"
        },
        {
            "category":"Home & Garden",
            "subcategory":"Home Furnishings",
            "type":"Retail Goods"
        },
        {
            "category":"Building & Trades",
            "subcategory":"Construction",
            "type":"Services"
        },
        {
            "category":"Home & Garden",
            "subcategory":"Furniture",
            "type":"Retail Goods"
        }
    ],
    "sg:phone":"+1 866 671 7423",
    "sg:postcode":"65020",
    "sg:province":"MO",
    "sg:tags":[
        "repair",
        "industrial",
        "deck",
        "resurfacing",
        "planning",
        "roofing",
        "bathroom",
        "stair",
        "windows-repair",
        "contractor",
        "refacing",
        "treatment",
        "maintenance",
        "remodeling",
        "contractors-commercial",
        "material",
        "handyman",
        "specialty",
        "carpenter",
        "cabinet",
        "cabinets-refinishing",
        "kitchen",
        "installation",
        "altering",
        "builder",
        "siding",
        "tile-contractors",
        "painting",
        "replacement"
    ],
    "wof:name":"EZtime Construction",
    "wof:placetype":"venue"
},
  "geometry": {"coordinates":[-92.705354,37.923651],"type":"Point"}
}