{
  "type": "Feature",
  "properties": {
    "iso:country":"US",
    "sg:address":"1400 Independence Rd",
    "sg:city":"Rolla",
    "sg:classifiers":[
        {
            "category":"Real Estate",
            "subcategory":"Real Estate Operator",
            "type":"Services"
        }
    ],
    "sg:phone":"+1 573 341 3531",
    "sg:postcode":"65401",
    "sg:province":"MO",
    "sg:tags":[
        "building",
        "nonresidential"
    ],
    "wof:name":"H & H Rolla",
    "wof:placetype":"venue"
},
  "geometry": {"coordinates":[-91.745171,37.954449],"type":"Point"}
}