{
  "type": "Feature",
  "properties": {
    "iso:country":"US",
    "sg:address":"503 Broadway St",
    "sg:city":"Elsberry",
    "sg:classifiers":[
        {
            "category":"Education",
            "subcategory":"Special Training",
            "type":"Public Place"
        }
    ],
    "sg:phone":"+1 573 898 9700",
    "sg:postcode":"63343",
    "sg:province":"MO",
    "sg:tags":[
        "educational"
    ],
    "wof:name":"Mesker & Sons Enterprise",
    "wof:placetype":"venue"
},
  "geometry": {"coordinates":[-90.78470299999999,39.164988],"type":"Point"}
}