{
  "type": "Feature",
  "properties": {
    "addr:full":"3505 Tree Court Industrl Blvd St Louis MO 63122",
    "addr:housenumber":"3505",
    "addr:postcode":"63122",
    "addr:street":"Tree Court Industrl Blvd",
    "iso:country":"US",
    "sg:address":"3505 Tree Court Industrl Blvd",
    "sg:city":"St Louis",
    "sg:classifiers":[
        {
            "category":"Manufacturing",
            "subcategory":"Paper Products",
            "type":"Manufacturing & Wholesale Goods"
        }
    ],
    "sg:phone":"+1 636 861 5120",
    "sg:postcode":"63122",
    "sg:province":"MO",
    "sg:tags":[
        "box",
        "fiber",
        "business",
        "mfg"
    ],
    "sg:website":"www.smurfit.com",
    "wof:name":"Smurfit Stone Container Corp",
    "wof:placetype":"venue"
},
  "geometry": {"coordinates":[-90.455943,38.560745],"type":"Point"}
}