{
  "type": "Feature",
  "properties": {
    "iso:country":"US",
    "sg:address":"8600 NE Underground Dr",
    "sg:city":"Kansas City",
    "sg:classifiers":[
        {
            "category":"Manufacturing",
            "subcategory":"Tools & Machinery",
            "type":"Manufacturing & Wholesale Goods"
        }
    ],
    "sg:phone":"+1 816 455 5035",
    "sg:postcode":"64161",
    "sg:province":"MO",
    "sg:tags":[
        "manufacture",
        "heavy",
        "outdoor",
        "equipment"
    ],
    "wof:name":"Collins Machinery",
    "wof:placetype":"venue"
},
  "geometry": {"coordinates":[-94.484033,39.156402],"type":"Point"}
}