{
  "type": "Feature",
  "properties": {
    "iso:country":"US",
    "sg:address":"10 E 5th St",
    "sg:city":"Fulton",
    "sg:classifiers":[
        {
            "category":"Government",
            "subcategory":"Office",
            "type":"Public Place"
        }
    ],
    "sg:phone":"+1 573 642 0737",
    "sg:postcode":"65251",
    "sg:province":"MO",
    "wof:name":"Callaway County Commissioners",
    "wof:placetype":"venue"
},
  "geometry": {"coordinates":[-91.94790399999999,38.847299],"type":"Point"}
}