{
  "type": "Feature",
  "properties": {
    "iso:country":"US",
    "sg:address":"1015 1st St",
    "sg:city":"Kennett",
    "sg:classifiers":[
        {
            "category":"Autos & Motor Vehicles",
            "subcategory":"Automobile Sales",
            "type":"Retail Goods"
        }
    ],
    "sg:phone":"+1 573 888 5939",
    "sg:postcode":"63857",
    "sg:province":"MO",
    "sg:tags":[
        "car",
        "used",
        "dealer"
    ],
    "wof:name":"Gibson's Auto Sales",
    "wof:placetype":"venue"
},
  "geometry": {"coordinates":[-90.04648400000001,36.2365],"type":"Point"}
}