{
  "type": "Feature",
  "properties": {
    "iso:country":"US",
    "sg:address":"2218 E Latoka St",
    "sg:city":"Springfield",
    "sg:classifiers":[
        {
            "category":"Personal",
            "type":"Services"
        }
    ],
    "sg:phone":"+1 417 861 0602",
    "sg:postcode":"65804",
    "sg:province":"MO",
    "sg:tags":[
        "therapist",
        "massage"
    ],
    "wof:name":"Sarah Herschend Massage Thrpst",
    "wof:placetype":"venue"
},
  "geometry": {"coordinates":[-93.25250800000001,37.178655],"type":"Point"}
}