{
  "type": "Feature",
  "properties": {
    "iso:country":"US",
    "sg:address":"32875 Mount Hope Rd",
    "sg:city":"California",
    "sg:classifiers":[
        {
            "category":"Farming",
            "subcategory":"Livestock Farm",
            "type":"Manufacturing & Wholesale Goods"
        }
    ],
    "sg:phone":"+1 573 796 3671",
    "sg:postcode":"65018",
    "sg:province":"MO",
    "sg:tags":[
        "beef",
        "feedlot",
        "cattle"
    ],
    "wof:name":"Gary Fleischmann",
    "wof:placetype":"venue"
},
  "geometry": {"coordinates":[-92.46251599999999,38.587202],"type":"Point"}
}