{
  "type": "Feature",
  "properties": {
    "iso:country":"US",
    "sg:address":"7413 State Hwy 116 SW",
    "sg:city":"Polo",
    "sg:classifiers":[
        {
            "category":"Freight",
            "type":"Transportation"
        }
    ],
    "sg:phone":"+1 816 586 2309",
    "sg:postcode":"64671",
    "sg:province":"MO",
    "sg:tags":[
        "trucking"
    ],
    "wof:name":"Express Air Cargo",
    "wof:placetype":"venue"
},
  "geometry": {"coordinates":[-94.143827,39.555103],"type":"Point"}
}