{
  "type": "Feature",
  "properties": {
    "iso:country":"US",
    "sg:address":"1532 Bayonne Dr",
    "sg:city":"Saint Louis",
    "sg:classifiers":[
        {
            "category":"Organizations",
            "subcategory":"Religious Organization",
            "type":"Services"
        }
    ],
    "sg:phone":"+1 314 438 8114",
    "sg:postcode":"63138",
    "sg:province":"MO",
    "wof:name":"Fahamme Temp of Divn Undrt Inc",
    "wof:placetype":"venue"
},
  "geometry": {"coordinates":[-90.218261,38.779556],"type":"Point"}
}