{
  "type": "Feature",
  "properties": {
    "iso:country":"US",
    "sg:address":"230 Main St",
    "sg:city":"Platte City",
    "sg:classifiers":[
        {
            "category":"Organizations",
            "subcategory":"Non-profit Organization",
            "type":"Services"
        }
    ],
    "sg:phone":"+1 816 858 3117",
    "sg:postcode":"64079",
    "sg:province":"MO",
    "wof:name":"Platte City Solutions Group",
    "wof:placetype":"venue"
},
  "geometry": {"coordinates":[-94.78122999999999,39.370319],"type":"Point"}
}