{
  "type": "Feature",
  "properties": {
    "iso:country":"US",
    "sg:address":"13208 Tesson Ferry Rd",
    "sg:city":"Sappington",
    "sg:classifiers":[
        {
            "category":"Shopping",
            "subcategory":"Used Merchandise",
            "type":"Retail Goods"
        }
    ],
    "sg:phone":"+1 314 842 5566",
    "sg:postcode":"63128",
    "sg:province":"MO",
    "sg:tags":[
        "antique"
    ],
    "wof:name":"South County Antique Mall Inc",
    "wof:placetype":"venue"
},
  "geometry": {"coordinates":[-90.38367599999999,38.485867],"type":"Point"}
}