{
  "type": "Feature",
  "properties": {
    "iso:country":"US",
    "sg:address":"4675 Gravois Rd",
    "sg:city":"House Springs",
    "sg:classifiers":[
        {
            "category":"Banks & Credit Unions",
            "subcategory":"Bank",
            "type":"Services"
        }
    ],
    "sg:phone":"+1 636 671 3373",
    "sg:postcode":"63051",
    "sg:province":"MO",
    "wof:name":"Eagle Bank & Trust Co",
    "wof:placetype":"venue"
},
  "geometry": {"coordinates":[-90.58108,38.412436],"type":"Point"}
}