{
  "type": "Feature",
  "properties": {
    "iso:country":"US",
    "sg:address":"5250 State Hwy A",
    "sg:city":"Dutchtown",
    "sg:classifiers":[
        {
            "category":"Real Estate",
            "subcategory":"Real Estate Agent",
            "type":"Services"
        }
    ],
    "sg:phone":"+1 573 794 9093",
    "sg:postcode":"63748",
    "sg:province":"MO",
    "wof:name":"Midas Realty",
    "wof:placetype":"venue"
},
  "geometry": {"coordinates":[-89.62920800000001,37.631305],"type":"Point"}
}