{
  "type": "Feature",
  "properties": {
    "iso:country":"US",
    "sg:address":"3525 S National Ave",
    "sg:city":"Springfield",
    "sg:classifiers":[
        {
            "category":"Health Services",
            "subcategory":"Doctor",
            "type":"Services"
        }
    ],
    "sg:phone":"+1 417 889 9860",
    "sg:postcode":"65807",
    "sg:province":"MO",
    "sg:tags":[
        "medical"
    ],
    "wof:name":"David Lay",
    "wof:placetype":"venue"
},
  "geometry": {"coordinates":[-93.27783700000001,37.149681],"type":"Point"}
}