{
  "type": "Feature",
  "properties": {
    "iso:country":"US",
    "sg:address":"821 SW Bishop Ct",
    "sg:city":"Blue Springs",
    "sg:classifiers":[
        {
            "category":"Arts & Performance",
            "subcategory":"Theater",
            "type":"Entertainment"
        }
    ],
    "sg:phone":"+1 816 220 2029",
    "sg:postcode":"64015",
    "sg:province":"MO",
    "sg:tags":[
        "group"
    ],
    "wof:name":"Superb Sound Mobil Dj Service",
    "wof:placetype":"venue"
},
  "geometry": {"coordinates":[-94.27636200000001,38.986978],"type":"Point"}
}