{
  "type": "Feature",
  "properties": {
    "addr:full":"3801 Oakland Ave St Joseph MO 64506",
    "addr:housenumber":"3801",
    "addr:postcode":"64506",
    "addr:street":"Oakland Ave",
    "iso:country":"US",
    "sg:address":"3801 Oakland Ave",
    "sg:city":"St Joseph",
    "sg:classifiers":[
        {
            "category":"Insurance",
            "subcategory":"Insurance Agent",
            "type":"Services"
        }
    ],
    "sg:phone":"+1 816 387 9120",
    "sg:postcode":"64506",
    "sg:province":"MO",
    "wof:name":"American National Insurance Co",
    "wof:placetype":"venue"
},
  "geometry": {"coordinates":[-94.79999100000001,39.782848],"type":"Point"}
}