{
  "type": "Feature",
  "properties": {
    "iso:country":"US",
    "sg:address":"3955 W 83rd St",
    "sg:city":"Prairie Village",
    "sg:classifiers":[
        {
            "category":"Sports & Exercise",
            "subcategory":"Gym",
            "type":"Entertainment"
        }
    ],
    "sg:phone":"+1 913 649 4440",
    "sg:postcode":"66208",
    "sg:province":"MO",
    "sg:tags":[
        "club",
        "health",
        "studio",
        "gymnasium"
    ],
    "wof:name":"Ultimate Fitness",
    "wof:placetype":"venue"
},
  "geometry": {"coordinates":[-94.632668,38.978612],"type":"Point"}
}