{
  "type": "Feature",
  "properties": {
    "iso:country":"US",
    "sg:address":"720 Olive St",
    "sg:city":"Saint Louis",
    "sg:classifiers":[
        {
            "category":"Real Estate",
            "subcategory":"Developer",
            "type":"Services"
        }
    ],
    "sg:phone":"+1 314 342 0500",
    "sg:postcode":"63101",
    "sg:province":"MO",
    "sg:tags":[
        "development",
        "company"
    ],
    "wof:name":"Laclede Development Company",
    "wof:placetype":"venue"
},
  "geometry": {"coordinates":[-90.191316,38.62826],"type":"Point"}
}