{
  "type": "Feature",
  "properties": {
    "iso:country":"US",
    "sg:address":"702 N Main St",
    "sg:city":"De Soto",
    "sg:classifiers":[
        {
            "category":"Social Services",
            "subcategory":"Job Training",
            "type":"Services"
        }
    ],
    "sg:phone":"+1 636 586 3887",
    "sg:postcode":"63020",
    "sg:province":"MO",
    "sg:tags":[
        "rehabilitation"
    ],
    "wof:name":"Jmh Rehab Ctr",
    "wof:placetype":"venue"
},
  "geometry": {"coordinates":[-90.551278,38.145875],"type":"Point"}
}