{
  "type": "Feature",
  "properties": {
    "iso:country":"US",
    "sg:address":"711 N 17th St",
    "sg:city":"Lexington",
    "sg:classifiers":[
        {
            "category":"Professional",
            "subcategory":"Detective & Security Services",
            "type":"Services"
        }
    ],
    "sg:phone":"+1 660 259 3002",
    "sg:postcode":"64067",
    "sg:province":"MO",
    "sg:tags":[
        "information",
        "bureau"
    ],
    "wof:name":"Tom Hufft Construction Services",
    "wof:placetype":"venue"
},
  "geometry": {"coordinates":[-93.874797,39.195326],"type":"Point"}
}