{
  "type": "Feature",
  "properties": {
    "iso:country":"US",
    "sg:address":"1101 Carleton Ave",
    "sg:city":"Caruthersville",
    "sg:classifiers":[
        {
            "category":"Organizations",
            "subcategory":"Community Association",
            "type":"Services"
        }
    ],
    "sg:phone":"+1 573 333 9921",
    "sg:postcode":"63830",
    "sg:province":"MO",
    "sg:tags":[
        "civic"
    ],
    "wof:name":"Caruthersville Community Ctr",
    "wof:placetype":"venue"
},
  "geometry": {"coordinates":[-89.66143,36.186655],"type":"Point"}
}