{
  "type": "Feature",
  "properties": {
    "iso:country":"US",
    "sg:address":"11545 Gravois Rd",
    "sg:city":"Saint Louis",
    "sg:classifiers":[
        {
            "category":"Banks & Credit Unions",
            "subcategory":"Investment Brokerage",
            "type":"Services"
        }
    ],
    "sg:phone":"+1 314 842 0412",
    "sg:postcode":"63126",
    "sg:province":"MO",
    "sg:tags":[
        "security"
    ],
    "wof:name":"Edward Jones 05156",
    "wof:placetype":"venue"
},
  "geometry": {"coordinates":[-90.378776,38.5372],"type":"Point"}
}