{
  "type": "Feature",
  "properties": {
    "iso:country":"US",
    "sg:address":"1608 Brookfield Mnr",
    "sg:city":"Columbia",
    "sg:classifiers":[
        {
            "category":"Education",
            "subcategory":"Special Training",
            "type":"Public Place"
        }
    ],
    "sg:phone":"+1 573 256 5478",
    "sg:postcode":"65203",
    "sg:province":"MO",
    "sg:tags":[
        "educational"
    ],
    "wof:name":"Habib Zaghouani",
    "wof:placetype":"venue"
},
  "geometry": {"coordinates":[-92.364037,38.897604],"type":"Point"}
}