{
  "type": "Feature",
  "properties": {
    "iso:country":"US",
    "sg:address":"916 Main St",
    "sg:city":"Unionville",
    "sg:classifiers":[
        {
            "category":"Coffee & Tea",
            "type":"Food & Drink"
        },
        {
            "category":"Restaurant",
            "type":"Food & Drink"
        }
    ],
    "sg:phone":"+1 660 947 3501",
    "sg:postcode":"63565",
    "sg:province":"MO",
    "sg:tags":[
        "lunch",
        "brunch",
        "espresso",
        "breakfast"
    ],
    "wof:name":"Deb's Cafe",
    "wof:placetype":"venue"
},
  "geometry": {"coordinates":[-92.992535,40.476781],"type":"Point"}
}