{
  "type": "Feature",
  "properties": {
    "iso:country":"US",
    "sg:address":"47314 Liberty Ln",
    "sg:city":"Vandalia",
    "sg:classifiers":[
        {
            "category":"Freight",
            "type":"Transportation"
        }
    ],
    "sg:phone":"+1 573 594 3476",
    "sg:postcode":"63382",
    "sg:province":"MO",
    "sg:tags":[
        "operator",
        "trucking"
    ],
    "wof:name":"Fowler Trucking",
    "wof:placetype":"venue"
},
  "geometry": {"coordinates":[-91.565963,39.366807],"type":"Point"}
}