{
  "type": "Feature",
  "properties": {
    "iso:country":"US",
    "sg:address":"329 Mid Rivers Mall Dr",
    "sg:city":"St Peters",
    "sg:classifiers":[
        {
            "category":"Retail",
            "subcategory":"Portrait Studio",
            "type":"Services"
        }
    ],
    "sg:phone":"+1 636 970 3712",
    "sg:postcode":"63376",
    "sg:province":"MO",
    "sg:tags":[
        "photographer"
    ],
    "wof:name":"Prestige Portraits",
    "wof:placetype":"venue"
},
  "geometry": {"coordinates":[-90.624819,38.791307],"type":"Point"}
}