{
  "type": "Feature",
  "properties": {
    "iso:country":"US",
    "sg:address":"222 E Dunklin St",
    "sg:city":"Jefferson City",
    "sg:classifiers":[
        {
            "category":"Education",
            "subcategory":"Library",
            "type":"Public Place"
        }
    ],
    "sg:phone":"+1 573 634 3894",
    "sg:postcode":"65101",
    "sg:province":"MO",
    "sg:tags":[
        "legal"
    ],
    "wof:name":"Jeff City Filing Service",
    "wof:placetype":"venue"
},
  "geometry": {"coordinates":[-92.175601,38.571751],"type":"Point"}
}