{
  "type": "Feature",
  "properties": {
    "iso:country":"US",
    "sg:address":"4730 Flat River Rd",
    "sg:city":"Farmington",
    "sg:classifiers":[
        {
            "category":"Retail",
            "subcategory":"Veterinary Services",
            "type":"Services"
        }
    ],
    "sg:phone":"+1 573 756 9400",
    "sg:postcode":"63640",
    "sg:province":"MO",
    "sg:tags":[
        "veterinarian"
    ],
    "wof:name":"Veterinary Clinic/Mineral Area",
    "wof:placetype":"venue"
},
  "geometry": {"coordinates":[-90.448616,37.812784],"type":"Point"}
}