{
  "type": "Feature",
  "properties": {
    "iso:country":"US",
    "sg:address":"6106 NW Bell Rd",
    "sg:city":"Kansas City",
    "sg:classifiers":[
        {
            "category":"Building & Trades",
            "subcategory":"Construction",
            "type":"Services"
        }
    ],
    "sg:phone":"+1 816 741 2067",
    "sg:postcode":"64152",
    "sg:province":"MO",
    "sg:tags":[
        "masonry",
        "contractor"
    ],
    "wof:name":"Osage Masonry Inc",
    "wof:placetype":"venue"
},
  "geometry": {"coordinates":[-94.687167,39.208754],"type":"Point"}
}