{
  "type": "Feature",
  "properties": {
    "iso:country":"US",
    "sg:address":"1431 Cora Ave",
    "sg:city":"Saint Louis",
    "sg:classifiers":[
        {
            "category":"Retail",
            "subcategory":"Auto Repair",
            "type":"Services"
        }
    ],
    "sg:phone":"+1 314 652 6803",
    "sg:postcode":"63113",
    "sg:province":"MO",
    "sg:tags":[
        "body",
        "shop"
    ],
    "wof:name":"Hill's Auto Body",
    "wof:placetype":"venue"
},
  "geometry": {"coordinates":[-90.252098,38.6591],"type":"Point"}
}