{
  "type": "Feature",
  "properties": {
    "iso:country":"US",
    "sg:address":"7616 Big Bend Blvd",
    "sg:city":"Saint Louis",
    "sg:classifiers":[
        {
            "category":"Wholesale",
            "subcategory":"Jewelry",
            "type":"Manufacturing & Wholesale Goods"
        }
    ],
    "sg:phone":"+1 314 644 6140",
    "sg:postcode":"63119",
    "sg:province":"MO",
    "sg:tags":[
        "stone"
    ],
    "wof:name":"Lady Bugs Beads LLC",
    "wof:placetype":"venue"
},
  "geometry": {"coordinates":[-90.32963599999999,38.598395],"type":"Point"}
}