{
  "type": "Feature",
  "properties": {
    "iso:country":"US",
    "sg:address":"5904 Brown Station Rd",
    "sg:city":"Columbia",
    "sg:classifiers":[
        {
            "category":"Building & Trades",
            "subcategory":"Plumbing",
            "type":"Services"
        },
        {
            "category":"Home & Garden",
            "subcategory":"Building Materials",
            "type":"Retail Goods"
        },
        {
            "category":"Building & Trades",
            "subcategory":"Construction",
            "type":"Services"
        },
        {
            "category":"Utilities",
            "subcategory":"Sewage",
            "type":"Services"
        }
    ],
    "sg:phone":"+1 573 474 2370",
    "sg:postcode":"65202",
    "sg:province":"MO",
    "sg:tags":[
        "heater",
        "plumber",
        "excavation",
        "contractor",
        "water",
        "sewer",
        "cleaning",
        "plumbing-drain"
    ],
    "sg:website":"http://www.rotorooter.com",
    "wof:name":"Roto-Rooter Plumbing & Drain Services",
    "wof:placetype":"venue"
},
  "geometry": {"coordinates":[-92.27791000000001,39.014295],"type":"Point"}
}