{
  "type": "Feature",
  "properties": {
    "iso:country":"US",
    "sg:address":"3925 Hwy D",
    "sg:city":"Defiance",
    "sg:classifiers":[
        {
            "category":"Social Services",
            "subcategory":"Child Care",
            "type":"Services"
        },
        {
            "category":"Education",
            "subcategory":"School",
            "type":"Public Place"
        }
    ],
    "sg:phone":"+1 636 398 3000",
    "sg:postcode":"63341",
    "sg:province":"MO",
    "sg:tags":[
        "academic",
        "day",
        "special"
    ],
    "wof:name":"Ages & Stages Learning Center",
    "wof:placetype":"venue"
},
  "geometry": {"coordinates":[-90.810626,38.693963],"type":"Point"}
}