{
  "type": "Feature",
  "properties": {
    "iso:country":"US",
    "sg:address":"1201 Briarbrook Dr",
    "sg:city":"Carl Junction",
    "sg:classifiers":[
        {
            "category":"Restaurant",
            "type":"Food & Drink"
        }
    ],
    "sg:menulink":"http://www.allmenus.com/mo/galena/225247-caseys-general-store/menu/",
    "sg:phone":"+1 417 623 1717",
    "sg:postcode":"64834",
    "sg:province":"MO",
    "sg:tags":[
        "american",
        "pizza"
    ],
    "wof:name":"Casey's General Store",
    "wof:placetype":"venue"
},
  "geometry": {"coordinates":[-94.537521,37.144748],"type":"Point"}
}