{
  "type": "Feature",
  "properties": {
    "iso:country":"US",
    "sg:address":"13240 Manchester Rd",
    "sg:city":"St Louis",
    "sg:classifiers":[
        {
            "category":"Building & Trades",
            "subcategory":"Construction",
            "type":"Services"
        }
    ],
    "sg:phone":"+1 314 965 8280",
    "sg:postcode":"63131",
    "sg:province":"MO",
    "sg:tags":[
        "contractor",
        "designer",
        "dealer",
        "pool",
        "swimming"
    ],
    "wof:name":"Baker Pool & Spa",
    "wof:placetype":"venue"
},
  "geometry": {"coordinates":[-90.469072,38.598755],"type":"Point"}
}