{
  "type": "Feature",
  "properties": {
    "iso:country":"US",
    "sg:address":"5500 Lost Trails Dr",
    "sg:city":"Antonia",
    "sg:classifiers":[
        {
            "category":"Wholesale",
            "subcategory":"Machinery & Supplies",
            "type":"Manufacturing & Wholesale Goods"
        },
        {
            "category":"Government",
            "subcategory":"Fire Station",
            "type":"Public Place"
        }
    ],
    "sg:phone":"+1 636 942 7200",
    "sg:postcode":"63052",
    "sg:province":"MO",
    "sg:tags":[
        "protection",
        "sprinkler"
    ],
    "wof:name":"Accel Fire Protection Inc",
    "wof:placetype":"venue"
},
  "geometry": {"coordinates":[-90.47274,38.40377],"type":"Point"}
}