{
  "type": "Feature",
  "properties": {
    "iso:country":"US",
    "sg:address":"1230 Dougherty Ferry Rd",
    "sg:city":"Valley Park",
    "sg:classifiers":[
        {
            "category":"Social Services",
            "subcategory":"Child Care",
            "type":"Services"
        }
    ],
    "sg:phone":"+1 636 225 4800",
    "sg:postcode":"63088",
    "sg:province":"MO",
    "sg:tags":[
        "day"
    ],
    "wof:name":"Lakeside Child Care Center",
    "wof:placetype":"venue"
},
  "geometry": {"coordinates":[-90.479096,38.566044],"type":"Point"}
}