{
  "type": "Feature",
  "properties": {
    "iso:country":"US",
    "sg:address":"312 Porter Wagoner Blvd",
    "sg:city":"West Plains",
    "sg:classifiers":[
        {
            "category":"Professional",
            "type":"Services"
        }
    ],
    "sg:phone":"+1 417 256 2899",
    "sg:postcode":"65775",
    "sg:province":"MO",
    "sg:tags":[
        "establishment"
    ],
    "wof:name":"Parkside Pantry",
    "wof:placetype":"venue"
},
  "geometry": {"coordinates":[-91.863924,36.731266],"type":"Point"}
}