{
  "type": "Feature",
  "properties": {
    "iso:country":"US",
    "sg:address":"1234 Commercial Blvd",
    "sg:city":"Herculaneum",
    "sg:classifiers":[
        {
            "category":"Government",
            "subcategory":"Post Office",
            "type":"Public Place"
        }
    ],
    "sg:phone":"+1 636 937 7220",
    "sg:postcode":"63048",
    "sg:province":"MO",
    "sg:tags":[
        "postal",
        "us"
    ],
    "wof:name":"US Post Office",
    "wof:placetype":"venue"
},
  "geometry": {"coordinates":[-90.393086,38.255105],"type":"Point"}
}