{
  "type": "Feature",
  "properties": {
    "iso:country":"US",
    "sg:address":"8817 N Forest Ave",
    "sg:city":"Kansas City",
    "sg:classifiers":[
        {
            "category":"Building & Trades",
            "subcategory":"Landscaping Services",
            "type":"Services"
        }
    ],
    "sg:phone":"+1 816 436 1466",
    "sg:postcode":"64155",
    "sg:province":"MO",
    "wof:name":"Backhus Lawn Service",
    "wof:placetype":"venue"
},
  "geometry": {"coordinates":[-94.565337,39.25718],"type":"Point"}
}