{
  "type": "Feature",
  "properties": {
    "iso:country":"US",
    "sg:address":"247 Chesterfield Industrial Blvd",
    "sg:city":"Chesterfield",
    "sg:classifiers":[
        {
            "category":"Real Estate",
            "subcategory":"Real Estate Agent",
            "type":"Services"
        }
    ],
    "sg:phone":"+1 636 532 5155",
    "sg:postcode":"63005",
    "sg:province":"MO",
    "sg:tags":[
        "appraisal",
        "appraiser"
    ],
    "wof:name":"Appraisal Centre Inc",
    "wof:placetype":"venue"
},
  "geometry": {"coordinates":[-90.622272,38.667304],"type":"Point"}
}