{
  "type": "Feature",
  "properties": {
    "iso:country":"US",
    "sg:address":"2745 High Ridge Blvd",
    "sg:city":"High Ridge",
    "sg:classifiers":[
        {
            "category":"Professional",
            "subcategory":"Employment Agencies",
            "type":"Services"
        }
    ],
    "sg:phone":"+1 636 677 9753",
    "sg:postcode":"63049",
    "sg:province":"MO",
    "sg:tags":[
        "help",
        "contractor"
    ],
    "wof:name":"Excel Temporary Svc",
    "wof:placetype":"venue"
},
  "geometry": {"coordinates":[-90.52857400000001,38.464641],"type":"Point"}
}