{
  "type": "Feature",
  "properties": {
    "iso:country":"US",
    "sg:address":"226 Baker Ave",
    "sg:city":"Forsyth",
    "sg:classifiers":[
        {
            "category":"Travel",
            "subcategory":"Campground",
            "type":"Entertainment"
        }
    ],
    "sg:phone":"+1 417 546 4222",
    "sg:postcode":"65653",
    "sg:province":"MO",
    "sg:tags":[
        "trailer"
    ],
    "wof:name":"Bar Bee R V Park",
    "wof:placetype":"venue"
},
  "geometry": {"coordinates":[-93.10205000000001,36.678183],"type":"Point"}
}