{
  "type": "Feature",
  "properties": {
    "iso:country":"US",
    "sg:address":"327 de Baliviere Ave",
    "sg:city":"St Louis",
    "sg:classifiers":[
        {
            "category":"Real Estate",
            "subcategory":"Developer",
            "type":"Services"
        }
    ],
    "sg:phone":"+1 314 367 1674",
    "sg:postcode":"63112",
    "sg:province":"MO",
    "wof:name":"Development Investments",
    "wof:placetype":"venue"
},
  "geometry": {"coordinates":[-90.285156,38.649027],"type":"Point"}
}