{
  "type": "Feature",
  "properties": {
    "iso:country":"US",
    "sg:address":"111 W Broadway St",
    "sg:city":"Bolivar",
    "sg:classifiers":[
        {
            "category":"Professional",
            "subcategory":"Lawyer & Legal Services",
            "type":"Services"
        }
    ],
    "sg:phone":"+1 417 326 5261",
    "sg:postcode":"65613",
    "sg:province":"MO",
    "sg:tags":[
        "attorney"
    ],
    "sg:website":"http://www.bolivarlaw.com",
    "wof:name":"Douglas Haun & Heidemann PC",
    "wof:placetype":"venue"
},
  "geometry": {"coordinates":[-93.411786,37.613994],"type":"Point"}
}