{
  "type": "Feature",
  "properties": {
    "iso:country":"US",
    "sg:address":"7800 Natural Bridge Rd",
    "sg:city":"Saint Louis",
    "sg:classifiers":[
        {
            "category":"Education",
            "subcategory":"University",
            "type":"Public Place"
        }
    ],
    "sg:phone":"+1 314 516 5131",
    "sg:postcode":"63121",
    "sg:province":"MO",
    "sg:tags":[
        "college"
    ],
    "sg:website":"www.umsl.edu",
    "wof:name":"University of Missouri-St Louis",
    "wof:placetype":"venue"
},
  "geometry": {"coordinates":[-90.305378,38.706816],"type":"Point"}
}