{
  "type": "Feature",
  "properties": {
    "iso:country":"US",
    "sg:address":"5935 Wornall Rd",
    "sg:city":"Kansas City",
    "sg:classifiers":[
        {
            "category":"Banks & Credit Unions",
            "subcategory":"Bank",
            "type":"Services"
        }
    ],
    "sg:phone":"+1 816 361 6188",
    "sg:postcode":"64113",
    "sg:province":"MO",
    "sg:tags":[
        "loan",
        "real estate"
    ],
    "wof:name":"Burke Capital Funding",
    "wof:placetype":"venue"
},
  "geometry": {"coordinates":[-94.59285199999999,39.019032],"type":"Point"}
}