{
  "type": "Feature",
  "properties": {
    "iso:country":"US",
    "sg:address":"34676 Elkhorn Trl",
    "sg:city":"Graham",
    "sg:classifiers":[
        {
            "category":"Mining & Drilling",
            "type":"Manufacturing & Wholesale Goods"
        }
    ],
    "sg:phone":"+1 660 939 4745",
    "sg:postcode":"64455",
    "sg:province":"MO",
    "sg:tags":[
        "broken",
        "limestone",
        "crushed"
    ],
    "wof:name":"Schildberg Construction Co Inc",
    "wof:placetype":"venue"
},
  "geometry": {"coordinates":[-95.029723,40.223749],"type":"Point"}
}