{
  "type": "Feature",
  "properties": {
    "iso:country":"US",
    "sg:address":"229 Copperwood Trl",
    "sg:city":"Saint Charles",
    "sg:classifiers":[
        {
            "category":"Insurance",
            "subcategory":"Insurance Agent",
            "type":"Services"
        }
    ],
    "sg:phone":"+1 636 926 2498",
    "sg:postcode":"63304",
    "sg:province":"MO",
    "sg:tags":[
        "adjusting"
    ],
    "wof:name":"Todd K Fischer Pub Adjusters",
    "wof:placetype":"venue"
},
  "geometry": {"coordinates":[-90.643591,38.741191],"type":"Point"}
}