{
  "type": "Feature",
  "properties": {
    "iso:country":"US",
    "sg:address":"141 Industrial Park Dr",
    "sg:city":"Hollister",
    "sg:classifiers":[
        {
            "category":"Bakery",
            "type":"Food & Drink"
        }
    ],
    "sg:phone":"+1 417 337 9838",
    "sg:postcode":"65672",
    "sg:province":"MO",
    "wof:name":"Colonial Baking Co",
    "wof:placetype":"venue"
},
  "geometry": {"coordinates":[-93.22467399999999,36.609988],"type":"Point"}
}