{
  "type": "Feature",
  "properties": {
    "iso:country":"US",
    "sg:address":"114 E Lafayette St",
    "sg:city":"Palmyra",
    "sg:classifiers":[
        {
            "category":"Professional",
            "subcategory":"Lawyer & Legal Services",
            "type":"Services"
        }
    ],
    "sg:phone":"+1 573 769 4636",
    "sg:postcode":"63461",
    "sg:province":"MO",
    "sg:tags":[
        "attorney"
    ],
    "wof:name":"Thomas P Meade",
    "wof:placetype":"venue"
},
  "geometry": {"coordinates":[-91.52293299999999,39.798837],"type":"Point"}
}