{
  "type": "Feature",
  "properties": {
    "iso:country":"US",
    "sg:address":"409 SW Moreland School Rd",
    "sg:city":"Blue Springs",
    "sg:classifiers":[
        {
            "category":"Professional",
            "subcategory":"Computer Services",
            "type":"Services"
        }
    ],
    "sg:phone":"+1 816 224 8498",
    "sg:postcode":"64014",
    "sg:province":"MO",
    "sg:tags":[
        "bar",
        "coding"
    ],
    "wof:name":"Ameritags",
    "wof:placetype":"venue"
},
  "geometry": {"coordinates":[-94.269119,38.987413],"type":"Point"}
}