{
  "type": "Feature",
  "properties": {
    "iso:country":"US",
    "sg:address":"928 E 1st St",
    "sg:city":"Peculiar",
    "sg:classifiers":[
        {
            "category":"Shopping",
            "subcategory":"Gifts & Souvenirs",
            "type":"Retail Goods"
        }
    ],
    "sg:phone":"+1 816 779 4170",
    "sg:postcode":"64078",
    "sg:province":"MO",
    "sg:tags":[
        "collectible"
    ],
    "wof:name":"Collectorholics",
    "wof:placetype":"venue"
},
  "geometry": {"coordinates":[-94.458326,38.730783],"type":"Point"}
}