{
  "type": "Feature",
  "properties": {
    "iso:country":"US",
    "sg:address":"2415 Fairlawn Ave",
    "sg:city":"Carthage",
    "sg:classifiers":[
        {
            "category":"Real Estate",
            "subcategory":"Real Estate Services",
            "type":"Services"
        }
    ],
    "sg:phone":"+1 417 358 6494",
    "sg:postcode":"64836",
    "sg:province":"MO",
    "wof:name":"American Research Unltd Inc",
    "wof:placetype":"venue"
},
  "geometry": {"coordinates":[-94.311488,37.148242],"type":"Point"}
}