{
  "type": "Feature",
  "properties": {
    "iso:country":"US",
    "sg:address":"11457 Olive Blvd",
    "sg:city":"St Louis",
    "sg:classifiers":[
        {
            "category":"Travel",
            "subcategory":"Travel Agent",
            "type":"Entertainment"
        }
    ],
    "sg:phone":"+1 314 432 6020",
    "sg:postcode":"63141",
    "sg:province":"MO",
    "sg:tags":[
        "agency",
        "bureau"
    ],
    "sg:website":"www.cruizeco.com",
    "wof:name":"Travel Co",
    "wof:placetype":"venue"
},
  "geometry": {"coordinates":[-90.434622,38.671285],"type":"Point"}
}