{
  "type": "Feature",
  "properties": {
    "iso:country":"US",
    "sg:address":"11840 Bellefontaine Rd",
    "sg:city":"Saint Louis",
    "sg:classifiers":[
        {
            "category":"Professional",
            "subcategory":"Business Services",
            "type":"Services"
        }
    ],
    "sg:phone":"+1 314 653 8651",
    "sg:postcode":"63138",
    "sg:province":"MO",
    "wof:name":"L Crenshaw Enterprises Inc",
    "wof:placetype":"venue"
},
  "geometry": {"coordinates":[-90.21701299999999,38.785111],"type":"Point"}
}