{
  "type": "Feature",
  "properties": {
    "iso:country":"US",
    "sg:address":"210 W 19th Ter",
    "sg:city":"Kansas City",
    "sg:classifiers":[
        {
            "category":"Professional",
            "subcategory":"Management & Consulting",
            "type":"Services"
        }
    ],
    "sg:phone":"+1 816 448 6700",
    "sg:postcode":"64108",
    "sg:province":"MO",
    "sg:tags":[
        "marketing",
        "event"
    ],
    "wof:name":"Three Wide Marketing",
    "wof:placetype":"venue"
},
  "geometry": {"coordinates":[-94.587372,39.090159],"type":"Point"}
}