{
  "type": "Feature",
  "properties": {
    "iso:country":"US",
    "sg:address":"5257 Maple Ave",
    "sg:city":"Saint Louis",
    "sg:classifiers":[
        {
            "category":"Building & Trades",
            "subcategory":"Cleaning & Sanitation",
            "type":"Services"
        }
    ],
    "sg:phone":"+1 314 367 0310",
    "sg:postcode":"63113",
    "sg:province":"MO",
    "sg:tags":[
        "maintenance"
    ],
    "wof:name":"Jani-King",
    "wof:placetype":"venue"
},
  "geometry": {"coordinates":[-90.27081800000001,38.659797],"type":"Point"}
}