{
  "type": "Feature",
  "properties": {
    "iso:country":"US",
    "sg:address":"100 N Broadway St",
    "sg:city":"Princeton",
    "sg:classifiers":[
        {
            "category":"Real Estate",
            "subcategory":"Real Estate Agent",
            "type":"Services"
        }
    ],
    "sg:phone":"+1 660 748 4077",
    "sg:postcode":"64673",
    "sg:province":"MO",
    "wof:name":"George & Merrill Realty",
    "wof:placetype":"venue"
},
  "geometry": {"coordinates":[-93.58595699999999,40.397633],"type":"Point"}
}