{
  "type": "Feature",
  "properties": {
    "iso:country":"US",
    "sg:address":"8716 Gravois Rd",
    "sg:city":"Saint Louis",
    "sg:classifiers":[
        {
            "category":"Retail",
            "subcategory":"Repair Shop",
            "type":"Services"
        }
    ],
    "sg:phone":"+1 314 256 0555",
    "sg:postcode":"63123",
    "sg:province":"MO",
    "wof:name":"Z Ato Lock Key Inc",
    "wof:placetype":"venue"
},
  "geometry": {"coordinates":[-90.309861,38.556262],"type":"Point"}
}