{
  "type": "Feature",
  "properties": {
    "iso:country":"US",
    "sg:address":"19362 Highway 87",
    "sg:city":"Jamestown",
    "sg:classifiers":[
        {
            "category":"Manufacturing",
            "subcategory":"Food",
            "type":"Manufacturing & Wholesale Goods"
        }
    ],
    "sg:phone":"+1 660 849 2365",
    "sg:postcode":"65046",
    "sg:province":"MO",
    "sg:tags":[
        "product"
    ],
    "wof:name":"Roy Schoenthal",
    "wof:placetype":"venue"
},
  "geometry": {"coordinates":[-92.50083100000001,38.786946],"type":"Point"}
}