{
  "type": "Feature",
  "properties": {
    "iso:country":"US",
    "sg:address":"351 Jasper Ln",
    "sg:city":"Jackson",
    "sg:classifiers":[
        {
            "category":"Farming",
            "subcategory":"Farm",
            "type":"Manufacturing & Wholesale Goods"
        }
    ],
    "sg:phone":"+1 573 243 4178",
    "sg:postcode":"63755",
    "sg:province":"MO",
    "sg:tags":[
        "crop",
        "general"
    ],
    "wof:name":"Voshage Farms",
    "wof:placetype":"venue"
},
  "geometry": {"coordinates":[-89.73653,37.35852],"type":"Point"}
}