{
  "type": "Feature",
  "properties": {
    "iso:country":"US",
    "sg:address":"1005 McCausland Ave",
    "sg:city":"Saint Louis",
    "sg:classifiers":[
        {
            "category":"Cinema",
            "subcategory":"Movie Theater",
            "type":"Entertainment"
        }
    ],
    "sg:phone":"+1 314 781 1051",
    "sg:postcode":"63117",
    "sg:province":"MO",
    "wof:name":"Hi Pointe Cinema",
    "wof:placetype":"venue"
},
  "geometry": {"coordinates":[-90.30500000000001,38.632],"type":"Point"}
}