{
  "type": "Feature",
  "properties": {
    "iso:country":"US",
    "sg:address":"5950 Telegraph Rd",
    "sg:city":"St Louis",
    "sg:classifiers":[
        {
            "category":"Education",
            "subcategory":"School",
            "type":"Public Place"
        }
    ],
    "sg:phone":"+1 314 467 7400",
    "sg:postcode":"63129",
    "sg:province":"MO",
    "sg:website":"www.mehlvilleschooldistrict.com",
    "wof:name":"Oakville Middle School",
    "wof:placetype":"venue"
},
  "geometry": {"coordinates":[-90.306247,38.454352],"type":"Point"}
}