{
  "type": "Feature",
  "properties": {
    "iso:country":"US",
    "sg:address":"2123 Charbonier Rd",
    "sg:city":"Florissant",
    "sg:classifiers":[
        {
            "category":"Recreation",
            "type":"Entertainment"
        }
    ],
    "sg:phone":"+1 314 838 9200",
    "sg:postcode":"63031",
    "sg:province":"MO",
    "sg:tags":[
        "martial",
        "arts",
        "instruction"
    ],
    "wof:name":"American Karate Studios",
    "wof:placetype":"venue"
},
  "geometry": {"coordinates":[-90.358614,38.80855],"type":"Point"}
}