{
  "type": "Feature",
  "properties": {
    "iso:country":"US",
    "sg:address":"2200 E Sunshine St",
    "sg:city":"Springfield",
    "sg:classifiers":[
        {
            "category":"Health Services",
            "subcategory":"Health Practitioner",
            "type":"Services"
        }
    ],
    "sg:phone":"+1 417 882 4485",
    "sg:postcode":"65804",
    "sg:province":"MO",
    "wof:name":"Frank E Bartlett",
    "wof:placetype":"venue"
},
  "geometry": {"coordinates":[-93.25179,37.18118],"type":"Point"}
}