{
  "type": "Feature",
  "properties": {
    "iso:country":"US",
    "sg:address":"1508 Heck Ave",
    "sg:city":"Sedalia",
    "sg:classifiers":[
        {
            "category":"Organizations",
            "subcategory":"Religious Organization",
            "type":"Services"
        }
    ],
    "sg:phone":"+1 660 826 5145",
    "sg:postcode":"65301",
    "sg:province":"MO",
    "sg:tags":[
        "church"
    ],
    "wof:name":"Calvary Temple Church",
    "wof:placetype":"venue"
},
  "geometry": {"coordinates":[-93.25098,38.68827],"type":"Point"}
}