{
  "type": "Feature",
  "properties": {
    "iso:country":"US",
    "sg:address":"13801 E 253rd St",
    "sg:city":"Peculiar",
    "sg:classifiers":[
        {
            "category":"Building & Trades",
            "subcategory":"Plumbing",
            "type":"Services"
        }
    ],
    "sg:phone":"+1 816 836 1300",
    "sg:postcode":"64078",
    "sg:province":"MO",
    "sg:tags":[
        "plumbing",
        "contractor"
    ],
    "wof:name":"We Plumbing & Mechanical Inc",
    "wof:placetype":"venue"
},
  "geometry": {"coordinates":[-94.435028,38.659521],"type":"Point"}
}