{
  "type": "Feature",
  "properties": {
    "iso:country":"US",
    "sg:address":"11765 Buddington Ct",
    "sg:city":"Florissant",
    "sg:classifiers":[
        {
            "category":"Wholesale",
            "subcategory":"Machinery & Supplies",
            "type":"Manufacturing & Wholesale Goods"
        }
    ],
    "sg:phone":"+1 314 291 4403",
    "sg:postcode":"63044",
    "sg:province":"MO",
    "sg:tags":[
        "equipment",
        "industrial"
    ],
    "wof:name":"Power Prime Pumps",
    "wof:placetype":"venue"
},
  "geometry": {"coordinates":[-90.419785,38.741793],"type":"Point"}
}