{
  "type": "Feature",
  "properties": {
    "iso:country":"US",
    "sg:address":"5623 State Hwy 94",
    "sg:city":"Tebbetts",
    "sg:classifiers":[
        {
            "category":"Wholesale",
            "subcategory":"Farm Supplies",
            "type":"Manufacturing & Wholesale Goods"
        }
    ],
    "sg:phone":"+1 573 295 4583",
    "sg:postcode":"65080",
    "sg:province":"MO",
    "sg:tags":[
        "grain"
    ],
    "wof:name":"Smart Bros Farms Inc",
    "wof:placetype":"venue"
},
  "geometry": {"coordinates":[-91.94739800000001,38.626726],"type":"Point"}
}