{
  "type": "Feature",
  "properties": {
    "iso:country":"US",
    "sg:address":"4951 NE Goodview Cir",
    "sg:city":"Lees Summit",
    "sg:classifiers":[
        {
            "category":"Health Services",
            "subcategory":"Doctor",
            "type":"Services"
        }
    ],
    "sg:phone":"+1 816 373 5574",
    "sg:postcode":"64064",
    "sg:province":"MO",
    "sg:tags":[
        "dentist",
        "clinic"
    ],
    "wof:name":"Robert J Lockard DDS",
    "wof:placetype":"venue"
},
  "geometry": {"coordinates":[-94.35444099999999,39.002009],"type":"Point"}
}