{
  "type": "Feature",
  "properties": {
    "iso:country":"US",
    "sg:address":"1173 Hillside Dr",
    "sg:city":"Saint Louis",
    "sg:classifiers":[
        {
            "category":"Professional",
            "subcategory":"Business Services",
            "type":"Services"
        }
    ],
    "sg:phone":"+1 314 645 1073",
    "sg:postcode":"63117",
    "sg:province":"MO",
    "wof:name":"Transcom Management Co",
    "wof:placetype":"venue"
},
  "geometry": {"coordinates":[-90.32815100000001,38.635169],"type":"Point"}
}