{
  "type": "Feature",
  "properties": {
    "iso:country":"US",
    "sg:address":"165 Missouri Ave",
    "sg:city":"Laurie",
    "sg:classifiers":[
        {
            "category":"Wholesale",
            "subcategory":"Medical Equipment & Supplies",
            "type":"Manufacturing & Wholesale Goods"
        }
    ],
    "sg:phone":"+1 573 374 1717",
    "sg:postcode":"65014",
    "sg:province":"MO",
    "sg:tags":[
        "physician",
        "surgeon"
    ],
    "wof:name":"Just What The Doctor Ordered",
    "wof:placetype":"venue"
},
  "geometry": {"coordinates":[-91.632576,38.301223],"type":"Point"}
}