{
  "type": "Feature",
  "properties": {
    "iso:country":"US",
    "sg:address":"219 US Hwy 50 W",
    "sg:city":"Union",
    "sg:classifiers":[
        {
            "category":"Bars & Pubs",
            "type":"Food & Drink"
        }
    ],
    "sg:phone":"+1 636 583 5405",
    "sg:postcode":"63084",
    "sg:province":"MO",
    "sg:tags":[
        "drinking"
    ],
    "wof:name":"Theos Colonial Bar",
    "wof:placetype":"venue"
},
  "geometry": {"coordinates":[-91.010306,38.440613],"type":"Point"}
}