{
  "type": "Feature",
  "properties": {
    "addr:full":"65 Broadview Dr Saint Louis MO 63105",
    "addr:housenumber":"65",
    "addr:postcode":"63105",
    "addr:street":"Broadview Dr",
    "iso:country":"US",
    "sg:address":"65 Broadview Dr",
    "sg:city":"Saint Louis",
    "sg:classifiers":[
        {
            "category":"Banks & Credit Unions",
            "subcategory":"Bank",
            "type":"Services"
        }
    ],
    "sg:phone":"+1 314 381 5112",
    "sg:postcode":"63105",
    "sg:province":"MO",
    "sg:tags":[
        "national"
    ],
    "wof:name":"US Bank",
    "wof:placetype":"venue"
},
  "geometry": {"coordinates":[-90.32252099999999,38.637578],"type":"Point"}
}