{
  "type": "Feature",
  "properties": {
    "iso:country":"US",
    "sg:address":"1722 S Glenstone Ave",
    "sg:city":"Springfield",
    "sg:classifiers":[
        {
            "category":"Health Services",
            "subcategory":"Doctor",
            "type":"Services"
        }
    ],
    "sg:phone":"+1 417 823 4900",
    "sg:postcode":"65804",
    "sg:province":"MO",
    "sg:tags":[
        "dentist"
    ],
    "wof:name":"Premier Dental",
    "wof:placetype":"venue"
},
  "geometry": {"coordinates":[-93.262255,37.183579],"type":"Point"}
}