{
  "type": "Feature",
  "properties": {
    "iso:country":"US",
    "sg:address":"920 Timber Glen Ln",
    "sg:city":"Ballwin",
    "sg:classifiers":[
        {
            "category":"Food & Beverages",
            "subcategory":"Groceries & Convenience Stores",
            "type":"Retail Goods"
        }
    ],
    "sg:phone":"+1 636 230 3031",
    "sg:postcode":"63021",
    "sg:province":"MO",
    "wof:name":"Theoality Markets, Inc.",
    "wof:placetype":"venue"
},
  "geometry": {"coordinates":[-90.571882,38.561063],"type":"Point"}
}