{
  "type": "Feature",
  "properties": {
    "iso:country":"US",
    "sg:address":"6330 McPherson Ave",
    "sg:city":"Saint Louis",
    "sg:classifiers":[
        {
            "category":"Health Services",
            "subcategory":"Doctor",
            "type":"Services"
        }
    ],
    "sg:phone":"+1 314 725 4796",
    "sg:postcode":"63130",
    "sg:province":"MO",
    "sg:tags":[
        "medical"
    ],
    "wof:name":"L Henares MD",
    "wof:placetype":"venue"
},
  "geometry": {"coordinates":[-90.30359900000001,38.652624],"type":"Point"}
}