{
  "type": "Feature",
  "properties": {
    "iso:country":"US",
    "sg:address":"4951 NE Goodview Cir",
    "sg:city":"Lees Summit",
    "sg:classifiers":[
        {
            "category":"Professional",
            "subcategory":"Lawyer & Legal Services",
            "type":"Services"
        }
    ],
    "sg:phone":"+1 816 373 8881",
    "sg:postcode":"64064",
    "sg:province":"MO",
    "sg:tags":[
        "attorney"
    ],
    "wof:name":"Cowing & Mendelson PC",
    "wof:placetype":"venue"
},
  "geometry": {"coordinates":[-94.35444099999999,39.002009],"type":"Point"}
}