{
  "type": "Feature",
  "properties": {
    "iso:country":"US",
    "sg:address":"4011 Camelot Estates Ct",
    "sg:city":"Saint Louis",
    "sg:classifiers":[
        {
            "category":"Professional",
            "subcategory":"Accounting & Tax Preparation",
            "type":"Services"
        }
    ],
    "sg:phone":"+1 314 894 2174",
    "sg:postcode":"63129",
    "sg:province":"MO",
    "wof:name":"Larry J Schmieg CPA PC",
    "wof:placetype":"venue"
},
  "geometry": {"coordinates":[-90.350658,38.480822],"type":"Point"}
}