{
  "type": "Feature",
  "properties": {
    "iso:country":"US",
    "sg:address":"2051 N Commercial St",
    "sg:city":"Harrisonville",
    "sg:classifiers":[
        {
            "category":"Shopping",
            "subcategory":"Gifts & Souvenirs",
            "type":"Retail Goods"
        }
    ],
    "sg:phone":"+1 816 380 7577",
    "sg:postcode":"64701",
    "sg:province":"MO",
    "sg:tags":[
        "shop"
    ],
    "wof:name":"Margie's Hallmark",
    "wof:placetype":"venue"
},
  "geometry": {"coordinates":[-94.365494,38.663127],"type":"Point"}
}