{
  "type": "Feature",
  "properties": {
    "iso:country":"US",
    "sg:address":"7420 Michigan Ave",
    "sg:city":"St Louis",
    "sg:classifiers":[
        {
            "category":"Organizations",
            "subcategory":"Religious Organization",
            "type":"Services"
        }
    ],
    "sg:phone":"+1 314 752 5150",
    "sg:postcode":"63111",
    "sg:province":"MO",
    "sg:tags":[
        "church"
    ],
    "wof:name":"Seed Faith World Fellowship",
    "wof:placetype":"venue"
},
  "geometry": {"coordinates":[-90.25975099999999,38.550147],"type":"Point"}
}