{
  "type": "Feature",
  "properties": {
    "iso:country":"US",
    "sg:address":"120 E Pearce Blvd",
    "sg:city":"Wentzville",
    "sg:classifiers":[
        {
            "category":"Health Services",
            "subcategory":"Chiropractor",
            "type":"Services"
        }
    ],
    "sg:phone":"+1 636 327 4747",
    "sg:postcode":"63385",
    "sg:province":"MO",
    "wof:name":"Ditson Chiropractic Center",
    "wof:placetype":"venue"
},
  "geometry": {"coordinates":[-90.85177,38.812205],"type":"Point"}
}