{
  "type": "Feature",
  "properties": {
    "iso:country":"US",
    "sg:address":"301 W High St",
    "sg:city":"Jefferson City",
    "sg:classifiers":[
        {
            "category":"Government",
            "subcategory":"Office",
            "type":"Public Place"
        }
    ],
    "sg:phone":"+1 573 751 4044",
    "sg:postcode":"65101",
    "sg:province":"MO",
    "sg:tags":[
        "state",
        "safety",
        "order"
    ],
    "wof:name":"Missouri Risk Management",
    "wof:placetype":"venue"
},
  "geometry": {"coordinates":[-92.176333,38.579815],"type":"Point"}
}