{
  "type": "Feature",
  "properties": {
    "iso:country":"US",
    "sg:address":"1767 Larkin Williams Rd",
    "sg:city":"Fenton",
    "sg:classifiers":[
        {
            "category":"Real Estate",
            "subcategory":"Real Estate Services",
            "type":"Services"
        }
    ],
    "sg:phone":"+1 636 326 2996",
    "sg:postcode":"63026",
    "sg:province":"MO",
    "sg:tags":[
        "company",
        "title"
    ],
    "sg:website":"www.abstartitle.com",
    "wof:name":"ABSTARTITLE.COM",
    "wof:placetype":"venue"
},
  "geometry": {"coordinates":[-90.457334,38.540034],"type":"Point"}
}