{
  "type": "Feature",
  "properties": {
    "iso:country":"US",
    "sg:address":"1351 McNutt St",
    "sg:city":"Herculaneum",
    "sg:classifiers":[
        {
            "category":"Real Estate",
            "subcategory":"Real Estate Services",
            "type":"Services"
        }
    ],
    "sg:phone":"+1 636 933 7328",
    "sg:postcode":"63048",
    "sg:province":"MO",
    "sg:tags":[
        "company",
        "title"
    ],
    "wof:name":"Mississippi Valley Title",
    "wof:placetype":"venue"
},
  "geometry": {"coordinates":[-90.40384400000001,38.252538],"type":"Point"}
}