{
  "type": "Feature",
  "properties": {
    "iso:country":"US",
    "sg:address":"1405 S Stewart Ave",
    "sg:city":"Sedalia",
    "sg:classifiers":[
        {
            "category":"Building & Trades",
            "subcategory":"Plumbing",
            "type":"Services"
        }
    ],
    "sg:phone":"+1 660 827 2746",
    "sg:postcode":"65301",
    "sg:province":"MO",
    "sg:tags":[
        "contractor"
    ],
    "wof:name":"Mathis & Sons Plumbing",
    "wof:placetype":"venue"
},
  "geometry": {"coordinates":[-93.240015,38.700224],"type":"Point"}
}