{
  "type": "Feature",
  "properties": {
    "iso:country":"US",
    "sg:address":"12187 Apple Rd",
    "sg:city":"Carthage",
    "sg:classifiers":[
        {
            "category":"Building & Trades",
            "subcategory":"Construction",
            "type":"Services"
        }
    ],
    "sg:phone":"+1 417 358 7553",
    "sg:postcode":"64836",
    "sg:province":"MO",
    "sg:tags":[
        "plastering",
        "drywall",
        "stucco",
        "contractor"
    ],
    "wof:name":"Lloyd Greenwood Plastering Co",
    "wof:placetype":"venue"
},
  "geometry": {"coordinates":[-94.27674399999999,37.067499],"type":"Point"}
}