{
  "type": "Feature",
  "properties": {
    "iso:country":"US",
    "sg:address":"500 E 9 St",
    "sg:city":"Kansas City",
    "sg:classifiers":[
        {
            "category":"Insurance",
            "subcategory":"Insurance Agent",
            "type":"Services"
        }
    ],
    "sg:phone":"+1 816 842 6300",
    "sg:postcode":"64106",
    "sg:province":"MO",
    "sg:website":"www.ozark-national.com",
    "wof:name":"Ozark National Life Ins Co",
    "wof:placetype":"venue"
},
  "geometry": {"coordinates":[-94.57607,39.103324],"type":"Point"}
}