{
  "type": "Feature",
  "properties": {
    "iso:country":"US",
    "sg:address":"12 Westbury Dr",
    "sg:city":"Saint Charles",
    "sg:classifiers":[
        {
            "category":"Health Services",
            "subcategory":"Doctor",
            "type":"Services"
        }
    ],
    "sg:phone":"+1 636 723 7333",
    "sg:postcode":"63301",
    "sg:province":"MO",
    "sg:tags":[
        "medical"
    ],
    "wof:name":"Richard E Cannon",
    "wof:placetype":"venue"
},
  "geometry": {"coordinates":[-90.517579,38.783632],"type":"Point"}
}