{
  "type": "Feature",
  "properties": {
    "iso:country":"US",
    "sg:address":"2939 Mayer Dr",
    "sg:city":"St Charles",
    "sg:classifiers":[
        {
            "category":"Social Services",
            "subcategory":"Job Training",
            "type":"Services"
        },
        {
            "category":"Social Services",
            "type":"Services"
        }
    ],
    "sg:phone":"+1 636 723 2828",
    "sg:postcode":"63301",
    "sg:province":"MO",
    "sg:tags":[
        "disabled",
        "developmentally"
    ],
    "wof:name":"Respite Care Home",
    "wof:placetype":"venue"
},
  "geometry": {"coordinates":[-90.51768,38.79277],"type":"Point"}
}