{
  "type": "Feature",
  "properties": {
    "iso:country":"US",
    "sg:address":"4343 N Chouteau Trfy",
    "sg:city":"Kansas City",
    "sg:classifiers":[
        {
            "category":"Banks & Credit Unions",
            "subcategory":"Bank",
            "type":"Services"
        }
    ],
    "sg:phone":"+1 816 455 0444",
    "sg:postcode":"64117",
    "sg:province":"MO",
    "sg:tags":[
        "personal",
        "institution"
    ],
    "wof:name":"Advance America",
    "wof:placetype":"venue"
},
  "geometry": {"coordinates":[-94.53361200000001,39.171445],"type":"Point"}
}