{
  "type": "Feature",
  "properties": {
    "iso:country":"US",
    "sg:address":"8507 Tally Ho Dr",
    "sg:city":"Hazelwood",
    "sg:classifiers":[
        {
            "category":"Real Estate",
            "subcategory":"Real Estate Operator",
            "type":"Services"
        }
    ],
    "sg:phone":"+1 314 524 6105",
    "sg:postcode":"63042",
    "sg:province":"MO",
    "sg:tags":[
        "building",
        "apartment"
    ],
    "wof:name":"Trotwood Downs Apartment",
    "wof:placetype":"venue"
},
  "geometry": {"coordinates":[-90.331806,38.773252],"type":"Point"}
}