{
  "type": "Feature",
  "properties": {
    "iso:country":"US",
    "sg:address":"131 E Walnut St",
    "sg:city":"Thayer",
    "sg:classifiers":[
        {
            "category":"Personal",
            "subcategory":"Beauty Salon",
            "type":"Services"
        }
    ],
    "sg:phone":"+1 417 264 3647",
    "sg:postcode":"65791",
    "sg:province":"MO",
    "sg:tags":[
        "hair",
        "stylist"
    ],
    "wof:name":"Unique Hair Designers",
    "wof:placetype":"venue"
},
  "geometry": {"coordinates":[-91.538521,36.523513],"type":"Point"}
}