{
  "type": "Feature",
  "properties": {
    "iso:country":"US",
    "sg:address":"334 N Sarah St",
    "sg:city":"Saint Louis",
    "sg:classifiers":[
        {
            "category":"Shopping",
            "subcategory":"Computers & Home Electronics",
            "type":"Retail Goods"
        }
    ],
    "sg:phone":"+1 314 652 8888",
    "sg:postcode":"63108",
    "sg:province":"MO",
    "wof:name":"National Rent To Own",
    "wof:placetype":"venue"
},
  "geometry": {"coordinates":[-90.245598,38.640202],"type":"Point"}
}