{
  "type": "Feature",
  "properties": {
    "iso:country":"US",
    "sg:address":"101 N 1st St",
    "sg:city":"Owensville",
    "sg:classifiers":[
        {
            "category":"Restaurant",
            "type":"Food & Drink"
        }
    ],
    "sg:phone":"+1 573 437 8464",
    "sg:postcode":"65066",
    "sg:province":"MO",
    "sg:tags":[
        "mexican"
    ],
    "wof:name":"Dos Primos Mexican Restaurant",
    "wof:placetype":"venue"
},
  "geometry": {"coordinates":[-91.500473,38.347092],"type":"Point"}
}