{
  "type": "Feature",
  "properties": {
    "iso:country":"US",
    "sg:address":"6400 Chippewa St",
    "sg:city":"Saint Louis",
    "sg:classifiers":[
        {
            "category":"Retail",
            "subcategory":"Veterinary Services",
            "type":"Services"
        }
    ],
    "sg:phone":"+1 314 351 4700",
    "sg:postcode":"63109",
    "sg:province":"MO",
    "sg:tags":[
        "veterinarian"
    ],
    "wof:name":"Jewell Animal Clinic",
    "wof:placetype":"venue"
},
  "geometry": {"coordinates":[-90.297997,38.593899],"type":"Point"}
}