{
  "type": "Feature",
  "properties": {
    "iso:country":"US",
    "sg:address":"1500 Continental Dr",
    "sg:city":"Wentzville",
    "sg:classifiers":[
        {
            "category":"Travel",
            "subcategory":"Hotels & Motels",
            "type":"Entertainment"
        }
    ],
    "sg:phone":"+1 636 327 5212",
    "sg:postcode":"63385",
    "sg:province":"MO",
    "wof:name":"Knights Inn",
    "wof:placetype":"venue"
},
  "geometry": {"coordinates":[-90.830051,38.806621],"type":"Point"}
}