{
  "type": "Feature",
  "properties": {
    "iso:country":"US",
    "sg:address":"19546 Golden Dr",
    "sg:city":"Raymondville",
    "sg:classifiers":[
        {
            "category":"Real Estate",
            "subcategory":"Real Estate Services",
            "type":"Services"
        },
        {
            "category":"Travel",
            "subcategory":"Resort",
            "type":"Entertainment"
        }
    ],
    "sg:phone":"+1 417 457 6222",
    "sg:postcode":"65555",
    "sg:province":"MO",
    "sg:tags":[
        "buyer",
        "broker"
    ],
    "wof:name":"Golden Hills Trail Rides & Resort",
    "wof:placetype":"venue"
},
  "geometry": {"coordinates":[-91.815956,37.323501],"type":"Point"}
}