{
  "type": "Feature",
  "properties": {
    "iso:country":"US",
    "sg:address":"430 Old Rte 66",
    "sg:city":"St Robert",
    "sg:classifiers":[
        {
            "category":"Personal",
            "subcategory":"Beauty Salon",
            "type":"Services"
        }
    ],
    "sg:phone":"+1 573 336 4454",
    "sg:postcode":"65584",
    "sg:province":"MO",
    "wof:name":"Linda's Hair Designs",
    "wof:placetype":"venue"
},
  "geometry": {"coordinates":[-92.20140000000001,37.828646],"type":"Point"}
}