{
  "type": "Feature",
  "properties": {
    "iso:country":"US",
    "sg:address":"1596 Green Valley Rd",
    "sg:city":"Clever",
    "sg:classifiers":[
        {
            "category":"Building & Trades",
            "subcategory":"Construction",
            "type":"Services"
        }
    ],
    "sg:phone":"+1 417 743 2120",
    "sg:postcode":"65631",
    "sg:province":"MO",
    "sg:tags":[
        "contracting",
        "general"
    ],
    "wof:name":"Area Wide Construction Inc",
    "wof:placetype":"venue"
},
  "geometry": {"coordinates":[-93.42455200000001,37.036957],"type":"Point"}
}