{
  "type": "Feature",
  "properties": {
    "iso:country":"US",
    "sg:address":"25 Hammes Dr",
    "sg:city":"Florissant",
    "sg:classifiers":[
        {
            "category":"Professional",
            "subcategory":"Business Services",
            "type":"Services"
        }
    ],
    "sg:phone":"+1 314 972 9727",
    "sg:postcode":"63031",
    "sg:province":"MO",
    "wof:name":"Rayburn Home Inspection Sv LLC",
    "wof:placetype":"venue"
},
  "geometry": {"coordinates":[-90.339035,38.804263],"type":"Point"}
}