{
  "type": "Feature",
  "properties": {
    "addr:full":"2103 E Franklin St Clinton MO 64735",
    "addr:housenumber":"2103",
    "addr:postcode":"64735",
    "addr:street":"E Franklin St",
    "iso:country":"US",
    "sg:address":"2103 E Franklin St",
    "sg:city":"Clinton",
    "sg:classifiers":[
        {
            "category":"Organizations",
            "subcategory":"Community Association",
            "type":"Services"
        }
    ],
    "sg:phone":"+1 660 885 3481",
    "sg:postcode":"64735",
    "sg:province":"MO",
    "sg:tags":[
        "fraternal"
    ],
    "wof:name":"Elks Lodge",
    "wof:placetype":"venue"
},
  "geometry": {"coordinates":[-93.744412,38.370126],"type":"Point"}
}