{
  "type": "Feature",
  "properties": {
    "iso:country":"US",
    "sg:address":"4101 Frederick Ave",
    "sg:city":"Saint Joseph",
    "sg:classifiers":[
        {
            "category":"Restaurant",
            "type":"Food & Drink"
        }
    ],
    "sg:menulink":"http://www.allmenus.com/mo/st-joseph/127862-red-lobster/menu/",
    "sg:phone":"+1 816 232 5011",
    "sg:postcode":"64506",
    "sg:province":"MO",
    "sg:tags":[
        "seafood",
        "american"
    ],
    "wof:name":"Red Lobster",
    "wof:placetype":"venue"
},
  "geometry": {"coordinates":[-94.79572899999999,39.777037],"type":"Point"}
}