{
  "type": "Feature",
  "properties": {
    "iso:country":"US",
    "sg:address":"209 Monroe St",
    "sg:city":"Brunswick",
    "sg:classifiers":[
        {
            "category":"Building & Trades",
            "subcategory":"Construction",
            "type":"Services"
        }
    ],
    "sg:phone":"+1 660 548 3553",
    "sg:postcode":"65236",
    "sg:province":"MO",
    "sg:tags":[
        "pipe",
        "line",
        "contractor"
    ],
    "wof:name":"Grand River Construction Inc",
    "wof:placetype":"venue"
},
  "geometry": {"coordinates":[-93.12689899999999,39.42209],"type":"Point"}
}