{
  "type": "Feature",
  "properties": {
    "iso:country":"US",
    "sg:address":"601 E 63rd St",
    "sg:city":"Kansas City",
    "sg:classifiers":[
        {
            "category":"Health Services",
            "subcategory":"Clinic",
            "type":"Services"
        }
    ],
    "sg:phone":"+1 816 444 4477",
    "sg:postcode":"64110",
    "sg:province":"MO",
    "sg:tags":[
        "specialty",
        "outpatient"
    ],
    "wof:name":"South Kans Cy Mntal Hlth Clnic",
    "wof:placetype":"venue"
},
  "geometry": {"coordinates":[-94.57918100000001,39.013448],"type":"Point"}
}