{
  "type": "Feature",
  "properties": {
    "iso:country":"US",
    "sg:address":"4872 Hammett Pl",
    "sg:city":"St Louis",
    "sg:classifiers":[
        {
            "category":"Personal",
            "subcategory":"Beauty Salon",
            "type":"Services"
        }
    ],
    "sg:phone":"+1 314 533 0011",
    "sg:postcode":"63113",
    "sg:province":"MO",
    "wof:name":"Profiles Hair & Nail Care",
    "wof:placetype":"venue"
},
  "geometry": {"coordinates":[-90.251642,38.66407],"type":"Point"}
}