{
  "type": "Feature",
  "properties": {
    "iso:country":"US",
    "sg:address":"313 E Osage St",
    "sg:city":"Pacific",
    "sg:classifiers":[
        {
            "category":"Shopping",
            "subcategory":"Shoes",
            "type":"Retail Goods"
        }
    ],
    "sg:phone":"+1 636 257 3985",
    "sg:postcode":"63069",
    "sg:province":"MO",
    "wof:name":"Meier Shoe",
    "wof:placetype":"venue"
},
  "geometry": {"coordinates":[-90.736931,38.484172],"type":"Point"}
}