{
  "type": "Feature",
  "properties": {
    "iso:country":"US",
    "sg:address":"220 W 43 St",
    "sg:city":"Kansas City",
    "sg:classifiers":[
        {
            "category":"Professional",
            "type":"Services"
        }
    ],
    "sg:phone":"+1 816 753 0307",
    "sg:postcode":"64111",
    "sg:province":"MO",
    "sg:tags":[
        "establishment"
    ],
    "wof:name":"Jordco",
    "wof:placetype":"venue"
},
  "geometry": {"coordinates":[-94.58853999999999,39.049451],"type":"Point"}
}