{
  "type": "Feature",
  "properties": {
    "iso:country":"US",
    "sg:address":"3146 Locust St",
    "sg:city":"Saint Louis",
    "sg:classifiers":[
        {
            "category":"Bars & Pubs",
            "subcategory":"Nightclub",
            "type":"Food & Drink"
        }
    ],
    "sg:phone":"+1 314 534 1500",
    "sg:postcode":"63103",
    "sg:province":"MO",
    "sg:tags":[
        "nightlife"
    ],
    "wof:name":"Exo Restaurant & Lounge",
    "wof:placetype":"venue"
},
  "geometry": {"coordinates":[-90.22434,38.636184],"type":"Point"}
}