{
  "type": "Feature",
  "properties": {
    "iso:country":"US",
    "sg:address":"8088 Watson Rd",
    "sg:city":"Saint Louis",
    "sg:classifiers":[
        {
            "category":"Retail",
            "subcategory":"Veterinary Services",
            "type":"Services"
        }
    ],
    "sg:phone":"+1 314 843 2394",
    "sg:postcode":"63119",
    "sg:province":"MO",
    "wof:name":"Yorkshire Animal Hospital",
    "wof:placetype":"venue"
},
  "geometry": {"coordinates":[-90.343129,38.56738],"type":"Point"}
}