{
  "type": "Feature",
  "properties": {
    "iso:country":"US",
    "sg:address":"3612 US Hwy 54",
    "sg:city":"Fulton",
    "sg:classifiers":[
        {
            "category":"Professional",
            "type":"Services"
        }
    ],
    "sg:phone":"+1 573 592 8670",
    "sg:postcode":"65251",
    "sg:province":"MO",
    "sg:tags":[
        "establishment"
    ],
    "wof:name":"Houf Farm",
    "wof:placetype":"venue"
},
  "geometry": {"coordinates":[-91.941828,38.920232],"type":"Point"}
}