{
  "type": "Feature",
  "properties": {
    "iso:country":"US",
    "sg:address":"106 S Folger St",
    "sg:city":"Carrollton",
    "sg:classifiers":[
        {
            "category":"Government",
            "subcategory":"Police Station",
            "type":"Public Place"
        }
    ],
    "sg:phone":"+1 660 542 2828",
    "sg:postcode":"64633",
    "sg:province":"MO",
    "sg:tags":[
        "sheriff"
    ],
    "wof:name":"Carroll County Sheriff",
    "wof:placetype":"venue"
},
  "geometry": {"coordinates":[-93.497011,39.357083],"type":"Point"}
}