{
  "type": "Feature",
  "properties": {
    "iso:country":"US",
    "sg:address":"1739 W Nottingham St",
    "sg:city":"Springfield",
    "sg:classifiers":[
        {
            "category":"Building & Trades",
            "subcategory":"Construction",
            "type":"Services"
        }
    ],
    "sg:phone":"+1 417 886 5024",
    "sg:postcode":"65810",
    "sg:province":"MO",
    "sg:tags":[
        "house"
    ],
    "wof:name":"Built By Brett Inc",
    "wof:placetype":"venue"
},
  "geometry": {"coordinates":[-93.316711,37.120222],"type":"Point"}
}