{
  "type": "Feature",
  "properties": {
    "iso:country":"US",
    "sg:address":"2801 State Hwy 291",
    "sg:city":"Harrisonville",
    "sg:classifiers":[
        {
            "category":"Banks & Credit Unions",
            "subcategory":"Bank",
            "type":"Services"
        }
    ],
    "sg:phone":"+1 816 887 5200",
    "sg:postcode":"64701",
    "sg:province":"MO",
    "sg:tags":[
        "depository",
        "banking"
    ],
    "wof:name":"Cash Advance Of Harrisonville",
    "wof:placetype":"venue"
},
  "geometry": {"coordinates":[-94.365281,38.677521],"type":"Point"}
}