{
  "type": "Feature",
  "properties": {
    "iso:country":"US",
    "sg:address":"21754 Shelton Rd",
    "sg:city":"Polo",
    "sg:classifiers":[
        {
            "category":"Insurance",
            "subcategory":"Hazard Insurance",
            "type":"Services"
        }
    ],
    "sg:phone":"+1 660 352 6256",
    "sg:postcode":"64671",
    "sg:province":"MO",
    "sg:tags":[
        "commercial",
        "business"
    ],
    "wof:name":"Mynatt Family Insurance",
    "wof:placetype":"venue"
},
  "geometry": {"coordinates":[-94.003544,39.482454],"type":"Point"}
}