{
  "type": "Feature",
  "properties": {
    "iso:country":"US",
    "sg:address":"153 E Main St",
    "sg:city":"Warsaw",
    "sg:classifiers":[
        {
            "category":"Retail",
            "subcategory":"Portrait Studio",
            "type":"Services"
        }
    ],
    "sg:phone":"+1 660 438 7400",
    "sg:postcode":"65355",
    "sg:province":"MO",
    "sg:tags":[
        "photographer"
    ],
    "wof:name":"Masterpiece Photography",
    "wof:placetype":"venue"
},
  "geometry": {"coordinates":[-93.38112599999999,38.241393],"type":"Point"}
}