{
  "type": "Feature",
  "properties": {
    "iso:country":"US",
    "sg:address":"2007 NE 65 St",
    "sg:city":"Kansas City",
    "sg:classifiers":[
        {
            "category":"Professional",
            "type":"Services"
        }
    ],
    "sg:phone":"+1 816 454 2966",
    "sg:postcode":"64118",
    "sg:province":"MO",
    "wof:name":"Geoffrey A Hood",
    "wof:placetype":"venue"
},
  "geometry": {"coordinates":[-94.554581,39.210336],"type":"Point"}
}