{
  "type": "Feature",
  "properties": {
    "iso:country":"US",
    "sg:address":"700 S Holden St",
    "sg:city":"Warrensburg",
    "sg:classifiers":[
        {
            "category":"Real Estate",
            "subcategory":"Real Estate Operator",
            "type":"Services"
        }
    ],
    "sg:phone":"+1 660 429 2248",
    "sg:postcode":"64093",
    "sg:province":"MO",
    "sg:tags":[
        "building",
        "apartment"
    ],
    "wof:name":"Dutches Haus Apartments",
    "wof:placetype":"venue"
},
  "geometry": {"coordinates":[-93.740781,38.755731],"type":"Point"}
}