{
  "type": "Feature",
  "properties": {
    "iso:country":"US",
    "sg:address":"2365 Hampton Ave",
    "sg:city":"St Louis",
    "sg:classifiers":[
        {
            "category":"Professional",
            "type":"Services"
        }
    ],
    "sg:phone":"+1 314 965 2554",
    "sg:postcode":"63139",
    "sg:province":"MO",
    "wof:name":"World Travel Svc",
    "wof:placetype":"venue"
},
  "geometry": {"coordinates":[-90.287954,38.613298],"type":"Point"}
}