{
  "type": "Feature",
  "properties": {
    "iso:country":"US",
    "sg:address":"3127 N State Hwy F",
    "sg:city":"Ash Grove",
    "sg:classifiers":[
        {
            "category":"Farming",
            "subcategory":"Livestock Farm",
            "type":"Manufacturing & Wholesale Goods"
        }
    ],
    "sg:phone":"+1 417 751 3862",
    "sg:postcode":"65604",
    "sg:province":"MO",
    "sg:tags":[
        "beef",
        "feedlot",
        "cattle"
    ],
    "wof:name":"Ben Coble",
    "wof:placetype":"venue"
},
  "geometry": {"coordinates":[-93.588379,37.258296],"type":"Point"}
}