{
  "type": "Feature",
  "properties": {
    "iso:country":"US",
    "sg:address":"56 Keyes School Rd",
    "sg:city":"Ulman",
    "sg:classifiers":[
        {
            "category":"Farming",
            "subcategory":"Farm",
            "type":"Manufacturing & Wholesale Goods"
        }
    ],
    "sg:phone":"+1 573 369 2627",
    "sg:postcode":"65083",
    "sg:province":"MO",
    "sg:tags":[
        "preparation",
        "tax",
        "return",
        "crop",
        "general"
    ],
    "wof:name":"Halderman Tax Svc Hlderman Frm",
    "wof:placetype":"venue"
},
  "geometry": {"coordinates":[-92.421589,38.158875],"type":"Point"}
}