{
  "type": "Feature",
  "properties": {
    "iso:country":"US",
    "sg:address":"19216 Saint Albans Forest Ln",
    "sg:city":"Glencoe",
    "sg:classifiers":[
        {
            "category":"Building & Trades",
            "subcategory":"Cleaning & Sanitation",
            "type":"Services"
        }
    ],
    "sg:phone":"+1 636 227 9986",
    "sg:postcode":"63038",
    "sg:province":"MO",
    "sg:tags":[
        "duct",
        "air"
    ],
    "wof:name":"Indoor Air Quality Solutions",
    "wof:placetype":"venue"
},
  "geometry": {"coordinates":[-90.724604,38.575838],"type":"Point"}
}