{
  "type": "Feature",
  "properties": {
    "iso:country":"US",
    "sg:address":"13732 Parker Ave",
    "sg:city":"Grandview",
    "sg:classifiers":[
        {
            "category":"Professional",
            "type":"Services"
        }
    ],
    "sg:phone":"+1 816 966 1507",
    "sg:postcode":"64030",
    "sg:province":"MO",
    "sg:tags":[
        "establishment"
    ],
    "wof:name":"C & K Fire",
    "wof:placetype":"venue"
},
  "geometry": {"coordinates":[-94.520448,38.874727],"type":"Point"}
}