{
  "type": "Feature",
  "properties": {
    "iso:country":"US",
    "sg:address":"7266 Manchester Rd",
    "sg:city":"St. Louis",
    "sg:classifiers":[
        {
            "category":"Restaurant",
            "type":"Food & Drink"
        }
    ],
    "sg:phone":"+1 314 644 1790",
    "sg:postcode":"63143",
    "sg:province":"MO",
    "sg:tags":[
        "italian"
    ],
    "wof:name":"Acero",
    "wof:placetype":"venue"
},
  "geometry": {"coordinates":[-90.315944,38.613323],"type":"Point"}
}