{
  "type": "Feature",
  "properties": {
    "iso:country":"US",
    "sg:address":"5481 E Saint Charles Rd",
    "sg:city":"Columbia",
    "sg:classifiers":[
        {
            "category":"Food & Beverages",
            "subcategory":"Groceries & Convenience Stores",
            "type":"Retail Goods"
        }
    ],
    "sg:phone":"+1 573 474 6652",
    "sg:postcode":"65201",
    "sg:province":"MO",
    "wof:name":"Lake Of Woods Little Gen Str",
    "wof:placetype":"venue"
},
  "geometry": {"coordinates":[-92.254001,38.958247],"type":"Point"}
}