{
  "type": "Feature",
  "properties": {
    "iso:country":"US",
    "sg:address":"2221 1st Capitol Dr",
    "sg:city":"Saint Charles",
    "sg:classifiers":[
        {
            "category":"Ice Cream",
            "type":"Food & Drink"
        }
    ],
    "sg:menulink":"http://www.allmenus.com/mo/frontier/92637-steak-n-shake/menu/",
    "sg:phone":"+1 636 724 3234",
    "sg:postcode":"63301",
    "sg:province":"MO",
    "sg:tags":[
        "american"
    ],
    "wof:name":"Steak 'n Shake",
    "wof:placetype":"venue"
},
  "geometry": {"coordinates":[-90.508087,38.780539],"type":"Point"}
}