{
  "type": "Feature",
  "properties": {
    "iso:country":"US",
    "sg:address":"2201 Washington Ave",
    "sg:city":"St Louis",
    "sg:classifiers":[
        {
            "category":"Professional",
            "type":"Services"
        }
    ],
    "sg:phone":"+1 314 241 1755",
    "sg:postcode":"63103",
    "sg:province":"MO",
    "sg:tags":[
        "establishment"
    ],
    "wof:name":"West Town Loft LLC",
    "wof:placetype":"venue"
},
  "geometry": {"coordinates":[-90.21214999999999,38.634973],"type":"Point"}
}