{
  "type": "Feature",
  "properties": {
    "iso:country":"US",
    "sg:address":"1040 Kathryn St",
    "sg:city":"Nixa",
    "sg:classifiers":[
        {
            "category":"Home & Garden",
            "subcategory":"Building Materials",
            "type":"Retail Goods"
        },
        {
            "category":"Building & Trades",
            "subcategory":"Construction",
            "type":"Services"
        }
    ],
    "sg:phone":"+1 417 725 7706",
    "sg:postcode":"65714",
    "sg:province":"MO",
    "sg:tags":[
        "insulation",
        "heat",
        "contractor"
    ],
    "wof:name":"Southwestern Insulation & Mtls",
    "wof:placetype":"venue"
},
  "geometry": {"coordinates":[-93.313626,37.060082],"type":"Point"}
}