{
  "type": "Feature",
  "properties": {
    "iso:country":"US",
    "sg:address":"5112 Country Club Dr",
    "sg:city":"High Ridge",
    "sg:classifiers":[
        {
            "category":"Professional",
            "type":"Services"
        }
    ],
    "sg:phone":"+1 636 677 9718",
    "sg:postcode":"63049",
    "sg:province":"MO",
    "wof:name":"Kendall Inc",
    "wof:placetype":"venue"
},
  "geometry": {"coordinates":[-90.50308,38.475329],"type":"Point"}
}