{
  "type": "Feature",
  "properties": {
    "addr:full":"809 State St Mound City MO 64470",
    "addr:housenumber":"809",
    "addr:postcode":"64470",
    "addr:street":"State St",
    "iso:country":"US",
    "sg:address":"809 State St",
    "sg:city":"Mound City",
    "sg:classifiers":[
        {
            "category":"Restaurant",
            "type":"Food & Drink"
        }
    ],
    "sg:menulink":"http://www.allmenus.com/mo/benton/194249-mcdonalds/menu/",
    "sg:postcode":"64470",
    "sg:province":"MO",
    "sg:tags":[
        "burger",
        "american"
    ],
    "wof:name":"McDonald's",
    "wof:placetype":"venue"
},
  "geometry": {"coordinates":[-95.233469,40.133092],"type":"Point"}
}