{
  "type": "Feature",
  "properties": {
    "iso:country":"US",
    "sg:address":"1111 Kathryn St",
    "sg:city":"Nixa",
    "sg:classifiers":[
        {
            "category":"Professional",
            "type":"Services"
        }
    ],
    "sg:phone":"+1 417 725 8707",
    "sg:postcode":"65714",
    "sg:province":"MO",
    "wof:name":"Ozark Mountain Classics LLC",
    "wof:placetype":"venue"
},
  "geometry": {"coordinates":[-93.31631299999999,37.060052],"type":"Point"}
}