{
  "type": "Feature",
  "properties": {
    "iso:country":"US",
    "sg:address":"2759 Kehrs Mill Rd",
    "sg:city":"Chesterfield",
    "sg:classifiers":[
        {
            "category":"Building & Trades",
            "subcategory":"Construction",
            "type":"Services"
        }
    ],
    "sg:phone":"+1 636 227 6080",
    "sg:postcode":"63017",
    "sg:province":"MO",
    "sg:tags":[
        "contractor"
    ],
    "wof:name":"Lydon Contracting LLC",
    "wof:placetype":"venue"
},
  "geometry": {"coordinates":[-90.570449,38.616994],"type":"Point"}
}