{
  "type": "Feature",
  "properties": {
    "iso:country":"US",
    "sg:address":"317 Westport Rd",
    "sg:city":"Kansas City",
    "sg:classifiers":[
        {
            "category":"Professional",
            "subcategory":"Business Services",
            "type":"Services"
        }
    ],
    "sg:phone":"+1 913 432 6200",
    "sg:postcode":"64111",
    "sg:province":"MO",
    "sg:tags":[
        "inventory"
    ],
    "wof:name":"Almack Ric-Ra Estate Sales",
    "wof:placetype":"venue"
},
  "geometry": {"coordinates":[-94.59007099999999,39.053451],"type":"Point"}
}