{
  "type": "Feature",
  "properties": {
    "iso:country":"US",
    "sg:address":"249 W Mill St",
    "sg:city":"Liberty",
    "sg:classifiers":[
        {
            "category":"Shopping",
            "subcategory":"Clothing, Apparel, & Fashions",
            "type":"Retail Goods"
        },
        {
            "category":"Shopping",
            "subcategory":"Thrift Store",
            "type":"Retail Goods"
        },
        {
            "category":"Shopping",
            "subcategory":"Used Merchandise",
            "type":"Retail Goods"
        }
    ],
    "sg:phone":"+1 816 407 1677",
    "sg:postcode":"64068",
    "sg:province":"MO",
    "sg:tags":[
        "shop",
        "clothing",
        "consignment",
        "resale"
    ],
    "wof:name":"Tattletale Trends",
    "wof:placetype":"venue"
},
  "geometry": {"coordinates":[-94.424443,39.24473],"type":"Point"}
}