{
  "type": "Feature",
  "properties": {
    "iso:country":"US",
    "sg:address":"12927 Gravois Rd",
    "sg:city":"Sappington",
    "sg:phone":"+1 314 842 4571",
    "sg:postcode":"63127",
    "sg:province":"MO",
    "sg:tags":[
        "equipment",
        "supply"
    ],
    "wof:name":"National Fabco Mfg Inc",
    "wof:placetype":"venue"
},
  "geometry": {"coordinates":[-90.41386300000001,38.51562],"type":"Point"}
}