{
  "type": "Feature",
  "properties": {
    "iso:country":"US",
    "sg:address":"605 Coeur Deville Dr",
    "sg:city":"Creve Coeur",
    "sg:classifiers":[
        {
            "category":"Social Services",
            "subcategory":"Adult Care",
            "type":"Services"
        }
    ],
    "sg:phone":"+1 314 542 2500",
    "sg:postcode":"63141",
    "sg:province":"MO",
    "sg:tags":[
        "home",
        "residential"
    ],
    "wof:name":"Parc Provence",
    "wof:placetype":"venue"
},
  "geometry": {"coordinates":[-90.451114,38.672518],"type":"Point"}
}