{
  "type": "Feature",
  "properties": {
    "iso:country":"US",
    "sg:address":"1309 N Walnut St",
    "sg:city":"Cameron",
    "sg:classifiers":[
        {
            "category":"Real Estate",
            "subcategory":"Real Estate Agent",
            "type":"Services"
        }
    ],
    "sg:phone":"+1 816 632 3721",
    "sg:postcode":"64429",
    "sg:province":"MO",
    "wof:name":"United Co Real /O'Connor Agcy",
    "wof:placetype":"venue"
},
  "geometry": {"coordinates":[-94.234911,39.74961],"type":"Point"}
}