{
  "type": "Feature",
  "properties": {
    "iso:country":"US",
    "sg:address":"1726 Paris Rd",
    "sg:city":"Columbia",
    "sg:classifiers":[
        {
            "category":"Retail",
            "subcategory":"Auto Repair",
            "type":"Services"
        }
    ],
    "sg:phone":"+1 573 443 2622",
    "sg:postcode":"65201",
    "sg:province":"MO",
    "sg:tags":[
        "body"
    ],
    "wof:name":"Cooks Repair",
    "wof:placetype":"venue"
},
  "geometry": {"coordinates":[-92.31171500000001,38.963487],"type":"Point"}
}