{
  "type": "Feature",
  "properties": {
    "iso:country":"US",
    "sg:address":"3001 S Westwood Blvd",
    "sg:city":"Poplar Bluff",
    "sg:classifiers":[
        {
            "category":"Autos & Motor Vehicles",
            "subcategory":"Boat Sales",
            "type":"Retail Goods"
        }
    ],
    "sg:phone":"+1 573 785 8298",
    "sg:postcode":"63901",
    "sg:province":"MO",
    "sg:tags":[
        "dealer",
        "sales"
    ],
    "wof:name":"Francis Enterprises Inc",
    "wof:placetype":"venue"
},
  "geometry": {"coordinates":[-90.432011,36.733699],"type":"Point"}
}