{
  "type": "Feature",
  "properties": {
    "iso:country":"US",
    "sg:address":"215 S Gex St",
    "sg:city":"La Plata",
    "sg:classifiers":[
        {
            "category":"Organizations",
            "subcategory":"Religious Organization",
            "type":"Services"
        }
    ],
    "sg:phone":"+1 660 332 7779",
    "sg:postcode":"63549",
    "sg:province":"MO",
    "sg:tags":[
        "church"
    ],
    "wof:name":"Faith Methodist Reformed Chr",
    "wof:placetype":"venue"
},
  "geometry": {"coordinates":[-92.49162699999999,40.022055],"type":"Point"}
}