{
  "type": "Feature",
  "properties": {
    "iso:country":"US",
    "sg:address":"474 S Main St",
    "sg:city":"Ironton",
    "sg:classifiers":[
        {
            "category":"Home & Garden",
            "subcategory":"Hardware",
            "type":"Retail Goods"
        },
        {
            "category":"Home & Garden",
            "subcategory":"Building Materials",
            "type":"Retail Goods"
        }
    ],
    "sg:phone":"+1 573 546 7424",
    "sg:postcode":"63650",
    "sg:province":"MO",
    "sg:tags":[
        "store"
    ],
    "wof:name":"Arcadia Valley Building Supply",
    "wof:placetype":"venue"
},
  "geometry": {"coordinates":[-90.628182,37.604592],"type":"Point"}
}