{
  "type": "Feature",
  "properties": {
    "iso:country":"US",
    "sg:address":"119 W Main St",
    "sg:city":"Fredericktown",
    "sg:classifiers":[
        {
            "category":"Banks & Credit Unions",
            "subcategory":"Bank",
            "type":"Services"
        }
    ],
    "sg:phone":"+1 573 783 3084",
    "sg:postcode":"63645",
    "sg:province":"MO",
    "sg:tags":[
        "cashing",
        "check"
    ],
    "wof:name":"Quik Cash",
    "wof:placetype":"venue"
},
  "geometry": {"coordinates":[-90.29452499999999,37.559629],"type":"Point"}
}