{
  "type": "Feature",
  "properties": {
    "iso:country":"US",
    "sg:address":"1331 Brush Creek Blvd",
    "sg:city":"Kansas City",
    "sg:classifiers":[
        {
            "category":"Retail",
            "subcategory":"Funeral Services",
            "type":"Services"
        }
    ],
    "sg:phone":"+1 816 561 0024",
    "sg:postcode":"64110",
    "sg:province":"MO",
    "sg:tags":[
        "plan"
    ],
    "sg:website":"www.dwnewcomers.com",
    "wof:name":"D W Newcomer's Sons",
    "wof:placetype":"venue"
},
  "geometry": {"coordinates":[-94.569901,39.043375],"type":"Point"}
}