{
  "type": "Feature",
  "properties": {
    "iso:country":"US",
    "sg:address":"300 SW 9th St",
    "sg:city":"Concordia",
    "sg:classifiers":[
        {
            "category":"Real Estate",
            "subcategory":"Real Estate Operator",
            "type":"Services"
        }
    ],
    "sg:phone":"+1 660 463 7820",
    "sg:postcode":"64020",
    "sg:province":"MO",
    "sg:tags":[
        "building",
        "apartment"
    ],
    "wof:name":"Concordia Estates",
    "wof:placetype":"venue"
},
  "geometry": {"coordinates":[-93.573629,38.980312],"type":"Point"}
}