{
  "type": "Feature",
  "properties": {
    "iso:country":"US",
    "sg:address":"1218 Big Bend Crossing Dr",
    "sg:city":"Valley Park",
    "sg:classifiers":[
        {
            "category":"Professional",
            "subcategory":"Business Services",
            "type":"Services"
        }
    ],
    "sg:phone":"+1 636 225 0488",
    "sg:postcode":"63088",
    "sg:province":"MO",
    "sg:tags":[
        "consultant",
        "contractor",
        "design",
        "interior",
        "trade",
        "decorator"
    ],
    "wof:name":"Gallo's Touch Interiors",
    "wof:placetype":"venue"
},
  "geometry": {"coordinates":[-90.487914,38.566892],"type":"Point"}
}