{
  "type": "Feature",
  "properties": {
    "iso:country":"US",
    "sg:address":"700 Blue Ridge Ext",
    "sg:city":"Grandview",
    "sg:classifiers":[
        {
            "category":"Building & Trades",
            "subcategory":"Construction",
            "type":"Services"
        }
    ],
    "sg:phone":"+1 816 331 6053",
    "sg:postcode":"64030",
    "sg:province":"MO",
    "sg:tags":[
        "repair",
        "system",
        "specialty",
        "heating",
        "contractor",
        "air conditioning"
    ],
    "wof:name":"Aire Serv",
    "wof:placetype":"venue"
},
  "geometry": {"coordinates":[-94.536376,38.898516],"type":"Point"}
}