{
  "type": "Feature",
  "properties": {
    "iso:country":"US",
    "sg:address":"204 SW 11 St",
    "sg:city":"Blue Springs",
    "sg:classifiers":[
        {
            "category":"Shopping",
            "subcategory":"Used Merchandise",
            "type":"Retail Goods"
        }
    ],
    "sg:phone":"+1 816 224 3799",
    "sg:postcode":"64015",
    "sg:province":"MO",
    "sg:tags":[
        "shop",
        "consignment"
    ],
    "wof:name":"Signature Consignment",
    "wof:placetype":"venue"
},
  "geometry": {"coordinates":[-94.277807,39.017131],"type":"Point"}
}