{
  "type": "Feature",
  "properties": {
    "iso:country":"US",
    "sg:address":"2299 Technology Dr",
    "sg:city":"O Fallon",
    "sg:classifiers":[
        {
            "category":"Professional",
            "subcategory":"Management & Consulting",
            "type":"Services"
        }
    ],
    "sg:phone":"+1 636 561 4950",
    "sg:postcode":"63368",
    "sg:province":"MO",
    "sg:tags":[
        "consultant",
        "resource",
        "human"
    ],
    "sg:website":"www.gpg-inc.net",
    "wof:name":"Griffin Personnel Group",
    "wof:placetype":"venue"
},
  "geometry": {"coordinates":[-90.79092,38.783539],"type":"Point"}
}