{
  "type": "Feature",
  "properties": {
    "iso:country":"US",
    "sg:address":"16425 Village Plaza View Dr",
    "sg:city":"Ballwin",
    "sg:classifiers":[
        {
            "category":"Retail",
            "subcategory":"Animal Services",
            "type":"Services"
        }
    ],
    "sg:phone":"+1 636 273 4440",
    "sg:postcode":"63011",
    "sg:province":"MO",
    "sg:tags":[
        "pet",
        "grooming",
        "washing"
    ],
    "wof:name":"Pet Clips By Kathy",
    "wof:placetype":"venue"
},
  "geometry": {"coordinates":[-90.61742599999999,38.583182],"type":"Point"}
}