{
  "type": "Feature",
  "properties": {
    "iso:country":"US",
    "sg:address":"313 Macon St",
    "sg:city":"Meadville",
    "sg:classifiers":[
        {
            "category":"Retail",
            "subcategory":"Auto Repair",
            "type":"Services"
        }
    ],
    "sg:phone":"+1 660 938 4411",
    "sg:postcode":"64659",
    "sg:province":"MO",
    "sg:tags":[
        "repairing",
        "automobile"
    ],
    "wof:name":"Sutton Garage",
    "wof:placetype":"venue"
},
  "geometry": {"coordinates":[-93.30206699999999,39.788171],"type":"Point"}
}