{
  "type": "Feature",
  "properties": {
    "iso:country":"US",
    "sg:address":"204 Peach Way Ste H",
    "sg:city":"Columbia",
    "sg:classifiers":[
        {
            "category":"Professional",
            "subcategory":"Management & Consulting",
            "type":"Services"
        },
        {
            "category":"Professional",
            "subcategory":"Advertising",
            "type":"Services"
        },
        {
            "category":"Professional",
            "subcategory":"Business Services",
            "type":"Services"
        },
        {
            "category":"Professional",
            "subcategory":"Art Services",
            "type":"Services"
        }
    ],
    "sg:phone":"+1 573 449 8567",
    "sg:postcode":"65203",
    "sg:province":"MO",
    "sg:tags":[
        "graphic",
        "coach",
        "marketing",
        "agency",
        "specialty",
        "designer",
        "program",
        "relation",
        "consultant",
        "counselor",
        "public"
    ],
    "wof:name":"Visionworks Marketing & Comms",
    "wof:placetype":"venue"
},
  "geometry": {"coordinates":[-92.336711,38.905256],"type":"Point"}
}