{
  "type": "Feature",
  "properties": {
    "iso:country":"US",
    "sg:address":"4840 Arevalo Dr",
    "sg:city":"Saint Louis",
    "sg:classifiers":[
        {
            "category":"Organizations",
            "subcategory":"Membership Organization",
            "type":"Services"
        }
    ],
    "sg:phone":"+1 314 892 1687",
    "sg:postcode":"63128",
    "sg:province":"MO",
    "wof:name":"Rose of Life Inc",
    "wof:placetype":"venue"
},
  "geometry": {"coordinates":[-90.37597700000001,38.49147],"type":"Point"}
}