{
  "type": "Feature",
  "properties": {
    "iso:country":"US",
    "sg:address":"2104 Tenbrook Rd",
    "sg:city":"Arnold",
    "sg:classifiers":[
        {
            "category":"Personal",
            "subcategory":"Beauty Salon",
            "type":"Services"
        }
    ],
    "sg:phone":"+1 636 296 4900",
    "sg:postcode":"63010",
    "sg:province":"MO",
    "wof:name":"Hair I AM",
    "wof:placetype":"venue"
},
  "geometry": {"coordinates":[-90.369106,38.448543],"type":"Point"}
}