{
  "type": "Feature",
  "properties": {
    "iso:country":"US",
    "sg:address":"1153 State Highway F",
    "sg:city":"Cardwell",
    "sg:classifiers":[
        {
            "category":"Manufacturing",
            "subcategory":"Textiles",
            "type":"Manufacturing & Wholesale Goods"
        }
    ],
    "sg:phone":"+1 573 654 3909",
    "sg:postcode":"63829",
    "sg:province":"MO",
    "sg:tags":[
        "broker",
        "cotton"
    ],
    "wof:name":"Brent Marret",
    "wof:placetype":"venue"
},
  "geometry": {"coordinates":[-90.32614700000001,36.017307],"type":"Point"}
}