{
  "type": "Feature",
  "properties": {
    "iso:country":"US",
    "sg:address":"7108 N Oak Fwy",
    "sg:city":"Kansas City",
    "sg:classifiers":[
        {
            "category":"Restaurant",
            "type":"Food & Drink"
        }
    ],
    "sg:phone":"+1 816 468 0044",
    "sg:postcode":"64118",
    "sg:province":"MO",
    "wof:name":"L C Hamburgers Etc",
    "wof:placetype":"venue"
},
  "geometry": {"coordinates":[-94.576161,39.22261],"type":"Point"}
}