{
  "type": "Feature",
  "properties": {
    "iso:country":"US",
    "sg:address":"23489 Haygood Rd",
    "sg:city":"Higginsville",
    "sg:phone":"+1 660 584 3894",
    "sg:postcode":"64037",
    "sg:province":"MO",
    "sg:tags":[
        "farm",
        "corn",
        "soybean"
    ],
    "wof:name":"Soendker Farm",
    "wof:placetype":"venue"
},
  "geometry": {"coordinates":[-93.671982,39.043215],"type":"Point"}
}