{
  "type": "Feature",
  "properties": {
    "iso:country":"US",
    "sg:address":"2 Jacklynn Ct",
    "sg:city":"Saint Louis",
    "sg:classifiers":[
        {
            "category":"Real Estate",
            "subcategory":"Real Estate Operator",
            "type":"Services"
        }
    ],
    "sg:phone":"+1 314 991 4440",
    "sg:postcode":"63132",
    "sg:province":"MO",
    "sg:tags":[
        "building",
        "apartment",
        "commercial",
        "family"
    ],
    "wof:name":"OK Ventures",
    "wof:placetype":"venue"
},
  "geometry": {"coordinates":[-90.3806,38.665776],"type":"Point"}
}