{
  "type": "Feature",
  "properties": {
    "addr:full":"200 S East St California MO 65018",
    "addr:housenumber":"200",
    "addr:postcode":"65018",
    "addr:street":"S East St",
    "iso:country":"US",
    "sg:address":"200 S East St",
    "sg:city":"California",
    "sg:classifiers":[
        {
            "category":"Organizations",
            "subcategory":"Professional Association",
            "type":"Services"
        }
    ],
    "sg:phone":"+1 573 796 4502",
    "sg:postcode":"65018",
    "sg:province":"MO",
    "wof:name":"Masonic Lodge",
    "wof:placetype":"venue"
},
  "geometry": {"coordinates":[-92.56450100000001,38.632221],"type":"Point"}
}