{
  "type": "Feature",
  "properties": {
    "iso:country":"US",
    "sg:address":"9109 Nemo Dr",
    "sg:city":"Saint Louis",
    "sg:classifiers":[
        {
            "category":"Bars & Pubs",
            "type":"Food & Drink"
        }
    ],
    "sg:phone":"+1 314 631 9309",
    "sg:postcode":"63123",
    "sg:province":"MO",
    "sg:tags":[
        "drinking"
    ],
    "wof:name":"Saint Andrews Restaurant & Pub",
    "wof:placetype":"venue"
},
  "geometry": {"coordinates":[-90.31777,38.542037],"type":"Point"}
}