{
  "type": "Feature",
  "properties": {
    "iso:country":"US",
    "sg:address":"101 E Scioto St",
    "sg:city":"St James",
    "sg:classifiers":[
        {
            "category":"Education",
            "subcategory":"School",
            "type":"Public Place"
        }
    ],
    "sg:phone":"+1 573 265 5818",
    "sg:postcode":"65559",
    "sg:province":"MO",
    "wof:name":"A Plus Office",
    "wof:placetype":"venue"
},
  "geometry": {"coordinates":[-91.611648,37.99603],"type":"Point"}
}