{
  "type": "Feature",
  "properties": {
    "iso:country":"US",
    "sg:address":"215 W Main St",
    "sg:city":"Malden",
    "sg:classifiers":[
        {
            "category":"Retail",
            "subcategory":"Auto Repair",
            "type":"Services"
        }
    ],
    "sg:phone":"+1 573 276 4209",
    "sg:postcode":"63863",
    "sg:province":"MO",
    "sg:tags":[
        "repairing",
        "automobile"
    ],
    "wof:name":"Main Street Auto Svc",
    "wof:placetype":"venue"
},
  "geometry": {"coordinates":[-89.58444299999999,36.759043],"type":"Point"}
}