{
  "type": "Feature",
  "properties": {
    "iso:country":"US",
    "sg:address":"23 Lacey Oak Ct",
    "sg:city":"Troy",
    "sg:classifiers":[
        {
            "category":"Building & Trades",
            "subcategory":"Landscaping Services",
            "type":"Services"
        }
    ],
    "sg:phone":"+1 314 565 3688",
    "sg:postcode":"63379",
    "sg:province":"MO",
    "sg:tags":[
        "lawn"
    ],
    "wof:name":"Pleasant Landscaping",
    "wof:placetype":"venue"
},
  "geometry": {"coordinates":[-91.089831,38.947355],"type":"Point"}
}