{
  "type": "Feature",
  "properties": {
    "iso:country":"US",
    "sg:address":"3877 S State Hwy J",
    "sg:city":"Springfield",
    "sg:classifiers":[
        {
            "category":"Organizations",
            "subcategory":"Religious Organization",
            "type":"Services"
        }
    ],
    "sg:phone":"+1 417 882 3133",
    "sg:postcode":"65809",
    "sg:province":"MO",
    "wof:name":"Kinser Chpl Ch (ch of God Hln)",
    "wof:placetype":"venue"
},
  "geometry": {"coordinates":[-93.19022,37.146893],"type":"Point"}
}