{
  "type": "Feature",
  "properties": {
    "addr:full":"201 W Capitol Ave Jefferson City MO 65101",
    "addr:housenumber":"201",
    "addr:postcode":"65101",
    "addr:street":"W Capitol Ave",
    "iso:country":"US",
    "sg:address":"201 W Capitol Ave",
    "sg:city":"Jefferson City",
    "sg:classifiers":[
        {
            "category":"Government",
            "subcategory":"Office",
            "type":"Public Place"
        }
    ],
    "sg:phone":"+1 573 751 4223",
    "sg:postcode":"65101",
    "sg:province":"MO",
    "sg:tags":[
        "legislative",
        "research"
    ],
    "wof:name":"Legislative Research",
    "wof:placetype":"venue"
},
  "geometry": {"coordinates":[-92.17397699999999,38.579969],"type":"Point"}
}