{
  "type": "Feature",
  "properties": {
    "iso:country":"US",
    "sg:address":"42 W Hwy N",
    "sg:city":"Wentzville",
    "sg:classifiers":[
        {
            "category":"Autos & Motor Vehicles",
            "subcategory":"Fuel & Gas Station",
            "type":"Retail Goods"
        }
    ],
    "sg:phone":"+1 636 332 6829",
    "sg:postcode":"63385",
    "sg:province":"MO",
    "sg:tags":[
        "station",
        "gasoline"
    ],
    "wof:name":"Mobil",
    "wof:placetype":"venue"
},
  "geometry": {"coordinates":[-90.864664,38.773986],"type":"Point"}
}