{
  "type": "Feature",
  "properties": {
    "iso:country":"US",
    "sg:address":"5370 Pershing Ave Apt 717",
    "sg:city":"Saint Louis",
    "sg:classifiers":[
        {
            "category":"Professional",
            "subcategory":"Lawyer & Legal Services",
            "type":"Services"
        }
    ],
    "sg:phone":"+1 314 361 4222",
    "sg:postcode":"63112",
    "sg:province":"MO",
    "sg:tags":[
        "notary"
    ],
    "wof:name":"Anytime Anywhere Notary Public",
    "wof:placetype":"venue"
},
  "geometry": {"coordinates":[-90.27724600000001,38.647869],"type":"Point"}
}