{
  "type": "Feature",
  "properties": {
    "iso:country":"US",
    "sg:address":"903 W Broadway St",
    "sg:city":"West Plains",
    "sg:classifiers":[
        {
            "category":"Personal",
            "subcategory":"Beauty Salon",
            "type":"Services"
        }
    ],
    "sg:phone":"+1 417 257 7979",
    "sg:postcode":"65775",
    "sg:province":"MO",
    "sg:tags":[
        "shop"
    ],
    "wof:name":"Sophisticuts",
    "wof:placetype":"venue"
},
  "geometry": {"coordinates":[-91.86127399999999,36.731397],"type":"Point"}
}