{
  "type": "Feature",
  "properties": {
    "iso:country":"US",
    "sg:address":"1701 US Hwy 40",
    "sg:city":"Blue Springs",
    "sg:classifiers":[
        {
            "category":"Building & Trades",
            "subcategory":"Construction",
            "type":"Services"
        }
    ],
    "sg:phone":"+1 816 229 3365",
    "sg:postcode":"64015",
    "sg:province":"MO",
    "sg:tags":[
        "home",
        "builder"
    ],
    "wof:name":"Graham Construction",
    "wof:placetype":"venue"
},
  "geometry": {"coordinates":[-94.28361200000001,39.009649],"type":"Point"}
}