{
  "type": "Feature",
  "properties": {
    "iso:country":"US",
    "sg:address":"28425 Spring Rd",
    "sg:city":"Richland",
    "sg:classifiers":[
        {
            "category":"Travel",
            "subcategory":"Campground",
            "type":"Entertainment"
        }
    ],
    "sg:phone":"+1 573 765 3044",
    "sg:postcode":"65556",
    "sg:province":"MO",
    "sg:website":"www.canoemissouri.com",
    "wof:name":"Gasconade Hills Camp & Float",
    "wof:placetype":"venue"
},
  "geometry": {"coordinates":[-92.394852,37.7511],"type":"Point"}
}