{
  "type": "Feature",
  "properties": {
    "iso:country":"US",
    "sg:address":"409 NE Moreland Dr",
    "sg:city":"Kansas City",
    "sg:classifiers":[
        {
            "category":"Professional",
            "subcategory":"Management & Consulting",
            "type":"Services"
        }
    ],
    "sg:phone":"+1 816 455 3432",
    "sg:postcode":"64118",
    "sg:province":"MO",
    "sg:tags":[
        "personnel",
        "consultant"
    ],
    "wof:name":"Exceptional Health Care Stffng",
    "wof:placetype":"venue"
},
  "geometry": {"coordinates":[-94.57465000000001,39.20367],"type":"Point"}
}