{
  "type": "Feature",
  "properties": {
    "iso:country":"US",
    "sg:address":"18118 Chesterfield Airport Rd",
    "sg:city":"Chesterfield",
    "sg:classifiers":[
        {
            "category":"Building & Trades",
            "subcategory":"Pest Control",
            "type":"Services"
        }
    ],
    "sg:phone":"+1 314 469 6966",
    "sg:postcode":"63005",
    "sg:province":"MO",
    "sg:tags":[
        "exterminating"
    ],
    "sg:website":"www.stopke.com",
    "wof:name":"Stopke Pest Control Inc",
    "wof:placetype":"venue"
},
  "geometry": {"coordinates":[-90.640017,38.669822],"type":"Point"}
}