{
  "type": "Feature",
  "properties": {
    "iso:country":"US",
    "sg:address":"21042 State Hwy J",
    "sg:city":"Granby",
    "sg:classifiers":[
        {
            "category":"Shopping",
            "subcategory":"Gifts & Souvenirs",
            "type":"Retail Goods"
        }
    ],
    "sg:phone":"+1 417 325 4401",
    "sg:postcode":"64844",
    "sg:province":"MO",
    "sg:tags":[
        "fragrant",
        "oil",
        "perfumed"
    ],
    "wof:name":"Scenacous Scents",
    "wof:placetype":"venue"
},
  "geometry": {"coordinates":[-94.260409,36.994794],"type":"Point"}
}