{
  "type": "Feature",
  "properties": {
    "iso:country":"US",
    "sg:address":"5360 S Campbell Ave",
    "sg:city":"Springfield",
    "sg:classifiers":[
        {
            "category":"Restaurant",
            "type":"Food & Drink"
        }
    ],
    "sg:phone":"+1 417 883 5305",
    "sg:postcode":"65810",
    "sg:province":"MO",
    "sg:tags":[
        "mexican"
    ],
    "wof:name":"Purple Burrito",
    "wof:placetype":"venue"
},
  "geometry": {"coordinates":[-93.296305,37.116427],"type":"Point"}
}