{
  "type": "Feature",
  "properties": {
    "iso:country":"US",
    "sg:address":"910 W Oaks Dr",
    "sg:city":"Ashland",
    "sg:classifiers":[
        {
            "category":"Building & Trades",
            "subcategory":"Construction",
            "type":"Services"
        }
    ],
    "sg:phone":"+1 573 268 7899",
    "sg:postcode":"65010",
    "sg:province":"MO",
    "sg:tags":[
        "management"
    ],
    "wof:name":"Ricky Mckee",
    "wof:placetype":"venue"
},
  "geometry": {"coordinates":[-92.274612,38.777136],"type":"Point"}
}