{
  "type": "Feature",
  "properties": {
    "iso:country":"US",
    "sg:address":"9940 Raccoon Rd",
    "sg:city":"Granby",
    "sg:classifiers":[
        {
            "category":"Autos & Motor Vehicles",
            "subcategory":"Automobile Sales",
            "type":"Retail Goods"
        }
    ],
    "sg:phone":"+1 417 472 3547",
    "sg:postcode":"64844",
    "sg:province":"MO",
    "sg:tags":[
        "replica",
        "designed"
    ],
    "wof:name":"B & B Manufacturing",
    "wof:placetype":"venue"
},
  "geometry": {"coordinates":[-94.226676,36.921732],"type":"Point"}
}