{
  "type": "Feature",
  "properties": {
    "iso:country":"US",
    "sg:address":"PO Box 11986",
    "sg:city":"Saint Louis",
    "sg:classifiers":[
        {
            "category":"Organizations",
            "subcategory":"Religious Organization",
            "type":"Services"
        }
    ],
    "sg:phone":"+1 314 385 8900",
    "sg:postcode":"63112",
    "sg:province":"MO",
    "wof:name":"St Paul AME Church",
    "wof:placetype":"venue"
},
  "geometry": {"coordinates":[-90.286697,38.660999],"type":"Point"}
}