{
  "type": "Feature",
  "properties": {
    "iso:country":"US",
    "sg:address":"3019 NE Winn Rd",
    "sg:city":"Kansas City",
    "sg:classifiers":[
        {
            "category":"Building & Trades",
            "subcategory":"Landscaping Services",
            "type":"Services"
        }
    ],
    "sg:phone":"+1 816 452 2010",
    "sg:postcode":"64117",
    "sg:province":"MO",
    "sg:tags":[
        "landscape",
        "contractor"
    ],
    "wof:name":"General Hauling",
    "wof:placetype":"venue"
},
  "geometry": {"coordinates":[-94.54514399999999,39.159426],"type":"Point"}
}