{
  "type": "Feature",
  "properties": {
    "addr:full":"2601 NE 78 St Kansas City MO 64119",
    "addr:housenumber":"2601;78",
    "addr:postcode":"64119",
    "addr:street":"Ne;St",
    "iso:country":"US",
    "sg:address":"2601 NE 78 St",
    "sg:city":"Kansas City",
    "sg:classifiers":[
        {
            "category":"Insurance",
            "subcategory":"Insurance Agent",
            "type":"Services"
        }
    ],
    "sg:phone":"+1 816 436 4258",
    "sg:postcode":"64119",
    "sg:province":"MO",
    "wof:name":"Thrivent Financial-Lutherans",
    "wof:placetype":"venue"
},
  "geometry": {"coordinates":[-94.55006899999999,39.234165],"type":"Point"}
}