{
  "type": "Feature",
  "properties": {
    "iso:country":"US",
    "sg:address":"1341 W Battlefield Rd",
    "sg:city":"Springfield",
    "sg:classifiers":[
        {
            "category":"Utilities",
            "subcategory":"Telephone",
            "type":"Services"
        }
    ],
    "sg:phone":"+1 417 882 0120",
    "sg:postcode":"65807",
    "sg:province":"MO",
    "sg:tags":[
        "communication",
        "datum"
    ],
    "sg:website":"www.datatrade.com",
    "wof:name":"Datatrade Inc",
    "wof:placetype":"venue"
},
  "geometry": {"coordinates":[-93.310805,37.160232],"type":"Point"}
}