{
  "type": "Feature",
  "properties": {
    "iso:country":"US",
    "sg:address":"109 S Main St",
    "sg:city":"Poplar Bluff",
    "sg:classifiers":[
        {
            "category":"Insurance",
            "subcategory":"Insurance Agent",
            "type":"Services"
        }
    ],
    "sg:phone":"+1 573 785 7591",
    "sg:postcode":"63901",
    "sg:province":"MO",
    "wof:name":"Huff & Assoc Insurance",
    "wof:placetype":"venue"
},
  "geometry": {"coordinates":[-90.393072,36.756181],"type":"Point"}
}