{
  "type": "Feature",
  "properties": {
    "iso:country":"US",
    "sg:address":"4814 Parker Rd",
    "sg:city":"Florissant",
    "sg:classifiers":[
        {
            "category":"Restaurant",
            "type":"Food & Drink"
        }
    ],
    "sg:phone":"+1 314 355 3242",
    "sg:postcode":"63033",
    "sg:province":"MO",
    "wof:name":"Angelo's Pizzeria",
    "wof:placetype":"venue"
},
  "geometry": {"coordinates":[-90.26655100000001,38.793325],"type":"Point"}
}