{
  "type": "Feature",
  "properties": {
    "iso:country":"US",
    "sg:address":"1700 W College St",
    "sg:city":"Springfield",
    "sg:classifiers":[
        {
            "category":"Personal",
            "subcategory":"Beauty Salon",
            "type":"Services"
        }
    ],
    "sg:phone":"+1 417 866 5136",
    "sg:postcode":"65806",
    "sg:province":"MO",
    "wof:name":"Cindy's Family Hair Fashions",
    "wof:placetype":"venue"
},
  "geometry": {"coordinates":[-93.315026,37.208542],"type":"Point"}
}