{
  "type": "Feature",
  "properties": {
    "addr:full":"3545 Lafayette Ave Saint Louis MO 63104",
    "addr:housenumber":"3545",
    "addr:postcode":"63104",
    "addr:street":"Lafayette Ave",
    "iso:country":"US",
    "sg:address":"3545 Lafayette Ave",
    "sg:city":"Saint Louis",
    "sg:classifiers":[
        {
            "category":"Professional",
            "subcategory":"Management & Consulting",
            "type":"Services"
        }
    ],
    "sg:phone":"+1 314 977 2827",
    "sg:postcode":"63104",
    "sg:province":"MO",
    "sg:tags":[
        "retail",
        "direct",
        "sales"
    ],
    "wof:name":"Chartwells",
    "wof:placetype":"venue"
},
  "geometry": {"coordinates":[-90.23830100000001,38.616969],"type":"Point"}
}