{
  "type": "Feature",
  "properties": {
    "iso:country":"US",
    "sg:address":"1415 S Farm Rd 65",
    "sg:city":"Springfield",
    "sg:classifiers":[
        {
            "category":"Professional",
            "subcategory":"Business Services",
            "type":"Services"
        }
    ],
    "sg:phone":"+1 417 882 2334",
    "sg:postcode":"65802",
    "sg:province":"MO",
    "wof:name":"No American Property Auctions",
    "wof:placetype":"venue"
},
  "geometry": {"coordinates":[-93.50948699999999,37.192309],"type":"Point"}
}