{
  "type": "Feature",
  "properties": {
    "iso:country":"US",
    "sg:address":"1253 Mule Barn Dr",
    "sg:city":"Cape Fair",
    "sg:classifiers":[
        {
            "category":"Real Estate",
            "subcategory":"Developer",
            "type":"Services"
        }
    ],
    "sg:phone":"+1 417 538 4306",
    "sg:postcode":"65624",
    "sg:province":"MO",
    "sg:website":"www.edgewatervillage.com",
    "wof:name":"Edge Water Village",
    "wof:placetype":"venue"
},
  "geometry": {"coordinates":[-93.476814,36.725771],"type":"Point"}
}