{
  "type": "Feature",
  "properties": {
    "iso:country":"US",
    "sg:address":"1301 Mullanphy St",
    "sg:city":"St Louis",
    "sg:classifiers":[
        {
            "category":"Retail",
            "subcategory":"Auto Repair",
            "type":"Services"
        }
    ],
    "sg:phone":"+1 314 621 8087",
    "sg:postcode":"63106",
    "sg:province":"MO",
    "sg:tags":[
        "repairing",
        "automobile"
    ],
    "wof:name":"Seventh Street Svc",
    "wof:placetype":"venue"
},
  "geometry": {"coordinates":[-90.19414399999999,38.642573],"type":"Point"}
}