{
  "type": "Feature",
  "properties": {
    "iso:country":"US",
    "sg:address":"249 Old Meramec Station Rd",
    "sg:city":"Ballwin",
    "sg:classifiers":[
        {
            "category":"Shopping",
            "subcategory":"Party Supplies",
            "type":"Retail Goods"
        },
        {
            "category":"Building & Trades",
            "subcategory":"Equipment Rental",
            "type":"Services"
        },
        {
            "category":"Personal",
            "type":"Services"
        }
    ],
    "sg:phone":"+1 314 606 5114",
    "sg:postcode":"63021",
    "sg:province":"MO",
    "sg:tags":[
        "favors",
        "chair",
        "planning",
        "tents-rental",
        "event"
    ],
    "sg:website":"http://www.leahypartyrentals.com",
    "wof:name":"Leahy Party Rentals",
    "wof:placetype":"venue"
},
  "geometry": {"coordinates":[-90.511809,38.58998],"type":"Point"}
}