{
  "type": "Feature",
  "properties": {
    "iso:country":"US",
    "sg:address":"164 Cricket Ln",
    "sg:city":"Rogersville",
    "sg:classifiers":[
        {
            "category":"Professional",
            "subcategory":"Business Services",
            "type":"Services"
        }
    ],
    "sg:phone":"+1 417 753 9446",
    "sg:postcode":"65742",
    "sg:province":"MO",
    "sg:tags":[
        "consultant",
        "coach"
    ],
    "wof:name":"Jm Outdoor Consulting Inc",
    "wof:placetype":"venue"
},
  "geometry": {"coordinates":[-93.064072,37.066208],"type":"Point"}
}