{
  "type": "Feature",
  "properties": {
    "iso:country":"US",
    "sg:address":"112 W 5th St",
    "sg:city":"Mound City",
    "sg:classifiers":[
        {
            "category":"Home & Garden",
            "subcategory":"Furniture",
            "type":"Retail Goods"
        },
        {
            "category":"Building & Trades",
            "subcategory":"Construction",
            "type":"Services"
        }
    ],
    "sg:phone":"+1 660 442 5509",
    "sg:postcode":"64470",
    "sg:province":"MO",
    "sg:tags":[
        "custom",
        "builder",
        "carpentry",
        "contractor"
    ],
    "wof:name":"Nowling Custom Cabinet Shop",
    "wof:placetype":"venue"
},
  "geometry": {"coordinates":[-95.232225,40.130496],"type":"Point"}
}