{
  "type": "Feature",
  "properties": {
    "iso:country":"US",
    "sg:address":"1355 E Bradford Pkwy",
    "sg:city":"Springfield",
    "sg:classifiers":[
        {
            "category":"Professional",
            "subcategory":"Management & Consulting",
            "type":"Services"
        }
    ],
    "sg:phone":"+1 417 881 9855",
    "sg:postcode":"65804",
    "sg:province":"MO",
    "wof:name":"Compensation Benefit Services",
    "wof:placetype":"venue"
},
  "geometry": {"coordinates":[-93.27188599999999,37.147449],"type":"Point"}
}