{
  "type": "Feature",
  "properties": {
    "iso:country":"US",
    "sg:address":"2115 59th St",
    "sg:city":"Saint Louis",
    "sg:classifiers":[
        {
            "category":"Professional",
            "subcategory":"Printing & Photocopies",
            "type":"Services"
        }
    ],
    "sg:phone":"+1 314 781 6505",
    "sg:postcode":"63110",
    "sg:province":"MO",
    "sg:website":"www.midtownprinting.net",
    "wof:name":"Midtown Printing",
    "wof:placetype":"venue"
},
  "geometry": {"coordinates":[-90.285135,38.616925],"type":"Point"}
}