{
  "type": "Feature",
  "properties": {
    "iso:country":"US",
    "sg:address":"12964 Tesson Ferry Rd",
    "sg:city":"St Louis",
    "sg:classifiers":[
        {
            "category":"Professional",
            "subcategory":"Lawyer & Legal Services",
            "type":"Services"
        }
    ],
    "sg:phone":"+1 314 843 0220",
    "sg:postcode":"63128",
    "sg:province":"MO",
    "sg:tags":[
        "attorney"
    ],
    "wof:name":"Roc Law",
    "wof:placetype":"venue"
},
  "geometry": {"coordinates":[-90.38155,38.494924],"type":"Point"}
}