{
  "type": "Feature",
  "properties": {
    "iso:country":"US",
    "sg:address":"1935 Casa Dr",
    "sg:city":"Arnold",
    "sg:classifiers":[
        {
            "category":"Shopping",
            "subcategory":"Gifts & Souvenirs",
            "type":"Retail Goods"
        }
    ],
    "sg:phone":"+1 636 287 8950",
    "sg:postcode":"63010",
    "sg:province":"MO",
    "wof:name":"K B Collectibles",
    "wof:placetype":"venue"
},
  "geometry": {"coordinates":[-90.38900700000001,38.440408],"type":"Point"}
}