{
  "type": "Feature",
  "properties": {
    "addr:full":"212 S Main St Gravois Mills MO 65037",
    "addr:housenumber":"212",
    "addr:postcode":"65037",
    "addr:street":"S Main St",
    "iso:country":"US",
    "sg:address":"212 S Main St",
    "sg:city":"Gravois Mills",
    "sg:classifiers":[
        {
            "category":"Banks & Credit Unions",
            "subcategory":"Bank",
            "type":"Services"
        }
    ],
    "sg:phone":"+1 573 374 5185",
    "sg:postcode":"65037",
    "sg:province":"MO",
    "sg:tags":[
        "cashing",
        "check"
    ],
    "wof:name":"Money Mart",
    "wof:placetype":"venue"
},
  "geometry": {"coordinates":[-92.82844,38.196154],"type":"Point"}
}