{
  "type": "Feature",
  "properties": {
    "iso:country":"US",
    "sg:address":"938 S Main St",
    "sg:city":"Maryville",
    "sg:classifiers":[
        {
            "category":"Personal",
            "subcategory":"Beauty Salon",
            "type":"Services"
        }
    ],
    "sg:phone":"+1 660 562 3003",
    "sg:postcode":"64468",
    "sg:province":"MO",
    "sg:tags":[
        "shop"
    ],
    "wof:name":"Cline's Hair Studio",
    "wof:placetype":"venue"
},
  "geometry": {"coordinates":[-94.873857,40.337129],"type":"Point"}
}