{
  "type": "Feature",
  "properties": {
    "iso:country":"US",
    "sg:address":"308 1st St",
    "sg:city":"Kennett",
    "sg:classifiers":[
        {
            "category":"Professional",
            "subcategory":"Lawyer & Legal Services",
            "type":"Services"
        }
    ],
    "sg:phone":"+1 573 888 4664",
    "sg:postcode":"63857",
    "sg:province":"MO",
    "sg:tags":[
        "attorney"
    ],
    "wof:name":"Crow Reynolds Shetley & Mc Vey",
    "wof:placetype":"venue"
},
  "geometry": {"coordinates":[-90.054446,36.236592],"type":"Point"}
}