{
  "type": "Feature",
  "properties": {
    "iso:country":"US",
    "sg:address":"5300 NW Pennington Ln",
    "sg:city":"Blue Springs",
    "sg:classifiers":[
        {
            "category":"Wholesale",
            "subcategory":"Durable Goods & Equipment",
            "type":"Manufacturing & Wholesale Goods"
        }
    ],
    "sg:phone":"+1 816 228 3115",
    "sg:postcode":"64015",
    "sg:province":"MO",
    "sg:tags":[
        "specializing",
        "product",
        "distributes",
        "architectural",
        "sign"
    ],
    "wof:name":"Pennington Specialty",
    "wof:placetype":"venue"
},
  "geometry": {"coordinates":[-94.318214,39.02915],"type":"Point"}
}