{
  "type": "Feature",
  "properties": {
    "iso:country":"US",
    "sg:address":"10734 Burrow Dr",
    "sg:city":"Saint Louis",
    "sg:classifiers":[
        {
            "category":"Real Estate",
            "subcategory":"Real Estate Agent",
            "type":"Services"
        }
    ],
    "sg:phone":"+1 314 842 4474",
    "sg:postcode":"63128",
    "sg:province":"MO",
    "wof:name":"Ahrens L L C",
    "wof:placetype":"venue"
},
  "geometry": {"coordinates":[-90.382572,38.518491],"type":"Point"}
}