{
  "type": "Feature",
  "properties": {
    "iso:country":"US",
    "sg:address":"7 N Main Cross St",
    "sg:city":"Bowling Green",
    "sg:classifiers":[
        {
            "category":"Professional",
            "subcategory":"Business Services",
            "type":"Services"
        }
    ],
    "sg:phone":"+1 573 324 6565",
    "sg:postcode":"63334",
    "sg:province":"MO",
    "wof:name":"Allen Pools",
    "wof:placetype":"venue"
},
  "geometry": {"coordinates":[-91.19415100000001,39.342764],"type":"Point"}
}