{
  "type": "Feature",
  "properties": {
    "iso:country":"US",
    "sg:address":"211 N Main St",
    "sg:city":"Urbana",
    "sg:classifiers":[
        {
            "category":"Organizations",
            "subcategory":"Religious Organization",
            "type":"Services"
        }
    ],
    "sg:phone":"+1 417 993 4403",
    "sg:postcode":"65767",
    "sg:province":"MO",
    "sg:tags":[
        "church"
    ],
    "wof:name":"Prairie Chapel United Meth Chr",
    "wof:placetype":"venue"
},
  "geometry": {"coordinates":[-93.165893,37.843016],"type":"Point"}
}