{
  "type": "Feature",
  "properties": {
    "iso:country":"US",
    "sg:address":"606 N High St",
    "sg:city":"Butler",
    "sg:classifiers":[
        {
            "category":"Professional",
            "subcategory":"Business Services",
            "type":"Services"
        }
    ],
    "sg:phone":"+1 660 679 4584",
    "sg:postcode":"64730",
    "sg:province":"MO",
    "wof:name":"Bone Enterprises",
    "wof:placetype":"venue"
},
  "geometry": {"coordinates":[-94.34012199999999,38.264879],"type":"Point"}
}