{
  "type": "Feature",
  "properties": {
    "iso:country":"US",
    "sg:address":"2021 S Grand Blvd",
    "sg:city":"St Louis",
    "sg:classifiers":[
        {
            "category":"Professional",
            "subcategory":"Management & Consulting",
            "type":"Services"
        }
    ],
    "sg:phone":"+1 314 772 8154",
    "sg:postcode":"63104",
    "sg:province":"MO",
    "sg:tags":[
        "consultant",
        "business"
    ],
    "wof:name":"Hempen & Assoc",
    "wof:placetype":"venue"
},
  "geometry": {"coordinates":[-90.240042,38.613609],"type":"Point"}
}