{
  "type": "Feature",
  "properties": {
    "iso:country":"US",
    "sg:address":"909 Paulina Hills Dr",
    "sg:city":"Arnold",
    "sg:classifiers":[
        {
            "category":"Building & Trades",
            "subcategory":"Construction",
            "type":"Services"
        }
    ],
    "sg:phone":"+1 636 282 0711",
    "sg:postcode":"63010",
    "sg:province":"MO",
    "sg:tags":[
        "stone",
        "pointing"
    ],
    "wof:name":"Henry's Engineering",
    "wof:placetype":"venue"
},
  "geometry": {"coordinates":[-90.429096,38.461764],"type":"Point"}
}