{
  "type": "Feature",
  "properties": {
    "iso:country":"US",
    "sg:address":"1275 W Farm Rd 84",
    "sg:city":"Springfield",
    "sg:classifiers":[
        {
            "category":"Shopping",
            "subcategory":"Beauty & Cosmetics",
            "type":"Retail Goods"
        }
    ],
    "sg:phone":"+1 417 833 3641",
    "sg:postcode":"65803",
    "sg:province":"MO",
    "sg:tags":[
        "merchandise"
    ],
    "wof:name":"Jafra Cosmetics International",
    "wof:placetype":"venue"
},
  "geometry": {"coordinates":[-93.30388499999999,37.289217],"type":"Point"}
}