{
  "type": "Feature",
  "properties": {
    "iso:country":"US",
    "sg:address":"8727 Tennessee Ave",
    "sg:city":"Kansas City",
    "sg:classifiers":[
        {
            "category":"Freight",
            "type":"Transportation"
        }
    ],
    "sg:phone":"+1 816 356 4718",
    "sg:postcode":"64138",
    "sg:province":"MO",
    "sg:tags":[
        "delivery",
        "product"
    ],
    "wof:name":"R and R Enterprises of K C",
    "wof:placetype":"venue"
},
  "geometry": {"coordinates":[-94.481315,38.963114],"type":"Point"}
}