{
  "type": "Feature",
  "properties": {
    "iso:country":"US",
    "sg:address":"408 SW 7 St",
    "sg:city":"Oak Grove",
    "sg:classifiers":[
        {
            "category":"Banks & Credit Unions",
            "subcategory":"Financial Services",
            "type":"Services"
        }
    ],
    "sg:phone":"+1 573 443 2021",
    "sg:postcode":"64075",
    "sg:province":"MO",
    "sg:tags":[
        "company",
        "investment"
    ],
    "wof:name":"Jeffrey E Smith Inv Co Lc",
    "wof:placetype":"venue"
},
  "geometry": {"coordinates":[-94.13273700000001,39.009953],"type":"Point"}
}