{
  "type": "Feature",
  "properties": {
    "iso:country":"US",
    "sg:address":"523 W Chase St",
    "sg:city":"Springfield",
    "sg:classifiers":[
        {
            "category":"Retail",
            "subcategory":"Auto Repair",
            "type":"Services"
        },
        {
            "category":"Manufacturing",
            "subcategory":"Tools & Machinery",
            "type":"Manufacturing & Wholesale Goods"
        }
    ],
    "sg:phone":"+1 417 865 3620",
    "sg:postcode":"65803",
    "sg:province":"MO",
    "sg:tags":[
        "exchanging",
        "machine",
        "engine",
        "shop"
    ],
    "wof:name":"Dick's Machine & Motor Supply",
    "wof:placetype":"venue"
},
  "geometry": {"coordinates":[-93.29521800000001,37.231045],"type":"Point"}
}