{
  "type": "Feature",
  "properties": {
    "iso:country":"US",
    "sg:address":"1329 Carriage Crossing Ln",
    "sg:city":"Chesterfield",
    "sg:classifiers":[
        {
            "category":"Shopping",
            "subcategory":"Computers & Home Electronics",
            "type":"Retail Goods"
        }
    ],
    "sg:phone":"+1 636 532 0546",
    "sg:postcode":"63005",
    "sg:province":"MO",
    "wof:name":"Gary P Gordon Inc",
    "wof:placetype":"venue"
},
  "geometry": {"coordinates":[-90.610516,38.647727],"type":"Point"}
}