{
  "type": "Feature",
  "properties": {
    "iso:country":"US",
    "sg:address":"611 S 1st St",
    "sg:city":"Owensville",
    "sg:phone":"+1 573 437 2049",
    "sg:postcode":"65066",
    "sg:province":"MO",
    "sg:tags":[
        "farm",
        "corn"
    ],
    "wof:name":"James Wacker",
    "wof:placetype":"venue"
},
  "geometry": {"coordinates":[-91.50057,38.341905],"type":"Point"}
}