{
  "type": "Feature",
  "properties": {
    "iso:country":"US",
    "sg:address":"2305 E Kearney St",
    "sg:city":"Springfield",
    "sg:classifiers":[
        {
            "category":"Museum",
            "type":"Entertainment"
        }
    ],
    "sg:phone":"+1 417 864 7997",
    "sg:postcode":"65803",
    "sg:province":"MO",
    "sg:tags":[
        "gallery"
    ],
    "wof:name":"Air & Mlitary Museum of Ozarks",
    "wof:placetype":"venue"
},
  "geometry": {"coordinates":[-93.248098,37.23971],"type":"Point"}
}