{
  "type": "Feature",
  "properties": {
    "iso:country":"US",
    "sg:address":"10821 W Florissant Ave",
    "sg:city":"St Louis",
    "sg:classifiers":[
        {
            "category":"Personal",
            "subcategory":"Beauty Salon",
            "type":"Services"
        }
    ],
    "sg:phone":"+1 314 521 2155",
    "sg:postcode":"63136",
    "sg:province":"MO",
    "sg:tags":[
        "shop"
    ],
    "wof:name":"Salon Selected",
    "wof:placetype":"venue"
},
  "geometry": {"coordinates":[-90.280185,38.769723],"type":"Point"}
}