{
  "type": "Feature",
  "properties": {
    "iso:country":"US",
    "sg:address":"1371 McNutt St",
    "sg:city":"Herculaneum",
    "sg:classifiers":[
        {
            "category":"Professional",
            "subcategory":"Lawyer & Legal Services",
            "type":"Services"
        }
    ],
    "sg:phone":"+1 636 931 9993",
    "sg:postcode":"63048",
    "sg:province":"MO",
    "sg:tags":[
        "attorney"
    ],
    "wof:name":"Premier Title Co",
    "wof:placetype":"venue"
},
  "geometry": {"coordinates":[-90.403756,38.252163],"type":"Point"}
}