{
  "type": "Feature",
  "properties": {
    "iso:country":"US",
    "sg:address":"600 NE Colbern Rd",
    "sg:city":"Lees Summit",
    "sg:classifiers":[
        {
            "category":"Government",
            "subcategory":"Office",
            "type":"Public Place"
        }
    ],
    "sg:phone":"+1 816 622 6500",
    "sg:postcode":"64086",
    "sg:province":"MO",
    "sg:tags":[
        "state",
        "program"
    ],
    "wof:name":"Transportation Dept",
    "wof:placetype":"venue"
},
  "geometry": {"coordinates":[-94.362038,38.946281],"type":"Point"}
}