{
  "type": "Feature",
  "properties": {
    "iso:country":"US",
    "sg:address":"29626 Outer Rd",
    "sg:city":"Bethany",
    "sg:classifiers":[
        {
            "category":"Restaurant",
            "type":"Food & Drink"
        },
        {
            "category":"Food & Beverages",
            "subcategory":"Groceries & Convenience Stores",
            "type":"Retail Goods"
        }
    ],
    "sg:phone":"+1 660 425 4406",
    "sg:postcode":"64424",
    "sg:province":"MO",
    "sg:tags":[
        "shop",
        "sandwich"
    ],
    "wof:name":"Subway Offices",
    "wof:placetype":"venue"
},
  "geometry": {"coordinates":[-94.01136,40.28446],"type":"Point"}
}