{
  "type": "Feature",
  "properties": {
    "iso:country":"US",
    "sg:address":"5634 S Kingshighway Blvd",
    "sg:city":"Saint Louis",
    "sg:classifiers":[
        {
            "category":"Education",
            "subcategory":"Music School",
            "type":"Public Place"
        }
    ],
    "sg:phone":"+1 314 353 7015",
    "sg:postcode":"63109",
    "sg:province":"MO",
    "sg:tags":[
        "instrument",
        "teacher",
        "musical"
    ],
    "sg:website":"www.winstonorgan.com",
    "wof:name":"Winston Electronics",
    "wof:placetype":"venue"
},
  "geometry": {"coordinates":[-90.281097,38.579399],"type":"Point"}
}