{
  "type": "Feature",
  "properties": {
    "iso:country":"US",
    "sg:address":"1534 Stonegate St",
    "sg:city":"Farmington",
    "sg:classifiers":[
        {
            "category":"Freight",
            "type":"Transportation"
        }
    ],
    "sg:phone":"+1 573 438 3216",
    "sg:postcode":"63640",
    "sg:province":"MO",
    "sg:tags":[
        "operator",
        "local",
        "trucking"
    ],
    "wof:name":"Kenda K Skaggs",
    "wof:placetype":"venue"
},
  "geometry": {"coordinates":[-90.401788,37.797143],"type":"Point"}
}