{
  "type": "Feature",
  "properties": {
    "iso:country":"US",
    "sg:address":"2244 Kehrsglen Ct",
    "sg:city":"Chesterfield",
    "sg:classifiers":[
        {
            "category":"Real Estate",
            "subcategory":"Real Estate Agent",
            "type":"Services"
        }
    ],
    "sg:phone":"+1 636 532 7676",
    "sg:postcode":"63005",
    "sg:province":"MO",
    "wof:name":"Harold M Klamen",
    "wof:placetype":"venue"
},
  "geometry": {"coordinates":[-90.596131,38.626031],"type":"Point"}
}