{
  "type": "Feature",
  "properties": {
    "iso:country":"US",
    "sg:address":"502 E Chicago Ave",
    "sg:city":"Marceline",
    "sg:classifiers":[
        {
            "category":"Farming",
            "subcategory":"Poultry Farm",
            "type":"Manufacturing & Wholesale Goods"
        }
    ],
    "sg:phone":"+1 660 376 2282",
    "sg:postcode":"64658",
    "sg:province":"MO",
    "sg:tags":[
        "hog",
        "chicken",
        "egg",
        "or",
        "feedlot"
    ],
    "wof:name":"Bill Niemeier",
    "wof:placetype":"venue"
},
  "geometry": {"coordinates":[-92.941906,39.714761],"type":"Point"}
}