{
  "type": "Feature",
  "properties": {
    "iso:country":"US",
    "sg:address":"1116 NE Bryco Dr",
    "sg:city":"Lees Summit",
    "sg:classifiers":[
        {
            "category":"Health Services",
            "subcategory":"Health Practitioner",
            "type":"Services"
        }
    ],
    "sg:phone":"+1 816 524 3284",
    "sg:postcode":"64086",
    "sg:province":"MO",
    "wof:name":"Mind Body Connection",
    "wof:placetype":"venue"
},
  "geometry": {"coordinates":[-94.353307,38.928344],"type":"Point"}
}