{
  "type": "Feature",
  "properties": {
    "iso:country":"US",
    "sg:address":"4695 Crossroads Industrial Dr",
    "sg:city":"Bridgeton",
    "sg:classifiers":[
        {
            "category":"Building & Trades",
            "subcategory":"Landscaping Services",
            "type":"Services"
        },
        {
            "category":"Building & Trades",
            "subcategory":"Pest Control",
            "type":"Services"
        }
    ],
    "sg:phone":"+1 314 738 0070",
    "sg:postcode":"63044",
    "sg:province":"MO",
    "sg:tags":[
        "lawn",
        "landscape",
        "maintenance",
        "contractor"
    ],
    "sg:website":"http://iyp.scottslawnservice.com",
    "wof:name":"Scotts LawnService",
    "wof:placetype":"venue"
},
  "geometry": {"coordinates":[-90.45295,38.776531],"type":"Point"}
}