{
  "type": "Feature",
  "properties": {
    "iso:country":"US",
    "sg:address":"13004 US Hwy 40",
    "sg:city":"Independence",
    "sg:classifiers":[
        {
            "category":"Real Estate",
            "subcategory":"Real Estate Operator",
            "type":"Services"
        }
    ],
    "sg:phone":"+1 816 373 8514",
    "sg:postcode":"64055",
    "sg:province":"MO",
    "sg:tags":[
        "building",
        "apartment"
    ],
    "wof:name":"Burning Tree Apartments",
    "wof:placetype":"venue"
},
  "geometry": {"coordinates":[-94.427306,39.037604],"type":"Point"}
}