{
  "type": "Feature",
  "properties": {
    "iso:country":"US",
    "sg:address":"16000 State Rte B",
    "sg:city":"St James",
    "sg:classifiers":[
        {
            "category":"Professional",
            "subcategory":"Engineering",
            "type":"Services"
        }
    ],
    "sg:phone":"+1 573 265 3865",
    "sg:postcode":"65559",
    "sg:province":"MO",
    "sg:tags":[
        "water",
        "treatment",
        "engineer"
    ],
    "wof:name":"St James Treatment Plant",
    "wof:placetype":"venue"
},
  "geometry": {"coordinates":[-91.59885,38.030749],"type":"Point"}
}