{
  "type": "Feature",
  "properties": {
    "iso:country":"US",
    "sg:address":"5845 US Hwy 54",
    "sg:city":"Osage Beach",
    "sg:classifiers":[
        {
            "category":"Shopping",
            "subcategory":"Clothing, Apparel, & Fashions",
            "type":"Retail Goods"
        }
    ],
    "sg:phone":"+1 573 348 5101",
    "sg:postcode":"65065",
    "sg:province":"MO",
    "sg:tags":[
        "wear",
        "shoes"
    ],
    "wof:name":"Blairs Landing",
    "wof:placetype":"venue"
},
  "geometry": {"coordinates":[-92.667236,38.126589],"type":"Point"}
}