{
  "type": "Feature",
  "properties": {
    "iso:country":"US",
    "sg:address":"122 E High St",
    "sg:city":"Jefferson City",
    "sg:classifiers":[
        {
            "category":"Organizations",
            "subcategory":"Religious Organization",
            "type":"Services"
        }
    ],
    "sg:phone":"+1 573 635 2689",
    "sg:postcode":"65101",
    "sg:province":"MO",
    "wof:name":"Missouri Impact",
    "wof:placetype":"venue"
},
  "geometry": {"coordinates":[-92.172208,38.576725],"type":"Point"}
}