{
  "type": "Feature",
  "properties": {
    "iso:country":"US",
    "sg:address":"2401 NW Ashton Dr",
    "sg:city":"Blue Springs",
    "sg:classifiers":[
        {
            "category":"Recreation",
            "type":"Entertainment"
        }
    ],
    "sg:phone":"+1 816 228 0188",
    "sg:postcode":"64015",
    "sg:province":"MO",
    "sg:tags":[
        "pool",
        "swimming"
    ],
    "wof:name":"Blue Springs Swimming Pool",
    "wof:placetype":"venue"
},
  "geometry": {"coordinates":[-94.290735,39.028462],"type":"Point"}
}