{
  "type": "Feature",
  "properties": {
    "addr:full":"120 US Hwy 24 Buckner MO 64016",
    "addr:housenumber":"120",
    "addr:postcode":"64016",
    "addr:street":"Us Hwy 24 Buckner",
    "iso:country":"US",
    "sg:address":"120 US Hwy 24",
    "sg:city":"Buckner",
    "sg:classifiers":[
        {
            "category":"Autos & Motor Vehicles",
            "subcategory":"Auto Supplies",
            "type":"Retail Goods"
        }
    ],
    "sg:phone":"+1 816 650 5449",
    "sg:postcode":"64016",
    "sg:province":"MO",
    "sg:tags":[
        "automobile",
        "parts"
    ],
    "wof:name":"O'REILLY Auto Parts",
    "wof:placetype":"venue"
},
  "geometry": {"coordinates":[-94.198753,39.138034],"type":"Point"}
}