{
  "type": "Feature",
  "properties": {
    "iso:country":"US",
    "sg:address":"3420 Broadway St",
    "sg:city":"Kansas City",
    "sg:classifiers":[
        {
            "category":"Organizations",
            "subcategory":"Non-profit Organization",
            "type":"Services"
        },
        {
            "category":"Organizations",
            "subcategory":"Professional Association",
            "type":"Services"
        }
    ],
    "sg:phone":"+1 816 753 2220",
    "sg:postcode":"64111",
    "sg:province":"MO",
    "sg:tags":[
        "social"
    ],
    "wof:name":"Arthritis Foundation",
    "wof:placetype":"venue"
},
  "geometry": {"coordinates":[-94.590355,39.065361],"type":"Point"}
}