{
  "type": "Feature",
  "properties": {
    "addr:full":"15820 Clayton Rd Ballwin MO 63011",
    "addr:housenumber":"15820",
    "addr:postcode":"63011",
    "addr:street":"Clayton Rd",
    "iso:country":"US",
    "sg:address":"15820 Clayton Rd",
    "sg:city":"Ballwin",
    "sg:classifiers":[
        {
            "category":"Retail",
            "subcategory":"Funeral Services",
            "type":"Services"
        }
    ],
    "sg:phone":"+1 636 391 0030",
    "sg:postcode":"63011",
    "sg:province":"MO",
    "wof:name":"SCI",
    "wof:placetype":"venue"
},
  "geometry": {"coordinates":[-90.585689,38.604852],"type":"Point"}
}