{
  "type": "Feature",
  "properties": {
    "iso:country":"US",
    "sg:address":"301 N Fulton St",
    "sg:city":"Butler",
    "sg:classifiers":[
        {
            "category":"Organizations",
            "subcategory":"Religious Organization",
            "type":"Services"
        }
    ],
    "sg:phone":"+1 660 679 3933",
    "sg:postcode":"64730",
    "sg:province":"MO",
    "sg:tags":[
        "church"
    ],
    "wof:name":"Presbyterian Church",
    "wof:placetype":"venue"
},
  "geometry": {"coordinates":[-94.33548999999999,38.260087],"type":"Point"}
}