{
  "type": "Feature",
  "properties": {
    "iso:country":"US",
    "sg:address":"625 W Nursery St",
    "sg:city":"Butler",
    "sg:classifiers":[
        {
            "category":"Government",
            "subcategory":"Office",
            "type":"Public Place"
        }
    ],
    "sg:phone":"+1 660 679 6112",
    "sg:postcode":"64730",
    "sg:province":"MO",
    "sg:tags":[
        "use",
        "land",
        "commodity",
        "related",
        "program",
        "administers"
    ],
    "wof:name":"Farm Service Agency",
    "wof:placetype":"venue"
},
  "geometry": {"coordinates":[-94.340834,38.249468],"type":"Point"}
}