{
  "type": "Feature",
  "properties": {
    "iso:country":"US",
    "sg:address":"2003 Orchard Rd",
    "sg:city":"Harrisonville",
    "sg:classifiers":[
        {
            "category":"Retail",
            "subcategory":"Repair Shop",
            "type":"Services"
        }
    ],
    "sg:phone":"+1 816 380 7821",
    "sg:postcode":"64701",
    "sg:province":"MO",
    "wof:name":"Hicks Repair Service",
    "wof:placetype":"venue"
},
  "geometry": {"coordinates":[-94.348173,38.642522],"type":"Point"}
}