{
  "type": "Feature",
  "properties": {
    "iso:country":"US",
    "sg:address":"528 N Allen St",
    "sg:city":"Montgomery City",
    "sg:classifiers":[
        {
            "category":"Food & Beverages",
            "subcategory":"Specialty",
            "type":"Retail Goods"
        }
    ],
    "sg:phone":"+1 573 564 2545",
    "sg:postcode":"63361",
    "sg:province":"MO",
    "wof:name":"Shaklee Fd Supplements & Cosmt",
    "wof:placetype":"venue"
},
  "geometry": {"coordinates":[-91.508763,38.980256],"type":"Point"}
}