{
  "type": "Feature",
  "properties": {
    "iso:country":"US",
    "sg:address":"113 Jefferson St",
    "sg:city":"Doniphan",
    "sg:classifiers":[
        {
            "category":"Autos & Motor Vehicles",
            "subcategory":"Fuel & Gas Station",
            "type":"Retail Goods"
        }
    ],
    "sg:phone":"+1 573 996 7731",
    "sg:postcode":"63935",
    "sg:province":"MO",
    "sg:tags":[
        "station",
        "gasoline"
    ],
    "wof:name":"Texaco",
    "wof:placetype":"venue"
},
  "geometry": {"coordinates":[-90.828282,36.617504],"type":"Point"}
}