{
  "type": "Feature",
  "properties": {
    "iso:country":"US",
    "sg:address":"510 W McGaughy St",
    "sg:city":"Hamilton",
    "sg:classifiers":[
        {
            "category":"Sports & Exercise",
            "subcategory":"Bowling",
            "type":"Entertainment"
        }
    ],
    "sg:phone":"+1 816 583 4933",
    "sg:postcode":"64644",
    "sg:province":"MO",
    "sg:tags":[
        "center"
    ],
    "wof:name":"Womens International Bowl",
    "wof:placetype":"venue"
},
  "geometry": {"coordinates":[-94.00503399999999,39.743197],"type":"Point"}
}