{
  "type": "Feature",
  "properties": {
    "iso:country":"US",
    "sg:address":"18650 N Roddy Rd",
    "sg:city":"Centralia",
    "sg:classifiers":[
        {
            "category":"Manufacturing",
            "subcategory":"Wood Products",
            "type":"Manufacturing & Wholesale Goods"
        }
    ],
    "sg:phone":"+1 573 682 1805",
    "sg:postcode":"65240",
    "sg:province":"MO",
    "sg:tags":[
        "millwork-wholesale",
        "millwork",
        "manufacturer"
    ],
    "wof:name":"Mills Fine Woodworking",
    "wof:placetype":"venue"
},
  "geometry": {"coordinates":[-92.158781,39.171874],"type":"Point"}
}