{
  "type": "Feature",
  "properties": {
    "iso:country":"US",
    "sg:address":"143 Jamestown Mall",
    "sg:city":"Florissant",
    "sg:classifiers":[
        {
            "category":"Shopping",
            "subcategory":"Clothing, Apparel, & Fashions",
            "type":"Retail Goods"
        }
    ],
    "sg:phone":"+1 314 355 7477",
    "sg:postcode":"63034",
    "sg:province":"MO",
    "wof:name":"Foxmoor",
    "wof:placetype":"venue"
},
  "geometry": {"coordinates":[-90.24946300000001,38.821017],"type":"Point"}
}