{
  "type": "Feature",
  "properties": {
    "iso:country":"US",
    "sg:address":"320 E McCarty St",
    "sg:city":"Jefferson City",
    "sg:classifiers":[
        {
            "category":"Government",
            "subcategory":"Office",
            "type":"Public Place"
        }
    ],
    "sg:phone":"+1 573 634 6304",
    "sg:postcode":"65101",
    "sg:province":"MO",
    "sg:tags":[
        "village"
    ],
    "wof:name":"Jefferson City City Adm",
    "wof:placetype":"venue"
},
  "geometry": {"coordinates":[-92.17080799999999,38.573892],"type":"Point"}
}