{
  "type": "Feature",
  "properties": {
    "iso:country":"US",
    "sg:address":"7015 NW Winter Ave",
    "sg:city":"Kansas City",
    "sg:classifiers":[
        {
            "category":"Organizations",
            "subcategory":"Professional Association",
            "type":"Services"
        },
        {
            "category":"Organizations",
            "subcategory":"Community Association",
            "type":"Services"
        }
    ],
    "sg:phone":"+1 816 741 9340",
    "sg:postcode":"64152",
    "sg:province":"MO",
    "sg:tags":[
        "homeowner"
    ],
    "wof:name":"Chapel Woods Homes Association",
    "wof:placetype":"venue"
},
  "geometry": {"coordinates":[-94.662584,39.221646],"type":"Point"}
}