{
  "type": "Feature",
  "properties": {
    "iso:country":"US",
    "sg:address":"1420 US Hwy 61",
    "sg:city":"Festus",
    "sg:classifiers":[
        {
            "category":"Health Services",
            "subcategory":"Doctor",
            "type":"Services"
        }
    ],
    "sg:phone":"+1 636 933 0303",
    "sg:postcode":"63028",
    "sg:province":"MO",
    "sg:tags":[
        "medical"
    ],
    "wof:name":"Logie Macdonald B MD Facr",
    "wof:placetype":"venue"
},
  "geometry": {"coordinates":[-90.39540599999999,38.195238],"type":"Point"}
}