{
  "type": "Feature",
  "properties": {
    "iso:country":"US",
    "sg:address":"155 Greenfield Ln",
    "sg:city":"Marshfield",
    "sg:classifiers":[
        {
            "category":"Retail",
            "subcategory":"Repair Shop",
            "type":"Services"
        }
    ],
    "sg:phone":"+1 417 859 3176",
    "sg:postcode":"65706",
    "sg:province":"MO",
    "sg:tags":[
        "electrical"
    ],
    "wof:name":"Bill Burnside",
    "wof:placetype":"venue"
},
  "geometry": {"coordinates":[-92.91735799999999,37.304159],"type":"Point"}
}