{
  "type": "Feature",
  "properties": {
    "iso:country":"US",
    "sg:address":"14505 Craig Ave",
    "sg:city":"Grandview",
    "sg:classifiers":[
        {
            "category":"Shopping",
            "subcategory":"Gifts & Souvenirs",
            "type":"Retail Goods"
        }
    ],
    "sg:phone":"+1 816 761 1387",
    "sg:postcode":"64030",
    "sg:province":"MO",
    "wof:name":"Pats Gift Baskets",
    "wof:placetype":"venue"
},
  "geometry": {"coordinates":[-94.516144,38.860866],"type":"Point"}
}