{
  "type": "Feature",
  "properties": {
    "iso:country":"US",
    "sg:address":"16 Maple Tree Dr",
    "sg:city":"Marshfield",
    "sg:classifiers":[
        {
            "category":"Manufacturing",
            "subcategory":"Buildings",
            "type":"Manufacturing & Wholesale Goods"
        },
        {
            "category":"Building & Trades",
            "subcategory":"Construction",
            "type":"Services"
        }
    ],
    "sg:phone":"+1 417 838 1484",
    "sg:postcode":"65706",
    "sg:province":"MO",
    "sg:tags":[
        "home",
        "builder",
        "contractor"
    ],
    "wof:name":"M & A Home Solutions Inc.",
    "wof:placetype":"venue"
},
  "geometry": {"coordinates":[-92.896258,37.287604],"type":"Point"}
}