{
  "type": "Feature",
  "properties": {
    "iso:country":"US",
    "sg:address":"116 N Allen St",
    "sg:city":"Centralia",
    "sg:classifiers":[
        {
            "category":"Professional",
            "subcategory":"Lawyer & Legal Services",
            "type":"Services"
        }
    ],
    "sg:phone":"+1 573 682 2114",
    "sg:postcode":"65240",
    "sg:province":"MO",
    "sg:tags":[
        "attorney"
    ],
    "wof:name":"Ausmus Ausmus & Beck",
    "wof:placetype":"venue"
},
  "geometry": {"coordinates":[-92.138625,39.212175],"type":"Point"}
}