{
  "type": "Feature",
  "properties": {
    "iso:country":"US",
    "sg:address":"5621 Audrain Road 209",
    "sg:city":"Centralia",
    "sg:phone":"+1 573 682 5011",
    "sg:postcode":"65240",
    "sg:province":"MO",
    "sg:tags":[
        "farm",
        "corn",
        "wheat"
    ],
    "wof:name":"Samuel Breid",
    "wof:placetype":"venue"
},
  "geometry": {"coordinates":[-92.02630499999999,39.258191],"type":"Point"}
}