{
  "type": "Feature",
  "properties": {
    "iso:country":"US",
    "sg:address":"6900 E 39 St",
    "sg:city":"Kansas City",
    "sg:classifiers":[
        {
            "category":"Building & Trades",
            "subcategory":"Equipment Rental",
            "type":"Services"
        }
    ],
    "sg:phone":"+1 816 923 2036",
    "sg:postcode":"64129",
    "sg:province":"MO",
    "sg:tags":[
        "contractor"
    ],
    "sg:website":"www.resuncorp.com",
    "wof:name":"Resun",
    "wof:placetype":"venue"
},
  "geometry": {"coordinates":[-94.501374,39.053865],"type":"Point"}
}