{
  "type": "Feature",
  "properties": {
    "iso:country":"US",
    "sg:address":"307 Sunrise Blvd",
    "sg:city":"Ballwin",
    "sg:classifiers":[
        {
            "category":"Education",
            "subcategory":"Dance Studio",
            "type":"Public Place"
        }
    ],
    "sg:phone":"+1 636 230 5266",
    "sg:postcode":"63021",
    "sg:province":"MO",
    "wof:name":"Dance Academy",
    "wof:placetype":"venue"
},
  "geometry": {"coordinates":[-90.537588,38.579693],"type":"Point"}
}