{
  "type": "Feature",
  "properties": {
    "iso:country":"US",
    "sg:address":"10305 Concord School Rd",
    "sg:city":"Sappington",
    "sg:classifiers":[
        {
            "category":"Education",
            "subcategory":"School",
            "type":"Public Place"
        }
    ],
    "sg:phone":"+1 314 842 3050",
    "sg:postcode":"63128",
    "sg:province":"MO",
    "wof:name":"Affton-Lindbergh Early Child",
    "wof:placetype":"venue"
},
  "geometry": {"coordinates":[-90.370833,38.521236],"type":"Point"}
}