{
  "type": "Feature",
  "properties": {
    "iso:country":"US",
    "sg:address":"202 W Main St",
    "sg:city":"Kahoka",
    "sg:classifiers":[
        {
            "category":"Autos & Motor Vehicles",
            "subcategory":"Automobile Sales",
            "type":"Retail Goods"
        }
    ],
    "sg:phone":"+1 660 727 3366",
    "sg:postcode":"63445",
    "sg:province":"MO",
    "sg:tags":[
        "new",
        "used"
    ],
    "wof:name":"Bentz Chevrolet Buick",
    "wof:placetype":"venue"
},
  "geometry": {"coordinates":[-91.721468,40.420504],"type":"Point"}
}