{
  "type": "Feature",
  "properties": {
    "iso:country":"US",
    "sg:address":"260 Wolfner Dr.",
    "sg:city":"Fenton",
    "sg:classifiers":[
        {
            "category":"Professional",
            "subcategory":"Advertising",
            "type":"Services"
        },
        {
            "category":"Professional",
            "subcategory":"Computer Services",
            "type":"Services"
        },
        {
            "category":"Communications",
            "subcategory":"Film & Video Production",
            "type":"Services"
        },
        {
            "category":"Internet Cafe",
            "subcategory":"None",
            "type":"Food & Drink"
        }
    ],
    "sg:phone":"+1 314 714 5448",
    "sg:postcode":"63026",
    "sg:province":"MO",
    "sg:tags":[
        "web",
        "product",
        "graphic",
        "marketing",
        "site",
        "hosting",
        "medium",
        "interactive"
    ],
    "sg:website":"http://www.314media.com",
    "wof:name":"314media",
    "wof:placetype":"venue"
},
  "geometry": {"coordinates":[-90.44299599999999,38.533211],"type":"Point"}
}