{
  "type": "Feature",
  "properties": {
    "iso:country":"US",
    "sg:address":"22210 Bangor Rd",
    "sg:city":"Crocker",
    "sg:classifiers":[
        {
            "category":"Building & Trades",
            "subcategory":"Construction",
            "type":"Services"
        }
    ],
    "sg:phone":"+1 573 736 5581",
    "sg:postcode":"65452",
    "sg:province":"MO",
    "sg:tags":[
        "contractor"
    ],
    "wof:name":"Ed & Sons Roofing",
    "wof:placetype":"venue"
},
  "geometry": {"coordinates":[-92.24193699999999,37.922228],"type":"Point"}
}