{
  "type": "Feature",
  "properties": {
    "iso:country":"US",
    "sg:address":"3312 Beck Rd",
    "sg:city":"St Joseph",
    "sg:classifiers":[
        {
            "category":"Education",
            "subcategory":"School",
            "type":"Public Place"
        }
    ],
    "sg:phone":"+1 816 671 4100",
    "sg:postcode":"64506",
    "sg:province":"MO",
    "wof:name":"Coleman Elementary School",
    "wof:placetype":"venue"
},
  "geometry": {"coordinates":[-94.80997000000001,39.785909],"type":"Point"}
}