{
  "type": "Feature",
  "properties": {
    "iso:country":"US",
    "sg:address":"123 W 2nd St",
    "sg:city":"Holden",
    "sg:classifiers":[
        {
            "category":"Real Estate",
            "subcategory":"Real Estate Services",
            "type":"Services"
        },
        {
            "category":"Banks & Credit Unions",
            "subcategory":"Bank",
            "type":"Services"
        },
        {
            "category":"Banks & Credit Unions",
            "subcategory":"Financial Services",
            "type":"Services"
        }
    ],
    "sg:phone":"+1 816 850 5535",
    "sg:postcode":"64040",
    "sg:province":"MO",
    "sg:tags":[
        "saving",
        "loan",
        "commercial"
    ],
    "sg:website":"http://www.firstcentral.net",
    "wof:name":"First Central Bank",
    "wof:placetype":"venue"
},
  "geometry": {"coordinates":[-93.990028,38.717948],"type":"Point"}
}