{
  "type": "Feature",
  "properties": {
    "iso:country":"US",
    "sg:address":"11043 Whitbyhall Dr",
    "sg:city":"Bridgeton",
    "sg:classifiers":[
        {
            "category":"Autos & Motor Vehicles",
            "subcategory":"Auto Supplies",
            "type":"Retail Goods"
        }
    ],
    "sg:phone":"+1 314 739 6928",
    "sg:postcode":"63044",
    "sg:province":"MO",
    "wof:name":"E & R Auto Parts",
    "wof:placetype":"venue"
},
  "geometry": {"coordinates":[-90.41196600000001,38.723879],"type":"Point"}
}