{
  "type": "Feature",
  "properties": {
    "iso:country":"US",
    "sg:address":"1100 Dean Dr",
    "sg:city":"Grain Valley",
    "sg:classifiers":[
        {
            "category":"Personal",
            "subcategory":"Beauty Salon",
            "type":"Services"
        }
    ],
    "sg:phone":"+1 816 347 1700",
    "sg:postcode":"64029",
    "sg:province":"MO",
    "sg:tags":[
        "treatment",
        "skin"
    ],
    "wof:name":"Designer Tan",
    "wof:placetype":"venue"
},
  "geometry": {"coordinates":[-94.21826799999999,39.006727],"type":"Point"}
}