{
  "type": "Feature",
  "properties": {
    "iso:country":"US",
    "sg:address":"3265 Dunn Rd",
    "sg:city":"Florissant",
    "sg:classifiers":[
        {
            "category":"Organizations",
            "subcategory":"Religious Organization",
            "type":"Services"
        }
    ],
    "sg:phone":"+1 314 921 8700",
    "sg:postcode":"63033",
    "sg:province":"MO",
    "wof:name":"House Harvest Worship Center",
    "wof:placetype":"venue"
},
  "geometry": {"coordinates":[-90.275812,38.771585],"type":"Point"}
}