{
  "type": "Feature",
  "properties": {
    "iso:country":"US",
    "sg:address":"547 Washington St",
    "sg:city":"St Charles",
    "sg:classifiers":[
        {
            "category":"Organizations",
            "subcategory":"Religious Organization",
            "type":"Services"
        }
    ],
    "sg:phone":"+1 636 946 9311",
    "sg:postcode":"63301",
    "sg:province":"MO",
    "sg:tags":[
        "church"
    ],
    "wof:name":"St Johns AME Church",
    "wof:placetype":"venue"
},
  "geometry": {"coordinates":[-90.487422,38.78422],"type":"Point"}
}