{
  "type": "Feature",
  "properties": {
    "iso:country":"US",
    "sg:address":"301 N Main St",
    "sg:city":"Arcadia",
    "sg:classifiers":[
        {
            "category":"Insurance",
            "subcategory":"Hazard Insurance",
            "type":"Services"
        },
        {
            "category":"Insurance",
            "subcategory":"Health Insurance",
            "type":"Services"
        }
    ],
    "sg:phone":"+1 573 546 7676",
    "sg:postcode":"63621",
    "sg:province":"MO",
    "sg:tags":[
        "employee",
        "benefit",
        "commercial",
        "business"
    ],
    "wof:name":"Semo Insurance Network",
    "wof:placetype":"venue"
},
  "geometry": {"coordinates":[-90.627937,37.602211],"type":"Point"}
}