{
  "type": "Feature",
  "properties": {
    "iso:country":"US",
    "sg:address":"806 Wild Hickory Ln",
    "sg:city":"Ballwin",
    "sg:classifiers":[
        {
            "category":"Building & Trades",
            "subcategory":"Construction",
            "type":"Services"
        }
    ],
    "sg:phone":"+1 636 391 1656",
    "sg:postcode":"63021",
    "sg:province":"MO",
    "sg:tags":[
        "contractor",
        "commercial",
        "gen",
        "general"
    ],
    "wof:name":"A & E Construction Company",
    "wof:placetype":"venue"
},
  "geometry": {"coordinates":[-90.51338699999999,38.579125],"type":"Point"}
}