{
  "type": "Feature",
  "properties": {
    "iso:country":"US",
    "sg:address":"1650 Madison 234",
    "sg:city":"Fredericktown",
    "sg:classifiers":[
        {
            "category":"Professional",
            "type":"Services"
        }
    ],
    "sg:phone":"+1 573 783 7738",
    "sg:postcode":"63645",
    "sg:province":"MO",
    "sg:tags":[
        "establishment"
    ],
    "wof:name":"Ferguson",
    "wof:placetype":"venue"
},
  "geometry": {"coordinates":[-90.246302,37.523532],"type":"Point"}
}