{
  "type": "Feature",
  "properties": {
    "iso:country":"US",
    "sg:address":"3022 E University St",
    "sg:city":"Springfield",
    "sg:classifiers":[
        {
            "category":"Building & Trades",
            "subcategory":"Construction",
            "type":"Services"
        }
    ],
    "sg:phone":"+1 417 886 7658",
    "sg:postcode":"65804",
    "sg:province":"MO",
    "sg:tags":[
        "contractor"
    ],
    "wof:name":"Kitchen Solvers",
    "wof:placetype":"venue"
},
  "geometry": {"coordinates":[-93.23344299999999,37.181988],"type":"Point"}
}