{
  "type": "Feature",
  "properties": {
    "iso:country":"US",
    "sg:address":"2020 E Dale St",
    "sg:city":"Springfield",
    "sg:classifiers":[
        {
            "category":"Landmark",
            "subcategory":"Fountain",
            "type":"Public Place"
        },
        {
            "category":"Government",
            "subcategory":"Department Of Motor Vehicles",
            "type":"Public Place"
        }
    ],
    "sg:phone":"+1 417 862 3545",
    "sg:postcode":"65803",
    "sg:province":"MO",
    "sg:tags":[
        "tank",
        "cleaning",
        "tanks-repair"
    ],
    "sg:website":"http://www.bristolmfg.com",
    "wof:name":"Bristol Manufacturing Co Inc",
    "wof:placetype":"venue"
},
  "geometry": {"coordinates":[-93.256513,37.234474],"type":"Point"}
}