{
  "type": "Feature",
  "properties": {
    "iso:country":"US",
    "sg:address":"12277 Natural Bridge Rd",
    "sg:city":"Bridgeton",
    "sg:classifiers":[
        {
            "category":"Restaurant",
            "type":"Food & Drink"
        }
    ],
    "sg:phone":"+1 314 291 1288",
    "sg:postcode":"63044",
    "sg:province":"MO",
    "sg:tags":[
        "eating"
    ],
    "wof:name":"Lees Family Buffet",
    "wof:placetype":"venue"
},
  "geometry": {"coordinates":[-90.418559,38.755819],"type":"Point"}
}