{
  "type": "Feature",
  "properties": {
    "iso:country":"US",
    "sg:address":"5424 Troost Ave",
    "sg:city":"Kansas City",
    "sg:classifiers":[
        {
            "category":"Bars & Pubs",
            "type":"Food & Drink"
        }
    ],
    "sg:phone":"+1 816 333 7423",
    "sg:postcode":"64110",
    "sg:province":"MO",
    "sg:tags":[
        "drinking"
    ],
    "sg:website":"www.mikestavernonline.com",
    "wof:name":"Mike's Tavern",
    "wof:placetype":"venue"
},
  "geometry": {"coordinates":[-94.573849,39.02763],"type":"Point"}
}