{
  "type": "Feature",
  "properties": {
    "iso:country":"US",
    "sg:address":"805 E Randolph St",
    "sg:city":"Kirksville",
    "sg:classifiers":[
        {
            "category":"Retail",
            "subcategory":"Auto Repair",
            "type":"Services"
        }
    ],
    "sg:phone":"+1 660 665 6424",
    "sg:postcode":"63501",
    "sg:province":"MO",
    "sg:tags":[
        "repairing",
        "automobile"
    ],
    "wof:name":"Gunnels General Repair",
    "wof:placetype":"venue"
},
  "geometry": {"coordinates":[-92.57544300000001,40.187157],"type":"Point"}
}