{
  "type": "Feature",
  "properties": {
    "iso:country":"US",
    "sg:address":"2245 S Grand Blvd",
    "sg:city":"Saint Louis",
    "sg:classifiers":[
        {
            "category":"Retail",
            "subcategory":"Veterinary Services",
            "type":"Services"
        }
    ],
    "sg:phone":"+1 314 773 6400",
    "sg:postcode":"63104",
    "sg:province":"MO",
    "sg:tags":[
        "veterinarian"
    ],
    "wof:name":"St Louis Pet Clinic",
    "wof:placetype":"venue"
},
  "geometry": {"coordinates":[-90.240601,38.610298],"type":"Point"}
}