{
  "type": "Feature",
  "properties": {
    "iso:country":"US",
    "sg:address":"1104 Mill St",
    "sg:city":"Cassville",
    "sg:classifiers":[
        {
            "category":"Place Of Worship",
            "subcategory":"Church",
            "type":"Public Place"
        },
        {
            "category":"Place Of Worship",
            "type":"Public Place"
        }
    ],
    "sg:phone":"+1 417 847 2374",
    "sg:postcode":"65625",
    "sg:province":"MO",
    "sg:tags":[
        "christ",
        "denomination",
        "testament",
        "christ-new",
        "churches-interdenominational",
        "churches-church",
        "churches-various"
    ],
    "wof:name":"Church Of Christ",
    "wof:placetype":"venue"
},
  "geometry": {"coordinates":[-93.865246,36.681422],"type":"Point"}
}