{
  "type": "Feature",
  "properties": {
    "iso:country":"US",
    "sg:address":"418 E Dake St",
    "sg:city":"Brookfield",
    "sg:classifiers":[
        {
            "category":"Personal",
            "subcategory":"Beauty Salon",
            "type":"Services"
        }
    ],
    "sg:phone":"+1 660 258 2661",
    "sg:postcode":"64628",
    "sg:province":"MO",
    "wof:name":"Magic Mirror",
    "wof:placetype":"venue"
},
  "geometry": {"coordinates":[-93.070385,39.793549],"type":"Point"}
}