{
  "type": "Feature",
  "properties": {
    "iso:country":"US",
    "sg:address":"8173 State Hwy Zz",
    "sg:city":"West Plains",
    "sg:classifiers":[
        {
            "category":"Wholesale",
            "subcategory":"Construction Materials",
            "type":"Manufacturing & Wholesale Goods"
        }
    ],
    "sg:phone":"+1 417 256 7298",
    "sg:postcode":"65775",
    "sg:province":"MO",
    "sg:tags":[
        "limestone",
        "lime"
    ],
    "wof:name":"Hampton Soil Svc",
    "wof:placetype":"venue"
},
  "geometry": {"coordinates":[-91.754926,36.713697],"type":"Point"}
}