{
  "type": "Feature",
  "properties": {
    "iso:country":"US",
    "sg:address":"4963 Hwy D",
    "sg:city":"Defiance",
    "sg:classifiers":[
        {
            "category":"Building & Trades",
            "subcategory":"Construction",
            "type":"Services"
        }
    ],
    "sg:phone":"+1 636 398 6151",
    "sg:postcode":"63341",
    "sg:province":"MO",
    "sg:tags":[
        "builder",
        "deck"
    ],
    "wof:name":"Add-A-Deck",
    "wof:placetype":"venue"
},
  "geometry": {"coordinates":[-90.84998899999999,38.70916],"type":"Point"}
}