{
  "type": "Feature",
  "properties": {
    "iso:country":"US",
    "sg:address":"1100 Mable St",
    "sg:city":"Trenton",
    "sg:classifiers":[
        {
            "category":"Museum",
            "type":"Entertainment"
        }
    ],
    "sg:phone":"+1 660 359 2411",
    "sg:postcode":"64683",
    "sg:province":"MO",
    "wof:name":"Grundy County Museum",
    "wof:placetype":"venue"
},
  "geometry": {"coordinates":[-93.61669500000001,40.076758],"type":"Point"}
}