{
  "type": "Feature",
  "properties": {
    "iso:country":"US",
    "sg:address":"1639 Lawrence 2140",
    "sg:city":"Sarcoxie",
    "sg:classifiers":[
        {
            "category":"Farming",
            "subcategory":"Farm",
            "type":"Manufacturing & Wholesale Goods"
        }
    ],
    "sg:phone":"+1 417 548 2103",
    "sg:postcode":"64862",
    "sg:province":"MO",
    "sg:tags":[
        "crop",
        "general"
    ],
    "wof:name":"Double T Farm of Missouri",
    "wof:placetype":"venue"
},
  "geometry": {"coordinates":[-94.030304,37.076094],"type":"Point"}
}