{
  "type": "Feature",
  "properties": {
    "iso:country":"US",
    "sg:address":"101 N Oaks Plz",
    "sg:city":"Saint Louis",
    "sg:classifiers":[
        {
            "category":"Sports & Exercise",
            "subcategory":"Bowling",
            "type":"Entertainment"
        }
    ],
    "sg:phone":"+1 314 382 5757",
    "sg:postcode":"63121",
    "sg:province":"MO",
    "sg:website":"www.northoaksbowl.com",
    "wof:name":"North Oaks Bowl",
    "wof:placetype":"venue"
},
  "geometry": {"coordinates":[-90.290199,38.701],"type":"Point"}
}