{
  "type": "Feature",
  "properties": {
    "iso:country":"US",
    "sg:address":"6730 Pennsylvania Ave",
    "sg:city":"Kansas City",
    "sg:classifiers":[
        {
            "category":"Farming",
            "subcategory":"Farm",
            "type":"Manufacturing & Wholesale Goods"
        }
    ],
    "sg:phone":"+1 816 361 9587",
    "sg:postcode":"64113",
    "sg:province":"MO",
    "sg:tags":[
        "crop",
        "general"
    ],
    "wof:name":"James McLarney",
    "wof:placetype":"venue"
},
  "geometry": {"coordinates":[-94.59637499999999,39.005867],"type":"Point"}
}