{
  "type": "Feature",
  "properties": {
    "iso:country":"US",
    "sg:address":"1402 Veterns Memorial Pkwy",
    "sg:city":"Warrenton",
    "sg:classifiers":[
        {
            "category":"Manufacturing",
            "subcategory":"Metals",
            "type":"Manufacturing & Wholesale Goods"
        }
    ],
    "sg:phone":"+1 636 456 8200",
    "sg:postcode":"63383",
    "sg:province":"MO",
    "sg:tags":[
        "cloth",
        "wire"
    ],
    "wof:name":"Metso Minerals",
    "wof:placetype":"venue"
},
  "geometry": {"coordinates":[-91.127021,38.817969],"type":"Point"}
}