{
  "type": "Feature",
  "properties": {
    "iso:country":"US",
    "sg:address":"2701 Arsenal St",
    "sg:city":"St Louis",
    "sg:classifiers":[
        {
            "category":"Professional",
            "type":"Services"
        }
    ],
    "sg:phone":"+1 314 773 6614",
    "sg:postcode":"63118",
    "sg:province":"MO",
    "sg:tags":[
        "establishment"
    ],
    "wof:name":"Terr's Classic VW Shop",
    "wof:placetype":"venue"
},
  "geometry": {"coordinates":[-90.227082,38.599705],"type":"Point"}
}