{
  "type": "Feature",
  "properties": {
    "iso:country":"US",
    "sg:address":"139 N Belt Hwy",
    "sg:city":"St Joseph",
    "sg:classifiers":[
        {
            "category":"Shopping",
            "subcategory":"Music",
            "type":"Retail Goods"
        }
    ],
    "sg:phone":"+1 816 364 0748",
    "sg:postcode":"64506",
    "sg:province":"MO",
    "sg:tags":[
        "compact",
        "record",
        "disc",
        "tape"
    ],
    "wof:name":"Cd Tradepost",
    "wof:placetype":"venue"
},
  "geometry": {"coordinates":[-94.80357100000001,39.766973],"type":"Point"}
}