{
  "type": "Feature",
  "properties": {
    "iso:country":"US",
    "sg:address":"701 Bates St",
    "sg:city":"Saint Louis",
    "sg:classifiers":[
        {
            "category":"Organizations",
            "subcategory":"Community Association",
            "type":"Services"
        }
    ],
    "sg:phone":"+1 314 352 0313",
    "sg:postcode":"63111",
    "sg:province":"MO",
    "wof:name":"American Legion Post 3",
    "wof:placetype":"venue"
},
  "geometry": {"coordinates":[-90.250179,38.566309],"type":"Point"}
}