{
  "type": "Feature",
  "properties": {
    "iso:country":"US",
    "sg:address":"1028 SW 14 St",
    "sg:city":"Lees Summit",
    "sg:classifiers":[
        {
            "category":"Building & Trades",
            "subcategory":"Construction",
            "type":"Services"
        }
    ],
    "sg:phone":"+1 913 484 1461",
    "sg:postcode":"64081",
    "sg:province":"MO",
    "sg:tags":[
        "hanging",
        "contractor"
    ],
    "wof:name":"Steel Painting & Home Imprv",
    "wof:placetype":"venue"
},
  "geometry": {"coordinates":[-94.39797,38.895221],"type":"Point"}
}