{
  "type": "Feature",
  "properties": {
    "iso:country":"US",
    "sg:address":"224 Turnberry Place Dr",
    "sg:city":"Ballwin",
    "sg:classifiers":[
        {
            "category":"Professional",
            "subcategory":"Computer Services",
            "type":"Services"
        }
    ],
    "sg:phone":"+1 636 458 2866",
    "sg:postcode":"63011",
    "sg:province":"MO",
    "sg:tags":[
        "internet"
    ],
    "wof:name":"St Louis Internet Inc",
    "wof:placetype":"venue"
},
  "geometry": {"coordinates":[-90.603679,38.604397],"type":"Point"}
}