{
  "type": "Feature",
  "properties": {
    "iso:country":"US",
    "sg:address":"2123 Dartmouth Gate Ct",
    "sg:city":"Ballwin",
    "sg:classifiers":[
        {
            "category":"Professional",
            "subcategory":"Management & Consulting",
            "type":"Services"
        }
    ],
    "sg:phone":"+1 636 458 0709",
    "sg:postcode":"63011",
    "sg:province":"MO",
    "sg:tags":[
        "business"
    ],
    "wof:name":"Linwood Consulting Inc",
    "wof:placetype":"venue"
},
  "geometry": {"coordinates":[-90.632784,38.599664],"type":"Point"}
}