{
  "type": "Feature",
  "properties": {
    "iso:country":"US",
    "sg:address":"1316 N Range Line Rd",
    "sg:city":"Joplin",
    "sg:classifiers":[
        {
            "category":"Wholesale",
            "subcategory":"Farm Supplies",
            "type":"Manufacturing & Wholesale Goods"
        },
        {
            "category":"Shopping",
            "type":"Retail Goods"
        }
    ],
    "sg:phone":"+1 417 781 7111",
    "sg:postcode":"64801",
    "sg:province":"MO",
    "sg:tags":[
        "store"
    ],
    "sg:website":"www.mytscstore.com",
    "wof:name":"Tractor Supply Co 329",
    "wof:placetype":"venue"
},
  "geometry": {"coordinates":[-94.47671800000001,37.098623],"type":"Point"}
}