{
  "type": "Feature",
  "properties": {
    "iso:country":"US",
    "sg:address":"1104 Concord Dr",
    "sg:city":"Saint Charles",
    "sg:classifiers":[
        {
            "category":"Professional",
            "subcategory":"Business Services",
            "type":"Services"
        }
    ],
    "sg:phone":"+1 636 477 9284",
    "sg:postcode":"63303",
    "sg:province":"MO",
    "wof:name":"Lsmarty Enterprises",
    "wof:placetype":"venue"
},
  "geometry": {"coordinates":[-90.571038,38.734029],"type":"Point"}
}