{
  "type": "Feature",
  "properties": {
    "iso:country":"US",
    "sg:address":"5836 S Foxboro Trl",
    "sg:city":"Springfield",
    "sg:classifiers":[
        {
            "category":"Personal",
            "type":"Services"
        },
        {
            "category":"Professional",
            "subcategory":"Art Services",
            "type":"Services"
        }
    ],
    "sg:phone":"+1 417 890 7450",
    "sg:postcode":"65804",
    "sg:province":"MO",
    "sg:tags":[
        "photography",
        "videography",
        "photographers-portrait",
        "wedding"
    ],
    "wof:name":"Dawn Sheilds Photography",
    "wof:placetype":"venue"
},
  "geometry": {"coordinates":[-93.234717,37.106191],"type":"Point"}
}