{
  "type": "Feature",
  "properties": {
    "iso:country":"US",
    "sg:address":"12300 Arrowhead Trfy",
    "sg:city":"Kansas City",
    "sg:classifiers":[
        {
            "category":"Organizations",
            "subcategory":"Religious Organization",
            "type":"Services"
        }
    ],
    "sg:phone":"+1 816 734 8100",
    "sg:postcode":"64165",
    "sg:province":"MO",
    "sg:website":"www.vineyardkcnorth.com",
    "wof:name":"Vineyard Church",
    "wof:placetype":"venue"
},
  "geometry": {"coordinates":[-94.584183,39.316992],"type":"Point"}
}