{
  "type": "Feature",
  "properties": {
    "iso:country":"US",
    "sg:address":"11718 Wyandotte St",
    "sg:city":"Kansas City",
    "sg:classifiers":[
        {
            "category":"Professional",
            "type":"Services"
        }
    ],
    "sg:phone":"+1 816 942 4256",
    "sg:postcode":"64114",
    "sg:province":"MO",
    "wof:name":"Deeper Waters Inc",
    "wof:placetype":"venue"
},
  "geometry": {"coordinates":[-94.59401099999999,38.914186],"type":"Point"}
}