{
  "type": "Feature",
  "properties": {
    "iso:country":"US",
    "sg:address":"3550 E Evergreen St",
    "sg:city":"Springfield",
    "sg:classifiers":[
        {
            "category":"Travel",
            "subcategory":"Hotels & Motels",
            "type":"Entertainment"
        }
    ],
    "sg:phone":"+1 417 831 1080",
    "sg:postcode":"65803",
    "sg:province":"MO",
    "sg:tags":[
        "operation"
    ],
    "wof:name":"American Inn",
    "wof:placetype":"venue"
},
  "geometry": {"coordinates":[-93.21711000000001,37.249163],"type":"Point"}
}