{
  "type": "Feature",
  "properties": {
    "iso:country":"US",
    "sg:address":"20895 State Hwy Hh",
    "sg:city":"Kirksville",
    "sg:classifiers":[
        {
            "category":"Recreation",
            "type":"Entertainment"
        }
    ],
    "sg:phone":"+1 660 332 6139",
    "sg:postcode":"63501",
    "sg:province":"MO",
    "wof:name":"Mid States Rodeo",
    "wof:placetype":"venue"
},
  "geometry": {"coordinates":[-92.65146,40.063556],"type":"Point"}
}