{
  "type": "Feature",
  "properties": {
    "iso:country":"US",
    "sg:address":"2020 Iowa Ave",
    "sg:city":"Joplin",
    "sg:classifiers":[
        {
            "category":"Education",
            "subcategory":"Vocational School",
            "type":"Public Place"
        },
        {
            "category":"Education",
            "subcategory":"School",
            "type":"Public Place"
        }
    ],
    "sg:phone":"+1 417 625 5260",
    "sg:postcode":"64804",
    "sg:province":"MO",
    "sg:tags":[
        "technical",
        "industrial",
        "business",
        "trade"
    ],
    "sg:website":"http://www.ftcjoplinenroll.com/franklintech/",
    "wof:name":"Franklin Technical School",
    "wof:placetype":"venue"
},
  "geometry": {"coordinates":[-94.50756699999999,37.069172],"type":"Point"}
}