{
  "type": "Feature",
  "properties": {
    "iso:country":"US",
    "sg:address":"148 S Main St",
    "sg:city":"Liberal",
    "sg:classifiers":[
        {
            "category":"Social Services",
            "type":"Services"
        },
        {
            "category":"Health Services",
            "subcategory":"Clinic",
            "type":"Services"
        },
        {
            "category":"Personal",
            "type":"Services"
        }
    ],
    "sg:phone":"+1 417 843 2130",
    "sg:postcode":"64762",
    "sg:province":"MO",
    "sg:tags":[
        "information",
        "mental",
        "family",
        "child",
        "counselors-licensed",
        "individual",
        "marriage",
        "welfare",
        "professional",
        "counselor"
    ],
    "wof:name":"Allied Mental Health",
    "wof:placetype":"venue"
},
  "geometry": {"coordinates":[-94.520197,37.556106],"type":"Point"}
}