{
  "type": "Feature",
  "properties": {
    "iso:country":"US",
    "sg:address":"4013 NW Claymont Dr",
    "sg:city":"Kansas City",
    "sg:classifiers":[
        {
            "category":"Professional",
            "subcategory":"Business Services",
            "type":"Services"
        }
    ],
    "sg:phone":"+1 816 452 3123",
    "sg:postcode":"64116",
    "sg:province":"MO",
    "wof:name":"American Business Resources",
    "wof:placetype":"venue"
},
  "geometry": {"coordinates":[-94.592377,39.168274],"type":"Point"}
}