{
  "type": "Feature",
  "properties": {
    "iso:country":"US",
    "sg:address":"1915 Iron Gates Rd",
    "sg:city":"Joplin",
    "sg:classifiers":[
        {
            "category":"Manufacturing",
            "subcategory":"Tools & Machinery",
            "type":"Manufacturing & Wholesale Goods"
        }
    ],
    "sg:phone":"+1 417 624 1684",
    "sg:postcode":"64804",
    "sg:province":"MO",
    "sg:tags":[
        "industrial",
        "mfg"
    ],
    "wof:name":"Massey Machine Shop LLC",
    "wof:placetype":"venue"
},
  "geometry": {"coordinates":[-94.556274,37.070446],"type":"Point"}
}