{
  "type": "Feature",
  "properties": {
    "iso:country":"US",
    "sg:address":"3713 S Kingshighway Blvd",
    "sg:city":"St Louis",
    "sg:classifiers":[
        {
            "category":"Personal",
            "subcategory":"Barber",
            "type":"Services"
        }
    ],
    "sg:phone":"+1 314 351 3737",
    "sg:postcode":"63109",
    "sg:province":"MO",
    "wof:name":"Top Flight",
    "wof:placetype":"venue"
},
  "geometry": {"coordinates":[-90.272577,38.592545],"type":"Point"}
}