{
  "type": "Feature",
  "properties": {
    "addr:full":"1338 E Fairview Ave Carthage MO 64836",
    "addr:housenumber":"1338",
    "addr:postcode":"64836",
    "addr:street":"E Fairview Ave",
    "iso:country":"US",
    "sg:address":"1338 E Fairview Ave",
    "sg:city":"Carthage",
    "sg:classifiers":[
        {
            "category":"Organizations",
            "subcategory":"Religious Organization",
            "type":"Services"
        }
    ],
    "sg:phone":"+1 417 358 1043",
    "sg:postcode":"64836",
    "sg:province":"MO",
    "wof:name":"Corporation of President of Th",
    "wof:placetype":"venue"
},
  "geometry": {"coordinates":[-94.293828,37.154561],"type":"Point"}
}