{
  "type": "Feature",
  "properties": {
    "iso:country":"US",
    "sg:address":"6014 Delmar Blvd",
    "sg:city":"St Louis",
    "sg:classifiers":[
        {
            "category":"Real Estate",
            "subcategory":"Architect",
            "type":"Services"
        }
    ],
    "sg:phone":"+1 314 863 1313",
    "sg:postcode":"63112",
    "sg:province":"MO",
    "sg:tags":[
        "architectural"
    ],
    "sg:website":"www.stlda.com",
    "wof:name":"St Louis Design Alliance Inc",
    "wof:placetype":"venue"
},
  "geometry": {"coordinates":[-90.29588200000001,38.654971],"type":"Point"}
}