{
  "type": "Feature",
  "properties": {
    "iso:country":"US",
    "sg:address":"2022 Medicine Bow Dr",
    "sg:city":"Ballwin",
    "sg:classifiers":[
        {
            "category":"Food & Beverages",
            "subcategory":"Liquor & Beverages",
            "type":"Retail Goods"
        }
    ],
    "sg:phone":"+1 636 458 2416",
    "sg:postcode":"63011",
    "sg:province":"MO",
    "sg:tags":[
        "alcoholic"
    ],
    "wof:name":"Valley Wines",
    "wof:placetype":"venue"
},
  "geometry": {"coordinates":[-90.624048,38.59601],"type":"Point"}
}