{
  "type": "Feature",
  "properties": {
    "iso:country":"US",
    "sg:address":"6025 Chippewa St Ste 207",
    "sg:city":"Saint Louis",
    "sg:classifiers":[
        {
            "category":"Professional",
            "subcategory":"Lawyer & Legal Services",
            "type":"Services"
        }
    ],
    "sg:phone":"+1 314 351 6260",
    "sg:postcode":"63109",
    "sg:province":"MO",
    "wof:name":"Neilson Gordon W Atty",
    "wof:placetype":"venue"
},
  "geometry": {"coordinates":[-90.29450199999999,38.593399],"type":"Point"}
}