{
  "type": "Feature",
  "properties": {
    "iso:country":"US",
    "sg:address":"800 W Frost St",
    "sg:city":"Plattsburg",
    "sg:classifiers":[
        {
            "category":"Local Transit",
            "type":"Transportation"
        }
    ],
    "sg:phone":"+1 816 539 3333",
    "sg:postcode":"64477",
    "sg:province":"MO",
    "sg:tags":[
        "bus",
        "line"
    ],
    "wof:name":"Hill Peoples Leasing",
    "wof:placetype":"venue"
},
  "geometry": {"coordinates":[-94.45608900000001,39.561808],"type":"Point"}
}