{
  "type": "Feature",
  "properties": {
    "iso:country":"US",
    "sg:address":"10636 Bellefontaine Rd",
    "sg:city":"St Louis",
    "sg:classifiers":[
        {
            "category":"Organizations",
            "subcategory":"Religious Organization",
            "type":"Services"
        }
    ],
    "sg:phone":"+1 314 869 7777",
    "sg:postcode":"63137",
    "sg:province":"MO",
    "sg:tags":[
        "church"
    ],
    "sg:website":"www.hopechurch.org",
    "wof:name":"Hope Church",
    "wof:placetype":"venue"
},
  "geometry": {"coordinates":[-90.221892,38.762593],"type":"Point"}
}