{
  "type": "Feature",
  "properties": {
    "iso:country":"US",
    "sg:address":"6274 Gravois Ave",
    "sg:city":"St Louis",
    "sg:classifiers":[
        {
            "category":"Retail",
            "subcategory":"Repair Shop",
            "type":"Services"
        },
        {
            "category":"Building & Trades",
            "subcategory":"Plumbing",
            "type":"Services"
        }
    ],
    "sg:phone":"+1 314 832 2288",
    "sg:postcode":"63116",
    "sg:province":"MO",
    "sg:tags":[
        "equipment",
        "contractor"
    ],
    "wof:name":"Kitchen-Aire Engineering Inc",
    "wof:placetype":"venue"
},
  "geometry": {"coordinates":[-90.280081,38.574031],"type":"Point"}
}