{
  "type": "Feature",
  "properties": {
    "iso:country":"US",
    "sg:address":"4305 N Antioch Rd",
    "sg:city":"Kansas City",
    "sg:classifiers":[
        {
            "category":"Autos & Motor Vehicles",
            "subcategory":"Fuel & Gas Station",
            "type":"Retail Goods"
        }
    ],
    "sg:phone":"+1 816 452 0798",
    "sg:postcode":"64117",
    "sg:province":"MO",
    "sg:tags":[
        "oil"
    ],
    "wof:name":"Sinclair",
    "wof:placetype":"venue"
},
  "geometry": {"coordinates":[-94.548928,39.172399],"type":"Point"}
}