{
  "type": "Feature",
  "properties": {
    "iso:country":"US",
    "sg:address":"12004 Sommerer Rd",
    "sg:city":"Henley",
    "sg:classifiers":[
        {
            "category":"Farming",
            "subcategory":"Livestock Farm",
            "type":"Manufacturing & Wholesale Goods"
        }
    ],
    "sg:phone":"+1 573 496 3852",
    "sg:postcode":"65040",
    "sg:province":"MO",
    "sg:tags":[
        "ranch"
    ],
    "wof:name":"Angus Sommerer Ranch",
    "wof:placetype":"venue"
},
  "geometry": {"coordinates":[-92.291587,38.411831],"type":"Point"}
}