{
  "type": "Feature",
  "properties": {
    "iso:country":"US",
    "sg:address":"5600 E Bannister Rd",
    "sg:city":"Kansas City",
    "sg:classifiers":[
        {
            "category":"Ice Cream",
            "type":"Food & Drink"
        }
    ],
    "sg:menulink":"http://www.allmenus.com/mo/royal-oaks/224148-freshens/menu/",
    "sg:phone":"+1 816 761 4448",
    "sg:postcode":"64192",
    "sg:province":"MO",
    "sg:tags":[
        "smoothy",
        "juice",
        "american"
    ],
    "wof:name":"Freshens",
    "wof:placetype":"venue"
},
  "geometry": {"coordinates":[-94.526432,38.953288],"type":"Point"}
}