{
  "type": "Feature",
  "properties": {
    "iso:country":"US",
    "sg:address":"200 S Main St",
    "sg:city":"Poplar Bluff",
    "sg:classifiers":[
        {
            "category":"Banks & Credit Unions",
            "subcategory":"Investment Brokerage",
            "type":"Services"
        }
    ],
    "sg:phone":"+1 573 785 7741",
    "sg:postcode":"63901",
    "sg:province":"MO",
    "sg:tags":[
        "security"
    ],
    "wof:name":"Century Securities Assoc",
    "wof:placetype":"venue"
},
  "geometry": {"coordinates":[-90.393164,36.755496],"type":"Point"}
}