{
  "type": "Feature",
  "properties": {
    "iso:country":"US",
    "sg:address":"453 Lafayette Ct",
    "sg:city":"Ballwin",
    "sg:classifiers":[
        {
            "category":"Health Services",
            "subcategory":"Doctor",
            "type":"Services"
        }
    ],
    "sg:phone":"+1 636 394 5215",
    "sg:postcode":"63011",
    "sg:province":"MO",
    "wof:name":"T M McKenna Dss",
    "wof:placetype":"venue"
},
  "geometry": {"coordinates":[-90.592241,38.604873],"type":"Point"}
}