{
  "type": "Feature",
  "properties": {
    "iso:country":"US",
    "sg:address":"305 W Jackson St",
    "sg:city":"Mexico",
    "sg:classifiers":[
        {
            "category":"Education",
            "subcategory":"Library",
            "type":"Public Place"
        },
        {
            "category":"Government",
            "subcategory":"Office",
            "type":"Public Place"
        }
    ],
    "sg:phone":"+1 573 581 4939",
    "sg:postcode":"65265",
    "sg:province":"MO",
    "sg:tags":[
        "township",
        "government-city",
        "village"
    ],
    "wof:name":"Mexico-Audrain County Library",
    "wof:placetype":"venue"
},
  "geometry": {"coordinates":[-91.884755,39.172181],"type":"Point"}
}