{
  "type": "Feature",
  "properties": {
    "iso:country":"US",
    "sg:address":"2918 Tracy Ave",
    "sg:city":"Kansas City",
    "sg:classifiers":[
        {
            "category":"Organizations",
            "subcategory":"Religious Organization",
            "type":"Services"
        }
    ],
    "sg:phone":"+1 816 753 0073",
    "sg:postcode":"64109",
    "sg:province":"MO",
    "sg:website":"www.sspx.org",
    "wof:name":"Society Of St Pius X",
    "wof:placetype":"venue"
},
  "geometry": {"coordinates":[-94.568659,39.072558],"type":"Point"}
}