{
  "type": "Feature",
  "properties": {
    "iso:country":"US",
    "sg:address":"964 State Hwy 76",
    "sg:city":"Willow Springs",
    "sg:classifiers":[
        {
            "category":"Freight",
            "type":"Transportation"
        }
    ],
    "sg:phone":"+1 417 469 4851",
    "sg:postcode":"65793",
    "sg:province":"MO",
    "sg:tags":[
        "trucking"
    ],
    "wof:name":"TNT Trucking",
    "wof:placetype":"venue"
},
  "geometry": {"coordinates":[-92.06064600000001,36.982931],"type":"Point"}
}