{
  "type": "Feature",
  "properties": {
    "iso:country":"US",
    "sg:address":"6784 Mexico Rd",
    "sg:city":"St Peters",
    "sg:classifiers":[
        {
            "category":"Health Services",
            "subcategory":"Chiropractor",
            "type":"Services"
        }
    ],
    "sg:phone":"+1 636 397 8384",
    "sg:postcode":"63376",
    "sg:province":"MO",
    "wof:name":"Country Hill Chiropractic",
    "wof:placetype":"venue"
},
  "geometry": {"coordinates":[-90.61801,38.78817],"type":"Point"}
}