{
  "type": "Feature",
  "properties": {
    "iso:country":"US",
    "sg:address":"16091 Swingley Ridge Rd",
    "sg:city":"Chesterfield",
    "sg:classifiers":[
        {
            "category":"Wholesale",
            "subcategory":"Stationery",
            "type":"Manufacturing & Wholesale Goods"
        }
    ],
    "sg:phone":"+1 636 537 5558",
    "sg:postcode":"63017",
    "sg:province":"MO",
    "sg:tags":[
        "company",
        "software"
    ],
    "wof:name":"NPS Systems Inc",
    "wof:placetype":"venue"
},
  "geometry": {"coordinates":[-90.56107,38.654668],"type":"Point"}
}