{
  "type": "Feature",
  "properties": {
    "iso:country":"US",
    "sg:address":"16895 Rankin Mill Ln",
    "sg:city":"Boonville",
    "sg:classifiers":[
        {
            "category":"Health Services",
            "subcategory":"Doctor",
            "type":"Services"
        },
        {
            "category":"Health Services",
            "subcategory":"Clinic",
            "type":"Services"
        },
        {
            "category":"Health Services",
            "subcategory":"Hospital",
            "type":"Services"
        }
    ],
    "sg:phone":"+1 660 882 2466",
    "sg:postcode":"65233",
    "sg:province":"MO",
    "sg:tags":[
        "physician",
        "dialysis",
        "medical",
        "surgeons",
        "nephrology",
        "kidneys"
    ],
    "sg:website":"http://www.khgreensboro.com",
    "wof:name":"Dialysis Clinic Inc",
    "wof:placetype":"venue"
},
  "geometry": {"coordinates":[-92.741577,38.948154],"type":"Point"}
}