{
  "type": "Feature",
  "properties": {
    "iso:country":"US",
    "sg:address":"2001 S Hanley Rd",
    "sg:city":"St Louis",
    "sg:classifiers":[
        {
            "category":"Banks & Credit Unions",
            "subcategory":"Bank",
            "type":"Services"
        }
    ],
    "sg:phone":"+1 314 961 0079",
    "sg:postcode":"63144",
    "sg:province":"MO",
    "sg:tags":[
        "loan",
        "real estate"
    ],
    "wof:name":"Midco Mortgage",
    "wof:placetype":"venue"
},
  "geometry": {"coordinates":[-90.334519,38.622309],"type":"Point"}
}