{
  "type": "Feature",
  "properties": {
    "iso:country":"US",
    "sg:address":"299 N 20th St",
    "sg:city":"Ozark",
    "sg:classifiers":[
        {
            "category":"Travel",
            "subcategory":"Hotels & Motels",
            "type":"Entertainment"
        },
        {
            "category":"Travel",
            "subcategory":"Bed & Breakfast",
            "type":"Entertainment"
        }
    ],
    "sg:phone":"+1 417 581 8800",
    "sg:postcode":"65721",
    "sg:province":"MO",
    "sg:tags":[
        "inn",
        "lodging"
    ],
    "sg:website":"http://www.americasbestvalueinn.com/",
    "wof:name":"Americas Best Value Inn",
    "wof:placetype":"venue"
},
  "geometry": {"coordinates":[-93.23086600000001,37.023509],"type":"Point"}
}