{
  "type": "Feature",
  "properties": {
    "iso:country":"US",
    "sg:address":"23104 State Hwy B",
    "sg:city":"Tarkio",
    "sg:phone":"+1 660 984 5554",
    "sg:postcode":"64491",
    "sg:province":"MO",
    "sg:tags":[
        "farm",
        "corn"
    ],
    "wof:name":"Phillip Hull",
    "wof:placetype":"venue"
},
  "geometry": {"coordinates":[-95.413752,40.539093],"type":"Point"}
}