{
  "type": "Feature",
  "properties": {
    "iso:country":"US",
    "sg:address":"1011 Central St",
    "sg:city":"Kansas City",
    "sg:classifiers":[
        {
            "category":"Professional",
            "subcategory":"Management & Consulting",
            "type":"Services"
        }
    ],
    "sg:phone":"+1 816 472 5954",
    "sg:postcode":"64105",
    "sg:province":"MO",
    "sg:tags":[
        "search",
        "executive",
        "resource",
        "human"
    ],
    "wof:name":"Allcare Consulting",
    "wof:placetype":"venue"
},
  "geometry": {"coordinates":[-94.58688600000001,39.101098],"type":"Point"}
}