{
  "type": "Feature",
  "properties": {
    "iso:country":"US",
    "sg:address":"225 Industrial Dr",
    "sg:city":"Sullivan",
    "sg:classifiers":[
        {
            "category":"Wholesale",
            "subcategory":"Durable Goods & Equipment",
            "type":"Manufacturing & Wholesale Goods"
        }
    ],
    "sg:phone":"+1 573 468 5551",
    "sg:postcode":"63080",
    "sg:province":"MO",
    "sg:tags":[
        "representative",
        "manufacturer"
    ],
    "sg:website":"www.aerofil.com",
    "wof:name":"Aerofil Technology Inc",
    "wof:placetype":"venue"
},
  "geometry": {"coordinates":[-91.171604,38.22625],"type":"Point"}
}