{
  "type": "Feature",
  "properties": {
    "iso:country":"US",
    "sg:address":"6508 Jefferson St",
    "sg:city":"Kansas City",
    "sg:classifiers":[
        {
            "category":"Professional",
            "subcategory":"Computer Services",
            "type":"Services"
        }
    ],
    "sg:phone":"+1 816 363 4783",
    "sg:postcode":"64113",
    "sg:province":"MO",
    "sg:tags":[
        "website",
        "design"
    ],
    "sg:website":"www.kcwda.com",
    "wof:name":"Web Design Assoc",
    "wof:placetype":"venue"
},
  "geometry": {"coordinates":[-94.597382,39.00844],"type":"Point"}
}