{
  "type": "Feature",
  "properties": {
    "iso:country":"US",
    "sg:address":"11344 Highridge Dr",
    "sg:city":"Independence",
    "sg:classifiers":[
        {
            "category":"Building & Trades",
            "subcategory":"Construction",
            "type":"Services"
        }
    ],
    "sg:phone":"+1 816 353 4053",
    "sg:postcode":"64052",
    "sg:province":"MO",
    "sg:tags":[
        "house"
    ],
    "wof:name":"Fuendling Construction",
    "wof:placetype":"venue"
},
  "geometry": {"coordinates":[-94.442542,39.048062],"type":"Point"}
}