{
  "type": "Feature",
  "properties": {
    "iso:country":"US",
    "sg:address":"1815 Locust St",
    "sg:city":"Saint Louis",
    "sg:classifiers":[
        {
            "category":"Wholesale",
            "subcategory":"Auto Parts",
            "type":"Manufacturing & Wholesale Goods"
        }
    ],
    "sg:phone":"+1 314 621 8954",
    "sg:postcode":"63103",
    "sg:province":"MO",
    "sg:tags":[
        "tire"
    ],
    "wof:name":"Original Tire Mart",
    "wof:placetype":"venue"
},
  "geometry": {"coordinates":[-90.20590199999999,38.632401],"type":"Point"}
}