{
  "type": "Feature",
  "properties": {
    "iso:country":"US",
    "sg:address":"7115 NW Chapel Woods Ln",
    "sg:city":"Kansas City",
    "sg:classifiers":[
        {
            "category":"Shopping",
            "subcategory":"Jewelry",
            "type":"Retail Goods"
        }
    ],
    "sg:phone":"+1 816 587 9401",
    "sg:postcode":"64152",
    "sg:province":"MO",
    "wof:name":"Bijoux Gigis",
    "wof:placetype":"venue"
},
  "geometry": {"coordinates":[-94.663291,39.222755],"type":"Point"}
}