{
  "type": "Feature",
  "properties": {
    "iso:country":"US",
    "sg:address":"202 Jefferson St",
    "sg:city":"Doniphan",
    "sg:classifiers":[
        {
            "category":"Professional",
            "type":"Services"
        }
    ],
    "sg:phone":"+1 573 996 7294",
    "sg:postcode":"63935",
    "sg:province":"MO",
    "sg:tags":[
        "establishment"
    ],
    "wof:name":"Sno Shack",
    "wof:placetype":"venue"
},
  "geometry": {"coordinates":[-90.829409,36.617428],"type":"Point"}
}