{
  "type": "Feature",
  "properties": {
    "iso:country":"US",
    "sg:address":"509 S Jefferson St",
    "sg:city":"Saint James",
    "sg:classifiers":[
        {
            "category":"Farming",
            "subcategory":"Livestock Farm",
            "type":"Manufacturing & Wholesale Goods"
        }
    ],
    "sg:phone":"+1 573 265 7432",
    "sg:postcode":"65559",
    "sg:province":"MO",
    "sg:tags":[
        "beef",
        "feedlot",
        "cattle"
    ],
    "wof:name":"James Mc Bride",
    "wof:placetype":"venue"
},
  "geometry": {"coordinates":[-91.612829,37.992382],"type":"Point"}
}