{
  "type": "Feature",
  "properties": {
    "iso:country":"US",
    "sg:address":"5414 Southfield Center",
    "sg:city":"St Louis",
    "sg:classifiers":[
        {
            "category":"Professional",
            "subcategory":"Business Services",
            "type":"Services"
        }
    ],
    "sg:phone":"+1 314 849 9550",
    "sg:postcode":"63123",
    "sg:province":"MO",
    "sg:tags":[
        "embroidery"
    ],
    "wof:name":"Embroidme",
    "wof:placetype":"venue"
},
  "geometry": {"coordinates":[-90.358704,38.525236],"type":"Point"}
}