{
  "type": "Feature",
  "properties": {
    "iso:country":"US",
    "sg:address":"202 E 32nd St",
    "sg:city":"Joplin",
    "sg:classifiers":[
        {
            "category":"Communications",
            "subcategory":"Radio Station",
            "type":"Services"
        }
    ],
    "sg:phone":"+1 417 623 1025",
    "sg:postcode":"64804",
    "sg:province":"MO",
    "sg:tags":[
        "broadcast"
    ],
    "wof:name":"K I X Q K I X 1025",
    "wof:placetype":"venue"
},
  "geometry": {"coordinates":[-94.51271,37.054932],"type":"Point"}
}