{
  "type": "Feature",
  "properties": {
    "iso:country":"US",
    "sg:address":"7047 W Florissant Ave",
    "sg:city":"Saint Louis",
    "sg:classifiers":[
        {
            "category":"Shopping",
            "subcategory":"Jewelry",
            "type":"Retail Goods"
        }
    ],
    "sg:phone":"+1 314 381 9700",
    "sg:postcode":"63136",
    "sg:province":"MO",
    "wof:name":"Leemark Pawn & Jewelry",
    "wof:placetype":"venue"
},
  "geometry": {"coordinates":[-90.262901,38.7187],"type":"Point"}
}