{
  "type": "Feature",
  "properties": {
    "iso:country":"US",
    "sg:address":"12896 Pennridge Dr",
    "sg:city":"Bridgeton",
    "sg:classifiers":[
        {
            "category":"Building & Trades",
            "subcategory":"Construction",
            "type":"Services"
        }
    ],
    "sg:phone":"+1 314 344 3288",
    "sg:postcode":"63044",
    "sg:province":"MO",
    "sg:tags":[
        "dry wall",
        "contractor"
    ],
    "wof:name":"Sundermeyer Limited",
    "wof:placetype":"venue"
},
  "geometry": {"coordinates":[-90.429861,38.763593],"type":"Point"}
}