{
  "type": "Feature",
  "properties": {
    "iso:country":"US",
    "sg:address":"5608 Heege Rd",
    "sg:city":"St Louis",
    "sg:classifiers":[
        {
            "category":"Retail",
            "subcategory":"Auto Repair",
            "type":"Services"
        }
    ],
    "sg:phone":"+1 314 351 1352",
    "sg:postcode":"63123",
    "sg:province":"MO",
    "sg:tags":[
        "repairing",
        "automotive",
        "general",
        "automobile"
    ],
    "wof:name":"Affton Auto",
    "wof:placetype":"venue"
},
  "geometry": {"coordinates":[-90.31258099999999,38.564772],"type":"Point"}
}