{
  "type": "Feature",
  "properties": {
    "iso:country":"US",
    "sg:address":"4049 Pennsylvania Ave",
    "sg:city":"Kansas City",
    "sg:classifiers":[
        {
            "category":"Real Estate",
            "subcategory":"Real Estate Operator",
            "type":"Services"
        }
    ],
    "sg:phone":"+1 816 531 5181",
    "sg:postcode":"64111",
    "sg:province":"MO",
    "sg:tags":[
        "building",
        "apartment"
    ],
    "wof:name":"Westport Chrprctic Accpuncture",
    "wof:placetype":"venue"
},
  "geometry": {"coordinates":[-94.591526,39.053104],"type":"Point"}
}