{
  "type": "Feature",
  "properties": {
    "iso:country":"US",
    "sg:address":"825 Sioux Ave",
    "sg:city":"Independence",
    "sg:classifiers":[
        {
            "category":"Professional",
            "type":"Services"
        }
    ],
    "sg:phone":"+1 816 796 8241",
    "sg:postcode":"64056",
    "sg:province":"MO",
    "wof:name":"Jason Snider",
    "wof:placetype":"venue"
},
  "geometry": {"coordinates":[-94.347765,39.117983],"type":"Point"}
}