{
  "type": "Feature",
  "properties": {
    "iso:country":"US",
    "sg:address":"3125 Roanoke Rd",
    "sg:city":"Kansas City",
    "sg:classifiers":[
        {
            "category":"Manufacturing",
            "subcategory":"Food",
            "type":"Manufacturing & Wholesale Goods"
        }
    ],
    "sg:phone":"+1 816 753 7096",
    "sg:postcode":"64111",
    "sg:province":"MO",
    "sg:tags":[
        "brewer"
    ],
    "sg:website":"www.blvdbeer.com",
    "wof:name":"Boulevard Brewing Co",
    "wof:placetype":"venue"
},
  "geometry": {"coordinates":[-94.60432,39.068334],"type":"Point"}
}