{
  "type": "Feature",
  "properties": {
    "iso:country":"US",
    "sg:address":"1060 Country Club Rd",
    "sg:city":"St Charles",
    "sg:classifiers":[
        {
            "category":"Real Estate",
            "subcategory":"Real Estate Agent",
            "type":"Services"
        }
    ],
    "sg:phone":"+1 636 947 4455",
    "sg:postcode":"63303",
    "sg:province":"MO",
    "sg:website":"www.scottsacco.com",
    "wof:name":"Delta Group Real Estate LC",
    "wof:placetype":"venue"
},
  "geometry": {"coordinates":[-90.53689799999999,38.785937],"type":"Point"}
}