{
  "type": "Feature",
  "properties": {
    "iso:country":"US",
    "sg:address":"111 W Commercial St",
    "sg:city":"Kahoka",
    "sg:classifiers":[
        {
            "category":"Government",
            "subcategory":"Post Office",
            "type":"Public Place"
        }
    ],
    "sg:phone":"+1 660 727 2430",
    "sg:postcode":"63445",
    "sg:province":"MO",
    "sg:tags":[
        "postal",
        "us"
    ],
    "wof:name":"US Post Office",
    "wof:placetype":"venue"
},
  "geometry": {"coordinates":[-91.72077400000001,40.421469],"type":"Point"}
}