{
  "type": "Feature",
  "properties": {
    "iso:country":"US",
    "sg:address":"11555 Saint Charles Rock Rd",
    "sg:city":"Bridgeton",
    "sg:classifiers":[
        {
            "category":"Insurance",
            "subcategory":"Insurance Agent",
            "type":"Services"
        }
    ],
    "sg:phone":"+1 314 291 2020",
    "sg:postcode":"63044",
    "sg:province":"MO",
    "wof:name":"American Family Insurance",
    "wof:placetype":"venue"
},
  "geometry": {"coordinates":[-90.40781200000001,38.74229],"type":"Point"}
}