{
  "type": "Feature",
  "properties": {
    "iso:country":"US",
    "sg:address":"406 W 34 Ter",
    "sg:city":"Kansas City",
    "sg:classifiers":[
        {
            "category":"Organizations",
            "subcategory":"Community Association",
            "type":"Services"
        }
    ],
    "sg:phone":"+1 816 561 8655",
    "sg:postcode":"64111",
    "sg:province":"MO",
    "sg:tags":[
        "to",
        "lady",
        "auxiliary"
    ],
    "wof:name":"The To Ladies Auxiliary",
    "wof:placetype":"venue"
},
  "geometry": {"coordinates":[-94.591402,39.065396],"type":"Point"}
}