{
  "type": "Feature",
  "properties": {
    "iso:country":"US",
    "sg:address":"415 E McCarty St",
    "sg:city":"Jefferson City",
    "sg:classifiers":[
        {
            "category":"Social Services",
            "type":"Services"
        }
    ],
    "sg:phone":"+1 573 634 4161",
    "sg:postcode":"65101",
    "sg:province":"MO",
    "wof:name":"M C A D V",
    "wof:placetype":"venue"
},
  "geometry": {"coordinates":[-92.16954,38.573123],"type":"Point"}
}