{
  "type": "Feature",
  "properties": {
    "iso:country":"US",
    "sg:address":"2095 Autumn Wood Dr",
    "sg:city":"Saint Charles",
    "sg:classifiers":[
        {
            "category":"Wholesale",
            "subcategory":"Drugs",
            "type":"Manufacturing & Wholesale Goods"
        }
    ],
    "sg:phone":"+1 314 757 2033",
    "sg:postcode":"63303",
    "sg:province":"MO",
    "wof:name":"Evesgarden17",
    "wof:placetype":"venue"
},
  "geometry": {"coordinates":[-90.559065,38.772966],"type":"Point"}
}