{
  "type": "Feature",
  "properties": {
    "iso:country":"US",
    "sg:address":"1320 Alma Ave",
    "sg:city":"Perryville",
    "sg:classifiers":[
        {
            "category":"Food & Beverages",
            "subcategory":"Candy",
            "type":"Retail Goods"
        },
        {
            "category":"Manufacturing",
            "subcategory":"Food",
            "type":"Manufacturing & Wholesale Goods"
        }
    ],
    "sg:phone":"+1 573 547 2122",
    "sg:postcode":"63775",
    "sg:province":"MO",
    "sg:tags":[
        "confectionery-wholesale",
        "confectionery",
        "manufacturer"
    ],
    "wof:name":"Favier, Joseph & Patricia",
    "wof:placetype":"venue"
},
  "geometry": {"coordinates":[-89.884905,37.711467],"type":"Point"}
}