{
  "type": "Feature",
  "properties": {
    "iso:country":"US",
    "sg:address":"400 S 11th St",
    "sg:city":"Poplar Bluff",
    "sg:classifiers":[
        {
            "category":"Health Services",
            "subcategory":"Chiropractor",
            "type":"Services"
        }
    ],
    "sg:phone":"+1 573 785 5666",
    "sg:postcode":"63901",
    "sg:province":"MO",
    "wof:name":"Rushin Chiropractic Ctr",
    "wof:placetype":"venue"
},
  "geometry": {"coordinates":[-90.40679799999999,36.75476],"type":"Point"}
}