{
  "type": "Feature",
  "properties": {
    "iso:country":"US",
    "sg:address":"16205 Vicie Ave",
    "sg:city":"Belton",
    "sg:classifiers":[
        {
            "category":"Organizations",
            "subcategory":"Religious Organization",
            "type":"Services"
        }
    ],
    "sg:phone":"+1 816 322 4300",
    "sg:postcode":"64012",
    "sg:province":"MO",
    "sg:tags":[
        "churches-baptist"
    ],
    "sg:website":"http://www.sbcbelton.com",
    "wof:name":"Southland Baptist Church",
    "wof:placetype":"venue"
},
  "geometry": {"coordinates":[-94.515778,38.83004],"type":"Point"}
}