{
  "type": "Feature",
  "properties": {
    "iso:country":"US",
    "sg:address":"616 N Byers Ave",
    "sg:city":"Joplin",
    "sg:classifiers":[
        {
            "category":"Professional",
            "subcategory":"Business Services",
            "type":"Services"
        }
    ],
    "sg:phone":"+1 417 781 3944",
    "sg:postcode":"64801",
    "sg:province":"MO",
    "sg:tags":[
        "auctioneer"
    ],
    "wof:name":"Cope Auction Svc",
    "wof:placetype":"venue"
},
  "geometry": {"coordinates":[-94.517475,37.098401],"type":"Point"}
}