{
  "type": "Feature",
  "properties": {
    "iso:country":"US",
    "sg:address":"12152 Tesson Ferry Rd",
    "sg:city":"St Louis",
    "sg:classifiers":[
        {
            "category":"Health Services",
            "subcategory":"Doctor",
            "type":"Services"
        }
    ],
    "sg:phone":"+1 314 714 1070",
    "sg:postcode":"63128",
    "sg:province":"MO",
    "sg:tags":[
        "physician",
        "surgeon"
    ],
    "wof:name":"Paulo S Bicalho MD",
    "wof:placetype":"venue"
},
  "geometry": {"coordinates":[-90.36846799999999,38.515252],"type":"Point"}
}