{
  "type": "Feature",
  "properties": {
    "iso:country":"US",
    "sg:address":"2801 S Ohio Ave",
    "sg:city":"Sedalia",
    "sg:classifiers":[
        {
            "category":"Shopping",
            "subcategory":"Gifts & Souvenirs",
            "type":"Retail Goods"
        }
    ],
    "sg:phone":"+1 660 826 0444",
    "sg:postcode":"65301",
    "sg:province":"MO",
    "sg:tags":[
        "repair",
        "stereo",
        "equipment"
    ],
    "wof:name":"Sound Spectrum",
    "wof:placetype":"venue"
},
  "geometry": {"coordinates":[-93.22960999999999,38.686598],"type":"Point"}
}