{
  "type": "Feature",
  "properties": {
    "iso:country":"US",
    "sg:address":"36510 E Church Rd",
    "sg:city":"Oak Grove",
    "sg:classifiers":[
        {
            "category":"Professional",
            "subcategory":"Accounting & Tax Preparation",
            "type":"Services"
        }
    ],
    "sg:phone":"+1 816 690 4468",
    "sg:postcode":"64075",
    "sg:province":"MO",
    "sg:tags":[
        "return"
    ],
    "wof:name":"Lakes Tax Service",
    "wof:placetype":"venue"
},
  "geometry": {"coordinates":[-94.156925,38.983952],"type":"Point"}
}