{
  "type": "Feature",
  "properties": {
    "iso:country":"US",
    "sg:address":"19 W Linwood Blvd",
    "sg:city":"Kansas City",
    "sg:classifiers":[
        {
            "category":"Recreation",
            "type":"Entertainment"
        }
    ],
    "sg:phone":"+1 816 753 3535",
    "sg:postcode":"64111",
    "sg:province":"MO",
    "sg:tags":[
        "hall",
        "auditorium"
    ],
    "wof:name":"Drexel Hall Ballroom & Meeting",
    "wof:placetype":"venue"
},
  "geometry": {"coordinates":[-94.58648700000001,39.068026],"type":"Point"}
}