{
  "type": "Feature",
  "properties": {
    "iso:country":"US",
    "sg:address":"681 US Hwy 60",
    "sg:city":"Republic",
    "sg:classifiers":[
        {
            "category":"Shopping",
            "type":"Retail Goods"
        }
    ],
    "sg:phone":"+1 417 732 7855",
    "sg:postcode":"65738",
    "sg:province":"MO",
    "sg:tags":[
        "merchandise"
    ],
    "wof:name":"Landscape Shoppe",
    "wof:placetype":"venue"
},
  "geometry": {"coordinates":[-93.469453,37.119949],"type":"Point"}
}