{
  "type": "Feature",
  "properties": {
    "iso:country":"US",
    "sg:address":"3418 Teagues Road",
    "sg:city":"Marshfield",
    "sg:classifiers":[
        {
            "category":"Retail",
            "subcategory":"Auto Repair",
            "type":"Services"
        }
    ],
    "sg:phone":"+1 417 468 2326",
    "sg:postcode":"65706",
    "sg:province":"MO",
    "sg:tags":[
        "body",
        "painting",
        "repairing",
        "automobile"
    ],
    "wof:name":"Steel Thunder Custom Cycles",
    "wof:placetype":"venue"
},
  "geometry": {"coordinates":[-92.82546499999999,37.252686],"type":"Point"}
}