{
  "type": "Feature",
  "properties": {
    "iso:country":"US",
    "sg:address":"104 E 5 St",
    "sg:city":"Kansas City",
    "sg:classifiers":[
        {
            "category":"Health Services",
            "subcategory":"Health Practitioner",
            "type":"Services"
        }
    ],
    "sg:phone":"+1 816 472 1898",
    "sg:postcode":"64106",
    "sg:province":"MO",
    "sg:tags":[
        "acupuncture"
    ],
    "wof:name":"Dr Jiang's Traditional Chinese",
    "wof:placetype":"venue"
},
  "geometry": {"coordinates":[-94.58054,39.10884],"type":"Point"}
}