{
  "type": "Feature",
  "properties": {
    "iso:country":"US",
    "sg:address":"518 NW Englewood Rd",
    "sg:city":"Kansas City",
    "sg:classifiers":[
        {
            "category":"Personal",
            "subcategory":"Tanning Parlor",
            "type":"Services"
        }
    ],
    "sg:phone":"+1 816 453 5858",
    "sg:postcode":"64118",
    "sg:province":"MO",
    "sg:tags":[
        "salon"
    ],
    "wof:name":"Island Tan 3 Downunder",
    "wof:placetype":"venue"
},
  "geometry": {"coordinates":[-94.58832099999999,39.195614],"type":"Point"}
}