{
  "type": "Feature",
  "properties": {
    "iso:country":"US",
    "sg:address":"5600 E 34 Ter",
    "sg:city":"Kansas City",
    "sg:classifiers":[
        {
            "category":"Social Services",
            "subcategory":"Child Care",
            "type":"Services"
        }
    ],
    "sg:phone":"+1 816 861 4556",
    "sg:postcode":"64128",
    "sg:province":"MO",
    "sg:tags":[
        "day"
    ],
    "wof:name":"Reach & Teach Child Care",
    "wof:placetype":"venue"
},
  "geometry": {"coordinates":[-94.518013,39.0627],"type":"Point"}
}