{
  "type": "Feature",
  "properties": {
    "iso:country":"US",
    "sg:address":"7620 Wornall Rd",
    "sg:city":"Kansas City",
    "sg:classifiers":[
        {
            "category":"Autos & Motor Vehicles",
            "subcategory":"Auto Supplies",
            "type":"Retail Goods"
        }
    ],
    "sg:phone":"+1 816 361 0400",
    "sg:postcode":"64114",
    "sg:province":"MO",
    "sg:tags":[
        "tire"
    ],
    "wof:name":"Goodyear Auto Svc Ctr",
    "wof:placetype":"venue"
},
  "geometry": {"coordinates":[-94.594444,38.989121],"type":"Point"}
}