{
  "type": "Feature",
  "properties": {
    "iso:country":"US",
    "sg:address":"108 W McPherson St",
    "sg:city":"Knob Noster",
    "sg:classifiers":[
        {
            "category":"Retail",
            "subcategory":"Auto Repair",
            "type":"Services"
        }
    ],
    "sg:phone":"+1 660 563 2991",
    "sg:postcode":"65336",
    "sg:province":"MO",
    "sg:tags":[
        "muffler",
        "exhaust",
        "system"
    ],
    "wof:name":"Muffler Shop",
    "wof:placetype":"venue"
},
  "geometry": {"coordinates":[-93.55762799999999,38.765127],"type":"Point"}
}