{
  "type": "Feature",
  "properties": {
    "iso:country":"US",
    "sg:address":"2708A Sutton Blvd",
    "sg:city":"Maplewood",
    "sg:classifiers":[
        {
            "category":"Building & Trades",
            "subcategory":"Construction",
            "type":"Services"
        }
    ],
    "sg:phone":"+1 314 645 4101",
    "sg:postcode":"63143",
    "sg:province":"MO",
    "sg:tags":[
        "interior",
        "design"
    ],
    "sg:website":"www.floradiva.com",
    "wof:name":"Flora Diva",
    "wof:placetype":"venue"
},
  "geometry": {"coordinates":[-90.319791,38.612255],"type":"Point"}
}