{
  "type": "Feature",
  "properties": {
    "iso:country":"US",
    "sg:address":"1510 Bridlewood Ln",
    "sg:city":"Raymore",
    "sg:classifiers":[
        {
            "category":"Professional",
            "subcategory":"Management & Consulting",
            "type":"Services"
        }
    ],
    "sg:phone":"+1 816 322 1759",
    "sg:postcode":"64083",
    "sg:province":"MO",
    "sg:tags":[
        "business"
    ],
    "wof:name":"Risk Rewards Consulting Svcs",
    "wof:placetype":"venue"
},
  "geometry": {"coordinates":[-94.481002,38.796145],"type":"Point"}
}