{
  "type": "Feature",
  "properties": {
    "iso:country":"US",
    "sg:address":"4109 Pennsylvania Ave",
    "sg:city":"Kansas City",
    "sg:classifiers":[
        {
            "category":"Restaurant",
            "type":"Food & Drink"
        }
    ],
    "sg:menulink":"http://www.allmenus.com/mo/kaw/10121-harpos-kansas-city/menu/",
    "sg:phone":"+1 816 753 3434",
    "sg:postcode":"64111",
    "sg:province":"MO",
    "sg:tags":[
        "american"
    ],
    "wof:name":"Harpo's Kansas City",
    "wof:placetype":"venue"
},
  "geometry": {"coordinates":[-94.59122600000001,39.052576],"type":"Point"}
}