{
  "type": "Feature",
  "properties": {
    "iso:country":"US",
    "sg:address":"306 Wollard Blvd",
    "sg:city":"Richmond",
    "sg:classifiers":[
        {
            "category":"Professional",
            "type":"Services"
        }
    ],
    "sg:phone":"+1 816 776 2066",
    "sg:postcode":"64085",
    "sg:province":"MO",
    "wof:name":"Amery Rachelle Esthetician",
    "wof:placetype":"venue"
},
  "geometry": {"coordinates":[-93.960269,39.275732],"type":"Point"}
}