{
  "type": "Feature",
  "properties": {
    "iso:country":"US",
    "sg:address":"6635 Creekstone Dr",
    "sg:city":"Barnhart",
    "sg:classifiers":[
        {
            "category":"Building & Trades",
            "subcategory":"Construction",
            "type":"Services"
        }
    ],
    "sg:phone":"+1 636 942 4867",
    "sg:postcode":"63012",
    "sg:province":"MO",
    "sg:tags":[
        "house"
    ],
    "wof:name":"Pj Zysk Construction Inc",
    "wof:placetype":"venue"
},
  "geometry": {"coordinates":[-90.422715,38.353287],"type":"Point"}
}