{
  "type": "Feature",
  "properties": {
    "iso:country":"US",
    "sg:address":"626 Axminister Dr",
    "sg:city":"Fenton",
    "sg:classifiers":[
        {
            "category":"Mining & Drilling",
            "type":"Manufacturing & Wholesale Goods"
        }
    ],
    "sg:phone":"+1 636 343 9004",
    "sg:postcode":"63026",
    "sg:province":"MO",
    "sg:tags":[
        "foundry"
    ],
    "wof:name":"Graphic Links",
    "wof:placetype":"venue"
},
  "geometry": {"coordinates":[-90.45290900000001,38.536867],"type":"Point"}
}