{
  "type": "Feature",
  "properties": {
    "iso:country":"US",
    "sg:address":"101 S Washington St",
    "sg:city":"Neosho",
    "sg:classifiers":[
        {
            "category":"Manufacturing",
            "subcategory":"Printing",
            "type":"Manufacturing & Wholesale Goods"
        },
        {
            "category":"Manufacturing",
            "subcategory":"Motor Vehicles & Parts",
            "type":"Manufacturing & Wholesale Goods"
        }
    ],
    "sg:phone":"+1 417 451 6242",
    "sg:postcode":"64850",
    "sg:province":"MO",
    "sg:tags":[
        "screen",
        "mfg",
        "trimming"
    ],
    "wof:name":"Wink's Custom Screen Printing",
    "wof:placetype":"venue"
},
  "geometry": {"coordinates":[-94.36716699999999,36.869661],"type":"Point"}
}