{
  "type": "Feature",
  "properties": {
    "iso:country":"US",
    "sg:address":"123 McDonnell Blvd",
    "sg:city":"Hazelwood",
    "sg:classifiers":[
        {
            "category":"Wholesale",
            "subcategory":"Stationery",
            "type":"Manufacturing & Wholesale Goods"
        }
    ],
    "sg:phone":"+1 314 968 9400",
    "sg:postcode":"63042",
    "sg:province":"MO",
    "sg:tags":[
        "distributor",
        "packaging",
        "material"
    ],
    "wof:name":"Crown Packaging Corp",
    "wof:placetype":"venue"
},
  "geometry": {"coordinates":[-90.366474,38.762939],"type":"Point"}
}