{
  "type": "Feature",
  "properties": {
    "iso:country":"US",
    "sg:address":"302 S County Center Way",
    "sg:city":"St Louis",
    "sg:classifiers":[
        {
            "category":"Shopping",
            "subcategory":"Jewelry",
            "type":"Retail Goods"
        }
    ],
    "sg:phone":"+1 314 487 2321",
    "sg:postcode":"63129",
    "sg:province":"MO",
    "sg:tags":[
        "jeweler"
    ],
    "wof:name":"J B Robinson Jewelers",
    "wof:placetype":"venue"
},
  "geometry": {"coordinates":[-90.329838,38.505309],"type":"Point"}
}