{
  "type": "Feature",
  "properties": {
    "iso:country":"US",
    "sg:address":"16909 E 4 St S",
    "sg:city":"Independence",
    "sg:classifiers":[
        {
            "category":"Retail",
            "subcategory":"Car Wash",
            "type":"Services"
        }
    ],
    "sg:phone":"+1 816 215 9788",
    "sg:postcode":"64056",
    "sg:province":"MO",
    "sg:tags":[
        "polishing",
        "washing"
    ],
    "wof:name":"X-Treme Pressure Cleaning Svc",
    "wof:placetype":"venue"
},
  "geometry": {"coordinates":[-94.376418,39.103164],"type":"Point"}
}