{
  "type": "Feature",
  "properties": {
    "iso:country":"US",
    "sg:address":"2605 Hood Ave",
    "sg:city":"Saint Louis",
    "sg:classifiers":[
        {
            "category":"Health Services",
            "subcategory":"Health Practitioner",
            "type":"Services"
        }
    ],
    "sg:phone":"+1 314 994 1231",
    "sg:postcode":"63114",
    "sg:province":"MO",
    "sg:tags":[
        "organization",
        "religious"
    ],
    "wof:name":"Body Tunes",
    "wof:placetype":"venue"
},
  "geometry": {"coordinates":[-90.367847,38.706548],"type":"Point"}
}