{
  "type": "Feature",
  "properties": {
    "addr:full":"32 S Spanish St Cape Girardeau MO 63703",
    "addr:housenumber":"32",
    "addr:postcode":"63703",
    "addr:street":"S Spanish St",
    "iso:country":"US",
    "sg:address":"32 S Spanish St",
    "sg:city":"Cape Girardeau",
    "sg:classifiers":[
        {
            "category":"Professional",
            "subcategory":"Business Services",
            "type":"Services"
        }
    ],
    "sg:phone":"+1 573 335 6828",
    "sg:postcode":"63703",
    "sg:province":"MO",
    "wof:name":"Custom Designs",
    "wof:placetype":"venue"
},
  "geometry": {"coordinates":[-89.51953899999999,37.303013],"type":"Point"}
}