{
  "type": "Feature",
  "properties": {
    "iso:country":"US",
    "sg:address":"22740 Prairie Rd",
    "sg:city":"Prairie Home",
    "sg:classifiers":[
        {
            "category":"Farming",
            "subcategory":"Poultry Farm",
            "type":"Manufacturing & Wholesale Goods"
        }
    ],
    "sg:phone":"+1 660 427 5738",
    "sg:postcode":"65068",
    "sg:province":"MO",
    "sg:tags":[
        "egg"
    ],
    "wof:name":"Sells Farms",
    "wof:placetype":"venue"
},
  "geometry": {"coordinates":[-92.633251,38.774028],"type":"Point"}
}