{
  "type": "Feature",
  "properties": {
    "iso:country":"US",
    "sg:address":"63 Florissant Park Dr",
    "sg:city":"Florissant",
    "sg:classifiers":[
        {
            "category":"Banks & Credit Unions",
            "subcategory":"Bank",
            "type":"Services"
        }
    ],
    "sg:phone":"+1 314 921 2399",
    "sg:postcode":"63031",
    "sg:province":"MO",
    "wof:name":"Arsenal Credit Union",
    "wof:placetype":"venue"
},
  "geometry": {"coordinates":[-90.334639,38.804966],"type":"Point"}
}