{
  "type": "Feature",
  "properties": {
    "iso:country":"US",
    "sg:address":"2525 Bolton St",
    "sg:city":"St Charles",
    "sg:classifiers":[
        {
            "category":"Shopping",
            "type":"Retail Goods"
        }
    ],
    "sg:phone":"+1 636 949 0490",
    "sg:postcode":"63301",
    "sg:province":"MO",
    "sg:tags":[
        "wedding",
        "supply"
    ],
    "wof:name":"Double D Productions",
    "wof:placetype":"venue"
},
  "geometry": {"coordinates":[-90.53706,38.796549],"type":"Point"}
}