{
  "type": "Feature",
  "properties": {
    "iso:country":"US",
    "sg:address":"1800 E Liberty St",
    "sg:city":"Mexico",
    "sg:classifiers":[
        {
            "category":"Autos & Motor Vehicles",
            "subcategory":"Fuel & Gas Station",
            "type":"Retail Goods"
        },
        {
            "category":"Retail",
            "subcategory":"Auto Repair",
            "type":"Services"
        }
    ],
    "sg:phone":"+1 573 581 4429",
    "sg:postcode":"65265",
    "sg:province":"MO",
    "sg:website":"http://www.bp.com",
    "wof:name":"Amoco",
    "wof:placetype":"venue"
},
  "geometry": {"coordinates":[-91.884398,39.170569],"type":"Point"}
}