{
  "type": "Feature",
  "properties": {
    "iso:country":"US",
    "sg:address":"121 E Gregory Blvd",
    "sg:city":"Kansas City",
    "sg:classifiers":[
        {
            "category":"Building & Trades",
            "subcategory":"Electrical",
            "type":"Services"
        }
    ],
    "sg:phone":"+1 816 361 1117",
    "sg:postcode":"64114",
    "sg:province":"MO",
    "sg:tags":[
        "contracting",
        "electrical"
    ],
    "wof:name":"Harris Electric Service Inc",
    "wof:placetype":"venue"
},
  "geometry": {"coordinates":[-94.586977,38.999247],"type":"Point"}
}