{
  "type": "Feature",
  "properties": {
    "iso:country":"US",
    "sg:address":"19 E Gregory Blvd",
    "sg:city":"Kansas City",
    "sg:classifiers":[
        {
            "category":"Health Services",
            "subcategory":"Doctor",
            "type":"Services"
        }
    ],
    "sg:phone":"+1 816 444 2483",
    "sg:postcode":"64114",
    "sg:province":"MO",
    "sg:tags":[
        "dentist"
    ],
    "wof:name":"Children's Dental Care",
    "wof:placetype":"venue"
},
  "geometry": {"coordinates":[-94.588149,38.999296],"type":"Point"}
}