{
  "type": "Feature",
  "properties": {
    "iso:country":"US",
    "sg:address":"3050 Hwy 52",
    "sg:city":"Eldon",
    "sg:classifiers":[
        {
            "category":"Shopping",
            "subcategory":"Used Merchandise",
            "type":"Retail Goods"
        }
    ],
    "sg:phone":"+1 573 392 8400",
    "sg:postcode":"65026",
    "sg:province":"MO",
    "sg:tags":[
        "antique"
    ],
    "wof:name":"Red's Antique Mall",
    "wof:placetype":"venue"
},
  "geometry": {"coordinates":[-92.58748199999999,38.327336],"type":"Point"}
}