{
  "type": "Feature",
  "properties": {
    "addr:full":"901 State Hwy 25 Malden MO 63863",
    "addr:housenumber":"901",
    "addr:postcode":"63863",
    "addr:street":"State Hwy 25",
    "iso:country":"US",
    "sg:address":"901 State Hwy 25",
    "sg:city":"Malden",
    "sg:classifiers":[
        {
            "category":"Restaurant",
            "type":"Food & Drink"
        }
    ],
    "sg:phone":"+1 573 276 5101",
    "sg:postcode":"63863",
    "sg:province":"MO",
    "sg:tags":[
        "pizza"
    ],
    "wof:name":"Pizza Hut",
    "wof:placetype":"venue"
},
  "geometry": {"coordinates":[-89.96651199999999,36.54583],"type":"Point"}
}