{
  "type": "Feature",
  "properties": {
    "iso:country":"US",
    "sg:address":"106 Hwy C",
    "sg:city":"New Haven",
    "sg:classifiers":[
        {
            "category":"Food & Beverages",
            "subcategory":"Groceries & Convenience Stores",
            "type":"Retail Goods"
        }
    ],
    "sg:phone":"+1 573 237 9135",
    "sg:postcode":"63068",
    "sg:province":"MO",
    "sg:tags":[
        "carry",
        "out",
        "station",
        "gas",
        "pizza"
    ],
    "wof:name":"Caseys 1658",
    "wof:placetype":"venue"
},
  "geometry": {"coordinates":[-91.219419,38.600776],"type":"Point"}
}