{
  "type": "Feature",
  "properties": {
    "iso:country":"US",
    "sg:address":"160 Chesterfield Industrial Blvd",
    "sg:city":"Chesterfield",
    "sg:classifiers":[
        {
            "category":"Wholesale",
            "subcategory":"Tobacco Products",
            "type":"Manufacturing & Wholesale Goods"
        }
    ],
    "sg:phone":"+1 636 536 2513",
    "sg:postcode":"63005",
    "sg:province":"MO",
    "sg:tags":[
        "import",
        "cigarette"
    ],
    "wof:name":"Tradecorp International",
    "wof:placetype":"venue"
},
  "geometry": {"coordinates":[-90.621724,38.66493],"type":"Point"}
}