{
  "type": "Feature",
  "properties": {
    "iso:country":"US",
    "sg:address":"10815 E Winner Rd",
    "sg:city":"Independence",
    "sg:classifiers":[
        {
            "category":"Professional",
            "subcategory":"Business Services",
            "type":"Services"
        }
    ],
    "sg:phone":"+1 816 252 9192",
    "sg:postcode":"64052",
    "sg:province":"MO",
    "sg:tags":[
        "interior",
        "consultant",
        "design",
        "decorator"
    ],
    "wof:name":"Sermon-Anderson Inc",
    "wof:placetype":"venue"
},
  "geometry": {"coordinates":[-94.44957599999999,39.087634],"type":"Point"}
}