{
  "type": "Feature",
  "properties": {
    "iso:country":"US",
    "sg:address":"110 S Kingshighway St",
    "sg:city":"St Charles",
    "sg:classifiers":[
        {
            "category":"Health Services",
            "subcategory":"Podiatrist",
            "type":"Services"
        }
    ],
    "sg:phone":"+1 636 723 6454",
    "sg:postcode":"63301",
    "sg:province":"MO",
    "wof:name":"Saint Charles Foot Care Center",
    "wof:placetype":"venue"
},
  "geometry": {"coordinates":[-90.496887,38.785344],"type":"Point"}
}