{
  "type": "Feature",
  "properties": {
    "iso:country":"US",
    "sg:address":"1457 E Lindberg St",
    "sg:city":"Springfield",
    "sg:classifiers":[
        {
            "category":"Professional",
            "subcategory":"Business Services",
            "type":"Services"
        }
    ],
    "sg:phone":"+1 417 883 9602",
    "sg:postcode":"65804",
    "sg:province":"MO",
    "wof:name":"Window Dresser",
    "wof:placetype":"venue"
},
  "geometry": {"coordinates":[-93.270285,37.176349],"type":"Point"}
}