{
  "type": "Feature",
  "properties": {
    "iso:country":"US",
    "sg:address":"15700 Walnut Dr",
    "sg:city":"Falcon",
    "sg:classifiers":[
        {
            "category":"Farming",
            "subcategory":"Livestock Farm",
            "type":"Manufacturing & Wholesale Goods"
        }
    ],
    "sg:phone":"+1 417 453 6470",
    "sg:postcode":"65470",
    "sg:province":"MO",
    "sg:tags":[
        "beef",
        "feedlot",
        "cattle"
    ],
    "wof:name":"James Mansker",
    "wof:placetype":"venue"
},
  "geometry": {"coordinates":[-92.28487699999999,37.557106],"type":"Point"}
}