{
  "type": "Feature",
  "properties": {
    "iso:country":"US",
    "sg:address":"510 Stone Ridge Rd",
    "sg:city":"Joplin",
    "sg:classifiers":[
        {
            "category":"Organizations",
            "subcategory":"Religious Organization",
            "type":"Services"
        }
    ],
    "sg:phone":"+1 417 623 0712",
    "sg:postcode":"64804",
    "sg:province":"MO",
    "wof:name":"Paul F Dilts Rev",
    "wof:placetype":"venue"
},
  "geometry": {"coordinates":[-94.508499,37.04194],"type":"Point"}
}