{
  "type": "Feature",
  "properties": {
    "iso:country":"US",
    "sg:address":"2545 W Kearney St",
    "sg:city":"Springfield",
    "sg:classifiers":[
        {
            "category":"Wholesale",
            "subcategory":"Construction Materials",
            "type":"Manufacturing & Wholesale Goods"
        }
    ],
    "sg:phone":"+1 417 831 0900",
    "sg:postcode":"65803",
    "sg:province":"MO",
    "sg:tags":[
        "equipment",
        "masonry",
        "supply"
    ],
    "wof:name":"Alandsons Supply Co Inc",
    "wof:placetype":"venue"
},
  "geometry": {"coordinates":[-93.32625299999999,37.24127],"type":"Point"}
}