{
  "type": "Feature",
  "properties": {
    "iso:country":"US",
    "sg:address":"4436 W Manufacturers St",
    "sg:city":"Springfield",
    "sg:classifiers":[
        {
            "category":"Professional",
            "subcategory":"Business Services",
            "type":"Services"
        }
    ],
    "sg:phone":"+1 417 862 9511",
    "sg:postcode":"65803",
    "sg:province":"MO",
    "sg:tags":[
        "mail",
        "messenger",
        "shipping"
    ],
    "wof:name":"Core Design",
    "wof:placetype":"venue"
},
  "geometry": {"coordinates":[-93.370165,37.236],"type":"Point"}
}