{
  "type": "Feature",
  "properties": {
    "iso:country":"US",
    "sg:address":"2284 State Hwy B",
    "sg:city":"Elsberry",
    "sg:classifiers":[
        {
            "category":"Building & Trades",
            "subcategory":"Construction",
            "type":"Services"
        }
    ],
    "sg:phone":"+1 573 898 9884",
    "sg:postcode":"63343",
    "sg:province":"MO",
    "sg:tags":[
        "excavating",
        "contractor"
    ],
    "wof:name":"Mound Excavating LLC",
    "wof:placetype":"venue"
},
  "geometry": {"coordinates":[-90.85032,39.142206],"type":"Point"}
}