{
  "type": "Feature",
  "properties": {
    "iso:country":"US",
    "sg:address":"4246 Shaw Blvd",
    "sg:city":"St Louis",
    "sg:classifiers":[
        {
            "category":"Organizations",
            "subcategory":"Religious Organization",
            "type":"Services"
        }
    ],
    "sg:phone":"+1 314 771 5714",
    "sg:postcode":"63110",
    "sg:province":"MO",
    "sg:tags":[
        "church"
    ],
    "wof:name":"Mount Olive Baptist Church",
    "wof:placetype":"venue"
},
  "geometry": {"coordinates":[-90.25521500000001,38.61648],"type":"Point"}
}