{
  "type": "Feature",
  "properties": {
    "iso:country":"US",
    "sg:address":"485 Wildwood Pkwy",
    "sg:city":"Ballwin",
    "sg:classifiers":[
        {
            "category":"Health Services",
            "subcategory":"Chiropractor",
            "type":"Services"
        },
        {
            "category":"Professional",
            "subcategory":"Business Services",
            "type":"Services"
        }
    ],
    "sg:phone":"+1 636 391 1800",
    "sg:postcode":"63011",
    "sg:province":"MO",
    "wof:name":"Health Solutions",
    "wof:placetype":"venue"
},
  "geometry": {"coordinates":[-90.53707199999999,38.617527],"type":"Point"}
}