{
  "type": "Feature",
  "properties": {
    "iso:country":"US",
    "sg:address":"1729 Grand Blvd",
    "sg:city":"Kansas City",
    "sg:classifiers":[
        {
            "category":"Government",
            "subcategory":"Office",
            "type":"Public Place"
        }
    ],
    "sg:phone":"+1 816 234 5968",
    "sg:postcode":"64108",
    "sg:province":"MO",
    "sg:tags":[
        "department",
        "health",
        "mental"
    ],
    "wof:name":"Regional Coordinator",
    "wof:placetype":"venue"
},
  "geometry": {"coordinates":[-94.581244,39.092178],"type":"Point"}
}