{
  "type": "Feature",
  "properties": {
    "iso:country":"US",
    "sg:address":"1840 W Maple St",
    "sg:city":"Nevada",
    "sg:classifiers":[
        {
            "category":"Wholesale",
            "subcategory":"Vending Machines",
            "type":"Manufacturing & Wholesale Goods"
        }
    ],
    "sg:phone":"+1 417 667 3899",
    "sg:postcode":"64772",
    "sg:province":"MO",
    "wof:name":"Stangeland Vending & Distr",
    "wof:placetype":"venue"
},
  "geometry": {"coordinates":[-94.382334,37.834344],"type":"Point"}
}