{
  "type": "Feature",
  "properties": {
    "iso:country":"US",
    "sg:address":"7090 NE State Rte 6",
    "sg:city":"St Joseph",
    "sg:classifiers":[
        {
            "category":"Retail",
            "subcategory":"Animal Services",
            "type":"Services"
        }
    ],
    "sg:phone":"+1 816 667 5717",
    "sg:postcode":"64507",
    "sg:province":"MO",
    "sg:tags":[
        "pet",
        "boarding",
        "sitting"
    ],
    "wof:name":"Evergreen Boarding Kennels",
    "wof:placetype":"venue"
},
  "geometry": {"coordinates":[-94.736852,39.783939],"type":"Point"}
}