{
  "type": "Feature",
  "properties": {
    "iso:country":"US",
    "sg:address":"101 N 4th St",
    "sg:city":"Columbia",
    "sg:classifiers":[
        {
            "category":"Professional",
            "subcategory":"Advertising",
            "type":"Services"
        }
    ],
    "sg:phone":"+1 573 874 6420",
    "sg:postcode":"65201",
    "sg:province":"MO",
    "sg:tags":[
        "mail",
        "direct"
    ],
    "wof:name":"Ad Mail",
    "wof:placetype":"venue"
},
  "geometry": {"coordinates":[-92.33288899999999,38.95368],"type":"Point"}
}