{
  "type": "Feature",
  "properties": {
    "iso:country":"US",
    "sg:address":"1376 Ferguson Ave",
    "sg:city":"St Louis",
    "sg:classifiers":[
        {
            "category":"Wholesale",
            "subcategory":"Machinery & Supplies",
            "type":"Manufacturing & Wholesale Goods"
        },
        {
            "category":"Manufacturing",
            "subcategory":"Motor Vehicles & Parts",
            "type":"Manufacturing & Wholesale Goods"
        }
    ],
    "sg:phone":"+1 314 721 5111",
    "sg:postcode":"63133",
    "sg:province":"MO",
    "sg:tags":[
        "on",
        "bottler",
        "screen",
        "plastic",
        "equipment",
        "printing"
    ],
    "wof:name":"Pogue Label & Screen Inc",
    "wof:placetype":"venue"
},
  "geometry": {"coordinates":[-90.308301,38.678133],"type":"Point"}
}