{
  "type": "Feature",
  "properties": {
    "iso:country":"US",
    "sg:address":"12730 Dorsett Rd",
    "sg:city":"Maryland Heights",
    "sg:classifiers":[
        {
            "category":"Restaurant",
            "type":"Food & Drink"
        }
    ],
    "sg:menulink":"http://www.allmenus.com/mo/maryland-heights/210925-arbys/menu/",
    "sg:phone":"+1 314 576 4200",
    "sg:postcode":"63043",
    "sg:province":"MO",
    "sg:tags":[
        "burger",
        "american"
    ],
    "wof:name":"Arby's",
    "wof:placetype":"venue"
},
  "geometry": {"coordinates":[-90.458158,38.714156],"type":"Point"}
}