{
  "type": "Feature",
  "properties": {
    "iso:country":"US",
    "sg:address":"2620 Forum Blvd",
    "sg:city":"Columbia",
    "sg:classifiers":[
        {
            "category":"Health Services",
            "subcategory":"Medical Lab",
            "type":"Services"
        }
    ],
    "sg:phone":"+1 573 446 2015",
    "sg:postcode":"65203",
    "sg:province":"MO",
    "sg:tags":[
        "laboratory",
        "dental"
    ],
    "wof:name":"Stewart Dental Lab",
    "wof:placetype":"venue"
},
  "geometry": {"coordinates":[-92.365347,38.92252],"type":"Point"}
}