{
  "type": "Feature",
  "properties": {
    "iso:country":"US",
    "sg:address":"1821 Queen Anne Ct",
    "sg:city":"Wentzville",
    "sg:classifiers":[
        {
            "category":"Organizations",
            "subcategory":"Religious Organization",
            "type":"Services"
        }
    ],
    "sg:phone":"+1 636 327 6728",
    "sg:postcode":"63385",
    "sg:province":"MO",
    "wof:name":"Christian Vision Church",
    "wof:placetype":"venue"
},
  "geometry": {"coordinates":[-90.885942,38.834828],"type":"Point"}
}