{
  "type": "Feature",
  "properties": {
    "iso:country":"US",
    "sg:address":"1004 N College Ave",
    "sg:city":"Columbia",
    "sg:classifiers":[
        {
            "category":"Shopping",
            "subcategory":"Used Merchandise",
            "type":"Retail Goods"
        }
    ],
    "sg:phone":"+1 573 449 3964",
    "sg:postcode":"65201",
    "sg:province":"MO",
    "sg:tags":[
        "pawnshop",
        "operates"
    ],
    "wof:name":"Family Pawn Store",
    "wof:placetype":"venue"
},
  "geometry": {"coordinates":[-92.321135,38.961619],"type":"Point"}
}