{
  "type": "Feature",
  "properties": {
    "iso:country":"US",
    "sg:address":"29 Summerhill Ln",
    "sg:city":"Chesterfield",
    "sg:classifiers":[
        {
            "category":"Professional",
            "subcategory":"Management & Consulting",
            "type":"Services"
        }
    ],
    "sg:phone":"+1 314 453 0588",
    "sg:postcode":"63017",
    "sg:province":"MO",
    "wof:name":"Robert Taylor",
    "wof:placetype":"venue"
},
  "geometry": {"coordinates":[-90.500244,38.627402],"type":"Point"}
}