{
  "type": "Feature",
  "properties": {
    "iso:country":"US",
    "sg:address":"3114 N Belt Hwy",
    "sg:city":"Saint Joseph",
    "sg:classifiers":[
        {
            "category":"Restaurant",
            "type":"Food & Drink"
        }
    ],
    "sg:menulink":"http://www.allmenus.com/mo/st-joseph/148527-subway/menu/",
    "sg:phone":"+1 816 232 3362",
    "sg:postcode":"64506",
    "sg:province":"MO",
    "sg:tags":[
        "american",
        "sandwich"
    ],
    "wof:name":"Subway",
    "wof:placetype":"venue"
},
  "geometry": {"coordinates":[-94.813385,39.796948],"type":"Point"}
}