{
  "type": "Feature",
  "properties": {
    "iso:country":"US",
    "sg:address":"7268 Manchester Rd",
    "sg:city":"Saint Louis",
    "sg:classifiers":[
        {
            "category":"Shopping",
            "subcategory":"Antiques",
            "type":"Retail Goods"
        },
        {
            "category":"Building & Trades",
            "subcategory":"Construction",
            "type":"Services"
        }
    ],
    "sg:phone":"+1 314 644 0828",
    "sg:postcode":"63143",
    "sg:province":"MO",
    "sg:tags":[
        "interior",
        "design"
    ],
    "wof:name":"Elizabeth House",
    "wof:placetype":"venue"
},
  "geometry": {"coordinates":[-90.316101,38.613701],"type":"Point"}
}