{
  "type": "Feature",
  "properties": {
    "addr:full":"8440 N Madison Ave Kansas City MO 64155",
    "addr:housenumber":"8440",
    "addr:postcode":"64155",
    "addr:street":"N Madison Ave",
    "iso:country":"US",
    "sg:address":"8440 N Madison Ave",
    "sg:city":"Kansas City",
    "sg:classifiers":[
        {
            "category":"Shopping",
            "subcategory":"Hobbies, Toys, & Games",
            "type":"Retail Goods"
        }
    ],
    "sg:phone":"+1 816 468 8692",
    "sg:postcode":"64155",
    "sg:province":"MO",
    "sg:tags":[
        "craft",
        "supply"
    ],
    "wof:name":"Michaels Arts & Crafts Store",
    "wof:placetype":"venue"
},
  "geometry": {"coordinates":[-94.59343200000001,39.247486],"type":"Point"}
}