{
  "type": "Feature",
  "properties": {
    "iso:country":"US",
    "sg:address":"1016 S Brentwood Blvd",
    "sg:city":"St Louis",
    "sg:classifiers":[
        {
            "category":"Shopping",
            "subcategory":"Clothing, Apparel, & Fashions",
            "type":"Retail Goods"
        }
    ],
    "sg:phone":"+1 314 721 3356",
    "sg:postcode":"63117",
    "sg:province":"MO",
    "sg:tags":[
        "furnishing"
    ],
    "sg:website":"www.menswarehouse.com",
    "wof:name":"Men's Wearhouse",
    "wof:placetype":"venue"
},
  "geometry": {"coordinates":[-90.345551,38.637489],"type":"Point"}
}