{
  "type": "Feature",
  "properties": {
    "iso:country":"US",
    "sg:address":"313 S Liberty St",
    "sg:city":"Independence",
    "sg:classifiers":[
        {
            "category":"Government",
            "subcategory":"Office",
            "type":"Public Place"
        }
    ],
    "sg:phone":"+1 816 404 6415",
    "sg:postcode":"64050",
    "sg:province":"MO",
    "sg:tags":[
        "county",
        "program",
        "health"
    ],
    "wof:name":"Jackson County Health Dept",
    "wof:placetype":"venue"
},
  "geometry": {"coordinates":[-94.417157,39.089656],"type":"Point"}
}