{
  "type": "Feature",
  "properties": {
    "iso:country":"US",
    "sg:address":"815 Locust St",
    "sg:city":"Saint Louis",
    "sg:classifiers":[
        {
            "category":"Building & Trades",
            "subcategory":"Construction",
            "type":"Services"
        }
    ],
    "sg:phone":"+1 314 522 0512",
    "sg:postcode":"63101",
    "sg:province":"MO",
    "sg:tags":[
        "house",
        "industrial",
        "co"
    ],
    "wof:name":"Lombardo & Sons LLC",
    "wof:placetype":"venue"
},
  "geometry": {"coordinates":[-90.192362,38.629471],"type":"Point"}
}