{
  "type": "Feature",
  "properties": {
    "iso:country":"US",
    "sg:address":"3608 Bates St",
    "sg:city":"Saint Louis",
    "sg:classifiers":[
        {
            "category":"Food & Beverages",
            "subcategory":"Groceries & Convenience Stores",
            "type":"Retail Goods"
        }
    ],
    "sg:phone":"+1 314 352 4999",
    "sg:postcode":"63116",
    "sg:province":"MO",
    "sg:tags":[
        "grocer"
    ],
    "wof:name":"Ariana Market",
    "wof:placetype":"venue"
},
  "geometry": {"coordinates":[-90.254733,38.568589],"type":"Point"}
}