{
  "type": "Feature",
  "properties": {
    "iso:country":"US",
    "sg:address":"12300 Hibler Oaks Ct",
    "sg:city":"Saint Louis",
    "sg:classifiers":[
        {
            "category":"Professional",
            "subcategory":"Business Services",
            "type":"Services"
        }
    ],
    "sg:phone":"+1 314 434 3485",
    "sg:postcode":"63141",
    "sg:province":"MO",
    "wof:name":"Susan Taylor Interior",
    "wof:placetype":"venue"
},
  "geometry": {"coordinates":[-90.458226,38.661605],"type":"Point"}
}