{
  "type": "Feature",
  "properties": {
    "iso:country":"US",
    "sg:address":"33 High Trails Dr",
    "sg:city":"Eureka",
    "sg:classifiers":[
        {
            "category":"Shopping",
            "subcategory":"Stationery & Office Supplies",
            "type":"Retail Goods"
        },
        {
            "category":"Professional",
            "subcategory":"Advertising",
            "type":"Services"
        }
    ],
    "sg:phone":"+1 636 587 2943",
    "sg:postcode":"63025",
    "sg:province":"MO",
    "wof:name":"Global Docu Graphix",
    "wof:placetype":"venue"
},
  "geometry": {"coordinates":[-90.63441,38.46441],"type":"Point"}
}