{
  "type": "Feature",
  "properties": {
    "iso:country":"US",
    "sg:address":"110 E Main St",
    "sg:city":"Sedalia",
    "sg:classifiers":[
        {
            "category":"Professional",
            "subcategory":"Art Services",
            "type":"Services"
        }
    ],
    "sg:phone":"+1 660 827 5154",
    "sg:postcode":"65301",
    "sg:province":"MO",
    "sg:tags":[
        "artist"
    ],
    "wof:name":"Freed Douglass Studio",
    "wof:placetype":"venue"
},
  "geometry": {"coordinates":[-93.22749399999999,38.710599],"type":"Point"}
}