{
  "type": "Feature",
  "properties": {
    "iso:country":"US",
    "sg:address":"3438 Troost Ave",
    "sg:city":"Kansas City",
    "sg:classifiers":[
        {
            "category":"Autos & Motor Vehicles",
            "subcategory":"Fuel & Gas Station",
            "type":"Retail Goods"
        }
    ],
    "sg:phone":"+1 816 931 4201",
    "sg:postcode":"64109",
    "sg:province":"MO",
    "sg:tags":[
        "station",
        "gasoline"
    ],
    "wof:name":"Service Oil Company",
    "wof:placetype":"venue"
},
  "geometry": {"coordinates":[-94.57177299999999,39.063867],"type":"Point"}
}