{
  "type": "Feature",
  "properties": {
    "iso:country":"US",
    "sg:address":"400 W Mechanic St",
    "sg:city":"Harrisonville",
    "sg:classifiers":[
        {
            "category":"Travel",
            "subcategory":"Hotels & Motels",
            "type":"Entertainment"
        },
        {
            "category":"Travel",
            "subcategory":"Bed & Breakfast",
            "type":"Entertainment"
        }
    ],
    "sg:phone":"+1 816 380 7800",
    "sg:postcode":"64701",
    "sg:province":"MO",
    "sg:tags":[
        "inn",
        "lodging"
    ],
    "wof:name":"Shiloh Bed & Breakfast",
    "wof:placetype":"venue"
},
  "geometry": {"coordinates":[-94.346611,38.65308],"type":"Point"}
}