{
  "type": "Feature",
  "properties": {
    "iso:country":"US",
    "sg:address":"3029 S Campbell Ave",
    "sg:city":"Springfield",
    "sg:classifiers":[
        {
            "category":"Restaurant",
            "type":"Food & Drink"
        }
    ],
    "sg:menulink":"http://www.allmenus.com/mo/springfield/52143-chinese-chef/menu/",
    "sg:phone":"+1 417 883 4770",
    "sg:postcode":"65807",
    "sg:province":"MO",
    "sg:tags":[
        "asian",
        "chinese"
    ],
    "wof:name":"Chinese Chef",
    "wof:placetype":"venue"
},
  "geometry": {"coordinates":[-93.29547599999999,37.159029],"type":"Point"}
}