{
  "type": "Feature",
  "properties": {
    "iso:country":"US",
    "sg:address":"1924 W 4th St",
    "sg:city":"Joplin",
    "sg:classifiers":[
        {
            "category":"Retail",
            "subcategory":"Auto Rental",
            "type":"Services"
        }
    ],
    "sg:phone":"+1 417 781 6411",
    "sg:postcode":"64801",
    "sg:province":"MO",
    "sg:tags":[
        "renting",
        "automobile",
        "passenger",
        "car"
    ],
    "wof:name":"A & A Auto Rental",
    "wof:placetype":"venue"
},
  "geometry": {"coordinates":[-94.537379,37.088272],"type":"Point"}
}