{
  "type": "Feature",
  "properties": {
    "iso:country":"US",
    "sg:address":"3701 W Geospace Dr",
    "sg:city":"Independence",
    "sg:classifiers":[
        {
            "category":"Professional",
            "subcategory":"Business Services",
            "type":"Services"
        }
    ],
    "sg:phone":"+1 816 257 0690",
    "sg:postcode":"64056",
    "sg:province":"MO",
    "wof:name":"Secure Document Solutions",
    "wof:placetype":"venue"
},
  "geometry": {"coordinates":[-94.373808,39.100403],"type":"Point"}
}