{
  "type": "Feature",
  "properties": {
    "iso:country":"US",
    "sg:address":"155 Twin City Mall",
    "sg:city":"Crystal City",
    "sg:classifiers":[
        {
            "category":"Retail",
            "subcategory":"Portrait Studio",
            "type":"Services"
        }
    ],
    "sg:phone":"+1 314 933 0394",
    "sg:postcode":"63019",
    "sg:province":"MO",
    "wof:name":"Olan Mills Studios",
    "wof:placetype":"venue"
},
  "geometry": {"coordinates":[-90.38760600000001,38.218253],"type":"Point"}
}