{
  "type": "Feature",
  "properties": {
    "iso:country":"US",
    "sg:address":"2841 State Highway 86 Ste D",
    "sg:city":"Ridgedale",
    "sg:classifiers":[
        {
            "category":"Real Estate",
            "subcategory":"Real Estate Services",
            "type":"Services"
        },
        {
            "category":"Real Estate",
            "subcategory":"Real Estate Agent",
            "type":"Services"
        }
    ],
    "sg:phone":"+1 417 335 5253",
    "sg:postcode":"65739",
    "sg:province":"MO",
    "sg:tags":[
        "buyer",
        "broker"
    ],
    "wof:name":"Tri Lakes Realtors Inc",
    "wof:placetype":"venue"
},
  "geometry": {"coordinates":[-93.2993,36.527854],"type":"Point"}
}