{
  "type": "Feature",
  "properties": {
    "iso:country":"US",
    "sg:address":"8511 Hillcrest Rd",
    "sg:city":"Kansas City",
    "sg:classifiers":[
        {
            "category":"Health Services",
            "subcategory":"Doctor",
            "type":"Services"
        }
    ],
    "sg:phone":"+1 816 361 7755",
    "sg:postcode":"64138",
    "sg:province":"MO",
    "sg:tags":[
        "physician",
        "surgeon"
    ],
    "wof:name":"Concentra Medical Ctr",
    "wof:placetype":"venue"
},
  "geometry": {"coordinates":[-94.52087899999999,38.971174],"type":"Point"}
}