{
  "type": "Feature",
  "properties": {
    "iso:country":"US",
    "sg:address":"1001 Cherry St",
    "sg:city":"Columbia",
    "sg:classifiers":[
        {
            "category":"Real Estate",
            "subcategory":"Real Estate Agent",
            "type":"Services"
        }
    ],
    "sg:phone":"+1 573 442 3037",
    "sg:postcode":"65201",
    "sg:province":"MO",
    "wof:name":"Tkg Real Estate Services",
    "wof:placetype":"venue"
},
  "geometry": {"coordinates":[-92.32550999999999,38.95045],"type":"Point"}
}