{
  "type": "Feature",
  "properties": {
    "iso:country":"US",
    "sg:address":"1715 S Madison St",
    "sg:city":"Webb City",
    "sg:classifiers":[
        {
            "category":"Food & Beverages",
            "subcategory":"Groceries & Convenience Stores",
            "type":"Retail Goods"
        }
    ],
    "sg:phone":"+1 417 673 4426",
    "sg:postcode":"64870",
    "sg:province":"MO",
    "wof:name":"Perrys Market",
    "wof:placetype":"venue"
},
  "geometry": {"coordinates":[-94.475472,37.125002],"type":"Point"}
}