{
  "type": "Feature",
  "properties": {
    "iso:country":"US",
    "sg:address":"1623 Jeffco Blvd",
    "sg:city":"Arnold",
    "sg:classifiers":[
        {
            "category":"Health Services",
            "subcategory":"Clinic",
            "type":"Services"
        }
    ],
    "sg:phone":"+1 636 282 2649",
    "sg:postcode":"63010",
    "sg:province":"MO",
    "wof:name":"United Health Care Workers",
    "wof:placetype":"venue"
},
  "geometry": {"coordinates":[-90.37937100000001,38.43099],"type":"Point"}
}