{
  "type": "Feature",
  "properties": {
    "iso:country":"US",
    "sg:address":"4703 N Mulberry Ct",
    "sg:city":"Kansas City",
    "sg:classifiers":[
        {
            "category":"Professional",
            "subcategory":"Advertising",
            "type":"Services"
        }
    ],
    "sg:phone":"+1 816 746 6699",
    "sg:postcode":"64116",
    "sg:province":"MO",
    "sg:tags":[
        "mail",
        "direct"
    ],
    "wof:name":"McManus Direct",
    "wof:placetype":"venue"
},
  "geometry": {"coordinates":[-94.598024,39.180753],"type":"Point"}
}