{
  "type": "Feature",
  "properties": {
    "iso:country":"US",
    "sg:address":"5728 Hwy C",
    "sg:city":"Joplin",
    "sg:classifiers":[
        {
            "category":"Manufacturing",
            "subcategory":"Signs",
            "type":"Manufacturing & Wholesale Goods"
        }
    ],
    "sg:phone":"+1 417 626 2086",
    "sg:postcode":"64804",
    "sg:province":"MO",
    "sg:tags":[
        "specialty",
        "mfg"
    ],
    "wof:name":"Hammer's Signs",
    "wof:placetype":"venue"
},
  "geometry": {"coordinates":[-94.53722399999999,36.98798],"type":"Point"}
}