{
  "type": "Feature",
  "properties": {
    "iso:country":"US",
    "sg:address":"300 W Washington St",
    "sg:city":"Kirksville",
    "sg:classifiers":[
        {
            "category":"Personal",
            "subcategory":"Beauty Salon",
            "type":"Services"
        }
    ],
    "sg:phone":"+1 660 665 2222",
    "sg:postcode":"63501",
    "sg:province":"MO",
    "sg:tags":[
        "shop"
    ],
    "wof:name":"Razors Edge",
    "wof:placetype":"venue"
},
  "geometry": {"coordinates":[-92.585363,40.1947],"type":"Point"}
}