{
  "type": "Feature",
  "properties": {
    "iso:country":"US",
    "sg:address":"5901 Beechwood Ct",
    "sg:city":"Parkville",
    "sg:classifiers":[
        {
            "category":"Professional",
            "subcategory":"Management & Consulting",
            "type":"Services"
        }
    ],
    "sg:phone":"+1 816 891 2444",
    "sg:postcode":"64152",
    "sg:province":"MO",
    "sg:tags":[
        "construction"
    ],
    "wof:name":"Homoly & Assoc",
    "wof:placetype":"venue"
},
  "geometry": {"coordinates":[-94.66110399999999,39.206551],"type":"Point"}
}