{
  "type": "Feature",
  "properties": {
    "iso:country":"US",
    "sg:address":"601 Magnolia Ave",
    "sg:city":"Poplar Bluff",
    "sg:classifiers":[
        {
            "category":"Autos & Motor Vehicles",
            "subcategory":"Auto Supplies",
            "type":"Retail Goods"
        }
    ],
    "sg:phone":"+1 573 785 2519",
    "sg:postcode":"63901",
    "sg:province":"MO",
    "sg:tags":[
        "tire"
    ],
    "wof:name":"Crow Tire Inc",
    "wof:placetype":"venue"
},
  "geometry": {"coordinates":[-90.38256699999999,36.760296],"type":"Point"}
}