{
  "type": "Feature",
  "properties": {
    "iso:country":"US",
    "sg:address":"2910 Osceola",
    "sg:city":"St Louis",
    "sg:classifiers":[
        {
            "category":"Building & Trades",
            "subcategory":"Cleaning & Sanitation",
            "type":"Services"
        },
        {
            "category":"Shopping",
            "subcategory":"Pets & Pet Supplies",
            "type":"Retail Goods"
        },
        {
            "category":"Retail",
            "subcategory":"Pet Boarding",
            "type":"Services"
        }
    ],
    "sg:phone":"+1 314 223 3358",
    "sg:postcode":"63111",
    "sg:province":"MO",
    "sg:tags":[
        "walker",
        "home",
        "dog",
        "boarding/pet",
        "sitting"
    ],
    "wof:name":"Vacuum and a Leash",
    "wof:placetype":"venue"
},
  "geometry": {"coordinates":[-90.236845,38.576199],"type":"Point"}
}