{
  "type": "Feature",
  "properties": {
    "iso:country":"US",
    "sg:address":"800 Broadway St",
    "sg:city":"Kansas City",
    "sg:classifiers":[
        {
            "category":"Shopping",
            "subcategory":"Used Merchandise",
            "type":"Retail Goods"
        },
        {
            "category":"Home & Garden",
            "subcategory":"Furniture",
            "type":"Retail Goods"
        }
    ],
    "sg:phone":"+1 816 471 0990",
    "sg:postcode":"64105",
    "sg:province":"MO",
    "wof:name":"Gerald Jones & Co Inc",
    "wof:placetype":"venue"
},
  "geometry": {"coordinates":[-94.58825,39.103745],"type":"Point"}
}