{
  "type": "Feature",
  "properties": {
    "iso:country":"US",
    "sg:address":"7382 Pershing Ave",
    "sg:city":"St Louis",
    "sg:classifiers":[
        {
            "category":"Education",
            "subcategory":"Special Training",
            "type":"Public Place"
        }
    ],
    "sg:phone":"+1 314 726 1215",
    "sg:postcode":"63130",
    "sg:province":"MO",
    "sg:tags":[
        "tutoring"
    ],
    "wof:name":"Professional Skills Institute",
    "wof:placetype":"venue"
},
  "geometry": {"coordinates":[-90.32907899999999,38.653447],"type":"Point"}
}