{
  "type": "Feature",
  "properties": {
    "iso:country":"US",
    "sg:address":"901 E Saint Louis St",
    "sg:city":"Springfield",
    "sg:classifiers":[
        {
            "category":"Government",
            "subcategory":"Office",
            "type":"Public Place"
        }
    ],
    "sg:phone":"+1 417 831 5226",
    "sg:postcode":"65806",
    "sg:province":"MO",
    "sg:tags":[
        "government-united",
        "state"
    ],
    "wof:name":"US Department of Labor",
    "wof:placetype":"venue"
},
  "geometry": {"coordinates":[-93.28193400000001,37.208874],"type":"Point"}
}