{
  "type": "Feature",
  "properties": {
    "iso:country":"US",
    "sg:address":"10853 Chase Park Ln",
    "sg:city":"St Louis",
    "sg:classifiers":[
        {
            "category":"Autos & Motor Vehicles",
            "subcategory":"Automobile Sales",
            "type":"Retail Goods"
        }
    ],
    "sg:phone":"+1 314 692 7117",
    "sg:postcode":"63141",
    "sg:province":"MO",
    "sg:tags":[
        "equipment",
        "aircraft",
        "parts",
        "supply"
    ],
    "wof:name":"Hamilton Sundstrand",
    "wof:placetype":"venue"
},
  "geometry": {"coordinates":[-90.41980599999999,38.674278],"type":"Point"}
}