{
  "type": "Feature",
  "properties": {
    "iso:country":"US",
    "sg:address":"320 US Hwy 60 Bus",
    "sg:city":"Dexter",
    "sg:classifiers":[
        {
            "category":"Shopping",
            "type":"Retail Goods"
        }
    ],
    "sg:phone":"+1 573 624 8488",
    "sg:postcode":"63841",
    "sg:province":"MO",
    "sg:tags":[
        "equipment",
        "telephone",
        "supply"
    ],
    "wof:name":"Le Grand's Communications Inc",
    "wof:placetype":"venue"
},
  "geometry": {"coordinates":[-89.962433,36.799847],"type":"Point"}
}