{
  "type": "Feature",
  "properties": {
    "iso:country":"US",
    "sg:address":"310 E Old Plank Rd",
    "sg:city":"Columbia",
    "sg:classifiers":[
        {
            "category":"Social Services",
            "subcategory":"Child Care",
            "type":"Services"
        }
    ],
    "sg:phone":"+1 573 442 4487",
    "sg:postcode":"65203",
    "sg:province":"MO",
    "sg:tags":[
        "day",
        "night"
    ],
    "wof:name":"Patricia Forward",
    "wof:placetype":"venue"
},
  "geometry": {"coordinates":[-92.34160799999999,38.891574],"type":"Point"}
}