{
  "type": "Feature",
  "properties": {
    "iso:country":"US",
    "sg:address":"16408 US Hwy 63 N",
    "sg:city":"Sturgeon",
    "sg:classifiers":[
        {
            "category":"Social Services",
            "subcategory":"Child Care",
            "type":"Services"
        }
    ],
    "sg:phone":"+1 573 817 9338",
    "sg:postcode":"65284",
    "sg:province":"MO",
    "sg:tags":[
        "day"
    ],
    "wof:name":"Busy Bees Daycare",
    "wof:placetype":"venue"
},
  "geometry": {"coordinates":[-92.33159499999999,39.145145],"type":"Point"}
}