{
  "type": "Feature",
  "properties": {
    "iso:country":"US",
    "sg:address":"16009 Manchester Rd",
    "sg:city":"Ballwin",
    "sg:classifiers":[
        {
            "category":"Shopping",
            "subcategory":"Jewelry",
            "type":"Retail Goods"
        }
    ],
    "sg:phone":"+1 636 532 3626",
    "sg:postcode":"63011",
    "sg:province":"MO",
    "sg:tags":[
        "jeweler"
    ],
    "wof:name":"Robert Hunn Jewelers Inc",
    "wof:placetype":"venue"
},
  "geometry": {"coordinates":[-90.59693300000001,38.590364],"type":"Point"}
}