{
  "type": "Feature",
  "properties": {
    "iso:country":"US",
    "sg:address":"205 E Broadway St",
    "sg:city":"Monett",
    "sg:classifiers":[
        {
            "category":"Home & Garden",
            "subcategory":"Furniture",
            "type":"Retail Goods"
        }
    ],
    "sg:phone":"+1 417 235 1006",
    "sg:postcode":"65708",
    "sg:province":"MO",
    "sg:tags":[
        "store"
    ],
    "wof:name":"Terry's Outlet",
    "wof:placetype":"venue"
},
  "geometry": {"coordinates":[-93.925068,36.920331],"type":"Point"}
}