{
  "type": "Feature",
  "properties": {
    "iso:country":"US",
    "sg:address":"14531 Audrain Rd 937",
    "sg:city":"Mexico",
    "sg:classifiers":[
        {
            "category":"Farming",
            "subcategory":"Livestock Farm",
            "type":"Manufacturing & Wholesale Goods"
        }
    ],
    "sg:phone":"+1 573 581 2625",
    "sg:postcode":"65265",
    "sg:province":"MO",
    "sg:tags":[
        "soybean",
        "general"
    ],
    "wof:name":"David Moore",
    "wof:placetype":"venue"
},
  "geometry": {"coordinates":[-91.968591,39.127906],"type":"Point"}
}