{
  "type": "Feature",
  "properties": {
    "iso:country":"US",
    "sg:address":"562 Axminister Dr",
    "sg:city":"Fenton",
    "sg:classifiers":[
        {
            "category":"Banks & Credit Unions",
            "subcategory":"Bank",
            "type":"Services"
        }
    ],
    "sg:phone":"+1 636 533 0145",
    "sg:postcode":"63026",
    "sg:province":"MO",
    "sg:tags":[
        "personal",
        "institution"
    ],
    "wof:name":"American Credit Services LLC",
    "wof:placetype":"venue"
},
  "geometry": {"coordinates":[-90.44837200000001,38.536798],"type":"Point"}
}