{
  "type": "Feature",
  "properties": {
    "iso:country":"US",
    "sg:address":"607 State Highway 165 # 8",
    "sg:city":"Branson",
    "sg:classifiers":[
        {
            "category":"Health Services",
            "subcategory":"Doctor",
            "type":"Services"
        }
    ],
    "sg:phone":"+1 417 332 2777",
    "sg:postcode":"65616",
    "sg:province":"MO",
    "sg:tags":[
        "physician",
        "surgeon"
    ],
    "wof:name":"Md Niell Us",
    "wof:placetype":"venue"
},
  "geometry": {"coordinates":[-93.280144,36.632378],"type":"Point"}
}