{
  "type": "Feature",
  "properties": {
    "iso:country":"US",
    "sg:address":"15641 Pike 292",
    "sg:city":"Bowling Green",
    "sg:classifiers":[
        {
            "category":"Shopping",
            "subcategory":"Computers & Home Electronics",
            "type":"Retail Goods"
        }
    ],
    "sg:phone":"+1 573 324 0142",
    "sg:postcode":"63334",
    "sg:province":"MO",
    "sg:tags":[
        "equipment",
        "electronic",
        "supply"
    ],
    "wof:name":"Pearl's Electronics",
    "wof:placetype":"venue"
},
  "geometry": {"coordinates":[-91.179986,39.362362],"type":"Point"}
}