{
  "type": "Feature",
  "properties": {
    "iso:country":"US",
    "sg:address":"1120 Villaview Dr",
    "sg:city":"Manchester",
    "sg:classifiers":[
        {
            "category":"Wholesale",
            "subcategory":"Computers",
            "type":"Manufacturing & Wholesale Goods"
        }
    ],
    "sg:phone":"+1 636 825 7544",
    "sg:postcode":"63021",
    "sg:province":"MO",
    "sg:tags":[
        "information",
        "retrieval"
    ],
    "wof:name":"E Job 4 You",
    "wof:placetype":"venue"
},
  "geometry": {"coordinates":[-90.501082,38.574811],"type":"Point"}
}