{
  "type": "Feature",
  "properties": {
    "iso:country":"US",
    "sg:address":"278 SW Blue Pkwy",
    "sg:city":"Lees Summit",
    "sg:classifiers":[
        {
            "category":"Health Services",
            "subcategory":"Doctor",
            "type":"Services"
        }
    ],
    "sg:phone":"+1 816 554 9588",
    "sg:postcode":"64063",
    "sg:province":"MO",
    "sg:tags":[
        "dentist"
    ],
    "wof:name":"Afzali Mojan DDS",
    "wof:placetype":"venue"
},
  "geometry": {"coordinates":[-94.382797,38.905405],"type":"Point"}
}