{
  "type": "Feature",
  "properties": {
    "iso:country":"US",
    "sg:address":"11663 Lime Kiln Dr",
    "sg:city":"Neosho",
    "sg:classifiers":[
        {
            "category":"Manufacturing",
            "subcategory":"Tools & Machinery",
            "type":"Manufacturing & Wholesale Goods"
        }
    ],
    "sg:phone":"+1 417 451 5350",
    "sg:postcode":"64850",
    "sg:province":"MO",
    "sg:tags":[
        "mfg",
        "industrial",
        "general"
    ],
    "wof:name":"Hickman Service",
    "wof:placetype":"venue"
},
  "geometry": {"coordinates":[-94.36950899999999,36.894998],"type":"Point"}
}