{
  "type": "Feature",
  "properties": {
    "iso:country":"US",
    "sg:address":"107 SE 421st Rd",
    "sg:city":"Warrensburg",
    "sg:classifiers":[
        {
            "category":"Professional",
            "subcategory":"Advertising",
            "type":"Services"
        }
    ],
    "sg:phone":"+1 660 747 7569",
    "sg:postcode":"64093",
    "sg:province":"MO",
    "sg:tags":[
        "outdoor",
        "agency"
    ],
    "wof:name":"Apple Advertising",
    "wof:placetype":"venue"
},
  "geometry": {"coordinates":[-93.66366499999999,38.742483],"type":"Point"}
}