{
  "type": "Feature",
  "properties": {
    "iso:country":"US",
    "sg:address":"600 N 18th St",
    "sg:city":"Unionville",
    "sg:classifiers":[
        {
            "category":"Real Estate",
            "subcategory":"Real Estate Operator",
            "type":"Services"
        }
    ],
    "sg:phone":"+1 660 947 3385",
    "sg:postcode":"63565",
    "sg:province":"MO",
    "sg:tags":[
        "apartment"
    ],
    "wof:name":"Unionville Estates",
    "wof:placetype":"venue"
},
  "geometry": {"coordinates":[-93.00436999999999,40.483596],"type":"Point"}
}