{
  "type": "Feature",
  "properties": {
    "iso:country":"US",
    "sg:address":"223 N Main St",
    "sg:city":"Paris",
    "sg:classifiers":[
        {
            "category":"Shopping",
            "subcategory":"Pharmacy",
            "type":"Retail Goods"
        }
    ],
    "sg:phone":"+1 660 327 4514",
    "sg:postcode":"65275",
    "sg:province":"MO",
    "sg:tags":[
        "proprietary",
        "drug",
        "store"
    ],
    "wof:name":"Paris Pharmacy Inc",
    "wof:placetype":"venue"
},
  "geometry": {"coordinates":[-92.00026,39.482268],"type":"Point"}
}