{
  "type": "Feature",
  "properties": {
    "iso:country":"US",
    "sg:address":"13606 Monroe Road 1014",
    "sg:city":"Madison",
    "sg:classifiers":[
        {
            "category":"Professional",
            "subcategory":"Management & Consulting",
            "type":"Services"
        }
    ],
    "sg:phone":"+1 660 291 8112",
    "sg:postcode":"65263",
    "sg:province":"MO",
    "sg:tags":[
        "farm"
    ],
    "wof:name":"Hayes Organic Farms",
    "wof:placetype":"venue"
},
  "geometry": {"coordinates":[-92.212089,39.368481],"type":"Point"}
}