{
  "type": "Feature",
  "properties": {
    "addr:full":"123 E Gay St Warrensburg MO 64093",
    "addr:housenumber":"123",
    "addr:postcode":"64093",
    "addr:street":"E Gay St",
    "iso:country":"US",
    "sg:address":"123 E Gay St",
    "sg:city":"Warrensburg",
    "sg:classifiers":[
        {
            "category":"Organizations",
            "subcategory":"Political Organization",
            "type":"Services"
        }
    ],
    "sg:phone":"+1 660 747 7723",
    "sg:postcode":"64093",
    "sg:province":"MO",
    "wof:name":"Republican Headquarters",
    "wof:placetype":"venue"
},
  "geometry": {"coordinates":[-93.73980400000001,38.766099],"type":"Point"}
}