{
  "type": "Feature",
  "properties": {
    "iso:country":"US",
    "sg:address":"2031 N Courtney Rd",
    "sg:city":"Independence",
    "sg:classifiers":[
        {
            "category":"Building & Trades",
            "subcategory":"Construction",
            "type":"Services"
        }
    ],
    "sg:phone":"+1 816 836 0685",
    "sg:postcode":"64050",
    "sg:province":"MO",
    "sg:tags":[
        "product",
        "asphalt"
    ],
    "wof:name":"APAC",
    "wof:placetype":"venue"
},
  "geometry": {"coordinates":[-94.404624,39.132903],"type":"Point"}
}