{
  "type": "Feature",
  "properties": {
    "iso:country":"US",
    "sg:address":"841 W 39 St",
    "sg:city":"Kansas City",
    "sg:classifiers":[
        {
            "category":"Shopping",
            "subcategory":"Clothing, Apparel, & Fashions",
            "type":"Retail Goods"
        }
    ],
    "sg:phone":"+1 816 756 5031",
    "sg:postcode":"64111",
    "sg:province":"MO",
    "sg:tags":[
        "infant",
        "wear"
    ],
    "wof:name":"Annie's",
    "wof:placetype":"venue"
},
  "geometry": {"coordinates":[-94.598265,39.056946],"type":"Point"}
}