{
  "type": "Feature",
  "properties": {
    "iso:country":"US",
    "sg:address":"7729 Zero Rd",
    "sg:city":"Berger",
    "sg:phone":"+1 573 834 5271",
    "sg:postcode":"63014",
    "sg:province":"MO",
    "sg:tags":[
        "farm",
        "soybean"
    ],
    "wof:name":"Dan Haid",
    "wof:placetype":"venue"
},
  "geometry": {"coordinates":[-91.360477,38.689591],"type":"Point"}
}