{
  "type": "Feature",
  "properties": {
    "iso:country":"US",
    "sg:address":"500 W Coates St",
    "sg:city":"Moberly",
    "sg:classifiers":[
        {
            "category":"Banks & Credit Unions",
            "subcategory":"Bank",
            "type":"Services"
        }
    ],
    "sg:phone":"+1 660 263 1177",
    "sg:postcode":"65270",
    "sg:province":"MO",
    "sg:tags":[
        "commercial"
    ],
    "wof:name":"City Bank Info Line",
    "wof:placetype":"venue"
},
  "geometry": {"coordinates":[-92.443276,39.420892],"type":"Point"}
}