{
  "type": "Feature",
  "properties": {
    "iso:country":"US",
    "sg:address":"16603 NE 113th St",
    "sg:city":"Liberty",
    "sg:classifiers":[
        {
            "category":"Shopping",
            "type":"Retail Goods"
        }
    ],
    "sg:phone":"+1 816 781 7428",
    "sg:postcode":"64068",
    "sg:province":"MO",
    "sg:tags":[
        "baby",
        "product",
        "accessory"
    ],
    "wof:name":"Cradles-N-More",
    "wof:placetype":"venue"
},
  "geometry": {"coordinates":[-94.375758,39.298311],"type":"Point"}
}