{
  "type": "Feature",
  "properties": {
    "iso:country":"US",
    "sg:address":"200 NE Missouri Rd",
    "sg:city":"Lees Summit",
    "sg:classifiers":[
        {
            "category":"Banks & Credit Unions",
            "subcategory":"Bank",
            "type":"Services"
        }
    ],
    "sg:phone":"+1 816 251 4525",
    "sg:postcode":"64086",
    "sg:province":"MO",
    "sg:tags":[
        "loan",
        "real estate"
    ],
    "wof:name":"Affordable Mortgage Solutions",
    "wof:placetype":"venue"
},
  "geometry": {"coordinates":[-94.37607300000001,38.94192],"type":"Point"}
}