{
  "type": "Feature",
  "properties": {
    "iso:country":"US",
    "sg:address":"4326 W Florissant Ave",
    "sg:city":"Saint Louis",
    "sg:classifiers":[
        {
            "category":"Personal",
            "subcategory":"Barber",
            "type":"Services"
        }
    ],
    "sg:phone":"+1 314 382 6677",
    "sg:postcode":"63115",
    "sg:province":"MO",
    "wof:name":"La Rose Barber & Cosmetology Specialists",
    "wof:placetype":"venue"
},
  "geometry": {"coordinates":[-90.224602,38.680801],"type":"Point"}
}