{
  "type": "Feature",
  "properties": {
    "iso:country":"US",
    "sg:address":"1408 Wills Hollow Rd",
    "sg:city":"Glencoe",
    "sg:classifiers":[
        {
            "category":"Shopping",
            "subcategory":"Used Merchandise",
            "type":"Retail Goods"
        }
    ],
    "sg:phone":"+1 636 394 2867",
    "sg:postcode":"63038",
    "sg:province":"MO",
    "wof:name":"Red Rooster Antiques",
    "wof:placetype":"venue"
},
  "geometry": {"coordinates":[-90.61341400000001,38.54592],"type":"Point"}
}