{
  "type": "Feature",
  "properties": {
    "iso:country":"US",
    "sg:address":"19 N Water St",
    "sg:city":"Cape Girardeau",
    "sg:classifiers":[
        {
            "category":"Restaurant",
            "type":"Food & Drink"
        }
    ],
    "sg:phone":"+1 573 334 0954",
    "sg:postcode":"63701",
    "sg:province":"MO",
    "wof:name":"Port Cape Girardeau",
    "wof:placetype":"venue"
},
  "geometry": {"coordinates":[-89.51786199999999,37.304479],"type":"Point"}
}