{
  "type": "Feature",
  "properties": {
    "iso:country":"US",
    "sg:address":"43 Centre Pt",
    "sg:city":"St Peters",
    "sg:classifiers":[
        {
            "category":"Home & Garden",
            "subcategory":"Carpets & Floor Coverings",
            "type":"Retail Goods"
        }
    ],
    "sg:phone":"+1 636 939 9339",
    "sg:postcode":"63304",
    "sg:province":"MO",
    "sg:tags":[
        "material"
    ],
    "sg:website":"www.signaturefloor.com",
    "wof:name":"Js Services",
    "wof:placetype":"venue"
},
  "geometry": {"coordinates":[-90.58457300000001,38.748823],"type":"Point"}
}