{
  "type": "Feature",
  "properties": {
    "iso:country":"US",
    "sg:address":"2 Industrial Dr",
    "sg:city":"St James",
    "sg:classifiers":[
        {
            "category":"Building & Trades",
            "subcategory":"Construction",
            "type":"Services"
        }
    ],
    "sg:phone":"+1 573 265 7000",
    "sg:postcode":"65565",
    "sg:province":"MO",
    "sg:tags":[
        "boring",
        "drilling",
        "contractor"
    ],
    "wof:name":"Gahr Line & Cable",
    "wof:placetype":"venue"
},
  "geometry": {"coordinates":[-91.34147,37.971924],"type":"Point"}
}