{
  "type": "Feature",
  "properties": {
    "iso:country":"US",
    "sg:address":"555 NW Platte Valley Dr",
    "sg:city":"Kansas City",
    "sg:classifiers":[
        {
            "category":"Retail",
            "subcategory":"Auto Repair",
            "type":"Services"
        }
    ],
    "sg:phone":"+1 816 587 6533",
    "sg:postcode":"64150",
    "sg:province":"MO",
    "sg:tags":[
        "automobile",
        "top",
        "upholstery"
    ],
    "wof:name":"Woodbridge Corp-KC Foam Div",
    "wof:placetype":"venue"
},
  "geometry": {"coordinates":[-94.63410399999999,39.172536],"type":"Point"}
}