{
  "type": "Feature",
  "properties": {
    "iso:country":"US",
    "sg:address":"901 E Saint Louis St",
    "sg:city":"Springfield",
    "sg:classifiers":[
        {
            "category":"Government",
            "subcategory":"Police Station",
            "type":"Public Place"
        },
        {
            "category":"Professional",
            "subcategory":"Lawyer & Legal Services",
            "type":"Services"
        }
    ],
    "sg:phone":"+1 417 831 6363",
    "sg:postcode":"65806",
    "sg:province":"MO",
    "sg:tags":[
        "attorney",
        "law",
        "family",
        "federal",
        "divorce",
        "traffic",
        "criminal"
    ],
    "sg:website":"http://www.carvercantin.com",
    "wof:name":"Carver & Cantin",
    "wof:placetype":"venue"
},
  "geometry": {"coordinates":[-93.28193400000001,37.208874],"type":"Point"}
}