{
  "type": "Feature",
  "properties": {
    "iso:country":"US",
    "sg:address":"719 W Centennial Ave",
    "sg:city":"Carthage",
    "sg:classifiers":[
        {
            "category":"Health Services",
            "subcategory":"Doctor",
            "type":"Services"
        }
    ],
    "sg:phone":"+1 417 359 9502",
    "sg:postcode":"64836",
    "sg:province":"MO",
    "sg:tags":[
        "medical"
    ],
    "wof:name":"Harold A Smart Do",
    "wof:placetype":"venue"
},
  "geometry": {"coordinates":[-94.3198,37.162086],"type":"Point"}
}