{
  "type": "Feature",
  "properties": {
    "iso:country":"US",
    "sg:address":"206 Zinnia Ln",
    "sg:city":"Kirbyville",
    "sg:classifiers":[
        {
            "category":"Building & Trades",
            "subcategory":"Landscaping Services",
            "type":"Services"
        }
    ],
    "sg:phone":"+1 417 334 8046",
    "sg:postcode":"65679",
    "sg:province":"MO",
    "sg:tags":[
        "lawn",
        "maintenance"
    ],
    "wof:name":"Four Seasons' Yard Care",
    "wof:placetype":"venue"
},
  "geometry": {"coordinates":[-93.15007,36.607641],"type":"Point"}
}