{
  "type": "Feature",
  "properties": {
    "iso:country":"US",
    "sg:address":"323 S Newsome St",
    "sg:city":"Cardwell",
    "sg:classifiers":[
        {
            "category":"Professional",
            "type":"Services"
        }
    ],
    "sg:phone":"+1 573 654 2006",
    "sg:postcode":"63829",
    "sg:province":"MO",
    "wof:name":"Gibson El",
    "wof:placetype":"venue"
},
  "geometry": {"coordinates":[-90.290694,36.046561],"type":"Point"}
}