{
  "type": "Feature",
  "properties": {
    "iso:country":"US",
    "sg:address":"7507 Woodbridge Estates Ct",
    "sg:city":"Saint Louis",
    "sg:classifiers":[
        {
            "category":"Insurance",
            "subcategory":"Insurance Agent",
            "type":"Services"
        }
    ],
    "sg:phone":"+1 314 846 7842",
    "sg:postcode":"63129",
    "sg:province":"MO",
    "wof:name":"Joseph Gary Abele",
    "wof:placetype":"venue"
},
  "geometry": {"coordinates":[-90.33253000000001,38.422216],"type":"Point"}
}