{
  "type": "Feature",
  "properties": {
    "iso:country":"US",
    "sg:address":"205 S Vandeventer Ave",
    "sg:city":"Saint Louis",
    "sg:classifiers":[
        {
            "category":"Autos & Motor Vehicles",
            "subcategory":"Fuel & Gas Station",
            "type":"Retail Goods"
        }
    ],
    "sg:phone":"+1 314 652 3434",
    "sg:postcode":"63110",
    "sg:province":"MO",
    "wof:name":"Johnson's Amoco Food Shop",
    "wof:placetype":"venue"
},
  "geometry": {"coordinates":[-90.242401,38.634102],"type":"Point"}
}