{
  "type": "Feature",
  "properties": {
    "iso:country":"US",
    "sg:address":"2107 Schuetz Rd",
    "sg:city":"St Louis",
    "sg:classifiers":[
        {
            "category":"Food & Beverages",
            "subcategory":"Groceries & Convenience Stores",
            "type":"Retail Goods"
        }
    ],
    "sg:phone":"+1 314 569 3474",
    "sg:postcode":"63146",
    "sg:province":"MO",
    "wof:name":"7-Eleven",
    "wof:placetype":"venue"
},
  "geometry": {"coordinates":[-90.429717,38.698874],"type":"Point"}
}