{
  "type": "Feature",
  "properties": {
    "iso:country":"US",
    "sg:address":"1014 W Weaver Ct N",
    "sg:city":"Springfield",
    "sg:classifiers":[
        {
            "category":"Building & Trades",
            "subcategory":"Cleaning & Sanitation",
            "type":"Services"
        }
    ],
    "sg:phone":"+1 417 862 7520",
    "sg:postcode":"65806",
    "sg:province":"MO",
    "sg:tags":[
        "window"
    ],
    "wof:name":"Carpenter's Cleaning Ctr",
    "wof:placetype":"venue"
},
  "geometry": {"coordinates":[-93.303433,37.203749],"type":"Point"}
}