{
  "type": "Feature",
  "properties": {
    "iso:country":"US",
    "sg:address":"310 W Monroe St",
    "sg:city":"Mexico",
    "sg:classifiers":[
        {
            "category":"Wholesale",
            "subcategory":"Meat",
            "type":"Manufacturing & Wholesale Goods"
        }
    ],
    "sg:phone":"+1 573 581 2691",
    "sg:postcode":"65265",
    "sg:province":"MO",
    "wof:name":"Randy's Frozen Meats",
    "wof:placetype":"venue"
},
  "geometry": {"coordinates":[-91.885654,39.172948],"type":"Point"}
}