{
  "type": "Feature",
  "properties": {
    "iso:country":"US",
    "sg:address":"7427 Wayne Ave",
    "sg:city":"Saint Louis",
    "sg:classifiers":[
        {
            "category":"Health Services",
            "subcategory":"Clinic",
            "type":"Services"
        }
    ],
    "sg:phone":"+1 314 862 3631",
    "sg:postcode":"63130",
    "sg:province":"MO",
    "sg:tags":[
        "home",
        "care"
    ],
    "wof:name":"W & O Home Rehab",
    "wof:placetype":"venue"
},
  "geometry": {"coordinates":[-90.33045199999999,38.67886],"type":"Point"}
}