{
  "type": "Feature",
  "properties": {
    "iso:country":"US",
    "sg:address":"90 Village Square Shopping Center",
    "sg:city":"Hazelwood",
    "sg:classifiers":[
        {
            "category":"Banks & Credit Unions",
            "subcategory":"Bank",
            "type":"Services"
        }
    ],
    "sg:phone":"+1 314 731 0229",
    "sg:postcode":"63042",
    "sg:province":"MO",
    "wof:name":"Superior Bank",
    "wof:placetype":"venue"
},
  "geometry": {"coordinates":[-90.361073,38.782429],"type":"Point"}
}