{
  "type": "Feature",
  "properties": {
    "iso:country":"US",
    "sg:address":"2600 E State Highway 76",
    "sg:city":"Branson",
    "sg:phone":"+1 417 337 9459",
    "sg:postcode":"65616",
    "sg:province":"MO",
    "wof:name":"Andy Williams Moon River Grill",
    "wof:placetype":"venue"
},
  "geometry": {"coordinates":[-93.28476000000001,36.638245],"type":"Point"}
}