{
  "type": "Feature",
  "properties": {
    "iso:country":"US",
    "sg:address":"14 Burgoyne Dr",
    "sg:city":"West Plains",
    "sg:classifiers":[
        {
            "category":"Social Services",
            "subcategory":"Child Care",
            "type":"Services"
        }
    ],
    "sg:phone":"+1 417 255 2688",
    "sg:postcode":"65775",
    "sg:province":"MO",
    "sg:tags":[
        "day"
    ],
    "wof:name":"Little Blessings Day Care",
    "wof:placetype":"venue"
},
  "geometry": {"coordinates":[-91.872508,36.749843],"type":"Point"}
}