{
  "type": "Feature",
  "properties": {
    "iso:country":"US",
    "sg:address":"501 Cambridge Ave",
    "sg:city":"Kansas City",
    "sg:classifiers":[
        {
            "category":"Manufacturing",
            "subcategory":"Printing",
            "type":"Manufacturing & Wholesale Goods"
        }
    ],
    "sg:phone":"+1 816 241 6908",
    "sg:postcode":"64125",
    "sg:province":"MO",
    "sg:tags":[
        "lithographic",
        "printer",
        "commercial"
    ],
    "sg:website":"www.championgraphics.com",
    "wof:name":"Champion Graphics Co Inc",
    "wof:placetype":"venue"
},
  "geometry": {"coordinates":[-94.501645,39.104603],"type":"Point"}
}