{
  "type": "Feature",
  "properties": {
    "iso:country":"US",
    "sg:address":"811 S 6th St",
    "sg:city":"St Joseph",
    "sg:classifiers":[
        {
            "category":"Autos & Motor Vehicles",
            "subcategory":"Fuel & Gas Station",
            "type":"Retail Goods"
        }
    ],
    "sg:phone":"+1 816 232 1475",
    "sg:postcode":"64501",
    "sg:province":"MO",
    "sg:tags":[
        "oil"
    ],
    "wof:name":"Imperial Super Gas Inc",
    "wof:placetype":"venue"
},
  "geometry": {"coordinates":[-94.85275900000001,39.759133],"type":"Point"}
}