{
  "type": "Feature",
  "properties": {
    "iso:country":"US",
    "sg:address":"3535 S Jefferson Ave Ste 107",
    "sg:city":"Saint Louis",
    "sg:classifiers":[
        {
            "category":"Health Services",
            "subcategory":"Doctor",
            "type":"Services"
        }
    ],
    "sg:phone":"+1 314 865 2730",
    "sg:postcode":"63118",
    "sg:province":"MO",
    "sg:tags":[
        "psychiatrist"
    ],
    "wof:name":"Patel Jitendra",
    "wof:placetype":"venue"
},
  "geometry": {"coordinates":[-90.22612,38.590887],"type":"Point"}
}