{
  "type": "Feature",
  "properties": {
    "iso:country":"US",
    "sg:address":"301 E High St",
    "sg:city":"Potosi",
    "sg:classifiers":[
        {
            "category":"Retail",
            "subcategory":"Funeral Services",
            "type":"Services"
        }
    ],
    "sg:phone":"+1 573 438 2105",
    "sg:postcode":"63664",
    "sg:province":"MO",
    "sg:tags":[
        "home"
    ],
    "wof:name":"Britton Funeral Home",
    "wof:placetype":"venue"
},
  "geometry": {"coordinates":[-90.784689,37.934302],"type":"Point"}
}