{
  "type": "Feature",
  "properties": {
    "iso:country":"US",
    "sg:address":"2740 N Mayfair Ave",
    "sg:city":"Springfield",
    "sg:classifiers":[
        {
            "category":"Professional",
            "type":"Services"
        }
    ],
    "sg:phone":"+1 417 863 0016",
    "sg:postcode":"65803",
    "sg:province":"MO",
    "sg:tags":[
        "establishment"
    ],
    "wof:name":"W P Advantis",
    "wof:placetype":"venue"
},
  "geometry": {"coordinates":[-93.229032,37.245234],"type":"Point"}
}