{
  "type": "Feature",
  "properties": {
    "iso:country":"US",
    "sg:address":"19177 Rapid Rd",
    "sg:city":"Richland",
    "sg:classifiers":[
        {
            "category":"Retail",
            "subcategory":"Repair Shop",
            "type":"Services"
        }
    ],
    "sg:phone":"+1 573 765 4079",
    "sg:postcode":"65556",
    "sg:province":"MO",
    "sg:tags":[
        "welding"
    ],
    "wof:name":"Dw Welding & Trucking Inc",
    "wof:placetype":"venue"
},
  "geometry": {"coordinates":[-92.34943800000001,37.882695],"type":"Point"}
}