{
  "type": "Feature",
  "properties": {
    "iso:country":"US",
    "sg:address":"400 S Woods Mill Rd",
    "sg:city":"Chesterfield",
    "sg:classifiers":[
        {
            "category":"Communications",
            "type":"Services"
        }
    ],
    "sg:phone":"+1 636 614 1364",
    "sg:postcode":"63017",
    "sg:province":"MO",
    "wof:name":"Buzz Broadband",
    "wof:placetype":"venue"
},
  "geometry": {"coordinates":[-90.51274100000001,38.646252],"type":"Point"}
}