{
  "type": "Feature",
  "properties": {
    "iso:country":"US",
    "sg:address":"105 W College Ave",
    "sg:city":"Fredericktown",
    "sg:classifiers":[
        {
            "category":"Retail",
            "subcategory":"Laundry & Dry Cleaning",
            "type":"Services"
        }
    ],
    "sg:phone":"+1 573 783 3135",
    "sg:postcode":"63645",
    "sg:province":"MO",
    "sg:tags":[
        "drycleaning",
        "plant"
    ],
    "wof:name":"Cr Cleaners",
    "wof:placetype":"venue"
},
  "geometry": {"coordinates":[-90.295281,37.557719],"type":"Point"}
}