{
  "type": "Feature",
  "properties": {
    "iso:country":"US",
    "sg:address":"120 Swearengin Dr",
    "sg:city":"Rogersville",
    "sg:classifiers":[
        {
            "category":"Building & Trades",
            "subcategory":"Electrical",
            "type":"Services"
        }
    ],
    "sg:phone":"+1 417 753 2780",
    "sg:postcode":"65742",
    "sg:province":"MO",
    "sg:tags":[
        "electrical",
        "contractor"
    ],
    "wof:name":"Savage Electric",
    "wof:placetype":"venue"
},
  "geometry": {"coordinates":[-93.00391999999999,37.057052],"type":"Point"}
}