{
  "type": "Feature",
  "properties": {
    "iso:country":"US",
    "sg:address":"210 Windwood Lake Dr",
    "sg:city":"Cape Girardeau",
    "sg:classifiers":[
        {
            "category":"Real Estate",
            "subcategory":"Developer",
            "type":"Services"
        }
    ],
    "sg:phone":"+1 573 339 1105",
    "sg:postcode":"63701",
    "sg:province":"MO",
    "wof:name":"Mc Lane Development",
    "wof:placetype":"venue"
},
  "geometry": {"coordinates":[-89.58908099999999,37.266034],"type":"Point"}
}