{
  "type": "Feature",
  "properties": {
    "iso:country":"US",
    "sg:address":"6869 Co Rd 118",
    "sg:city":"Fulton",
    "sg:classifiers":[
        {
            "category":"Farming",
            "subcategory":"Livestock Farm",
            "type":"Manufacturing & Wholesale Goods"
        }
    ],
    "sg:phone":"+1 573 642 5254",
    "sg:postcode":"65251",
    "sg:province":"MO",
    "sg:tags":[
        "feedlot",
        "field",
        "crop",
        "beef",
        "cattle"
    ],
    "wof:name":"Robert Maddox",
    "wof:placetype":"venue"
},
  "geometry": {"coordinates":[-91.882948,38.914967],"type":"Point"}
}