{
  "type": "Feature",
  "properties": {
    "iso:country":"US",
    "sg:address":"810 W 35th St",
    "sg:city":"Higginsville",
    "sg:classifiers":[
        {
            "category":"Shopping",
            "subcategory":"Pharmacy",
            "type":"Retail Goods"
        }
    ],
    "sg:phone":"+1 660 584 5944",
    "sg:postcode":"64037",
    "sg:province":"MO",
    "wof:name":"All Pro Pharmacy",
    "wof:placetype":"venue"
},
  "geometry": {"coordinates":[-93.72820900000001,39.060898],"type":"Point"}
}