{
  "type": "Feature",
  "properties": {
    "iso:country":"US",
    "sg:address":"26 Maryland Plz",
    "sg:city":"Saint Louis",
    "sg:classifiers":[
        {
            "category":"Shopping",
            "subcategory":"Clothing, Apparel, & Fashions",
            "type":"Retail Goods"
        }
    ],
    "sg:phone":"+1 314 361 4475",
    "sg:postcode":"63108",
    "sg:province":"MO",
    "sg:tags":[
        "clothing",
        "women's"
    ],
    "wof:name":"Girl Boutique",
    "wof:placetype":"venue"
},
  "geometry": {"coordinates":[-90.262506,38.644939],"type":"Point"}
}