{
  "type": "Feature",
  "properties": {
    "iso:country":"US",
    "sg:address":"909 Chestnut St",
    "sg:city":"St Louis",
    "sg:classifiers":[
        {
            "category":"Personal",
            "type":"Services"
        },
        {
            "category":"Social Services",
            "type":"Services"
        }
    ],
    "sg:phone":"+1 314 588 1060",
    "sg:postcode":"63101",
    "sg:province":"MO",
    "sg:tags":[
        "therapist",
        "massage"
    ],
    "wof:name":"Stress Management Solutions",
    "wof:placetype":"venue"
},
  "geometry": {"coordinates":[-90.195114,38.627638],"type":"Point"}
}