{
  "type": "Feature",
  "properties": {
    "iso:country":"US",
    "sg:address":"841 Hwy 42",
    "sg:city":"Iberia",
    "sg:classifiers":[
        {
            "category":"Banks & Credit Unions",
            "subcategory":"Bank",
            "type":"Services"
        }
    ],
    "sg:phone":"+1 573 793 2224",
    "sg:postcode":"65486",
    "sg:province":"MO",
    "sg:website":"www.bankofiberia.com",
    "wof:name":"Bank Of Iberia",
    "wof:placetype":"venue"
},
  "geometry": {"coordinates":[-92.294225,38.09026],"type":"Point"}
}