{
  "type": "Feature",
  "properties": {
    "iso:country":"US",
    "sg:address":"17212 Liv 403",
    "sg:city":"Mooresville",
    "sg:phone":"+1 660 755 4411",
    "sg:postcode":"64664",
    "sg:province":"MO",
    "sg:tags":[
        "farm",
        "soybean"
    ],
    "wof:name":"Bothwell Farms",
    "wof:placetype":"venue"
},
  "geometry": {"coordinates":[-93.741275,39.722145],"type":"Point"}
}