{
  "type": "Feature",
  "properties": {
    "iso:country":"US",
    "sg:address":"301 NW 11 St",
    "sg:city":"Blue Springs",
    "sg:classifiers":[
        {
            "category":"Home & Garden",
            "subcategory":"Building Materials",
            "type":"Retail Goods"
        }
    ],
    "sg:phone":"+1 816 228 1777",
    "sg:postcode":"64015",
    "sg:province":"MO",
    "sg:tags":[
        "glass",
        "window",
        "plate"
    ],
    "wof:name":"Austin Glass Connection Inc",
    "wof:placetype":"venue"
},
  "geometry": {"coordinates":[-94.277861,39.019062],"type":"Point"}
}