{
  "type": "Feature",
  "properties": {
    "iso:country":"US",
    "sg:address":"600 Barclay St",
    "sg:city":"Herculaneum",
    "sg:classifiers":[
        {
            "category":"Education",
            "subcategory":"School",
            "type":"Public Place"
        }
    ],
    "sg:phone":"+1 636 479 5604",
    "sg:postcode":"63048",
    "sg:province":"MO",
    "wof:name":"Dunklin R-5 School District",
    "wof:placetype":"venue"
},
  "geometry": {"coordinates":[-90.378445,38.267986],"type":"Point"}
}