{
  "type": "Feature",
  "properties": {
    "iso:country":"US",
    "sg:address":"223 Weber Dr",
    "sg:city":"Eureka",
    "sg:classifiers":[
        {
            "category":"Building & Trades",
            "subcategory":"Landscaping Services",
            "type":"Services"
        }
    ],
    "sg:phone":"+1 636 938 3049",
    "sg:postcode":"63025",
    "sg:province":"MO",
    "sg:tags":[
        "landscape"
    ],
    "wof:name":"Kwik Kerb By J&K Curbing",
    "wof:placetype":"venue"
},
  "geometry": {"coordinates":[-90.63411600000001,38.49855],"type":"Point"}
}