{
  "type": "Feature",
  "properties": {
    "iso:country":"US",
    "sg:address":"705 N Jefferson St",
    "sg:city":"Kearney",
    "sg:classifiers":[
        {
            "category":"Insurance",
            "subcategory":"Hazard Insurance",
            "type":"Services"
        }
    ],
    "sg:phone":"+1 816 628 5053",
    "sg:postcode":"64060",
    "sg:province":"MO",
    "sg:website":"http://www.kofc.org",
    "wof:name":"Knights Of Columbus",
    "wof:placetype":"venue"
},
  "geometry": {"coordinates":[-94.366512,39.380643],"type":"Point"}
}