{
  "type": "Feature",
  "properties": {
    "iso:country":"US",
    "sg:address":"1525 Garfield Ave",
    "sg:city":"St Joseph",
    "sg:classifiers":[
        {
            "category":"Autos & Motor Vehicles",
            "subcategory":"Automobile Sales",
            "type":"Retail Goods"
        }
    ],
    "sg:phone":"+1 816 364 2991",
    "sg:postcode":"64503",
    "sg:province":"MO",
    "sg:tags":[
        "car",
        "dealer"
    ],
    "wof:name":"L & L Auto Sales & Svc",
    "wof:placetype":"venue"
},
  "geometry": {"coordinates":[-94.842325,39.739227],"type":"Point"}
}