{
  "type": "Feature",
  "properties": {
    "iso:country":"US",
    "sg:address":"700 Spencer Dr",
    "sg:city":"Neosho",
    "sg:classifiers":[
        {
            "category":"Organizations",
            "subcategory":"Religious Organization",
            "type":"Services"
        }
    ],
    "sg:phone":"+1 417 451 1858",
    "sg:postcode":"64850",
    "sg:province":"MO",
    "sg:tags":[
        "church"
    ],
    "wof:name":"Abundant Life Assembly of God Church",
    "wof:placetype":"venue"
},
  "geometry": {"coordinates":[-94.38755,36.861649],"type":"Point"}
}