{
  "type": "Feature",
  "properties": {
    "addr:full":"1204 Grand Blvd Kansas City MO 64106",
    "addr:housenumber":"1204",
    "addr:postcode":"64106",
    "addr:street":"Grand Blvd",
    "iso:country":"US",
    "sg:address":"1204 Grand Blvd",
    "sg:city":"Kansas City",
    "sg:classifiers":[
        {
            "category":"Professional",
            "subcategory":"Accounting & Tax Preparation",
            "type":"Services"
        }
    ],
    "sg:phone":"+1 816 472 8727",
    "sg:postcode":"64106",
    "sg:province":"MO",
    "sg:tags":[
        "return"
    ],
    "wof:name":"H & R Block",
    "wof:placetype":"venue"
},
  "geometry": {"coordinates":[-94.581047,39.098567],"type":"Point"}
}