{
  "type": "Feature",
  "properties": {
    "iso:country":"US",
    "sg:address":"4638 J C Nichols Pkwy",
    "sg:city":"Kansas City",
    "sg:classifiers":[
        {
            "category":"Health Services",
            "subcategory":"Health Practitioner",
            "type":"Services"
        }
    ],
    "sg:phone":"+1 816 210 0721",
    "sg:postcode":"64112",
    "sg:province":"MO",
    "sg:tags":[
        "psychotherapist"
    ],
    "wof:name":"Michal Drabanski",
    "wof:placetype":"venue"
},
  "geometry": {"coordinates":[-94.588263,39.04314],"type":"Point"}
}