{
  "type": "Feature",
  "properties": {
    "iso:country":"US",
    "sg:address":"47 N Star Cir",
    "sg:city":"Kaiser",
    "sg:classifiers":[
        {
            "category":"Home & Garden",
            "subcategory":"Household Appliances",
            "type":"Retail Goods"
        }
    ],
    "sg:phone":"+1 573 348 1972",
    "sg:postcode":"65047",
    "sg:province":"MO",
    "wof:name":"Love To Sew Boutique",
    "wof:placetype":"venue"
},
  "geometry": {"coordinates":[-92.58126300000001,38.16786],"type":"Point"}
}