{
  "type": "Feature",
  "properties": {
    "iso:country":"US",
    "sg:address":"1143 NE 451st Rd",
    "sg:city":"Concordia",
    "sg:classifiers":[
        {
            "category":"Farming",
            "subcategory":"Livestock Farm",
            "type":"Manufacturing & Wholesale Goods"
        }
    ],
    "sg:phone":"+1 660 463 2765",
    "sg:postcode":"64020",
    "sg:province":"MO",
    "sg:tags":[
        "beef",
        "feedlot",
        "cattle"
    ],
    "wof:name":"Vernon Ohrenberg",
    "wof:placetype":"venue"
},
  "geometry": {"coordinates":[-93.658272,38.925561],"type":"Point"}
}