{
  "type": "Feature",
  "properties": {
    "iso:country":"US",
    "sg:address":"302 N Elm St",
    "sg:city":"Dexter",
    "sg:classifiers":[
        {
            "category":"Building & Trades",
            "subcategory":"Landscaping Services",
            "type":"Services"
        },
        {
            "category":"Social Services",
            "subcategory":"Job Training",
            "type":"Services"
        },
        {
            "category":"Health Services",
            "subcategory":"Nursing And Care Facility",
            "type":"Services"
        },
        {
            "category":"Social Services",
            "subcategory":"Retirement Home",
            "type":"Services"
        }
    ],
    "sg:phone":"+1 573 624 0011",
    "sg:postcode":"63841",
    "sg:province":"MO",
    "sg:tags":[
        "convalescent",
        "aged",
        "rest",
        "homes-skilled",
        "homes-institutional"
    ],
    "wof:name":"Central Gardens Residential Care",
    "wof:placetype":"venue"
},
  "geometry": {"coordinates":[-89.954909,36.795682],"type":"Point"}
}