{
  "type": "Feature",
  "properties": {
    "iso:country":"US",
    "sg:address":"4200 Pennsylvania Ave",
    "sg:city":"Kansas City",
    "sg:classifiers":[
        {
            "category":"Communications",
            "subcategory":"Film & Video Production",
            "type":"Services"
        }
    ],
    "sg:phone":"+1 816 931 9884",
    "sg:postcode":"64111",
    "sg:province":"MO",
    "sg:tags":[
        "motion"
    ],
    "wof:name":"Mk12",
    "wof:placetype":"venue"
},
  "geometry": {"coordinates":[-94.59002,39.050604],"type":"Point"}
}