{
  "type": "Feature",
  "properties": {
    "iso:country":"US",
    "sg:address":"304 Sharyhill Rd",
    "sg:city":"Branson",
    "sg:classifiers":[
        {
            "category":"Building & Trades",
            "subcategory":"Construction",
            "type":"Services"
        }
    ],
    "sg:phone":"+1 417 335 6948",
    "sg:postcode":"65616",
    "sg:province":"MO",
    "sg:tags":[
        "industrial",
        "contractors-commercial"
    ],
    "sg:website":"http://www.zipweb.com/?businessName=BobsRemodeling/",
    "wof:name":"Bob's Remodeling",
    "wof:placetype":"venue"
},
  "geometry": {"coordinates":[-93.204267,36.69794],"type":"Point"}
}