{
  "type": "Feature",
  "properties": {
    "iso:country":"US",
    "sg:address":"3 Oak Hill Cluster",
    "sg:city":"Independence",
    "sg:classifiers":[
        {
            "category":"Building & Trades",
            "subcategory":"Electrical",
            "type":"Services"
        }
    ],
    "sg:phone":"+1 816 229 6836",
    "sg:postcode":"64057",
    "sg:province":"MO",
    "sg:tags":[
        "electrical",
        "contractor"
    ],
    "wof:name":"Andromeda Electric",
    "wof:placetype":"venue"
},
  "geometry": {"coordinates":[-94.27958,39.071666],"type":"Point"}
}