{
  "type": "Feature",
  "properties": {
    "iso:country":"US",
    "sg:address":"189 Greenbriar Estates Dr",
    "sg:city":"Saint Louis",
    "sg:classifiers":[
        {
            "category":"Professional",
            "subcategory":"Business Services",
            "type":"Services"
        }
    ],
    "sg:phone":"+1 314 609 3449",
    "sg:postcode":"63122",
    "sg:province":"MO",
    "wof:name":"Asci",
    "wof:placetype":"venue"
},
  "geometry": {"coordinates":[-90.456861,38.576182],"type":"Point"}
}