{
  "type": "Feature",
  "properties": {
    "iso:country":"US",
    "sg:address":"1383 Beltower Dr",
    "sg:city":"Florissant",
    "sg:classifiers":[
        {
            "category":"Travel",
            "subcategory":"Hotels & Motels",
            "type":"Entertainment"
        }
    ],
    "sg:phone":"+1 314 921 8359",
    "sg:postcode":"63033",
    "sg:province":"MO",
    "sg:tags":[
        "breakfast",
        "consulting",
        "bed"
    ],
    "wof:name":"Charlenes Place",
    "wof:placetype":"venue"
},
  "geometry": {"coordinates":[-90.31824400000001,38.803953],"type":"Point"}
}