{
  "type": "Feature",
  "properties": {
    "iso:country":"US",
    "sg:address":"212 Patty Lynn St",
    "sg:city":"Kennett",
    "sg:classifiers":[
        {
            "category":"Organizations",
            "subcategory":"Religious Organization",
            "type":"Services"
        }
    ],
    "sg:phone":"+1 573 888 6110",
    "sg:postcode":"63857",
    "sg:province":"MO",
    "sg:tags":[
        "church"
    ],
    "wof:name":"Providence Baptist Church",
    "wof:placetype":"venue"
},
  "geometry": {"coordinates":[-90.05423,36.223382],"type":"Point"}
}