{
  "type": "Feature",
  "properties": {
    "iso:country":"US",
    "sg:address":"1111 McIntosh Cir",
    "sg:city":"Joplin",
    "sg:classifiers":[
        {
            "category":"Health Services",
            "subcategory":"Doctor",
            "type":"Services"
        }
    ],
    "sg:phone":"+1 417 347 8706",
    "sg:postcode":"64804",
    "sg:province":"MO",
    "sg:tags":[
        "physician",
        "medical",
        "surgeon"
    ],
    "wof:name":"Christina R Bratcher MD",
    "wof:placetype":"venue"
},
  "geometry": {"coordinates":[-94.52727299999999,37.050914],"type":"Point"}
}