{
  "type": "Feature",
  "properties": {
    "iso:country":"US",
    "sg:address":"2217 E 67 Ter",
    "sg:city":"Kansas City",
    "sg:classifiers":[
        {
            "category":"Retail",
            "subcategory":"Repair Shop",
            "type":"Services"
        }
    ],
    "sg:phone":"+1 816 361 2672",
    "sg:postcode":"64132",
    "sg:province":"MO",
    "sg:tags":[
        "house",
        "construction"
    ],
    "wof:name":"Haynes Home Improvements",
    "wof:placetype":"venue"
},
  "geometry": {"coordinates":[-94.560399,39.004475],"type":"Point"}
}