{
  "type": "Feature",
  "properties": {
    "iso:country":"US",
    "sg:address":"13922 Highway 17",
    "sg:city":"Plato",
    "sg:classifiers":[
        {
            "category":"Personal",
            "type":"Services"
        },
        {
            "category":"Shopping",
            "subcategory":"Florist",
            "type":"Retail Goods"
        }
    ],
    "sg:phone":"+1 417 458 4285",
    "sg:postcode":"65552",
    "sg:province":"MO",
    "sg:tags":[
        "consultant",
        "planning",
        "wedding"
    ],
    "sg:website":"http://www.vividimpressions.net",
    "wof:name":"Vivid Impressions Floral",
    "wof:placetype":"venue"
},
  "geometry": {"coordinates":[-92.19337,37.568815],"type":"Point"}
}