{
  "type": "Feature",
  "properties": {
    "iso:country":"US",
    "sg:address":"7235 Washington St",
    "sg:city":"Kansas City",
    "sg:classifiers":[
        {
            "category":"Building & Trades",
            "subcategory":"Construction",
            "type":"Services"
        }
    ],
    "sg:phone":"+1 816 695 6640",
    "sg:postcode":"64114",
    "sg:province":"MO",
    "sg:tags":[
        "painter"
    ],
    "wof:name":"A & L Painting",
    "wof:placetype":"venue"
},
  "geometry": {"coordinates":[-94.595024,38.996644],"type":"Point"}
}