{
  "type": "Feature",
  "properties": {
    "iso:country":"US",
    "sg:address":"11495 Natural Bridge Rd",
    "sg:city":"Bridgeton",
    "sg:classifiers":[
        {
            "category":"Professional",
            "type":"Services"
        },
        {
            "category":"Social Services",
            "type":"Services"
        }
    ],
    "sg:phone":"+1 314 895 5563",
    "sg:postcode":"63044",
    "sg:province":"MO",
    "sg:tags":[
        "establishment"
    ],
    "wof:name":"Operation Lift Off Inc",
    "wof:placetype":"venue"
},
  "geometry": {"coordinates":[-90.38707100000001,38.752732],"type":"Point"}
}