{
  "type": "Feature",
  "properties": {
    "iso:country":"US",
    "sg:address":"215 N Main St",
    "sg:city":"Blackburn",
    "sg:classifiers":[
        {
            "category":"Banks & Credit Unions",
            "subcategory":"Bank",
            "type":"Services"
        }
    ],
    "sg:phone":"+1 660 538 4301",
    "sg:postcode":"65321",
    "sg:province":"MO",
    "sg:tags":[
        "saving",
        "commercial"
    ],
    "wof:name":"Community Bank Of Marshall",
    "wof:placetype":"venue"
},
  "geometry": {"coordinates":[-93.48375,39.105615],"type":"Point"}
}