{
  "type": "Feature",
  "properties": {
    "iso:country":"US",
    "sg:address":"4025 Central St",
    "sg:city":"Kansas City",
    "sg:classifiers":[
        {
            "category":"Professional",
            "subcategory":"Accounting & Tax Preparation",
            "type":"Services"
        }
    ],
    "sg:phone":"+1 816 531 4646",
    "sg:postcode":"64111",
    "sg:province":"MO",
    "sg:tags":[
        "accountant"
    ],
    "wof:name":"Emerick & Co",
    "wof:placetype":"venue"
},
  "geometry": {"coordinates":[-94.588432,39.052815],"type":"Point"}
}