{
  "type": "Feature",
  "properties": {
    "iso:country":"US",
    "sg:address":"250 NE Tudor Rd",
    "sg:city":"Lees Summit",
    "sg:classifiers":[
        {
            "category":"Professional",
            "subcategory":"Engineering",
            "type":"Services"
        }
    ],
    "sg:phone":"+1 816 525 3562",
    "sg:postcode":"64086",
    "sg:province":"MO",
    "sg:tags":[
        "consulting",
        "engineer"
    ],
    "wof:name":"Bartlett & West Engineers Inc",
    "wof:placetype":"venue"
},
  "geometry": {"coordinates":[-94.376907,38.930739],"type":"Point"}
}