{
  "type": "Feature",
  "properties": {
    "iso:country":"US",
    "sg:address":"400 S 11th St",
    "sg:city":"Hannibal",
    "sg:classifiers":[
        {
            "category":"Manufacturing",
            "subcategory":"Tools & Machinery",
            "type":"Manufacturing & Wholesale Goods"
        }
    ],
    "sg:phone":"+1 573 248 1545",
    "sg:postcode":"63401",
    "sg:province":"MO",
    "sg:tags":[
        "machine",
        "shop"
    ],
    "wof:name":"Hannibal Machine Inc",
    "wof:placetype":"venue"
},
  "geometry": {"coordinates":[-91.36395899999999,39.703142],"type":"Point"}
}