{
  "type": "Feature",
  "properties": {
    "iso:country":"US",
    "sg:address":"325 N Kings Hwy",
    "sg:city":"Noel",
    "sg:classifiers":[
        {
            "category":"Professional",
            "subcategory":"Management & Consulting",
            "type":"Services"
        }
    ],
    "sg:phone":"+1 417 475 6310",
    "sg:postcode":"64854",
    "sg:province":"MO",
    "wof:name":"Elk River Laundromat",
    "wof:placetype":"venue"
},
  "geometry": {"coordinates":[-94.480379,36.547956],"type":"Point"}
}