{
  "type": "Feature",
  "properties": {
    "iso:country":"US",
    "sg:address":"454 Redings Mill Rd",
    "sg:city":"Joplin",
    "sg:classifiers":[
        {
            "category":"Food & Beverages",
            "subcategory":"Candy",
            "type":"Retail Goods"
        }
    ],
    "sg:phone":"+1 417 624 1515",
    "sg:postcode":"64804",
    "sg:province":"MO",
    "sg:tags":[
        "mfg"
    ],
    "wof:name":"Richardsons Candy House",
    "wof:placetype":"venue"
},
  "geometry": {"coordinates":[-94.516986,37.014716],"type":"Point"}
}