{
  "type": "Feature",
  "properties": {
    "iso:country":"US",
    "sg:address":"67 S County Center Way",
    "sg:city":"St Louis",
    "sg:classifiers":[
        {
            "category":"Shopping",
            "subcategory":"Shoes",
            "type":"Retail Goods"
        },
        {
            "category":"Shopping",
            "subcategory":"Clothing, Apparel, & Fashions",
            "type":"Retail Goods"
        }
    ],
    "sg:phone":"+1 314 416 9660",
    "sg:postcode":"63129",
    "sg:province":"MO",
    "sg:tags":[
        "athletic",
        "leisure",
        "footwear",
        "sportswear"
    ],
    "sg:website":"www.finishline.com",
    "wof:name":"Finish Line",
    "wof:placetype":"venue"
},
  "geometry": {"coordinates":[-90.329155,38.505008],"type":"Point"}
}