{
  "type": "Feature",
  "properties": {
    "iso:country":"US",
    "sg:address":"7659 NW Prairie View Rd",
    "sg:city":"Kansas City",
    "sg:classifiers":[
        {
            "category":"Professional",
            "type":"Services"
        }
    ],
    "sg:phone":"+1 816 505 1717",
    "sg:postcode":"64151",
    "sg:province":"MO",
    "wof:name":"Beadazzler",
    "wof:placetype":"venue"
},
  "geometry": {"coordinates":[-94.658485,39.233331],"type":"Point"}
}