{
  "type": "Feature",
  "properties": {
    "iso:country":"US",
    "sg:address":"5805 Goodfellow",
    "sg:city":"Saint Louis",
    "sg:classifiers":[
        {
            "category":"Shopping",
            "subcategory":"Beauty & Cosmetics",
            "type":"Retail Goods"
        }
    ],
    "sg:phone":"+1 314 381 1030",
    "sg:postcode":"63101",
    "sg:province":"MO",
    "sg:tags":[
        "supply"
    ],
    "wof:name":"Paradise Beauty Supply",
    "wof:placetype":"venue"
},
  "geometry": {"coordinates":[-90.255045,38.713136],"type":"Point"}
}