{
  "type": "Feature",
  "properties": {
    "iso:country":"US",
    "sg:address":"1910 Pine St Ste 412",
    "sg:city":"Saint Louis",
    "sg:classifiers":[
        {
            "category":"Real Estate",
            "subcategory":"Architect",
            "type":"Services"
        }
    ],
    "sg:phone":"+1 314 436 0865",
    "sg:postcode":"63103",
    "sg:province":"MO",
    "wof:name":"Woolpert Llp",
    "wof:placetype":"venue"
},
  "geometry": {"coordinates":[-90.207674,38.631278],"type":"Point"}
}