{
  "type": "Feature",
  "properties": {
    "iso:country":"US",
    "sg:address":"2201 59th St",
    "sg:city":"St Louis",
    "sg:classifiers":[
        {
            "category":"Professional",
            "type":"Services"
        }
    ],
    "sg:phone":"+1 314 647 0148",
    "sg:postcode":"63110",
    "sg:province":"MO",
    "sg:tags":[
        "establishment"
    ],
    "wof:name":"Apprent",
    "wof:placetype":"venue"
},
  "geometry": {"coordinates":[-90.284947,38.616131],"type":"Point"}
}