{
  "type": "Feature",
  "properties": {
    "iso:country":"US",
    "sg:address":"2111 Bellevue Ave Apt E",
    "sg:city":"Saint Louis",
    "sg:classifiers":[
        {
            "category":"Real Estate",
            "subcategory":"Real Estate Operator",
            "type":"Services"
        }
    ],
    "sg:phone":"+1 314 647 4847",
    "sg:postcode":"63143",
    "sg:province":"MO",
    "sg:tags":[
        "apartment"
    ],
    "wof:name":"Peppertree Apartments",
    "wof:placetype":"venue"
},
  "geometry": {"coordinates":[-90.3134,38.619999],"type":"Point"}
}