{
  "type": "Feature",
  "properties": {
    "iso:country":"US",
    "sg:address":"747 Perry Ave",
    "sg:city":"Cape Girardeau",
    "sg:classifiers":[
        {
            "category":"Shopping",
            "subcategory":"Computers & Home Electronics",
            "type":"Retail Goods"
        }
    ],
    "sg:phone":"+1 573 576 8228",
    "sg:postcode":"63701",
    "sg:province":"MO",
    "sg:tags":[
        "equipment",
        "satellite",
        "system"
    ],
    "wof:name":"Satellites Plus",
    "wof:placetype":"venue"
},
  "geometry": {"coordinates":[-89.53918,37.31508],"type":"Point"}
}