{
  "type": "Feature",
  "properties": {
    "iso:country":"US",
    "sg:address":"1828 Walnut St",
    "sg:city":"Kansas City",
    "sg:classifiers":[
        {
            "category":"Real Estate",
            "subcategory":"Architect",
            "type":"Services"
        }
    ],
    "sg:phone":"+1 816 421 6711",
    "sg:postcode":"64108",
    "sg:province":"MO",
    "wof:name":"Rodriguez & Assoc",
    "wof:placetype":"venue"
},
  "geometry": {"coordinates":[-94.582487,39.091744],"type":"Point"}
}