{
  "type": "Feature",
  "properties": {
    "iso:country":"US",
    "sg:address":"755 Pardella Ave",
    "sg:city":"St Louis",
    "sg:classifiers":[
        {
            "category":"Real Estate",
            "subcategory":"Real Estate Operator",
            "type":"Services"
        },
        {
            "category":"Bars & Pubs",
            "type":"Food & Drink"
        }
    ],
    "sg:phone":"+1 314 544 0600",
    "sg:postcode":"63125",
    "sg:province":"MO",
    "sg:tags":[
        "building",
        "drinking",
        "nonresidential"
    ],
    "wof:name":"John and Mary Pardella Club",
    "wof:placetype":"venue"
},
  "geometry": {"coordinates":[-90.281217,38.541593],"type":"Point"}
}