{
  "type": "Feature",
  "properties": {
    "iso:country":"US",
    "sg:address":"1614 Business Loop 70 W",
    "sg:city":"Columbia",
    "sg:classifiers":[
        {
            "category":"Building & Trades",
            "subcategory":"Construction",
            "type":"Services"
        }
    ],
    "sg:phone":"+1 573 445 7098",
    "sg:postcode":"65202",
    "sg:province":"MO",
    "sg:tags":[
        "system",
        "specialty",
        "heating",
        "contractor",
        "air conditioning"
    ],
    "wof:name":"Cockrum Heating & Cooling",
    "wof:placetype":"venue"
},
  "geometry": {"coordinates":[-92.362106,38.967588],"type":"Point"}
}