{
  "type": "Feature",
  "properties": {
    "iso:country":"US",
    "sg:address":"1334 E Republic Rd",
    "sg:city":"Springfield",
    "sg:classifiers":[
        {
            "category":"Real Estate",
            "subcategory":"Real Estate Agent",
            "type":"Services"
        }
    ],
    "sg:phone":"+1 417 887 6664",
    "sg:postcode":"65804",
    "sg:province":"MO",
    "sg:tags":[
        "agency"
    ],
    "wof:name":"Coldwell Banker",
    "wof:placetype":"venue"
},
  "geometry": {"coordinates":[-93.274522,37.137532],"type":"Point"}
}