{
  "type": "Feature",
  "properties": {
    "iso:country":"US",
    "sg:address":"232 NW Oldham Pkwy",
    "sg:city":"Lees Summit",
    "sg:classifiers":[
        {
            "category":"Shopping",
            "subcategory":"Pharmacy",
            "type":"Retail Goods"
        }
    ],
    "sg:phone":"+1 816 347 9839",
    "sg:postcode":"64081",
    "sg:province":"MO",
    "wof:name":"CVS Pharmacy",
    "wof:placetype":"venue"
},
  "geometry": {"coordinates":[-94.40087,38.916876],"type":"Point"}
}