{
  "type": "Feature",
  "properties": {
    "iso:country":"US",
    "sg:address":"238 Madison St",
    "sg:city":"Jefferson City",
    "sg:classifiers":[
        {
            "category":"Banks & Credit Unions",
            "subcategory":"Investment Brokerage",
            "type":"Services"
        }
    ],
    "sg:phone":"+1 573 634 1330",
    "sg:postcode":"65101",
    "sg:province":"MO",
    "sg:tags":[
        "security"
    ],
    "wof:name":"Central Capital Markets",
    "wof:placetype":"venue"
},
  "geometry": {"coordinates":[-92.170404,38.576747],"type":"Point"}
}