{
  "type": "Feature",
  "properties": {
    "iso:country":"US",
    "sg:address":"514 W Mount Vernon St",
    "sg:city":"Springfield",
    "sg:classifiers":[
        {
            "category":"Place Of Worship",
            "subcategory":"Church",
            "type":"Public Place"
        },
        {
            "category":"Place Of Worship",
            "type":"Public Place"
        },
        {
            "category":"Organizations",
            "subcategory":"Religious Organization",
            "type":"Services"
        }
    ],
    "sg:phone":"+1 417 865 3114",
    "sg:postcode":"65806",
    "sg:province":"MO",
    "sg:tags":[
        "god",
        "god-independent",
        "churches-assemblies"
    ],
    "wof:name":"Grace Assembly of God",
    "wof:placetype":"venue"
},
  "geometry": {"coordinates":[-93.29583,37.204191],"type":"Point"}
}