{
  "type": "Feature",
  "properties": {
    "iso:country":"US",
    "sg:address":"70 Garnet Ln",
    "sg:city":"Cape Girardeau",
    "sg:classifiers":[
        {
            "category":"Shopping",
            "subcategory":"Clothing, Apparel, & Fashions",
            "type":"Retail Goods"
        }
    ],
    "sg:phone":"+1 573 651 6007",
    "sg:postcode":"63701",
    "sg:province":"MO",
    "wof:name":"Leannas Exotic Fashions",
    "wof:placetype":"venue"
},
  "geometry": {"coordinates":[-89.599113,37.321892],"type":"Point"}
}