{
  "type": "Feature",
  "properties": {
    "iso:country":"US",
    "sg:address":"4838 Vermillion Dr",
    "sg:city":"Saint Louis",
    "sg:classifiers":[
        {
            "category":"Government",
            "subcategory":"Office",
            "type":"Public Place"
        }
    ],
    "sg:phone":"+1 314 487 9590",
    "sg:postcode":"63128",
    "sg:province":"MO",
    "sg:tags":[
        "program",
        "administrative"
    ],
    "wof:name":"E E O Consulting",
    "wof:placetype":"venue"
},
  "geometry": {"coordinates":[-90.35762099999999,38.505615],"type":"Point"}
}