{
  "type": "Feature",
  "properties": {
    "iso:country":"US",
    "sg:address":"2302 S Moffet Ave",
    "sg:city":"Joplin",
    "sg:classifiers":[
        {
            "category":"Social Services",
            "subcategory":"Child Care",
            "type":"Services"
        }
    ],
    "sg:phone":"+1 417 781 0707",
    "sg:postcode":"64804",
    "sg:province":"MO",
    "sg:tags":[
        "day"
    ],
    "wof:name":"Lil Rascals Daycare",
    "wof:placetype":"venue"
},
  "geometry": {"coordinates":[-94.5201,37.064706],"type":"Point"}
}