{
  "type": "Feature",
  "properties": {
    "iso:country":"US",
    "sg:address":"939 W Liberty Dr",
    "sg:city":"Liberty",
    "sg:classifiers":[
        {
            "category":"Personal",
            "subcategory":"Beauty Salon",
            "type":"Services"
        }
    ],
    "sg:phone":"+1 816 781 9544",
    "sg:postcode":"64068",
    "sg:province":"MO",
    "sg:tags":[
        "shop",
        "spa",
        "day"
    ],
    "wof:name":"Shear Delight Inc",
    "wof:placetype":"venue"
},
  "geometry": {"coordinates":[-94.435515,39.239751],"type":"Point"}
}