{
  "type": "Feature",
  "properties": {
    "iso:country":"US",
    "sg:address":"409 S 7th St",
    "sg:city":"Sarcoxie",
    "sg:classifiers":[
        {
            "category":"Farming",
            "subcategory":"Nursery",
            "type":"Manufacturing & Wholesale Goods"
        }
    ],
    "sg:phone":"+1 417 548 2009",
    "sg:postcode":"64862",
    "sg:province":"MO",
    "sg:tags":[
        "ornamental"
    ],
    "wof:name":"Salyer Greenhouse",
    "wof:placetype":"venue"
},
  "geometry": {"coordinates":[-94.117527,37.063917],"type":"Point"}
}