{
  "type": "Feature",
  "properties": {
    "iso:country":"US",
    "sg:address":"4717 Grand Ave",
    "sg:city":"Kansas City",
    "sg:classifiers":[
        {
            "category":"Professional",
            "subcategory":"Employment Agencies",
            "type":"Services"
        }
    ],
    "sg:phone":"+1 816 561 2222",
    "sg:postcode":"64112",
    "sg:province":"MO",
    "sg:tags":[
        "opportunity"
    ],
    "sg:website":"www.spencerreed.com",
    "wof:name":"Personnel Connection",
    "wof:placetype":"venue"
},
  "geometry": {"coordinates":[-94.585121,39.041947],"type":"Point"}
}