{
  "type": "Feature",
  "properties": {
    "iso:country":"US",
    "sg:address":"15329 Manchester Rd",
    "sg:city":"Ballwin",
    "sg:classifiers":[
        {
            "category":"Shopping",
            "subcategory":"Shoes",
            "type":"Retail Goods"
        }
    ],
    "sg:phone":"+1 636 394 9447",
    "sg:postcode":"63011",
    "sg:province":"MO",
    "wof:name":"Supermarket of Shoes 530",
    "wof:placetype":"venue"
},
  "geometry": {"coordinates":[-90.55859100000001,38.592915],"type":"Point"}
}