{
  "type": "Feature",
  "properties": {
    "iso:country":"US",
    "sg:address":"16500 E Independence Ave",
    "sg:city":"Independence",
    "sg:classifiers":[
        {
            "category":"Retail",
            "subcategory":"Auto Repair",
            "type":"Services"
        },
        {
            "category":"Wholesale",
            "subcategory":"Auto Parts",
            "type":"Manufacturing & Wholesale Goods"
        }
    ],
    "sg:phone":"+1 816 254 0800",
    "sg:postcode":"64050",
    "sg:province":"MO",
    "sg:tags":[
        "transmission",
        "automobile",
        "rebuilt"
    ],
    "wof:name":"A To Z Foreign Auto Parts Inc",
    "wof:placetype":"venue"
},
  "geometry": {"coordinates":[-94.38168899999999,39.099719],"type":"Point"}
}