{
  "type": "Feature",
  "properties": {
    "iso:country":"US",
    "sg:address":"12703 N Robinhood Ln",
    "sg:city":"Kansas City",
    "sg:classifiers":[
        {
            "category":"Freight",
            "type":"Transportation"
        }
    ],
    "sg:phone":"+1 816 734 9900",
    "sg:postcode":"64164",
    "sg:province":"MO",
    "sg:tags":[
        "mover"
    ],
    "wof:name":"Metropolitan Movers",
    "wof:placetype":"venue"
},
  "geometry": {"coordinates":[-94.621093,39.31277],"type":"Point"}
}