{
  "type": "Feature",
  "properties": {
    "iso:country":"US",
    "sg:address":"1402 Hudson Lndg",
    "sg:city":"Saint Charles",
    "sg:classifiers":[
        {
            "category":"Professional",
            "type":"Services"
        }
    ],
    "sg:phone":"+1 636 477 1111",
    "sg:postcode":"63303",
    "sg:province":"MO",
    "wof:name":"M F Farhat",
    "wof:placetype":"venue"
},
  "geometry": {"coordinates":[-90.55161,38.747479],"type":"Point"}
}