{
  "type": "Feature",
  "properties": {
    "iso:country":"US",
    "sg:address":"309 S Oak St",
    "sg:city":"California",
    "sg:classifiers":[
        {
            "category":"Insurance",
            "subcategory":"Hazard Insurance",
            "type":"Services"
        }
    ],
    "sg:phone":"+1 573 796 4622",
    "sg:postcode":"65018",
    "sg:province":"MO",
    "sg:tags":[
        "commercial",
        "business"
    ],
    "sg:website":"http://wolkeninsurance.com",
    "wof:name":"Ken Wolken Insurance Agency",
    "wof:placetype":"venue"
},
  "geometry": {"coordinates":[-92.566322,38.634654],"type":"Point"}
}