{
  "type": "Feature",
  "properties": {
    "iso:country":"US",
    "sg:address":"104 College Ave",
    "sg:city":"Kennett",
    "sg:classifiers":[
        {
            "category":"Government",
            "subcategory":"Office",
            "type":"Public Place"
        }
    ],
    "sg:phone":"+1 573 888 9513",
    "sg:postcode":"63857",
    "sg:province":"MO",
    "sg:tags":[
        "admin",
        "affairs",
        "state"
    ],
    "wof:name":"Veterans Affairs Div",
    "wof:placetype":"venue"
},
  "geometry": {"coordinates":[-90.05558000000001,36.236573],"type":"Point"}
}