{
  "type": "Feature",
  "properties": {
    "iso:country":"US",
    "sg:address":"4 S Central Ave",
    "sg:city":"St Louis",
    "sg:classifiers":[
        {
            "category":"Organizations",
            "subcategory":"Political Organization",
            "type":"Services"
        }
    ],
    "sg:phone":"+1 314 721 5554",
    "sg:postcode":"63105",
    "sg:province":"MO",
    "wof:name":"Dooley For St Louis County",
    "wof:placetype":"venue"
},
  "geometry": {"coordinates":[-90.338368,38.648992],"type":"Point"}
}