{
  "type": "Feature",
  "properties": {
    "iso:country":"US",
    "sg:address":"3547 Ritz Center",
    "sg:city":"St Louis",
    "sg:classifiers":[
        {
            "category":"Building & Trades",
            "subcategory":"Construction",
            "type":"Services"
        }
    ],
    "sg:phone":"+1 314 576 9123",
    "sg:postcode":"63125",
    "sg:province":"MO",
    "sg:tags":[
        "roofing",
        "contractor"
    ],
    "wof:name":"Eagle Contracting",
    "wof:placetype":"venue"
},
  "geometry": {"coordinates":[-90.32350700000001,38.506471],"type":"Point"}
}