{
  "type": "Feature",
  "properties": {
    "iso:country":"US",
    "sg:address":"4723 Dr Martin Luther King Dr",
    "sg:city":"St Louis",
    "sg:classifiers":[
        {
            "category":"Autos & Motor Vehicles",
            "subcategory":"Auto Supplies",
            "type":"Retail Goods"
        }
    ],
    "sg:phone":"+1 314 533 7180",
    "sg:postcode":"63113",
    "sg:province":"MO",
    "sg:tags":[
        "automobile",
        "parts"
    ],
    "wof:name":"American Auto Parts",
    "wof:placetype":"venue"
},
  "geometry": {"coordinates":[-90.25502400000001,38.660886],"type":"Point"}
}