{
  "type": "Feature",
  "properties": {
    "iso:country":"US",
    "sg:address":"800 Chickesaw St",
    "sg:city":"Seneca",
    "sg:classifiers":[
        {
            "category":"Real Estate",
            "subcategory":"Real Estate Operator",
            "type":"Services"
        }
    ],
    "sg:phone":"+1 417 776 2141",
    "sg:postcode":"64865",
    "sg:province":"MO",
    "sg:tags":[
        "apartment"
    ],
    "wof:name":"Indian Hills Apartments",
    "wof:placetype":"venue"
},
  "geometry": {"coordinates":[-94.61565899999999,36.845031],"type":"Point"}
}