{
  "type": "Feature",
  "properties": {
    "iso:country":"US",
    "sg:address":"4632 W Mount Vernon St",
    "sg:city":"Springfield",
    "sg:classifiers":[
        {
            "category":"Professional",
            "subcategory":"Detective & Security Services",
            "type":"Services"
        }
    ],
    "sg:phone":"+1 417 864 7717",
    "sg:postcode":"65802",
    "sg:province":"MO",
    "sg:tags":[
        "car",
        "agency"
    ],
    "wof:name":"C and W Investigating",
    "wof:placetype":"venue"
},
  "geometry": {"coordinates":[-93.375913,37.205118],"type":"Point"}
}