{
  "type": "Feature",
  "properties": {
    "iso:country":"US",
    "sg:address":"701 Hwy 50",
    "sg:city":"Union",
    "sg:classifiers":[
        {
            "category":"Manufacturing",
            "subcategory":"Signs",
            "type":"Manufacturing & Wholesale Goods"
        }
    ],
    "sg:phone":"+1 636 583 8186",
    "sg:postcode":"63084",
    "sg:province":"MO",
    "wof:name":"Union Sign Shop",
    "wof:placetype":"venue"
},
  "geometry": {"coordinates":[-91.016333,38.439329],"type":"Point"}
}