{
  "type": "Feature",
  "properties": {
    "iso:country":"US",
    "sg:address":"134 S Ridge Ave",
    "sg:city":"Liberty",
    "sg:classifiers":[
        {
            "category":"Social Services",
            "type":"Services"
        }
    ],
    "sg:phone":"+1 816 781 1314",
    "sg:postcode":"64068",
    "sg:province":"MO",
    "wof:name":"Dorothy Smith",
    "wof:placetype":"venue"
},
  "geometry": {"coordinates":[-94.43313499999999,39.24425],"type":"Point"}
}