{
  "type": "Feature",
  "properties": {
    "iso:country":"US",
    "sg:address":"236 Turner Blvd",
    "sg:city":"St Peters",
    "sg:classifiers":[
        {
            "category":"Building & Trades",
            "subcategory":"Construction",
            "type":"Services"
        }
    ],
    "sg:phone":"+1 636 278 8787",
    "sg:postcode":"63376",
    "sg:province":"MO",
    "sg:tags":[
        "siding",
        "contractor"
    ],
    "wof:name":"Dalco Industries",
    "wof:placetype":"venue"
},
  "geometry": {"coordinates":[-90.648313,38.805807],"type":"Point"}
}