{
  "type": "Feature",
  "properties": {
    "iso:country":"US",
    "sg:address":"4839 Greenburg Dr",
    "sg:city":"Saint Charles",
    "sg:classifiers":[
        {
            "category":"Railroad",
            "type":"Transportation"
        }
    ],
    "sg:phone":"+1 636 926 7528",
    "sg:postcode":"63304",
    "sg:province":"MO",
    "sg:tags":[
        "operator",
        "line"
    ],
    "wof:name":"Union Pacific Railroad Company",
    "wof:placetype":"venue"
},
  "geometry": {"coordinates":[-90.628384,38.725405],"type":"Point"}
}