{
  "type": "Feature",
  "properties": {
    "addr:full":"1080 Mid Rivers Mall St Peters MO 63376",
    "addr:housenumber":"1080",
    "addr:postcode":"63376",
    "addr:street":"Mid Rivers Mall",
    "iso:country":"US",
    "sg:address":"1080 Mid Rivers Mall",
    "sg:city":"St Peters",
    "sg:classifiers":[
        {
            "category":"Food & Beverages",
            "subcategory":"Bakery",
            "type":"Retail Goods"
        }
    ],
    "sg:phone":"+1 636 278 1450",
    "sg:postcode":"63376",
    "sg:province":"MO",
    "sg:tags":[
        "baker"
    ],
    "wof:name":"Proud Baker Cafe & Creamery",
    "wof:placetype":"venue"
},
  "geometry": {"coordinates":[-90.619827,38.797833],"type":"Point"}
}