{
  "type": "Feature",
  "properties": {
    "iso:country":"US",
    "sg:address":"300 Westport Rd",
    "sg:city":"Kansas City",
    "sg:classifiers":[
        {
            "category":"Professional",
            "subcategory":"Management & Consulting",
            "type":"Services"
        }
    ],
    "sg:phone":"+1 816 531 2222",
    "sg:postcode":"64111",
    "sg:province":"MO",
    "sg:tags":[
        "public",
        "relations"
    ],
    "wof:name":"Primetime Pblcy Mdia Cnsulting",
    "wof:placetype":"venue"
},
  "geometry": {"coordinates":[-94.59026799999999,39.053419],"type":"Point"}
}