{
  "type": "Feature",
  "properties": {
    "iso:country":"US",
    "sg:address":"23651 N Highway 151",
    "sg:city":"Centralia",
    "sg:classifiers":[
        {
            "category":"Organizations",
            "subcategory":"Membership Organization",
            "type":"Services"
        }
    ],
    "sg:phone":"+1 573 682 3613",
    "sg:postcode":"65240",
    "sg:province":"MO",
    "sg:tags":[
        "military",
        "veteran"
    ],
    "wof:name":"Vfw",
    "wof:placetype":"venue"
},
  "geometry": {"coordinates":[-92.142564,39.22975],"type":"Point"}
}