{
  "type": "Feature",
  "properties": {
    "iso:country":"US",
    "sg:address":"5100 Daggett Ave",
    "sg:city":"Saint Louis",
    "sg:classifiers":[
        {
            "category":"Restaurant",
            "type":"Food & Drink"
        }
    ],
    "sg:menulink":"http://www.allmenus.com/mo/st-louis/40411-della-pizzeria/menu/",
    "sg:phone":"+1 314 762 9100",
    "sg:postcode":"63110",
    "sg:province":"MO",
    "sg:tags":[
        "american",
        "pizza"
    ],
    "wof:name":"Della Pizzeria",
    "wof:placetype":"venue"
},
  "geometry": {"coordinates":[-90.270757,38.616583],"type":"Point"}
}