{
  "type": "Feature",
  "properties": {
    "iso:country":"US",
    "sg:address":"128 Jungermann Rd",
    "sg:city":"Saint Peters",
    "sg:classifiers":[
        {
            "category":"Professional",
            "subcategory":"Accounting & Tax Preparation",
            "type":"Services"
        }
    ],
    "sg:phone":"+1 636 922 2226",
    "sg:postcode":"63376",
    "sg:province":"MO",
    "wof:name":"Wayne C Coleman",
    "wof:placetype":"venue"
},
  "geometry": {"coordinates":[-90.576329,38.792559],"type":"Point"}
}