{
  "type": "Feature",
  "properties": {
    "iso:country":"US",
    "sg:address":"2186 Dry Fork Rd",
    "sg:city":"Warrenton",
    "sg:classifiers":[
        {
            "category":"Wholesale",
            "subcategory":"Non-durable Goods",
            "type":"Manufacturing & Wholesale Goods"
        }
    ],
    "sg:phone":"+1 636 456 8513",
    "sg:postcode":"63383",
    "sg:province":"MO",
    "wof:name":"Pumpkins & Pines",
    "wof:placetype":"venue"
},
  "geometry": {"coordinates":[-91.16380599999999,38.704508],"type":"Point"}
}