{
  "type": "Feature",
  "properties": {
    "iso:country":"US",
    "sg:address":"311 S Main St",
    "sg:city":"St Charles",
    "sg:classifiers":[
        {
            "category":"Professional",
            "subcategory":"Management & Consulting",
            "type":"Services"
        }
    ],
    "sg:phone":"+1 636 940 0047",
    "sg:postcode":"63301",
    "sg:province":"MO",
    "sg:tags":[
        "party",
        "planning"
    ],
    "sg:website":"www.bearfactory.com",
    "wof:name":"Bear Factory",
    "wof:placetype":"venue"
},
  "geometry": {"coordinates":[-90.482709,38.77882],"type":"Point"}
}