{
  "type": "Feature",
  "properties": {
    "iso:country":"US",
    "sg:address":"8901 Weldon Ave",
    "sg:city":"St Louis",
    "sg:classifiers":[
        {
            "category":"Real Estate",
            "subcategory":"Real Estate Operator",
            "type":"Services"
        }
    ],
    "sg:phone":"+1 314 521 0388",
    "sg:postcode":"63121",
    "sg:province":"MO",
    "sg:tags":[
        "building",
        "apartment"
    ],
    "wof:name":"Heritage Dunbar Apartments",
    "wof:placetype":"venue"
},
  "geometry": {"coordinates":[-90.320115,38.719896],"type":"Point"}
}