{
  "type": "Feature",
  "properties": {
    "iso:country":"US",
    "sg:address":"510 S Price Rd",
    "sg:city":"Saint Louis",
    "sg:classifiers":[
        {
            "category":"Professional",
            "subcategory":"Lawyer & Legal Services",
            "type":"Services"
        }
    ],
    "sg:phone":"+1 314 727 0911",
    "sg:postcode":"63124",
    "sg:province":"MO",
    "sg:tags":[
        "law"
    ],
    "wof:name":"David R Hess Lc",
    "wof:placetype":"venue"
},
  "geometry": {"coordinates":[-90.366731,38.644017],"type":"Point"}
}