{
  "type": "Feature",
  "properties": {
    "iso:country":"US",
    "sg:address":"311 S Main St",
    "sg:city":"Concordia",
    "sg:classifiers":[
        {
            "category":"Health Services",
            "subcategory":"Doctor",
            "type":"Services"
        },
        {
            "category":"Health Services",
            "subcategory":"Chiropractor",
            "type":"Services"
        }
    ],
    "sg:phone":"+1 660 463 1400",
    "sg:postcode":"64020",
    "sg:province":"MO",
    "sg:tags":[
        "physician",
        "surgeon",
        "chiropractic"
    ],
    "sg:website":"http://www.drtindall.org",
    "wof:name":"Tindall John DR",
    "wof:placetype":"venue"
},
  "geometry": {"coordinates":[-93.56806,38.986183],"type":"Point"}
}