{
  "type": "Feature",
  "properties": {
    "iso:country":"US",
    "sg:address":"16407 Keegan Bluff Ct",
    "sg:city":"Chesterfield",
    "sg:classifiers":[
        {
            "category":"Professional",
            "subcategory":"Business Services",
            "type":"Services"
        },
        {
            "category":"Building & Trades",
            "subcategory":"Construction",
            "type":"Services"
        }
    ],
    "sg:phone":"+1 636 227 0240",
    "sg:postcode":"63005",
    "sg:province":"MO",
    "sg:tags":[
        "floor",
        "laying",
        "contractor"
    ],
    "wof:name":"Flooring Technology Inc",
    "wof:placetype":"venue"
},
  "geometry": {"coordinates":[-90.600793,38.611784],"type":"Point"}
}