{
  "type": "Feature",
  "properties": {
    "iso:country":"US",
    "sg:address":"321 E 1st St",
    "sg:city":"Mountain Grove",
    "sg:classifiers":[
        {
            "category":"Personal",
            "subcategory":"Beauty Salon",
            "type":"Services"
        }
    ],
    "sg:phone":"+1 417 926 7338",
    "sg:postcode":"65711",
    "sg:province":"MO",
    "sg:tags":[
        "shop"
    ],
    "wof:name":"BJs Styles & Smiles",
    "wof:placetype":"venue"
},
  "geometry": {"coordinates":[-92.26087200000001,37.129104],"type":"Point"}
}