{
  "type": "Feature",
  "properties": {
    "iso:country":"US",
    "sg:address":"901 W Broadway St",
    "sg:city":"West Plains",
    "sg:classifiers":[
        {
            "category":"Real Estate",
            "subcategory":"Real Estate Agent",
            "type":"Services"
        }
    ],
    "sg:phone":"+1 417 256 4882",
    "sg:postcode":"65775",
    "sg:province":"MO",
    "sg:website":"www.garysexton.com",
    "wof:name":"Broadway Advantage",
    "wof:placetype":"venue"
},
  "geometry": {"coordinates":[-91.86129099999999,36.731322],"type":"Point"}
}