{
  "type": "Feature",
  "properties": {
    "iso:country":"US",
    "sg:address":"707 Spring Garden Dr",
    "sg:city":"Saint Louis",
    "sg:classifiers":[
        {
            "category":"Social Services",
            "subcategory":"Child Care",
            "type":"Services"
        }
    ],
    "sg:phone":"+1 314 388 5710",
    "sg:postcode":"63137",
    "sg:province":"MO",
    "sg:tags":[
        "childcare",
        "daycare"
    ],
    "wof:name":"Built To Last Dev Inst LLC",
    "wof:placetype":"venue"
},
  "geometry": {"coordinates":[-90.197802,38.748825],"type":"Point"}
}