{
  "type": "Feature",
  "properties": {
    "iso:country":"US",
    "sg:address":"1661 US Hwy 61",
    "sg:city":"Portageville",
    "sg:classifiers":[
        {
            "category":"Wholesale",
            "subcategory":"Chemicals & Plastics",
            "type":"Manufacturing & Wholesale Goods"
        }
    ],
    "sg:phone":"+1 573 379 5674",
    "sg:postcode":"63873",
    "sg:province":"MO",
    "wof:name":"UAP Retail",
    "wof:placetype":"venue"
},
  "geometry": {"coordinates":[-89.679299,36.450427],"type":"Point"}
}