{
  "type": "Feature",
  "properties": {
    "iso:country":"US",
    "sg:address":"807 S Court St",
    "sg:city":"Bowling Green",
    "sg:classifiers":[
        {
            "category":"Organizations",
            "subcategory":"Religious Organization",
            "type":"Services"
        }
    ],
    "sg:phone":"+1 573 324 2450",
    "sg:postcode":"63334",
    "sg:province":"MO",
    "sg:tags":[
        "church"
    ],
    "wof:name":"Church Of The Nazarene",
    "wof:placetype":"venue"
},
  "geometry": {"coordinates":[-91.194925,39.335311],"type":"Point"}
}