{
  "type": "Feature",
  "properties": {
    "iso:country":"US",
    "sg:address":"48 Granada Way",
    "sg:city":"St Louis",
    "sg:classifiers":[
        {
            "category":"Professional",
            "subcategory":"Engineering",
            "type":"Services"
        },
        {
            "category":"Building & Trades",
            "subcategory":"Construction",
            "type":"Services"
        }
    ],
    "sg:phone":"+1 314 991 3018",
    "sg:postcode":"63124",
    "sg:province":"MO",
    "sg:tags":[
        "house",
        "engineer"
    ],
    "sg:website":"www.carolweisman.com",
    "wof:name":"Board Builders",
    "wof:placetype":"venue"
},
  "geometry": {"coordinates":[-90.370633,38.659916],"type":"Point"}
}