{
  "type": "Feature",
  "properties": {
    "iso:country":"US",
    "sg:address":"1338 E Independence Center Dr",
    "sg:city":"Independence",
    "sg:classifiers":[
        {
            "category":"Ice Cream",
            "type":"Food & Drink"
        }
    ],
    "sg:menulink":"http://www.allmenus.com/mo/blue/227044-dippin-dots/menu/",
    "sg:phone":"0",
    "sg:postcode":"64057",
    "sg:province":"MO",
    "sg:tags":[
        "american"
    ],
    "wof:name":"Dippin' Dots",
    "wof:placetype":"venue"
},
  "geometry": {"coordinates":[-94.3604,39.047124],"type":"Point"}
}