{
  "type": "Feature",
  "properties": {
    "iso:country":"US",
    "sg:address":"206 Industrial Dr",
    "sg:city":"Richmond",
    "sg:classifiers":[
        {
            "category":"Manufacturing",
            "subcategory":"Metals",
            "type":"Manufacturing & Wholesale Goods"
        }
    ],
    "sg:phone":"+1 816 776 3121",
    "sg:postcode":"64085",
    "sg:province":"MO",
    "sg:tags":[
        "metal-wholesale",
        "manufacturer"
    ],
    "wof:name":"Spartan Metals, Inc.",
    "wof:placetype":"venue"
},
  "geometry": {"coordinates":[-93.99404199999999,39.278781],"type":"Point"}
}