{
  "type": "Feature",
  "properties": {
    "iso:country":"US",
    "sg:address":"110 N Mine la Motte Ave",
    "sg:city":"Fredericktown",
    "sg:classifiers":[
        {
            "category":"Professional",
            "subcategory":"Lawyer & Legal Services",
            "type":"Services"
        }
    ],
    "sg:phone":"+1 573 783 8745",
    "sg:postcode":"63645",
    "sg:province":"MO",
    "sg:tags":[
        "attorney"
    ],
    "wof:name":"Michael J Anderson",
    "wof:placetype":"venue"
},
  "geometry": {"coordinates":[-90.29283,37.560976],"type":"Point"}
}