{
  "type": "Feature",
  "properties": {
    "iso:country":"US",
    "sg:address":"215 W Atlantic St",
    "sg:city":"Branson",
    "sg:classifiers":[
        {
            "category":"Health Services",
            "subcategory":"Dentist",
            "type":"Services"
        }
    ],
    "sg:phone":"+1 417 334 3213",
    "sg:postcode":"65616",
    "sg:province":"MO",
    "wof:name":"Robert E Cowan Dds",
    "wof:placetype":"venue"
},
  "geometry": {"coordinates":[-93.218414,36.645085],"type":"Point"}
}