{
  "type": "Feature",
  "properties": {
    "iso:country":"US",
    "sg:address":"615 N Boonville Ave",
    "sg:city":"Springfield",
    "sg:classifiers":[
        {
            "category":"Manufacturing",
            "subcategory":"Printing",
            "type":"Manufacturing & Wholesale Goods"
        }
    ],
    "sg:phone":"+1 417 837 1951",
    "sg:postcode":"65806",
    "sg:province":"MO",
    "sg:tags":[
        "periodical"
    ],
    "wof:name":"Parent & Family Magazine",
    "wof:placetype":"venue"
},
  "geometry": {"coordinates":[-93.29243700000001,37.214722],"type":"Point"}
}