{
  "type": "Feature",
  "properties": {
    "iso:country":"US",
    "sg:address":"1801 Old Boyd St",
    "sg:city":"De Soto",
    "sg:classifiers":[
        {
            "category":"Autos & Motor Vehicles",
            "subcategory":"Automobile Sales",
            "type":"Retail Goods"
        }
    ],
    "sg:phone":"+1 636 586 1970",
    "sg:postcode":"63020",
    "sg:province":"MO",
    "wof:name":"B & L Auto Sales",
    "wof:placetype":"venue"
},
  "geometry": {"coordinates":[-90.57701900000001,38.14682],"type":"Point"}
}