{
  "type": "Feature",
  "properties": {
    "iso:country":"US",
    "sg:address":"342 Commercial Aly",
    "sg:city":"Pineville",
    "sg:classifiers":[
        {
            "category":"Personal",
            "subcategory":"Beauty Salon",
            "type":"Services"
        }
    ],
    "sg:phone":"+1 417 226 0236",
    "sg:postcode":"64801",
    "sg:province":"MO",
    "wof:name":"Smart Style Family Hair Salon",
    "wof:placetype":"venue"
},
  "geometry": {"coordinates":[-94.51042200000001,37.084865],"type":"Point"}
}