{
  "type": "Feature",
  "properties": {
    "iso:country":"US",
    "sg:address":"915 5th St",
    "sg:city":"Monett",
    "sg:classifiers":[
        {
            "category":"Professional",
            "subcategory":"Accounting & Tax Preparation",
            "type":"Services"
        }
    ],
    "sg:phone":"+1 417 235 5469",
    "sg:postcode":"65708",
    "sg:province":"MO",
    "wof:name":"Doris Meyer Tax Services",
    "wof:placetype":"venue"
},
  "geometry": {"coordinates":[-93.923435,36.929777],"type":"Point"}
}