{
  "type": "Feature",
  "properties": {
    "iso:country":"US",
    "sg:address":"601 W Nifong Blvd Ste 1A",
    "sg:city":"Columbia",
    "sg:classifiers":[
        {
            "category":"Insurance",
            "subcategory":"Hazard Insurance",
            "type":"Services"
        }
    ],
    "sg:phone":"+1 573 256 7744",
    "sg:postcode":"65203",
    "sg:province":"MO",
    "sg:website":"http://statefarm.mqgroup.com/url.asp?usr=253762",
    "wof:name":"State Farm Insurance Agent-Dale Parker",
    "wof:placetype":"venue"
},
  "geometry": {"coordinates":[-92.348022,38.90778],"type":"Point"}
}