{
  "type": "Feature",
  "properties": {
    "iso:country":"US",
    "sg:address":"114 S Smith St",
    "sg:city":"Albany",
    "sg:classifiers":[
        {
            "category":"Insurance",
            "subcategory":"Insurance Agent",
            "type":"Services"
        }
    ],
    "sg:phone":"+1 660 726 3310",
    "sg:postcode":"64402",
    "sg:province":"MO",
    "sg:tags":[
        "consultant"
    ],
    "wof:name":"Farmers Mutual Fire Insurance",
    "wof:placetype":"venue"
},
  "geometry": {"coordinates":[-94.332621,40.247747],"type":"Point"}
}