{
  "type": "Feature",
  "properties": {
    "iso:country":"US",
    "sg:address":"161 N Outer Rd",
    "sg:city":"Bourbon",
    "sg:classifiers":[
        {
            "category":"Food & Beverages",
            "subcategory":"Groceries & Convenience Stores",
            "type":"Retail Goods"
        }
    ],
    "sg:phone":"+1 573 732 5907",
    "sg:postcode":"65441",
    "sg:province":"MO",
    "wof:name":"Bourbon One Stop",
    "wof:placetype":"venue"
},
  "geometry": {"coordinates":[-91.294428,38.133318],"type":"Point"}
}