{
  "type": "Feature",
  "properties": {
    "iso:country":"US",
    "sg:address":"39 Normandy Rd",
    "sg:city":"Fordland",
    "sg:classifiers":[
        {
            "category":"Building & Trades",
            "subcategory":"Construction",
            "type":"Services"
        }
    ],
    "sg:phone":"+1 417 738 2330",
    "sg:postcode":"65652",
    "sg:province":"MO",
    "sg:tags":[
        "dry wall",
        "contractor"
    ],
    "wof:name":"Hoagland Dry Wall",
    "wof:placetype":"venue"
},
  "geometry": {"coordinates":[-92.918797,37.180888],"type":"Point"}
}