{
  "type": "Feature",
  "properties": {
    "iso:country":"US",
    "sg:address":"121 S Meramec Ave",
    "sg:city":"Saint Louis",
    "sg:classifiers":[
        {
            "category":"Government",
            "subcategory":"Office",
            "type":"Public Place"
        }
    ],
    "sg:phone":"+1 314 615 4414",
    "sg:postcode":"63105",
    "sg:province":"MO",
    "sg:tags":[
        "development",
        "community"
    ],
    "wof:name":"St Louis Home Consortium",
    "wof:placetype":"venue"
},
  "geometry": {"coordinates":[-90.340048,38.648022],"type":"Point"}
}