{
  "type": "Feature",
  "properties": {
    "iso:country":"US",
    "sg:address":"1823 Lawanda Dr",
    "sg:city":"Cape Girardeau",
    "sg:classifiers":[
        {
            "category":"Arts & Performance",
            "subcategory":"Theater",
            "type":"Entertainment"
        }
    ],
    "sg:phone":"+1 573 335 2116",
    "sg:postcode":"63701",
    "sg:province":"MO",
    "sg:tags":[
        "group"
    ],
    "wof:name":"G M Ryan Consulting LLC",
    "wof:placetype":"venue"
},
  "geometry": {"coordinates":[-89.541573,37.32301],"type":"Point"}
}