{
  "type": "Feature",
  "properties": {
    "iso:country":"US",
    "sg:address":"815 N Glenstone Ave",
    "sg:city":"Springfield",
    "sg:classifiers":[
        {
            "category":"Travel",
            "subcategory":"Hotels & Motels",
            "type":"Entertainment"
        }
    ],
    "sg:phone":"+1 417 865 6681",
    "sg:postcode":"65802",
    "sg:province":"MO",
    "sg:tags":[
        "communications",
        "operation",
        "telegraph"
    ],
    "wof:name":"Dogwood Park Inn",
    "wof:placetype":"venue"
},
  "geometry": {"coordinates":[-93.261746,37.216077],"type":"Point"}
}