{
  "type": "Feature",
  "properties": {
    "iso:country":"US",
    "sg:address":"1104 E 13th St",
    "sg:city":"Joplin",
    "sg:classifiers":[
        {
            "category":"Retail",
            "subcategory":"Auto Repair",
            "type":"Services"
        }
    ],
    "sg:phone":"+1 417 681 0848",
    "sg:postcode":"64801",
    "sg:province":"MO",
    "sg:tags":[
        "repairing",
        "automobile"
    ],
    "wof:name":"C-Mac Auto Repair",
    "wof:placetype":"venue"
},
  "geometry": {"coordinates":[-94.501735,37.077013],"type":"Point"}
}