{
  "type": "Feature",
  "properties": {
    "iso:country":"US",
    "sg:address":"567 Oakhaven Ln",
    "sg:city":"Saint Louis",
    "sg:classifiers":[
        {
            "category":"Professional",
            "subcategory":"Lawyer & Legal Services",
            "type":"Services"
        }
    ],
    "sg:phone":"+1 314 567 7283",
    "sg:postcode":"63141",
    "sg:province":"MO",
    "wof:name":"Scott Greenberg Atty",
    "wof:placetype":"venue"
},
  "geometry": {"coordinates":[-90.423529,38.66882],"type":"Point"}
}