{
  "type": "Feature",
  "properties": {
    "iso:country":"US",
    "sg:address":"18452 State Hwy 13",
    "sg:city":"Reeds Spring",
    "sg:classifiers":[
        {
            "category":"Health Services",
            "subcategory":"Health Practitioner",
            "type":"Services"
        }
    ],
    "sg:phone":"+1 417 272 1881",
    "sg:postcode":"65737",
    "sg:province":"MO",
    "sg:tags":[
        "therapist",
        "physical"
    ],
    "wof:name":"Branson West Rehab Svc",
    "wof:placetype":"venue"
},
  "geometry": {"coordinates":[-93.369722,36.702079],"type":"Point"}
}