{
  "type": "Feature",
  "properties": {
    "iso:country":"US",
    "sg:address":"14780 Manchester Rd",
    "sg:city":"Ballwin",
    "sg:classifiers":[
        {
            "category":"Sports & Exercise",
            "subcategory":"Gym",
            "type":"Entertainment"
        }
    ],
    "sg:phone":"+1 636 527 5930",
    "sg:postcode":"63011",
    "sg:province":"MO",
    "sg:tags":[
        "club",
        "health",
        "studio",
        "gymnasium"
    ],
    "wof:name":"Fitness Factory",
    "wof:placetype":"venue"
},
  "geometry": {"coordinates":[-90.53330099999999,38.592987],"type":"Point"}
}