{
  "type": "Feature",
  "properties": {
    "iso:country":"US",
    "sg:address":"225 S Meramec Ave",
    "sg:city":"St Louis",
    "sg:classifiers":[
        {
            "category":"Social Services",
            "type":"Services"
        }
    ],
    "sg:phone":"+1 314 412 1445",
    "sg:postcode":"63105",
    "sg:province":"MO",
    "sg:tags":[
        "counselor",
        "marriage",
        "family"
    ],
    "wof:name":"Carol Coulson",
    "wof:placetype":"venue"
},
  "geometry": {"coordinates":[-90.340318,38.64624],"type":"Point"}
}