{
  "type": "Feature",
  "properties": {
    "iso:country":"US",
    "sg:address":"186 NW Oldham Pkwy",
    "sg:city":"Lees Summit",
    "sg:classifiers":[
        {
            "category":"Recreation",
            "type":"Entertainment"
        }
    ],
    "sg:phone":"+1 816 524 2636",
    "sg:postcode":"64081",
    "sg:province":"MO",
    "sg:tags":[
        "instruction",
        "gymnastic"
    ],
    "wof:name":"Little Gym Of Lee's Summit Inc",
    "wof:placetype":"venue"
},
  "geometry": {"coordinates":[-94.401337,38.917568],"type":"Point"}
}