{
  "type": "Feature",
  "properties": {
    "iso:country":"US",
    "sg:address":"7006 NW Barry Rd",
    "sg:city":"Kansas City",
    "sg:classifiers":[
        {
            "category":"Restaurant",
            "type":"Food & Drink"
        }
    ],
    "sg:menulink":"http://www.allmenus.com/mo/may/12105-outback-steakhouse/menu/",
    "sg:phone":"+1 816 741 8900",
    "sg:postcode":"64153",
    "sg:province":"MO",
    "sg:tags":[
        "american",
        "steakhouse"
    ],
    "wof:name":"Outback Steakhouse",
    "wof:placetype":"venue"
},
  "geometry": {"coordinates":[-94.662233,39.246909],"type":"Point"}
}