{
  "type": "Feature",
  "properties": {
    "iso:country":"US",
    "sg:address":"112 E Pine St",
    "sg:city":"Strafford",
    "sg:classifiers":[
        {
            "category":"Government",
            "subcategory":"Office",
            "type":"Public Place"
        }
    ],
    "sg:phone":"+1 417 736 2154",
    "sg:postcode":"65757",
    "sg:province":"MO",
    "sg:tags":[
        "city"
    ],
    "wof:name":"Strafford City Hall",
    "wof:placetype":"venue"
},
  "geometry": {"coordinates":[-93.11734,37.26891],"type":"Point"}
}