{
  "type": "Feature",
  "properties": {
    "iso:country":"US",
    "sg:address":"2498 Old Springfield Rd",
    "sg:city":"Cuba",
    "sg:classifiers":[
        {
            "category":"Personal",
            "type":"Services"
        }
    ],
    "sg:phone":"+1 573 885 7445",
    "sg:postcode":"65453",
    "sg:province":"MO",
    "sg:tags":[
        "assistant"
    ],
    "wof:name":"Shelter Pals Of Crawford County",
    "wof:placetype":"venue"
},
  "geometry": {"coordinates":[-91.456658,38.062308],"type":"Point"}
}