{
  "type": "Feature",
  "properties": {
    "iso:country":"US",
    "sg:address":"1325 S Glenstone Ave",
    "sg:city":"Springfield",
    "sg:classifiers":[
        {
            "category":"Food & Beverages",
            "subcategory":"Groceries & Convenience Stores",
            "type":"Retail Goods"
        }
    ],
    "sg:phone":"+1 417 887 9244",
    "sg:postcode":"65804",
    "sg:province":"MO",
    "sg:tags":[
        "eating"
    ],
    "wof:name":"Country Deli",
    "wof:placetype":"venue"
},
  "geometry": {"coordinates":[-93.262282,37.189459],"type":"Point"}
}