{
  "type": "Feature",
  "properties": {
    "iso:country":"US",
    "sg:address":"7910 Gravois Rd",
    "sg:city":"Saint Louis",
    "sg:classifiers":[
        {
            "category":"Shopping",
            "subcategory":"Computers & Home Electronics",
            "type":"Retail Goods"
        }
    ],
    "sg:phone":"+1 314 631 7070",
    "sg:postcode":"63123",
    "sg:province":"MO",
    "wof:name":"D & S Satellite & Video",
    "wof:placetype":"venue"
},
  "geometry": {"coordinates":[-90.299092,38.561006],"type":"Point"}
}