{
  "type": "Feature",
  "properties": {
    "iso:country":"US",
    "sg:address":"2927 S Sterling Ave",
    "sg:city":"Independence",
    "sg:classifiers":[
        {
            "category":"Professional",
            "type":"Services"
        }
    ],
    "sg:phone":"+1 816 252 1074",
    "sg:postcode":"64052",
    "sg:province":"MO",
    "wof:name":"Hunt Te Inc",
    "wof:placetype":"venue"
},
  "geometry": {"coordinates":[-94.446613,39.067852],"type":"Point"}
}