{
  "type": "Feature",
  "properties": {
    "iso:country":"US",
    "sg:address":"2408 Blue Ridge Blvd",
    "sg:city":"Kansas City",
    "sg:classifiers":[
        {
            "category":"Wholesale",
            "subcategory":"Auto Parts",
            "type":"Manufacturing & Wholesale Goods"
        }
    ],
    "sg:phone":"+1 816 252 1940",
    "sg:postcode":"64129",
    "sg:province":"MO",
    "sg:tags":[
        "automobile",
        "rebuilt"
    ],
    "wof:name":"Greenleaf Auto Recyclers",
    "wof:placetype":"venue"
},
  "geometry": {"coordinates":[-94.470707,39.076437],"type":"Point"}
}