{
  "type": "Feature",
  "properties": {
    "iso:country":"US",
    "sg:address":"707 N 36th St",
    "sg:city":"St Joseph",
    "sg:classifiers":[
        {
            "category":"Health Services",
            "subcategory":"Optometrist",
            "type":"Services"
        }
    ],
    "sg:phone":"+1 816 279 5683",
    "sg:postcode":"64506",
    "sg:province":"MO",
    "wof:name":"Bonebrake Vision & Eye Ctr",
    "wof:placetype":"venue"
},
  "geometry": {"coordinates":[-94.806156,39.774125],"type":"Point"}
}