{
  "type": "Feature",
  "properties": {
    "iso:country":"US",
    "sg:address":"717 W Pearce Blvd",
    "sg:city":"Wentzville",
    "sg:classifiers":[
        {
            "category":"Education",
            "subcategory":"School",
            "type":"Public Place"
        }
    ],
    "sg:phone":"+1 636 332 5837",
    "sg:postcode":"63385",
    "sg:province":"MO",
    "wof:name":"Futures Learning Ctr",
    "wof:placetype":"venue"
},
  "geometry": {"coordinates":[-90.862651,38.810382],"type":"Point"}
}