{
  "type": "Feature",
  "properties": {
    "iso:country":"US",
    "sg:address":"1800 E Langsford Rd",
    "sg:city":"Lees Summit",
    "sg:classifiers":[
        {
            "category":"Restaurant",
            "type":"Food & Drink"
        }
    ],
    "sg:phone":"+1 816 524 7908",
    "sg:postcode":"64063",
    "sg:province":"MO",
    "sg:tags":[
        "out"
    ],
    "wof:name":"Casey's Carry Out Pizza",
    "wof:placetype":"venue"
},
  "geometry": {"coordinates":[-94.33626099999999,38.916775],"type":"Point"}
}