{
  "type": "Feature",
  "properties": {
    "iso:country":"US",
    "sg:address":"5343 Botanical Ave",
    "sg:city":"St Louis",
    "sg:classifiers":[
        {
            "category":"Organizations",
            "subcategory":"Religious Organization",
            "type":"Services"
        }
    ],
    "sg:phone":"+1 314 771 3222",
    "sg:postcode":"63110",
    "sg:province":"MO",
    "sg:tags":[
        "church"
    ],
    "wof:name":"Bansuk Baptist Church",
    "wof:placetype":"venue"
},
  "geometry": {"coordinates":[-90.27698700000001,38.612481],"type":"Point"}
}