{
  "type": "Feature",
  "properties": {
    "iso:country":"US",
    "sg:address":"9 Apache Dr",
    "sg:city":"Greenwood",
    "sg:classifiers":[
        {
            "category":"Insurance",
            "subcategory":"Insurance Agent",
            "type":"Services"
        }
    ],
    "sg:phone":"+1 816 537 0063",
    "sg:postcode":"64034",
    "sg:province":"MO",
    "wof:name":"Pallante Insurance Agency",
    "wof:placetype":"venue"
},
  "geometry": {"coordinates":[-94.35979399999999,38.830645],"type":"Point"}
}