{
  "type": "Feature",
  "properties": {
    "iso:country":"US",
    "sg:address":"26883 US Hwy 136",
    "sg:city":"Bethany",
    "sg:phone":"+1 660 425 6566",
    "sg:postcode":"64424",
    "sg:province":"MO",
    "sg:tags":[
        "beef",
        "farm",
        "corn",
        "cash",
        "grain",
        "cattle",
        "feedlot"
    ],
    "wof:name":"Butler Farms",
    "wof:placetype":"venue"
},
  "geometry": {"coordinates":[-93.918603,40.264311],"type":"Point"}
}