{
  "type": "Feature",
  "properties": {
    "iso:country":"US",
    "sg:address":"3817 S Kingshighway Blvd",
    "sg:city":"Saint Louis",
    "sg:classifiers":[
        {
            "category":"Personal",
            "subcategory":"Barber",
            "type":"Services"
        }
    ],
    "sg:phone":"+1 314 752 4747",
    "sg:postcode":"63109",
    "sg:province":"MO",
    "sg:tags":[
        "shop"
    ],
    "wof:name":"Sure Cut Barber Salon & Co",
    "wof:placetype":"venue"
},
  "geometry": {"coordinates":[-90.27269699999999,38.592098],"type":"Point"}
}