{
  "type": "Feature",
  "properties": {
    "iso:country":"US",
    "sg:address":"1704 Buckingham St",
    "sg:city":"St Joseph",
    "sg:classifiers":[
        {
            "category":"Social Services",
            "type":"Services"
        }
    ],
    "sg:phone":"+1 816 233 1351",
    "sg:postcode":"64506",
    "sg:province":"MO",
    "sg:tags":[
        "youth",
        "organization",
        "center"
    ],
    "sg:website":"www.micosay.org",
    "wof:name":"Boy Scouts Of America",
    "wof:placetype":"venue"
},
  "geometry": {"coordinates":[-94.792672,39.781766],"type":"Point"}
}