{
  "type": "Feature",
  "properties": {
    "addr:full":"811 US Highway 60 E Republic MO 65738",
    "addr:housenumber":"811",
    "addr:postcode":"65738",
    "addr:street":"Us Highway 60 E",
    "iso:country":"US",
    "sg:address":"811 US Highway 60 E",
    "sg:city":"Republic",
    "sg:classifiers":[
        {
            "category":"Banks & Credit Unions",
            "subcategory":"Bank",
            "type":"Services"
        },
        {
            "category":"Banks & Credit Unions",
            "subcategory":"Financial Services",
            "type":"Services"
        }
    ],
    "sg:phone":"+1 800 734 4667",
    "sg:postcode":"65738",
    "sg:province":"MO",
    "sg:tags":[
        "commercial",
        "loan",
        "saving"
    ],
    "sg:website":"http://www.regionsbank.com",
    "wof:name":"Regions Bank",
    "wof:placetype":"venue"
},
  "geometry": {"coordinates":[-93.447304,37.13773],"type":"Point"}
}