{
  "type": "Feature",
  "properties": {
    "iso:country":"US",
    "sg:address":"620 Doddridge St Ste B",
    "sg:city":"Saint Louis",
    "sg:classifiers":[
        {
            "category":"Education",
            "subcategory":"School",
            "type":"Public Place"
        }
    ],
    "sg:phone":"+1 314 868 0228",
    "sg:postcode":"63147",
    "sg:province":"MO",
    "wof:name":"Durham School Services",
    "wof:placetype":"venue"
},
  "geometry": {"coordinates":[-90.226226,38.718597],"type":"Point"}
}