{
  "type": "Feature",
  "properties": {
    "iso:country":"US",
    "sg:address":"219 Frisco Rd",
    "sg:city":"Campbell",
    "sg:classifiers":[
        {
            "category":"Food & Beverages",
            "subcategory":"Groceries & Convenience Stores",
            "type":"Retail Goods"
        }
    ],
    "sg:phone":"+1 573 246 3333",
    "sg:postcode":"63933",
    "sg:province":"MO",
    "wof:name":"Country Corner",
    "wof:placetype":"venue"
},
  "geometry": {"coordinates":[-90.077588,36.493411],"type":"Point"}
}