{
  "type": "Feature",
  "properties": {
    "iso:country":"US",
    "sg:address":"501 US Hwy 24",
    "sg:city":"Salisbury",
    "sg:classifiers":[
        {
            "category":"Professional",
            "type":"Services"
        }
    ],
    "sg:phone":"+1 660 388 6406",
    "sg:postcode":"65281",
    "sg:province":"MO",
    "sg:tags":[
        "establishment"
    ],
    "wof:name":"Reel Deals LLC",
    "wof:placetype":"venue"
},
  "geometry": {"coordinates":[-92.795841,39.430534],"type":"Point"}
}