{
  "type": "Feature",
  "properties": {
    "iso:country":"US",
    "sg:address":"1800 Shadywood Ct",
    "sg:city":"Chesterfield",
    "sg:classifiers":[
        {
            "category":"Education",
            "subcategory":"Special Training",
            "type":"Public Place"
        }
    ],
    "sg:phone":"+1 636 537 1847",
    "sg:postcode":"63017",
    "sg:province":"MO",
    "sg:tags":[
        "speaker"
    ],
    "wof:name":"Franz Wippold",
    "wof:placetype":"venue"
},
  "geometry": {"coordinates":[-90.54836899999999,38.642469],"type":"Point"}
}