{
  "type": "Feature",
  "properties": {
    "iso:country":"US",
    "sg:address":"11951 E Englewood Rd",
    "sg:city":"Ashland",
    "sg:classifiers":[
        {
            "category":"Organizations",
            "subcategory":"Community Association",
            "type":"Services"
        }
    ],
    "sg:phone":"+1 573 657 2649",
    "sg:postcode":"65010",
    "sg:province":"MO",
    "wof:name":"Veterans of Foreign Wars 6762",
    "wof:placetype":"venue"
},
  "geometry": {"coordinates":[-92.157963,38.817377],"type":"Point"}
}