{
  "type": "Feature",
  "properties": {
    "iso:country":"US",
    "sg:address":"1050 NW S Outer Rd",
    "sg:city":"Blue Springs",
    "sg:classifiers":[
        {
            "category":"Building & Trades",
            "subcategory":"Construction",
            "type":"Services"
        }
    ],
    "sg:phone":"+1 816 229 4042",
    "sg:postcode":"64015",
    "sg:province":"MO",
    "sg:tags":[
        "designer",
        "dealer",
        "pool",
        "swimming"
    ],
    "sg:website":"www.yournextpool.com",
    "wof:name":"B Carpenter & Sons Inc",
    "wof:placetype":"venue"
},
  "geometry": {"coordinates":[-94.278125,39.030513],"type":"Point"}
}