{
  "type": "Feature",
  "properties": {
    "iso:country":"US",
    "sg:address":"76 Main St",
    "sg:city":"Cassville",
    "sg:classifiers":[
        {
            "category":"Government",
            "subcategory":"Office",
            "type":"Public Place"
        }
    ],
    "sg:phone":"+1 417 847 2862",
    "sg:postcode":"65625",
    "sg:province":"MO",
    "sg:tags":[
        "use",
        "land",
        "commodity",
        "related",
        "program",
        "administers"
    ],
    "wof:name":"Farm Service Agency",
    "wof:placetype":"venue"
},
  "geometry": {"coordinates":[-93.874005,36.672885],"type":"Point"}
}