{
  "type": "Feature",
  "properties": {
    "iso:country":"US",
    "sg:address":"1304 S 25th St",
    "sg:city":"Bethany",
    "sg:classifiers":[
        {
            "category":"Autos & Motor Vehicles",
            "subcategory":"Fuel & Gas Station",
            "type":"Retail Goods"
        }
    ],
    "sg:phone":"+1 660 425 2312",
    "sg:postcode":"64424",
    "sg:province":"MO",
    "sg:tags":[
        "oil"
    ],
    "wof:name":"Alexander MFA",
    "wof:placetype":"venue"
},
  "geometry": {"coordinates":[-94.02704199999999,40.255321],"type":"Point"}
}