{
  "type": "Feature",
  "properties": {
    "iso:country":"US",
    "sg:address":"24261 Hwy 5",
    "sg:city":"Versailles",
    "sg:classifiers":[
        {
            "category":"Building & Trades",
            "subcategory":"Construction",
            "type":"Services"
        }
    ],
    "sg:phone":"+1 573 372 3853",
    "sg:postcode":"65084",
    "sg:province":"MO",
    "sg:tags":[
        "contractor"
    ],
    "wof:name":"Above All Enterprises",
    "wof:placetype":"venue"
},
  "geometry": {"coordinates":[-92.846988,38.33115],"type":"Point"}
}