{
  "type": "Feature",
  "properties": {
    "iso:country":"US",
    "sg:address":"1500 Kearney Rd",
    "sg:city":"Excelsior Spgs",
    "sg:classifiers":[
        {
            "category":"Banks & Credit Unions",
            "subcategory":"Bank",
            "type":"Services"
        }
    ],
    "sg:phone":"+1 816 979 6942",
    "sg:postcode":"64024",
    "sg:province":"MO",
    "sg:tags":[
        "mortgage"
    ],
    "wof:name":"Bank of America",
    "wof:placetype":"venue"
},
  "geometry": {"coordinates":[-94.24193099999999,39.338452],"type":"Point"}
}