{
  "type": "Feature",
  "properties": {
    "iso:country":"US",
    "sg:address":"13302 Manchester Rd",
    "sg:city":"Saint Louis",
    "sg:classifiers":[
        {
            "category":"Health Services",
            "subcategory":"Doctor",
            "type":"Services"
        }
    ],
    "sg:phone":"+1 314 984 9900",
    "sg:postcode":"63131",
    "sg:province":"MO",
    "wof:name":"Fink Debra DMD PC",
    "wof:placetype":"venue"
},
  "geometry": {"coordinates":[-90.468119,38.599637],"type":"Point"}
}