{
  "type": "Feature",
  "properties": {
    "iso:country":"US",
    "sg:address":"306 S 6th St",
    "sg:city":"Hannibal",
    "sg:classifiers":[
        {
            "category":"Sports & Exercise",
            "subcategory":"Bowling",
            "type":"Entertainment"
        }
    ],
    "sg:phone":"+1 573 221 8381",
    "sg:postcode":"63401",
    "sg:province":"MO",
    "sg:tags":[
        "center"
    ],
    "wof:name":"Ten Pin Alleys",
    "wof:placetype":"venue"
},
  "geometry": {"coordinates":[-91.359072,39.706163],"type":"Point"}
}