{
  "type": "Feature",
  "properties": {
    "iso:country":"US",
    "sg:address":"18022 Main St",
    "sg:city":"Eagleville",
    "sg:classifiers":[
        {
            "category":"Professional",
            "subcategory":"Business Services",
            "type":"Services"
        }
    ],
    "sg:phone":"+1 660 867 5355",
    "sg:postcode":"64442",
    "sg:province":"MO",
    "wof:name":"Sunn Dogg Duplication",
    "wof:placetype":"venue"
},
  "geometry": {"coordinates":[-93.977469,40.468941],"type":"Point"}
}