{
  "type": "Feature",
  "properties": {
    "iso:country":"US",
    "sg:address":"6436 Chippewa St",
    "sg:city":"St Louis",
    "sg:classifiers":[
        {
            "category":"Personal",
            "subcategory":"Beauty Salon",
            "type":"Services"
        }
    ],
    "sg:phone":"+1 314 353 2324",
    "sg:postcode":"63109",
    "sg:province":"MO",
    "sg:tags":[
        "shop"
    ],
    "wof:name":"Custom Hair Design Inc",
    "wof:placetype":"venue"
},
  "geometry": {"coordinates":[-90.30017100000001,38.593239],"type":"Point"}
}