{
  "type": "Feature",
  "properties": {
    "iso:country":"US",
    "sg:address":"1212 N Main St",
    "sg:city":"Mountain Grove",
    "sg:classifiers":[
        {
            "category":"Professional",
            "subcategory":"Accounting & Tax Preparation",
            "type":"Services"
        }
    ],
    "sg:phone":"+1 417 926 7788",
    "sg:postcode":"65711",
    "sg:province":"MO",
    "wof:name":"Darrah & Co",
    "wof:placetype":"venue"
},
  "geometry": {"coordinates":[-92.26297700000001,37.138951],"type":"Point"}
}