{
  "type": "Feature",
  "properties": {
    "iso:country":"US",
    "sg:address":"1 Crown Dr",
    "sg:city":"Kirksville",
    "sg:classifiers":[
        {
            "category":"Health Services",
            "subcategory":"Doctor",
            "type":"Services"
        }
    ],
    "sg:phone":"+1 660 665 2844",
    "sg:postcode":"63501",
    "sg:province":"MO",
    "sg:tags":[
        "gynecology",
        "physician",
        "surgeon",
        "surgeons",
        "obstetrics"
    ],
    "wof:name":"Freeland, Arthur G",
    "wof:placetype":"venue"
},
  "geometry": {"coordinates":[-92.57405900000001,40.204632],"type":"Point"}
}