{
  "type": "Feature",
  "properties": {
    "iso:country":"US",
    "sg:address":"305 N Walnut St",
    "sg:city":"Fair Play",
    "sg:classifiers":[
        {
            "category":"Education",
            "subcategory":"School",
            "type":"Public Place"
        }
    ],
    "sg:phone":"+1 417 654 2232",
    "sg:postcode":"65649",
    "sg:province":"MO",
    "wof:name":"Fair Play High School",
    "wof:placetype":"venue"
},
  "geometry": {"coordinates":[-93.57620199999999,37.634713],"type":"Point"}
}