{
  "type": "Feature",
  "properties": {
    "iso:country":"US",
    "sg:address":"11710 Saint Charles Rock Rd",
    "sg:city":"Bridgeton",
    "sg:classifiers":[
        {
            "category":"Building & Trades",
            "subcategory":"Equipment Rental",
            "type":"Services"
        }
    ],
    "sg:phone":"+1 314 291 7210",
    "sg:postcode":"63044",
    "sg:province":"MO",
    "sg:tags":[
        "personal"
    ],
    "wof:name":"Sun Rental Companies Inc",
    "wof:placetype":"venue"
},
  "geometry": {"coordinates":[-90.412865,38.74397],"type":"Point"}
}