{
  "type": "Feature",
  "properties": {
    "iso:country":"US",
    "sg:address":"62 Georgetown Cir",
    "sg:city":"O Fallon",
    "sg:classifiers":[
        {
            "category":"Professional",
            "subcategory":"Business Services",
            "type":"Services"
        }
    ],
    "sg:phone":"+1 636 244 0312",
    "sg:postcode":"63368",
    "sg:province":"MO",
    "wof:name":"Vedder & Assoc",
    "wof:placetype":"venue"
},
  "geometry": {"coordinates":[-90.696422,38.735306],"type":"Point"}
}