{
  "type": "Feature",
  "properties": {
    "iso:country":"US",
    "sg:address":"2018 W Donna Dr",
    "sg:city":"Excelsior Spgs",
    "sg:classifiers":[
        {
            "category":"Food & Beverages",
            "subcategory":"Specialty",
            "type":"Retail Goods"
        }
    ],
    "sg:phone":"+1 816 637 4372",
    "sg:postcode":"64024",
    "sg:province":"MO",
    "sg:tags":[
        "chemical",
        "herb",
        "industrial",
        "organic",
        "mfg"
    ],
    "wof:name":"Marlene's Herbs & More",
    "wof:placetype":"venue"
},
  "geometry": {"coordinates":[-94.19174,39.339682],"type":"Point"}
}