{
  "type": "Feature",
  "properties": {
    "iso:country":"US",
    "sg:address":"235 Spring Dr",
    "sg:city":"St Charles",
    "sg:classifiers":[
        {
            "category":"Retail",
            "subcategory":"Auto Repair",
            "type":"Services"
        }
    ],
    "sg:phone":"+1 636 946 1757",
    "sg:postcode":"63303",
    "sg:province":"MO",
    "sg:tags":[
        "body",
        "automobile",
        "painting"
    ],
    "wof:name":"House Auto Body",
    "wof:placetype":"venue"
},
  "geometry": {"coordinates":[-90.554906,38.784582],"type":"Point"}
}