{
  "type": "Feature",
  "properties": {
    "addr:full":"2545 W Kearney St Springfield MO 65803",
    "addr:housenumber":"2545",
    "addr:postcode":"65803",
    "addr:street":"W Kearney St",
    "iso:country":"US",
    "sg:address":"2545 W Kearney St",
    "sg:city":"Springfield",
    "sg:classifiers":[
        {
            "category":"Banks & Credit Unions",
            "subcategory":"Bank",
            "type":"Services"
        }
    ],
    "sg:phone":"+1 417 866 1828",
    "sg:postcode":"65803",
    "sg:province":"MO",
    "sg:tags":[
        "financing"
    ],
    "wof:name":"Beneficial Finance",
    "wof:placetype":"venue"
},
  "geometry": {"coordinates":[-93.32661400000001,37.241325],"type":"Point"}
}