{
  "type": "Feature",
  "properties": {
    "iso:country":"US",
    "sg:address":"7106 NW Prairie View Rd",
    "sg:city":"Kansas City",
    "sg:classifiers":[
        {
            "category":"Restaurant",
            "type":"Food & Drink"
        }
    ],
    "sg:menulink":"http://www.allmenus.com/mo/fox/183136-kfc---kentucky-fried-chicken/menu/",
    "sg:phone":"+1 816 741 2710",
    "sg:postcode":"64151",
    "sg:province":"MO",
    "sg:tags":[
        "american",
        "chicken"
    ],
    "wof:name":"KFC - Kentucky Fried Chicken",
    "wof:placetype":"venue"
},
  "geometry": {"coordinates":[-94.651048,39.223919],"type":"Point"}
}