{
  "type": "Feature",
  "properties": {
    "iso:country":"US",
    "sg:address":"215 SW County Road Bb",
    "sg:city":"Warrensburg",
    "sg:classifiers":[
        {
            "category":"Retail",
            "subcategory":"Laundry & Dry Cleaning",
            "type":"Services"
        },
        {
            "category":"Building & Trades",
            "subcategory":"Cleaning & Sanitation",
            "type":"Services"
        },
        {
            "category":"Building & Trades",
            "subcategory":"Construction",
            "type":"Services"
        }
    ],
    "sg:phone":"+1 660 429 6344",
    "sg:postcode":"64093",
    "sg:province":"MO",
    "sg:tags":[
        "cleaner",
        "upholstery",
        "fire",
        "rug",
        "damage",
        "water",
        "restoration",
        "contractor",
        "carpet"
    ],
    "wof:name":"Steamagic Carpet Care",
    "wof:placetype":"venue"
},
  "geometry": {"coordinates":[-93.791376,38.724639],"type":"Point"}
}