{
  "type": "Feature",
  "properties": {
    "iso:country":"US",
    "sg:address":"6257 US Hwy 54",
    "sg:city":"Osage Beach",
    "sg:classifiers":[
        {
            "category":"Professional",
            "subcategory":"Business Services",
            "type":"Services"
        }
    ],
    "sg:phone":"+1 573 348 4883",
    "sg:postcode":"65065",
    "sg:province":"MO",
    "sg:tags":[
        "interior",
        "consultant",
        "design",
        "decorator"
    ],
    "wof:name":"Interior Motifs",
    "wof:placetype":"venue"
},
  "geometry": {"coordinates":[-92.686182,38.101346],"type":"Point"}
}