{
  "type": "Feature",
  "properties": {
    "iso:country":"US",
    "sg:address":"212 Portland St",
    "sg:city":"Columbia",
    "sg:classifiers":[
        {
            "category":"Organizations",
            "subcategory":"Religious Organization",
            "type":"Services"
        }
    ],
    "sg:phone":"+1 573 499 9087",
    "sg:postcode":"65201",
    "sg:province":"MO",
    "sg:tags":[
        "church"
    ],
    "wof:name":"Victory Christian Church",
    "wof:placetype":"venue"
},
  "geometry": {"coordinates":[-92.28883500000001,38.953184],"type":"Point"}
}