{
  "type": "Feature",
  "properties": {
    "iso:country":"US",
    "sg:address":"2300 E Meyer Blvd",
    "sg:city":"Kansas City",
    "sg:classifiers":[
        {
            "category":"Health Services",
            "subcategory":"Hospital",
            "type":"Services"
        }
    ],
    "sg:phone":"+1 816 276 9111",
    "sg:postcode":"64132",
    "sg:province":"MO",
    "wof:name":"HCA Inc",
    "wof:placetype":"venue"
},
  "geometry": {"coordinates":[-94.560147,39.00723],"type":"Point"}
}