{
  "type": "Feature",
  "properties": {
    "iso:country":"US",
    "sg:address":"112 W 10th St",
    "sg:city":"Lamar",
    "sg:classifiers":[
        {
            "category":"Personal",
            "subcategory":"Shoe Repair & Shine",
            "type":"Services"
        }
    ],
    "sg:phone":"+1 417 682 5449",
    "sg:postcode":"64759",
    "sg:province":"MO",
    "sg:tags":[
        "repairing",
        "parlor",
        "boot",
        "shoes"
    ],
    "wof:name":"Castles Shoe Shop",
    "wof:placetype":"venue"
},
  "geometry": {"coordinates":[-94.27748,37.495819],"type":"Point"}
}