{
  "type": "Feature",
  "properties": {
    "iso:country":"US",
    "sg:address":"24223 Maple Rd",
    "sg:city":"Oronogo",
    "sg:classifiers":[
        {
            "category":"Manufacturing",
            "subcategory":"Buildings",
            "type":"Manufacturing & Wholesale Goods"
        },
        {
            "category":"Building & Trades",
            "subcategory":"Construction",
            "type":"Services"
        }
    ],
    "sg:phone":"+1 417 673 4489",
    "sg:postcode":"64855",
    "sg:province":"MO",
    "sg:tags":[
        "industrial",
        "system",
        "specialty",
        "builder",
        "heating",
        "contractor",
        "contractors-commercial",
        "home",
        "air conditioning"
    ],
    "wof:name":"Norm's General Contractors Inc",
    "wof:placetype":"venue"
},
  "geometry": {"coordinates":[-94.491387,37.243506],"type":"Point"}
}