{
  "type": "Feature",
  "properties": {
    "iso:country":"US",
    "sg:address":"110 Magnolia Ave",
    "sg:city":"Hannibal",
    "sg:classifiers":[
        {
            "category":"Health Services",
            "subcategory":"Doctor",
            "type":"Services"
        }
    ],
    "sg:phone":"+1 573 221 7876",
    "sg:postcode":"63401",
    "sg:province":"MO",
    "sg:tags":[
        "medical"
    ],
    "wof:name":"Glenn L Gordon",
    "wof:placetype":"venue"
},
  "geometry": {"coordinates":[-91.381534,39.70702],"type":"Point"}
}