{
  "type": "Feature",
  "properties": {
    "iso:country":"US",
    "sg:address":"333 Ozark Trail Dr",
    "sg:city":"Ballwin",
    "sg:classifiers":[
        {
            "category":"Insurance",
            "subcategory":"Insurance Agent",
            "type":"Services"
        }
    ],
    "sg:phone":"+1 636 391 4841",
    "sg:postcode":"63011",
    "sg:province":"MO",
    "sg:website":"www.rsimo.com",
    "wof:name":"RSI Intl Inc",
    "wof:placetype":"venue"
},
  "geometry": {"coordinates":[-90.58847299999999,38.602168],"type":"Point"}
}