{
  "type": "Feature",
  "properties": {
    "iso:country":"US",
    "sg:address":"912 Bus Loop 70 E",
    "sg:city":"Columbia",
    "sg:classifiers":[
        {
            "category":"Arts & Performance",
            "subcategory":"Theater",
            "type":"Entertainment"
        }
    ],
    "sg:phone":"+1 573 442 7491",
    "sg:postcode":"65201",
    "sg:province":"MO",
    "wof:name":"Club Vogue",
    "wof:placetype":"venue"
},
  "geometry": {"coordinates":[-92.324771,38.963905],"type":"Point"}
}