{
  "type": "Feature",
  "properties": {
    "iso:country":"US",
    "sg:address":"203 W Liberty St",
    "sg:city":"Farmington",
    "sg:classifiers":[
        {
            "category":"Communications",
            "subcategory":"Film & Video Production",
            "type":"Services"
        },
        {
            "category":"Retail",
            "subcategory":"Repair Shop",
            "type":"Services"
        },
        {
            "category":"Shopping",
            "subcategory":"Computers & Home Electronics",
            "type":"Retail Goods"
        }
    ],
    "sg:phone":"+1 573 756 6966",
    "sg:postcode":"63640",
    "sg:province":"MO",
    "sg:tags":[
        "television",
        "equipment-installation",
        "radio",
        "store",
        "radio-service"
    ],
    "wof:name":"Wade's TV",
    "wof:placetype":"venue"
},
  "geometry": {"coordinates":[-90.422754,37.781383],"type":"Point"}
}