{
  "type": "Feature",
  "properties": {
    "iso:country":"US",
    "sg:address":"408 Admiral Blvd",
    "sg:city":"Kansas City",
    "sg:classifiers":[
        {
            "category":"Real Estate",
            "subcategory":"Real Estate Agent",
            "type":"Services"
        }
    ],
    "sg:phone":"+1 816 842 2151",
    "sg:postcode":"64106",
    "sg:province":"MO",
    "sg:tags":[
        "management"
    ],
    "wof:name":"Admiral Properties",
    "wof:placetype":"venue"
},
  "geometry": {"coordinates":[-94.578036,39.105391],"type":"Point"}
}