{
  "type": "Feature",
  "properties": {
    "iso:country":"US",
    "sg:address":"205 S Main St",
    "sg:city":"Mt Vernon",
    "sg:classifiers":[
        {
            "category":"Personal",
            "subcategory":"Barber",
            "type":"Services"
        }
    ],
    "sg:phone":"+1 417 466 3303",
    "sg:postcode":"65712",
    "sg:province":"MO",
    "sg:tags":[
        "shop"
    ],
    "wof:name":"Gene's Barber Shop",
    "wof:placetype":"venue"
},
  "geometry": {"coordinates":[-93.81847500000001,37.103026],"type":"Point"}
}