{
  "type": "Feature",
  "properties": {
    "iso:country":"US",
    "sg:address":"100 N Tucker Blvd",
    "sg:city":"Saint Louis",
    "sg:classifiers":[
        {
            "category":"Taxi",
            "type":"Transportation"
        }
    ],
    "sg:phone":"+1 314 241 7600",
    "sg:postcode":"63101",
    "sg:province":"MO",
    "sg:tags":[
        "taxicab"
    ],
    "wof:name":"Metro Taxicab",
    "wof:placetype":"venue"
},
  "geometry": {"coordinates":[-90.19779,38.628966],"type":"Point"}
}