{
  "type": "Feature",
  "properties": {
    "iso:country":"US",
    "sg:address":"4417 N Chestnut Ave",
    "sg:city":"Kansas City",
    "sg:classifiers":[
        {
            "category":"Professional",
            "subcategory":"Business Services",
            "type":"Services"
        }
    ],
    "sg:phone":"+1 816 454 7659",
    "sg:postcode":"64117",
    "sg:province":"MO",
    "wof:name":"Ace Interiors",
    "wof:placetype":"venue"
},
  "geometry": {"coordinates":[-94.54589799999999,39.175805],"type":"Point"}
}