{
  "type": "Feature",
  "properties": {
    "iso:country":"US",
    "sg:address":"4020 Fee Fee Rd",
    "sg:city":"Bridgeton",
    "sg:classifiers":[
        {
            "category":"Banks & Credit Unions",
            "subcategory":"Bank",
            "type":"Services"
        }
    ],
    "sg:phone":"+1 314 264 5325",
    "sg:postcode":"63044",
    "sg:province":"MO",
    "sg:tags":[
        "federal"
    ],
    "wof:name":"Educational Employees Credit U",
    "wof:placetype":"venue"
},
  "geometry": {"coordinates":[-90.40235699999999,38.742074],"type":"Point"}
}