{
  "type": "Feature",
  "properties": {
    "iso:country":"US",
    "sg:address":"1401 N Kingshighway Blvd",
    "sg:city":"Saint Louis",
    "sg:classifiers":[
        {
            "category":"Professional",
            "subcategory":"Lawyer & Legal Services",
            "type":"Services"
        }
    ],
    "sg:phone":"+1 314 367 9529",
    "sg:postcode":"63113",
    "sg:province":"MO",
    "wof:name":"The Law Office",
    "wof:placetype":"venue"
},
  "geometry": {"coordinates":[-90.261973,38.661572],"type":"Point"}
}