{
  "type": "Feature",
  "properties": {
    "iso:country":"US",
    "sg:address":"31752 State Hwy U",
    "sg:city":"Sedalia",
    "sg:classifiers":[
        {
            "category":"Building & Trades",
            "subcategory":"Plumbing",
            "type":"Services"
        }
    ],
    "sg:phone":"+1 660 826 8899",
    "sg:postcode":"65301",
    "sg:province":"MO",
    "sg:tags":[
        "plumbing",
        "contractor"
    ],
    "wof:name":"Paul's Plumbing",
    "wof:placetype":"venue"
},
  "geometry": {"coordinates":[-93.216661,38.611537],"type":"Point"}
}