{
  "type": "Feature",
  "properties": {
    "iso:country":"US",
    "sg:address":"151 Blue Ridge Rd",
    "sg:city":"Kaiser",
    "sg:classifiers":[
        {
            "category":"Local Transit",
            "type":"Transportation"
        }
    ],
    "sg:phone":"+1 573 348 4433",
    "sg:postcode":"65047",
    "sg:province":"MO",
    "sg:tags":[
        "line"
    ],
    "wof:name":"Lake Community Transit",
    "wof:placetype":"venue"
},
  "geometry": {"coordinates":[-92.57155899999999,38.156568],"type":"Point"}
}