{
  "type": "Feature",
  "properties": {
    "iso:country":"US",
    "sg:address":"1409 Quiver Dr",
    "sg:city":"O Fallon",
    "sg:classifiers":[
        {
            "category":"Manufacturing",
            "subcategory":"Toys & Sporting Goods",
            "type":"Manufacturing & Wholesale Goods"
        }
    ],
    "sg:phone":"+1 636 399 0523",
    "sg:postcode":"63366",
    "sg:province":"MO",
    "sg:tags":[
        "equipment",
        "sport",
        "developer"
    ],
    "wof:name":"Nathan Place",
    "wof:placetype":"venue"
},
  "geometry": {"coordinates":[-90.74300599999999,38.78675],"type":"Point"}
}