{
  "type": "Feature",
  "properties": {
    "iso:country":"US",
    "sg:address":"410 S Hastings St",
    "sg:city":"La Plata",
    "sg:classifiers":[
        {
            "category":"Shopping",
            "subcategory":"Bicycles & Sporting Goods",
            "type":"Retail Goods"
        }
    ],
    "sg:phone":"+1 660 332 7630",
    "sg:postcode":"63549",
    "sg:province":"MO",
    "sg:tags":[
        "equipment",
        "golf",
        "supply"
    ],
    "wof:name":"LA Plata Golf",
    "wof:placetype":"venue"
},
  "geometry": {"coordinates":[-92.497939,40.020087],"type":"Point"}
}