{
  "type": "Feature",
  "properties": {
    "addr:full":"1800 State Hwy J Malden MO 63863",
    "addr:housenumber":"1800",
    "addr:postcode":"63863",
    "addr:street":"State Hwy J Malden",
    "iso:country":"US",
    "sg:address":"1800 State Hwy J",
    "sg:city":"Malden",
    "sg:classifiers":[
        {
            "category":"Organizations",
            "subcategory":"Religious Organization",
            "type":"Services"
        }
    ],
    "sg:phone":"+1 573 276 4129",
    "sg:postcode":"63863",
    "sg:province":"MO",
    "sg:tags":[
        "church"
    ],
    "wof:name":"First Church Of The Nazarene",
    "wof:placetype":"venue"
},
  "geometry": {"coordinates":[-89.986593,36.564286],"type":"Point"}
}