{
  "type": "Feature",
  "properties": {
    "iso:country":"US",
    "sg:address":"1112 N Woodridge Ln",
    "sg:city":"Liberty",
    "sg:classifiers":[
        {
            "category":"Retail",
            "subcategory":"Laundry & Dry Cleaning",
            "type":"Services"
        },
        {
            "category":"Building & Trades",
            "subcategory":"Cleaning & Sanitation",
            "type":"Services"
        }
    ],
    "sg:phone":"+1 816 415 4621",
    "sg:postcode":"64068",
    "sg:province":"MO",
    "sg:tags":[
        "cleaner",
        "house"
    ],
    "wof:name":"Andrews Cleaning Service",
    "wof:placetype":"venue"
},
  "geometry": {"coordinates":[-94.43152499999999,39.259208],"type":"Point"}
}