{
  "type": "Feature",
  "properties": {
    "iso:country":"US",
    "sg:address":"14821 Pheasant Hill Ct",
    "sg:city":"Chesterfield",
    "sg:classifiers":[
        {
            "category":"Professional",
            "type":"Services"
        }
    ],
    "sg:phone":"+1 636 532 9523",
    "sg:postcode":"63017",
    "sg:province":"MO",
    "wof:name":"Ldl",
    "wof:placetype":"venue"
},
  "geometry": {"coordinates":[-90.542469,38.636938],"type":"Point"}
}