{
  "type": "Feature",
  "properties": {
    "iso:country":"US",
    "sg:address":"9596 Krommer Rd",
    "sg:city":"Cedar Hill",
    "sg:classifiers":[
        {
            "category":"Manufacturing",
            "subcategory":"Tools & Machinery",
            "type":"Manufacturing & Wholesale Goods"
        }
    ],
    "sg:phone":"+1 636 274 2643",
    "sg:postcode":"63016",
    "sg:province":"MO",
    "sg:tags":[
        "mfg"
    ],
    "wof:name":"J & C Die Service Inc",
    "wof:placetype":"venue"
},
  "geometry": {"coordinates":[-90.70229399999999,38.351947],"type":"Point"}
}