{
  "type": "Feature",
  "properties": {
    "iso:country":"US",
    "sg:address":"11535 Hickman Mills Dr",
    "sg:city":"Kansas City",
    "sg:classifiers":[
        {
            "category":"Insurance",
            "subcategory":"Insurance Agent",
            "type":"Services"
        }
    ],
    "sg:phone":"+1 816 761 3230",
    "sg:postcode":"64134",
    "sg:province":"MO",
    "wof:name":"Tozier Parkway Housh Jones Ins",
    "wof:placetype":"venue"
},
  "geometry": {"coordinates":[-94.523894,38.911609],"type":"Point"}
}