{
  "type": "Feature",
  "properties": {
    "iso:country":"US",
    "sg:address":"5214 Pernod Ave",
    "sg:city":"Saint Louis",
    "sg:classifiers":[
        {
            "category":"Professional",
            "type":"Services"
        }
    ],
    "sg:phone":"+1 314 481 6186",
    "sg:postcode":"63139",
    "sg:province":"MO",
    "wof:name":"Amy Sprout",
    "wof:placetype":"venue"
},
  "geometry": {"coordinates":[-90.281308,38.595425],"type":"Point"}
}