{
  "type": "Feature",
  "properties": {
    "iso:country":"US",
    "sg:address":"2096 State Hwy 100",
    "sg:city":"Hermann",
    "sg:classifiers":[
        {
            "category":"Freight",
            "type":"Transportation"
        }
    ],
    "sg:phone":"+1 573 486 3322",
    "sg:postcode":"65041",
    "sg:province":"MO",
    "sg:tags":[
        "trucking"
    ],
    "wof:name":"Tri-County Trucking Inc",
    "wof:placetype":"venue"
},
  "geometry": {"coordinates":[-91.44794899999999,38.687832],"type":"Point"}
}