{
  "type": "Feature",
  "properties": {
    "iso:country":"US",
    "sg:address":"406 W 34 Ter",
    "sg:city":"Kansas City",
    "sg:classifiers":[
        {
            "category":"Wholesale",
            "subcategory":"Home Furnishings",
            "type":"Manufacturing & Wholesale Goods"
        }
    ],
    "sg:phone":"+1 816 531 2299",
    "sg:postcode":"64111",
    "sg:province":"MO",
    "wof:name":"Garry Marshall S",
    "wof:placetype":"venue"
},
  "geometry": {"coordinates":[-94.591402,39.065396],"type":"Point"}
}