{
  "type": "Feature",
  "properties": {
    "iso:country":"US",
    "sg:address":"68 4 Seasons Shopping Ctr",
    "sg:city":"Chesterfield",
    "sg:classifiers":[
        {
            "category":"Restaurant",
            "type":"Food & Drink"
        }
    ],
    "sg:menulink":"http://www.allmenus.com/mo/maryland-heights/54891-talaynas/menu/",
    "sg:phone":"+1 314 469 6650",
    "sg:postcode":"63017",
    "sg:province":"MO",
    "sg:tags":[
        "italian"
    ],
    "wof:name":"Talayna's",
    "wof:placetype":"venue"
},
  "geometry": {"coordinates":[-90.502214,38.678741],"type":"Point"}
}