{
  "type": "Feature",
  "properties": {
    "iso:country":"US",
    "sg:address":"11225 Liv 269",
    "sg:city":"Wheeling",
    "sg:classifiers":[
        {
            "category":"Manufacturing",
            "subcategory":"Food",
            "type":"Manufacturing & Wholesale Goods"
        }
    ],
    "sg:phone":"+1 660 659 2347",
    "sg:postcode":"64688",
    "sg:province":"MO",
    "sg:tags":[
        "product"
    ],
    "wof:name":"David Graham",
    "wof:placetype":"venue"
},
  "geometry": {"coordinates":[-93.40267799999999,39.819151],"type":"Point"}
}