{
  "type": "Feature",
  "properties": {
    "iso:country":"US",
    "sg:address":"851 W Grant St",
    "sg:city":"Dexter",
    "sg:classifiers":[
        {
            "category":"Health Services",
            "subcategory":"Doctor",
            "type":"Services"
        }
    ],
    "sg:phone":"+1 573 624 8005",
    "sg:postcode":"63841",
    "sg:province":"MO",
    "sg:tags":[
        "dentist"
    ],
    "wof:name":"Demaree Mitchell Family Dental",
    "wof:placetype":"venue"
},
  "geometry": {"coordinates":[-89.97014900000001,36.78896],"type":"Point"}
}