{
  "type": "Feature",
  "properties": {
    "iso:country":"US",
    "sg:address":"5300 W Florissant Ave",
    "sg:city":"St Louis",
    "sg:classifiers":[
        {
            "category":"Professional",
            "subcategory":"Accounting & Tax Preparation",
            "type":"Services"
        }
    ],
    "sg:phone":"+1 314 385 5586",
    "sg:postcode":"63120",
    "sg:province":"MO",
    "sg:tags":[
        "return",
        "filing"
    ],
    "wof:name":"Tax Savers Inc",
    "wof:placetype":"venue"
},
  "geometry": {"coordinates":[-90.23971899999999,38.695672],"type":"Point"}
}