{
  "type": "Feature",
  "properties": {
    "iso:country":"US",
    "sg:address":"844 Knox Ave",
    "sg:city":"Hollister",
    "sg:classifiers":[
        {
            "category":"Education",
            "subcategory":"Music School",
            "type":"Public Place"
        }
    ],
    "sg:phone":"+1 417 676 0443",
    "sg:postcode":"65672",
    "sg:province":"MO",
    "sg:tags":[
        "instruction-instrumental"
    ],
    "wof:name":"Brian Winger Guitar Co",
    "wof:placetype":"venue"
},
  "geometry": {"coordinates":[-93.211265,36.634218],"type":"Point"}
}