{
  "type": "Feature",
  "properties": {
    "iso:country":"US",
    "sg:address":"15685 S Hwy 39",
    "sg:city":"Stockton",
    "sg:classifiers":[
        {
            "category":"Retail",
            "subcategory":"Auto Repair",
            "type":"Services"
        }
    ],
    "sg:phone":"+1 417 276 5288",
    "sg:postcode":"65785",
    "sg:province":"MO",
    "sg:tags":[
        "repairing",
        "automobile"
    ],
    "wof:name":"Scott's Auto Parts & Garage",
    "wof:placetype":"venue"
},
  "geometry": {"coordinates":[-93.81408500000001,37.669036],"type":"Point"}
}