{
  "type": "Feature",
  "properties": {
    "iso:country":"US",
    "sg:address":"14582 State Hwy A",
    "sg:city":"Monticello",
    "sg:phone":"+1 573 767 5361",
    "sg:postcode":"63457",
    "sg:province":"MO",
    "sg:tags":[
        "farm",
        "corn",
        "soybean"
    ],
    "wof:name":"Glenn Krueger",
    "wof:placetype":"venue"
},
  "geometry": {"coordinates":[-91.746163,40.187467],"type":"Point"}
}