{
  "type": "Feature",
  "properties": {
    "iso:country":"US",
    "sg:address":"504 E Broadway",
    "sg:city":"Ashland",
    "sg:classifiers":[
        {
            "category":"Health Services",
            "subcategory":"Doctor",
            "type":"Services"
        }
    ],
    "sg:phone":"+1 573 657 9354",
    "sg:postcode":"65010",
    "sg:province":"MO",
    "sg:tags":[
        "medical"
    ],
    "wof:name":"Southern Boone Cnty Fmly Care",
    "wof:placetype":"venue"
},
  "geometry": {"coordinates":[-92.25626,38.77444],"type":"Point"}
}