{
  "type": "Feature",
  "properties": {
    "iso:country":"US",
    "sg:address":"906 Pheasant Hill",
    "sg:city":"Rolla",
    "sg:classifiers":[
        {
            "category":"Shopping",
            "subcategory":"Catalog Store",
            "type":"Retail Goods"
        }
    ],
    "sg:phone":"+1 573 341 5933",
    "sg:postcode":"65401",
    "sg:province":"MO",
    "sg:tags":[
        "mail",
        "order"
    ],
    "wof:name":"Seriously Shady",
    "wof:placetype":"venue"
},
  "geometry": {"coordinates":[-91.75688100000001,37.928396],"type":"Point"}
}