{
  "type": "Feature",
  "properties": {
    "iso:country":"US",
    "sg:address":"3790 Harvester Rd",
    "sg:city":"Saint Charles",
    "sg:classifiers":[
        {
            "category":"Wholesale",
            "subcategory":"Home Furnishings",
            "type":"Manufacturing & Wholesale Goods"
        }
    ],
    "sg:phone":"+1 636 928 8258",
    "sg:postcode":"63303",
    "sg:province":"MO",
    "sg:tags":[
        "floor",
        "covering"
    ],
    "wof:name":"Buchholz Interiors Inc",
    "wof:placetype":"venue"
},
  "geometry": {"coordinates":[-90.58100899999999,38.74489],"type":"Point"}
}