{
  "type": "Feature",
  "properties": {
    "iso:country":"US",
    "sg:address":"1020 3rd St",
    "sg:city":"Chillicothe",
    "sg:classifiers":[
        {
            "category":"Retail",
            "subcategory":"Repair Shop",
            "type":"Services"
        }
    ],
    "sg:phone":"+1 660 646 3183",
    "sg:postcode":"64601",
    "sg:province":"MO",
    "sg:tags":[
        "appliance"
    ],
    "wof:name":"Gary's Appliance Svc",
    "wof:placetype":"venue"
},
  "geometry": {"coordinates":[-93.556692,39.789568],"type":"Point"}
}