{
  "type": "Feature",
  "properties": {
    "iso:country":"US",
    "sg:address":"109 E Buffalo St",
    "sg:city":"Humansville",
    "sg:classifiers":[
        {
            "category":"Retail",
            "subcategory":"Funeral Services",
            "type":"Services"
        }
    ],
    "sg:phone":"+1 417 754 2215",
    "sg:postcode":"65674",
    "sg:province":"MO",
    "sg:tags":[
        "director",
        "contractor"
    ],
    "sg:website":"http://www.murrayfuneralhomes.com",
    "wof:name":"Murray Funeral Home",
    "wof:placetype":"venue"
},
  "geometry": {"coordinates":[-93.577023,37.795506],"type":"Point"}
}