{
  "type": "Feature",
  "properties": {
    "iso:country":"US",
    "sg:address":"1427 S 3rd St",
    "sg:city":"Saint Louis",
    "sg:classifiers":[
        {
            "category":"Retail",
            "subcategory":"Auto Rental",
            "type":"Services"
        }
    ],
    "sg:phone":"+1 314 231 3673",
    "sg:postcode":"63104",
    "sg:province":"MO",
    "sg:tags":[
        "car"
    ],
    "wof:name":"Broadway Truck & Van Rental",
    "wof:placetype":"venue"
},
  "geometry": {"coordinates":[-90.19499999999999,38.612202],"type":"Point"}
}