{
  "type": "Feature",
  "properties": {
    "iso:country":"US",
    "sg:address":"4100 Independence Ave",
    "sg:city":"Kansas City",
    "sg:classifiers":[
        {
            "category":"Bars & Pubs",
            "type":"Food & Drink"
        }
    ],
    "sg:phone":"+1 816 241 3316",
    "sg:postcode":"64124",
    "sg:province":"MO",
    "sg:tags":[
        "drinking"
    ],
    "wof:name":"Imperiales",
    "wof:placetype":"venue"
},
  "geometry": {"coordinates":[-94.533024,39.1057],"type":"Point"}
}