{
  "type": "Feature",
  "properties": {
    "iso:country":"US",
    "sg:address":"3616 S Big Bend Blvd",
    "sg:city":"Maplewood",
    "sg:classifiers":[
        {
            "category":"Wholesale",
            "subcategory":"Machinery & Supplies",
            "type":"Manufacturing & Wholesale Goods"
        },
        {
            "category":"Wholesale",
            "subcategory":"Groceries",
            "type":"Manufacturing & Wholesale Goods"
        }
    ],
    "sg:phone":"+1 314 644 6166",
    "sg:postcode":"63143",
    "sg:province":"MO",
    "sg:tags":[
        "equipment",
        "product",
        "bakery",
        "baker"
    ],
    "wof:name":"Bono Burns Distributing Inc",
    "wof:placetype":"venue"
},
  "geometry": {"coordinates":[-90.32571299999999,38.601653],"type":"Point"}
}