{
  "type": "Feature",
  "properties": {
    "addr:full":"505 East St Cassville MO 65625",
    "addr:housenumber":"505",
    "addr:postcode":"65625",
    "addr:street":"East St",
    "iso:country":"US",
    "sg:address":"505 East St",
    "sg:city":"Cassville",
    "sg:classifiers":[
        {
            "category":"Government",
            "subcategory":"Office",
            "type":"Public Place"
        }
    ],
    "sg:phone":"+1 417 847 6556",
    "sg:postcode":"65625",
    "sg:province":"MO",
    "sg:tags":[
        "sheriff"
    ],
    "wof:name":"Sheriffs Department",
    "wof:placetype":"venue"
},
  "geometry": {"coordinates":[-93.86844499999999,36.67697],"type":"Point"}
}