{
  "type": "Feature",
  "properties": {
    "iso:country":"US",
    "sg:address":"2323 S Highview Ave",
    "sg:city":"Joplin",
    "sg:classifiers":[
        {
            "category":"Building & Trades",
            "subcategory":"Plumbing",
            "type":"Services"
        }
    ],
    "sg:phone":"+1 417 623 2423",
    "sg:postcode":"64804",
    "sg:province":"MO",
    "sg:tags":[
        "plumbing",
        "contractor"
    ],
    "wof:name":"J E Patterson Inc",
    "wof:placetype":"venue"
},
  "geometry": {"coordinates":[-94.480206,37.065149],"type":"Point"}
}