{
  "type": "Feature",
  "properties": {
    "iso:country":"US",
    "sg:address":"135 N Meramec Ave",
    "sg:city":"St Louis",
    "sg:classifiers":[
        {
            "category":"Real Estate",
            "subcategory":"Architect",
            "type":"Services"
        }
    ],
    "sg:phone":"+1 314 725 8440",
    "sg:postcode":"63105",
    "sg:province":"MO",
    "wof:name":"Paradigm Architects",
    "wof:placetype":"venue"
},
  "geometry": {"coordinates":[-90.33945799999999,38.652097],"type":"Point"}
}