{
  "type": "Feature",
  "properties": {
    "iso:country":"US",
    "sg:address":"3000 E Heartland Dr",
    "sg:city":"Liberty",
    "sg:classifiers":[
        {
            "category":"Manufacturing",
            "subcategory":"Metals",
            "type":"Manufacturing & Wholesale Goods"
        }
    ],
    "sg:phone":"+1 816 781 5717",
    "sg:postcode":"64068",
    "sg:province":"MO",
    "sg:tags":[
        "fabricated",
        "structural"
    ],
    "wof:name":"Shaped Steel Inc",
    "wof:placetype":"venue"
},
  "geometry": {"coordinates":[-94.39802400000001,39.28528],"type":"Point"}
}