{
  "type": "Feature",
  "properties": {
    "iso:country":"US",
    "sg:address":"41 Forest Club Dr",
    "sg:city":"Chesterfield",
    "sg:classifiers":[
        {
            "category":"Shopping",
            "subcategory":"Clothing, Apparel, & Fashions",
            "type":"Retail Goods"
        }
    ],
    "sg:phone":"+1 636 230 0777",
    "sg:postcode":"63005",
    "sg:province":"MO",
    "sg:tags":[
        "lingerie"
    ],
    "wof:name":"Bella Notte",
    "wof:placetype":"venue"
},
  "geometry": {"coordinates":[-90.586308,38.620672],"type":"Point"}
}