{
  "type": "Feature",
  "properties": {
    "addr:full":"101 N Range Line Rd Joplin MO 64801",
    "addr:housenumber":"101",
    "addr:postcode":"64801",
    "addr:street":"N Range Line Rd",
    "iso:country":"US",
    "sg:address":"101 N Range Line Rd",
    "sg:city":"Joplin",
    "sg:classifiers":[
        {
            "category":"Shopping",
            "subcategory":"Shoes",
            "type":"Retail Goods"
        }
    ],
    "sg:phone":"+1 417 781 4370",
    "sg:postcode":"64801",
    "sg:province":"MO",
    "sg:tags":[
        "athletic"
    ],
    "wof:name":"Lady Foot Locker",
    "wof:placetype":"venue"
},
  "geometry": {"coordinates":[-94.47687500000001,37.093661],"type":"Point"}
}