{
  "type": "Feature",
  "properties": {
    "iso:country":"US",
    "sg:address":"4 Randy Ct",
    "sg:city":"Saint Peters",
    "sg:classifiers":[
        {
            "category":"Building & Trades",
            "subcategory":"Landscaping Services",
            "type":"Services"
        }
    ],
    "sg:phone":"+1 636 397 5477",
    "sg:postcode":"63376",
    "sg:province":"MO",
    "sg:tags":[
        "lawn",
        "care"
    ],
    "wof:name":"Maurer Lawn Care",
    "wof:placetype":"venue"
},
  "geometry": {"coordinates":[-90.65626,38.780107],"type":"Point"}
}