{
  "type": "Feature",
  "properties": {
    "iso:country":"US",
    "sg:address":"119 W Parker St",
    "sg:city":"Slater",
    "sg:classifiers":[
        {
            "category":"Place Of Worship",
            "type":"Public Place"
        }
    ],
    "sg:phone":"+1 660 529 2868",
    "sg:postcode":"65349",
    "sg:province":"MO",
    "sg:tags":[
        "church"
    ],
    "wof:name":"Salem Evangelical Church",
    "wof:placetype":"venue"
},
  "geometry": {"coordinates":[-93.062395,39.222482],"type":"Point"}
}