{
  "type": "Feature",
  "properties": {
    "iso:country":"US",
    "sg:address":"5749 Era Ave",
    "sg:city":"Saint Louis",
    "sg:classifiers":[
        {
            "category":"Professional",
            "type":"Services"
        }
    ],
    "sg:phone":"+1 314 383 1007",
    "sg:postcode":"63136",
    "sg:province":"MO",
    "wof:name":"Traci Inc",
    "wof:placetype":"venue"
},
  "geometry": {"coordinates":[-90.25466400000001,38.710214],"type":"Point"}
}