{
  "type": "Feature",
  "properties": {
    "iso:country":"US",
    "sg:address":"10641 Old Saint Louis Rd",
    "sg:city":"De Soto",
    "sg:classifiers":[
        {
            "category":"Farming",
            "subcategory":"Livestock Farm",
            "type":"Manufacturing & Wholesale Goods"
        }
    ],
    "sg:phone":"+1 636 937 4820",
    "sg:postcode":"63020",
    "sg:province":"MO",
    "wof:name":"Gj Our Ranchs",
    "wof:placetype":"venue"
},
  "geometry": {"coordinates":[-90.41713,38.041719],"type":"Point"}
}