{
  "type": "Feature",
  "properties": {
    "iso:country":"US",
    "sg:address":"6450 Raytown Trfy",
    "sg:city":"Raytown",
    "sg:classifiers":[
        {
            "category":"Personal",
            "subcategory":"Beauty Salon",
            "type":"Services"
        }
    ],
    "sg:phone":"+1 816 358 8232",
    "sg:postcode":"64133",
    "sg:province":"MO",
    "wof:name":"Tadaah Salon",
    "wof:placetype":"venue"
},
  "geometry": {"coordinates":[-94.464108,39.005914],"type":"Point"}
}