{
  "type": "Feature",
  "properties": {
    "iso:country":"US",
    "sg:address":"542 Branson Landing Blvd",
    "sg:city":"Branson",
    "sg:classifiers":[
        {
            "category":"Retail",
            "subcategory":"Funeral Services",
            "type":"Services"
        }
    ],
    "sg:phone":"+1 417 335 3670",
    "sg:postcode":"65616",
    "sg:province":"MO",
    "sg:tags":[
        "director",
        "embalmer"
    ],
    "wof:name":"Snapp- Bearden Funeral Professionals",
    "wof:placetype":"venue"
},
  "geometry": {"coordinates":[-93.21392299999999,36.640984],"type":"Point"}
}