{
  "type": "Feature",
  "properties": {
    "iso:country":"US",
    "sg:address":"305 E Miller St",
    "sg:city":"Jefferson City",
    "sg:classifiers":[
        {
            "category":"Government",
            "subcategory":"Fire Station",
            "type":"Public Place"
        }
    ],
    "sg:phone":"+1 573 634 6401",
    "sg:postcode":"65101",
    "sg:province":"MO",
    "sg:tags":[
        "department"
    ],
    "sg:website":"www.jeffcitymo.org",
    "wof:name":"Jefferson City Fire Dept",
    "wof:placetype":"venue"
},
  "geometry": {"coordinates":[-92.17210900000001,38.57313],"type":"Point"}
}