{
  "type": "Feature",
  "properties": {
    "iso:country":"US",
    "sg:address":"6435 College Ave",
    "sg:city":"Kansas City",
    "sg:classifiers":[
        {
            "category":"Professional",
            "type":"Services"
        }
    ],
    "sg:phone":"+1 816 363 4050",
    "sg:postcode":"64132",
    "sg:province":"MO",
    "sg:tags":[
        "establishment"
    ],
    "wof:name":"Banana Split Kids",
    "wof:placetype":"venue"
},
  "geometry": {"coordinates":[-94.548141,39.008704],"type":"Point"}
}