{
  "type": "Feature",
  "properties": {
    "iso:country":"US",
    "sg:address":"4901 E 215th St",
    "sg:city":"Belton",
    "sg:classifiers":[
        {
            "category":"Shopping",
            "subcategory":"Catalog Store",
            "type":"Retail Goods"
        }
    ],
    "sg:phone":"+1 816 618 3499",
    "sg:postcode":"64012",
    "sg:province":"MO",
    "sg:tags":[
        "house",
        "jewelry",
        "mail"
    ],
    "sg:website":"www.discovermagnetics.com",
    "wof:name":"Discover Magnetics",
    "wof:placetype":"venue"
},
  "geometry": {"coordinates":[-94.54358000000001,38.735193],"type":"Point"}
}