{
  "type": "Feature",
  "properties": {
    "addr:full":"113 S Monroe St Versailles MO 65084",
    "addr:housenumber":"113",
    "addr:postcode":"65084",
    "addr:street":"S Monroe St",
    "iso:country":"US",
    "sg:address":"113 S Monroe St",
    "sg:city":"Versailles",
    "sg:classifiers":[
        {
            "category":"Sports & Exercise",
            "subcategory":"Gym",
            "type":"Entertainment"
        }
    ],
    "sg:phone":"+1 573 378 7497",
    "sg:postcode":"65084",
    "sg:province":"MO",
    "sg:tags":[
        "club",
        "health",
        "studio",
        "gymnasium"
    ],
    "wof:name":"Curves For Women",
    "wof:placetype":"venue"
},
  "geometry": {"coordinates":[-92.841905,38.431545],"type":"Point"}
}