{
  "type": "Feature",
  "properties": {
    "iso:country":"US",
    "sg:address":"164 Co Rd 213",
    "sg:city":"Chaffee",
    "sg:classifiers":[
        {
            "category":"Communications",
            "subcategory":"Film & Video Production",
            "type":"Services"
        }
    ],
    "sg:phone":"+1 573 545 4425",
    "sg:postcode":"63740",
    "sg:province":"MO",
    "sg:tags":[
        "taping"
    ],
    "wof:name":"Gary Reischman Video Prdctns",
    "wof:placetype":"venue"
},
  "geometry": {"coordinates":[-89.582769,37.150255],"type":"Point"}
}