{
  "type": "Feature",
  "properties": {
    "iso:country":"US",
    "sg:address":"7529 Forsyth Blvd",
    "sg:city":"St Louis",
    "sg:classifiers":[
        {
            "category":"Personal",
            "subcategory":"Beauty Salon",
            "type":"Services"
        }
    ],
    "sg:phone":"+1 314 863 5583",
    "sg:postcode":"63105",
    "sg:province":"MO",
    "sg:tags":[
        "shop"
    ],
    "wof:name":"S Styles",
    "wof:placetype":"venue"
},
  "geometry": {"coordinates":[-90.332651,38.649855],"type":"Point"}
}