{
  "type": "Feature",
  "properties": {
    "iso:country":"US",
    "sg:address":"1404 Hebert St",
    "sg:city":"St Louis",
    "sg:classifiers":[
        {
            "category":"Professional",
            "subcategory":"Employment Agencies",
            "type":"Services"
        }
    ],
    "sg:phone":"+1 314 621 5635",
    "sg:postcode":"63107",
    "sg:province":"MO",
    "sg:tags":[
        "opportunity"
    ],
    "wof:name":"Helping Hand Ready Labor",
    "wof:placetype":"venue"
},
  "geometry": {"coordinates":[-90.19859,38.654098],"type":"Point"}
}