{
  "type": "Feature",
  "properties": {
    "iso:country":"US",
    "sg:address":"9537 Lackland Rd",
    "sg:city":"Overland",
    "sg:classifiers":[
        {
            "category":"Health Services",
            "subcategory":"Health Practitioner",
            "type":"Services"
        }
    ],
    "sg:phone":"+1 314 427 8508",
    "sg:postcode":"63114",
    "sg:province":"MO",
    "sg:tags":[
        "psychologist"
    ],
    "wof:name":"Mental Health Consultants",
    "wof:placetype":"venue"
},
  "geometry": {"coordinates":[-90.368167,38.700808],"type":"Point"}
}