{
  "type": "Feature",
  "properties": {
    "iso:country":"US",
    "sg:address":"1000 Graves St",
    "sg:city":"Chillicothe",
    "sg:classifiers":[
        {
            "category":"Professional",
            "subcategory":"Accounting & Tax Preparation",
            "type":"Services"
        }
    ],
    "sg:phone":"+1 660 707 1067",
    "sg:postcode":"64601",
    "sg:province":"MO",
    "sg:tags":[
        "return",
        "filing"
    ],
    "wof:name":"H & R Block Tax Svc",
    "wof:placetype":"venue"
},
  "geometry": {"coordinates":[-93.554045,39.777542],"type":"Point"}
}