{
  "type": "Feature",
  "properties": {
    "iso:country":"US",
    "sg:address":"1751 Robertson Rd",
    "sg:city":"Moberly",
    "sg:classifiers":[
        {
            "category":"Manufacturing",
            "subcategory":"Paper Products",
            "type":"Manufacturing & Wholesale Goods"
        }
    ],
    "sg:phone":"+1 660 263 1455",
    "sg:postcode":"65270",
    "sg:province":"MO",
    "sg:tags":[
        "cards",
        "die",
        "greeting",
        "mfg"
    ],
    "wof:name":"Carrollton Specialty Pdts Co",
    "wof:placetype":"venue"
},
  "geometry": {"coordinates":[-92.442403,39.439553],"type":"Point"}
}