{
  "type": "Feature",
  "properties": {
    "iso:country":"US",
    "sg:address":"7301 Mission Rd",
    "sg:city":"Shawnee Mission",
    "sg:classifiers":[
        {
            "category":"Retail",
            "subcategory":"Auto Repair",
            "type":"Services"
        }
    ],
    "sg:phone":"+1 913 236 8060",
    "sg:postcode":"66208",
    "sg:province":"MO",
    "sg:tags":[
        "automotive"
    ],
    "wof:name":"Ralph Myers Equipment",
    "wof:placetype":"venue"
},
  "geometry": {"coordinates":[-94.630408,38.996572],"type":"Point"}
}