{
  "type": "Feature",
  "properties": {
    "iso:country":"US",
    "sg:address":"102 Royal Oaks Dr",
    "sg:city":"O Fallon",
    "sg:classifiers":[
        {
            "category":"Banks & Credit Unions",
            "subcategory":"Bank",
            "type":"Services"
        }
    ],
    "sg:phone":"+1 636 978 9777",
    "sg:postcode":"63366",
    "sg:province":"MO",
    "sg:tags":[
        "loan",
        "real estate"
    ],
    "wof:name":"River City Mortgage",
    "wof:placetype":"venue"
},
  "geometry": {"coordinates":[-90.731251,38.837199],"type":"Point"}
}