{
  "type": "Feature",
  "properties": {
    "iso:country":"US",
    "sg:address":"605 Old Ballas Rd",
    "sg:city":"Saint Louis",
    "sg:classifiers":[
        {
            "category":"Social Services",
            "type":"Services"
        }
    ],
    "sg:phone":"+1 314 991 8014",
    "sg:postcode":"63141",
    "sg:province":"MO",
    "wof:name":"Constance C Jones",
    "wof:placetype":"venue"
},
  "geometry": {"coordinates":[-90.43863,38.668237],"type":"Point"}
}