{
  "type": "Feature",
  "properties": {
    "iso:country":"US",
    "sg:address":"1100 12th St E",
    "sg:city":"Lamar",
    "sg:classifiers":[
        {
            "category":"Wholesale",
            "subcategory":"Sporting Goods",
            "type":"Manufacturing & Wholesale Goods"
        }
    ],
    "sg:phone":"+1 417 682 3556",
    "sg:postcode":"64759",
    "sg:province":"MO",
    "wof:name":"James C Rogers Jr",
    "wof:placetype":"venue"
},
  "geometry": {"coordinates":[-94.263651,37.492703],"type":"Point"}
}