{
  "type": "Feature",
  "properties": {
    "iso:country":"US",
    "sg:address":"327 E 13th Ave",
    "sg:city":"Kansas City",
    "sg:classifiers":[
        {
            "category":"Building & Trades",
            "subcategory":"Electrical",
            "type":"Services"
        }
    ],
    "sg:phone":"+1 816 842 3222",
    "sg:postcode":"64116",
    "sg:province":"MO",
    "sg:tags":[
        "electric",
        "contractor"
    ],
    "wof:name":"Independent Electrical Contrs",
    "wof:placetype":"venue"
},
  "geometry": {"coordinates":[-94.57642300000001,39.132255],"type":"Point"}
}