{
  "type": "Feature",
  "properties": {
    "iso:country":"US",
    "sg:address":"753 Westgate Ave",
    "sg:city":"Saint Louis",
    "sg:classifiers":[
        {
            "category":"Communications",
            "type":"Services"
        }
    ],
    "sg:phone":"+1 314 863 9270",
    "sg:postcode":"63130",
    "sg:province":"MO",
    "sg:tags":[
        "communication"
    ],
    "wof:name":"Kwanza Store",
    "wof:placetype":"venue"
},
  "geometry": {"coordinates":[-90.304502,38.657558],"type":"Point"}
}