{
  "type": "Feature",
  "properties": {
    "iso:country":"US",
    "sg:address":"10328 Blue Ridge Blvd",
    "sg:city":"Kansas City",
    "sg:classifiers":[
        {
            "category":"Restaurant",
            "type":"Food & Drink"
        }
    ],
    "sg:phone":"+1 816 763 8787",
    "sg:postcode":"64134",
    "sg:province":"MO",
    "sg:tags":[
        "eating"
    ],
    "wof:name":"Smoke ME Baby Bar B Que",
    "wof:placetype":"venue"
},
  "geometry": {"coordinates":[-94.508691,38.938422],"type":"Point"}
}