{
  "type": "Feature",
  "properties": {
    "iso:country":"US",
    "sg:address":"316 S Washington St",
    "sg:city":"Walnut Grove",
    "sg:classifiers":[
        {
            "category":"Wholesale",
            "subcategory":"Farm Supplies",
            "type":"Manufacturing & Wholesale Goods"
        }
    ],
    "sg:phone":"+1 417 788 3333",
    "sg:postcode":"65770",
    "sg:province":"MO",
    "sg:tags":[
        "feed"
    ],
    "wof:name":"Max's Feed",
    "wof:placetype":"venue"
},
  "geometry": {"coordinates":[-93.54972100000001,37.408951],"type":"Point"}
}