{
  "type": "Feature",
  "properties": {
    "iso:country":"US",
    "sg:address":"6053 Hampton Ave",
    "sg:city":"St Louis",
    "sg:classifiers":[
        {
            "category":"Insurance",
            "subcategory":"Insurance Agent",
            "type":"Services"
        }
    ],
    "sg:phone":"+1 314 678 0108",
    "sg:postcode":"63109",
    "sg:province":"MO",
    "wof:name":"Rob Ellis",
    "wof:placetype":"venue"
},
  "geometry": {"coordinates":[-90.29474999999999,38.574564],"type":"Point"}
}