{
  "type": "Feature",
  "properties": {
    "iso:country":"US",
    "sg:address":"455 N Elliston Rd",
    "sg:city":"Cuba",
    "sg:classifiers":[
        {
            "category":"Farming",
            "subcategory":"Farm",
            "type":"Manufacturing & Wholesale Goods"
        }
    ],
    "sg:phone":"+1 573 885 3696",
    "sg:postcode":"65453",
    "sg:province":"MO",
    "wof:name":"Holtz Farm",
    "wof:placetype":"venue"
},
  "geometry": {"coordinates":[-91.371999,38.122524],"type":"Point"}
}