{
  "type": "Feature",
  "properties": {
    "iso:country":"US",
    "sg:address":"851 Middleton Rd",
    "sg:city":"Taneyville",
    "sg:classifiers":[
        {
            "category":"Manufacturing",
            "subcategory":"Buildings",
            "type":"Manufacturing & Wholesale Goods"
        },
        {
            "category":"Building & Trades",
            "subcategory":"Construction",
            "type":"Services"
        }
    ],
    "sg:phone":"+1 417 796 2276",
    "sg:postcode":"65759",
    "sg:province":"MO",
    "sg:tags":[
        "home",
        "builder",
        "industrial",
        "contractors-commercial",
        "contractor"
    ],
    "wof:name":"Travis Snelling Construction, Inc",
    "wof:placetype":"venue"
},
  "geometry": {"coordinates":[-93.017119,36.797263],"type":"Point"}
}