{
  "type": "Feature",
  "properties": {
    "iso:country":"US",
    "sg:address":"104 E 7th St",
    "sg:city":"Rolla",
    "sg:classifiers":[
        {
            "category":"Organizations",
            "subcategory":"Non-profit Organization",
            "type":"Services"
        }
    ],
    "sg:phone":"+1 573 368 4755",
    "sg:postcode":"65401",
    "sg:province":"MO",
    "sg:tags":[
        "information",
        "alcoholism",
        "treatment"
    ],
    "wof:name":"Prevention Consultants Of Mo",
    "wof:placetype":"venue"
},
  "geometry": {"coordinates":[-91.769631,37.949086],"type":"Point"}
}