{
  "type": "Feature",
  "properties": {
    "iso:country":"US",
    "sg:address":"3445 Woodland Ave",
    "sg:city":"Kansas City",
    "sg:classifiers":[
        {
            "category":"Food & Beverages",
            "subcategory":"Groceries & Convenience Stores",
            "type":"Retail Goods"
        }
    ],
    "sg:phone":"+1 816 924 3321",
    "sg:postcode":"64109",
    "sg:province":"MO",
    "wof:name":"Midtown Grocers & Liquors",
    "wof:placetype":"venue"
},
  "geometry": {"coordinates":[-94.56235100000001,39.063747],"type":"Point"}
}