{
  "type": "Feature",
  "properties": {
    "iso:country":"US",
    "sg:address":"3631 Gravois Ave",
    "sg:city":"St. Louis",
    "sg:classifiers":[
        {
            "category":"Retail",
            "subcategory":"Portrait Studio",
            "type":"Services"
        },
        {
            "category":"Shopping",
            "subcategory":"Pharmacy",
            "type":"Retail Goods"
        }
    ],
    "sg:phone":"+1 314 772 4446",
    "sg:postcode":"63116",
    "sg:province":"MO",
    "sg:tags":[
        "photography",
        "drugstore",
        "store"
    ],
    "sg:website":"www.walgreens.com",
    "wof:name":"Walgreens",
    "wof:placetype":"venue"
},
  "geometry": {"coordinates":[-90.24550600000001,38.592087],"type":"Point"}
}