{
  "type": "Feature",
  "properties": {
    "iso:country":"US",
    "sg:address":"16004 Gracey Creek Rd",
    "sg:city":"Barnett",
    "sg:classifiers":[
        {
            "category":"Recreation",
            "subcategory":"Picnic Area",
            "type":"Entertainment"
        }
    ],
    "sg:phone":"+1 573 378 5930",
    "sg:postcode":"65011",
    "sg:province":"MO",
    "sg:tags":[
        "farm",
        "repair",
        "equipment-parts"
    ],
    "wof:name":"C S Sales & Service",
    "wof:placetype":"venue"
},
  "geometry": {"coordinates":[-92.702536,38.440453],"type":"Point"}
}