{
  "type": "Feature",
  "properties": {
    "iso:country":"US",
    "sg:address":"925 Highway 181",
    "sg:city":"Cabool",
    "sg:classifiers":[
        {
            "category":"Farming",
            "subcategory":"Livestock Farm",
            "type":"Manufacturing & Wholesale Goods"
        }
    ],
    "sg:phone":"+1 417 962 4107",
    "sg:postcode":"65689",
    "sg:province":"MO",
    "sg:tags":[
        "ranch"
    ],
    "wof:name":"Everett & Dixie Beller",
    "wof:placetype":"venue"
},
  "geometry": {"coordinates":[-92.105988,37.086552],"type":"Point"}
}