{
  "type": "Feature",
  "properties": {
    "iso:country":"US",
    "sg:address":"904 S Main St",
    "sg:city":"Joplin",
    "sg:classifiers":[
        {
            "category":"Professional",
            "type":"Services"
        }
    ],
    "sg:phone":"+1 417 206 3531",
    "sg:postcode":"64801",
    "sg:province":"MO",
    "sg:tags":[
        "establishment"
    ],
    "wof:name":"Pub Bar",
    "wof:placetype":"venue"
},
  "geometry": {"coordinates":[-94.51373,37.080443],"type":"Point"}
}