{
  "type": "Feature",
  "properties": {
    "iso:country":"US",
    "sg:address":"710 N 5th St",
    "sg:city":"Elsberry",
    "sg:classifiers":[
        {
            "category":"Personal",
            "subcategory":"Beauty Salon",
            "type":"Services"
        },
        {
            "category":"Personal",
            "subcategory":"Tanning Parlor",
            "type":"Services"
        }
    ],
    "sg:phone":"+1 573 898 2223",
    "sg:postcode":"63343",
    "sg:province":"MO",
    "wof:name":"The Hair Movement",
    "wof:placetype":"venue"
},
  "geometry": {"coordinates":[-90.788527,39.17051],"type":"Point"}
}