{
  "type": "Feature",
  "properties": {
    "iso:country":"US",
    "sg:address":"1013 E Morningside St",
    "sg:city":"Springfield",
    "sg:classifiers":[
        {
            "category":"Food & Beverages",
            "subcategory":"Bakery",
            "type":"Retail Goods"
        }
    ],
    "sg:phone":"+1 417 882 6938",
    "sg:postcode":"65807",
    "sg:province":"MO",
    "wof:name":"H&C Sweet Treats Inc",
    "wof:placetype":"venue"
},
  "geometry": {"coordinates":[-93.278491,37.166615],"type":"Point"}
}