{
  "type": "Feature",
  "properties": {
    "iso:country":"US",
    "sg:address":"323 State Hwy Hh",
    "sg:city":"Piedmont",
    "sg:classifiers":[
        {
            "category":"Shopping",
            "subcategory":"Computers & Home Electronics",
            "type":"Retail Goods"
        }
    ],
    "sg:phone":"+1 573 223 7406",
    "sg:postcode":"63957",
    "sg:province":"MO",
    "sg:tags":[
        "equipment",
        "electronic",
        "supply"
    ],
    "wof:name":"Radio Shack",
    "wof:placetype":"venue"
},
  "geometry": {"coordinates":[-90.70225600000001,37.138981],"type":"Point"}
}