{
  "type": "Feature",
  "properties": {
    "iso:country":"US",
    "sg:address":"2525 Glenn Hendren Dr",
    "sg:city":"Liberty",
    "sg:classifiers":[
        {
            "category":"Banks & Credit Unions",
            "subcategory":"Bank",
            "type":"Services"
        }
    ],
    "sg:phone":"+1 816 234 7434",
    "sg:postcode":"64068",
    "sg:province":"MO",
    "sg:website":"http://www.commercebank.com",
    "wof:name":"Commerce Bank, National Association, Inc.",
    "wof:placetype":"venue"
},
  "geometry": {"coordinates":[-94.424684,39.27656],"type":"Point"}
}