{
  "type": "Feature",
  "properties": {
    "iso:country":"US",
    "sg:address":"6154 Limbwood Ct",
    "sg:city":"Florissant",
    "sg:classifiers":[
        {
            "category":"Professional",
            "type":"Services"
        }
    ],
    "sg:phone":"+1 314 355 0623",
    "sg:postcode":"63033",
    "sg:province":"MO",
    "wof:name":"Danielle S First",
    "wof:placetype":"venue"
},
  "geometry": {"coordinates":[-90.24804399999999,38.806425],"type":"Point"}
}