{
  "type": "Feature",
  "properties": {
    "iso:country":"US",
    "sg:address":"216 Leslie Ln",
    "sg:city":"Ballwin",
    "sg:classifiers":[
        {
            "category":"Professional",
            "subcategory":"Computer Services",
            "type":"Services"
        }
    ],
    "sg:phone":"+1 314 323 3895",
    "sg:postcode":"63021",
    "sg:province":"MO",
    "wof:name":"Ultimate Setup",
    "wof:placetype":"venue"
},
  "geometry": {"coordinates":[-90.548602,38.586037],"type":"Point"}
}