{
  "type": "Feature",
  "properties": {
    "iso:country":"US",
    "sg:address":"36 W Vine St",
    "sg:city":"Sullivan",
    "sg:classifiers":[
        {
            "category":"Organizations",
            "subcategory":"Community Association",
            "type":"Services"
        }
    ],
    "sg:phone":"+1 573 468 6723",
    "sg:postcode":"63080",
    "sg:province":"MO",
    "wof:name":"Hall Masonic",
    "wof:placetype":"venue"
},
  "geometry": {"coordinates":[-91.158283,38.209268],"type":"Point"}
}