{
  "type": "Feature",
  "properties": {
    "iso:country":"US",
    "sg:address":"314 N 6th St",
    "sg:city":"Walker",
    "sg:classifiers":[
        {
            "category":"Building & Trades",
            "subcategory":"Construction",
            "type":"Services"
        }
    ],
    "sg:phone":"+1 417 465 2526",
    "sg:postcode":"64790",
    "sg:province":"MO",
    "sg:tags":[
        "excavation",
        "contractor"
    ],
    "wof:name":"Gundys Construction",
    "wof:placetype":"venue"
},
  "geometry": {"coordinates":[-94.232061,37.900909],"type":"Point"}
}