{
  "type": "Feature",
  "properties": {
    "iso:country":"US",
    "sg:address":"1920 N Bluff St",
    "sg:city":"Fulton",
    "sg:classifiers":[
        {
            "category":"Museum",
            "type":"Entertainment"
        }
    ],
    "sg:phone":"+1 573 642 2080",
    "sg:postcode":"65251",
    "sg:province":"MO",
    "wof:name":"Auto World Car Museum By Backe",
    "wof:placetype":"venue"
},
  "geometry": {"coordinates":[-91.943714,38.869239],"type":"Point"}
}