{
  "type": "Feature",
  "properties": {
    "iso:country":"US",
    "sg:address":"107 SE 10 St",
    "sg:city":"Oak Grove",
    "sg:classifiers":[
        {
            "category":"Manufacturing",
            "subcategory":"Tools & Machinery",
            "type":"Manufacturing & Wholesale Goods"
        }
    ],
    "sg:phone":"+1 816 690 8870",
    "sg:postcode":"64075",
    "sg:province":"MO",
    "sg:tags":[
        "machine",
        "shop"
    ],
    "wof:name":"Whiting Custom Enterprises",
    "wof:placetype":"venue"
},
  "geometry": {"coordinates":[-94.127894,39.006412],"type":"Point"}
}