{
  "type": "Feature",
  "properties": {
    "iso:country":"US",
    "sg:address":"11875 Brookington Dr",
    "sg:city":"Bridgeton",
    "sg:classifiers":[
        {
            "category":"Banks & Credit Unions",
            "subcategory":"Investment Brokerage",
            "type":"Services"
        }
    ],
    "sg:phone":"+1 314 344 9902",
    "sg:postcode":"63044",
    "sg:province":"MO",
    "sg:tags":[
        "advisory"
    ],
    "wof:name":"John E Harper Investor",
    "wof:placetype":"venue"
},
  "geometry": {"coordinates":[-90.42662,38.743248],"type":"Point"}
}