{
  "type": "Feature",
  "properties": {
    "iso:country":"US",
    "sg:address":"4641 E Bittersweet Way",
    "sg:city":"Springfield",
    "sg:classifiers":[
        {
            "category":"Professional",
            "type":"Services"
        }
    ],
    "sg:phone":"+1 417 887 2598",
    "sg:postcode":"65809",
    "sg:province":"MO",
    "wof:name":"Briant Cap",
    "wof:placetype":"venue"
},
  "geometry": {"coordinates":[-93.19704400000001,37.185459],"type":"Point"}
}