{
  "type": "Feature",
  "properties": {
    "addr:full":"6564 Red Bud Fulton MO 65251",
    "addr:housenumber":"6564;bud",
    "addr:postcode":"65251",
    "addr:street":"Red",
    "iso:country":"US",
    "sg:address":"6564 Red Bud",
    "sg:city":"Fulton",
    "sg:classifiers":[
        {
            "category":"Insurance",
            "subcategory":"Hazard Insurance",
            "type":"Services"
        }
    ],
    "sg:phone":"+1 573 642 1197",
    "sg:postcode":"65251",
    "sg:province":"MO",
    "wof:name":"James G Kern",
    "wof:placetype":"venue"
},
  "geometry": {"coordinates":[-91.829269,38.828493],"type":"Point"}
}