{
  "type": "Feature",
  "properties": {
    "iso:country":"US",
    "sg:address":"206 Veterans Blvd",
    "sg:city":"Branson",
    "sg:classifiers":[
        {
            "category":"Autos & Motor Vehicles",
            "subcategory":"Auto Supplies",
            "type":"Retail Goods"
        },
        {
            "category":"Retail",
            "subcategory":"Auto Repair",
            "type":"Services"
        }
    ],
    "sg:phone":"+1 417 334 0501",
    "sg:postcode":"65616",
    "sg:province":"MO",
    "sg:tags":[
        "recap",
        "retread",
        "tire"
    ],
    "wof:name":"Branson Tire & Auto",
    "wof:placetype":"venue"
},
  "geometry": {"coordinates":[-93.218277,36.645159],"type":"Point"}
}