{
  "type": "Feature",
  "properties": {
    "iso:country":"US",
    "sg:address":"2803 Fischer Rd",
    "sg:city":"Lohman",
    "sg:classifiers":[
        {
            "category":"Government",
            "subcategory":"Office",
            "type":"Public Place"
        }
    ],
    "sg:phone":"+1 573 782 3175",
    "sg:postcode":"65053",
    "sg:province":"MO",
    "sg:tags":[
        "management"
    ],
    "wof:name":"Top of Line Home Impr",
    "wof:placetype":"venue"
},
  "geometry": {"coordinates":[-92.40760299999999,38.544832],"type":"Point"}
}