{
  "type": "Feature",
  "properties": {
    "iso:country":"US",
    "sg:address":"112 W Pine St",
    "sg:city":"Warrensburg",
    "sg:classifiers":[
        {
            "category":"Bars & Pubs",
            "type":"Food & Drink"
        }
    ],
    "sg:phone":"+1 660 747 5988",
    "sg:postcode":"64093",
    "sg:province":"MO",
    "sg:tags":[
        "drinking"
    ],
    "wof:name":"Star Bar",
    "wof:placetype":"venue"
},
  "geometry": {"coordinates":[-93.74251700000001,38.763379],"type":"Point"}
}