{
  "type": "Feature",
  "properties": {
    "iso:country":"US",
    "sg:address":"826 Warne St",
    "sg:city":"Festus",
    "sg:classifiers":[
        {
            "category":"Building & Trades",
            "subcategory":"Construction",
            "type":"Services"
        }
    ],
    "sg:phone":"+1 636 937 9988",
    "sg:postcode":"63028",
    "sg:province":"MO",
    "sg:tags":[
        "general",
        "contractor"
    ],
    "wof:name":"Honey Do All Construction",
    "wof:placetype":"venue"
},
  "geometry": {"coordinates":[-90.394064,38.228413],"type":"Point"}
}