{
  "type": "Feature",
  "properties": {
    "iso:country":"US",
    "sg:address":"931 N Truman Blvd",
    "sg:city":"Caruthersville",
    "sg:classifiers":[
        {
            "category":"Real Estate",
            "subcategory":"Real Estate Agent",
            "type":"Services"
        }
    ],
    "sg:phone":"+1 573 333 4900",
    "sg:postcode":"63830",
    "sg:province":"MO",
    "sg:tags":[
        "management"
    ],
    "wof:name":"Movie Hut",
    "wof:placetype":"venue"
},
  "geometry": {"coordinates":[-89.667017,36.191244],"type":"Point"}
}