{
  "type": "Feature",
  "properties": {
    "iso:country":"US",
    "sg:address":"37497 Maple Grove Rd",
    "sg:city":"Windsor",
    "sg:classifiers":[
        {
            "category":"Farming",
            "subcategory":"Crops",
            "type":"Manufacturing & Wholesale Goods"
        }
    ],
    "sg:phone":"+1 660 647 2209",
    "sg:postcode":"65360",
    "sg:province":"MO",
    "sg:tags":[
        "grove",
        "nut",
        "tree"
    ],
    "wof:name":"Carroll Chancellor",
    "wof:placetype":"venue"
},
  "geometry": {"coordinates":[-93.43788499999999,38.532516],"type":"Point"}
}