{
  "type": "Feature",
  "properties": {
    "iso:country":"US",
    "sg:address":"18 Doctors Park",
    "sg:city":"Cape Girardeau",
    "sg:classifiers":[
        {
            "category":"Shopping",
            "type":"Retail Goods"
        }
    ],
    "sg:phone":"+1 573 335 4448",
    "sg:postcode":"63703",
    "sg:province":"MO",
    "sg:tags":[
        "health",
        "merchandise"
    ],
    "wof:name":"Cape Girardeau Audiology",
    "wof:placetype":"venue"
},
  "geometry": {"coordinates":[-89.576168,37.297846],"type":"Point"}
}