{
  "type": "Feature",
  "properties": {
    "iso:country":"US",
    "sg:address":"7955 Manchester Rd",
    "sg:city":"St Louis",
    "sg:classifiers":[
        {
            "category":"Manufacturing",
            "subcategory":"Retail Goods",
            "type":"Manufacturing & Wholesale Goods"
        }
    ],
    "sg:phone":"+1 314 644 0770",
    "sg:postcode":"63143",
    "sg:province":"MO",
    "sg:tags":[
        "assembly",
        "fabricating"
    ],
    "wof:name":"Custom Fabrication & Coat Inc",
    "wof:placetype":"venue"
},
  "geometry": {"coordinates":[-90.331709,38.613635],"type":"Point"}
}