{
  "type": "Feature",
  "properties": {
    "iso:country":"US",
    "sg:address":"20100 E Jackson Dr",
    "sg:city":"Independence",
    "sg:classifiers":[
        {
            "category":"Shopping",
            "type":"Retail Goods"
        }
    ],
    "sg:phone":"+1 816 478 2866",
    "sg:postcode":"64057",
    "sg:province":"MO",
    "sg:tags":[
        "cosmetic",
        "perfume"
    ],
    "wof:name":"Avon",
    "wof:placetype":"venue"
},
  "geometry": {"coordinates":[-94.345645,39.041258],"type":"Point"}
}