{
  "type": "Feature",
  "properties": {
    "iso:country":"US",
    "sg:address":"1301 E State Highway 76",
    "sg:city":"Branson",
    "sg:classifiers":[
        {
            "category":"Autos & Motor Vehicles",
            "subcategory":"Automobile Sales",
            "type":"Retail Goods"
        }
    ],
    "sg:phone":"+1 417 339 4463",
    "sg:postcode":"65616",
    "sg:province":"MO",
    "sg:tags":[
        "dealers-used",
        "car",
        "used",
        "cars-wholesale"
    ],
    "wof:name":"Marzano's East 76 Motors",
    "wof:placetype":"venue"
},
  "geometry": {"coordinates":[-93.28476000000001,36.638245],"type":"Point"}
}