{
  "type": "Feature",
  "properties": {
    "iso:country":"US",
    "sg:address":"417 Front St",
    "sg:city":"Thayer",
    "sg:classifiers":[
        {
            "category":"Autos & Motor Vehicles",
            "subcategory":"Auto Supplies",
            "type":"Retail Goods"
        }
    ],
    "sg:phone":"+1 417 264 7271",
    "sg:postcode":"65791",
    "sg:province":"MO",
    "sg:tags":[
        "accessories-wholesale",
        "automobile",
        "part",
        "parts",
        "manufacturer"
    ],
    "sg:website":"http://www.innerspacelasvegas.com",
    "wof:name":"Ram Parts Inc",
    "wof:placetype":"venue"
},
  "geometry": {"coordinates":[-91.540491,36.527578],"type":"Point"}
}