{
  "type": "Feature",
  "properties": {
    "iso:country":"US",
    "sg:address":"13913 Manchester Rd",
    "sg:city":"Ballwin",
    "sg:classifiers":[
        {
            "category":"Shopping",
            "subcategory":"Clothing, Apparel, & Fashions",
            "type":"Retail Goods"
        }
    ],
    "sg:phone":"+1 636 394 2839",
    "sg:postcode":"63011",
    "sg:province":"MO",
    "sg:tags":[
        "miscellaneous"
    ],
    "sg:website":"www.oldnavy.com",
    "wof:name":"Old Navy",
    "wof:placetype":"venue"
},
  "geometry": {"coordinates":[-90.48736599999999,38.596617],"type":"Point"}
}