{
  "type": "Feature",
  "properties": {
    "iso:country":"US",
    "sg:address":"1717 S Madison St",
    "sg:city":"Webb City",
    "sg:classifiers":[
        {
            "category":"Manufacturing",
            "subcategory":"Printing",
            "type":"Manufacturing & Wholesale Goods"
        }
    ],
    "sg:phone":"+1 417 673 3445",
    "sg:postcode":"64870",
    "sg:province":"MO",
    "sg:tags":[
        "screen"
    ],
    "wof:name":"Dugout Sport Shop Inc",
    "wof:placetype":"venue"
},
  "geometry": {"coordinates":[-94.475471,37.12503],"type":"Point"}
}