{
  "type": "Feature",
  "properties": {
    "iso:country":"US",
    "sg:address":"1432 South Dr",
    "sg:city":"St Charles",
    "sg:classifiers":[
        {
            "category":"Building & Trades",
            "subcategory":"Construction",
            "type":"Services"
        }
    ],
    "sg:phone":"+1 636 441 7374",
    "sg:postcode":"63303",
    "sg:province":"MO",
    "sg:tags":[
        "fence",
        "contractor"
    ],
    "wof:name":"Fence Depot Inc",
    "wof:placetype":"venue"
},
  "geometry": {"coordinates":[-90.507491,38.771723],"type":"Point"}
}