{
  "type": "Feature",
  "properties": {
    "iso:country":"US",
    "sg:address":"8770 State Hwy 5",
    "sg:city":"Camdenton",
    "sg:classifiers":[
        {
            "category":"Food & Beverages",
            "subcategory":"Groceries & Convenience Stores",
            "type":"Retail Goods"
        }
    ],
    "sg:phone":"+1 573 346 3868",
    "sg:postcode":"65020",
    "sg:province":"MO",
    "wof:name":"Decaturville One Stop",
    "wof:placetype":"venue"
},
  "geometry": {"coordinates":[-92.82198,38.101724],"type":"Point"}
}