{
  "type": "Feature",
  "properties": {
    "iso:country":"US",
    "sg:address":"6900 W Florissant Ave",
    "sg:city":"Saint Louis",
    "sg:classifiers":[
        {
            "category":"Autos & Motor Vehicles",
            "subcategory":"Auto Supplies",
            "type":"Retail Goods"
        }
    ],
    "sg:phone":"+1 314 382 0122",
    "sg:postcode":"63136",
    "sg:province":"MO",
    "sg:tags":[
        "tire"
    ],
    "sg:website":"www.midas.com",
    "wof:name":"Midas Auto Service Experts",
    "wof:placetype":"venue"
},
  "geometry": {"coordinates":[-90.260821,38.716784],"type":"Point"}
}