{
  "type": "Feature",
  "properties": {
    "iso:country":"US",
    "sg:address":"105 Johnstown Dr",
    "sg:city":"Rogersville",
    "sg:classifiers":[
        {
            "category":"Professional",
            "subcategory":"Accounting & Tax Preparation",
            "type":"Services"
        },
        {
            "category":"Banks & Credit Unions",
            "subcategory":"Financial Services",
            "type":"Services"
        }
    ],
    "sg:phone":"+1 417 753 3900",
    "sg:postcode":"65742",
    "sg:province":"MO",
    "sg:tags":[
        "return",
        "preparation-business",
        "taxes-consultants",
        "loan",
        "reporting",
        "representative",
        "alternative",
        "bookkeeping"
    ],
    "sg:website":"http://www.hrblock.com",
    "wof:name":"H&R Block",
    "wof:placetype":"venue"
},
  "geometry": {"coordinates":[-93.057185,37.109009],"type":"Point"}
}