{
  "type": "Feature",
  "properties": {
    "iso:country":"US",
    "sg:address":"1821 E Saint Louis St",
    "sg:city":"Springfield",
    "sg:classifiers":[
        {
            "category":"Retail",
            "subcategory":"Car Wash",
            "type":"Services"
        }
    ],
    "sg:phone":"+1 417 862 4353",
    "sg:postcode":"65802",
    "sg:province":"MO",
    "sg:tags":[
        "truck",
        "detail"
    ],
    "wof:name":"Kearney St Trck Repr & Neon",
    "wof:placetype":"venue"
},
  "geometry": {"coordinates":[-93.25939099999999,37.209298],"type":"Point"}
}