{
  "type": "Feature",
  "properties": {
    "iso:country":"US",
    "sg:address":"11519 Craig Ct",
    "sg:city":"Saint Louis",
    "sg:classifiers":[
        {
            "category":"Home & Garden",
            "subcategory":"Home Furnishings",
            "type":"Retail Goods"
        }
    ],
    "sg:phone":"+1 314 989 9002",
    "sg:postcode":"63146",
    "sg:province":"MO",
    "sg:tags":[
        "grill",
        "accessory"
    ],
    "wof:name":"Direct Sales Limited",
    "wof:placetype":"venue"
},
  "geometry": {"coordinates":[-90.4388,38.674045],"type":"Point"}
}