{
  "type": "Feature",
  "properties": {
    "iso:country":"US",
    "sg:address":"601 Bus Loop 70 E",
    "sg:city":"Columbia",
    "sg:classifiers":[
        {
            "category":"Health Services",
            "subcategory":"Clinic",
            "type":"Services"
        }
    ],
    "sg:phone":"+1 573 884 2689",
    "sg:postcode":"65201",
    "sg:province":"MO",
    "sg:tags":[
        "home"
    ],
    "wof:name":"University Nurses Sr Care",
    "wof:placetype":"venue"
},
  "geometry": {"coordinates":[-92.32946200000001,38.964224],"type":"Point"}
}