{
  "type": "Feature",
  "properties": {
    "iso:country":"US",
    "sg:address":"7750 Maryland Ave",
    "sg:city":"St Louis",
    "sg:classifiers":[
        {
            "category":"Government",
            "subcategory":"Post Office",
            "type":"Public Place"
        }
    ],
    "sg:phone":"+1 314 862 0531",
    "sg:postcode":"63105",
    "sg:province":"MO",
    "sg:tags":[
        "postal",
        "us"
    ],
    "sg:website":"www.usps.gov",
    "wof:name":"US Post Office",
    "wof:placetype":"venue"
},
  "geometry": {"coordinates":[-90.336671,38.651565],"type":"Point"}
}