{
  "type": "Feature",
  "properties": {
    "iso:country":"US",
    "sg:address":"1880 Lunenburg Dr",
    "sg:city":"Saint Peters",
    "sg:classifiers":[
        {
            "category":"Manufacturing",
            "subcategory":"Retail Goods",
            "type":"Manufacturing & Wholesale Goods"
        }
    ],
    "sg:phone":"+1 636 379 0972",
    "sg:postcode":"63376",
    "sg:province":"MO",
    "sg:tags":[
        "marking",
        "devices",
        "mfg"
    ],
    "wof:name":"Mary Maude",
    "wof:placetype":"venue"
},
  "geometry": {"coordinates":[-90.672065,38.78578],"type":"Point"}
}