{
  "type": "Feature",
  "properties": {
    "iso:country":"US",
    "sg:address":"9315 Manchester Rd",
    "sg:city":"Saint Louis",
    "sg:classifiers":[
        {
            "category":"Banks & Credit Unions",
            "subcategory":"Bank",
            "type":"Services"
        }
    ],
    "sg:phone":"+1 636 394 3300",
    "sg:postcode":"63119",
    "sg:province":"MO",
    "sg:tags":[
        "broker",
        "mortgage",
        "banker"
    ],
    "wof:name":"Ameristar",
    "wof:placetype":"venue"
},
  "geometry": {"coordinates":[-90.36027900000001,38.610786],"type":"Point"}
}