{
  "type": "Feature",
  "properties": {
    "iso:country":"US",
    "sg:address":"604 E 165th St",
    "sg:city":"Belton",
    "sg:classifiers":[
        {
            "category":"Professional",
            "subcategory":"Business Services",
            "type":"Services"
        }
    ],
    "sg:phone":"+1 816 322 7732",
    "sg:postcode":"64012",
    "sg:province":"MO",
    "wof:name":"Mew Design Services Inc",
    "wof:placetype":"venue"
},
  "geometry": {"coordinates":[-94.585674,38.836564],"type":"Point"}
}