{
  "type": "Feature",
  "properties": {
    "iso:country":"US",
    "sg:address":"2907 W Broadway Blvd",
    "sg:city":"Sedalia",
    "sg:classifiers":[
        {
            "category":"Home & Garden",
            "subcategory":"Hardware",
            "type":"Retail Goods"
        }
    ],
    "sg:phone":"+1 660 826 3100",
    "sg:postcode":"65301",
    "sg:province":"MO",
    "sg:tags":[
        "tool"
    ],
    "wof:name":"Clarks Tools",
    "wof:placetype":"venue"
},
  "geometry": {"coordinates":[-93.26227,38.707362],"type":"Point"}
}