{
  "type": "Feature",
  "properties": {
    "iso:country":"US",
    "sg:address":"3252 W Latoka St",
    "sg:city":"Springfield",
    "sg:classifiers":[
        {
            "category":"Retail",
            "subcategory":"Repair Shop",
            "type":"Services"
        }
    ],
    "sg:phone":"+1 417 882 4529",
    "sg:postcode":"65807",
    "sg:province":"MO",
    "sg:tags":[
        "machine",
        "sewing"
    ],
    "wof:name":"Greene Sewing Machine Service",
    "wof:placetype":"venue"
},
  "geometry": {"coordinates":[-93.343712,37.179528],"type":"Point"}
}