{
  "type": "Feature",
  "properties": {
    "iso:country":"US",
    "sg:address":"7613 Hwy C",
    "sg:city":"Dawn",
    "sg:classifiers":[
        {
            "category":"Government",
            "subcategory":"Post Office",
            "type":"Public Place"
        }
    ],
    "sg:phone":"+1 660 745 3330",
    "sg:postcode":"64638",
    "sg:province":"MO",
    "wof:name":"US Post Office",
    "wof:placetype":"venue"
},
  "geometry": {"coordinates":[-93.636945,39.668316],"type":"Point"}
}