{
  "type": "Feature",
  "properties": {
    "iso:country":"US",
    "sg:address":"203 E Morrison St",
    "sg:city":"Fayette",
    "sg:classifiers":[
        {
            "category":"Government",
            "subcategory":"Office",
            "type":"Public Place"
        }
    ],
    "sg:phone":"+1 660 248 2490",
    "sg:postcode":"65248",
    "sg:province":"MO",
    "sg:tags":[
        "state",
        "program"
    ],
    "wof:name":"Transportation Dept",
    "wof:placetype":"venue"
},
  "geometry": {"coordinates":[-92.681617,39.146538],"type":"Point"}
}