{
  "type": "Feature",
  "properties": {
    "iso:country":"US",
    "sg:address":"1115 Alaska St",
    "sg:city":"West Plains",
    "sg:classifiers":[
        {
            "category":"Health Services",
            "subcategory":"Doctor",
            "type":"Services"
        }
    ],
    "sg:phone":"+1 417 255 9700",
    "sg:postcode":"65775",
    "sg:province":"MO",
    "sg:tags":[
        "physician",
        "surgeon",
        "medical"
    ],
    "wof:name":"Ozark Neurosurgical Assoc LLC",
    "wof:placetype":"venue"
},
  "geometry": {"coordinates":[-91.87359600000001,36.738758],"type":"Point"}
}