{
  "type": "Feature",
  "properties": {
    "iso:country":"US",
    "sg:address":"6 Southwoods Dr",
    "sg:city":"Festus",
    "sg:classifiers":[
        {
            "category":"Building & Trades",
            "subcategory":"Construction",
            "type":"Services"
        }
    ],
    "sg:phone":"+1 636 931 2415",
    "sg:postcode":"63028",
    "sg:province":"MO",
    "sg:tags":[
        "house"
    ],
    "wof:name":"Vogelsang & Sons",
    "wof:placetype":"venue"
},
  "geometry": {"coordinates":[-90.357552,38.099701],"type":"Point"}
}