{
  "type": "Feature",
  "properties": {
    "iso:country":"US",
    "sg:address":"424 N Kentucky St",
    "sg:city":"Mexico",
    "sg:classifiers":[
        {
            "category":"Building & Trades",
            "subcategory":"Plumbing",
            "type":"Services"
        },
        {
            "category":"Building & Trades",
            "subcategory":"Construction",
            "type":"Services"
        }
    ],
    "sg:phone":"+1 573 581 2696",
    "sg:postcode":"65265",
    "sg:province":"MO",
    "sg:tags":[
        "plumber",
        "heating",
        "special",
        "contractor"
    ],
    "wof:name":"Miller's Plumbing & Heating",
    "wof:placetype":"venue"
},
  "geometry": {"coordinates":[-91.898583,39.174724],"type":"Point"}
}