{
  "type": "Feature",
  "properties": {
    "iso:country":"US",
    "sg:address":"1222 E 3rd St",
    "sg:city":"Maryville",
    "sg:classifiers":[
        {
            "category":"Shopping",
            "subcategory":"Hobbies, Toys, & Games",
            "type":"Retail Goods"
        }
    ],
    "sg:phone":"+1 660 582 8967",
    "sg:postcode":"64468",
    "sg:province":"MO",
    "wof:name":"CJ Ceramics",
    "wof:placetype":"venue"
},
  "geometry": {"coordinates":[-94.859578,40.347578],"type":"Point"}
}