{
  "type": "Feature",
  "properties": {
    "iso:country":"US",
    "sg:address":"1780 W Terra Ln",
    "sg:city":"O Fallon",
    "sg:classifiers":[
        {
            "category":"Autos & Motor Vehicles",
            "subcategory":"Automobile Sales",
            "type":"Retail Goods"
        }
    ],
    "sg:phone":"+1 636 272 2131",
    "sg:postcode":"63366",
    "sg:province":"MO",
    "sg:tags":[
        "truck"
    ],
    "wof:name":"Ryder",
    "wof:placetype":"venue"
},
  "geometry": {"coordinates":[-90.752121,38.805171],"type":"Point"}
}