{
  "type": "Feature",
  "properties": {
    "addr:full":"3304 Watson Rd St Louis MO 63139",
    "addr:housenumber":"3304",
    "addr:postcode":"63139",
    "addr:street":"Watson Rd",
    "iso:country":"US",
    "sg:address":"3304 Watson Rd",
    "sg:city":"St Louis",
    "sg:classifiers":[
        {
            "category":"Insurance",
            "subcategory":"Insurance Agent",
            "type":"Services"
        }
    ],
    "sg:phone":"+1 314 781 2290",
    "sg:postcode":"63139",
    "sg:province":"MO",
    "wof:name":"State Farm Insurance",
    "wof:placetype":"venue"
},
  "geometry": {"coordinates":[-90.29918499999999,38.601905],"type":"Point"}
}