{
  "type": "Feature",
  "properties": {
    "iso:country":"US",
    "sg:address":"106 Renee Dr",
    "sg:city":"Ashland",
    "sg:classifiers":[
        {
            "category":"Building & Trades",
            "subcategory":"Construction",
            "type":"Services"
        }
    ],
    "sg:phone":"+1 573 657 0083",
    "sg:postcode":"65010",
    "sg:province":"MO",
    "sg:tags":[
        "house"
    ],
    "wof:name":"Cosper Construction",
    "wof:placetype":"venue"
},
  "geometry": {"coordinates":[-92.25903700000001,38.765203],"type":"Point"}
}