{
  "type": "Feature",
  "properties": {
    "iso:country":"US",
    "sg:address":"1501 Hwy O",
    "sg:city":"Gravois Mills",
    "sg:classifiers":[
        {
            "category":"Social Services",
            "subcategory":"Adult Care",
            "type":"Services"
        }
    ],
    "sg:phone":"+1 573 372 3588",
    "sg:postcode":"65037",
    "sg:province":"MO",
    "sg:tags":[
        "organization",
        "senior",
        "citizen"
    ],
    "wof:name":"Westside Senior Assoc",
    "wof:placetype":"venue"
},
  "geometry": {"coordinates":[-92.79877999999999,38.22365],"type":"Point"}
}