{
  "type": "Feature",
  "properties": {
    "iso:country":"US",
    "sg:address":"10702 Trenton Ave",
    "sg:city":"St Louis",
    "sg:classifiers":[
        {
            "category":"Manufacturing",
            "subcategory":"Retail Goods",
            "type":"Manufacturing & Wholesale Goods"
        }
    ],
    "sg:phone":"+1 314 427 5310",
    "sg:postcode":"63132",
    "sg:province":"MO",
    "sg:tags":[
        "souvenir"
    ],
    "sg:website":"www.uniquecrafterscompany.com",
    "wof:name":"Unique Crafters Co",
    "wof:placetype":"venue"
},
  "geometry": {"coordinates":[-90.399636,38.69075],"type":"Point"}
}