{
  "type": "Feature",
  "properties": {
    "iso:country":"US",
    "sg:address":"2005 S Lexington St",
    "sg:city":"Holden",
    "sg:classifiers":[
        {
            "category":"Health Services",
            "subcategory":"Nursing And Care Facility",
            "type":"Services"
        },
        {
            "category":"Social Services",
            "subcategory":"Retirement Home",
            "type":"Services"
        },
        {
            "category":"Social Services",
            "subcategory":"Adult Care",
            "type":"Services"
        }
    ],
    "sg:phone":"+1 816 732 4138",
    "sg:postcode":"64040",
    "sg:province":"MO",
    "sg:tags":[
        "living",
        "people",
        "assisted",
        "community",
        "elder",
        "convalescent",
        "homes-elderly"
    ],
    "wof:name":"Holden Manor Care Center",
    "wof:placetype":"venue"
},
  "geometry": {"coordinates":[-93.994561,38.702197],"type":"Point"}
}