{
  "type": "Feature",
  "properties": {
    "iso:country":"US",
    "sg:address":"7536 Forsyth Blvd",
    "sg:city":"Saint Louis",
    "sg:classifiers":[
        {
            "category":"Professional",
            "subcategory":"Management & Consulting",
            "type":"Services"
        }
    ],
    "sg:phone":"+1 314 286 3951",
    "sg:postcode":"63105",
    "sg:province":"MO",
    "sg:tags":[
        "business"
    ],
    "wof:name":"Mellon Consultants Inc",
    "wof:placetype":"venue"
},
  "geometry": {"coordinates":[-90.33033,38.6495],"type":"Point"}
}