{
  "type": "Feature",
  "properties": {
    "iso:country":"US",
    "sg:address":"3132 S Kingshighway Blvd",
    "sg:city":"Saint Louis",
    "sg:classifiers":[
        {
            "category":"Restaurant",
            "type":"Food & Drink"
        },
        {
            "category":"Bars & Pubs",
            "subcategory":"Nightclub",
            "type":"Food & Drink"
        }
    ],
    "sg:phone":"+1 314 772 9691",
    "sg:postcode":"63139",
    "sg:province":"MO",
    "sg:tags":[
        "nightlife"
    ],
    "wof:name":"Real Bar & Grill",
    "wof:placetype":"venue"
},
  "geometry": {"coordinates":[-90.269501,38.604099],"type":"Point"}
}