{
  "type": "Feature",
  "properties": {
    "iso:country":"US",
    "sg:address":"4056 Liberty Woods Ct",
    "sg:city":"Hartsburg",
    "sg:classifiers":[
        {
            "category":"Retail",
            "subcategory":"Repair Shop",
            "type":"Services"
        }
    ],
    "sg:phone":"+1 573 657 2101",
    "sg:postcode":"65039",
    "sg:province":"MO",
    "sg:tags":[
        "plumbing",
        "head",
        "installation",
        "sprinkler",
        "welding"
    ],
    "wof:name":"Dan Woods Fire Protection & In",
    "wof:placetype":"venue"
},
  "geometry": {"coordinates":[-92.281525,38.765576],"type":"Point"}
}