{
  "type": "Feature",
  "properties": {
    "iso:country":"US",
    "sg:address":"1230 W Springfield Ave",
    "sg:city":"Union",
    "sg:classifiers":[
        {
            "category":"Home & Garden",
            "subcategory":"Garden Supply",
            "type":"Retail Goods"
        }
    ],
    "sg:phone":"+1 636 583 5772",
    "sg:postcode":"63084",
    "sg:province":"MO",
    "sg:tags":[
        "nurseryman"
    ],
    "wof:name":"Platt Nursery & Greenhouses",
    "wof:placetype":"venue"
},
  "geometry": {"coordinates":[-91.030034,38.442826],"type":"Point"}
}