{
  "type": "Feature",
  "properties": {
    "iso:country":"US",
    "sg:address":"2434 State Hwy F",
    "sg:city":"Hermann",
    "sg:classifiers":[
        {
            "category":"Building & Trades",
            "subcategory":"Cleaning & Sanitation",
            "type":"Services"
        }
    ],
    "sg:phone":"+1 573 486 3136",
    "sg:postcode":"65041",
    "sg:province":"MO",
    "sg:tags":[
        "maintenance"
    ],
    "wof:name":"Maxine P Barnes",
    "wof:placetype":"venue"
},
  "geometry": {"coordinates":[-91.49075000000001,38.563852],"type":"Point"}
}