{
  "type": "Feature",
  "properties": {
    "iso:country":"US",
    "sg:address":"1202 S 28th St",
    "sg:city":"St Joseph",
    "sg:classifiers":[
        {
            "category":"Education",
            "subcategory":"School",
            "type":"Public Place"
        }
    ],
    "sg:phone":"+1 816 671 4300",
    "sg:postcode":"64507",
    "sg:province":"MO",
    "sg:website":"www.sjsd.k12.mo.us",
    "wof:name":"Keatley Center",
    "wof:placetype":"venue"
},
  "geometry": {"coordinates":[-94.82471700000001,39.755886],"type":"Point"}
}