{
  "type": "Feature",
  "properties": {
    "iso:country":"US",
    "sg:address":"10541 US Hwy 24",
    "sg:city":"Independence",
    "sg:classifiers":[
        {
            "category":"Autos & Motor Vehicles",
            "subcategory":"Automobile Sales",
            "type":"Retail Goods"
        }
    ],
    "sg:phone":"+1 816 254 1177",
    "sg:postcode":"64053",
    "sg:province":"MO",
    "sg:tags":[
        "car",
        "dealer"
    ],
    "wof:name":"Custom Car Ctr",
    "wof:placetype":"venue"
},
  "geometry": {"coordinates":[-94.45270600000001,39.102665],"type":"Point"}
}