{
  "type": "Feature",
  "properties": {
    "iso:country":"US",
    "sg:address":"9994 Tesson Creek Estates Dr",
    "sg:city":"St Louis",
    "sg:classifiers":[
        {
            "category":"Social Services",
            "subcategory":"Child Care",
            "type":"Services"
        }
    ],
    "sg:phone":"+1 314 638 1568",
    "sg:postcode":"63123",
    "sg:province":"MO",
    "sg:tags":[
        "day"
    ],
    "wof:name":"Apple Of Your Eye Learning Ctr",
    "wof:placetype":"venue"
},
  "geometry": {"coordinates":[-90.336546,38.536435],"type":"Point"}
}