{
  "type": "Feature",
  "properties": {
    "iso:country":"US",
    "sg:address":"7505 N Campbell St",
    "sg:city":"Kansas City",
    "sg:classifiers":[
        {
            "category":"Social Services",
            "subcategory":"Child Care",
            "type":"Services"
        }
    ],
    "sg:phone":"+1 816 436 0666",
    "sg:postcode":"64118",
    "sg:province":"MO",
    "sg:tags":[
        "day"
    ],
    "wof:name":"Englewood Learning Center Inc",
    "wof:placetype":"venue"
},
  "geometry": {"coordinates":[-94.570364,39.230402],"type":"Point"}
}