{
  "type": "Feature",
  "properties": {
    "iso:country":"US",
    "sg:address":"611 Edmond St",
    "sg:city":"St Joseph",
    "sg:classifiers":[
        {
            "category":"Personal",
            "subcategory":"Tattoo Parlor",
            "type":"Services"
        },
        {
            "category":"Retail",
            "subcategory":"Auto Repair",
            "type":"Services"
        }
    ],
    "sg:phone":"+1 816 364 4484",
    "sg:postcode":"64501",
    "sg:province":"MO",
    "sg:tags":[
        "tattooing",
        "general"
    ],
    "wof:name":"A Garage Ink",
    "wof:placetype":"venue"
},
  "geometry": {"coordinates":[-94.85198699999999,39.765887],"type":"Point"}
}