{
  "type": "Feature",
  "properties": {
    "iso:country":"US",
    "sg:address":"23 Civic Park Ct",
    "sg:city":"O Fallon",
    "sg:classifiers":[
        {
            "category":"Health Services",
            "subcategory":"Clinic",
            "type":"Services"
        }
    ],
    "sg:phone":"+1 636 980 4256",
    "sg:postcode":"63366",
    "sg:province":"MO",
    "sg:tags":[
        "home",
        "care"
    ],
    "sg:website":"www.angelsonduty.com",
    "wof:name":"Angels On Duty Inc",
    "wof:placetype":"venue"
},
  "geometry": {"coordinates":[-90.711056,38.811262],"type":"Point"}
}