{
  "type": "Feature",
  "properties": {
    "iso:country":"US",
    "sg:address":"3761 Eiler St",
    "sg:city":"St Louis",
    "sg:classifiers":[
        {
            "category":"Manufacturing",
            "subcategory":"Tools & Machinery",
            "type":"Manufacturing & Wholesale Goods"
        }
    ],
    "sg:phone":"+1 314 481 7171",
    "sg:postcode":"63116",
    "sg:province":"MO",
    "sg:tags":[
        "machine",
        "shop"
    ],
    "wof:name":"South Side Machine Works Inc",
    "wof:placetype":"venue"
},
  "geometry": {"coordinates":[-90.257175,38.57189],"type":"Point"}
}