{
  "type": "Feature",
  "properties": {
    "iso:country":"US",
    "sg:address":"113 N Alvarado Ave",
    "sg:city":"Belle",
    "sg:classifiers":[
        {
            "category":"Health Services",
            "subcategory":"Optometrist",
            "type":"Services"
        }
    ],
    "sg:phone":"+1 573 859 6614",
    "sg:postcode":"65013",
    "sg:province":"MO",
    "wof:name":"Obermark Optometry",
    "wof:placetype":"venue"
},
  "geometry": {"coordinates":[-91.72093,38.288321],"type":"Point"}
}