{
  "type": "Feature",
  "properties": {
    "iso:country":"US",
    "sg:address":"1907 N Providence Rd",
    "sg:city":"Columbia",
    "sg:classifiers":[
        {
            "category":"Retail",
            "subcategory":"Repair Shop",
            "type":"Services"
        }
    ],
    "sg:phone":"+1 573 449 0343",
    "sg:postcode":"65203",
    "sg:province":"MO",
    "sg:tags":[
        "glassware",
        "chinaware"
    ],
    "wof:name":"Show Me China Repair",
    "wof:placetype":"venue"
},
  "geometry": {"coordinates":[-92.333724,38.973929],"type":"Point"}
}