{
  "type": "Feature",
  "properties": {
    "iso:country":"US",
    "sg:address":"603 S Market St",
    "sg:city":"Alton",
    "sg:classifiers":[
        {
            "category":"Restaurant",
            "type":"Food & Drink"
        }
    ],
    "sg:phone":"+1 417 778 2110",
    "sg:postcode":"65606",
    "sg:province":"MO",
    "sg:tags":[
        "pizza"
    ],
    "wof:name":"Pizza & More",
    "wof:placetype":"venue"
},
  "geometry": {"coordinates":[-91.395408,36.690029],"type":"Point"}
}