{
  "type": "Feature",
  "properties": {
    "iso:country":"US",
    "sg:address":"4214 SE Victory Dr",
    "sg:city":"Lees Summit",
    "sg:classifiers":[
        {
            "category":"Building & Trades",
            "subcategory":"Construction",
            "type":"Services"
        }
    ],
    "sg:phone":"+1 816 537 8766",
    "sg:postcode":"64082",
    "sg:province":"MO",
    "sg:tags":[
        "excavation",
        "contractor"
    ],
    "wof:name":"Green & Green Construction",
    "wof:placetype":"venue"
},
  "geometry": {"coordinates":[-94.37181699999999,38.842469],"type":"Point"}
}