{
  "type": "Feature",
  "properties": {
    "iso:country":"US",
    "sg:address":"28 N 8th St",
    "sg:city":"Columbia",
    "sg:classifiers":[
        {
            "category":"Building & Trades",
            "subcategory":"Construction",
            "type":"Services"
        }
    ],
    "sg:phone":"+1 573 442 1370",
    "sg:postcode":"65201",
    "sg:province":"MO",
    "sg:tags":[
        "general",
        "commercial",
        "contractor"
    ],
    "wof:name":"Gerardi Construction Company",
    "wof:placetype":"venue"
},
  "geometry": {"coordinates":[-92.328525,38.951809],"type":"Point"}
}