{
  "type": "Feature",
  "properties": {
    "iso:country":"US",
    "sg:address":"4013 Highway 50",
    "sg:city":"Beaufort",
    "sg:classifiers":[
        {
            "category":"Home & Garden",
            "subcategory":"Furniture",
            "type":"Retail Goods"
        }
    ],
    "sg:phone":"+1 636 221 1658",
    "sg:postcode":"63013",
    "sg:province":"MO",
    "sg:tags":[
        "store"
    ],
    "wof:name":"Kojak Cabinets Furniture",
    "wof:placetype":"venue"
},
  "geometry": {"coordinates":[-91.187181,38.420321],"type":"Point"}
}