{
  "type": "Feature",
  "properties": {
    "iso:country":"US",
    "sg:address":"14021 Botts Rd",
    "sg:city":"Grandview",
    "sg:classifiers":[
        {
            "category":"Wholesale",
            "subcategory":"Machinery & Supplies",
            "type":"Manufacturing & Wholesale Goods"
        }
    ],
    "sg:phone":"+1 816 767 1767",
    "sg:postcode":"64030",
    "sg:province":"MO",
    "sg:tags":[
        "equipment",
        "industrial",
        "metal",
        "center"
    ],
    "sg:website":"www.heartlandwaterworks.com",
    "wof:name":"Heartland Waterworks Supply",
    "wof:placetype":"venue"
},
  "geometry": {"coordinates":[-94.54553300000001,38.869505],"type":"Point"}
}