{
  "type": "Feature",
  "properties": {
    "iso:country":"US",
    "sg:address":"909 N 20th St",
    "sg:city":"Saint Louis",
    "sg:classifiers":[
        {
            "category":"Shopping",
            "subcategory":"Clothing, Apparel, & Fashions",
            "type":"Retail Goods"
        }
    ],
    "sg:phone":"+1 314 802 6343",
    "sg:postcode":"63106",
    "sg:province":"MO",
    "sg:tags":[
        "garment",
        "sportswear"
    ],
    "wof:name":"Legacy Group LLC",
    "wof:placetype":"venue"
},
  "geometry": {"coordinates":[-90.206571,38.637607],"type":"Point"}
}