{
  "type": "Feature",
  "properties": {
    "iso:country":"US",
    "sg:address":"2625 Victron Dr",
    "sg:city":"Saint Louis",
    "sg:classifiers":[
        {
            "category":"Shopping",
            "subcategory":"Gifts & Souvenirs",
            "type":"Retail Goods"
        }
    ],
    "sg:phone":"+1 314 894 9786",
    "sg:postcode":"63129",
    "sg:province":"MO",
    "sg:tags":[
        "equipment",
        "commercial"
    ],
    "wof:name":"Shadow Box Displays",
    "wof:placetype":"venue"
},
  "geometry": {"coordinates":[-90.30976099999999,38.478664],"type":"Point"}
}