{
  "type": "Feature",
  "properties": {
    "iso:country":"US",
    "sg:address":"1010 State Hwy 84",
    "sg:city":"Hayti",
    "sg:classifiers":[
        {
            "category":"Wholesale",
            "subcategory":"Farm Supplies",
            "type":"Manufacturing & Wholesale Goods"
        }
    ],
    "sg:phone":"+1 573 359 6300",
    "sg:postcode":"63851",
    "sg:province":"MO",
    "wof:name":"Us Ag Inc",
    "wof:placetype":"venue"
},
  "geometry": {"coordinates":[-89.763734,36.233846],"type":"Point"}
}