{
  "type": "Feature",
  "properties": {
    "iso:country":"US",
    "sg:address":"3504 SW Park Ln",
    "sg:city":"Blue Springs",
    "sg:classifiers":[
        {
            "category":"Professional",
            "subcategory":"Business Services",
            "type":"Services"
        }
    ],
    "sg:phone":"+1 816 229 0022",
    "sg:postcode":"64015",
    "sg:province":"MO",
    "wof:name":"Heart of America Home Insptn",
    "wof:placetype":"venue"
},
  "geometry": {"coordinates":[-94.288303,38.986121],"type":"Point"}
}