{
  "type": "Feature",
  "properties": {
    "iso:country":"US",
    "sg:address":"702 E 34th St Ste 100",
    "sg:city":"Joplin",
    "sg:classifiers":[
        {
            "category":"Health Services",
            "subcategory":"Doctor",
            "type":"Services"
        }
    ],
    "sg:phone":"+1 417 782 1700",
    "sg:postcode":"64804",
    "sg:province":"MO",
    "sg:tags":[
        "physician",
        "surgeon"
    ],
    "wof:name":"Melvin Karges Md",
    "wof:placetype":"venue"
},
  "geometry": {"coordinates":[-94.506283,37.05135],"type":"Point"}
}