{
  "type": "Feature",
  "properties": {
    "iso:country":"US",
    "sg:address":"2580 State Highway 165",
    "sg:city":"Branson",
    "sg:classifiers":[
        {
            "category":"Real Estate",
            "subcategory":"Developer",
            "type":"Services"
        }
    ],
    "sg:phone":"+1 417 334 4189",
    "sg:postcode":"65616",
    "sg:province":"MO",
    "sg:website":"http://www.hilcoent.com",
    "wof:name":"Branson Hwy K Marina",
    "wof:placetype":"venue"
},
  "geometry": {"coordinates":[-93.297828,36.603559],"type":"Point"}
}