{
  "type": "Feature",
  "properties": {
    "iso:country":"US",
    "sg:address":"1644 SE Decker",
    "sg:city":"Lees Summit",
    "sg:classifiers":[
        {
            "category":"Building & Trades",
            "subcategory":"Construction",
            "type":"Services"
        }
    ],
    "sg:phone":"+1 816 524 2830",
    "sg:postcode":"64081",
    "sg:province":"MO",
    "sg:tags":[
        "sheet",
        "mfg"
    ],
    "sg:website":"www.eldonandsons.com",
    "wof:name":"Eldon & Sons Inc",
    "wof:placetype":"venue"
},
  "geometry": {"coordinates":[-94.37174400000001,38.891596],"type":"Point"}
}