{
  "type": "Feature",
  "properties": {
    "iso:country":"US",
    "sg:address":"108 E Lark Dr",
    "sg:city":"Fenton",
    "sg:classifiers":[
        {
            "category":"Farming",
            "subcategory":"Farm",
            "type":"Manufacturing & Wholesale Goods"
        }
    ],
    "sg:phone":"+1 636 326 0788",
    "sg:postcode":"63026",
    "sg:province":"MO",
    "sg:tags":[
        "crop",
        "general"
    ],
    "wof:name":"Jake Sprock",
    "wof:placetype":"venue"
},
  "geometry": {"coordinates":[-90.48993900000001,38.49563],"type":"Point"}
}