{
  "type": "Feature",
  "properties": {
    "iso:country":"US",
    "sg:address":"115 Meramec Park Dr",
    "sg:city":"Sullivan",
    "sg:classifiers":[
        {
            "category":"Park",
            "type":"Public Place"
        }
    ],
    "sg:phone":"+1 573 468 8155",
    "sg:postcode":"63080",
    "sg:province":"MO",
    "wof:name":"Meramec State Park Naturalist",
    "wof:placetype":"venue"
},
  "geometry": {"coordinates":[-91.110738,38.191064],"type":"Point"}
}