{
  "type": "Feature",
  "properties": {
    "iso:country":"US",
    "sg:address":"14000 Alpine Ave",
    "sg:city":"New Boston",
    "sg:classifiers":[
        {
            "category":"Farming",
            "subcategory":"Livestock Farm",
            "type":"Manufacturing & Wholesale Goods"
        }
    ],
    "sg:phone":"+1 660 689 3409",
    "sg:postcode":"63557",
    "sg:province":"MO",
    "sg:tags":[
        "beef",
        "feedlot",
        "cattle"
    ],
    "wof:name":"West Acres Ranch",
    "wof:placetype":"venue"
},
  "geometry": {"coordinates":[-92.85037,40.006781],"type":"Point"}
}