{
  "type": "Feature",
  "properties": {
    "iso:country":"US",
    "sg:address":"11804 State Hwy 72",
    "sg:city":"Millersville",
    "sg:classifiers":[
        {
            "category":"Retail",
            "subcategory":"Auto Repair",
            "type":"Services"
        }
    ],
    "sg:phone":"+1 573 243 6681",
    "sg:postcode":"63766",
    "sg:province":"MO",
    "sg:tags":[
        "wrecker"
    ],
    "wof:name":"A-1 Towing",
    "wof:placetype":"venue"
},
  "geometry": {"coordinates":[-89.83682399999999,37.441086],"type":"Point"}
}