{
  "type": "Feature",
  "properties": {
    "iso:country":"US",
    "sg:address":"186 Black Oak Dr",
    "sg:city":"Foley",
    "sg:classifiers":[
        {
            "category":"Wholesale",
            "subcategory":"Construction Materials",
            "type":"Manufacturing & Wholesale Goods"
        }
    ],
    "sg:phone":"+1 636 662 2404",
    "sg:postcode":"63347",
    "sg:province":"MO",
    "wof:name":"Style Step",
    "wof:placetype":"venue"
},
  "geometry": {"coordinates":[-90.77069,39.04572],"type":"Point"}
}