{
  "type": "Feature",
  "properties": {
    "iso:country":"US",
    "sg:address":"16 Ronnie Dr",
    "sg:city":"O Fallon",
    "sg:classifiers":[
        {
            "category":"Retail",
            "subcategory":"Repair Shop",
            "type":"Services"
        },
        {
            "category":"Building & Trades",
            "subcategory":"Construction",
            "type":"Services"
        }
    ],
    "sg:phone":"+1 636 240 8892",
    "sg:postcode":"63366",
    "sg:province":"MO",
    "sg:tags":[
        "welding",
        "contractor"
    ],
    "wof:name":"Berry's Welding",
    "wof:placetype":"venue"
},
  "geometry": {"coordinates":[-90.69356500000001,38.811146],"type":"Point"}
}