{
  "type": "Feature",
  "properties": {
    "iso:country":"US",
    "sg:address":"5355 N Clearbrook Ln",
    "sg:city":"Strafford",
    "sg:classifiers":[
        {
            "category":"Building & Trades",
            "subcategory":"Construction",
            "type":"Services"
        }
    ],
    "sg:phone":"+1 417 736 3058",
    "sg:postcode":"65757",
    "sg:province":"MO",
    "sg:tags":[
        "house"
    ],
    "wof:name":"Flatness Construction",
    "wof:placetype":"venue"
},
  "geometry": {"coordinates":[-93.15878499999999,37.28742],"type":"Point"}
}