{
  "type": "Feature",
  "properties": {
    "iso:country":"US",
    "sg:address":"275 N Washington St",
    "sg:city":"Kahoka",
    "sg:classifiers":[
        {
            "category":"Government",
            "subcategory":"Office",
            "type":"Public Place"
        }
    ],
    "sg:phone":"+1 660 727 3700",
    "sg:postcode":"63445",
    "sg:province":"MO",
    "sg:tags":[
        "city",
        "program",
        "adm"
    ],
    "wof:name":"Kahoka City Economic Dev",
    "wof:placetype":"venue"
},
  "geometry": {"coordinates":[-91.72219200000001,40.42214],"type":"Point"}
}