{
  "type": "Feature",
  "properties": {
    "iso:country":"US",
    "sg:address":"5605 Troost Ave",
    "sg:city":"Kansas City",
    "sg:classifiers":[
        {
            "category":"Social Services",
            "type":"Services"
        }
    ],
    "sg:phone":"+1 816 333 4963",
    "sg:postcode":"64110",
    "sg:province":"MO",
    "sg:tags":[
        "organization",
        "welfare"
    ],
    "wof:name":"49-63 Neighborhood Coalition",
    "wof:placetype":"venue"
},
  "geometry": {"coordinates":[-94.57391800000001,39.023642],"type":"Point"}
}