{
  "type": "Feature",
  "properties": {
    "iso:country":"US",
    "sg:address":"18202 E Union School Rd",
    "sg:city":"Independence",
    "sg:classifiers":[
        {
            "category":"Professional",
            "subcategory":"Management & Consulting",
            "type":"Services"
        }
    ],
    "sg:phone":"+1 816 796 6017",
    "sg:postcode":"64058",
    "sg:province":"MO",
    "sg:tags":[
        "support",
        "facility"
    ],
    "wof:name":"John W & Yvonne D Brockman",
    "wof:placetype":"venue"
},
  "geometry": {"coordinates":[-94.36782599999999,39.150262],"type":"Point"}
}