{
  "type": "Feature",
  "properties": {
    "iso:country":"US",
    "sg:address":"409 SW 25 St",
    "sg:city":"Blue Springs",
    "sg:classifiers":[
        {
            "category":"Freight",
            "type":"Transportation"
        }
    ],
    "sg:phone":"+1 816 228 3315",
    "sg:postcode":"64015",
    "sg:province":"MO",
    "sg:tags":[
        "trucking"
    ],
    "wof:name":"R G W Trucking Inc",
    "wof:placetype":"venue"
},
  "geometry": {"coordinates":[-94.292732,39.014515],"type":"Point"}
}