{
  "type": "Feature",
  "properties": {
    "iso:country":"US",
    "sg:address":"3898 Quince Rd",
    "sg:city":"Seneca",
    "sg:classifiers":[
        {
            "category":"Shopping",
            "subcategory":"Computers & Home Electronics",
            "type":"Retail Goods"
        }
    ],
    "sg:phone":"+1 417 776 8111",
    "sg:postcode":"64865",
    "sg:province":"MO",
    "sg:tags":[
        "equipment",
        "dealer"
    ],
    "wof:name":"Seneca Border Town Computers",
    "wof:placetype":"venue"
},
  "geometry": {"coordinates":[-94.582931,36.809047],"type":"Point"}
}