{
  "type": "Feature",
  "properties": {
    "iso:country":"US",
    "sg:address":"109 N Keene St",
    "sg:city":"Columbia",
    "sg:classifiers":[
        {
            "category":"Health Services",
            "subcategory":"Nursing And Care Facility",
            "type":"Services"
        }
    ],
    "sg:phone":"+1 573 443 2007",
    "sg:postcode":"65201",
    "sg:province":"MO",
    "sg:tags":[
        "home",
        "retirement",
        "community"
    ],
    "wof:name":"Boone Landing",
    "wof:placetype":"venue"
},
  "geometry": {"coordinates":[-92.29064,38.950347],"type":"Point"}
}