{
  "type": "Feature",
  "properties": {
    "iso:country":"US",
    "sg:address":"6901 MacKenzie Rd",
    "sg:city":"Saint Louis",
    "sg:classifiers":[
        {
            "category":"Retail",
            "subcategory":"Funeral Services",
            "type":"Services"
        }
    ],
    "sg:phone":"+1 314 352 5300",
    "sg:postcode":"63123",
    "sg:province":"MO",
    "sg:tags":[
        "cemetery"
    ],
    "wof:name":"Resurrection Cemetery & Mausoleum",
    "wof:placetype":"venue"
},
  "geometry": {"coordinates":[-90.319397,38.574299],"type":"Point"}
}