{
  "type": "Feature",
  "properties": {
    "iso:country":"US",
    "sg:address":"810 Baltimore Ave",
    "sg:city":"Kansas City",
    "sg:classifiers":[
        {
            "category":"Organizations",
            "subcategory":"Professional Association",
            "type":"Services"
        }
    ],
    "sg:phone":"+1 816 474 8677",
    "sg:postcode":"64105",
    "sg:province":"MO",
    "wof:name":"Amatuer Baseball Umpires Assn",
    "wof:placetype":"venue"
},
  "geometry": {"coordinates":[-94.584395,39.103698],"type":"Point"}
}