{
  "type": "Feature",
  "properties": {
    "iso:country":"US",
    "sg:address":"1808 Swift Ave",
    "sg:city":"Kansas City",
    "sg:classifiers":[
        {
            "category":"Building & Trades",
            "subcategory":"Construction",
            "type":"Services"
        }
    ],
    "sg:phone":"+1 816 221 1225",
    "sg:postcode":"64116",
    "sg:province":"MO",
    "wof:name":"Ivan Cox General Contractor",
    "wof:placetype":"venue"
},
  "geometry": {"coordinates":[-94.57737400000001,39.14094],"type":"Point"}
}