{
  "type": "Feature",
  "properties": {
    "iso:country":"US",
    "sg:address":"3712 E 39 St",
    "sg:city":"Kansas City",
    "sg:classifiers":[
        {
            "category":"Professional",
            "type":"Services"
        }
    ],
    "sg:phone":"+1 816 924 0300",
    "sg:postcode":"64128",
    "sg:province":"MO",
    "wof:name":"Kic Corp",
    "wof:placetype":"venue"
},
  "geometry": {"coordinates":[-94.53988699999999,39.055051],"type":"Point"}
}