{
  "type": "Feature",
  "properties": {
    "iso:country":"US",
    "sg:address":"601 Collins Dr",
    "sg:city":"Festus",
    "sg:classifiers":[
        {
            "category":"Organizations",
            "subcategory":"Religious Organization",
            "type":"Services"
        }
    ],
    "sg:phone":"+1 636 937 0565",
    "sg:postcode":"63028",
    "sg:province":"MO",
    "sg:tags":[
        "church"
    ],
    "wof:name":"Jehovah's Witnesses Of Festus",
    "wof:placetype":"venue"
},
  "geometry": {"coordinates":[-90.41225,38.213159],"type":"Point"}
}