{
  "type": "Feature",
  "properties": {
    "iso:country":"US",
    "sg:address":"1217 State Hwy 7",
    "sg:city":"Blue Springs",
    "sg:classifiers":[
        {
            "category":"Personal",
            "subcategory":"Beauty Salon",
            "type":"Services"
        }
    ],
    "sg:phone":"+1 816 224 5333",
    "sg:postcode":"64014",
    "sg:province":"MO",
    "wof:name":"Oasis Tan",
    "wof:placetype":"venue"
},
  "geometry": {"coordinates":[-94.27299600000001,39.002237],"type":"Point"}
}