{
  "type": "Feature",
  "properties": {
    "iso:country":"US",
    "sg:address":"700 Karnes Blvd",
    "sg:city":"Kansas City",
    "sg:classifiers":[
        {
            "category":"Banks & Credit Unions",
            "subcategory":"Financial Services",
            "type":"Services"
        }
    ],
    "sg:phone":"+1 816 751 5900",
    "sg:postcode":"64108",
    "sg:province":"MO",
    "sg:tags":[
        "funds",
        "mutual"
    ],
    "wof:name":"Jones & Babson Distributors",
    "wof:placetype":"venue"
},
  "geometry": {"coordinates":[-94.59281900000001,39.071385],"type":"Point"}
}