{
  "type": "Feature",
  "properties": {
    "iso:country":"US",
    "sg:address":"3007 S Belt Hwy",
    "sg:city":"St Joseph",
    "sg:classifiers":[
        {
            "category":"Health Services",
            "subcategory":"Health Practitioner",
            "type":"Services"
        }
    ],
    "sg:phone":"+1 816 387 9800",
    "sg:postcode":"64503",
    "sg:province":"MO",
    "sg:tags":[
        "pathologist",
        "speech"
    ],
    "wof:name":"Weber Speech Clinic",
    "wof:placetype":"venue"
},
  "geometry": {"coordinates":[-94.80109,39.739928],"type":"Point"}
}