{
  "type": "Feature",
  "properties": {
    "iso:country":"US",
    "sg:address":"1306 E Main St",
    "sg:city":"Linn",
    "sg:classifiers":[
        {
            "category":"Health Services",
            "subcategory":"Doctor",
            "type":"Services"
        }
    ],
    "sg:phone":"+1 573 897 2202",
    "sg:postcode":"65051",
    "sg:province":"MO",
    "sg:tags":[
        "clinic"
    ],
    "wof:name":"Family Care Clinic",
    "wof:placetype":"venue"
},
  "geometry": {"coordinates":[-91.83509599999999,38.473686],"type":"Point"}
}