{
  "type": "Feature",
  "properties": {
    "iso:country":"US",
    "sg:address":"35 Pine Oak Dr",
    "sg:city":"Iberia",
    "sg:classifiers":[
        {
            "category":"Retail",
            "subcategory":"Auto Repair",
            "type":"Services"
        }
    ],
    "sg:phone":"+1 573 793 2152",
    "sg:postcode":"65486",
    "sg:province":"MO",
    "sg:tags":[
        "body"
    ],
    "wof:name":"B&J Mobile Home Service",
    "wof:placetype":"venue"
},
  "geometry": {"coordinates":[-92.357001,38.144543],"type":"Point"}
}