{
  "type": "Feature",
  "properties": {
    "iso:country":"US",
    "sg:address":"1300 E Main St",
    "sg:city":"Linn",
    "sg:classifiers":[
        {
            "category":"Restaurant",
            "type":"Food & Drink"
        }
    ],
    "sg:phone":"+1 573 897 0495",
    "sg:postcode":"65051",
    "sg:province":"MO",
    "wof:name":"Taco Bell",
    "wof:placetype":"venue"
},
  "geometry": {"coordinates":[-91.83599100000001,38.474612],"type":"Point"}
}