{
  "type": "Feature",
  "properties": {
    "iso:country":"US",
    "sg:address":"2501 SW Whispering Creek Ct",
    "sg:city":"Blue Springs",
    "sg:classifiers":[
        {
            "category":"Professional",
            "type":"Services"
        }
    ],
    "sg:phone":"+1 816 220 3570",
    "sg:postcode":"64015",
    "sg:province":"MO",
    "sg:tags":[
        "establishment"
    ],
    "wof:name":"Mckesson",
    "wof:placetype":"venue"
},
  "geometry": {"coordinates":[-94.283134,38.993847],"type":"Point"}
}