{
  "type": "Feature",
  "properties": {
    "iso:country":"US",
    "sg:address":"926 Keeneland Rd",
    "sg:city":"Florissant",
    "sg:classifiers":[
        {
            "category":"Wholesale",
            "subcategory":"Jewelry",
            "type":"Manufacturing & Wholesale Goods"
        }
    ],
    "sg:phone":"+1 314 839 0128",
    "sg:postcode":"63034",
    "sg:province":"MO",
    "sg:tags":[
        "stone"
    ],
    "wof:name":"Bella Linx",
    "wof:placetype":"venue"
},
  "geometry": {"coordinates":[-90.30170099999999,38.835153],"type":"Point"}
}