{
  "type": "Feature",
  "properties": {
    "addr:full":"7406 N Oak Fwy Kansas City MO 64118",
    "addr:housenumber":"7406",
    "addr:postcode":"64118",
    "addr:street":"N Oak Fwy",
    "iso:country":"US",
    "sg:address":"7406 N Oak Fwy",
    "sg:city":"Kansas City",
    "sg:classifiers":[
        {
            "category":"Building & Trades",
            "subcategory":"Construction",
            "type":"Services"
        }
    ],
    "sg:phone":"+1 816 797 0345",
    "sg:postcode":"64118",
    "sg:province":"MO",
    "sg:tags":[
        "auto",
        "window",
        "commercial",
        "tinting",
        "residential"
    ],
    "wof:name":"Cutting Edge",
    "wof:placetype":"venue"
},
  "geometry": {"coordinates":[-94.57615800000001,39.22893],"type":"Point"}
}