{
  "type": "Feature",
  "properties": {
    "iso:country":"US",
    "sg:address":"6924 W Florissant Ave",
    "sg:city":"Saint Louis",
    "sg:classifiers":[
        {
            "category":"Manufacturing",
            "subcategory":"Printing",
            "type":"Manufacturing & Wholesale Goods"
        }
    ],
    "sg:phone":"+1 314 381 6554",
    "sg:postcode":"63136",
    "sg:province":"MO",
    "sg:tags":[
        "lithographic",
        "commercial"
    ],
    "wof:name":"Print Shop The",
    "wof:placetype":"venue"
},
  "geometry": {"coordinates":[-90.260989,38.717283],"type":"Point"}
}