{
  "type": "Feature",
  "properties": {
    "iso:country":"US",
    "sg:address":"400 Geronimo Dr",
    "sg:city":"Independence",
    "sg:classifiers":[
        {
            "category":"Manufacturing",
            "subcategory":"Apparel",
            "type":"Manufacturing & Wholesale Goods"
        }
    ],
    "sg:phone":"+1 816 796 8613",
    "sg:postcode":"64056",
    "sg:province":"MO",
    "wof:name":"Crickett Embroidery",
    "wof:placetype":"venue"
},
  "geometry": {"coordinates":[-94.359329,39.110381],"type":"Point"}
}