{
  "type": "Feature",
  "properties": {
    "addr:full":"1901 E 32nd St Joplin MO 64804",
    "addr:housenumber":"1901",
    "addr:postcode":"64804",
    "addr:street":"E 32Nd St",
    "iso:country":"US",
    "sg:address":"1901 E 32nd St",
    "sg:city":"Joplin",
    "sg:classifiers":[
        {
            "category":"Banks & Credit Unions",
            "subcategory":"Bank",
            "type":"Services"
        }
    ],
    "sg:phone":"+1 417 782 6555",
    "sg:postcode":"64804",
    "sg:province":"MO",
    "sg:tags":[
        "cashing",
        "personal",
        "check",
        "institution"
    ],
    "wof:name":"Advance America",
    "wof:placetype":"venue"
},
  "geometry": {"coordinates":[-94.49399699999999,37.054801],"type":"Point"}
}