{
  "type": "Feature",
  "properties": {
    "iso:country":"US",
    "sg:address":"4404 NE Antioch Rd",
    "sg:city":"Kansas City",
    "sg:classifiers":[
        {
            "category":"Restaurant",
            "type":"Food & Drink"
        }
    ],
    "sg:menulink":"http://www.allmenus.com/mo/gallatin/141694-waffle-house/menu/",
    "sg:phone":"+1 816 454 5505",
    "sg:postcode":"64117",
    "sg:province":"MO",
    "sg:tags":[
        "american"
    ],
    "wof:name":"Waffle House",
    "wof:placetype":"venue"
},
  "geometry": {"coordinates":[-94.54952299999999,39.174471],"type":"Point"}
}