{
  "type": "Feature",
  "properties": {
    "iso:country":"US",
    "sg:address":"986 SW 37 St",
    "sg:city":"Blue Springs",
    "sg:classifiers":[
        {
            "category":"Health Services",
            "subcategory":"Clinic",
            "type":"Services"
        },
        {
            "category":"Professional",
            "subcategory":"Employment Agencies",
            "type":"Services"
        }
    ],
    "sg:phone":"+1 816 228 1300",
    "sg:postcode":"64015",
    "sg:province":"MO",
    "sg:tags":[
        "home",
        "care"
    ],
    "wof:name":"Cascade Health Services",
    "wof:placetype":"venue"
},
  "geometry": {"coordinates":[-94.30667099999999,39.011364],"type":"Point"}
}