{
  "type": "Feature",
  "properties": {
    "iso:country":"US",
    "sg:address":"2131 S River St",
    "sg:city":"Carthage",
    "sg:classifiers":[
        {
            "category":"Social Services",
            "subcategory":"Adult Care",
            "type":"Services"
        }
    ],
    "sg:phone":"+1 417 358 9788",
    "sg:postcode":"64836",
    "sg:province":"MO",
    "sg:tags":[
        "home",
        "residential"
    ],
    "wof:name":"Bristol Manor",
    "wof:placetype":"venue"
},
  "geometry": {"coordinates":[-94.30120599999999,37.15216],"type":"Point"}
}