{
  "type": "Feature",
  "properties": {
    "iso:country":"US",
    "sg:address":"8432 Eager Rd",
    "sg:city":"St Louis",
    "sg:classifiers":[
        {
            "category":"Retail",
            "subcategory":"Laundry & Dry Cleaning",
            "type":"Services"
        }
    ],
    "sg:phone":"+1 314 918 1191",
    "sg:postcode":"63144",
    "sg:province":"MO",
    "sg:tags":[
        "cleaners",
        "plant",
        "drycleaning"
    ],
    "wof:name":"VIP Dry Cleaners",
    "wof:placetype":"venue"
},
  "geometry": {"coordinates":[-90.340993,38.62916],"type":"Point"}
}