{
  "type": "Feature",
  "properties": {
    "iso:country":"US",
    "sg:address":"222 E Madison St",
    "sg:city":"Marshfield",
    "sg:classifiers":[
        {
            "category":"Retail",
            "subcategory":"Repair Shop",
            "type":"Services"
        }
    ],
    "sg:phone":"+1 417 859 2117",
    "sg:postcode":"65706",
    "sg:province":"MO",
    "sg:tags":[
        "farm",
        "equipment",
        "parts"
    ],
    "wof:name":"Marshfield Machinery Co",
    "wof:placetype":"venue"
},
  "geometry": {"coordinates":[-92.905146,37.338004],"type":"Point"}
}