{
  "type": "Feature",
  "properties": {
    "iso:country":"US",
    "sg:address":"820 N Main St",
    "sg:city":"Sikeston",
    "sg:classifiers":[
        {
            "category":"Professional",
            "subcategory":"Lawyer & Legal Services",
            "type":"Services"
        }
    ],
    "sg:phone":"+1 573 471 8300",
    "sg:postcode":"63801",
    "sg:province":"MO",
    "sg:tags":[
        "attorney",
        "criminal",
        "law"
    ],
    "sg:website":"http://mcclellanlawfirm.com",
    "wof:name":"James McClellan",
    "wof:placetype":"venue"
},
  "geometry": {"coordinates":[-89.58268,36.887665],"type":"Point"}
}