{
  "type": "Feature",
  "properties": {
    "iso:country":"US",
    "sg:address":"661 Saint Ferdinand St",
    "sg:city":"Florissant",
    "sg:classifiers":[
        {
            "category":"Building & Trades",
            "subcategory":"Plumbing",
            "type":"Services"
        }
    ],
    "sg:phone":"+1 314 837 3351",
    "sg:postcode":"63031",
    "sg:province":"MO",
    "sg:tags":[
        "plumbing",
        "contractor"
    ],
    "wof:name":"Miller Phil L Plbg & Htg Co",
    "wof:placetype":"venue"
},
  "geometry": {"coordinates":[-90.330938,38.79592],"type":"Point"}
}