{
  "type": "Feature",
  "properties": {
    "iso:country":"US",
    "sg:address":"6141 Natural Bridge Ave",
    "sg:city":"St Louis",
    "sg:classifiers":[
        {
            "category":"Personal",
            "subcategory":"Beauty Salon",
            "type":"Services"
        }
    ],
    "sg:phone":"+1 314 383 5850",
    "sg:postcode":"63120",
    "sg:province":"MO",
    "wof:name":"Gertha's Hair Fashions",
    "wof:placetype":"venue"
},
  "geometry": {"coordinates":[-90.276827,38.690697],"type":"Point"}
}