{
  "type": "Feature",
  "properties": {
    "iso:country":"US",
    "sg:address":"108 Brook Dr",
    "sg:city":"Fenton",
    "sg:classifiers":[
        {
            "category":"Professional",
            "subcategory":"Accounting & Tax Preparation",
            "type":"Services"
        }
    ],
    "sg:phone":"+1 636 326 0564",
    "sg:postcode":"63026",
    "sg:province":"MO",
    "sg:tags":[
        "return",
        "filing"
    ],
    "wof:name":"Abell's Tax Svc",
    "wof:placetype":"venue"
},
  "geometry": {"coordinates":[-90.46718799999999,38.496668],"type":"Point"}
}