{
  "type": "Feature",
  "properties": {
    "addr:full":"8654 Natural Bridge Rd Saint Louis MO 63121",
    "addr:housenumber":"8654",
    "addr:postcode":"63121",
    "addr:street":"Natural Bridge Rd",
    "iso:country":"US",
    "sg:address":"8654 Natural Bridge Rd",
    "sg:city":"Saint Louis",
    "sg:classifiers":[
        {
            "category":"Restaurant",
            "type":"Food & Drink"
        }
    ],
    "sg:menulink":"http://www.allmenus.com/mo/normandy/155452-popeyes-chicken--biscuits/menu/",
    "sg:postcode":"63121",
    "sg:province":"MO",
    "sg:tags":[
        "american",
        "wing"
    ],
    "wof:name":"Popeyes Chicken & Biscuits",
    "wof:placetype":"venue"
},
  "geometry": {"coordinates":[-90.321133,38.7116],"type":"Point"}
}