{
  "type": "Feature",
  "properties": {
    "iso:country":"US",
    "sg:address":"2928 N Euclid Ave",
    "sg:city":"St Louis",
    "sg:classifiers":[
        {
            "category":"Real Estate",
            "subcategory":"Real Estate Agent",
            "type":"Services"
        }
    ],
    "sg:phone":"+1 314 382 6582",
    "sg:postcode":"63115",
    "sg:province":"MO",
    "wof:name":"Harris Group Property Sltns",
    "wof:placetype":"venue"
},
  "geometry": {"coordinates":[-90.252111,38.670943],"type":"Point"}
}