{
  "type": "Feature",
  "properties": {
    "iso:country":"US",
    "sg:address":"12771 Broadridge Ln",
    "sg:city":"Florissant",
    "sg:classifiers":[
        {
            "category":"Banks & Credit Unions",
            "subcategory":"Investment Brokerage",
            "type":"Services"
        }
    ],
    "sg:phone":"+1 314 438 8766",
    "sg:postcode":"63033",
    "sg:province":"MO",
    "wof:name":"Barnes Investment Svc",
    "wof:placetype":"venue"
},
  "geometry": {"coordinates":[-90.264135,38.799004],"type":"Point"}
}