{
  "type": "Feature",
  "properties": {
    "iso:country":"US",
    "sg:address":"555 Saint Josephs Ln",
    "sg:city":"Ballwin",
    "sg:classifiers":[
        {
            "category":"Education",
            "subcategory":"School",
            "type":"Public Place"
        }
    ],
    "sg:phone":"+1 636 391 1253",
    "sg:postcode":"63021",
    "sg:province":"MO",
    "wof:name":"St Joseph Church",
    "wof:placetype":"venue"
},
  "geometry": {"coordinates":[-90.517786,38.586993],"type":"Point"}
}