{
  "type": "Feature",
  "properties": {
    "iso:country":"US",
    "sg:address":"282 N Greenway Dr",
    "sg:city":"Holts Summit",
    "sg:classifiers":[
        {
            "category":"Recreation",
            "type":"Entertainment"
        },
        {
            "category":"Organizations",
            "subcategory":"Community Association",
            "type":"Services"
        }
    ],
    "sg:phone":"+1 573 896 4488",
    "sg:postcode":"65043",
    "sg:province":"MO",
    "sg:tags":[
        "executive",
        "parks"
    ],
    "wof:name":"Holts Summit Civic Association",
    "wof:placetype":"venue"
},
  "geometry": {"coordinates":[-92.121904,38.659746],"type":"Point"}
}