{
  "type": "Feature",
  "properties": {
    "iso:country":"US",
    "sg:address":"4204 Virginia Ave",
    "sg:city":"St Louis",
    "sg:classifiers":[
        {
            "category":"Organizations",
            "subcategory":"Community Association",
            "type":"Services"
        }
    ],
    "sg:phone":"+1 314 352 4865",
    "sg:postcode":"63111",
    "sg:province":"MO",
    "sg:tags":[
        "civic"
    ],
    "wof:name":"Dutchtown South Community Corp",
    "wof:placetype":"venue"
},
  "geometry": {"coordinates":[-90.242,38.577059],"type":"Point"}
}