{
  "type": "Feature",
  "properties": {
    "iso:country":"US",
    "sg:address":"2014 E Malone Ave",
    "sg:city":"Sikeston",
    "sg:classifiers":[
        {
            "category":"Home & Garden",
            "subcategory":"Building Materials",
            "type":"Retail Goods"
        },
        {
            "category":"Home & Garden",
            "subcategory":"Carpets & Floor Coverings",
            "type":"Retail Goods"
        }
    ],
    "sg:phone":"+1 573 471 2376",
    "sg:postcode":"63801",
    "sg:province":"MO",
    "sg:tags":[
        "rug",
        "improvement"
    ],
    "sg:website":"http://www.modernfloorcoverings.com",
    "wof:name":"Modern Floor Coverings",
    "wof:placetype":"venue"
},
  "geometry": {"coordinates":[-89.53196,36.89296],"type":"Point"}
}