{
  "type": "Feature",
  "properties": {
    "iso:country":"US",
    "sg:address":"7622 Wydown Blvd",
    "sg:city":"St Louis",
    "sg:classifiers":[
        {
            "category":"Sports & Exercise",
            "subcategory":"Gym",
            "type":"Entertainment"
        }
    ],
    "sg:phone":"+1 314 727 4489",
    "sg:postcode":"63105",
    "sg:province":"MO",
    "sg:tags":[
        "personal",
        "trainer"
    ],
    "wof:name":"Muscle-Up Fitness",
    "wof:placetype":"venue"
},
  "geometry": {"coordinates":[-90.335021,38.64298],"type":"Point"}
}