{
  "type": "Feature",
  "properties": {
    "iso:country":"US",
    "sg:address":"4706 NE Vivion Rd",
    "sg:city":"Kansas City",
    "sg:classifiers":[
        {
            "category":"Retail",
            "subcategory":"Animal Services",
            "type":"Services"
        }
    ],
    "sg:phone":"+1 816 454 7562",
    "sg:postcode":"64119",
    "sg:province":"MO",
    "sg:tags":[
        "pet",
        "grooming",
        "washing"
    ],
    "wof:name":"Animal Attic II",
    "wof:placetype":"venue"
},
  "geometry": {"coordinates":[-94.52356,39.188076],"type":"Point"}
}