{
  "type": "Feature",
  "properties": {
    "iso:country":"US",
    "sg:address":"2086 Craigshire Rd",
    "sg:city":"St Louis",
    "sg:classifiers":[
        {
            "category":"Professional",
            "subcategory":"Employment Agencies",
            "type":"Services"
        }
    ],
    "sg:phone":"+1 314 434 0076",
    "sg:postcode":"63146",
    "sg:province":"MO",
    "sg:tags":[
        "consultant",
        "search",
        "executive"
    ],
    "wof:name":"Executive Management Group",
    "wof:placetype":"venue"
},
  "geometry": {"coordinates":[-90.44843,38.692612],"type":"Point"}
}