{
  "type": "Feature",
  "properties": {
    "addr:full":"11157 Lindbergh Business Ct St Louis MO 63123",
    "addr:housenumber":"11157",
    "addr:postcode":"63123",
    "addr:street":"Lindbergh Business Ct",
    "iso:country":"US",
    "sg:address":"11157 Lindbergh Business Ct",
    "sg:city":"St Louis",
    "sg:classifiers":[
        {
            "category":"Autos & Motor Vehicles",
            "subcategory":"Automobile Sales",
            "type":"Retail Goods"
        }
    ],
    "sg:phone":"+1 314 892 9600",
    "sg:postcode":"63123",
    "sg:province":"MO",
    "sg:tags":[
        "car",
        "used",
        "dealer",
        "new"
    ],
    "wof:name":"Saturn",
    "wof:placetype":"venue"
},
  "geometry": {"coordinates":[-90.337481,38.516326],"type":"Point"}
}