{
  "type": "Feature",
  "properties": {
    "iso:country":"US",
    "sg:address":"18017 S State Route Y",
    "sg:city":"Belton",
    "sg:classifiers":[
        {
            "category":"Home & Garden",
            "subcategory":"Building Materials",
            "type":"Retail Goods"
        },
        {
            "category":"Building & Trades",
            "subcategory":"Construction",
            "type":"Services"
        }
    ],
    "sg:phone":"+1 816 322 6005",
    "sg:postcode":"64012",
    "sg:province":"MO",
    "sg:tags":[
        "concrete",
        "staining",
        "contractor"
    ],
    "wof:name":"Sb Wyatt Contracting, Inc.",
    "wof:placetype":"venue"
},
  "geometry": {"coordinates":[-94.531751,38.790603],"type":"Point"}
}