{
  "type": "Feature",
  "properties": {
    "iso:country":"US",
    "sg:address":"315 Nichols Rd",
    "sg:city":"Kansas City",
    "sg:classifiers":[
        {
            "category":"Organizations",
            "subcategory":"Professional Association",
            "type":"Services"
        }
    ],
    "sg:phone":"+1 816 531 8432",
    "sg:postcode":"64112",
    "sg:province":"MO",
    "sg:tags":[
        "membership"
    ],
    "wof:name":"Metro Med",
    "wof:placetype":"venue"
},
  "geometry": {"coordinates":[-94.591494,39.041203],"type":"Point"}
}