{
  "type": "Feature",
  "properties": {
    "iso:country":"US",
    "sg:address":"1905 S Ingram Mill Rd",
    "sg:city":"Springfield",
    "sg:classifiers":[
        {
            "category":"Building & Trades",
            "subcategory":"Construction",
            "type":"Services"
        }
    ],
    "sg:phone":"+1 417 886 9538",
    "sg:postcode":"65804",
    "sg:province":"MO",
    "sg:tags":[
        "house",
        "general",
        "contractor"
    ],
    "wof:name":"A W Construction",
    "wof:placetype":"venue"
},
  "geometry": {"coordinates":[-93.22604200000001,37.178337],"type":"Point"}
}