{
  "type": "Feature",
  "properties": {
    "iso:country":"US",
    "sg:address":"7655 W Sugar Creek Dr",
    "sg:city":"Columbia",
    "sg:classifiers":[
        {
            "category":"Manufacturing",
            "subcategory":"Food",
            "type":"Manufacturing & Wholesale Goods"
        }
    ],
    "sg:phone":"+1 573 445 1915",
    "sg:postcode":"65203",
    "sg:province":"MO",
    "sg:tags":[
        "ice"
    ],
    "wof:name":"Tiger Ice Co",
    "wof:placetype":"venue"
},
  "geometry": {"coordinates":[-92.450701,38.970369],"type":"Point"}
}