{
  "type": "Feature",
  "properties": {
    "iso:country":"US",
    "sg:address":"2554 Woodson Rd",
    "sg:city":"Saint Louis",
    "sg:classifiers":[
        {
            "category":"Retail",
            "subcategory":"Repair Shop",
            "type":"Services"
        }
    ],
    "sg:phone":"+1 314 427 2277",
    "sg:postcode":"63114",
    "sg:province":"MO",
    "wof:name":"Pizzas",
    "wof:placetype":"venue"
},
  "geometry": {"coordinates":[-90.361437,38.704945],"type":"Point"}
}