{
  "type": "Feature",
  "properties": {
    "iso:country":"US",
    "sg:address":"5440 Blue Ridge Blvd Cut Off",
    "sg:city":"Raytown",
    "sg:classifiers":[
        {
            "category":"Personal",
            "subcategory":"Beauty Salon",
            "type":"Services"
        }
    ],
    "sg:phone":"+1 816 737 1011",
    "sg:postcode":"64133",
    "sg:province":"MO",
    "wof:name":"Baptist Temple Beauty Salon",
    "wof:placetype":"venue"
},
  "geometry": {"coordinates":[-94.44731,39.022812],"type":"Point"}
}