{
  "type": "Feature",
  "properties": {
    "iso:country":"US",
    "sg:address":"2405 E Truman Rd",
    "sg:city":"Kansas City",
    "sg:classifiers":[
        {
            "category":"Home & Garden",
            "subcategory":"Furniture",
            "type":"Retail Goods"
        }
    ],
    "sg:phone":"+1 816 483 2405",
    "sg:postcode":"64127",
    "sg:province":"MO",
    "sg:tags":[
        "household",
        "bedding"
    ],
    "wof:name":"Gaines Furniture Outlet",
    "wof:placetype":"venue"
},
  "geometry": {"coordinates":[-94.552831,39.094637],"type":"Point"}
}