{
  "type": "Feature",
  "properties": {
    "iso:country":"US",
    "sg:address":"1719 S Main St",
    "sg:city":"Joplin",
    "sg:classifiers":[
        {
            "category":"Restaurant",
            "type":"Food & Drink"
        }
    ],
    "sg:phone":"+1 417 781 5341",
    "sg:postcode":"64804",
    "sg:province":"MO",
    "sg:tags":[
        "eating"
    ],
    "wof:name":"Fred & Reds Chili House",
    "wof:placetype":"venue"
},
  "geometry": {"coordinates":[-94.51394999999999,37.072094],"type":"Point"}
}