{
  "type": "Feature",
  "properties": {
    "iso:country":"US",
    "sg:address":"4321 Washington St",
    "sg:city":"Kansas City",
    "sg:classifiers":[
        {
            "category":"Health Services",
            "subcategory":"Doctor",
            "type":"Services"
        }
    ],
    "sg:phone":"+1 816 756 2255",
    "sg:postcode":"64111",
    "sg:province":"MO",
    "sg:tags":[
        "medical",
        "clinic"
    ],
    "wof:name":"MPclinical Research",
    "wof:placetype":"venue"
},
  "geometry": {"coordinates":[-94.591999,39.048995],"type":"Point"}
}