{
  "type": "Feature",
  "properties": {
    "iso:country":"US",
    "sg:address":"139 E Holden Ave",
    "sg:city":"Saint Louis",
    "sg:classifiers":[
        {
            "category":"Building & Trades",
            "subcategory":"Construction",
            "type":"Services"
        }
    ],
    "sg:phone":"+1 314 638 3398",
    "sg:postcode":"63125",
    "sg:province":"MO",
    "sg:tags":[
        "contractor"
    ],
    "wof:name":"Ziegler Contracting Inc",
    "wof:placetype":"venue"
},
  "geometry": {"coordinates":[-90.275598,38.528974],"type":"Point"}
}