{
  "type": "Feature",
  "properties": {
    "iso:country":"US",
    "sg:address":"510 Glenmeadow Dr",
    "sg:city":"Ballwin",
    "sg:classifiers":[
        {
            "category":"Health Services",
            "subcategory":"Health Practitioner",
            "type":"Services"
        }
    ],
    "sg:phone":"+1 314 862 1500",
    "sg:postcode":"63011",
    "sg:province":"MO",
    "wof:name":"Carnoske Professional Services",
    "wof:placetype":"venue"
},
  "geometry": {"coordinates":[-90.52152,38.610152],"type":"Point"}
}