{
  "type": "Feature",
  "properties": {
    "iso:country":"US",
    "sg:address":"9428 Lackland Rd",
    "sg:city":"Overland",
    "sg:classifiers":[
        {
            "category":"Professional",
            "subcategory":"Accounting & Tax Preparation",
            "type":"Services"
        }
    ],
    "sg:phone":"+1 314 426 1480",
    "sg:postcode":"63114",
    "sg:province":"MO",
    "sg:tags":[
        "accountant"
    ],
    "wof:name":"Brown Renshaw & Co",
    "wof:placetype":"venue"
},
  "geometry": {"coordinates":[-90.36245700000001,38.700338],"type":"Point"}
}