{
  "type": "Feature",
  "properties": {
    "iso:country":"US",
    "sg:address":"5050 Oakland Ave",
    "sg:city":"St Louis",
    "sg:classifiers":[
        {
            "category":"Professional",
            "subcategory":"Management & Consulting",
            "type":"Services"
        }
    ],
    "sg:phone":"+1 314 534 7730",
    "sg:postcode":"63110",
    "sg:province":"MO",
    "sg:tags":[
        "food"
    ],
    "wof:name":"Centerplate",
    "wof:placetype":"venue"
},
  "geometry": {"coordinates":[-90.26634799999999,38.628931],"type":"Point"}
}