{
  "type": "Feature",
  "properties": {
    "iso:country":"US",
    "sg:address":"907 Stokelan Dr",
    "sg:city":"Malden",
    "sg:classifiers":[
        {
            "category":"Building & Trades",
            "subcategory":"Construction",
            "type":"Services"
        }
    ],
    "sg:phone":"+1 573 276 5557",
    "sg:postcode":"63863",
    "sg:province":"MO",
    "sg:tags":[
        "house"
    ],
    "wof:name":"Marchbanks Construction",
    "wof:placetype":"venue"
},
  "geometry": {"coordinates":[-89.975275,36.569331],"type":"Point"}
}