{
  "type": "Feature",
  "properties": {
    "iso:country":"US",
    "sg:address":"614 E 9th St",
    "sg:city":"Trenton",
    "sg:classifiers":[
        {
            "category":"Health Services",
            "subcategory":"Optometrist",
            "type":"Services"
        },
        {
            "category":"Shopping",
            "subcategory":"Optical Goods",
            "type":"Retail Goods"
        }
    ],
    "sg:phone":"+1 660 359 3957",
    "sg:postcode":"64683",
    "sg:province":"MO",
    "sg:tags":[
        "lens",
        "contact"
    ],
    "sg:website":"http://www.premiereyecare.biz",
    "wof:name":"Premier Eyecare Associates",
    "wof:placetype":"venue"
},
  "geometry": {"coordinates":[-93.612405,40.074465],"type":"Point"}
}