{
  "type": "Feature",
  "properties": {
    "iso:country":"US",
    "sg:address":"338 Broadway St",
    "sg:city":"Cape Girardeau",
    "sg:classifiers":[
        {
            "category":"Restaurant",
            "type":"Food & Drink"
        }
    ],
    "sg:phone":"+1 573 651 0050",
    "sg:postcode":"63701",
    "sg:province":"MO",
    "wof:name":"Gatherings Cafe & Bakery",
    "wof:placetype":"venue"
},
  "geometry": {"coordinates":[-89.52163,37.306302],"type":"Point"}
}