{
  "type": "Feature",
  "properties": {
    "iso:country":"US",
    "sg:address":"301 Court St",
    "sg:city":"Fulton",
    "sg:classifiers":[
        {
            "category":"Government",
            "subcategory":"Post Office",
            "type":"Public Place"
        }
    ],
    "sg:phone":"+1 573 642 7788",
    "sg:postcode":"65251",
    "sg:province":"MO",
    "sg:tags":[
        "postal",
        "us"
    ],
    "wof:name":"US Post Office",
    "wof:placetype":"venue"
},
  "geometry": {"coordinates":[-91.948021,38.846646],"type":"Point"}
}