{
  "type": "Feature",
  "properties": {
    "iso:country":"US",
    "sg:address":"2460 N Truman Blvd",
    "sg:city":"Crystal City",
    "sg:classifiers":[
        {
            "category":"Wholesale",
            "subcategory":"Electrical",
            "type":"Manufacturing & Wholesale Goods"
        }
    ],
    "sg:phone":"+1 636 937 9444",
    "sg:postcode":"63019",
    "sg:province":"MO",
    "sg:tags":[
        "equipment"
    ],
    "wof:name":"Butler Supply Inc",
    "wof:placetype":"venue"
},
  "geometry": {"coordinates":[-90.39610999999999,38.243598],"type":"Point"}
}