{
  "type": "Feature",
  "properties": {
    "iso:country":"US",
    "sg:address":"1339 Hawthorne Rd",
    "sg:city":"Highlandville",
    "sg:classifiers":[
        {
            "category":"Building & Trades",
            "subcategory":"Construction",
            "type":"Services"
        }
    ],
    "sg:phone":"+1 417 839 7148",
    "sg:postcode":"65669",
    "sg:province":"MO",
    "sg:tags":[
        "carpenter"
    ],
    "wof:name":"J And M Custom Carpentry",
    "wof:placetype":"venue"
},
  "geometry": {"coordinates":[-93.307907,36.903993],"type":"Point"}
}