{
  "type": "Feature",
  "properties": {
    "iso:country":"US",
    "sg:address":"1920 E Kearney St",
    "sg:city":"Springfield",
    "sg:classifiers":[
        {
            "category":"Shopping",
            "subcategory":"Department Store",
            "type":"Retail Goods"
        },
        {
            "category":"Shopping",
            "subcategory":"Clothing, Apparel, & Fashions",
            "type":"Retail Goods"
        },
        {
            "category":"Shopping",
            "type":"Retail Goods"
        },
        {
            "category":"Shopping",
            "subcategory":"Discount & Variety Stores",
            "type":"Retail Goods"
        }
    ],
    "sg:phone":"+1 417 865 1250",
    "sg:postcode":"65803",
    "sg:province":"MO",
    "sg:tags":[
        "clothing",
        "merchandise"
    ],
    "sg:website":"http://www.walmart.com",
    "wof:name":"Wal-Mart",
    "wof:placetype":"venue"
},
  "geometry": {"coordinates":[-93.316208,37.241032],"type":"Point"}
}