{
  "type": "Feature",
  "properties": {
    "iso:country":"US",
    "sg:address":"4031 Botanical Ave",
    "sg:city":"Saint Louis",
    "sg:classifiers":[
        {
            "category":"Shopping",
            "subcategory":"Clothing, Apparel, & Fashions",
            "type":"Retail Goods"
        }
    ],
    "sg:phone":"+1 314 772 0827",
    "sg:postcode":"63110",
    "sg:province":"MO",
    "sg:tags":[
        "design",
        "commercial"
    ],
    "wof:name":"Simon Seyz Jeans Company",
    "wof:placetype":"venue"
},
  "geometry": {"coordinates":[-90.250811,38.609701],"type":"Point"}
}