{
  "type": "Feature",
  "properties": {
    "iso:country":"US",
    "sg:address":"422 Brooks Glen Ct",
    "sg:city":"Ballwin",
    "sg:classifiers":[
        {
            "category":"Professional",
            "subcategory":"Employment Agencies",
            "type":"Services"
        }
    ],
    "sg:phone":"+1 636 394 8155",
    "sg:postcode":"63021",
    "sg:province":"MO",
    "sg:tags":[
        "recruitment",
        "university",
        "co",
        "staffing",
        "relations"
    ],
    "wof:name":"Martinez Group Inc The",
    "wof:placetype":"venue"
},
  "geometry": {"coordinates":[-90.54721000000001,38.563005],"type":"Point"}
}