{
  "type": "Feature",
  "properties": {
    "iso:country":"US",
    "sg:address":"925 Wilderness Ct",
    "sg:city":"Liberty",
    "sg:classifiers":[
        {
            "category":"Travel",
            "subcategory":"Travel Agent",
            "type":"Entertainment"
        }
    ],
    "sg:phone":"+1 816 792 3388",
    "sg:postcode":"64068",
    "sg:province":"MO",
    "sg:tags":[
        "agency",
        "bureau"
    ],
    "wof:name":"Travel Quest",
    "wof:placetype":"venue"
},
  "geometry": {"coordinates":[-94.404628,39.209532],"type":"Point"}
}