{
  "type": "Feature",
  "properties": {
    "iso:country":"US",
    "sg:address":"107 Hwy O",
    "sg:city":"Laurie",
    "sg:classifiers":[
        {
            "category":"Bars & Pubs",
            "type":"Food & Drink"
        }
    ],
    "sg:phone":"+1 573 374 9973",
    "sg:postcode":"65037",
    "sg:province":"MO",
    "sg:tags":[
        "lounge",
        "cocktail"
    ],
    "wof:name":"Marz Pizza & Venus Lounge",
    "wof:placetype":"venue"
},
  "geometry": {"coordinates":[-92.833631,38.199157],"type":"Point"}
}