{
  "type": "Feature",
  "properties": {
    "iso:country":"US",
    "sg:address":"9902 E 62nd St",
    "sg:city":"Raytown",
    "sg:classifiers":[
        {
            "category":"Building & Trades",
            "subcategory":"Construction",
            "type":"Services"
        },
        {
            "category":"Home & Garden",
            "subcategory":"Carpets & Floor Coverings",
            "type":"Retail Goods"
        }
    ],
    "sg:phone":"+1 816 358 2440",
    "sg:postcode":"64133",
    "sg:province":"MO",
    "sg:tags":[
        "material",
        "specialty",
        "flooring",
        "contractor"
    ],
    "wof:name":"Floor Layers Local Union 1179",
    "wof:placetype":"venue"
},
  "geometry": {"coordinates":[-94.46413200000001,39.011139],"type":"Point"}
}