{
  "type": "Feature",
  "properties": {
    "iso:country":"US",
    "sg:address":"1009 US Hwy 60",
    "sg:city":"Van Buren",
    "sg:classifiers":[
        {
            "category":"Health Services",
            "subcategory":"Doctor",
            "type":"Services"
        }
    ],
    "sg:phone":"+1 573 323 4812",
    "sg:postcode":"63901",
    "sg:province":"MO",
    "sg:tags":[
        "physician",
        "surgeon"
    ],
    "wof:name":"Shannon County Medical Clinic",
    "wof:placetype":"venue"
},
  "geometry": {"coordinates":[-90.319345,36.793523],"type":"Point"}
}