{
  "type": "Feature",
  "properties": {
    "iso:country":"US",
    "sg:address":"3800 Park Ave",
    "sg:city":"Saint Louis",
    "sg:classifiers":[
        {
            "category":"Manufacturing",
            "subcategory":"Printing",
            "type":"Manufacturing & Wholesale Goods"
        }
    ],
    "sg:phone":"+1 314 776 6666",
    "sg:postcode":"63110",
    "sg:province":"MO",
    "sg:tags":[
        "development",
        "software",
        "digital",
        "internet"
    ],
    "wof:name":"Mira Digital Publishing",
    "wof:placetype":"venue"
},
  "geometry": {"coordinates":[-90.24441899999999,38.621286],"type":"Point"}
}