{
  "type": "Feature",
  "properties": {
    "iso:country":"US",
    "sg:address":"13108 Butler Oak Dr",
    "sg:city":"Saint Louis",
    "sg:classifiers":[
        {
            "category":"Real Estate",
            "subcategory":"Real Estate Operator",
            "type":"Services"
        }
    ],
    "sg:phone":"+1 314 842 4781",
    "sg:postcode":"63128",
    "sg:province":"MO",
    "sg:tags":[
        "building",
        "apartment"
    ],
    "wof:name":"Butler Hill Apts",
    "wof:placetype":"venue"
},
  "geometry": {"coordinates":[-90.380683,38.491983],"type":"Point"}
}