{
  "type": "Feature",
  "properties": {
    "iso:country":"US",
    "sg:address":"1645 SE Decker",
    "sg:city":"Lees Summit",
    "sg:classifiers":[
        {
            "category":"Wholesale",
            "subcategory":"Farm Supplies",
            "type":"Manufacturing & Wholesale Goods"
        }
    ],
    "sg:phone":"+1 816 524 0840",
    "sg:postcode":"64081",
    "sg:province":"MO",
    "sg:tags":[
        "bulb",
        "seed"
    ],
    "sg:website":"www.stuifbergenbulb.com",
    "wof:name":"Pete Stuifbergen Bulb Import",
    "wof:placetype":"venue"
},
  "geometry": {"coordinates":[-94.371594,38.89159],"type":"Point"}
}