{
  "type": "Feature",
  "properties": {
    "iso:country":"US",
    "sg:address":"4333 Butler Hill Rd",
    "sg:city":"St Louis",
    "sg:classifiers":[
        {
            "category":"Food & Beverages",
            "subcategory":"Groceries & Convenience Stores",
            "type":"Retail Goods"
        },
        {
            "category":"Shopping",
            "subcategory":"Pharmacy",
            "type":"Retail Goods"
        }
    ],
    "sg:phone":"+1 314 894 1227",
    "sg:postcode":"63128",
    "sg:province":"MO",
    "sg:tags":[
        "grocer",
        "eating"
    ],
    "wof:name":"Schnucks",
    "wof:placetype":"venue"
},
  "geometry": {"coordinates":[-90.35803,38.485762],"type":"Point"}
}