{
  "type": "Feature",
  "properties": {
    "iso:country":"US",
    "sg:address":"11674 Gravois Rd",
    "sg:city":"Saint Louis",
    "sg:classifiers":[
        {
            "category":"Wholesale",
            "subcategory":"Vending Machines",
            "type":"Manufacturing & Wholesale Goods"
        }
    ],
    "sg:phone":"+1 314 843 2200",
    "sg:postcode":"63126",
    "sg:province":"MO",
    "sg:tags":[
        "automatic",
        "merchandise"
    ],
    "wof:name":"Saint Louis Vendors Inc",
    "wof:placetype":"venue"
},
  "geometry": {"coordinates":[-90.384411,38.533151],"type":"Point"}
}