{
  "type": "Feature",
  "properties": {
    "iso:country":"US",
    "sg:address":"695 Villar St",
    "sg:city":"Sainte Genevieve",
    "sg:classifiers":[
        {
            "category":"Professional",
            "type":"Services"
        }
    ],
    "sg:phone":"+1 573 883 3267",
    "sg:postcode":"63645",
    "sg:province":"MO",
    "wof:name":"Absolute Disposal",
    "wof:placetype":"venue"
},
  "geometry": {"coordinates":[-90.293133,37.568507],"type":"Point"}
}