{
  "type": "Feature",
  "properties": {
    "iso:country":"US",
    "sg:address":"14786 Manchester Rd",
    "sg:city":"Ballwin",
    "sg:classifiers":[
        {
            "category":"Professional",
            "subcategory":"Business Services",
            "type":"Services"
        }
    ],
    "sg:phone":"+1 636 256 8100",
    "sg:postcode":"63011",
    "sg:province":"MO",
    "sg:tags":[
        "interior",
        "consultant",
        "design",
        "decorator"
    ],
    "wof:name":"Interior Accents Gallery",
    "wof:placetype":"venue"
},
  "geometry": {"coordinates":[-90.53521499999999,38.592926],"type":"Point"}
}