{
  "type": "Feature",
  "properties": {
    "iso:country":"US",
    "sg:address":"7440 N Lindbergh Blvd",
    "sg:city":"Hazelwood",
    "sg:classifiers":[
        {
            "category":"Food & Beverages",
            "subcategory":"Bakery",
            "type":"Retail Goods"
        }
    ],
    "sg:phone":"+1 314 831 5695",
    "sg:postcode":"63042",
    "sg:province":"MO",
    "wof:name":"Yum Yum Donut Shop",
    "wof:placetype":"venue"
},
  "geometry": {"coordinates":[-90.353478,38.784882],"type":"Point"}
}