{
  "type": "Feature",
  "properties": {
    "iso:country":"US",
    "sg:address":"1007 Kingshighway St",
    "sg:city":"Rolla",
    "sg:classifiers":[
        {
            "category":"Restaurant",
            "type":"Food & Drink"
        }
    ],
    "sg:menulink":"http://www.allmenus.com/mo/rolla/182074-wendys/menu/",
    "sg:phone":"+1 573 364 5500",
    "sg:postcode":"65401",
    "sg:province":"MO",
    "sg:tags":[
        "burger",
        "american",
        "soup"
    ],
    "wof:name":"Wendy's",
    "wof:placetype":"venue"
},
  "geometry": {"coordinates":[-91.77909699999999,37.946211],"type":"Point"}
}