{
  "type": "Feature",
  "properties": {
    "iso:country":"US",
    "sg:address":"3954 S Broadway",
    "sg:city":"Saint Louis",
    "sg:classifiers":[
        {
            "category":"Restaurant",
            "type":"Food & Drink"
        }
    ],
    "sg:phone":"+1 314 776 5400",
    "sg:postcode":"63118",
    "sg:province":"MO",
    "sg:tags":[
        "chinese"
    ],
    "wof:name":"China King",
    "wof:placetype":"venue"
},
  "geometry": {"coordinates":[-90.22761199999999,38.58301],"type":"Point"}
}