{
  "type": "Feature",
  "properties": {
    "iso:country":"US",
    "sg:address":"1904 Telegraph Rd",
    "sg:city":"Saint Louis",
    "sg:classifiers":[
        {
            "category":"Real Estate",
            "subcategory":"Real Estate Agent",
            "type":"Services"
        }
    ],
    "sg:phone":"+1 314 544 2302",
    "sg:postcode":"63125",
    "sg:province":"MO",
    "wof:name":"Bill Schliebe Real Est",
    "wof:placetype":"venue"
},
  "geometry": {"coordinates":[-90.28553700000001,38.525942],"type":"Point"}
}