{
  "type": "Feature",
  "properties": {
    "iso:country":"US",
    "sg:address":"201 Slack St",
    "sg:city":"Chillicothe",
    "sg:classifiers":[
        {
            "category":"Building & Trades",
            "subcategory":"Plumbing",
            "type":"Services"
        }
    ],
    "sg:phone":"+1 660 646 4868",
    "sg:postcode":"64601",
    "sg:province":"MO",
    "sg:tags":[
        "contractor"
    ],
    "wof:name":"Hess Heating & Cooling Inc",
    "wof:placetype":"venue"
},
  "geometry": {"coordinates":[-93.549171,39.788909],"type":"Point"}
}