{
  "type": "Feature",
  "properties": {
    "iso:country":"US",
    "sg:address":"372 NW 110th St",
    "sg:city":"Spickard",
    "sg:classifiers":[
        {
            "category":"Farming",
            "subcategory":"Dairy Farm",
            "type":"Manufacturing & Wholesale Goods"
        }
    ],
    "sg:phone":"+1 660 485 6256",
    "sg:postcode":"64679",
    "sg:province":"MO",
    "wof:name":"Jack Lovell",
    "wof:placetype":"venue"
},
  "geometry": {"coordinates":[-93.675281,40.234277],"type":"Point"}
}