{
  "type": "Feature",
  "properties": {
    "iso:country":"US",
    "sg:address":"9229 E Truman Rd",
    "sg:city":"Independence",
    "sg:classifiers":[
        {
            "category":"Organizations",
            "subcategory":"Non-profit Organization",
            "type":"Services"
        }
    ],
    "sg:phone":"+1 816 833 6400",
    "sg:postcode":"64052",
    "sg:province":"MO",
    "sg:tags":[
        "info",
        "addiction",
        "abuse",
        "treatment",
        "drug"
    ],
    "wof:name":"Addiction Recovery Svc",
    "wof:placetype":"venue"
},
  "geometry": {"coordinates":[-94.47024999999999,39.093959],"type":"Point"}
}