{
  "type": "Feature",
  "properties": {
    "iso:country":"US",
    "sg:address":"101 State Hwy 72",
    "sg:city":"Rolla",
    "sg:classifiers":[
        {
            "category":"Food & Beverages",
            "subcategory":"Groceries & Convenience Stores",
            "type":"Retail Goods"
        }
    ],
    "sg:phone":"+1 573 364 2402",
    "sg:postcode":"65401",
    "sg:province":"MO",
    "wof:name":"Delano Station Break 72",
    "wof:placetype":"venue"
},
  "geometry": {"coordinates":[-91.771123,37.942403],"type":"Point"}
}