{
  "type": "Feature",
  "properties": {
    "iso:country":"US",
    "sg:address":"3330 Sunset Dr",
    "sg:city":"Joplin",
    "sg:classifiers":[
        {
            "category":"Professional",
            "type":"Services"
        }
    ],
    "sg:phone":"+1 417 206 2249",
    "sg:postcode":"64804",
    "sg:province":"MO",
    "wof:name":"Wendy Vrooman",
    "wof:placetype":"venue"
},
  "geometry": {"coordinates":[-94.55415499999999,37.058585],"type":"Point"}
}