{
  "type": "Feature",
  "properties": {
    "iso:country":"US",
    "sg:address":"700 E Highway 72",
    "sg:city":"Fredericktown",
    "sg:classifiers":[
        {
            "category":"Freight",
            "type":"Transportation"
        },
        {
            "category":"Local Transit",
            "type":"Transportation"
        }
    ],
    "sg:phone":"+1 573 783 5505",
    "sg:postcode":"63645",
    "sg:province":"MO",
    "sg:tags":[
        "bus",
        "line",
        "public",
        "trucking"
    ],
    "wof:name":"Southeast Missouri Transportation Service",
    "wof:placetype":"venue"
},
  "geometry": {"coordinates":[-90.280584,37.567528],"type":"Point"}
}