{
  "type": "Feature",
  "properties": {
    "iso:country":"US",
    "sg:address":"306 W 6th St",
    "sg:city":"Tina",
    "sg:classifiers":[
        {
            "category":"Manufacturing",
            "subcategory":"Food",
            "type":"Manufacturing & Wholesale Goods"
        }
    ],
    "sg:phone":"+1 660 622 4482",
    "sg:postcode":"64682",
    "sg:province":"MO",
    "sg:tags":[
        "product"
    ],
    "wof:name":"Willard Todd",
    "wof:placetype":"venue"
},
  "geometry": {"coordinates":[-93.442882,39.541549],"type":"Point"}
}