{
  "type": "Feature",
  "properties": {
    "iso:country":"US",
    "sg:address":"1022 Lindenwood Ln",
    "sg:city":"Liberty",
    "sg:classifiers":[
        {
            "category":"Wholesale",
            "subcategory":"Electrical",
            "type":"Manufacturing & Wholesale Goods"
        }
    ],
    "sg:phone":"+1 816 781 3770",
    "sg:postcode":"64068",
    "sg:province":"MO",
    "sg:tags":[
        "cell",
        "photo",
        "electric",
        "equipment"
    ],
    "wof:name":"Custom Industrial Controls Inc",
    "wof:placetype":"venue"
},
  "geometry": {"coordinates":[-94.44205599999999,39.232491],"type":"Point"}
}