{
  "type": "Feature",
  "properties": {
    "iso:country":"US",
    "sg:address":"160 Proverbs Ct",
    "sg:city":"Forsyth",
    "sg:classifiers":[
        {
            "category":"Building & Trades",
            "subcategory":"Landscaping Services",
            "type":"Services"
        }
    ],
    "sg:phone":"+1 417 230 9555",
    "sg:postcode":"65653",
    "sg:province":"MO",
    "sg:tags":[
        "lawn",
        "maintenance"
    ],
    "wof:name":"Wages Lawn Care",
    "wof:placetype":"venue"
},
  "geometry": {"coordinates":[-93.096999,36.667245],"type":"Point"}
}