{
  "type": "Feature",
  "properties": {
    "iso:country":"US",
    "sg:address":"7721 Hwy H",
    "sg:city":"Gerald",
    "sg:classifiers":[
        {
            "category":"Building & Trades",
            "subcategory":"Construction",
            "type":"Services"
        }
    ],
    "sg:phone":"+1 573 764 2696",
    "sg:postcode":"63037",
    "sg:province":"MO",
    "sg:tags":[
        "concrete",
        "contractor"
    ],
    "wof:name":"Trowell Cement",
    "wof:placetype":"venue"
},
  "geometry": {"coordinates":[-91.32302799999999,38.38228],"type":"Point"}
}