{
  "type": "Feature",
  "properties": {
    "iso:country":"US",
    "sg:address":"501 S Park Ave",
    "sg:city":"Fayette",
    "sg:classifiers":[
        {
            "category":"Health Services",
            "subcategory":"Nursing And Care Facility",
            "type":"Services"
        },
        {
            "category":"Professional",
            "subcategory":"Business Services",
            "type":"Services"
        }
    ],
    "sg:phone":"+1 660 248 3371",
    "sg:postcode":"65248",
    "sg:province":"MO",
    "sg:tags":[
        "home",
        "convalescent"
    ],
    "wof:name":"Fayette Caring Center",
    "wof:placetype":"venue"
},
  "geometry": {"coordinates":[-92.686892,39.138964],"type":"Point"}
}