{
  "type": "Feature",
  "properties": {
    "iso:country":"US",
    "sg:address":"612 Nirk Ave",
    "sg:city":"Saint Louis",
    "sg:classifiers":[
        {
            "category":"Shopping",
            "type":"Retail Goods"
        }
    ],
    "sg:phone":"+1 314 966 0663",
    "sg:postcode":"63122",
    "sg:province":"MO",
    "sg:tags":[
        "merchandise"
    ],
    "wof:name":"House of Wallace",
    "wof:placetype":"venue"
},
  "geometry": {"coordinates":[-90.420784,38.576373],"type":"Point"}
}