{
  "type": "Feature",
  "properties": {
    "iso:country":"US",
    "sg:address":"1916 SW 200th Rd",
    "sg:city":"Kingsville",
    "sg:classifiers":[
        {
            "category":"Professional",
            "subcategory":"Computer Services",
            "type":"Services"
        }
    ],
    "sg:phone":"+1 816 720 3387",
    "sg:postcode":"64061",
    "sg:province":"MO",
    "sg:tags":[
        "related"
    ],
    "wof:name":"Anderson Consulting Services",
    "wof:placetype":"venue"
},
  "geometry": {"coordinates":[-94.105198,38.744175],"type":"Point"}
}