{
  "type": "Feature",
  "properties": {
    "iso:country":"US",
    "sg:address":"102 N Locust St",
    "sg:city":"Oak Grove",
    "sg:classifiers":[
        {
            "category":"Autos & Motor Vehicles",
            "subcategory":"Boat Sales",
            "type":"Retail Goods"
        }
    ],
    "sg:phone":"+1 816 690 0020",
    "sg:postcode":"64075",
    "sg:province":"MO",
    "sg:tags":[
        "dealer",
        "sales"
    ],
    "wof:name":"Xtreme Marine",
    "wof:placetype":"venue"
},
  "geometry": {"coordinates":[-94.133197,39.016889],"type":"Point"}
}