{
  "type": "Feature",
  "properties": {
    "iso:country":"US",
    "sg:address":"209 W Arthur St",
    "sg:city":"Farber",
    "sg:classifiers":[
        {
            "category":"Freight",
            "type":"Transportation"
        }
    ],
    "sg:phone":"+1 573 249 2350",
    "sg:postcode":"63345",
    "sg:province":"MO",
    "sg:tags":[
        "provider"
    ],
    "wof:name":"Scotts Transportation",
    "wof:placetype":"venue"
},
  "geometry": {"coordinates":[-91.578568,39.274014],"type":"Point"}
}