{
  "type": "Feature",
  "properties": {
    "iso:country":"US",
    "sg:address":"1201 Stacey St",
    "sg:city":"Seymour",
    "sg:classifiers":[
        {
            "category":"Professional",
            "subcategory":"Computer Services",
            "type":"Services"
        }
    ],
    "sg:phone":"+1 417 935 2260",
    "sg:postcode":"65746",
    "sg:province":"MO",
    "sg:tags":[
        "isp",
        "provider",
        "internet"
    ],
    "sg:website":"http://www.ptcavaness.com",
    "wof:name":"Organic Bedding & More",
    "wof:placetype":"venue"
},
  "geometry": {"coordinates":[-92.78376799999999,37.14481],"type":"Point"}
}