{
  "type": "Feature",
  "properties": {
    "iso:country":"US",
    "sg:address":"2731 Hwy 100",
    "sg:city":"Gray Summit",
    "sg:classifiers":[
        {
            "category":"Real Estate",
            "subcategory":"Real Estate Operator",
            "type":"Services"
        }
    ],
    "sg:phone":"+1 636 742 6006",
    "sg:postcode":"63039",
    "sg:province":"MO",
    "sg:tags":[
        "apartment"
    ],
    "wof:name":"Daniel Boone Inn & Suites",
    "wof:placetype":"venue"
},
  "geometry": {"coordinates":[-90.82252099999999,38.484481],"type":"Point"}
}