{
  "type": "Feature",
  "properties": {
    "iso:country":"US",
    "sg:address":"12456 Manchester Ave",
    "sg:city":"Grandview",
    "sg:classifiers":[
        {
            "category":"Shopping",
            "subcategory":"Clothing, Apparel, & Fashions",
            "type":"Retail Goods"
        }
    ],
    "sg:phone":"+1 816 765 2401",
    "sg:postcode":"64030",
    "sg:province":"MO",
    "wof:name":"Julie's Family Wear",
    "wof:placetype":"venue"
},
  "geometry": {"coordinates":[-94.502852,38.897977],"type":"Point"}
}