{
  "type": "Feature",
  "properties": {
    "iso:country":"US",
    "sg:address":"206 N Mill St",
    "sg:city":"Vienna",
    "sg:classifiers":[
        {
            "category":"Personal",
            "subcategory":"Beauty Salon",
            "type":"Services"
        }
    ],
    "sg:phone":"+1 573 422 6060",
    "sg:postcode":"65582",
    "sg:province":"MO",
    "sg:tags":[
        "hair",
        "stylist"
    ],
    "wof:name":"Classic Cuts",
    "wof:placetype":"venue"
},
  "geometry": {"coordinates":[-91.94606,38.186977],"type":"Point"}
}