{
  "type": "Feature",
  "properties": {
    "iso:country":"US",
    "sg:address":"561 Dogwood Rd",
    "sg:city":"Lake Ozark",
    "sg:classifiers":[
        {
            "category":"Marine",
            "type":"Transportation"
        }
    ],
    "sg:phone":"+1 573 365 5023",
    "sg:postcode":"65049",
    "sg:province":"MO",
    "sg:tags":[
        "water",
        "transport"
    ],
    "wof:name":"Lakeside Marine Transport",
    "wof:placetype":"venue"
},
  "geometry": {"coordinates":[-92.69183700000001,38.206112],"type":"Point"}
}