{
  "type": "Feature",
  "properties": {
    "iso:country":"US",
    "sg:address":"331 De Baliviere Ave",
    "sg:city":"Saint Louis",
    "sg:classifiers":[
        {
            "category":"Health Services",
            "subcategory":"Dentist",
            "type":"Services"
        }
    ],
    "sg:phone":"+1 314 454 0888",
    "sg:postcode":"63112",
    "sg:province":"MO",
    "wof:name":"Davis Dental Care",
    "wof:placetype":"venue"
},
  "geometry": {"coordinates":[-90.285202,38.6497],"type":"Point"}
}