{
  "type": "Feature",
  "properties": {
    "iso:country":"US",
    "sg:address":"2800 E State Highway 76",
    "sg:city":"Branson",
    "sg:classifiers":[
        {
            "category":"Restaurant",
            "type":"Food & Drink"
        }
    ],
    "sg:menulink":"http://www.allmenus.com/mo/branson/182652-mels-hard-luck-diner/menu/",
    "sg:phone":"+1 417 332 0150",
    "sg:postcode":"65616",
    "sg:province":"MO",
    "sg:tags":[
        "american"
    ],
    "wof:name":"Mel's Hard Luck Diner",
    "wof:placetype":"venue"
},
  "geometry": {"coordinates":[-93.26968100000001,36.638738],"type":"Point"}
}