{
  "type": "Feature",
  "properties": {
    "iso:country":"US",
    "sg:address":"901 N 1st St",
    "sg:city":"Saint Louis",
    "sg:classifiers":[
        {
            "category":"Travel",
            "subcategory":"Hotels & Motels",
            "type":"Entertainment"
        }
    ],
    "sg:phone":"+1 972 444 4900",
    "sg:postcode":"63102",
    "sg:province":"MO",
    "sg:tags":[
        "operation"
    ],
    "wof:name":"Embassy Suites",
    "wof:placetype":"venue"
},
  "geometry": {"coordinates":[-90.18273600000001,38.633007],"type":"Point"}
}