{
  "type": "Feature",
  "properties": {
    "iso:country":"US",
    "sg:address":"861 State Rd Mm",
    "sg:city":"Holts Summit",
    "sg:classifiers":[
        {
            "category":"Building & Trades",
            "subcategory":"Construction",
            "type":"Services"
        }
    ],
    "sg:phone":"+1 573 491 4132",
    "sg:postcode":"65063",
    "sg:province":"MO",
    "sg:tags":[
        "house",
        "contractor",
        "concrete"
    ],
    "wof:name":"Crocker Construction",
    "wof:placetype":"venue"
},
  "geometry": {"coordinates":[-92.185908,38.706509],"type":"Point"}
}