{
  "type": "Feature",
  "properties": {
    "iso:country":"US",
    "sg:address":"472 Paul Ave",
    "sg:city":"Ferguson",
    "sg:classifiers":[
        {
            "category":"Wholesale",
            "subcategory":"Metals & Minerals",
            "type":"Manufacturing & Wholesale Goods"
        }
    ],
    "sg:phone":"+1 314 524 1900",
    "sg:postcode":"63135",
    "sg:province":"MO",
    "sg:tags":[
        "pipe"
    ],
    "sg:website":"www.permalok.com",
    "wof:name":"Permalok Corp",
    "wof:placetype":"venue"
},
  "geometry": {"coordinates":[-90.296019,38.738846],"type":"Point"}
}