{
  "type": "Feature",
  "properties": {
    "iso:country":"US",
    "sg:address":"1709 Doubet Rd",
    "sg:city":"Farmington",
    "sg:classifiers":[
        {
            "category":"Manufacturing",
            "subcategory":"Tools & Machinery",
            "type":"Manufacturing & Wholesale Goods"
        }
    ],
    "sg:phone":"+1 573 756 3255",
    "sg:postcode":"63640",
    "sg:province":"MO",
    "sg:tags":[
        "machine",
        "shop"
    ],
    "wof:name":"Farmington Machine Shop",
    "wof:placetype":"venue"
},
  "geometry": {"coordinates":[-90.435658,37.764514],"type":"Point"}
}