{
  "type": "Feature",
  "properties": {
    "iso:country":"US",
    "sg:address":"510 2nd St",
    "sg:city":"Annapolis",
    "sg:classifiers":[
        {
            "category":"Social Services",
            "subcategory":"Adult Care",
            "type":"Services"
        }
    ],
    "sg:phone":"+1 573 598 4202",
    "sg:postcode":"63620",
    "sg:province":"MO",
    "sg:tags":[
        "home",
        "residential"
    ],
    "wof:name":"Patricia's Residential Care",
    "wof:placetype":"venue"
},
  "geometry": {"coordinates":[-90.694171,37.360268],"type":"Point"}
}