{
  "type": "Feature",
  "properties": {
    "iso:country":"US",
    "sg:address":"1010 State Hwy Z",
    "sg:city":"Bates City",
    "sg:phone":"+1 816 690 4928",
    "sg:postcode":"64011",
    "sg:province":"MO",
    "sg:tags":[
        "gas"
    ],
    "wof:name":"Salley's Propane Inc",
    "wof:placetype":"venue"
},
  "geometry": {"coordinates":[-94.058044,38.938593],"type":"Point"}
}