{
  "type": "Feature",
  "properties": {
    "iso:country":"US",
    "sg:address":"356 Midway Cir",
    "sg:city":"Nixa",
    "sg:classifiers":[
        {
            "category":"Retail",
            "subcategory":"Auto Repair",
            "type":"Services"
        }
    ],
    "sg:phone":"+1 417 753 3525",
    "sg:postcode":"65714",
    "sg:province":"MO",
    "sg:tags":[
        "glass",
        "coating",
        "tinting"
    ],
    "wof:name":"C S Window Tinting",
    "wof:placetype":"venue"
},
  "geometry": {"coordinates":[-93.303808,37.093421],"type":"Point"}
}