{
  "type": "Feature",
  "properties": {
    "iso:country":"US",
    "sg:address":"530 E 23rd St S",
    "sg:city":"Independence",
    "sg:classifiers":[
        {
            "category":"Professional",
            "subcategory":"Lawyer & Legal Services",
            "type":"Services"
        }
    ],
    "sg:phone":"+1 816 836 4000",
    "sg:postcode":"64055",
    "sg:province":"MO",
    "wof:name":"Wight Les",
    "wof:placetype":"venue"
},
  "geometry": {"coordinates":[-94.408373,39.079029],"type":"Point"}
}