{
  "type": "Feature",
  "properties": {
    "iso:country":"US",
    "sg:address":"1325 S Belt Hwy",
    "sg:city":"Saint Joseph",
    "sg:classifiers":[
        {
            "category":"Home & Garden",
            "subcategory":"Hardware",
            "type":"Retail Goods"
        }
    ],
    "sg:phone":"+1 816 232 5545",
    "sg:postcode":"64507",
    "sg:province":"MO",
    "wof:name":"Ace Hardware",
    "wof:placetype":"venue"
},
  "geometry": {"coordinates":[-94.803585,39.754461],"type":"Point"}
}