{
  "type": "Feature",
  "properties": {
    "iso:country":"US",
    "sg:address":"17901 E 227th St",
    "sg:city":"Harrisonville",
    "sg:classifiers":[
        {
            "category":"Building & Trades",
            "subcategory":"Construction",
            "type":"Services"
        }
    ],
    "sg:phone":"+1 816 779 6232",
    "sg:postcode":"64701",
    "sg:province":"MO",
    "sg:tags":[
        "tile-contractors"
    ],
    "wof:name":"Larson Ed Ceramic Tile",
    "wof:placetype":"venue"
},
  "geometry": {"coordinates":[-94.384641,38.707485],"type":"Point"}
}