{
  "type": "Feature",
  "properties": {
    "iso:country":"US",
    "sg:address":"1434 Chambers Rd",
    "sg:city":"St Louis",
    "sg:classifiers":[
        {
            "category":"Professional",
            "subcategory":"Management & Consulting",
            "type":"Services"
        }
    ],
    "sg:phone":"+1 314 521 0868",
    "sg:postcode":"63135",
    "sg:province":"MO",
    "sg:tags":[
        "consultant",
        "business"
    ],
    "wof:name":"Network Unlimited",
    "wof:placetype":"venue"
},
  "geometry": {"coordinates":[-90.281818,38.749367],"type":"Point"}
}