{
  "type": "Feature",
  "properties": {
    "iso:country":"US",
    "sg:address":"8084 Newt Dr",
    "sg:city":"Neosho",
    "sg:classifiers":[
        {
            "category":"Farming",
            "subcategory":"Poultry Farm",
            "type":"Manufacturing & Wholesale Goods"
        }
    ],
    "sg:phone":"+1 417 451 4772",
    "sg:postcode":"64850",
    "sg:province":"MO",
    "sg:tags":[
        "hatchery",
        "chicken",
        "egg"
    ],
    "wof:name":"Ozark Hatcheries",
    "wof:placetype":"venue"
},
  "geometry": {"coordinates":[-94.31697800000001,36.950854],"type":"Point"}
}