{
  "type": "Feature",
  "properties": {
    "iso:country":"US",
    "sg:address":"900 Winchester Rd",
    "sg:city":"Sedalia",
    "sg:classifiers":[
        {
            "category":"Real Estate",
            "subcategory":"Real Estate Operator",
            "type":"Services"
        }
    ],
    "sg:phone":"+1 660 826 3663",
    "sg:postcode":"65301",
    "sg:province":"MO",
    "sg:tags":[
        "apartment"
    ],
    "wof:name":"Winchester West Apartments",
    "wof:placetype":"venue"
},
  "geometry": {"coordinates":[-93.271863,38.707419],"type":"Point"}
}