{
  "type": "Feature",
  "properties": {
    "iso:country":"US",
    "sg:address":"722 W 12th St",
    "sg:city":"Trenton",
    "sg:classifiers":[
        {
            "category":"Building & Trades",
            "subcategory":"Plumbing",
            "type":"Services"
        }
    ],
    "sg:phone":"+1 660 359 6672",
    "sg:postcode":"64683",
    "sg:province":"MO",
    "sg:tags":[
        "air",
        "heating",
        "conditioning",
        "contractor"
    ],
    "wof:name":"School & Hamilton Heating",
    "wof:placetype":"venue"
},
  "geometry": {"coordinates":[-93.624455,40.076646],"type":"Point"}
}