{
  "type": "Feature",
  "properties": {
    "iso:country":"US",
    "sg:address":"8117 N Chatham Ave",
    "sg:city":"Kansas City",
    "sg:classifiers":[
        {
            "category":"Real Estate",
            "subcategory":"Real Estate Agent",
            "type":"Services"
        }
    ],
    "sg:phone":"+1 816 587 5255",
    "sg:postcode":"64151",
    "sg:province":"MO",
    "wof:name":"Jack Miller Properties",
    "wof:placetype":"venue"
},
  "geometry": {"coordinates":[-94.64196,39.242732],"type":"Point"}
}