{
  "type": "Feature",
  "properties": {
    "iso:country":"US",
    "sg:address":"18600 E 37 Ter S",
    "sg:city":"Independence",
    "sg:classifiers":[
        {
            "category":"Building & Trades",
            "subcategory":"Plumbing",
            "type":"Services"
        }
    ],
    "sg:phone":"+1 816 795 0684",
    "sg:postcode":"64057",
    "sg:province":"MO",
    "sg:tags":[
        "mechanical",
        "contractor"
    ],
    "wof:name":"Mechanical Technologies Inc",
    "wof:placetype":"venue"
},
  "geometry": {"coordinates":[-94.36171299999999,39.0505],"type":"Point"}
}