{
  "type": "Feature",
  "properties": {
    "iso:country":"US",
    "sg:address":"10 Terrestrial Dr",
    "sg:city":"Saint Peters",
    "sg:classifiers":[
        {
            "category":"Autos & Motor Vehicles",
            "subcategory":"Automobile Sales",
            "type":"Retail Goods"
        }
    ],
    "sg:phone":"+1 636 928 1685",
    "sg:postcode":"63376",
    "sg:province":"MO",
    "sg:tags":[
        "used"
    ],
    "wof:name":"Charlack Auto Sales",
    "wof:placetype":"venue"
},
  "geometry": {"coordinates":[-90.588627,38.773376],"type":"Point"}
}