{
  "type": "Feature",
  "properties": {
    "iso:country":"US",
    "sg:address":"9116 State Hwy Ee",
    "sg:city":"Liberty",
    "sg:phone":"+1 816 792 2462",
    "sg:postcode":"64068",
    "sg:province":"MO",
    "sg:tags":[
        "farm",
        "soybean"
    ],
    "wof:name":"Hale Farms",
    "wof:placetype":"venue"
},
  "geometry": {"coordinates":[-94.334565,39.254843],"type":"Point"}
}