{
  "type": "Feature",
  "properties": {
    "iso:country":"US",
    "sg:address":"411 State Rd Z",
    "sg:city":"Fulton",
    "sg:classifiers":[
        {
            "category":"Retail",
            "subcategory":"Auto Repair",
            "type":"Services"
        }
    ],
    "sg:phone":"+1 573 642 8811",
    "sg:postcode":"65251",
    "sg:province":"MO",
    "sg:tags":[
        "general"
    ],
    "wof:name":"Bus Barn",
    "wof:placetype":"venue"
},
  "geometry": {"coordinates":[-91.942644,38.861306],"type":"Point"}
}