{
  "type": "Feature",
  "properties": {
    "iso:country":"US",
    "sg:address":"1619 Irish Sea",
    "sg:city":"High Ridge",
    "sg:classifiers":[
        {
            "category":"Shopping",
            "subcategory":"Computers & Home Electronics",
            "type":"Retail Goods"
        }
    ],
    "sg:phone":"+1 636 677 6097",
    "sg:postcode":"63049",
    "sg:province":"MO",
    "wof:name":"Home Computer Solutions",
    "wof:placetype":"venue"
},
  "geometry": {"coordinates":[-90.51267,38.48482],"type":"Point"}
}