{
  "type": "Feature",
  "properties": {
    "iso:country":"US",
    "sg:address":"1900 W Sunshine St",
    "sg:city":"Springfield",
    "sg:classifiers":[
        {
            "category":"Health Services",
            "subcategory":"Hospital",
            "type":"Services"
        }
    ],
    "sg:phone":"+1 417 862 7041",
    "sg:postcode":"65807",
    "sg:province":"MO",
    "wof:name":"US Medical Ctr For Prisoners",
    "wof:placetype":"venue"
},
  "geometry": {"coordinates":[-93.31837,37.18246],"type":"Point"}
}