{
  "type": "Feature",
  "properties": {
    "iso:country":"US",
    "sg:address":"3302 Terrace St",
    "sg:city":"Kansas City",
    "sg:classifiers":[
        {
            "category":"Building & Trades",
            "subcategory":"Construction",
            "type":"Services"
        }
    ],
    "sg:phone":"+1 816 931 5311",
    "sg:postcode":"64111",
    "sg:province":"MO",
    "sg:tags":[
        "waterproofing",
        "contractor"
    ],
    "sg:website":"www.swwaterproofing.com",
    "wof:name":"S & W Waterproofing Inc",
    "wof:placetype":"venue"
},
  "geometry": {"coordinates":[-94.600971,39.06665],"type":"Point"}
}