{
  "type": "Feature",
  "properties": {
    "iso:country":"US",
    "sg:address":"715 N Elm St",
    "sg:city":"Cameron",
    "sg:classifiers":[
        {
            "category":"Building & Trades",
            "subcategory":"Construction",
            "type":"Services"
        }
    ],
    "sg:phone":"+1 816 632 1884",
    "sg:postcode":"64429",
    "sg:province":"MO",
    "sg:tags":[
        "heavy"
    ],
    "wof:name":"Cameron Trenching",
    "wof:placetype":"venue"
},
  "geometry": {"coordinates":[-94.230345,39.745974],"type":"Point"}
}