{
  "type": "Feature",
  "properties": {
    "iso:country":"US",
    "sg:address":"7000 Chippewa St",
    "sg:city":"Webster Groves",
    "sg:classifiers":[
        {
            "category":"Arts & Performance",
            "subcategory":"Theater",
            "type":"Entertainment"
        }
    ],
    "sg:phone":"+1 314 352 2100",
    "sg:postcode":"63119",
    "sg:province":"MO",
    "sg:tags":[
        "television",
        "program",
        "producer"
    ],
    "wof:name":"Spirit Sports & Events Mrktng",
    "wof:placetype":"venue"
},
  "geometry": {"coordinates":[-90.31497899999999,38.585588],"type":"Point"}
}