{
  "type": "Feature",
  "properties": {
    "iso:country":"US",
    "sg:address":"6236 N Chatham Ave",
    "sg:city":"Kansas City",
    "sg:classifiers":[
        {
            "category":"Shopping",
            "subcategory":"Computers & Home Electronics",
            "type":"Retail Goods"
        }
    ],
    "sg:phone":"+1 816 741 7788",
    "sg:postcode":"64151",
    "sg:province":"MO",
    "wof:name":"Radio Shack",
    "wof:placetype":"venue"
},
  "geometry": {"coordinates":[-94.643145,39.208743],"type":"Point"}
}