{
  "type": "Feature",
  "properties": {
    "iso:country":"US",
    "sg:address":"1650 Broadway St",
    "sg:city":"Kansas City",
    "sg:classifiers":[
        {
            "category":"Health Services",
            "subcategory":"Doctor",
            "type":"Services"
        }
    ],
    "sg:phone":"+1 816 842 2020",
    "sg:postcode":"64108",
    "sg:province":"MO",
    "sg:tags":[
        "medical"
    ],
    "wof:name":"Ohs-Comp Care",
    "wof:placetype":"venue"
},
  "geometry": {"coordinates":[-94.588779,39.093833],"type":"Point"}
}