{
  "type": "Feature",
  "properties": {
    "iso:country":"US",
    "sg:address":"32106 E Burgess Rd",
    "sg:city":"Buckner",
    "sg:classifiers":[
        {
            "category":"Manufacturing",
            "subcategory":"Wood Products",
            "type":"Manufacturing & Wholesale Goods"
        }
    ],
    "sg:phone":"+1 816 650 5792",
    "sg:postcode":"64016",
    "sg:province":"MO",
    "sg:tags":[
        "mfg"
    ],
    "wof:name":"Berkes Flycrafts Co",
    "wof:placetype":"venue"
},
  "geometry": {"coordinates":[-94.20410200000001,39.094754],"type":"Point"}
}