{
  "type": "Feature",
  "properties": {
    "iso:country":"US",
    "sg:address":"1383 S Bishop Ave",
    "sg:city":"Rolla",
    "sg:classifiers":[
        {
            "category":"Manufacturing",
            "subcategory":"Signs",
            "type":"Manufacturing & Wholesale Goods"
        }
    ],
    "sg:phone":"+1 573 364 3876",
    "sg:postcode":"65401",
    "sg:province":"MO",
    "wof:name":"Star Signs",
    "wof:placetype":"venue"
},
  "geometry": {"coordinates":[-91.78004199999999,37.924062],"type":"Point"}
}