{
  "type": "Feature",
  "properties": {
    "iso:country":"US",
    "sg:address":"33400 State Hwy 150",
    "sg:city":"Lees Summit",
    "sg:classifiers":[
        {
            "category":"Insurance",
            "subcategory":"Insurance Agent",
            "type":"Services"
        }
    ],
    "sg:phone":"+1 816 697 3423",
    "sg:postcode":"64086",
    "sg:province":"MO",
    "wof:name":"Patrons Mutual Insurance Co",
    "wof:placetype":"venue"
},
  "geometry": {"coordinates":[-94.200473,38.863885],"type":"Point"}
}