{
  "type": "Feature",
  "properties": {
    "iso:country":"US",
    "sg:address":"16639 Old 66 Blvd",
    "sg:city":"Carthage",
    "sg:classifiers":[
        {
            "category":"Wholesale",
            "subcategory":"Metals & Minerals",
            "type":"Manufacturing & Wholesale Goods"
        }
    ],
    "sg:phone":"+1 417 358 8816",
    "sg:postcode":"64836",
    "sg:province":"MO",
    "sg:tags":[
        "pipe"
    ],
    "wof:name":"Industrial Pipe & Supply",
    "wof:placetype":"venue"
},
  "geometry": {"coordinates":[-94.359866,37.173405],"type":"Point"}
}