{
  "type": "Feature",
  "properties": {
    "iso:country":"US",
    "sg:address":"6723 Roberts Ave",
    "sg:city":"Saint Louis",
    "sg:classifiers":[
        {
            "category":"Professional",
            "subcategory":"Lawyer & Legal Services",
            "type":"Services"
        }
    ],
    "sg:phone":"+1 314 727 2621",
    "sg:postcode":"63133",
    "sg:province":"MO",
    "wof:name":"Boll Paul J Atty",
    "wof:placetype":"venue"
},
  "geometry": {"coordinates":[-90.307297,38.672199],"type":"Point"}
}