{
  "type": "Feature",
  "properties": {
    "iso:country":"US",
    "sg:address":"17404 Hwy D",
    "sg:city":"Mexico",
    "sg:classifiers":[
        {
            "category":"Farming",
            "subcategory":"Farm & Veterinary Services",
            "type":"Manufacturing & Wholesale Goods"
        }
    ],
    "sg:phone":"+1 573 581 2724",
    "sg:postcode":"65265",
    "sg:province":"MO",
    "sg:tags":[
        "crop",
        "harvesting"
    ],
    "wof:name":"Dan Benne",
    "wof:placetype":"venue"
},
  "geometry": {"coordinates":[-92.002979,39.120882],"type":"Point"}
}