{
  "type": "Feature",
  "properties": {
    "iso:country":"US",
    "sg:address":"8205 Harris Ave",
    "sg:city":"Raytown",
    "sg:classifiers":[
        {
            "category":"Restaurant",
            "type":"Food & Drink"
        }
    ],
    "sg:phone":"+1 816 737 0676",
    "sg:postcode":"64138",
    "sg:province":"MO",
    "wof:name":"Girls On The Run Of Jackson County",
    "wof:placetype":"venue"
},
  "geometry": {"coordinates":[-94.45300899999999,38.973655],"type":"Point"}
}