{
  "type": "Feature",
  "properties": {
    "iso:country":"US",
    "sg:address":"2629 N Kansas Expy",
    "sg:city":"Springfield",
    "sg:classifiers":[
        {
            "category":"Shopping",
            "subcategory":"Discount & Variety Stores",
            "type":"Retail Goods"
        }
    ],
    "sg:phone":"+1 417 864 6285",
    "sg:postcode":"65803",
    "sg:province":"MO",
    "sg:tags":[
        "merchandise",
        "general"
    ],
    "wof:name":"One Dollar Shops Inc",
    "wof:placetype":"venue"
},
  "geometry": {"coordinates":[-93.31093,37.24558],"type":"Point"}
}