{
  "type": "Feature",
  "properties": {
    "iso:country":"US",
    "sg:address":"3228 E Broadway Blvd",
    "sg:city":"Sedalia",
    "sg:classifiers":[
        {
            "category":"Building & Trades",
            "subcategory":"Construction",
            "type":"Services"
        }
    ],
    "sg:phone":"+1 660 826 2688",
    "sg:postcode":"65301",
    "sg:province":"MO",
    "sg:tags":[
        "house"
    ],
    "wof:name":"Central Properties",
    "wof:placetype":"venue"
},
  "geometry": {"coordinates":[-93.190121,38.699751],"type":"Point"}
}