{
  "type": "Feature",
  "properties": {
    "iso:country":"US",
    "sg:address":"6575 Romiss Ct",
    "sg:city":"St Louis",
    "sg:classifiers":[
        {
            "category":"Wholesale",
            "subcategory":"Construction Materials",
            "type":"Manufacturing & Wholesale Goods"
        }
    ],
    "sg:phone":"+1 314 521 3363",
    "sg:postcode":"63134",
    "sg:province":"MO",
    "sg:tags":[
        "fence"
    ],
    "wof:name":"Merchants Metals",
    "wof:placetype":"venue"
},
  "geometry": {"coordinates":[-90.34234600000001,38.759033],"type":"Point"}
}