{
  "type": "Feature",
  "properties": {
    "iso:country":"US",
    "sg:address":"4820 N Sycamore Ave",
    "sg:city":"Kansas City",
    "sg:classifiers":[
        {
            "category":"Professional",
            "subcategory":"Engineering",
            "type":"Services"
        }
    ],
    "sg:phone":"+1 816 452 7146",
    "sg:postcode":"64119",
    "sg:province":"MO",
    "wof:name":"Sunrise Resources",
    "wof:placetype":"venue"
},
  "geometry": {"coordinates":[-94.48286899999999,39.182823],"type":"Point"}
}