{
  "type": "Feature",
  "properties": {
    "iso:country":"US",
    "sg:address":"125 E Main St",
    "sg:city":"Drexel",
    "sg:classifiers":[
        {
            "category":"Autos & Motor Vehicles",
            "subcategory":"Automobile Sales",
            "type":"Retail Goods"
        }
    ],
    "sg:phone":"+1 816 657 2050",
    "sg:postcode":"64742",
    "sg:province":"MO",
    "sg:tags":[
        "dealers-used",
        "car",
        "used",
        "cars-wholesale",
        "new"
    ],
    "wof:name":"Drexel Auto Sales",
    "wof:placetype":"venue"
},
  "geometry": {"coordinates":[-94.609305,38.479431],"type":"Point"}
}