{
  "type": "Feature",
  "properties": {
    "iso:country":"US",
    "sg:address":"306 State Hwy 7",
    "sg:city":"Blue Springs",
    "sg:classifiers":[
        {
            "category":"Autos & Motor Vehicles",
            "subcategory":"Auto Supplies",
            "type":"Retail Goods"
        }
    ],
    "sg:phone":"+1 816 228 1166",
    "sg:postcode":"64014",
    "sg:province":"MO",
    "sg:tags":[
        "automobile",
        "parts"
    ],
    "wof:name":"Advance Auto Parts Inc",
    "wof:placetype":"venue"
},
  "geometry": {"coordinates":[-94.272451,39.013003],"type":"Point"}
}