{
  "type": "Feature",
  "properties": {
    "iso:country":"US",
    "sg:address":"1231 Madison 203",
    "sg:city":"Fredericktown",
    "sg:classifiers":[
        {
            "category":"Retail",
            "subcategory":"Auto Repair",
            "type":"Services"
        }
    ],
    "sg:phone":"+1 573 783 8228",
    "sg:postcode":"63645",
    "sg:province":"MO",
    "sg:tags":[
        "body",
        "painting",
        "repairing",
        "automobile"
    ],
    "wof:name":"Ultimate Wrecker Service",
    "wof:placetype":"venue"
},
  "geometry": {"coordinates":[-90.259377,37.508432],"type":"Point"}
}