{
  "type": "Feature",
  "properties": {
    "iso:country":"US",
    "sg:address":"713 E 3rd St",
    "sg:city":"Cameron",
    "sg:classifiers":[
        {
            "category":"Food & Beverages",
            "subcategory":"Specialty",
            "type":"Retail Goods"
        }
    ],
    "sg:phone":"+1 816 632 8822",
    "sg:postcode":"64429",
    "sg:province":"MO",
    "wof:name":"Case Enterprises",
    "wof:placetype":"venue"
},
  "geometry": {"coordinates":[-94.230447,39.741118],"type":"Point"}
}