{
  "type": "Feature",
  "properties": {
    "iso:country":"US",
    "sg:address":"6 Calumet Dr",
    "sg:city":"Saint Peters",
    "sg:classifiers":[
        {
            "category":"Professional",
            "subcategory":"Business Services",
            "type":"Services"
        }
    ],
    "sg:phone":"+1 636 970 3752",
    "sg:postcode":"63376",
    "sg:province":"MO",
    "wof:name":"C Pack Crating Serv Co",
    "wof:placetype":"venue"
},
  "geometry": {"coordinates":[-90.63342,38.790169],"type":"Point"}
}