{
  "type": "Feature",
  "properties": {
    "iso:country":"US",
    "sg:address":"2421 Muegge Rd",
    "sg:city":"Saint Charles",
    "sg:classifiers":[
        {
            "category":"Manufacturing",
            "subcategory":"Textiles",
            "type":"Manufacturing & Wholesale Goods"
        }
    ],
    "sg:phone":"+1 636 734 6498",
    "sg:postcode":"63303",
    "sg:province":"MO",
    "sg:tags":[
        "automobile"
    ],
    "wof:name":"Alpha Accesories LLC",
    "wof:placetype":"venue"
},
  "geometry": {"coordinates":[-90.558577,38.782362],"type":"Point"}
}