{
  "type": "Feature",
  "properties": {
    "iso:country":"US",
    "sg:address":"4231 N Grand Blvd",
    "sg:city":"Saint Louis",
    "sg:classifiers":[
        {
            "category":"Social Services",
            "subcategory":"Child Care",
            "type":"Services"
        },
        {
            "category":"Education",
            "subcategory":"Preschool",
            "type":"Public Place"
        },
        {
            "category":"Education",
            "subcategory":"School",
            "type":"Public Place"
        }
    ],
    "sg:phone":"+1 314 531 5511",
    "sg:postcode":"63107",
    "sg:province":"MO",
    "sg:tags":[
        "elementary",
        "day"
    ],
    "sg:website":"www.juntosds.com",
    "wof:name":"Children of Promise Learning Center",
    "wof:placetype":"venue"
},
  "geometry": {"coordinates":[-90.212414,38.6675],"type":"Point"}
}