{
  "type": "Feature",
  "properties": {
    "iso:country":"US",
    "sg:address":"1737 Macklind Ave",
    "sg:city":"Saint Louis",
    "sg:classifiers":[
        {
            "category":"Building & Trades",
            "subcategory":"Construction",
            "type":"Services"
        }
    ],
    "sg:phone":"+1 314 776 1189",
    "sg:postcode":"63110",
    "sg:province":"MO",
    "sg:tags":[
        "contractor"
    ],
    "sg:website":"www.volkconstruction.com",
    "wof:name":"Volk Construction Co",
    "wof:placetype":"venue"
},
  "geometry": {"coordinates":[-90.27629899999999,38.6203],"type":"Point"}
}