{
  "type": "Feature",
  "properties": {
    "iso:country":"US",
    "sg:address":"1120 Saline St",
    "sg:city":"Kansas City",
    "sg:classifiers":[
        {
            "category":"Freight",
            "type":"Transportation"
        }
    ],
    "sg:phone":"+1 816 474 0220",
    "sg:postcode":"64116",
    "sg:province":"MO",
    "sg:tags":[
        "forwarder"
    ],
    "wof:name":"U P S Sup Chain Solutions Inc",
    "wof:placetype":"venue"
},
  "geometry": {"coordinates":[-94.560016,39.130699],"type":"Point"}
}