{
  "type": "Feature",
  "properties": {
    "iso:country":"US",
    "sg:address":"10116 Bellefontaine Rd",
    "sg:city":"Saint Louis",
    "sg:classifiers":[
        {
            "category":"Building & Trades",
            "subcategory":"Construction",
            "type":"Services"
        }
    ],
    "sg:phone":"+1 314 869 8119",
    "sg:postcode":"63137",
    "sg:province":"MO",
    "sg:tags":[
        "hanging",
        "contractor"
    ],
    "wof:name":"Jj Painting",
    "wof:placetype":"venue"
},
  "geometry": {"coordinates":[-90.223153,38.753487],"type":"Point"}
}