{
  "type": "Feature",
  "properties": {
    "iso:country":"US",
    "sg:address":"3170 US Hwy 61",
    "sg:city":"Hannibal",
    "sg:classifiers":[
        {
            "category":"Health Services",
            "subcategory":"Nursing And Care Facility",
            "type":"Services"
        }
    ],
    "sg:phone":"+1 573 221 5533",
    "sg:postcode":"63401",
    "sg:province":"MO",
    "sg:tags":[
        "home",
        "retirement",
        "community"
    ],
    "wof:name":"Luther Manor Retirement Ctr",
    "wof:placetype":"venue"
},
  "geometry": {"coordinates":[-91.390545,39.708457],"type":"Point"}
}