{
  "type": "Feature",
  "properties": {
    "iso:country":"US",
    "sg:address":"602 E Jackson St",
    "sg:city":"Carterville",
    "sg:classifiers":[
        {
            "category":"Building & Trades",
            "subcategory":"Construction",
            "type":"Services"
        }
    ],
    "sg:phone":"+1 417 673 4837",
    "sg:postcode":"64835",
    "sg:province":"MO",
    "sg:tags":[
        "carpenter"
    ],
    "wof:name":"Cjf Carpentry",
    "wof:placetype":"venue"
},
  "geometry": {"coordinates":[-94.435404,37.145595],"type":"Point"}
}