{
  "type": "Feature",
  "properties": {
    "iso:country":"US",
    "sg:address":"1823 E 20th St",
    "sg:city":"Joplin",
    "sg:classifiers":[
        {
            "category":"Professional",
            "subcategory":"Lawyer & Legal Services",
            "type":"Services"
        }
    ],
    "sg:phone":"+1 417 624 0700",
    "sg:postcode":"64804",
    "sg:province":"MO",
    "sg:tags":[
        "plan"
    ],
    "wof:name":"Michael Roberts Attorney At Law",
    "wof:placetype":"venue"
},
  "geometry": {"coordinates":[-94.495678,37.069283],"type":"Point"}
}