{
  "type": "Feature",
  "properties": {
    "iso:country":"US",
    "sg:address":"1829 S Aztec Ave",
    "sg:city":"Independence",
    "sg:classifiers":[
        {
            "category":"Organizations",
            "subcategory":"Political Organization",
            "type":"Services"
        }
    ],
    "sg:phone":"+1 816 796 3088",
    "sg:postcode":"64057",
    "sg:province":"MO",
    "wof:name":"Citizens To Elect Franklin",
    "wof:placetype":"venue"
},
  "geometry": {"coordinates":[-94.34968499999999,39.084879],"type":"Point"}
}