{
  "type": "Feature",
  "properties": {
    "iso:country":"US",
    "sg:address":"13021 Saller Dr",
    "sg:city":"Saint Louis",
    "sg:classifiers":[
        {
            "category":"Professional",
            "subcategory":"Printing & Photocopies",
            "type":"Services"
        }
    ],
    "sg:phone":"+1 314 821 6845",
    "sg:postcode":"63127",
    "sg:province":"MO",
    "sg:tags":[
        "photocopying"
    ],
    "wof:name":"High Volume Duplicators",
    "wof:placetype":"venue"
},
  "geometry": {"coordinates":[-90.42285699999999,38.546736],"type":"Point"}
}