{
  "type": "Feature",
  "properties": {
    "iso:country":"US",
    "sg:address":"1604 S Ellis St",
    "sg:city":"Webb City",
    "sg:classifiers":[
        {
            "category":"Real Estate",
            "subcategory":"Real Estate Operator",
            "type":"Services"
        }
    ],
    "sg:phone":"+1 417 673 1444",
    "sg:postcode":"64870",
    "sg:province":"MO",
    "sg:tags":[
        "building",
        "apartment"
    ],
    "wof:name":"Webb City Apartments",
    "wof:placetype":"venue"
},
  "geometry": {"coordinates":[-94.47772500000001,37.130551],"type":"Point"}
}