{
  "type": "Feature",
  "properties": {
    "iso:country":"US",
    "sg:address":"16564 Thunderhead Canyon Ct",
    "sg:city":"Ballwin",
    "sg:classifiers":[
        {
            "category":"Insurance",
            "subcategory":"Hazard Insurance",
            "type":"Services"
        }
    ],
    "sg:phone":"+1 636 458 2152",
    "sg:postcode":"63011",
    "sg:province":"MO",
    "wof:name":"Droege Insurance",
    "wof:placetype":"venue"
},
  "geometry": {"coordinates":[-90.624195,38.59332],"type":"Point"}
}