{
  "type": "Feature",
  "properties": {
    "iso:country":"US",
    "sg:address":"2669 E Blaine St",
    "sg:city":"Springfield",
    "sg:classifiers":[
        {
            "category":"Social Services",
            "subcategory":"Child Care",
            "type":"Services"
        }
    ],
    "sg:phone":"+1 417 831 9368",
    "sg:postcode":"65803",
    "sg:province":"MO",
    "sg:tags":[
        "day"
    ],
    "wof:name":"Nannys Home Day Care",
    "wof:placetype":"venue"
},
  "geometry": {"coordinates":[-93.24025399999999,37.228447],"type":"Point"}
}