{
  "type": "Feature",
  "properties": {
    "iso:country":"US",
    "sg:address":"510 Sunset Dr",
    "sg:city":"Palmyra",
    "sg:classifiers":[
        {
            "category":"Professional",
            "type":"Services"
        }
    ],
    "sg:phone":"+1 573 769 3728",
    "sg:postcode":"63461",
    "sg:province":"MO",
    "wof:name":"Lovelace John",
    "wof:placetype":"venue"
},
  "geometry": {"coordinates":[-91.52879,39.80319],"type":"Point"}
}