{
  "type": "Feature",
  "properties": {
    "iso:country":"US",
    "sg:address":"1024 N Morley St",
    "sg:city":"Moberly",
    "sg:classifiers":[
        {
            "category":"Banks & Credit Unions",
            "subcategory":"Bank",
            "type":"Services"
        }
    ],
    "sg:phone":"+1 660 263 5955",
    "sg:postcode":"65270",
    "sg:province":"MO",
    "sg:tags":[
        "savings",
        "institution"
    ],
    "wof:name":"United Credit Union",
    "wof:placetype":"venue"
},
  "geometry": {"coordinates":[-92.433114,39.430584],"type":"Point"}
}