{
  "type": "Feature",
  "properties": {
    "iso:country":"US",
    "sg:address":"802 N Hundley St",
    "sg:city":"Albany",
    "sg:classifiers":[
        {
            "category":"Organizations",
            "subcategory":"Community Association",
            "type":"Services"
        }
    ],
    "sg:phone":"+1 660 726 5275",
    "sg:postcode":"64402",
    "sg:province":"MO",
    "wof:name":"Royal Select Masters York Rite",
    "wof:placetype":"venue"
},
  "geometry": {"coordinates":[-94.33179699999999,40.253538],"type":"Point"}
}