{
  "type": "Feature",
  "properties": {
    "iso:country":"US",
    "sg:address":"1320 Midland Dr",
    "sg:city":"St Louis",
    "sg:classifiers":[
        {
            "category":"Professional",
            "subcategory":"Management & Consulting",
            "type":"Services"
        }
    ],
    "sg:phone":"+1 314 725 1994",
    "sg:postcode":"63130",
    "sg:province":"MO",
    "sg:tags":[
        "consultant",
        "business"
    ],
    "wof:name":"Owens Drake Consulting Inc",
    "wof:placetype":"venue"
},
  "geometry": {"coordinates":[-90.32538,38.674511],"type":"Point"}
}