{
  "type": "Feature",
  "properties": {
    "iso:country":"US",
    "sg:address":"114 E Washington St",
    "sg:city":"Kirksville",
    "sg:classifiers":[
        {
            "category":"Shopping",
            "type":"Retail Goods"
        }
    ],
    "sg:phone":"+1 660 665 4531",
    "sg:postcode":"63501",
    "sg:province":"MO",
    "sg:tags":[
        "picture",
        "frame"
    ],
    "wof:name":"Beard's",
    "wof:placetype":"venue"
},
  "geometry": {"coordinates":[-92.583038,40.194641],"type":"Point"}
}