{
  "type": "Feature",
  "properties": {
    "iso:country":"US",
    "sg:address":"328 Booneslick Rd",
    "sg:city":"New Florence",
    "sg:classifiers":[
        {
            "category":"Home & Garden",
            "subcategory":"Building Materials",
            "type":"Retail Goods"
        }
    ],
    "sg:phone":"+1 636 456 2551",
    "sg:postcode":"63363",
    "sg:province":"MO",
    "sg:tags":[
        "mixed",
        "concrete"
    ],
    "wof:name":"Warren County Concrete",
    "wof:placetype":"venue"
},
  "geometry": {"coordinates":[-91.53392599999999,38.908681],"type":"Point"}
}