{
  "type": "Feature",
  "properties": {
    "iso:country":"US",
    "sg:address":"2352 Centerline Industrl Dr",
    "sg:city":"Saint Louis",
    "sg:classifiers":[
        {
            "category":"Professional",
            "subcategory":"Advertising",
            "type":"Services"
        }
    ],
    "sg:phone":"+1 314 432 7411",
    "sg:postcode":"63146",
    "sg:province":"MO",
    "sg:tags":[
        "mail",
        "direct"
    ],
    "wof:name":"Mailworks",
    "wof:placetype":"venue"
},
  "geometry": {"coordinates":[-90.43435700000001,38.703544],"type":"Point"}
}