{
  "type": "Feature",
  "properties": {
    "iso:country":"US",
    "sg:address":"127 Cedar Cir",
    "sg:city":"Jackson",
    "sg:classifiers":[
        {
            "category":"Wholesale",
            "subcategory":"Machinery & Supplies",
            "type":"Manufacturing & Wholesale Goods"
        }
    ],
    "sg:phone":"+1 573 204 1016",
    "sg:postcode":"63755",
    "sg:province":"MO",
    "sg:tags":[
        "equipment",
        "industrial"
    ],
    "wof:name":"Environmental Technology Equip",
    "wof:placetype":"venue"
},
  "geometry": {"coordinates":[-89.648348,37.45189],"type":"Point"}
}