{
  "type": "Feature",
  "properties": {
    "iso:country":"US",
    "sg:address":"400 N Baltimore St",
    "sg:city":"Kirksville",
    "sg:classifiers":[
        {
            "category":"Personal",
            "subcategory":"Beauty Salon",
            "type":"Services"
        },
        {
            "category":"Personal",
            "subcategory":"Barber",
            "type":"Services"
        },
        {
            "category":"Personal",
            "subcategory":"Tanning Parlor",
            "type":"Services"
        }
    ],
    "sg:phone":"+1 660 665 4288",
    "sg:postcode":"63501",
    "sg:province":"MO",
    "sg:tags":[
        "hair",
        "stylist"
    ],
    "wof:name":"Tina's Hairport",
    "wof:placetype":"venue"
},
  "geometry": {"coordinates":[-92.571968,40.192261],"type":"Point"}
}