{
  "type": "Feature",
  "properties": {
    "addr:full":"836 Hwy 42 Iberia MO 65486",
    "addr:housenumber":"836",
    "addr:postcode":"65486",
    "addr:street":"Hwy 42",
    "iso:country":"US",
    "sg:address":"836 Hwy 42",
    "sg:city":"Iberia",
    "sg:classifiers":[
        {
            "category":"Building & Trades",
            "subcategory":"Equipment Rental",
            "type":"Services"
        }
    ],
    "sg:phone":"+1 573 793 6967",
    "sg:postcode":"65486",
    "sg:province":"MO",
    "wof:name":"U-Haul",
    "wof:placetype":"venue"
},
  "geometry": {"coordinates":[-92.297168,38.089228],"type":"Point"}
}