{
  "type": "Feature",
  "properties": {
    "iso:country":"US",
    "sg:address":"6368 Delmar",
    "sg:city":"Saint Louis",
    "sg:classifiers":[
        {
            "category":"Shopping",
            "subcategory":"Clothing, Apparel, & Fashions",
            "type":"Retail Goods"
        },
        {
            "category":"Restaurant",
            "type":"Food & Drink"
        }
    ],
    "sg:phone":"+1 314 727 4400",
    "sg:postcode":"63130",
    "sg:province":"MO",
    "sg:tags":[
        "flavor",
        "local"
    ],
    "sg:website":"www.bakedts.com",
    "wof:name":"Baked T's",
    "wof:placetype":"venue"
},
  "geometry": {"coordinates":[-90.304408,38.655895],"type":"Point"}
}