{
  "type": "Feature",
  "properties": {
    "iso:country":"US",
    "sg:address":"709 Main St",
    "sg:city":"Cassville",
    "sg:classifiers":[
        {
            "category":"Shopping",
            "subcategory":"Clothing, Apparel, & Fashions",
            "type":"Retail Goods"
        }
    ],
    "sg:phone":"+1 417 847 2365",
    "sg:postcode":"65625",
    "sg:province":"MO",
    "sg:tags":[
        "family"
    ],
    "wof:name":"Smiths Clothing Store",
    "wof:placetype":"venue"
},
  "geometry": {"coordinates":[-93.867886,36.679171],"type":"Point"}
}