{
  "type": "Feature",
  "properties": {
    "iso:country":"US",
    "sg:address":"1404 Charleston Ct",
    "sg:city":"Warrensburg",
    "sg:classifiers":[
        {
            "category":"Restaurant",
            "type":"Food & Drink"
        }
    ],
    "sg:phone":"+1 660 422 6899",
    "sg:postcode":"64093",
    "sg:province":"MO",
    "sg:tags":[
        "eating"
    ],
    "wof:name":"Sweet Treats Vending",
    "wof:placetype":"venue"
},
  "geometry": {"coordinates":[-93.71253,38.752752],"type":"Point"}
}