{
  "type": "Feature",
  "properties": {
    "iso:country":"US",
    "sg:address":"400 Lewis St",
    "sg:city":"Canton",
    "sg:classifiers":[
        {
            "category":"Communications",
            "type":"Services"
        },
        {
            "category":"Communications",
            "subcategory":"Television Station",
            "type":"Services"
        }
    ],
    "sg:phone":"+1 573 288 3021",
    "sg:postcode":"63435",
    "sg:province":"MO",
    "sg:tags":[
        "satellite",
        "cable"
    ],
    "wof:name":"Dish Zero",
    "wof:placetype":"venue"
},
  "geometry": {"coordinates":[-91.51873000000001,40.130341],"type":"Point"}
}