{
  "type": "Feature",
  "properties": {
    "iso:country":"US",
    "sg:address":"3045 S National Ave",
    "sg:city":"Springfield",
    "sg:classifiers":[
        {
            "category":"Health Services",
            "subcategory":"Health Practitioner",
            "type":"Services"
        }
    ],
    "sg:phone":"+1 417 823 3888",
    "sg:postcode":"65804",
    "sg:province":"MO",
    "sg:tags":[
        "gambling",
        "addiction-information",
        "treatment"
    ],
    "wof:name":"Functional Individualized Training, Inc.",
    "wof:placetype":"venue"
},
  "geometry": {"coordinates":[-93.277505,37.158299],"type":"Point"}
}