{
  "type": "Feature",
  "properties": {
    "iso:country":"US",
    "sg:address":"3530 Jarvis Rd",
    "sg:city":"Hillsboro",
    "sg:classifiers":[
        {
            "category":"Retail",
            "subcategory":"Auto Repair",
            "type":"Services"
        },
        {
            "category":"Wholesale",
            "subcategory":"Auto Parts",
            "type":"Manufacturing & Wholesale Goods"
        }
    ],
    "sg:phone":"+1 636 479 4975",
    "sg:postcode":"63050",
    "sg:province":"MO",
    "sg:tags":[
        "automotive",
        "rebuilt",
        "used",
        "automobile"
    ],
    "wof:name":"Reaves Brothers Auto Salvage",
    "wof:placetype":"venue"
},
  "geometry": {"coordinates":[-90.47268,38.26468],"type":"Point"}
}