{
  "type": "Feature",
  "properties": {
    "iso:country":"US",
    "sg:address":"137 N Washington St",
    "sg:city":"Clinton",
    "sg:classifiers":[
        {
            "category":"Professional",
            "subcategory":"Lawyer & Legal Services",
            "type":"Services"
        }
    ],
    "sg:phone":"+1 660 885 6137",
    "sg:postcode":"64735",
    "sg:province":"MO",
    "wof:name":"Kenney Law Office",
    "wof:placetype":"venue"
},
  "geometry": {"coordinates":[-93.77783599999999,38.371585],"type":"Point"}
}