{
  "type": "Feature",
  "properties": {
    "iso:country":"US",
    "sg:address":"1217 W 12 St",
    "sg:city":"Kansas City",
    "sg:classifiers":[
        {
            "category":"Manufacturing",
            "subcategory":"Chemicals & Compounds",
            "type":"Manufacturing & Wholesale Goods"
        }
    ],
    "sg:phone":"+1 816 421 4070",
    "sg:postcode":"64101",
    "sg:province":"MO",
    "sg:tags":[
        "pesticide",
        "ag"
    ],
    "sg:website":"www.pbigordon.com",
    "wof:name":"PBI Gordon Corp",
    "wof:placetype":"venue"
},
  "geometry": {"coordinates":[-94.59988,39.100606],"type":"Point"}
}