{
  "type": "Feature",
  "properties": {
    "iso:country":"US",
    "sg:address":"7151 Olive Blvd",
    "sg:city":"St Louis",
    "sg:classifiers":[
        {
            "category":"Health Services",
            "subcategory":"Doctor",
            "type":"Services"
        }
    ],
    "sg:phone":"+1 314 862 2082",
    "sg:postcode":"63130",
    "sg:province":"MO",
    "sg:tags":[
        "dentist"
    ],
    "wof:name":"Oswald L Thomas DDS",
    "wof:placetype":"venue"
},
  "geometry": {"coordinates":[-90.32080000000001,38.669175],"type":"Point"}
}