{
  "type": "Feature",
  "properties": {
    "iso:country":"US",
    "sg:address":"6500 N Fisk Ct",
    "sg:city":"Kansas City",
    "sg:classifiers":[
        {
            "category":"Food & Beverages",
            "subcategory":"Groceries & Convenience Stores",
            "type":"Retail Goods"
        }
    ],
    "sg:phone":"+1 816 505 2225",
    "sg:postcode":"64151",
    "sg:province":"MO",
    "wof:name":"Market Merchandisers",
    "wof:placetype":"venue"
},
  "geometry": {"coordinates":[-94.65603900000001,39.214099],"type":"Point"}
}