{
  "type": "Feature",
  "properties": {
    "iso:country":"US",
    "sg:address":"4596 Concord School Rd",
    "sg:city":"Bloomsdale",
    "sg:classifiers":[
        {
            "category":"Building & Trades",
            "subcategory":"Construction",
            "type":"Services"
        }
    ],
    "sg:phone":"+1 573 483 9669",
    "sg:postcode":"63627",
    "sg:province":"MO",
    "sg:tags":[
        "concrete",
        "contractor"
    ],
    "wof:name":"Govero Brothers Inc",
    "wof:placetype":"venue"
},
  "geometry": {"coordinates":[-90.277411,38.060015],"type":"Point"}
}