{
  "type": "Feature",
  "properties": {
    "iso:country":"US",
    "sg:address":"1628 Coronita Dr",
    "sg:city":"Fenton",
    "sg:classifiers":[
        {
            "category":"Professional",
            "subcategory":"Detective & Security Services",
            "type":"Services"
        }
    ],
    "sg:phone":"+1 636 343 0068",
    "sg:postcode":"63026",
    "sg:province":"MO",
    "sg:tags":[
        "information",
        "bureau"
    ],
    "wof:name":"Ricks Vending Service",
    "wof:placetype":"venue"
},
  "geometry": {"coordinates":[-90.47224799999999,38.527685],"type":"Point"}
}