{
  "type": "Feature",
  "properties": {
    "iso:country":"US",
    "sg:address":"815 E South St",
    "sg:city":"Richmond",
    "sg:classifiers":[
        {
            "category":"Insurance",
            "subcategory":"Hazard Insurance",
            "type":"Services"
        }
    ],
    "sg:phone":"+1 816 470 2303",
    "sg:postcode":"64085",
    "sg:province":"MO",
    "wof:name":"Shelter Insurance",
    "wof:placetype":"venue"
},
  "geometry": {"coordinates":[-93.962789,39.270811],"type":"Point"}
}