{
  "type": "Feature",
  "properties": {
    "iso:country":"US",
    "sg:address":"3067 S Westwood Blvd",
    "sg:city":"Poplar Bluff",
    "sg:classifiers":[
        {
            "category":"Restaurant",
            "type":"Food & Drink"
        }
    ],
    "sg:phone":"+1 573 785 4051",
    "sg:postcode":"63901",
    "sg:province":"MO",
    "wof:name":"Cow Shed",
    "wof:placetype":"venue"
},
  "geometry": {"coordinates":[-90.43498200000001,36.733249],"type":"Point"}
}