{
  "type": "Feature",
  "properties": {
    "iso:country":"US",
    "sg:address":"12773 Orley Dr",
    "sg:city":"Florissant",
    "sg:classifiers":[
        {
            "category":"Professional",
            "subcategory":"Computer Services",
            "type":"Services"
        }
    ],
    "sg:phone":"+1 314 741 7468",
    "sg:postcode":"63033",
    "sg:province":"MO",
    "sg:tags":[
        "related"
    ],
    "wof:name":"Bischoff Consulting Service",
    "wof:placetype":"venue"
},
  "geometry": {"coordinates":[-90.264072,38.797691],"type":"Point"}
}