{
  "type": "Feature",
  "properties": {
    "iso:country":"US",
    "sg:address":"20015 S 1125 Rd",
    "sg:city":"Stockton",
    "sg:classifiers":[
        {
            "category":"Farming",
            "subcategory":"Dairy Farm",
            "type":"Manufacturing & Wholesale Goods"
        },
        {
            "category":"Farming",
            "subcategory":"Farm",
            "type":"Manufacturing & Wholesale Goods"
        }
    ],
    "sg:phone":"+1 417 276 3070",
    "sg:postcode":"65785",
    "sg:province":"MO",
    "wof:name":"Burns Dairy",
    "wof:placetype":"venue"
},
  "geometry": {"coordinates":[-93.871782,37.637311],"type":"Point"}
}