{
  "type": "Feature",
  "properties": {
    "iso:country":"US",
    "sg:address":"1265 E Republic Rd",
    "sg:city":"Springfield",
    "sg:classifiers":[
        {
            "category":"Real Estate",
            "subcategory":"Real Estate Services",
            "type":"Services"
        }
    ],
    "sg:phone":"+1 417 889 2394",
    "sg:postcode":"65804",
    "sg:province":"MO",
    "sg:tags":[
        "company",
        "title"
    ],
    "wof:name":"Preferred Title Of Missouri",
    "wof:placetype":"venue"
},
  "geometry": {"coordinates":[-93.27670500000001,37.137756],"type":"Point"}
}