{
  "type": "Feature",
  "properties": {
    "iso:country":"US",
    "sg:address":"3267 Old Fredericktown Rd",
    "sg:city":"Farmington",
    "sg:classifiers":[
        {
            "category":"Building & Trades",
            "subcategory":"Construction",
            "type":"Services"
        }
    ],
    "sg:phone":"+1 573 701 3728",
    "sg:postcode":"63640",
    "sg:province":"MO",
    "wof:name":"Quality Builders",
    "wof:placetype":"venue"
},
  "geometry": {"coordinates":[-90.41306299999999,37.764452],"type":"Point"}
}