{
  "type": "Feature",
  "properties": {
    "iso:country":"US",
    "sg:address":"2495 Marshall Rd",
    "sg:city":"St Louis",
    "sg:classifiers":[
        {
            "category":"Education",
            "subcategory":"School",
            "type":"Public Place"
        }
    ],
    "sg:phone":"+1 636 225 5485",
    "sg:postcode":"63122",
    "sg:province":"MO",
    "wof:name":"Apprende Private School",
    "wof:placetype":"venue"
},
  "geometry": {"coordinates":[-90.45481599999999,38.556675],"type":"Point"}
}