{
  "type": "Feature",
  "properties": {
    "iso:country":"US",
    "sg:address":"114 W N Main St",
    "sg:city":"Richmond",
    "sg:classifiers":[
        {
            "category":"Professional",
            "type":"Services"
        }
    ],
    "sg:phone":"+1 816 470 5333",
    "sg:postcode":"64085",
    "sg:province":"MO",
    "wof:name":"Fine Designs",
    "wof:placetype":"venue"
},
  "geometry": {"coordinates":[-93.977726,39.279051],"type":"Point"}
}