{
  "type": "Feature",
  "properties": {
    "iso:country":"US",
    "sg:address":"2724 S Glenstone Ave",
    "sg:city":"Springfield",
    "sg:classifiers":[
        {
            "category":"Banks & Credit Unions",
            "subcategory":"Bank",
            "type":"Services"
        }
    ],
    "sg:phone":"+1 417 881 0303",
    "sg:postcode":"65804",
    "sg:province":"MO",
    "sg:tags":[
        "personal",
        "institution"
    ],
    "wof:name":"Wells Fargo",
    "wof:placetype":"venue"
},
  "geometry": {"coordinates":[-93.262415,37.165781],"type":"Point"}
}