{
  "type": "Feature",
  "properties": {
    "iso:country":"US",
    "sg:address":"807 Homecrest St",
    "sg:city":"Kennett",
    "sg:classifiers":[
        {
            "category":"Retail",
            "subcategory":"Veterinary Services",
            "type":"Services"
        }
    ],
    "sg:phone":"+1 573 888 9968",
    "sg:postcode":"63857",
    "sg:province":"MO",
    "sg:tags":[
        "clinic",
        "hospital",
        "veterinarian",
        "specialty"
    ],
    "wof:name":"KenMo Veterinary Clinic",
    "wof:placetype":"venue"
},
  "geometry": {"coordinates":[-90.068121,36.245111],"type":"Point"}
}