{
  "type": "Feature",
  "properties": {
    "iso:country":"US",
    "sg:address":"2309 Cherokee St",
    "sg:city":"St Louis",
    "sg:classifiers":[
        {
            "category":"Shopping",
            "type":"Retail Goods"
        }
    ],
    "sg:postcode":"63118",
    "sg:province":"MO",
    "wof:name":"Treasure Trove",
    "wof:placetype":"venue"
},
  "geometry": {"coordinates":[-90.224556,38.593412],"type":"Point"}
}