{
  "type": "Feature",
  "properties": {
    "iso:country":"US",
    "sg:address":"3500 Jeffco Blvd",
    "sg:city":"Arnold",
    "sg:classifiers":[
        {
            "category":"Health Services",
            "subcategory":"Doctor",
            "type":"Services"
        }
    ],
    "sg:phone":"+1 636 296 8738",
    "sg:postcode":"63010",
    "sg:province":"MO",
    "sg:tags":[
        "dentist"
    ],
    "wof:name":"Arnold Dental Care",
    "wof:placetype":"venue"
},
  "geometry": {"coordinates":[-90.376723,38.415609],"type":"Point"}
}