{
  "type": "Feature",
  "properties": {
    "iso:country":"US",
    "sg:address":"236 NW Oldham Pkwy",
    "sg:city":"Lees Summit",
    "sg:classifiers":[
        {
            "category":"Building & Trades",
            "subcategory":"Equipment Rental",
            "type":"Services"
        }
    ],
    "sg:phone":"+1 816 524 5535",
    "sg:postcode":"64081",
    "sg:province":"MO",
    "sg:tags":[
        "medical"
    ],
    "wof:name":"Medic House Inc",
    "wof:placetype":"venue"
},
  "geometry": {"coordinates":[-94.400836,38.916818],"type":"Point"}
}