{
  "type": "Feature",
  "properties": {
    "iso:country":"US",
    "sg:address":"14181 Manchester Rd",
    "sg:city":"Ballwin",
    "sg:classifiers":[
        {
            "category":"Autos & Motor Vehicles",
            "subcategory":"Fuel & Gas Station",
            "type":"Retail Goods"
        }
    ],
    "sg:phone":"+1 636 394 4130",
    "sg:postcode":"63011",
    "sg:province":"MO",
    "sg:tags":[
        "oil"
    ],
    "wof:name":"Phillips 66",
    "wof:placetype":"venue"
},
  "geometry": {"coordinates":[-90.500753,38.592903],"type":"Point"}
}