{
  "type": "Feature",
  "properties": {
    "iso:country":"US",
    "sg:address":"2223 W Sunset St",
    "sg:city":"Springfield",
    "sg:classifiers":[
        {
            "category":"Professional",
            "type":"Services"
        }
    ],
    "sg:phone":"+1 417 889 1179",
    "sg:postcode":"65807",
    "sg:province":"MO",
    "sg:tags":[
        "establishment"
    ],
    "wof:name":"Simplex Grinell",
    "wof:placetype":"venue"
},
  "geometry": {"coordinates":[-93.32186900000001,37.166878],"type":"Point"}
}