{
  "type": "Feature",
  "properties": {
    "iso:country":"US",
    "sg:address":"513 South Dr",
    "sg:city":"Marshall",
    "sg:classifiers":[
        {
            "category":"Health Services",
            "subcategory":"Nursing And Care Facility",
            "type":"Services"
        }
    ],
    "sg:phone":"+1 660 886 2697",
    "sg:postcode":"65340",
    "sg:province":"MO",
    "sg:tags":[
        "skilled"
    ],
    "wof:name":"Arrow Manor 1",
    "wof:placetype":"venue"
},
  "geometry": {"coordinates":[-93.203135,39.105305],"type":"Point"}
}