{
  "type": "Feature",
  "properties": {
    "iso:country":"US",
    "sg:address":"300 S Franklin St",
    "sg:city":"Windsor",
    "sg:classifiers":[
        {
            "category":"Utilities",
            "subcategory":"Water",
            "type":"Services"
        }
    ],
    "sg:phone":"+1 660 647 5912",
    "sg:postcode":"65360",
    "sg:province":"MO",
    "sg:tags":[
        "company-utility",
        "system",
        "supply"
    ],
    "wof:name":"Fosnow Water Hauling",
    "wof:placetype":"venue"
},
  "geometry": {"coordinates":[-93.52570299999999,38.532249],"type":"Point"}
}