{
  "type": "Feature",
  "properties": {
    "iso:country":"US",
    "sg:address":"318 S 6th St",
    "sg:city":"Saint Joseph",
    "sg:classifiers":[
        {
            "category":"Building & Trades",
            "subcategory":"Equipment Rental",
            "type":"Services"
        }
    ],
    "sg:phone":"+1 816 232 2111",
    "sg:postcode":"64501",
    "sg:province":"MO",
    "wof:name":"Rent-A-Center",
    "wof:placetype":"venue"
},
  "geometry": {"coordinates":[-94.853078,39.76433],"type":"Point"}
}