{
  "type": "Feature",
  "properties": {
    "iso:country":"US",
    "sg:address":"291 Chesterfield Mall",
    "sg:city":"Chesterfield",
    "sg:classifiers":[
        {
            "category":"Building & Trades",
            "subcategory":"Cleaning & Sanitation",
            "type":"Services"
        }
    ],
    "sg:phone":"+1 636 536 5388",
    "sg:postcode":"63017",
    "sg:province":"MO",
    "sg:tags":[
        "janitorial"
    ],
    "wof:name":"Ermc",
    "wof:placetype":"venue"
},
  "geometry": {"coordinates":[-90.565214,38.649401],"type":"Point"}
}