{
  "type": "Feature",
  "properties": {
    "iso:country":"US",
    "sg:address":"8853 NE Jackson Dr",
    "sg:city":"Hamilton",
    "sg:classifiers":[
        {
            "category":"Farming",
            "subcategory":"Dairy Farm",
            "type":"Manufacturing & Wholesale Goods"
        }
    ],
    "sg:phone":"+1 816 583 2645",
    "sg:postcode":"64644",
    "sg:province":"MO",
    "wof:name":"Cornelius Farms",
    "wof:placetype":"venue"
},
  "geometry": {"coordinates":[-93.874392,39.77964],"type":"Point"}
}