{
  "type": "Feature",
  "properties": {
    "iso:country":"US",
    "sg:address":"1801 Zumbehl Rd",
    "sg:city":"St Charles",
    "sg:classifiers":[
        {
            "category":"Restaurant",
            "type":"Food & Drink"
        }
    ],
    "sg:phone":"+1 636 947 9100",
    "sg:postcode":"63303",
    "sg:province":"MO",
    "sg:tags":[
        "eating"
    ],
    "wof:name":"Ho Ho Chinese Restaurant",
    "wof:placetype":"venue"
},
  "geometry": {"coordinates":[-90.52745899999999,38.775749],"type":"Point"}
}