{
  "type": "Feature",
  "properties": {
    "iso:country":"US",
    "sg:address":"1016 Autumn Oaks Dr",
    "sg:city":"Imperial",
    "sg:classifiers":[
        {
            "category":"Professional",
            "subcategory":"Business Services",
            "type":"Services"
        }
    ],
    "sg:phone":"+1 636 467 9925",
    "sg:postcode":"63052",
    "sg:province":"MO",
    "sg:tags":[
        "lecture",
        "bureau",
        "seminar"
    ],
    "wof:name":"National Seminars Group",
    "wof:placetype":"venue"
},
  "geometry": {"coordinates":[-90.376884,38.388064],"type":"Point"}
}