{
  "type": "Feature",
  "properties": {
    "iso:country":"US",
    "sg:address":"116 W Main St",
    "sg:city":"Washington",
    "sg:classifiers":[
        {
            "category":"Shopping",
            "subcategory":"Thrift Store",
            "type":"Retail Goods"
        },
        {
            "category":"Banks & Credit Unions",
            "subcategory":"Bank",
            "type":"Services"
        }
    ],
    "sg:phone":"+1 636 239 5750",
    "sg:postcode":"63090",
    "sg:province":"MO",
    "sg:tags":[
        "shop",
        "second",
        "hand"
    ],
    "wof:name":"The Purple Toad",
    "wof:placetype":"venue"
},
  "geometry": {"coordinates":[-91.011661,38.55997],"type":"Point"}
}