{
  "type": "Feature",
  "properties": {
    "iso:country":"US",
    "sg:address":"4660 W Florissant Ave",
    "sg:city":"St Louis",
    "sg:classifiers":[
        {
            "category":"Professional",
            "subcategory":"Computer Services",
            "type":"Services"
        }
    ],
    "sg:phone":"+1 314 382 1650",
    "sg:postcode":"63115",
    "sg:province":"MO",
    "sg:tags":[
        "website",
        "design"
    ],
    "wof:name":"Web Innovations & Tech Svc",
    "wof:placetype":"venue"
},
  "geometry": {"coordinates":[-90.231722,38.686178],"type":"Point"}
}