{
  "type": "Feature",
  "properties": {
    "addr:full":"8069 Clayton Rd St Louis MO 63117",
    "addr:housenumber":"8069",
    "addr:postcode":"63117",
    "addr:street":"Clayton Rd",
    "iso:country":"US",
    "sg:address":"8069 Clayton Rd",
    "sg:city":"St Louis",
    "sg:classifiers":[
        {
            "category":"Real Estate",
            "subcategory":"Real Estate Agent",
            "type":"Services"
        }
    ],
    "sg:phone":"+1 314 862 7500",
    "sg:postcode":"63117",
    "sg:province":"MO",
    "sg:website":"www.cbgundaker.com",
    "wof:name":"Coldwell Banker",
    "wof:placetype":"venue"
},
  "geometry": {"coordinates":[-90.345152,38.638134],"type":"Point"}
}