{
  "type": "Feature",
  "properties": {
    "iso:country":"US",
    "sg:address":"8817 S Litchford Rd",
    "sg:city":"Grain Valley",
    "sg:classifiers":[
        {
            "category":"Building & Trades",
            "subcategory":"Construction",
            "type":"Services"
        }
    ],
    "sg:phone":"+1 816 229 6496",
    "sg:postcode":"64029",
    "sg:province":"MO",
    "sg:tags":[
        "hanging",
        "contractor"
    ],
    "wof:name":"Rogers Painting",
    "wof:placetype":"venue"
},
  "geometry": {"coordinates":[-94.23674,38.95719],"type":"Point"}
}