{
  "type": "Feature",
  "properties": {
    "iso:country":"US",
    "sg:address":"1966 Randol Ave",
    "sg:city":"Cape Girardeau",
    "sg:classifiers":[
        {
            "category":"Personal",
            "type":"Services"
        }
    ],
    "sg:phone":"+1 573 334 3884",
    "sg:postcode":"63701",
    "sg:province":"MO",
    "wof:name":"Planet Tan",
    "wof:placetype":"venue"
},
  "geometry": {"coordinates":[-89.554795,37.335792],"type":"Point"}
}