{
  "type": "Feature",
  "properties": {
    "iso:country":"US",
    "sg:address":"4871 State Highway Jj",
    "sg:city":"Hollister",
    "sg:classifiers":[
        {
            "category":"Real Estate",
            "subcategory":"Real Estate Agent",
            "type":"Services"
        }
    ],
    "sg:phone":"+1 417 334 7828",
    "sg:postcode":"65672",
    "sg:province":"MO",
    "wof:name":"Benedetti Enterprises",
    "wof:placetype":"venue"
},
  "geometry": {"coordinates":[-93.166282,36.52565],"type":"Point"}
}