{
  "type": "Feature",
  "properties": {
    "iso:country":"US",
    "sg:address":"49 Ozark Ln",
    "sg:city":"Arnold",
    "sg:classifiers":[
        {
            "category":"Building & Trades",
            "subcategory":"Electrical",
            "type":"Services"
        }
    ],
    "sg:phone":"+1 636 296 5911",
    "sg:postcode":"63010",
    "sg:province":"MO",
    "sg:tags":[
        "electrical",
        "electric",
        "contractor"
    ],
    "wof:name":"Unash Electric Inc",
    "wof:placetype":"venue"
},
  "geometry": {"coordinates":[-90.460746,38.439453],"type":"Point"}
}