{
  "type": "Feature",
  "properties": {
    "iso:country":"US",
    "sg:address":"606 E Fountain Rd",
    "sg:city":"Joplin",
    "sg:classifiers":[
        {
            "category":"Freight",
            "type":"Transportation"
        }
    ],
    "sg:phone":"+1 417 626 7078",
    "sg:postcode":"64801",
    "sg:province":"MO",
    "sg:tags":[
        "commercial",
        "storage",
        "special"
    ],
    "wof:name":"T N J Mini Storage & Propertie",
    "wof:placetype":"venue"
},
  "geometry": {"coordinates":[-94.502938,37.127902],"type":"Point"}
}