{
  "type": "Feature",
  "properties": {
    "iso:country":"US",
    "sg:address":"510 W 12th St",
    "sg:city":"Lamar",
    "sg:classifiers":[
        {
            "category":"Wholesale",
            "subcategory":"Hardware",
            "type":"Manufacturing & Wholesale Goods"
        },
        {
            "category":"Home & Garden",
            "subcategory":"Garden Supply",
            "type":"Retail Goods"
        },
        {
            "category":"Retail",
            "subcategory":"Repair Shop",
            "type":"Services"
        }
    ],
    "sg:phone":"+1 417 682 5556",
    "sg:postcode":"64759",
    "sg:province":"MO",
    "sg:tags":[
        "renting",
        "lawn",
        "outdoor",
        "power",
        "landscaping",
        "equipment-sales",
        "equipment",
        "saw"
    ],
    "sg:website":"http://www.stihldealer.net/default-dealer-012080.aspx",
    "wof:name":"Legacy Farm and Lawn",
    "wof:placetype":"venue"
},
  "geometry": {"coordinates":[-94.282232,37.493464],"type":"Point"}
}