{
  "type": "Feature",
  "properties": {
    "iso:country":"US",
    "sg:address":"13673 State Hwy 53",
    "sg:city":"Qulin",
    "sg:classifiers":[
        {
            "category":"Farming",
            "subcategory":"Farm & Veterinary Services",
            "type":"Manufacturing & Wholesale Goods"
        }
    ],
    "sg:phone":"+1 573 328 4338",
    "sg:postcode":"63961",
    "sg:province":"MO",
    "sg:tags":[
        "aerial",
        "applicator"
    ],
    "wof:name":"Horner Flying Ser",
    "wof:placetype":"venue"
},
  "geometry": {"coordinates":[-90.24910300000001,36.592347],"type":"Point"}
}