{
  "type": "Feature",
  "properties": {
    "iso:country":"US",
    "sg:address":"610 NW 1751st Rd",
    "sg:city":"Kingsville",
    "sg:classifiers":[
        {
            "category":"Manufacturing",
            "subcategory":"Tools & Machinery",
            "type":"Manufacturing & Wholesale Goods"
        }
    ],
    "sg:phone":"+1 816 697 2886",
    "sg:postcode":"64061",
    "sg:province":"MO",
    "sg:tags":[
        "equipment",
        "conveyor",
        "conveying"
    ],
    "wof:name":"Ward LTD",
    "wof:placetype":"venue"
},
  "geometry": {"coordinates":[-94.074437,38.860829],"type":"Point"}
}