{
  "type": "Feature",
  "properties": {
    "iso:country":"US",
    "sg:address":"7005 E Farm Rd 156",
    "sg:city":"Rogersville",
    "sg:classifiers":[
        {
            "category":"Building & Trades",
            "subcategory":"Construction",
            "type":"Services"
        }
    ],
    "sg:phone":"+1 417 882 8899",
    "sg:postcode":"65742",
    "sg:province":"MO",
    "sg:tags":[
        "carpentry",
        "contractor"
    ],
    "wof:name":"Classic Woods",
    "wof:placetype":"venue"
},
  "geometry": {"coordinates":[-93.144215,37.163487],"type":"Point"}
}