{
  "type": "Feature",
  "properties": {
    "iso:country":"US",
    "sg:address":"125 E 8th St",
    "sg:city":"Fort Leonard Wood",
    "sg:classifiers":[
        {
            "category":"Government",
            "subcategory":"Office",
            "type":"Public Place"
        }
    ],
    "sg:phone":"+1 573 596 0629",
    "sg:postcode":"65401",
    "sg:province":"MO",
    "sg:tags":[
        "national",
        "security"
    ],
    "wof:name":"Legal Assistance",
    "wof:placetype":"venue"
},
  "geometry": {"coordinates":[-91.77014,37.950018],"type":"Point"}
}