{
  "type": "Feature",
  "properties": {
    "iso:country":"US",
    "sg:address":"7000 Clayton Rd",
    "sg:city":"Saint Louis",
    "sg:classifiers":[
        {
            "category":"Shopping",
            "subcategory":"Florist",
            "type":"Retail Goods"
        }
    ],
    "sg:phone":"+1 314 644 3566",
    "sg:postcode":"63117",
    "sg:province":"MO",
    "sg:tags":[
        "fresh",
        "flower",
        "artificial"
    ],
    "wof:name":"Waldbart Alex Florist",
    "wof:placetype":"venue"
},
  "geometry": {"coordinates":[-90.319199,38.634899],"type":"Point"}
}