{
  "type": "Feature",
  "properties": {
    "iso:country":"US",
    "sg:address":"432 N Scott Ave",
    "sg:city":"Belton",
    "sg:classifiers":[
        {
            "category":"Autos & Motor Vehicles",
            "subcategory":"Automobile Sales",
            "type":"Retail Goods"
        }
    ],
    "sg:phone":"+1 816 318 1000",
    "sg:postcode":"64012",
    "sg:province":"MO",
    "sg:tags":[
        "used"
    ],
    "wof:name":"Holtzen Auto Sales",
    "wof:placetype":"venue"
},
  "geometry": {"coordinates":[-94.534487,38.820843],"type":"Point"}
}