{
  "type": "Feature",
  "properties": {
    "iso:country":"US",
    "sg:address":"1109 Bus Loop 70 E",
    "sg:city":"Columbia",
    "sg:classifiers":[
        {
            "category":"Personal",
            "subcategory":"Beauty Salon",
            "type":"Services"
        }
    ],
    "sg:phone":"+1 573 442 3464",
    "sg:postcode":"65201",
    "sg:province":"MO",
    "sg:tags":[
        "shop",
        "manicuring"
    ],
    "wof:name":"Lucky Nails",
    "wof:placetype":"venue"
},
  "geometry": {"coordinates":[-92.32449,38.96405],"type":"Point"}
}