{
  "type": "Feature",
  "properties": {
    "iso:country":"US",
    "sg:address":"1409 W Center St",
    "sg:city":"Salem",
    "sg:classifiers":[
        {
            "category":"Home & Garden",
            "subcategory":"Building Materials",
            "type":"Retail Goods"
        }
    ],
    "sg:phone":"+1 573 729 2794",
    "sg:postcode":"65560",
    "sg:province":"MO",
    "sg:tags":[
        "lumber"
    ],
    "wof:name":"Spencer Lumber LLC",
    "wof:placetype":"venue"
},
  "geometry": {"coordinates":[-91.553653,37.643366],"type":"Point"}
}