{
  "type": "Feature",
  "properties": {
    "iso:country":"US",
    "sg:address":"1699 W 5th St",
    "sg:city":"Eureka",
    "sg:classifiers":[
        {
            "category":"Autos & Motor Vehicles",
            "subcategory":"Automobile Sales",
            "type":"Retail Goods"
        },
        {
            "category":"Retail",
            "subcategory":"Auto Rental",
            "type":"Services"
        },
        {
            "category":"Building & Trades",
            "subcategory":"Equipment Rental",
            "type":"Services"
        }
    ],
    "sg:phone":"+1 636 587 2070",
    "sg:postcode":"63025",
    "sg:province":"MO",
    "sg:tags":[
        "truck",
        "used",
        "moving"
    ],
    "sg:website":"http://budgettruck.com/IYP_tl",
    "wof:name":"Eureka Self Storage DBA/Budget Truck Rental",
    "wof:placetype":"venue"
},
  "geometry": {"coordinates":[-90.661743,38.50449],"type":"Point"}
}