{
  "type": "Feature",
  "properties": {
    "iso:country":"US",
    "sg:address":"208 W Main St",
    "sg:city":"Cole Camp",
    "sg:classifiers":[
        {
            "category":"Organizations",
            "subcategory":"Membership Organization",
            "type":"Services"
        }
    ],
    "sg:phone":"+1 660 668 3677",
    "sg:postcode":"65325",
    "sg:province":"MO",
    "wof:name":"J CS",
    "wof:placetype":"venue"
},
  "geometry": {"coordinates":[-93.206137,38.460416],"type":"Point"}
}