{
  "type": "Feature",
  "properties": {
    "iso:country":"US",
    "sg:address":"1663 Fenton Business Park Ct",
    "sg:city":"Fenton",
    "sg:classifiers":[
        {
            "category":"Manufacturing",
            "subcategory":"Tools & Machinery",
            "type":"Manufacturing & Wholesale Goods"
        }
    ],
    "sg:phone":"+1 636 343 8300",
    "sg:postcode":"63026",
    "sg:province":"MO",
    "sg:tags":[
        "dental",
        "mfg"
    ],
    "wof:name":"Spartan Marketing Group",
    "wof:placetype":"venue"
},
  "geometry": {"coordinates":[-90.44703,38.541035],"type":"Point"}
}