{
  "type": "Feature",
  "properties": {
    "iso:country":"US",
    "sg:address":"572 Hitching Post Dr",
    "sg:city":"St Charles",
    "sg:classifiers":[
        {
            "category":"Building & Trades",
            "subcategory":"Construction",
            "type":"Services"
        }
    ],
    "sg:phone":"+1 636 928 6700",
    "sg:postcode":"63304",
    "sg:province":"MO",
    "sg:tags":[
        "repairing",
        "nonresidential",
        "remodeling",
        "contractor"
    ],
    "wof:name":"Distinctive Contracting",
    "wof:placetype":"venue"
},
  "geometry": {"coordinates":[-90.602284,38.723236],"type":"Point"}
}