{
  "type": "Feature",
  "properties": {
    "iso:country":"US",
    "sg:address":"11902 Blue Ridge Ext",
    "sg:city":"Grandview",
    "sg:classifiers":[
        {
            "category":"Deli",
            "type":"Food & Drink"
        },
        {
            "category":"Food & Beverages",
            "subcategory":"Liquor & Beverages",
            "type":"Retail Goods"
        }
    ],
    "sg:phone":"+1 816 767 8100",
    "sg:postcode":"64030",
    "sg:province":"MO",
    "sg:tags":[
        "delicatessen",
        "ale",
        "beer",
        "store"
    ],
    "wof:name":"Bi-Rite Liquors",
    "wof:placetype":"venue"
},
  "geometry": {"coordinates":[-94.524397,38.907803],"type":"Point"}
}