{
  "type": "Feature",
  "properties": {
    "iso:country":"US",
    "sg:address":"13835 Botts Rd",
    "sg:city":"Grandview",
    "sg:phone":"+1 816 761 2700",
    "sg:postcode":"64030",
    "sg:province":"MO",
    "sg:tags":[
        "scale"
    ],
    "wof:name":"Mettler-Toledo Inc",
    "wof:placetype":"venue"
},
  "geometry": {"coordinates":[-94.54520599999999,38.873538],"type":"Point"}
}