{
  "type": "Feature",
  "properties": {
    "iso:country":"US",
    "sg:address":"17221 Chesterfield Airport Rd",
    "sg:city":"Chesterfield",
    "sg:classifiers":[
        {
            "category":"Shopping",
            "subcategory":"Used Merchandise",
            "type":"Retail Goods"
        }
    ],
    "sg:phone":"+1 636 532 8999",
    "sg:postcode":"63005",
    "sg:province":"MO",
    "wof:name":"Act II",
    "wof:placetype":"venue"
},
  "geometry": {"coordinates":[-90.59303199999999,38.668519],"type":"Point"}
}