{
  "type": "Feature",
  "properties": {
    "iso:country":"US",
    "sg:address":"3019 Jules St",
    "sg:city":"St Joseph",
    "sg:classifiers":[
        {
            "category":"Professional",
            "type":"Services"
        },
        {
            "category":"Personal",
            "type":"Services"
        }
    ],
    "sg:phone":"+1 816 233 4636",
    "sg:postcode":"64501",
    "sg:province":"MO",
    "sg:tags":[
        "miscellaneous",
        "errand"
    ],
    "wof:name":"Errands R US",
    "wof:placetype":"venue"
},
  "geometry": {"coordinates":[-94.818144,39.768459],"type":"Point"}
}