{
  "type": "Feature",
  "properties": {
    "iso:country":"US",
    "sg:address":"503 Windsor Mill Dr",
    "sg:city":"Ballwin",
    "sg:classifiers":[
        {
            "category":"Education",
            "subcategory":"Music School",
            "type":"Public Place"
        }
    ],
    "sg:phone":"+1 636 230 9884",
    "sg:postcode":"63011",
    "sg:province":"MO",
    "sg:tags":[
        "instruction-instrumental"
    ],
    "wof:name":"Jennifer Spohr Piano Studio",
    "wof:placetype":"venue"
},
  "geometry": {"coordinates":[-90.542114,38.600772],"type":"Point"}
}