{
  "type": "Feature",
  "properties": {
    "addr:full":"1000 Pat Nash Dr Ste 12 Branson MO 65616",
    "addr:housenumber":"1000",
    "addr:postcode":"65616",
    "addr:street":"Pat Nash Dr Ste 12",
    "iso:country":"US",
    "sg:address":"1000 Pat Nash Dr Ste 12",
    "sg:city":"Branson",
    "sg:classifiers":[
        {
            "category":"Shopping",
            "subcategory":"Shoes",
            "type":"Retail Goods"
        }
    ],
    "sg:phone":"+1 417 337 5651",
    "sg:postcode":"65616",
    "sg:province":"MO",
    "sg:tags":[
        "store"
    ],
    "wof:name":"Naturalizer",
    "wof:placetype":"venue"
},
  "geometry": {"coordinates":[-93.28038599999999,36.645341],"type":"Point"}
}