{
  "type": "Feature",
  "properties": {
    "iso:country":"US",
    "sg:address":"11503 Saint Charles Rock Rd",
    "sg:city":"Bridgeton",
    "sg:classifiers":[
        {
            "category":"Autos & Motor Vehicles",
            "subcategory":"Automobile Sales",
            "type":"Retail Goods"
        }
    ],
    "sg:phone":"+1 314 291 2050",
    "sg:postcode":"63044",
    "sg:province":"MO",
    "sg:tags":[
        "body",
        "repair",
        "general"
    ],
    "wof:name":"Don Schunk Chrysler Plymouth",
    "wof:placetype":"venue"
},
  "geometry": {"coordinates":[-90.405525,38.741393],"type":"Point"}
}