{
  "type": "Feature",
  "properties": {
    "iso:country":"US",
    "sg:address":"5976 Howdershell Rd Ste 113",
    "sg:city":"Hazelwood",
    "sg:classifiers":[
        {
            "category":"Real Estate",
            "subcategory":"Real Estate Services",
            "type":"Services"
        },
        {
            "category":"Real Estate",
            "subcategory":"Real Estate Agent",
            "type":"Services"
        }
    ],
    "sg:phone":"+1 314 731 4445",
    "sg:postcode":"63042",
    "sg:province":"MO",
    "sg:tags":[
        "buyer",
        "broker"
    ],
    "wof:name":"Property Valuations Group",
    "wof:placetype":"venue"
},
  "geometry": {"coordinates":[-90.388622,38.781635],"type":"Point"}
}