{
  "type": "Feature",
  "properties": {
    "iso:country":"US",
    "sg:address":"6206 28th St Ter",
    "sg:city":"Saint Joseph",
    "sg:classifiers":[
        {
            "category":"Social Services",
            "subcategory":"Child Care",
            "type":"Services"
        }
    ],
    "sg:phone":"+1 816 233 4273",
    "sg:postcode":"64505",
    "sg:province":"MO",
    "sg:tags":[
        "day"
    ],
    "wof:name":"Marjories Day Care",
    "wof:placetype":"venue"
},
  "geometry": {"coordinates":[-94.82677,39.822017],"type":"Point"}
}