{
  "type": "Feature",
  "properties": {
    "iso:country":"US",
    "sg:address":"6250 Page Ave",
    "sg:city":"Saint Louis",
    "sg:classifiers":[
        {
            "category":"Shopping",
            "subcategory":"Mobile Phones",
            "type":"Retail Goods"
        }
    ],
    "sg:phone":"+1 314 727 2789",
    "sg:postcode":"63133",
    "sg:province":"MO",
    "wof:name":"Skylink Cellular",
    "wof:placetype":"venue"
},
  "geometry": {"coordinates":[-90.292599,38.671411],"type":"Point"}
}