{
  "type": "Feature",
  "properties": {
    "iso:country":"US",
    "sg:address":"720 E Pacific Ave",
    "sg:city":"Saint Louis",
    "sg:classifiers":[
        {
            "category":"Manufacturing",
            "subcategory":"Tools & Machinery",
            "type":"Manufacturing & Wholesale Goods"
        }
    ],
    "sg:phone":"+1 314 660 4090",
    "sg:postcode":"63119",
    "sg:province":"MO",
    "sg:tags":[
        "platform",
        "mfg"
    ],
    "wof:name":"Pacific Equipment Group Inc",
    "wof:placetype":"venue"
},
  "geometry": {"coordinates":[-90.33750499999999,38.607328],"type":"Point"}
}