{
  "type": "Feature",
  "properties": {
    "iso:country":"US",
    "sg:address":"2531 Prospect Ave",
    "sg:city":"Kansas City",
    "sg:classifiers":[
        {
            "category":"Professional",
            "subcategory":"Business Services",
            "type":"Services"
        }
    ],
    "sg:phone":"+1 816 241 7143",
    "sg:postcode":"64127",
    "sg:province":"MO",
    "sg:tags":[
        "food",
        "vending",
        "catering"
    ],
    "wof:name":"Springer Food Service LLC",
    "wof:placetype":"venue"
},
  "geometry": {"coordinates":[-94.55230299999999,39.079459],"type":"Point"}
}