{
  "type": "Feature",
  "properties": {
    "iso:country":"US",
    "sg:address":"679 Jeffco Blvd",
    "sg:city":"Arnold",
    "sg:classifiers":[
        {
            "category":"Banks & Credit Unions",
            "subcategory":"Bank",
            "type":"Services"
        }
    ],
    "sg:phone":"+1 636 296 3331",
    "sg:postcode":"63010",
    "sg:province":"MO",
    "sg:tags":[
        "cashing",
        "sell",
        "money",
        "order",
        "check"
    ],
    "wof:name":"ACE Cash Express",
    "wof:placetype":"venue"
},
  "geometry": {"coordinates":[-90.36581099999999,38.450744],"type":"Point"}
}