{
  "type": "Feature",
  "properties": {
    "iso:country":"US",
    "sg:address":"405 Dairy St",
    "sg:city":"Monett",
    "sg:classifiers":[
        {
            "category":"Social Services",
            "type":"Services"
        }
    ],
    "sg:phone":"+1 417 235 3285",
    "sg:postcode":"65708",
    "sg:province":"MO",
    "sg:tags":[
        "consulting",
        "geriatric"
    ],
    "wof:name":"Southwest Missouri Office On Aging",
    "wof:placetype":"venue"
},
  "geometry": {"coordinates":[-93.918495,36.915945],"type":"Point"}
}