{
  "type": "Feature",
  "properties": {
    "iso:country":"US",
    "sg:address":"361 S 1st St",
    "sg:city":"Owensville",
    "sg:classifiers":[
        {
            "category":"Health Services",
            "subcategory":"Doctor",
            "type":"Services"
        }
    ],
    "sg:phone":"+1 573 764 3913",
    "sg:postcode":"65066",
    "sg:province":"MO",
    "sg:tags":[
        "medical"
    ],
    "wof:name":"Gerald Chriopractic",
    "wof:placetype":"venue"
},
  "geometry": {"coordinates":[-91.50055399999999,38.344395],"type":"Point"}
}