{
  "type": "Feature",
  "properties": {
    "iso:country":"US",
    "sg:address":"2207 NE 58 Ter",
    "sg:city":"Kansas City",
    "sg:classifiers":[
        {
            "category":"Professional",
            "subcategory":"Employment Agencies",
            "type":"Services"
        }
    ],
    "sg:phone":"+1 816 353 6196",
    "sg:postcode":"64118",
    "sg:province":"MO",
    "sg:tags":[
        "help",
        "supply"
    ],
    "wof:name":"Alta Falke",
    "wof:placetype":"venue"
},
  "geometry": {"coordinates":[-94.553433,39.199714],"type":"Point"}
}