{
  "type": "Feature",
  "properties": {
    "iso:country":"US",
    "sg:address":"12755 Olive Blvd",
    "sg:city":"Saint Louis",
    "sg:classifiers":[
        {
            "category":"Insurance",
            "subcategory":"Hazard Insurance",
            "type":"Services"
        }
    ],
    "sg:phone":"+1 314 434 7592",
    "sg:postcode":"63141",
    "sg:province":"MO",
    "sg:tags":[
        "carrier",
        "public"
    ],
    "wof:name":"F D I C",
    "wof:placetype":"venue"
},
  "geometry": {"coordinates":[-90.472675,38.679995],"type":"Point"}
}