{
  "type": "Feature",
  "properties": {
    "iso:country":"US",
    "sg:address":"6903 Manchester Ave",
    "sg:city":"Saint Louis",
    "sg:classifiers":[
        {
            "category":"Communications",
            "subcategory":"Newspaper",
            "type":"Services"
        }
    ],
    "sg:phone":"+1 314 646 1902",
    "sg:postcode":"63143",
    "sg:province":"MO",
    "sg:tags":[
        "print",
        "medium"
    ],
    "wof:name":"Louie Magazine",
    "wof:placetype":"venue"
},
  "geometry": {"coordinates":[-90.306962,38.617333],"type":"Point"}
}