{
  "type": "Feature",
  "properties": {
    "iso:country":"US",
    "sg:address":"24 Chaminade Dr",
    "sg:city":"Saint Louis",
    "sg:classifiers":[
        {
            "category":"Building & Trades",
            "subcategory":"Construction",
            "type":"Services"
        }
    ],
    "sg:phone":"+1 314 997 9113",
    "sg:postcode":"63141",
    "sg:province":"MO",
    "sg:tags":[
        "house"
    ],
    "wof:name":"Rien Development",
    "wof:placetype":"venue"
},
  "geometry": {"coordinates":[-90.41374999999999,38.6482],"type":"Point"}
}