{
  "type": "Feature",
  "properties": {
    "iso:country":"US",
    "sg:address":"6100 S Grand Blvd",
    "sg:city":"Saint Louis",
    "sg:classifiers":[
        {
            "category":"Professional",
            "subcategory":"Lawyer & Legal Services",
            "type":"Services"
        }
    ],
    "sg:phone":"+1 314 352 0505",
    "sg:postcode":"63111",
    "sg:province":"MO",
    "wof:name":"Kriegel and Ituarte PC",
    "wof:placetype":"venue"
},
  "geometry": {"coordinates":[-90.25728599999999,38.56518],"type":"Point"}
}