{
  "type": "Feature",
  "properties": {
    "iso:country":"US",
    "sg:address":"27104 E Argo Rd",
    "sg:city":"Independence",
    "sg:classifiers":[
        {
            "category":"Building & Trades",
            "subcategory":"Construction",
            "type":"Services"
        }
    ],
    "sg:phone":"+1 816 220 0008",
    "sg:postcode":"64057",
    "sg:province":"MO",
    "sg:tags":[
        "concrete",
        "contractor"
    ],
    "wof:name":"Independent Finishing Con Co",
    "wof:placetype":"venue"
},
  "geometry": {"coordinates":[-94.266614,39.067248],"type":"Point"}
}