{
  "type": "Feature",
  "properties": {
    "iso:country":"US",
    "sg:address":"313 Bedford Dr",
    "sg:city":"Warrenton",
    "sg:classifiers":[
        {
            "category":"Building & Trades",
            "subcategory":"Construction",
            "type":"Services"
        }
    ],
    "sg:phone":"+1 636 456 3439",
    "sg:postcode":"63383",
    "sg:province":"MO",
    "sg:tags":[
        "repair",
        "handyman",
        "maintenance",
        "home"
    ],
    "wof:name":"Git R Done",
    "wof:placetype":"venue"
},
  "geometry": {"coordinates":[-91.13156,38.821794],"type":"Point"}
}