{
  "type": "Feature",
  "properties": {
    "iso:country":"US",
    "sg:address":"1304 W Battlefield Rd",
    "sg:city":"Springfield",
    "sg:classifiers":[
        {
            "category":"Professional",
            "subcategory":"Lawyer & Legal Services",
            "type":"Services"
        }
    ],
    "sg:phone":"+1 417 887 3434",
    "sg:postcode":"65807",
    "sg:province":"MO",
    "wof:name":"Daniel P Ramsdell & Associates",
    "wof:placetype":"venue"
},
  "geometry": {"coordinates":[-93.311053,37.160085],"type":"Point"}
}