{
  "type": "Feature",
  "properties": {
    "iso:country":"US",
    "sg:address":"601 W Mohawk Rd",
    "sg:city":"Chillicothe",
    "sg:classifiers":[
        {
            "category":"Government",
            "subcategory":"Office",
            "type":"Public Place"
        }
    ],
    "sg:phone":"+1 660 646 0024",
    "sg:postcode":"64601",
    "sg:province":"MO",
    "sg:tags":[
        "state",
        "program"
    ],
    "wof:name":"Design & Construction",
    "wof:placetype":"venue"
},
  "geometry": {"coordinates":[-93.551345,39.818875],"type":"Point"}
}