{
  "type": "Feature",
  "properties": {
    "iso:country":"US",
    "sg:address":"704 W Battlefield Rd",
    "sg:city":"Springfield",
    "sg:classifiers":[
        {
            "category":"Manufacturing",
            "subcategory":"Electronics",
            "type":"Manufacturing & Wholesale Goods"
        }
    ],
    "sg:phone":"+1 417 887 3770",
    "sg:postcode":"65807",
    "sg:province":"MO",
    "sg:tags":[
        "mfg",
        "wiring",
        "component",
        "devices",
        "conductive",
        "electronic"
    ],
    "wof:name":"Tytewadd Power Filters",
    "wof:placetype":"venue"
},
  "geometry": {"coordinates":[-93.300856,37.159912],"type":"Point"}
}