{
  "type": "Feature",
  "properties": {
    "iso:country":"US",
    "sg:address":"4166 Olive",
    "sg:city":"St Louis",
    "sg:classifiers":[
        {
            "category":"Sports & Exercise",
            "subcategory":"Gym",
            "type":"Entertainment"
        }
    ],
    "sg:phone":"+1 314 534 9200",
    "sg:postcode":"63108",
    "sg:province":"MO",
    "sg:website":"www.theboxinggym-stl.com/",
    "wof:name":"The Boxing Gym",
    "wof:placetype":"venue"
},
  "geometry": {"coordinates":[-90.2457,38.644088],"type":"Point"}
}