{
  "type": "Feature",
  "properties": {
    "iso:country":"US",
    "sg:address":"5 S Vandeventer Ave",
    "sg:city":"Saint Louis",
    "sg:classifiers":[
        {
            "category":"Restaurant",
            "type":"Food & Drink"
        }
    ],
    "sg:phone":"+1 314 652 0171",
    "sg:postcode":"63108",
    "sg:province":"MO",
    "wof:name":"Niner Diner the",
    "wof:placetype":"venue"
},
  "geometry": {"coordinates":[-90.241798,38.636002],"type":"Point"}
}