{
  "type": "Feature",
  "properties": {
    "iso:country":"US",
    "sg:address":"326 S Highway J Kk",
    "sg:city":"Lamar",
    "sg:classifiers":[
        {
            "category":"Farming",
            "subcategory":"Livestock Farm",
            "type":"Manufacturing & Wholesale Goods"
        }
    ],
    "sg:phone":"+1 417 682 2843",
    "sg:postcode":"64759",
    "sg:province":"MO",
    "sg:tags":[
        "ranch"
    ],
    "wof:name":"Max Todd",
    "wof:placetype":"venue"
},
  "geometry": {"coordinates":[-94.354389,37.450245],"type":"Point"}
}