{
  "type": "Feature",
  "properties": {
    "iso:country":"US",
    "sg:address":"1925 Central St",
    "sg:city":"Kansas City",
    "sg:classifiers":[
        {
            "category":"Professional",
            "subcategory":"Employment Agencies",
            "type":"Services"
        }
    ],
    "sg:phone":"+1 816 931 8988",
    "sg:postcode":"64108",
    "sg:province":"MO",
    "sg:tags":[
        "consultant",
        "staffing"
    ],
    "wof:name":"Nash Resources Inc",
    "wof:placetype":"venue"
},
  "geometry": {"coordinates":[-94.587468,39.089199],"type":"Point"}
}