{
  "type": "Feature",
  "properties": {
    "iso:country":"US",
    "sg:address":"103 S Diamond Loop",
    "sg:city":"Diamond",
    "sg:classifiers":[
        {
            "category":"Building & Trades",
            "subcategory":"Electrical",
            "type":"Services"
        }
    ],
    "sg:phone":"+1 417 325 5101",
    "sg:postcode":"64840",
    "sg:province":"MO",
    "sg:tags":[
        "electrical",
        "contractor"
    ],
    "wof:name":"C&D Electric",
    "wof:placetype":"venue"
},
  "geometry": {"coordinates":[-94.31774900000001,36.999032],"type":"Point"}
}