{
  "type": "Feature",
  "properties": {
    "iso:country":"US",
    "sg:address":"38 N 8th St",
    "sg:city":"Columbia",
    "sg:classifiers":[
        {
            "category":"Bars & Pubs",
            "type":"Food & Drink"
        }
    ],
    "sg:phone":"+1 573 443 6996",
    "sg:postcode":"65201",
    "sg:province":"MO",
    "wof:name":"Otto's Corner Bar & Grill",
    "wof:placetype":"venue"
},
  "geometry": {"coordinates":[-92.328525,38.951697],"type":"Point"}
}