{
  "type": "Feature",
  "properties": {
    "iso:country":"US",
    "sg:address":"501 S Broadway",
    "sg:city":"Salisbury",
    "sg:classifiers":[
        {
            "category":"Education",
            "subcategory":"Library",
            "type":"Public Place"
        }
    ],
    "sg:phone":"+1 660 388 5712",
    "sg:postcode":"65281",
    "sg:province":"MO",
    "wof:name":"Dulany Memorial Library",
    "wof:placetype":"venue"
},
  "geometry": {"coordinates":[-92.801528,39.420601],"type":"Point"}
}