{
  "type": "Feature",
  "properties": {
    "iso:country":"US",
    "sg:address":"135 N Meramec Ave",
    "sg:city":"Saint Louis",
    "sg:classifiers":[
        {
            "category":"Professional",
            "subcategory":"Lawyer & Legal Services",
            "type":"Services"
        }
    ],
    "sg:phone":"+1 314 726 2131",
    "sg:postcode":"63105",
    "sg:province":"MO",
    "wof:name":"Hirschfeld Mark Atty At Law",
    "wof:placetype":"venue"
},
  "geometry": {"coordinates":[-90.33945799999999,38.652097],"type":"Point"}
}