{
  "type": "Feature",
  "properties": {
    "iso:country":"US",
    "sg:address":"3210 Bluff Creek Dr",
    "sg:city":"Columbia",
    "sg:classifiers":[
        {
            "category":"Banks & Credit Unions",
            "subcategory":"Bank",
            "type":"Services"
        }
    ],
    "sg:phone":"+1 573 441 7044",
    "sg:postcode":"65201",
    "sg:province":"MO",
    "sg:tags":[
        "financial",
        "loan",
        "commercial",
        "residential"
    ],
    "wof:name":"Vertical Group LLC",
    "wof:placetype":"venue"
},
  "geometry": {"coordinates":[-92.298109,38.916],"type":"Point"}
}