{
  "type": "Feature",
  "properties": {
    "iso:country":"US",
    "sg:address":"130 E Loch Lloyd Pkwy",
    "sg:city":"Vlg Loch Lloyd",
    "sg:classifiers":[
        {
            "category":"Health Services",
            "subcategory":"Health Practitioner",
            "type":"Services"
        }
    ],
    "sg:phone":"+1 816 318 8681",
    "sg:postcode":"64012",
    "sg:province":"MO",
    "sg:tags":[
        "nutritionist"
    ],
    "wof:name":"Bio Nutrition LLC",
    "wof:placetype":"venue"
},
  "geometry": {"coordinates":[-94.599351,38.832744],"type":"Point"}
}