{
  "type": "Feature",
  "properties": {
    "addr:full":"1900 Bus Loop 70 E Columbia MO 65201",
    "addr:housenumber":"70 e",
    "addr:postcode":"1900;65201",
    "addr:street":"Bus Loop",
    "iso:country":"US",
    "sg:address":"1900 Bus Loop 70 E",
    "sg:city":"Columbia",
    "sg:classifiers":[
        {
            "category":"Home & Garden",
            "subcategory":"Hardware",
            "type":"Retail Goods"
        }
    ],
    "sg:phone":"+1 573 449 7277",
    "sg:postcode":"65201",
    "sg:province":"MO",
    "wof:name":"Westlake Ace Hardware",
    "wof:placetype":"venue"
},
  "geometry": {"coordinates":[-92.30873,38.96385],"type":"Point"}
}