{
  "type": "Feature",
  "properties": {
    "iso:country":"US",
    "sg:address":"8744 Watson Rd",
    "sg:city":"St Louis",
    "sg:classifiers":[
        {
            "category":"Retail",
            "subcategory":"Auto Repair",
            "type":"Services"
        }
    ],
    "sg:phone":"+1 314 843 1122",
    "sg:postcode":"63119",
    "sg:province":"MO",
    "sg:tags":[
        "transmission"
    ],
    "wof:name":"Cottman Transmissions Comm Crp",
    "wof:placetype":"venue"
},
  "geometry": {"coordinates":[-90.363046,38.564131],"type":"Point"}
}