{
  "type": "Feature",
  "properties": {
    "iso:country":"US",
    "sg:address":"180 Main St",
    "sg:city":"Morrison",
    "sg:classifiers":[
        {
            "category":"Bars & Pubs",
            "type":"Food & Drink"
        }
    ],
    "sg:phone":"+1 573 294 0404",
    "sg:postcode":"65061",
    "sg:province":"MO",
    "sg:tags":[
        "drinking"
    ],
    "wof:name":"Morrison Bar & Grill",
    "wof:placetype":"venue"
},
  "geometry": {"coordinates":[-91.63110399999999,38.671576],"type":"Point"}
}