{
  "type": "Feature",
  "properties": {
    "iso:country":"US",
    "sg:address":"513 Clark St",
    "sg:city":"St Charles",
    "sg:classifiers":[
        {
            "category":"Wholesale",
            "subcategory":"Sporting Goods",
            "type":"Manufacturing & Wholesale Goods"
        },
        {
            "category":"Shopping",
            "subcategory":"Bicycles & Sporting Goods",
            "type":"Retail Goods"
        }
    ],
    "sg:phone":"+1 636 255 0707",
    "sg:postcode":"63301",
    "sg:province":"MO",
    "sg:tags":[
        "equipment",
        "s",
        "diver",
        "supply"
    ],
    "wof:name":"Midwest Scuba",
    "wof:placetype":"venue"
},
  "geometry": {"coordinates":[-90.484404,38.786318],"type":"Point"}
}