{
  "type": "Feature",
  "properties": {
    "iso:country":"US",
    "sg:address":"4 Timber Creek Dr",
    "sg:city":"Platte City",
    "sg:classifiers":[
        {
            "category":"Wholesale",
            "subcategory":"Construction Materials",
            "type":"Manufacturing & Wholesale Goods"
        }
    ],
    "sg:phone":"+1 816 464 5045",
    "sg:postcode":"64079",
    "sg:province":"MO",
    "sg:tags":[
        "timberland",
        "company",
        "timber"
    ],
    "wof:name":"Timber Creek Dev Co",
    "wof:placetype":"venue"
},
  "geometry": {"coordinates":[-94.73280699999999,39.3571],"type":"Point"}
}