{
  "type": "Feature",
  "properties": {
    "iso:country":"US",
    "sg:address":"10000 NW Prairie View Rd",
    "sg:city":"Kansas City",
    "sg:classifiers":[
        {
            "category":"Wholesale",
            "subcategory":"Electrical",
            "type":"Manufacturing & Wholesale Goods"
        }
    ],
    "sg:phone":"+1 816 436 2120",
    "sg:postcode":"64153",
    "sg:province":"MO",
    "sg:tags":[
        "lighting",
        "fixture"
    ],
    "sg:website":"www.designlighting.com",
    "wof:name":"Design Lighting Inc",
    "wof:placetype":"venue"
},
  "geometry": {"coordinates":[-94.67137200000001,39.275141],"type":"Point"}
}