{
  "type": "Feature",
  "properties": {
    "iso:country":"US",
    "sg:address":"502 Airport Rd",
    "sg:city":"Ferguson",
    "sg:classifiers":[
        {
            "category":"Retail",
            "subcategory":"Auto Rental",
            "type":"Services"
        }
    ],
    "sg:phone":"+1 314 524 4001",
    "sg:postcode":"63135",
    "sg:province":"MO",
    "sg:tags":[
        "renting",
        "automobile"
    ],
    "wof:name":"Aboard Rent A Car",
    "wof:placetype":"venue"
},
  "geometry": {"coordinates":[-90.31130899999999,38.747157],"type":"Point"}
}