{
  "type": "Feature",
  "properties": {
    "iso:country":"US",
    "sg:address":"623 NW 45th Ave",
    "sg:city":"Trenton",
    "sg:phone":"+1 660 485 6344",
    "sg:postcode":"64683",
    "sg:province":"MO",
    "sg:tags":[
        "farm",
        "soybean"
    ],
    "wof:name":"Dennis Moore",
    "wof:placetype":"venue"
},
  "geometry": {"coordinates":[-93.68776699999999,40.183651],"type":"Point"}
}