{
  "type": "Feature",
  "properties": {
    "iso:country":"US",
    "sg:address":"1333 N 6th St",
    "sg:city":"Saint Louis",
    "sg:classifiers":[
        {
            "category":"Shopping",
            "subcategory":"Stationery & Office Supplies",
            "type":"Retail Goods"
        }
    ],
    "sg:phone":"+1 314 241 0600",
    "sg:postcode":"63106",
    "sg:province":"MO",
    "sg:tags":[
        "equipment"
    ],
    "wof:name":"McGuire Moving & Storage Co",
    "wof:placetype":"venue"
},
  "geometry": {"coordinates":[-90.187302,38.6367],"type":"Point"}
}