{
  "type": "Feature",
  "properties": {
    "iso:country":"US",
    "sg:address":"305 N Main St",
    "sg:city":"Clarkton",
    "sg:classifiers":[
        {
            "category":"Education",
            "subcategory":"Library",
            "type":"Public Place"
        }
    ],
    "sg:phone":"+1 573 448 3803",
    "sg:postcode":"63837",
    "sg:province":"MO",
    "wof:name":"Clarkton Branch Library",
    "wof:placetype":"venue"
},
  "geometry": {"coordinates":[-89.967862,36.455529],"type":"Point"}
}