{
  "type": "Feature",
  "properties": {
    "iso:country":"US",
    "sg:address":"5714 Pennsylvania Ave",
    "sg:city":"Saint Louis",
    "sg:classifiers":[
        {
            "category":"Professional",
            "subcategory":"Business Services",
            "type":"Services"
        }
    ],
    "sg:phone":"+1 314 353 3278",
    "sg:postcode":"63111",
    "sg:province":"MO",
    "wof:name":"Jerry Simpson",
    "wof:placetype":"venue"
},
  "geometry": {"coordinates":[-90.243954,38.560841],"type":"Point"}
}