{
  "type": "Feature",
  "properties": {
    "iso:country":"US",
    "sg:address":"910 North Byp",
    "sg:city":"Kennett",
    "sg:classifiers":[
        {
            "category":"Retail",
            "subcategory":"Funeral Services",
            "type":"Services"
        }
    ],
    "sg:phone":"+1 573 888 6626",
    "sg:postcode":"63857",
    "sg:province":"MO",
    "sg:tags":[
        "director"
    ],
    "wof:name":"Bradshaw Funeral Home Inc",
    "wof:placetype":"venue"
},
  "geometry": {"coordinates":[-90.046842,36.251331],"type":"Point"}
}