{
  "type": "Feature",
  "properties": {
    "iso:country":"US",
    "sg:address":"3060 S Fremont Ave",
    "sg:city":"Springfield",
    "sg:classifiers":[
        {
            "category":"Real Estate",
            "subcategory":"Architect",
            "type":"Services"
        }
    ],
    "sg:phone":"+1 417 887 1999",
    "sg:postcode":"65804",
    "sg:province":"MO",
    "sg:tags":[
        "interior",
        "design",
        "r",
        "commercial",
        "architectural"
    ],
    "wof:name":"Interior Construction Concepts",
    "wof:placetype":"venue"
},
  "geometry": {"coordinates":[-93.271625,37.158713],"type":"Point"}
}