{
  "type": "Feature",
  "properties": {
    "iso:country":"US",
    "sg:address":"7110 NW Country Wood Ln",
    "sg:city":"Kansas City",
    "sg:classifiers":[
        {
            "category":"Restaurant",
            "type":"Food & Drink"
        }
    ],
    "sg:phone":"+1 816 891 8917",
    "sg:postcode":"64152",
    "sg:province":"MO",
    "sg:tags":[
        "eating",
        "business"
    ],
    "wof:name":"Ernies Recreation",
    "wof:placetype":"venue"
},
  "geometry": {"coordinates":[-94.755202,39.228136],"type":"Point"}
}