{
  "type": "Feature",
  "properties": {
    "iso:country":"US",
    "sg:address":"3355 Watson Rd",
    "sg:city":"Festus",
    "sg:classifiers":[
        {
            "category":"Professional",
            "type":"Services"
        },
        {
            "category":"Utilities",
            "subcategory":"Refuse",
            "type":"Services"
        }
    ],
    "sg:phone":"+1 636 931 1818",
    "sg:postcode":"63028",
    "sg:province":"MO",
    "sg:tags":[
        "garbage",
        "collection"
    ],
    "wof:name":"County Container Services Inc",
    "wof:placetype":"venue"
},
  "geometry": {"coordinates":[-90.466331,38.188349],"type":"Point"}
}