{
  "type": "Feature",
  "properties": {
    "iso:country":"US",
    "sg:address":"6594 Scanlan Ave",
    "sg:city":"Saint Louis",
    "sg:classifiers":[
        {
            "category":"Bars & Pubs",
            "subcategory":"Dive Bar",
            "type":"Food & Drink"
        }
    ],
    "sg:phone":"+1 314 647 0804",
    "sg:postcode":"63139",
    "sg:province":"MO",
    "wof:name":"Jody T's",
    "wof:placetype":"venue"
},
  "geometry": {"coordinates":[-90.301498,38.605701],"type":"Point"}
}