{
  "type": "Feature",
  "properties": {
    "iso:country":"US",
    "sg:address":"534 N East View St",
    "sg:city":"Eldon",
    "sg:classifiers":[
        {
            "category":"Freight",
            "type":"Transportation"
        }
    ],
    "sg:phone":"+1 573 392 7926",
    "sg:postcode":"65026",
    "sg:province":"MO",
    "sg:tags":[
        "moving"
    ],
    "wof:name":"Eldon Moving LLC",
    "wof:placetype":"venue"
},
  "geometry": {"coordinates":[-92.55220300000001,38.353111],"type":"Point"}
}