{
  "type": "Feature",
  "properties": {
    "iso:country":"US",
    "sg:address":"9600 Sandy Church Rd",
    "sg:city":"Hillsboro",
    "sg:classifiers":[
        {
            "category":"Professional",
            "subcategory":"Detective & Security Services",
            "type":"Services"
        }
    ],
    "sg:phone":"+1 636 475 3117",
    "sg:postcode":"63050",
    "sg:province":"MO",
    "sg:tags":[
        "information",
        "bureau"
    ],
    "wof:name":"Jdh Exterior Services Inc",
    "wof:placetype":"venue"
},
  "geometry": {"coordinates":[-90.48484500000001,38.270085],"type":"Point"}
}