{
  "type": "Feature",
  "properties": {
    "iso:country":"US",
    "sg:address":"141 N Greentrails Dr",
    "sg:city":"Chesterfield",
    "sg:classifiers":[
        {
            "category":"Professional",
            "subcategory":"Business Services",
            "type":"Services"
        }
    ],
    "sg:phone":"+1 314 579 9560",
    "sg:postcode":"63017",
    "sg:province":"MO",
    "sg:tags":[
        "close",
        "liquidation",
        "broker",
        "out"
    ],
    "wof:name":"Transworld Liquidations",
    "wof:placetype":"venue"
},
  "geometry": {"coordinates":[-90.519398,38.666496],"type":"Point"}
}