{
  "type": "Feature",
  "properties": {
    "addr:full":"300 2nd St Warrensburg MO 64093",
    "addr:housenumber":"300",
    "addr:postcode":"64093",
    "addr:street":"2Nd St",
    "iso:country":"US",
    "sg:address":"300 2nd St",
    "sg:city":"Warrensburg",
    "sg:classifiers":[
        {
            "category":"Social Services",
            "subcategory":"Adult Care",
            "type":"Services"
        },
        {
            "category":"Organizations",
            "subcategory":"Non-profit Organization",
            "type":"Services"
        }
    ],
    "sg:phone":"+1 660 747 6313",
    "sg:postcode":"64093",
    "sg:province":"MO",
    "sg:tags":[
        "residential",
        "treatment",
        "alcoholism",
        "information"
    ],
    "wof:name":"Alcoholics Anonymous",
    "wof:placetype":"venue"
},
  "geometry": {"coordinates":[-93.75555199999999,38.766568],"type":"Point"}
}