{
  "type": "Feature",
  "properties": {
    "iso:country":"US",
    "sg:address":"14739 Crystal Dr",
    "sg:city":"Excelsior Spgs",
    "sg:classifiers":[
        {
            "category":"Organizations",
            "subcategory":"Professional Association",
            "type":"Services"
        }
    ],
    "sg:phone":"+1 816 630 2600",
    "sg:postcode":"64024",
    "sg:province":"MO",
    "wof:name":"Crystal Lakes Property Owners",
    "wof:placetype":"venue"
},
  "geometry": {"coordinates":[-94.195719,39.362594],"type":"Point"}
}