{
  "type": "Feature",
  "properties": {
    "iso:country":"US",
    "sg:address":"1307 Knight Cir",
    "sg:city":"Oak Grove",
    "sg:classifiers":[
        {
            "category":"Social Services",
            "subcategory":"Child Care",
            "type":"Services"
        }
    ],
    "sg:phone":"+1 816 690 6156",
    "sg:postcode":"64075",
    "sg:province":"MO",
    "sg:tags":[
        "day"
    ],
    "wof:name":"Jays Learning Center",
    "wof:placetype":"venue"
},
  "geometry": {"coordinates":[-94.112212,39.003009],"type":"Point"}
}