{
  "type": "Feature",
  "properties": {
    "iso:country":"US",
    "sg:address":"1229 S Kirkwood Rd",
    "sg:city":"Kirkwood",
    "sg:classifiers":[
        {
            "category":"Shopping",
            "subcategory":"Crafts & Fabrics",
            "type":"Retail Goods"
        }
    ],
    "sg:phone":"+1 314 822 9405",
    "sg:postcode":"63122",
    "sg:province":"MO",
    "sg:tags":[
        "shop",
        "store"
    ],
    "wof:name":"Hancock Fabrics",
    "wof:placetype":"venue"
},
  "geometry": {"coordinates":[-90.40689399999999,38.565102],"type":"Point"}
}