{
  "type": "Feature",
  "properties": {
    "iso:country":"US",
    "sg:address":"12955 Maurer Ind Dr",
    "sg:city":"Sappington",
    "sg:classifiers":[
        {
            "category":"Professional",
            "subcategory":"Engineering",
            "type":"Services"
        }
    ],
    "sg:phone":"+1 314 842 3323",
    "sg:postcode":"63127",
    "sg:province":"MO",
    "sg:tags":[
        "engineer"
    ],
    "sg:website":"www.mdaturbines.com",
    "wof:name":"Mechanical Dynamics & Analysis",
    "wof:placetype":"venue"
},
  "geometry": {"coordinates":[-90.417995,38.521534],"type":"Point"}
}