{
  "type": "Feature",
  "properties": {
    "iso:country":"US",
    "sg:address":"5102 State Hwy 77",
    "sg:city":"Benton",
    "sg:classifiers":[
        {
            "category":"Professional",
            "subcategory":"Engineering",
            "type":"Services"
        }
    ],
    "sg:phone":"+1 573 545 4546",
    "sg:postcode":"63736",
    "sg:province":"MO",
    "wof:name":"M R I",
    "wof:placetype":"venue"
},
  "geometry": {"coordinates":[-89.502651,37.066481],"type":"Point"}
}