{
  "type": "Feature",
  "properties": {
    "iso:country":"US",
    "sg:address":"3243 N Mohawk Ln",
    "sg:city":"Kansas City",
    "sg:classifiers":[
        {
            "category":"Building & Trades",
            "subcategory":"Construction",
            "type":"Services"
        }
    ],
    "sg:phone":"+1 816 452 0000",
    "sg:postcode":"64116",
    "sg:province":"MO",
    "sg:tags":[
        "house"
    ],
    "wof:name":"Sir Richards Rmdlg",
    "wof:placetype":"venue"
},
  "geometry": {"coordinates":[-94.55709899999999,39.155958],"type":"Point"}
}