{
  "type": "Feature",
  "properties": {
    "iso:country":"US",
    "sg:address":"7728 Meadow Dr",
    "sg:city":"Hillsboro",
    "sg:classifiers":[
        {
            "category":"Social Services",
            "subcategory":"Job Training",
            "type":"Services"
        }
    ],
    "sg:phone":"+1 636 274 4474",
    "sg:postcode":"63050",
    "sg:province":"MO",
    "wof:name":"Ms Hilda Adventure Matter Wrld",
    "wof:placetype":"venue"
},
  "geometry": {"coordinates":[-90.601614,38.313519],"type":"Point"}
}