{
  "type": "Feature",
  "properties": {
    "iso:country":"US",
    "sg:address":"204 E Steel St",
    "sg:city":"Seymour",
    "sg:classifiers":[
        {
            "category":"Autos & Motor Vehicles",
            "subcategory":"Automobile Sales",
            "type":"Retail Goods"
        }
    ],
    "sg:phone":"+1 417 935 2306",
    "sg:postcode":"65746",
    "sg:province":"MO",
    "sg:tags":[
        "car",
        "dealer"
    ],
    "wof:name":"Haynes Auto Sales",
    "wof:placetype":"venue"
},
  "geometry": {"coordinates":[-92.767003,37.155555],"type":"Point"}
}