{
  "type": "Feature",
  "properties": {
    "iso:country":"US",
    "sg:address":"807 Hampton Ln",
    "sg:city":"Canton",
    "sg:classifiers":[
        {
            "category":"Personal",
            "subcategory":"Beauty Salon",
            "type":"Services"
        }
    ],
    "sg:phone":"+1 573 288 3725",
    "sg:postcode":"63435",
    "sg:province":"MO",
    "sg:tags":[
        "shop"
    ],
    "wof:name":"Classic Designs",
    "wof:placetype":"venue"
},
  "geometry": {"coordinates":[-91.528206,40.134999],"type":"Point"}
}