{
  "type": "Feature",
  "properties": {
    "iso:country":"US",
    "sg:address":"909 E State Hwy D",
    "sg:city":"Springfield",
    "sg:classifiers":[
        {
            "category":"Professional",
            "subcategory":"Management & Consulting",
            "type":"Services"
        }
    ],
    "sg:phone":"+1 417 882 7183",
    "sg:postcode":"65807",
    "sg:province":"MO",
    "wof:name":"Management Financial Services",
    "wof:placetype":"venue"
},
  "geometry": {"coordinates":[-93.282608,37.182158],"type":"Point"}
}