{
  "type": "Feature",
  "properties": {
    "iso:country":"US",
    "sg:address":"12758 Boenker Ln",
    "sg:city":"Bridgeton",
    "sg:classifiers":[
        {
            "category":"Health Services",
            "subcategory":"Dentist",
            "type":"Services"
        }
    ],
    "sg:phone":"+1 314 739 3300",
    "sg:postcode":"63044",
    "sg:province":"MO",
    "sg:tags":[
        "product",
        "dentists-cosmetic",
        "dentistry",
        "dentists-periodontists",
        "whitening",
        "teeth",
        "implant",
        "dentists-orthodontists",
        "dentists-implantology"
    ],
    "sg:website":"http://www.stlafd.com",
    "wof:name":"Advanced Family Dental",
    "wof:placetype":"venue"
},
  "geometry": {"coordinates":[-90.43688899999999,38.759533],"type":"Point"}
}