{
  "type": "Feature",
  "properties": {
    "iso:country":"US",
    "sg:address":"121 N Jefferson St",
    "sg:city":"Saint James",
    "sg:classifiers":[
        {
            "category":"Professional",
            "subcategory":"Business Services",
            "type":"Services"
        }
    ],
    "sg:phone":"+1 573 265 8333",
    "sg:postcode":"65559",
    "sg:province":"MO",
    "wof:name":"Anri Financial Services",
    "wof:placetype":"venue"
},
  "geometry": {"coordinates":[-91.614912,37.99776],"type":"Point"}
}