{
  "type": "Feature",
  "properties": {
    "iso:country":"US",
    "sg:address":"522 Campbell St",
    "sg:city":"Kansas City",
    "sg:classifiers":[
        {
            "category":"Restaurant",
            "type":"Food & Drink"
        }
    ],
    "sg:phone":"+1 816 472 4888",
    "sg:postcode":"64106",
    "sg:province":"MO",
    "sg:tags":[
        "eating"
    ],
    "wof:name":"Vietnam Cafe",
    "wof:placetype":"venue"
},
  "geometry": {"coordinates":[-94.573392,39.110201],"type":"Point"}
}