{
  "type": "Feature",
  "properties": {
    "iso:country":"US",
    "sg:address":"6009 Co Rd 150",
    "sg:city":"Bethel",
    "sg:classifiers":[
        {
            "category":"Farming",
            "subcategory":"Livestock Farm",
            "type":"Manufacturing & Wholesale Goods"
        }
    ],
    "sg:phone":"+1 660 284 6257",
    "sg:postcode":"63434",
    "sg:province":"MO",
    "sg:tags":[
        "specialty",
        "animal"
    ],
    "wof:name":"Bills Wild Exotic Ranch",
    "wof:placetype":"venue"
},
  "geometry": {"coordinates":[-92.02142000000001,39.943093],"type":"Point"}
}