{
  "type": "Feature",
  "properties": {
    "iso:country":"US",
    "sg:address":"2116 Cherokee St",
    "sg:city":"Saint Louis",
    "sg:classifiers":[
        {
            "category":"Shopping",
            "subcategory":"Antiques",
            "type":"Retail Goods"
        },
        {
            "category":"Shopping",
            "subcategory":"Used Merchandise",
            "type":"Retail Goods"
        }
    ],
    "sg:phone":"+1 314 776 3739",
    "sg:postcode":"63118",
    "sg:province":"MO",
    "sg:tags":[
        "vintage",
        "consignment"
    ],
    "sg:website":"cherokeeantiquerow.net/",
    "wof:name":"Retro 101",
    "wof:placetype":"venue"
},
  "geometry": {"coordinates":[-90.222702,38.593102],"type":"Point"}
}