{
  "type": "Feature",
  "properties": {
    "iso:country":"US",
    "sg:address":"303 W Vassar St",
    "sg:city":"St Joseph",
    "sg:classifiers":[
        {
            "category":"Building & Trades",
            "subcategory":"Construction",
            "type":"Services"
        }
    ],
    "sg:phone":"+1 816 238 0930",
    "sg:postcode":"64504",
    "sg:province":"MO",
    "sg:tags":[
        "layer",
        "contractor",
        "laying",
        "floor",
        "carpet"
    ],
    "wof:name":"Steve Brown Floor Covering",
    "wof:placetype":"venue"
},
  "geometry": {"coordinates":[-94.859855,39.712682],"type":"Point"}
}