{
  "type": "Feature",
  "properties": {
    "iso:country":"US",
    "sg:address":"3216 Locust St",
    "sg:city":"St Louis",
    "sg:classifiers":[
        {
            "category":"Real Estate",
            "subcategory":"Real Estate Agent",
            "type":"Services"
        }
    ],
    "sg:phone":"+1 314 534 3359",
    "sg:postcode":"63103",
    "sg:province":"MO",
    "wof:name":"Ryebacki Properties",
    "wof:placetype":"venue"
},
  "geometry": {"coordinates":[-90.22651399999999,38.636771],"type":"Point"}
}