{
  "type": "Feature",
  "properties": {
    "iso:country":"US",
    "sg:address":"5861 Wellington Farm Dr",
    "sg:city":"Saint Charles",
    "sg:classifiers":[
        {
            "category":"Professional",
            "subcategory":"Business Services",
            "type":"Services"
        }
    ],
    "sg:phone":"+1 636 441 8802",
    "sg:postcode":"63304",
    "sg:province":"MO",
    "wof:name":"Heirloom Est Sales Ltd Inc",
    "wof:placetype":"venue"
},
  "geometry": {"coordinates":[-90.67303,38.72417],"type":"Point"}
}