{
  "type": "Feature",
  "properties": {
    "iso:country":"US",
    "sg:address":"1418 N Glen Ellyn St",
    "sg:city":"Independence",
    "sg:classifiers":[
        {
            "category":"Building & Trades",
            "subcategory":"Electrical",
            "type":"Services"
        }
    ],
    "sg:phone":"+1 816 739 7596",
    "sg:postcode":"64056",
    "sg:province":"MO",
    "sg:tags":[
        "electrician"
    ],
    "wof:name":"Kansas City Electric",
    "wof:placetype":"venue"
},
  "geometry": {"coordinates":[-94.34522,39.128899],"type":"Point"}
}