{
  "type": "Feature",
  "properties": {
    "iso:country":"US",
    "sg:address":"215 S Hickory St",
    "sg:city":"Mount Vernon",
    "sg:classifiers":[
        {
            "category":"Retail",
            "subcategory":"Portrait Studio",
            "type":"Services"
        }
    ],
    "sg:phone":"+1 417 461 1122",
    "sg:postcode":"65712",
    "sg:province":"MO",
    "sg:tags":[
        "photo"
    ],
    "wof:name":"Freeze Frame Photography",
    "wof:placetype":"venue"
},
  "geometry": {"coordinates":[-93.81790700000001,37.102969],"type":"Point"}
}