{
  "type": "Feature",
  "properties": {
    "iso:country":"US",
    "sg:address":"2111 W Broadway Blvd",
    "sg:city":"Sedalia",
    "sg:classifiers":[
        {
            "category":"Real Estate",
            "subcategory":"Real Estate Agent",
            "type":"Services"
        }
    ],
    "sg:phone":"+1 660 829 2777",
    "sg:postcode":"65301",
    "sg:province":"MO",
    "sg:tags":[
        "appraiser"
    ],
    "wof:name":"Boeschen & Assoc",
    "wof:placetype":"venue"
},
  "geometry": {"coordinates":[-93.25267100000001,38.705068],"type":"Point"}
}