{
  "type": "Feature",
  "properties": {
    "iso:country":"US",
    "sg:address":"512 N Main St",
    "sg:city":"Centerview",
    "sg:classifiers":[
        {
            "category":"Freight",
            "type":"Transportation"
        }
    ],
    "sg:phone":"+1 660 656 3289",
    "sg:postcode":"64019",
    "sg:province":"MO",
    "sg:tags":[
        "commercial",
        "storage"
    ],
    "wof:name":"Todd Estate Storage",
    "wof:placetype":"venue"
},
  "geometry": {"coordinates":[-93.844967,38.750017],"type":"Point"}
}