{
  "type": "Feature",
  "properties": {
    "iso:country":"US",
    "sg:address":"2820 Co Rd 631",
    "sg:city":"Fisk",
    "sg:phone":"+1 573 967 3557",
    "sg:postcode":"63940",
    "sg:province":"MO",
    "sg:tags":[
        "farm",
        "soybean"
    ],
    "wof:name":"Neil Dabbs",
    "wof:placetype":"venue"
},
  "geometry": {"coordinates":[-90.227512,36.720929],"type":"Point"}
}