{
  "type": "Feature",
  "properties": {
    "iso:country":"US",
    "sg:address":"1636 Headland Dr",
    "sg:city":"Fenton",
    "sg:classifiers":[
        {
            "category":"Building & Trades",
            "subcategory":"Construction",
            "type":"Services"
        }
    ],
    "sg:phone":"+1 636 343 8109",
    "sg:postcode":"63026",
    "sg:province":"MO",
    "sg:tags":[
        "asbestos",
        "removal"
    ],
    "wof:name":"Environmental Ctrl & Abatement",
    "wof:placetype":"venue"
},
  "geometry": {"coordinates":[-90.440941,38.533544],"type":"Point"}
}