{
  "type": "Feature",
  "properties": {
    "iso:country":"US",
    "sg:address":"1947 Cherokee St",
    "sg:city":"Saint Louis",
    "sg:classifiers":[
        {
            "category":"Shopping",
            "subcategory":"Used Merchandise",
            "type":"Retail Goods"
        }
    ],
    "sg:phone":"+1 314 772 9177",
    "sg:postcode":"63118",
    "sg:province":"MO",
    "sg:tags":[
        "antique"
    ],
    "wof:name":"Riverside Architectural Antiques",
    "wof:placetype":"venue"
},
  "geometry": {"coordinates":[-90.22049699999999,38.592602],"type":"Point"}
}