{
  "type": "Feature",
  "properties": {
    "iso:country":"US",
    "sg:address":"11001 W 23rd St S",
    "sg:city":"Independence",
    "sg:classifiers":[
        {
            "category":"Food & Beverages",
            "subcategory":"Groceries & Convenience Stores",
            "type":"Retail Goods"
        }
    ],
    "sg:phone":"+1 816 461 0158",
    "sg:postcode":"64052",
    "sg:province":"MO",
    "wof:name":"7-Eleven",
    "wof:placetype":"venue"
},
  "geometry": {"coordinates":[-94.44834400000001,39.080372],"type":"Point"}
}