{
  "type": "Feature",
  "properties": {
    "addr:full":"1213 N Green St Kirksville MO 63501",
    "addr:housenumber":"1213",
    "addr:postcode":"63501",
    "addr:street":"N Green St",
    "iso:country":"US",
    "sg:address":"1213 N Green St",
    "sg:city":"Kirksville",
    "sg:classifiers":[
        {
            "category":"Retail",
            "subcategory":"Car Wash",
            "type":"Services"
        }
    ],
    "sg:phone":"+1 660 665 2960",
    "sg:postcode":"63501",
    "sg:province":"MO",
    "sg:tags":[
        "polishing",
        "washing"
    ],
    "wof:name":"Super Wash",
    "wof:placetype":"venue"
},
  "geometry": {"coordinates":[-92.581507,40.20404],"type":"Point"}
}