{
  "type": "Feature",
  "properties": {
    "iso:country":"US",
    "sg:address":"5190 S Limit Ave",
    "sg:city":"Sedalia",
    "sg:classifiers":[
        {
            "category":"Retail",
            "subcategory":"Auto Repair",
            "type":"Services"
        }
    ],
    "sg:phone":"+1 660 829 3502",
    "sg:postcode":"65301",
    "sg:province":"MO",
    "sg:tags":[
        "wheel",
        "alignment",
        "axle",
        "general"
    ],
    "wof:name":"Alignment Specialists",
    "wof:placetype":"venue"
},
  "geometry": {"coordinates":[-93.25358,38.660135],"type":"Point"}
}