{
  "type": "Feature",
  "properties": {
    "iso:country":"US",
    "sg:address":"816 Halifax Dr",
    "sg:city":"Rolla",
    "sg:classifiers":[
        {
            "category":"Personal",
            "type":"Services"
        }
    ],
    "sg:phone":"+1 573 364 4290",
    "sg:postcode":"65401",
    "sg:province":"MO",
    "sg:tags":[
        "program",
        "physical",
        "exercise",
        "fitness"
    ],
    "wof:name":"Peak Physique",
    "wof:placetype":"venue"
},
  "geometry": {"coordinates":[-91.754344,37.936621],"type":"Point"}
}