{
  "type": "Feature",
  "properties": {
    "iso:country":"US",
    "sg:address":"16471 S Hawkins Rd",
    "sg:city":"Ashland",
    "sg:classifiers":[
        {
            "category":"Health Services",
            "subcategory":"Doctor",
            "type":"Services"
        },
        {
            "category":"Personal",
            "type":"Services"
        }
    ],
    "sg:phone":"+1 573 443 4038",
    "sg:postcode":"65010",
    "sg:province":"MO",
    "sg:tags":[
        "counseling",
        "psychologist"
    ],
    "wof:name":"La Mar, Diane Med Lpc",
    "wof:placetype":"venue"
},
  "geometry": {"coordinates":[-92.214394,38.752923],"type":"Point"}
}