{
  "type": "Feature",
  "properties": {
    "iso:country":"US",
    "sg:address":"10301 E 63rd St Ste B",
    "sg:city":"Raytown",
    "sg:classifiers":[
        {
            "category":"Insurance",
            "subcategory":"Hazard Insurance",
            "type":"Services"
        }
    ],
    "sg:phone":"+1 816 358 8323",
    "sg:postcode":"64133",
    "sg:province":"MO",
    "sg:tags":[
        "commercial",
        "business"
    ],
    "wof:name":"American Familymustual Ins Co",
    "wof:placetype":"venue"
},
  "geometry": {"coordinates":[-94.459671,39.00864],"type":"Point"}
}