{
  "type": "Feature",
  "properties": {
    "iso:country":"US",
    "sg:address":"510 Otto Dr",
    "sg:city":"Jackson",
    "sg:classifiers":[
        {
            "category":"Wholesale",
            "subcategory":"Groceries",
            "type":"Manufacturing & Wholesale Goods"
        }
    ],
    "sg:phone":"+1 573 243 7986",
    "sg:postcode":"63755",
    "sg:province":"MO",
    "sg:tags":[
        "general"
    ],
    "wof:name":"Streiler Distributing",
    "wof:placetype":"venue"
},
  "geometry": {"coordinates":[-89.642223,37.376965],"type":"Point"}
}