{
  "type": "Feature",
  "properties": {
    "iso:country":"US",
    "sg:address":"1608 Shelby Dr",
    "sg:city":"Raymore",
    "sg:classifiers":[
        {
            "category":"Professional",
            "type":"Services"
        }
    ],
    "sg:phone":"+1 816 348 7893",
    "sg:postcode":"64083",
    "sg:province":"MO",
    "wof:name":"Drews Editorial Svcs",
    "wof:placetype":"venue"
},
  "geometry": {"coordinates":[-94.48442799999999,38.802987],"type":"Point"}
}