{
  "type": "Feature",
  "properties": {
    "iso:country":"US",
    "sg:address":"11811 Northport Dr",
    "sg:city":"Florissant",
    "sg:classifiers":[
        {
            "category":"Retail",
            "subcategory":"Laundry & Dry Cleaning",
            "type":"Services"
        }
    ],
    "sg:phone":"+1 314 921 3980",
    "sg:postcode":"63033",
    "sg:province":"MO",
    "sg:tags":[
        "drycleaning",
        "plant"
    ],
    "wof:name":"Sewell Drycleaning Equipment",
    "wof:placetype":"venue"
},
  "geometry": {"coordinates":[-90.284136,38.780742],"type":"Point"}
}