{
  "type": "Feature",
  "properties": {
    "iso:country":"US",
    "sg:address":"721 Benham St",
    "sg:city":"Bonne Terre",
    "sg:classifiers":[
        {
            "category":"Building & Trades",
            "subcategory":"Construction",
            "type":"Services"
        }
    ],
    "sg:phone":"+1 573 358 7332",
    "sg:postcode":"63628",
    "sg:province":"MO",
    "sg:tags":[
        "residential"
    ],
    "wof:name":"Lance Brewen",
    "wof:placetype":"venue"
},
  "geometry": {"coordinates":[-90.543825,37.922686],"type":"Point"}
}