{
  "type": "Feature",
  "properties": {
    "iso:country":"US",
    "sg:address":"2700 NE Jellison Rd",
    "sg:city":"Blue Springs",
    "sg:classifiers":[
        {
            "category":"Building & Trades",
            "subcategory":"Construction",
            "type":"Services"
        }
    ],
    "sg:phone":"+1 816 220 0855",
    "sg:postcode":"64014",
    "sg:province":"MO",
    "sg:tags":[
        "house"
    ],
    "wof:name":"Trb Craftsman",
    "wof:placetype":"venue"
},
  "geometry": {"coordinates":[-94.24319,39.048009],"type":"Point"}
}