{
  "type": "Feature",
  "properties": {
    "iso:country":"US",
    "sg:address":"405 E Cedar St",
    "sg:city":"Bertrand",
    "sg:classifiers":[
        {
            "category":"Government",
            "subcategory":"Fire Station",
            "type":"Public Place"
        }
    ],
    "sg:phone":"+1 573 683 3051",
    "sg:postcode":"63823",
    "sg:province":"MO",
    "sg:tags":[
        "department"
    ],
    "wof:name":"Bertrand Fire Dept",
    "wof:placetype":"venue"
},
  "geometry": {"coordinates":[-89.445391,36.9098],"type":"Point"}
}