{
  "type": "Feature",
  "properties": {
    "iso:country":"US",
    "sg:address":"307 E South St",
    "sg:city":"Harrisonville",
    "sg:classifiers":[
        {
            "category":"Social Services",
            "subcategory":"Job Training",
            "type":"Services"
        }
    ],
    "sg:phone":"+1 816 887 2378",
    "sg:postcode":"64701",
    "sg:province":"MO",
    "sg:tags":[
        "rehabilitation"
    ],
    "wof:name":"Rehab Care Group",
    "wof:placetype":"venue"
},
  "geometry": {"coordinates":[-94.347528,38.646571],"type":"Point"}
}