{
  "type": "Feature",
  "properties": {
    "iso:country":"US",
    "sg:address":"15610 E Independence Ave",
    "sg:city":"Independence",
    "sg:classifiers":[
        {
            "category":"Professional",
            "subcategory":"Computer Services",
            "type":"Services"
        }
    ],
    "sg:phone":"+1 816 836 5800",
    "sg:postcode":"64050",
    "sg:province":"MO",
    "sg:tags":[
        "programming"
    ],
    "wof:name":"Affordable Data Recovery",
    "wof:placetype":"venue"
},
  "geometry": {"coordinates":[-94.389549,39.100269],"type":"Point"}
}