{
  "type": "Feature",
  "properties": {
    "iso:country":"US",
    "sg:address":"38385 Freds Rd",
    "sg:city":"Latham",
    "sg:classifiers":[
        {
            "category":"Professional",
            "type":"Services"
        }
    ],
    "sg:phone":"+1 660 458 6568",
    "sg:postcode":"65050",
    "sg:province":"MO",
    "sg:tags":[
        "establishment"
    ],
    "wof:name":"Waking Acres",
    "wof:placetype":"venue"
},
  "geometry": {"coordinates":[-92.65961,38.517055],"type":"Point"}
}