{
  "type": "Feature",
  "properties": {
    "iso:country":"US",
    "sg:address":"9101 E Starr Rd",
    "sg:city":"Columbia",
    "sg:classifiers":[
        {
            "category":"Manufacturing",
            "subcategory":"Lumber",
            "type":"Manufacturing & Wholesale Goods"
        }
    ],
    "sg:phone":"+1 573 443 0207",
    "sg:postcode":"65201",
    "sg:province":"MO",
    "sg:tags":[
        "timber",
        "operation",
        "material",
        "tract"
    ],
    "wof:name":"Starr Farm Timber Products",
    "wof:placetype":"venue"
},
  "geometry": {"coordinates":[-92.199861,38.833929],"type":"Point"}
}