{
  "type": "Feature",
  "properties": {
    "iso:country":"US",
    "sg:address":"19032 State Hwy 174",
    "sg:city":"Mt Vernon",
    "sg:classifiers":[
        {
            "category":"Food & Beverages",
            "subcategory":"Groceries & Convenience Stores",
            "type":"Retail Goods"
        },
        {
            "category":"Autos & Motor Vehicles",
            "subcategory":"Fuel & Gas Station",
            "type":"Retail Goods"
        }
    ],
    "sg:phone":"+1 417 466 7042",
    "sg:postcode":"65712",
    "sg:province":"MO",
    "sg:tags":[
        "oil"
    ],
    "wof:name":"Country Junction",
    "wof:placetype":"venue"
},
  "geometry": {"coordinates":[-93.940417,37.103476],"type":"Point"}
}