{
  "type": "Feature",
  "properties": {
    "iso:country":"US",
    "sg:address":"5717 Grand Ave",
    "sg:city":"Kansas City",
    "sg:classifiers":[
        {
            "category":"Professional",
            "subcategory":"Lawyer & Legal Services",
            "type":"Services"
        }
    ],
    "sg:phone":"+1 816 561 3700",
    "sg:postcode":"64113",
    "sg:province":"MO",
    "sg:tags":[
        "attorney"
    ],
    "wof:name":"William Mallory",
    "wof:placetype":"venue"
},
  "geometry": {"coordinates":[-94.58556400000001,39.022191],"type":"Point"}
}