{
  "type": "Feature",
  "properties": {
    "iso:country":"US",
    "sg:address":"102 N Range Line Rd",
    "sg:city":"Joplin",
    "sg:classifiers":[
        {
            "category":"Shopping",
            "subcategory":"Music",
            "type":"Retail Goods"
        }
    ],
    "sg:phone":"+1 417 621 9100",
    "sg:postcode":"64801",
    "sg:province":"MO",
    "wof:name":"Cds Etc",
    "wof:placetype":"venue"
},
  "geometry": {"coordinates":[-94.476951,37.093638],"type":"Point"}
}