{
  "type": "Feature",
  "properties": {
    "iso:country":"US",
    "sg:address":"1965 Cardinal Ln",
    "sg:city":"Aurora",
    "sg:classifiers":[
        {
            "category":"Organizations",
            "subcategory":"Religious Organization",
            "type":"Services"
        }
    ],
    "sg:phone":"+1 417 678 5220",
    "sg:postcode":"65605",
    "sg:province":"MO",
    "sg:tags":[
        "church"
    ],
    "wof:name":"Orange Cumberland Presbyterian",
    "wof:placetype":"venue"
},
  "geometry": {"coordinates":[-93.75091500000001,36.967871],"type":"Point"}
}