{
  "type": "Feature",
  "properties": {
    "iso:country":"US",
    "sg:address":"1630 W Republic Rd",
    "sg:city":"Springfield",
    "sg:classifiers":[
        {
            "category":"Organizations",
            "subcategory":"Religious Organization",
            "type":"Services"
        }
    ],
    "sg:phone":"+1 417 881 7405",
    "sg:postcode":"65807",
    "sg:province":"MO",
    "wof:name":"Southland Christian Church",
    "wof:placetype":"venue"
},
  "geometry": {"coordinates":[-93.315928,37.138224],"type":"Point"}
}