{
  "type": "Feature",
  "properties": {
    "iso:country":"US",
    "sg:address":"404 Huck Finn Shopping Ctr",
    "sg:city":"Hannibal",
    "sg:classifiers":[
        {
            "category":"Utilities",
            "subcategory":"Mobile Phone",
            "type":"Services"
        },
        {
            "category":"Utilities",
            "subcategory":"Telephone",
            "type":"Services"
        },
        {
            "category":"Shopping",
            "subcategory":"Computers & Home Electronics",
            "type":"Retail Goods"
        },
        {
            "category":"Manufacturing",
            "subcategory":"Electronics",
            "type":"Manufacturing & Wholesale Goods"
        },
        {
            "category":"Communications",
            "type":"Services"
        }
    ],
    "sg:phone":"+1 573 231 7007",
    "sg:postcode":"63401",
    "sg:province":"MO",
    "sg:tags":[
        "sound",
        "television",
        "telecommunications-equipment",
        "supply",
        "system",
        "equipment",
        "radio",
        "cellular",
        "store"
    ],
    "sg:website":"http://www.midamericawireless.com",
    "wof:name":"Mid-America Wireless",
    "wof:placetype":"venue"
},
  "geometry": {"coordinates":[-91.393549,39.723384],"type":"Point"}
}