{
  "type": "Feature",
  "properties": {
    "iso:country":"US",
    "sg:address":"134 Westwoods Dr",
    "sg:city":"Liberty",
    "sg:classifiers":[
        {
            "category":"Health Services",
            "subcategory":"Clinic",
            "type":"Services"
        },
        {
            "category":"Personal",
            "type":"Services"
        }
    ],
    "sg:phone":"+1 816 792 3363",
    "sg:postcode":"64068",
    "sg:province":"MO",
    "sg:tags":[
        "information",
        "mental",
        "counseling"
    ],
    "wof:name":"Liberty Counseling Services",
    "wof:placetype":"venue"
},
  "geometry": {"coordinates":[-94.436218,39.246781],"type":"Point"}
}