{
  "type": "Feature",
  "properties": {
    "iso:country":"US",
    "sg:address":"208 Main St",
    "sg:city":"Ellington",
    "sg:classifiers":[
        {
            "category":"Utilities",
            "subcategory":"Electric",
            "type":"Services"
        }
    ],
    "sg:phone":"+1 573 663 2226",
    "sg:postcode":"63638",
    "sg:province":"MO",
    "sg:tags":[
        "company"
    ],
    "wof:name":"Black River Electric Co-Op",
    "wof:placetype":"venue"
},
  "geometry": {"coordinates":[-90.969849,37.242616],"type":"Point"}
}