{
  "type": "Feature",
  "properties": {
    "iso:country":"US",
    "sg:address":"4779 Valley Dr",
    "sg:city":"Sullivan",
    "sg:classifiers":[
        {
            "category":"Personal",
            "subcategory":"Barber",
            "type":"Services"
        }
    ],
    "sg:phone":"+1 573 468 3350",
    "sg:postcode":"63080",
    "sg:province":"MO",
    "sg:tags":[
        "shop"
    ],
    "wof:name":"Bob's Barber Shop",
    "wof:placetype":"venue"
},
  "geometry": {"coordinates":[-91.19776299999999,38.187161],"type":"Point"}
}