{
  "type": "Feature",
  "properties": {
    "iso:country":"US",
    "sg:address":"7002 King Hill Ave",
    "sg:city":"Saint Joseph",
    "sg:classifiers":[
        {
            "category":"Wholesale",
            "subcategory":"Machinery & Supplies",
            "type":"Manufacturing & Wholesale Goods"
        }
    ],
    "sg:phone":"+1 816 238 8720",
    "sg:postcode":"64504",
    "sg:province":"MO",
    "sg:tags":[
        "leather"
    ],
    "wof:name":"Fern-Thatcher Company Inc",
    "wof:placetype":"venue"
},
  "geometry": {"coordinates":[-94.86438699999999,39.700786],"type":"Point"}
}