{
  "type": "Feature",
  "properties": {
    "iso:country":"US",
    "sg:address":"9308 State Hwy 76",
    "sg:city":"Reeds Spring",
    "sg:classifiers":[
        {
            "category":"Shopping",
            "subcategory":"Gifts & Souvenirs",
            "type":"Retail Goods"
        }
    ],
    "sg:phone":"+1 417 338 8574",
    "sg:postcode":"65737",
    "sg:province":"MO",
    "wof:name":"Ozark Village",
    "wof:placetype":"venue"
},
  "geometry": {"coordinates":[-93.340395,36.686634],"type":"Point"}
}