{
  "type": "Feature",
  "properties": {
    "iso:country":"US",
    "sg:address":"2979 E Chestnut Expy",
    "sg:city":"Springfield",
    "sg:classifiers":[
        {
            "category":"Home & Garden",
            "subcategory":"Home Furnishings",
            "type":"Retail Goods"
        },
        {
            "category":"Building & Trades",
            "subcategory":"Plumbing",
            "type":"Services"
        }
    ],
    "sg:phone":"+1 417 866 3400",
    "sg:postcode":"65802",
    "sg:province":"MO",
    "sg:tags":[
        "plumbing",
        "contractor"
    ],
    "wof:name":"Son Plumbing Inc",
    "wof:placetype":"venue"
},
  "geometry": {"coordinates":[-93.235579,37.209929],"type":"Point"}
}