{
  "type": "Feature",
  "properties": {
    "iso:country":"US",
    "sg:address":"30139 Thyme Rd",
    "sg:city":"Asbury",
    "sg:classifiers":[
        {
            "category":"Farming",
            "subcategory":"Poultry Farm",
            "type":"Manufacturing & Wholesale Goods"
        }
    ],
    "sg:phone":"+1 417 238 8712",
    "sg:postcode":"64832",
    "sg:province":"MO",
    "sg:tags":[
        "egg"
    ],
    "wof:name":"Turkey Creek Farms",
    "wof:placetype":"venue"
},
  "geometry": {"coordinates":[-94.59773800000001,37.342079],"type":"Point"}
}