{
  "type": "Feature",
  "properties": {
    "iso:country":"US",
    "sg:address":"833 Bourbon Red Dr",
    "sg:city":"Saint Louis",
    "sg:classifiers":[
        {
            "category":"Health Services",
            "subcategory":"Doctor",
            "type":"Services"
        }
    ],
    "sg:phone":"+1 314 965 8833",
    "sg:postcode":"63131",
    "sg:province":"MO",
    "wof:name":"Health Center Family Dentistry",
    "wof:placetype":"venue"
},
  "geometry": {"coordinates":[-90.454216,38.594704],"type":"Point"}
}