{
  "type": "Feature",
  "properties": {
    "iso:country":"US",
    "sg:address":"11520 Old St Charles Rd",
    "sg:city":"Bridgeton",
    "sg:classifiers":[
        {
            "category":"Health Services",
            "subcategory":"Doctor",
            "type":"Services"
        }
    ],
    "sg:phone":"+1 314 298 7772",
    "sg:postcode":"63044",
    "sg:province":"MO",
    "sg:tags":[
        "dentist"
    ],
    "wof:name":"St Louis Smile Ctr",
    "wof:placetype":"venue"
},
  "geometry": {"coordinates":[-90.416831,38.73819],"type":"Point"}
}