{
  "type": "Feature",
  "properties": {
    "iso:country":"US",
    "sg:address":"16801 State Hwy P",
    "sg:city":"Kennett",
    "sg:classifiers":[
        {
            "category":"Professional",
            "type":"Services"
        }
    ],
    "sg:phone":"+1 573 738 3371",
    "sg:postcode":"63857",
    "sg:province":"MO",
    "sg:tags":[
        "establishment"
    ],
    "wof:name":"Delta Fiber Co",
    "wof:placetype":"venue"
},
  "geometry": {"coordinates":[-90.090913,36.134076],"type":"Point"}
}