{
  "type": "Feature",
  "properties": {
    "iso:country":"US",
    "sg:address":"119 Big Bend Ln",
    "sg:city":"Steelville",
    "sg:classifiers":[
        {
            "category":"Travel",
            "subcategory":"Campground",
            "type":"Entertainment"
        }
    ],
    "sg:phone":"+1 573 775 5534",
    "sg:postcode":"65565",
    "sg:province":"MO",
    "wof:name":"Country's Get-Away",
    "wof:placetype":"venue"
},
  "geometry": {"coordinates":[-91.44755499999999,37.985738],"type":"Point"}
}