{
  "type": "Feature",
  "properties": {
    "iso:country":"US",
    "sg:address":"805 N Valleyview Dr",
    "sg:city":"Columbia",
    "sg:classifiers":[
        {
            "category":"Professional",
            "type":"Services"
        }
    ],
    "sg:phone":"+1 573 449 5946",
    "sg:postcode":"65201",
    "sg:province":"MO",
    "sg:tags":[
        "artist"
    ],
    "wof:name":"Christine Doerr",
    "wof:placetype":"venue"
},
  "geometry": {"coordinates":[-92.30798900000001,38.940109],"type":"Point"}
}