{
  "type": "Feature",
  "properties": {
    "iso:country":"US",
    "sg:address":"324 N Riverview Dr",
    "sg:city":"Poplar Bluff",
    "sg:classifiers":[
        {
            "category":"Building & Trades",
            "subcategory":"Construction",
            "type":"Services"
        }
    ],
    "sg:phone":"+1 573 727 9925",
    "sg:postcode":"63901",
    "sg:province":"MO",
    "sg:tags":[
        "dry wall",
        "contractor"
    ],
    "wof:name":"Empire Drywall Co",
    "wof:placetype":"venue"
},
  "geometry": {"coordinates":[-90.388893,36.758287],"type":"Point"}
}