{
  "type": "Feature",
  "properties": {
    "iso:country":"US",
    "sg:address":"10908 N Holly St",
    "sg:city":"Kansas City",
    "sg:classifiers":[
        {
            "category":"Professional",
            "type":"Services"
        }
    ],
    "sg:phone":"+1 816 734 0985",
    "sg:postcode":"64155",
    "sg:province":"MO",
    "wof:name":"North American Imaging",
    "wof:placetype":"venue"
},
  "geometry": {"coordinates":[-94.592814,39.289671],"type":"Point"}
}