{
  "type": "Feature",
  "properties": {
    "iso:country":"US",
    "sg:address":"2920 Wentworth Ct",
    "sg:city":"Saint Charles",
    "sg:classifiers":[
        {
            "category":"Professional",
            "type":"Services"
        }
    ],
    "sg:phone":"+1 636 947 0543",
    "sg:postcode":"63301",
    "sg:province":"MO",
    "wof:name":"Dan Westhues",
    "wof:placetype":"venue"
},
  "geometry": {"coordinates":[-90.53203499999999,38.80361],"type":"Point"}
}