{
  "type": "Feature",
  "properties": {
    "iso:country":"US",
    "sg:address":"4116 Park Hill Ct",
    "sg:city":"Saint Louis",
    "sg:classifiers":[
        {
            "category":"Social Services",
            "type":"Services"
        }
    ],
    "sg:phone":"+1 314 863 3365",
    "sg:postcode":"63125",
    "sg:province":"MO",
    "sg:tags":[
        "personal"
    ],
    "wof:name":"Dolen Co",
    "wof:placetype":"venue"
},
  "geometry": {"coordinates":[-90.317897,38.523993],"type":"Point"}
}