{
  "type": "Feature",
  "properties": {
    "iso:country":"US",
    "sg:address":"153 Moon Rd",
    "sg:city":"Forsyth",
    "sg:classifiers":[
        {
            "category":"Professional",
            "subcategory":"Management & Consulting",
            "type":"Services"
        }
    ],
    "sg:phone":"+1 417 546 5612",
    "sg:postcode":"65653",
    "sg:province":"MO",
    "sg:tags":[
        "consultant",
        "business"
    ],
    "wof:name":"Buddy Roberts Sales Co",
    "wof:placetype":"venue"
},
  "geometry": {"coordinates":[-93.13750400000001,36.661582],"type":"Point"}
}