{
  "type": "Feature",
  "properties": {
    "iso:country":"US",
    "sg:address":"380 Mid Rivers Mall Dr",
    "sg:city":"Saint Peters",
    "sg:classifiers":[
        {
            "category":"Shopping",
            "subcategory":"Optical Goods",
            "type":"Retail Goods"
        }
    ],
    "sg:phone":"+1 636 397 0242",
    "sg:postcode":"63376",
    "sg:province":"MO",
    "wof:name":"Spectrum Eyeglass Repair Inc",
    "wof:placetype":"venue"
},
  "geometry": {"coordinates":[-90.62560499999999,38.789977],"type":"Point"}
}