{
  "type": "Feature",
  "properties": {
    "iso:country":"US",
    "sg:address":"16 Pendleton Hills Ests",
    "sg:city":"Warrenton",
    "sg:classifiers":[
        {
            "category":"Retail",
            "subcategory":"Auto Repair",
            "type":"Services"
        }
    ],
    "sg:phone":"+1 636 456 0614",
    "sg:postcode":"63383",
    "sg:province":"MO",
    "sg:tags":[
        "body",
        "automobile",
        "top",
        "upholstery"
    ],
    "wof:name":"Ace Auto Tops & Trim",
    "wof:placetype":"venue"
},
  "geometry": {"coordinates":[-91.246073,38.811657],"type":"Point"}
}