{
  "type": "Feature",
  "properties": {
    "iso:country":"US",
    "sg:address":"12222 Saint Charles Rock Rd",
    "sg:city":"Hazelwood",
    "sg:classifiers":[
        {
            "category":"Shopping",
            "subcategory":"Department Store",
            "type":"Retail Goods"
        }
    ],
    "sg:phone":"+1 314 739 7622",
    "sg:postcode":"63044",
    "sg:province":"MO",
    "sg:website":"www.kohls.com",
    "wof:name":"Kohl's",
    "wof:placetype":"venue"
},
  "geometry": {"coordinates":[-90.427108,38.751755],"type":"Point"}
}