{
  "type": "Feature",
  "properties": {
    "iso:country":"US",
    "sg:address":"9904 Rte Bb",
    "sg:city":"Eugene",
    "sg:classifiers":[
        {
            "category":"Building & Trades",
            "subcategory":"Landscaping Services",
            "type":"Services"
        }
    ],
    "sg:phone":"+1 573 498 3458",
    "sg:postcode":"65032",
    "sg:province":"MO",
    "wof:name":"Nolan Enterprises",
    "wof:placetype":"venue"
},
  "geometry": {"coordinates":[-92.37726600000001,38.363917],"type":"Point"}
}