{
  "type": "Feature",
  "properties": {
    "addr:full":"3702 Frederick Ave Saint Joseph MO 64506",
    "addr:housenumber":"3702",
    "addr:postcode":"64506",
    "addr:street":"Frederick Ave",
    "iso:country":"US",
    "sg:address":"3702 Frederick Ave",
    "sg:city":"Saint Joseph",
    "sg:classifiers":[
        {
            "category":"Shopping",
            "subcategory":"Jewelry",
            "type":"Retail Goods"
        }
    ],
    "sg:phone":"+1 816 232 1300",
    "sg:postcode":"64506",
    "sg:province":"MO",
    "wof:name":"Zales Jewelers",
    "wof:placetype":"venue"
},
  "geometry": {"coordinates":[-94.80159,39.77687],"type":"Point"}
}