{
  "type": "Feature",
  "properties": {
    "iso:country":"US",
    "sg:address":"30579 State Hwy 46",
    "sg:city":"Fairfax",
    "sg:phone":"+1 660 686 2812",
    "sg:postcode":"64446",
    "sg:province":"MO",
    "sg:tags":[
        "beef",
        "farm",
        "corn",
        "soybean",
        "cattle",
        "feedlot"
    ],
    "wof:name":"Gary Burns",
    "wof:placetype":"venue"
},
  "geometry": {"coordinates":[-95.282703,40.335541],"type":"Point"}
}