{
  "type": "Feature",
  "properties": {
    "iso:country":"US",
    "sg:address":"7 Cedar Ct",
    "sg:city":"Union",
    "sg:classifiers":[
        {
            "category":"Manufacturing",
            "subcategory":"Signs",
            "type":"Manufacturing & Wholesale Goods"
        }
    ],
    "sg:phone":"+1 636 583 1145",
    "sg:postcode":"63084",
    "sg:province":"MO",
    "sg:tags":[
        "rubber",
        "mfg",
        "specialty",
        "mechanical"
    ],
    "wof:name":"Real Time Products",
    "wof:placetype":"venue"
},
  "geometry": {"coordinates":[-91.02221400000001,38.463183],"type":"Point"}
}