{
  "type": "Feature",
  "properties": {
    "iso:country":"US",
    "sg:address":"1339 Harvestowne Ind Dr",
    "sg:city":"St Charles",
    "sg:classifiers":[
        {
            "category":"Retail",
            "subcategory":"Funeral Services",
            "type":"Services"
        }
    ],
    "sg:phone":"+1 636 447 6944",
    "sg:postcode":"63304",
    "sg:province":"MO",
    "sg:tags":[
        "crematory"
    ],
    "wof:name":"Broder Cremation Svc Inc",
    "wof:placetype":"venue"
},
  "geometry": {"coordinates":[-90.607174,38.740177],"type":"Point"}
}