{
  "type": "Feature",
  "properties": {
    "iso:country":"US",
    "sg:address":"3740 S Noland Rd",
    "sg:city":"Independence",
    "sg:classifiers":[
        {
            "category":"Shopping",
            "type":"Retail Goods"
        }
    ],
    "sg:phone":"+1 816 252 6652",
    "sg:postcode":"64055",
    "sg:province":"MO",
    "sg:tags":[
        "mexican"
    ],
    "wof:name":"LA Tapatia",
    "wof:placetype":"venue"
},
  "geometry": {"coordinates":[-94.415071,39.050923],"type":"Point"}
}