{
  "type": "Feature",
  "properties": {
    "addr:full":"6425 Natural Bridge Rd St Louis MO 63121",
    "addr:housenumber":"6425",
    "addr:postcode":"63121",
    "addr:street":"Natural Bridge Rd",
    "iso:country":"US",
    "sg:address":"6425 Natural Bridge Rd",
    "sg:city":"St Louis",
    "sg:classifiers":[
        {
            "category":"Utilities",
            "subcategory":"Mobile Phone",
            "type":"Services"
        }
    ],
    "sg:phone":"+1 314 383 2501",
    "sg:postcode":"63121",
    "sg:province":"MO",
    "sg:tags":[
        "telephone",
        "cellular"
    ],
    "wof:name":"Nextel",
    "wof:placetype":"venue"
},
  "geometry": {"coordinates":[-90.28213100000001,38.694253],"type":"Point"}
}