{
  "type": "Feature",
  "properties": {
    "iso:country":"US",
    "sg:address":"2771 Co Rd 5600",
    "sg:city":"Willow Springs",
    "sg:classifiers":[
        {
            "category":"Professional",
            "type":"Services"
        }
    ],
    "sg:phone":"+1 417 469 3445",
    "sg:postcode":"65793",
    "sg:province":"MO",
    "wof:name":"Lee Wood",
    "wof:placetype":"venue"
},
  "geometry": {"coordinates":[-91.99159,36.966506],"type":"Point"}
}