{
  "type": "Feature",
  "properties": {
    "iso:country":"US",
    "sg:address":"9267 State Hwy 76",
    "sg:city":"Reeds Spring",
    "sg:classifiers":[
        {
            "category":"Food & Beverages",
            "subcategory":"Groceries & Convenience Stores",
            "type":"Retail Goods"
        }
    ],
    "sg:phone":"+1 417 338 2928",
    "sg:postcode":"65737",
    "sg:province":"MO",
    "wof:name":"Wagner's One Stop",
    "wof:placetype":"venue"
},
  "geometry": {"coordinates":[-93.340395,36.686634],"type":"Point"}
}