{
  "type": "Feature",
  "properties": {
    "iso:country":"US",
    "sg:address":"18680 E 39th St S",
    "sg:city":"Independence",
    "sg:classifiers":[
        {
            "category":"Home & Garden",
            "subcategory":"Furniture",
            "type":"Retail Goods"
        }
    ],
    "sg:phone":"+1 816 795 5200",
    "sg:postcode":"64057",
    "sg:province":"MO",
    "wof:name":"Ethan Allen Interiors Inc",
    "wof:placetype":"venue"
},
  "geometry": {"coordinates":[-94.35764500000001,39.048044],"type":"Point"}
}