{
  "type": "Feature",
  "properties": {
    "iso:country":"US",
    "sg:address":"11242 N Ave",
    "sg:city":"Westboro",
    "sg:phone":"+1 660 984 5697",
    "sg:postcode":"64498",
    "sg:province":"MO",
    "sg:tags":[
        "farm",
        "corn",
        "soybean"
    ],
    "wof:name":"Peregrine Bros Farms",
    "wof:placetype":"venue"
},
  "geometry": {"coordinates":[-95.43141,40.564431],"type":"Point"}
}