{
  "type": "Feature",
  "properties": {
    "iso:country":"US",
    "sg:address":"9213 Cyclone School Rd",
    "sg:city":"Lees Summit",
    "sg:classifiers":[
        {
            "category":"Social Services",
            "subcategory":"Child Care",
            "type":"Services"
        }
    ],
    "sg:phone":"+1 816 246 8986",
    "sg:postcode":"64064",
    "sg:province":"MO",
    "sg:tags":[
        "day"
    ],
    "wof:name":"Edukids Inc",
    "wof:placetype":"venue"
},
  "geometry": {"coordinates":[-94.307733,38.952451],"type":"Point"}
}