{
  "type": "Feature",
  "properties": {
    "iso:country":"US",
    "sg:address":"RR 2 Box 26",
    "sg:city":"Memphis",
    "sg:classifiers":[
        {
            "category":"Manufacturing",
            "subcategory":"Pet Food",
            "type":"Manufacturing & Wholesale Goods"
        },
        {
            "category":"Farming",
            "subcategory":"Farm",
            "type":"Manufacturing & Wholesale Goods"
        }
    ],
    "sg:phone":"+1 660 328 6275",
    "sg:postcode":"63555",
    "sg:province":"MO",
    "sg:tags":[
        "hay"
    ],
    "wof:name":"Baker, Hillis",
    "wof:placetype":"venue"
},
  "geometry": {"coordinates":[-92.171558,40.465805],"type":"Point"}
}