{
  "type": "Feature",
  "properties": {
    "iso:country":"US",
    "sg:address":"2 2nd St",
    "sg:city":"Butler",
    "sg:classifiers":[
        {
            "category":"Building & Trades",
            "subcategory":"Construction",
            "type":"Services"
        }
    ],
    "sg:phone":"+1 660 679 5980",
    "sg:postcode":"64734",
    "sg:province":"MO",
    "sg:tags":[
        "contractor"
    ],
    "wof:name":"South 71 Rebuilders",
    "wof:placetype":"venue"
},
  "geometry": {"coordinates":[-94.592556,38.6789],"type":"Point"}
}