{
  "type": "Feature",
  "properties": {
    "iso:country":"US",
    "sg:address":"1106 S Farm Rd 201",
    "sg:city":"Springfield",
    "sg:classifiers":[
        {
            "category":"Building & Trades",
            "subcategory":"Landscaping Services",
            "type":"Services"
        }
    ],
    "sg:phone":"+1 417 831 8251",
    "sg:postcode":"65809",
    "sg:province":"MO",
    "wof:name":"Jon Waltz",
    "wof:placetype":"venue"
},
  "geometry": {"coordinates":[-93.179782,37.19278],"type":"Point"}
}