{
  "type": "Feature",
  "properties": {
    "iso:country":"US",
    "sg:address":"3961 S Campbell Ave",
    "sg:city":"Springfield",
    "sg:classifiers":[
        {
            "category":"Banks & Credit Unions",
            "subcategory":"Bank",
            "type":"Services"
        }
    ],
    "sg:phone":"+1 417 888 5880",
    "sg:postcode":"65807",
    "sg:province":"MO",
    "sg:tags":[
        "state",
        "commercial",
        "investment"
    ],
    "sg:website":"http://www.greatsouthernbank.com",
    "wof:name":"Great Southern Bank",
    "wof:placetype":"venue"
},
  "geometry": {"coordinates":[-93.296125,37.142365],"type":"Point"}
}