{
  "type": "Feature",
  "properties": {
    "iso:country":"US",
    "sg:address":"15322 Scarborough Ct",
    "sg:city":"Chesterfield",
    "sg:classifiers":[
        {
            "category":"Manufacturing",
            "subcategory":"Signs",
            "type":"Manufacturing & Wholesale Goods"
        }
    ],
    "sg:phone":"+1 636 532 1655",
    "sg:postcode":"63017",
    "sg:province":"MO",
    "sg:tags":[
        "advertising",
        "specialty",
        "mfg"
    ],
    "wof:name":"Ad Lady Impressions",
    "wof:placetype":"venue"
},
  "geometry": {"coordinates":[-90.558454,38.620699],"type":"Point"}
}