{
  "type": "Feature",
  "properties": {
    "iso:country":"US",
    "sg:address":"5201 Delmar Blvd",
    "sg:city":"Saint Louis",
    "sg:classifiers":[
        {
            "category":"Personal",
            "type":"Services"
        }
    ],
    "sg:phone":"+1 314 367 9444",
    "sg:postcode":"63108",
    "sg:province":"MO",
    "sg:tags":[
        "mover"
    ],
    "wof:name":"Al Thomas Moving & Storage Company",
    "wof:placetype":"venue"
},
  "geometry": {"coordinates":[-90.271004,38.652199],"type":"Point"}
}