{
  "type": "Feature",
  "properties": {
    "iso:country":"US",
    "sg:address":"4580 Laclede Ave",
    "sg:city":"St Louis",
    "sg:classifiers":[
        {
            "category":"Restaurant",
            "type":"Food & Drink"
        }
    ],
    "sg:phone":"+1 314 454 0600",
    "sg:postcode":"63108",
    "sg:province":"MO",
    "sg:tags":[
        "french"
    ],
    "sg:website":"www.brasseriebyniche.com/",
    "wof:name":"Brasserie by Niche",
    "wof:placetype":"venue"
},
  "geometry": {"coordinates":[-90.261777,38.640172],"type":"Point"}
}