{
  "type": "Feature",
  "properties": {
    "iso:country":"US",
    "sg:address":"182 Juanita Ln",
    "sg:city":"Arnold",
    "sg:classifiers":[
        {
            "category":"Professional",
            "subcategory":"Business Services",
            "type":"Services"
        }
    ],
    "sg:phone":"+1 636 296 0570",
    "sg:postcode":"63010",
    "sg:province":"MO",
    "wof:name":"Whetstone Enterprises Inc",
    "wof:placetype":"venue"
},
  "geometry": {"coordinates":[-90.401798,38.41183],"type":"Point"}
}