{
  "type": "Feature",
  "properties": {
    "iso:country":"US",
    "sg:address":"18716 State Hwy 177",
    "sg:city":"Jackson",
    "sg:classifiers":[
        {
            "category":"Utilities",
            "subcategory":"Refuse",
            "type":"Services"
        }
    ],
    "sg:phone":"+1 573 335 3330",
    "sg:postcode":"63755",
    "sg:province":"MO",
    "sg:tags":[
        "garbage",
        "collection"
    ],
    "wof:name":"Continental Waste Ind-Jackson",
    "wof:placetype":"venue"
},
  "geometry": {"coordinates":[-89.58695299999999,37.464612],"type":"Point"}
}