{
  "type": "Feature",
  "properties": {
    "iso:country":"US",
    "sg:address":"9884 Copper Hill Rd",
    "sg:city":"St Louis",
    "sg:classifiers":[
        {
            "category":"Real Estate",
            "subcategory":"Real Estate Agent",
            "type":"Services"
        }
    ],
    "sg:phone":"+1 314 965 0100",
    "sg:postcode":"63124",
    "sg:province":"MO",
    "sg:tags":[
        "management"
    ],
    "wof:name":"Duggan Samuel W Inc Realtor",
    "wof:placetype":"venue"
},
  "geometry": {"coordinates":[-90.38395,38.612035],"type":"Point"}
}