{
  "type": "Feature",
  "properties": {
    "iso:country":"US",
    "sg:address":"9350 Lincoln Dr",
    "sg:city":"St Louis",
    "sg:classifiers":[
        {
            "category":"Professional",
            "subcategory":"Art Services",
            "type":"Services"
        }
    ],
    "sg:phone":"+1 314 821 8100",
    "sg:postcode":"63127",
    "sg:province":"MO",
    "sg:tags":[
        "graphic",
        "designer"
    ],
    "wof:name":"Norton's House Inc",
    "wof:placetype":"venue"
},
  "geometry": {"coordinates":[-90.400338,38.538911],"type":"Point"}
}