{
  "type": "Feature",
  "properties": {
    "iso:country":"US",
    "sg:address":"4911 Wyaconda St",
    "sg:city":"Hannibal",
    "sg:classifiers":[
        {
            "category":"Manufacturing",
            "subcategory":"Buildings",
            "type":"Manufacturing & Wholesale Goods"
        },
        {
            "category":"Professional",
            "subcategory":"Employment Agencies",
            "type":"Services"
        },
        {
            "category":"Building & Trades",
            "subcategory":"Construction",
            "type":"Services"
        }
    ],
    "sg:phone":"+1 573 406 0889",
    "sg:postcode":"63401",
    "sg:province":"MO",
    "sg:tags":[
        "industrial",
        "builder",
        "accessibility",
        "preservation",
        "contractor",
        "disabled",
        "restoration",
        "contractors-commercial",
        "home"
    ],
    "sg:website":"http://www.godertconstruction.com",
    "wof:name":"Godert Construction",
    "wof:placetype":"venue"
},
  "geometry": {"coordinates":[-91.387254,39.725281],"type":"Point"}
}