{
  "type": "Feature",
  "properties": {
    "iso:country":"US",
    "sg:address":"3008 Sutton Blvd",
    "sg:city":"Saint Louis",
    "sg:classifiers":[
        {
            "category":"Real Estate",
            "subcategory":"Architect",
            "type":"Services"
        }
    ],
    "sg:phone":"+1 314 781 2977",
    "sg:postcode":"63143",
    "sg:province":"MO",
    "wof:name":"Fairchild Peter W Architect",
    "wof:placetype":"venue"
},
  "geometry": {"coordinates":[-90.32028,38.608951],"type":"Point"}
}