{
  "type": "Feature",
  "properties": {
    "iso:country":"US",
    "sg:address":"6607 Chippewa St",
    "sg:city":"Saint Louis",
    "sg:classifiers":[
        {
            "category":"Bakery",
            "type":"Food & Drink"
        }
    ],
    "sg:menulink":"http://www.allmenus.com/mo/st-louis/105889-panera-bread/menu/",
    "sg:phone":"+1 314 781 6469",
    "sg:postcode":"63109",
    "sg:province":"MO",
    "sg:tags":[
        "american",
        "sandwich",
        "pastry"
    ],
    "wof:name":"Panera Bread",
    "wof:placetype":"venue"
},
  "geometry": {"coordinates":[-90.305013,38.591174],"type":"Point"}
}