{
  "type": "Feature",
  "properties": {
    "iso:country":"US",
    "sg:address":"950 Kent St",
    "sg:city":"Liberty",
    "sg:classifiers":[
        {
            "category":"Wholesale",
            "subcategory":"Electrical",
            "type":"Manufacturing & Wholesale Goods"
        }
    ],
    "sg:phone":"+1 816 792 0160",
    "sg:postcode":"64068",
    "sg:province":"MO",
    "sg:tags":[
        "supply"
    ],
    "wof:name":"Jr Electrical Supply",
    "wof:placetype":"venue"
},
  "geometry": {"coordinates":[-94.433723,39.234368],"type":"Point"}
}