{
  "type": "Feature",
  "properties": {
    "iso:country":"US",
    "sg:address":"20 S Jefferson Ave",
    "sg:city":"Marshall",
    "sg:classifiers":[
        {
            "category":"Professional",
            "subcategory":"Computer Services",
            "type":"Services"
        }
    ],
    "sg:phone":"+1 660 886 9944",
    "sg:postcode":"65340",
    "sg:province":"MO",
    "sg:tags":[
        "repair",
        "consulting",
        "networking"
    ],
    "wof:name":"Lamm Technical Resources",
    "wof:placetype":"venue"
},
  "geometry": {"coordinates":[-93.19584999999999,39.12063],"type":"Point"}
}