{
  "type": "Feature",
  "properties": {
    "iso:country":"US",
    "sg:address":"504 N Belt Hwy",
    "sg:city":"Saint Joseph",
    "sg:classifiers":[
        {
            "category":"Restaurant",
            "type":"Food & Drink"
        }
    ],
    "sg:menulink":"http://www.allmenus.com/mo/st-joseph/121733-fazolis/menu/",
    "sg:phone":"+1 816 387 9539",
    "sg:postcode":"64506",
    "sg:province":"MO",
    "sg:tags":[
        "italian"
    ],
    "wof:name":"Fazoli's",
    "wof:placetype":"venue"
},
  "geometry": {"coordinates":[-94.803512,39.770855],"type":"Point"}
}