{
  "type": "Feature",
  "properties": {
    "iso:country":"US",
    "sg:address":"929 W 7th St",
    "sg:city":"Joplin",
    "sg:classifiers":[
        {
            "category":"Autos & Motor Vehicles",
            "subcategory":"Automobile Sales",
            "type":"Retail Goods"
        }
    ],
    "sg:phone":"+1 417 206 2233",
    "sg:postcode":"64801",
    "sg:province":"MO",
    "sg:tags":[
        "used"
    ],
    "wof:name":"Quality Auto Exchange",
    "wof:placetype":"venue"
},
  "geometry": {"coordinates":[-94.523454,37.084394],"type":"Point"}
}