{
  "type": "Feature",
  "properties": {
    "addr:full":"6 Clarkson Wilson Center Chesterfield MO 63017",
    "addr:housenumber":"6",
    "addr:postcode":"63017",
    "addr:street":"Clarkson Wilson Center",
    "iso:country":"US",
    "sg:address":"6 Clarkson Wilson Center",
    "sg:city":"Chesterfield",
    "sg:classifiers":[
        {
            "category":"Manufacturing",
            "subcategory":"Printing",
            "type":"Manufacturing & Wholesale Goods"
        }
    ],
    "sg:phone":"+1 636 530 0020",
    "sg:postcode":"63017",
    "sg:province":"MO",
    "sg:tags":[
        "print",
        "shop"
    ],
    "wof:name":"Minuteman Press",
    "wof:placetype":"venue"
},
  "geometry": {"coordinates":[-90.578284,38.627395],"type":"Point"}
}