{
  "type": "Feature",
  "properties": {
    "iso:country":"US",
    "sg:address":"9720 Page Ave",
    "sg:city":"Saint Louis",
    "sg:classifiers":[
        {
            "category":"Cafe",
            "type":"Food & Drink"
        }
    ],
    "sg:menulink":"http://www.allmenus.com/mo/creve-coeur/54251-vn-cafe/menu/",
    "sg:phone":"+1 314 426 7950",
    "sg:postcode":"63132",
    "sg:province":"MO",
    "sg:tags":[
        "asian",
        "vietnamese"
    ],
    "wof:name":"V.n. Cafe",
    "wof:placetype":"venue"
},
  "geometry": {"coordinates":[-90.374341,38.688248],"type":"Point"}
}