{
  "type": "Feature",
  "properties": {
    "iso:country":"US",
    "sg:address":"1507 W 23rd St S",
    "sg:city":"Independence",
    "sg:classifiers":[
        {
            "category":"Retail",
            "subcategory":"Repair Shop",
            "type":"Services"
        }
    ],
    "sg:phone":"+1 816 836 5700",
    "sg:postcode":"64050",
    "sg:province":"MO",
    "sg:tags":[
        "equipment",
        "electronic",
        "communication"
    ],
    "sg:website":"www.kcwirelessinc.com",
    "wof:name":"K C Wireless Inc",
    "wof:placetype":"venue"
},
  "geometry": {"coordinates":[-94.436021,39.079874],"type":"Point"}
}