{
  "type": "Feature",
  "properties": {
    "iso:country":"US",
    "sg:address":"6400 E 40 Ter",
    "sg:city":"Kansas City",
    "sg:classifiers":[
        {
            "category":"Building & Trades",
            "subcategory":"Construction",
            "type":"Services"
        }
    ],
    "sg:phone":"+1 816 921 7373",
    "sg:postcode":"64129",
    "sg:province":"MO",
    "sg:tags":[
        "sandblasting"
    ],
    "wof:name":"GED Inc",
    "wof:placetype":"venue"
},
  "geometry": {"coordinates":[-94.509608,39.052443],"type":"Point"}
}