{
  "type": "Feature",
  "properties": {
    "iso:country":"US",
    "sg:address":"12326 State Highway 153",
    "sg:city":"Essex",
    "sg:classifiers":[
        {
            "category":"Insurance",
            "subcategory":"Hazard Insurance",
            "type":"Services"
        },
        {
            "category":"Banks & Credit Unions",
            "subcategory":"Financial Services",
            "type":"Services"
        },
        {
            "category":"Organizations",
            "subcategory":"Membership Organization",
            "type":"Services"
        }
    ],
    "sg:phone":"+1 573 283 5925",
    "sg:postcode":"63846",
    "sg:province":"MO",
    "sg:tags":[
        "consultant",
        "planning",
        "fraternal"
    ],
    "sg:website":"http://www.modern-woodmen.org",
    "wof:name":"Modern Woodmen of America",
    "wof:placetype":"venue"
},
  "geometry": {"coordinates":[-89.808129,36.795527],"type":"Point"}
}