{
  "type": "Feature",
  "properties": {
    "addr:full":"700 Main St Trenton MO 64683",
    "addr:housenumber":"700",
    "addr:postcode":"64683",
    "addr:street":"Main St",
    "iso:country":"US",
    "sg:address":"700 Main St",
    "sg:city":"Trenton",
    "sg:classifiers":[
        {
            "category":"Government",
            "subcategory":"Office",
            "type":"Public Place"
        }
    ],
    "sg:phone":"+1 660 359 5643",
    "sg:postcode":"64683",
    "sg:province":"MO",
    "sg:tags":[
        "agricultural",
        "regulation",
        "marketing"
    ],
    "wof:name":"Grundy County Extension Agent",
    "wof:placetype":"venue"
},
  "geometry": {"coordinates":[-93.61875999999999,40.074174],"type":"Point"}
}