{
  "type": "Feature",
  "properties": {
    "iso:country":"US",
    "sg:address":"11810 Borman Dr",
    "sg:city":"St Louis",
    "sg:classifiers":[
        {
            "category":"Professional",
            "type":"Services"
        },
        {
            "category":"Professional",
            "subcategory":"Research",
            "type":"Services"
        }
    ],
    "sg:phone":"+1 314 991 1857",
    "sg:postcode":"63146",
    "sg:province":"MO",
    "sg:tags":[
        "laboratory",
        "consulting",
        "chemist"
    ],
    "sg:website":"www.ww-ww.com/gateway",
    "wof:name":"Gateway Chemical Technology",
    "wof:placetype":"venue"
},
  "geometry": {"coordinates":[-90.43835900000001,38.693685],"type":"Point"}
}