{
  "type": "Feature",
  "properties": {
    "iso:country":"US",
    "sg:address":"216 Spooners Mill Dr",
    "sg:city":"Ballwin",
    "sg:classifiers":[
        {
            "category":"Professional",
            "type":"Services"
        }
    ],
    "sg:phone":"+1 636 391 8855",
    "sg:postcode":"63011",
    "sg:province":"MO",
    "wof:name":"Imogene O Hopper",
    "wof:placetype":"venue"
},
  "geometry": {"coordinates":[-90.546164,38.599069],"type":"Point"}
}