{
  "type": "Feature",
  "properties": {
    "iso:country":"US",
    "sg:address":"3402 Bluff View Dr",
    "sg:city":"St Charles",
    "sg:classifiers":[
        {
            "category":"Professional",
            "type":"Services"
        }
    ],
    "sg:phone":"+1 636 939 9422",
    "sg:postcode":"63303",
    "sg:province":"MO",
    "sg:tags":[
        "establishment"
    ],
    "wof:name":"Weeks & Weeks",
    "wof:placetype":"venue"
},
  "geometry": {"coordinates":[-90.560548,38.719476],"type":"Point"}
}