{
  "type": "Feature",
  "properties": {
    "iso:country":"US",
    "sg:address":"3107 N Union St",
    "sg:city":"Independence",
    "sg:classifiers":[
        {
            "category":"Professional",
            "subcategory":"Secretarial Services",
            "type":"Services"
        }
    ],
    "sg:phone":"+1 816 254 4445",
    "sg:postcode":"64050",
    "sg:province":"MO",
    "sg:tags":[
        "reporting"
    ],
    "wof:name":"Ace Scrtarial Office Solutions",
    "wof:placetype":"venue"
},
  "geometry": {"coordinates":[-94.4221,39.12269],"type":"Point"}
}