{
  "type": "Feature",
  "properties": {
    "iso:country":"US",
    "sg:address":"30 NW 1621st Rd",
    "sg:city":"Kingsville",
    "sg:classifiers":[
        {
            "category":"Retail",
            "subcategory":"Auto Repair",
            "type":"Services"
        }
    ],
    "sg:phone":"+1 816 597 3800",
    "sg:postcode":"64061",
    "sg:province":"MO",
    "sg:tags":[
        "repairing",
        "automobile"
    ],
    "wof:name":"Pitstop Auto Svc & Detail",
    "wof:placetype":"venue"
},
  "geometry": {"coordinates":[-94.05177399999999,38.776289],"type":"Point"}
}