{
  "type": "Feature",
  "properties": {
    "iso:country":"US",
    "sg:address":"2520 S Mina Ave",
    "sg:city":"Joplin",
    "sg:classifiers":[
        {
            "category":"Manufacturing",
            "subcategory":"Tools & Machinery",
            "type":"Manufacturing & Wholesale Goods"
        }
    ],
    "sg:phone":"+1 417 627 0083",
    "sg:postcode":"64804",
    "sg:province":"MO",
    "wof:name":"Fr3 Tool Distributor",
    "wof:placetype":"venue"
},
  "geometry": {"coordinates":[-94.55216,37.063021],"type":"Point"}
}