{
  "type": "Feature",
  "properties": {
    "iso:country":"US",
    "sg:address":"1264 Arch Ter",
    "sg:city":"Saint Louis",
    "sg:classifiers":[
        {
            "category":"Organizations",
            "subcategory":"Religious Organization",
            "type":"Services"
        }
    ],
    "sg:phone":"+1 314 645 1445",
    "sg:postcode":"63117",
    "sg:province":"MO",
    "wof:name":"Church of Little Flower",
    "wof:placetype":"venue"
},
  "geometry": {"coordinates":[-90.328024,38.631839],"type":"Point"}
}