{
  "type": "Feature",
  "properties": {
    "iso:country":"US",
    "sg:address":"11325 State Hwy M",
    "sg:city":"Ste Genevieve",
    "sg:classifiers":[
        {
            "category":"Retail",
            "subcategory":"Animal Services",
            "type":"Services"
        }
    ],
    "sg:phone":"+1 573 883 7989",
    "sg:postcode":"63670",
    "sg:province":"MO",
    "sg:tags":[
        "pet",
        "grooming",
        "washing"
    ],
    "wof:name":"Doghouse",
    "wof:placetype":"venue"
},
  "geometry": {"coordinates":[-90.041658,37.954823],"type":"Point"}
}