{
  "type": "Feature",
  "properties": {
    "iso:country":"US",
    "sg:address":"1442 Hoelzer Ct",
    "sg:city":"Pacific",
    "sg:classifiers":[
        {
            "category":"Professional",
            "subcategory":"Computer Services",
            "type":"Services"
        }
    ],
    "sg:phone":"+1 636 257 3530",
    "sg:postcode":"63069",
    "sg:province":"MO",
    "sg:tags":[
        "prepackaged",
        "software"
    ],
    "wof:name":"Bugeye Technologies",
    "wof:placetype":"venue"
},
  "geometry": {"coordinates":[-90.75810300000001,38.458911],"type":"Point"}
}