{
  "type": "Feature",
  "properties": {
    "iso:country":"US",
    "sg:address":"1500 W 7th St",
    "sg:city":"Fulton",
    "sg:classifiers":[
        {
            "category":"Wholesale",
            "subcategory":"Scrap",
            "type":"Manufacturing & Wholesale Goods"
        }
    ],
    "sg:phone":"+1 573 642 2582",
    "sg:postcode":"65251",
    "sg:province":"MO",
    "sg:tags":[
        "material"
    ],
    "wof:name":"Davids Recycling",
    "wof:placetype":"venue"
},
  "geometry": {"coordinates":[-91.97764599999999,38.855443],"type":"Point"}
}