{
  "type": "Feature",
  "properties": {
    "iso:country":"US",
    "sg:address":"7711 Carondelet Ave",
    "sg:city":"Saint Louis",
    "sg:classifiers":[
        {
            "category":"Real Estate",
            "subcategory":"Real Estate Agent",
            "type":"Services"
        }
    ],
    "sg:phone":"+1 314 863 2004",
    "sg:postcode":"63105",
    "sg:province":"MO",
    "sg:tags":[
        "brokerage",
        "management"
    ],
    "wof:name":"Commercial Realty Associates",
    "wof:placetype":"venue"
},
  "geometry": {"coordinates":[-90.33683000000001,38.648858],"type":"Point"}
}