{
  "type": "Feature",
  "properties": {
    "iso:country":"US",
    "sg:address":"525 Ellis Blvd",
    "sg:city":"Jefferson City",
    "sg:classifiers":[
        {
            "category":"Personal",
            "type":"Services"
        }
    ],
    "sg:phone":"+1 573 680 6768",
    "sg:postcode":"65101",
    "sg:province":"MO",
    "sg:tags":[
        "therapist",
        "massage"
    ],
    "wof:name":"Capitol City Sportsmassage",
    "wof:placetype":"venue"
},
  "geometry": {"coordinates":[-92.193012,38.55223],"type":"Point"}
}