{
  "type": "Feature",
  "properties": {
    "iso:country":"US",
    "sg:address":"1766 Burns Ave",
    "sg:city":"Saint Louis",
    "sg:classifiers":[
        {
            "category":"Insurance",
            "subcategory":"Insurance Agent",
            "type":"Services"
        }
    ],
    "sg:phone":"+1 314 381 0800",
    "sg:postcode":"63132",
    "sg:province":"MO",
    "wof:name":"Ivan North Insurance Agency",
    "wof:placetype":"venue"
},
  "geometry": {"coordinates":[-90.367671,38.686558],"type":"Point"}
}