{
  "type": "Feature",
  "properties": {
    "iso:country":"US",
    "sg:address":"1704 W A St",
    "sg:city":"Joplin",
    "sg:classifiers":[
        {
            "category":"Wholesale",
            "subcategory":"Hardware",
            "type":"Manufacturing & Wholesale Goods"
        }
    ],
    "sg:phone":"+1 417 623 7676",
    "sg:postcode":"64801",
    "sg:province":"MO",
    "sg:tags":[
        "heating"
    ],
    "wof:name":"Goodman Midwest",
    "wof:placetype":"venue"
},
  "geometry": {"coordinates":[-94.53234,37.092296],"type":"Point"}
}