{
  "type": "Feature",
  "properties": {
    "iso:country":"US",
    "sg:address":"900 N 18th St",
    "sg:city":"Ozark",
    "sg:classifiers":[
        {
            "category":"Travel",
            "subcategory":"Hotels & Motels",
            "type":"Entertainment"
        }
    ],
    "sg:phone":"+1 417 581 5800",
    "sg:postcode":"65721",
    "sg:province":"MO",
    "sg:tags":[
        "lodging"
    ],
    "sg:website":"http://www.daysinn.com",
    "wof:name":"Days Inn Ozark",
    "wof:placetype":"venue"
},
  "geometry": {"coordinates":[-93.227971,37.027281],"type":"Point"}
}