{
  "type": "Feature",
  "properties": {
    "iso:country":"US",
    "sg:address":"16049 Wilson Manor Dr",
    "sg:city":"Chesterfield",
    "sg:classifiers":[
        {
            "category":"Utilities",
            "subcategory":"Refuse",
            "type":"Services"
        }
    ],
    "sg:phone":"+1 636 536 1155",
    "sg:postcode":"63005",
    "sg:province":"MO",
    "sg:tags":[
        "garbage",
        "collection"
    ],
    "wof:name":"J D Express",
    "wof:placetype":"venue"
},
  "geometry": {"coordinates":[-90.583596,38.639547],"type":"Point"}
}