{
  "type": "Feature",
  "properties": {
    "iso:country":"US",
    "sg:address":"222 W Gregory Blvd",
    "sg:city":"Kansas City",
    "sg:classifiers":[
        {
            "category":"Organizations",
            "subcategory":"Non-profit Organization",
            "type":"Services"
        },
        {
            "category":"Professional",
            "subcategory":"Business Services",
            "type":"Services"
        }
    ],
    "sg:phone":"+1 816 333 1644",
    "sg:postcode":"64114",
    "sg:province":"MO",
    "sg:tags":[
        "fund",
        "counselor",
        "raising"
    ],
    "wof:name":"Pelofsky & Associates Inc",
    "wof:placetype":"venue"
},
  "geometry": {"coordinates":[-94.592941,38.999643],"type":"Point"}
}