{
  "type": "Feature",
  "properties": {
    "iso:country":"US",
    "sg:address":"433 State Hwy 13",
    "sg:city":"Warrensburg",
    "sg:classifiers":[
        {
            "category":"Autos & Motor Vehicles",
            "subcategory":"Automobile Sales",
            "type":"Retail Goods"
        }
    ],
    "sg:phone":"+1 660 429 2277",
    "sg:postcode":"64093",
    "sg:province":"MO",
    "sg:tags":[
        "car",
        "dealer"
    ],
    "wof:name":"Budget Auto Sales",
    "wof:placetype":"venue"
},
  "geometry": {"coordinates":[-93.735545,38.765971],"type":"Point"}
}