{
  "type": "Feature",
  "properties": {
    "iso:country":"US",
    "sg:address":"1308 S Maywood Ave",
    "sg:city":"Independence",
    "sg:classifiers":[
        {
            "category":"Utilities",
            "type":"Services"
        }
    ],
    "sg:phone":"+1 816 252 7989",
    "sg:postcode":"64052",
    "sg:province":"MO",
    "sg:tags":[
        "sanitary",
        "concrete",
        "automobile",
        "parking"
    ],
    "wof:name":"Precision Care Seal Coating Co",
    "wof:placetype":"venue"
},
  "geometry": {"coordinates":[-94.457514,39.094318],"type":"Point"}
}