{
  "type": "Feature",
  "properties": {
    "iso:country":"US",
    "sg:address":"19800 Wilderness Camp Rd",
    "sg:city":"Lawson",
    "sg:classifiers":[
        {
            "category":"Manufacturing",
            "subcategory":"Furniture",
            "type":"Manufacturing & Wholesale Goods"
        }
    ],
    "sg:phone":"+1 816 580 4972",
    "sg:postcode":"64062",
    "sg:province":"MO",
    "sg:tags":[
        "mfg"
    ],
    "wof:name":"Hull Manufacturing",
    "wof:placetype":"venue"
},
  "geometry": {"coordinates":[-94.130554,39.455379],"type":"Point"}
}