{
  "type": "Feature",
  "properties": {
    "iso:country":"US",
    "sg:address":"6312 Monterey Dr",
    "sg:city":"St Louis",
    "sg:classifiers":[
        {
            "category":"Organizations",
            "subcategory":"Religious Organization",
            "type":"Services"
        }
    ],
    "sg:phone":"+1 314 351 7736",
    "sg:postcode":"63123",
    "sg:province":"MO",
    "sg:tags":[
        "monastery",
        "convent"
    ],
    "wof:name":"Sisters Of St Joseph",
    "wof:placetype":"venue"
},
  "geometry": {"coordinates":[-90.322912,38.567648],"type":"Point"}
}