{
  "type": "Feature",
  "properties": {
    "iso:country":"US",
    "sg:address":"6850 Gravois Ave",
    "sg:city":"St Louis",
    "sg:classifiers":[
        {
            "category":"Food & Beverages",
            "subcategory":"Groceries & Convenience Stores",
            "type":"Retail Goods"
        }
    ],
    "sg:phone":"+1 314 832 7711",
    "sg:postcode":"63116",
    "sg:province":"MO",
    "wof:name":"7-Eleven",
    "wof:placetype":"venue"
},
  "geometry": {"coordinates":[-90.284514,38.570631],"type":"Point"}
}