{
  "type": "Feature",
  "properties": {
    "iso:country":"US",
    "sg:address":"1115 NE Deerbrook Ter",
    "sg:city":"Lees Summit",
    "sg:classifiers":[
        {
            "category":"Professional",
            "subcategory":"Computer Services",
            "type":"Services"
        }
    ],
    "sg:phone":"+1 816 347 8310",
    "sg:postcode":"64086",
    "sg:province":"MO",
    "sg:tags":[
        "datum"
    ],
    "wof:name":"Web Millard Development",
    "wof:placetype":"venue"
},
  "geometry": {"coordinates":[-94.350937,38.934415],"type":"Point"}
}