{
  "type": "Feature",
  "properties": {
    "iso:country":"US",
    "sg:address":"3303 Meramec St",
    "sg:city":"Saint Louis",
    "sg:classifiers":[
        {
            "category":"Freight",
            "type":"Transportation"
        }
    ],
    "sg:phone":"+1 314 481 5151",
    "sg:postcode":"63118",
    "sg:province":"MO",
    "sg:tags":[
        "operator",
        "local",
        "trucking"
    ],
    "wof:name":"Go For Delivery Co",
    "wof:placetype":"venue"
},
  "geometry": {"coordinates":[-90.24206100000001,38.580735],"type":"Point"}
}