{
  "type": "Feature",
  "properties": {
    "iso:country":"US",
    "sg:address":"8126 Big Bend Blvd",
    "sg:city":"Saint Louis",
    "sg:classifiers":[
        {
            "category":"Personal",
            "subcategory":"Tanning Parlor",
            "type":"Services"
        },
        {
            "category":"Sports & Exercise",
            "subcategory":"Gym",
            "type":"Entertainment"
        }
    ],
    "sg:phone":"+1 314 968 1449",
    "sg:postcode":"63119",
    "sg:province":"MO",
    "sg:tags":[
        "salon",
        "fitness",
        "physical",
        "facility"
    ],
    "wof:name":"Maui Sun In Webster Groves",
    "wof:placetype":"venue"
},
  "geometry": {"coordinates":[-90.338329,38.591604],"type":"Point"}
}