{
  "type": "Feature",
  "properties": {
    "iso:country":"US",
    "sg:address":"1610 Jeffco Blvd",
    "sg:city":"Arnold",
    "sg:classifiers":[
        {
            "category":"Personal",
            "subcategory":"Beauty Salon",
            "type":"Services"
        }
    ],
    "sg:phone":"+1 636 287 8981",
    "sg:postcode":"63010",
    "sg:province":"MO",
    "sg:tags":[
        "shop"
    ],
    "wof:name":"5 Stars Nails",
    "wof:placetype":"venue"
},
  "geometry": {"coordinates":[-90.379182,38.431293],"type":"Point"}
}