{
  "type": "Feature",
  "properties": {
    "iso:country":"US",
    "sg:address":"2213 Pendleton Cir",
    "sg:city":"O Fallon",
    "sg:classifiers":[
        {
            "category":"Arts & Performance",
            "subcategory":"Theater",
            "type":"Entertainment"
        }
    ],
    "sg:phone":"+1 636 939 5007",
    "sg:postcode":"63368",
    "sg:province":"MO",
    "sg:tags":[
        "group"
    ],
    "wof:name":"Ameridj",
    "wof:placetype":"venue"
},
  "geometry": {"coordinates":[-90.69477000000001,38.727429],"type":"Point"}
}