{
  "type": "Feature",
  "properties": {
    "iso:country":"US",
    "sg:address":"17550 SE 11th Rd",
    "sg:city":"Dearborn",
    "sg:phone":"+1 816 685 3472",
    "sg:postcode":"64448",
    "sg:province":"MO",
    "sg:tags":[
        "farm",
        "corn",
        "soybean"
    ],
    "wof:name":"Francis Dreier Jr",
    "wof:placetype":"venue"
},
  "geometry": {"coordinates":[-94.849282,39.549511],"type":"Point"}
}