{
  "type": "Feature",
  "properties": {
    "iso:country":"US",
    "sg:address":"115 SW 1991st Rd",
    "sg:city":"Kingsville",
    "sg:classifiers":[
        {
            "category":"Manufacturing",
            "subcategory":"Printing",
            "type":"Manufacturing & Wholesale Goods"
        }
    ],
    "sg:phone":"+1 816 781 2378",
    "sg:postcode":"64061",
    "sg:province":"MO",
    "sg:tags":[
        "sewing",
        "publishing"
    ],
    "wof:name":"Blue Whale Designs",
    "wof:placetype":"venue"
},
  "geometry": {"coordinates":[-94.122499,38.75738],"type":"Point"}
}