{
  "type": "Feature",
  "properties": {
    "iso:country":"US",
    "sg:address":"1205 W 8th St",
    "sg:city":"Cameron",
    "sg:classifiers":[
        {
            "category":"Farming",
            "subcategory":"Livestock Farm",
            "type":"Manufacturing & Wholesale Goods"
        }
    ],
    "sg:phone":"+1 816 632 6081",
    "sg:postcode":"64429",
    "sg:province":"MO",
    "sg:tags":[
        "beef",
        "feedlot",
        "cattle"
    ],
    "wof:name":"Ken Bray",
    "wof:placetype":"venue"
},
  "geometry": {"coordinates":[-94.25399,39.746326],"type":"Point"}
}