{
  "type": "Feature",
  "properties": {
    "iso:country":"US",
    "sg:address":"1523 E Saint Louis St",
    "sg:city":"Springfield",
    "sg:classifiers":[
        {
            "category":"Personal",
            "subcategory":"Beauty Salon",
            "type":"Services"
        }
    ],
    "sg:phone":"+1 417 865 2737",
    "sg:postcode":"65802",
    "sg:province":"MO",
    "sg:tags":[
        "shop"
    ],
    "wof:name":"Mixed Company",
    "wof:placetype":"venue"
},
  "geometry": {"coordinates":[-93.26657899999999,37.209445],"type":"Point"}
}