{
  "type": "Feature",
  "properties": {
    "iso:country":"US",
    "sg:address":"18067 Edison Ave",
    "sg:city":"Chesterfield",
    "sg:classifiers":[
        {
            "category":"Home & Garden",
            "subcategory":"Hardware",
            "type":"Retail Goods"
        }
    ],
    "sg:phone":"+1 636 532 9888",
    "sg:postcode":"63005",
    "sg:province":"MO",
    "sg:tags":[
        "tool"
    ],
    "sg:website":"www.buffalotools.com",
    "wof:name":"New Buffalo Corp",
    "wof:placetype":"venue"
},
  "geometry": {"coordinates":[-90.640743,38.664103],"type":"Point"}
}