{
  "type": "Feature",
  "properties": {
    "addr:full":"3407 S Campbell Ave Springfield MO 65807",
    "addr:housenumber":"3407",
    "addr:postcode":"65807",
    "addr:street":"S Campbell Ave",
    "iso:country":"US",
    "sg:address":"3407 S Campbell Ave",
    "sg:city":"Springfield",
    "sg:classifiers":[
        {
            "category":"Shopping",
            "subcategory":"Shoes",
            "type":"Retail Goods"
        }
    ],
    "sg:phone":"+1 417 886 2177",
    "sg:postcode":"65807",
    "sg:province":"MO",
    "wof:name":"Payless Shoe Source",
    "wof:placetype":"venue"
},
  "geometry": {"coordinates":[-93.295901,37.149969],"type":"Point"}
}