{
  "type": "Feature",
  "properties": {
    "iso:country":"US",
    "sg:address":"702 State Hwy 47",
    "sg:city":"Warrenton",
    "sg:classifiers":[
        {
            "category":"Shopping",
            "subcategory":"Stationery & Office Supplies",
            "type":"Retail Goods"
        }
    ],
    "sg:phone":"+1 636 456 3461",
    "sg:postcode":"63383",
    "sg:province":"MO",
    "wof:name":"Wilcoxen Office Supply",
    "wof:placetype":"venue"
},
  "geometry": {"coordinates":[-91.144381,38.803615],"type":"Point"}
}