{
  "type": "Feature",
  "properties": {
    "iso:country":"US",
    "sg:address":"721 Jefferson St",
    "sg:city":"Jefferson City",
    "sg:classifiers":[
        {
            "category":"Building & Trades",
            "subcategory":"Cleaning & Sanitation",
            "type":"Services"
        }
    ],
    "sg:phone":"+1 573 635 9297",
    "sg:postcode":"65101",
    "sg:province":"MO",
    "sg:tags":[
        "maintenance"
    ],
    "wof:name":"B G Maintenance",
    "wof:placetype":"venue"
},
  "geometry": {"coordinates":[-92.17728099999999,38.572702],"type":"Point"}
}