{
  "type": "Feature",
  "properties": {
    "iso:country":"US",
    "sg:address":"10837 W Florissant Ave",
    "sg:city":"Saint Louis",
    "sg:classifiers":[
        {
            "category":"Autos & Motor Vehicles",
            "subcategory":"Automobile Sales",
            "type":"Retail Goods"
        }
    ],
    "sg:phone":"+1 314 521 1258",
    "sg:postcode":"63136",
    "sg:province":"MO",
    "sg:tags":[
        "used"
    ],
    "wof:name":"Ferguson Bus Liason Office",
    "wof:placetype":"venue"
},
  "geometry": {"coordinates":[-90.280199,38.769607],"type":"Point"}
}