{
  "type": "Feature",
  "properties": {
    "iso:country":"US",
    "sg:address":"335 S Kirkwood Rd",
    "sg:city":"St Louis",
    "sg:classifiers":[
        {
            "category":"Organizations",
            "subcategory":"Religious Organization",
            "type":"Services"
        }
    ],
    "sg:phone":"+1 314 965 3700",
    "sg:postcode":"63122",
    "sg:province":"MO",
    "sg:tags":[
        "monastery",
        "order",
        "convent"
    ],
    "sg:website":"www.franciscansisters-olph.org",
    "wof:name":"Franciscan Sisters",
    "wof:placetype":"venue"
},
  "geometry": {"coordinates":[-90.406458,38.576955],"type":"Point"}
}