{
  "type": "Feature",
  "properties": {
    "iso:country":"US",
    "sg:address":"4003 E 137th Ter",
    "sg:city":"Grandview",
    "sg:classifiers":[
        {
            "category":"Manufacturing",
            "subcategory":"Rubber & Plastics",
            "type":"Manufacturing & Wholesale Goods"
        }
    ],
    "sg:phone":"+1 816 761 8484",
    "sg:postcode":"64030",
    "sg:province":"MO",
    "sg:tags":[
        "a",
        "product",
        "mfg"
    ],
    "sg:website":"www.levicplastics.com",
    "wof:name":"Levic Plastics Inc",
    "wof:placetype":"venue"
},
  "geometry": {"coordinates":[-94.546733,38.876447],"type":"Point"}
}