{
  "type": "Feature",
  "properties": {
    "iso:country":"US",
    "sg:address":"3651 Telegraph Rd",
    "sg:city":"Arnold",
    "sg:classifiers":[
        {
            "category":"Organizations",
            "subcategory":"Religious Organization",
            "type":"Services"
        }
    ],
    "sg:phone":"+1 636 464 2808",
    "sg:postcode":"63010",
    "sg:province":"MO",
    "sg:tags":[
        "church"
    ],
    "wof:name":"Arnold Church of Nazarene",
    "wof:placetype":"venue"
},
  "geometry": {"coordinates":[-90.372922,38.407073],"type":"Point"}
}