{
  "type": "Feature",
  "properties": {
    "iso:country":"US",
    "sg:address":"521 Park Dr",
    "sg:city":"Ironton",
    "sg:classifiers":[
        {
            "category":"Place Of Worship",
            "subcategory":"Church",
            "type":"Public Place"
        },
        {
            "category":"Place Of Worship",
            "type":"Public Place"
        }
    ],
    "sg:phone":"+1 573 546 7985",
    "sg:postcode":"63650",
    "sg:province":"MO",
    "sg:tags":[
        "churches-methodist"
    ],
    "wof:name":"Arcadia Valley Untd Methdst Ch",
    "wof:placetype":"venue"
},
  "geometry": {"coordinates":[-90.632628,37.594389],"type":"Point"}
}