{
  "type": "Feature",
  "properties": {
    "iso:country":"US",
    "sg:address":"310 E Washington Blvd",
    "sg:city":"Cuba",
    "sg:classifiers":[
        {
            "category":"Shopping",
            "subcategory":"Florist",
            "type":"Retail Goods"
        }
    ],
    "sg:phone":"+1 573 885 6370",
    "sg:postcode":"65453",
    "sg:province":"MO",
    "wof:name":"Wildflower",
    "wof:placetype":"venue"
},
  "geometry": {"coordinates":[-91.400603,38.063439],"type":"Point"}
}