{
  "type": "Feature",
  "properties": {
    "iso:country":"US",
    "sg:address":"888 Diehnwells Dr",
    "sg:city":"Saint Louis",
    "sg:classifiers":[
        {
            "category":"Wholesale",
            "subcategory":"Electrical",
            "type":"Manufacturing & Wholesale Goods"
        }
    ],
    "sg:phone":"+1 314 968 3456",
    "sg:postcode":"63119",
    "sg:province":"MO",
    "sg:tags":[
        "equipment",
        "electric",
        "supply"
    ],
    "wof:name":"T 2 Technologies",
    "wof:placetype":"venue"
},
  "geometry": {"coordinates":[-90.338707,38.574762],"type":"Point"}
}