{
  "type": "Feature",
  "properties": {
    "iso:country":"US",
    "sg:address":"802 1st St",
    "sg:city":"Kennett",
    "sg:classifiers":[
        {
            "category":"Manufacturing",
            "subcategory":"Rubber & Plastics",
            "type":"Manufacturing & Wholesale Goods"
        }
    ],
    "sg:phone":"+1 573 888 4938",
    "sg:postcode":"63857",
    "sg:province":"MO",
    "sg:tags":[
        "automotive",
        "tube",
        "mfg",
        "supply"
    ],
    "wof:name":"Linnorab",
    "wof:placetype":"venue"
},
  "geometry": {"coordinates":[-90.04904399999999,36.236643],"type":"Point"}
}