{
  "type": "Feature",
  "properties": {
    "iso:country":"US",
    "sg:address":"6091 State Hwy 168",
    "sg:city":"Palmyra",
    "sg:classifiers":[
        {
            "category":"Building & Trades",
            "subcategory":"Plumbing",
            "type":"Services"
        }
    ],
    "sg:phone":"+1 573 221 2250",
    "sg:postcode":"63461",
    "sg:province":"MO",
    "sg:tags":[
        "conditioning",
        "air",
        "system",
        "contractor"
    ],
    "wof:name":"Hannibal Heating & Air Cond",
    "wof:placetype":"venue"
},
  "geometry": {"coordinates":[-91.561633,39.805219],"type":"Point"}
}