{
  "type": "Feature",
  "properties": {
    "iso:country":"US",
    "sg:address":"209 W Promenade St",
    "sg:city":"Mexico",
    "sg:classifiers":[
        {
            "category":"Building & Trades",
            "subcategory":"Pest Control",
            "type":"Services"
        }
    ],
    "sg:phone":"+1 573 581 6002",
    "sg:postcode":"65265",
    "sg:province":"MO",
    "wof:name":"Bug Out Pest Control",
    "wof:placetype":"venue"
},
  "geometry": {"coordinates":[-91.884685,39.171421],"type":"Point"}
}