{
  "type": "Feature",
  "properties": {
    "iso:country":"US",
    "sg:address":"501 Manor Dr",
    "sg:city":"Columbia",
    "sg:classifiers":[
        {
            "category":"Building & Trades",
            "subcategory":"Construction",
            "type":"Services"
        }
    ],
    "sg:phone":"+1 573 489 1296",
    "sg:postcode":"65203",
    "sg:province":"MO",
    "sg:tags":[
        "industrial",
        "contractors-commercial",
        "contractor"
    ],
    "wof:name":"Midway Expo",
    "wof:placetype":"venue"
},
  "geometry": {"coordinates":[-92.362905,38.948316],"type":"Point"}
}