{
  "type": "Feature",
  "properties": {
    "iso:country":"US",
    "sg:address":"878 US Hwy 60",
    "sg:city":"Monett",
    "sg:classifiers":[
        {
            "category":"Building & Trades",
            "subcategory":"Construction",
            "type":"Services"
        }
    ],
    "sg:phone":"+1 417 235 2223",
    "sg:postcode":"65708",
    "sg:province":"MO",
    "sg:tags":[
        "dock"
    ],
    "sg:website":"www.ez-dock.com",
    "wof:name":"E Z Dock",
    "wof:placetype":"venue"
},
  "geometry": {"coordinates":[-93.94717300000001,36.915771],"type":"Point"}
}