{
  "type": "Feature",
  "properties": {
    "iso:country":"US",
    "sg:address":"808 S Illinois Ave",
    "sg:city":"Republic",
    "sg:classifiers":[
        {
            "category":"Restaurant",
            "type":"Food & Drink"
        }
    ],
    "sg:menulink":"http://www.allmenus.com/mo/west-republic/190920-burger-king/menu/",
    "sg:phone":"+1 417 732 4922",
    "sg:postcode":"65738",
    "sg:province":"MO",
    "sg:tags":[
        "burger",
        "american"
    ],
    "wof:name":"Burger King",
    "wof:placetype":"venue"
},
  "geometry": {"coordinates":[-93.49252,37.106984],"type":"Point"}
}