{
  "type": "Feature",
  "properties": {
    "iso:country":"US",
    "sg:address":"1800 N Main St",
    "sg:city":"De Soto",
    "sg:classifiers":[
        {
            "category":"Home & Garden",
            "subcategory":"Garden Supply",
            "type":"Retail Goods"
        }
    ],
    "sg:phone":"+1 636 586 2980",
    "sg:postcode":"63020",
    "sg:province":"MO",
    "sg:tags":[
        "engine",
        "repair",
        "lawn",
        "automotive",
        "small",
        "tractor"
    ],
    "wof:name":"Mueller Motors",
    "wof:placetype":"venue"
},
  "geometry": {"coordinates":[-90.54965900000001,38.155002],"type":"Point"}
}