{
  "type": "Feature",
  "properties": {
    "iso:country":"US",
    "sg:address":"4771 N Farm Road 189",
    "sg:city":"Springfield",
    "sg:classifiers":[
        {
            "category":"Autos & Motor Vehicles",
            "subcategory":"Auto Supplies",
            "type":"Retail Goods"
        }
    ],
    "sg:phone":"+1 417 869 2888",
    "sg:postcode":"65803",
    "sg:province":"MO",
    "sg:tags":[
        "tire"
    ],
    "wof:name":"Eaton Quality Retreads",
    "wof:placetype":"venue"
},
  "geometry": {"coordinates":[-93.20469300000001,37.280911],"type":"Point"}
}