{
  "type": "Feature",
  "properties": {
    "iso:country":"US",
    "sg:address":"204 Oak St",
    "sg:city":"Washington",
    "sg:classifiers":[
        {
            "category":"Real Estate",
            "subcategory":"Surveying",
            "type":"Services"
        }
    ],
    "sg:phone":"+1 636 239 1247",
    "sg:postcode":"63090",
    "sg:province":"MO",
    "sg:tags":[
        "surveyor",
        "land",
        "engineer"
    ],
    "wof:name":"Muser & Associates Land Surveying",
    "wof:placetype":"venue"
},
  "geometry": {"coordinates":[-91.013025,38.559609],"type":"Point"}
}