{
  "type": "Feature",
  "properties": {
    "iso:country":"US",
    "sg:address":"11600 Blue Ridge Blvd",
    "sg:city":"Kansas City",
    "sg:classifiers":[
        {
            "category":"Organizations",
            "subcategory":"Community Association",
            "type":"Services"
        }
    ],
    "sg:phone":"+1 816 965 0598",
    "sg:postcode":"64134",
    "sg:province":"MO",
    "sg:tags":[
        "military"
    ],
    "wof:name":"American Legion 598",
    "wof:placetype":"venue"
},
  "geometry": {"coordinates":[-94.51732800000001,38.912846],"type":"Point"}
}