{
  "type": "Feature",
  "properties": {
    "iso:country":"US",
    "sg:address":"2027 S Elliott Ave",
    "sg:city":"Aurora",
    "sg:classifiers":[
        {
            "category":"Restaurant",
            "type":"Food & Drink"
        }
    ],
    "sg:phone":"+1 417 678 1104",
    "sg:postcode":"65605",
    "sg:province":"MO",
    "wof:name":"Azteca Restaurant",
    "wof:placetype":"venue"
},
  "geometry": {"coordinates":[-93.718552,36.950908],"type":"Point"}
}