{
  "type": "Feature",
  "properties": {
    "iso:country":"US",
    "sg:address":"429 E Hauser St",
    "sg:city":"Marceline",
    "sg:classifiers":[
        {
            "category":"Retail",
            "subcategory":"Veterinary Services",
            "type":"Services"
        }
    ],
    "sg:phone":"+1 660 376 3373",
    "sg:postcode":"64658",
    "sg:province":"MO",
    "sg:tags":[
        "veterinarian",
        "specialty"
    ],
    "wof:name":"Joyce Deweese Dvm",
    "wof:placetype":"venue"
},
  "geometry": {"coordinates":[-92.94073299999999,39.717876],"type":"Point"}
}