{
  "type": "Feature",
  "properties": {
    "iso:country":"US",
    "sg:address":"256 Irish Hills Dr",
    "sg:city":"Camdenton",
    "sg:classifiers":[
        {
            "category":"Travel",
            "subcategory":"Hotels & Motels",
            "type":"Entertainment"
        },
        {
            "category":"Travel",
            "subcategory":"Resort",
            "type":"Entertainment"
        }
    ],
    "sg:phone":"+1 573 873 5375",
    "sg:postcode":"65020",
    "sg:province":"MO",
    "wof:name":"Irish Hills Lakeside Resort",
    "wof:placetype":"venue"
},
  "geometry": {"coordinates":[-92.812176,38.057697],"type":"Point"}
}