{
  "type": "Feature",
  "properties": {
    "iso:country":"US",
    "sg:address":"100 SW State Hwy 131",
    "sg:city":"Holden",
    "sg:classifiers":[
        {
            "category":"Professional",
            "type":"Services"
        }
    ],
    "sg:phone":"+1 816 732 0142",
    "sg:postcode":"64040",
    "sg:province":"MO",
    "sg:tags":[
        "establishment"
    ],
    "wof:name":"Swpc",
    "wof:placetype":"venue"
},
  "geometry": {"coordinates":[-93.99121,38.758579],"type":"Point"}
}