{
  "type": "Feature",
  "properties": {
    "iso:country":"US",
    "sg:address":"926 Imperial Pt",
    "sg:city":"Ballwin",
    "sg:classifiers":[
        {
            "category":"Travel",
            "subcategory":"Hotels & Motels",
            "type":"Entertainment"
        }
    ],
    "sg:phone":"+1 636 225 7204",
    "sg:postcode":"63021",
    "sg:province":"MO",
    "sg:tags":[
        "resort"
    ],
    "wof:name":"Hilton Cancun Beach & Gulf",
    "wof:placetype":"venue"
},
  "geometry": {"coordinates":[-90.486985,38.570509],"type":"Point"}
}