{
  "type": "Feature",
  "properties": {
    "iso:country":"US",
    "sg:address":"310 S Ohio Ave",
    "sg:city":"Sedalia",
    "sg:classifiers":[
        {
            "category":"Shopping",
            "subcategory":"Computers & Home Electronics",
            "type":"Retail Goods"
        }
    ],
    "sg:phone":"+1 660 826 1203",
    "sg:postcode":"65301",
    "sg:province":"MO",
    "sg:tags":[
        "equipment",
        "satellite",
        "system"
    ],
    "wof:name":"Y Not Electronics",
    "wof:placetype":"venue"
},
  "geometry": {"coordinates":[-93.228236,38.708555],"type":"Point"}
}