{
  "type": "Feature",
  "properties": {
    "iso:country":"US",
    "sg:address":"518 N Jefferson Ave",
    "sg:city":"Springfield",
    "sg:classifiers":[
        {
            "category":"Wholesale",
            "subcategory":"Machinery & Supplies",
            "type":"Manufacturing & Wholesale Goods"
        }
    ],
    "sg:phone":"+1 417 864 8584",
    "sg:postcode":"65806",
    "sg:province":"MO",
    "sg:tags":[
        "equipment",
        "mining",
        "industrial",
        "quarry"
    ],
    "wof:name":"Horton Supply Co Inc",
    "wof:placetype":"venue"
},
  "geometry": {"coordinates":[-93.289582,37.212241],"type":"Point"}
}