{
  "type": "Feature",
  "properties": {
    "addr:full":"201 Wolfe Dr Duenweg MO 64841",
    "addr:housenumber":"201",
    "addr:postcode":"64841",
    "addr:street":"Wolfe Dr",
    "iso:country":"US",
    "sg:address":"201 Wolfe Dr",
    "sg:city":"Duenweg",
    "sg:classifiers":[
        {
            "category":"Government",
            "subcategory":"Post Office",
            "type":"Public Place"
        }
    ],
    "sg:phone":"+1 417 782 1463",
    "sg:postcode":"64841",
    "sg:province":"MO",
    "sg:tags":[
        "postal",
        "us"
    ],
    "wof:name":"US Post Office",
    "wof:placetype":"venue"
},
  "geometry": {"coordinates":[-94.409448,37.081677],"type":"Point"}
}