{
  "type": "Feature",
  "properties": {
    "iso:country":"US",
    "sg:address":"25 SW 3 St",
    "sg:city":"Lees Summit",
    "sg:classifiers":[
        {
            "category":"Personal",
            "subcategory":"Barber",
            "type":"Services"
        }
    ],
    "sg:phone":"+1 816 524 4246",
    "sg:postcode":"64063",
    "sg:province":"MO",
    "sg:tags":[
        "shop"
    ],
    "wof:name":"Gene's Barber Shop",
    "wof:placetype":"venue"
},
  "geometry": {"coordinates":[-94.37813300000001,38.911707],"type":"Point"}
}