{
  "type": "Feature",
  "properties": {
    "iso:country":"US",
    "sg:address":"3801 Jennings Station Rd",
    "sg:city":"Saint Louis",
    "sg:classifiers":[
        {
            "category":"Education",
            "subcategory":"School",
            "type":"Public Place"
        }
    ],
    "sg:phone":"+1 314 383 3022",
    "sg:postcode":"63121",
    "sg:province":"MO",
    "wof:name":"Normandy School District",
    "wof:placetype":"venue"
},
  "geometry": {"coordinates":[-90.27668199999999,38.692401],"type":"Point"}
}