{
  "type": "Feature",
  "properties": {
    "iso:country":"US",
    "sg:address":"303 Gill Ave",
    "sg:city":"Saint Louis",
    "sg:classifiers":[
        {
            "category":"Professional",
            "type":"Services"
        }
    ],
    "sg:phone":"+1 314 835 9038",
    "sg:postcode":"63122",
    "sg:province":"MO",
    "wof:name":"Elwes Mar MO Land & Cattl",
    "wof:placetype":"venue"
},
  "geometry": {"coordinates":[-90.401099,38.585206],"type":"Point"}
}