{
  "type": "Feature",
  "properties": {
    "iso:country":"US",
    "sg:address":"14321 Manchester Rd",
    "sg:city":"Ballwin",
    "sg:classifiers":[
        {
            "category":"Utilities",
            "subcategory":"Mobile Phone",
            "type":"Services"
        },
        {
            "category":"Utilities",
            "subcategory":"Telephone",
            "type":"Services"
        },
        {
            "category":"Manufacturing",
            "subcategory":"Electronics",
            "type":"Manufacturing & Wholesale Goods"
        }
    ],
    "sg:phone":"+1 636 227 8484",
    "sg:postcode":"63011",
    "sg:province":"MO",
    "sg:tags":[
        "equipment",
        "telecommunications-equipment",
        "system",
        "cellular",
        "supply"
    ],
    "sg:website":"http://www.customstl.com",
    "wof:name":"Custom Cellular, Inc.",
    "wof:placetype":"venue"
},
  "geometry": {"coordinates":[-90.513199,38.59293],"type":"Point"}
}