{
  "type": "Feature",
  "properties": {
    "iso:country":"US",
    "sg:address":"23 Locust St",
    "sg:city":"Chillicothe",
    "sg:classifiers":[
        {
            "category":"Wholesale",
            "subcategory":"Groceries",
            "type":"Manufacturing & Wholesale Goods"
        }
    ],
    "sg:phone":"+1 660 646 0466",
    "sg:postcode":"64601",
    "sg:province":"MO",
    "wof:name":"Old Home Bakery",
    "wof:placetype":"venue"
},
  "geometry": {"coordinates":[-93.552127,39.78789],"type":"Point"}
}