{
  "type": "Feature",
  "properties": {
    "iso:country":"US",
    "sg:address":"609 State Hwy 291",
    "sg:city":"Lees Summit",
    "sg:classifiers":[
        {
            "category":"Health Services",
            "subcategory":"Doctor",
            "type":"Services"
        }
    ],
    "sg:phone":"+1 816 525 7100",
    "sg:postcode":"64086",
    "sg:province":"MO",
    "sg:tags":[
        "dentist"
    ],
    "wof:name":"Sue E Higgins DDS",
    "wof:placetype":"venue"
},
  "geometry": {"coordinates":[-94.36095400000001,38.922907],"type":"Point"}
}