{
  "type": "Feature",
  "properties": {
    "iso:country":"US",
    "sg:address":"6710 W Florissant Ave",
    "sg:city":"Saint Louis",
    "sg:classifiers":[
        {
            "category":"Restaurant",
            "type":"Food & Drink"
        }
    ],
    "sg:phone":"+1 314 389 8863",
    "sg:postcode":"63136",
    "sg:province":"MO",
    "sg:website":"www.rallyburger.com",
    "wof:name":"Rally's Drive Thru",
    "wof:placetype":"venue"
},
  "geometry": {"coordinates":[-90.258698,38.7159],"type":"Point"}
}