{
  "type": "Feature",
  "properties": {
    "iso:country":"US",
    "sg:address":"19993 State Hwy U",
    "sg:city":"Higginsville",
    "sg:phone":"+1 660 584 2523",
    "sg:postcode":"64037",
    "sg:province":"MO",
    "sg:tags":[
        "farm",
        "corn",
        "soybean",
        "crop",
        "general"
    ],
    "wof:name":"Melvin Oetting",
    "wof:placetype":"venue"
},
  "geometry": {"coordinates":[-93.73759200000001,38.949516],"type":"Point"}
}