{
  "type": "Feature",
  "properties": {
    "iso:country":"US",
    "sg:address":"12043 State Hwy 77",
    "sg:city":"Chaffee",
    "sg:classifiers":[
        {
            "category":"Retail",
            "subcategory":"Auto Repair",
            "type":"Services"
        }
    ],
    "sg:phone":"+1 573 887 6282",
    "sg:postcode":"63740",
    "sg:province":"MO",
    "sg:tags":[
        "body",
        "automobile",
        "painting"
    ],
    "wof:name":"Beck's Body Shop",
    "wof:placetype":"venue"
},
  "geometry": {"coordinates":[-89.66727299999999,37.169257],"type":"Point"}
}