{
  "type": "Feature",
  "properties": {
    "iso:country":"US",
    "sg:address":"830 Alexandra Ave",
    "sg:city":"Saint Louis",
    "sg:classifiers":[
        {
            "category":"Professional",
            "type":"Services"
        }
    ],
    "sg:phone":"+1 314 965 2174",
    "sg:postcode":"63122",
    "sg:province":"MO",
    "wof:name":"Larry Barker Music Inc",
    "wof:placetype":"venue"
},
  "geometry": {"coordinates":[-90.387376,38.596231],"type":"Point"}
}