{
  "type": "Feature",
  "properties": {
    "iso:country":"US",
    "sg:address":"1 Barton St",
    "sg:city":"St Louis",
    "sg:classifiers":[
        {
            "category":"Manufacturing",
            "subcategory":"Metals",
            "type":"Manufacturing & Wholesale Goods"
        },
        {
            "category":"Building & Trades",
            "subcategory":"Construction",
            "type":"Services"
        }
    ],
    "sg:phone":"+1 314 771 2828",
    "sg:postcode":"63104",
    "sg:province":"MO",
    "sg:tags":[
        "plate",
        "mfg",
        "fabricated",
        "s",
        "architectural",
        "fabricator"
    ],
    "wof:name":"Tishler Industries Inc",
    "wof:placetype":"venue"
},
  "geometry": {"coordinates":[-90.19735799999999,38.600065],"type":"Point"}
}