{
  "type": "Feature",
  "properties": {
    "iso:country":"US",
    "sg:address":"12366 Olive Blvd",
    "sg:city":"Creve Coeur",
    "sg:classifiers":[
        {
            "category":"Wholesale",
            "subcategory":"Medical Equipment & Supplies",
            "type":"Manufacturing & Wholesale Goods"
        }
    ],
    "sg:phone":"+1 314 205 8086",
    "sg:postcode":"63141",
    "sg:province":"MO",
    "sg:tags":[
        "physician",
        "surgeon"
    ],
    "wof:name":"Gateway Diabetes Ctr",
    "wof:placetype":"venue"
},
  "geometry": {"coordinates":[-90.456311,38.673317],"type":"Point"}
}