{
  "type": "Feature",
  "properties": {
    "iso:country":"US",
    "sg:address":"355 E Cherry St",
    "sg:city":"Troy",
    "sg:classifiers":[
        {
            "category":"Communications",
            "subcategory":"Radio Station",
            "type":"Services"
        }
    ],
    "sg:phone":"+1 636 528 5300",
    "sg:postcode":"63379",
    "sg:province":"MO",
    "sg:tags":[
        "company",
        "broadcasting"
    ],
    "wof:name":"KZMM",
    "wof:placetype":"venue"
},
  "geometry": {"coordinates":[-90.97856,38.980412],"type":"Point"}
}