{
  "type": "Feature",
  "properties": {
    "iso:country":"US",
    "sg:address":"808 W Highway 32",
    "sg:city":"Stockton",
    "sg:classifiers":[
        {
            "category":"Organizations",
            "subcategory":"Membership Organization",
            "type":"Services"
        }
    ],
    "sg:phone":"+1 417 276 3249",
    "sg:postcode":"65785",
    "sg:province":"MO",
    "sg:tags":[
        "military",
        "veteran"
    ],
    "wof:name":"Stockton V F W Post 5525",
    "wof:placetype":"venue"
},
  "geometry": {"coordinates":[-93.808713,37.701564],"type":"Point"}
}