{
  "type": "Feature",
  "properties": {
    "iso:country":"US",
    "sg:address":"2 Claas Crossing Dr",
    "sg:city":"Tipton",
    "sg:classifiers":[
        {
            "category":"Building & Trades",
            "subcategory":"Construction",
            "type":"Services"
        }
    ],
    "sg:phone":"+1 660 433 5747",
    "sg:postcode":"65237",
    "sg:province":"MO",
    "sg:tags":[
        "utility",
        "contractor"
    ],
    "wof:name":"Vanwestton Groundworks Constr",
    "wof:placetype":"venue"
},
  "geometry": {"coordinates":[-92.82068099999999,38.698903],"type":"Point"}
}