{
  "type": "Feature",
  "properties": {
    "iso:country":"US",
    "sg:address":"27821 State Hwy 7",
    "sg:city":"Harrisonville",
    "sg:classifiers":[
        {
            "category":"Building & Trades",
            "subcategory":"Construction",
            "type":"Services"
        }
    ],
    "sg:phone":"+1 816 380 3721",
    "sg:postcode":"64701",
    "sg:province":"MO",
    "sg:tags":[
        "road",
        "contractor"
    ],
    "sg:website":"www.modot.mo.gov",
    "wof:name":"Highway Dept",
    "wof:placetype":"venue"
},
  "geometry": {"coordinates":[-94.30227499999999,38.609041],"type":"Point"}
}