{
  "type": "Feature",
  "properties": {
    "iso:country":"US",
    "sg:address":"6251 N Belton Ct",
    "sg:city":"Kansas City",
    "sg:classifiers":[
        {
            "category":"Professional",
            "subcategory":"Advertising",
            "type":"Services"
        }
    ],
    "sg:phone":"+1 816 587 8812",
    "sg:postcode":"64151",
    "sg:province":"MO",
    "sg:tags":[
        "agency"
    ],
    "wof:name":"Creative Minds",
    "wof:placetype":"venue"
},
  "geometry": {"coordinates":[-94.61993,39.208233],"type":"Point"}
}