{
  "type": "Feature",
  "properties": {
    "iso:country":"US",
    "sg:address":"5001 S Providence Rd",
    "sg:city":"Columbia",
    "sg:classifiers":[
        {
            "category":"Real Estate",
            "subcategory":"Real Estate Operator",
            "type":"Services"
        }
    ],
    "sg:phone":"+1 573 443 7221",
    "sg:postcode":"65203",
    "sg:province":"MO",
    "sg:tags":[
        "apartment"
    ],
    "sg:website":"http://www.dbcrentals.com",
    "wof:name":"DBC Rentals",
    "wof:placetype":"venue"
},
  "geometry": {"coordinates":[-92.335762,38.895222],"type":"Point"}
}