{
  "type": "Feature",
  "properties": {
    "iso:country":"US",
    "sg:address":"444 N Scott Ave",
    "sg:city":"Belton",
    "sg:classifiers":[
        {
            "category":"Restaurant",
            "type":"Food & Drink"
        }
    ],
    "sg:phone":"+1 816 322 1847",
    "sg:postcode":"64012",
    "sg:province":"MO",
    "sg:tags":[
        "house",
        "steak"
    ],
    "wof:name":"Mi Pueblito",
    "wof:placetype":"venue"
},
  "geometry": {"coordinates":[-94.534367,38.821272],"type":"Point"}
}