{
  "type": "Feature",
  "properties": {
    "iso:country":"US",
    "sg:address":"3102 Patterson Rd",
    "sg:city":"Owensville",
    "sg:classifiers":[
        {
            "category":"Shopping",
            "subcategory":"Beauty & Cosmetics",
            "type":"Retail Goods"
        }
    ],
    "sg:phone":"+1 573 437 4435",
    "sg:postcode":"65066",
    "sg:province":"MO",
    "sg:tags":[
        "perfume",
        "salons-equipment",
        "supply"
    ],
    "wof:name":"Betty Niederer",
    "wof:placetype":"venue"
},
  "geometry": {"coordinates":[-91.553072,38.392767],"type":"Point"}
}