{
  "type": "Feature",
  "properties": {
    "iso:country":"US",
    "sg:address":"114 Chapel Dr",
    "sg:city":"Monett",
    "sg:phone":"+1 417 235 3350",
    "sg:postcode":"65708",
    "sg:province":"MO",
    "wof:name":"Grant's Restaurant",
    "wof:placetype":"venue"
},
  "geometry": {"coordinates":[-93.900717,36.914263],"type":"Point"}
}