{
  "type": "Feature",
  "properties": {
    "iso:country":"US",
    "sg:address":"3775 Kossuth Ave",
    "sg:city":"Saint Louis",
    "sg:classifiers":[
        {
            "category":"Retail",
            "subcategory":"Car Wash",
            "type":"Services"
        }
    ],
    "sg:phone":"+1 314 517 3365",
    "sg:postcode":"63107",
    "sg:province":"MO",
    "sg:tags":[
        "carwash"
    ],
    "wof:name":"2n2 Fox Inc",
    "wof:placetype":"venue"
},
  "geometry": {"coordinates":[-90.217693,38.666324],"type":"Point"}
}