{
  "type": "Feature",
  "properties": {
    "iso:country":"US",
    "sg:address":"3405 Bent Ave",
    "sg:city":"Saint Louis",
    "sg:classifiers":[
        {
            "category":"Building & Trades",
            "subcategory":"Electrical",
            "type":"Services"
        }
    ],
    "sg:phone":"+1 314 772 5400",
    "sg:postcode":"63116",
    "sg:province":"MO",
    "sg:tags":[
        "electrician",
        "contractor"
    ],
    "sg:website":"www.geco.com",
    "wof:name":"Guarantee Electrical Company",
    "wof:placetype":"venue"
},
  "geometry": {"coordinates":[-90.258904,38.596298],"type":"Point"}
}