{
  "type": "Feature",
  "properties": {
    "iso:country":"US",
    "sg:address":"27 S Madison St",
    "sg:city":"Webb City",
    "sg:classifiers":[
        {
            "category":"Manufacturing",
            "subcategory":"Metals",
            "type":"Manufacturing & Wholesale Goods"
        }
    ],
    "sg:phone":"+1 417 673 1239",
    "sg:postcode":"64870",
    "sg:province":"MO",
    "sg:tags":[
        "metalwork",
        "sheet",
        "mfg"
    ],
    "wof:name":"Eppright Custom Sheet Metal",
    "wof:placetype":"venue"
},
  "geometry": {"coordinates":[-94.474532,37.145451],"type":"Point"}
}