{
  "type": "Feature",
  "properties": {
    "iso:country":"US",
    "sg:address":"19700 N Mount Pleasant Rd",
    "sg:city":"Hartsburg",
    "sg:classifiers":[
        {
            "category":"Government",
            "subcategory":"Police Station",
            "type":"Public Place"
        }
    ],
    "sg:phone":"+1 573 636 8858",
    "sg:postcode":"65039",
    "sg:province":"MO",
    "sg:tags":[
        "sheriff"
    ],
    "wof:name":"Boone County Sheriffs Dept",
    "wof:placetype":"venue"
},
  "geometry": {"coordinates":[-92.25514099999999,38.710235],"type":"Point"}
}