{
  "type": "Feature",
  "properties": {
    "iso:country":"US",
    "sg:address":"1104 S Main St",
    "sg:city":"Piedmont",
    "sg:classifiers":[
        {
            "category":"Food & Beverages",
            "subcategory":"Groceries & Convenience Stores",
            "type":"Retail Goods"
        }
    ],
    "sg:phone":"+1 573 223 9305",
    "sg:postcode":"63957",
    "sg:province":"MO",
    "wof:name":"Caseys 2017",
    "wof:placetype":"venue"
},
  "geometry": {"coordinates":[-90.700468,37.144712],"type":"Point"}
}