{
  "type": "Feature",
  "properties": {
    "iso:country":"US",
    "sg:address":"1193 Madison 301",
    "sg:city":"Marquand",
    "sg:classifiers":[
        {
            "category":"Social Services",
            "subcategory":"Child Care",
            "type":"Services"
        }
    ],
    "sg:phone":"+1 573 783 6605",
    "sg:postcode":"63655",
    "sg:province":"MO",
    "sg:tags":[
        "nursery",
        "day"
    ],
    "wof:name":"Cub House Day Care",
    "wof:placetype":"venue"
},
  "geometry": {"coordinates":[-90.274453,37.362592],"type":"Point"}
}