{
  "type": "Feature",
  "properties": {
    "iso:country":"US",
    "sg:address":"1120 SE Broadway Dr",
    "sg:city":"Lees Summit",
    "sg:classifiers":[
        {
            "category":"Home & Garden",
            "subcategory":"Carpets & Floor Coverings",
            "type":"Retail Goods"
        }
    ],
    "sg:phone":"+1 816 246 6568",
    "sg:postcode":"64081",
    "sg:province":"MO",
    "sg:tags":[
        "dealer",
        "rug"
    ],
    "wof:name":"Carpet Direct",
    "wof:placetype":"venue"
},
  "geometry": {"coordinates":[-94.35732299999999,38.898322],"type":"Point"}
}