{
  "type": "Feature",
  "properties": {
    "iso:country":"US",
    "sg:address":"2104 S Washington Ave",
    "sg:city":"Sedalia",
    "sg:classifiers":[
        {
            "category":"Travel",
            "subcategory":"Bed & Breakfast",
            "type":"Entertainment"
        }
    ],
    "sg:phone":"+1 660 826 3911",
    "sg:postcode":"65301",
    "sg:province":"MO",
    "sg:tags":[
        "house"
    ],
    "wof:name":"Elder Care",
    "wof:placetype":"venue"
},
  "geometry": {"coordinates":[-93.22537,38.692689],"type":"Point"}
}