{
  "type": "Feature",
  "properties": {
    "iso:country":"US",
    "sg:address":"590 SE 10th Ln",
    "sg:city":"Lamar",
    "sg:classifiers":[
        {
            "category":"Restaurant",
            "type":"Food & Drink"
        }
    ],
    "sg:phone":"+1 417 682 3007",
    "sg:postcode":"64759",
    "sg:province":"MO",
    "sg:tags":[
        "eating"
    ],
    "wof:name":"Whippoorwill Cafe",
    "wof:placetype":"venue"
},
  "geometry": {"coordinates":[-94.28160699999999,37.413799],"type":"Point"}
}