{
  "type": "Feature",
  "properties": {
    "iso:country":"US",
    "sg:address":"623 S Pickwick Ave",
    "sg:city":"Springfield",
    "sg:classifiers":[
        {
            "category":"Organizations",
            "subcategory":"Religious Organization",
            "type":"Services"
        }
    ],
    "sg:phone":"+1 417 869 6858",
    "sg:postcode":"65802",
    "sg:province":"MO",
    "sg:tags":[
        "church"
    ],
    "wof:name":"Campbell United Methodist Ch",
    "wof:placetype":"venue"
},
  "geometry": {"coordinates":[-93.269768,37.202319],"type":"Point"}
}