{
  "type": "Feature",
  "properties": {
    "iso:country":"US",
    "sg:address":"210 Ste Genevieve Dr",
    "sg:city":"Ste Genevieve",
    "sg:classifiers":[
        {
            "category":"Autos & Motor Vehicles",
            "subcategory":"Auto Supplies",
            "type":"Retail Goods"
        }
    ],
    "sg:phone":"+1 573 883 8833",
    "sg:postcode":"63670",
    "sg:province":"MO",
    "sg:tags":[
        "tire"
    ],
    "wof:name":"Plaza Tire Svc",
    "wof:placetype":"venue"
},
  "geometry": {"coordinates":[-90.040485,37.967464],"type":"Point"}
}