{
  "type": "Feature",
  "properties": {
    "iso:country":"US",
    "sg:address":"15 Goodwin Dr",
    "sg:city":"Festus",
    "sg:classifiers":[
        {
            "category":"Building & Trades",
            "subcategory":"Construction",
            "type":"Services"
        }
    ],
    "sg:phone":"+1 636 937 1268",
    "sg:postcode":"63028",
    "sg:province":"MO",
    "sg:tags":[
        "excavating",
        "contractor"
    ],
    "wof:name":"R & K Excavation",
    "wof:placetype":"venue"
},
  "geometry": {"coordinates":[-90.39099,38.199913],"type":"Point"}
}