{
  "type": "Feature",
  "properties": {
    "iso:country":"US",
    "sg:address":"19903 Bobcat Rd",
    "sg:city":"Burlington Junction",
    "sg:classifiers":[
        {
            "category":"Insurance",
            "subcategory":"Insurance Agent",
            "type":"Services"
        }
    ],
    "sg:phone":"+1 660 725 4436",
    "sg:postcode":"64428",
    "sg:province":"MO",
    "wof:name":"Nicholas Terry",
    "wof:placetype":"venue"
},
  "geometry": {"coordinates":[-95.12496299999999,40.441858],"type":"Point"}
}