{
  "type": "Feature",
  "properties": {
    "iso:country":"US",
    "sg:address":"4675 S Grand Blvd",
    "sg:city":"Saint Louis",
    "sg:classifiers":[
        {
            "category":"Health Services",
            "subcategory":"Doctor",
            "type":"Services"
        }
    ],
    "sg:phone":"+1 314 752 8600",
    "sg:postcode":"63111",
    "sg:province":"MO",
    "wof:name":"Geromed Llc",
    "wof:placetype":"venue"
},
  "geometry": {"coordinates":[-90.249027,38.575146],"type":"Point"}
}