{
  "type": "Feature",
  "properties": {
    "iso:country":"US",
    "sg:address":"11422 Gravois Rd",
    "sg:city":"Sappington",
    "sg:classifiers":[
        {
            "category":"Professional",
            "subcategory":"Accounting & Tax Preparation",
            "type":"Services"
        }
    ],
    "sg:phone":"+1 314 843 5570",
    "sg:postcode":"63126",
    "sg:province":"MO",
    "sg:tags":[
        "accountant"
    ],
    "sg:website":"www.mjcpa-ebm.com",
    "wof:name":"Maloney & Jackson",
    "wof:placetype":"venue"
},
  "geometry": {"coordinates":[-90.376531,38.538013],"type":"Point"}
}