{
  "type": "Feature",
  "properties": {
    "iso:country":"US",
    "sg:address":"1013 Brooksgate Manor Dr",
    "sg:city":"Saint Louis",
    "sg:classifiers":[
        {
            "category":"Wholesale",
            "subcategory":"Furniture",
            "type":"Manufacturing & Wholesale Goods"
        }
    ],
    "sg:phone":"+1 314 965 9310",
    "sg:postcode":"63122",
    "sg:province":"MO",
    "sg:tags":[
        "mfr",
        "representative"
    ],
    "wof:name":"Contract Resources Inc",
    "wof:placetype":"venue"
},
  "geometry": {"coordinates":[-90.415592,38.566232],"type":"Point"}
}