{
  "type": "Feature",
  "properties": {
    "addr:full":"1810 Craig Rd Saint Louis MO 63146",
    "addr:housenumber":"1810",
    "addr:postcode":"63146",
    "addr:street":"Craig Rd",
    "iso:country":"US",
    "sg:address":"1810 Craig Rd",
    "sg:city":"Saint Louis",
    "sg:classifiers":[
        {
            "category":"Wholesale",
            "subcategory":"Medical Equipment & Supplies",
            "type":"Manufacturing & Wholesale Goods"
        }
    ],
    "sg:phone":"+1 314 439 0508",
    "sg:postcode":"63146",
    "sg:province":"MO",
    "wof:name":"Kinetic Concepts Inc",
    "wof:placetype":"venue"
},
  "geometry": {"coordinates":[-90.444417,38.692016],"type":"Point"}
}