{
  "type": "Feature",
  "properties": {
    "iso:country":"US",
    "sg:address":"2407 Green Mountain Dr",
    "sg:city":"Branson",
    "sg:classifiers":[
        {
            "category":"Bakery",
            "type":"Food & Drink"
        }
    ],
    "sg:menulink":"http://www.allmenus.com/mo/branson/54188-panera-bread/menu/",
    "sg:phone":"+1 417 336 4550",
    "sg:postcode":"65616",
    "sg:province":"MO",
    "sg:tags":[
        "american",
        "sandwich",
        "pastry"
    ],
    "wof:name":"Panera Bread",
    "wof:placetype":"venue"
},
  "geometry": {"coordinates":[-93.26246999999999,36.63917],"type":"Point"}
}