{
  "type": "Feature",
  "properties": {
    "iso:country":"US",
    "sg:address":"1005 E Dale St",
    "sg:city":"Springfield",
    "sg:classifiers":[
        {
            "category":"Organizations",
            "subcategory":"Religious Organization",
            "type":"Services"
        }
    ],
    "sg:phone":"+1 417 866 7638",
    "sg:postcode":"65803",
    "sg:province":"MO",
    "wof:name":"Bethel Assembly Of God Church",
    "wof:placetype":"venue"
},
  "geometry": {"coordinates":[-93.279287,37.235143],"type":"Point"}
}