{
  "type": "Feature",
  "properties": {
    "iso:country":"US",
    "sg:address":"10814 State Hwy 21",
    "sg:city":"Hillsboro",
    "sg:classifiers":[
        {
            "category":"Professional",
            "subcategory":"Research",
            "type":"Services"
        }
    ],
    "sg:phone":"+1 636 789 2330",
    "sg:postcode":"63050",
    "sg:province":"MO",
    "sg:tags":[
        "development",
        "laboratory"
    ],
    "wof:name":"Research In Records",
    "wof:placetype":"venue"
},
  "geometry": {"coordinates":[-90.571164,38.224867],"type":"Point"}
}