{
  "type": "Feature",
  "properties": {
    "iso:country":"US",
    "sg:address":"11550 N Platte Purchase Dr",
    "sg:city":"Kansas City",
    "sg:classifiers":[
        {
            "category":"Building & Trades",
            "subcategory":"Plumbing",
            "type":"Services"
        }
    ],
    "sg:phone":"+1 816 734 9233",
    "sg:postcode":"64154",
    "sg:province":"MO",
    "sg:tags":[
        "contractor"
    ],
    "wof:name":"Numers Plumbing",
    "wof:placetype":"venue"
},
  "geometry": {"coordinates":[-94.600576,39.302634],"type":"Point"}
}