{
  "type": "Feature",
  "properties": {
    "iso:country":"US",
    "sg:address":"1231 Hodiamont Ave",
    "sg:city":"St Louis",
    "sg:classifiers":[
        {
            "category":"Manufacturing",
            "subcategory":"Textiles",
            "type":"Manufacturing & Wholesale Goods"
        }
    ],
    "sg:phone":"+1 314 725 1007",
    "sg:postcode":"63112",
    "sg:province":"MO",
    "sg:tags":[
        "knitting",
        "mills"
    ],
    "wof:name":"Sheona's Knit & Sew",
    "wof:placetype":"venue"
},
  "geometry": {"coordinates":[-90.29086,38.668413],"type":"Point"}
}