{
  "type": "Feature",
  "properties": {
    "iso:country":"US",
    "sg:address":"3242 Holmes St",
    "sg:city":"Kansas City",
    "sg:classifiers":[
        {
            "category":"Local Transit",
            "type":"Transportation"
        }
    ],
    "sg:phone":"+1 816 756 3100",
    "sg:postcode":"64109",
    "sg:province":"MO",
    "sg:tags":[
        "passenger"
    ],
    "wof:name":"Pech Limousine & Delivery Inc",
    "wof:placetype":"venue"
},
  "geometry": {"coordinates":[-94.576747,39.06872],"type":"Point"}
}