{
  "type": "Feature",
  "properties": {
    "iso:country":"US",
    "sg:address":"223 12th St W",
    "sg:city":"Lamar",
    "sg:classifiers":[
        {
            "category":"Retail",
            "subcategory":"Photofinishing",
            "type":"Services"
        }
    ],
    "sg:phone":"+1 417 681 0650",
    "sg:postcode":"64759",
    "sg:province":"MO",
    "sg:tags":[
        "laboratory"
    ],
    "wof:name":"I Photo",
    "wof:placetype":"venue"
},
  "geometry": {"coordinates":[-94.27891700000001,37.493299],"type":"Point"}
}