{
  "type": "Feature",
  "properties": {
    "iso:country":"US",
    "sg:address":"905 S Florissant Rd",
    "sg:city":"Saint Louis",
    "sg:classifiers":[
        {
            "category":"Real Estate",
            "subcategory":"Real Estate Operator",
            "type":"Services"
        }
    ],
    "sg:phone":"+1 314 522 9105",
    "sg:postcode":"63135",
    "sg:province":"MO",
    "sg:tags":[
        "management"
    ],
    "wof:name":"Wines Enterprises Inc",
    "wof:placetype":"venue"
},
  "geometry": {"coordinates":[-90.301815,38.732824],"type":"Point"}
}