{
  "type": "Feature",
  "properties": {
    "iso:country":"US",
    "sg:address":"3227 Olive St",
    "sg:city":"St Joseph",
    "sg:classifiers":[
        {
            "category":"Education",
            "subcategory":"School",
            "type":"Public Place"
        }
    ],
    "sg:phone":"+1 816 671 4400",
    "sg:postcode":"64507",
    "sg:province":"MO",
    "sg:tags":[
        "middle"
    ],
    "sg:website":"www.sjsd.k12.mo.us",
    "wof:name":"Harry S Truman Middle School",
    "wof:placetype":"venue"
},
  "geometry": {"coordinates":[-94.81472599999999,39.759003],"type":"Point"}
}