{
  "type": "Feature",
  "properties": {
    "iso:country":"US",
    "sg:address":"3100 Falling Leaf Ct",
    "sg:city":"Columbia",
    "sg:classifiers":[
        {
            "category":"Real Estate",
            "subcategory":"Real Estate Agent",
            "type":"Services"
        }
    ],
    "sg:phone":"+1 573 442 5510",
    "sg:postcode":"65201",
    "sg:province":"MO",
    "wof:name":"Jones Co Real Estate LLC",
    "wof:placetype":"venue"
},
  "geometry": {"coordinates":[-92.29525700000001,38.91587],"type":"Point"}
}