{
  "type": "Feature",
  "properties": {
    "iso:country":"US",
    "sg:address":"2725 Oakshire Cir",
    "sg:city":"Cape Girardeau",
    "sg:classifiers":[
        {
            "category":"Wholesale",
            "subcategory":"Chemicals & Plastics",
            "type":"Manufacturing & Wholesale Goods"
        }
    ],
    "sg:phone":"+1 573 204 1166",
    "sg:postcode":"63701",
    "sg:province":"MO",
    "wof:name":"Southeast Manufacturing",
    "wof:placetype":"venue"
},
  "geometry": {"coordinates":[-89.525764,37.356718],"type":"Point"}
}