{
  "type": "Feature",
  "properties": {
    "iso:country":"US",
    "sg:address":"703 Long Road Crossing Dr",
    "sg:city":"Chesterfield",
    "sg:classifiers":[
        {
            "category":"Food & Beverages",
            "subcategory":"Specialty",
            "type":"Retail Goods"
        },
        {
            "category":"Restaurant",
            "type":"Food & Drink"
        }
    ],
    "sg:phone":"+1 636 519 7775",
    "sg:postcode":"63005",
    "sg:province":"MO",
    "sg:tags":[
        "product",
        "health",
        "diet"
    ],
    "sg:website":"http://www.smoothieking.com",
    "wof:name":"Smoothie King",
    "wof:placetype":"venue"
},
  "geometry": {"coordinates":[-90.619589,38.668289],"type":"Point"}
}