{
  "type": "Feature",
  "properties": {
    "iso:country":"US",
    "sg:address":"640 W Independence St",
    "sg:city":"Jackson",
    "sg:classifiers":[
        {
            "category":"Cemetery",
            "type":"Public Place"
        },
        {
            "category":"Retail",
            "subcategory":"Funeral Services",
            "type":"Services"
        }
    ],
    "sg:phone":"+1 573 243 2424",
    "sg:postcode":"63755",
    "sg:province":"MO",
    "sg:tags":[
        "director",
        "embalmer",
        "crematory"
    ],
    "wof:name":"Mc Combs Funeral Home Inc",
    "wof:placetype":"venue"
},
  "geometry": {"coordinates":[-89.671345,37.393027],"type":"Point"}
}