{
  "type": "Feature",
  "properties": {
    "iso:country":"US",
    "sg:address":"7606 NE 75 Ter",
    "sg:city":"Kansas City",
    "sg:classifiers":[
        {
            "category":"Farming",
            "subcategory":"Farm",
            "type":"Manufacturing & Wholesale Goods"
        }
    ],
    "sg:phone":"+1 816 792 5239",
    "sg:postcode":"64158",
    "sg:province":"MO",
    "sg:tags":[
        "crop",
        "general"
    ],
    "wof:name":"Pletcher John",
    "wof:placetype":"venue"
},
  "geometry": {"coordinates":[-94.49093000000001,39.23038],"type":"Point"}
}