{
  "type": "Feature",
  "properties": {
    "iso:country":"US",
    "sg:address":"713 Washington St",
    "sg:city":"Jefferson City",
    "sg:classifiers":[
        {
            "category":"Health Services",
            "subcategory":"Hospital",
            "type":"Services"
        }
    ],
    "sg:phone":"+1 573 659 7304",
    "sg:postcode":"65101",
    "sg:province":"MO",
    "sg:tags":[
        "mental"
    ],
    "wof:name":"Central House",
    "wof:placetype":"venue"
},
  "geometry": {"coordinates":[-92.178488,38.573676],"type":"Point"}
}