{
  "type": "Feature",
  "properties": {
    "iso:country":"US",
    "sg:address":"3040 Brentmoor Dr",
    "sg:city":"St Charles",
    "sg:classifiers":[
        {
            "category":"Professional",
            "type":"Services"
        }
    ],
    "sg:phone":"+1 636 936 8195",
    "sg:postcode":"63303",
    "sg:province":"MO",
    "sg:tags":[
        "establishment"
    ],
    "wof:name":"Dallas & Dallas",
    "wof:placetype":"venue"
},
  "geometry": {"coordinates":[-90.563676,38.739767],"type":"Point"}
}