{
  "type": "Feature",
  "properties": {
    "iso:country":"US",
    "sg:address":"13925 US Hwy 136",
    "sg:city":"New Hampton",
    "sg:classifiers":[
        {
            "category":"Wholesale",
            "subcategory":"Hardware",
            "type":"Manufacturing & Wholesale Goods"
        }
    ],
    "sg:phone":"+1 660 439 2785",
    "sg:postcode":"64471",
    "sg:province":"MO",
    "sg:tags":[
        "tool"
    ],
    "sg:website":"www.buzzardgulch.com",
    "wof:name":"Buzzard Gulch Inc",
    "wof:placetype":"venue"
},
  "geometry": {"coordinates":[-94.16064799999999,40.254341],"type":"Point"}
}