{
  "type": "Feature",
  "properties": {
    "iso:country":"US",
    "sg:address":"108 N Hughes St",
    "sg:city":"Windsor",
    "sg:classifiers":[
        {
            "category":"Building & Trades",
            "subcategory":"Landscaping Services",
            "type":"Services"
        }
    ],
    "sg:phone":"+1 660 525 2646",
    "sg:postcode":"65360",
    "sg:province":"MO",
    "sg:tags":[
        "lawn",
        "maintenance"
    ],
    "wof:name":"James A Bunch",
    "wof:placetype":"venue"
},
  "geometry": {"coordinates":[-93.52037,38.530956],"type":"Point"}
}