{
  "type": "Feature",
  "properties": {
    "iso:country":"US",
    "sg:address":"1135 Lakeview Ave",
    "sg:city":"Saint Louis",
    "sg:classifiers":[
        {
            "category":"Retail",
            "subcategory":"Auto Repair",
            "type":"Services"
        }
    ],
    "sg:phone":"+1 314 422 1915",
    "sg:postcode":"63138",
    "sg:province":"MO",
    "sg:tags":[
        "transportation"
    ],
    "wof:name":"Er Service",
    "wof:placetype":"venue"
},
  "geometry": {"coordinates":[-90.20225499999999,38.787736],"type":"Point"}
}