{
  "type": "Feature",
  "properties": {
    "addr:full":"102 S Jackson St Farmington MO 63640",
    "addr:housenumber":"102",
    "addr:postcode":"63640",
    "addr:street":"S Jackson St",
    "iso:country":"US",
    "sg:address":"102 S Jackson St",
    "sg:city":"Farmington",
    "sg:classifiers":[
        {
            "category":"Shopping",
            "subcategory":"Hobbies, Toys, & Games",
            "type":"Retail Goods"
        }
    ],
    "sg:phone":"+1 573 756 8060",
    "sg:postcode":"63640",
    "sg:province":"MO",
    "sg:tags":[
        "craft",
        "supply"
    ],
    "wof:name":"Red Rooster",
    "wof:placetype":"venue"
},
  "geometry": {"coordinates":[-90.42001,37.779561],"type":"Point"}
}