{
  "type": "Feature",
  "properties": {
    "iso:country":"US",
    "sg:address":"2964 S National Ave",
    "sg:city":"Springfield",
    "sg:classifiers":[
        {
            "category":"Restaurant",
            "type":"Food & Drink"
        }
    ],
    "sg:phone":"+1 417 881 6098",
    "sg:postcode":"65804",
    "sg:province":"MO",
    "sg:website":"http://www.captainds.com",
    "wof:name":"Captain D's Seafood Kitchen",
    "wof:placetype":"venue"
},
  "geometry": {"coordinates":[-93.277151,37.160787],"type":"Point"}
}