{
  "type": "Feature",
  "properties": {
    "iso:country":"US",
    "sg:address":"216 2nd St",
    "sg:city":"Mountain View",
    "sg:classifiers":[
        {
            "category":"Health Services",
            "subcategory":"Doctor",
            "type":"Services"
        }
    ],
    "sg:phone":"+1 417 934 2624",
    "sg:postcode":"65548",
    "sg:province":"MO",
    "sg:tags":[
        "dentist"
    ],
    "wof:name":"Billy E Dunlap DDS",
    "wof:placetype":"venue"
},
  "geometry": {"coordinates":[-91.69956500000001,36.996765],"type":"Point"}
}