{
  "type": "Feature",
  "properties": {
    "iso:country":"US",
    "sg:address":"2601 W Broadway",
    "sg:city":"Columbia",
    "sg:classifiers":[
        {
            "category":"Organizations",
            "subcategory":"Religious Organization",
            "type":"Services"
        }
    ],
    "sg:phone":"+1 573 445 5312",
    "sg:postcode":"65203",
    "sg:province":"MO",
    "sg:tags":[
        "churches-reformed",
        "church"
    ],
    "sg:website":"www.broadwaychristian.net",
    "wof:name":"Broadway Christian Church",
    "wof:placetype":"venue"
},
  "geometry": {"coordinates":[-92.377197,38.954399],"type":"Point"}
}