{
  "type": "Feature",
  "properties": {
    "iso:country":"US",
    "sg:address":"5500 S Broadway",
    "sg:city":"St Louis",
    "sg:classifiers":[
        {
            "category":"Social Services",
            "subcategory":"Adult Care",
            "type":"Services"
        }
    ],
    "sg:phone":"+1 314 353 5900",
    "sg:postcode":"63111",
    "sg:province":"MO",
    "sg:tags":[
        "home",
        "residential"
    ],
    "wof:name":"Riverview",
    "wof:placetype":"venue"
},
  "geometry": {"coordinates":[-90.243127,38.560269],"type":"Point"}
}