{
  "type": "Feature",
  "properties": {
    "iso:country":"US",
    "sg:address":"14251 Pingleton Rd",
    "sg:city":"Centralia",
    "sg:phone":"+1 573 682 5367",
    "sg:postcode":"65240",
    "sg:province":"MO",
    "sg:tags":[
        "farm",
        "corn",
        "wheat",
        "soybean"
    ],
    "wof:name":"Riedel Farms",
    "wof:placetype":"venue"
},
  "geometry": {"coordinates":[-92.109292,39.126669],"type":"Point"}
}