{
  "type": "Feature",
  "properties": {
    "iso:country":"US",
    "sg:address":"8033 N Broadway",
    "sg:city":"St Louis",
    "sg:classifiers":[
        {
            "category":"Professional",
            "type":"Services"
        },
        {
            "category":"Building & Trades",
            "subcategory":"Equipment Rental",
            "type":"Services"
        }
    ],
    "sg:phone":"+1 314 383 9704",
    "sg:postcode":"63147",
    "sg:province":"MO",
    "sg:tags":[
        "heavy",
        "construction",
        "establishment"
    ],
    "wof:name":"Weavers & Cranes",
    "wof:placetype":"venue"
},
  "geometry": {"coordinates":[-90.23035,38.710371],"type":"Point"}
}