{
  "type": "Feature",
  "properties": {
    "iso:country":"US",
    "sg:address":"8251 Maryland Ave",
    "sg:city":"St Louis",
    "sg:classifiers":[
        {
            "category":"Professional",
            "subcategory":"Computer Services",
            "type":"Services"
        }
    ],
    "sg:phone":"+1 314 678 0800",
    "sg:postcode":"63105",
    "sg:province":"MO",
    "sg:tags":[
        "consultant",
        "designer"
    ],
    "wof:name":"Kiosite LLC",
    "wof:placetype":"venue"
},
  "geometry": {"coordinates":[-90.345568,38.652768],"type":"Point"}
}