{
  "type": "Feature",
  "properties": {
    "iso:country":"US",
    "sg:address":"2746 Askew Ave",
    "sg:city":"Kansas City",
    "sg:classifiers":[
        {
            "category":"Social Services",
            "subcategory":"Child Care",
            "type":"Services"
        }
    ],
    "sg:phone":"+1 816 921 0991",
    "sg:postcode":"64128",
    "sg:province":"MO",
    "sg:tags":[
        "day"
    ],
    "wof:name":"Collins Family Day Care Home",
    "wof:placetype":"venue"
},
  "geometry": {"coordinates":[-94.54112600000001,39.075755],"type":"Point"}
}