{
  "type": "Feature",
  "properties": {
    "iso:country":"US",
    "sg:address":"114 Holloway Rd",
    "sg:city":"Ballwin",
    "sg:classifiers":[
        {
            "category":"Real Estate",
            "subcategory":"Architect",
            "type":"Services"
        }
    ],
    "sg:phone":"+1 636 394 6857",
    "sg:postcode":"63011",
    "sg:province":"MO",
    "wof:name":"Charles L Willis III & Assoc",
    "wof:placetype":"venue"
},
  "geometry": {"coordinates":[-90.546037,38.593134],"type":"Point"}
}