{
  "type": "Feature",
  "properties": {
    "iso:country":"US",
    "sg:address":"647 E Holly Ave",
    "sg:city":"Saint Louis",
    "sg:classifiers":[
        {
            "category":"Communications",
            "type":"Services"
        }
    ],
    "sg:phone":"+1 314 382 1650",
    "sg:postcode":"63147",
    "sg:province":"MO",
    "sg:tags":[
        "web",
        "design"
    ],
    "wof:name":"Web Innovations and Technology Services",
    "wof:placetype":"venue"
},
  "geometry": {"coordinates":[-90.214731,38.684166],"type":"Point"}
}