{
  "type": "Feature",
  "properties": {
    "iso:country":"US",
    "sg:address":"2493 Roxie Rd",
    "sg:city":"Poplar Bluff",
    "sg:classifiers":[
        {
            "category":"Retail",
            "subcategory":"Auto Repair",
            "type":"Services"
        }
    ],
    "sg:phone":"+1 573 686 9087",
    "sg:postcode":"63901",
    "sg:province":"MO",
    "sg:tags":[
        "automobile",
        "top",
        "upholstery"
    ],
    "wof:name":"Classic Auto Interiors",
    "wof:placetype":"venue"
},
  "geometry": {"coordinates":[-90.426767,36.762202],"type":"Point"}
}