{
  "type": "Feature",
  "properties": {
    "iso:country":"US",
    "sg:address":"2157 S Jefferson Ave",
    "sg:city":"Saint Louis",
    "sg:classifiers":[
        {
            "category":"Organizations",
            "subcategory":"Religious Organization",
            "type":"Services"
        }
    ],
    "sg:phone":"+1 314 601 3660",
    "sg:postcode":"63104",
    "sg:province":"MO",
    "sg:tags":[
        "church"
    ],
    "wof:name":"Christ Temple On the Rock",
    "wof:placetype":"venue"
},
  "geometry": {"coordinates":[-90.221802,38.6101],"type":"Point"}
}