{
  "type": "Feature",
  "properties": {
    "iso:country":"US",
    "sg:address":"21 Old Governor Pl",
    "sg:city":"St Charles",
    "sg:classifiers":[
        {
            "category":"Real Estate",
            "subcategory":"Developer",
            "type":"Services"
        },
        {
            "category":"Building & Trades",
            "subcategory":"Construction",
            "type":"Services"
        }
    ],
    "sg:phone":"+1 636 946 6750",
    "sg:postcode":"63301",
    "sg:province":"MO",
    "sg:tags":[
        "home",
        "builder"
    ],
    "wof:name":"A & O Development Inc",
    "wof:placetype":"venue"
},
  "geometry": {"coordinates":[-90.530477,38.810013],"type":"Point"}
}