{
  "type": "Feature",
  "properties": {
    "iso:country":"US",
    "sg:address":"1709A Colonial Dr",
    "sg:city":"Branson",
    "sg:classifiers":[
        {
            "category":"Farming",
            "subcategory":"Farm",
            "type":"Manufacturing & Wholesale Goods"
        }
    ],
    "sg:phone":"+1 417 838 2079",
    "sg:postcode":"65616",
    "sg:province":"MO",
    "wof:name":"Vsar",
    "wof:placetype":"venue"
},
  "geometry": {"coordinates":[-93.249725,36.642894],"type":"Point"}
}