{
  "type": "Feature",
  "properties": {
    "iso:country":"US",
    "sg:address":"3937 Cordes Dr",
    "sg:city":"St Louis",
    "sg:classifiers":[
        {
            "category":"Shopping",
            "type":"Retail Goods"
        }
    ],
    "sg:phone":"+1 314 416 0050",
    "sg:postcode":"63125",
    "sg:province":"MO",
    "sg:tags":[
        "cosmetic",
        "perfume"
    ],
    "wof:name":"Auto Cosmetics",
    "wof:placetype":"venue"
},
  "geometry": {"coordinates":[-90.327056,38.509496],"type":"Point"}
}