{
  "type": "Feature",
  "properties": {
    "iso:country":"US",
    "sg:address":"1020 Oklahoma Ave",
    "sg:city":"Trenton",
    "sg:classifiers":[
        {
            "category":"Home & Garden",
            "subcategory":"Building Materials",
            "type":"Retail Goods"
        }
    ],
    "sg:phone":"+1 660 359 2070",
    "sg:postcode":"64683",
    "sg:province":"MO",
    "sg:tags":[
        "lumber"
    ],
    "wof:name":"Grundy County Lumber Co",
    "wof:placetype":"venue"
},
  "geometry": {"coordinates":[-93.595336,40.075767],"type":"Point"}
}