{
  "type": "Feature",
  "properties": {
    "iso:country":"US",
    "sg:address":"200 S Bemiston Ave",
    "sg:city":"St Louis",
    "sg:classifiers":[
        {
            "category":"Real Estate",
            "subcategory":"Real Estate Operator",
            "type":"Services"
        }
    ],
    "sg:phone":"+1 314 727 1834",
    "sg:postcode":"63105",
    "sg:province":"MO",
    "sg:tags":[
        "building",
        "parks"
    ],
    "wof:name":"Slavin Building",
    "wof:placetype":"venue"
},
  "geometry": {"coordinates":[-90.337428,38.646135],"type":"Point"}
}