{
  "type": "Feature",
  "properties": {
    "iso:country":"US",
    "sg:address":"18590 Edison Ave",
    "sg:city":"Chesterfield",
    "sg:classifiers":[
        {
            "category":"Social Services",
            "type":"Services"
        }
    ],
    "sg:phone":"+1 636 537 1302",
    "sg:postcode":"63005",
    "sg:province":"MO",
    "wof:name":"Wings of Hope Inc",
    "wof:placetype":"venue"
},
  "geometry": {"coordinates":[-90.65697,38.663926],"type":"Point"}
}