{
  "type": "Feature",
  "properties": {
    "iso:country":"US",
    "sg:address":"405 E 13 St",
    "sg:city":"Kansas City",
    "sg:classifiers":[
        {
            "category":"Professional",
            "subcategory":"Lawyer & Legal Services",
            "type":"Services"
        }
    ],
    "sg:phone":"+1 816 474 4488",
    "sg:postcode":"64106",
    "sg:province":"MO",
    "sg:tags":[
        "attorney"
    ],
    "wof:name":"Peper & Dunning",
    "wof:placetype":"venue"
},
  "geometry": {"coordinates":[-94.577505,39.098356],"type":"Point"}
}