{
  "type": "Feature",
  "properties": {
    "addr:full":"300 E Hwy 24 Moberly MO 65270",
    "addr:housenumber":"300",
    "addr:postcode":"65270",
    "addr:street":"E Hwy 24 Moberly",
    "iso:country":"US",
    "sg:address":"300 E Hwy 24",
    "sg:city":"Moberly",
    "sg:classifiers":[
        {
            "category":"Travel",
            "subcategory":"Hotels & Motels",
            "type":"Entertainment"
        }
    ],
    "sg:phone":"+1 660 263 8862",
    "sg:postcode":"65270",
    "sg:province":"MO",
    "sg:tags":[
        "operation"
    ],
    "wof:name":"Super 8 Motel",
    "wof:placetype":"venue"
},
  "geometry": {"coordinates":[-92.43230200000001,39.441522],"type":"Point"}
}