{
  "type": "Feature",
  "properties": {
    "iso:country":"US",
    "sg:address":"1110 N 2nd St",
    "sg:city":"Festus",
    "sg:classifiers":[
        {
            "category":"Autos & Motor Vehicles",
            "subcategory":"Motorcycle Sales",
            "type":"Retail Goods"
        }
    ],
    "sg:phone":"+1 636 931 7212",
    "sg:postcode":"63028",
    "sg:province":"MO",
    "sg:tags":[
        "scooter"
    ],
    "wof:name":"Hole Shots Custom Motorcycle",
    "wof:placetype":"venue"
},
  "geometry": {"coordinates":[-90.40875200000001,38.220309],"type":"Point"}
}