{
  "type": "Feature",
  "properties": {
    "iso:country":"US",
    "sg:address":"308 E Koenig St",
    "sg:city":"Wentzville",
    "sg:classifiers":[
        {
            "category":"Organizations",
            "subcategory":"Religious Organization",
            "type":"Services"
        }
    ],
    "sg:phone":"+1 636 327 8801",
    "sg:postcode":"63385",
    "sg:province":"MO",
    "sg:tags":[
        "church"
    ],
    "wof:name":"National Conference-Pioneering",
    "wof:placetype":"venue"
},
  "geometry": {"coordinates":[-90.850955,38.812888],"type":"Point"}
}