{
  "type": "Feature",
  "properties": {
    "iso:country":"US",
    "sg:address":"8654 N Boardwalk Ave",
    "sg:city":"Kansas City",
    "sg:classifiers":[
        {
            "category":"Home & Garden",
            "subcategory":"Building Materials",
            "type":"Retail Goods"
        }
    ],
    "sg:phone":"+1 816 505 3300",
    "sg:postcode":"64154",
    "sg:province":"MO",
    "sg:tags":[
        "furnishing",
        "accessory"
    ],
    "wof:name":"Kirkland's",
    "wof:placetype":"venue"
},
  "geometry": {"coordinates":[-94.651723,39.252544],"type":"Point"}
}