{
  "type": "Feature",
  "properties": {
    "iso:country":"US",
    "sg:address":"14515 Titan Ave",
    "sg:city":"Winston",
    "sg:classifiers":[
        {
            "category":"Banks & Credit Unions",
            "subcategory":"Bank",
            "type":"Services"
        }
    ],
    "sg:phone":"+1 660 749 5272",
    "sg:postcode":"64689",
    "sg:province":"MO",
    "sg:tags":[
        "mortgage"
    ],
    "wof:name":"A G Mortgage",
    "wof:placetype":"venue"
},
  "geometry": {"coordinates":[-94.129092,39.859175],"type":"Point"}
}