{
  "type": "Feature",
  "properties": {
    "iso:country":"US",
    "sg:address":"15250 Old Bloomfield Rd",
    "sg:city":"Dexter",
    "sg:classifiers":[
        {
            "category":"Building & Trades",
            "subcategory":"Landfill",
            "type":"Services"
        }
    ],
    "sg:phone":"+1 573 624 8135",
    "sg:postcode":"63841",
    "sg:province":"MO",
    "wof:name":"Lemons Landfill",
    "wof:placetype":"venue"
},
  "geometry": {"coordinates":[-89.940776,36.83654],"type":"Point"}
}