{
  "type": "Feature",
  "properties": {
    "iso:country":"US",
    "sg:address":"7295 S Hwy 94",
    "sg:city":"St Charles",
    "sg:classifiers":[
        {
            "category":"Government",
            "subcategory":"Office",
            "type":"Public Place"
        }
    ],
    "sg:phone":"+1 636 441 8978",
    "sg:postcode":"63304",
    "sg:province":"MO",
    "sg:tags":[
        "federal",
        "govt"
    ],
    "wof:name":"US Energy Dept",
    "wof:placetype":"venue"
},
  "geometry": {"coordinates":[-90.72413,38.694929],"type":"Point"}
}