{
  "type": "Feature",
  "properties": {
    "iso:country":"US",
    "sg:address":"1262 W Foxwood Dr",
    "sg:city":"Raymore",
    "sg:classifiers":[
        {
            "category":"Wholesale",
            "subcategory":"Machinery & Supplies",
            "type":"Manufacturing & Wholesale Goods"
        }
    ],
    "sg:phone":"+1 816 322 6207",
    "sg:postcode":"64083",
    "sg:province":"MO",
    "sg:tags":[
        "printer",
        "cartridge"
    ],
    "wof:name":"Hometown Toner & Ink",
    "wof:placetype":"venue"
},
  "geometry": {"coordinates":[-94.47794,38.812267],"type":"Point"}
}