{
  "type": "Feature",
  "properties": {
    "addr:full":"100 Arnold Crossroads Ctr Arnold MO 63010",
    "addr:housenumber":"100",
    "addr:postcode":"63010",
    "addr:street":"Arnold Crossroads Ctr",
    "iso:country":"US",
    "sg:address":"100 Arnold Crossroads Ctr",
    "sg:city":"Arnold",
    "sg:classifiers":[
        {
            "category":"Restaurant",
            "type":"Food & Drink"
        }
    ],
    "sg:menulink":"http://www.allmenus.com/mo/arnold/121546-fazolis/menu/",
    "sg:phone":"+1 636 282 9033",
    "sg:postcode":"63010",
    "sg:province":"MO",
    "sg:tags":[
        "italian"
    ],
    "wof:name":"Fazoli's",
    "wof:placetype":"venue"
},
  "geometry": {"coordinates":[-90.377197,38.443915],"type":"Point"}
}