{
  "type": "Feature",
  "properties": {
    "addr:full":"721 Olive St St Louis MO 63101",
    "addr:housenumber":"721",
    "addr:postcode":"63101",
    "addr:street":"Olive St",
    "iso:country":"US",
    "sg:address":"721 Olive St",
    "sg:city":"St Louis",
    "sg:classifiers":[
        {
            "category":"Arts & Performance",
            "subcategory":"Theater",
            "type":"Entertainment"
        }
    ],
    "sg:phone":"+1 314 486 7488",
    "sg:postcode":"63101",
    "sg:province":"MO",
    "sg:tags":[
        "bureau"
    ],
    "wof:name":"Dream Quest",
    "wof:placetype":"venue"
},
  "geometry": {"coordinates":[-90.191669,38.628395],"type":"Point"}
}