{
  "type": "Feature",
  "properties": {
    "iso:country":"US",
    "sg:address":"605 S 10th St",
    "sg:city":"Tarkio",
    "sg:classifiers":[
        {
            "category":"Building & Trades",
            "subcategory":"Construction",
            "type":"Services"
        }
    ],
    "sg:phone":"+1 660 736 4333",
    "sg:postcode":"64491",
    "sg:province":"MO",
    "sg:tags":[
        "excavating",
        "contractor"
    ],
    "wof:name":"Levings Construction",
    "wof:placetype":"venue"
},
  "geometry": {"coordinates":[-95.387626,40.436051],"type":"Point"}
}