{
  "type": "Feature",
  "properties": {
    "iso:country":"US",
    "sg:address":"584 Cosie Dr",
    "sg:city":"St Louis",
    "sg:classifiers":[
        {
            "category":"Building & Trades",
            "subcategory":"Landscaping Services",
            "type":"Services"
        }
    ],
    "sg:phone":"+1 314 388 3223",
    "sg:postcode":"63137",
    "sg:province":"MO",
    "sg:tags":[
        "landscape",
        "contractor"
    ],
    "wof:name":"Lyons Lawn & Landscaping",
    "wof:placetype":"venue"
},
  "geometry": {"coordinates":[-90.21742999999999,38.752966],"type":"Point"}
}