{
  "type": "Feature",
  "properties": {
    "iso:country":"US",
    "sg:address":"550 E Chestnut Expy",
    "sg:city":"Springfield",
    "sg:classifiers":[
        {
            "category":"Restaurant",
            "type":"Food & Drink"
        }
    ],
    "sg:menulink":"http://www.allmenus.com/mo/springfield/55022-steak-out/menu/",
    "sg:phone":"+1 417 873 9400",
    "sg:postcode":"65806",
    "sg:province":"MO",
    "sg:tags":[
        "american",
        "steakhouse"
    ],
    "wof:name":"Steak-Out",
    "wof:placetype":"venue"
},
  "geometry": {"coordinates":[-93.28654,37.214901],"type":"Point"}
}