{
  "type": "Feature",
  "properties": {
    "iso:country":"US",
    "sg:address":"3640 S Noland Rd",
    "sg:city":"Independence",
    "sg:classifiers":[
        {
            "category":"Professional",
            "subcategory":"Computer Services",
            "type":"Services"
        }
    ],
    "sg:phone":"+1 816 252 4446",
    "sg:postcode":"64055",
    "sg:province":"MO",
    "sg:tags":[
        "design",
        "system",
        "programing",
        "custom"
    ],
    "wof:name":"Equitrac Corporation",
    "wof:placetype":"venue"
},
  "geometry": {"coordinates":[-94.414886,39.057359],"type":"Point"}
}