{
  "type": "Feature",
  "properties": {
    "iso:country":"US",
    "sg:address":"121 S 5th St",
    "sg:city":"Hannibal",
    "sg:classifiers":[
        {
            "category":"Real Estate",
            "subcategory":"Real Estate Operator",
            "type":"Services"
        }
    ],
    "sg:phone":"+1 573 248 3469",
    "sg:postcode":"63401",
    "sg:province":"MO",
    "sg:tags":[
        "apartment"
    ],
    "wof:name":"Twain Mark Apartment Rental Co",
    "wof:placetype":"venue"
},
  "geometry": {"coordinates":[-91.359167,39.708057],"type":"Point"}
}