{
  "type": "Feature",
  "properties": {
    "iso:country":"US",
    "sg:address":"755 N 3rd St",
    "sg:city":"Ste Genevieve",
    "sg:classifiers":[
        {
            "category":"Building & Trades",
            "subcategory":"Construction",
            "type":"Services"
        }
    ],
    "sg:phone":"+1 573 883 3220",
    "sg:postcode":"63670",
    "sg:province":"MO",
    "sg:tags":[
        "residential",
        "general",
        "commercial",
        "contractor"
    ],
    "wof:name":"Donze Construction Inc",
    "wof:placetype":"venue"
},
  "geometry": {"coordinates":[-90.048575,37.986629],"type":"Point"}
}