{
  "type": "Feature",
  "properties": {
    "iso:country":"US",
    "sg:address":"10428 Lackland Rd",
    "sg:city":"Saint Louis",
    "sg:classifiers":[
        {
            "category":"Freight",
            "type":"Transportation"
        }
    ],
    "sg:phone":"+1 314 429 2781",
    "sg:postcode":"63114",
    "sg:province":"MO",
    "sg:tags":[
        "operator",
        "local",
        "trucking"
    ],
    "wof:name":"Branson Delivery Inc",
    "wof:placetype":"venue"
},
  "geometry": {"coordinates":[-90.391076,38.696625],"type":"Point"}
}