{
  "type": "Feature",
  "properties": {
    "iso:country":"US",
    "sg:address":"212 S Washington St",
    "sg:city":"Clinton",
    "sg:classifiers":[
        {
            "category":"Wholesale",
            "subcategory":"Books, Periodicals, & Newspapers",
            "type":"Manufacturing & Wholesale Goods"
        }
    ],
    "sg:phone":"+1 660 885 2281",
    "sg:postcode":"64735",
    "sg:province":"MO",
    "sg:tags":[
        "distributor"
    ],
    "wof:name":"Clinton Daily Democrat",
    "wof:placetype":"venue"
},
  "geometry": {"coordinates":[-93.777793,38.36932],"type":"Point"}
}