{
  "type": "Feature",
  "properties": {
    "iso:country":"US",
    "sg:address":"1255 E Republic Rd",
    "sg:city":"Springfield",
    "sg:classifiers":[
        {
            "category":"Recreation",
            "type":"Entertainment"
        }
    ],
    "sg:phone":"+1 417 883 7327",
    "sg:postcode":"65804",
    "sg:province":"MO",
    "wof:name":"Budo Ki-Fight Game Productions",
    "wof:placetype":"venue"
},
  "geometry": {"coordinates":[-93.27645,37.137744],"type":"Point"}
}