{
  "type": "Feature",
  "properties": {
    "iso:country":"US",
    "sg:address":"7401 Balson Ave",
    "sg:city":"St Louis",
    "sg:classifiers":[
        {
            "category":"Education",
            "subcategory":"School",
            "type":"Public Place"
        }
    ],
    "sg:phone":"+1 314 290 4100",
    "sg:postcode":"63130",
    "sg:province":"MO",
    "sg:website":"www.ucityschools.org",
    "wof:name":"University City Senior High",
    "wof:placetype":"venue"
},
  "geometry": {"coordinates":[-90.33216299999999,38.664548],"type":"Point"}
}