{
  "type": "Feature",
  "properties": {
    "iso:country":"US",
    "sg:address":"3415 Taft Ave",
    "sg:city":"Saint Louis",
    "sg:classifiers":[
        {
            "category":"Organizations",
            "subcategory":"Religious Organization",
            "type":"Services"
        }
    ],
    "sg:phone":"+1 314 832 0118",
    "sg:postcode":"63111",
    "sg:province":"MO",
    "wof:name":"St Luke's Ev Lutheran Church",
    "wof:placetype":"venue"
},
  "geometry": {"coordinates":[-90.243202,38.5746],"type":"Point"}
}