{
  "type": "Feature",
  "properties": {
    "iso:country":"US",
    "sg:address":"219 Emerson St",
    "sg:city":"Warrensburg",
    "sg:classifiers":[
        {
            "category":"Building & Trades",
            "subcategory":"Plumbing",
            "type":"Services"
        }
    ],
    "sg:phone":"+1 660 747 1117",
    "sg:postcode":"64093",
    "sg:province":"MO",
    "sg:tags":[
        "conditioning",
        "air",
        "system",
        "contractor"
    ],
    "wof:name":"Apex Heating & Cooling LLC",
    "wof:placetype":"venue"
},
  "geometry": {"coordinates":[-93.737475,38.76846],"type":"Point"}
}