{
  "type": "Feature",
  "properties": {
    "iso:country":"US",
    "sg:address":"101 S Highway 59",
    "sg:city":"Anderson",
    "sg:classifiers":[
        {
            "category":"Banks & Credit Unions",
            "subcategory":"Investment Brokerage",
            "type":"Services"
        },
        {
            "category":"Banks & Credit Unions",
            "subcategory":"Bank",
            "type":"Services"
        },
        {
            "category":"Banks & Credit Unions",
            "subcategory":"Financial Services",
            "type":"Services"
        },
        {
            "category":"Insurance",
            "subcategory":"Insurance Agent",
            "type":"Services"
        },
        {
            "category":"Insurance",
            "subcategory":"Life Insurance",
            "type":"Services"
        },
        {
            "category":"Professional",
            "subcategory":"Management & Consulting",
            "type":"Services"
        },
        {
            "category":"Insurance",
            "subcategory":"Hazard Insurance",
            "type":"Services"
        }
    ],
    "sg:phone":"+1 417 845 8820",
    "sg:postcode":"64831",
    "sg:province":"MO",
    "sg:tags":[
        "advisory",
        "mutual",
        "retirement",
        "planner",
        "profit",
        "transfer",
        "sharing",
        "broker",
        "pension",
        "fund",
        "consultant",
        "planning",
        "plan",
        "annuity",
        "bond",
        "counseling",
        "security",
        "debt",
        "analyst",
        "financing",
        "stock"
    ],
    "sg:website":"http://national.citysearch.com/profile/external/38019997/anderson_mo/edward_jones_kim_ramsay.html?publisher=yellowpages&reference_id=1&placement=ypwebsitemip",
    "wof:name":"Edward Jones - KIM RAMSAY",
    "wof:placetype":"venue"
},
  "geometry": {"coordinates":[-94.44606,36.651062],"type":"Point"}
}