{
  "type": "Feature",
  "properties": {
    "iso:country":"US",
    "sg:address":"7515 York Dr",
    "sg:city":"Saint Louis",
    "sg:classifiers":[
        {
            "category":"Real Estate",
            "subcategory":"Real Estate Agent",
            "type":"Services"
        }
    ],
    "sg:phone":"+1 314 721 8881",
    "sg:postcode":"63105",
    "sg:province":"MO",
    "sg:tags":[
        "property"
    ],
    "wof:name":"Monik",
    "wof:placetype":"venue"
},
  "geometry": {"coordinates":[-90.332769,38.638443],"type":"Point"}
}