{
  "type": "Feature",
  "properties": {
    "iso:country":"US",
    "sg:address":"3010 N Hwy 94",
    "sg:city":"Saint Charles",
    "sg:classifiers":[
        {
            "category":"Health Services",
            "subcategory":"Health Practitioner",
            "type":"Services"
        }
    ],
    "sg:phone":"+1 636 925 3933",
    "sg:postcode":"63301",
    "sg:province":"MO",
    "wof:name":"370 Chrprctic Rhabilitation PC",
    "wof:placetype":"venue"
},
  "geometry": {"coordinates":[-90.473707,38.814693],"type":"Point"}
}