{
  "type": "Feature",
  "properties": {
    "iso:country":"US",
    "sg:address":"109 NW Barry Rd",
    "sg:city":"Kansas City",
    "sg:classifiers":[
        {
            "category":"Personal",
            "subcategory":"Beauty Salon",
            "type":"Services"
        }
    ],
    "sg:phone":"+1 816 420 9200",
    "sg:postcode":"64155",
    "sg:province":"MO",
    "sg:tags":[
        "shop"
    ],
    "wof:name":"Foxy",
    "wof:placetype":"venue"
},
  "geometry": {"coordinates":[-94.582269,39.246258],"type":"Point"}
}