{
  "type": "Feature",
  "properties": {
    "iso:country":"US",
    "sg:address":"12566 Cumberland Ave",
    "sg:city":"Marceline",
    "sg:classifiers":[
        {
            "category":"Restaurant",
            "type":"Food & Drink"
        }
    ],
    "sg:phone":"+1 660 376 2477",
    "sg:postcode":"64658",
    "sg:province":"MO",
    "sg:tags":[
        "style",
        "family"
    ],
    "wof:name":"Darling Denny",
    "wof:placetype":"venue"
},
  "geometry": {"coordinates":[-92.93356300000001,39.66415],"type":"Point"}
}