{
  "type": "Feature",
  "properties": {
    "iso:country":"US",
    "sg:address":"1500 Robertson Ave",
    "sg:city":"Carthage",
    "sg:classifiers":[
        {
            "category":"Travel",
            "subcategory":"Travel Agent",
            "type":"Entertainment"
        }
    ],
    "sg:phone":"+1 417 358 2210",
    "sg:postcode":"64836",
    "sg:province":"MO",
    "sg:tags":[
        "operator",
        "tour",
        "agency"
    ],
    "wof:name":"Horizon's Travel",
    "wof:placetype":"venue"
},
  "geometry": {"coordinates":[-94.324928,37.163219],"type":"Point"}
}