{
  "type": "Feature",
  "properties": {
    "iso:country":"US",
    "sg:address":"253 Carmel Woods Dr",
    "sg:city":"Ballwin",
    "sg:classifiers":[
        {
            "category":"Arts & Performance",
            "subcategory":"Theater",
            "type":"Entertainment"
        }
    ],
    "sg:phone":"+1 636 230 9990",
    "sg:postcode":"63021",
    "sg:province":"MO",
    "sg:tags":[
        "group"
    ],
    "wof:name":"Encore Band & Entertainment AG",
    "wof:placetype":"venue"
},
  "geometry": {"coordinates":[-90.58419600000001,38.588106],"type":"Point"}
}