{
  "type": "Feature",
  "properties": {
    "iso:country":"US",
    "sg:address":"4431 S Fremont Ave",
    "sg:city":"Springfield",
    "sg:classifiers":[
        {
            "category":"Shopping",
            "subcategory":"Books",
            "type":"Retail Goods"
        }
    ],
    "sg:phone":"+1 417 841 5050",
    "sg:postcode":"65804",
    "sg:province":"MO",
    "wof:name":"Bookstore",
    "wof:placetype":"venue"
},
  "geometry": {"coordinates":[-93.272212,37.13535],"type":"Point"}
}