{
  "type": "Feature",
  "properties": {
    "iso:country":"US",
    "sg:address":"15435 State Hwy 28",
    "sg:city":"Vienna",
    "sg:classifiers":[
        {
            "category":"Shopping",
            "subcategory":"Department Store",
            "type":"Retail Goods"
        }
    ],
    "sg:phone":"+1 573 422 3504",
    "sg:postcode":"65582",
    "sg:province":"MO",
    "wof:name":"Dollar World",
    "wof:placetype":"venue"
},
  "geometry": {"coordinates":[-91.987323,38.108064],"type":"Point"}
}