{
  "type": "Feature",
  "properties": {
    "iso:country":"US",
    "sg:address":"6115 W Florissant Ave",
    "sg:city":"Saint Louis",
    "sg:classifiers":[
        {
            "category":"Social Services",
            "subcategory":"Child Care",
            "type":"Services"
        },
        {
            "category":"Education",
            "subcategory":"Preschool",
            "type":"Public Place"
        },
        {
            "category":"Education",
            "subcategory":"School",
            "type":"Public Place"
        },
        {
            "category":"Food & Beverages",
            "subcategory":"Groceries & Convenience Stores",
            "type":"Retail Goods"
        }
    ],
    "sg:phone":"+1 314 383 2273",
    "sg:postcode":"63136",
    "sg:province":"MO",
    "sg:tags":[
        "elementary",
        "day"
    ],
    "wof:name":"New Day Child Development Center",
    "wof:placetype":"venue"
},
  "geometry": {"coordinates":[-90.253601,38.7113],"type":"Point"}
}