{
  "type": "Feature",
  "properties": {
    "iso:country":"US",
    "sg:address":"8500 Audrain Rd 369",
    "sg:city":"Mexico",
    "sg:classifiers":[
        {
            "category":"Building & Trades",
            "subcategory":"Electrical",
            "type":"Services"
        }
    ],
    "sg:phone":"+1 573 581 8925",
    "sg:postcode":"65265",
    "sg:province":"MO",
    "sg:tags":[
        "electric",
        "contractor"
    ],
    "wof:name":"Settle Electric",
    "wof:placetype":"venue"
},
  "geometry": {"coordinates":[-91.91904,39.218787],"type":"Point"}
}