{
  "type": "Feature",
  "properties": {
    "iso:country":"US",
    "sg:address":"4120 Dr Greaves Rd",
    "sg:city":"Grandview",
    "sg:classifiers":[
        {
            "category":"Professional",
            "subcategory":"Business Services",
            "type":"Services"
        }
    ],
    "sg:phone":"+1 816 356 7773",
    "sg:postcode":"64030",
    "sg:province":"MO",
    "sg:tags":[
        "contractor"
    ],
    "wof:name":"J & J Roofing",
    "wof:placetype":"venue"
},
  "geometry": {"coordinates":[-94.546429,38.904351],"type":"Point"}
}