{
  "type": "Feature",
  "properties": {
    "iso:country":"US",
    "sg:address":"12529 Westport Dr",
    "sg:city":"Saint Louis",
    "sg:classifiers":[
        {
            "category":"Shopping",
            "subcategory":"Gifts & Souvenirs",
            "type":"Retail Goods"
        }
    ],
    "sg:phone":"+1 314 434 8888",
    "sg:postcode":"63146",
    "sg:province":"MO",
    "wof:name":"Treasure Cove Collectibles",
    "wof:placetype":"venue"
},
  "geometry": {"coordinates":[-90.457883,38.690867],"type":"Point"}
}