{
  "type": "Feature",
  "properties": {
    "iso:country":"US",
    "sg:address":"5646 Carver Rd",
    "sg:city":"Diamond",
    "sg:classifiers":[
        {
            "category":"Government",
            "subcategory":"Office",
            "type":"Public Place"
        }
    ],
    "sg:phone":"+1 417 325 4151",
    "sg:postcode":"64840",
    "sg:province":"MO",
    "sg:tags":[
        "national",
        "park"
    ],
    "wof:name":"George Wash Carver Nat Monu",
    "wof:placetype":"venue"
},
  "geometry": {"coordinates":[-94.350949,36.985958],"type":"Point"}
}