{
  "type": "Feature",
  "properties": {
    "iso:country":"US",
    "sg:address":"299 Turkey Creek Bottom Ln",
    "sg:city":"Hawk Point",
    "sg:classifiers":[
        {
            "category":"Farming",
            "subcategory":"Livestock Farm",
            "type":"Manufacturing & Wholesale Goods"
        },
        {
            "category":"Recreation",
            "type":"Entertainment"
        }
    ],
    "sg:phone":"+1 636 338 4766",
    "sg:postcode":"63349",
    "sg:province":"MO",
    "sg:tags":[
        "equine",
        "stable"
    ],
    "wof:name":"Equine Specialties",
    "wof:placetype":"venue"
},
  "geometry": {"coordinates":[-91.140368,38.988735],"type":"Point"}
}