{
  "type": "Feature",
  "properties": {
    "iso:country":"US",
    "sg:address":"437 Caroline Ave",
    "sg:city":"St Louis",
    "sg:classifiers":[
        {
            "category":"Retail",
            "subcategory":"Repair Shop",
            "type":"Services"
        }
    ],
    "sg:phone":"+1 314 966 2914",
    "sg:postcode":"63122",
    "sg:province":"MO",
    "sg:tags":[
        "bathtub",
        "sink",
        "refinishing"
    ],
    "wof:name":"Cantino Bathtub & Tile",
    "wof:placetype":"venue"
},
  "geometry": {"coordinates":[-90.42256500000001,38.575078],"type":"Point"}
}