{
  "type": "Feature",
  "properties": {
    "iso:country":"US",
    "sg:address":"401 90th Rd SE",
    "sg:city":"Saint Joseph",
    "sg:phone":"+1 816 667 5600",
    "sg:postcode":"64507",
    "sg:province":"MO",
    "sg:tags":[
        "farm",
        "corn",
        "soybean"
    ],
    "wof:name":"Willie Knadler",
    "wof:placetype":"venue"
},
  "geometry": {"coordinates":[-94.70223799999999,39.769636],"type":"Point"}
}