{
  "type": "Feature",
  "properties": {
    "iso:country":"US",
    "sg:address":"7931 Big Bend Blvd",
    "sg:city":"Saint Louis",
    "sg:classifiers":[
        {
            "category":"Real Estate",
            "subcategory":"Architect",
            "type":"Services"
        }
    ],
    "sg:phone":"+1 314 961 7345",
    "sg:postcode":"63119",
    "sg:province":"MO",
    "sg:tags":[
        "architectural"
    ],
    "wof:name":"Tangent Architecture & Plan",
    "wof:placetype":"venue"
},
  "geometry": {"coordinates":[-90.334484,38.594845],"type":"Point"}
}