{
  "type": "Feature",
  "properties": {
    "iso:country":"US",
    "sg:address":"832 W 62 St",
    "sg:city":"Kansas City",
    "sg:classifiers":[
        {
            "category":"Building & Trades",
            "subcategory":"Construction",
            "type":"Services"
        }
    ],
    "sg:phone":"+1 816 361 9119",
    "sg:postcode":"64113",
    "sg:province":"MO",
    "sg:tags":[
        "house"
    ],
    "wof:name":"Gude Co",
    "wof:placetype":"venue"
},
  "geometry": {"coordinates":[-94.60086699999999,39.015527],"type":"Point"}
}