{
  "type": "Feature",
  "properties": {
    "iso:country":"US",
    "sg:address":"3882 Pershall Rd",
    "sg:city":"Ferguson",
    "sg:classifiers":[
        {
            "category":"Insurance",
            "subcategory":"Insurance Agent",
            "type":"Services"
        }
    ],
    "sg:phone":"+1 314 522 3200",
    "sg:postcode":"63135",
    "sg:province":"MO",
    "wof:name":"Thrivent Financial-Lutherans",
    "wof:placetype":"venue"
},
  "geometry": {"coordinates":[-90.304883,38.771993],"type":"Point"}
}