{
  "type": "Feature",
  "properties": {
    "iso:country":"US",
    "sg:address":"3702 Frederick Ave",
    "sg:city":"Saint Joseph",
    "sg:classifiers":[
        {
            "category":"Shopping",
            "subcategory":"Clothing, Apparel, & Fashions",
            "type":"Retail Goods"
        }
    ],
    "sg:phone":"+1 816 232 6663",
    "sg:postcode":"64506",
    "sg:province":"MO",
    "wof:name":"Rue 21 319",
    "wof:placetype":"venue"
},
  "geometry": {"coordinates":[-94.80159,39.77687],"type":"Point"}
}