{
  "type": "Feature",
  "properties": {
    "iso:country":"US",
    "sg:address":"13642 Co Rd 612",
    "sg:city":"Dexter",
    "sg:classifiers":[
        {
            "category":"Banks & Credit Unions",
            "subcategory":"Investment Brokerage",
            "type":"Services"
        }
    ],
    "sg:phone":"+1 573 624 8870",
    "sg:postcode":"63841",
    "sg:province":"MO",
    "sg:tags":[
        "security"
    ],
    "wof:name":"Alanar Inc",
    "wof:placetype":"venue"
},
  "geometry": {"coordinates":[-90.03193,36.789882],"type":"Point"}
}