{
  "type": "Feature",
  "properties": {
    "iso:country":"US",
    "sg:address":"4358 State Rd Aa",
    "sg:city":"Tebbetts",
    "sg:classifiers":[
        {
            "category":"Insurance",
            "subcategory":"Insurance Agent",
            "type":"Services"
        }
    ],
    "sg:phone":"+1 573 295 4735",
    "sg:postcode":"65080",
    "sg:province":"MO",
    "wof:name":"Eugene Richards",
    "wof:placetype":"venue"
},
  "geometry": {"coordinates":[-92.01511600000001,38.619603],"type":"Point"}
}