{
  "type": "Feature",
  "properties": {
    "addr:full":"670 Co Rd 442 New Franklin MO 65274",
    "addr:housenumber":"670;442",
    "addr:postcode":"65274",
    "addr:street":"Co Rd;New Franklin",
    "iso:country":"US",
    "sg:address":"670 Co Rd 442",
    "sg:city":"New Franklin",
    "sg:classifiers":[
        {
            "category":"Building & Trades",
            "subcategory":"Construction",
            "type":"Services"
        }
    ],
    "sg:phone":"+1 660 848 2771",
    "sg:postcode":"65274",
    "sg:province":"MO",
    "sg:tags":[
        "contractor"
    ],
    "wof:name":"R & R Construction",
    "wof:placetype":"venue"
},
  "geometry": {"coordinates":[-92.64248499999999,39.015494],"type":"Point"}
}