{
  "type": "Feature",
  "properties": {
    "iso:country":"US",
    "sg:address":"507 Pacific Dr",
    "sg:city":"Crane",
    "sg:classifiers":[
        {
            "category":"Building & Trades",
            "subcategory":"Landscaping Services",
            "type":"Services"
        }
    ],
    "sg:phone":"+1 417 723 5944",
    "sg:postcode":"65633",
    "sg:province":"MO",
    "sg:tags":[
        "landscape",
        "contractor"
    ],
    "wof:name":"Patterson Paitten Landscaping",
    "wof:placetype":"venue"
},
  "geometry": {"coordinates":[-93.56177099999999,36.870571],"type":"Point"}
}