{
  "type": "Feature",
  "properties": {
    "iso:country":"US",
    "sg:address":"520 NE Colbern Rd",
    "sg:city":"Lees Summit",
    "sg:classifiers":[
        {
            "category":"Insurance",
            "subcategory":"Insurance Agent",
            "type":"Services"
        }
    ],
    "sg:phone":"+1 816 434 3600",
    "sg:postcode":"64086",
    "sg:province":"MO",
    "wof:name":"Lumbermen's-Kansas City",
    "wof:placetype":"venue"
},
  "geometry": {"coordinates":[-94.36295699999999,38.946305],"type":"Point"}
}