{
  "type": "Feature",
  "properties": {
    "iso:country":"US",
    "sg:address":"324 E Torrance St",
    "sg:city":"Maryville",
    "sg:classifiers":[
        {
            "category":"Recreation",
            "type":"Entertainment"
        }
    ],
    "sg:phone":"+1 660 582 3752",
    "sg:postcode":"64468",
    "sg:province":"MO",
    "wof:name":"Nodaway County Community Fair",
    "wof:placetype":"venue"
},
  "geometry": {"coordinates":[-94.870417,40.340248],"type":"Point"}
}