{
  "type": "Feature",
  "properties": {
    "iso:country":"US",
    "sg:address":"503 N Maguire St",
    "sg:city":"Warrensburg",
    "sg:classifiers":[
        {
            "category":"Shopping",
            "subcategory":"Books",
            "type":"Retail Goods"
        }
    ],
    "sg:phone":"+1 660 747 9232",
    "sg:postcode":"64093",
    "sg:province":"MO",
    "sg:tags":[
        "dealer"
    ],
    "wof:name":"Warrensburg 1/2 Off Books",
    "wof:placetype":"venue"
},
  "geometry": {"coordinates":[-93.73555399999999,38.76834],"type":"Point"}
}