{
  "type": "Feature",
  "properties": {
    "iso:country":"US",
    "sg:address":"605 S Main St",
    "sg:city":"Salem",
    "sg:classifiers":[
        {
            "category":"Professional",
            "subcategory":"Business Services",
            "type":"Services"
        }
    ],
    "sg:phone":"+1 573 729 6332",
    "sg:postcode":"65560",
    "sg:province":"MO",
    "sg:tags":[
        "holding"
    ],
    "wof:name":"Studt Holdings",
    "wof:placetype":"venue"
},
  "geometry": {"coordinates":[-91.535106,37.639254],"type":"Point"}
}