{
  "type": "Feature",
  "properties": {
    "iso:country":"US",
    "sg:address":"301 N County Park Rd",
    "sg:city":"Easton",
    "sg:classifiers":[
        {
            "category":"Education",
            "subcategory":"School",
            "type":"Public Place"
        }
    ],
    "sg:phone":"+1 816 473 2451",
    "sg:postcode":"64443",
    "sg:province":"MO",
    "sg:tags":[
        "middle"
    ],
    "wof:name":"East Buchanan Middle School",
    "wof:placetype":"venue"
},
  "geometry": {"coordinates":[-94.63649,39.722267],"type":"Point"}
}