{
  "type": "Feature",
  "properties": {
    "iso:country":"US",
    "sg:address":"211 N Main St",
    "sg:city":"Monroe City",
    "sg:classifiers":[
        {
            "category":"Professional",
            "subcategory":"Lawyer & Legal Services",
            "type":"Services"
        }
    ],
    "sg:phone":"+1 573 735 4590",
    "sg:postcode":"63456",
    "sg:province":"MO",
    "wof:name":"Sandifer Samuel J Atty At Law",
    "wof:placetype":"venue"
},
  "geometry": {"coordinates":[-91.73473300000001,39.653698],"type":"Point"}
}