{
  "type": "Feature",
  "properties": {
    "iso:country":"US",
    "sg:address":"423 US Hwy 60 Bus",
    "sg:city":"Dexter",
    "sg:classifiers":[
        {
            "category":"Health Services",
            "subcategory":"Nursing And Care Facility",
            "type":"Services"
        }
    ],
    "sg:phone":"+1 573 614 4774",
    "sg:postcode":"63841",
    "sg:province":"MO",
    "sg:tags":[
        "hospice"
    ],
    "wof:name":"Preferred Hospice",
    "wof:placetype":"venue"
},
  "geometry": {"coordinates":[-89.963466,36.799768],"type":"Point"}
}