{
  "type": "Feature",
  "properties": {
    "iso:country":"US",
    "sg:address":"609 Main St",
    "sg:city":"Boonville",
    "sg:classifiers":[
        {
            "category":"Freight",
            "type":"Transportation"
        }
    ],
    "sg:phone":"+1 660 882 5858",
    "sg:postcode":"65233",
    "sg:province":"MO",
    "sg:tags":[
        "arrangement"
    ],
    "wof:name":"Howard Cooper County Regional",
    "wof:placetype":"venue"
},
  "geometry": {"coordinates":[-92.743255,38.973432],"type":"Point"}
}