{
  "type": "Feature",
  "properties": {
    "iso:country":"US",
    "sg:address":"301 W 13 St",
    "sg:city":"Kansas City",
    "sg:classifiers":[
        {
            "category":"Professional",
            "subcategory":"Business Services",
            "type":"Services"
        },
        {
            "category":"Government",
            "subcategory":"Office",
            "type":"Public Place"
        }
    ],
    "sg:phone":"+1 816 513 5000",
    "sg:postcode":"64105",
    "sg:province":"MO",
    "sg:tags":[
        "convention",
        "center",
        "village"
    ],
    "wof:name":"Convention Center",
    "wof:placetype":"venue"
},
  "geometry": {"coordinates":[-94.588483,39.098802],"type":"Point"}
}