{
  "type": "Feature",
  "properties": {
    "iso:country":"US",
    "sg:address":"620 Spirit Of Saint Louis Blvd",
    "sg:city":"Chesterfield",
    "sg:phone":"+1 636 530 1779",
    "sg:postcode":"63005",
    "sg:province":"MO",
    "wof:name":"Cobitco Inc",
    "wof:placetype":"venue"
},
  "geometry": {"coordinates":[-90.645006,38.665627],"type":"Point"}
}