{
  "type": "Feature",
  "properties": {
    "iso:country":"US",
    "sg:address":"710 Highland Ave",
    "sg:city":"Warrensburg",
    "sg:classifiers":[
        {
            "category":"Retail",
            "subcategory":"Repair Shop",
            "type":"Services"
        }
    ],
    "sg:phone":"+1 660 747 2716",
    "sg:postcode":"64093",
    "sg:province":"MO",
    "sg:tags":[
        "upholsterer"
    ],
    "wof:name":"R & S Enterprises",
    "wof:placetype":"venue"
},
  "geometry": {"coordinates":[-93.737404,38.754268],"type":"Point"}
}