{
  "type": "Feature",
  "properties": {
    "iso:country":"US",
    "sg:address":"11428 E 17 St S",
    "sg:city":"Independence",
    "sg:classifiers":[
        {
            "category":"Building & Trades",
            "subcategory":"Pest Control",
            "type":"Services"
        }
    ],
    "sg:phone":"+1 816 252 4716",
    "sg:postcode":"64052",
    "sg:province":"MO",
    "wof:name":"New Generations Pest Control",
    "wof:placetype":"venue"
},
  "geometry": {"coordinates":[-94.440251,39.088612],"type":"Point"}
}