{
  "type": "Feature",
  "properties": {
    "iso:country":"US",
    "sg:address":"575 Co Rd 363",
    "sg:city":"Taylor",
    "sg:classifiers":[
        {
            "category":"Building & Trades",
            "subcategory":"Construction",
            "type":"Services"
        }
    ],
    "sg:phone":"+1 573 393 2332",
    "sg:postcode":"63471",
    "sg:province":"MO",
    "sg:tags":[
        "heavy"
    ],
    "wof:name":"Martins Trenching & Back",
    "wof:placetype":"venue"
},
  "geometry": {"coordinates":[-91.52344600000001,39.927497],"type":"Point"}
}