{
  "type": "Feature",
  "properties": {
    "iso:country":"US",
    "sg:address":"1437 Whittier St",
    "sg:city":"Saint Louis",
    "sg:classifiers":[
        {
            "category":"Real Estate",
            "subcategory":"Real Estate Agent",
            "type":"Services"
        }
    ],
    "sg:phone":"+1 314 652 7632",
    "sg:postcode":"63113",
    "sg:province":"MO",
    "wof:name":"Isaac Randle Inc",
    "wof:placetype":"venue"
},
  "geometry": {"coordinates":[-90.23886899999999,38.653659],"type":"Point"}
}