{
  "type": "Feature",
  "properties": {
    "iso:country":"US",
    "sg:address":"30 S Miramiguoa Dr",
    "sg:city":"Sullivan",
    "sg:classifiers":[
        {
            "category":"Structure",
            "subcategory":"Office Building",
            "type":"Public Place"
        }
    ],
    "sg:phone":"+1 573 468 8641",
    "sg:postcode":"63080",
    "sg:province":"MO",
    "sg:tags":[
        "park"
    ],
    "wof:name":"Asd Properties",
    "wof:placetype":"venue"
},
  "geometry": {"coordinates":[-91.097413,38.229375],"type":"Point"}
}