{
  "type": "Feature",
  "properties": {
    "iso:country":"US",
    "sg:address":"406 Russell Rd",
    "sg:city":"Sullivan",
    "sg:classifiers":[
        {
            "category":"Travel",
            "subcategory":"Hotels & Motels",
            "type":"Entertainment"
        }
    ],
    "sg:phone":"+1 573 468 4731",
    "sg:postcode":"63080",
    "sg:province":"MO",
    "wof:name":"Northside Properties",
    "wof:placetype":"venue"
},
  "geometry": {"coordinates":[-91.149072,38.206886],"type":"Point"}
}