{
  "type": "Feature",
  "properties": {
    "iso:country":"US",
    "sg:address":"829 S Kingshighway",
    "sg:city":"Cape Girardeau",
    "sg:classifiers":[
        {
            "category":"Bars & Pubs",
            "type":"Food & Drink"
        }
    ],
    "sg:phone":"+1 573 335 9597",
    "sg:postcode":"63703",
    "sg:province":"MO",
    "sg:tags":[
        "drinking"
    ],
    "wof:name":"Daytimers Lounge",
    "wof:placetype":"venue"
},
  "geometry": {"coordinates":[-89.55571399999999,37.285706],"type":"Point"}
}