{
  "type": "Feature",
  "properties": {
    "iso:country":"US",
    "sg:address":"14805 N Outer 40 Rd Suite 320",
    "sg:city":"Chesterfield",
    "sg:classifiers":[
        {
            "category":"Community Center",
            "subcategory":"Senior",
            "type":"Public Place"
        },
        {
            "category":"Health Services",
            "subcategory":"Nursing And Care Facility",
            "type":"Services"
        },
        {
            "category":"Health Services",
            "subcategory":"Health Practitioner",
            "type":"Services"
        },
        {
            "category":"Social Services",
            "subcategory":"Adult Care",
            "type":"Services"
        }
    ],
    "sg:phone":"+1 636 821 8061",
    "sg:postcode":"63017",
    "sg:province":"MO",
    "sg:tags":[
        "nurses-home",
        "therapist",
        "citizen",
        "home",
        "eldercare-home",
        "physical"
    ],
    "sg:website":"http://www.delmargardens.com/homecare",
    "wof:name":"Delmar Gardens Home Care",
    "wof:placetype":"venue"
},
  "geometry": {"coordinates":[-90.546368,38.650053],"type":"Point"}
}