{
  "type": "Feature",
  "properties": {
    "iso:country":"US",
    "sg:address":"12404 Blue Ridge Exd",
    "sg:city":"Grandview",
    "sg:classifiers":[
        {
            "category":"Organizations",
            "subcategory":"Religious Organization",
            "type":"Services"
        }
    ],
    "sg:phone":"+1 816 763 1144",
    "sg:postcode":"64030",
    "sg:province":"MO",
    "sg:tags":[
        "church"
    ],
    "wof:name":"Calvary Chapel Of KC",
    "wof:placetype":"venue"
},
  "geometry": {"coordinates":[-94.53375200000001,38.89872],"type":"Point"}
}