{
  "type": "Feature",
  "properties": {
    "iso:country":"US",
    "sg:address":"1314 Webster St",
    "sg:city":"West Plains",
    "sg:classifiers":[
        {
            "category":"Social Services",
            "subcategory":"Adult Care",
            "type":"Services"
        }
    ],
    "sg:phone":"+1 417 257 6977",
    "sg:postcode":"65775",
    "sg:province":"MO",
    "sg:tags":[
        "home",
        "residential"
    ],
    "wof:name":"Professional Asst Living Systm",
    "wof:placetype":"venue"
},
  "geometry": {"coordinates":[-91.866347,36.729548],"type":"Point"}
}