{
  "type": "Feature",
  "properties": {
    "iso:country":"US",
    "sg:address":"8 Pine Ridge Ln",
    "sg:city":"Eureka",
    "sg:classifiers":[
        {
            "category":"Building & Trades",
            "subcategory":"Construction",
            "type":"Services"
        }
    ],
    "sg:phone":"+1 636 938 3277",
    "sg:postcode":"63025",
    "sg:province":"MO",
    "sg:tags":[
        "house"
    ],
    "wof:name":"Rainbow Builders",
    "wof:placetype":"venue"
},
  "geometry": {"coordinates":[-90.647385,38.441511],"type":"Point"}
}