{
  "type": "Feature",
  "properties": {
    "iso:country":"US",
    "sg:address":"1205 W 50 Ter",
    "sg:city":"Kansas City",
    "sg:classifiers":[
        {
            "category":"Professional",
            "subcategory":"Business Services",
            "type":"Services"
        }
    ],
    "sg:phone":"+1 816 756 0011",
    "sg:postcode":"64112",
    "sg:province":"MO",
    "wof:name":"Us Franchise Systems",
    "wof:placetype":"venue"
},
  "geometry": {"coordinates":[-94.60357399999999,39.036307],"type":"Point"}
}