{
  "type": "Feature",
  "properties": {
    "iso:country":"US",
    "sg:address":"8422 State Hwy 7",
    "sg:city":"Blue Springs",
    "sg:classifiers":[
        {
            "category":"Autos & Motor Vehicles",
            "subcategory":"Automobile Sales",
            "type":"Retail Goods"
        }
    ],
    "sg:phone":"+1 816 578 5111",
    "sg:postcode":"64014",
    "sg:province":"MO",
    "sg:tags":[
        "car",
        "dealer"
    ],
    "wof:name":"Executive Automotive Svc",
    "wof:placetype":"venue"
},
  "geometry": {"coordinates":[-94.27454899999999,38.962385],"type":"Point"}
}