{
  "type": "Feature",
  "properties": {
    "iso:country":"US",
    "sg:address":"16463 Birch Forest Dr",
    "sg:city":"Ballwin",
    "sg:classifiers":[
        {
            "category":"Professional",
            "type":"Services"
        }
    ],
    "sg:phone":"+1 636 273 4671",
    "sg:postcode":"63011",
    "sg:province":"MO",
    "wof:name":"Ross Systems",
    "wof:placetype":"venue"
},
  "geometry": {"coordinates":[-90.623552,38.589096],"type":"Point"}
}