{
  "type": "Feature",
  "properties": {
    "iso:country":"US",
    "sg:address":"9094 Overland Plz",
    "sg:city":"Overland",
    "sg:classifiers":[
        {
            "category":"Real Estate",
            "subcategory":"Architect",
            "type":"Services"
        }
    ],
    "sg:phone":"+1 314 427 0707",
    "sg:postcode":"63114",
    "sg:province":"MO",
    "sg:tags":[
        "architectural"
    ],
    "wof:name":"Associates",
    "wof:placetype":"venue"
},
  "geometry": {"coordinates":[-90.357375,38.686437],"type":"Point"}
}