{
  "type": "Feature",
  "properties": {
    "iso:country":"US",
    "sg:address":"4720 Jamieson Ave",
    "sg:city":"Saint Louis",
    "sg:classifiers":[
        {
            "category":"Organizations",
            "subcategory":"Religious Organization",
            "type":"Services"
        }
    ],
    "sg:phone":"+1 314 752 1015",
    "sg:postcode":"63109",
    "sg:province":"MO",
    "wof:name":"Trinity Christian Ctr Churches",
    "wof:placetype":"venue"
},
  "geometry": {"coordinates":[-90.30892799999999,38.588628],"type":"Point"}
}