{
  "type": "Feature",
  "properties": {
    "iso:country":"US",
    "sg:address":"121 S Ohio St",
    "sg:city":"Humansville",
    "sg:classifiers":[
        {
            "category":"Insurance",
            "subcategory":"Insurance Agent",
            "type":"Services"
        }
    ],
    "sg:phone":"+1 417 754 8377",
    "sg:postcode":"65674",
    "sg:province":"MO",
    "wof:name":"Arlene Lear Insurance",
    "wof:placetype":"venue"
},
  "geometry": {"coordinates":[-93.577589,37.79382],"type":"Point"}
}