{
  "type": "Feature",
  "properties": {
    "iso:country":"US",
    "sg:address":"8124 Saint Charles Rock Rd",
    "sg:city":"Saint Louis",
    "sg:classifiers":[
        {
            "category":"Bars & Pubs",
            "type":"Food & Drink"
        }
    ],
    "sg:phone":"+1 314 429 2279",
    "sg:postcode":"63114",
    "sg:province":"MO",
    "sg:tags":[
        "drinking"
    ],
    "wof:name":"Saloon Block House",
    "wof:placetype":"venue"
},
  "geometry": {"coordinates":[-90.329775,38.699592],"type":"Point"}
}