{
  "type": "Feature",
  "properties": {
    "iso:country":"US",
    "sg:address":"206 N Grove St",
    "sg:city":"Kearney",
    "sg:classifiers":[
        {
            "category":"Farming",
            "subcategory":"Farm",
            "type":"Manufacturing & Wholesale Goods"
        }
    ],
    "sg:phone":"+1 816 628 2200",
    "sg:postcode":"64060",
    "sg:province":"MO",
    "wof:name":"Shanks Farms",
    "wof:placetype":"venue"
},
  "geometry": {"coordinates":[-94.36077899999999,39.373986],"type":"Point"}
}