{
  "type": "Feature",
  "properties": {
    "iso:country":"US",
    "sg:address":"437 US Hwy 69",
    "sg:city":"Kansas City",
    "sg:classifiers":[
        {
            "category":"Shopping",
            "subcategory":"Used Merchandise",
            "type":"Retail Goods"
        }
    ],
    "sg:phone":"+1 816 452 5100",
    "sg:postcode":"64119",
    "sg:province":"MO",
    "sg:tags":[
        "shop",
        "thrift"
    ],
    "sg:website":"www.majorthrift.com",
    "wof:name":"Maj-R Thrift & Discount Store",
    "wof:placetype":"venue"
},
  "geometry": {"coordinates":[-94.493691,39.201964],"type":"Point"}
}