{
  "type": "Feature",
  "properties": {
    "iso:country":"US",
    "sg:address":"600 N Kingshighway Blvd Ofc",
    "sg:city":"Saint Louis",
    "sg:classifiers":[
        {
            "category":"Real Estate",
            "subcategory":"Real Estate Operator",
            "type":"Services"
        }
    ],
    "sg:phone":"+1 314 361 1400",
    "sg:postcode":"63108",
    "sg:province":"MO",
    "sg:tags":[
        "apartment"
    ],
    "wof:name":"Washington Apartments",
    "wof:placetype":"venue"
},
  "geometry": {"coordinates":[-90.26370199999999,38.650501],"type":"Point"}
}