{
  "type": "Feature",
  "properties": {
    "iso:country":"US",
    "sg:address":"10627 Tesshire Dr",
    "sg:city":"Saint Louis",
    "sg:classifiers":[
        {
            "category":"Building & Trades",
            "subcategory":"Electrical",
            "type":"Services"
        }
    ],
    "sg:phone":"+1 314 842 7660",
    "sg:postcode":"63123",
    "sg:province":"MO",
    "sg:tags":[
        "electrical",
        "contractor"
    ],
    "wof:name":"Amptron Electric Company Inc",
    "wof:placetype":"venue"
},
  "geometry": {"coordinates":[-90.343535,38.533135],"type":"Point"}
}