{
  "type": "Feature",
  "properties": {
    "iso:country":"US",
    "sg:address":"203 E Dunklin St",
    "sg:city":"Jefferson City",
    "sg:classifiers":[
        {
            "category":"Organizations",
            "subcategory":"Religious Organization",
            "type":"Services"
        }
    ],
    "sg:phone":"+1 573 635 9544",
    "sg:postcode":"65101",
    "sg:province":"MO",
    "sg:tags":[
        "church"
    ],
    "wof:name":"VIP ASSAA Buddhist Church",
    "wof:placetype":"venue"
},
  "geometry": {"coordinates":[-92.175764,38.57205],"type":"Point"}
}