{
  "type": "Feature",
  "properties": {
    "iso:country":"US",
    "sg:address":"2725 Clifton Ave",
    "sg:city":"St Louis",
    "sg:classifiers":[
        {
            "category":"Organizations",
            "subcategory":"Labor Organization",
            "type":"Services"
        }
    ],
    "sg:phone":"+1 314 647 9950",
    "sg:postcode":"63139",
    "sg:province":"MO",
    "wof:name":"Service Employees Int Union Lo",
    "wof:placetype":"venue"
},
  "geometry": {"coordinates":[-90.29249,38.611916],"type":"Point"}
}