{
  "type": "Feature",
  "properties": {
    "iso:country":"US",
    "sg:address":"3709 Gumtree Ln",
    "sg:city":"Saint Louis",
    "sg:classifiers":[
        {
            "category":"Social Services",
            "subcategory":"Child Care",
            "type":"Services"
        }
    ],
    "sg:phone":"+1 314 894 0934",
    "sg:postcode":"63129",
    "sg:province":"MO",
    "sg:tags":[
        "day"
    ],
    "wof:name":"A Child Is A Child Inc",
    "wof:placetype":"venue"
},
  "geometry": {"coordinates":[-90.347973,38.473088],"type":"Point"}
}