{
  "type": "Feature",
  "properties": {
    "iso:country":"US",
    "sg:address":"3922 NE Chouteau Trfy",
    "sg:city":"Kansas City",
    "sg:classifiers":[
        {
            "category":"Professional",
            "subcategory":"Accounting & Tax Preparation",
            "type":"Services"
        }
    ],
    "sg:phone":"+1 816 455 4444",
    "sg:postcode":"64117",
    "sg:province":"MO",
    "sg:tags":[
        "return",
        "filing"
    ],
    "wof:name":"Liberty Tax Svc",
    "wof:placetype":"venue"
},
  "geometry": {"coordinates":[-94.532207,39.165815],"type":"Point"}
}