{
  "type": "Feature",
  "properties": {
    "iso:country":"US",
    "sg:address":"578 Weslee Ln",
    "sg:city":"Galena",
    "sg:classifiers":[
        {
            "category":"Manufacturing",
            "subcategory":"Lumber",
            "type":"Manufacturing & Wholesale Goods"
        }
    ],
    "sg:phone":"+1 417 272 8462",
    "sg:postcode":"65656",
    "sg:province":"MO",
    "sg:tags":[
        "sawmill"
    ],
    "wof:name":"Jim's Portable Sawmill",
    "wof:placetype":"venue"
},
  "geometry": {"coordinates":[-93.439305,36.700007],"type":"Point"}
}