{
  "type": "Feature",
  "properties": {
    "iso:country":"US",
    "sg:address":"4132 Shore Line Dr",
    "sg:city":"Earth City",
    "sg:classifiers":[
        {
            "category":"Professional",
            "subcategory":"Advertising",
            "type":"Services"
        }
    ],
    "sg:phone":"+1 314 209 7533",
    "sg:postcode":"63044",
    "sg:province":"MO",
    "wof:name":"Canon House Ltd",
    "wof:placetype":"venue"
},
  "geometry": {"coordinates":[-90.467843,38.767289],"type":"Point"}
}