{
  "type": "Feature",
  "properties": {
    "iso:country":"US",
    "sg:address":"32876 State Hwy 25",
    "sg:city":"Advance",
    "sg:classifiers":[
        {
            "category":"Wholesale",
            "subcategory":"Farm Supplies",
            "type":"Manufacturing & Wholesale Goods"
        }
    ],
    "sg:phone":"+1 573 722 3923",
    "sg:postcode":"63730",
    "sg:province":"MO",
    "wof:name":"Southeast Cooperative Svc Co",
    "wof:placetype":"venue"
},
  "geometry": {"coordinates":[-89.90454800000001,37.092975],"type":"Point"}
}