{
  "type": "Feature",
  "properties": {
    "iso:country":"US",
    "sg:address":"215 E McClurg St",
    "sg:city":"Richland",
    "sg:classifiers":[
        {
            "category":"Food & Beverages",
            "subcategory":"Liquor & Beverages",
            "type":"Retail Goods"
        }
    ],
    "sg:phone":"+1 573 765 4420",
    "sg:postcode":"65556",
    "sg:province":"MO",
    "wof:name":"B & B Package Store",
    "wof:placetype":"venue"
},
  "geometry": {"coordinates":[-92.40256599999999,37.855126],"type":"Point"}
}