{
  "type": "Feature",
  "properties": {
    "iso:country":"US",
    "sg:address":"10 Southern Hills Ct",
    "sg:city":"O Fallon",
    "sg:classifiers":[
        {
            "category":"Banks & Credit Unions",
            "subcategory":"Bank",
            "type":"Services"
        }
    ],
    "sg:phone":"+1 636 240 0291",
    "sg:postcode":"63366",
    "sg:province":"MO",
    "sg:tags":[
        "mortgage"
    ],
    "wof:name":"Ksm Group LLC",
    "wof:placetype":"venue"
},
  "geometry": {"coordinates":[-90.72308,38.794593],"type":"Point"}
}