{
  "type": "Feature",
  "properties": {
    "iso:country":"US",
    "sg:address":"7777 Watson Rd",
    "sg:city":"St Louis",
    "sg:classifiers":[
        {
            "category":"Shopping",
            "type":"Retail Goods"
        },
        {
            "category":"Shopping",
            "subcategory":"Bicycles & Sporting Goods",
            "type":"Retail Goods"
        }
    ],
    "sg:phone":"+1 314 918 9484",
    "sg:postcode":"63119",
    "sg:province":"MO",
    "sg:tags":[
        "apparel",
        "bowling",
        "merchandise",
        "accessory"
    ],
    "wof:name":"Bowl TS Bowling & Trophy Shop",
    "wof:placetype":"venue"
},
  "geometry": {"coordinates":[-90.33475300000001,38.571869],"type":"Point"}
}