{
  "type": "Feature",
  "properties": {
    "iso:country":"US",
    "sg:address":"208 W Coler St",
    "sg:city":"Neosho",
    "sg:classifiers":[
        {
            "category":"Professional",
            "subcategory":"Lawyer & Legal Services",
            "type":"Services"
        }
    ],
    "sg:phone":"+1 417 659 2940",
    "sg:postcode":"64850",
    "sg:province":"MO",
    "wof:name":"Prosecuting Attorneys Office",
    "wof:placetype":"venue"
},
  "geometry": {"coordinates":[-94.370679,36.872746],"type":"Point"}
}