{
  "type": "Feature",
  "properties": {
    "iso:country":"US",
    "sg:address":"2225 E 67 Ter",
    "sg:city":"Kansas City",
    "sg:classifiers":[
        {
            "category":"Local Transit",
            "type":"Transportation"
        }
    ],
    "sg:phone":"+1 816 822 7919",
    "sg:postcode":"64132",
    "sg:province":"MO",
    "sg:tags":[
        "passenger"
    ],
    "wof:name":"Adriene Exclusive Limousines",
    "wof:placetype":"venue"
},
  "geometry": {"coordinates":[-94.560503,39.004481],"type":"Point"}
}