{
  "type": "Feature",
  "properties": {
    "iso:country":"US",
    "sg:address":"212 Camelot Dr",
    "sg:city":"Saint Charles",
    "sg:classifiers":[
        {
            "category":"Manufacturing",
            "subcategory":"Signs",
            "type":"Manufacturing & Wholesale Goods"
        }
    ],
    "sg:phone":"+1 636 300 0552",
    "sg:postcode":"63304",
    "sg:province":"MO",
    "sg:tags":[
        "specialty",
        "mfg"
    ],
    "wof:name":"Marketching Solutions",
    "wof:placetype":"venue"
},
  "geometry": {"coordinates":[-90.64944199999999,38.71001],"type":"Point"}
}