{
  "type": "Feature",
  "properties": {
    "iso:country":"US",
    "sg:address":"11820 Tesson Ferry Rd",
    "sg:city":"St Louis",
    "sg:classifiers":[
        {
            "category":"Professional",
            "subcategory":"Lawyer & Legal Services",
            "type":"Services"
        }
    ],
    "sg:phone":"+1 314 729 1943",
    "sg:postcode":"63128",
    "sg:province":"MO",
    "sg:tags":[
        "attorney"
    ],
    "wof:name":"Shelton & Madrid Attys At Law",
    "wof:placetype":"venue"
},
  "geometry": {"coordinates":[-90.362787,38.51982],"type":"Point"}
}