{
  "type": "Feature",
  "properties": {
    "iso:country":"US",
    "sg:address":"901 Main St",
    "sg:city":"Blue Springs",
    "sg:classifiers":[
        {
            "category":"Professional",
            "subcategory":"Lawyer & Legal Services",
            "type":"Services"
        }
    ],
    "sg:phone":"+1 816 228 6400",
    "sg:postcode":"64015",
    "sg:province":"MO",
    "sg:tags":[
        "attorney"
    ],
    "wof:name":"Tyree Eskew & Roberts LC",
    "wof:placetype":"venue"
},
  "geometry": {"coordinates":[-94.27678299999999,39.018346],"type":"Point"}
}