{
  "type": "Feature",
  "properties": {
    "iso:country":"US",
    "sg:address":"422 E Broadway St",
    "sg:city":"Monett",
    "sg:classifiers":[
        {
            "category":"Personal",
            "subcategory":"Beauty Salon",
            "type":"Services"
        }
    ],
    "sg:phone":"+1 417 236 9010",
    "sg:postcode":"65708",
    "sg:province":"MO",
    "sg:tags":[
        "shop"
    ],
    "wof:name":"Yolanda Soto",
    "wof:placetype":"venue"
},
  "geometry": {"coordinates":[-93.92236,36.921161],"type":"Point"}
}