{
  "type": "Feature",
  "properties": {
    "iso:country":"US",
    "sg:address":"6700 E 58 St",
    "sg:city":"Kansas City",
    "sg:classifiers":[
        {
            "category":"Social Services",
            "subcategory":"Child Care",
            "type":"Services"
        }
    ],
    "sg:phone":"+1 816 921 8484",
    "sg:postcode":"64129",
    "sg:province":"MO",
    "wof:name":"Manners Matter Child Care",
    "wof:placetype":"venue"
},
  "geometry": {"coordinates":[-94.506698,39.020021],"type":"Point"}
}