{
  "type": "Feature",
  "properties": {
    "iso:country":"US",
    "sg:address":"12820 E 47 St S",
    "sg:city":"Independence",
    "sg:classifiers":[
        {
            "category":"Personal",
            "subcategory":"Beauty Salon",
            "type":"Services"
        }
    ],
    "sg:phone":"+1 816 313 2633",
    "sg:postcode":"64055",
    "sg:province":"MO",
    "sg:tags":[
        "shop"
    ],
    "wof:name":"Soothing Moments Day Spa",
    "wof:placetype":"venue"
},
  "geometry": {"coordinates":[-94.42681,39.036154],"type":"Point"}
}