{
  "type": "Feature",
  "properties": {
    "iso:country":"US",
    "sg:address":"19900 E Jackson Dr",
    "sg:city":"Independence",
    "sg:classifiers":[
        {
            "category":"Food & Beverages",
            "subcategory":"Groceries & Convenience Stores",
            "type":"Retail Goods"
        }
    ],
    "sg:phone":"+1 816 795 6700",
    "sg:postcode":"64057",
    "sg:province":"MO",
    "sg:tags":[
        "market"
    ],
    "wof:name":"Cost Plus World Market",
    "wof:placetype":"venue"
},
  "geometry": {"coordinates":[-94.346537,39.041749],"type":"Point"}
}