{
  "type": "Feature",
  "properties": {
    "iso:country":"US",
    "sg:address":"721 Foxx Dr",
    "sg:city":"Nixa",
    "sg:classifiers":[
        {
            "category":"Building & Trades",
            "subcategory":"Construction",
            "type":"Services"
        }
    ],
    "sg:phone":"+1 417 725 4668",
    "sg:postcode":"65714",
    "sg:province":"MO",
    "sg:tags":[
        "house"
    ],
    "wof:name":"Strode Remodeling",
    "wof:placetype":"venue"
},
  "geometry": {"coordinates":[-93.325423,37.026776],"type":"Point"}
}