{
  "type": "Feature",
  "properties": {
    "iso:country":"US",
    "sg:address":"1814 E Ohio St",
    "sg:city":"Clinton",
    "sg:classifiers":[
        {
            "category":"Shopping",
            "subcategory":"Clothing, Apparel, & Fashions",
            "type":"Retail Goods"
        }
    ],
    "sg:phone":"+1 660 885 9500",
    "sg:postcode":"64735",
    "sg:province":"MO",
    "sg:tags":[
        "garment"
    ],
    "wof:name":"Fairy Tales Children's Apparel",
    "wof:placetype":"venue"
},
  "geometry": {"coordinates":[-93.748518,38.366073],"type":"Point"}
}