{
  "type": "Feature",
  "properties": {
    "iso:country":"US",
    "sg:address":"169 State Hwy 100",
    "sg:city":"Hermann",
    "sg:classifiers":[
        {
            "category":"Home & Garden",
            "subcategory":"Garden Supply",
            "type":"Retail Goods"
        }
    ],
    "sg:phone":"+1 573 486 8849",
    "sg:postcode":"65041",
    "sg:province":"MO",
    "sg:tags":[
        "nurseryman"
    ],
    "wof:name":"Creekside Nursery Inc",
    "wof:placetype":"venue"
},
  "geometry": {"coordinates":[-91.436008,38.706987],"type":"Point"}
}