{
  "type": "Feature",
  "properties": {
    "iso:country":"US",
    "sg:address":"8043 State Hwy Tt",
    "sg:city":"Clarence",
    "sg:classifiers":[
        {
            "category":"Farming",
            "subcategory":"Livestock Farm",
            "type":"Manufacturing & Wholesale Goods"
        }
    ],
    "sg:phone":"+1 660 699 3602",
    "sg:postcode":"63437",
    "sg:province":"MO",
    "sg:tags":[
        "beef",
        "feedlot",
        "cattle"
    ],
    "wof:name":"Lyle Tracy",
    "wof:placetype":"venue"
},
  "geometry": {"coordinates":[-92.18504900000001,39.663589],"type":"Point"}
}