{
  "type": "Feature",
  "properties": {
    "iso:country":"US",
    "sg:address":"17538 Manchester Rd",
    "sg:city":"Glencoe",
    "sg:classifiers":[
        {
            "category":"Building & Trades",
            "subcategory":"Electrical",
            "type":"Services"
        }
    ],
    "sg:phone":"+1 636 458 3658",
    "sg:postcode":"63038",
    "sg:province":"MO",
    "sg:tags":[
        "work",
        "electrical",
        "contractor"
    ],
    "wof:name":"Lindsey Electric Inc",
    "wof:placetype":"venue"
},
  "geometry": {"coordinates":[-90.66726800000001,38.583217],"type":"Point"}
}