{
  "type": "Feature",
  "properties": {
    "iso:country":"US",
    "sg:address":"5196 W Farm Rd 54",
    "sg:city":"Willard",
    "sg:classifiers":[
        {
            "category":"Manufacturing",
            "subcategory":"Furniture",
            "type":"Manufacturing & Wholesale Goods"
        },
        {
            "category":"Home & Garden",
            "subcategory":"Furniture",
            "type":"Retail Goods"
        }
    ],
    "sg:phone":"+1 417 742 2072",
    "sg:postcode":"65781",
    "sg:province":"MO",
    "sg:tags":[
        "mfg",
        "top",
        "wood",
        "counter"
    ],
    "wof:name":"Fine Designs",
    "wof:placetype":"venue"
},
  "geometry": {"coordinates":[-93.382441,37.345589],"type":"Point"}
}