{
  "type": "Feature",
  "properties": {
    "iso:country":"US",
    "sg:address":"413 W Reed St",
    "sg:city":"Moberly",
    "sg:classifiers":[
        {
            "category":"Shopping",
            "subcategory":"Florist",
            "type":"Retail Goods"
        }
    ],
    "sg:phone":"+1 660 263 6286",
    "sg:postcode":"65270",
    "sg:province":"MO",
    "wof:name":"Tedford Florists",
    "wof:placetype":"venue"
},
  "geometry": {"coordinates":[-92.44134099999999,39.419837],"type":"Point"}
}