{
  "type": "Feature",
  "properties": {
    "iso:country":"US",
    "sg:address":"319 N 4th St",
    "sg:city":"St Louis",
    "sg:classifiers":[
        {
            "category":"Professional",
            "subcategory":"Lawyer & Legal Services",
            "type":"Services"
        }
    ],
    "sg:phone":"+1 314 436 0030",
    "sg:postcode":"63102",
    "sg:province":"MO",
    "sg:tags":[
        "attorney"
    ],
    "wof:name":"Francis H Kennedy",
    "wof:placetype":"venue"
},
  "geometry": {"coordinates":[-90.187726,38.62808],"type":"Point"}
}