{
  "type": "Feature",
  "properties": {
    "iso:country":"US",
    "sg:address":"4 N Iron St",
    "sg:city":"Salem",
    "sg:classifiers":[
        {
            "category":"Insurance",
            "subcategory":"Insurance Agent",
            "type":"Services"
        }
    ],
    "sg:phone":"+1 573 729 3326",
    "sg:postcode":"65560",
    "sg:province":"MO",
    "wof:name":"Bob Webber Ins Agency",
    "wof:placetype":"venue"
},
  "geometry": {"coordinates":[-91.535117,37.643723],"type":"Point"}
}