{
  "type": "Feature",
  "properties": {
    "iso:country":"US",
    "sg:address":"314 Kentucky St",
    "sg:city":"West Plains",
    "sg:classifiers":[
        {
            "category":"Health Services",
            "subcategory":"Doctor",
            "type":"Services"
        }
    ],
    "sg:phone":"+1 417 255 8337",
    "sg:postcode":"65775",
    "sg:province":"MO",
    "sg:tags":[
        "physician",
        "surgeon"
    ],
    "wof:name":"Urology Center Of West Plains",
    "wof:placetype":"venue"
},
  "geometry": {"coordinates":[-91.87626899999999,36.731733],"type":"Point"}
}