{
  "type": "Feature",
  "properties": {
    "iso:country":"US",
    "sg:address":"3628 Diamond Head Dr",
    "sg:city":"Saint Louis",
    "sg:classifiers":[
        {
            "category":"Professional",
            "type":"Services"
        }
    ],
    "sg:phone":"+1 314 892 6807",
    "sg:postcode":"63125",
    "sg:province":"MO",
    "wof:name":"Kathryns of St Louis",
    "wof:placetype":"venue"
},
  "geometry": {"coordinates":[-90.32690100000001,38.511581],"type":"Point"}
}