{
  "type": "Feature",
  "properties": {
    "iso:country":"US",
    "sg:address":"806 S 40th St",
    "sg:city":"Saint Joseph",
    "sg:classifiers":[
        {
            "category":"Wholesale",
            "subcategory":"Apparel",
            "type":"Manufacturing & Wholesale Goods"
        }
    ],
    "sg:phone":"+1 816 364 2233",
    "sg:postcode":"64507",
    "sg:province":"MO",
    "sg:tags":[
        "clothing"
    ],
    "wof:name":"Ryno Sports",
    "wof:placetype":"venue"
},
  "geometry": {"coordinates":[-94.797747,39.758612],"type":"Point"}
}