{
  "type": "Feature",
  "properties": {
    "iso:country":"US",
    "sg:address":"420 Remington Plaza Ct",
    "sg:city":"Raymore",
    "sg:classifiers":[
        {
            "category":"Insurance",
            "subcategory":"Insurance Agent",
            "type":"Services"
        },
        {
            "category":"Insurance",
            "subcategory":"Hazard Insurance",
            "type":"Services"
        },
        {
            "category":"Insurance",
            "subcategory":"Title Insurance",
            "type":"Services"
        },
        {
            "category":"Insurance",
            "subcategory":"Life Insurance",
            "type":"Services"
        }
    ],
    "sg:phone":"+1 816 322 2888",
    "sg:postcode":"64083",
    "sg:province":"MO",
    "sg:tags":[
        "business",
        "auto",
        "commercial",
        "homeowner",
        "motorcycle",
        "renter"
    ],
    "wof:name":"Allstate Insurance Company - Terry Mammen",
    "wof:placetype":"venue"
},
  "geometry": {"coordinates":[-94.47192699999999,38.812965],"type":"Point"}
}