{
  "type": "Feature",
  "properties": {
    "iso:country":"US",
    "sg:address":"809 NE Colleen Dr",
    "sg:city":"Lees Summit",
    "sg:classifiers":[
        {
            "category":"Building & Trades",
            "subcategory":"Construction",
            "type":"Services"
        }
    ],
    "sg:phone":"+1 816 347 8645",
    "sg:postcode":"64086",
    "sg:province":"MO",
    "sg:tags":[
        "house"
    ],
    "wof:name":"Blc Remodeling & Repair",
    "wof:placetype":"venue"
},
  "geometry": {"coordinates":[-94.342116,38.926464],"type":"Point"}
}