{
  "type": "Feature",
  "properties": {
    "iso:country":"US",
    "sg:address":"24298 210th St",
    "sg:city":"Gallatin",
    "sg:classifiers":[
        {
            "category":"Farming",
            "subcategory":"Farm",
            "type":"Manufacturing & Wholesale Goods"
        }
    ],
    "sg:phone":"+1 660 663 3235",
    "sg:postcode":"64640",
    "sg:province":"MO",
    "sg:tags":[
        "crop",
        "general"
    ],
    "wof:name":"Robert Bird",
    "wof:placetype":"venue"
},
  "geometry": {"coordinates":[-94.00550800000001,39.923625],"type":"Point"}
}