{
  "type": "Feature",
  "properties": {
    "iso:country":"US",
    "sg:address":"108 N 16th St",
    "sg:city":"St Joseph",
    "sg:classifiers":[
        {
            "category":"Social Services",
            "subcategory":"Adult Care",
            "type":"Services"
        },
        {
            "category":"Health Services",
            "subcategory":"Nursing And Care Facility",
            "type":"Services"
        }
    ],
    "sg:phone":"+1 816 233 9623",
    "sg:postcode":"64501",
    "sg:province":"MO",
    "sg:tags":[
        "home",
        "retirement",
        "community",
        "residential"
    ],
    "wof:name":"Nesa House",
    "wof:placetype":"venue"
},
  "geometry": {"coordinates":[-94.841292,39.767407],"type":"Point"}
}