{
  "type": "Feature",
  "properties": {
    "iso:country":"US",
    "sg:address":"1387 Co Rd K",
    "sg:city":"Clark",
    "sg:phone":"+1 573 641 5283",
    "sg:postcode":"65254",
    "sg:province":"MO",
    "sg:tags":[
        "farm",
        "corn",
        "wheat",
        "soybean"
    ],
    "wof:name":"Sammie Asbury",
    "wof:placetype":"venue"
},
  "geometry": {"coordinates":[-92.907066,39.10653],"type":"Point"}
}