{
  "type": "Feature",
  "properties": {
    "iso:country":"US",
    "sg:address":"11224 Big Bend Rd",
    "sg:city":"Saint Louis",
    "sg:classifiers":[
        {
            "category":"Manufacturing",
            "subcategory":"Printing",
            "type":"Manufacturing & Wholesale Goods"
        }
    ],
    "sg:phone":"+1 314 821 0809",
    "sg:postcode":"63122",
    "sg:province":"MO",
    "sg:tags":[
        "commercial"
    ],
    "wof:name":"Custom Cards",
    "wof:placetype":"venue"
},
  "geometry": {"coordinates":[-90.418104,38.566811],"type":"Point"}
}