{
  "type": "Feature",
  "properties": {
    "iso:country":"US",
    "sg:address":"100 Miller St",
    "sg:city":"New Haven",
    "sg:classifiers":[
        {
            "category":"Government",
            "subcategory":"Fire Station",
            "type":"Public Place"
        }
    ],
    "sg:phone":"+1 573 237 3229",
    "sg:postcode":"63068",
    "sg:province":"MO",
    "sg:tags":[
        "department"
    ],
    "wof:name":"New Haven Fire Dept",
    "wof:placetype":"venue"
},
  "geometry": {"coordinates":[-91.21506100000001,38.603289],"type":"Point"}
}