{
  "type": "Feature",
  "properties": {
    "iso:country":"US",
    "sg:address":"409 S Grand Ave",
    "sg:city":"Salisbury",
    "sg:classifiers":[
        {
            "category":"Retail",
            "subcategory":"Animal Services",
            "type":"Services"
        }
    ],
    "sg:phone":"+1 660 222 3276",
    "sg:postcode":"65281",
    "sg:province":"MO",
    "sg:tags":[
        "pet",
        "boarding",
        "sitting"
    ],
    "wof:name":"Middlefork Kennels",
    "wof:placetype":"venue"
},
  "geometry": {"coordinates":[-92.79995,39.421683],"type":"Point"}
}