{
  "type": "Feature",
  "properties": {
    "iso:country":"US",
    "sg:address":"15275 New Halls Ferry Rd",
    "sg:city":"Florissant",
    "sg:classifiers":[
        {
            "category":"Recreation",
            "type":"Entertainment"
        }
    ],
    "sg:phone":"+1 314 837 4909",
    "sg:postcode":"63031",
    "sg:province":"MO",
    "sg:tags":[
        "club",
        "membership"
    ],
    "wof:name":"Wedgwood Bath & Tennis Club",
    "wof:placetype":"venue"
},
  "geometry": {"coordinates":[-90.30807799999999,38.82317],"type":"Point"}
}