{
  "type": "Feature",
  "properties": {
    "iso:country":"US",
    "sg:address":"852 Co Rd 263",
    "sg:city":"Auxvasse",
    "sg:phone":"+1 573 387 4492",
    "sg:postcode":"65231",
    "sg:province":"MO",
    "sg:tags":[
        "farm",
        "field",
        "crop"
    ],
    "wof:name":"Terry Eckley",
    "wof:placetype":"venue"
},
  "geometry": {"coordinates":[-92.031773,39.034048],"type":"Point"}
}