{
  "type": "Feature",
  "properties": {
    "iso:country":"US",
    "sg:address":"7661 Hwy P",
    "sg:city":"Neosho",
    "sg:classifiers":[
        {
            "category":"Professional",
            "subcategory":"Accounting & Tax Preparation",
            "type":"Services"
        }
    ],
    "sg:phone":"+1 417 624 7210",
    "sg:postcode":"64850",
    "sg:province":"MO",
    "wof:name":"Bookkeeping Specialists",
    "wof:placetype":"venue"
},
  "geometry": {"coordinates":[-94.50615500000001,36.953694],"type":"Point"}
}