{
  "type": "Feature",
  "properties": {
    "iso:country":"US",
    "sg:address":"33 Rio Vista Dr",
    "sg:city":"Saint Louis",
    "sg:classifiers":[
        {
            "category":"Professional",
            "subcategory":"Business Services",
            "type":"Services"
        }
    ],
    "sg:phone":"+1 314 997 7843",
    "sg:postcode":"63124",
    "sg:province":"MO",
    "wof:name":"Lois Levy Interiors",
    "wof:placetype":"venue"
},
  "geometry": {"coordinates":[-90.36968299999999,38.655868],"type":"Point"}
}