{
  "type": "Feature",
  "properties": {
    "iso:country":"US",
    "sg:address":"1302 E Elm St",
    "sg:city":"Springfield",
    "sg:classifiers":[
        {
            "category":"Real Estate",
            "subcategory":"Real Estate Operator",
            "type":"Services"
        }
    ],
    "sg:phone":"+1 417 862 8341",
    "sg:postcode":"65802",
    "sg:province":"MO",
    "sg:tags":[
        "building",
        "apartment"
    ],
    "wof:name":"Cherry Plaza",
    "wof:placetype":"venue"
},
  "geometry": {"coordinates":[-93.27117200000001,37.204956],"type":"Point"}
}