{
  "type": "Feature",
  "properties": {
    "iso:country":"US",
    "sg:address":"368 S Prairie St",
    "sg:city":"East Prairie",
    "sg:classifiers":[
        {
            "category":"Professional",
            "subcategory":"Business Services",
            "type":"Services"
        }
    ],
    "sg:phone":"+1 573 649 3874",
    "sg:postcode":"63825",
    "sg:province":"MO",
    "wof:name":"Wolford Brothers",
    "wof:placetype":"venue"
},
  "geometry": {"coordinates":[-89.929299,36.88414],"type":"Point"}
}