{
  "type": "Feature",
  "properties": {
    "iso:country":"US",
    "sg:address":"215 W 18 St",
    "sg:city":"Kansas City",
    "sg:classifiers":[
        {
            "category":"Professional",
            "subcategory":"Lawyer & Legal Services",
            "type":"Services"
        }
    ],
    "sg:phone":"+1 816 931 7797",
    "sg:postcode":"64108",
    "sg:province":"MO",
    "sg:tags":[
        "attorney"
    ],
    "wof:name":"James E Martin Law Office",
    "wof:placetype":"venue"
},
  "geometry": {"coordinates":[-94.58722299999999,39.091825],"type":"Point"}
}