{
  "type": "Feature",
  "properties": {
    "iso:country":"US",
    "sg:address":"405 W Washington Blvd",
    "sg:city":"Cuba",
    "sg:classifiers":[
        {
            "category":"Health Services",
            "subcategory":"Doctor",
            "type":"Services"
        }
    ],
    "sg:phone":"+1 573 885 2142",
    "sg:postcode":"65453",
    "sg:province":"MO",
    "sg:tags":[
        "dentist"
    ],
    "wof:name":"Cuba Dental Center Inc",
    "wof:placetype":"venue"
},
  "geometry": {"coordinates":[-91.405706,38.062283],"type":"Point"}
}