{
  "type": "Feature",
  "properties": {
    "addr:full":"321 N Kansas Ave Marceline MO 64658",
    "addr:housenumber":"321",
    "addr:postcode":"64658",
    "addr:street":"N Kansas Ave",
    "iso:country":"US",
    "sg:address":"321 N Kansas Ave",
    "sg:city":"Marceline",
    "sg:classifiers":[
        {
            "category":"Organizations",
            "subcategory":"Religious Organization",
            "type":"Services"
        }
    ],
    "sg:phone":"+1 660 376 2444",
    "sg:postcode":"64658",
    "sg:province":"MO",
    "wof:name":"United Methodist Church",
    "wof:placetype":"venue"
},
  "geometry": {"coordinates":[-92.949133,39.716956],"type":"Point"}
}