{
  "type": "Feature",
  "properties": {
    "iso:country":"US",
    "sg:address":"1113 Shady Pine St",
    "sg:city":"Joplin",
    "sg:classifiers":[
        {
            "category":"Building & Trades",
            "subcategory":"Plumbing",
            "type":"Services"
        }
    ],
    "sg:phone":"+1 417 626 8424",
    "sg:postcode":"64801",
    "sg:province":"MO",
    "sg:tags":[
        "contractor"
    ],
    "wof:name":"Springers Remodeling & HM Repr",
    "wof:placetype":"venue"
},
  "geometry": {"coordinates":[-94.55792700000001,37.080067],"type":"Point"}
}