{
  "type": "Feature",
  "properties": {
    "iso:country":"US",
    "sg:address":"11939 Manchester Rd",
    "sg:city":"St Louis",
    "sg:classifiers":[
        {
            "category":"Professional",
            "subcategory":"Lawyer & Legal Services",
            "type":"Services"
        }
    ],
    "sg:phone":"+1 314 822 8558",
    "sg:postcode":"63131",
    "sg:province":"MO",
    "sg:tags":[
        "attorney"
    ],
    "wof:name":"Patrick D Kelly",
    "wof:placetype":"venue"
},
  "geometry": {"coordinates":[-90.43433400000001,38.601652],"type":"Point"}
}