{
  "type": "Feature",
  "properties": {
    "addr:full":"12038 Blue Ridge Exd Grandview MO 64030",
    "addr:housenumber":"12038",
    "addr:postcode":"64030",
    "addr:street":"Blue Ridge Exd",
    "iso:country":"US",
    "sg:address":"12038 Blue Ridge Exd",
    "sg:city":"Grandview",
    "sg:classifiers":[
        {
            "category":"Personal",
            "subcategory":"Beauty Salon",
            "type":"Services"
        }
    ],
    "sg:phone":"+1 816 767 8877",
    "sg:postcode":"64030",
    "sg:province":"MO",
    "sg:tags":[
        "manicuring"
    ],
    "wof:name":"Foxy Nails",
    "wof:placetype":"venue"
},
  "geometry": {"coordinates":[-94.529285,38.904793],"type":"Point"}
}