{
  "type": "Feature",
  "properties": {
    "iso:country":"US",
    "sg:address":"2615 Hampton Ave",
    "sg:city":"Saint Louis",
    "sg:classifiers":[
        {
            "category":"Professional",
            "subcategory":"Employment Agencies",
            "type":"Services"
        }
    ],
    "sg:phone":"+1 314 353 4060",
    "sg:postcode":"63139",
    "sg:province":"MO",
    "sg:website":"www.southsidetemporaries.com",
    "wof:name":"Southside Temporaries",
    "wof:placetype":"venue"
},
  "geometry": {"coordinates":[-90.288435,38.610999],"type":"Point"}
}