{
  "type": "Feature",
  "properties": {
    "iso:country":"US",
    "sg:address":"2122 Oaklawn Dr",
    "sg:city":"Chillicothe",
    "sg:classifiers":[
        {
            "category":"Real Estate",
            "subcategory":"Real Estate Agent",
            "type":"Services"
        }
    ],
    "sg:phone":"+1 660 646 5030",
    "sg:postcode":"64601",
    "sg:province":"MO",
    "wof:name":"Burton Real Estate",
    "wof:placetype":"venue"
},
  "geometry": {"coordinates":[-93.560968,39.811055],"type":"Point"}
}