{
  "type": "Feature",
  "properties": {
    "iso:country":"US",
    "sg:address":"2825 S Glenstone Ave",
    "sg:city":"Springfield",
    "sg:classifiers":[
        {
            "category":"Shopping",
            "subcategory":"Clothing, Apparel, & Fashions",
            "type":"Retail Goods"
        }
    ],
    "sg:phone":"+1 417 890 6811",
    "sg:postcode":"65804",
    "sg:province":"MO",
    "sg:tags":[
        "infant",
        "wear"
    ],
    "sg:website":"www.limitedtoo.com",
    "wof:name":"Limited Too",
    "wof:placetype":"venue"
},
  "geometry": {"coordinates":[-93.262649,37.160053],"type":"Point"}
}