{
  "type": "Feature",
  "properties": {
    "iso:country":"US",
    "sg:address":"102 Crystal Springs Ct",
    "sg:city":"Chesterfield",
    "sg:classifiers":[
        {
            "category":"Shopping",
            "subcategory":"Pets & Pet Supplies",
            "type":"Retail Goods"
        }
    ],
    "sg:phone":"+1 636 530 7133",
    "sg:postcode":"63005",
    "sg:province":"MO",
    "sg:tags":[
        "specialty"
    ],
    "wof:name":"Fabick Cat",
    "wof:placetype":"venue"
},
  "geometry": {"coordinates":[-90.593273,38.660473],"type":"Point"}
}