{
  "type": "Feature",
  "properties": {
    "iso:country":"US",
    "sg:address":"371 State Hwy M",
    "sg:city":"Everton",
    "sg:classifiers":[
        {
            "category":"Building & Trades",
            "subcategory":"Construction",
            "type":"Services"
        }
    ],
    "sg:phone":"+1 417 751 2221",
    "sg:postcode":"65646",
    "sg:province":"MO",
    "sg:tags":[
        "general",
        "contractor"
    ],
    "wof:name":"IPC",
    "wof:placetype":"venue"
},
  "geometry": {"coordinates":[-93.710809,37.279579],"type":"Point"}
}