{
  "type": "Feature",
  "properties": {
    "iso:country":"US",
    "sg:address":"7668 Lindbergh Dr",
    "sg:city":"Saint Louis",
    "sg:classifiers":[
        {
            "category":"Building & Trades",
            "subcategory":"Landscaping Services",
            "type":"Services"
        }
    ],
    "sg:phone":"+1 314 644 3252",
    "sg:postcode":"63117",
    "sg:province":"MO",
    "sg:tags":[
        "landscape"
    ],
    "wof:name":"Griesedieck Bros Landscap",
    "wof:placetype":"venue"
},
  "geometry": {"coordinates":[-90.32402399999999,38.624246],"type":"Point"}
}