{
  "type": "Feature",
  "properties": {
    "iso:country":"US",
    "sg:address":"1239 Cheverly Ct",
    "sg:city":"Saint Louis",
    "sg:classifiers":[
        {
            "category":"Professional",
            "type":"Services"
        }
    ],
    "sg:phone":"+1 314 434 6932",
    "sg:postcode":"63146",
    "sg:province":"MO",
    "sg:tags":[
        "technical",
        "writing"
    ],
    "wof:name":"Technical Writing",
    "wof:placetype":"venue"
},
  "geometry": {"coordinates":[-90.455613,38.680941],"type":"Point"}
}