{
  "type": "Feature",
  "properties": {
    "iso:country":"US",
    "sg:address":"105 E 5 St",
    "sg:city":"Kansas City",
    "sg:classifiers":[
        {
            "category":"Professional",
            "subcategory":"Lawyer & Legal Services",
            "type":"Services"
        }
    ],
    "sg:phone":"+1 816 474 3113",
    "sg:postcode":"64106",
    "sg:province":"MO",
    "sg:tags":[
        "attorney"
    ],
    "wof:name":"Mc Cormick Adam & Long",
    "wof:placetype":"venue"
},
  "geometry": {"coordinates":[-94.58050299999999,39.108695],"type":"Point"}
}