{
  "type": "Feature",
  "properties": {
    "iso:country":"US",
    "sg:address":"114 N Polk St",
    "sg:city":"Albany",
    "sg:classifiers":[
        {
            "category":"Bars & Pubs",
            "type":"Food & Drink"
        }
    ],
    "sg:phone":"+1 660 726 4169",
    "sg:postcode":"64402",
    "sg:province":"MO",
    "sg:tags":[
        "drinking"
    ],
    "wof:name":"Raedell's Hideaway",
    "wof:placetype":"venue"
},
  "geometry": {"coordinates":[-94.333707,40.248479],"type":"Point"}
}