{
  "type": "Feature",
  "properties": {
    "iso:country":"US",
    "sg:address":"7375 Shaftesbury Ave",
    "sg:city":"St Louis",
    "sg:classifiers":[
        {
            "category":"Shopping",
            "subcategory":"Bicycles & Sporting Goods",
            "type":"Retail Goods"
        }
    ],
    "sg:phone":"+1 314 862 4041",
    "sg:postcode":"63130",
    "sg:province":"MO",
    "sg:tags":[
        "bike"
    ],
    "sg:website":"www.recycledcycles.net/",
    "wof:name":"Recycled Cycles & Service",
    "wof:placetype":"venue"
},
  "geometry": {"coordinates":[-90.32768,38.666177],"type":"Point"}
}