{
  "type": "Feature",
  "properties": {
    "iso:country":"US",
    "sg:address":"2513 Hwy Ah",
    "sg:city":"Union",
    "sg:classifiers":[
        {
            "category":"Retail",
            "subcategory":"Repair Shop",
            "type":"Services"
        },
        {
            "category":"Building & Trades",
            "subcategory":"Plumbing",
            "type":"Services"
        }
    ],
    "sg:phone":"+1 636 629 0291",
    "sg:postcode":"63084",
    "sg:province":"MO",
    "sg:tags":[
        "plumbing",
        "drain",
        "cleaning",
        "sewer",
        "contractor"
    ],
    "wof:name":"Stephens Plumbing Service Inc",
    "wof:placetype":"venue"
},
  "geometry": {"coordinates":[-90.90600000000001,38.389222],"type":"Point"}
}