{
  "type": "Feature",
  "properties": {
    "iso:country":"US",
    "sg:address":"4820 Elm Dr",
    "sg:city":"Joplin",
    "sg:classifiers":[
        {
            "category":"Freight",
            "type":"Transportation"
        }
    ],
    "sg:phone":"+1 417 781 0520",
    "sg:postcode":"64804",
    "sg:province":"MO",
    "sg:tags":[
        "operator",
        "trucking"
    ],
    "wof:name":"J & B Trucking",
    "wof:placetype":"venue"
},
  "geometry": {"coordinates":[-94.561031,36.979825],"type":"Point"}
}