{
  "type": "Feature",
  "properties": {
    "iso:country":"US",
    "sg:address":"10 Cemetery Rd",
    "sg:city":"Wellsville",
    "sg:classifiers":[
        {
            "category":"Farming",
            "subcategory":"Livestock Farm",
            "type":"Manufacturing & Wholesale Goods"
        }
    ],
    "sg:phone":"+1 573 684 2488",
    "sg:postcode":"63384",
    "sg:province":"MO",
    "sg:tags":[
        "feedlot",
        "field",
        "crop",
        "beef",
        "cattle"
    ],
    "wof:name":"Roger Scott",
    "wof:placetype":"venue"
},
  "geometry": {"coordinates":[-91.56768099999999,39.06124],"type":"Point"}
}