{
  "type": "Feature",
  "properties": {
    "iso:country":"US",
    "sg:address":"23043 US Hwy 136",
    "sg:city":"Bethany",
    "sg:classifiers":[
        {
            "category":"Farming",
            "subcategory":"Dairy Farm",
            "type":"Manufacturing & Wholesale Goods"
        }
    ],
    "sg:phone":"+1 660 425 6859",
    "sg:postcode":"64424",
    "sg:province":"MO",
    "wof:name":"Guernsey Family Dairy",
    "wof:placetype":"venue"
},
  "geometry": {"coordinates":[-93.98831,40.265014],"type":"Point"}
}