{
  "type": "Feature",
  "properties": {
    "iso:country":"US",
    "sg:address":"1921 Guinotte Ave",
    "sg:city":"Kansas City",
    "sg:classifiers":[
        {
            "category":"Retail",
            "subcategory":"Auto Repair",
            "type":"Services"
        }
    ],
    "sg:phone":"+1 816 472 1750",
    "sg:postcode":"64120",
    "sg:province":"MO",
    "sg:tags":[
        "trailer"
    ],
    "wof:name":"Linney's Trailer Shop Inc",
    "wof:placetype":"venue"
},
  "geometry": {"coordinates":[-94.559871,39.116845],"type":"Point"}
}