{
  "type": "Feature",
  "properties": {
    "iso:country":"US",
    "sg:address":"701 N Miller Ave",
    "sg:city":"Springfield",
    "sg:classifiers":[
        {
            "category":"Government",
            "subcategory":"Office",
            "type":"Public Place"
        }
    ],
    "sg:phone":"+1 417 895 6861",
    "sg:postcode":"65802",
    "sg:province":"MO",
    "sg:tags":[
        "state",
        "program"
    ],
    "wof:name":"Veterinary Diagnostic Lab",
    "wof:placetype":"venue"
},
  "geometry": {"coordinates":[-93.37345999999999,37.216249],"type":"Point"}
}