{
  "type": "Feature",
  "properties": {
    "iso:country":"US",
    "sg:address":"2415 E Commercial St",
    "sg:city":"Springfield",
    "sg:classifiers":[
        {
            "category":"Freight",
            "type":"Transportation"
        }
    ],
    "sg:phone":"+1 417 864 5337",
    "sg:postcode":"65803",
    "sg:province":"MO",
    "sg:tags":[
        "operator",
        "local",
        "trucking"
    ],
    "wof:name":"Wayne Choate Dump Trucking",
    "wof:placetype":"venue"
},
  "geometry": {"coordinates":[-93.246016,37.229415],"type":"Point"}
}