{
  "type": "Feature",
  "properties": {
    "iso:country":"US",
    "sg:address":"109 W 8th St",
    "sg:city":"Stewartsville",
    "sg:classifiers":[
        {
            "category":"Organizations",
            "subcategory":"Religious Organization",
            "type":"Services"
        }
    ],
    "sg:phone":"+1 816 669 3263",
    "sg:postcode":"64490",
    "sg:province":"MO",
    "sg:tags":[
        "church"
    ],
    "wof:name":"First Baptist Church",
    "wof:placetype":"venue"
},
  "geometry": {"coordinates":[-94.496798,39.752374],"type":"Point"}
}