{
  "type": "Feature",
  "properties": {
    "iso:country":"US",
    "sg:address":"404 Ward Ave",
    "sg:city":"Caruthersville",
    "sg:classifiers":[
        {
            "category":"Professional",
            "subcategory":"Lawyer & Legal Services",
            "type":"Services"
        }
    ],
    "sg:phone":"+1 573 333 2600",
    "sg:postcode":"63830",
    "sg:province":"MO",
    "sg:tags":[
        "attorney",
        "criminal",
        "personal",
        "divorce",
        "medical",
        "malpractice",
        "injury",
        "law"
    ],
    "sg:website":"http://wendellhoskins.com",
    "wof:name":"Hoskins Wendell L II Law Office Of",
    "wof:placetype":"venue"
},
  "geometry": {"coordinates":[-89.654888,36.191569],"type":"Point"}
}