{
  "type": "Feature",
  "properties": {
    "iso:country":"US",
    "sg:address":"5 Forest Acres Ct",
    "sg:city":"O Fallon",
    "sg:classifiers":[
        {
            "category":"Shopping",
            "subcategory":"Crafts & Fabrics",
            "type":"Retail Goods"
        }
    ],
    "sg:phone":"+1 636 240 4344",
    "sg:postcode":"63366",
    "sg:province":"MO",
    "sg:tags":[
        "sewing"
    ],
    "wof:name":"Quilt n Craft Corner",
    "wof:placetype":"venue"
},
  "geometry": {"coordinates":[-90.736608,38.81588],"type":"Point"}
}