{
  "type": "Feature",
  "properties": {
    "iso:country":"US",
    "sg:address":"2445 N Kansas Expy",
    "sg:city":"Springfield",
    "sg:classifiers":[
        {
            "category":"Deli",
            "type":"Food & Drink"
        }
    ],
    "sg:menulink":"http://www.allmenus.com/mo/springfield/54380-mcalisters-deli/menu/",
    "sg:phone":"+1 417 866 2331",
    "sg:postcode":"65803",
    "sg:province":"MO",
    "sg:tags":[
        "american"
    ],
    "wof:name":"Mcalister's Deli",
    "wof:placetype":"venue"
},
  "geometry": {"coordinates":[-93.311094,37.241926],"type":"Point"}
}