{
  "type": "Feature",
  "properties": {
    "iso:country":"US",
    "sg:address":"2155 Barrett Station Rd",
    "sg:city":"Saint Louis",
    "sg:classifiers":[
        {
            "category":"Travel",
            "subcategory":"Travel Agent",
            "type":"Entertainment"
        }
    ],
    "sg:phone":"+1 314 835 1000",
    "sg:postcode":"63131",
    "sg:province":"MO",
    "sg:tags":[
        "agency"
    ],
    "wof:name":"Travelstars International",
    "wof:placetype":"venue"
},
  "geometry": {"coordinates":[-90.474046,38.598879],"type":"Point"}
}