{
  "type": "Feature",
  "properties": {
    "iso:country":"US",
    "sg:address":"810 W Monroe St",
    "sg:city":"Mexico",
    "sg:classifiers":[
        {
            "category":"Food & Beverages",
            "subcategory":"Groceries & Convenience Stores",
            "type":"Retail Goods"
        }
    ],
    "sg:phone":"+1 573 000 1111",
    "sg:postcode":"65265",
    "sg:province":"MO",
    "sg:tags":[
        "grocer"
    ],
    "wof:name":"Aldi",
    "wof:placetype":"venue"
},
  "geometry": {"coordinates":[-91.89270399999999,39.172989],"type":"Point"}
}