{
  "type": "Feature",
  "properties": {
    "iso:country":"US",
    "sg:address":"108 S Main St",
    "sg:city":"St Charles",
    "sg:classifiers":[
        {
            "category":"Restaurant",
            "type":"Food & Drink"
        }
    ],
    "sg:phone":"+1 636 946 1632",
    "sg:postcode":"63301",
    "sg:province":"MO",
    "wof:name":"Frontier Cafe & Pub",
    "wof:placetype":"venue"
},
  "geometry": {"coordinates":[-90.48170500000001,38.780417],"type":"Point"}
}