{
  "type": "Feature",
  "properties": {
    "iso:country":"US",
    "sg:address":"1788 US Hwy 61",
    "sg:city":"Festus",
    "sg:classifiers":[
        {
            "category":"Retail",
            "subcategory":"Repair Shop",
            "type":"Services"
        }
    ],
    "sg:phone":"+1 636 937 9470",
    "sg:postcode":"63028",
    "sg:province":"MO",
    "sg:tags":[
        "welding"
    ],
    "wof:name":"A & B Custom Welding & Fab",
    "wof:placetype":"venue"
},
  "geometry": {"coordinates":[-90.392166,38.182391],"type":"Point"}
}