{
  "type": "Feature",
  "properties": {
    "iso:country":"US",
    "sg:address":"11665 Lilburn Park Rd",
    "sg:city":"St Louis",
    "sg:classifiers":[
        {
            "category":"Insurance",
            "subcategory":"Insurance Agent",
            "type":"Services"
        }
    ],
    "sg:phone":"+1 314 692 9890",
    "sg:postcode":"63146",
    "sg:province":"MO",
    "sg:tags":[
        "consultant"
    ],
    "wof:name":"LWG Consulting",
    "wof:placetype":"venue"
},
  "geometry": {"coordinates":[-90.427138,38.696177],"type":"Point"}
}