{
  "type": "Feature",
  "properties": {
    "iso:country":"US",
    "sg:address":"634 E State Hwy 174",
    "sg:city":"Republic",
    "sg:classifiers":[
        {
            "category":"Social Services",
            "subcategory":"Adult Care",
            "type":"Services"
        }
    ],
    "sg:phone":"+1 417 732 8998",
    "sg:postcode":"65738",
    "sg:province":"MO",
    "sg:tags":[
        "home",
        "residential"
    ],
    "wof:name":"Bristol Manor",
    "wof:placetype":"venue"
},
  "geometry": {"coordinates":[-93.468754,37.128813],"type":"Point"}
}