{
  "type": "Feature",
  "properties": {
    "iso:country":"US",
    "sg:address":"5151 Hwy K",
    "sg:city":"Sullivan",
    "sg:classifiers":[
        {
            "category":"Building & Trades",
            "subcategory":"Construction",
            "type":"Services"
        }
    ],
    "sg:phone":"+1 573 468 6278",
    "sg:postcode":"63080",
    "sg:province":"MO",
    "sg:tags":[
        "carpentry",
        "contractor"
    ],
    "wof:name":"Stanley G Laubinger",
    "wof:placetype":"venue"
},
  "geometry": {"coordinates":[-91.032139,38.208256],"type":"Point"}
}