{
  "type": "Feature",
  "properties": {
    "iso:country":"US",
    "sg:address":"115 Gravois Bluffs Plaza Dr",
    "sg:city":"Fenton",
    "sg:classifiers":[
        {
            "category":"Shopping",
            "subcategory":"Department Store",
            "type":"Retail Goods"
        }
    ],
    "sg:phone":"+1 636 349 9952",
    "sg:postcode":"63026",
    "sg:province":"MO",
    "sg:website":"http://www.kohls.com",
    "wof:name":"Kohl's",
    "wof:placetype":"venue"
},
  "geometry": {"coordinates":[-90.44680200000001,38.506498],"type":"Point"}
}