{
  "type": "Feature",
  "properties": {
    "iso:country":"US",
    "sg:address":"2400 Boonslick Dr",
    "sg:city":"Boonville",
    "sg:classifiers":[
        {
            "category":"Food & Beverages",
            "subcategory":"Groceries & Convenience Stores",
            "type":"Retail Goods"
        }
    ],
    "sg:phone":"+1 660 882 7170",
    "sg:postcode":"65233",
    "sg:province":"MO",
    "sg:tags":[
        "product"
    ],
    "wof:name":"Horizon Health Inc",
    "wof:placetype":"venue"
},
  "geometry": {"coordinates":[-92.74242599999999,38.946315],"type":"Point"}
}