{
  "type": "Feature",
  "properties": {
    "iso:country":"US",
    "sg:address":"139 N Main St",
    "sg:city":"Cape Girardeau",
    "sg:classifiers":[
        {
            "category":"Home & Garden",
            "subcategory":"Home Furnishings",
            "type":"Retail Goods"
        }
    ],
    "sg:phone":"+1 573 335 5683",
    "sg:postcode":"63701",
    "sg:province":"MO",
    "wof:name":"Renaissance",
    "wof:placetype":"venue"
},
  "geometry": {"coordinates":[-89.518354,37.30548],"type":"Point"}
}