{
  "type": "Feature",
  "properties": {
    "iso:country":"US",
    "sg:address":"310 N Marguerite Ave",
    "sg:city":"Saint Louis",
    "sg:classifiers":[
        {
            "category":"Food & Beverages",
            "subcategory":"Groceries & Convenience Stores",
            "type":"Retail Goods"
        }
    ],
    "sg:phone":"+1 314 427 4212",
    "sg:postcode":"63135",
    "sg:province":"MO",
    "wof:name":"Edmundson Food Mart",
    "wof:placetype":"venue"
},
  "geometry": {"coordinates":[-90.31370099999999,38.74924],"type":"Point"}
}