{
  "type": "Feature",
  "properties": {
    "iso:country":"US",
    "sg:address":"311 W Howell Ave",
    "sg:city":"Marceline",
    "sg:classifiers":[
        {
            "category":"Personal",
            "subcategory":"Beauty Salon",
            "type":"Services"
        }
    ],
    "sg:phone":"+1 660 376 4499",
    "sg:postcode":"64658",
    "sg:province":"MO",
    "sg:tags":[
        "shop"
    ],
    "wof:name":"Styles R US",
    "wof:placetype":"venue"
},
  "geometry": {"coordinates":[-92.95528299999999,39.716398],"type":"Point"}
}