{
  "type": "Feature",
  "properties": {
    "iso:country":"US",
    "sg:address":"3528 W Nichols St",
    "sg:city":"Springfield",
    "sg:classifiers":[
        {
            "category":"Building & Trades",
            "subcategory":"Construction",
            "type":"Services"
        }
    ],
    "sg:phone":"+1 417 831 4706",
    "sg:postcode":"65803",
    "sg:province":"MO",
    "sg:tags":[
        "dry wall",
        "contractor"
    ],
    "wof:name":"Artisan Construction Svc Inc",
    "wof:placetype":"venue"
},
  "geometry": {"coordinates":[-93.348681,37.219467],"type":"Point"}
}