{
  "type": "Feature",
  "properties": {
    "iso:country":"US",
    "sg:address":"1729 E 7th St",
    "sg:city":"Joplin",
    "sg:classifiers":[
        {
            "category":"Bars & Pubs",
            "type":"Food & Drink"
        }
    ],
    "sg:phone":"+1 417 627 0876",
    "sg:postcode":"64801",
    "sg:province":"MO",
    "wof:name":"Red Lion Bar",
    "wof:placetype":"venue"
},
  "geometry": {"coordinates":[-94.495372,37.083925],"type":"Point"}
}