{
  "type": "Feature",
  "properties": {
    "iso:country":"US",
    "sg:address":"17022 Hwy CC",
    "sg:city":"Neosho",
    "sg:classifiers":[
        {
            "category":"Organizations",
            "subcategory":"Non-profit Organization",
            "type":"Services"
        }
    ],
    "sg:phone":"+1 417 776 3755",
    "sg:postcode":"64850",
    "sg:province":"MO",
    "sg:tags":[
        "social"
    ],
    "wof:name":"Seneca Head Start",
    "wof:placetype":"venue"
},
  "geometry": {"coordinates":[-94.520065,36.836265],"type":"Point"}
}