{
  "type": "Feature",
  "properties": {
    "iso:country":"US",
    "sg:address":"728 N Clark St",
    "sg:city":"Mexico",
    "sg:classifiers":[
        {
            "category":"Retail",
            "subcategory":"Repair Shop",
            "type":"Services"
        }
    ],
    "sg:phone":"+1 573 581 6041",
    "sg:postcode":"65265",
    "sg:province":"MO",
    "sg:tags":[
        "sharpening"
    ],
    "wof:name":"R D Barnett Complete Sharp",
    "wof:placetype":"venue"
},
  "geometry": {"coordinates":[-91.884424,39.177842],"type":"Point"}
}