{
  "type": "Feature",
  "properties": {
    "iso:country":"US",
    "sg:address":"163 W Center St",
    "sg:city":"Peculiar",
    "sg:classifiers":[
        {
            "category":"Organizations",
            "subcategory":"Non-profit Organization",
            "type":"Services"
        }
    ],
    "sg:phone":"+1 816 779 7338",
    "sg:postcode":"64078",
    "sg:province":"MO",
    "sg:tags":[
        "charity",
        "foundations-educational",
        "philanthropic",
        "research"
    ],
    "wof:name":"Peculiar Charitable Found",
    "wof:placetype":"venue"
},
  "geometry": {"coordinates":[-94.461102,38.719441],"type":"Point"}
}