{
  "type": "Feature",
  "properties": {
    "iso:country":"US",
    "sg:address":"105 Main St",
    "sg:city":"Steelville",
    "sg:classifiers":[
        {
            "category":"Restaurant",
            "type":"Food & Drink"
        }
    ],
    "sg:phone":"+1 573 775 4175",
    "sg:postcode":"65565",
    "sg:province":"MO",
    "wof:name":"Healthy Cuisine & Selective",
    "wof:placetype":"venue"
},
  "geometry": {"coordinates":[-91.35487000000001,37.96805],"type":"Point"}
}