{
  "type": "Feature",
  "properties": {
    "iso:country":"US",
    "sg:address":"1706 N Corrington Ave",
    "sg:city":"Kansas City",
    "sg:classifiers":[
        {
            "category":"Health Services",
            "subcategory":"Medical Lab",
            "type":"Services"
        }
    ],
    "sg:phone":"+1 816 483 1177",
    "sg:postcode":"64120",
    "sg:province":"MO",
    "sg:tags":[
        "laboratory"
    ],
    "sg:website":"www.labcorp.com",
    "wof:name":"Laboratory Corp Of America",
    "wof:placetype":"venue"
},
  "geometry": {"coordinates":[-94.49627,39.131811],"type":"Point"}
}