{
  "type": "Feature",
  "properties": {
    "iso:country":"US",
    "sg:address":"32249 State Hwy U",
    "sg:city":"Oregon",
    "sg:classifiers":[
        {
            "category":"Farming",
            "subcategory":"Farm",
            "type":"Manufacturing & Wholesale Goods"
        }
    ],
    "sg:phone":"+1 660 446 2942",
    "sg:postcode":"64473",
    "sg:province":"MO",
    "sg:tags":[
        "crop",
        "general"
    ],
    "wof:name":"John R Polaski Farm",
    "wof:placetype":"venue"
},
  "geometry": {"coordinates":[-95.040193,39.934939],"type":"Point"}
}