{
  "type": "Feature",
  "properties": {
    "iso:country":"US",
    "sg:address":"1116 Country Club Dr",
    "sg:city":"Kirksville",
    "sg:classifiers":[
        {
            "category":"Restaurant",
            "type":"Food & Drink"
        }
    ],
    "sg:menulink":"http://www.allmenus.com/mo/benton/214672-ponderosa-steak-house/menu/",
    "sg:phone":"+1 660 665 6336",
    "sg:postcode":"63501",
    "sg:province":"MO",
    "sg:tags":[
        "american",
        "steakhouse"
    ],
    "wof:name":"Ponderosa Steak House",
    "wof:placetype":"venue"
},
  "geometry": {"coordinates":[-92.570457,40.170588],"type":"Point"}
}