{
  "type": "Feature",
  "properties": {
    "iso:country":"US",
    "sg:address":"1041 Wolfrum Rd",
    "sg:city":"St Charles",
    "sg:classifiers":[
        {
            "category":"Health Services",
            "subcategory":"Doctor",
            "type":"Services"
        }
    ],
    "sg:phone":"+1 636 300 4545",
    "sg:postcode":"63304",
    "sg:province":"MO",
    "sg:tags":[
        "dentist"
    ],
    "wof:name":"Shannon Ankenbrandt DDS",
    "wof:placetype":"venue"
},
  "geometry": {"coordinates":[-90.644462,38.729512],"type":"Point"}
}