{
  "type": "Feature",
  "properties": {
    "iso:country":"US",
    "sg:address":"11706 E 211th St",
    "sg:city":"Peculiar",
    "sg:classifiers":[
        {
            "category":"Education",
            "subcategory":"School",
            "type":"Public Place"
        }
    ],
    "sg:phone":"+1 816 779 6694",
    "sg:postcode":"64078",
    "sg:province":"MO",
    "sg:website":"www.raypec.k12.mo.us",
    "wof:name":"Shull Intermediate School",
    "wof:placetype":"venue"
},
  "geometry": {"coordinates":[-94.45832799999999,38.740172],"type":"Point"}
}