{
  "type": "Feature",
  "properties": {
    "iso:country":"US",
    "sg:address":"14057 Moss Dr",
    "sg:city":"New Boston",
    "sg:classifiers":[
        {
            "category":"Farming",
            "subcategory":"Livestock Farm",
            "type":"Manufacturing & Wholesale Goods"
        }
    ],
    "sg:phone":"+1 660 689 7256",
    "sg:postcode":"63557",
    "sg:province":"MO",
    "sg:tags":[
        "beef",
        "feedlot",
        "cattle"
    ],
    "wof:name":"Mills Farms",
    "wof:placetype":"venue"
},
  "geometry": {"coordinates":[-92.88814000000001,39.976886],"type":"Point"}
}