{
  "type": "Feature",
  "properties": {
    "iso:country":"US",
    "sg:address":"351 Timber Creek",
    "sg:city":"Nixa",
    "sg:classifiers":[
        {
            "category":"Building & Trades",
            "subcategory":"Construction",
            "type":"Services"
        }
    ],
    "sg:phone":"+1 417 725 0465",
    "sg:postcode":"65714",
    "sg:province":"MO",
    "wof:name":"View John A III & Patrici",
    "wof:placetype":"venue"
},
  "geometry": {"coordinates":[-93.272087,37.039788],"type":"Point"}
}