{
  "type": "Feature",
  "properties": {
    "iso:country":"US",
    "sg:address":"202 Lincoln Dr",
    "sg:city":"Fredericktown",
    "sg:classifiers":[
        {
            "category":"Autos & Motor Vehicles",
            "subcategory":"Automobile Sales",
            "type":"Retail Goods"
        }
    ],
    "sg:phone":"+1 573 783 0076",
    "sg:postcode":"63645",
    "sg:province":"MO",
    "sg:tags":[
        "used"
    ],
    "wof:name":"K C Auto Source",
    "wof:placetype":"venue"
},
  "geometry": {"coordinates":[-90.29077700000001,37.563106],"type":"Point"}
}