{
  "type": "Feature",
  "properties": {
    "iso:country":"US",
    "sg:address":"305 S Main St",
    "sg:city":"Chaffee",
    "sg:classifiers":[
        {
            "category":"Shopping",
            "subcategory":"Books",
            "type":"Retail Goods"
        }
    ],
    "sg:phone":"+1 573 887 3527",
    "sg:postcode":"63740",
    "sg:province":"MO",
    "wof:name":"Main Street Bookstore",
    "wof:placetype":"venue"
},
  "geometry": {"coordinates":[-89.65621,37.178152],"type":"Point"}
}