{
  "type": "Feature",
  "properties": {
    "iso:country":"US",
    "sg:address":"979 W Rue de la Banque",
    "sg:city":"St Louis",
    "sg:classifiers":[
        {
            "category":"Organizations",
            "subcategory":"Religious Organization",
            "type":"Services"
        }
    ],
    "sg:phone":"+1 314 993 5624",
    "sg:postcode":"63141",
    "sg:province":"MO",
    "sg:tags":[
        "church"
    ],
    "wof:name":"Jesus Christ Laterday Saints",
    "wof:placetype":"venue"
},
  "geometry": {"coordinates":[-90.446029,38.671701],"type":"Point"}
}