{
  "type": "Feature",
  "properties": {
    "iso:country":"US",
    "sg:address":"404 Main St",
    "sg:city":"Weston",
    "sg:classifiers":[
        {
            "category":"Recreation",
            "type":"Entertainment"
        }
    ],
    "sg:phone":"+1 816 386 2358",
    "sg:postcode":"64098",
    "sg:province":"MO",
    "sg:tags":[
        "stable"
    ],
    "wof:name":"Celtic Ranch",
    "wof:placetype":"venue"
},
  "geometry": {"coordinates":[-94.90177300000001,39.411204],"type":"Point"}
}