{
  "type": "Feature",
  "properties": {
    "iso:country":"US",
    "sg:address":"907 Mallory St",
    "sg:city":"Dexter",
    "sg:classifiers":[
        {
            "category":"Professional",
            "subcategory":"Business Services",
            "type":"Services"
        }
    ],
    "sg:phone":"+1 573 624 7055",
    "sg:postcode":"63841",
    "sg:province":"MO",
    "wof:name":"Express Tax",
    "wof:placetype":"venue"
},
  "geometry": {"coordinates":[-89.973491,36.80376],"type":"Point"}
}