{
  "type": "Feature",
  "properties": {
    "iso:country":"US",
    "sg:address":"4510 US Hwy 169",
    "sg:city":"St Joseph",
    "sg:classifiers":[
        {
            "category":"Banks & Credit Unions",
            "subcategory":"Investment Brokerage",
            "type":"Services"
        }
    ],
    "sg:phone":"+1 816 232 5077",
    "sg:postcode":"64507",
    "sg:province":"MO",
    "sg:tags":[
        "advisory",
        "financial"
    ],
    "wof:name":"H R Financial",
    "wof:placetype":"venue"
},
  "geometry": {"coordinates":[-94.78469699999999,39.724069],"type":"Point"}
}