{
  "type": "Feature",
  "properties": {
    "iso:country":"US",
    "sg:address":"13912 S Noland Ct",
    "sg:city":"Independence",
    "sg:classifiers":[
        {
            "category":"Professional",
            "subcategory":"Lawyer & Legal Services",
            "type":"Services"
        }
    ],
    "sg:phone":"+1 816 252 2771",
    "sg:postcode":"64055",
    "sg:province":"MO",
    "sg:tags":[
        "attorney"
    ],
    "wof:name":"Kathy Robinson Law & Conflict",
    "wof:placetype":"venue"
},
  "geometry": {"coordinates":[-94.41543900000001,39.054457],"type":"Point"}
}