{
  "type": "Feature",
  "properties": {
    "iso:country":"US",
    "sg:address":"1710 Mississippi Ave",
    "sg:city":"Saint Louis",
    "sg:classifiers":[
        {
            "category":"Shopping",
            "subcategory":"Books",
            "type":"Retail Goods"
        }
    ],
    "sg:phone":"+1 314 773 5464",
    "sg:postcode":"63104",
    "sg:province":"MO",
    "sg:tags":[
        "bookstore"
    ],
    "wof:name":"All About the Kingdom Book & Gifts",
    "wof:placetype":"venue"
},
  "geometry": {"coordinates":[-90.214021,38.613222],"type":"Point"}
}