{
  "type": "Feature",
  "properties": {
    "iso:country":"US",
    "sg:address":"116 N Cedar St",
    "sg:city":"Nevada",
    "sg:classifiers":[
        {
            "category":"Shopping",
            "subcategory":"Stationery & Office Supplies",
            "type":"Retail Goods"
        }
    ],
    "sg:phone":"+1 417 667 5444",
    "sg:postcode":"64772",
    "sg:province":"MO",
    "sg:tags":[
        "album",
        "scrapbook"
    ],
    "wof:name":"Once Upon A Time",
    "wof:placetype":"venue"
},
  "geometry": {"coordinates":[-94.356511,37.839023],"type":"Point"}
}