{
  "type": "Feature",
  "properties": {
    "iso:country":"US",
    "sg:address":"10087 W Florissant Ave",
    "sg:city":"St Louis",
    "sg:classifiers":[
        {
            "category":"Utilities",
            "subcategory":"Mobile Phone",
            "type":"Services"
        },
        {
            "category":"Wholesale",
            "subcategory":"Electrical",
            "type":"Manufacturing & Wholesale Goods"
        }
    ],
    "sg:phone":"+1 314 655 7243",
    "sg:postcode":"63136",
    "sg:province":"MO",
    "sg:tags":[
        "communication",
        "radio",
        "radiotelephone"
    ],
    "wof:name":"E Z Page Inc",
    "wof:placetype":"venue"
},
  "geometry": {"coordinates":[-90.279971,38.750531],"type":"Point"}
}