{
  "type": "Feature",
  "properties": {
    "iso:country":"US",
    "sg:address":"8820 Lawn Ave",
    "sg:city":"St Louis",
    "sg:classifiers":[
        {
            "category":"Organizations",
            "subcategory":"Religious Organization",
            "type":"Services"
        }
    ],
    "sg:phone":"+1 314 962 3161",
    "sg:postcode":"63144",
    "sg:province":"MO",
    "sg:tags":[
        "church"
    ],
    "sg:website":"www.brentwoodbiblechurch.com",
    "wof:name":"Brentwood Bible Church Inc",
    "wof:placetype":"venue"
},
  "geometry": {"coordinates":[-90.349648,38.623545],"type":"Point"}
}