{
  "type": "Feature",
  "properties": {
    "iso:country":"US",
    "sg:address":"110 N. Mason",
    "sg:city":"Carrollton",
    "sg:classifiers":[
        {
            "category":"Travel",
            "subcategory":"Hotels & Motels",
            "type":"Entertainment"
        }
    ],
    "sg:phone":"+1 660 542 3331",
    "sg:postcode":"64633",
    "sg:province":"MO",
    "sg:website":"http://www.masonmotel.com",
    "wof:name":"Carrollton Mason Motel",
    "wof:placetype":"venue"
},
  "geometry": {"coordinates":[-93.48884,39.359344],"type":"Point"}
}