{
  "type": "Feature",
  "properties": {
    "iso:country":"US",
    "sg:address":"2650 W Alta St",
    "sg:city":"Springfield",
    "sg:classifiers":[
        {
            "category":"Retail",
            "subcategory":"Laundry & Dry Cleaning",
            "type":"Services"
        }
    ],
    "sg:phone":"+1 417 882 2727",
    "sg:postcode":"65810",
    "sg:province":"MO",
    "sg:tags":[
        "cleaners",
        "rug",
        "carpet"
    ],
    "wof:name":"Chemdry Of Southwest Missouri",
    "wof:placetype":"venue"
},
  "geometry": {"coordinates":[-93.33142700000001,37.126021],"type":"Point"}
}