{
  "type": "Feature",
  "properties": {
    "iso:country":"US",
    "sg:address":"3528 Market St",
    "sg:city":"Hannibal",
    "sg:classifiers":[
        {
            "category":"Autos & Motor Vehicles",
            "subcategory":"Automobile Sales",
            "type":"Retail Goods"
        }
    ],
    "sg:phone":"+1 573 231 0821",
    "sg:postcode":"63401",
    "sg:province":"MO",
    "sg:tags":[
        "car",
        "dealer"
    ],
    "wof:name":"Clark Motors",
    "wof:placetype":"venue"
},
  "geometry": {"coordinates":[-91.39610399999999,39.685705],"type":"Point"}
}