{
  "type": "Feature",
  "properties": {
    "iso:country":"US",
    "sg:address":"12010 Tindall Dr",
    "sg:city":"Saint Louis",
    "sg:classifiers":[
        {
            "category":"Professional",
            "subcategory":"Business Services",
            "type":"Services"
        }
    ],
    "sg:phone":"+1 314 989 9679",
    "sg:postcode":"63131",
    "sg:province":"MO",
    "wof:name":"Vantage Point Group",
    "wof:placetype":"venue"
},
  "geometry": {"coordinates":[-90.43478399999999,38.625164],"type":"Point"}
}