{
  "type": "Feature",
  "properties": {
    "iso:country":"US",
    "sg:address":"32 Clermont Ln",
    "sg:city":"Saint Louis",
    "sg:classifiers":[
        {
            "category":"Professional",
            "type":"Services"
        }
    ],
    "sg:phone":"+1 314 432 3944",
    "sg:postcode":"63124",
    "sg:province":"MO",
    "wof:name":"Andrew R Spann",
    "wof:placetype":"venue"
},
  "geometry": {"coordinates":[-90.40242000000001,38.652294],"type":"Point"}
}