{
  "type": "Feature",
  "properties": {
    "iso:country":"US",
    "sg:address":"508 N Kirkwood Rd",
    "sg:city":"St Louis",
    "sg:classifiers":[
        {
            "category":"Health Services",
            "subcategory":"Doctor",
            "type":"Services"
        }
    ],
    "sg:phone":"+1 314 965 8283",
    "sg:postcode":"63122",
    "sg:province":"MO",
    "sg:tags":[
        "dentist"
    ],
    "wof:name":"Richard D Snitzer DMD PC",
    "wof:placetype":"venue"
},
  "geometry": {"coordinates":[-90.40620199999999,38.588803],"type":"Point"}
}