{
  "type": "Feature",
  "properties": {
    "iso:country":"US",
    "sg:address":"7 E 34 St",
    "sg:city":"Kansas City",
    "sg:classifiers":[
        {
            "category":"Real Estate",
            "subcategory":"Architect",
            "type":"Services"
        }
    ],
    "sg:phone":"+1 816 756 3439",
    "sg:postcode":"64111",
    "sg:province":"MO",
    "sg:tags":[
        "architectural"
    ],
    "wof:name":"Hueser John Assoc Architects",
    "wof:placetype":"venue"
},
  "geometry": {"coordinates":[-94.58444,39.065648],"type":"Point"}
}