{
  "type": "Feature",
  "properties": {
    "iso:country":"US",
    "sg:address":"6400 Clayton Rd",
    "sg:city":"Saint Louis",
    "sg:classifiers":[
        {
            "category":"Health Services",
            "subcategory":"Doctor",
            "type":"Services"
        }
    ],
    "sg:phone":"+1 314 645 6450",
    "sg:postcode":"63117",
    "sg:province":"MO",
    "sg:tags":[
        "specializing"
    ],
    "wof:name":"Metro Heart Group of St Louis",
    "wof:placetype":"venue"
},
  "geometry": {"coordinates":[-90.311926,38.634128],"type":"Point"}
}