{
  "type": "Feature",
  "properties": {
    "iso:country":"US",
    "sg:address":"27205 E 197th St",
    "sg:city":"Pleasant Hill",
    "sg:classifiers":[
        {
            "category":"Building & Trades",
            "subcategory":"Construction",
            "type":"Services"
        }
    ],
    "sg:phone":"+1 816 987 4168",
    "sg:postcode":"64080",
    "sg:province":"MO",
    "sg:tags":[
        "residential"
    ],
    "wof:name":"Frances Atkinson Group",
    "wof:placetype":"venue"
},
  "geometry": {"coordinates":[-94.276459,38.758588],"type":"Point"}
}