{
  "type": "Feature",
  "properties": {
    "iso:country":"US",
    "sg:address":"2466 SE Rogers Rd",
    "sg:city":"Cameron",
    "sg:classifiers":[
        {
            "category":"Building & Trades",
            "subcategory":"Construction",
            "type":"Services"
        }
    ],
    "sg:phone":"+1 816 632 3900",
    "sg:postcode":"64429",
    "sg:province":"MO",
    "sg:tags":[
        "concrete",
        "contractor"
    ],
    "wof:name":"P & P Quality Concrete Constr",
    "wof:placetype":"venue"
},
  "geometry": {"coordinates":[-94.30971,39.776212],"type":"Point"}
}