{
  "type": "Feature",
  "properties": {
    "iso:country":"US",
    "sg:address":"45 N St",
    "sg:city":"Lees Summit",
    "sg:classifiers":[
        {
            "category":"Professional",
            "type":"Services"
        }
    ],
    "sg:phone":"+1 816 578 5726",
    "sg:postcode":"64086",
    "sg:province":"MO",
    "wof:name":"Doug Fulks Pen & Ink",
    "wof:placetype":"venue"
},
  "geometry": {"coordinates":[-94.25535600000001,38.912106],"type":"Point"}
}