{
  "type": "Feature",
  "properties": {
    "iso:country":"US",
    "sg:address":"3031 Washington Ave",
    "sg:city":"St Louis",
    "sg:classifiers":[
        {
            "category":"Manufacturing",
            "subcategory":"Tools & Machinery",
            "type":"Manufacturing & Wholesale Goods"
        },
        {
            "category":"Retail",
            "subcategory":"Auto Repair",
            "type":"Services"
        }
    ],
    "sg:phone":"+1 314 535 6618",
    "sg:postcode":"63103",
    "sg:province":"MO",
    "sg:tags":[
        "machine",
        "automobile",
        "shop",
        "automotive"
    ],
    "wof:name":"Lens Crankshaft Co",
    "wof:placetype":"venue"
},
  "geometry": {"coordinates":[-90.222604,38.637],"type":"Point"}
}