{
  "type": "Feature",
  "properties": {
    "iso:country":"US",
    "sg:address":"13721 Shore Line Ct",
    "sg:city":"Earth City",
    "sg:classifiers":[
        {
            "category":"Professional",
            "subcategory":"Business Services",
            "type":"Services"
        }
    ],
    "sg:phone":"+1 314 738 0147",
    "sg:postcode":"63044",
    "sg:province":"MO",
    "wof:name":"Installation Solutions Inc",
    "wof:placetype":"venue"
},
  "geometry": {"coordinates":[-90.464714,38.768606],"type":"Point"}
}