{
  "type": "Feature",
  "properties": {
    "iso:country":"US",
    "sg:address":"2329 State Hwy 291",
    "sg:city":"Independence",
    "sg:classifiers":[
        {
            "category":"Shopping",
            "type":"Retail Goods"
        }
    ],
    "sg:phone":"+1 816 373 1003",
    "sg:postcode":"64057",
    "sg:province":"MO",
    "sg:tags":[
        "merchandise"
    ],
    "wof:name":"Tropical Fish Cove",
    "wof:placetype":"venue"
},
  "geometry": {"coordinates":[-94.378924,39.074821],"type":"Point"}
}