{
  "type": "Feature",
  "properties": {
    "iso:country":"US",
    "sg:address":"15 E Dakota St",
    "sg:city":"Butler",
    "sg:classifiers":[
        {
            "category":"Professional",
            "subcategory":"Lawyer & Legal Services",
            "type":"Services"
        }
    ],
    "sg:phone":"+1 660 679 3161",
    "sg:postcode":"64730",
    "sg:province":"MO",
    "wof:name":"Nordyke Law Offices of",
    "wof:placetype":"venue"
},
  "geometry": {"coordinates":[-94.331767,38.25736],"type":"Point"}
}