{
  "type": "Feature",
  "properties": {
    "iso:country":"US",
    "sg:address":"6043 Lemay Ferry Rd",
    "sg:city":"St Louis",
    "sg:classifiers":[
        {
            "category":"Home & Garden",
            "subcategory":"Garden Supply",
            "type":"Retail Goods"
        },
        {
            "category":"Building & Trades",
            "subcategory":"Landscaping Services",
            "type":"Services"
        }
    ],
    "sg:phone":"+1 314 894 8692",
    "sg:postcode":"63129",
    "sg:province":"MO",
    "sg:tags":[
        "center"
    ],
    "wof:name":"Haegele Nursery & Garden Ctr",
    "wof:placetype":"venue"
},
  "geometry": {"coordinates":[-90.35698499999999,38.465255],"type":"Point"}
}