{
  "type": "Feature",
  "properties": {
    "iso:country":"US",
    "sg:address":"83 State Hwy Hh",
    "sg:city":"Galena",
    "sg:classifiers":[
        {
            "category":"Farming",
            "subcategory":"Orchard",
            "type":"Manufacturing & Wholesale Goods"
        }
    ],
    "sg:phone":"+1 417 272 3699",
    "sg:postcode":"65656",
    "sg:province":"MO",
    "sg:tags":[
        "grove",
        "management"
    ],
    "wof:name":"Table Rock Orchard",
    "wof:placetype":"venue"
},
  "geometry": {"coordinates":[-93.429796,36.742248],"type":"Point"}
}