{
  "type": "Feature",
  "properties": {
    "iso:country":"US",
    "sg:address":"200 S Main St",
    "sg:city":"Webb City",
    "sg:classifiers":[
        {
            "category":"Government",
            "subcategory":"Office",
            "type":"Public Place"
        }
    ],
    "sg:phone":"+1 417 673 4064",
    "sg:postcode":"64870",
    "sg:province":"MO",
    "sg:tags":[
        "village"
    ],
    "wof:name":"WEBB City Collector Ofc",
    "wof:placetype":"venue"
},
  "geometry": {"coordinates":[-94.46321399999999,37.142872],"type":"Point"}
}