{
  "type": "Feature",
  "properties": {
    "iso:country":"US",
    "sg:address":"311 N Lindbergh Blvd",
    "sg:city":"St Louis",
    "sg:classifiers":[
        {
            "category":"Banks & Credit Unions",
            "subcategory":"Investment Brokerage",
            "type":"Services"
        }
    ],
    "sg:phone":"+1 314 872 2900",
    "sg:postcode":"63141",
    "sg:province":"MO",
    "wof:name":"Ark Investments",
    "wof:placetype":"venue"
},
  "geometry": {"coordinates":[-90.40521200000001,38.661038],"type":"Point"}
}