{
  "type": "Feature",
  "properties": {
    "iso:country":"US",
    "sg:address":"631 Loughmor Pass",
    "sg:city":"Saint Charles",
    "sg:classifiers":[
        {
            "category":"Recreation",
            "type":"Entertainment"
        }
    ],
    "sg:phone":"+1 636 939 3608",
    "sg:postcode":"63304",
    "sg:province":"MO",
    "wof:name":"Tennismith",
    "wof:placetype":"venue"
},
  "geometry": {"coordinates":[-90.623744,38.721132],"type":"Point"}
}