{
  "type": "Feature",
  "properties": {
    "iso:country":"US",
    "sg:address":"534 W Walnut St",
    "sg:city":"Springfield",
    "sg:classifiers":[
        {
            "category":"Wholesale",
            "subcategory":"Electrical",
            "type":"Manufacturing & Wholesale Goods"
        }
    ],
    "sg:phone":"+1 417 862 5214",
    "sg:postcode":"65806",
    "sg:province":"MO",
    "sg:tags":[
        "communication",
        "system",
        "systems-wholesale",
        "equipment",
        "radio",
        "manufacturer"
    ],
    "sg:website":"http://www.radiophonewireless.com",
    "wof:name":"Radiophone Engineering Inc.",
    "wof:placetype":"venue"
},
  "geometry": {"coordinates":[-93.29605599999999,37.20719],"type":"Point"}
}