{
  "type": "Feature",
  "properties": {
    "addr:full":"2202 Main St Lexington MO 64067",
    "addr:housenumber":"2202",
    "addr:postcode":"64067",
    "addr:street":"Main St",
    "iso:country":"US",
    "sg:address":"2202 Main St",
    "sg:city":"Lexington",
    "sg:classifiers":[
        {
            "category":"Health Services",
            "subcategory":"Doctor",
            "type":"Services"
        },
        {
            "category":"Health Services",
            "subcategory":"Chiropractor",
            "type":"Services"
        }
    ],
    "sg:phone":"+1 660 259 4323",
    "sg:postcode":"64067",
    "sg:province":"MO",
    "sg:tags":[
        "physician",
        "surgeon",
        "chiropractic"
    ],
    "wof:name":"James P Foltz Dc",
    "wof:placetype":"venue"
},
  "geometry": {"coordinates":[-93.886436,39.18564],"type":"Point"}
}