{
  "type": "Feature",
  "properties": {
    "iso:country":"US",
    "sg:address":"41133 Kelp Rd",
    "sg:city":"Newtown",
    "sg:classifiers":[
        {
            "category":"Professional",
            "subcategory":"Management & Consulting",
            "type":"Services"
        }
    ],
    "sg:phone":"+1 618 946 0418",
    "sg:postcode":"64667",
    "sg:province":"MO",
    "sg:tags":[
        "consultant"
    ],
    "wof:name":"A & S Consulting",
    "wof:placetype":"venue"
},
  "geometry": {"coordinates":[-93.344746,40.352293],"type":"Point"}
}