{
  "type": "Feature",
  "properties": {
    "iso:country":"US",
    "sg:address":"3208 Lemone Industrial Blvd",
    "sg:city":"Columbia",
    "sg:classifiers":[
        {
            "category":"Wholesale",
            "subcategory":"Machinery & Supplies",
            "type":"Manufacturing & Wholesale Goods"
        }
    ],
    "sg:phone":"+1 573 499 9144",
    "sg:postcode":"65201",
    "sg:province":"MO",
    "sg:tags":[
        "equipment",
        "concrete"
    ],
    "wof:name":"Goedecke Co",
    "wof:placetype":"venue"
},
  "geometry": {"coordinates":[-92.291706,38.915349],"type":"Point"}
}