{
  "type": "Feature",
  "properties": {
    "iso:country":"US",
    "sg:address":"401 Bell St",
    "sg:city":"Bonne Terre",
    "sg:classifiers":[
        {
            "category":"Professional",
            "subcategory":"Business Services",
            "type":"Services"
        }
    ],
    "sg:phone":"+1 573 431 4667",
    "sg:postcode":"63628",
    "sg:province":"MO",
    "sg:tags":[
        "auctioneer"
    ],
    "wof:name":"Tooter Gower",
    "wof:placetype":"venue"
},
  "geometry": {"coordinates":[-90.560351,37.916925],"type":"Point"}
}