{
  "type": "Feature",
  "properties": {
    "iso:country":"US",
    "sg:address":"4420 Klable Rd",
    "sg:city":"Barnhart",
    "sg:classifiers":[
        {
            "category":"Building & Trades",
            "subcategory":"Equipment Rental",
            "type":"Services"
        }
    ],
    "sg:phone":"+1 636 942 2366",
    "sg:postcode":"63012",
    "sg:province":"MO",
    "sg:tags":[
        "yard",
        "leasing",
        "store"
    ],
    "wof:name":"Bk Leasing",
    "wof:placetype":"venue"
},
  "geometry": {"coordinates":[-90.4976,38.329152],"type":"Point"}
}