{
  "type": "Feature",
  "properties": {
    "iso:country":"US",
    "sg:address":"906 Woodson Way",
    "sg:city":"Columbia",
    "sg:classifiers":[
        {
            "category":"Health Services",
            "subcategory":"Clinic",
            "type":"Services"
        }
    ],
    "sg:phone":"+1 573 449 3961",
    "sg:postcode":"65201",
    "sg:province":"MO",
    "sg:tags":[
        "banks",
        "blood",
        "center"
    ],
    "wof:name":"Plasma Biological Svc Inc",
    "wof:placetype":"venue"
},
  "geometry": {"coordinates":[-92.327518,38.947364],"type":"Point"}
}