{
  "type": "Feature",
  "properties": {
    "iso:country":"US",
    "sg:address":"3903 Goodfellow Blvd",
    "sg:city":"Saint Louis",
    "sg:classifiers":[
        {
            "category":"Social Services",
            "subcategory":"Child Care",
            "type":"Services"
        }
    ],
    "sg:phone":"+1 314 383 5115",
    "sg:postcode":"63120",
    "sg:province":"MO",
    "sg:tags":[
        "day"
    ],
    "wof:name":"Fairy Tale Day Care Center",
    "wof:placetype":"venue"
},
  "geometry": {"coordinates":[-90.27089700000001,38.6875],"type":"Point"}
}