{
  "type": "Feature",
  "properties": {
    "iso:country":"US",
    "sg:address":"801 Main St",
    "sg:city":"Troy",
    "sg:classifiers":[
        {
            "category":"Organizations",
            "subcategory":"Community Association",
            "type":"Services"
        }
    ],
    "sg:phone":"+1 636 528 4631",
    "sg:postcode":"63379",
    "sg:province":"MO",
    "wof:name":"Optimist Club of Troy",
    "wof:placetype":"venue"
},
  "geometry": {"coordinates":[-90.97994,38.976886],"type":"Point"}
}