{
  "type": "Feature",
  "properties": {
    "iso:country":"US",
    "sg:address":"615 N Broadview St",
    "sg:city":"Cape Girardeau",
    "sg:classifiers":[
        {
            "category":"Retail",
            "subcategory":"Repair Shop",
            "type":"Services"
        }
    ],
    "sg:phone":"+1 573 334 2122",
    "sg:postcode":"63701",
    "sg:province":"MO",
    "sg:tags":[
        "equipment",
        "telephone",
        "system"
    ],
    "wof:name":"Cape Communications Corp",
    "wof:placetype":"venue"
},
  "geometry": {"coordinates":[-89.553774,37.313775],"type":"Point"}
}