{
  "type": "Feature",
  "properties": {
    "iso:country":"US",
    "sg:address":"1125 Lenco Ave",
    "sg:city":"Jackson",
    "sg:classifiers":[
        {
            "category":"Manufacturing",
            "subcategory":"Food",
            "type":"Manufacturing & Wholesale Goods"
        }
    ],
    "sg:phone":"+1 573 243 3134",
    "sg:postcode":"63755",
    "sg:province":"MO",
    "sg:tags":[
        "bottler"
    ],
    "wof:name":"Coca-Cola Bottling Co",
    "wof:placetype":"venue"
},
  "geometry": {"coordinates":[-89.685923,37.3697],"type":"Point"}
}