{
  "type": "Feature",
  "properties": {
    "iso:country":"US",
    "sg:address":"2700 Clay Edwards Dr",
    "sg:city":"Kansas City",
    "sg:classifiers":[
        {
            "category":"Health Services",
            "subcategory":"Clinic",
            "type":"Services"
        }
    ],
    "sg:phone":"+1 816 778 0501",
    "sg:postcode":"64116",
    "sg:province":"MO",
    "wof:name":"Health South HRC Works",
    "wof:placetype":"venue"
},
  "geometry": {"coordinates":[-94.55015899999999,39.150519],"type":"Point"}
}