{
  "type": "Feature",
  "properties": {
    "iso:country":"US",
    "sg:address":"3045 Wild Horse Ln",
    "sg:city":"Foristell",
    "sg:classifiers":[
        {
            "category":"Professional",
            "type":"Services"
        }
    ],
    "sg:phone":"+1 636 463 1310",
    "sg:postcode":"63348",
    "sg:province":"MO",
    "wof:name":"Sammelman Inc",
    "wof:placetype":"venue"
},
  "geometry": {"coordinates":[-90.93926399999999,38.866345],"type":"Point"}
}