{
  "type": "Feature",
  "properties": {
    "iso:country":"US",
    "sg:address":"400 Schindler Rd",
    "sg:city":"Augusta",
    "sg:classifiers":[
        {
            "category":"Personal",
            "subcategory":"Beauty Salon",
            "type":"Services"
        }
    ],
    "sg:phone":"+1 636 482 4060",
    "sg:postcode":"63332",
    "sg:province":"MO",
    "wof:name":"Lisa's Hair Designs",
    "wof:placetype":"venue"
},
  "geometry": {"coordinates":[-90.877357,38.58899],"type":"Point"}
}