{
  "type": "Feature",
  "properties": {
    "iso:country":"US",
    "sg:address":"601 E Walnut St",
    "sg:city":"Columbia",
    "sg:classifiers":[
        {
            "category":"Professional",
            "subcategory":"Lawyer & Legal Services",
            "type":"Services"
        }
    ],
    "sg:phone":"+1 573 882 9701",
    "sg:postcode":"65201",
    "sg:province":"MO",
    "sg:tags":[
        "executive"
    ],
    "wof:name":"Public Defenders Off Area 13",
    "wof:placetype":"venue"
},
  "geometry": {"coordinates":[-92.32965,38.952609],"type":"Point"}
}