{
  "type": "Feature",
  "properties": {
    "iso:country":"US",
    "sg:address":"69 Bellerive Acres",
    "sg:city":"St Louis",
    "sg:classifiers":[
        {
            "category":"Wholesale",
            "subcategory":"Computers",
            "type":"Manufacturing & Wholesale Goods"
        }
    ],
    "sg:phone":"+1 314 381 2299",
    "sg:postcode":"63121",
    "sg:province":"MO",
    "sg:tags":[
        "equipment",
        "processing",
        "datum"
    ],
    "wof:name":"Direct Data Corp",
    "wof:placetype":"venue"
},
  "geometry": {"coordinates":[-90.316025,38.71112],"type":"Point"}
}