{
  "type": "Feature",
  "properties": {
    "iso:country":"US",
    "sg:address":"1926 Richardson Rd",
    "sg:city":"Arnold",
    "sg:classifiers":[
        {
            "category":"Restaurant",
            "type":"Food & Drink"
        }
    ],
    "sg:menulink":"http://www.allmenus.com/mo/arnold/65641-pizza-hut/menu/",
    "sg:phone":"+1 636 467 5909",
    "sg:postcode":"63010",
    "sg:province":"MO",
    "sg:tags":[
        "american",
        "pizza"
    ],
    "wof:name":"Pizza Hut",
    "wof:placetype":"venue"
},
  "geometry": {"coordinates":[-90.38435200000001,38.412026],"type":"Point"}
}