{
  "type": "Feature",
  "properties": {
    "iso:country":"US",
    "sg:address":"813 N Kingshighway Blvd",
    "sg:city":"Saint Louis",
    "sg:classifiers":[
        {
            "category":"Bars & Pubs",
            "subcategory":"Nightclub",
            "type":"Food & Drink"
        }
    ],
    "sg:phone":"+1 314 361 7857",
    "sg:postcode":"63108",
    "sg:province":"MO",
    "sg:tags":[
        "nightlife"
    ],
    "wof:name":"Club Elite",
    "wof:placetype":"venue"
},
  "geometry": {"coordinates":[-90.263397,38.653301],"type":"Point"}
}