{
  "type": "Feature",
  "properties": {
    "iso:country":"US",
    "sg:address":"610 Jeffco Blvd",
    "sg:city":"Arnold",
    "sg:classifiers":[
        {
            "category":"Retail",
            "subcategory":"Laundry & Dry Cleaning",
            "type":"Services"
        }
    ],
    "sg:phone":"+1 636 287 1313",
    "sg:postcode":"63010",
    "sg:province":"MO",
    "sg:tags":[
        "laundries-self",
        "operated",
        "washer",
        "dryer",
        "coin"
    ],
    "wof:name":"Wash City Laundromat",
    "wof:placetype":"venue"
},
  "geometry": {"coordinates":[-90.364942,38.451065],"type":"Point"}
}