{
  "type": "Feature",
  "properties": {
    "iso:country":"US",
    "sg:address":"13900 E Hwy 32",
    "sg:city":"Stockton",
    "sg:classifiers":[
        {
            "category":"Organizations",
            "subcategory":"Religious Organization",
            "type":"Services"
        }
    ],
    "sg:phone":"+1 417 276 5331",
    "sg:postcode":"65785",
    "sg:province":"MO",
    "sg:tags":[
        "church"
    ],
    "wof:name":"Stockton Presbyterian Church",
    "wof:placetype":"venue"
},
  "geometry": {"coordinates":[-93.82534699999999,37.702046],"type":"Point"}
}