{
  "type": "Feature",
  "properties": {
    "iso:country":"US",
    "sg:address":"122 Jefferson Rd",
    "sg:city":"Saint Louis",
    "sg:classifiers":[
        {
            "category":"Real Estate",
            "subcategory":"Real Estate Operator",
            "type":"Services"
        }
    ],
    "sg:phone":"+1 314 961 9289",
    "sg:postcode":"63119",
    "sg:province":"MO",
    "sg:tags":[
        "building",
        "nonresidential"
    ],
    "wof:name":"Hvk Partnership",
    "wof:placetype":"venue"
},
  "geometry": {"coordinates":[-90.363692,38.589406],"type":"Point"}
}