{
  "type": "Feature",
  "properties": {
    "iso:country":"US",
    "sg:address":"403 N Jefferson St",
    "sg:city":"Mexico",
    "sg:classifiers":[
        {
            "category":"Utilities",
            "subcategory":"Water",
            "type":"Services"
        },
        {
            "category":"Building & Trades",
            "subcategory":"Plumbing",
            "type":"Services"
        },
        {
            "category":"Home & Garden",
            "subcategory":"Hardware",
            "type":"Retail Goods"
        }
    ],
    "sg:phone":"+1 573 581 1071",
    "sg:postcode":"65265",
    "sg:province":"MO",
    "sg:tags":[
        "filtration",
        "softening",
        "supply",
        "work",
        "purification",
        "equipment",
        "conditioning"
    ],
    "wof:name":"Carter W D Water Conditioning",
    "wof:placetype":"venue"
},
  "geometry": {"coordinates":[-91.882491,39.174646],"type":"Point"}
}