{
  "type": "Feature",
  "properties": {
    "iso:country":"US",
    "sg:address":"3080 Iron Hill Rd",
    "sg:city":"Union",
    "sg:classifiers":[
        {
            "category":"Education",
            "subcategory":"Vocational School",
            "type":"Public Place"
        }
    ],
    "sg:phone":"+1 636 629 3341",
    "sg:postcode":"63084",
    "sg:province":"MO",
    "wof:name":"Regent Construction Inc",
    "wof:placetype":"venue"
},
  "geometry": {"coordinates":[-90.927285,38.389732],"type":"Point"}
}