{
  "type": "Feature",
  "properties": {
    "iso:country":"US",
    "sg:address":"308 Oakmont Farm Dr",
    "sg:city":"Ballwin",
    "sg:classifiers":[
        {
            "category":"Professional",
            "type":"Services"
        }
    ],
    "sg:phone":"+1 636 207 7132",
    "sg:postcode":"63021",
    "sg:province":"MO",
    "wof:name":"GE Capital Fleet Svc",
    "wof:placetype":"venue"
},
  "geometry": {"coordinates":[-90.576078,38.582648],"type":"Point"}
}