{
  "type": "Feature",
  "properties": {
    "iso:country":"US",
    "sg:address":"104 Main St",
    "sg:city":"Sweet Springs",
    "sg:classifiers":[
        {
            "category":"Organizations",
            "subcategory":"Religious Organization",
            "type":"Services"
        }
    ],
    "sg:phone":"+1 660 335 6919",
    "sg:postcode":"65351",
    "sg:province":"MO",
    "wof:name":"First Baptist Church",
    "wof:placetype":"venue"
},
  "geometry": {"coordinates":[-93.415222,38.963776],"type":"Point"}
}