{
  "type": "Feature",
  "properties": {
    "iso:country":"US",
    "sg:address":"231 S Bemiston Ave",
    "sg:city":"St Louis",
    "sg:classifiers":[
        {
            "category":"Personal",
            "type":"Services"
        }
    ],
    "sg:phone":"+1 314 662 3141",
    "sg:postcode":"63105",
    "sg:province":"MO",
    "sg:tags":[
        "dating"
    ],
    "wof:name":"B Meyer & Assoc",
    "wof:placetype":"venue"
},
  "geometry": {"coordinates":[-90.337445,38.646569],"type":"Point"}
}