{
  "type": "Feature",
  "properties": {
    "iso:country":"US",
    "sg:address":"109 Bosa Dr",
    "sg:city":"Waynesville",
    "sg:classifiers":[
        {
            "category":"Professional",
            "subcategory":"Computer Services",
            "type":"Services"
        }
    ],
    "sg:phone":"+1 573 336 2121",
    "sg:postcode":"65584",
    "sg:province":"MO",
    "sg:tags":[
        "equipment",
        "consultant",
        "sales",
        "internet"
    ],
    "wof:name":"Jobe Internet Services",
    "wof:placetype":"venue"
},
  "geometry": {"coordinates":[-92.137873,37.808281],"type":"Point"}
}