{
  "type": "Feature",
  "properties": {
    "iso:country":"US",
    "sg:address":"1101 Sainte Genevieve Ave",
    "sg:city":"Farmington",
    "sg:classifiers":[
        {
            "category":"Organizations",
            "subcategory":"Religious Organization",
            "type":"Services"
        }
    ],
    "sg:phone":"+1 573 756 7810",
    "sg:postcode":"63640",
    "sg:province":"MO",
    "sg:tags":[
        "church"
    ],
    "wof:name":"Unity Christ Center",
    "wof:placetype":"venue"
},
  "geometry": {"coordinates":[-90.407961,37.77783],"type":"Point"}
}