{
  "type": "Feature",
  "properties": {
    "iso:country":"US",
    "sg:address":"1 N 6th St",
    "sg:city":"Saint Louis",
    "sg:classifiers":[
        {
            "category":"Professional",
            "subcategory":"Advertising",
            "type":"Services"
        }
    ],
    "sg:phone":"+1 314 589 3000",
    "sg:postcode":"63101",
    "sg:province":"MO",
    "sg:tags":[
        "agency"
    ],
    "wof:name":"Mega Advertising Inc",
    "wof:placetype":"venue"
},
  "geometry": {"coordinates":[-90.19080599999999,38.626488],"type":"Point"}
}