{
  "type": "Feature",
  "properties": {
    "iso:country":"US",
    "sg:address":"133 S 11th St",
    "sg:city":"St Louis",
    "sg:classifiers":[
        {
            "category":"Professional",
            "subcategory":"Lawyer & Legal Services",
            "type":"Services"
        }
    ],
    "sg:phone":"+1 314 621 3006",
    "sg:postcode":"63102",
    "sg:province":"MO",
    "sg:tags":[
        "attorney"
    ],
    "sg:website":"www.kimtucker.com",
    "wof:name":"Kimyard H Tucker",
    "wof:placetype":"venue"
},
  "geometry": {"coordinates":[-90.197772,38.625127],"type":"Point"}
}