{
  "type": "Feature",
  "properties": {
    "iso:country":"US",
    "sg:address":"17311 US Hwy 40",
    "sg:city":"Independence",
    "sg:classifiers":[
        {
            "category":"Building & Trades",
            "subcategory":"Construction",
            "type":"Services"
        }
    ],
    "sg:phone":"+1 816 686 3890",
    "sg:postcode":"64055",
    "sg:province":"MO",
    "sg:tags":[
        "hanging",
        "contractor"
    ],
    "wof:name":"Robert Allens Painting",
    "wof:placetype":"venue"
},
  "geometry": {"coordinates":[-94.37570700000001,39.033916],"type":"Point"}
}