{
  "type": "Feature",
  "properties": {
    "iso:country":"US",
    "sg:address":"135 Decora Ct",
    "sg:city":"Elsberry",
    "sg:classifiers":[
        {
            "category":"Freight",
            "type":"Transportation"
        }
    ],
    "sg:phone":"+1 573 898 2136",
    "sg:postcode":"63343",
    "sg:province":"MO",
    "sg:tags":[
        "operator",
        "trucking"
    ],
    "wof:name":"Att Trucking Inc",
    "wof:placetype":"venue"
},
  "geometry": {"coordinates":[-90.820364,39.124277],"type":"Point"}
}