{
  "type": "Feature",
  "properties": {
    "addr:full":"605 E Washington St Hayti MO 63851",
    "addr:housenumber":"605",
    "addr:postcode":"63851",
    "addr:street":"E Washington St",
    "iso:country":"US",
    "sg:address":"605 E Washington St",
    "sg:city":"Hayti",
    "sg:classifiers":[
        {
            "category":"Shopping",
            "subcategory":"Computers & Home Electronics",
            "type":"Retail Goods"
        }
    ],
    "sg:phone":"+1 573 359 6266",
    "sg:postcode":"63851",
    "sg:province":"MO",
    "sg:tags":[
        "high",
        "fidelity",
        "stereophonic"
    ],
    "wof:name":"Rent A Ctr",
    "wof:placetype":"venue"
},
  "geometry": {"coordinates":[-89.745411,36.233912],"type":"Point"}
}