{
  "type": "Feature",
  "properties": {
    "iso:country":"US",
    "sg:address":"1501 Penrose St",
    "sg:city":"St Louis",
    "sg:classifiers":[
        {
            "category":"Organizations",
            "subcategory":"Religious Organization",
            "type":"Services"
        }
    ],
    "sg:phone":"+1 314 531 4221",
    "sg:postcode":"63107",
    "sg:province":"MO",
    "sg:tags":[
        "church"
    ],
    "wof:name":"Revelation Missionary Baptist",
    "wof:placetype":"venue"
},
  "geometry": {"coordinates":[-90.20450599999999,38.666019],"type":"Point"}
}