{
  "type": "Feature",
  "properties": {
    "iso:country":"US",
    "sg:address":"11301 State Hwy 350",
    "sg:city":"Raytown",
    "sg:classifiers":[
        {
            "category":"Autos & Motor Vehicles",
            "subcategory":"Automobile Sales",
            "type":"Retail Goods"
        }
    ],
    "sg:phone":"+1 816 358 2277",
    "sg:postcode":"64138",
    "sg:province":"MO",
    "sg:tags":[
        "car",
        "dealer"
    ],
    "wof:name":"K C Cars4less",
    "wof:placetype":"venue"
},
  "geometry": {"coordinates":[-94.44760599999999,38.976592],"type":"Point"}
}