{
  "type": "Feature",
  "properties": {
    "iso:country":"US",
    "sg:address":"7230 N Lindbergh Blvd",
    "sg:city":"Hazelwood",
    "sg:classifiers":[
        {
            "category":"Autos & Motor Vehicles",
            "subcategory":"Auto Supplies",
            "type":"Retail Goods"
        }
    ],
    "sg:phone":"+1 314 731 7838",
    "sg:postcode":"63042",
    "sg:province":"MO",
    "sg:tags":[
        "automobile",
        "parts",
        "accessory",
        "part",
        "accessories-wholesale",
        "manufacturer"
    ],
    "wof:name":"Motive Parts Company",
    "wof:placetype":"venue"
},
  "geometry": {"coordinates":[-90.355048,38.783955],"type":"Point"}
}