{
  "type": "Feature",
  "properties": {
    "iso:country":"US",
    "sg:address":"5753 State Highway 165",
    "sg:city":"Branson",
    "sg:classifiers":[
        {
            "category":"Restaurant",
            "type":"Food & Drink"
        }
    ],
    "sg:phone":"+1 417 334 0677",
    "sg:postcode":"65616",
    "sg:province":"MO",
    "sg:tags":[
        "mexican"
    ],
    "wof:name":"7 Mares Mexican Restaurant",
    "wof:placetype":"venue"
},
  "geometry": {"coordinates":[-93.31204700000001,36.584531],"type":"Point"}
}