{
  "type": "Feature",
  "properties": {
    "iso:country":"US",
    "sg:address":"2345 McGee St",
    "sg:city":"Kansas City",
    "sg:classifiers":[
        {
            "category":"Shopping",
            "subcategory":"Gifts & Souvenirs",
            "type":"Retail Goods"
        }
    ],
    "sg:phone":"+1 816 474 8627",
    "sg:postcode":"64108",
    "sg:province":"MO",
    "sg:tags":[
        "shop"
    ],
    "wof:name":"W H Smith",
    "wof:placetype":"venue"
},
  "geometry": {"coordinates":[-94.58047999999999,39.085301],"type":"Point"}
}