{
  "type": "Feature",
  "properties": {
    "iso:country":"US",
    "sg:address":"1108 S Birch St",
    "sg:city":"Buffalo",
    "sg:classifiers":[
        {
            "category":"Autos & Motor Vehicles",
            "subcategory":"Auto Supplies",
            "type":"Retail Goods"
        },
        {
            "category":"Manufacturing",
            "subcategory":"Motor Vehicles & Parts",
            "type":"Manufacturing & Wholesale Goods"
        },
        {
            "category":"Retail",
            "subcategory":"Auto Repair",
            "type":"Services"
        }
    ],
    "sg:phone":"+1 417 345 2886",
    "sg:postcode":"65622",
    "sg:province":"MO",
    "sg:tags":[
        "body",
        "buses-distributors",
        "shop",
        "automobile",
        "buses-parts",
        "equipment",
        "parts",
        "accessories-wholesale",
        "painting",
        "repairing",
        "manufacturer"
    ],
    "wof:name":"Premier Body Paint",
    "wof:placetype":"venue"
},
  "geometry": {"coordinates":[-93.102702,37.633823],"type":"Point"}
}