{
  "type": "Feature",
  "properties": {
    "iso:country":"US",
    "sg:address":"86 Woodland Dr",
    "sg:city":"Sullivan",
    "sg:classifiers":[
        {
            "category":"Shopping",
            "subcategory":"Hobbies, Toys, & Games",
            "type":"Retail Goods"
        }
    ],
    "sg:phone":"+1 573 468 5763",
    "sg:postcode":"63080",
    "sg:province":"MO",
    "sg:tags":[
        "equipment",
        "ceramic",
        "supply"
    ],
    "wof:name":"Ceramic Creations",
    "wof:placetype":"venue"
},
  "geometry": {"coordinates":[-91.065532,38.106027],"type":"Point"}
}