{
  "type": "Feature",
  "properties": {
    "iso:country":"US",
    "sg:address":"407 S 4th St",
    "sg:city":"Canton",
    "sg:classifiers":[
        {
            "category":"Organizations",
            "subcategory":"Community Association",
            "type":"Services"
        }
    ],
    "sg:phone":"+1 217 224 1740",
    "sg:postcode":"63435",
    "sg:province":"MO",
    "wof:name":"Chapter N",
    "wof:placetype":"venue"
},
  "geometry": {"coordinates":[-91.518624,40.127448],"type":"Point"}
}