{
  "type": "Feature",
  "properties": {
    "iso:country":"US",
    "sg:address":"3025 Mable St",
    "sg:city":"Trenton",
    "sg:classifiers":[
        {
            "category":"Wholesale",
            "subcategory":"Tobacco Products",
            "type":"Manufacturing & Wholesale Goods"
        }
    ],
    "sg:phone":"+1 660 359 3710",
    "sg:postcode":"64683",
    "sg:province":"MO",
    "sg:tags":[
        "cigarette",
        "cigar",
        "dealer"
    ],
    "wof:name":"Bond Wholesale Inc",
    "wof:placetype":"venue"
},
  "geometry": {"coordinates":[-93.61702699999999,40.09319],"type":"Point"}
}