{
  "type": "Feature",
  "properties": {
    "iso:country":"US",
    "sg:address":"3800 S Ponca Dr",
    "sg:city":"Independence",
    "sg:classifiers":[
        {
            "category":"Building & Trades",
            "subcategory":"Cleaning & Sanitation",
            "type":"Services"
        }
    ],
    "sg:phone":"+1 816 795 6203",
    "sg:postcode":"64057",
    "sg:province":"MO",
    "sg:tags":[
        "maintenance"
    ],
    "wof:name":"Elite Janitorial",
    "wof:placetype":"venue"
},
  "geometry": {"coordinates":[-94.36347000000001,39.052115],"type":"Point"}
}