{
  "type": "Feature",
  "properties": {
    "iso:country":"US",
    "sg:address":"7014 Clayton Rd",
    "sg:city":"Saint Louis",
    "sg:classifiers":[
        {
            "category":"Shopping",
            "subcategory":"Used Merchandise",
            "type":"Retail Goods"
        }
    ],
    "sg:phone":"+1 314 645 2722",
    "sg:postcode":"63117",
    "sg:province":"MO",
    "sg:tags":[
        "antique",
        "gift",
        "furniture"
    ],
    "sg:website":"www.jonpauldesigns.com",
    "wof:name":"Jon Paul Designs & Collectibles",
    "wof:placetype":"venue"
},
  "geometry": {"coordinates":[-90.319298,38.634899],"type":"Point"}
}