{
  "type": "Feature",
  "properties": {
    "iso:country":"US",
    "sg:address":"2754 N US Hwy 67",
    "sg:city":"Florissant",
    "sg:classifiers":[
        {
            "category":"Health Services",
            "subcategory":"Optometrist",
            "type":"Services"
        }
    ],
    "sg:phone":"+1 314 839 4040",
    "sg:postcode":"63033",
    "sg:province":"MO",
    "wof:name":"Eye Care Ctr Of Florissant",
    "wof:placetype":"venue"
},
  "geometry": {"coordinates":[-90.302745,38.807039],"type":"Point"}
}