{
  "type": "Feature",
  "properties": {
    "iso:country":"US",
    "sg:address":"15256 Manchester Rd",
    "sg:city":"Ballwin",
    "sg:classifiers":[
        {
            "category":"Home & Garden",
            "subcategory":"Building Materials",
            "type":"Retail Goods"
        }
    ],
    "sg:phone":"+1 636 256 7740",
    "sg:postcode":"63011",
    "sg:province":"MO",
    "wof:name":"St Loius Stain Glass",
    "wof:placetype":"venue"
},
  "geometry": {"coordinates":[-90.555179,38.592794],"type":"Point"}
}