{
  "type": "Feature",
  "properties": {
    "iso:country":"US",
    "sg:address":"338 Imperial Point Rd",
    "sg:city":"Lake Ozark",
    "sg:classifiers":[
        {
            "category":"Wholesale",
            "subcategory":"Stationery",
            "type":"Manufacturing & Wholesale Goods"
        }
    ],
    "sg:phone":"+1 573 365 3226",
    "sg:postcode":"65049",
    "sg:province":"MO",
    "sg:tags":[
        "product",
        "paper",
        "polyethylene",
        "vinyl"
    ],
    "wof:name":"Refco Inc",
    "wof:placetype":"venue"
},
  "geometry": {"coordinates":[-92.73474899999999,38.207913],"type":"Point"}
}