{
  "type": "Feature",
  "properties": {
    "iso:country":"US",
    "sg:address":"17015 State Route K",
    "sg:city":"Beulah",
    "sg:classifiers":[
        {
            "category":"Place Of Worship",
            "subcategory":"Church",
            "type":"Public Place"
        },
        {
            "category":"Place Of Worship",
            "type":"Public Place"
        }
    ],
    "sg:phone":"+1 573 435 9401",
    "sg:postcode":"65436",
    "sg:province":"MO",
    "sg:tags":[
        "churches-interdenominational",
        "churches-various",
        "denomination"
    ],
    "wof:name":"Rambo Assembly Of God",
    "wof:placetype":"venue"
},
  "geometry": {"coordinates":[-91.88079999999999,37.628489],"type":"Point"}
}