{
  "type": "Feature",
  "properties": {
    "iso:country":"US",
    "sg:address":"105 N Main St",
    "sg:city":"Fayette",
    "sg:classifiers":[
        {
            "category":"Organizations",
            "subcategory":"Professional Association",
            "type":"Services"
        }
    ],
    "sg:phone":"+1 573 446 0600",
    "sg:postcode":"65248",
    "sg:province":"MO",
    "sg:tags":[
        "sale"
    ],
    "wof:name":"Colonial Mercantile Co",
    "wof:placetype":"venue"
},
  "geometry": {"coordinates":[-92.682655,39.146222],"type":"Point"}
}