{
  "type": "Feature",
  "properties": {
    "iso:country":"US",
    "sg:address":"428 N Barr St",
    "sg:city":"Centralia",
    "sg:classifiers":[
        {
            "category":"Retail",
            "subcategory":"Repair Shop",
            "type":"Services"
        }
    ],
    "sg:phone":"+1 573 682 9800",
    "sg:postcode":"65240",
    "sg:province":"MO",
    "sg:tags":[
        "plumbing",
        "drain",
        "cleaning",
        "sewer"
    ],
    "wof:name":"Brown's Plumbing Heating",
    "wof:placetype":"venue"
},
  "geometry": {"coordinates":[-92.139979,39.216298],"type":"Point"}
}