{
  "type": "Feature",
  "properties": {
    "iso:country":"US",
    "sg:address":"506 S Oxford Ave",
    "sg:city":"Independence",
    "sg:classifiers":[
        {
            "category":"Retail",
            "subcategory":"Auto Repair",
            "type":"Services"
        }
    ],
    "sg:phone":"+1 816 833 4414",
    "sg:postcode":"64053",
    "sg:province":"MO",
    "sg:tags":[
        "automobile",
        "restoration",
        "classic"
    ],
    "wof:name":"Body Shop No Fifty Two",
    "wof:placetype":"venue"
},
  "geometry": {"coordinates":[-94.466869,39.103389],"type":"Point"}
}