{
  "type": "Feature",
  "properties": {
    "iso:country":"US",
    "sg:address":"10875 Timber Dr",
    "sg:city":"Rolla",
    "sg:classifiers":[
        {
            "category":"Professional",
            "subcategory":"Engineering",
            "type":"Services"
        }
    ],
    "sg:phone":"+1 573 341 4670",
    "sg:postcode":"65401",
    "sg:province":"MO",
    "wof:name":"Walter Eversman",
    "wof:placetype":"venue"
},
  "geometry": {"coordinates":[-91.71369300000001,37.963491],"type":"Point"}
}