{
  "type": "Feature",
  "properties": {
    "iso:country":"US",
    "sg:address":"21 Center St",
    "sg:city":"Elkland",
    "sg:classifiers":[
        {
            "category":"Farming",
            "subcategory":"Livestock Farm",
            "type":"Manufacturing & Wholesale Goods"
        }
    ],
    "sg:phone":"+1 417 345 8449",
    "sg:postcode":"65656",
    "sg:province":"MO",
    "sg:tags":[
        "dairy",
        "beef",
        "feedlot",
        "cattle"
    ],
    "wof:name":"Hardison Dairy",
    "wof:placetype":"venue"
},
  "geometry": {"coordinates":[-93.503671,36.788752],"type":"Point"}
}