{
  "type": "Feature",
  "properties": {
    "iso:country":"US",
    "sg:address":"621 Landmark Dr",
    "sg:city":"Arnold",
    "sg:classifiers":[
        {
            "category":"Wholesale",
            "subcategory":"Machinery & Supplies",
            "type":"Manufacturing & Wholesale Goods"
        },
        {
            "category":"Professional",
            "subcategory":"Business Services",
            "type":"Services"
        },
        {
            "category":"Recreation",
            "type":"Entertainment"
        },
        {
            "category":"Building & Trades",
            "subcategory":"Landscaping Services",
            "type":"Services"
        },
        {
            "category":"Home & Garden",
            "subcategory":"Garden Supply",
            "type":"Retail Goods"
        },
        {
            "category":"Utilities",
            "subcategory":"Sewage",
            "type":"Services"
        }
    ],
    "sg:phone":"+1 636 475 7522",
    "sg:postcode":"63010",
    "sg:province":"MO",
    "sg:tags":[
        "lawn",
        "installation",
        "snow",
        "light",
        "sprinklers-garden",
        "irrigation",
        "system",
        "removal",
        "decoration",
        "equipment",
        "drainage",
        "contractor",
        "christmas",
        "landscape",
        "consultant"
    ],
    "sg:website":"http://www.h2proinc.com",
    "wof:name":"H 2 Pro, Inc",
    "wof:placetype":"venue"
},
  "geometry": {"coordinates":[-90.42689,38.460369],"type":"Point"}
}