{
  "type": "Feature",
  "properties": {
    "iso:country":"US",
    "sg:address":"100 N Ravine St",
    "sg:city":"Fulton",
    "sg:classifiers":[
        {
            "category":"Shopping",
            "subcategory":"Bicycles & Sporting Goods",
            "type":"Retail Goods"
        }
    ],
    "sg:phone":"+1 573 642 7952",
    "sg:postcode":"65251",
    "sg:province":"MO",
    "wof:name":"Ravine Street Bicycle",
    "wof:placetype":"venue"
},
  "geometry": {"coordinates":[-91.946319,38.844454],"type":"Point"}
}