{
  "type": "Feature",
  "properties": {
    "iso:country":"US",
    "sg:address":"1302 Clarkson Clayton Center",
    "sg:city":"Ballwin",
    "sg:classifiers":[
        {
            "category":"Professional",
            "subcategory":"Lawyer & Legal Services",
            "type":"Services"
        }
    ],
    "sg:phone":"+1 636 394 7400",
    "sg:postcode":"63011",
    "sg:province":"MO",
    "sg:tags":[
        "attorney"
    ],
    "wof:name":"Throneberry Law Offices",
    "wof:placetype":"venue"
},
  "geometry": {"coordinates":[-90.58651,38.603385],"type":"Point"}
}