{
  "type": "Feature",
  "properties": {
    "iso:country":"US",
    "sg:address":"822 N Main St",
    "sg:city":"Gravois Mills",
    "sg:classifiers":[
        {
            "category":"Autos & Motor Vehicles",
            "subcategory":"Automobile Sales",
            "type":"Retail Goods"
        }
    ],
    "sg:phone":"+1 573 374 1313",
    "sg:postcode":"65037",
    "sg:province":"MO",
    "sg:tags":[
        "repair",
        "used",
        "general"
    ],
    "wof:name":"Laurie Motors",
    "wof:placetype":"venue"
},
  "geometry": {"coordinates":[-92.84471600000001,38.211029],"type":"Point"}
}