{
  "type": "Feature",
  "properties": {
    "iso:country":"US",
    "sg:address":"1409 McGee St",
    "sg:city":"Kansas City",
    "sg:classifiers":[
        {
            "category":"Retail",
            "subcategory":"Auto Repair",
            "type":"Services"
        }
    ],
    "sg:phone":"+1 816 421 5342",
    "sg:postcode":"64106",
    "sg:province":"MO",
    "sg:tags":[
        "general"
    ],
    "wof:name":"Downtown Service",
    "wof:placetype":"venue"
},
  "geometry": {"coordinates":[-94.57985499999999,39.096343],"type":"Point"}
}