{
  "type": "Feature",
  "properties": {
    "iso:country":"US",
    "sg:address":"150 Timber Trl",
    "sg:city":"Branson",
    "sg:classifiers":[
        {
            "category":"Professional",
            "subcategory":"Lawyer & Legal Services",
            "type":"Services"
        },
        {
            "category":"Insurance",
            "subcategory":"Title Insurance",
            "type":"Services"
        }
    ],
    "sg:phone":"+1 417 239 3398",
    "sg:postcode":"65616",
    "sg:province":"MO",
    "sg:tags":[
        "plan"
    ],
    "sg:website":"http://www.qtclosings.com",
    "wof:name":"Quality Timeshare Closing Inc",
    "wof:placetype":"venue"
},
  "geometry": {"coordinates":[-93.17998799999999,36.658019],"type":"Point"}
}