{
  "type": "Feature",
  "properties": {
    "iso:country":"US",
    "sg:address":"108 S Main St",
    "sg:city":"Senath",
    "sg:classifiers":[
        {
            "category":"Professional",
            "subcategory":"Management & Consulting",
            "type":"Services"
        },
        {
            "category":"Retail",
            "subcategory":"Funeral Services",
            "type":"Services"
        }
    ],
    "sg:phone":"+1 573 738 2311",
    "sg:postcode":"63876",
    "sg:province":"MO",
    "sg:tags":[
        "director",
        "embalmer",
        "consultant"
    ],
    "wof:name":"Mcdaniel Funeral Services Inc",
    "wof:placetype":"venue"
},
  "geometry": {"coordinates":[-90.159277,36.134052],"type":"Point"}
}