{
  "type": "Feature",
  "properties": {
    "iso:country":"US",
    "sg:address":"3606 NE Grant St",
    "sg:city":"Lees Summit",
    "sg:classifiers":[
        {
            "category":"Arts & Performance",
            "subcategory":"Theater",
            "type":"Entertainment"
        }
    ],
    "sg:phone":"+1 816 525 8718",
    "sg:postcode":"64064",
    "sg:province":"MO",
    "sg:tags":[
        "theatrical",
        "group"
    ],
    "wof:name":"Magical Entertainers Assn",
    "wof:placetype":"venue"
},
  "geometry": {"coordinates":[-94.36989699999999,38.978229],"type":"Point"}
}