{
  "type": "Feature",
  "properties": {
    "iso:country":"US",
    "sg:address":"1605 Fairground Rd",
    "sg:city":"Mexico",
    "sg:classifiers":[
        {
            "category":"Building & Trades",
            "subcategory":"Construction",
            "type":"Services"
        }
    ],
    "sg:phone":"+1 573 582 7087",
    "sg:postcode":"65265",
    "sg:province":"MO",
    "sg:tags":[
        "contractor"
    ],
    "wof:name":"L & S Construction",
    "wof:placetype":"venue"
},
  "geometry": {"coordinates":[-91.89732600000001,39.158119],"type":"Point"}
}