{
  "type": "Feature",
  "properties": {
    "iso:country":"US",
    "sg:address":"10461 Manchester Rd",
    "sg:city":"Saint Louis",
    "sg:classifiers":[
        {
            "category":"Shopping",
            "subcategory":"Florist",
            "type":"Retail Goods"
        }
    ],
    "sg:phone":"+1 314 984 0522",
    "sg:postcode":"63122",
    "sg:province":"MO",
    "wof:name":"Flower Box",
    "wof:placetype":"venue"
},
  "geometry": {"coordinates":[-90.399968,38.600697],"type":"Point"}
}