{
  "type": "Feature",
  "properties": {
    "iso:country":"US",
    "sg:address":"717 Berick Dr",
    "sg:city":"Saint Louis",
    "sg:classifiers":[
        {
            "category":"Retail",
            "subcategory":"Animal Services",
            "type":"Services"
        }
    ],
    "sg:phone":"+1 314 994 1997",
    "sg:postcode":"63132",
    "sg:province":"MO",
    "wof:name":"Paws On Go",
    "wof:placetype":"venue"
},
  "geometry": {"coordinates":[-90.356092,38.662708],"type":"Point"}
}