{
  "type": "Feature",
  "properties": {
    "iso:country":"US",
    "sg:address":"20926 Timber Shores Rd",
    "sg:city":"Rocky Mount",
    "sg:classifiers":[
        {
            "category":"Freight",
            "type":"Transportation"
        },
        {
            "category":"Retail",
            "subcategory":"Repair Shop",
            "type":"Services"
        }
    ],
    "sg:phone":"+1 573 964 0484",
    "sg:postcode":"65072",
    "sg:province":"MO",
    "sg:tags":[
        "cargo",
        "handler",
        "marine",
        "welding"
    ],
    "wof:name":"Bill's Dock Co",
    "wof:placetype":"venue"
},
  "geometry": {"coordinates":[-92.69749299999999,38.24364],"type":"Point"}
}