{
  "type": "Feature",
  "properties": {
    "iso:country":"US",
    "sg:address":"102 N Range Line Rd",
    "sg:city":"Joplin",
    "sg:classifiers":[
        {
            "category":"Shopping",
            "subcategory":"Computers & Home Electronics",
            "type":"Retail Goods"
        }
    ],
    "sg:phone":"+1 417 623 5004",
    "sg:postcode":"64801",
    "sg:province":"MO",
    "sg:tags":[
        "game",
        "video"
    ],
    "wof:name":"Game Exchange",
    "wof:placetype":"venue"
},
  "geometry": {"coordinates":[-94.476951,37.093638],"type":"Point"}
}