{
  "type": "Feature",
  "properties": {
    "iso:country":"US",
    "sg:address":"17103 Co Rd 8190",
    "sg:city":"Newburg",
    "sg:classifiers":[
        {
            "category":"Utilities",
            "subcategory":"Refuse",
            "type":"Services"
        }
    ],
    "sg:phone":"+1 573 762 3707",
    "sg:postcode":"65550",
    "sg:province":"MO",
    "sg:tags":[
        "garbage",
        "collection"
    ],
    "wof:name":"WCA Waste Corp",
    "wof:placetype":"venue"
},
  "geometry": {"coordinates":[-91.888818,37.950544],"type":"Point"}
}