{
  "type": "Feature",
  "properties": {
    "addr:full":"13307 Manchester Rd Saint Louis MO 63131",
    "addr:housenumber":"13307",
    "addr:postcode":"63131",
    "addr:street":"Manchester Rd",
    "iso:country":"US",
    "sg:address":"13307 Manchester Rd",
    "sg:city":"Saint Louis",
    "sg:classifiers":[
        {
            "category":"Restaurant",
            "type":"Food & Drink"
        }
    ],
    "sg:menulink":"http://www.allmenus.com/mo/missouri-river/104715-noodles--company/menu/",
    "sg:phone":"+1 314 966 3708",
    "sg:postcode":"63131",
    "sg:province":"MO",
    "sg:tags":[
        "noodle",
        "bar",
        "salad",
        "chinese",
        "japanese",
        "soup",
        "american",
        "asian",
        "thai",
        "italian"
    ],
    "wof:name":"Noodles & Company",
    "wof:placetype":"venue"
},
  "geometry": {"coordinates":[-90.466295,38.601028],"type":"Point"}
}