{
  "type": "Feature",
  "properties": {
    "iso:country":"US",
    "sg:address":"10617 Lawrence 1082",
    "sg:city":"Mount Vernon",
    "sg:classifiers":[
        {
            "category":"Farming",
            "subcategory":"Farm",
            "type":"Manufacturing & Wholesale Goods"
        }
    ],
    "sg:phone":"+1 417 285 3381",
    "sg:postcode":"65712",
    "sg:province":"MO",
    "sg:tags":[
        "crop",
        "general"
    ],
    "wof:name":"Alan Scrivner",
    "wof:placetype":"venue"
},
  "geometry": {"coordinates":[-93.922139,37.125858],"type":"Point"}
}