{
  "type": "Feature",
  "properties": {
    "iso:country":"US",
    "sg:address":"2226 S Main St",
    "sg:city":"Joplin",
    "sg:classifiers":[
        {
            "category":"Shopping",
            "subcategory":"Used Merchandise",
            "type":"Retail Goods"
        }
    ],
    "sg:phone":"+1 417 623 5226",
    "sg:postcode":"64804",
    "sg:province":"MO",
    "wof:name":"Just In Time Fashion Resale",
    "wof:placetype":"venue"
},
  "geometry": {"coordinates":[-94.514369,37.066214],"type":"Point"}
}