{
  "type": "Feature",
  "properties": {
    "iso:country":"US",
    "sg:address":"10951 E Bozarth Ln",
    "sg:city":"Columbia",
    "sg:classifiers":[
        {
            "category":"Retail",
            "subcategory":"Repair Shop",
            "type":"Services"
        }
    ],
    "sg:phone":"+1 573 474 6209",
    "sg:postcode":"65201",
    "sg:province":"MO",
    "sg:tags":[
        "upholsterer"
    ],
    "wof:name":"Terwelp Upholstery Inc",
    "wof:placetype":"venue"
},
  "geometry": {"coordinates":[-92.167571,38.947685],"type":"Point"}
}