{
  "type": "Feature",
  "properties": {
    "iso:country":"US",
    "sg:address":"18706 State Hwy Kk",
    "sg:city":"Burlington Junction",
    "sg:phone":"+1 660 725 4555",
    "sg:postcode":"64428",
    "sg:province":"MO",
    "sg:tags":[
        "farm",
        "corn",
        "soybean"
    ],
    "wof:name":"Roy Lyle",
    "wof:placetype":"venue"
},
  "geometry": {"coordinates":[-95.120012,40.452466],"type":"Point"}
}