{
  "type": "Feature",
  "properties": {
    "iso:country":"US",
    "sg:address":"2508 Brenna Ct",
    "sg:city":"Saint Louis",
    "sg:classifiers":[
        {
            "category":"Utilities",
            "type":"Services"
        }
    ],
    "sg:phone":"+1 314 846 6499",
    "sg:postcode":"63129",
    "sg:province":"MO",
    "sg:tags":[
        "sanitary"
    ],
    "wof:name":"P Novara",
    "wof:placetype":"venue"
},
  "geometry": {"coordinates":[-90.309224,38.451438],"type":"Point"}
}