{
  "type": "Feature",
  "properties": {
    "iso:country":"US",
    "sg:address":"3011 Paddlewheel Ct",
    "sg:city":"Saint Charles",
    "sg:classifiers":[
        {
            "category":"Building & Trades",
            "subcategory":"Cleaning & Sanitation",
            "type":"Services"
        }
    ],
    "sg:phone":"+1 636 578 3604",
    "sg:postcode":"63303",
    "sg:province":"MO",
    "sg:tags":[
        "maintenance"
    ],
    "wof:name":"It Brigade Inc",
    "wof:placetype":"venue"
},
  "geometry": {"coordinates":[-90.544042,38.736698],"type":"Point"}
}