{
  "type": "Feature",
  "properties": {
    "iso:country":"US",
    "sg:address":"4200 S Quail Creek Ave",
    "sg:city":"Springfield",
    "sg:classifiers":[
        {
            "category":"Restaurant",
            "type":"Food & Drink"
        }
    ],
    "sg:phone":"+1 417 887 0942",
    "sg:postcode":"65810",
    "sg:province":"MO",
    "sg:tags":[
        "eating"
    ],
    "wof:name":"Taco Bell",
    "wof:placetype":"venue"
},
  "geometry": {"coordinates":[-93.31159,37.1376],"type":"Point"}
}