{
  "type": "Feature",
  "properties": {
    "iso:country":"US",
    "sg:address":"301 N Warson Rd",
    "sg:city":"St Louis",
    "sg:classifiers":[
        {
            "category":"Autos & Motor Vehicles",
            "subcategory":"Fuel & Gas Station",
            "type":"Retail Goods"
        }
    ],
    "sg:phone":"+1 314 993 9962",
    "sg:postcode":"63141",
    "sg:province":"MO",
    "sg:tags":[
        "oil"
    ],
    "wof:name":"Ladue Automotive Svc Inc",
    "wof:placetype":"venue"
},
  "geometry": {"coordinates":[-90.39523699999999,38.660368],"type":"Point"}
}