{
  "type": "Feature",
  "properties": {
    "iso:country":"US",
    "sg:address":"6800 Langley Ave",
    "sg:city":"St Louis",
    "sg:classifiers":[
        {
            "category":"Building & Trades",
            "subcategory":"Construction",
            "type":"Services"
        }
    ],
    "sg:phone":"+1 314 832 1422",
    "sg:postcode":"63123",
    "sg:province":"MO",
    "sg:tags":[
        "concrete",
        "contractor"
    ],
    "wof:name":"Stika Brothers Concrete Constr",
    "wof:placetype":"venue"
},
  "geometry": {"coordinates":[-90.32956299999999,38.560935],"type":"Point"}
}