{
  "type": "Feature",
  "properties": {
    "iso:country":"US",
    "sg:address":"1211 W 16th St",
    "sg:city":"Maryville",
    "sg:classifiers":[
        {
            "category":"Real Estate",
            "subcategory":"Real Estate Operator",
            "type":"Services"
        }
    ],
    "sg:phone":"+1 660 582 7725",
    "sg:postcode":"64468",
    "sg:province":"MO",
    "sg:tags":[
        "building",
        "apartment"
    ],
    "wof:name":"Village O Apartments Inc",
    "wof:placetype":"venue"
},
  "geometry": {"coordinates":[-94.887056,40.360388],"type":"Point"}
}