{
  "type": "Feature",
  "properties": {
    "iso:country":"US",
    "sg:address":"126 Beaver St",
    "sg:city":"Granby",
    "sg:classifiers":[
        {
            "category":"Utilities",
            "subcategory":"Telephone",
            "type":"Services"
        },
        {
            "category":"Professional",
            "subcategory":"Computer Services",
            "type":"Services"
        }
    ],
    "sg:phone":"+1 417 472 5726",
    "sg:postcode":"64831",
    "sg:province":"MO",
    "sg:tags":[
        "distance",
        "long",
        "internet"
    ],
    "wof:name":"Stouffer Communications Long",
    "wof:placetype":"venue"
},
  "geometry": {"coordinates":[-94.444289,36.650156],"type":"Point"}
}