{
  "type": "Feature",
  "properties": {
    "iso:country":"US",
    "sg:address":"12721 Carrollton Industrl Ct",
    "sg:city":"Hazelwood",
    "sg:classifiers":[
        {
            "category":"Freight",
            "type":"Transportation"
        }
    ],
    "sg:phone":"+1 314 291 7100",
    "sg:postcode":"63044",
    "sg:province":"MO",
    "sg:tags":[
        "delivery"
    ],
    "sg:website":"www.straightshotexpress.com",
    "wof:name":"Straight Shot Express",
    "wof:placetype":"venue"
},
  "geometry": {"coordinates":[-90.43031999999999,38.763058],"type":"Point"}
}