{
  "type": "Feature",
  "properties": {
    "iso:country":"US",
    "sg:address":"9294 Dielman Industrial Dr",
    "sg:city":"St Louis",
    "sg:classifiers":[
        {
            "category":"Building & Trades",
            "subcategory":"Pest Control",
            "type":"Services"
        },
        {
            "category":"Utilities",
            "type":"Services"
        }
    ],
    "sg:phone":"+1 314 835 9361",
    "sg:postcode":"63132",
    "sg:province":"MO",
    "sg:tags":[
        "fly",
        "abatement",
        "specialized",
        "mosquito"
    ],
    "wof:name":"United Mosquito & Fly Control",
    "wof:placetype":"venue"
},
  "geometry": {"coordinates":[-90.373272,38.676731],"type":"Point"}
}