{
  "type": "Feature",
  "properties": {
    "iso:country":"US",
    "sg:address":"10801 NE Reinking Rd",
    "sg:city":"Kansas City",
    "sg:classifiers":[
        {
            "category":"Insurance",
            "subcategory":"Insurance Agent",
            "type":"Services"
        }
    ],
    "sg:phone":"+1 816 792 3663",
    "sg:postcode":"64156",
    "sg:province":"MO",
    "wof:name":"Viatical Settlements Inc",
    "wof:placetype":"venue"
},
  "geometry": {"coordinates":[-94.501436,39.295474],"type":"Point"}
}