{
  "type": "Feature",
  "properties": {
    "iso:country":"US",
    "sg:address":"13144 Keene Ln",
    "sg:city":"Neosho",
    "sg:classifiers":[
        {
            "category":"Wholesale",
            "subcategory":"Electrical",
            "type":"Manufacturing & Wholesale Goods"
        },
        {
            "category":"Shopping",
            "subcategory":"Computers & Home Electronics",
            "type":"Retail Goods"
        }
    ],
    "sg:phone":"+1 417 451 6829",
    "sg:postcode":"64850",
    "sg:province":"MO",
    "sg:tags":[
        "communication",
        "2",
        "radio",
        "system"
    ],
    "wof:name":"Southwest Communications",
    "wof:placetype":"venue"
},
  "geometry": {"coordinates":[-94.406874,36.879006],"type":"Point"}
}