{
  "type": "Feature",
  "properties": {
    "iso:country":"US",
    "sg:address":"145 Eugene Field Rd",
    "sg:city":"Kansas City",
    "sg:classifiers":[
        {
            "category":"Building & Trades",
            "subcategory":"Construction",
            "type":"Services"
        },
        {
            "category":"Building & Trades",
            "subcategory":"Plumbing",
            "type":"Services"
        }
    ],
    "sg:phone":"+1 816 455 5250",
    "sg:postcode":"64119",
    "sg:province":"MO",
    "sg:tags":[
        "sheet",
        "work",
        "metal",
        "contractor"
    ],
    "wof:name":"American Sheet Metal Inc",
    "wof:placetype":"venue"
},
  "geometry": {"coordinates":[-94.50716300000001,39.200431],"type":"Point"}
}