{
  "type": "Feature",
  "properties": {
    "iso:country":"US",
    "sg:address":"2507 NE Shady Lane Dr",
    "sg:city":"Kansas City",
    "sg:classifiers":[
        {
            "category":"Retail",
            "subcategory":"Auto Repair",
            "type":"Services"
        }
    ],
    "sg:phone":"+1 816 270 0559",
    "sg:postcode":"64118",
    "sg:province":"MO",
    "sg:tags":[
        "general"
    ],
    "wof:name":"Mitchell Repair",
    "wof:placetype":"venue"
},
  "geometry": {"coordinates":[-94.550799,39.206626],"type":"Point"}
}