{
  "type": "Feature",
  "properties": {
    "iso:country":"US",
    "sg:address":"207 Old Glory Rd",
    "sg:city":"Montreal",
    "sg:classifiers":[
        {
            "category":"Autos & Motor Vehicles",
            "subcategory":"Auto Supplies",
            "type":"Retail Goods"
        },
        {
            "category":"Retail",
            "subcategory":"Auto Repair",
            "type":"Services"
        }
    ],
    "sg:phone":"+1 573 346 4160",
    "sg:postcode":"65591",
    "sg:province":"MO",
    "sg:tags":[
        "body",
        "lettering",
        "automobile",
        "truck",
        "painting",
        "repairing"
    ],
    "wof:name":"Kustom Body Shop",
    "wof:placetype":"venue"
},
  "geometry": {"coordinates":[-92.65908,38.04284],"type":"Point"}
}