{
  "type": "Feature",
  "properties": {
    "iso:country":"US",
    "sg:address":"4210 NE Edmonson Ct",
    "sg:city":"Lees Summit",
    "sg:classifiers":[
        {
            "category":"Personal",
            "type":"Services"
        },
        {
            "category":"Professional",
            "subcategory":"Management & Consulting",
            "type":"Services"
        }
    ],
    "sg:phone":"+1 816 373 0213",
    "sg:postcode":"64064",
    "sg:province":"MO",
    "sg:tags":[
        "party",
        "planning"
    ],
    "wof:name":"Event Specialists Inc",
    "wof:placetype":"venue"
},
  "geometry": {"coordinates":[-94.360669,38.989983],"type":"Point"}
}