{
  "type": "Feature",
  "properties": {
    "iso:country":"US",
    "sg:address":"310 Patton St",
    "sg:city":"Moberly",
    "sg:classifiers":[
        {
            "category":"Building & Trades",
            "subcategory":"Construction",
            "type":"Services"
        }
    ],
    "sg:phone":"+1 660 263 3294",
    "sg:postcode":"65270",
    "sg:province":"MO",
    "sg:tags":[
        "house"
    ],
    "wof:name":"Magic City Builders",
    "wof:placetype":"venue"
},
  "geometry": {"coordinates":[-92.43298799999999,39.43304],"type":"Point"}
}