{
  "type": "Feature",
  "properties": {
    "iso:country":"US",
    "sg:address":"3135 Meramec St",
    "sg:city":"Saint Louis",
    "sg:classifiers":[
        {
            "category":"Travel",
            "subcategory":"Hotels & Motels",
            "type":"Entertainment"
        }
    ],
    "sg:phone":"+1 314 351 4988",
    "sg:postcode":"63118",
    "sg:province":"MO",
    "sg:tags":[
        "membership",
        "lodging"
    ],
    "wof:name":"Laclede Home Association Inc",
    "wof:placetype":"venue"
},
  "geometry": {"coordinates":[-90.239688,38.580428],"type":"Point"}
}