{
  "type": "Feature",
  "properties": {
    "iso:country":"US",
    "sg:address":"18931 E Valley View Pkwy",
    "sg:city":"Independence",
    "sg:classifiers":[
        {
            "category":"Shopping",
            "type":"Retail Goods"
        }
    ],
    "sg:phone":"+1 816 502 2702",
    "sg:postcode":"64055",
    "sg:province":"MO",
    "sg:tags":[
        "telephone",
        "cellular"
    ],
    "wof:name":"Commenco Inc",
    "wof:placetype":"venue"
},
  "geometry": {"coordinates":[-94.349114,39.038333],"type":"Point"}
}