{
  "type": "Feature",
  "properties": {
    "iso:country":"US",
    "sg:address":"1515 Hazel St Ste 201",
    "sg:city":"Carthage",
    "sg:classifiers":[
        {
            "category":"Professional",
            "subcategory":"Management & Consulting",
            "type":"Services"
        }
    ],
    "sg:phone":"+1 417 237 0070",
    "sg:postcode":"64836",
    "sg:province":"MO",
    "sg:tags":[
        "consultant"
    ],
    "wof:name":"Psychological Associates",
    "wof:placetype":"venue"
},
  "geometry": {"coordinates":[-94.318938,37.163345],"type":"Point"}
}