{
  "type": "Feature",
  "properties": {
    "iso:country":"US",
    "sg:address":"214 Hunter St",
    "sg:city":"Charleston",
    "sg:classifiers":[
        {
            "category":"Retail",
            "subcategory":"Animal Services",
            "type":"Services"
        }
    ],
    "sg:phone":"+1 573 683 2790",
    "sg:postcode":"63834",
    "sg:province":"MO",
    "wof:name":"Green Enterprises",
    "wof:placetype":"venue"
},
  "geometry": {"coordinates":[-89.348377,36.926064],"type":"Point"}
}