{
  "type": "Feature",
  "properties": {
    "iso:country":"US",
    "sg:address":"4331 Natural Bridge Ave",
    "sg:city":"St Louis",
    "sg:classifiers":[
        {
            "category":"Food & Beverages",
            "subcategory":"Groceries & Convenience Stores",
            "type":"Retail Goods"
        }
    ],
    "sg:phone":"+1 314 383 2273",
    "sg:postcode":"63115",
    "sg:province":"MO",
    "sg:tags":[
        "grocer"
    ],
    "wof:name":"Schnucks",
    "wof:placetype":"venue"
},
  "geometry": {"coordinates":[-90.23596499999999,38.669624],"type":"Point"}
}