{
  "type": "Feature",
  "properties": {
    "iso:country":"US",
    "sg:address":"301 W Main St",
    "sg:city":"Malden",
    "sg:classifiers":[
        {
            "category":"Retail",
            "subcategory":"Repair Shop",
            "type":"Services"
        }
    ],
    "sg:phone":"+1 573 276 2616",
    "sg:postcode":"63863",
    "sg:province":"MO",
    "wof:name":"Moore Electric",
    "wof:placetype":"venue"
},
  "geometry": {"coordinates":[-89.969959,36.558302],"type":"Point"}
}