{
  "type": "Feature",
  "properties": {
    "iso:country":"US",
    "sg:address":"2009 Brighton Ave",
    "sg:city":"Kansas City",
    "sg:classifiers":[
        {
            "category":"Professional",
            "type":"Services"
        }
    ],
    "sg:phone":"+1 816 241 6599",
    "sg:postcode":"64127",
    "sg:province":"MO",
    "wof:name":"Chocolate Ta",
    "wof:placetype":"venue"
},
  "geometry": {"coordinates":[-94.524333,39.0853],"type":"Point"}
}