{
  "type": "Feature",
  "properties": {
    "iso:country":"US",
    "sg:address":"10505 State Hwy N",
    "sg:city":"Mount Vernon",
    "sg:classifiers":[
        {
            "category":"Professional",
            "subcategory":"Business Services",
            "type":"Services"
        }
    ],
    "sg:phone":"+1 417 466 4912",
    "sg:postcode":"65712",
    "sg:province":"MO",
    "sg:tags":[
        "personal",
        "broker",
        "agent"
    ],
    "wof:name":"Paintings By Becky",
    "wof:placetype":"venue"
},
  "geometry": {"coordinates":[-92.85426699999999,37.1742],"type":"Point"}
}