{
  "type": "Feature",
  "properties": {
    "iso:country":"US",
    "sg:address":"1435 Wibracht Pl",
    "sg:city":"Saint Louis",
    "sg:classifiers":[
        {
            "category":"Social Services",
            "subcategory":"Child Care",
            "type":"Services"
        }
    ],
    "sg:phone":"+1 314 432 4054",
    "sg:postcode":"63132",
    "sg:province":"MO",
    "sg:tags":[
        "day"
    ],
    "wof:name":"Christine Moore",
    "wof:placetype":"venue"
},
  "geometry": {"coordinates":[-90.377484,38.685776],"type":"Point"}
}