{
  "type": "Feature",
  "properties": {
    "iso:country":"US",
    "sg:address":"18921 E Valley View Pkwy G",
    "sg:city":"Independence",
    "sg:classifiers":[
        {
            "category":"Wholesale",
            "subcategory":"Machinery & Supplies",
            "type":"Manufacturing & Wholesale Goods"
        }
    ],
    "sg:phone":"+1 816 358 5591",
    "sg:postcode":"64055",
    "sg:province":"MO",
    "sg:tags":[
        "industrial",
        "equipment",
        "used",
        "machinery-new",
        "supplies-wholesale"
    ],
    "sg:website":"http://www.armathan.com",
    "wof:name":"Arrowhead Supply Company",
    "wof:placetype":"venue"
},
  "geometry": {"coordinates":[-94.356286,39.034002],"type":"Point"}
}