{
  "type": "Feature",
  "properties": {
    "iso:country":"US",
    "sg:address":"65 Grandview Plaza Shopping Center",
    "sg:city":"Florissant",
    "sg:classifiers":[
        {
            "category":"Government",
            "subcategory":"Office",
            "type":"Public Place"
        }
    ],
    "sg:phone":"+1 314 831 0915",
    "sg:postcode":"63033",
    "sg:province":"MO",
    "sg:tags":[
        "armed",
        "national",
        "force",
        "security",
        "recruiting"
    ],
    "wof:name":"US Recruiting Air Force",
    "wof:placetype":"venue"
},
  "geometry": {"coordinates":[-90.308879,38.774217],"type":"Point"}
}