{
  "type": "Feature",
  "properties": {
    "iso:country":"US",
    "sg:address":"11205 Twitty Dr",
    "sg:city":"Rolla",
    "sg:classifiers":[
        {
            "category":"Wholesale",
            "subcategory":"Hardware",
            "type":"Manufacturing & Wholesale Goods"
        }
    ],
    "sg:phone":"+1 573 308 1859",
    "sg:postcode":"65401",
    "sg:province":"MO",
    "sg:tags":[
        "plumbing",
        "fixture",
        "supply"
    ],
    "wof:name":"Rolla Winnelson",
    "wof:placetype":"venue"
},
  "geometry": {"coordinates":[-91.756399,37.96856],"type":"Point"}
}