{
  "type": "Feature",
  "properties": {
    "iso:country":"US",
    "sg:address":"11500 Olive Blvd",
    "sg:city":"St Louis",
    "sg:classifiers":[
        {
            "category":"Insurance",
            "subcategory":"Insurance Agent",
            "type":"Services"
        }
    ],
    "sg:phone":"+1 314 432 6676",
    "sg:postcode":"63141",
    "sg:province":"MO",
    "wof:name":"Robert Grone Insurance",
    "wof:placetype":"venue"
},
  "geometry": {"coordinates":[-90.438537,38.670988],"type":"Point"}
}