{
  "type": "Feature",
  "properties": {
    "iso:country":"US",
    "sg:address":"5201 N Belt Hwy",
    "sg:city":"St Joseph",
    "sg:classifiers":[
        {
            "category":"Shopping",
            "type":"Retail Goods"
        }
    ],
    "sg:phone":"+1 816 233 3082",
    "sg:postcode":"64506",
    "sg:province":"MO",
    "sg:tags":[
        "pet",
        "food",
        "supply"
    ],
    "wof:name":"PETCO",
    "wof:placetype":"venue"
},
  "geometry": {"coordinates":[-94.814955,39.813229],"type":"Point"}
}