{
  "type": "Feature",
  "properties": {
    "addr:full":"2660 E 32nd St Joplin MO 64804",
    "addr:housenumber":"2660",
    "addr:postcode":"64804",
    "addr:street":"E 32Nd St",
    "iso:country":"US",
    "sg:address":"2660 E 32nd St",
    "sg:city":"Joplin",
    "sg:classifiers":[
        {
            "category":"Professional",
            "subcategory":"Employment Agencies",
            "type":"Services"
        }
    ],
    "sg:phone":"+1 417 781 8572",
    "sg:postcode":"64804",
    "sg:province":"MO",
    "wof:name":"Manpower",
    "wof:placetype":"venue"
},
  "geometry": {"coordinates":[-94.482332,37.054725],"type":"Point"}
}