{
  "type": "Feature",
  "properties": {
    "iso:country":"US",
    "sg:address":"2984 State Hwy K",
    "sg:city":"Oak Ridge",
    "sg:classifiers":[
        {
            "category":"Autos & Motor Vehicles",
            "subcategory":"Fuel & Gas Station",
            "type":"Retail Goods"
        }
    ],
    "sg:phone":"+1 573 788 2700",
    "sg:postcode":"63703",
    "sg:province":"MO",
    "sg:tags":[
        "station",
        "gasoline"
    ],
    "wof:name":"Sewing Mobile",
    "wof:placetype":"venue"
},
  "geometry": {"coordinates":[-89.567459,37.300964],"type":"Point"}
}