{
  "type": "Feature",
  "properties": {
    "iso:country":"US",
    "sg:address":"9001 Newby St",
    "sg:city":"St Louis",
    "sg:classifiers":[
        {
            "category":"Social Services",
            "subcategory":"Child Care",
            "type":"Services"
        }
    ],
    "sg:phone":"+1 314 830 3153",
    "sg:postcode":"63147",
    "sg:province":"MO",
    "wof:name":"Jelly Beans Daycare Inc",
    "wof:placetype":"venue"
},
  "geometry": {"coordinates":[-90.234858,38.722069],"type":"Point"}
}