{
  "type": "Feature",
  "properties": {
    "iso:country":"US",
    "sg:address":"12060 Manchester Rd",
    "sg:city":"St Louis",
    "sg:classifiers":[
        {
            "category":"Insurance",
            "subcategory":"Insurance Agent",
            "type":"Services"
        }
    ],
    "sg:phone":"+1 314 821 3300",
    "sg:postcode":"63131",
    "sg:province":"MO",
    "wof:name":"All Insurance LLC",
    "wof:placetype":"venue"
},
  "geometry": {"coordinates":[-90.43711,38.602121],"type":"Point"}
}