{
  "type": "Feature",
  "properties": {
    "iso:country":"US",
    "sg:address":"11881 Co Rd 7690",
    "sg:city":"Caulfield",
    "sg:classifiers":[
        {
            "category":"Building & Trades",
            "subcategory":"Construction",
            "type":"Services"
        }
    ],
    "sg:phone":"+1 417 284 3771",
    "sg:postcode":"65626",
    "sg:province":"AR",
    "sg:tags":[
        "house"
    ],
    "wof:name":"Ross Construction",
    "wof:placetype":"venue"
},
  "geometry": {"coordinates":[-92.087075,36.619824],"type":"Point"}
}