{
  "type": "Feature",
  "properties": {
    "iso:country":"US",
    "sg:address":"1908 Walnut St",
    "sg:city":"Higginsville",
    "sg:classifiers":[
        {
            "category":"Social Services",
            "subcategory":"Adult Care",
            "type":"Services"
        }
    ],
    "sg:phone":"+1 660 584 7682",
    "sg:postcode":"64037",
    "sg:province":"MO",
    "sg:tags":[
        "residential"
    ],
    "wof:name":"Covenant House",
    "wof:placetype":"venue"
},
  "geometry": {"coordinates":[-93.71844400000001,39.075136],"type":"Point"}
}