{
  "type": "Feature",
  "properties": {
    "iso:country":"US",
    "sg:address":"8175 Big Bend Blvd",
    "sg:city":"Saint Louis",
    "sg:classifiers":[
        {
            "category":"Health Services",
            "subcategory":"Doctor",
            "type":"Services"
        }
    ],
    "sg:phone":"+1 314 961 4295",
    "sg:postcode":"63119",
    "sg:province":"MO",
    "sg:tags":[
        "medical"
    ],
    "wof:name":"Tenet",
    "wof:placetype":"venue"
},
  "geometry": {"coordinates":[-90.339547,38.591194],"type":"Point"}
}