{
  "type": "Feature",
  "properties": {
    "iso:country":"US",
    "sg:address":"101 N Commercial St",
    "sg:city":"Crocker",
    "sg:classifiers":[
        {
            "category":"Health Services",
            "subcategory":"Doctor",
            "type":"Services"
        }
    ],
    "sg:phone":"+1 573 736 2422",
    "sg:postcode":"65452",
    "sg:province":"MO",
    "sg:tags":[
        "clinic"
    ],
    "wof:name":"Crocker Medical Ctr",
    "wof:placetype":"venue"
},
  "geometry": {"coordinates":[-92.263818,37.950067],"type":"Point"}
}