{
  "type": "Feature",
  "properties": {
    "iso:country":"US",
    "sg:address":"1414 S Glenstone Ave",
    "sg:city":"Springfield",
    "sg:classifiers":[
        {
            "category":"Professional",
            "subcategory":"Employment Agencies",
            "type":"Services"
        }
    ],
    "sg:phone":"+1 417 890 0575",
    "sg:postcode":"65804",
    "sg:province":"MO",
    "wof:name":"Labor Finders",
    "wof:placetype":"venue"
},
  "geometry": {"coordinates":[-93.262158,37.188275],"type":"Point"}
}