{
  "type": "Feature",
  "properties": {
    "iso:country":"US",
    "sg:address":"34780 Brown Rd",
    "sg:city":"Rushville",
    "sg:classifiers":[
        {
            "category":"Farming",
            "subcategory":"Farm",
            "type":"Manufacturing & Wholesale Goods"
        }
    ],
    "sg:phone":"+1 816 579 5803",
    "sg:postcode":"64484",
    "sg:province":"MO",
    "sg:tags":[
        "crop",
        "general"
    ],
    "wof:name":"Brian Miller",
    "wof:placetype":"venue"
},
  "geometry": {"coordinates":[-94.985007,39.512136],"type":"Point"}
}