{
  "type": "Feature",
  "properties": {
    "iso:country":"US",
    "sg:address":"311 E 7th St",
    "sg:city":"Joplin",
    "sg:classifiers":[
        {
            "category":"Autos & Motor Vehicles",
            "subcategory":"Automobile Sales",
            "type":"Retail Goods"
        },
        {
            "category":"Autos & Motor Vehicles",
            "subcategory":"Auto Supplies",
            "type":"Retail Goods"
        }
    ],
    "sg:phone":"+1 417 624 7373",
    "sg:postcode":"64801",
    "sg:province":"MO",
    "sg:tags":[
        "equipment",
        "part",
        "electrical",
        "accessory"
    ],
    "sg:website":"http://www.napaonline.com",
    "wof:name":"Joplin Auto Supply",
    "wof:placetype":"venue"
},
  "geometry": {"coordinates":[-94.511189,37.083985],"type":"Point"}
}