{
  "type": "Feature",
  "properties": {
    "iso:country":"US",
    "sg:address":"2010 Seckman Rd",
    "sg:city":"Imperial",
    "sg:classifiers":[
        {
            "category":"Organizations",
            "subcategory":"Religious Organization",
            "type":"Services"
        }
    ],
    "sg:phone":"+1 636 464 8730",
    "sg:postcode":"63052",
    "sg:province":"MO",
    "wof:name":"Seckman Road Baptist Church",
    "wof:placetype":"venue"
},
  "geometry": {"coordinates":[-90.401355,38.382516],"type":"Point"}
}