{
  "type": "Feature",
  "properties": {
    "iso:country":"US",
    "sg:address":"1388 Timothyridge Dr",
    "sg:city":"Saint Charles",
    "sg:classifiers":[
        {
            "category":"Building & Trades",
            "subcategory":"Construction",
            "type":"Services"
        }
    ],
    "sg:phone":"+1 636 928 3100",
    "sg:postcode":"63304",
    "sg:province":"MO",
    "sg:tags":[
        "wallpaper",
        "hanging"
    ],
    "wof:name":"Stack Interiors and Exteriors",
    "wof:placetype":"venue"
},
  "geometry": {"coordinates":[-90.622215,38.734294],"type":"Point"}
}