{
  "type": "Feature",
  "properties": {
    "iso:country":"US",
    "sg:address":"26903 State Hwy Oo",
    "sg:city":"Bevier",
    "sg:classifiers":[
        {
            "category":"Building & Trades",
            "subcategory":"Construction",
            "type":"Services"
        }
    ],
    "sg:phone":"+1 660 773 5484",
    "sg:postcode":"63532",
    "sg:province":"MO",
    "sg:tags":[
        "excavation",
        "excavating",
        "contractor"
    ],
    "wof:name":"Rick L Mc Vicker",
    "wof:placetype":"venue"
},
  "geometry": {"coordinates":[-92.56308199999999,39.797129],"type":"Point"}
}