{
  "type": "Feature",
  "properties": {
    "iso:country":"US",
    "sg:address":"1864 State Hwy Aa",
    "sg:city":"Poplar Bluff",
    "sg:classifiers":[
        {
            "category":"Organizations",
            "subcategory":"Religious Organization",
            "type":"Services"
        }
    ],
    "sg:phone":"+1 573 686 2874",
    "sg:postcode":"63901",
    "sg:province":"MO",
    "sg:tags":[
        "church"
    ],
    "wof:name":"New Home General Baptst Church",
    "wof:placetype":"venue"
},
  "geometry": {"coordinates":[-90.334715,36.765429],"type":"Point"}
}