{
  "type": "Feature",
  "properties": {
    "iso:country":"US",
    "sg:address":"323 E Walnut St",
    "sg:city":"Thayer",
    "sg:classifiers":[
        {
            "category":"Banks & Credit Unions",
            "subcategory":"Investment Brokerage",
            "type":"Services"
        },
        {
            "category":"Banks & Credit Unions",
            "subcategory":"Bank",
            "type":"Services"
        },
        {
            "category":"Banks & Credit Unions",
            "subcategory":"Financial Services",
            "type":"Services"
        }
    ],
    "sg:phone":"+1 417 264 7104",
    "sg:postcode":"65791",
    "sg:province":"MO",
    "sg:tags":[
        "financing",
        "loan",
        "mortgage"
    ],
    "sg:website":"http://www.greatsouthernbank.com",
    "wof:name":"Great Southern Bank",
    "wof:placetype":"venue"
},
  "geometry": {"coordinates":[-91.54057899999999,36.523429],"type":"Point"}
}