{
  "type": "Feature",
  "properties": {
    "iso:country":"US",
    "sg:address":"6401 E 40 St",
    "sg:city":"Kansas City",
    "sg:classifiers":[
        {
            "category":"Shopping",
            "subcategory":"Discount & Variety Stores",
            "type":"Retail Goods"
        },
        {
            "category":"Wholesale",
            "subcategory":"Construction Materials",
            "type":"Manufacturing & Wholesale Goods"
        }
    ],
    "sg:phone":"+1 816 924 1333",
    "sg:postcode":"64129",
    "sg:province":"MO",
    "sg:tags":[
        "merchandise",
        "general"
    ],
    "wof:name":"Masonry Supply",
    "wof:placetype":"venue"
},
  "geometry": {"coordinates":[-94.508757,39.053012],"type":"Point"}
}