{
  "type": "Feature",
  "properties": {
    "iso:country":"US",
    "sg:address":"1231 Darding Dr",
    "sg:city":"Saint Louis",
    "sg:classifiers":[
        {
            "category":"Building & Trades",
            "subcategory":"Plumbing",
            "type":"Services"
        }
    ],
    "sg:phone":"+1 314 631 4442",
    "sg:postcode":"63125",
    "sg:province":"MO",
    "sg:tags":[
        "condition",
        "contractor"
    ],
    "wof:name":"Harry Hacker Heating",
    "wof:placetype":"venue"
},
  "geometry": {"coordinates":[-90.30328,38.516527],"type":"Point"}
}