{
  "type": "Feature",
  "properties": {
    "iso:country":"US",
    "sg:address":"621 Locust St",
    "sg:city":"Chillicothe",
    "sg:classifiers":[
        {
            "category":"Shopping",
            "subcategory":"Clothing, Apparel, & Fashions",
            "type":"Retail Goods"
        }
    ],
    "sg:phone":"+1 660 707 1234",
    "sg:postcode":"64601",
    "sg:province":"MO",
    "sg:tags":[
        "dancing",
        "supply"
    ],
    "wof:name":"Rhythm Wear Apparel",
    "wof:placetype":"venue"
},
  "geometry": {"coordinates":[-93.55246099999999,39.794082],"type":"Point"}
}