{
  "type": "Feature",
  "properties": {
    "iso:country":"US",
    "sg:address":"106 Old US Hwy 40",
    "sg:city":"O Fallon",
    "sg:classifiers":[
        {
            "category":"Building & Trades",
            "subcategory":"Pest Control",
            "type":"Services"
        }
    ],
    "sg:phone":"+1 636 281 4020",
    "sg:postcode":"63366",
    "sg:province":"MO",
    "wof:name":"Bruce Terminix Service Co",
    "wof:placetype":"venue"
},
  "geometry": {"coordinates":[-90.69991899999999,38.80026],"type":"Point"}
}