{
  "type": "Feature",
  "properties": {
    "iso:country":"US",
    "sg:address":"8110 US Hwy 69",
    "sg:city":"Liberty",
    "sg:classifiers":[
        {
            "category":"Banks & Credit Unions",
            "subcategory":"Bank",
            "type":"Services"
        }
    ],
    "sg:phone":"+1 816 454 4445",
    "sg:postcode":"64068",
    "sg:province":"MO",
    "sg:tags":[
        "depository",
        "banking"
    ],
    "wof:name":"Qc Financial Services Inc",
    "wof:placetype":"venue"
},
  "geometry": {"coordinates":[-94.458834,39.240538],"type":"Point"}
}