{
  "type": "Feature",
  "properties": {
    "iso:country":"US",
    "sg:address":"304 S Florissant Rd",
    "sg:city":"Ferguson",
    "sg:classifiers":[
        {
            "category":"Restaurant",
            "type":"Food & Drink"
        }
    ],
    "sg:phone":"+1 314 521 0440",
    "sg:postcode":"63135",
    "sg:province":"MO",
    "sg:tags":[
        "eating"
    ],
    "wof:name":"Thyme Table Cafe",
    "wof:placetype":"venue"
},
  "geometry": {"coordinates":[-90.303543,38.741059],"type":"Point"}
}