{
  "type": "Feature",
  "properties": {
    "iso:country":"US",
    "sg:address":"35 Ofallon Sq",
    "sg:city":"O Fallon",
    "sg:classifiers":[
        {
            "category":"Restaurant",
            "type":"Food & Drink"
        }
    ],
    "sg:phone":"+1 636 272 1989",
    "sg:postcode":"63366",
    "sg:province":"MO",
    "wof:name":"Pham's Restaurant",
    "wof:placetype":"venue"
},
  "geometry": {"coordinates":[-90.701323,38.801459],"type":"Point"}
}