{
  "type": "Feature",
  "properties": {
    "iso:country":"US",
    "sg:address":"6301 Delmar",
    "sg:city":"St Louis",
    "sg:classifiers":[
        {
            "category":"Food & Beverages",
            "subcategory":"Bakery",
            "type":"Retail Goods"
        }
    ],
    "sg:phone":"+1 314 725 4800",
    "sg:postcode":"63130",
    "sg:province":"MO",
    "sg:tags":[
        "sandwich"
    ],
    "sg:website":"www.eatsnarfs.com",
    "wof:name":"Snarf's",
    "wof:placetype":"venue"
},
  "geometry": {"coordinates":[-90.302696,38.655816],"type":"Point"}
}