{
  "type": "Feature",
  "properties": {
    "iso:country":"US",
    "sg:address":"9369 Olive Blvd",
    "sg:city":"St Louis",
    "sg:classifiers":[
        {
            "category":"Shopping",
            "subcategory":"Pharmacy",
            "type":"Retail Goods"
        }
    ],
    "sg:phone":"+1 314 983 9036",
    "sg:postcode":"63132",
    "sg:province":"MO",
    "wof:name":"Shoppe Canada Prescriptions",
    "wof:placetype":"venue"
},
  "geometry": {"coordinates":[-90.373468,38.67418],"type":"Point"}
}