{
  "type": "Feature",
  "properties": {
    "iso:country":"US",
    "sg:address":"1301 Village Dr",
    "sg:city":"St Joseph",
    "sg:classifiers":[
        {
            "category":"Travel",
            "subcategory":"Travel Agent",
            "type":"Entertainment"
        }
    ],
    "sg:phone":"+1 816 364 3232",
    "sg:postcode":"64506",
    "sg:province":"MO",
    "sg:tags":[
        "agency",
        "bureau"
    ],
    "wof:name":"Cotter Travel Assoc",
    "wof:placetype":"venue"
},
  "geometry": {"coordinates":[-94.799896,39.778111],"type":"Point"}
}