{
  "type": "Feature",
  "properties": {
    "iso:country":"US",
    "sg:address":"3221 E Lark St",
    "sg:city":"Springfield",
    "sg:classifiers":[
        {
            "category":"Manufacturing",
            "subcategory":"Retail Goods",
            "type":"Manufacturing & Wholesale Goods"
        }
    ],
    "sg:phone":"+1 417 799 1161",
    "sg:postcode":"65804",
    "sg:province":"MO",
    "sg:tags":[
        "product",
        "mfg"
    ],
    "wof:name":"Ladybug Industries Inc",
    "wof:placetype":"venue"
},
  "geometry": {"coordinates":[-93.233991,37.135974],"type":"Point"}
}