{
  "type": "Feature",
  "properties": {
    "iso:country":"US",
    "sg:address":"156 Ofallon Plz",
    "sg:city":"O Fallon",
    "sg:classifiers":[
        {
            "category":"Building & Trades",
            "subcategory":"Construction",
            "type":"Services"
        }
    ],
    "sg:phone":"+1 636 379 3080",
    "sg:postcode":"63366",
    "sg:province":"MO",
    "sg:tags":[
        "contractor"
    ],
    "wof:name":"American Roofing",
    "wof:placetype":"venue"
},
  "geometry": {"coordinates":[-90.698821,38.808812],"type":"Point"}
}