{
  "type": "Feature",
  "properties": {
    "iso:country":"US",
    "sg:address":"4309 State Hwy U",
    "sg:city":"Freeburg",
    "sg:classifiers":[
        {
            "category":"Education",
            "subcategory":"School",
            "type":"Public Place"
        }
    ],
    "sg:phone":"+1 573 744 5898",
    "sg:postcode":"65074",
    "sg:province":"MO",
    "wof:name":"Sacred Heart School",
    "wof:placetype":"venue"
},
  "geometry": {"coordinates":[-92.430442,38.518834],"type":"Point"}
}