{
  "type": "Feature",
  "properties": {
    "iso:country":"US",
    "sg:address":"1 Ronnies Plz",
    "sg:city":"Sappington",
    "sg:classifiers":[
        {
            "category":"Personal",
            "subcategory":"Beauty Salon",
            "type":"Services"
        }
    ],
    "sg:phone":"+1 314 842 6500",
    "sg:postcode":"63126",
    "sg:province":"MO",
    "sg:tags":[
        "spa",
        "day"
    ],
    "sg:website":"www.seasonsspa.com",
    "wof:name":"Seasons Spa & Salon",
    "wof:placetype":"venue"
},
  "geometry": {"coordinates":[-90.36053099999999,38.526838],"type":"Point"}
}