{
  "type": "Feature",
  "properties": {
    "iso:country":"US",
    "sg:address":"910 Montebello Rd",
    "sg:city":"Imperial",
    "sg:classifiers":[
        {
            "category":"Organizations",
            "subcategory":"Community Association",
            "type":"Services"
        }
    ],
    "sg:phone":"+1 636 464 9608",
    "sg:postcode":"63052",
    "sg:province":"MO",
    "wof:name":"Rock Memorial Post 283",
    "wof:placetype":"venue"
},
  "geometry": {"coordinates":[-90.369165,38.381847],"type":"Point"}
}