{
  "type": "Feature",
  "properties": {
    "iso:country":"US",
    "sg:address":"918 E Kearney St",
    "sg:city":"Springfield",
    "sg:classifiers":[
        {
            "category":"Autos & Motor Vehicles",
            "subcategory":"Auto Supplies",
            "type":"Retail Goods"
        }
    ],
    "sg:phone":"+1 417 831 5059",
    "sg:postcode":"65803",
    "sg:province":"MO",
    "wof:name":"Tire Barn",
    "wof:placetype":"venue"
},
  "geometry": {"coordinates":[-93.279521,37.240567],"type":"Point"}
}