{
  "type": "Feature",
  "properties": {
    "iso:country":"US",
    "sg:address":"1723 W Sunshine St",
    "sg:city":"Springfield",
    "sg:classifiers":[
        {
            "category":"Wholesale",
            "subcategory":"Office Equipment",
            "type":"Manufacturing & Wholesale Goods"
        }
    ],
    "sg:phone":"+1 417 334 1131",
    "sg:postcode":"65807",
    "sg:province":"MO",
    "sg:tags":[
        "machine",
        "duplicating",
        "copying"
    ],
    "sg:website":"www.officeconceptsofmo.com",
    "wof:name":"Office Concepts Of Missouri",
    "wof:placetype":"venue"
},
  "geometry": {"coordinates":[-93.315864,37.182553],"type":"Point"}
}