{
  "type": "Feature",
  "properties": {
    "iso:country":"US",
    "sg:address":"2233 N Glenstone Ave",
    "sg:city":"Springfield",
    "sg:classifiers":[
        {
            "category":"Travel",
            "subcategory":"Hotels & Motels",
            "type":"Entertainment"
        }
    ],
    "sg:phone":"+1 417 865 5566",
    "sg:postcode":"65803",
    "sg:province":"MO",
    "wof:name":"Maple Inn",
    "wof:placetype":"venue"
},
  "geometry": {"coordinates":[-93.261169,37.236993],"type":"Point"}
}