{
  "type": "Feature",
  "properties": {
    "iso:country":"US",
    "sg:address":"9703 Gumbo Rd",
    "sg:city":"Mountain Grove",
    "sg:classifiers":[
        {
            "category":"Wholesale",
            "subcategory":"Electrical",
            "type":"Manufacturing & Wholesale Goods"
        }
    ],
    "sg:phone":"+1 417 926 4351",
    "sg:postcode":"65711",
    "sg:province":"MO",
    "sg:tags":[
        "electronic"
    ],
    "wof:name":"K M C Recording & Sound",
    "wof:placetype":"venue"
},
  "geometry": {"coordinates":[-92.263615,37.103581],"type":"Point"}
}