{
  "type": "Feature",
  "properties": {
    "iso:country":"US",
    "sg:address":"16253 Bent Tree Dr",
    "sg:city":"Chesterfield",
    "sg:classifiers":[
        {
            "category":"Food & Beverages",
            "subcategory":"Groceries & Convenience Stores",
            "type":"Retail Goods"
        }
    ],
    "sg:phone":"+1 314 993 8254",
    "sg:postcode":"63005",
    "sg:province":"MO",
    "wof:name":"Walnut Farm Foods",
    "wof:placetype":"venue"
},
  "geometry": {"coordinates":[-90.57835900000001,38.632832],"type":"Point"}
}