{
  "type": "Feature",
  "properties": {
    "iso:country":"US",
    "sg:address":"2 Taylor Woods Dr",
    "sg:city":"Saint Louis",
    "sg:classifiers":[
        {
            "category":"Professional",
            "subcategory":"Management & Consulting",
            "type":"Services"
        }
    ],
    "sg:phone":"+1 314 909 8482",
    "sg:postcode":"63122",
    "sg:province":"MO",
    "sg:tags":[
        "public",
        "relations"
    ],
    "wof:name":"Bjb Creative Services",
    "wof:placetype":"venue"
},
  "geometry": {"coordinates":[-90.403927,38.592233],"type":"Point"}
}