{
  "type": "Feature",
  "properties": {
    "iso:country":"US",
    "sg:address":"18054 Shepard Ridge Rd",
    "sg:city":"Glencoe",
    "sg:classifiers":[
        {
            "category":"Manufacturing",
            "subcategory":"Musical Instruments",
            "type":"Manufacturing & Wholesale Goods"
        }
    ],
    "sg:phone":"+1 636 458 3772",
    "sg:postcode":"63038",
    "sg:province":"MO",
    "sg:tags":[
        "instruments-industrial-repairing"
    ],
    "wof:name":"On Site Power Equip Service Company",
    "wof:placetype":"venue"
},
  "geometry": {"coordinates":[-90.628406,38.617744],"type":"Point"}
}