{
  "type": "Feature",
  "properties": {
    "iso:country":"US",
    "sg:address":"18 Pines Dr",
    "sg:city":"St Peters",
    "sg:classifiers":[
        {
            "category":"Travel",
            "subcategory":"Travel Agent",
            "type":"Entertainment"
        }
    ],
    "sg:phone":"+1 636 922 4340",
    "sg:postcode":"63376",
    "sg:province":"MO",
    "sg:tags":[
        "agency",
        "bureau"
    ],
    "wof:name":"Cruises N More",
    "wof:placetype":"venue"
},
  "geometry": {"coordinates":[-90.61359,38.75425],"type":"Point"}
}