{
  "type": "Feature",
  "properties": {
    "iso:country":"US",
    "sg:address":"2105 E 24 Ter",
    "sg:city":"Kansas City",
    "sg:classifiers":[
        {
            "category":"Taxi",
            "type":"Transportation"
        }
    ],
    "sg:phone":"+1 816 483 5247",
    "sg:postcode":"64127",
    "sg:province":"MO",
    "sg:tags":[
        "taxicab"
    ],
    "wof:name":"Aaron Edwards Cab Driver",
    "wof:placetype":"venue"
},
  "geometry": {"coordinates":[-94.557339,39.081909],"type":"Point"}
}