{
  "type": "Feature",
  "properties": {
    "iso:country":"US",
    "sg:address":"13418 Charlotte St",
    "sg:city":"Kansas City",
    "sg:classifiers":[
        {
            "category":"Professional",
            "type":"Services"
        }
    ],
    "sg:phone":"+1 816 941 8869",
    "sg:postcode":"64146",
    "sg:province":"MO",
    "sg:tags":[
        "establishment"
    ],
    "wof:name":"Fiorella's Jack Stack World",
    "wof:placetype":"venue"
},
  "geometry": {"coordinates":[-94.58551799999999,38.882488],"type":"Point"}
}