{
  "type": "Feature",
  "properties": {
    "iso:country":"US",
    "sg:address":"108 E Pearl St",
    "sg:city":"Harrisonville",
    "sg:classifiers":[
        {
            "category":"Banks & Credit Unions",
            "subcategory":"Investment Brokerage",
            "type":"Services"
        }
    ],
    "sg:phone":"+1 816 380 7491",
    "sg:postcode":"64701",
    "sg:province":"MO",
    "sg:tags":[
        "security"
    ],
    "wof:name":"Edward Jones Co",
    "wof:placetype":"venue"
},
  "geometry": {"coordinates":[-94.348679,38.654968],"type":"Point"}
}