{
  "type": "Feature",
  "properties": {
    "iso:country":"US",
    "sg:address":"1024 Co Rd 365",
    "sg:city":"Taylor",
    "sg:classifiers":[
        {
            "category":"Education",
            "subcategory":"Special Training",
            "type":"Public Place"
        }
    ],
    "sg:phone":"+1 573 769 2286",
    "sg:postcode":"63471",
    "sg:province":"MO",
    "wof:name":"Dino Discovery",
    "wof:placetype":"venue"
},
  "geometry": {"coordinates":[-91.525745,39.9102],"type":"Point"}
}