{
  "type": "Feature",
  "properties": {
    "iso:country":"US",
    "sg:address":"9854 Manchester Rd",
    "sg:city":"Saint Louis",
    "sg:classifiers":[
        {
            "category":"Shopping",
            "type":"Retail Goods"
        }
    ],
    "sg:phone":"+1 314 961 0860",
    "sg:postcode":"63119",
    "sg:province":"MO",
    "sg:tags":[
        "merchandise"
    ],
    "wof:name":"American Visions Inc",
    "wof:placetype":"venue"
},
  "geometry": {"coordinates":[-90.374595,38.606436],"type":"Point"}
}