{
  "type": "Feature",
  "properties": {
    "iso:country":"US",
    "sg:address":"300 Ralph St",
    "sg:city":"Ethel",
    "sg:classifiers":[
        {
            "category":"Government",
            "subcategory":"Fire Station",
            "type":"Public Place"
        }
    ],
    "sg:phone":"+1 660 486 3201",
    "sg:postcode":"63539",
    "sg:province":"MO",
    "sg:tags":[
        "department"
    ],
    "wof:name":"Ethel Community Fire Department",
    "wof:placetype":"venue"
},
  "geometry": {"coordinates":[-92.739903,39.890857],"type":"Point"}
}