{
  "type": "Feature",
  "properties": {
    "iso:country":"US",
    "sg:address":"6500 W Florissant Ave",
    "sg:city":"Saint Louis",
    "sg:classifiers":[
        {
            "category":"Shopping",
            "subcategory":"Pawn Shop",
            "type":"Retail Goods"
        }
    ],
    "sg:phone":"+1 314 382 2274",
    "sg:postcode":"63136",
    "sg:province":"MO",
    "wof:name":"Pit Stop Pawn Shop",
    "wof:placetype":"venue"
},
  "geometry": {"coordinates":[-90.257248,38.714297],"type":"Point"}
}