{
  "type": "Feature",
  "properties": {
    "iso:country":"US",
    "sg:address":"10 Van Cleve Ct",
    "sg:city":"Overland",
    "sg:classifiers":[
        {
            "category":"Building & Trades",
            "subcategory":"Construction",
            "type":"Services"
        }
    ],
    "sg:phone":"+1 314 427 7711",
    "sg:postcode":"63114",
    "sg:province":"MO",
    "sg:tags":[
        "fire",
        "restoration",
        "damage"
    ],
    "wof:name":"Repair Masters Construction",
    "wof:placetype":"venue"
},
  "geometry": {"coordinates":[-90.400745,38.706667],"type":"Point"}
}