{
  "type": "Feature",
  "properties": {
    "iso:country":"US",
    "sg:address":"10987 Old US Hwy 54",
    "sg:city":"Holts Summit",
    "sg:classifiers":[
        {
            "category":"Building & Trades",
            "subcategory":"Construction",
            "type":"Services"
        }
    ],
    "sg:phone":"+1 573 896 4145",
    "sg:postcode":"65043",
    "sg:province":"MO",
    "sg:tags":[
        "development"
    ],
    "wof:name":"Ranquest Development Co",
    "wof:placetype":"venue"
},
  "geometry": {"coordinates":[-92.111047,38.662698],"type":"Point"}
}