{
  "type": "Feature",
  "properties": {
    "iso:country":"US",
    "sg:address":"1102 W Clay Ave",
    "sg:city":"Plattsburg",
    "sg:classifiers":[
        {
            "category":"Insurance",
            "subcategory":"Insurance Agent",
            "type":"Services"
        }
    ],
    "sg:phone":"+1 816 539 2411",
    "sg:postcode":"64477",
    "sg:province":"MO",
    "sg:tags":[
        "broker"
    ],
    "wof:name":"Farm Bureau Insurance Services",
    "wof:placetype":"venue"
},
  "geometry": {"coordinates":[-94.46029299999999,39.564402],"type":"Point"}
}