{
  "type": "Feature",
  "properties": {
    "iso:country":"US",
    "sg:address":"2028 Savannah Ave",
    "sg:city":"Saint Joseph",
    "sg:classifiers":[
        {
            "category":"Building & Trades",
            "subcategory":"Construction",
            "type":"Services"
        }
    ],
    "sg:phone":"+1 816 676 1569",
    "sg:postcode":"64505",
    "sg:province":"MO",
    "sg:tags":[
        "hanging",
        "contractor"
    ],
    "wof:name":"Moffatt Painting Barry",
    "wof:placetype":"venue"
},
  "geometry": {"coordinates":[-94.852762,39.782429],"type":"Point"}
}