{
  "type": "Feature",
  "properties": {
    "iso:country":"US",
    "sg:address":"54 N Franklin St",
    "sg:city":"Kingston",
    "sg:classifiers":[
        {
            "category":"Government",
            "subcategory":"Police Station",
            "type":"Public Place"
        }
    ],
    "sg:phone":"+1 816 586 2681",
    "sg:postcode":"64650",
    "sg:province":"MO",
    "sg:tags":[
        "sheriff"
    ],
    "wof:name":"Caldwell Sheriffs Dept",
    "wof:placetype":"venue"
},
  "geometry": {"coordinates":[-94.037699,39.642892],"type":"Point"}
}