{
  "type": "Feature",
  "properties": {
    "iso:country":"US",
    "sg:address":"3737 Truman Rd",
    "sg:city":"St Charles",
    "sg:classifiers":[
        {
            "category":"Social Services",
            "type":"Services"
        }
    ],
    "sg:phone":"+1 636 940 0659",
    "sg:postcode":"63301",
    "sg:province":"MO",
    "sg:tags":[
        "organization",
        "welfare"
    ],
    "wof:name":"Grace Hill",
    "wof:placetype":"venue"
},
  "geometry": {"coordinates":[-90.56055000000001,38.797246],"type":"Point"}
}