{
  "type": "Feature",
  "properties": {
    "iso:country":"US",
    "sg:address":"427 N Kingshighway St",
    "sg:city":"St Charles",
    "sg:classifiers":[
        {
            "category":"Real Estate",
            "subcategory":"Real Estate Agent",
            "type":"Services"
        }
    ],
    "sg:phone":"+1 636 949 6828",
    "sg:postcode":"63301",
    "sg:province":"MO",
    "sg:tags":[
        "appraiser"
    ],
    "wof:name":"Midwest Appraisals",
    "wof:placetype":"venue"
},
  "geometry": {"coordinates":[-90.491777,38.788217],"type":"Point"}
}