{
  "type": "Feature",
  "properties": {
    "iso:country":"US",
    "sg:address":"1436 W Ashley Rd",
    "sg:city":"Boonville",
    "sg:classifiers":[
        {
            "category":"Landmark",
            "subcategory":"Monument",
            "type":"Public Place"
        }
    ],
    "sg:phone":"+1 660 882 2227",
    "sg:postcode":"65233",
    "sg:province":"MO",
    "sg:website":"http://www.morivermonument.com",
    "wof:name":"Missouri River Monument Co.",
    "wof:placetype":"venue"
},
  "geometry": {"coordinates":[-92.770774,38.944556],"type":"Point"}
}