{
  "type": "Feature",
  "properties": {
    "iso:country":"US",
    "sg:address":"9350 Watson Industrial Park",
    "sg:city":"St Louis",
    "sg:classifiers":[
        {
            "category":"Wholesale",
            "subcategory":"Scrap",
            "type":"Manufacturing & Wholesale Goods"
        }
    ],
    "sg:phone":"+1 314 918 7550",
    "sg:postcode":"63126",
    "sg:province":"MO",
    "sg:tags":[
        "waste"
    ],
    "wof:name":"Renaissance Technologies",
    "wof:placetype":"venue"
},
  "geometry": {"coordinates":[-90.373617,38.56154],"type":"Point"}
}