{
  "type": "Feature",
  "properties": {
    "iso:country":"US",
    "sg:address":"1805 S Highview Ave",
    "sg:city":"Joplin",
    "sg:classifiers":[
        {
            "category":"Building & Trades",
            "subcategory":"Construction",
            "type":"Services"
        }
    ],
    "sg:phone":"+1 417 624 8111",
    "sg:postcode":"64804",
    "sg:province":"MO",
    "sg:tags":[
        "house"
    ],
    "wof:name":"Rek Homes",
    "wof:placetype":"venue"
},
  "geometry": {"coordinates":[-94.480023,37.069984],"type":"Point"}
}