{
  "type": "Feature",
  "properties": {
    "iso:country":"US",
    "sg:address":"1460 Tina Dr",
    "sg:city":"Florissant",
    "sg:classifiers":[
        {
            "category":"Professional",
            "subcategory":"Business Services",
            "type":"Services"
        }
    ],
    "sg:phone":"+1 314 839 9300",
    "sg:postcode":"63033",
    "sg:province":"MO",
    "sg:tags":[
        "inspection"
    ],
    "wof:name":"Doerr & Associates",
    "wof:placetype":"venue"
},
  "geometry": {"coordinates":[-90.280146,38.798762],"type":"Point"}
}