{
  "type": "Feature",
  "properties": {
    "iso:country":"US",
    "sg:address":"281 Woodson Bnd",
    "sg:city":"Branson",
    "sg:classifiers":[
        {
            "category":"Shopping",
            "subcategory":"Beauty & Cosmetics",
            "type":"Retail Goods"
        }
    ],
    "sg:phone":"+1 417 336 1997",
    "sg:postcode":"65616",
    "sg:province":"MO",
    "sg:tags":[
        "perfume",
        "salons-equipment",
        "supply"
    ],
    "wof:name":"Campbell, Christi",
    "wof:placetype":"venue"
},
  "geometry": {"coordinates":[-93.204901,36.654592],"type":"Point"}
}