{
  "type": "Feature",
  "properties": {
    "iso:country":"US",
    "sg:address":"1618 Polar Dr",
    "sg:city":"Wentzville",
    "sg:classifiers":[
        {
            "category":"Health Services",
            "subcategory":"Chiropractor",
            "type":"Services"
        }
    ],
    "sg:phone":"+1 636 828 5151",
    "sg:postcode":"63385",
    "sg:province":"MO",
    "wof:name":"Bauer Chiropractic",
    "wof:placetype":"venue"
},
  "geometry": {"coordinates":[-90.888018,38.816456],"type":"Point"}
}