{
  "type": "Feature",
  "properties": {
    "iso:country":"US",
    "sg:address":"720 S Schifferdecker Ave",
    "sg:city":"Joplin",
    "sg:classifiers":[
        {
            "category":"Utilities",
            "subcategory":"Electric",
            "type":"Services"
        }
    ],
    "sg:phone":"+1 417 659 9215",
    "sg:postcode":"64801",
    "sg:province":"MO",
    "sg:tags":[
        "company"
    ],
    "wof:name":"Empire District Electric Co",
    "wof:placetype":"venue"
},
  "geometry": {"coordinates":[-94.54906099999999,37.084567],"type":"Point"}
}