{
  "type": "Feature",
  "properties": {
    "iso:country":"US",
    "sg:address":"711 Maryland Ave",
    "sg:city":"Columbia",
    "sg:classifiers":[
        {
            "category":"Organizations",
            "subcategory":"Community Association",
            "type":"Services"
        }
    ],
    "sg:phone":"+1 573 443 1991",
    "sg:postcode":"65201",
    "sg:province":"MO",
    "sg:tags":[
        "sorority",
        "fraternity"
    ],
    "wof:name":"Delta Upsilon Inc",
    "wof:placetype":"venue"
},
  "geometry": {"coordinates":[-92.33002399999999,38.94246],"type":"Point"}
}