{
  "type": "Feature",
  "properties": {
    "iso:country":"US",
    "sg:address":"65 Birdsong Dr",
    "sg:city":"Frohna",
    "sg:classifiers":[
        {
            "category":"Manufacturing",
            "subcategory":"Food",
            "type":"Manufacturing & Wholesale Goods"
        },
        {
            "category":"Farming",
            "subcategory":"Farm",
            "type":"Manufacturing & Wholesale Goods"
        }
    ],
    "sg:phone":"+1 573 824 5625",
    "sg:postcode":"63748",
    "sg:province":"MO",
    "sg:tags":[
        "corn",
        "product"
    ],
    "wof:name":"Howard Fiehler",
    "wof:placetype":"venue"
},
  "geometry": {"coordinates":[-89.630425,37.638242],"type":"Point"}
}