{
  "type": "Feature",
  "properties": {
    "iso:country":"US",
    "sg:address":"2421 Oklahoma Ave",
    "sg:city":"Trenton",
    "sg:classifiers":[
        {
            "category":"Organizations",
            "subcategory":"Religious Organization",
            "type":"Services"
        }
    ],
    "sg:phone":"+1 660 359 3898",
    "sg:postcode":"64683",
    "sg:province":"MO",
    "sg:tags":[
        "church"
    ],
    "wof:name":"First Baptist Church Inc",
    "wof:placetype":"venue"
},
  "geometry": {"coordinates":[-93.603711,40.087141],"type":"Point"}
}