{
  "type": "Feature",
  "properties": {
    "iso:country":"US",
    "sg:address":"1219 W Main St",
    "sg:city":"Union",
    "sg:classifiers":[
        {
            "category":"Retail",
            "subcategory":"Auto Repair",
            "type":"Services"
        }
    ],
    "sg:phone":"+1 636 583 2275",
    "sg:postcode":"63084",
    "sg:province":"MO",
    "sg:tags":[
        "body",
        "automobile",
        "painting"
    ],
    "wof:name":"Bartel Auto Body",
    "wof:placetype":"venue"
},
  "geometry": {"coordinates":[-91.02977799999999,38.446841],"type":"Point"}
}