{
  "type": "Feature",
  "properties": {
    "iso:country":"US",
    "sg:address":"903 College St",
    "sg:city":"Campbell",
    "sg:classifiers":[
        {
            "category":"Personal",
            "subcategory":"Beauty Salon",
            "type":"Services"
        },
        {
            "category":"Personal",
            "subcategory":"Tanning Parlor",
            "type":"Services"
        }
    ],
    "sg:phone":"+1 573 246 2556",
    "sg:postcode":"63933",
    "sg:province":"MO",
    "wof:name":"Cut Curl & Tan",
    "wof:placetype":"venue"
},
  "geometry": {"coordinates":[-90.065681,36.493408],"type":"Point"}
}