{
  "type": "Feature",
  "properties": {
    "iso:country":"US",
    "sg:address":"620 W College St",
    "sg:city":"Springfield",
    "sg:classifiers":[
        {
            "category":"Bars & Pubs",
            "type":"Food & Drink"
        },
        {
            "category":"Bars & Pubs",
            "subcategory":"Nightclub",
            "type":"Food & Drink"
        }
    ],
    "sg:phone":"+1 417 865 7922",
    "sg:postcode":"65806",
    "sg:province":"MO",
    "sg:tags":[
        "club",
        "night"
    ],
    "wof:name":"Softails",
    "wof:placetype":"venue"
},
  "geometry": {"coordinates":[-93.297372,37.208662],"type":"Point"}
}