{
  "type": "Feature",
  "properties": {
    "iso:country":"US",
    "sg:address":"702 Market St",
    "sg:city":"Fulton",
    "sg:classifiers":[
        {
            "category":"Utilities",
            "subcategory":"Telephone",
            "type":"Services"
        }
    ],
    "sg:phone":"+1 573 642 2200",
    "sg:postcode":"65251",
    "sg:province":"MO",
    "sg:tags":[
        "communications"
    ],
    "wof:name":"Southwestern Bell Telephone LP",
    "wof:placetype":"venue"
},
  "geometry": {"coordinates":[-91.94677,38.85039],"type":"Point"}
}