{
  "type": "Feature",
  "properties": {
    "iso:country":"US",
    "sg:address":"7220 S Roland Blvd",
    "sg:city":"St Louis",
    "sg:classifiers":[
        {
            "category":"Professional",
            "subcategory":"Business Services",
            "type":"Services"
        }
    ],
    "sg:phone":"+1 314 963 3239",
    "sg:postcode":"63121",
    "sg:province":"MO",
    "sg:tags":[
        "interior",
        "consultant",
        "design",
        "decorator"
    ],
    "wof:name":"Tiernan Design",
    "wof:placetype":"venue"
},
  "geometry": {"coordinates":[-90.291172,38.70878],"type":"Point"}
}