{
  "type": "Feature",
  "properties": {
    "iso:country":"US",
    "sg:address":"1001 S 10th St",
    "sg:city":"Saint Joseph",
    "sg:classifiers":[
        {
            "category":"Organizations",
            "subcategory":"Religious Organization",
            "type":"Services"
        }
    ],
    "sg:phone":"+1 816 364 1013",
    "sg:postcode":"64503",
    "sg:province":"MO",
    "wof:name":"Born Again Tabernacle",
    "wof:placetype":"venue"
},
  "geometry": {"coordinates":[-94.84803599999999,39.757191],"type":"Point"}
}