{
  "type": "Feature",
  "properties": {
    "iso:country":"US",
    "sg:address":"820 N Sprigg St",
    "sg:city":"Cape Girardeau",
    "sg:classifiers":[
        {
            "category":"Personal",
            "type":"Services"
        }
    ],
    "sg:phone":"+1 573 651 3950",
    "sg:postcode":"63701",
    "sg:province":"MO",
    "wof:name":"Tan It All",
    "wof:placetype":"venue"
},
  "geometry": {"coordinates":[-89.52531500000001,37.315019],"type":"Point"}
}