{
  "type": "Feature",
  "properties": {
    "iso:country":"US",
    "sg:address":"29025 Bethel Church Rd",
    "sg:city":"Alma",
    "sg:classifiers":[
        {
            "category":"Manufacturing",
            "subcategory":"Buildings",
            "type":"Manufacturing & Wholesale Goods"
        }
    ],
    "sg:phone":"+1 660 674 2492",
    "sg:postcode":"64001",
    "sg:province":"MO",
    "sg:tags":[
        "home",
        "builder"
    ],
    "wof:name":"Steven Ray Lovercamp",
    "wof:placetype":"venue"
},
  "geometry": {"coordinates":[-93.553601,39.069274],"type":"Point"}
}