{
  "type": "Feature",
  "properties": {
    "iso:country":"US",
    "sg:address":"9800 NW Polo Dr",
    "sg:city":"Kansas City",
    "sg:classifiers":[
        {
            "category":"Professional",
            "subcategory":"Lawyer & Legal Services",
            "type":"Services"
        }
    ],
    "sg:phone":"+1 816 454 2525",
    "sg:postcode":"64153",
    "sg:province":"MO",
    "wof:name":"Davis Patrick M & Assoc PC",
    "wof:placetype":"venue"
},
  "geometry": {"coordinates":[-94.666498,39.273419],"type":"Point"}
}