{
  "type": "Feature",
  "properties": {
    "iso:country":"US",
    "sg:address":"8001 Clayton Rd",
    "sg:city":"St Louis",
    "sg:classifiers":[
        {
            "category":"Real Estate",
            "subcategory":"Real Estate Agent",
            "type":"Services"
        }
    ],
    "sg:phone":"+1 314 725 4518",
    "sg:postcode":"63117",
    "sg:province":"MO",
    "wof:name":"Sage Properties",
    "wof:placetype":"venue"
},
  "geometry": {"coordinates":[-90.343288,38.637887],"type":"Point"}
}