{
  "type": "Feature",
  "properties": {
    "iso:country":"US",
    "sg:address":"221 W 4th St",
    "sg:city":"Maryville",
    "sg:classifiers":[
        {
            "category":"Food & Beverages",
            "subcategory":"Groceries & Convenience Stores",
            "type":"Retail Goods"
        }
    ],
    "sg:phone":"+1 660 562 4600",
    "sg:postcode":"64468",
    "sg:province":"MO",
    "wof:name":"Bearcat Express",
    "wof:placetype":"venue"
},
  "geometry": {"coordinates":[-94.875055,40.34891],"type":"Point"}
}