{
  "type": "Feature",
  "properties": {
    "iso:country":"US",
    "sg:address":"4944 Christy Blvd",
    "sg:city":"St Louis",
    "sg:classifiers":[
        {
            "category":"Fast Food",
            "type":"Food & Drink"
        }
    ],
    "sg:phone":"+1 314 351 6000",
    "sg:postcode":"63116",
    "sg:province":"MO",
    "sg:tags":[
        "burger"
    ],
    "wof:name":"Keeton's Double Play",
    "wof:placetype":"venue"
},
  "geometry": {"coordinates":[-90.276633,38.584089],"type":"Point"}
}