{
  "type": "Feature",
  "properties": {
    "iso:country":"US",
    "sg:address":"416 Sherry Ln",
    "sg:city":"Liberty",
    "sg:classifiers":[
        {
            "category":"Shopping",
            "type":"Retail Goods"
        }
    ],
    "sg:phone":"+1 816 517 3228",
    "sg:postcode":"64068",
    "sg:province":"MO",
    "sg:tags":[
        "merchandise"
    ],
    "wof:name":"Leatherman Tool Shop",
    "wof:placetype":"venue"
},
  "geometry": {"coordinates":[-94.459051,39.227919],"type":"Point"}
}