{
  "type": "Feature",
  "properties": {
    "iso:country":"US",
    "sg:address":"3345 W 20th St",
    "sg:city":"Joplin",
    "sg:classifiers":[
        {
            "category":"Retail",
            "subcategory":"Auto Repair",
            "type":"Services"
        }
    ],
    "sg:phone":"+1 417 781 9929",
    "sg:postcode":"64804",
    "sg:province":"MO",
    "sg:tags":[
        "body"
    ],
    "wof:name":"Russ Moser International",
    "wof:placetype":"venue"
},
  "geometry": {"coordinates":[-94.557677,37.070369],"type":"Point"}
}