{
  "type": "Feature",
  "properties": {
    "iso:country":"US",
    "sg:address":"2289 Hill House Rd",
    "sg:city":"Chesterfield",
    "sg:classifiers":[
        {
            "category":"Health Services",
            "subcategory":"Doctor",
            "type":"Services"
        }
    ],
    "sg:phone":"+1 636 391 0581",
    "sg:postcode":"63017",
    "sg:province":"MO",
    "sg:tags":[
        "physician",
        "surgeon"
    ],
    "wof:name":"John M Gerdes DO",
    "wof:placetype":"venue"
},
  "geometry": {"coordinates":[-90.57295000000001,38.61831],"type":"Point"}
}