{
  "type": "Feature",
  "properties": {
    "iso:country":"US",
    "sg:address":"404 S 8th St",
    "sg:city":"St Joseph",
    "sg:classifiers":[
        {
            "category":"Organizations",
            "subcategory":"Non-profit Organization",
            "type":"Services"
        },
        {
            "category":"Health Services",
            "subcategory":"Hospital",
            "type":"Services"
        }
    ],
    "sg:phone":"+1 816 279 5767",
    "sg:postcode":"64501",
    "sg:province":"MO",
    "sg:tags":[
        "information",
        "treatment",
        "alcoholism",
        "specialty"
    ],
    "wof:name":"Alcoholics Anonymous",
    "wof:placetype":"venue"
},
  "geometry": {"coordinates":[-94.850734,39.763436],"type":"Point"}
}