{
  "type": "Feature",
  "properties": {
    "iso:country":"US",
    "sg:address":"106 W Maple Ave",
    "sg:city":"Independence",
    "sg:classifiers":[
        {
            "category":"Restaurant",
            "type":"Food & Drink"
        }
    ],
    "sg:phone":"+1 816 461 1144",
    "sg:postcode":"64050",
    "sg:province":"MO",
    "sg:tags":[
        "house",
        "steak",
        "barbecue"
    ],
    "wof:name":"Gregory G's BBQ",
    "wof:placetype":"venue"
},
  "geometry": {"coordinates":[-94.415712,39.092779],"type":"Point"}
}