{
  "type": "Feature",
  "properties": {
    "iso:country":"US",
    "sg:address":"3338 Watson Rd",
    "sg:city":"Saint Louis",
    "sg:classifiers":[
        {
            "category":"Building & Trades",
            "subcategory":"Plumbing",
            "type":"Services"
        }
    ],
    "sg:phone":"+1 314 645 6228",
    "sg:postcode":"63139",
    "sg:province":"MO",
    "sg:tags":[
        "refrigeration",
        "contractor"
    ],
    "wof:name":"Goodenough Heating & AC",
    "wof:placetype":"venue"
},
  "geometry": {"coordinates":[-90.29943,38.601388],"type":"Point"}
}