{
  "type": "Feature",
  "properties": {
    "iso:country":"US",
    "sg:address":"5021 Fyler Ave",
    "sg:city":"Saint Louis",
    "sg:classifiers":[
        {
            "category":"Shopping",
            "subcategory":"Shoes",
            "type":"Retail Goods"
        }
    ],
    "sg:phone":"+1 314 231 4897",
    "sg:postcode":"63139",
    "sg:province":"MO",
    "sg:tags":[
        "store"
    ],
    "wof:name":"Weil M K Shoe Co",
    "wof:placetype":"venue"
},
  "geometry": {"coordinates":[-90.275285,38.601944],"type":"Point"}
}