{
  "type": "Feature",
  "properties": {
    "iso:country":"US",
    "sg:address":"1904 N le Compte Ave",
    "sg:city":"Springfield",
    "sg:classifiers":[
        {
            "category":"Manufacturing",
            "subcategory":"Metals",
            "type":"Manufacturing & Wholesale Goods"
        },
        {
            "category":"Home & Garden",
            "subcategory":"Building Materials",
            "type":"Retail Goods"
        },
        {
            "category":"Manufacturing",
            "subcategory":"Building Materials",
            "type":"Manufacturing & Wholesale Goods"
        }
    ],
    "sg:phone":"+1 417 832 0235",
    "sg:postcode":"65802",
    "sg:province":"MO",
    "sg:tags":[
        "frames",
        "window",
        "windows-metal",
        "doors",
        "accessory"
    ],
    "wof:name":"EFCO Corp",
    "wof:placetype":"venue"
},
  "geometry": {"coordinates":[-93.215735,37.230277],"type":"Point"}
}