{
  "type": "Feature",
  "properties": {
    "addr:full":"1040 E Karsch Blvd Farmington MO 63640",
    "addr:housenumber":"1040",
    "addr:postcode":"63640",
    "addr:street":"E Karsch Blvd",
    "iso:country":"US",
    "sg:address":"1040 E Karsch Blvd",
    "sg:city":"Farmington",
    "sg:classifiers":[
        {
            "category":"Banks & Credit Unions",
            "subcategory":"Bank",
            "type":"Services"
        }
    ],
    "sg:phone":"+1 573 431 2801",
    "sg:postcode":"63640",
    "sg:province":"MO",
    "sg:tags":[
        "national",
        "commercial"
    ],
    "wof:name":"Commerce Bank",
    "wof:placetype":"venue"
},
  "geometry": {"coordinates":[-90.406536,37.781271],"type":"Point"}
}