{
  "type": "Feature",
  "properties": {
    "iso:country":"US",
    "sg:address":"213 E Main St",
    "sg:city":"Festus",
    "sg:classifiers":[
        {
            "category":"Organizations",
            "subcategory":"Labor Organization",
            "type":"Services"
        }
    ],
    "sg:phone":"+1 636 937 2039",
    "sg:postcode":"63028",
    "sg:province":"MO",
    "wof:name":"United Brotherhood Carpenters",
    "wof:placetype":"venue"
},
  "geometry": {"coordinates":[-90.392189,38.219861],"type":"Point"}
}