{
  "type": "Feature",
  "properties": {
    "iso:country":"US",
    "sg:address":"11977 Niehaus Ln",
    "sg:city":"Saint Louis",
    "sg:classifiers":[
        {
            "category":"Professional",
            "type":"Services"
        }
    ],
    "sg:phone":"+1 314 994 3110",
    "sg:postcode":"63146",
    "sg:province":"MO",
    "wof:name":"Medibeacon",
    "wof:placetype":"venue"
},
  "geometry": {"coordinates":[-90.43483000000001,38.679299],"type":"Point"}
}