{
  "type": "Feature",
  "properties": {
    "iso:country":"US",
    "sg:address":"4098 W Farm Rd 94",
    "sg:city":"Springfield",
    "sg:classifiers":[
        {
            "category":"Banks & Credit Unions",
            "subcategory":"Financial Services",
            "type":"Services"
        }
    ],
    "sg:phone":"+1 417 869 9400",
    "sg:postcode":"65803",
    "sg:province":"MO",
    "sg:tags":[
        "company",
        "holding"
    ],
    "wof:name":"Springcreek Investments LLC",
    "wof:placetype":"venue"
},
  "geometry": {"coordinates":[-93.35648399999999,37.270725],"type":"Point"}
}