{
  "type": "Feature",
  "properties": {
    "iso:country":"US",
    "sg:address":"503 N Maguire St",
    "sg:city":"Warrensburg",
    "sg:classifiers":[
        {
            "category":"Personal",
            "subcategory":"Tanning Parlor",
            "type":"Services"
        },
        {
            "category":"Personal",
            "type":"Services"
        }
    ],
    "sg:phone":"+1 660 747 7500",
    "sg:postcode":"64093",
    "sg:province":"MO",
    "sg:tags":[
        "salon"
    ],
    "wof:name":"L A Tan & Spa",
    "wof:placetype":"venue"
},
  "geometry": {"coordinates":[-93.73555399999999,38.76834],"type":"Point"}
}