{
  "type": "Feature",
  "properties": {
    "iso:country":"US",
    "sg:address":"303 E 565th Rd",
    "sg:city":"Walnut Grove",
    "sg:classifiers":[
        {
            "category":"Farming",
            "subcategory":"Farm",
            "type":"Manufacturing & Wholesale Goods"
        }
    ],
    "sg:phone":"+1 417 788 2828",
    "sg:postcode":"65770",
    "sg:province":"MO",
    "sg:tags":[
        "crop",
        "general"
    ],
    "wof:name":"Bob Voris",
    "wof:placetype":"venue"
},
  "geometry": {"coordinates":[-93.580169,37.433907],"type":"Point"}
}