{
  "type": "Feature",
  "properties": {
    "iso:country":"US",
    "sg:address":"102 W 7th St",
    "sg:city":"Leadwood",
    "sg:classifiers":[
        {
            "category":"Government",
            "subcategory":"Court House",
            "type":"Public Place"
        }
    ],
    "sg:phone":"+1 573 562 7327",
    "sg:postcode":"63653",
    "sg:province":"MO",
    "sg:tags":[
        "city"
    ],
    "wof:name":"Leadwood Municipal Court",
    "wof:placetype":"venue"
},
  "geometry": {"coordinates":[-90.592102,37.864706],"type":"Point"}
}