{
  "type": "Feature",
  "properties": {
    "addr:full":"70 Mid Rivers Mall Dr Saint Peters MO 63376",
    "addr:housenumber":"70",
    "addr:postcode":"63376",
    "addr:street":"Mid Rivers Mall Dr",
    "iso:country":"US",
    "sg:address":"70 Mid Rivers Mall Dr",
    "sg:city":"Saint Peters",
    "sg:classifiers":[
        {
            "category":"Restaurant",
            "type":"Food & Drink"
        }
    ],
    "sg:menulink":"http://www.allmenus.com/mo/ofallon/41806-bob-evans/menu/",
    "sg:phone":"+1 314 487 1919",
    "sg:postcode":"63376",
    "sg:province":"MO",
    "sg:tags":[
        "american"
    ],
    "wof:name":"Bob Evans",
    "wof:placetype":"venue"
},
  "geometry": {"coordinates":[-90.621905,38.795441],"type":"Point"}
}