{
  "type": "Feature",
  "properties": {
    "addr:full":"4500 State Hwy 43 Joplin MO 64804",
    "addr:housenumber":"4500",
    "addr:postcode":"64804",
    "addr:street":"State Hwy 43",
    "iso:country":"US",
    "sg:address":"4500 State Hwy 43",
    "sg:city":"Joplin",
    "sg:classifiers":[
        {
            "category":"Autos & Motor Vehicles",
            "subcategory":"Fuel & Gas Station",
            "type":"Retail Goods"
        }
    ],
    "sg:phone":"+1 417 781 0255",
    "sg:postcode":"64804",
    "sg:province":"MO",
    "sg:tags":[
        "plaza",
        "truck",
        "stops"
    ],
    "sg:website":"www.pilotcorp.com",
    "wof:name":"Pilot Travel Ctr",
    "wof:placetype":"venue"
},
  "geometry": {"coordinates":[-94.551571,37.003088],"type":"Point"}
}