{
  "type": "Feature",
  "properties": {
    "iso:country":"US",
    "sg:address":"16472 Walnut Rail Rd",
    "sg:city":"Chesterfield",
    "sg:classifiers":[
        {
            "category":"Farming",
            "subcategory":"Farm & Veterinary Services",
            "type":"Manufacturing & Wholesale Goods"
        }
    ],
    "sg:phone":"+1 636 532 2373",
    "sg:postcode":"63005",
    "sg:province":"MO",
    "sg:tags":[
        "livestock"
    ],
    "wof:name":"Bar L Ranch Inc",
    "wof:placetype":"venue"
},
  "geometry": {"coordinates":[-90.60247699999999,38.640388],"type":"Point"}
}