{
  "type": "Feature",
  "properties": {
    "iso:country":"US",
    "sg:address":"1501 Stokelan Dr",
    "sg:city":"Malden",
    "sg:classifiers":[
        {
            "category":"Organizations",
            "subcategory":"Religious Organization",
            "type":"Services"
        }
    ],
    "sg:phone":"+1 573 276 2343",
    "sg:postcode":"63863",
    "sg:province":"MO",
    "sg:tags":[
        "church"
    ],
    "wof:name":"Stokelan Drive Christn Church",
    "wof:placetype":"venue"
},
  "geometry": {"coordinates":[-89.974974,36.579042],"type":"Point"}
}