{
  "type": "Feature",
  "properties": {
    "iso:country":"US",
    "sg:address":"144 Bonnie Dr",
    "sg:city":"Lebanon",
    "sg:classifiers":[
        {
            "category":"Personal",
            "subcategory":"Beauty Salon",
            "type":"Services"
        },
        {
            "category":"Personal",
            "subcategory":"Nail Salon",
            "type":"Services"
        }
    ],
    "sg:phone":"+1 417 533 5000",
    "sg:postcode":"65536",
    "sg:province":"MO",
    "wof:name":"Creative Salon",
    "wof:placetype":"venue"
},
  "geometry": {"coordinates":[-92.648175,37.651646],"type":"Point"}
}