{
  "type": "Feature",
  "properties": {
    "iso:country":"US",
    "sg:address":"3947 Main St",
    "sg:city":"Kansas City",
    "sg:classifiers":[
        {
            "category":"Bars & Pubs",
            "type":"Food & Drink"
        }
    ],
    "sg:phone":"+1 816 931 7940",
    "sg:postcode":"64111",
    "sg:province":"MO",
    "sg:tags":[
        "drinking"
    ],
    "wof:name":"Club 50 50",
    "wof:placetype":"venue"
},
  "geometry": {"coordinates":[-94.58607499999999,39.055917],"type":"Point"}
}