{
  "type": "Feature",
  "properties": {
    "addr:full":"205 S Elmwood Dr Mexico MO 65265",
    "addr:housenumber":"205",
    "addr:postcode":"65265",
    "addr:street":"S Elmwood Dr",
    "iso:country":"US",
    "sg:address":"205 S Elmwood Dr",
    "sg:city":"Mexico",
    "sg:classifiers":[
        {
            "category":"Organizations",
            "subcategory":"Community Association",
            "type":"Services"
        }
    ],
    "sg:phone":"+1 573 581 2288",
    "sg:postcode":"65265",
    "sg:province":"MO",
    "sg:tags":[
        "fraternal"
    ],
    "wof:name":"Loyal Order Of Moose",
    "wof:placetype":"venue"
},
  "geometry": {"coordinates":[-91.90621400000001,39.17153],"type":"Point"}
}