{
  "type": "Feature",
  "properties": {
    "iso:country":"US",
    "sg:address":"903 Hazelvalley Dr",
    "sg:city":"Hazelwood",
    "sg:classifiers":[
        {
            "category":"Professional",
            "subcategory":"Advertising",
            "type":"Services"
        }
    ],
    "sg:phone":"+1 314 830 4887",
    "sg:postcode":"63042",
    "sg:province":"MO",
    "sg:tags":[
        "agency"
    ],
    "wof:name":"Internet Advertising",
    "wof:placetype":"venue"
},
  "geometry": {"coordinates":[-90.355887,38.793288],"type":"Point"}
}