{
  "type": "Feature",
  "properties": {
    "iso:country":"US",
    "sg:address":"20490 Granite Rd",
    "sg:city":"Atlanta",
    "sg:phone":"+1 660 825 2483",
    "sg:postcode":"63530",
    "sg:province":"MO",
    "sg:tags":[
        "farm",
        "corn",
        "soybean"
    ],
    "wof:name":"Raymond Stull",
    "wof:placetype":"venue"
},
  "geometry": {"coordinates":[-92.608574,39.892531],"type":"Point"}
}