{
  "type": "Feature",
  "properties": {
    "iso:country":"US",
    "sg:address":"6 Westowne St",
    "sg:city":"Liberty",
    "sg:classifiers":[
        {
            "category":"Real Estate",
            "subcategory":"Real Estate Agent",
            "type":"Services"
        }
    ],
    "sg:phone":"+1 816 407 7900",
    "sg:postcode":"64068",
    "sg:province":"MO",
    "wof:name":"Cates Real Estate Co",
    "wof:placetype":"venue"
},
  "geometry": {"coordinates":[-94.439595,39.246144],"type":"Point"}
}