{
  "type": "Feature",
  "properties": {
    "iso:country":"US",
    "sg:address":"118 W Main St",
    "sg:city":"Branson",
    "sg:classifiers":[
        {
            "category":"Shopping",
            "type":"Retail Goods"
        }
    ],
    "sg:phone":"+1 417 334 8632",
    "sg:postcode":"65616",
    "sg:province":"MO",
    "sg:tags":[
        "merchandise"
    ],
    "wof:name":"J&J Jewerly Depot",
    "wof:placetype":"venue"
},
  "geometry": {"coordinates":[-93.217237,36.644135],"type":"Point"}
}