{
  "type": "Feature",
  "properties": {
    "iso:country":"US",
    "sg:address":"34101 Highway 63 N",
    "sg:city":"Vienna",
    "sg:classifiers":[
        {
            "category":"Farming",
            "subcategory":"Livestock Farm",
            "type":"Manufacturing & Wholesale Goods"
        }
    ],
    "sg:phone":"+1 573 422 6035",
    "sg:postcode":"65582",
    "sg:province":"MO",
    "sg:tags":[
        "ranch"
    ],
    "wof:name":"Wagner Farms",
    "wof:placetype":"venue"
},
  "geometry": {"coordinates":[-91.931077,38.247767],"type":"Point"}
}