{
  "type": "Feature",
  "properties": {
    "iso:country":"US",
    "sg:address":"678 Kehrs Mill Rd",
    "sg:city":"Ballwin",
    "sg:classifiers":[
        {
            "category":"Building & Trades",
            "subcategory":"Construction",
            "type":"Services"
        }
    ],
    "sg:phone":"+1 636 391 6515",
    "sg:postcode":"63011",
    "sg:province":"MO",
    "sg:tags":[
        "general",
        "contractor"
    ],
    "wof:name":"Bruder Construction Co",
    "wof:placetype":"venue"
},
  "geometry": {"coordinates":[-90.55646,38.601206],"type":"Point"}
}