{
  "type": "Feature",
  "properties": {
    "iso:country":"US",
    "sg:address":"1055 Carolyn Dr",
    "sg:city":"Jackson",
    "sg:classifiers":[
        {
            "category":"Retail",
            "subcategory":"Repair Shop",
            "type":"Services"
        }
    ],
    "sg:phone":"+1 573 243 5488",
    "sg:postcode":"63755",
    "sg:province":"MO",
    "wof:name":"Kps Kramer Plbg Septic & Svc",
    "wof:placetype":"venue"
},
  "geometry": {"coordinates":[-89.68371999999999,37.381059],"type":"Point"}
}