{
  "type": "Feature",
  "properties": {
    "iso:country":"US",
    "sg:address":"1633 Kehrs Mill Rd",
    "sg:city":"Chesterfield",
    "sg:classifiers":[
        {
            "category":"Education",
            "subcategory":"School",
            "type":"Public Place"
        }
    ],
    "sg:phone":"+1 636 532 3315",
    "sg:postcode":"63005",
    "sg:province":"MO",
    "sg:website":"www.lvcsstl.org",
    "wof:name":"Linda Vista Catholic School",
    "wof:placetype":"venue"
},
  "geometry": {"coordinates":[-90.612447,38.6433],"type":"Point"}
}