{
  "type": "Feature",
  "properties": {
    "iso:country":"US",
    "sg:address":"1202 Genessee St",
    "sg:city":"Kansas City",
    "sg:classifiers":[
        {
            "category":"Wholesale",
            "subcategory":"Construction Materials",
            "type":"Manufacturing & Wholesale Goods"
        }
    ],
    "sg:phone":"+1 816 474 9726",
    "sg:postcode":"64102",
    "sg:province":"MO",
    "sg:tags":[
        "brick",
        "common",
        "face"
    ],
    "wof:name":"Ben Tarbe Used Brick Inc",
    "wof:placetype":"venue"
},
  "geometry": {"coordinates":[-94.604837,39.099126],"type":"Point"}
}