{
  "type": "Feature",
  "properties": {
    "iso:country":"US",
    "sg:address":"1108 E Broadway St",
    "sg:city":"Monett",
    "sg:classifiers":[
        {
            "category":"Freight",
            "type":"Transportation"
        }
    ],
    "sg:phone":"+1 417 235 3766",
    "sg:postcode":"65708",
    "sg:province":"MO",
    "sg:tags":[
        "commercial",
        "storage"
    ],
    "wof:name":"Crossland Stor-All",
    "wof:placetype":"venue"
},
  "geometry": {"coordinates":[-93.914131,36.92331],"type":"Point"}
}