{
  "type": "Feature",
  "properties": {
    "iso:country":"US",
    "sg:address":"8 Champlain Ct",
    "sg:city":"Florissant",
    "sg:classifiers":[
        {
            "category":"Farming",
            "subcategory":"Livestock Farm",
            "type":"Manufacturing & Wholesale Goods"
        }
    ],
    "sg:phone":"+1 314 972 7165",
    "sg:postcode":"63031",
    "sg:province":"MO",
    "sg:tags":[
        "beef",
        "feedlot",
        "cattle"
    ],
    "wof:name":"Raymond Hoormann",
    "wof:placetype":"venue"
},
  "geometry": {"coordinates":[-90.32344399999999,38.799793],"type":"Point"}
}