{
  "type": "Feature",
  "properties": {
    "iso:country":"US",
    "sg:address":"9947 W Florissant Ave",
    "sg:city":"St Louis",
    "sg:classifiers":[
        {
            "category":"Autos & Motor Vehicles",
            "subcategory":"Auto Supplies",
            "type":"Retail Goods"
        }
    ],
    "sg:phone":"+1 314 522 1773",
    "sg:postcode":"63136",
    "sg:province":"MO",
    "sg:tags":[
        "automobile",
        "parts"
    ],
    "wof:name":"Autozone",
    "wof:placetype":"venue"
},
  "geometry": {"coordinates":[-90.279797,38.747761],"type":"Point"}
}