{
  "type": "Feature",
  "properties": {
    "iso:country":"US",
    "sg:address":"1500 S 5th St",
    "sg:city":"Saint Charles",
    "sg:classifiers":[
        {
            "category":"Professional",
            "subcategory":"Advertising",
            "type":"Services"
        }
    ],
    "sg:phone":"+1 636 723 1877",
    "sg:postcode":"63303",
    "sg:province":"MO",
    "sg:tags":[
        "agency"
    ],
    "wof:name":"Summit Communications",
    "wof:placetype":"venue"
},
  "geometry": {"coordinates":[-90.49623,38.76577],"type":"Point"}
}