{
  "type": "Feature",
  "properties": {
    "iso:country":"US",
    "sg:address":"204 N Alvarado St",
    "sg:city":"Belle",
    "sg:classifiers":[
        {
            "category":"Banks & Credit Unions",
            "subcategory":"Bank",
            "type":"Services"
        }
    ],
    "sg:phone":"+1 573 859 3311",
    "sg:postcode":"65013",
    "sg:province":"MO",
    "sg:tags":[
        "saving",
        "commercial"
    ],
    "sg:website":"http://www.legendsbk.com",
    "wof:name":"Legends Bank",
    "wof:placetype":"venue"
},
  "geometry": {"coordinates":[-91.721048,38.290316],"type":"Point"}
}