{
  "type": "Feature",
  "properties": {
    "iso:country":"US",
    "sg:address":"3552 E Carol Dr",
    "sg:city":"Springfield",
    "sg:classifiers":[
        {
            "category":"Insurance",
            "subcategory":"Hazard Insurance",
            "type":"Services"
        }
    ],
    "sg:phone":"+1 417 887 2874",
    "sg:postcode":"65809",
    "sg:province":"MO",
    "sg:tags":[
        "commercial",
        "business"
    ],
    "wof:name":"State Farm Insurance",
    "wof:placetype":"venue"
},
  "geometry": {"coordinates":[-93.221424,37.186117],"type":"Point"}
}