{
  "type": "Feature",
  "properties": {
    "iso:country":"US",
    "sg:address":"6520 Highway Yy",
    "sg:city":"Washington",
    "sg:classifiers":[
        {
            "category":"Education",
            "subcategory":"School",
            "type":"Public Place"
        }
    ],
    "sg:phone":"+1 636 239 2347",
    "sg:postcode":"63090",
    "sg:province":"MO",
    "sg:tags":[
        "k-",
        "private"
    ],
    "wof:name":"Dioease Of St Louis",
    "wof:placetype":"venue"
},
  "geometry": {"coordinates":[-91.048861,38.497326],"type":"Point"}
}