{
  "type": "Feature",
  "properties": {
    "iso:country":"US",
    "sg:address":"2600 S Quincy Ave",
    "sg:city":"Sedalia",
    "sg:classifiers":[
        {
            "category":"Education",
            "subcategory":"Preschool",
            "type":"Public Place"
        }
    ],
    "sg:phone":"+1 660 827 5651",
    "sg:postcode":"65301",
    "sg:province":"MO",
    "sg:tags":[
        "school",
        "nursery"
    ],
    "wof:name":"Donnas Day Care",
    "wof:placetype":"venue"
},
  "geometry": {"coordinates":[-93.239254,38.6886],"type":"Point"}
}