{
  "type": "Feature",
  "properties": {
    "iso:country":"US",
    "sg:address":"3021 Parkway A St",
    "sg:city":"Saint Joseph",
    "sg:classifiers":[
        {
            "category":"Travel",
            "subcategory":"Travel Agent",
            "type":"Entertainment"
        }
    ],
    "sg:phone":"+1 816 233 6751",
    "sg:postcode":"64507",
    "sg:province":"MO",
    "sg:tags":[
        "agency"
    ],
    "wof:name":"Brennco Travel Independent Con",
    "wof:placetype":"venue"
},
  "geometry": {"coordinates":[-94.81809699999999,39.759991],"type":"Point"}
}