{
  "type": "Feature",
  "properties": {
    "iso:country":"US",
    "sg:address":"206 Louisa Ave",
    "sg:city":"Saint Louis",
    "sg:classifiers":[
        {
            "category":"Shopping",
            "subcategory":"Clothing, Apparel, & Fashions",
            "type":"Retail Goods"
        }
    ],
    "sg:phone":"+1 314 621 8300",
    "sg:postcode":"63135",
    "sg:province":"MO",
    "wof:name":"Claires",
    "wof:placetype":"venue"
},
  "geometry": {"coordinates":[-90.309748,38.738745],"type":"Point"}
}