{
  "type": "Feature",
  "properties": {
    "addr:full":"3007 N Belt Hwy St Joseph MO 64506",
    "addr:housenumber":"3007",
    "addr:postcode":"64506",
    "addr:street":"N Belt Hwy St",
    "iso:country":"US",
    "sg:address":"3007 N Belt Hwy",
    "sg:city":"St Joseph",
    "sg:classifiers":[
        {
            "category":"Professional",
            "subcategory":"Accounting & Tax Preparation",
            "type":"Services"
        }
    ],
    "sg:phone":"+1 816 233 7005",
    "sg:postcode":"64506",
    "sg:province":"MO",
    "sg:tags":[
        "return",
        "filing"
    ],
    "wof:name":"H & R Block Tax Svc",
    "wof:placetype":"venue"
},
  "geometry": {"coordinates":[-94.810305,39.791899],"type":"Point"}
}