{
  "type": "Feature",
  "properties": {
    "iso:country":"US",
    "sg:address":"9614 Krommer Rd",
    "sg:city":"Cedar Hill",
    "sg:classifiers":[
        {
            "category":"Freight",
            "type":"Transportation"
        }
    ],
    "sg:phone":"+1 636 274 3819",
    "sg:postcode":"63016",
    "sg:province":"MO",
    "sg:tags":[
        "operator",
        "local",
        "trucking"
    ],
    "wof:name":"Kevin M Wilson",
    "wof:placetype":"venue"
},
  "geometry": {"coordinates":[-90.703535,38.351959],"type":"Point"}
}