{
  "type": "Feature",
  "properties": {
    "iso:country":"US",
    "sg:address":"Tower Grove Park 4256 Magnolia Ave",
    "sg:city":"St Louis",
    "sg:classifiers":[
        {
            "category":"Arts & Performance",
            "subcategory":"Festival",
            "type":"Entertainment"
        }
    ],
    "sg:postcode":"63110",
    "sg:province":"MO",
    "sg:website":"www.pridestl.org/",
    "wof:name":"PrideFest",
    "wof:placetype":"venue"
},
  "geometry": {"coordinates":[-90.257074,38.608688],"type":"Point"}
}