{
  "type": "Feature",
  "properties": {
    "iso:country":"US",
    "sg:address":"719 Garland Pl",
    "sg:city":"Saint Louis",
    "sg:classifiers":[
        {
            "category":"Professional",
            "subcategory":"Business Services",
            "type":"Services"
        }
    ],
    "sg:phone":"+1 314 821 7887",
    "sg:postcode":"63122",
    "sg:province":"MO",
    "sg:tags":[
        "interior",
        "designer"
    ],
    "wof:name":"Linda Cooperman Interiors",
    "wof:placetype":"venue"
},
  "geometry": {"coordinates":[-90.39139299999999,38.607554],"type":"Point"}
}