{
  "type": "Feature",
  "properties": {
    "iso:country":"US",
    "sg:address":"217 E 16th St",
    "sg:city":"Sedalia",
    "sg:classifiers":[
        {
            "category":"Wholesale",
            "subcategory":"Electrical",
            "type":"Manufacturing & Wholesale Goods"
        }
    ],
    "sg:phone":"+1 660 826 4247",
    "sg:postcode":"65301",
    "sg:province":"MO",
    "wof:name":"Rival Mfg Co",
    "wof:placetype":"venue"
},
  "geometry": {"coordinates":[-93.227357,38.697497],"type":"Point"}
}