{
  "type": "Feature",
  "properties": {
    "addr:full":"9 Dillon Plaza Dr High Ridge MO 63049",
    "addr:housenumber":"9",
    "addr:postcode":"63049",
    "addr:street":"Dillon Plaza Dr",
    "iso:country":"US",
    "sg:address":"9 Dillon Plaza Dr",
    "sg:city":"High Ridge",
    "sg:classifiers":[
        {
            "category":"Banks & Credit Unions",
            "subcategory":"Bank",
            "type":"Services"
        }
    ],
    "sg:phone":"+1 636 376 8414",
    "sg:postcode":"63049",
    "sg:province":"MO",
    "sg:tags":[
        "cashing",
        "check"
    ],
    "wof:name":"Check 'n Go",
    "wof:placetype":"venue"
},
  "geometry": {"coordinates":[-90.521235,38.4782],"type":"Point"}
}