{
  "type": "Feature",
  "properties": {
    "iso:country":"US",
    "sg:address":"1395 E State Hwy K",
    "sg:city":"West Plains",
    "sg:classifiers":[
        {
            "category":"Building & Trades",
            "subcategory":"Construction",
            "type":"Services"
        }
    ],
    "sg:phone":"+1 417 255 2798",
    "sg:postcode":"65775",
    "sg:province":"MO",
    "sg:tags":[
        "contractor"
    ],
    "wof:name":"Midwest Ornamental & Security",
    "wof:placetype":"venue"
},
  "geometry": {"coordinates":[-91.89015999999999,36.726519],"type":"Point"}
}