{
  "type": "Feature",
  "properties": {
    "iso:country":"US",
    "sg:address":"1449 S Vandeventer Ave",
    "sg:city":"Saint Louis",
    "sg:classifiers":[
        {
            "category":"Restaurant",
            "type":"Food & Drink"
        }
    ],
    "sg:menulink":"http://www.allmenus.com/mo/st-louis/157892-the-billy-goat/menu/",
    "sg:phone":"+1 314 371 4628",
    "sg:postcode":"63110",
    "sg:province":"MO",
    "sg:tags":[
        "wrap",
        "american",
        "sandwich"
    ],
    "wof:name":"The Billy Goat",
    "wof:placetype":"venue"
},
  "geometry": {"coordinates":[-90.253275,38.624411],"type":"Point"}
}