{
  "type": "Feature",
  "properties": {
    "iso:country":"US",
    "sg:address":"1666 Highway 28",
    "sg:city":"Owensville",
    "sg:classifiers":[
        {
            "category":"Wholesale",
            "subcategory":"Hardware",
            "type":"Manufacturing & Wholesale Goods"
        },
        {
            "category":"Home & Garden",
            "subcategory":"Garden Supply",
            "type":"Retail Goods"
        },
        {
            "category":"Retail",
            "subcategory":"Repair Shop",
            "type":"Services"
        }
    ],
    "sg:phone":"+1 573 437 2105",
    "sg:postcode":"65066",
    "sg:province":"MO",
    "sg:tags":[
        "renting",
        "lawn",
        "outdoor",
        "power",
        "landscaping",
        "equipment-sales",
        "equipment",
        "saw"
    ],
    "sg:website":"http://www.stihlusa.com/",
    "wof:name":"Donald Farm & Lawn, Inc.",
    "wof:placetype":"venue"
},
  "geometry": {"coordinates":[-91.472406,38.361091],"type":"Point"}
}