{
  "type": "Feature",
  "properties": {
    "addr:full":"314 N High St California MO 65018",
    "addr:housenumber":"314",
    "addr:postcode":"65018",
    "addr:street":"N High St",
    "iso:country":"US",
    "sg:address":"314 N High St",
    "sg:city":"California",
    "sg:classifiers":[
        {
            "category":"Organizations",
            "subcategory":"Community Association",
            "type":"Services"
        }
    ],
    "sg:phone":"+1 573 796 4027",
    "sg:postcode":"65018",
    "sg:province":"MO",
    "sg:tags":[
        "fraternal"
    ],
    "wof:name":"Fraternal Order Of Eagles",
    "wof:placetype":"venue"
},
  "geometry": {"coordinates":[-92.565282,38.6353],"type":"Point"}
}