{
  "type": "Feature",
  "properties": {
    "iso:country":"US",
    "sg:address":"5710 US Hwy 67",
    "sg:city":"Florissant",
    "sg:classifiers":[
        {
            "category":"Organizations",
            "subcategory":"Religious Organization",
            "type":"Services"
        }
    ],
    "sg:phone":"+1 314 741 1590",
    "sg:postcode":"63034",
    "sg:province":"MO",
    "wof:name":"Zion Untd Chrch of Christ of N",
    "wof:placetype":"venue"
},
  "geometry": {"coordinates":[-90.25109399999999,38.822939],"type":"Point"}
}