{
  "type": "Feature",
  "properties": {
    "iso:country":"US",
    "sg:address":"353 Mission Bay Ct",
    "sg:city":"Grover",
    "sg:classifiers":[
        {
            "category":"Wholesale",
            "subcategory":"Non-durable Goods",
            "type":"Manufacturing & Wholesale Goods"
        }
    ],
    "sg:phone":"+1 636 458 9582",
    "sg:postcode":"63040",
    "sg:province":"MO",
    "wof:name":"Gateway Safety Products Inc",
    "wof:placetype":"venue"
},
  "geometry": {"coordinates":[-90.611389,38.573838],"type":"Point"}
}