{
  "type": "Feature",
  "properties": {
    "iso:country":"US",
    "sg:address":"413 Fulton Ave",
    "sg:city":"Mokane",
    "sg:classifiers":[
        {
            "category":"Place Of Worship",
            "subcategory":"Church",
            "type":"Public Place"
        },
        {
            "category":"Place Of Worship",
            "type":"Public Place"
        }
    ],
    "sg:phone":"+1 573 676 3206",
    "sg:postcode":"65059",
    "sg:province":"MO",
    "sg:tags":[
        "churches-methodist"
    ],
    "wof:name":"Steedman Methodist Church",
    "wof:placetype":"venue"
},
  "geometry": {"coordinates":[-91.876664,38.674318],"type":"Point"}
}