{
  "type": "Feature",
  "properties": {
    "iso:country":"US",
    "sg:address":"21951 Bright Ln",
    "sg:city":"Lawson",
    "sg:classifiers":[
        {
            "category":"Personal",
            "subcategory":"Beauty Salon",
            "type":"Services"
        }
    ],
    "sg:phone":"+1 816 296 7340",
    "sg:postcode":"64062",
    "sg:province":"MO",
    "sg:tags":[
        "shop"
    ],
    "wof:name":"Shear Elegance",
    "wof:placetype":"venue"
},
  "geometry": {"coordinates":[-94.19104900000001,39.469298],"type":"Point"}
}