{
  "type": "Feature",
  "properties": {
    "iso:country":"US",
    "sg:address":"206 W Maple St",
    "sg:city":"Slater",
    "sg:classifiers":[
        {
            "category":"Professional",
            "subcategory":"Lawyer & Legal Services",
            "type":"Services"
        }
    ],
    "sg:phone":"+1 660 529 2266",
    "sg:postcode":"65349",
    "sg:province":"MO",
    "sg:tags":[
        "attorney"
    ],
    "wof:name":"George L Stafford",
    "wof:placetype":"venue"
},
  "geometry": {"coordinates":[-93.064065,39.219402],"type":"Point"}
}