{
  "type": "Feature",
  "properties": {
    "addr:full":"129 N Oaks Plz Saint Louis MO 63121",
    "addr:housenumber":"129",
    "addr:postcode":"63121",
    "addr:street":"N Oaks Plz",
    "iso:country":"US",
    "sg:address":"129 N Oaks Plz",
    "sg:city":"Saint Louis",
    "sg:classifiers":[
        {
            "category":"Restaurant",
            "type":"Food & Drink"
        }
    ],
    "sg:phone":"+1 314 389 1122",
    "sg:postcode":"63121",
    "sg:province":"MO",
    "sg:tags":[
        "pizza"
    ],
    "sg:website":"www.imospizza.com",
    "wof:name":"Imo's Pizza",
    "wof:placetype":"venue"
},
  "geometry": {"coordinates":[-90.290199,38.701],"type":"Point"}
}