{
  "type": "Feature",
  "properties": {
    "iso:country":"US",
    "sg:address":"6055 W Florissant Ave",
    "sg:city":"St Louis",
    "sg:classifiers":[
        {
            "category":"Personal",
            "subcategory":"Beauty Salon",
            "type":"Services"
        },
        {
            "category":"Personal",
            "subcategory":"Barber",
            "type":"Services"
        }
    ],
    "sg:phone":"+1 314 381 0287",
    "sg:postcode":"63136",
    "sg:province":"MO",
    "sg:tags":[
        "shop"
    ],
    "wof:name":"Jacquise's Hair Styling Salon",
    "wof:placetype":"venue"
},
  "geometry": {"coordinates":[-90.25294,38.710848],"type":"Point"}
}