{
  "type": "Feature",
  "properties": {
    "iso:country":"US",
    "sg:address":"7148 Maryland Ave",
    "sg:city":"Saint Louis",
    "sg:classifiers":[
        {
            "category":"Insurance",
            "subcategory":"Health Insurance",
            "type":"Services"
        }
    ],
    "sg:phone":"+1 314 256 1433",
    "sg:postcode":"63130",
    "sg:province":"MO",
    "sg:tags":[
        "market"
    ],
    "wof:name":"Allergaroo",
    "wof:placetype":"venue"
},
  "geometry": {"coordinates":[-90.319791,38.649769],"type":"Point"}
}