{
  "type": "Feature",
  "properties": {
    "iso:country":"US",
    "sg:address":"30918 State Hwy T",
    "sg:city":"Kirksville",
    "sg:classifiers":[
        {
            "category":"Organizations",
            "subcategory":"Religious Organization",
            "type":"Services"
        }
    ],
    "sg:phone":"+1 660 627 3721",
    "sg:postcode":"63501",
    "sg:province":"MO",
    "wof:name":"Bethel Community Church",
    "wof:placetype":"venue"
},
  "geometry": {"coordinates":[-92.46500899999999,40.280229],"type":"Point"}
}