{
  "type": "Feature",
  "properties": {
    "iso:country":"US",
    "sg:address":"2715 E McCarty St",
    "sg:city":"Jefferson City",
    "sg:classifiers":[
        {
            "category":"Restaurant",
            "type":"Food & Drink"
        }
    ],
    "sg:phone":"+1 573 635 1221",
    "sg:postcode":"65101",
    "sg:province":"MO",
    "sg:tags":[
        "eating"
    ],
    "wof:name":"Daisy Delight Restaurant",
    "wof:placetype":"venue"
},
  "geometry": {"coordinates":[-92.122742,38.554541],"type":"Point"}
}