{
  "type": "Feature",
  "properties": {
    "iso:country":"US",
    "sg:address":"43 Ross Ln Ste 225",
    "sg:city":"Lampe",
    "sg:classifiers":[
        {
            "category":"Professional",
            "subcategory":"Detective & Security Services",
            "type":"Services"
        }
    ],
    "sg:phone":"+1 417 779 2282",
    "sg:postcode":"65681",
    "sg:province":"MO",
    "sg:tags":[
        "information",
        "bureau"
    ],
    "wof:name":"Aircraft Cad Services",
    "wof:placetype":"venue"
},
  "geometry": {"coordinates":[-93.433689,36.567807],"type":"Point"}
}