{
  "type": "Feature",
  "properties": {
    "iso:country":"US",
    "sg:address":"6102 E 211th St",
    "sg:city":"Belton",
    "sg:classifiers":[
        {
            "category":"Restaurant",
            "type":"Food & Drink"
        }
    ],
    "sg:phone":"+1 816 331 8899",
    "sg:postcode":"64012",
    "sg:province":"MO",
    "sg:tags":[
        "eating"
    ],
    "wof:name":"Distinctive Home Services",
    "wof:placetype":"venue"
},
  "geometry": {"coordinates":[-94.53146099999999,38.741897],"type":"Point"}
}