{
  "type": "Feature",
  "properties": {
    "iso:country":"US",
    "sg:address":"8903 Wrenwood Ln",
    "sg:city":"Saint Louis",
    "sg:classifiers":[
        {
            "category":"Professional",
            "subcategory":"Management & Consulting",
            "type":"Services"
        }
    ],
    "sg:phone":"+1 314 968 7233",
    "sg:postcode":"63144",
    "sg:province":"MO",
    "sg:tags":[
        "business"
    ],
    "wof:name":"Daniel R Mandelker Aicp",
    "wof:placetype":"venue"
},
  "geometry": {"coordinates":[-90.35015300000001,38.625315],"type":"Point"}
}