{
  "type": "Feature",
  "properties": {
    "iso:country":"US",
    "sg:address":"2245 Old Toll Rd",
    "sg:city":"Jackson",
    "sg:classifiers":[
        {
            "category":"Place Of Worship",
            "subcategory":"Church",
            "type":"Public Place"
        },
        {
            "category":"Place Of Worship",
            "type":"Public Place"
        }
    ],
    "sg:phone":"+1 573 243 0973",
    "sg:postcode":"63755",
    "sg:province":"MO",
    "sg:tags":[
        "nazarene",
        "churches-church",
        "churches-nazarene"
    ],
    "wof:name":"Jackson Church of The Nazarene",
    "wof:placetype":"venue"
},
  "geometry": {"coordinates":[-89.695097,37.381471],"type":"Point"}
}