{
  "type": "Feature",
  "properties": {
    "iso:country":"US",
    "sg:address":"684 Jackson Trl",
    "sg:city":"Jackson",
    "sg:classifiers":[
        {
            "category":"Social Services",
            "type":"Services"
        }
    ],
    "sg:phone":"+1 573 243 3582",
    "sg:postcode":"63755",
    "sg:province":"MO",
    "sg:tags":[
        "youth",
        "organization",
        "center"
    ],
    "wof:name":"4 H Cape County",
    "wof:placetype":"venue"
},
  "geometry": {"coordinates":[-89.661214,37.371656],"type":"Point"}
}