{
  "type": "Feature",
  "properties": {
    "iso:country":"US",
    "sg:address":"1328 Washington Ave",
    "sg:city":"St Louis",
    "sg:classifiers":[
        {
            "category":"Personal",
            "subcategory":"Tattoo Parlor",
            "type":"Services"
        }
    ],
    "sg:phone":"+1 314 621 4660",
    "sg:postcode":"63103",
    "sg:province":"MO",
    "sg:website":"www.myspace.com/sistl",
    "wof:name":"Self Inflicted Studios",
    "wof:placetype":"venue"
},
  "geometry": {"coordinates":[-90.199399,38.632319],"type":"Point"}
}