{
  "type": "Feature",
  "properties": {
    "iso:country":"US",
    "sg:address":"2025 S Brentwood Blvd",
    "sg:city":"Saint Louis",
    "sg:classifiers":[
        {
            "category":"Professional",
            "subcategory":"Computer Services",
            "type":"Services"
        }
    ],
    "sg:phone":"+1 314 968 3372",
    "sg:postcode":"63144",
    "sg:province":"MO",
    "sg:tags":[
        "prepackaged",
        "advisory",
        "investment",
        "software"
    ],
    "wof:name":"Rice Money Managers",
    "wof:placetype":"venue"
},
  "geometry": {"coordinates":[-90.348422,38.623514],"type":"Point"}
}