{
  "type": "Feature",
  "properties": {
    "iso:country":"US",
    "sg:address":"98 S Washington St",
    "sg:city":"Chillicothe",
    "sg:classifiers":[
        {
            "category":"Government",
            "subcategory":"Jail",
            "type":"Public Place"
        }
    ],
    "sg:phone":"+1 660 646 4535",
    "sg:postcode":"64601",
    "sg:province":"MO",
    "sg:tags":[
        "probation",
        "parole"
    ],
    "wof:name":"District 2",
    "wof:placetype":"venue"
},
  "geometry": {"coordinates":[-93.55304099999999,39.785999],"type":"Point"}
}