{
  "type": "Feature",
  "properties": {
    "iso:country":"US",
    "sg:address":"212 Village Center St",
    "sg:city":"Nixa",
    "sg:classifiers":[
        {
            "category":"Professional",
            "subcategory":"Lawyer & Legal Services",
            "type":"Services"
        }
    ],
    "sg:phone":"+1 417 725 4429",
    "sg:postcode":"65714",
    "sg:province":"MO",
    "sg:tags":[
        "attorney"
    ],
    "wof:name":"Law Office Sam Gentry",
    "wof:placetype":"venue"
},
  "geometry": {"coordinates":[-93.30131900000001,37.04013],"type":"Point"}
}