{
  "type": "Feature",
  "properties": {
    "iso:country":"US",
    "sg:address":"2400 Lucy Lee Pkwy",
    "sg:city":"Poplar Bluff",
    "sg:classifiers":[
        {
            "category":"Health Services",
            "subcategory":"Doctor",
            "type":"Services"
        }
    ],
    "sg:phone":"+1 573 785 4043",
    "sg:postcode":"63901",
    "sg:province":"MO",
    "sg:tags":[
        "physician",
        "surgeon"
    ],
    "wof:name":"Orthopaedic Associates PC",
    "wof:placetype":"venue"
},
  "geometry": {"coordinates":[-90.424161,36.787407],"type":"Point"}
}