{
  "type": "Feature",
  "properties": {
    "iso:country":"US",
    "sg:address":"501 W Lexington Ave",
    "sg:city":"Independence",
    "sg:classifiers":[
        {
            "category":"Building & Trades",
            "subcategory":"Cleaning & Sanitation",
            "type":"Services"
        }
    ],
    "sg:phone":"+1 816 833 1800",
    "sg:postcode":"64050",
    "sg:province":"MO",
    "sg:tags":[
        "maintenance",
        "legal"
    ],
    "wof:name":"Constance Bradley A",
    "wof:placetype":"venue"
},
  "geometry": {"coordinates":[-94.424199,39.092357],"type":"Point"}
}