{
  "type": "Feature",
  "properties": {
    "iso:country":"US",
    "sg:address":"930 Kehrs Mill Rd",
    "sg:city":"Ballwin",
    "sg:classifiers":[
        {
            "category":"Place Of Worship",
            "subcategory":"Church",
            "type":"Public Place"
        },
        {
            "category":"Place Of Worship",
            "type":"Public Place"
        }
    ],
    "sg:phone":"+1 314 707 0055",
    "sg:postcode":"63011",
    "sg:province":"MO",
    "sg:tags":[
        "christ",
        "churches-community"
    ],
    "wof:name":"Red Tree Community Church",
    "wof:placetype":"venue"
},
  "geometry": {"coordinates":[-90.563957,38.605439],"type":"Point"}
}