{
  "type": "Feature",
  "properties": {
    "iso:country":"US",
    "sg:address":"150 Eberle Rd",
    "sg:city":"Silex",
    "sg:classifiers":[
        {
            "category":"Farming",
            "subcategory":"Livestock Farm",
            "type":"Manufacturing & Wholesale Goods"
        },
        {
            "category":"Farming",
            "subcategory":"Farm",
            "type":"Manufacturing & Wholesale Goods"
        }
    ],
    "sg:phone":"+1 573 384 5942",
    "sg:postcode":"63377",
    "sg:province":"MO",
    "sg:tags":[
        "ranch"
    ],
    "wof:name":"William Eberle",
    "wof:placetype":"venue"
},
  "geometry": {"coordinates":[-91.077341,39.121699],"type":"Point"}
}