{
  "type": "Feature",
  "properties": {
    "iso:country":"US",
    "sg:address":"511 S 16th St",
    "sg:city":"St Joseph",
    "sg:classifiers":[
        {
            "category":"Building & Trades",
            "subcategory":"Construction",
            "type":"Services"
        }
    ],
    "sg:phone":"+1 816 901 0200",
    "sg:postcode":"64501",
    "sg:province":"MO",
    "sg:tags":[
        "general",
        "contractor"
    ],
    "wof:name":"Trinity Management & Comm Dev",
    "wof:placetype":"venue"
},
  "geometry": {"coordinates":[-94.841076,39.762486],"type":"Point"}
}