{
  "type": "Feature",
  "properties": {
    "iso:country":"US",
    "sg:address":"123 E Park Ave",
    "sg:city":"Union",
    "sg:classifiers":[
        {
            "category":"Retail",
            "subcategory":"Repair Shop",
            "type":"Services"
        }
    ],
    "sg:phone":"+1 636 583 5935",
    "sg:postcode":"63084",
    "sg:province":"MO",
    "sg:tags":[
        "leather"
    ],
    "wof:name":"Woodland Gallery Taxidermy",
    "wof:placetype":"venue"
},
  "geometry": {"coordinates":[-91.008959,38.450329],"type":"Point"}
}