{
  "type": "Feature",
  "properties": {
    "iso:country":"US",
    "sg:address":"2346 Rust Ave",
    "sg:city":"Cape Girardeau",
    "sg:classifiers":[
        {
            "category":"Wholesale",
            "subcategory":"Beer",
            "type":"Manufacturing & Wholesale Goods"
        }
    ],
    "sg:phone":"+1 573 335 7717",
    "sg:postcode":"63703",
    "sg:province":"MO",
    "sg:tags":[
        "ale"
    ],
    "sg:website":"www.rivereagle.com",
    "wof:name":"River Eagle",
    "wof:placetype":"venue"
},
  "geometry": {"coordinates":[-89.550068,37.288604],"type":"Point"}
}