{
  "type": "Feature",
  "properties": {
    "iso:country":"US",
    "sg:address":"915 Rock St",
    "sg:city":"Hannibal",
    "sg:classifiers":[
        {
            "category":"Professional",
            "subcategory":"Business Services",
            "type":"Services"
        }
    ],
    "sg:phone":"+1 573 221 4085",
    "sg:postcode":"63401",
    "sg:province":"MO",
    "wof:name":"Dana Brothers",
    "wof:placetype":"venue"
},
  "geometry": {"coordinates":[-91.36645300000001,39.710153],"type":"Point"}
}