{
  "type": "Feature",
  "properties": {
    "iso:country":"US",
    "sg:address":"120 Tella Jane Ln",
    "sg:city":"Louisiana",
    "sg:classifiers":[
        {
            "category":"Personal",
            "subcategory":"Beauty Salon",
            "type":"Services"
        }
    ],
    "sg:phone":"+1 573 754 4179",
    "sg:postcode":"63353",
    "sg:province":"MO",
    "wof:name":"Lisa's Hair Design Shop",
    "wof:placetype":"venue"
},
  "geometry": {"coordinates":[-91.070027,39.434082],"type":"Point"}
}