{
  "type": "Feature",
  "properties": {
    "iso:country":"US",
    "sg:address":"1910 N Bishop Ave",
    "sg:city":"Rolla",
    "sg:classifiers":[
        {
            "category":"Restaurant",
            "type":"Food & Drink"
        }
    ],
    "sg:phone":"+1 573 341 2655",
    "sg:postcode":"65401",
    "sg:province":"MO",
    "sg:tags":[
        "eating"
    ],
    "wof:name":"Waffle House",
    "wof:placetype":"venue"
},
  "geometry": {"coordinates":[-91.76613999999999,37.96055],"type":"Point"}
}