{
  "type": "Feature",
  "properties": {
    "iso:country":"US",
    "sg:address":"9933 Arthur Ln",
    "sg:city":"Saint Louis",
    "sg:classifiers":[
        {
            "category":"Building & Trades",
            "subcategory":"Construction",
            "type":"Services"
        }
    ],
    "sg:phone":"+1 314 849 6413",
    "sg:postcode":"63128",
    "sg:province":"MO",
    "sg:tags":[
        "hanging",
        "contractor"
    ],
    "wof:name":"Hosang Painting",
    "wof:placetype":"venue"
},
  "geometry": {"coordinates":[-90.358923,38.522756],"type":"Point"}
}