{
  "type": "Feature",
  "properties": {
    "iso:country":"US",
    "sg:address":"342 N Scott Ave",
    "sg:city":"Belton",
    "sg:classifiers":[
        {
            "category":"Building & Trades",
            "subcategory":"Plumbing",
            "type":"Services"
        }
    ],
    "sg:phone":"+1 816 318 8062",
    "sg:postcode":"64012",
    "sg:province":"MO",
    "sg:tags":[
        "conditioning",
        "air",
        "system",
        "contractor"
    ],
    "wof:name":"Triece Mechanical Olc",
    "wof:placetype":"venue"
},
  "geometry": {"coordinates":[-94.53459599999999,38.819232],"type":"Point"}
}