{
  "type": "Feature",
  "properties": {
    "iso:country":"US",
    "sg:address":"4727 McPherson Ave",
    "sg:city":"Saint Louis",
    "sg:classifiers":[
        {
            "category":"Home & Garden",
            "subcategory":"Building Materials",
            "type":"Retail Goods"
        },
        {
            "category":"Home & Garden",
            "subcategory":"Furniture",
            "type":"Retail Goods"
        }
    ],
    "sg:phone":"+1 314 454 0111",
    "sg:postcode":"63108",
    "sg:province":"MO",
    "sg:tags":[
        "equipment",
        "lighting",
        "fixture",
        "store"
    ],
    "wof:name":"Centro Modern Furnishings",
    "wof:placetype":"venue"
},
  "geometry": {"coordinates":[-90.259399,38.647701],"type":"Point"}
}