{
  "type": "Feature",
  "properties": {
    "iso:country":"US",
    "sg:address":"355 S Main St",
    "sg:city":"Ironton",
    "sg:classifiers":[
        {
            "category":"Retail",
            "subcategory":"Auto Repair",
            "type":"Services"
        }
    ],
    "sg:phone":"+1 573 546 2724",
    "sg:postcode":"63650",
    "sg:province":"MO",
    "sg:tags":[
        "general"
    ],
    "wof:name":"Sams Service Center",
    "wof:placetype":"venue"
},
  "geometry": {"coordinates":[-90.627448,37.596298],"type":"Point"}
}