{
  "type": "Feature",
  "properties": {
    "iso:country":"US",
    "sg:address":"820 W Main St",
    "sg:city":"Jackson",
    "sg:classifiers":[
        {
            "category":"Shopping",
            "subcategory":"Tobacco",
            "type":"Retail Goods"
        }
    ],
    "sg:phone":"+1 573 243 6911",
    "sg:postcode":"63755",
    "sg:province":"MO",
    "sg:tags":[
        "shop",
        "cigarette"
    ],
    "wof:name":"Discount Smoke Shop Mo Inc",
    "wof:placetype":"venue"
},
  "geometry": {"coordinates":[-89.678444,37.383638],"type":"Point"}
}