{
  "type": "Feature",
  "properties": {
    "iso:country":"US",
    "sg:address":"6784 County Road 158",
    "sg:city":"Auxvasse",
    "sg:classifiers":[
        {
            "category":"Farming",
            "subcategory":"Farm",
            "type":"Manufacturing & Wholesale Goods"
        }
    ],
    "sg:phone":"+1 573 386 3459",
    "sg:postcode":"65231",
    "sg:province":"MO",
    "wof:name":"Mola Farms",
    "wof:placetype":"venue"
},
  "geometry": {"coordinates":[-91.886797,38.988733],"type":"Point"}
}