{
  "type": "Feature",
  "properties": {
    "iso:country":"US",
    "sg:address":"2134 Windmill Estates Dr",
    "sg:city":"Imperial",
    "sg:classifiers":[
        {
            "category":"Professional",
            "type":"Services"
        }
    ],
    "sg:phone":"+1 636 464 2426",
    "sg:postcode":"63052",
    "sg:province":"MO",
    "sg:website":"www.camservinc.com",
    "wof:name":"Cam Service Inc",
    "wof:placetype":"venue"
},
  "geometry": {"coordinates":[-90.411179,38.378984],"type":"Point"}
}