{
  "type": "Feature",
  "properties": {
    "iso:country":"US",
    "sg:address":"2513 Forest Leaf Pkwy",
    "sg:city":"Ballwin",
    "sg:classifiers":[
        {
            "category":"Food & Beverages",
            "subcategory":"Specialty",
            "type":"Retail Goods"
        }
    ],
    "sg:phone":"+1 636 458 8904",
    "sg:postcode":"63011",
    "sg:province":"MO",
    "wof:name":"Reliv Intl Independent Dist",
    "wof:placetype":"venue"
},
  "geometry": {"coordinates":[-90.624242,38.585599],"type":"Point"}
}