{
  "type": "Feature",
  "properties": {
    "iso:country":"US",
    "sg:address":"624 Castlewood Dr",
    "sg:city":"Ballwin",
    "sg:classifiers":[
        {
            "category":"Building & Trades",
            "subcategory":"Landscaping Services",
            "type":"Services"
        }
    ],
    "sg:phone":"+1 314 805 2777",
    "sg:postcode":"63021",
    "sg:province":"MO",
    "sg:tags":[
        "lawn",
        "snow",
        "maintenance",
        "removal"
    ],
    "sg:website":"http://www.MrPlowSTL.com",
    "wof:name":"Mr Plow STL",
    "wof:placetype":"venue"
},
  "geometry": {"coordinates":[-90.551757,38.549753],"type":"Point"}
}