{
  "type": "Feature",
  "properties": {
    "iso:country":"US",
    "sg:address":"2084 W State Highway Ww",
    "sg:city":"Springfield",
    "sg:classifiers":[
        {
            "category":"Home & Garden",
            "subcategory":"Building Materials",
            "type":"Retail Goods"
        },
        {
            "category":"Building & Trades",
            "subcategory":"Construction",
            "type":"Services"
        },
        {
            "category":"Military Area",
            "subcategory":"Armory",
            "type":"Public Place"
        }
    ],
    "sg:phone":"+1 417 894 6831",
    "sg:postcode":"65803",
    "sg:province":"MO",
    "sg:tags":[
        "repair",
        "fence",
        "builder",
        "contractor",
        "gazebo",
        "patio",
        "fence-sales"
    ],
    "wof:name":"Midwest Fence Co",
    "wof:placetype":"venue"
},
  "geometry": {"coordinates":[-93.316215,37.333231],"type":"Point"}
}