{
  "type": "Feature",
  "properties": {
    "iso:country":"US",
    "sg:address":"15620 Manchester Rd",
    "sg:city":"Ellisville",
    "sg:classifiers":[
        {
            "category":"Wholesale",
            "subcategory":"Hardware",
            "type":"Manufacturing & Wholesale Goods"
        }
    ],
    "sg:phone":"+1 636 391 6663",
    "sg:postcode":"63011",
    "sg:province":"MO",
    "sg:tags":[
        "stapler",
        "tacker",
        "staple"
    ],
    "wof:name":"Shank's Extracts Inc",
    "wof:placetype":"venue"
},
  "geometry": {"coordinates":[-90.57355699999999,38.592663],"type":"Point"}
}