{
  "type": "Feature",
  "properties": {
    "iso:country":"US",
    "sg:address":"250 Oak Ridge Dr",
    "sg:city":"Lake Ozark",
    "sg:classifiers":[
        {
            "category":"Building & Trades",
            "subcategory":"Landscaping Services",
            "type":"Services"
        }
    ],
    "sg:phone":"+1 573 365 5067",
    "sg:postcode":"65049",
    "sg:province":"MO",
    "wof:name":"Allmans Lawn Service",
    "wof:placetype":"venue"
},
  "geometry": {"coordinates":[-92.620755,38.176191],"type":"Point"}
}