{
  "type": "Feature",
  "properties": {
    "iso:country":"US",
    "sg:address":"1084 Keystone Trail Dr",
    "sg:city":"Chesterfield",
    "sg:classifiers":[
        {
            "category":"Wholesale",
            "subcategory":"Non-durable Goods",
            "type":"Manufacturing & Wholesale Goods"
        }
    ],
    "sg:phone":"+1 636 519 0441",
    "sg:postcode":"63005",
    "sg:province":"MO",
    "wof:name":"Atlas Trading Assoc LP",
    "wof:placetype":"venue"
},
  "geometry": {"coordinates":[-90.64895,38.641423],"type":"Point"}
}