{
  "type": "Feature",
  "properties": {
    "iso:country":"US",
    "sg:address":"492 State Hwy 13",
    "sg:city":"Warrensburg",
    "sg:classifiers":[
        {
            "category":"Building & Trades",
            "subcategory":"Construction",
            "type":"Services"
        }
    ],
    "sg:phone":"+1 660 747 6465",
    "sg:postcode":"64093",
    "sg:province":"MO",
    "sg:tags":[
        "excavating",
        "contractor"
    ],
    "wof:name":"Tim Marr Excavating",
    "wof:placetype":"venue"
},
  "geometry": {"coordinates":[-93.736051,38.758011],"type":"Point"}
}