{
  "type": "Feature",
  "properties": {
    "iso:country":"US",
    "sg:address":"224 W Valley St",
    "sg:city":"Granby",
    "sg:classifiers":[
        {
            "category":"Professional",
            "type":"Services"
        }
    ],
    "sg:phone":"+1 417 472 3411",
    "sg:postcode":"64844",
    "sg:province":"MO",
    "wof:name":"Newco Service",
    "wof:placetype":"venue"
},
  "geometry": {"coordinates":[-94.256158,36.919066],"type":"Point"}
}