{
  "type": "Feature",
  "properties": {
    "iso:country":"US",
    "sg:address":"8020 Saint Charles Rock Rd",
    "sg:city":"Overland",
    "sg:classifiers":[
        {
            "category":"Social Services",
            "subcategory":"Child Care",
            "type":"Services"
        }
    ],
    "sg:phone":"+1 314 426 0972",
    "sg:postcode":"63114",
    "sg:province":"MO",
    "wof:name":"Small Wonder Daycare & Dev",
    "wof:placetype":"venue"
},
  "geometry": {"coordinates":[-90.328469,38.698921],"type":"Point"}
}