{
  "type": "Feature",
  "properties": {
    "iso:country":"US",
    "sg:address":"5406 Hampton Ave.",
    "sg:city":"St Louis",
    "sg:classifiers":[
        {
            "category":"Restaurant",
            "type":"Food & Drink"
        }
    ],
    "sg:phone":"+1 314 832 8200",
    "sg:postcode":"63109",
    "sg:province":"MO",
    "sg:tags":[
        "pizza"
    ],
    "sg:website":"www.louiespizzaco.com",
    "wof:name":"Louie's Pizza Co.",
    "wof:placetype":"venue"
},
  "geometry": {"coordinates":[-90.293435,38.581582],"type":"Point"}
}