{
  "type": "Feature",
  "properties": {
    "iso:country":"US",
    "sg:address":"214 S Beech St",
    "sg:city":"Appleton City",
    "sg:classifiers":[
        {
            "category":"Social Services",
            "type":"Services"
        }
    ],
    "sg:phone":"+1 660 476 5877",
    "sg:postcode":"64724",
    "sg:province":"MO",
    "sg:tags":[
        "organization",
        "welfare"
    ],
    "wof:name":"Appleton City Head Start",
    "wof:placetype":"venue"
},
  "geometry": {"coordinates":[-94.023416,38.186824],"type":"Point"}
}