{
  "type": "Feature",
  "properties": {
    "iso:country":"US",
    "sg:address":"23209 Eclipse Dr",
    "sg:city":"Milan",
    "sg:classifiers":[
        {
            "category":"Travel",
            "subcategory":"Hotels & Motels",
            "type":"Entertainment"
        }
    ],
    "sg:phone":"+1 660 265 5400",
    "sg:postcode":"63556",
    "sg:province":"MO",
    "wof:name":"Milan Motel",
    "wof:placetype":"venue"
},
  "geometry": {"coordinates":[-93.13665399999999,40.189671],"type":"Point"}
}