{
  "type": "Feature",
  "properties": {
    "iso:country":"US",
    "sg:address":"11122 Saint Charles Rock Rd",
    "sg:city":"Saint Ann",
    "sg:classifiers":[
        {
            "category":"Restaurant",
            "type":"Food & Drink"
        }
    ],
    "sg:menulink":"http://www.allmenus.com/mo/airport/180435-jack-in-the-box/menu/",
    "sg:phone":"+1 314 739 0039",
    "sg:postcode":"63074",
    "sg:province":"MO",
    "sg:tags":[
        "burger",
        "american"
    ],
    "wof:name":"Jack in the Box",
    "wof:placetype":"venue"
},
  "geometry": {"coordinates":[-90.39747699999999,38.736792],"type":"Point"}
}