{
  "type": "Feature",
  "properties": {
    "iso:country":"US",
    "sg:address":"41 S Central Ave",
    "sg:city":"Clayton",
    "sg:classifiers":[
        {
            "category":"Recreation",
            "type":"Entertainment"
        }
    ],
    "sg:phone":"+1 314 615 4374",
    "sg:postcode":"63105",
    "sg:province":"MO",
    "sg:tags":[
        "parks"
    ],
    "wof:name":"St Louis County Parks",
    "wof:placetype":"venue"
},
  "geometry": {"coordinates":[-90.33845599999999,38.649504],"type":"Point"}
}