{
  "type": "Feature",
  "properties": {
    "iso:country":"US",
    "sg:address":"9834 Bellefontaine Rd",
    "sg:city":"St Louis",
    "sg:classifiers":[
        {
            "category":"Real Estate",
            "subcategory":"Architect",
            "type":"Services"
        }
    ],
    "sg:phone":"+1 314 868 9090",
    "sg:postcode":"63137",
    "sg:province":"MO",
    "wof:name":"Frank Kurz & Assoc",
    "wof:placetype":"venue"
},
  "geometry": {"coordinates":[-90.224712,38.745737],"type":"Point"}
}