{
  "type": "Feature",
  "properties": {
    "iso:country":"US",
    "sg:address":"810 W Marshall St",
    "sg:city":"Charleston",
    "sg:classifiers":[
        {
            "category":"Shopping",
            "subcategory":"Beauty & Cosmetics",
            "type":"Retail Goods"
        },
        {
            "category":"Personal",
            "subcategory":"Barber",
            "type":"Services"
        }
    ],
    "sg:phone":"+1 573 683 4855",
    "sg:postcode":"63834",
    "sg:province":"MO",
    "sg:tags":[
        "equipment",
        "salons-equipment",
        "supply"
    ],
    "wof:name":"J & V Beauty Supply",
    "wof:placetype":"venue"
},
  "geometry": {"coordinates":[-89.364724,36.920834],"type":"Point"}
}