{
  "type": "Feature",
  "properties": {
    "iso:country":"US",
    "sg:address":"417 E High St",
    "sg:city":"Potosi",
    "sg:classifiers":[
        {
            "category":"Building & Trades",
            "subcategory":"Construction",
            "type":"Services"
        }
    ],
    "sg:phone":"+1 573 438 5481",
    "sg:postcode":"63664",
    "sg:province":"MO",
    "sg:tags":[
        "general",
        "contractor"
    ],
    "wof:name":"Dave Degonia Construction",
    "wof:placetype":"venue"
},
  "geometry": {"coordinates":[-90.78205,37.932752],"type":"Point"}
}