{
  "type": "Feature",
  "properties": {
    "iso:country":"US",
    "sg:address":"4939 Childrens Pl",
    "sg:city":"Saint Louis",
    "sg:classifiers":[
        {
            "category":"Health Services",
            "subcategory":"Doctor",
            "type":"Services"
        }
    ],
    "sg:phone":"+1 314 362 8300",
    "sg:postcode":"63110",
    "sg:province":"MO",
    "wof:name":"Boineau John P MD",
    "wof:placetype":"venue"
},
  "geometry": {"coordinates":[-90.2659,38.637299],"type":"Point"}
}