{
  "type": "Feature",
  "properties": {
    "iso:country":"US",
    "sg:address":"108 E Grand Ave",
    "sg:city":"Jasper",
    "sg:classifiers":[
        {
            "category":"Shopping",
            "subcategory":"Used Merchandise",
            "type":"Retail Goods"
        }
    ],
    "sg:phone":"+1 417 394 2034",
    "sg:postcode":"64755",
    "sg:province":"MO",
    "sg:tags":[
        "antique"
    ],
    "wof:name":"Selvey's Antique Mall",
    "wof:placetype":"venue"
},
  "geometry": {"coordinates":[-94.302004,37.336085],"type":"Point"}
}