{
  "type": "Feature",
  "properties": {
    "iso:country":"US",
    "sg:address":"1280 Research Blvd",
    "sg:city":"St Louis",
    "sg:classifiers":[
        {
            "category":"Manufacturing",
            "subcategory":"Printing",
            "type":"Manufacturing & Wholesale Goods"
        }
    ],
    "sg:phone":"+1 314 991 9003",
    "sg:postcode":"63132",
    "sg:province":"MO",
    "sg:tags":[
        "color",
        "photo",
        "engrave"
    ],
    "sg:website":"www.colortek-inc.com",
    "wof:name":"Color Tek",
    "wof:placetype":"venue"
},
  "geometry": {"coordinates":[-90.398382,38.682458],"type":"Point"}
}