{
  "type": "Feature",
  "properties": {
    "iso:country":"US",
    "sg:address":"326 W Main St",
    "sg:city":"Carterville",
    "sg:classifiers":[
        {
            "category":"Manufacturing",
            "subcategory":"Building Materials",
            "type":"Manufacturing & Wholesale Goods"
        }
    ],
    "sg:phone":"+1 417 673 1962",
    "sg:postcode":"64835",
    "sg:province":"MO",
    "sg:tags":[
        "cabinet"
    ],
    "sg:website":"www.mortonbooth.com",
    "wof:name":"Morton Booth Co",
    "wof:placetype":"venue"
},
  "geometry": {"coordinates":[-94.44638500000001,37.149352],"type":"Point"}
}