{
  "type": "Feature",
  "properties": {
    "iso:country":"US",
    "sg:address":"1002 Golden Trout Ct",
    "sg:city":"Columbia",
    "sg:classifiers":[
        {
            "category":"Building & Trades",
            "subcategory":"Construction",
            "type":"Services"
        }
    ],
    "sg:phone":"+1 573 445 5140",
    "sg:postcode":"65203",
    "sg:province":"MO",
    "sg:tags":[
        "painting",
        "contractor"
    ],
    "wof:name":"J&G Fine Finishes",
    "wof:placetype":"venue"
},
  "geometry": {"coordinates":[-92.40258,38.9452],"type":"Point"}
}