{
  "type": "Feature",
  "properties": {
    "iso:country":"US",
    "sg:address":"2229 Ashby Rd",
    "sg:city":"Overland",
    "sg:classifiers":[
        {
            "category":"Shopping",
            "subcategory":"Computers & Home Electronics",
            "type":"Retail Goods"
        }
    ],
    "sg:phone":"+1 314 426 5030",
    "sg:postcode":"63114",
    "sg:province":"MO",
    "sg:tags":[
        "software"
    ],
    "wof:name":"Tri-V Computing Systems",
    "wof:placetype":"venue"
},
  "geometry": {"coordinates":[-90.391338,38.698261],"type":"Point"}
}