{
  "type": "Feature",
  "properties": {
    "iso:country":"US",
    "sg:address":"915 Imperial Pt",
    "sg:city":"Ballwin",
    "sg:classifiers":[
        {
            "category":"Professional",
            "subcategory":"Business Services",
            "type":"Services"
        },
        {
            "category":"Professional",
            "subcategory":"Management & Consulting",
            "type":"Services"
        }
    ],
    "sg:phone":"+1 636 861 0202",
    "sg:postcode":"63021",
    "sg:province":"MO",
    "sg:tags":[
        "program",
        "incentive"
    ],
    "wof:name":"Excellence In Motivation Inc",
    "wof:placetype":"venue"
},
  "geometry": {"coordinates":[-90.48692699999999,38.570189],"type":"Point"}
}