{
  "type": "Feature",
  "properties": {
    "iso:country":"US",
    "sg:address":"7418 College Ave",
    "sg:city":"Kansas City",
    "sg:classifiers":[
        {
            "category":"Food & Beverages",
            "subcategory":"Groceries & Convenience Stores",
            "type":"Retail Goods"
        }
    ],
    "sg:phone":"+1 816 363 8822",
    "sg:postcode":"64132",
    "sg:province":"MO",
    "sg:tags":[
        "product"
    ],
    "wof:name":"Food To Go",
    "wof:placetype":"venue"
},
  "geometry": {"coordinates":[-94.54915099999999,38.990787],"type":"Point"}
}