{
  "type": "Feature",
  "properties": {
    "iso:country":"US",
    "sg:address":"13285 Old Jamestown Rd",
    "sg:city":"Florissant",
    "sg:classifiers":[
        {
            "category":"Restaurant",
            "type":"Food & Drink"
        }
    ],
    "sg:phone":"+1 314 355 8607",
    "sg:postcode":"63033",
    "sg:province":"MO",
    "sg:tags":[
        "eating"
    ],
    "wof:name":"Roy Rogers Roofing LLC",
    "wof:placetype":"venue"
},
  "geometry": {"coordinates":[-90.25653200000001,38.804492],"type":"Point"}
}