{
  "type": "Feature",
  "properties": {
    "iso:country":"US",
    "sg:address":"114 W Maple St",
    "sg:city":"Slater",
    "sg:classifiers":[
        {
            "category":"Personal",
            "subcategory":"Beauty Salon",
            "type":"Services"
        }
    ],
    "sg:phone":"+1 660 529 3339",
    "sg:postcode":"65349",
    "sg:province":"MO",
    "wof:name":"Hair's The Place",
    "wof:placetype":"venue"
},
  "geometry": {"coordinates":[-93.06238500000001,39.21991],"type":"Point"}
}