{
  "type": "Feature",
  "properties": {
    "iso:country":"US",
    "sg:address":"8501 Delmar Blvd",
    "sg:city":"Saint Louis",
    "sg:classifiers":[
        {
            "category":"Restaurant",
            "type":"Food & Drink"
        }
    ],
    "sg:menulink":"http://www.allmenus.com/mo/university/185189-house-of-india/menu/",
    "sg:phone":"+1 314 567 6850",
    "sg:postcode":"63124",
    "sg:province":"MO",
    "sg:tags":[
        "indian",
        "asian"
    ],
    "wof:name":"House Of India",
    "wof:placetype":"venue"
},
  "geometry": {"coordinates":[-90.355958,38.660815],"type":"Point"}
}