{
  "type": "Feature",
  "properties": {
    "iso:country":"US",
    "sg:address":"13210 Jopling Mill Rd",
    "sg:city":"Nelson",
    "sg:classifiers":[
        {
            "category":"Farming",
            "subcategory":"Livestock Farm",
            "type":"Manufacturing & Wholesale Goods"
        }
    ],
    "sg:phone":"+1 660 826 4104",
    "sg:postcode":"65347",
    "sg:province":"MO",
    "sg:tags":[
        "feeding"
    ],
    "wof:name":"Nichols, John",
    "wof:placetype":"venue"
},
  "geometry": {"coordinates":[-93.145615,38.887233],"type":"Point"}
}