{
  "type": "Feature",
  "properties": {
    "iso:country":"US",
    "sg:address":"201 N Dodgion St",
    "sg:city":"Independence",
    "sg:classifiers":[
        {
            "category":"Autos & Motor Vehicles",
            "subcategory":"Automobile Sales",
            "type":"Retail Goods"
        }
    ],
    "sg:phone":"+1 816 325 7384",
    "sg:postcode":"64050",
    "sg:province":"MO",
    "sg:tags":[
        "new",
        "car"
    ],
    "wof:name":"Dept Of Park & Recreation",
    "wof:placetype":"venue"
},
  "geometry": {"coordinates":[-94.411374,39.093153],"type":"Point"}
}