{
  "type": "Feature",
  "properties": {
    "iso:country":"US",
    "sg:address":"324 S 3rd St",
    "sg:city":"Ozark",
    "sg:classifiers":[
        {
            "category":"Personal",
            "subcategory":"Nail Salon",
            "type":"Services"
        }
    ],
    "sg:phone":"+1 417 582 1033",
    "sg:postcode":"65721",
    "sg:province":"MO",
    "wof:name":"Aea Nails",
    "wof:placetype":"venue"
},
  "geometry": {"coordinates":[-93.20678700000001,37.011879],"type":"Point"}
}