{
  "type": "Feature",
  "properties": {
    "iso:country":"US",
    "sg:address":"368 S Ellsworth Ave",
    "sg:city":"Marshall",
    "sg:classifiers":[
        {
            "category":"Education",
            "subcategory":"School",
            "type":"Public Place"
        }
    ],
    "sg:phone":"+1 660 886 6390",
    "sg:postcode":"65340",
    "sg:province":"MO",
    "wof:name":"St Peter's School",
    "wof:placetype":"venue"
},
  "geometry": {"coordinates":[-93.200749,39.118048],"type":"Point"}
}