{
  "type": "Feature",
  "properties": {
    "iso:country":"US",
    "sg:address":"4949 W Pine Blvd Ofc",
    "sg:city":"Saint Louis",
    "sg:classifiers":[
        {
            "category":"Real Estate",
            "subcategory":"Real Estate Services",
            "type":"Services"
        }
    ],
    "sg:phone":"+1 314 361 7329",
    "sg:postcode":"63108",
    "sg:province":"MO",
    "wof:name":"Langsdorf Kenneth R Real Estate",
    "wof:placetype":"venue"
},
  "geometry": {"coordinates":[-90.26280199999999,38.641998],"type":"Point"}
}