{
  "type": "Feature",
  "properties": {
    "iso:country":"US",
    "sg:address":"1802 W 32nd St",
    "sg:city":"Joplin",
    "sg:classifiers":[
        {
            "category":"Food & Beverages",
            "subcategory":"Bakery",
            "type":"Retail Goods"
        }
    ],
    "sg:phone":"+1 417 659 8777",
    "sg:postcode":"64804",
    "sg:province":"MO",
    "sg:tags":[
        "doughnut"
    ],
    "sg:website":"www.javadaves.com",
    "wof:name":"Java Daves Coffee & Donut Shop",
    "wof:placetype":"venue"
},
  "geometry": {"coordinates":[-94.53738,37.055325],"type":"Point"}
}