{
  "type": "Feature",
  "properties": {
    "addr:full":"241 State Hwy Aa Doniphan MO 63901",
    "addr:housenumber":"241",
    "addr:postcode":"63901",
    "addr:street":"State Hwy Aa",
    "iso:country":"US",
    "sg:address":"241 State Hwy Aa",
    "sg:city":"Doniphan",
    "sg:classifiers":[
        {
            "category":"Insurance",
            "subcategory":"Insurance Agent",
            "type":"Services"
        }
    ],
    "sg:phone":"+1 573 996 3511",
    "sg:postcode":"63901",
    "sg:province":"MO",
    "wof:name":"Farmers Insurance Group",
    "wof:placetype":"venue"
},
  "geometry": {"coordinates":[-90.33457300000001,36.789314],"type":"Point"}
}