{
  "type": "Feature",
  "properties": {
    "iso:country":"US",
    "sg:address":"7114 Coram Dr",
    "sg:city":"Saint Louis",
    "sg:classifiers":[
        {
            "category":"Social Services",
            "subcategory":"Child Care",
            "type":"Services"
        }
    ],
    "sg:phone":"+1 314 846 6907",
    "sg:postcode":"63129",
    "sg:province":"MO",
    "sg:tags":[
        "day"
    ],
    "wof:name":"Debbies Day Care",
    "wof:placetype":"venue"
},
  "geometry": {"coordinates":[-90.322973,38.430378],"type":"Point"}
}