{
  "type": "Feature",
  "properties": {
    "iso:country":"US",
    "sg:address":"433 Jungs Station Rd",
    "sg:city":"Saint Charles",
    "sg:classifiers":[
        {
            "category":"Personal",
            "type":"Services"
        }
    ],
    "sg:phone":"+1 636 441 6348",
    "sg:postcode":"63303",
    "sg:province":"MO",
    "wof:name":"E D & D Remodeling",
    "wof:placetype":"venue"
},
  "geometry": {"coordinates":[-90.554013,38.731493],"type":"Point"}
}