{
  "type": "Feature",
  "properties": {
    "iso:country":"US",
    "sg:address":"490 N Kingshighway Blvd",
    "sg:city":"Saint Louis",
    "sg:classifiers":[
        {
            "category":"Retail",
            "subcategory":"Auto Repair",
            "type":"Services"
        }
    ],
    "sg:phone":"+1 314 367 8486",
    "sg:postcode":"63108",
    "sg:province":"MO",
    "sg:website":"relianceautomotive.com",
    "wof:name":"Reliance Automotive Inc",
    "wof:placetype":"venue"
},
  "geometry": {"coordinates":[-90.263702,38.649601],"type":"Point"}
}