{
  "type": "Feature",
  "properties": {
    "addr:full":"15355 Manchester Rd Ballwin MO 63011",
    "addr:housenumber":"15355",
    "addr:postcode":"63011",
    "addr:street":"Manchester Rd",
    "iso:country":"US",
    "sg:address":"15355 Manchester Rd",
    "sg:city":"Ballwin",
    "sg:classifiers":[
        {
            "category":"Shopping",
            "subcategory":"Books",
            "type":"Retail Goods"
        }
    ],
    "sg:phone":"+1 636 230 2992",
    "sg:postcode":"63011",
    "sg:province":"MO",
    "wof:name":"Borders",
    "wof:placetype":"venue"
},
  "geometry": {"coordinates":[-90.559668,38.592907],"type":"Point"}
}