{
  "type": "Feature",
  "properties": {
    "iso:country":"US",
    "sg:address":"11 Main St",
    "sg:city":"Parkville",
    "sg:classifiers":[
        {
            "category":"Organizations",
            "subcategory":"Community Association",
            "type":"Services"
        }
    ],
    "sg:phone":"+1 816 584 0044",
    "sg:postcode":"64152",
    "sg:province":"MO",
    "sg:tags":[
        "military"
    ],
    "wof:name":"American Legion",
    "wof:placetype":"venue"
},
  "geometry": {"coordinates":[-94.684043,39.188865],"type":"Point"}
}