{
  "type": "Feature",
  "properties": {
    "iso:country":"US",
    "sg:address":"2386 State Hwy 7",
    "sg:city":"Camdenton",
    "sg:classifiers":[
        {
            "category":"Professional",
            "subcategory":"Computer Services",
            "type":"Services"
        }
    ],
    "sg:phone":"+1 573 873 9645",
    "sg:postcode":"65020",
    "sg:province":"MO",
    "sg:tags":[
        "repair"
    ],
    "wof:name":"Three Monkeys Technology Svc",
    "wof:placetype":"venue"
},
  "geometry": {"coordinates":[-92.78308699999999,38.035178],"type":"Point"}
}