{
  "type": "Feature",
  "properties": {
    "iso:country":"US",
    "sg:address":"668 Rockwood Dr",
    "sg:city":"Arnold",
    "sg:classifiers":[
        {
            "category":"Building & Trades",
            "subcategory":"Cleaning & Sanitation",
            "type":"Services"
        }
    ],
    "sg:phone":"+1 636 461 0132",
    "sg:postcode":"63010",
    "sg:province":"MO",
    "sg:tags":[
        "maintenance"
    ],
    "wof:name":"Hake Chimney Service",
    "wof:placetype":"venue"
},
  "geometry": {"coordinates":[-90.361322,38.408546],"type":"Point"}
}