{
  "type": "Feature",
  "properties": {
    "iso:country":"US",
    "sg:address":"601 S Walnut St",
    "sg:city":"Mount Vernon",
    "sg:classifiers":[
        {
            "category":"Real Estate",
            "subcategory":"Real Estate Operator",
            "type":"Services"
        }
    ],
    "sg:phone":"+1 417 466 9467",
    "sg:postcode":"65712",
    "sg:province":"MO",
    "sg:tags":[
        "building",
        "apartment"
    ],
    "wof:name":"Jj Apts",
    "wof:placetype":"venue"
},
  "geometry": {"coordinates":[-93.81232199999999,37.099309],"type":"Point"}
}