{
  "type": "Feature",
  "properties": {
    "iso:country":"US",
    "sg:address":"8015 Big Bend Blvd",
    "sg:city":"Webster Groves",
    "sg:classifiers":[
        {
            "category":"Shopping",
            "subcategory":"Musical Instruments",
            "type":"Retail Goods"
        }
    ],
    "sg:phone":"+1 314 961 2838",
    "sg:postcode":"63119",
    "sg:province":"MO",
    "sg:website":"www.musicfolk.com",
    "wof:name":"Music Folk Inc",
    "wof:placetype":"venue"
},
  "geometry": {"coordinates":[-90.336853,38.592735],"type":"Point"}
}