{
  "type": "Feature",
  "properties": {
    "iso:country":"US",
    "sg:address":"210 N 4th St",
    "sg:city":"St Joseph",
    "sg:classifiers":[
        {
            "category":"Building & Trades",
            "subcategory":"Construction",
            "type":"Services"
        }
    ],
    "sg:phone":"+1 816 364 1460",
    "sg:postcode":"64501",
    "sg:province":"MO",
    "sg:tags":[
        "general",
        "contractor"
    ],
    "wof:name":"Fairway Construction",
    "wof:placetype":"venue"
},
  "geometry": {"coordinates":[-94.85553400000001,39.768106],"type":"Point"}
}