{
  "type": "Feature",
  "properties": {
    "iso:country":"US",
    "sg:address":"1835 W Calhoun St",
    "sg:city":"Springfield",
    "sg:classifiers":[
        {
            "category":"Manufacturing",
            "subcategory":"Glass & Minerals",
            "type":"Manufacturing & Wholesale Goods"
        }
    ],
    "sg:phone":"+1 417 862 7654",
    "sg:postcode":"65802",
    "sg:province":"MO",
    "sg:tags":[
        "product",
        "mfg"
    ],
    "wof:name":"Strohm's Stained Glass",
    "wof:placetype":"venue"
},
  "geometry": {"coordinates":[-93.315117,37.222467],"type":"Point"}
}