{
  "type": "Feature",
  "properties": {
    "iso:country":"US",
    "sg:address":"6850 N Fork Dr",
    "sg:city":"House Springs",
    "sg:classifiers":[
        {
            "category":"Real Estate",
            "subcategory":"Real Estate Operator",
            "type":"Services"
        }
    ],
    "sg:phone":"+1 636 677 2851",
    "sg:postcode":"63051",
    "sg:province":"MO",
    "sg:tags":[
        "mobile",
        "home",
        "community"
    ],
    "wof:name":"Byrnes Mill Farms Mobile Home",
    "wof:placetype":"venue"
},
  "geometry": {"coordinates":[-90.58359900000001,38.442499],"type":"Point"}
}