{
  "type": "Feature",
  "properties": {
    "iso:country":"US",
    "sg:address":"304 Co Rd 438",
    "sg:city":"Rocheport",
    "sg:classifiers":[
        {
            "category":"Farming",
            "subcategory":"Livestock Farm",
            "type":"Manufacturing & Wholesale Goods"
        }
    ],
    "sg:phone":"+1 573 698 3030",
    "sg:postcode":"65279",
    "sg:province":"MO",
    "sg:tags":[
        "beef",
        "feedlot",
        "cattle"
    ],
    "wof:name":"Mc Inerney Farms",
    "wof:placetype":"venue"
},
  "geometry": {"coordinates":[-92.560074,39.027017],"type":"Point"}
}