{
  "type": "Feature",
  "properties": {
    "iso:country":"US",
    "sg:address":"1328 Guinotte Ave",
    "sg:city":"Kansas City",
    "sg:classifiers":[
        {
            "category":"Professional",
            "type":"Services"
        }
    ],
    "sg:phone":"+1 816 221 9670",
    "sg:postcode":"64120",
    "sg:province":"MO",
    "wof:name":"Studio 13",
    "wof:placetype":"venue"
},
  "geometry": {"coordinates":[-94.568894,39.114677],"type":"Point"}
}