{
  "type": "Feature",
  "properties": {
    "iso:country":"US",
    "sg:address":"713 N New Ballas Rd",
    "sg:city":"St Louis",
    "sg:classifiers":[
        {
            "category":"Sports & Exercise",
            "subcategory":"Gym",
            "type":"Entertainment"
        }
    ],
    "sg:phone":"+1 314 569 9092",
    "sg:postcode":"63141",
    "sg:province":"MO",
    "sg:tags":[
        "club",
        "health",
        "studio",
        "gymnasium"
    ],
    "wof:name":"Curves For Women",
    "wof:placetype":"venue"
},
  "geometry": {"coordinates":[-90.443361,38.670344],"type":"Point"}
}