{
  "type": "Feature",
  "properties": {
    "iso:country":"US",
    "sg:address":"130 NE 1271",
    "sg:city":"Knob Noster",
    "sg:classifiers":[
        {
            "category":"Professional",
            "type":"Services"
        }
    ],
    "sg:phone":"+1 660 563 3640",
    "sg:postcode":"65336",
    "sg:province":"MO",
    "wof:name":"Annron Inc",
    "wof:placetype":"venue"
},
  "geometry": {"coordinates":[-93.504153,38.771095],"type":"Point"}
}