{
  "type": "Feature",
  "properties": {
    "iso:country":"US",
    "sg:address":"5808 W 78th St",
    "sg:city":"Shawnee Mission",
    "sg:classifiers":[
        {
            "category":"Building & Trades",
            "subcategory":"Construction",
            "type":"Services"
        }
    ],
    "sg:phone":"+1 913 649 2391",
    "sg:postcode":"66208",
    "sg:province":"MO",
    "sg:tags":[
        "home",
        "family"
    ],
    "wof:name":"Lavender Construction Inc",
    "wof:placetype":"venue"
},
  "geometry": {"coordinates":[-94.652924,38.987653],"type":"Point"}
}