{
  "type": "Feature",
  "properties": {
    "iso:country":"US",
    "sg:address":"7 Capper Dr",
    "sg:city":"Pacific",
    "sg:classifiers":[
        {
            "category":"Shopping",
            "subcategory":"Stationery & Office Supplies",
            "type":"Retail Goods"
        },
        {
            "category":"Shopping",
            "subcategory":"Gifts & Souvenirs",
            "type":"Retail Goods"
        }
    ],
    "sg:phone":"+1 636 257 5700",
    "sg:postcode":"63069",
    "sg:province":"MO",
    "sg:tags":[
        "shop",
        "store"
    ],
    "wof:name":"Aroma Specialities",
    "wof:placetype":"venue"
},
  "geometry": {"coordinates":[-90.757336,38.46013],"type":"Point"}
}