{
  "type": "Feature",
  "properties": {
    "iso:country":"US",
    "sg:address":"8635 Partridge Ave",
    "sg:city":"Saint Louis",
    "sg:classifiers":[
        {
            "category":"Wholesale",
            "subcategory":"Electrical",
            "type":"Manufacturing & Wholesale Goods"
        }
    ],
    "sg:phone":"+1 314 381 3135",
    "sg:postcode":"63147",
    "sg:province":"MO",
    "sg:tags":[
        "equipment"
    ],
    "wof:name":"Lewis Security Systems",
    "wof:placetype":"venue"
},
  "geometry": {"coordinates":[-90.240308,38.715632],"type":"Point"}
}