{
  "type": "Feature",
  "properties": {
    "iso:country":"US",
    "sg:address":"12025 Manchester Rd",
    "sg:city":"St Louis",
    "sg:classifiers":[
        {
            "category":"Professional",
            "subcategory":"Lawyer & Legal Services",
            "type":"Services"
        }
    ],
    "sg:phone":"+1 314 965 8052",
    "sg:postcode":"63131",
    "sg:province":"MO",
    "sg:tags":[
        "attorney"
    ],
    "wof:name":"Code Engineering",
    "wof:placetype":"venue"
},
  "geometry": {"coordinates":[-90.43597,38.601878],"type":"Point"}
}