{
  "type": "Feature",
  "properties": {
    "iso:country":"US",
    "sg:address":"3742 N Delaware Ave",
    "sg:city":"Springfield",
    "sg:classifiers":[
        {
            "category":"Wholesale",
            "subcategory":"Farm Supplies",
            "type":"Manufacturing & Wholesale Goods"
        }
    ],
    "sg:phone":"+1 417 833 8415",
    "sg:postcode":"65803",
    "sg:province":"MO",
    "sg:tags":[
        "bean",
        "prepared",
        "mfg"
    ],
    "wof:name":"Willards Feed & Fertilizer",
    "wof:placetype":"venue"
},
  "geometry": {"coordinates":[-93.266667,37.265364],"type":"Point"}
}