{
  "type": "Feature",
  "properties": {
    "iso:country":"US",
    "sg:address":"15973 State Hwy U",
    "sg:city":"Bernie",
    "sg:classifiers":[
        {
            "category":"Freight",
            "type":"Transportation"
        }
    ],
    "sg:phone":"+1 573 293 4472",
    "sg:postcode":"63822",
    "sg:province":"MO",
    "sg:tags":[
        "operator",
        "trucking"
    ],
    "wof:name":"Meese Trucking",
    "wof:placetype":"venue"
},
  "geometry": {"coordinates":[-89.992272,36.669639],"type":"Point"}
}