{
  "type": "Feature",
  "properties": {
    "iso:country":"US",
    "sg:address":"1334 Lonedell Rd",
    "sg:city":"Arnold",
    "sg:classifiers":[
        {
            "category":"Building & Trades",
            "subcategory":"Construction",
            "type":"Services"
        }
    ],
    "sg:phone":"+1 636 282 5000",
    "sg:postcode":"63010",
    "sg:province":"MO",
    "sg:tags":[
        "specializing",
        "metal",
        "contractor"
    ],
    "wof:name":"Perfection Steel Erection Inc",
    "wof:placetype":"venue"
},
  "geometry": {"coordinates":[-90.378456,38.450916],"type":"Point"}
}