{
  "type": "Feature",
  "properties": {
    "iso:country":"US",
    "sg:address":"550 E 13th Ave",
    "sg:city":"Kansas City",
    "sg:classifiers":[
        {
            "category":"Wholesale",
            "subcategory":"Wine & Distilled Alcoholic Beverages",
            "type":"Manufacturing & Wholesale Goods"
        }
    ],
    "sg:phone":"+1 816 701 2600",
    "sg:postcode":"64116",
    "sg:province":"MO",
    "sg:website":"www.majorbrands.com",
    "wof:name":"Major Brands",
    "wof:placetype":"venue"
},
  "geometry": {"coordinates":[-94.575661,39.132399],"type":"Point"}
}