{
  "type": "Feature",
  "properties": {
    "iso:country":"US",
    "sg:address":"9220 NE Barry Rd",
    "sg:city":"Kansas City",
    "sg:classifiers":[
        {
            "category":"Shopping",
            "subcategory":"Optical Goods",
            "type":"Retail Goods"
        }
    ],
    "sg:phone":"+1 816 781 1061",
    "sg:postcode":"64157",
    "sg:province":"MO",
    "wof:name":"Target Optical",
    "wof:placetype":"venue"
},
  "geometry": {"coordinates":[-94.467446,39.244648],"type":"Point"}
}