{
  "type": "Feature",
  "properties": {
    "iso:country":"US",
    "sg:address":"7576 Clayton Rd",
    "sg:city":"Saint Louis",
    "sg:classifiers":[
        {
            "category":"Arts & Performance",
            "subcategory":"Theater",
            "type":"Entertainment"
        }
    ],
    "sg:phone":"+1 314 647 7986",
    "sg:postcode":"63117",
    "sg:province":"MO",
    "sg:tags":[
        "group"
    ],
    "wof:name":"Symphony Showhouse",
    "wof:placetype":"venue"
},
  "geometry": {"coordinates":[-90.334772,38.637664],"type":"Point"}
}