{
  "type": "Feature",
  "properties": {
    "iso:country":"US",
    "sg:address":"505 Cherry St",
    "sg:city":"Columbia",
    "sg:classifiers":[
        {
            "category":"Food & Beverages",
            "subcategory":"Liquor & Beverages",
            "type":"Retail Goods"
        }
    ],
    "sg:phone":"+1 573 442 7281",
    "sg:postcode":"65201",
    "sg:province":"MO",
    "sg:tags":[
        "eating",
        "alcoholic"
    ],
    "wof:name":"Wine Cellar & Bistro",
    "wof:placetype":"venue"
},
  "geometry": {"coordinates":[-92.330823,38.950595],"type":"Point"}
}