{
  "type": "Feature",
  "properties": {
    "iso:country":"US",
    "sg:address":"1302 Sycamore St",
    "sg:city":"Pleasant Hill",
    "sg:classifiers":[
        {
            "category":"Building & Trades",
            "subcategory":"Plumbing",
            "type":"Services"
        }
    ],
    "sg:phone":"+1 816 540 6006",
    "sg:postcode":"64080",
    "sg:province":"MO",
    "sg:tags":[
        "heating",
        "contractor"
    ],
    "wof:name":"Advanced Heating & Cooling",
    "wof:placetype":"venue"
},
  "geometry": {"coordinates":[-94.25660999999999,38.797858],"type":"Point"}
}