{
  "type": "Feature",
  "properties": {
    "iso:country":"US",
    "sg:address":"15419 N Bales Rd",
    "sg:city":"Smithville",
    "sg:classifiers":[
        {
            "category":"Health Services",
            "subcategory":"Health Practitioner",
            "type":"Services"
        }
    ],
    "sg:phone":"+1 816 532 4583",
    "sg:postcode":"64089",
    "sg:province":"MO",
    "wof:name":"Kresser Paula Phd",
    "wof:placetype":"venue"
},
  "geometry": {"coordinates":[-94.535815,39.371112],"type":"Point"}
}