{
  "type": "Feature",
  "properties": {
    "iso:country":"US",
    "sg:address":"4062 State Highway H",
    "sg:city":"Lampe",
    "sg:classifiers":[
        {
            "category":"Recreation",
            "subcategory":"Boat Charter",
            "type":"Entertainment"
        },
        {
            "category":"Structure",
            "subcategory":"Warehouse",
            "type":"Public Place"
        },
        {
            "category":"Retail",
            "subcategory":"Storage",
            "type":"Services"
        }
    ],
    "sg:phone":"+1 417 779 4262",
    "sg:postcode":"65681",
    "sg:province":"MO",
    "sg:tags":[
        "commercial",
        "household",
        "yard",
        "warehouses-public-commercial",
        "self"
    ],
    "wof:name":"B & B Storage",
    "wof:placetype":"venue"
},
  "geometry": {"coordinates":[-93.4879,36.572968],"type":"Point"}
}