{
  "type": "Feature",
  "properties": {
    "addr:full":"313 3rd St Blackburn MO 65321",
    "addr:housenumber":"313",
    "addr:postcode":"65321",
    "addr:street":"3Rd St",
    "iso:country":"US",
    "sg:address":"313 3rd St",
    "sg:city":"Blackburn",
    "sg:classifiers":[
        {
            "category":"Organizations",
            "subcategory":"Religious Organization",
            "type":"Services"
        }
    ],
    "sg:phone":"+1 660 538 4493",
    "sg:postcode":"65321",
    "sg:province":"MO",
    "sg:tags":[
        "church"
    ],
    "wof:name":"Zion Lutheran Church",
    "wof:placetype":"venue"
},
  "geometry": {"coordinates":[-93.487163,39.106509],"type":"Point"}
}