{
  "type": "Feature",
  "properties": {
    "iso:country":"US",
    "sg:address":"705 Illinois Ave Ste 11",
    "sg:city":"Joplin",
    "sg:classifiers":[
        {
            "category":"Restaurant",
            "type":"Food & Drink"
        }
    ],
    "sg:phone":"+1 417 624 3700",
    "sg:postcode":"64801",
    "sg:province":"MO",
    "sg:website":"http://www.grannyshaffers.com",
    "wof:name":"Granny Shaffer's On The Plaza",
    "wof:placetype":"venue"
},
  "geometry": {"coordinates":[-94.50256400000001,37.083854],"type":"Point"}
}