{
  "type": "Feature",
  "properties": {
    "iso:country":"US",
    "sg:address":"101 Renee Ln",
    "sg:city":"Waynesville",
    "sg:classifiers":[
        {
            "category":"Real Estate",
            "subcategory":"Real Estate Operator",
            "type":"Services"
        }
    ],
    "sg:phone":"+1 573 774 3094",
    "sg:postcode":"65583",
    "sg:province":"MO",
    "sg:tags":[
        "apartment"
    ],
    "wof:name":"Viren Apartments",
    "wof:placetype":"venue"
},
  "geometry": {"coordinates":[-92.221329,37.819778],"type":"Point"}
}