{
  "type": "Feature",
  "properties": {
    "iso:country":"US",
    "sg:address":"2300 NW Vivion Rd",
    "sg:city":"Kansas City",
    "sg:classifiers":[
        {
            "category":"Retail",
            "subcategory":"Repair Shop",
            "type":"Services"
        }
    ],
    "sg:phone":"+1 816 587 0038",
    "sg:postcode":"64150",
    "sg:province":"MO",
    "wof:name":"Clark Upholstery",
    "wof:placetype":"venue"
},
  "geometry": {"coordinates":[-94.608814,39.179414],"type":"Point"}
}