{
  "type": "Feature",
  "properties": {
    "iso:country":"US",
    "sg:address":"6922 W Florissant Ave",
    "sg:city":"Saint Louis",
    "sg:classifiers":[
        {
            "category":"Bars & Pubs",
            "type":"Food & Drink"
        }
    ],
    "sg:phone":"+1 314 385 2929",
    "sg:postcode":"63136",
    "sg:province":"MO",
    "sg:tags":[
        "lounge",
        "drinking",
        "nightlife",
        "cocktail"
    ],
    "wof:name":"B J's Cocktail Lounge",
    "wof:placetype":"venue"
},
  "geometry": {"coordinates":[-90.260696,38.7173],"type":"Point"}
}