{
  "type": "Feature",
  "properties": {
    "iso:country":"US",
    "sg:address":"1901 Pennsylvania Dr C",
    "sg:city":"Columbia",
    "sg:classifiers":[
        {
            "category":"Wholesale",
            "subcategory":"Medical Equipment & Supplies",
            "type":"Manufacturing & Wholesale Goods"
        }
    ],
    "sg:phone":"+1 573 214 0472",
    "sg:postcode":"65202",
    "sg:province":"MO",
    "sg:tags":[
        "laboratory"
    ],
    "sg:website":"http://www.j2scientific.com",
    "wof:name":"J2 Scientific",
    "wof:placetype":"venue"
},
  "geometry": {"coordinates":[-92.309219,38.973721],"type":"Point"}
}