{
  "type": "Feature",
  "properties": {
    "addr:full":"16141 Swingley Ridge Rd Chesterfield MO 63017",
    "addr:housenumber":"16141",
    "addr:postcode":"63017",
    "addr:street":"Swingley Ridge Rd",
    "iso:country":"US",
    "sg:address":"16141 Swingley Ridge Rd",
    "sg:city":"Chesterfield",
    "sg:classifiers":[
        {
            "category":"Utilities",
            "subcategory":"Telephone",
            "type":"Services"
        }
    ],
    "sg:phone":"+1 636 537 6400",
    "sg:postcode":"63017",
    "sg:province":"MO",
    "sg:tags":[
        "company"
    ],
    "sg:website":"www.qwest.com",
    "wof:name":"Qwest",
    "wof:placetype":"venue"
},
  "geometry": {"coordinates":[-90.560267,38.654397],"type":"Point"}
}