{
  "type": "Feature",
  "properties": {
    "iso:country":"US",
    "sg:address":"301 NE 74 Ter",
    "sg:city":"Kansas City",
    "sg:classifiers":[
        {
            "category":"Arts & Performance",
            "subcategory":"Theater",
            "type":"Entertainment"
        }
    ],
    "sg:phone":"+1 816 468 6597",
    "sg:postcode":"64118",
    "sg:province":"MO",
    "sg:tags":[
        "band"
    ],
    "wof:name":"Lipriddle LLC",
    "wof:placetype":"venue"
},
  "geometry": {"coordinates":[-94.57958600000001,39.229124],"type":"Point"}
}