{
  "type": "Feature",
  "properties": {
    "iso:country":"US",
    "sg:address":"306 S Cherry St",
    "sg:city":"Keytesville",
    "sg:classifiers":[
        {
            "category":"Government",
            "subcategory":"Court House",
            "type":"Public Place"
        }
    ],
    "sg:phone":"+1 660 288 3602",
    "sg:postcode":"65261",
    "sg:province":"MO",
    "sg:tags":[
        "justice",
        "county"
    ],
    "wof:name":"Chariton County",
    "wof:placetype":"venue"
},
  "geometry": {"coordinates":[-92.94155000000001,39.433225],"type":"Point"}
}