{
  "type": "Feature",
  "properties": {
    "iso:country":"US",
    "sg:address":"6700 Natural Bridge Rd",
    "sg:city":"St Louis",
    "sg:classifiers":[
        {
            "category":"Autos & Motor Vehicles",
            "subcategory":"Auto Supplies",
            "type":"Retail Goods"
        }
    ],
    "sg:phone":"+1 314 385 3303",
    "sg:postcode":"63121",
    "sg:province":"MO",
    "sg:tags":[
        "automobile",
        "parts"
    ],
    "sg:website":"www.autozone.com",
    "wof:name":"Autozone",
    "wof:placetype":"venue"
},
  "geometry": {"coordinates":[-90.284661,38.694996],"type":"Point"}
}