{
  "type": "Feature",
  "properties": {
    "iso:country":"US",
    "sg:address":"28447 County Road 772",
    "sg:city":"Catron",
    "sg:classifiers":[
        {
            "category":"Professional",
            "subcategory":"Management & Consulting",
            "type":"Services"
        }
    ],
    "sg:phone":"+1 573 283 5905",
    "sg:postcode":"63833",
    "sg:province":"MO",
    "sg:tags":[
        "farm"
    ],
    "wof:name":"Stockton Farm",
    "wof:placetype":"venue"
},
  "geometry": {"coordinates":[-89.774188,36.685626],"type":"Point"}
}