{
  "type": "Feature",
  "properties": {
    "iso:country":"US",
    "sg:address":"307 E 3rd St",
    "sg:city":"Lawson",
    "sg:classifiers":[
        {
            "category":"Organizations",
            "subcategory":"Religious Organization",
            "type":"Services"
        }
    ],
    "sg:phone":"+1 816 296 7002",
    "sg:postcode":"64062",
    "sg:province":"MO",
    "sg:tags":[
        "church"
    ],
    "wof:name":"Lawson Baptist Church",
    "wof:placetype":"venue"
},
  "geometry": {"coordinates":[-94.20177700000001,39.437335],"type":"Point"}
}