{
  "type": "Feature",
  "properties": {
    "iso:country":"US",
    "sg:address":"20 N Gore Ave",
    "sg:city":"Saint Louis",
    "sg:classifiers":[
        {
            "category":"Insurance",
            "subcategory":"Insurance Agent",
            "type":"Services"
        }
    ],
    "sg:phone":"+1 314 961 1501",
    "sg:postcode":"63119",
    "sg:province":"MO",
    "sg:tags":[
        "agency"
    ],
    "wof:name":"Vincent K Blair Agency",
    "wof:placetype":"venue"
},
  "geometry": {"coordinates":[-90.359465,38.593343],"type":"Point"}
}