{
  "type": "Feature",
  "properties": {
    "iso:country":"US",
    "sg:address":"542 Watson Rd",
    "sg:city":"Sullivan",
    "sg:classifiers":[
        {
            "category":"Social Services",
            "subcategory":"Adult Care",
            "type":"Services"
        }
    ],
    "sg:phone":"+1 573 468 5037",
    "sg:postcode":"63080",
    "sg:province":"MO",
    "sg:tags":[
        "home",
        "residential"
    ],
    "wof:name":"Sullivan House Group Home",
    "wof:placetype":"venue"
},
  "geometry": {"coordinates":[-91.147639,38.209195],"type":"Point"}
}