{
  "type": "Feature",
  "properties": {
    "iso:country":"US",
    "sg:address":"727 Olive St",
    "sg:city":"Saint Louis",
    "sg:classifiers":[
        {
            "category":"Restaurant",
            "type":"Food & Drink"
        }
    ],
    "sg:phone":"+1 314 621 4086",
    "sg:postcode":"63101",
    "sg:province":"MO",
    "sg:tags":[
        "thai",
        "eating"
    ],
    "sg:website":"www.patsthairestaurants.com/expr...",
    "wof:name":"Thai Express",
    "wof:placetype":"venue"
},
  "geometry": {"coordinates":[-90.191585,38.628393],"type":"Point"}
}