{
  "type": "Feature",
  "properties": {
    "iso:country":"US",
    "sg:address":"2403 Lodgewood Ln",
    "sg:city":"St Peters",
    "sg:classifiers":[
        {
            "category":"Building & Trades",
            "subcategory":"Construction",
            "type":"Services"
        }
    ],
    "sg:phone":"+1 314 972 6001",
    "sg:postcode":"63376",
    "sg:province":"MO",
    "sg:tags":[
        "roofing",
        "contractor"
    ],
    "wof:name":"Weathershield Construction Inc",
    "wof:placetype":"venue"
},
  "geometry": {"coordinates":[-90.615972,38.79129],"type":"Point"}
}