{
  "type": "Feature",
  "properties": {
    "iso:country":"US",
    "sg:address":"616 Olive St",
    "sg:city":"Saint Louis",
    "sg:classifiers":[
        {
            "category":"Restaurant",
            "type":"Food & Drink"
        }
    ],
    "sg:menulink":"http://www.allmenus.com/mo/st-louis/122235-quiznos-sub/menu/",
    "sg:phone":"+1 314 436 2020",
    "sg:postcode":"63101",
    "sg:province":"MO",
    "sg:tags":[
        "wrap",
        "american",
        "sandwich"
    ],
    "wof:name":"Quiznos Sub",
    "wof:placetype":"venue"
},
  "geometry": {"coordinates":[-90.190853,38.62816],"type":"Point"}
}