{
  "type": "Feature",
  "properties": {
    "iso:country":"US",
    "sg:address":"1425 W 5th St",
    "sg:city":"Eureka",
    "sg:classifiers":[
        {
            "category":"Autos & Motor Vehicles",
            "subcategory":"Auto Supplies",
            "type":"Retail Goods"
        },
        {
            "category":"Wholesale",
            "subcategory":"Auto Parts",
            "type":"Manufacturing & Wholesale Goods"
        }
    ],
    "sg:phone":"+1 636 938 4950",
    "sg:postcode":"63025",
    "sg:province":"MO",
    "sg:tags":[
        "topper",
        "truck",
        "accessory"
    ],
    "wof:name":"Eureka Campers",
    "wof:placetype":"venue"
},
  "geometry": {"coordinates":[-90.659244,38.504498],"type":"Point"}
}