{
  "type": "Feature",
  "properties": {
    "iso:country":"US",
    "sg:address":"997 Elm Branch Dr",
    "sg:city":"Marshfield",
    "sg:classifiers":[
        {
            "category":"Professional",
            "type":"Services"
        }
    ],
    "sg:phone":"+1 417 859 4104",
    "sg:postcode":"65706",
    "sg:province":"MO",
    "wof:name":"Aulds Jewel",
    "wof:placetype":"venue"
},
  "geometry": {"coordinates":[-92.891257,37.343092],"type":"Point"}
}