{
  "type": "Feature",
  "properties": {
    "iso:country":"US",
    "sg:address":"4201 N Farm Rd 205",
    "sg:city":"Strafford",
    "sg:classifiers":[
        {
            "category":"Social Services",
            "subcategory":"Job Training",
            "type":"Services"
        }
    ],
    "sg:phone":"+1 417 833 2227",
    "sg:postcode":"65757",
    "sg:province":"MO",
    "wof:name":"Hawthorne Support Services",
    "wof:placetype":"venue"
},
  "geometry": {"coordinates":[-93.16897899999999,37.269981],"type":"Point"}
}