{
  "type": "Feature",
  "properties": {
    "iso:country":"US",
    "sg:address":"3115 N Belt Hwy",
    "sg:city":"St Joseph",
    "sg:classifiers":[
        {
            "category":"Shopping",
            "subcategory":"Gifts & Souvenirs",
            "type":"Retail Goods"
        },
        {
            "category":"Shopping",
            "subcategory":"Clothing, Apparel, & Fashions",
            "type":"Retail Goods"
        }
    ],
    "sg:phone":"+1 816 233 2121",
    "sg:postcode":"64506",
    "sg:province":"MO",
    "sg:tags":[
        "cards",
        "lingerie",
        "novelty"
    ],
    "wof:name":"Priscilla's",
    "wof:placetype":"venue"
},
  "geometry": {"coordinates":[-94.811291,39.793248],"type":"Point"}
}