{
  "type": "Feature",
  "properties": {
    "iso:country":"US",
    "sg:address":"1101 Garfield Ave",
    "sg:city":"St Joseph",
    "sg:classifiers":[
        {
            "category":"Autos & Motor Vehicles",
            "subcategory":"Automobile Sales",
            "type":"Retail Goods"
        }
    ],
    "sg:phone":"+1 816 233 7584",
    "sg:postcode":"64503",
    "sg:province":"MO",
    "sg:tags":[
        "car",
        "used",
        "dealer"
    ],
    "wof:name":"B & B Used Cars & Trucks Inc",
    "wof:placetype":"venue"
},
  "geometry": {"coordinates":[-94.84593599999999,39.74112],"type":"Point"}
}