{
  "type": "Feature",
  "properties": {
    "iso:country":"US",
    "sg:address":"216 S Russell St",
    "sg:city":"Jackson",
    "sg:classifiers":[
        {
            "category":"Education",
            "subcategory":"School",
            "type":"Public Place"
        }
    ],
    "sg:phone":"+1 573 243 5360",
    "sg:postcode":"63755",
    "sg:province":"MO",
    "sg:tags":[
        "organization",
        "religious"
    ],
    "wof:name":"St Pauls Lutheran School",
    "wof:placetype":"venue"
},
  "geometry": {"coordinates":[-89.670321,37.381672],"type":"Point"}
}