{
  "type": "Feature",
  "properties": {
    "iso:country":"US",
    "sg:address":"2625 Fairway Dr Ste G",
    "sg:city":"Fulton",
    "sg:classifiers":[
        {
            "category":"Insurance",
            "subcategory":"Hazard Insurance",
            "type":"Services"
        },
        {
            "category":"Insurance",
            "subcategory":"Insurance Agent",
            "type":"Services"
        },
        {
            "category":"Insurance",
            "subcategory":"Life Insurance",
            "type":"Services"
        },
        {
            "category":"Insurance",
            "subcategory":"Health Insurance",
            "type":"Services"
        }
    ],
    "sg:phone":"+1 573 642 2727",
    "sg:postcode":"65251",
    "sg:province":"MO",
    "sg:tags":[
        "employee",
        "auto",
        "benefit"
    ],
    "sg:website":"http://statefarm.mqgroup.com/url.asp?usr=253725",
    "wof:name":"State Farm Insurance Agent-Russ Weyland",
    "wof:placetype":"venue"
},
  "geometry": {"coordinates":[-91.965332,38.877806],"type":"Point"}
}