{
  "type": "Feature",
  "properties": {
    "iso:country":"US",
    "sg:address":"1228 Amberleaf Ln",
    "sg:city":"Fenton",
    "sg:classifiers":[
        {
            "category":"Real Estate",
            "subcategory":"Real Estate Operator",
            "type":"Services"
        }
    ],
    "sg:phone":"+1 636 349 7903",
    "sg:postcode":"63026",
    "sg:province":"MO",
    "sg:tags":[
        "mobile",
        "home",
        "site"
    ],
    "wof:name":"White Oak Estate Inc",
    "wof:placetype":"venue"
},
  "geometry": {"coordinates":[-90.45877,38.485029],"type":"Point"}
}