{
  "type": "Feature",
  "properties": {
    "iso:country":"US",
    "sg:address":"4962 McBride Rd",
    "sg:city":"Protem",
    "sg:classifiers":[
        {
            "category":"Farming",
            "subcategory":"Aquatic Farm",
            "type":"Manufacturing & Wholesale Goods"
        }
    ],
    "sg:phone":"+1 417 785 4375",
    "sg:postcode":"65733",
    "sg:province":"MO",
    "sg:tags":[
        "facility"
    ],
    "wof:name":"Blue Waters Resort",
    "wof:placetype":"venue"
},
  "geometry": {"coordinates":[-92.836043,36.483383],"type":"Point"}
}