{
  "type": "Feature",
  "properties": {
    "iso:country":"US",
    "sg:address":"4847 S Buckingham Ln",
    "sg:city":"Springfield",
    "sg:classifiers":[
        {
            "category":"Professional",
            "type":"Services"
        }
    ],
    "sg:phone":"+1 417 823 7629",
    "sg:postcode":"65810",
    "sg:province":"MO",
    "wof:name":"David & Julie Bixler",
    "wof:placetype":"venue"
},
  "geometry": {"coordinates":[-93.305097,37.124915],"type":"Point"}
}