{
  "type": "Feature",
  "properties": {
    "iso:country":"US",
    "sg:address":"2448 Taylor Rd",
    "sg:city":"Grover",
    "sg:classifiers":[
        {
            "category":"Insurance",
            "subcategory":"Insurance Agent",
            "type":"Services"
        },
        {
            "category":"Insurance",
            "subcategory":"Hazard Insurance",
            "type":"Services"
        }
    ],
    "sg:phone":"+1 636 821 8673",
    "sg:postcode":"63040",
    "sg:province":"MO",
    "sg:tags":[
        "auto",
        "property",
        "motorcycle",
        "casualty"
    ],
    "sg:website":"http://ad.doubleclick.net/clk;227136451;50888706;m?http://www.stillwellagency.com",
    "wof:name":"Save on Auto Insurance with Kendra Stillwell",
    "wof:placetype":"venue"
},
  "geometry": {"coordinates":[-90.62746799999999,38.581603],"type":"Point"}
}