{
  "type": "Feature",
  "properties": {
    "iso:country":"US",
    "sg:address":"18040 Edison Ave",
    "sg:city":"Chesterfield",
    "sg:classifiers":[
        {
            "category":"Wholesale",
            "subcategory":"Furniture",
            "type":"Manufacturing & Wholesale Goods"
        }
    ],
    "sg:phone":"+1 314 878 3088",
    "sg:postcode":"63005",
    "sg:province":"MO",
    "sg:website":"www.tttdesigncenter.com",
    "wof:name":"To The Trade",
    "wof:placetype":"venue"
},
  "geometry": {"coordinates":[-90.64124,38.663844],"type":"Point"}
}