{
  "type": "Feature",
  "properties": {
    "iso:country":"US",
    "sg:address":"42 S Main St",
    "sg:city":"Liberty",
    "sg:classifiers":[
        {
            "category":"Insurance",
            "subcategory":"Hazard Insurance",
            "type":"Services"
        }
    ],
    "sg:phone":"+1 816 781 2820",
    "sg:postcode":"64068",
    "sg:province":"MO",
    "sg:tags":[
        "bond"
    ],
    "wof:name":"Victory Bonding",
    "wof:placetype":"venue"
},
  "geometry": {"coordinates":[-94.420435,39.245317],"type":"Point"}
}