{
  "type": "Feature",
  "properties": {
    "iso:country":"US",
    "sg:address":"2800 E Heartland Dr",
    "sg:city":"Liberty",
    "sg:classifiers":[
        {
            "category":"Shopping",
            "subcategory":"Gifts & Souvenirs",
            "type":"Retail Goods"
        },
        {
            "category":"Manufacturing",
            "subcategory":"Retail Goods",
            "type":"Manufacturing & Wholesale Goods"
        }
    ],
    "sg:phone":"+1 816 792 8841",
    "sg:postcode":"64068",
    "sg:province":"MO",
    "sg:tags":[
        "shop",
        "giftware's-wholesale",
        "manufacturer"
    ],
    "wof:name":"Creative Happenings, Inc",
    "wof:placetype":"venue"
},
  "geometry": {"coordinates":[-94.39866600000001,39.280991],"type":"Point"}
}