{
  "type": "Feature",
  "properties": {
    "iso:country":"US",
    "sg:address":"400 E Spring St",
    "sg:city":"Boonville",
    "sg:classifiers":[
        {
            "category":"Banks & Credit Unions",
            "subcategory":"Bank",
            "type":"Services"
        },
        {
            "category":"Banks & Credit Unions",
            "subcategory":"Financial Services",
            "type":"Services"
        }
    ],
    "sg:phone":"+1 660 882 7476",
    "sg:postcode":"65233",
    "sg:province":"MO",
    "sg:tags":[
        "commercial",
        "loan",
        "saving"
    ],
    "sg:website":"http://www.ebankcbt.com",
    "wof:name":"Citizens Bank",
    "wof:placetype":"venue"
},
  "geometry": {"coordinates":[-92.74535400000001,38.975201],"type":"Point"}
}