{
  "type": "Feature",
  "properties": {
    "iso:country":"US",
    "sg:address":"3760 State Hwy E",
    "sg:city":"Silex",
    "sg:classifiers":[
        {
            "category":"Recreation",
            "type":"Entertainment"
        },
        {
            "category":"Organizations",
            "subcategory":"Community Association",
            "type":"Services"
        }
    ],
    "sg:phone":"+1 573 656 3655",
    "sg:postcode":"63377",
    "sg:province":"MO",
    "sg:tags":[
        "club",
        "membership"
    ],
    "wof:name":"Silex Lions Club",
    "wof:placetype":"venue"
},
  "geometry": {"coordinates":[-91.513121,38.979653],"type":"Point"}
}