{
  "type": "Feature",
  "properties": {
    "iso:country":"US",
    "sg:address":"240 S Westwood Blvd",
    "sg:city":"Poplar Bluff",
    "sg:classifiers":[
        {
            "category":"Autos & Motor Vehicles",
            "subcategory":"Automobile Sales",
            "type":"Retail Goods"
        }
    ],
    "sg:phone":"+1 573 785 8433",
    "sg:postcode":"63901",
    "sg:province":"MO",
    "sg:tags":[
        "car",
        "dealer"
    ],
    "wof:name":"Henderson Auto Sales",
    "wof:placetype":"venue"
},
  "geometry": {"coordinates":[-90.40783999999999,36.756189],"type":"Point"}
}