{
  "type": "Feature",
  "properties": {
    "iso:country":"US",
    "sg:address":"806 University Pl",
    "sg:city":"Saint Louis",
    "sg:classifiers":[
        {
            "category":"Wholesale",
            "subcategory":"Apparel",
            "type":"Manufacturing & Wholesale Goods"
        }
    ],
    "sg:phone":"+1 314 991 2533",
    "sg:postcode":"63132",
    "sg:province":"MO",
    "sg:tags":[
        "clothing"
    ],
    "wof:name":"Greens",
    "wof:placetype":"venue"
},
  "geometry": {"coordinates":[-90.351517,38.663889],"type":"Point"}
}