{
  "type": "Feature",
  "properties": {
    "iso:country":"US",
    "sg:address":"5504 E 31 St",
    "sg:city":"Kansas City",
    "sg:classifiers":[
        {
            "category":"Social Services",
            "subcategory":"Child Care",
            "type":"Services"
        }
    ],
    "sg:phone":"+1 816 921 2390",
    "sg:postcode":"64128",
    "sg:province":"MO",
    "wof:name":"I Know I Can Learning Ctr",
    "wof:placetype":"venue"
},
  "geometry": {"coordinates":[-94.519415,39.06886],"type":"Point"}
}