{
  "type": "Feature",
  "properties": {
    "iso:country":"US",
    "sg:address":"2612 Dry Hollow Rd",
    "sg:city":"Camdenton",
    "sg:classifiers":[
        {
            "category":"Retail",
            "subcategory":"Portrait Studio",
            "type":"Services"
        },
        {
            "category":"Professional",
            "subcategory":"Art Services",
            "type":"Services"
        },
        {
            "category":"Professional",
            "subcategory":"Printing & Photocopies",
            "type":"Services"
        }
    ],
    "sg:phone":"+1 573 745 1125",
    "sg:postcode":"65020",
    "sg:province":"MO",
    "sg:tags":[
        "rental",
        "photographers-portrait",
        "photographers-commercial",
        "photographic",
        "darkroom"
    ],
    "sg:website":"http://www.goodwinphoto.com",
    "wof:name":"Images By Doug Goodwin",
    "wof:placetype":"venue"
},
  "geometry": {"coordinates":[-92.738242,37.971773],"type":"Point"}
}