{
  "type": "Feature",
  "properties": {
    "iso:country":"US",
    "sg:address":"10474 Audrain Road 963",
    "sg:city":"Centralia",
    "sg:phone":"+1 573 581 0376",
    "sg:postcode":"65240",
    "sg:province":"MO",
    "sg:tags":[
        "farm"
    ],
    "wof:name":"Richard Ewigman",
    "wof:placetype":"venue"
},
  "geometry": {"coordinates":[-92.025042,39.189717],"type":"Point"}
}