{
  "type": "Feature",
  "properties": {
    "iso:country":"US",
    "sg:address":"8551 Ardelia Ave",
    "sg:city":"Saint Louis",
    "sg:classifiers":[
        {
            "category":"Organizations",
            "subcategory":"Religious Organization",
            "type":"Services"
        }
    ],
    "sg:phone":"+1 314 427 6699",
    "sg:postcode":"63114",
    "sg:province":"MO",
    "wof:name":"Ministries Hidden Treasur",
    "wof:placetype":"venue"
},
  "geometry": {"coordinates":[-90.337875,38.715787],"type":"Point"}
}