{
  "type": "Feature",
  "properties": {
    "iso:country":"US",
    "sg:address":"17263 Wild Horse Creek Rd",
    "sg:city":"Chesterfield",
    "sg:classifiers":[
        {
            "category":"Banks & Credit Unions",
            "subcategory":"Bank",
            "type":"Services"
        }
    ],
    "sg:phone":"+1 636 537 8080",
    "sg:postcode":"63005",
    "sg:province":"MO",
    "sg:tags":[
        "commercial"
    ],
    "wof:name":"Reliance Bank",
    "wof:placetype":"venue"
},
  "geometry": {"coordinates":[-90.617947,38.657462],"type":"Point"}
}