{
  "type": "Feature",
  "properties": {
    "iso:country":"US",
    "sg:address":"12311 Sorrel Rd",
    "sg:city":"Goodman",
    "sg:classifiers":[
        {
            "category":"Professional",
            "type":"Services"
        }
    ],
    "sg:phone":"+1 417 364 7840",
    "sg:postcode":"64843",
    "sg:province":"MO",
    "sg:tags":[
        "establishment"
    ],
    "wof:name":"Sunrise Puppies",
    "wof:placetype":"venue"
},
  "geometry": {"coordinates":[-94.428067,36.774588],"type":"Point"}
}