{
  "type": "Feature",
  "properties": {
    "iso:country":"US",
    "sg:address":"1200 Main St",
    "sg:city":"Kansas City",
    "sg:classifiers":[
        {
            "category":"Food & Beverages",
            "subcategory":"Groceries & Convenience Stores",
            "type":"Retail Goods"
        }
    ],
    "sg:phone":"+1 816 221 1701",
    "sg:postcode":"64105",
    "sg:province":"MO",
    "wof:name":"Grandmas Deli & Bake Shop",
    "wof:placetype":"venue"
},
  "geometry": {"coordinates":[-94.58326099999999,39.098597],"type":"Point"}
}