{
  "type": "Feature",
  "properties": {
    "iso:country":"US",
    "sg:address":"3623 State Hwy 19",
    "sg:city":"Cuba",
    "sg:classifiers":[
        {
            "category":"Building & Trades",
            "subcategory":"Construction",
            "type":"Services"
        }
    ],
    "sg:phone":"+1 573 885 2775",
    "sg:postcode":"65453",
    "sg:province":"MO",
    "sg:tags":[
        "general",
        "contractor"
    ],
    "wof:name":"Workman Construction Co",
    "wof:placetype":"venue"
},
  "geometry": {"coordinates":[-91.433713,38.12968],"type":"Point"}
}