{
  "type": "Feature",
  "properties": {
    "iso:country":"US",
    "sg:address":"3541 Heather Trail Dr",
    "sg:city":"Florissant",
    "sg:classifiers":[
        {
            "category":"Building & Trades",
            "subcategory":"Pest Control",
            "type":"Services"
        }
    ],
    "sg:phone":"+1 314 921 1022",
    "sg:postcode":"63031",
    "sg:province":"MO",
    "wof:name":"Bi State Pest Control Corp",
    "wof:placetype":"venue"
},
  "geometry": {"coordinates":[-90.31852499999999,38.836311],"type":"Point"}
}