{
  "type": "Feature",
  "properties": {
    "iso:country":"US",
    "sg:address":"618 E 1st St",
    "sg:city":"Trenton",
    "sg:classifiers":[
        {
            "category":"Health Services",
            "subcategory":"Doctor",
            "type":"Services"
        },
        {
            "category":"Health Services",
            "subcategory":"Clinic",
            "type":"Services"
        }
    ],
    "sg:phone":"+1 660 359 3899",
    "sg:postcode":"64683",
    "sg:province":"MO",
    "sg:tags":[
        "physician",
        "family",
        "practice",
        "surgeons",
        "osteopathic",
        "medicine"
    ],
    "wof:name":"McClure, Phil",
    "wof:placetype":"venue"
},
  "geometry": {"coordinates":[-93.612345,40.066429],"type":"Point"}
}