{
  "type": "Feature",
  "properties": {
    "addr:full":"9147 Watson Rd St Louis MO 63126",
    "addr:housenumber":"9147",
    "addr:postcode":"63126",
    "addr:street":"Watson Rd",
    "iso:country":"US",
    "sg:address":"9147 Watson Rd",
    "sg:city":"St Louis",
    "sg:classifiers":[
        {
            "category":"Insurance",
            "subcategory":"Insurance Agent",
            "type":"Services"
        }
    ],
    "sg:phone":"+1 314 918 1488",
    "sg:postcode":"63126",
    "sg:province":"MO",
    "wof:name":"Farmers Insurance",
    "wof:placetype":"venue"
},
  "geometry": {"coordinates":[-90.372986,38.560384],"type":"Point"}
}