{
  "type": "Feature",
  "properties": {
    "iso:country":"US",
    "sg:address":"514 E 6th St",
    "sg:city":"Cameron",
    "sg:classifiers":[
        {
            "category":"Professional",
            "type":"Services"
        }
    ],
    "sg:phone":"+1 816 632 1500",
    "sg:postcode":"64429",
    "sg:province":"MO",
    "wof:name":"Dave Gillette",
    "wof:placetype":"venue"
},
  "geometry": {"coordinates":[-94.232845,39.74419],"type":"Point"}
}