{
  "type": "Feature",
  "properties": {
    "iso:country":"US",
    "sg:address":"3691 Highway 54",
    "sg:city":"Curryville",
    "sg:classifiers":[
        {
            "category":"Wholesale",
            "subcategory":"Hardware",
            "type":"Manufacturing & Wholesale Goods"
        },
        {
            "category":"Home & Garden",
            "subcategory":"Garden Supply",
            "type":"Retail Goods"
        },
        {
            "category":"Retail",
            "subcategory":"Repair Shop",
            "type":"Services"
        }
    ],
    "sg:phone":"+1 573 594 6493",
    "sg:postcode":"63339",
    "sg:province":"MO",
    "sg:tags":[
        "renting",
        "lawn",
        "outdoor",
        "power",
        "landscaping",
        "equipment-sales",
        "equipment",
        "saw"
    ],
    "sg:website":"http://www.stihlusa.com/",
    "wof:name":"Sydenstricker Implement Co",
    "wof:placetype":"venue"
},
  "geometry": {"coordinates":[-91.414205,39.34601],"type":"Point"}
}