{
  "type": "Feature",
  "properties": {
    "iso:country":"US",
    "sg:address":"1810 State Hwy 291",
    "sg:city":"Harrisonville",
    "sg:classifiers":[
        {
            "category":"Shopping",
            "subcategory":"Computers & Home Electronics",
            "type":"Retail Goods"
        }
    ],
    "sg:phone":"+1 816 887 4731",
    "sg:postcode":"64701",
    "sg:province":"MO",
    "sg:tags":[
        "game",
        "video"
    ],
    "wof:name":"Game Stop Corp",
    "wof:placetype":"venue"
},
  "geometry": {"coordinates":[-94.3664,38.668534],"type":"Point"}
}