{
  "type": "Feature",
  "properties": {
    "iso:country":"US",
    "sg:address":"1502 Belleau Creek Rd",
    "sg:city":"O Fallon",
    "sg:classifiers":[
        {
            "category":"Building & Trades",
            "subcategory":"Construction",
            "type":"Services"
        }
    ],
    "sg:phone":"+1 636 272 2953",
    "sg:postcode":"63366",
    "sg:province":"MO",
    "sg:tags":[
        "masonry",
        "contractor"
    ],
    "wof:name":"O'Fallon Bricklaying",
    "wof:placetype":"venue"
},
  "geometry": {"coordinates":[-90.67215400000001,38.793565],"type":"Point"}
}