{
  "type": "Feature",
  "properties": {
    "iso:country":"US",
    "sg:address":"2523 W Woodland Dr",
    "sg:city":"Saint Joseph",
    "sg:classifiers":[
        {
            "category":"Building & Trades",
            "subcategory":"Landscaping Services",
            "type":"Services"
        }
    ],
    "sg:phone":"+1 816 279 1711",
    "sg:postcode":"64506",
    "sg:province":"MO",
    "wof:name":"Duvall Lawn Service",
    "wof:placetype":"venue"
},
  "geometry": {"coordinates":[-94.794826,39.790537],"type":"Point"}
}