{
  "type": "Feature",
  "properties": {
    "iso:country":"US",
    "sg:address":"150 Salt Lick Rd",
    "sg:city":"St Peters",
    "sg:classifiers":[
        {
            "category":"Food & Beverages",
            "subcategory":"Groceries & Convenience Stores",
            "type":"Retail Goods"
        }
    ],
    "sg:phone":"+1 636 397 4592",
    "sg:postcode":"63376",
    "sg:province":"MO",
    "wof:name":"Huck's Convenient Food Store",
    "wof:placetype":"venue"
},
  "geometry": {"coordinates":[-90.65312900000001,38.799649],"type":"Point"}
}