{
  "type": "Feature",
  "properties": {
    "iso:country":"US",
    "sg:address":"15032 State Hwy 133",
    "sg:city":"Dixon",
    "sg:classifiers":[
        {
            "category":"Home & Garden",
            "subcategory":"Garden Supply",
            "type":"Retail Goods"
        }
    ],
    "sg:phone":"+1 573 759 6249",
    "sg:postcode":"65459",
    "sg:province":"MO",
    "sg:tags":[
        "fertilizer"
    ],
    "wof:name":"Ralphie's Farm Products",
    "wof:placetype":"venue"
},
  "geometry": {"coordinates":[-92.121404,38.012562],"type":"Point"}
}