{
  "type": "Feature",
  "properties": {
    "iso:country":"US",
    "sg:address":"812 Clover Ln",
    "sg:city":"Farmington",
    "sg:classifiers":[
        {
            "category":"Home & Garden",
            "subcategory":"Furniture",
            "type":"Retail Goods"
        }
    ],
    "sg:phone":"+1 573 756 7040",
    "sg:postcode":"63640",
    "sg:province":"MO",
    "sg:tags":[
        "cabinet"
    ],
    "wof:name":"Oak Shop",
    "wof:placetype":"venue"
},
  "geometry": {"coordinates":[-90.439943,37.804135],"type":"Point"}
}