{
  "type": "Feature",
  "properties": {
    "iso:country":"US",
    "sg:address":"510 S Wall Ave",
    "sg:city":"Joplin",
    "sg:classifiers":[
        {
            "category":"Community Center",
            "subcategory":"Youth",
            "type":"Public Place"
        }
    ],
    "sg:phone":"+1 417 623 3144",
    "sg:postcode":"64801",
    "sg:province":"MO",
    "wof:name":"Young Life",
    "wof:placetype":"venue"
},
  "geometry": {"coordinates":[-94.515562,37.086639],"type":"Point"}
}