{
  "type": "Feature",
  "properties": {
    "iso:country":"US",
    "sg:address":"2411 Abbey Rd",
    "sg:city":"Cape Girardeau",
    "sg:classifiers":[
        {
            "category":"Organizations",
            "subcategory":"Religious Organization",
            "type":"Services"
        }
    ],
    "sg:phone":"+1 573 335 3422",
    "sg:postcode":"63701",
    "sg:province":"MO",
    "wof:name":"Disciples of Christ",
    "wof:placetype":"venue"
},
  "geometry": {"coordinates":[-89.567341,37.342537],"type":"Point"}
}