{
  "type": "Feature",
  "properties": {
    "iso:country":"US",
    "sg:address":"311 Sante Ave",
    "sg:city":"St Louis",
    "sg:classifiers":[
        {
            "category":"Building & Trades",
            "subcategory":"Landscaping Services",
            "type":"Services"
        }
    ],
    "sg:phone":"+1 314 965 0596",
    "sg:postcode":"63122",
    "sg:province":"MO",
    "sg:tags":[
        "lawn",
        "maintenance",
        "grounds"
    ],
    "wof:name":"Down To Earth Lawn & Landscpg",
    "wof:placetype":"venue"
},
  "geometry": {"coordinates":[-90.400916,38.577039],"type":"Point"}
}