{
  "type": "Feature",
  "properties": {
    "iso:country":"US",
    "sg:address":"28 E Nottingham Cir",
    "sg:city":"Sullivan",
    "sg:classifiers":[
        {
            "category":"Health Services",
            "subcategory":"Doctor",
            "type":"Services"
        }
    ],
    "sg:phone":"+1 573 927 5579",
    "sg:postcode":"63080",
    "sg:province":"MO",
    "sg:tags":[
        "physician",
        "surgeon"
    ],
    "wof:name":"Florante A Repaso Inc",
    "wof:placetype":"venue"
},
  "geometry": {"coordinates":[-91.127149,38.258155],"type":"Point"}
}