{
  "type": "Feature",
  "properties": {
    "iso:country":"US",
    "sg:address":"14803 Hwy 17",
    "sg:city":"Eugene",
    "sg:classifiers":[
        {
            "category":"Education",
            "subcategory":"School",
            "type":"Public Place"
        }
    ],
    "sg:phone":"+1 573 498 4000",
    "sg:postcode":"65032",
    "sg:province":"MO",
    "sg:website":"www.coler-v.k12.mo.us",
    "wof:name":"Cole County R-V Schools",
    "wof:placetype":"venue"
},
  "geometry": {"coordinates":[-92.397513,38.373813],"type":"Point"}
}