{
  "type": "Feature",
  "properties": {
    "iso:country":"US",
    "sg:address":"205 N Macon St",
    "sg:city":"Bevier",
    "sg:classifiers":[
        {
            "category":"Bars & Pubs",
            "type":"Food & Drink"
        },
        {
            "category":"Restaurant",
            "type":"Food & Drink"
        },
        {
            "category":"Sports & Exercise",
            "subcategory":"Sports Center",
            "type":"Entertainment"
        },
        {
            "category":"Organizations",
            "subcategory":"Membership Organization",
            "type":"Services"
        }
    ],
    "sg:phone":"+1 660 773 6643",
    "sg:postcode":"63532",
    "sg:province":"MO",
    "sg:tags":[
        "club",
        "private"
    ],
    "wof:name":"Bjs Country Club",
    "wof:placetype":"venue"
},
  "geometry": {"coordinates":[-92.561066,39.759121],"type":"Point"}
}