{
  "type": "Feature",
  "properties": {
    "iso:country":"US",
    "sg:address":"2284 Yale Ave",
    "sg:city":"Saint Louis",
    "sg:classifiers":[
        {
            "category":"Education",
            "subcategory":"Special Training",
            "type":"Public Place"
        }
    ],
    "sg:phone":"+1 314 647 0115",
    "sg:postcode":"63143",
    "sg:province":"MO",
    "sg:tags":[
        "e",
        "energy",
        "connection",
        "through",
        "college",
        "promote",
        "massage"
    ],
    "wof:name":"Massage & Energy Connection",
    "wof:placetype":"venue"
},
  "geometry": {"coordinates":[-90.312387,38.615106],"type":"Point"}
}