{
  "type": "Feature",
  "properties": {
    "iso:country":"US",
    "sg:address":"11570 Norway Rd",
    "sg:city":"Neosho",
    "sg:classifiers":[
        {
            "category":"Building & Trades",
            "subcategory":"Construction",
            "type":"Services"
        }
    ],
    "sg:phone":"+1 417 451 7526",
    "sg:postcode":"64850",
    "sg:province":"MO",
    "wof:name":"Four State Tower Erector Inc",
    "wof:placetype":"venue"
},
  "geometry": {"coordinates":[-94.438687,36.851607],"type":"Point"}
}