{
  "type": "Feature",
  "properties": {
    "iso:country":"US",
    "sg:address":"6953 N Farm Road 133",
    "sg:city":"Springfield",
    "sg:classifiers":[
        {
            "category":"Building & Trades",
            "subcategory":"Construction",
            "type":"Services"
        }
    ],
    "sg:phone":"+1 417 833 8715",
    "sg:postcode":"65803",
    "sg:province":"MO",
    "sg:tags":[
        "wallcoverings-installation",
        "wallpaper",
        "painting",
        "contractor"
    ],
    "wof:name":"Ed Wollen Contract Painting",
    "wof:placetype":"venue"
},
  "geometry": {"coordinates":[-93.34030199999999,37.321895],"type":"Point"}
}