{
  "type": "Feature",
  "properties": {
    "iso:country":"US",
    "sg:address":"400 E Clinton Pl",
    "sg:city":"Saint Louis",
    "sg:classifiers":[
        {
            "category":"Building & Trades",
            "subcategory":"Cleaning & Sanitation",
            "type":"Services"
        }
    ],
    "sg:phone":"+1 314 965 2751",
    "sg:postcode":"63122",
    "sg:province":"MO",
    "sg:tags":[
        "maintenance"
    ],
    "wof:name":"Gamel Company Inc",
    "wof:placetype":"venue"
},
  "geometry": {"coordinates":[-90.395932,38.574768],"type":"Point"}
}