{
  "type": "Feature",
  "properties": {
    "iso:country":"US",
    "sg:address":"1323 Caulks Hill Rd",
    "sg:city":"St Charles",
    "sg:classifiers":[
        {
            "category":"Building & Trades",
            "subcategory":"Construction",
            "type":"Services"
        }
    ],
    "sg:phone":"+1 636 928 0771",
    "sg:postcode":"63304",
    "sg:province":"MO",
    "sg:tags":[
        "house",
        "general",
        "residential",
        "contractor"
    ],
    "wof:name":"Petra Construction Inc",
    "wof:placetype":"venue"
},
  "geometry": {"coordinates":[-90.57900100000001,38.736365],"type":"Point"}
}