{
  "type": "Feature",
  "properties": {
    "iso:country":"US",
    "sg:address":"26548 Queens Lace Dr",
    "sg:city":"Stella",
    "sg:classifiers":[
        {
            "category":"Farming",
            "subcategory":"Farm",
            "type":"Manufacturing & Wholesale Goods"
        }
    ],
    "sg:phone":"+1 417 628 3069",
    "sg:postcode":"64867",
    "sg:province":"MO",
    "wof:name":"Gary J Granger",
    "wof:placetype":"venue"
},
  "geometry": {"coordinates":[-94.171768,36.78772],"type":"Point"}
}