{
  "type": "Feature",
  "properties": {
    "iso:country":"US",
    "sg:address":"3975 Co Rd 304",
    "sg:city":"Fulton",
    "sg:classifiers":[
        {
            "category":"Farming",
            "subcategory":"Livestock Farm",
            "type":"Manufacturing & Wholesale Goods"
        }
    ],
    "sg:phone":"+1 573 642 2544",
    "sg:postcode":"65251",
    "sg:province":"MO",
    "sg:tags":[
        "beef",
        "feedlot",
        "cattle"
    ],
    "wof:name":"Kenneth Means",
    "wof:placetype":"venue"
},
  "geometry": {"coordinates":[-92.024258,38.844241],"type":"Point"}
}