{
  "type": "Feature",
  "properties": {
    "iso:country":"US",
    "sg:address":"2410 Laclede Forest Dr",
    "sg:city":"Saint Louis",
    "sg:classifiers":[
        {
            "category":"Professional",
            "type":"Services"
        }
    ],
    "sg:phone":"+1 314 647 0944",
    "sg:postcode":"63143",
    "sg:province":"MO",
    "wof:name":"Dyer Delights",
    "wof:placetype":"venue"
},
  "geometry": {"coordinates":[-90.329887,38.617225],"type":"Point"}
}