{
  "type": "Feature",
  "properties": {
    "iso:country":"US",
    "sg:address":"1519 E Sunshine St",
    "sg:city":"Springfield",
    "sg:classifiers":[
        {
            "category":"Real Estate",
            "subcategory":"Real Estate Services",
            "type":"Services"
        },
        {
            "category":"Real Estate",
            "subcategory":"Real Estate Agent",
            "type":"Services"
        }
    ],
    "sg:phone":"+1 417 882 5595",
    "sg:postcode":"65804",
    "sg:province":"MO",
    "sg:tags":[
        "buyer",
        "management",
        "broker"
    ],
    "wof:name":"Dickens Gerri Realtors",
    "wof:placetype":"venue"
},
  "geometry": {"coordinates":[-93.270251,37.181759],"type":"Point"}
}