{
  "type": "Feature",
  "properties": {
    "iso:country":"US",
    "sg:address":"303 N Washington St",
    "sg:city":"Freeman",
    "sg:classifiers":[
        {
            "category":"Place Of Worship",
            "subcategory":"Church",
            "type":"Public Place"
        },
        {
            "category":"Place Of Worship",
            "type":"Public Place"
        }
    ],
    "sg:phone":"+1 816 899 5579",
    "sg:postcode":"64746",
    "sg:province":"MO",
    "sg:tags":[
        "churches-baptist-general",
        "denomination",
        "churches-baptist",
        "churches-interdenominational",
        "churches-various"
    ],
    "wof:name":"Freeman Baptist Church Inc",
    "wof:placetype":"venue"
},
  "geometry": {"coordinates":[-94.506446,38.619116],"type":"Point"}
}