{
  "type": "Feature",
  "properties": {
    "iso:country":"US",
    "sg:address":"8403 Olive Blvd",
    "sg:city":"St Louis",
    "sg:classifiers":[
        {
            "category":"Professional",
            "subcategory":"Management & Consulting",
            "type":"Services"
        }
    ],
    "sg:phone":"+1 314 333 4250",
    "sg:postcode":"63132",
    "sg:province":"MO",
    "sg:tags":[
        "consultant",
        "product"
    ],
    "wof:name":"Outdoor Innovations",
    "wof:placetype":"venue"
},
  "geometry": {"coordinates":[-90.35503,38.674119],"type":"Point"}
}