{
  "type": "Feature",
  "properties": {
    "iso:country":"US",
    "sg:address":"619 Lime Rock Dr",
    "sg:city":"Saint Charles",
    "sg:classifiers":[
        {
            "category":"Manufacturing",
            "subcategory":"Toys & Sporting Goods",
            "type":"Manufacturing & Wholesale Goods"
        }
    ],
    "sg:phone":"+1 636 441 7713",
    "sg:postcode":"63304",
    "sg:province":"MO",
    "sg:tags":[
        "mfg"
    ],
    "wof:name":"Show ME Golf",
    "wof:placetype":"venue"
},
  "geometry": {"coordinates":[-90.604122,38.756476],"type":"Point"}
}