{
  "type": "Feature",
  "properties": {
    "iso:country":"US",
    "sg:address":"1223 E Main St",
    "sg:city":"Perry",
    "sg:classifiers":[
        {
            "category":"Health Services",
            "subcategory":"Clinic",
            "type":"Services"
        }
    ],
    "sg:phone":"+1 573 565 2213",
    "sg:postcode":"63462",
    "sg:province":"MO",
    "sg:tags":[
        "osteopathic"
    ],
    "wof:name":"Joe T Beahan Do",
    "wof:placetype":"venue"
},
  "geometry": {"coordinates":[-91.661275,39.429553],"type":"Point"}
}