{
  "type": "Feature",
  "properties": {
    "iso:country":"US",
    "sg:address":"2940 W 17th St",
    "sg:city":"Joplin",
    "sg:classifiers":[
        {
            "category":"Organizations",
            "subcategory":"Membership Organization",
            "type":"Services"
        }
    ],
    "sg:phone":"+1 417 781 6728",
    "sg:postcode":"64801",
    "sg:province":"MO",
    "wof:name":"Missouri Guide Dog Users",
    "wof:placetype":"venue"
},
  "geometry": {"coordinates":[-94.550929,37.074047],"type":"Point"}
}