{
  "type": "Feature",
  "properties": {
    "iso:country":"US",
    "sg:address":"19800 E Truman Rd",
    "sg:city":"Independence",
    "sg:classifiers":[
        {
            "category":"Place Of Worship",
            "subcategory":"Church",
            "type":"Public Place"
        },
        {
            "category":"Place Of Worship",
            "type":"Public Place"
        }
    ],
    "sg:phone":"+1 816 796 2750",
    "sg:postcode":"64056",
    "sg:province":"MO",
    "sg:tags":[
        "nazarene",
        "churches-church",
        "churches-nazarene"
    ],
    "wof:name":"Trinity Church of The Nazarene",
    "wof:placetype":"venue"
},
  "geometry": {"coordinates":[-94.344689,39.091328],"type":"Point"}
}