{
  "type": "Feature",
  "properties": {
    "iso:country":"US",
    "sg:address":"12 Municipal Dr",
    "sg:city":"Arnold",
    "sg:classifiers":[
        {
            "category":"Insurance",
            "subcategory":"Hazard Insurance",
            "type":"Services"
        }
    ],
    "sg:phone":"+1 636 296 2949",
    "sg:postcode":"63010",
    "sg:province":"MO",
    "sg:tags":[
        "commercial",
        "business"
    ],
    "wof:name":"Millers First Insurance Co",
    "wof:placetype":"venue"
},
  "geometry": {"coordinates":[-90.401701,38.444891],"type":"Point"}
}