{
  "type": "Feature",
  "properties": {
    "iso:country":"US",
    "sg:address":"709 NE Karapat Dr",
    "sg:city":"Kansas City",
    "sg:classifiers":[
        {
            "category":"Building & Trades",
            "subcategory":"Construction",
            "type":"Services"
        }
    ],
    "sg:phone":"+1 816 507 6040",
    "sg:postcode":"64155",
    "sg:province":"MO",
    "sg:tags":[
        "hanging",
        "contractor"
    ],
    "wof:name":"Walker Painting & Wallcovering",
    "wof:placetype":"venue"
},
  "geometry": {"coordinates":[-94.572113,39.292283],"type":"Point"}
}