{
  "type": "Feature",
  "properties": {
    "iso:country":"US",
    "sg:address":"754 Oglala Ln",
    "sg:city":"Cape Girardeau",
    "sg:classifiers":[
        {
            "category":"Manufacturing",
            "subcategory":"Building Materials",
            "type":"Manufacturing & Wholesale Goods"
        }
    ],
    "sg:phone":"+1 573 651 6558",
    "sg:postcode":"63701",
    "sg:province":"MO",
    "wof:name":"Acorn Enterprises Inc",
    "wof:placetype":"venue"
},
  "geometry": {"coordinates":[-89.57084,37.416178],"type":"Point"}
}