{
  "type": "Feature",
  "properties": {
    "iso:country":"US",
    "sg:address":"21029 Nettle Ln",
    "sg:city":"Jasper",
    "sg:classifiers":[
        {
            "category":"Retail",
            "subcategory":"Repair Shop",
            "type":"Services"
        },
        {
            "category":"Building & Trades",
            "subcategory":"Construction",
            "type":"Services"
        }
    ],
    "sg:phone":"+1 417 525 6100",
    "sg:postcode":"64755",
    "sg:province":"MO",
    "sg:tags":[
        "welding",
        "contractor"
    ],
    "wof:name":"Cox Fabrication & Portable Svc",
    "wof:placetype":"venue"
},
  "geometry": {"coordinates":[-94.435937,37.251817],"type":"Point"}
}