{
  "type": "Feature",
  "properties": {
    "iso:country":"US",
    "sg:address":"9715 Gravois Rd",
    "sg:city":"St Louis",
    "sg:classifiers":[
        {
            "category":"Professional",
            "subcategory":"Printing & Photocopies",
            "type":"Services"
        }
    ],
    "sg:phone":"+1 314 631 7283",
    "sg:postcode":"63123",
    "sg:province":"MO",
    "sg:tags":[
        "printer",
        "duplicating",
        "copying"
    ],
    "wof:name":"Professional Services Copying",
    "wof:placetype":"venue"
},
  "geometry": {"coordinates":[-90.32522400000001,38.552254],"type":"Point"}
}