{
  "type": "Feature",
  "properties": {
    "iso:country":"US",
    "sg:address":"1141 Reco Ave",
    "sg:city":"St Louis",
    "sg:classifiers":[
        {
            "category":"Professional",
            "type":"Services"
        },
        {
            "category":"Building & Trades",
            "subcategory":"Plumbing",
            "type":"Services"
        }
    ],
    "sg:phone":"+1 314 721 4600",
    "sg:postcode":"63126",
    "sg:province":"MO",
    "sg:tags":[
        "equipment"
    ],
    "wof:name":"Climate Service Corporation",
    "wof:placetype":"venue"
},
  "geometry": {"coordinates":[-90.386537,38.563094],"type":"Point"}
}