{
  "type": "Feature",
  "properties": {
    "iso:country":"US",
    "sg:address":"4024 Fountain City Rd",
    "sg:city":"De Soto",
    "sg:classifiers":[
        {
            "category":"Shopping",
            "subcategory":"Bicycles & Sporting Goods",
            "type":"Retail Goods"
        }
    ],
    "sg:phone":"+1 636 586 6379",
    "sg:postcode":"63020",
    "sg:province":"MO",
    "sg:tags":[
        "tackle",
        "fishing"
    ],
    "wof:name":"Bassin' Shack",
    "wof:placetype":"venue"
},
  "geometry": {"coordinates":[-90.532876,38.147046],"type":"Point"}
}