{
  "type": "Feature",
  "properties": {
    "iso:country":"US",
    "sg:address":"201 E Church St",
    "sg:city":"Aurora",
    "sg:classifiers":[
        {
            "category":"Shopping",
            "type":"Retail Goods"
        }
    ],
    "sg:phone":"+1 417 678 6616",
    "sg:postcode":"65605",
    "sg:province":"MO",
    "sg:tags":[
        "merchandise"
    ],
    "wof:name":"Teleworld Communications",
    "wof:placetype":"venue"
},
  "geometry": {"coordinates":[-93.71808299999999,36.970627],"type":"Point"}
}