{
  "type": "Feature",
  "properties": {
    "iso:country":"US",
    "sg:address":"307 S Oak St",
    "sg:city":"California",
    "sg:classifiers":[
        {
            "category":"Shopping",
            "subcategory":"Discount & Variety Stores",
            "type":"Retail Goods"
        }
    ],
    "sg:phone":"+1 573 796 9519",
    "sg:postcode":"65018",
    "sg:province":"MO",
    "sg:tags":[
        "merchandise",
        "general"
    ],
    "wof:name":"Sweet Buy & Buy",
    "wof:placetype":"venue"
},
  "geometry": {"coordinates":[-92.566491,38.630909],"type":"Point"}
}