{
  "type": "Feature",
  "properties": {
    "iso:country":"US",
    "sg:address":"1807 E Seminole St",
    "sg:city":"Springfield",
    "sg:classifiers":[
        {
            "category":"Shopping",
            "subcategory":"Clothing, Apparel, & Fashions",
            "type":"Retail Goods"
        }
    ],
    "sg:phone":"+1 417 882 6327",
    "sg:postcode":"65804",
    "sg:province":"MO",
    "sg:tags":[
        "uniform"
    ],
    "wof:name":"C J's Uniforms Unlimited",
    "wof:placetype":"venue"
},
  "geometry": {"coordinates":[-93.261124,37.174286],"type":"Point"}
}