{
  "type": "Feature",
  "properties": {
    "iso:country":"US",
    "sg:address":"108 S Main Ave",
    "sg:city":"Republic",
    "sg:classifiers":[
        {
            "category":"Professional",
            "type":"Services"
        }
    ],
    "sg:phone":"+1 417 732 6689",
    "sg:postcode":"65738",
    "sg:province":"MO",
    "sg:tags":[
        "establishment"
    ],
    "wof:name":"MRA Inc",
    "wof:placetype":"venue"
},
  "geometry": {"coordinates":[-93.48050000000001,37.11706],"type":"Point"}
}