{
  "type": "Feature",
  "properties": {
    "iso:country":"US",
    "sg:address":"8106 Prospect Ave",
    "sg:city":"Kansas City",
    "sg:classifiers":[
        {
            "category":"Retail",
            "subcategory":"Auto Repair",
            "type":"Services"
        }
    ],
    "sg:phone":"+1 816 333 1187",
    "sg:postcode":"64132",
    "sg:province":"MO",
    "sg:tags":[
        "repairing",
        "automobile"
    ],
    "wof:name":"Brown's Automotive Svc",
    "wof:placetype":"venue"
},
  "geometry": {"coordinates":[-94.557833,38.979719],"type":"Point"}
}