{
  "type": "Feature",
  "properties": {
    "iso:country":"US",
    "sg:address":"130 Edgar Rd",
    "sg:city":"Saint Louis",
    "sg:classifiers":[
        {
            "category":"Arts & Performance",
            "subcategory":"Theater",
            "type":"Entertainment"
        }
    ],
    "sg:phone":"+1 314 968 4925",
    "sg:postcode":"63119",
    "sg:province":"MO",
    "sg:tags":[
        "theatrical"
    ],
    "wof:name":"Loretto Hilton",
    "wof:placetype":"venue"
},
  "geometry": {"coordinates":[-90.344629,38.590031],"type":"Point"}
}