{
  "type": "Feature",
  "properties": {
    "iso:country":"US",
    "sg:address":"293 N Hickman St",
    "sg:city":"Centralia",
    "sg:classifiers":[
        {
            "category":"Farming",
            "subcategory":"Farm & Veterinary Services",
            "type":"Manufacturing & Wholesale Goods"
        }
    ],
    "sg:phone":"+1 573 682 2616",
    "sg:postcode":"65240",
    "sg:province":"MO",
    "sg:tags":[
        "preparation",
        "crop",
        "for",
        "market",
        "supply"
    ],
    "wof:name":"Douglas Seed",
    "wof:placetype":"venue"
},
  "geometry": {"coordinates":[-92.139723,39.21327],"type":"Point"}
}