{
  "type": "Feature",
  "properties": {
    "iso:country":"US",
    "sg:address":"1327 State Hwy 53",
    "sg:city":"Poplar Bluff",
    "sg:classifiers":[
        {
            "category":"Retail",
            "subcategory":"Repair Shop",
            "type":"Services"
        }
    ],
    "sg:phone":"+1 573 686 6366",
    "sg:postcode":"63901",
    "sg:province":"MO",
    "sg:tags":[
        "upholsterer"
    ],
    "wof:name":"Bud's Auto Upholstery",
    "wof:placetype":"venue"
},
  "geometry": {"coordinates":[-90.407326,36.741476],"type":"Point"}
}