{
  "type": "Feature",
  "properties": {
    "iso:country":"US",
    "sg:address":"1690 Carman Mill Dr",
    "sg:city":"Ballwin",
    "sg:classifiers":[
        {
            "category":"Professional",
            "subcategory":"Art Services",
            "type":"Services"
        }
    ],
    "sg:phone":"+1 636 207 9880",
    "sg:postcode":"63021",
    "sg:province":"MO",
    "sg:tags":[
        "graphic",
        "designer"
    ],
    "sg:website":"www.creativeon-line.com",
    "wof:name":"Creative Department",
    "wof:placetype":"venue"
},
  "geometry": {"coordinates":[-90.480159,38.578046],"type":"Point"}
}