{
  "type": "Feature",
  "properties": {
    "iso:country":"US",
    "sg:address":"12741 Weber Hill Rd",
    "sg:city":"Saint Louis",
    "sg:classifiers":[
        {
            "category":"Professional",
            "subcategory":"Business Services",
            "type":"Services"
        }
    ],
    "sg:phone":"+1 314 842 8696",
    "sg:postcode":"63127",
    "sg:province":"MO",
    "wof:name":"Not A Communist Design Inc",
    "wof:placetype":"venue"
},
  "geometry": {"coordinates":[-90.414354,38.529951],"type":"Point"}
}