{
  "type": "Feature",
  "properties": {
    "iso:country":"US",
    "sg:address":"7485 S Hwy 47",
    "sg:city":"Union",
    "sg:phone":"+1 636 583 2960",
    "sg:postcode":"63084",
    "sg:province":"MO",
    "sg:tags":[
        "distributor",
        "oil",
        "marketer"
    ],
    "wof:name":"MFA Propane",
    "wof:placetype":"venue"
},
  "geometry": {"coordinates":[-90.990111,38.427764],"type":"Point"}
}