{
  "type": "Feature",
  "properties": {
    "iso:country":"US",
    "sg:address":"1108 Sunset Ave",
    "sg:city":"Chillicothe",
    "sg:classifiers":[
        {
            "category":"Building & Trades",
            "subcategory":"Plumbing",
            "type":"Services"
        }
    ],
    "sg:phone":"+1 660 646 3794",
    "sg:postcode":"64601",
    "sg:province":"MO",
    "sg:tags":[
        "plumbing",
        "heating",
        "air"
    ],
    "wof:name":"Constant Plumbing Service",
    "wof:placetype":"venue"
},
  "geometry": {"coordinates":[-93.568318,39.797165],"type":"Point"}
}