{
  "type": "Feature",
  "properties": {
    "iso:country":"US",
    "sg:address":"300 E 21 St",
    "sg:city":"Kearney",
    "sg:classifiers":[
        {
            "category":"Wholesale",
            "subcategory":"Machinery & Supplies",
            "type":"Manufacturing & Wholesale Goods"
        },
        {
            "category":"Retail",
            "subcategory":"Car Wash",
            "type":"Services"
        }
    ],
    "sg:phone":"+1 816 628 6688",
    "sg:postcode":"64060",
    "sg:province":"MO",
    "sg:tags":[
        "equipment",
        "industrial",
        "truck",
        "cleaning"
    ],
    "wof:name":"Kearney Mobile Wash Inc",
    "wof:placetype":"venue"
},
  "geometry": {"coordinates":[-94.35924199999999,39.350148],"type":"Point"}
}