{
  "type": "Feature",
  "properties": {
    "iso:country":"US",
    "sg:address":"325 W 40 St",
    "sg:city":"Kansas City",
    "sg:classifiers":[
        {
            "category":"Professional",
            "subcategory":"Art Services",
            "type":"Services"
        }
    ],
    "sg:phone":"+1 816 931 8905",
    "sg:postcode":"64111",
    "sg:province":"MO",
    "sg:tags":[
        "photography",
        "commercial"
    ],
    "wof:name":"Wans Studio Inc",
    "wof:placetype":"venue"
},
  "geometry": {"coordinates":[-94.590659,39.054215],"type":"Point"}
}