{
  "type": "Feature",
  "properties": {
    "iso:country":"US",
    "sg:address":"7831 Woodson Rd",
    "sg:city":"Kansas City",
    "sg:classifiers":[
        {
            "category":"Home & Garden",
            "subcategory":"Furniture",
            "type":"Retail Goods"
        }
    ],
    "sg:phone":"+1 816 353 6650",
    "sg:postcode":"64138",
    "sg:province":"MO",
    "sg:tags":[
        "bed"
    ],
    "wof:name":"Sleep Sound Enterprises",
    "wof:placetype":"venue"
},
  "geometry": {"coordinates":[-94.445566,38.979848],"type":"Point"}
}