{
  "type": "Feature",
  "properties": {
    "iso:country":"US",
    "sg:address":"1640 E Trafficway St",
    "sg:city":"Springfield",
    "sg:classifiers":[
        {
            "category":"Manufacturing",
            "subcategory":"Tools & Machinery",
            "type":"Manufacturing & Wholesale Goods"
        },
        {
            "category":"Wholesale",
            "subcategory":"Electrical",
            "type":"Manufacturing & Wholesale Goods"
        }
    ],
    "sg:phone":"+1 417 865 1626",
    "sg:postcode":"65802",
    "sg:province":"MO",
    "sg:tags":[
        "equipment",
        "electric",
        "motor"
    ],
    "sg:website":"www.iemco.com",
    "wof:name":"Independent Electric McHy Co",
    "wof:placetype":"venue"
},
  "geometry": {"coordinates":[-93.264689,37.210956],"type":"Point"}
}