{
  "type": "Feature",
  "properties": {
    "iso:country":"US",
    "sg:address":"1620 E 8 St",
    "sg:city":"Kansas City",
    "sg:classifiers":[
        {
            "category":"Wholesale",
            "subcategory":"Machinery & Supplies",
            "type":"Manufacturing & Wholesale Goods"
        }
    ],
    "sg:phone":"+1 816 471 6100",
    "sg:postcode":"64106",
    "sg:province":"MO",
    "sg:tags":[
        "machine",
        "equipment",
        "cutting",
        "printing",
        "paper",
        "drilling"
    ],
    "wof:name":"Fosters Services Inc",
    "wof:placetype":"venue"
},
  "geometry": {"coordinates":[-94.561746,39.103874],"type":"Point"}
}