{
  "type": "Feature",
  "properties": {
    "iso:country":"US",
    "sg:address":"5020 Waterman Blvd",
    "sg:city":"Saint Louis",
    "sg:classifiers":[
        {
            "category":"Place Of Worship",
            "subcategory":"Synagogue",
            "type":"Public Place"
        }
    ],
    "sg:phone":"+1 314 361 3919",
    "sg:postcode":"63108",
    "sg:province":"MO",
    "wof:name":"Central Reform Congregation",
    "wof:placetype":"venue"
},
  "geometry": {"coordinates":[-90.264702,38.6483],"type":"Point"}
}