{
  "type": "Feature",
  "properties": {
    "iso:country":"US",
    "sg:address":"18040 Shepard Ridge Rd",
    "sg:city":"Glencoe",
    "sg:classifiers":[
        {
            "category":"Building & Trades",
            "subcategory":"Electrical",
            "type":"Services"
        }
    ],
    "sg:phone":"+1 636 458 8151",
    "sg:postcode":"63038",
    "sg:province":"MO",
    "sg:tags":[
        "electrical",
        "contractor"
    ],
    "wof:name":"Devereaux Electric",
    "wof:placetype":"venue"
},
  "geometry": {"coordinates":[-90.62797999999999,38.619056],"type":"Point"}
}