{
  "type": "Feature",
  "properties": {
    "iso:country":"US",
    "sg:address":"207 W 7th St",
    "sg:city":"Lamar",
    "sg:classifiers":[
        {
            "category":"Education",
            "subcategory":"School",
            "type":"Public Place"
        }
    ],
    "sg:phone":"+1 417 682 2092",
    "sg:postcode":"64759",
    "sg:province":"MO",
    "sg:tags":[
        "academic",
        "special"
    ],
    "wof:name":"Special Education Cooperative",
    "wof:placetype":"venue"
},
  "geometry": {"coordinates":[-94.27874799999999,37.499408],"type":"Point"}
}