{
  "type": "Feature",
  "properties": {
    "iso:country":"US",
    "sg:address":"4509 NE 48 Ter",
    "sg:city":"Kansas City",
    "sg:classifiers":[
        {
            "category":"Professional",
            "subcategory":"Lawyer & Legal Services",
            "type":"Services"
        }
    ],
    "sg:phone":"+1 816 221 5546",
    "sg:postcode":"64119",
    "sg:province":"MO",
    "sg:tags":[
        "firm",
        "law"
    ],
    "wof:name":"Jones & Granger",
    "wof:placetype":"venue"
},
  "geometry": {"coordinates":[-94.526769,39.18265],"type":"Point"}
}