{
  "type": "Feature",
  "properties": {
    "iso:country":"US",
    "sg:address":"12864 Pennridge Dr",
    "sg:city":"Hazelwood",
    "sg:classifiers":[
        {
            "category":"Utilities",
            "subcategory":"Refuse",
            "type":"Services"
        }
    ],
    "sg:phone":"+1 314 739 8338",
    "sg:postcode":"63044",
    "sg:province":"MO",
    "sg:tags":[
        "garbage",
        "collection"
    ],
    "wof:name":"Excel Disposal Inc",
    "wof:placetype":"venue"
},
  "geometry": {"coordinates":[-90.43035399999999,38.764243],"type":"Point"}
}