{
  "type": "Feature",
  "properties": {
    "iso:country":"US",
    "sg:address":"5344 Tholozan Ave",
    "sg:city":"Saint Louis",
    "sg:classifiers":[
        {
            "category":"Landmark",
            "subcategory":"Tourist Information",
            "type":"Public Place"
        }
    ],
    "sg:phone":"+1 314 832 8880",
    "sg:postcode":"63109",
    "sg:province":"MO",
    "sg:tags":[
        "tour"
    ],
    "sg:website":"www.simplycruises.com",
    "wof:name":"Simply Cruises Inc",
    "wof:placetype":"venue"
},
  "geometry": {"coordinates":[-90.282139,38.594508],"type":"Point"}
}