{
  "type": "Feature",
  "properties": {
    "iso:country":"US",
    "sg:address":"1557 Robert Thompson Ln",
    "sg:city":"Festus",
    "sg:classifiers":[
        {
            "category":"Health Services",
            "subcategory":"Podiatrist",
            "type":"Services"
        }
    ],
    "sg:phone":"+1 636 933 4142",
    "sg:postcode":"63028",
    "sg:province":"MO",
    "wof:name":"Mitchell Needleman DPM",
    "wof:placetype":"venue"
},
  "geometry": {"coordinates":[-90.413049,38.211727],"type":"Point"}
}