{
  "type": "Feature",
  "properties": {
    "iso:country":"US",
    "sg:address":"5585 M Hwy",
    "sg:city":"Blackwater",
    "sg:classifiers":[
        {
            "category":"Retail",
            "subcategory":"Auto Repair",
            "type":"Services"
        }
    ],
    "sg:phone":"+1 660 846 3847",
    "sg:postcode":"65322",
    "sg:province":"MO",
    "wof:name":"Bmt Automotive",
    "wof:placetype":"venue"
},
  "geometry": {"coordinates":[-92.949917,38.937799],"type":"Point"}
}