{
  "type": "Feature",
  "properties": {
    "iso:country":"US",
    "sg:address":"26000 E 167th St",
    "sg:city":"Pleasant Hill",
    "sg:classifiers":[
        {
            "category":"Building & Trades",
            "subcategory":"Construction",
            "type":"Services"
        }
    ],
    "sg:phone":"+1 816 540 2078",
    "sg:postcode":"64080",
    "sg:province":"MO",
    "sg:tags":[
        "house"
    ],
    "wof:name":"Michael J Raysik Construction",
    "wof:placetype":"venue"
},
  "geometry": {"coordinates":[-94.27851200000001,38.81335],"type":"Point"}
}