{
  "type": "Feature",
  "properties": {
    "iso:country":"US",
    "sg:address":"3514 Susan Dr",
    "sg:city":"Imperial",
    "sg:classifiers":[
        {
            "category":"Building & Trades",
            "subcategory":"Construction",
            "type":"Services"
        }
    ],
    "sg:phone":"+1 636 942 4006",
    "sg:postcode":"63052",
    "sg:province":"MO",
    "sg:tags":[
        "residential"
    ],
    "wof:name":"New Way Development Inc",
    "wof:placetype":"venue"
},
  "geometry": {"coordinates":[-90.45328499999999,38.380945],"type":"Point"}
}