{
  "type": "Feature",
  "properties": {
    "addr:full":"3837 Vaile Ave Florissant MO 63034",
    "addr:housenumber":"3837",
    "addr:postcode":"63034",
    "addr:street":"Vaile Ave",
    "iso:country":"US",
    "sg:address":"3837 Vaile Ave",
    "sg:city":"Florissant",
    "sg:classifiers":[
        {
            "category":"Insurance",
            "subcategory":"Insurance Agent",
            "type":"Services"
        }
    ],
    "sg:phone":"+1 314 921 6275",
    "sg:postcode":"63034",
    "sg:province":"MO",
    "wof:name":"State Farm Insurance",
    "wof:placetype":"venue"
},
  "geometry": {"coordinates":[-90.308311,38.82631],"type":"Point"}
}