{
  "type": "Feature",
  "properties": {
    "iso:country":"US",
    "sg:address":"12930 Olive Blvd",
    "sg:city":"Creve Coeur",
    "sg:classifiers":[
        {
            "category":"Building & Trades",
            "subcategory":"Plumbing",
            "type":"Services"
        }
    ],
    "sg:phone":"+1 636 391 1090",
    "sg:postcode":"63141",
    "sg:province":"MO",
    "sg:tags":[
        "plumbing",
        "contractor"
    ],
    "wof:name":"Root-A-Way Plumbing Drain",
    "wof:placetype":"venue"
},
  "geometry": {"coordinates":[-90.48039,38.68243],"type":"Point"}
}