{
  "type": "Feature",
  "properties": {
    "iso:country":"US",
    "sg:address":"301 Mid Rivers Mall Dr",
    "sg:city":"St Peters",
    "sg:classifiers":[
        {
            "category":"Retail",
            "subcategory":"Portrait Studio",
            "type":"Services"
        }
    ],
    "sg:phone":"+1 636 926 0967",
    "sg:postcode":"63376",
    "sg:province":"MO",
    "sg:tags":[
        "photographer"
    ],
    "wof:name":"Hammond-Stevens Photography",
    "wof:placetype":"venue"
},
  "geometry": {"coordinates":[-90.62438,38.79199],"type":"Point"}
}