{
  "type": "Feature",
  "properties": {
    "iso:country":"US",
    "sg:address":"123 E Gay St",
    "sg:city":"Warrensburg",
    "sg:classifiers":[
        {
            "category":"Health Services",
            "subcategory":"Hospital",
            "type":"Services"
        },
        {
            "category":"Health Services",
            "subcategory":"Clinic",
            "type":"Services"
        }
    ],
    "sg:phone":"+1 660 747 9242",
    "sg:postcode":"64093",
    "sg:province":"MO",
    "sg:tags":[
        "mental",
        "outpatient",
        "specialty"
    ],
    "wof:name":"Healing Grace Counseling Ctrs",
    "wof:placetype":"venue"
},
  "geometry": {"coordinates":[-93.73980400000001,38.766099],"type":"Point"}
}