{
  "type": "Feature",
  "properties": {
    "iso:country":"US",
    "sg:address":"5246 E Pleasant Valley Ln",
    "sg:city":"Springfield",
    "sg:classifiers":[
        {
            "category":"Building & Trades",
            "subcategory":"Landscaping Services",
            "type":"Services"
        }
    ],
    "sg:phone":"+1 866 467 2416",
    "sg:postcode":"65809",
    "sg:province":"MO",
    "sg:tags":[
        "lawn",
        "snow",
        "maintenance",
        "removal"
    ],
    "wof:name":"Residential Enhancements",
    "wof:placetype":"venue"
},
  "geometry": {"coordinates":[-93.181816,37.175227],"type":"Point"}
}