{
  "type": "Feature",
  "properties": {
    "iso:country":"US",
    "sg:address":"1700 N Benton Ave",
    "sg:city":"Springfield",
    "sg:classifiers":[
        {
            "category":"Arts & Performance",
            "subcategory":"Theater",
            "type":"Entertainment"
        }
    ],
    "sg:phone":"+1 417 869 3790",
    "sg:postcode":"65803",
    "sg:province":"MO",
    "wof:name":"Stained Glass Performing Arts",
    "wof:placetype":"venue"
},
  "geometry": {"coordinates":[-93.28725,37.229479],"type":"Point"}
}