{
  "type": "Feature",
  "properties": {
    "iso:country":"US",
    "sg:address":"1001 Craig Rd",
    "sg:city":"St Louis",
    "sg:classifiers":[
        {
            "category":"Manufacturing",
            "subcategory":"Tools & Machinery",
            "type":"Manufacturing & Wholesale Goods"
        }
    ],
    "sg:phone":"+1 314 432 4300",
    "sg:postcode":"63146",
    "sg:province":"MO",
    "sg:tags":[
        "equipment",
        "processing",
        "datum"
    ],
    "wof:name":"Banc Tec Systems Inc",
    "wof:placetype":"venue"
},
  "geometry": {"coordinates":[-90.43808199999999,38.675243],"type":"Point"}
}