{
  "type": "Feature",
  "properties": {
    "iso:country":"US",
    "sg:address":"18973 Dixon Rd",
    "sg:city":"Licking",
    "sg:classifiers":[
        {
            "category":"Building & Trades",
            "subcategory":"Construction",
            "type":"Services"
        }
    ],
    "sg:phone":"+1 573 674 4410",
    "sg:postcode":"65542",
    "sg:province":"MO",
    "sg:tags":[
        "tile",
        "floor",
        "laying",
        "dealer",
        "contractor"
    ],
    "wof:name":"M & M Installations",
    "wof:placetype":"venue"
},
  "geometry": {"coordinates":[-91.837807,37.424929],"type":"Point"}
}