{
  "type": "Feature",
  "properties": {
    "iso:country":"US",
    "sg:address":"715 Goddard Ave",
    "sg:city":"Chesterfield",
    "sg:classifiers":[
        {
            "category":"Shopping",
            "type":"Retail Goods"
        }
    ],
    "sg:phone":"+1 636 530 1320",
    "sg:postcode":"63005",
    "sg:province":"MO",
    "sg:tags":[
        "equipment",
        "telephone",
        "supply"
    ],
    "sg:website":"www.cmsc.com",
    "wof:name":"CMS Communications",
    "wof:placetype":"venue"
},
  "geometry": {"coordinates":[-90.635233,38.667766],"type":"Point"}
}