{
  "type": "Feature",
  "properties": {
    "iso:country":"US",
    "sg:address":"1205 Old Jefferson City Rd",
    "sg:city":"Fulton",
    "sg:classifiers":[
        {
            "category":"Shopping",
            "subcategory":"Used Merchandise",
            "type":"Retail Goods"
        }
    ],
    "sg:phone":"+1 573 642 1717",
    "sg:postcode":"65251",
    "sg:province":"MO",
    "sg:tags":[
        "antique"
    ],
    "wof:name":"Granny's Attic",
    "wof:placetype":"venue"
},
  "geometry": {"coordinates":[-91.970568,38.83375],"type":"Point"}
}