{
  "type": "Feature",
  "properties": {
    "iso:country":"US",
    "sg:address":"107 W Main St",
    "sg:city":"Atlanta",
    "sg:classifiers":[
        {
            "category":"Government",
            "subcategory":"Fire Station",
            "type":"Public Place"
        }
    ],
    "sg:phone":"+1 660 239 4270",
    "sg:postcode":"63530",
    "sg:province":"MO",
    "sg:tags":[
        "department",
        "protection"
    ],
    "wof:name":"Atlanta Volunteer Fire Dept",
    "wof:placetype":"venue"
},
  "geometry": {"coordinates":[-92.479449,39.898602],"type":"Point"}
}