{
  "type": "Feature",
  "properties": {
    "iso:country":"US",
    "sg:address":"25 Foreway Dr",
    "sg:city":"St Louis",
    "sg:classifiers":[
        {
            "category":"Health Services",
            "subcategory":"Doctor",
            "type":"Services"
        }
    ],
    "sg:phone":"+1 314 567 1306",
    "sg:postcode":"63124",
    "sg:province":"MO",
    "sg:tags":[
        "physician",
        "surgeon"
    ],
    "wof:name":"Cardiothoracic & Anesthesia",
    "wof:placetype":"venue"
},
  "geometry": {"coordinates":[-90.377195,38.646979],"type":"Point"}
}