{
  "type": "Feature",
  "properties": {
    "iso:country":"US",
    "sg:address":"112 N Orange St",
    "sg:city":"Brunswick",
    "sg:classifiers":[
        {
            "category":"Social Services",
            "subcategory":"Child Care",
            "type":"Services"
        }
    ],
    "sg:phone":"+1 660 548 3676",
    "sg:postcode":"65236",
    "sg:province":"MO",
    "wof:name":"Little Lambs Daycare & Fun Ctr",
    "wof:placetype":"venue"
},
  "geometry": {"coordinates":[-93.122057,39.422729],"type":"Point"}
}