{
  "type": "Feature",
  "properties": {
    "iso:country":"US",
    "sg:address":"3851 Indiana Ave",
    "sg:city":"Kansas City",
    "sg:classifiers":[
        {
            "category":"Retail",
            "subcategory":"Laundry & Dry Cleaning",
            "type":"Services"
        }
    ],
    "sg:phone":"+1 816 921 6766",
    "sg:postcode":"64128",
    "sg:province":"MO",
    "sg:tags":[
        "drycleaning",
        "plant",
        "cleaners"
    ],
    "wof:name":"Brenda's Thriftway Cleaners",
    "wof:placetype":"venue"
},
  "geometry": {"coordinates":[-94.54426100000001,39.056036],"type":"Point"}
}