{
  "type": "Feature",
  "properties": {
    "iso:country":"US",
    "sg:address":"770 Admiral Blvd",
    "sg:city":"Kansas City",
    "sg:classifiers":[
        {
            "category":"Travel",
            "subcategory":"Hotels & Motels",
            "type":"Entertainment"
        }
    ],
    "sg:phone":"+1 816 587 4422",
    "sg:postcode":"64106",
    "sg:province":"MO",
    "wof:name":"Comfort Inn",
    "wof:placetype":"venue"
},
  "geometry": {"coordinates":[-94.574664,39.105239],"type":"Point"}
}