{
  "type": "Feature",
  "properties": {
    "iso:country":"US",
    "sg:address":"109 Watson Dr",
    "sg:city":"Malden",
    "sg:classifiers":[
        {
            "category":"Government",
            "subcategory":"Office",
            "type":"Public Place"
        }
    ],
    "sg:phone":"+1 573 276 3706",
    "sg:postcode":"63863",
    "sg:province":"MO",
    "sg:tags":[
        "government-united",
        "state"
    ],
    "wof:name":"Housing Authority City Of Malden",
    "wof:placetype":"venue"
},
  "geometry": {"coordinates":[-89.973826,36.600332],"type":"Point"}
}