{
  "type": "Feature",
  "properties": {
    "iso:country":"US",
    "sg:address":"1756 NW Chipman Rd",
    "sg:city":"Lees Summit",
    "sg:classifiers":[
        {
            "category":"Personal",
            "type":"Services"
        }
    ],
    "sg:phone":"+1 816 246 6458",
    "sg:postcode":"64081",
    "sg:province":"MO",
    "sg:tags":[
        "ear",
        "piercing"
    ],
    "wof:name":"Claire's",
    "wof:placetype":"venue"
},
  "geometry": {"coordinates":[-94.409504,38.926233],"type":"Point"}
}