{
  "type": "Feature",
  "properties": {
    "iso:country":"US",
    "sg:address":"4234 Shenandoah Ave",
    "sg:city":"St Louis",
    "sg:classifiers":[
        {
            "category":"Professional",
            "subcategory":"Art Services",
            "type":"Services"
        }
    ],
    "sg:phone":"+1 314 496 1883",
    "sg:postcode":"63110",
    "sg:province":"MO",
    "sg:tags":[
        "photographer"
    ],
    "sg:website":"www.beautifulmessphoto.com",
    "wof:name":"Beautiful Mess Photography",
    "wof:placetype":"venue"
},
  "geometry": {"coordinates":[-90.255641,38.610739],"type":"Point"}
}