{
  "type": "Feature",
  "properties": {
    "iso:country":"US",
    "sg:address":"205 W Normal St",
    "sg:city":"Iberia",
    "sg:classifiers":[
        {
            "category":"Organizations",
            "subcategory":"Religious Organization",
            "type":"Services"
        }
    ],
    "sg:phone":"+1 573 793 6415",
    "sg:postcode":"65486",
    "sg:province":"MO",
    "sg:tags":[
        "church"
    ],
    "wof:name":"First Christian Church",
    "wof:placetype":"venue"
},
  "geometry": {"coordinates":[-92.296423,38.09035],"type":"Point"}
}