{
  "type": "Feature",
  "properties": {
    "iso:country":"US",
    "sg:address":"1119 London Dr",
    "sg:city":"Columbia",
    "sg:classifiers":[
        {
            "category":"Building & Trades",
            "subcategory":"Landscaping Services",
            "type":"Services"
        }
    ],
    "sg:phone":"+1 573 442 8733",
    "sg:postcode":"65203",
    "sg:province":"MO",
    "sg:tags":[
        "arborist"
    ],
    "sg:website":"http://www.midwesttreesolutions.com",
    "wof:name":"Midwest Tree Solutions",
    "wof:placetype":"venue"
},
  "geometry": {"coordinates":[-92.35380499999999,38.962234],"type":"Point"}
}