{
  "type": "Feature",
  "properties": {
    "iso:country":"US",
    "sg:address":"5609 Independence Rd",
    "sg:city":"Saint Charles",
    "sg:classifiers":[
        {
            "category":"Building & Trades",
            "subcategory":"Construction",
            "type":"Services"
        }
    ],
    "sg:phone":"+1 314 280 1249",
    "sg:postcode":"63304",
    "sg:province":"MO",
    "sg:tags":[
        "nonresidential"
    ],
    "wof:name":"Missouri Outdoors Contg LLC",
    "wof:placetype":"venue"
},
  "geometry": {"coordinates":[-90.653178,38.714884],"type":"Point"}
}