{
  "type": "Feature",
  "properties": {
    "iso:country":"US",
    "sg:address":"160 S Main St",
    "sg:city":"Ste Genevieve",
    "sg:classifiers":[
        {
            "category":"Organizations",
            "subcategory":"Religious Organization",
            "type":"Services"
        }
    ],
    "sg:phone":"+1 573 883 3272",
    "sg:postcode":"63670",
    "sg:province":"MO",
    "sg:tags":[
        "church"
    ],
    "wof:name":"First Presbyterian Church",
    "wof:placetype":"venue"
},
  "geometry": {"coordinates":[-90.042835,37.978349],"type":"Point"}
}