{
  "type": "Feature",
  "properties": {
    "iso:country":"US",
    "sg:address":"1520 S Vandeventer Ave",
    "sg:city":"St Louis",
    "sg:classifiers":[
        {
            "category":"Manufacturing",
            "subcategory":"Tools & Machinery",
            "type":"Manufacturing & Wholesale Goods"
        }
    ],
    "sg:phone":"+1 314 772 4002",
    "sg:postcode":"63110",
    "sg:province":"MO",
    "sg:tags":[
        "compressor"
    ],
    "wof:name":"Worldwide Supply Corp",
    "wof:placetype":"venue"
},
  "geometry": {"coordinates":[-90.25603700000001,38.621827],"type":"Point"}
}