{
  "type": "Feature",
  "properties": {
    "iso:country":"US",
    "sg:address":"671 Meadow Ln",
    "sg:city":"Branson",
    "sg:classifiers":[
        {
            "category":"Building & Trades",
            "subcategory":"Plumbing",
            "type":"Services"
        }
    ],
    "sg:phone":"+1 417 334 2429",
    "sg:postcode":"65616",
    "sg:province":"MO",
    "sg:tags":[
        "plumber",
        "industrial",
        "contractors-commercial"
    ],
    "wof:name":"Stig's Plumbing",
    "wof:placetype":"venue"
},
  "geometry": {"coordinates":[-93.20703399999999,36.684092],"type":"Point"}
}