{
  "type": "Feature",
  "properties": {
    "iso:country":"US",
    "sg:address":"14651 Mallard Lake Dr",
    "sg:city":"Chesterfield",
    "sg:classifiers":[
        {
            "category":"Professional",
            "type":"Services"
        }
    ],
    "sg:phone":"+1 636 519 9645",
    "sg:postcode":"63017",
    "sg:province":"MO",
    "wof:name":"Robert M Andersen",
    "wof:placetype":"venue"
},
  "geometry": {"coordinates":[-90.52919900000001,38.642305],"type":"Point"}
}