{
  "type": "Feature",
  "properties": {
    "iso:country":"US",
    "sg:address":"3413 Auburn Dr",
    "sg:city":"Saint Joseph",
    "sg:classifiers":[
        {
            "category":"Building & Trades",
            "subcategory":"Construction",
            "type":"Services"
        }
    ],
    "sg:phone":"+1 816 232 3520",
    "sg:postcode":"64506",
    "sg:province":"MO",
    "sg:tags":[
        "cleaning",
        "contractor"
    ],
    "wof:name":"Swails Floor Care & Clng",
    "wof:placetype":"venue"
},
  "geometry": {"coordinates":[-94.807517,39.786921],"type":"Point"}
}