{
  "type": "Feature",
  "properties": {
    "iso:country":"US",
    "sg:address":"3350 Parker Spr",
    "sg:city":"Florissant",
    "sg:classifiers":[
        {
            "category":"Home & Garden",
            "subcategory":"Household Appliances",
            "type":"Retail Goods"
        },
        {
            "category":"Retail",
            "subcategory":"Repair Shop",
            "type":"Services"
        }
    ],
    "sg:phone":"+1 314 837 2723",
    "sg:postcode":"63033",
    "sg:province":"MO",
    "sg:tags":[
        "electric"
    ],
    "wof:name":"Keeven Appliance Co",
    "wof:placetype":"venue"
},
  "geometry": {"coordinates":[-90.28992700000001,38.795267],"type":"Point"}
}