{
  "type": "Feature",
  "properties": {
    "iso:country":"US",
    "sg:address":"1919 S Pin Oak Dr",
    "sg:city":"Springfield",
    "sg:classifiers":[
        {
            "category":"Building & Trades",
            "subcategory":"Construction",
            "type":"Services"
        }
    ],
    "sg:phone":"+1 417 882 2453",
    "sg:postcode":"65809",
    "sg:province":"MO",
    "sg:tags":[
        "residential",
        "home"
    ],
    "wof:name":"R W Maclachlan Company Inc",
    "wof:placetype":"venue"
},
  "geometry": {"coordinates":[-93.194519,37.179379],"type":"Point"}
}