{
  "type": "Feature",
  "properties": {
    "iso:country":"US",
    "sg:address":"130 Gravois Bluffs Cir",
    "sg:city":"Fenton",
    "sg:classifiers":[
        {
            "category":"Restaurant",
            "type":"Food & Drink"
        }
    ],
    "sg:menulink":"http://www.allmenus.com/mo/bonhomme/8701-red-robin/menu/",
    "sg:phone":"+1 636 305 9440",
    "sg:postcode":"63026",
    "sg:province":"MO",
    "sg:tags":[
        "american"
    ],
    "wof:name":"Red Robin",
    "wof:placetype":"venue"
},
  "geometry": {"coordinates":[-90.44533699999999,38.504999],"type":"Point"}
}