{
  "type": "Feature",
  "properties": {
    "iso:country":"US",
    "sg:address":"3300 Lake Bend Dr",
    "sg:city":"Valley Park",
    "sg:classifiers":[
        {
            "category":"Social Services",
            "subcategory":"Adult Care",
            "type":"Services"
        }
    ],
    "sg:phone":"+1 636 861 3200",
    "sg:postcode":"63088",
    "sg:province":"MO",
    "sg:tags":[
        "residential"
    ],
    "sg:website":"www.standrews1.com",
    "wof:name":"Cape Albeon",
    "wof:placetype":"venue"
},
  "geometry": {"coordinates":[-90.480577,38.563686],"type":"Point"}
}