{
  "type": "Feature",
  "properties": {
    "iso:country":"US",
    "sg:address":"412 SW Wintergarden Dr",
    "sg:city":"Lees Summit",
    "sg:classifiers":[
        {
            "category":"Wholesale",
            "subcategory":"Machinery & Supplies",
            "type":"Manufacturing & Wholesale Goods"
        }
    ],
    "sg:phone":"+1 816 525 5811",
    "sg:postcode":"64081",
    "sg:province":"MO",
    "sg:tags":[
        "equipment",
        "industrial"
    ],
    "wof:name":"Sugino Corp",
    "wof:placetype":"venue"
},
  "geometry": {"coordinates":[-94.436358,38.910115],"type":"Point"}
}