{
  "type": "Feature",
  "properties": {
    "iso:country":"US",
    "sg:address":"509 W Rollins St",
    "sg:city":"Moberly",
    "sg:classifiers":[
        {
            "category":"Banks & Credit Unions",
            "subcategory":"Bank",
            "type":"Services"
        }
    ],
    "sg:phone":"+1 660 263 9494",
    "sg:postcode":"65270",
    "sg:province":"MO",
    "sg:tags":[
        "loan"
    ],
    "wof:name":"Community Capital Funding",
    "wof:placetype":"venue"
},
  "geometry": {"coordinates":[-92.44219099999999,39.418838],"type":"Point"}
}