{
  "type": "Feature",
  "properties": {
    "iso:country":"US",
    "sg:address":"648 S Scenic Ave",
    "sg:city":"Springfield",
    "sg:classifiers":[
        {
            "category":"Food & Beverages",
            "subcategory":"Liquor & Beverages",
            "type":"Retail Goods"
        }
    ],
    "sg:phone":"+1 417 873 9040",
    "sg:postcode":"65802",
    "sg:province":"MO",
    "sg:tags":[
        "alcoholic"
    ],
    "wof:name":"ABC Spirits 4",
    "wof:placetype":"venue"
},
  "geometry": {"coordinates":[-93.33073,37.20379],"type":"Point"}
}