{
  "type": "Feature",
  "properties": {
    "iso:country":"US",
    "sg:address":"1200 N Kingshighway St",
    "sg:city":"Cape Girardeau",
    "sg:classifiers":[
        {
            "category":"Wholesale",
            "subcategory":"Groceries",
            "type":"Manufacturing & Wholesale Goods"
        }
    ],
    "sg:phone":"+1 573 335 5900",
    "sg:postcode":"63701",
    "sg:province":"MO",
    "sg:tags":[
        "food",
        "broker"
    ],
    "wof:name":"Sell Group",
    "wof:placetype":"venue"
},
  "geometry": {"coordinates":[-89.559693,37.322987],"type":"Point"}
}