{
  "type": "Feature",
  "properties": {
    "iso:country":"US",
    "sg:address":"1630 S 2nd St",
    "sg:city":"Saint Louis",
    "sg:classifiers":[
        {
            "category":"Wholesale",
            "subcategory":"Furniture",
            "type":"Manufacturing & Wholesale Goods"
        }
    ],
    "sg:phone":"+1 314 421 1630",
    "sg:postcode":"63104",
    "sg:province":"MO",
    "sg:tags":[
        "equipment"
    ],
    "wof:name":"R C Distributing",
    "wof:placetype":"venue"
},
  "geometry": {"coordinates":[-90.19699900000001,38.608501],"type":"Point"}
}