{
  "type": "Feature",
  "properties": {
    "iso:country":"US",
    "sg:address":"200 N Railroad",
    "sg:city":"Matthews",
    "sg:classifiers":[
        {
            "category":"Manufacturing",
            "subcategory":"Textiles",
            "type":"Manufacturing & Wholesale Goods"
        }
    ],
    "sg:phone":"+1 573 471 0269",
    "sg:postcode":"63867",
    "sg:province":"MO",
    "sg:tags":[
        "gin",
        "cotton"
    ],
    "wof:name":"Bootheel Cotton Company",
    "wof:placetype":"venue"
},
  "geometry": {"coordinates":[-89.58532700000001,36.760921],"type":"Point"}
}