{
  "type": "Feature",
  "properties": {
    "iso:country":"US",
    "sg:address":"6326 Waterman Ave",
    "sg:city":"Saint Louis",
    "sg:classifiers":[
        {
            "category":"Professional",
            "subcategory":"Management & Consulting",
            "type":"Services"
        }
    ],
    "sg:phone":"+1 314 727 9351",
    "sg:postcode":"63130",
    "sg:province":"MO",
    "wof:name":"Laurel Management Company",
    "wof:placetype":"venue"
},
  "geometry": {"coordinates":[-90.304964,38.652313],"type":"Point"}
}