{
  "type": "Feature",
  "properties": {
    "iso:country":"US",
    "sg:address":"2222 Hollis Dr",
    "sg:city":"Saint Louis",
    "sg:classifiers":[
        {
            "category":"Health Services",
            "subcategory":"Clinic",
            "type":"Services"
        }
    ],
    "sg:phone":"+1 314 867 9280",
    "sg:postcode":"63136",
    "sg:province":"MO",
    "sg:tags":[
        "home",
        "care"
    ],
    "wof:name":"Charity In Home Hlth Care Agcy",
    "wof:placetype":"venue"
},
  "geometry": {"coordinates":[-90.247705,38.746178],"type":"Point"}
}