{
  "type": "Feature",
  "properties": {
    "iso:country":"US",
    "sg:address":"3710 W Broadway",
    "sg:city":"Columbia",
    "sg:classifiers":[
        {
            "category":"Organizations",
            "subcategory":"Religious Organization",
            "type":"Services"
        }
    ],
    "sg:phone":"+1 573 446 2300",
    "sg:postcode":"65203",
    "sg:province":"MO",
    "sg:tags":[
        "place",
        "worship",
        "church"
    ],
    "wof:name":"Benedictine Sisters",
    "wof:placetype":"venue"
},
  "geometry": {"coordinates":[-92.389627,38.955552],"type":"Point"}
}