{
  "type": "Feature",
  "properties": {
    "iso:country":"US",
    "sg:address":"1257 Park Ln",
    "sg:city":"Liberty",
    "sg:classifiers":[
        {
            "category":"Professional",
            "subcategory":"Computer Services",
            "type":"Services"
        }
    ],
    "sg:phone":"+1 816 781 1825",
    "sg:postcode":"64068",
    "sg:province":"MO",
    "sg:tags":[
        "programing",
        "custom"
    ],
    "wof:name":"Payload Computer Services",
    "wof:placetype":"venue"
},
  "geometry": {"coordinates":[-94.44286,39.232624],"type":"Point"}
}