{
  "type": "Feature",
  "properties": {
    "iso:country":"US",
    "sg:address":"3120 W Clay St",
    "sg:city":"St Charles",
    "sg:classifiers":[
        {
            "category":"Personal",
            "subcategory":"Beauty Salon",
            "type":"Services"
        }
    ],
    "sg:phone":"+1 636 940 2150",
    "sg:postcode":"63301",
    "sg:province":"MO",
    "sg:tags":[
        "shop",
        "manicuring"
    ],
    "wof:name":"Nails-4-U",
    "wof:placetype":"venue"
},
  "geometry": {"coordinates":[-90.538696,38.788075],"type":"Point"}
}