{
  "type": "Feature",
  "properties": {
    "iso:country":"US",
    "sg:address":"6300 Knox Industrial Dr",
    "sg:city":"Saint Louis",
    "sg:classifiers":[
        {
            "category":"Wholesale",
            "subcategory":"Construction Materials",
            "type":"Manufacturing & Wholesale Goods"
        }
    ],
    "sg:phone":"+1 314 644 2225",
    "sg:postcode":"63139",
    "sg:province":"MO",
    "sg:tags":[
        "equipment",
        "roofing",
        "supply"
    ],
    "wof:name":"Spec Roofing Contractors Sup",
    "wof:placetype":"venue"
},
  "geometry": {"coordinates":[-90.293295,38.620011],"type":"Point"}
}