{
  "type": "Feature",
  "properties": {
    "iso:country":"US",
    "sg:address":"2136 E Langston St",
    "sg:city":"Springfield",
    "sg:classifiers":[
        {
            "category":"Insurance",
            "subcategory":"Health Insurance",
            "type":"Services"
        }
    ],
    "sg:phone":"+1 417 883 4205",
    "sg:postcode":"65804",
    "sg:province":"MO",
    "sg:tags":[
        "carrier"
    ],
    "wof:name":"Health Insurance Brokers",
    "wof:placetype":"venue"
},
  "geometry": {"coordinates":[-93.250664,37.176947],"type":"Point"}
}