{
  "type": "Feature",
  "properties": {
    "iso:country":"US",
    "sg:address":"3031 Frontage Rd",
    "sg:city":"Independence",
    "sg:classifiers":[
        {
            "category":"Banks & Credit Unions",
            "subcategory":"Bank",
            "type":"Services"
        }
    ],
    "sg:phone":"+1 816 478 2040",
    "sg:postcode":"64057",
    "sg:province":"MO",
    "sg:tags":[
        "loan",
        "real estate"
    ],
    "wof:name":"Home Smartz Mortgage",
    "wof:placetype":"venue"
},
  "geometry": {"coordinates":[-94.37408499999999,39.063379],"type":"Point"}
}