{
  "type": "Feature",
  "properties": {
    "iso:country":"US",
    "sg:address":"12315 Missile Ln",
    "sg:city":"Florissant",
    "sg:classifiers":[
        {
            "category":"Professional",
            "subcategory":"Lawyer & Legal Services",
            "type":"Services"
        }
    ],
    "sg:phone":"+1 314 741 8856",
    "sg:postcode":"63033",
    "sg:province":"MO",
    "sg:tags":[
        "attorney",
        "practice"
    ],
    "wof:name":"Louis Virdure",
    "wof:placetype":"venue"
},
  "geometry": {"coordinates":[-90.244489,38.799056],"type":"Point"}
}