{
  "type": "Feature",
  "properties": {
    "iso:country":"US",
    "sg:address":"2638 Lynch St",
    "sg:city":"St Louis",
    "sg:classifiers":[
        {
            "category":"Building & Trades",
            "subcategory":"Construction",
            "type":"Services"
        }
    ],
    "sg:phone":"+1 314 664 7679",
    "sg:postcode":"63118",
    "sg:province":"MO",
    "sg:tags":[
        "home",
        "window",
        "remodeling",
        "family",
        "replacement"
    ],
    "wof:name":"Excel Contracting Co",
    "wof:placetype":"venue"
},
  "geometry": {"coordinates":[-90.225343,38.603934],"type":"Point"}
}