{
  "type": "Feature",
  "properties": {
    "iso:country":"US",
    "sg:address":"8649 W Farm Rd 112",
    "sg:city":"Willard",
    "sg:classifiers":[
        {
            "category":"Health Services",
            "subcategory":"Clinic",
            "type":"Services"
        }
    ],
    "sg:phone":"+1 417 742 4298",
    "sg:postcode":"65781",
    "sg:province":"MO",
    "wof:name":"Preferred Independent Svc Inc",
    "wof:placetype":"venue"
},
  "geometry": {"coordinates":[-93.465902,37.250155],"type":"Point"}
}