{
  "type": "Feature",
  "properties": {
    "iso:country":"US",
    "sg:address":"1601 E Republic Rd",
    "sg:city":"Springfield",
    "sg:classifiers":[
        {
            "category":"Professional",
            "subcategory":"Advertising",
            "type":"Services"
        }
    ],
    "sg:phone":"+1 417 889 0772",
    "sg:postcode":"65804",
    "sg:province":"MO",
    "sg:tags":[
        "advertising-promotional",
        "product"
    ],
    "sg:website":"www.gopromoter.com",
    "wof:name":"Promoter Advertising Products",
    "wof:placetype":"venue"
},
  "geometry": {"coordinates":[-93.267219,37.137422],"type":"Point"}
}