{
  "type": "Feature",
  "properties": {
    "iso:country":"US",
    "sg:address":"3200 Miller St",
    "sg:city":"Bethany",
    "sg:classifiers":[
        {
            "category":"Banks & Credit Unions",
            "subcategory":"Bank",
            "type":"Services"
        }
    ],
    "sg:phone":"+1 660 425 2315",
    "sg:postcode":"64424",
    "sg:province":"MO",
    "wof:name":"Bank Northwest",
    "wof:placetype":"venue"
},
  "geometry": {"coordinates":[-94.020481,40.265168],"type":"Point"}
}