{
  "type": "Feature",
  "properties": {
    "iso:country":"US",
    "sg:address":"11787 Gamel Cemetery Rd",
    "sg:city":"Festus",
    "sg:classifiers":[
        {
            "category":"Insurance",
            "subcategory":"Insurance Agent",
            "type":"Services"
        }
    ],
    "sg:phone":"+1 636 931 3500",
    "sg:postcode":"63028",
    "sg:province":"MO",
    "sg:tags":[
        "business"
    ],
    "wof:name":"ACS Investigative Services",
    "wof:placetype":"venue"
},
  "geometry": {"coordinates":[-90.41473999999999,38.195869],"type":"Point"}
}