{
  "type": "Feature",
  "properties": {
    "iso:country":"US",
    "sg:address":"7605 NW 79 Pl",
    "sg:city":"Kansas City",
    "sg:classifiers":[
        {
            "category":"Building & Trades",
            "subcategory":"Construction",
            "type":"Services"
        }
    ],
    "sg:phone":"+1 816 746 0583",
    "sg:postcode":"64152",
    "sg:province":"MO",
    "sg:tags":[
        "siding",
        "contractor",
        "carpentry"
    ],
    "wof:name":"Heartland Construction & Mtls",
    "wof:placetype":"venue"
},
  "geometry": {"coordinates":[-94.67050999999999,39.239193],"type":"Point"}
}