{
  "type": "Feature",
  "properties": {
    "iso:country":"US",
    "sg:address":"306 Main St",
    "sg:city":"Noel",
    "sg:classifiers":[
        {
            "category":"Autos & Motor Vehicles",
            "subcategory":"Auto Supplies",
            "type":"Retail Goods"
        }
    ],
    "sg:phone":"+1 417 475 3155",
    "sg:postcode":"64854",
    "sg:province":"MO",
    "sg:tags":[
        "automobile",
        "parts"
    ],
    "wof:name":"O'REILLY Auto Parts",
    "wof:placetype":"venue"
},
  "geometry": {"coordinates":[-94.48577400000001,36.545292],"type":"Point"}
}