{
  "type": "Feature",
  "properties": {
    "iso:country":"US",
    "sg:address":"14020 Manchester Rd",
    "sg:city":"Ballwin",
    "sg:classifiers":[
        {
            "category":"Retail",
            "subcategory":"Veterinary Services",
            "type":"Services"
        }
    ],
    "sg:phone":"+1 636 256 7387",
    "sg:postcode":"63011",
    "sg:province":"MO",
    "sg:tags":[
        "pet",
        "grooming",
        "veterinarian"
    ],
    "sg:website":"http://www.countyanimalhosp.com",
    "wof:name":"County Animal Hospital",
    "wof:placetype":"venue"
},
  "geometry": {"coordinates":[-90.492589,38.595057],"type":"Point"}
}