{
  "type": "Feature",
  "properties": {
    "iso:country":"US",
    "sg:address":"401 Saint Louis Ave",
    "sg:city":"Fulton",
    "sg:classifiers":[
        {
            "category":"Organizations",
            "subcategory":"Religious Organization",
            "type":"Services"
        }
    ],
    "sg:phone":"+1 573 642 4614",
    "sg:postcode":"65251",
    "sg:province":"MO",
    "wof:name":"Second Christian Church",
    "wof:placetype":"venue"
},
  "geometry": {"coordinates":[-91.943117,38.852337],"type":"Point"}
}