{
  "type": "Feature",
  "properties": {
    "iso:country":"US",
    "sg:address":"4600 NE Vivion Rd",
    "sg:city":"Kansas City",
    "sg:classifiers":[
        {
            "category":"Autos & Motor Vehicles",
            "subcategory":"Auto Supplies",
            "type":"Retail Goods"
        }
    ],
    "sg:phone":"+1 816 452 6899",
    "sg:postcode":"64119",
    "sg:province":"MO",
    "sg:tags":[
        "automobile",
        "parts"
    ],
    "sg:website":"www.oreilly.com",
    "wof:name":"O'REILLY Auto Parts",
    "wof:placetype":"venue"
},
  "geometry": {"coordinates":[-94.525104,39.188068],"type":"Point"}
}