{
  "type": "Feature",
  "properties": {
    "iso:country":"US",
    "sg:address":"11326 Saint Charles Rock Rd",
    "sg:city":"Bridgeton",
    "sg:classifiers":[
        {
            "category":"Building & Trades",
            "subcategory":"Electrical",
            "type":"Services"
        }
    ],
    "sg:phone":"+1 314 770 2541",
    "sg:postcode":"63044",
    "sg:province":"MO",
    "sg:tags":[
        "electrical",
        "electric",
        "contractor"
    ],
    "wof:name":"Joseph Brothers Electric Co",
    "wof:placetype":"venue"
},
  "geometry": {"coordinates":[-90.403395,38.74011],"type":"Point"}
}