{
  "type": "Feature",
  "properties": {
    "iso:country":"US",
    "sg:address":"206 W Main St",
    "sg:city":"Cole Camp",
    "sg:classifiers":[
        {
            "category":"Insurance",
            "subcategory":"Insurance Agent",
            "type":"Services"
        }
    ],
    "sg:phone":"+1 660 668 2445",
    "sg:postcode":"65325",
    "sg:province":"MO",
    "wof:name":"Farmers Mutual Insurance Co",
    "wof:placetype":"venue"
},
  "geometry": {"coordinates":[-93.206157,38.460417],"type":"Point"}
}