{
  "type": "Feature",
  "properties": {
    "iso:country":"US",
    "sg:address":"4374 Victoria Rd",
    "sg:city":"Festus",
    "sg:classifiers":[
        {
            "category":"Retail",
            "subcategory":"Repair Shop",
            "type":"Services"
        }
    ],
    "sg:phone":"+1 636 337 7995",
    "sg:postcode":"63028",
    "sg:province":"MO",
    "sg:tags":[
        "welding"
    ],
    "wof:name":"Round Boys Welding",
    "wof:placetype":"venue"
},
  "geometry": {"coordinates":[-90.51300999999999,38.16982],"type":"Point"}
}