{
  "type": "Feature",
  "properties": {
    "iso:country":"US",
    "sg:address":"1214 Grant Dr",
    "sg:city":"Saint Louis",
    "sg:classifiers":[
        {
            "category":"Utilities",
            "subcategory":"Mobile Phone",
            "type":"Services"
        }
    ],
    "sg:phone":"+1 636 998 0104",
    "sg:postcode":"63132",
    "sg:province":"MO",
    "sg:tags":[
        "communication",
        "radiotelephone"
    ],
    "wof:name":"Dtg Enterprises",
    "wof:placetype":"venue"
},
  "geometry": {"coordinates":[-90.349991,38.673844],"type":"Point"}
}