{
  "type": "Feature",
  "properties": {
    "iso:country":"US",
    "sg:address":"217 B Ave",
    "sg:city":"Goodman",
    "sg:classifiers":[
        {
            "category":"Retail",
            "subcategory":"Auto Repair",
            "type":"Services"
        }
    ],
    "sg:phone":"+1 417 364 7010",
    "sg:postcode":"64843",
    "sg:province":"MO",
    "sg:tags":[
        "general"
    ],
    "wof:name":"D & D Auto & Muffler",
    "wof:placetype":"venue"
},
  "geometry": {"coordinates":[-94.412785,36.737716],"type":"Point"}
}