{
  "type": "Feature",
  "properties": {
    "iso:country":"US",
    "sg:address":"9499 Johnson Dr",
    "sg:city":"Odessa",
    "sg:classifiers":[
        {
            "category":"Professional",
            "subcategory":"Business Services",
            "type":"Services"
        }
    ],
    "sg:phone":"+1 816 633 7200",
    "sg:postcode":"64076",
    "sg:province":"MO",
    "wof:name":"Sharp Enterprise Services",
    "wof:placetype":"venue"
},
  "geometry": {"coordinates":[-93.939252,39.057404],"type":"Point"}
}