{
  "type": "Feature",
  "properties": {
    "iso:country":"US",
    "sg:address":"605 N Central City Rd",
    "sg:city":"Joplin",
    "sg:classifiers":[
        {
            "category":"Autos & Motor Vehicles",
            "subcategory":"Automobile Sales",
            "type":"Retail Goods"
        }
    ],
    "sg:phone":"+1 417 782 6944",
    "sg:postcode":"64801",
    "sg:province":"MO",
    "sg:tags":[
        "car",
        "dealer"
    ],
    "wof:name":"Central City Auto Sales",
    "wof:placetype":"venue"
},
  "geometry": {"coordinates":[-94.583107,37.093056],"type":"Point"}
}