{
  "type": "Feature",
  "properties": {
    "iso:country":"US",
    "sg:address":"900 Bybrook Dr",
    "sg:city":"Fenton",
    "sg:classifiers":[
        {
            "category":"Building & Trades",
            "subcategory":"Construction",
            "type":"Services"
        },
        {
            "category":"Home & Garden",
            "subcategory":"Mobile Homes",
            "type":"Retail Goods"
        }
    ],
    "sg:phone":"+1 636 343 2064",
    "sg:postcode":"63026",
    "sg:province":"MO",
    "sg:tags":[
        "manufactured",
        "housing-communities",
        "park"
    ],
    "wof:name":"Greenfield Manor",
    "wof:placetype":"venue"
},
  "geometry": {"coordinates":[-90.444519,38.470867],"type":"Point"}
}