{
  "type": "Feature",
  "properties": {
    "iso:country":"US",
    "sg:address":"5715 Elizabeth Ave",
    "sg:city":"St Louis",
    "sg:classifiers":[
        {
            "category":"Manufacturing",
            "subcategory":"Printing",
            "type":"Manufacturing & Wholesale Goods"
        }
    ],
    "sg:phone":"+1 314 781 2992",
    "sg:postcode":"63110",
    "sg:province":"MO",
    "sg:tags":[
        "screen"
    ],
    "wof:name":"Maestro Screen Printing",
    "wof:placetype":"venue"
},
  "geometry": {"coordinates":[-90.284425,38.614875],"type":"Point"}
}