{
  "type": "Feature",
  "properties": {
    "iso:country":"US",
    "sg:address":"355 Howdershell Rd",
    "sg:city":"Florissant",
    "sg:classifiers":[
        {
            "category":"Banks & Credit Unions",
            "subcategory":"Bank",
            "type":"Services"
        },
        {
            "category":"Banks & Credit Unions",
            "subcategory":"Financial Services",
            "type":"Services"
        }
    ],
    "sg:phone":"+1 314 837 3279",
    "sg:postcode":"63031",
    "sg:province":"MO",
    "sg:tags":[
        "loan"
    ],
    "sg:website":"http://www.neighborscu.org",
    "wof:name":"Neighbors Credit Union",
    "wof:placetype":"venue"
},
  "geometry": {"coordinates":[-90.361481,38.806648],"type":"Point"}
}