{
  "type": "Feature",
  "properties": {
    "iso:country":"US",
    "sg:address":"403 Jackson Ave",
    "sg:city":"Saint Louis",
    "sg:classifiers":[
        {
            "category":"Banks & Credit Unions",
            "subcategory":"Investment Brokerage",
            "type":"Services"
        }
    ],
    "sg:phone":"+1 314 721 8688",
    "sg:postcode":"63130",
    "sg:province":"MO",
    "sg:tags":[
        "security"
    ],
    "wof:name":"Edward Jones 08911",
    "wof:placetype":"venue"
},
  "geometry": {"coordinates":[-90.32939399999999,38.654409],"type":"Point"}
}