{
  "type": "Feature",
  "properties": {
    "iso:country":"US",
    "sg:address":"10659 Co Ln 127",
    "sg:city":"Carthage",
    "sg:classifiers":[
        {
            "category":"Building & Trades",
            "subcategory":"Construction",
            "type":"Services"
        }
    ],
    "sg:phone":"+1 417 358 0702",
    "sg:postcode":"64836",
    "sg:province":"MO",
    "sg:tags":[
        "house"
    ],
    "wof:name":"Randy Scott Construction",
    "wof:placetype":"venue"
},
  "geometry": {"coordinates":[-94.286529,37.20584],"type":"Point"}
}