{
  "type": "Feature",
  "properties": {
    "iso:country":"US",
    "sg:address":"802 Boundary St",
    "sg:city":"Marble Hill",
    "sg:classifiers":[
        {
            "category":"Social Services",
            "subcategory":"Child Care",
            "type":"Services"
        }
    ],
    "sg:phone":"+1 573 238 0122",
    "sg:postcode":"63764",
    "sg:province":"MO",
    "sg:tags":[
        "day"
    ],
    "wof:name":"My Kidz Day Care",
    "wof:placetype":"venue"
},
  "geometry": {"coordinates":[-89.96745300000001,37.305441],"type":"Point"}
}