{
  "type": "Feature",
  "properties": {
    "iso:country":"US",
    "sg:address":"11415 Flint St",
    "sg:city":"Platte City",
    "sg:classifiers":[
        {
            "category":"Retail",
            "subcategory":"Repair Shop",
            "type":"Services"
        }
    ],
    "sg:phone":"+1 816 243 7578",
    "sg:postcode":"64079",
    "sg:province":"MO",
    "wof:name":"Pro Action Of Kansas City",
    "wof:placetype":"venue"
},
  "geometry": {"coordinates":[-94.71150799999999,39.357713],"type":"Point"}
}