{
  "type": "Feature",
  "properties": {
    "iso:country":"US",
    "sg:address":"2890 N Westwood Blvd",
    "sg:city":"Poplar Bluff",
    "sg:classifiers":[
        {
            "category":"Shopping",
            "subcategory":"Computers & Home Electronics",
            "type":"Retail Goods"
        }
    ],
    "sg:phone":"+1 573 785 3600",
    "sg:postcode":"63901",
    "sg:province":"MO",
    "sg:tags":[
        "high",
        "stereo",
        "fidelity",
        "radio",
        "television"
    ],
    "wof:name":"American Superstores",
    "wof:placetype":"venue"
},
  "geometry": {"coordinates":[-90.43120399999999,36.787865],"type":"Point"}
}