{
  "type": "Feature",
  "properties": {
    "iso:country":"US",
    "sg:address":"312 Warren",
    "sg:city":"Wright City",
    "sg:classifiers":[
        {
            "category":"Restaurant",
            "type":"Food & Drink"
        }
    ],
    "sg:phone":"+1 636 745 2080",
    "sg:postcode":"63390",
    "sg:province":"MO",
    "sg:tags":[
        "american"
    ],
    "wof:name":"RR Restaurant & Lounge",
    "wof:placetype":"venue"
},
  "geometry": {"coordinates":[-91.02851,38.829858],"type":"Point"}
}