{
  "type": "Feature",
  "properties": {
    "iso:country":"US",
    "sg:address":"415 Grand Blvd",
    "sg:city":"Kansas City",
    "sg:classifiers":[
        {
            "category":"Wholesale",
            "subcategory":"Machinery & Supplies",
            "type":"Manufacturing & Wholesale Goods"
        },
        {
            "category":"Autos & Motor Vehicles",
            "subcategory":"Auto Supplies",
            "type":"Retail Goods"
        }
    ],
    "sg:phone":"+1 816 421 1414",
    "sg:postcode":"64106",
    "sg:province":"MO",
    "sg:tags":[
        "wholesaler",
        "filter",
        "gas",
        "air"
    ],
    "wof:name":"Kansas City Air Filter Inc",
    "wof:placetype":"venue"
},
  "geometry": {"coordinates":[-94.58044099999999,39.108929],"type":"Point"}
}