{
  "type": "Feature",
  "properties": {
    "iso:country":"US",
    "sg:address":"142 McDonnell Blvd",
    "sg:city":"Hazelwood",
    "sg:classifiers":[
        {
            "category":"Airline",
            "type":"Transportation"
        }
    ],
    "sg:phone":"+1 314 731 6630",
    "sg:postcode":"63042",
    "sg:province":"MO",
    "sg:tags":[
        "courier",
        "air"
    ],
    "wof:name":"Davidson Surface Air",
    "wof:placetype":"venue"
},
  "geometry": {"coordinates":[-90.36939700000001,38.764607],"type":"Point"}
}