{
  "type": "Feature",
  "properties": {
    "iso:country":"US",
    "sg:address":"2124 Rock Rd",
    "sg:city":"De Soto",
    "sg:classifiers":[
        {
            "category":"Shopping",
            "subcategory":"Tobacco",
            "type":"Retail Goods"
        }
    ],
    "sg:phone":"+1 636 586 2855",
    "sg:postcode":"63020",
    "sg:province":"MO",
    "sg:tags":[
        "cigarette",
        "product",
        "cigar",
        "dealer"
    ],
    "wof:name":"Smokey's Place Inc",
    "wof:placetype":"venue"
},
  "geometry": {"coordinates":[-90.57825699999999,38.142339],"type":"Point"}
}