{
  "type": "Feature",
  "properties": {
    "iso:country":"US",
    "sg:address":"645 3rd St",
    "sg:city":"Osceola",
    "sg:classifiers":[
        {
            "category":"Insurance",
            "subcategory":"Hazard Insurance",
            "type":"Services"
        },
        {
            "category":"Insurance",
            "subcategory":"Insurance Agent",
            "type":"Services"
        },
        {
            "category":"Insurance",
            "subcategory":"Life Insurance",
            "type":"Services"
        },
        {
            "category":"Insurance",
            "subcategory":"Title Insurance",
            "type":"Services"
        }
    ],
    "sg:phone":"+1 417 646 2316",
    "sg:postcode":"64776",
    "sg:province":"MO",
    "sg:tags":[
        "auto",
        "renter",
        "homeowner"
    ],
    "sg:website":"http://www.ShelterInsurance.com/CA/agent/ROBBELISLE",
    "wof:name":"Shelter Insurance - Robert Belisle",
    "wof:placetype":"venue"
},
  "geometry": {"coordinates":[-93.665314,37.987625],"type":"Point"}
}