{
  "type": "Feature",
  "properties": {
    "iso:country":"US",
    "sg:address":"412 Court St",
    "sg:city":"Savannah",
    "sg:classifiers":[
        {
            "category":"Insurance",
            "subcategory":"Hazard Insurance",
            "type":"Services"
        }
    ],
    "sg:phone":"+1 877 324 3193",
    "sg:postcode":"64485",
    "sg:province":"MO",
    "wof:name":"N.W. Insurance Agency",
    "wof:placetype":"venue"
},
  "geometry": {"coordinates":[-94.82893900000001,39.941009],"type":"Point"}
}