{
  "type": "Feature",
  "properties": {
    "iso:country":"US",
    "sg:address":"4530 S Lindbergh Blvd",
    "sg:city":"Saint Louis",
    "sg:classifiers":[
        {
            "category":"Travel",
            "subcategory":"Hotels & Motels",
            "type":"Entertainment"
        }
    ],
    "sg:phone":"+1 314 731 1652",
    "sg:postcode":"63127",
    "sg:province":"MO",
    "sg:tags":[
        "operation"
    ],
    "wof:name":"Howard Johnson",
    "wof:placetype":"venue"
},
  "geometry": {"coordinates":[-90.38567999999999,38.534068],"type":"Point"}
}