{
  "type": "Feature",
  "properties": {
    "iso:country":"US",
    "sg:address":"6 Wood Leaf Ct",
    "sg:city":"O Fallon",
    "sg:classifiers":[
        {
            "category":"Home & Garden",
            "subcategory":"Home Furnishings",
            "type":"Retail Goods"
        },
        {
            "category":"Wholesale",
            "subcategory":"Home Furnishings",
            "type":"Manufacturing & Wholesale Goods"
        }
    ],
    "sg:phone":"+1 636 980 1033",
    "sg:postcode":"63366",
    "sg:province":"MO",
    "sg:tags":[
        "curtain",
        "made",
        "drapery"
    ],
    "wof:name":"C & K Custom Stitches Inc",
    "wof:placetype":"venue"
},
  "geometry": {"coordinates":[-90.75972899999999,38.840864],"type":"Point"}
}