{
  "type": "Feature",
  "properties": {
    "iso:country":"US",
    "sg:address":"8516 Manchester Rd",
    "sg:city":"St Louis",
    "sg:classifiers":[
        {
            "category":"Professional",
            "subcategory":"Research",
            "type":"Services"
        }
    ],
    "sg:phone":"+1 314 963 9999",
    "sg:postcode":"63144",
    "sg:province":"MO",
    "sg:tags":[
        "laboratory"
    ],
    "wof:name":"American Orthotics Lab Inc",
    "wof:placetype":"venue"
},
  "geometry": {"coordinates":[-90.34364600000001,38.612218],"type":"Point"}
}