{
  "type": "Feature",
  "properties": {
    "iso:country":"US",
    "sg:address":"11159 Pritchard Dr",
    "sg:city":"Saint Louis",
    "sg:classifiers":[
        {
            "category":"Social Services",
            "subcategory":"Child Care",
            "type":"Services"
        }
    ],
    "sg:phone":"+1 314 653 0429",
    "sg:postcode":"63136",
    "sg:province":"MO",
    "sg:tags":[
        "day"
    ],
    "wof:name":"Jerrys Day Care",
    "wof:placetype":"venue"
},
  "geometry": {"coordinates":[-90.25881,38.777599],"type":"Point"}
}