{
  "type": "Feature",
  "properties": {
    "iso:country":"US",
    "sg:address":"1309 Harvest Ridge Dr",
    "sg:city":"St Charles",
    "sg:classifiers":[
        {
            "category":"Freight",
            "type":"Transportation"
        }
    ],
    "sg:phone":"+1 636 947 7689",
    "sg:postcode":"63303",
    "sg:province":"MO",
    "sg:tags":[
        "delivery",
        "courier"
    ],
    "wof:name":"Rino Inc",
    "wof:placetype":"venue"
},
  "geometry": {"coordinates":[-90.52540999999999,38.752647],"type":"Point"}
}