{
  "type": "Feature",
  "properties": {
    "iso:country":"US",
    "sg:address":"305 Kelsha St",
    "sg:city":"Rogersville",
    "sg:classifiers":[
        {
            "category":"Personal",
            "subcategory":"Beauty Salon",
            "type":"Services"
        }
    ],
    "sg:phone":"+1 417 379 5895",
    "sg:postcode":"65742",
    "sg:province":"MO",
    "wof:name":"Colorworx Salon And Spa",
    "wof:placetype":"venue"
},
  "geometry": {"coordinates":[-93.06212499999999,37.111429],"type":"Point"}
}