{
  "type": "Feature",
  "properties": {
    "iso:country":"US",
    "sg:address":"4107 NW Caramel Ct",
    "sg:city":"Blue Springs",
    "sg:classifiers":[
        {
            "category":"Building & Trades",
            "subcategory":"Construction",
            "type":"Services"
        }
    ],
    "sg:phone":"+1 816 483 2222",
    "sg:postcode":"64015",
    "sg:province":"MO",
    "sg:tags":[
        "repairing",
        "remodeling",
        "contractor"
    ],
    "wof:name":"Mark's Remodeling Co",
    "wof:placetype":"venue"
},
  "geometry": {"coordinates":[-94.312911,39.025661],"type":"Point"}
}