{
  "type": "Feature",
  "properties": {
    "iso:country":"US",
    "sg:address":"201 Stillbrook Estates Dr",
    "sg:city":"Fenton",
    "sg:classifiers":[
        {
            "category":"Building & Trades",
            "subcategory":"Construction",
            "type":"Services"
        }
    ],
    "sg:phone":"+1 636 326 1049",
    "sg:postcode":"63026",
    "sg:province":"MO",
    "sg:tags":[
        "general",
        "contractor"
    ],
    "wof:name":"G S & J General Contracting",
    "wof:placetype":"venue"
},
  "geometry": {"coordinates":[-90.430742,38.498653],"type":"Point"}
}