{
  "type": "Feature",
  "properties": {
    "iso:country":"US",
    "sg:address":"113 S Main St",
    "sg:city":"Hannibal",
    "sg:classifiers":[
        {
            "category":"Manufacturing",
            "subcategory":"Printing",
            "type":"Manufacturing & Wholesale Goods"
        }
    ],
    "sg:phone":"+1 573 231 0800",
    "sg:postcode":"63401",
    "sg:province":"MO",
    "sg:tags":[
        "commercial"
    ],
    "wof:name":"Landmarx Screen Printing & EMB",
    "wof:placetype":"venue"
},
  "geometry": {"coordinates":[-91.355773,39.709564],"type":"Point"}
}