{
  "type": "Feature",
  "properties": {
    "iso:country":"US",
    "sg:address":"2904 Rochester St",
    "sg:city":"Kansas City",
    "sg:classifiers":[
        {
            "category":"Manufacturing",
            "subcategory":"Signs",
            "type":"Manufacturing & Wholesale Goods"
        }
    ],
    "sg:phone":"+1 816 231 6388",
    "sg:postcode":"64120",
    "sg:province":"MO",
    "sg:tags":[
        "specialty",
        "mfg"
    ],
    "wof:name":"Expresschannel",
    "wof:placetype":"venue"
},
  "geometry": {"coordinates":[-94.54574599999999,39.121264],"type":"Point"}
}