{
  "type": "Feature",
  "properties": {
    "iso:country":"US",
    "sg:address":"143 Bedford St",
    "sg:city":"Moberly",
    "sg:classifiers":[
        {
            "category":"Real Estate",
            "subcategory":"Real Estate Services",
            "type":"Services"
        },
        {
            "category":"Real Estate",
            "subcategory":"Real Estate Agent",
            "type":"Services"
        }
    ],
    "sg:phone":"+1 660 263 7788",
    "sg:postcode":"65270",
    "sg:province":"MO",
    "sg:tags":[
        "management",
        "broker",
        "vacancy",
        "listing",
        "buyer",
        "rental"
    ],
    "wof:name":"J Kl Rock Properties",
    "wof:placetype":"venue"
},
  "geometry": {"coordinates":[-92.448342,39.417258],"type":"Point"}
}