{
  "type": "Feature",
  "properties": {
    "iso:country":"US",
    "sg:address":"11 Brady Cir",
    "sg:city":"Overland",
    "sg:classifiers":[
        {
            "category":"Government",
            "subcategory":"Office",
            "type":"Public Place"
        }
    ],
    "sg:phone":"+1 314 428 8470",
    "sg:postcode":"63114",
    "sg:province":"MO",
    "sg:tags":[
        "intermediate",
        "program",
        "health",
        "care",
        "administrative"
    ],
    "wof:name":"Northwest Habilitation Center",
    "wof:placetype":"venue"
},
  "geometry": {"coordinates":[-90.40443500000001,38.705761],"type":"Point"}
}