{
  "type": "Feature",
  "properties": {
    "iso:country":"US",
    "sg:address":"7 Newberry Ct",
    "sg:city":"Saint Peters",
    "sg:classifiers":[
        {
            "category":"Professional",
            "subcategory":"Business Services",
            "type":"Services"
        }
    ],
    "sg:phone":"+1 636 441 2019",
    "sg:postcode":"63376",
    "sg:province":"MO",
    "wof:name":"H L Byrne",
    "wof:placetype":"venue"
},
  "geometry": {"coordinates":[-90.61944200000001,38.754395],"type":"Point"}
}