{
  "type": "Feature",
  "properties": {
    "iso:country":"US",
    "sg:address":"5300 Dulin Creek Rd",
    "sg:city":"House Springs",
    "sg:classifiers":[
        {
            "category":"Sports & Exercise",
            "subcategory":"Golf",
            "type":"Entertainment"
        }
    ],
    "sg:phone":"+1 636 671 0447",
    "sg:postcode":"63051",
    "sg:province":"MO",
    "sg:tags":[
        "course",
        "public"
    ],
    "wof:name":"Deer Creek Golf Club",
    "wof:placetype":"venue"
},
  "geometry": {"coordinates":[-90.58511300000001,38.382108],"type":"Point"}
}