{
  "type": "Feature",
  "properties": {
    "addr:full":"109 E Jackson St Keytesville MO 65261",
    "addr:housenumber":"109",
    "addr:postcode":"65261",
    "addr:street":"E Jackson St",
    "iso:country":"US",
    "sg:address":"109 E Jackson St",
    "sg:city":"Keytesville",
    "sg:classifiers":[
        {
            "category":"Insurance",
            "subcategory":"Insurance Agent",
            "type":"Services"
        }
    ],
    "sg:phone":"+1 660 288 3291",
    "sg:postcode":"65261",
    "sg:province":"MO",
    "wof:name":"Farm Bureau Insurance",
    "wof:placetype":"venue"
},
  "geometry": {"coordinates":[-92.93634400000001,39.432968],"type":"Point"}
}