{
  "type": "Feature",
  "properties": {
    "iso:country":"US",
    "sg:address":"207 Mayfield Dr",
    "sg:city":"Marble Hill",
    "sg:classifiers":[
        {
            "category":"Museum",
            "type":"Entertainment"
        }
    ],
    "sg:phone":"+1 573 238 1174",
    "sg:postcode":"63764",
    "sg:province":"MO",
    "wof:name":"Bollinger County Museum",
    "wof:placetype":"venue"
},
  "geometry": {"coordinates":[-89.974626,37.306319],"type":"Point"}
}