{
  "type": "Feature",
  "properties": {
    "iso:country":"US",
    "sg:address":"136 Zumwalt Rd",
    "sg:city":"Silex",
    "sg:classifiers":[
        {
            "category":"Farming",
            "subcategory":"Livestock Farm",
            "type":"Manufacturing & Wholesale Goods"
        }
    ],
    "sg:phone":"+1 573 485 7261",
    "sg:postcode":"63377",
    "sg:province":"MO",
    "sg:tags":[
        "poultry",
        "beef",
        "ranch",
        "hatchery",
        "cattle",
        "feedlot"
    ],
    "wof:name":"Kelly Klober",
    "wof:placetype":"venue"
},
  "geometry": {"coordinates":[-91.03182200000001,39.188058],"type":"Point"}
}