{
  "type": "Feature",
  "properties": {
    "iso:country":"US",
    "sg:address":"1127 Main St",
    "sg:city":"Lexington",
    "sg:classifiers":[
        {
            "category":"Shopping",
            "subcategory":"Used Merchandise",
            "type":"Retail Goods"
        }
    ],
    "sg:phone":"+1 660 259 2550",
    "sg:postcode":"64067",
    "sg:province":"MO",
    "wof:name":"Dusty Treasures Pawn Shop",
    "wof:placetype":"venue"
},
  "geometry": {"coordinates":[-93.88124000000001,39.185402],"type":"Point"}
}