{
  "type": "Feature",
  "properties": {
    "iso:country":"US",
    "sg:address":"200 E High Point Ln",
    "sg:city":"Columbia",
    "sg:classifiers":[
        {
            "category":"Building & Trades",
            "subcategory":"Landscaping Services",
            "type":"Services"
        }
    ],
    "sg:phone":"+1 573 875 0962",
    "sg:postcode":"65203",
    "sg:province":"MO",
    "sg:tags":[
        "contracting",
        "lawn",
        "care",
        "plowing",
        "snow"
    ],
    "wof:name":"Highpoint Enterprises Inc",
    "wof:placetype":"venue"
},
  "geometry": {"coordinates":[-92.34234499999999,38.860879],"type":"Point"}
}