{
  "type": "Feature",
  "properties": {
    "iso:country":"US",
    "sg:address":"7045 W Florissant Ave",
    "sg:city":"St Louis",
    "sg:classifiers":[
        {
            "category":"Organizations",
            "subcategory":"Religious Organization",
            "type":"Services"
        }
    ],
    "sg:phone":"+1 314 385 9700",
    "sg:postcode":"63136",
    "sg:province":"MO",
    "sg:tags":[
        "church"
    ],
    "wof:name":"Temple Of Deliverance Outreach",
    "wof:placetype":"venue"
},
  "geometry": {"coordinates":[-90.262141,38.71831],"type":"Point"}
}