{
  "type": "Feature",
  "properties": {
    "iso:country":"US",
    "sg:address":"130 E Flint Hill School Rd",
    "sg:city":"Sturgeon",
    "sg:classifiers":[
        {
            "category":"Building & Trades",
            "subcategory":"Construction",
            "type":"Services"
        }
    ],
    "sg:phone":"+1 573 696 3125",
    "sg:postcode":"65284",
    "sg:province":"MO",
    "sg:tags":[
        "house"
    ],
    "wof:name":"Wrens Mobile Home Service",
    "wof:placetype":"venue"
},
  "geometry": {"coordinates":[-92.3364,39.136415],"type":"Point"}
}