{
  "type": "Feature",
  "properties": {
    "iso:country":"US",
    "sg:address":"1104 NE Banner Dr",
    "sg:city":"Lees Summit",
    "sg:classifiers":[
        {
            "category":"Building & Trades",
            "subcategory":"Construction",
            "type":"Services"
        }
    ],
    "sg:phone":"+1 816 935 2892",
    "sg:postcode":"64086",
    "sg:province":"MO",
    "wof:name":"Csd Construction Inc",
    "wof:placetype":"venue"
},
  "geometry": {"coordinates":[-94.354719,38.932079],"type":"Point"}
}