{
  "type": "Feature",
  "properties": {
    "iso:country":"US",
    "sg:address":"602 E Young St",
    "sg:city":"Warrensburg",
    "sg:classifiers":[
        {
            "category":"Food & Beverages",
            "subcategory":"Groceries & Convenience Stores",
            "type":"Retail Goods"
        }
    ],
    "sg:phone":"+1 660 747 9064",
    "sg:postcode":"64093",
    "sg:province":"MO",
    "wof:name":"Caseys 1114",
    "wof:placetype":"venue"
},
  "geometry": {"coordinates":[-93.72135299999999,38.771849],"type":"Point"}
}