{
  "type": "Feature",
  "properties": {
    "iso:country":"US",
    "sg:address":"106 E Washington Rd",
    "sg:city":"Smithton",
    "sg:classifiers":[
        {
            "category":"Manufacturing",
            "subcategory":"Pet Food",
            "type":"Manufacturing & Wholesale Goods"
        }
    ],
    "sg:phone":"+1 660 343 5319",
    "sg:postcode":"65350",
    "sg:province":"MO",
    "sg:tags":[
        "feed"
    ],
    "wof:name":"Cargill Animal Nutrition",
    "wof:placetype":"venue"
},
  "geometry": {"coordinates":[-93.09259299999999,38.683245],"type":"Point"}
}