{
  "type": "Feature",
  "properties": {
    "iso:country":"US",
    "sg:address":"3201 E Division St",
    "sg:city":"Springfield",
    "sg:classifiers":[
        {
            "category":"Wholesale",
            "subcategory":"Groceries",
            "type":"Manufacturing & Wholesale Goods"
        }
    ],
    "sg:phone":"+1 417 875 4000",
    "sg:postcode":"65802",
    "sg:province":"MO",
    "sg:tags":[
        "grocers-wholesale"
    ],
    "sg:website":"http://www.awgokc.com",
    "wof:name":"A W G Distribution Div 2",
    "wof:placetype":"venue"
},
  "geometry": {"coordinates":[-93.227658,37.224291],"type":"Point"}
}