{
  "type": "Feature",
  "properties": {
    "iso:country":"US",
    "sg:address":"1000 S Neosho Blvd",
    "sg:city":"Neosho",
    "sg:classifiers":[
        {
            "category":"Food & Beverages",
            "subcategory":"Groceries & Convenience Stores",
            "type":"Retail Goods"
        }
    ],
    "sg:phone":"+1 417 451 3628",
    "sg:postcode":"64850",
    "sg:province":"MO",
    "wof:name":"Rameys Supermarket",
    "wof:placetype":"venue"
},
  "geometry": {"coordinates":[-94.38400300000001,36.856308],"type":"Point"}
}