{
  "type": "Feature",
  "properties": {
    "iso:country":"US",
    "sg:address":"212 N Mill St",
    "sg:city":"Festus",
    "sg:classifiers":[
        {
            "category":"Government",
            "subcategory":"Fire Station",
            "type":"Public Place"
        }
    ],
    "sg:phone":"+1 636 937 7661",
    "sg:postcode":"63028",
    "sg:province":"MO",
    "sg:tags":[
        "department"
    ],
    "wof:name":"Festus Fire Dept",
    "wof:placetype":"venue"
},
  "geometry": {"coordinates":[-90.393209,38.221765],"type":"Point"}
}