{
  "type": "Feature",
  "properties": {
    "iso:country":"US",
    "sg:address":"160 Magee St",
    "sg:city":"Troy",
    "sg:classifiers":[
        {
            "category":"Autos & Motor Vehicles",
            "subcategory":"Auto Supplies",
            "type":"Retail Goods"
        }
    ],
    "sg:phone":"+1 636 528 7007",
    "sg:postcode":"63379",
    "sg:province":"MO",
    "sg:tags":[
        "automobile",
        "parts"
    ],
    "wof:name":"Mid Nite Auto Supply Inc",
    "wof:placetype":"venue"
},
  "geometry": {"coordinates":[-90.978251,38.987758],"type":"Point"}
}