{
  "type": "Feature",
  "properties": {
    "iso:country":"US",
    "sg:address":"1912 S Osage Ave",
    "sg:city":"Independence",
    "sg:classifiers":[
        {
            "category":"Building & Trades",
            "subcategory":"Construction",
            "type":"Services"
        }
    ],
    "sg:phone":"+1 816 833 3312",
    "sg:postcode":"64055",
    "sg:province":"MO",
    "sg:tags":[
        "residential"
    ],
    "wof:name":"Zeller Construction",
    "wof:placetype":"venue"
},
  "geometry": {"coordinates":[-94.41543799999999,39.066177],"type":"Point"}
}