{
  "type": "Feature",
  "properties": {
    "iso:country":"US",
    "sg:address":"4920 S Tierney Dr",
    "sg:city":"Independence",
    "sg:classifiers":[
        {
            "category":"Professional",
            "type":"Services"
        }
    ],
    "sg:phone":"+1 816 350 2443",
    "sg:postcode":"64055",
    "sg:province":"MO",
    "wof:name":"Alea Services",
    "wof:placetype":"venue"
},
  "geometry": {"coordinates":[-94.37041600000001,39.031039],"type":"Point"}
}