{
  "type": "Feature",
  "properties": {
    "iso:country":"US",
    "sg:address":"457 Pine Bend Dr",
    "sg:city":"Chesterfield",
    "sg:classifiers":[
        {
            "category":"Food & Beverages",
            "subcategory":"Specialty",
            "type":"Retail Goods"
        }
    ],
    "sg:phone":"+1 636 536 2137",
    "sg:postcode":"63005",
    "sg:province":"MO",
    "wof:name":"Sara Lee Coffee",
    "wof:placetype":"venue"
},
  "geometry": {"coordinates":[-90.656533,38.643134],"type":"Point"}
}