{
  "type": "Feature",
  "properties": {
    "iso:country":"US",
    "sg:address":"5 Wheelwright Ct",
    "sg:city":"Ballwin",
    "sg:classifiers":[
        {
            "category":"Travel",
            "subcategory":"Travel Agent",
            "type":"Entertainment"
        }
    ],
    "sg:phone":"+1 636 227 2400",
    "sg:postcode":"63021",
    "sg:province":"MO",
    "sg:tags":[
        "agency"
    ],
    "wof:name":"Funsea Cruise",
    "wof:placetype":"venue"
},
  "geometry": {"coordinates":[-90.516092,38.573277],"type":"Point"}
}