{
  "type": "Feature",
  "properties": {
    "iso:country":"US",
    "sg:address":"14323 S Outer 40",
    "sg:city":"Chesterfield",
    "sg:classifiers":[
        {
            "category":"Professional",
            "subcategory":"Management & Consulting",
            "type":"Services"
        },
        {
            "category":"Shopping",
            "subcategory":"Computers & Home Electronics",
            "type":"Retail Goods"
        }
    ],
    "sg:phone":"+1 314 576 4022",
    "sg:postcode":"63017",
    "sg:province":"MO",
    "sg:tags":[
        "employee",
        "benefit",
        "program",
        "administers",
        "software"
    ],
    "sg:website":"www.tri-starsystems.com",
    "wof:name":"Tri Star Benefit Systems Inc",
    "wof:placetype":"venue"
},
  "geometry": {"coordinates":[-90.52697000000001,38.645889],"type":"Point"}
}