{
  "type": "Feature",
  "properties": {
    "iso:country":"US",
    "sg:address":"142 Stutesmun Ln",
    "sg:city":"Highlandville",
    "sg:classifiers":[
        {
            "category":"Retail",
            "subcategory":"Auto Repair",
            "type":"Services"
        }
    ],
    "sg:phone":"+1 417 443 3593",
    "sg:postcode":"65669",
    "sg:province":"MO",
    "wof:name":"Bondtech Autoclave Corp.",
    "wof:placetype":"venue"
},
  "geometry": {"coordinates":[-93.232939,36.883821],"type":"Point"}
}