{
  "type": "Feature",
  "properties": {
    "iso:country":"US",
    "sg:address":"1144 W Jackson St",
    "sg:city":"Ozark",
    "sg:classifiers":[
        {
            "category":"Shopping",
            "subcategory":"Department Store",
            "type":"Retail Goods"
        },
        {
            "category":"Shopping",
            "subcategory":"Discount & Variety Stores",
            "type":"Retail Goods"
        },
        {
            "category":"Shopping",
            "subcategory":"Pharmacy",
            "type":"Retail Goods"
        }
    ],
    "sg:phone":"+1 417 581 9015",
    "sg:postcode":"65721",
    "sg:province":"MO",
    "wof:name":"Family Pharmacy Bargain Outlet",
    "wof:placetype":"venue"
},
  "geometry": {"coordinates":[-93.22995,37.023251],"type":"Point"}
}