{
  "type": "Feature",
  "properties": {
    "iso:country":"US",
    "sg:address":"4231 Laclede",
    "sg:city":"Saint Louis",
    "sg:classifiers":[
        {
            "category":"Health Services",
            "subcategory":"Doctor",
            "type":"Services"
        },
        {
            "category":"Health Services",
            "subcategory":"Clinic",
            "type":"Services"
        }
    ],
    "sg:phone":"+1 314 289 9981",
    "sg:postcode":"63108",
    "sg:province":"MO",
    "sg:tags":[
        "counseling",
        "mental"
    ],
    "wof:name":"Sharon Lightfoot, PHD",
    "wof:placetype":"venue"
},
  "geometry": {"coordinates":[-90.25014299999999,38.638263],"type":"Point"}
}