{
  "type": "Feature",
  "properties": {
    "iso:country":"US",
    "sg:address":"4151 W Church St",
    "sg:city":"Springfield",
    "sg:classifiers":[
        {
            "category":"Retail",
            "subcategory":"Auto Repair",
            "type":"Services"
        }
    ],
    "sg:phone":"+1 417 865 5604",
    "sg:postcode":"65802",
    "sg:province":"MO",
    "sg:tags":[
        "automotive"
    ],
    "wof:name":"M & B Automotive",
    "wof:placetype":"venue"
},
  "geometry": {"coordinates":[-93.363552,37.216916],"type":"Point"}
}