{
  "type": "Feature",
  "properties": {
    "addr:full":"469 Snyder Rd Troy MO 63379",
    "addr:housenumber":"469",
    "addr:postcode":"63379",
    "addr:street":"Snyder Rd",
    "iso:country":"US",
    "sg:address":"469 Snyder Rd",
    "sg:city":"Troy",
    "sg:classifiers":[
        {
            "category":"Shopping",
            "subcategory":"Beauty & Cosmetics",
            "type":"Retail Goods"
        }
    ],
    "sg:phone":"+1 636 528 8962",
    "sg:postcode":"63379",
    "sg:province":"MO",
    "sg:tags":[
        "perfume",
        "salons-equipment",
        "supply"
    ],
    "wof:name":"Mary Kay Cosmetics",
    "wof:placetype":"venue"
},
  "geometry": {"coordinates":[-91.022299,38.990239],"type":"Point"}
}