{
  "type": "Feature",
  "properties": {
    "addr:full":"8820 Ladue Rd St Louis MO 63124",
    "addr:postcode":"8820;63124",
    "addr:street":"Ladue Rd",
    "iso:country":"US",
    "sg:address":"8820 Ladue Rd",
    "sg:city":"St Louis",
    "sg:classifiers":[
        {
            "category":"Real Estate",
            "subcategory":"Real Estate Agent",
            "type":"Services"
        }
    ],
    "sg:phone":"+1 314 206 4600",
    "sg:postcode":"63124",
    "sg:province":"MO",
    "sg:website":"www.cbcstl.com",
    "wof:name":"Coldwell Banker",
    "wof:placetype":"venue"
},
  "geometry": {"coordinates":[-90.34997199999999,38.653259],"type":"Point"}
}