{
  "type": "Feature",
  "properties": {
    "iso:country":"US",
    "sg:address":"5831 Dr Martn Lthr Kng Dr",
    "sg:city":"Saint Louis",
    "sg:classifiers":[
        {
            "category":"Retail",
            "subcategory":"Auto Repair",
            "type":"Services"
        }
    ],
    "sg:phone":"+1 314 381 4470",
    "sg:postcode":"63112",
    "sg:province":"MO",
    "wof:name":"Bj Auto Repair",
    "wof:placetype":"venue"
},
  "geometry": {"coordinates":[-90.280296,38.672401],"type":"Point"}
}