{
  "type": "Feature",
  "properties": {
    "iso:country":"US",
    "sg:address":"1121 Olivette Executive Pkwy",
    "sg:city":"Saint Louis",
    "sg:classifiers":[
        {
            "category":"Insurance",
            "subcategory":"Insurance Agent",
            "type":"Services"
        }
    ],
    "sg:phone":"+1 314 997 6233",
    "sg:postcode":"63132",
    "sg:province":"MO",
    "sg:tags":[
        "life",
        "trust",
        "administration"
    ],
    "wof:name":"Trustbuilder Services LLC",
    "wof:placetype":"venue"
},
  "geometry": {"coordinates":[-90.372443,38.675746],"type":"Point"}
}