{
  "type": "Feature",
  "properties": {
    "iso:country":"US",
    "sg:address":"20399 Co Rd 287",
    "sg:city":"Puxico",
    "sg:classifiers":[
        {
            "category":"Professional",
            "subcategory":"Management & Consulting",
            "type":"Services"
        }
    ],
    "sg:phone":"+1 573 222 3480",
    "sg:postcode":"63960",
    "sg:province":"MO",
    "sg:tags":[
        "concrete",
        "bob",
        "construction",
        "cat"
    ],
    "wof:name":"Bob Cat Service",
    "wof:placetype":"venue"
},
  "geometry": {"coordinates":[-90.15173799999999,36.904145],"type":"Point"}
}