{
  "type": "Feature",
  "properties": {
    "iso:country":"US",
    "sg:address":"401 Par Ln",
    "sg:city":"St Louis",
    "sg:classifiers":[
        {
            "category":"Professional",
            "subcategory":"Lawyer & Legal Services",
            "type":"Services"
        }
    ],
    "sg:phone":"+1 314 909 9077",
    "sg:postcode":"63122",
    "sg:province":"MO",
    "sg:tags":[
        "attorney"
    ],
    "wof:name":"Daniel Mohs Attorney At Law",
    "wof:placetype":"venue"
},
  "geometry": {"coordinates":[-90.398831,38.592556],"type":"Point"}
}