{
  "type": "Feature",
  "properties": {
    "iso:country":"US",
    "sg:address":"1809 Locust St",
    "sg:city":"Kansas City",
    "sg:classifiers":[
        {
            "category":"Retail",
            "subcategory":"Auto Repair",
            "type":"Services"
        },
        {
            "category":"Manufacturing",
            "subcategory":"Motor Vehicles & Parts",
            "type":"Manufacturing & Wholesale Goods"
        }
    ],
    "sg:phone":"+1 816 221 8478",
    "sg:postcode":"64108",
    "sg:province":"MO",
    "sg:tags":[
        "travel",
        "trailer",
        "mfg"
    ],
    "wof:name":"Steversons Trailer Co",
    "wof:placetype":"venue"
},
  "geometry": {"coordinates":[-94.57777400000001,39.090707],"type":"Point"}
}