{
  "type": "Feature",
  "properties": {
    "iso:country":"US",
    "sg:address":"831 Charbonier Rd",
    "sg:city":"Florissant",
    "sg:classifiers":[
        {
            "category":"Building & Trades",
            "subcategory":"Construction",
            "type":"Services"
        }
    ],
    "sg:phone":"+1 314 805 0556",
    "sg:postcode":"63031",
    "sg:province":"MO",
    "sg:tags":[
        "house"
    ],
    "wof:name":"Hancock and Associates Cnstr",
    "wof:placetype":"venue"
},
  "geometry": {"coordinates":[-90.343862,38.799935],"type":"Point"}
}