{
  "type": "Feature",
  "properties": {
    "iso:country":"US",
    "sg:address":"103 Main St",
    "sg:city":"Eminence",
    "sg:classifiers":[
        {
            "category":"Banks & Credit Unions",
            "subcategory":"Bank",
            "type":"Services"
        }
    ],
    "sg:phone":"+1 573 226 3222",
    "sg:postcode":"65466",
    "sg:province":"MO",
    "wof:name":"Eminence Security Bank",
    "wof:placetype":"venue"
},
  "geometry": {"coordinates":[-91.35803900000001,37.142954],"type":"Point"}
}