{
  "type": "Feature",
  "properties": {
    "iso:country":"US",
    "sg:address":"113 E Main St",
    "sg:city":"Maysville",
    "sg:classifiers":[
        {
            "category":"Shopping",
            "subcategory":"Clothing, Apparel, & Fashions",
            "type":"Retail Goods"
        }
    ],
    "sg:phone":"+1 816 449 2447",
    "sg:postcode":"64469",
    "sg:province":"MO",
    "wof:name":"Dandy's",
    "wof:placetype":"venue"
},
  "geometry": {"coordinates":[-94.359245,39.889534],"type":"Point"}
}