{
  "type": "Feature",
  "properties": {
    "iso:country":"US",
    "sg:address":"29 Young St",
    "sg:city":"Ft Leonard Wood",
    "sg:classifiers":[
        {
            "category":"Social Services",
            "type":"Services"
        }
    ],
    "sg:phone":"+1 573 329 4513",
    "sg:postcode":"65473",
    "sg:province":"MO",
    "sg:tags":[
        "organization",
        "welfare"
    ],
    "wof:name":"YMCA",
    "wof:placetype":"venue"
},
  "geometry": {"coordinates":[-92.135464,37.783139],"type":"Point"}
}