{
  "type": "Feature",
  "properties": {
    "iso:country":"US",
    "sg:address":"595 Vista Hills Ct",
    "sg:city":"Eureka",
    "sg:classifiers":[
        {
            "category":"Home & Garden",
            "subcategory":"Hardware",
            "type":"Retail Goods"
        }
    ],
    "sg:phone":"+1 636 938 9633",
    "sg:postcode":"63025",
    "sg:province":"MO",
    "sg:tags":[
        "measuring",
        "device"
    ],
    "sg:website":"http://www.radio-telemetry.com",
    "wof:name":"Navionics Research Inc",
    "wof:placetype":"venue"
},
  "geometry": {"coordinates":[-90.660038,38.491793],"type":"Point"}
}