{
  "type": "Feature",
  "properties": {
    "iso:country":"US",
    "sg:address":"127 Cedar Hill Ln",
    "sg:city":"Marshfield",
    "sg:classifiers":[
        {
            "category":"Retail",
            "subcategory":"Repair Shop",
            "type":"Services"
        }
    ],
    "sg:phone":"+1 417 859 5883",
    "sg:postcode":"65706",
    "sg:province":"MO",
    "sg:tags":[
        "appliance"
    ],
    "wof:name":"Jeff Appliances & Refrig Svc",
    "wof:placetype":"venue"
},
  "geometry": {"coordinates":[-92.936925,37.298557],"type":"Point"}
}