{
  "type": "Feature",
  "properties": {
    "iso:country":"US",
    "sg:address":"1240 E Independence St",
    "sg:city":"Springfield",
    "sg:classifiers":[
        {
            "category":"Health Services",
            "subcategory":"Doctor",
            "type":"Services"
        }
    ],
    "sg:phone":"+1 417 823 3806",
    "sg:postcode":"65804",
    "sg:province":"MO",
    "sg:tags":[
        "physician",
        "surgeon"
    ],
    "wof:name":"Cosmetic Lasers Of Southwest",
    "wof:placetype":"venue"
},
  "geometry": {"coordinates":[-93.274039,37.145275],"type":"Point"}
}