{
  "type": "Feature",
  "properties": {
    "iso:country":"US",
    "sg:address":"1316 E Battlefield Rd",
    "sg:city":"Springfield",
    "sg:classifiers":[
        {
            "category":"Shopping",
            "subcategory":"Bicycles & Sporting Goods",
            "type":"Retail Goods"
        }
    ],
    "sg:phone":"+1 417 889 6548",
    "sg:postcode":"65804",
    "sg:province":"MO",
    "sg:tags":[
        "equipment",
        "outdoor",
        "clothing",
        "fishing"
    ],
    "wof:name":"Backcountry Outfitters",
    "wof:placetype":"venue"
},
  "geometry": {"coordinates":[-93.27224,37.15951],"type":"Point"}
}