{
  "type": "Feature",
  "properties": {
    "iso:country":"US",
    "sg:address":"1813 Barron Rd",
    "sg:city":"Poplar Bluff",
    "sg:classifiers":[
        {
            "category":"Organizations",
            "subcategory":"Religious Organization",
            "type":"Services"
        }
    ],
    "sg:phone":"+1 573 785 1250",
    "sg:postcode":"63901",
    "sg:province":"MO",
    "wof:name":"Temple Baptist Church-S B C",
    "wof:placetype":"venue"
},
  "geometry": {"coordinates":[-90.417748,36.784704],"type":"Point"}
}