{
  "type": "Feature",
  "properties": {
    "addr:full":"1107 E 11th St Trenton MO 64683",
    "addr:housenumber":"1107",
    "addr:postcode":"64683",
    "addr:street":"E 11Th St",
    "iso:country":"US",
    "sg:address":"1107 E 11th St",
    "sg:city":"Trenton",
    "sg:classifiers":[
        {
            "category":"Place Of Worship",
            "subcategory":"Church",
            "type":"Public Place"
        },
        {
            "category":"Place Of Worship",
            "type":"Public Place"
        },
        {
            "category":"Organizations",
            "subcategory":"Religious Organization",
            "type":"Services"
        }
    ],
    "sg:phone":"+1 660 359 4400",
    "sg:postcode":"64683",
    "sg:province":"MO",
    "sg:tags":[
        "god",
        "god-independent",
        "churches-assemblies"
    ],
    "sg:website":"http://www.trentonfirst.us",
    "wof:name":"First Assembly of God Church",
    "wof:placetype":"venue"
},
  "geometry": {"coordinates":[-93.607161,40.07626],"type":"Point"}
}