{
  "type": "Feature",
  "properties": {
    "addr:full":"408 N 2nd St Odessa MO 64076",
    "addr:housenumber":"408",
    "addr:postcode":"64076",
    "addr:street":"N 2Nd St",
    "iso:country":"US",
    "sg:address":"408 N 2nd St",
    "sg:city":"Odessa",
    "sg:classifiers":[
        {
            "category":"Restaurant",
            "type":"Food & Drink"
        }
    ],
    "sg:menulink":"http://www.allmenus.com/mo/clay/201638-sonic/menu/",
    "sg:phone":"+1 816 230 5588",
    "sg:postcode":"64076",
    "sg:province":"MO",
    "sg:tags":[
        "burger",
        "american"
    ],
    "wof:name":"Sonic",
    "wof:placetype":"venue"
},
  "geometry": {"coordinates":[-93.953148,39.004285],"type":"Point"}
}