{
  "type": "Feature",
  "properties": {
    "iso:country":"US",
    "sg:address":"561 Kingsland Ave",
    "sg:city":"St Louis",
    "sg:classifiers":[
        {
            "category":"Personal",
            "type":"Services"
        },
        {
            "category":"Professional",
            "subcategory":"Art Services",
            "type":"Services"
        }
    ],
    "sg:phone":"+1 314 753 7231",
    "sg:postcode":"63130",
    "sg:province":"MO",
    "sg:tags":[
        "photographer",
        "planning",
        "event",
        "party"
    ],
    "sg:website":"www.laughingpenguins.com",
    "wof:name":"Laughing Penguins Photo Booth Studio",
    "wof:placetype":"venue"
},
  "geometry": {"coordinates":[-90.309471,38.655968],"type":"Point"}
}