{
  "type": "Feature",
  "properties": {
    "iso:country":"US",
    "sg:address":"565 Virginia Ave",
    "sg:city":"New Madrid",
    "sg:classifiers":[
        {
            "category":"Professional",
            "subcategory":"Lawyer & Legal Services",
            "type":"Services"
        }
    ],
    "sg:phone":"+1 573 748 2890",
    "sg:postcode":"63869",
    "sg:province":"MO",
    "sg:tags":[
        "attorney"
    ],
    "wof:name":"Lewis H Recker",
    "wof:placetype":"venue"
},
  "geometry": {"coordinates":[-89.52776900000001,36.588183],"type":"Point"}
}