{
  "type": "Feature",
  "properties": {
    "iso:country":"US",
    "sg:address":"1045 Swift Ave",
    "sg:city":"Kansas City",
    "sg:classifiers":[
        {
            "category":"Social Services",
            "type":"Services"
        }
    ],
    "sg:phone":"+1 816 471 6433",
    "sg:postcode":"64116",
    "sg:province":"MO",
    "sg:website":"www.agrm.org",
    "wof:name":"Alcoholics Victorious",
    "wof:placetype":"venue"
},
  "geometry": {"coordinates":[-94.577397,39.127909],"type":"Point"}
}