{
  "type": "Feature",
  "properties": {
    "iso:country":"US",
    "sg:address":"865 Guenter Ln",
    "sg:city":"Pacific",
    "sg:classifiers":[
        {
            "category":"Manufacturing",
            "subcategory":"Lumber",
            "type":"Manufacturing & Wholesale Goods"
        }
    ],
    "sg:phone":"+1 636 742 2960",
    "sg:postcode":"63069",
    "sg:province":"MO",
    "sg:tags":[
        "sawmill"
    ],
    "wof:name":"Diamond E Sawmill",
    "wof:placetype":"venue"
},
  "geometry": {"coordinates":[-90.745692,38.519501],"type":"Point"}
}