{
  "type": "Feature",
  "properties": {
    "iso:country":"US",
    "sg:address":"14480 E 42nd St S",
    "sg:city":"Independence",
    "sg:classifiers":[
        {
            "category":"Professional",
            "subcategory":"Employment Agencies",
            "type":"Services"
        },
        {
            "category":"Health Services",
            "subcategory":"Nursing And Care Facility",
            "type":"Services"
        },
        {
            "category":"Health Services",
            "subcategory":"Health Practitioner",
            "type":"Services"
        },
        {
            "category":"Social Services",
            "subcategory":"Adult Care",
            "type":"Services"
        }
    ],
    "sg:phone":"+1 816 373 9688",
    "sg:postcode":"64055",
    "sg:province":"MO",
    "sg:tags":[
        "nurses-home",
        "nurse",
        "opportunity",
        "home"
    ],
    "sg:website":"http://www.1stcallstaffing.com",
    "wof:name":"First Call Staffing Solutions Inc",
    "wof:placetype":"venue"
},
  "geometry": {"coordinates":[-94.409854,39.044748],"type":"Point"}
}