{
  "type": "Feature",
  "properties": {
    "iso:country":"US",
    "sg:address":"105 N Central Dr",
    "sg:city":"O Fallon",
    "sg:classifiers":[
        {
            "category":"Freight",
            "type":"Transportation"
        }
    ],
    "sg:phone":"+1 636 978 2522",
    "sg:postcode":"63366",
    "sg:province":"MO",
    "sg:tags":[
        "trucking"
    ],
    "wof:name":"Stege Transportation Inc",
    "wof:placetype":"venue"
},
  "geometry": {"coordinates":[-90.726873,38.806394],"type":"Point"}
}