{
  "type": "Feature",
  "properties": {
    "iso:country":"US",
    "sg:address":"339 NW Barry Rd",
    "sg:city":"Kansas City",
    "sg:classifiers":[
        {
            "category":"Health Services",
            "subcategory":"Doctor",
            "type":"Services"
        }
    ],
    "sg:phone":"+1 816 420 8100",
    "sg:postcode":"64155",
    "sg:province":"MO",
    "sg:tags":[
        "dentist"
    ],
    "wof:name":"Kurt Kavanaugh Orthodontics",
    "wof:placetype":"venue"
},
  "geometry": {"coordinates":[-94.584546,39.246263],"type":"Point"}
}