{
  "type": "Feature",
  "properties": {
    "iso:country":"US",
    "sg:address":"1855 State Hwy CC",
    "sg:city":"Nixa",
    "sg:classifiers":[
        {
            "category":"Building & Trades",
            "subcategory":"Construction",
            "type":"Services"
        }
    ],
    "sg:phone":"+1 417 725 5329",
    "sg:postcode":"65714",
    "sg:province":"MO",
    "sg:tags":[
        "ac",
        "family",
        "power",
        "tool",
        "contractor",
        "home"
    ],
    "wof:name":"Larrys Tool & Supply",
    "wof:placetype":"venue"
},
  "geometry": {"coordinates":[-93.260198,37.071253],"type":"Point"}
}