{
  "type": "Feature",
  "properties": {
    "iso:country":"US",
    "sg:address":"105 Foursome Ln",
    "sg:city":"Carl Junction",
    "sg:classifiers":[
        {
            "category":"Professional",
            "subcategory":"Advertising",
            "type":"Services"
        }
    ],
    "sg:phone":"+1 417 649 6295",
    "sg:postcode":"64834",
    "sg:province":"MO",
    "wof:name":"FSBOLOCAL.COM",
    "wof:placetype":"venue"
},
  "geometry": {"coordinates":[-94.53622300000001,37.162357],"type":"Point"}
}