{
  "type": "Feature",
  "properties": {
    "iso:country":"US",
    "sg:address":"1806 US Hwy 63",
    "sg:city":"Rolla",
    "sg:classifiers":[
        {
            "category":"Shopping",
            "subcategory":"Bicycles & Sporting Goods",
            "type":"Retail Goods"
        }
    ],
    "sg:phone":"+1 573 368 4433",
    "sg:postcode":"65401",
    "sg:province":"MO",
    "sg:tags":[
        "bait",
        "fishing"
    ],
    "wof:name":"Dk's Good Vibrations",
    "wof:placetype":"venue"
},
  "geometry": {"coordinates":[-91.770011,37.959631],"type":"Point"}
}