{
  "type": "Feature",
  "properties": {
    "iso:country":"US",
    "sg:address":"1169 W Highpoint St",
    "sg:city":"Springfield",
    "sg:classifiers":[
        {
            "category":"Real Estate",
            "subcategory":"Real Estate Operator",
            "type":"Services"
        }
    ],
    "sg:phone":"+1 417 886 2603",
    "sg:postcode":"65810",
    "sg:province":"MO",
    "sg:tags":[
        "property",
        "lessor"
    ],
    "wof:name":"Mgc Properties LLC",
    "wof:placetype":"venue"
},
  "geometry": {"coordinates":[-93.309066,37.113332],"type":"Point"}
}