{
  "type": "Feature",
  "properties": {
    "iso:country":"US",
    "sg:address":"252 Old Sulphur Springs Rd",
    "sg:city":"Ballwin",
    "sg:classifiers":[
        {
            "category":"Wholesale",
            "subcategory":"Stationery",
            "type":"Manufacturing & Wholesale Goods"
        }
    ],
    "sg:phone":"+1 636 469 9636",
    "sg:postcode":"63021",
    "sg:province":"MO",
    "sg:tags":[
        "wholesaler",
        "product",
        "promotional"
    ],
    "wof:name":"Design Distribution Intl",
    "wof:placetype":"venue"
},
  "geometry": {"coordinates":[-90.51993899999999,38.589762],"type":"Point"}
}