{
  "type": "Feature",
  "properties": {
    "iso:country":"US",
    "sg:address":"7533 N Lindbergh Blvd",
    "sg:city":"Hazelwood",
    "sg:classifiers":[
        {
            "category":"Manufacturing",
            "subcategory":"Signs",
            "type":"Manufacturing & Wholesale Goods"
        }
    ],
    "sg:phone":"+1 314 838 6500",
    "sg:postcode":"63042",
    "sg:province":"MO",
    "sg:tags":[
        "manufacture"
    ],
    "wof:name":"Sign-A-Rama",
    "wof:placetype":"venue"
},
  "geometry": {"coordinates":[-90.35279800000001,38.785479],"type":"Point"}
}