{
  "type": "Feature",
  "properties": {
    "iso:country":"US",
    "sg:address":"5601 S Rte K",
    "sg:city":"Columbia",
    "sg:classifiers":[
        {
            "category":"Arts & Performance",
            "subcategory":"Theater",
            "type":"Entertainment"
        }
    ],
    "sg:phone":"+1 573 875 8754",
    "sg:postcode":"65203",
    "sg:province":"MO",
    "sg:tags":[
        "group"
    ],
    "wof:name":"Borlaheel Godnight Productions",
    "wof:placetype":"venue"
},
  "geometry": {"coordinates":[-92.34053,38.88742],"type":"Point"}
}