{
  "type": "Feature",
  "properties": {
    "iso:country":"US",
    "sg:address":"307 Shoreview Dr",
    "sg:city":"Raymore",
    "sg:classifiers":[
        {
            "category":"Real Estate",
            "subcategory":"Real Estate Agent",
            "type":"Services"
        }
    ],
    "sg:phone":"+1 816 678 9211",
    "sg:postcode":"64083",
    "sg:province":"MO",
    "wof:name":"Realty Group LLC",
    "wof:placetype":"venue"
},
  "geometry": {"coordinates":[-94.467489,38.801245],"type":"Point"}
}