{
  "type": "Feature",
  "properties": {
    "iso:country":"US",
    "sg:address":"868 Katie Trail Rd",
    "sg:city":"Lonedell",
    "sg:classifiers":[
        {
            "category":"Utilities",
            "subcategory":"Water",
            "type":"Services"
        },
        {
            "category":"Building & Trades",
            "subcategory":"Plumbing",
            "type":"Services"
        },
        {
            "category":"Home & Garden",
            "subcategory":"Hardware",
            "type":"Retail Goods"
        }
    ],
    "sg:phone":"+1 636 629 8205",
    "sg:postcode":"63060",
    "sg:province":"MO",
    "sg:tags":[
        "plumber",
        "industrial",
        "well",
        "pumping",
        "contractor",
        "pump",
        "contractors-commercial",
        "drilling"
    ],
    "wof:name":"Midwest Pump & Well Svc",
    "wof:placetype":"venue"
},
  "geometry": {"coordinates":[-90.864197,38.268985],"type":"Point"}
}