{
  "type": "Feature",
  "properties": {
    "iso:country":"US",
    "sg:address":"19256 Brookhollow Dr",
    "sg:city":"Glencoe",
    "sg:classifiers":[
        {
            "category":"Manufacturing",
            "subcategory":"Apparel",
            "type":"Manufacturing & Wholesale Goods"
        }
    ],
    "sg:phone":"+1 636 458 8561",
    "sg:postcode":"63038",
    "sg:province":"MO",
    "sg:tags":[
        "manufacture",
        "representative"
    ],
    "wof:name":"Specialty Metal Sales",
    "wof:placetype":"venue"
},
  "geometry": {"coordinates":[-90.714786,38.594492],"type":"Point"}
}