{
  "type": "Feature",
  "properties": {
    "iso:country":"US",
    "sg:address":"310 E Main St",
    "sg:city":"Fillmore",
    "sg:classifiers":[
        {
            "category":"Professional",
            "type":"Services"
        }
    ],
    "sg:phone":"+1 816 487 3620",
    "sg:postcode":"64449",
    "sg:province":"MO",
    "wof:name":"Zag Bag Designs",
    "wof:placetype":"venue"
},
  "geometry": {"coordinates":[-94.97143,40.025034],"type":"Point"}
}