{
  "type": "Feature",
  "properties": {
    "iso:country":"US",
    "sg:address":"115 S 7th St",
    "sg:city":"Hannibal",
    "sg:classifiers":[
        {
            "category":"Banks & Credit Unions",
            "subcategory":"Bank",
            "type":"Services"
        }
    ],
    "sg:phone":"+1 573 221 4222",
    "sg:postcode":"63401",
    "sg:province":"MO",
    "sg:tags":[
        "correspondent",
        "banker",
        "mortgage"
    ],
    "wof:name":"C & M Mortgage Inc",
    "wof:placetype":"venue"
},
  "geometry": {"coordinates":[-91.36144400000001,39.707142],"type":"Point"}
}