{
  "type": "Feature",
  "properties": {
    "iso:country":"US",
    "sg:address":"4291 Olive St",
    "sg:city":"Saint Louis",
    "sg:classifiers":[
        {
            "category":"Organizations",
            "subcategory":"Non-profit Organization",
            "type":"Services"
        }
    ],
    "sg:phone":"+1 314 652 2727",
    "sg:postcode":"63108",
    "sg:province":"MO",
    "sg:tags":[
        "service/non-profit",
        "community"
    ],
    "wof:name":"Daughters of Charity",
    "wof:placetype":"venue"
},
  "geometry": {"coordinates":[-90.24844,38.64547],"type":"Point"}
}