{
  "type": "Feature",
  "properties": {
    "iso:country":"US",
    "sg:address":"111 SW Cole Younger Dr",
    "sg:city":"Lees Summit",
    "sg:classifiers":[
        {
            "category":"Real Estate",
            "subcategory":"Real Estate Agent",
            "type":"Services"
        }
    ],
    "sg:phone":"+1 816 537 6656",
    "sg:postcode":"64082",
    "sg:province":"MO",
    "wof:name":"Raintree Lake Realty",
    "wof:placetype":"venue"
},
  "geometry": {"coordinates":[-94.385189,38.843534],"type":"Point"}
}