{
  "type": "Feature",
  "properties": {
    "iso:country":"US",
    "sg:address":"2640 E 32nd St",
    "sg:city":"Joplin",
    "sg:classifiers":[
        {
            "category":"Banks & Credit Unions",
            "subcategory":"Financial Services",
            "type":"Services"
        }
    ],
    "sg:phone":"+1 417 782 3800",
    "sg:postcode":"64804",
    "sg:province":"MO",
    "sg:tags":[
        "loan",
        "alternative",
        "financing",
        "payday"
    ],
    "sg:website":"http://www.heightsfinance.com",
    "wof:name":"Heights Finance Corporation",
    "wof:placetype":"venue"
},
  "geometry": {"coordinates":[-94.545654,37.055431],"type":"Point"}
}