{
  "type": "Feature",
  "properties": {
    "iso:country":"US",
    "sg:address":"924 NE Westwind Cir",
    "sg:city":"Lees Summit",
    "sg:classifiers":[
        {
            "category":"Building & Trades",
            "subcategory":"Construction",
            "type":"Services"
        }
    ],
    "sg:phone":"+1 816 246 8215",
    "sg:postcode":"64086",
    "sg:province":"MO",
    "sg:tags":[
        "hanging",
        "contractor"
    ],
    "wof:name":"Sheafer Painting",
    "wof:placetype":"venue"
},
  "geometry": {"coordinates":[-94.35655300000001,38.925725],"type":"Point"}
}