{
  "type": "Feature",
  "properties": {
    "addr:full":"251 Chesterfield Mall Chesterfield MO 63017",
    "addr:housenumber":"251",
    "addr:postcode":"63017",
    "addr:street":"Chesterfield Mall",
    "iso:country":"US",
    "sg:address":"251 Chesterfield Mall",
    "sg:city":"Chesterfield",
    "sg:classifiers":[
        {
            "category":"Shopping",
            "subcategory":"Clothing, Apparel, & Fashions",
            "type":"Retail Goods"
        }
    ],
    "sg:phone":"+1 636 536 9763",
    "sg:postcode":"63017",
    "sg:province":"MO",
    "wof:name":"Banana Republic",
    "wof:placetype":"venue"
},
  "geometry": {"coordinates":[-90.56188,38.650406],"type":"Point"}
}