{
  "type": "Feature",
  "properties": {
    "iso:country":"US",
    "sg:address":"1135 S Kirkwood Rd",
    "sg:city":"St Louis",
    "sg:classifiers":[
        {
            "category":"Shopping",
            "subcategory":"Department Store",
            "type":"Retail Goods"
        }
    ],
    "sg:phone":"+1 314 822 0165",
    "sg:postcode":"63122",
    "sg:province":"MO",
    "sg:tags":[
        "shop"
    ],
    "wof:name":"Dollar Tree",
    "wof:placetype":"venue"
},
  "geometry": {"coordinates":[-90.406789,38.563458],"type":"Point"}
}