{
  "type": "Feature",
  "properties": {
    "iso:country":"US",
    "sg:address":"13 W 21st St",
    "sg:city":"Higginsville",
    "sg:classifiers":[
        {
            "category":"Restaurant",
            "type":"Food & Drink"
        }
    ],
    "sg:phone":"+1 660 584 5400",
    "sg:postcode":"64037",
    "sg:province":"MO",
    "sg:tags":[
        "eating"
    ],
    "wof:name":"Ribs & More",
    "wof:placetype":"venue"
},
  "geometry": {"coordinates":[-93.718304,39.073971],"type":"Point"}
}