{
  "type": "Feature",
  "properties": {
    "iso:country":"US",
    "sg:address":"7223 Anna Ave",
    "sg:city":"Saint Louis",
    "sg:classifiers":[
        {
            "category":"Real Estate",
            "subcategory":"Real Estate Operator",
            "type":"Services"
        }
    ],
    "sg:phone":"+1 314 647 7368",
    "sg:postcode":"63143",
    "sg:province":"MO",
    "sg:tags":[
        "apartment"
    ],
    "wof:name":"Maplewood Village Apt",
    "wof:placetype":"venue"
},
  "geometry": {"coordinates":[-90.31390399999999,38.6115],"type":"Point"}
}