{
  "type": "Feature",
  "properties": {
    "iso:country":"US",
    "sg:address":"392 N Euclid Ave",
    "sg:city":"Saint Louis",
    "sg:classifiers":[
        {
            "category":"Restaurant",
            "type":"Food & Drink"
        }
    ],
    "sg:phone":"+1 314 361 0522",
    "sg:postcode":"63108",
    "sg:province":"MO",
    "sg:tags":[
        "new",
        "american",
        "brunch",
        "breakfast"
    ],
    "sg:website":"www.dineatduffs.com",
    "wof:name":"Duff's Restaurant",
    "wof:placetype":"venue"
},
  "geometry": {"coordinates":[-90.261053,38.647907],"type":"Point"}
}