{
  "type": "Feature",
  "properties": {
    "iso:country":"US",
    "sg:address":"822 N Bellefontaine Ave",
    "sg:city":"Kansas City",
    "sg:classifiers":[
        {
            "category":"Manufacturing",
            "subcategory":"Wood Products",
            "type":"Manufacturing & Wholesale Goods"
        }
    ],
    "sg:phone":"+1 816 231 1813",
    "sg:postcode":"64120",
    "sg:province":"MO",
    "sg:tags":[
        "equipment",
        "industrial",
        "mfg"
    ],
    "wof:name":"Pallet Solutions Inc",
    "wof:placetype":"venue"
},
  "geometry": {"coordinates":[-94.54491,39.124024],"type":"Point"}
}