{
  "type": "Feature",
  "properties": {
    "iso:country":"US",
    "sg:address":"1000 Executive Parkway Dr",
    "sg:city":"Saint Louis",
    "sg:classifiers":[
        {
            "category":"Organizations",
            "subcategory":"Non-profit Organization",
            "type":"Services"
        }
    ],
    "sg:phone":"+1 314 576 7730",
    "sg:postcode":"63141",
    "sg:province":"MO",
    "sg:tags":[
        "social"
    ],
    "wof:name":"Alpha Zeta Fraternity",
    "wof:placetype":"venue"
},
  "geometry": {"coordinates":[-90.472396,38.675197],"type":"Point"}
}