{
  "type": "Feature",
  "properties": {
    "iso:country":"US",
    "sg:address":"100 N Pine St",
    "sg:city":"Cole Camp",
    "sg:classifiers":[
        {
            "category":"Real Estate",
            "subcategory":"Real Estate Agent",
            "type":"Services"
        }
    ],
    "sg:phone":"+1 660 668 3905",
    "sg:postcode":"65325",
    "sg:province":"MO",
    "wof:name":"Co-Ca-Mo Realty",
    "wof:placetype":"venue"
},
  "geometry": {"coordinates":[-93.20002599999999,38.461276],"type":"Point"}
}