{
  "type": "Feature",
  "properties": {
    "iso:country":"US",
    "sg:address":"2819 S 18th St",
    "sg:city":"Saint Louis",
    "sg:classifiers":[
        {
            "category":"Professional",
            "subcategory":"Art Services",
            "type":"Services"
        }
    ],
    "sg:phone":"+1 314 771 0866",
    "sg:postcode":"63118",
    "sg:province":"MO",
    "sg:tags":[
        "commercial",
        "design",
        "architectural"
    ],
    "wof:name":"Improveyes Inc",
    "wof:placetype":"venue"
},
  "geometry": {"coordinates":[-90.21616,38.599238],"type":"Point"}
}