{
  "type": "Feature",
  "properties": {
    "iso:country":"US",
    "sg:address":"24001 S Chadwick Dr",
    "sg:city":"Peculiar",
    "sg:classifiers":[
        {
            "category":"Freight",
            "type":"Transportation"
        }
    ],
    "sg:phone":"+1 816 365 1281",
    "sg:postcode":"64078",
    "sg:province":"MO",
    "sg:tags":[
        "distance",
        "long",
        "trucking"
    ],
    "wof:name":"R & C Trucking",
    "wof:placetype":"venue"
},
  "geometry": {"coordinates":[-94.46843800000001,38.687456],"type":"Point"}
}