{
  "type": "Feature",
  "properties": {
    "iso:country":"US",
    "sg:address":"17053 US Hwy 71",
    "sg:city":"Belton",
    "sg:classifiers":[
        {
            "category":"Health Services",
            "subcategory":"Doctor",
            "type":"Services"
        }
    ],
    "sg:phone":"+1 816 331 4000",
    "sg:postcode":"64012",
    "sg:province":"MO",
    "sg:tags":[
        "physician",
        "surgeon"
    ],
    "wof:name":"HCA Midwest Medicine Assoc",
    "wof:placetype":"venue"
},
  "geometry": {"coordinates":[-94.504724,38.81435],"type":"Point"}
}