{
  "type": "Feature",
  "properties": {
    "iso:country":"US",
    "sg:address":"9140 Ward Pkwy S",
    "sg:city":"Kansas City",
    "sg:classifiers":[
        {
            "category":"Professional",
            "subcategory":"Lawyer & Legal Services",
            "type":"Services"
        }
    ],
    "sg:phone":"+1 816 822 8100",
    "sg:postcode":"64114",
    "sg:province":"MO",
    "sg:tags":[
        "attorney"
    ],
    "wof:name":"Gallas & Schultz",
    "wof:placetype":"venue"
},
  "geometry": {"coordinates":[-94.604232,38.963307],"type":"Point"}
}