{
  "type": "Feature",
  "properties": {
    "iso:country":"US",
    "sg:address":"115 S Main St",
    "sg:city":"Carthage",
    "sg:classifiers":[
        {
            "category":"Food & Beverages",
            "subcategory":"Bakery",
            "type":"Retail Goods"
        }
    ],
    "sg:phone":"+1 417 358 7708",
    "sg:postcode":"64836",
    "sg:province":"MO",
    "wof:name":"Panaderia El Quetzal",
    "wof:placetype":"venue"
},
  "geometry": {"coordinates":[-94.31097800000001,37.178495],"type":"Point"}
}