{
  "type": "Feature",
  "properties": {
    "iso:country":"US",
    "sg:address":"401 W Coates St",
    "sg:city":"Moberly",
    "sg:classifiers":[
        {
            "category":"Autos & Motor Vehicles",
            "subcategory":"Recreational Vehicle Sales",
            "type":"Retail Goods"
        }
    ],
    "sg:phone":"+1 660 263 5992",
    "sg:postcode":"65270",
    "sg:province":"MO",
    "wof:name":"U-Haul",
    "wof:placetype":"venue"
},
  "geometry": {"coordinates":[-92.441413,39.420819],"type":"Point"}
}