{
  "type": "Feature",
  "properties": {
    "iso:country":"US",
    "sg:address":"7 Huntleigh Woods",
    "sg:city":"Barnhart",
    "sg:classifiers":[
        {
            "category":"Farming",
            "subcategory":"Farm",
            "type":"Manufacturing & Wholesale Goods"
        }
    ],
    "sg:phone":"+1 636 464 7308",
    "sg:postcode":"63012",
    "sg:province":"MO",
    "sg:tags":[
        "crop",
        "general"
    ],
    "wof:name":"Mitchell Wilson",
    "wof:placetype":"venue"
},
  "geometry": {"coordinates":[-90.39396499999999,38.353437],"type":"Point"}
}