{
  "type": "Feature",
  "properties": {
    "iso:country":"US",
    "sg:address":"1419 Iowa Ave",
    "sg:city":"Joplin",
    "sg:classifiers":[
        {
            "category":"Personal",
            "subcategory":"Beauty Salon",
            "type":"Services"
        }
    ],
    "sg:phone":"+1 417 206 0866",
    "sg:postcode":"64801",
    "sg:province":"MO",
    "sg:tags":[
        "shop"
    ],
    "wof:name":"New Impressions",
    "wof:placetype":"venue"
},
  "geometry": {"coordinates":[-94.507231,37.075048],"type":"Point"}
}