{
  "type": "Feature",
  "properties": {
    "iso:country":"US",
    "sg:address":"303 N 2nd St",
    "sg:city":"Clinton",
    "sg:classifiers":[
        {
            "category":"Banks & Credit Unions",
            "subcategory":"Bank",
            "type":"Services"
        }
    ],
    "sg:phone":"+1 660 885 6881",
    "sg:postcode":"64735",
    "sg:province":"MO",
    "sg:tags":[
        "depository",
        "banking"
    ],
    "wof:name":"National Tiltle Loans",
    "wof:placetype":"venue"
},
  "geometry": {"coordinates":[-93.77390800000001,38.374699],"type":"Point"}
}