{
  "type": "Feature",
  "properties": {
    "iso:country":"US",
    "sg:address":"480 Main St",
    "sg:city":"Troy",
    "sg:classifiers":[
        {
            "category":"Organizations",
            "subcategory":"Religious Organization",
            "type":"Services"
        }
    ],
    "sg:phone":"+1 636 528 5362",
    "sg:postcode":"63379",
    "sg:province":"MO",
    "wof:name":"Louisiana Divisional Mission",
    "wof:placetype":"venue"
},
  "geometry": {"coordinates":[-90.980981,38.979062],"type":"Point"}
}