{
  "type": "Feature",
  "properties": {
    "iso:country":"US",
    "sg:address":"4615 Lindell Blvd Apt 204",
    "sg:city":"Saint Louis",
    "sg:classifiers":[
        {
            "category":"Real Estate",
            "subcategory":"Real Estate Operator",
            "type":"Services"
        }
    ],
    "sg:phone":"+1 314 367 1207",
    "sg:postcode":"63108",
    "sg:province":"MO",
    "sg:tags":[
        "apartment"
    ],
    "wof:name":"President Apartments",
    "wof:placetype":"venue"
},
  "geometry": {"coordinates":[-90.254402,38.644699],"type":"Point"}
}