{
  "type": "Feature",
  "properties": {
    "addr:full":"307 Marshall St Jefferson City MO 65101",
    "addr:housenumber":"307",
    "addr:postcode":"65101",
    "addr:street":"Marshall St",
    "iso:country":"US",
    "sg:address":"307 Marshall St",
    "sg:city":"Jefferson City",
    "sg:classifiers":[
        {
            "category":"Professional",
            "subcategory":"Business Services",
            "type":"Services"
        }
    ],
    "sg:phone":"+1 573 632 4400",
    "sg:postcode":"65101",
    "sg:province":"MO",
    "wof:name":"ServiceMaster",
    "wof:placetype":"venue"
},
  "geometry": {"coordinates":[-92.16598399999999,38.572275],"type":"Point"}
}