{
  "type": "Feature",
  "properties": {
    "iso:country":"US",
    "sg:address":"9264 Watson Rd",
    "sg:city":"St Louis",
    "sg:classifiers":[
        {
            "category":"Personal",
            "subcategory":"Beauty Salon",
            "type":"Services"
        }
    ],
    "sg:phone":"+1 314 843 9920",
    "sg:postcode":"63126",
    "sg:province":"MO",
    "wof:name":"Salon Mystique",
    "wof:placetype":"venue"
},
  "geometry": {"coordinates":[-90.374501,38.559706],"type":"Point"}
}