{
  "type": "Feature",
  "properties": {
    "iso:country":"US",
    "sg:address":"14506 US Hwy 169",
    "sg:city":"Smithville",
    "sg:classifiers":[
        {
            "category":"Freight",
            "type":"Transportation"
        }
    ],
    "sg:phone":"+1 816 532 6220",
    "sg:postcode":"64089",
    "sg:province":"MO",
    "sg:tags":[
        "general"
    ],
    "wof:name":"Smithville Self Storage",
    "wof:placetype":"venue"
},
  "geometry": {"coordinates":[-94.584017,39.359592],"type":"Point"}
}