{
  "type": "Feature",
  "properties": {
    "iso:country":"US",
    "sg:address":"8077 Watson Rd",
    "sg:city":"Webster Groves",
    "sg:classifiers":[
        {
            "category":"Manufacturing",
            "subcategory":"Printing",
            "type":"Manufacturing & Wholesale Goods"
        }
    ],
    "sg:phone":"+1 314 961 3499",
    "sg:postcode":"63119",
    "sg:province":"MO",
    "sg:tags":[
        "printer"
    ],
    "wof:name":"Carren Associates",
    "wof:placetype":"venue"
},
  "geometry": {"coordinates":[-90.342826,38.567597],"type":"Point"}
}