{
  "type": "Feature",
  "properties": {
    "iso:country":"US",
    "sg:address":"10450 Co Rd 2000",
    "sg:city":"Rolla",
    "sg:classifiers":[
        {
            "category":"Local Transit",
            "type":"Transportation"
        }
    ],
    "sg:phone":"+1 573 364 4349",
    "sg:postcode":"65401",
    "sg:province":"MO",
    "sg:tags":[
        "limousine"
    ],
    "wof:name":"Rockhard Limousine",
    "wof:placetype":"venue"
},
  "geometry": {"coordinates":[-91.747733,37.977281],"type":"Point"}
}