{
  "type": "Feature",
  "properties": {
    "iso:country":"US",
    "sg:address":"3321 E 30 St",
    "sg:city":"Kansas City",
    "sg:classifiers":[
        {
            "category":"Social Services",
            "subcategory":"Child Care",
            "type":"Services"
        }
    ],
    "sg:phone":"+1 816 861 1665",
    "sg:postcode":"64128",
    "sg:province":"MO",
    "wof:name":"Love N Hugs Christian Child Cr",
    "wof:placetype":"venue"
},
  "geometry": {"coordinates":[-94.543718,39.071296],"type":"Point"}
}