{
  "type": "Feature",
  "properties": {
    "iso:country":"US",
    "sg:address":"1048 S Moore School Rd",
    "sg:city":"Troy",
    "sg:classifiers":[
        {
            "category":"Farming",
            "subcategory":"Livestock Farm",
            "type":"Manufacturing & Wholesale Goods"
        }
    ],
    "sg:phone":"+1 636 528 4150",
    "sg:postcode":"63379",
    "sg:province":"MO",
    "sg:tags":[
        "feedlot",
        "hog",
        "or",
        "beef",
        "cattle"
    ],
    "wof:name":"Robert Brown",
    "wof:placetype":"venue"
},
  "geometry": {"coordinates":[-91.03614,38.930434],"type":"Point"}
}