{
  "type": "Feature",
  "properties": {
    "iso:country":"US",
    "sg:address":"3801 N 29th St",
    "sg:city":"St Joseph",
    "sg:classifiers":[
        {
            "category":"Health Services",
            "subcategory":"Clinic",
            "type":"Services"
        }
    ],
    "sg:phone":"+1 816 387 7874",
    "sg:postcode":"64506",
    "sg:province":"MO",
    "sg:tags":[
        "hypnotherapy"
    ],
    "wof:name":"Rush Hypnosis",
    "wof:placetype":"venue"
},
  "geometry": {"coordinates":[-94.823685,39.801514],"type":"Point"}
}