{
  "type": "Feature",
  "properties": {
    "iso:country":"US",
    "sg:address":"2121 Ashley Ct",
    "sg:city":"Arnold",
    "sg:classifiers":[
        {
            "category":"Health Services",
            "subcategory":"Clinic",
            "type":"Services"
        }
    ],
    "sg:phone":"+1 636 296 1964",
    "sg:postcode":"63010",
    "sg:province":"MO",
    "sg:tags":[
        "personal",
        "kidney",
        "dialysis",
        "center"
    ],
    "wof:name":"Fresenius Usa Inc",
    "wof:placetype":"venue"
},
  "geometry": {"coordinates":[-90.39870500000001,38.428726],"type":"Point"}
}