{
  "type": "Feature",
  "properties": {
    "iso:country":"US",
    "sg:address":"197 Highway W",
    "sg:city":"Eldon",
    "sg:classifiers":[
        {
            "category":"Shopping",
            "type":"Retail Goods"
        }
    ],
    "sg:phone":"+1 573 365 1190",
    "sg:postcode":"65026",
    "sg:province":"MO",
    "sg:tags":[
        "merchandise"
    ],
    "wof:name":"Grandpas Rock Shop",
    "wof:placetype":"venue"
},
  "geometry": {"coordinates":[-92.647982,38.229718],"type":"Point"}
}