{
  "type": "Feature",
  "properties": {
    "iso:country":"US",
    "sg:address":"200 N Center St",
    "sg:city":"Clarence",
    "sg:classifiers":[
        {
            "category":"Government",
            "subcategory":"Fire Station",
            "type":"Public Place"
        }
    ],
    "sg:phone":"+1 660 699 3310",
    "sg:postcode":"63437",
    "sg:province":"MO",
    "sg:tags":[
        "department"
    ],
    "sg:website":"www.clarencemissouri.com",
    "wof:name":"Clarence City Fire Dept",
    "wof:placetype":"venue"
},
  "geometry": {"coordinates":[-92.260947,39.744602],"type":"Point"}
}