{
  "type": "Feature",
  "properties": {
    "iso:country":"US",
    "sg:address":"116 Bethany Rd",
    "sg:city":"Forsyth",
    "sg:classifiers":[
        {
            "category":"Retail",
            "subcategory":"Auto Repair",
            "type":"Services"
        }
    ],
    "sg:phone":"+1 417 546 5809",
    "sg:postcode":"65653",
    "sg:province":"MO",
    "sg:tags":[
        "automotive",
        "general"
    ],
    "wof:name":"All Certified Rv",
    "wof:placetype":"venue"
},
  "geometry": {"coordinates":[-93.12450699999999,36.721615],"type":"Point"}
}