{
  "type": "Feature",
  "properties": {
    "iso:country":"US",
    "sg:address":"2822 Charles St",
    "sg:city":"Saint Joseph",
    "sg:classifiers":[
        {
            "category":"Building & Trades",
            "subcategory":"Construction",
            "type":"Services"
        }
    ],
    "sg:phone":"+1 816 232 9026",
    "sg:postcode":"64501",
    "sg:province":"MO",
    "sg:tags":[
        "house"
    ],
    "wof:name":"Nicks Home Repair",
    "wof:placetype":"venue"
},
  "geometry": {"coordinates":[-94.822754,39.765058],"type":"Point"}
}