{
  "type": "Feature",
  "properties": {
    "iso:country":"US",
    "sg:address":"7585 NW Bridle Parc Ln",
    "sg:city":"Parkville",
    "sg:classifiers":[
        {
            "category":"Social Services",
            "subcategory":"Job Training",
            "type":"Services"
        }
    ],
    "sg:phone":"+1 816 505 1545",
    "sg:postcode":"64152",
    "sg:province":"MO",
    "sg:tags":[
        "rehabilitation"
    ],
    "wof:name":"Stubbe & Assoc Inc",
    "wof:placetype":"venue"
},
  "geometry": {"coordinates":[-94.6819,39.233648],"type":"Point"}
}