{
  "type": "Feature",
  "properties": {
    "iso:country":"US",
    "sg:address":"258 W Main St",
    "sg:city":"Kahoka",
    "sg:classifiers":[
        {
            "category":"Shopping",
            "subcategory":"Clothing, Apparel, & Fashions",
            "type":"Retail Goods"
        }
    ],
    "sg:phone":"+1 660 727 3047",
    "sg:postcode":"63445",
    "sg:province":"MO",
    "sg:tags":[
        "salvage",
        "surplus",
        "merchandise"
    ],
    "wof:name":"Surplus Unlimited",
    "wof:placetype":"venue"
},
  "geometry": {"coordinates":[-91.72112,40.420343],"type":"Point"}
}