{
  "type": "Feature",
  "properties": {
    "iso:country":"US",
    "sg:address":"899 Whitmoor Dr",
    "sg:city":"Saint Charles",
    "sg:classifiers":[
        {
            "category":"Wholesale",
            "subcategory":"Non-durable Goods",
            "type":"Manufacturing & Wholesale Goods"
        }
    ],
    "sg:phone":"+1 636 447 1800",
    "sg:postcode":"63304",
    "sg:province":"MO",
    "sg:tags":[
        "distributor",
        "product"
    ],
    "wof:name":"Tomasi Marketing Solutions LLC",
    "wof:placetype":"venue"
},
  "geometry": {"coordinates":[-90.624267,38.714998],"type":"Point"}
}