{
  "type": "Feature",
  "properties": {
    "iso:country":"US",
    "sg:address":"307 W Jackson St",
    "sg:city":"Mexico",
    "sg:classifiers":[
        {
            "category":"Organizations",
            "subcategory":"Religious Organization",
            "type":"Services"
        }
    ],
    "sg:phone":"+1 573 581 4628",
    "sg:postcode":"65265",
    "sg:province":"MO",
    "sg:tags":[
        "church"
    ],
    "sg:website":"www.fcc-mexicomo.org",
    "wof:name":"First Christian Church",
    "wof:placetype":"venue"
},
  "geometry": {"coordinates":[-91.885732,39.172267],"type":"Point"}
}