{
  "type": "Feature",
  "properties": {
    "iso:country":"US",
    "sg:address":"11721 Lackland Rd",
    "sg:city":"St Louis",
    "sg:classifiers":[
        {
            "category":"Building & Trades",
            "subcategory":"Construction",
            "type":"Services"
        }
    ],
    "sg:phone":"+1 314 567 9915",
    "sg:postcode":"63146",
    "sg:province":"MO",
    "sg:tags":[
        "downspouts",
        "gutter"
    ],
    "sg:website":"www.leafguard.com",
    "wof:name":"Leafguard Of Missouri",
    "wof:placetype":"venue"
},
  "geometry": {"coordinates":[-90.430801,38.697098],"type":"Point"}
}