{
  "type": "Feature",
  "properties": {
    "iso:country":"US",
    "sg:address":"3853 Forest Park Ave",
    "sg:city":"Saint Louis",
    "sg:classifiers":[
        {
            "category":"Retail",
            "subcategory":"Car Wash",
            "type":"Services"
        }
    ],
    "sg:phone":"+1 314 533 1234",
    "sg:postcode":"63108",
    "sg:province":"MO",
    "wof:name":"Gas House Express Carwash Ctr",
    "wof:placetype":"venue"
},
  "geometry": {"coordinates":[-90.2416,38.634602],"type":"Point"}
}