{
  "type": "Feature",
  "properties": {
    "iso:country":"US",
    "sg:address":"41 S Sprigg St",
    "sg:city":"Cape Girardeau",
    "sg:classifiers":[
        {
            "category":"Shopping",
            "subcategory":"Florist",
            "type":"Retail Goods"
        }
    ],
    "sg:phone":"+1 573 334 0303",
    "sg:postcode":"63703",
    "sg:province":"MO",
    "wof:name":"Tonis Flower House Inc",
    "wof:placetype":"venue"
},
  "geometry": {"coordinates":[-89.527158,37.303622],"type":"Point"}
}