{
  "type": "Feature",
  "properties": {
    "iso:country":"US",
    "sg:address":"300 State Hwy 6",
    "sg:city":"Ewing",
    "sg:classifiers":[
        {
            "category":"Restaurant",
            "type":"Food & Drink"
        }
    ],
    "sg:phone":"+1 573 209 3423",
    "sg:postcode":"63447",
    "sg:province":"MO",
    "wof:name":"Edmonston Coop Station & Cafe",
    "wof:placetype":"venue"
},
  "geometry": {"coordinates":[-91.91301,40.116791],"type":"Point"}
}