{
  "type": "Feature",
  "properties": {
    "iso:country":"US",
    "sg:address":"850 E Kearney St",
    "sg:city":"Springfield",
    "sg:classifiers":[
        {
            "category":"Retail",
            "subcategory":"Auto Repair",
            "type":"Services"
        }
    ],
    "sg:phone":"+1 417 862 7333",
    "sg:postcode":"65803",
    "sg:province":"MO",
    "sg:tags":[
        "maintenance"
    ],
    "wof:name":"Jiffy Lube",
    "wof:placetype":"venue"
},
  "geometry": {"coordinates":[-93.280895,37.240565],"type":"Point"}
}