{
  "type": "Feature",
  "properties": {
    "iso:country":"US",
    "sg:address":"13345 Bahnfyre Dr",
    "sg:city":"Saint Louis",
    "sg:classifiers":[
        {
            "category":"Wholesale",
            "subcategory":"Groceries",
            "type":"Manufacturing & Wholesale Goods"
        }
    ],
    "sg:phone":"+1 314 729 0803",
    "sg:postcode":"63128",
    "sg:province":"MO",
    "sg:tags":[
        "general"
    ],
    "wof:name":"Resolve Sales and Marketing",
    "wof:placetype":"venue"
},
  "geometry": {"coordinates":[-90.389188,38.485753],"type":"Point"}
}