{
  "type": "Feature",
  "properties": {
    "iso:country":"US",
    "sg:address":"926 S Clark St",
    "sg:city":"Mexico",
    "sg:classifiers":[
        {
            "category":"Personal",
            "subcategory":"Beauty Salon",
            "type":"Services"
        }
    ],
    "sg:phone":"+1 573 581 7768",
    "sg:postcode":"65265",
    "sg:province":"MO",
    "sg:tags":[
        "shop"
    ],
    "wof:name":"Illusions Unlimited",
    "wof:placetype":"venue"
},
  "geometry": {"coordinates":[-91.88518999999999,39.164712],"type":"Point"}
}