{
  "type": "Feature",
  "properties": {
    "iso:country":"US",
    "sg:address":"17079 Audrain Rd 929",
    "sg:city":"Mexico",
    "sg:classifiers":[
        {
            "category":"Social Services",
            "type":"Services"
        }
    ],
    "sg:phone":"+1 573 581 8202",
    "sg:postcode":"65265",
    "sg:province":"MO",
    "sg:tags":[
        "counseling"
    ],
    "wof:name":"Finck & Associates Inc",
    "wof:placetype":"venue"
},
  "geometry": {"coordinates":[-91.946552,39.088302],"type":"Point"}
}