{
  "type": "Feature",
  "properties": {
    "iso:country":"US",
    "sg:address":"1176 State Hwy H",
    "sg:city":"Troy",
    "sg:classifiers":[
        {
            "category":"Freight",
            "type":"Transportation"
        }
    ],
    "sg:phone":"+1 636 338 9969",
    "sg:postcode":"63379",
    "sg:province":"MO",
    "sg:tags":[
        "operator",
        "local",
        "trucking"
    ],
    "wof:name":"B & G Trucking LLC",
    "wof:placetype":"venue"
},
  "geometry": {"coordinates":[-91.00916100000001,39.013265],"type":"Point"}
}