{
  "type": "Feature",
  "properties": {
    "iso:country":"US",
    "sg:address":"56 Meadowbrook Country Club Ests",
    "sg:city":"Ballwin",
    "sg:classifiers":[
        {
            "category":"Home & Garden",
            "subcategory":"Home Furnishings",
            "type":"Retail Goods"
        }
    ],
    "sg:phone":"+1 636 227 3444",
    "sg:postcode":"63011",
    "sg:province":"MO",
    "sg:tags":[
        "glassware",
        "chinaware"
    ],
    "wof:name":"China Matching Svc",
    "wof:placetype":"venue"
},
  "geometry": {"coordinates":[-90.56588600000001,38.612538],"type":"Point"}
}