{
  "type": "Feature",
  "properties": {
    "iso:country":"US",
    "sg:address":"269 Clarkson Rd",
    "sg:city":"Ballwin",
    "sg:classifiers":[
        {
            "category":"Health Services",
            "subcategory":"Doctor",
            "type":"Services"
        }
    ],
    "sg:phone":"+1 636 394 5200",
    "sg:postcode":"63011",
    "sg:province":"MO",
    "wof:name":"Frith Michael DDS",
    "wof:placetype":"venue"
},
  "geometry": {"coordinates":[-90.585577,38.600586],"type":"Point"}
}