{
  "type": "Feature",
  "properties": {
    "iso:country":"US",
    "sg:address":"326 S 21st St",
    "sg:city":"Saint Louis",
    "sg:classifiers":[
        {
            "category":"Professional",
            "subcategory":"Employment Agencies",
            "type":"Services"
        }
    ],
    "sg:phone":"+1 314 621 4900",
    "sg:postcode":"63103",
    "sg:province":"MO",
    "wof:name":"J E Wottowa & Associates",
    "wof:placetype":"venue"
},
  "geometry": {"coordinates":[-90.21109800000001,38.627998],"type":"Point"}
}