{
  "type": "Feature",
  "properties": {
    "iso:country":"US",
    "sg:address":"120 S Central Ave",
    "sg:city":"St Louis",
    "sg:classifiers":[
        {
            "category":"Wholesale",
            "subcategory":"Photographic Equipment",
            "type":"Manufacturing & Wholesale Goods"
        }
    ],
    "sg:phone":"+1 314 726 1060",
    "sg:postcode":"63105",
    "sg:province":"MO",
    "sg:tags":[
        "identification"
    ],
    "sg:website":"www.laserbandsolutions.com",
    "wof:name":"Laser Band",
    "wof:placetype":"venue"
},
  "geometry": {"coordinates":[-90.338522,38.647902],"type":"Point"}
}