{
  "type": "Feature",
  "properties": {
    "iso:country":"US",
    "sg:address":"8659 Olive Blvd",
    "sg:city":"Saint Louis",
    "sg:classifiers":[
        {
            "category":"Education",
            "subcategory":"School",
            "type":"Public Place"
        }
    ],
    "sg:phone":"+1 314 569 2929",
    "sg:postcode":"63132",
    "sg:province":"MO",
    "wof:name":"Torah Prep School",
    "wof:placetype":"venue"
},
  "geometry": {"coordinates":[-90.356652,38.674082],"type":"Point"}
}