{
  "type": "Feature",
  "properties": {
    "iso:country":"US",
    "sg:address":"1912 Boaz Ave",
    "sg:city":"Kirkwood",
    "sg:classifiers":[
        {
            "category":"Professional",
            "subcategory":"Business Services",
            "type":"Services"
        }
    ],
    "sg:phone":"+1 314 965 3495",
    "sg:postcode":"63122",
    "sg:province":"MO",
    "sg:tags":[
        "interior",
        "consultant",
        "design",
        "decorator"
    ],
    "wof:name":"Its Your Stuff",
    "wof:placetype":"venue"
},
  "geometry": {"coordinates":[-90.43786799999999,38.57616],"type":"Point"}
}