{
  "type": "Feature",
  "properties": {
    "iso:country":"US",
    "sg:address":"13126 US Hwy 71",
    "sg:city":"Grandview",
    "sg:classifiers":[
        {
            "category":"Personal",
            "subcategory":"Beauty Salon",
            "type":"Services"
        }
    ],
    "sg:phone":"+1 816 761 3970",
    "sg:postcode":"64030",
    "sg:province":"MO",
    "wof:name":"Shear Integrity Hair Cutting",
    "wof:placetype":"venue"
},
  "geometry": {"coordinates":[-94.52572499999999,38.883635],"type":"Point"}
}