{
  "type": "Feature",
  "properties": {
    "iso:country":"US",
    "sg:address":"9761 Clayton Rd",
    "sg:city":"St Louis",
    "sg:classifiers":[
        {
            "category":"Banks & Credit Unions",
            "subcategory":"Bank",
            "type":"Services"
        }
    ],
    "sg:phone":"+1 314 994 9968",
    "sg:postcode":"63124",
    "sg:province":"MO",
    "sg:tags":[
        "loan",
        "mortgage",
        "real estate"
    ],
    "wof:name":"Oaktree Mortgage",
    "wof:placetype":"venue"
},
  "geometry": {"coordinates":[-90.390719,38.638188],"type":"Point"}
}