{
  "type": "Feature",
  "properties": {
    "iso:country":"US",
    "sg:address":"1708 Vinyard Rd",
    "sg:city":"Marshfield",
    "sg:classifiers":[
        {
            "category":"Retail",
            "subcategory":"Auto Repair",
            "type":"Services"
        }
    ],
    "sg:phone":"+1 417 859 3970",
    "sg:postcode":"65706",
    "sg:province":"MO",
    "sg:tags":[
        "automotive"
    ],
    "wof:name":"B & E Towing",
    "wof:placetype":"venue"
},
  "geometry": {"coordinates":[-92.919208,37.391448],"type":"Point"}
}