{
  "type": "Feature",
  "properties": {
    "iso:country":"US",
    "sg:address":"310 S Elson St",
    "sg:city":"Kirksville",
    "sg:classifiers":[
        {
            "category":"Professional",
            "subcategory":"Accounting & Tax Preparation",
            "type":"Services"
        }
    ],
    "sg:phone":"+1 660 627 1259",
    "sg:postcode":"63501",
    "sg:province":"MO",
    "sg:tags":[
        "accountant"
    ],
    "wof:name":"John W Gillum CPA",
    "wof:placetype":"venue"
},
  "geometry": {"coordinates":[-92.584338,40.192941],"type":"Point"}
}