{
  "type": "Feature",
  "properties": {
    "iso:country":"US",
    "sg:address":"19109 E 12th Ter Ct N",
    "sg:city":"Independence",
    "sg:classifiers":[
        {
            "category":"Building & Trades",
            "subcategory":"Landscaping Services",
            "type":"Services"
        }
    ],
    "sg:phone":"+1 816 796 9901",
    "sg:postcode":"64056",
    "sg:province":"MO",
    "sg:tags":[
        "landscape"
    ],
    "wof:name":"Break Away Landscaping",
    "wof:placetype":"venue"
},
  "geometry": {"coordinates":[-94.35173,39.125286],"type":"Point"}
}