{
  "type": "Feature",
  "properties": {
    "iso:country":"US",
    "sg:address":"513 W Parker Ave",
    "sg:city":"Chaffee",
    "sg:classifiers":[
        {
            "category":"Building & Trades",
            "subcategory":"Construction",
            "type":"Services"
        }
    ],
    "sg:phone":"+1 573 887 6609",
    "sg:postcode":"63740",
    "sg:province":"MO",
    "sg:tags":[
        "contractor",
        "carpentry"
    ],
    "wof:name":"Sullinger Window and Awning",
    "wof:placetype":"venue"
},
  "geometry": {"coordinates":[-89.665846,37.181811],"type":"Point"}
}