{
  "type": "Feature",
  "properties": {
    "iso:country":"US",
    "sg:address":"430 NW 251 Rd",
    "sg:city":"Clinton",
    "sg:classifiers":[
        {
            "category":"Building & Trades",
            "subcategory":"Construction",
            "type":"Services"
        }
    ],
    "sg:phone":"+1 660 885 6465",
    "sg:postcode":"64735",
    "sg:province":"MO",
    "sg:tags":[
        "house"
    ],
    "wof:name":"Walrath Construction LLC",
    "wof:placetype":"venue"
},
  "geometry": {"coordinates":[-93.81707900000001,38.431585],"type":"Point"}
}