{
  "type": "Feature",
  "properties": {
    "iso:country":"US",
    "sg:address":"7607 NE 74 Ter",
    "sg:city":"Kansas City",
    "sg:classifiers":[
        {
            "category":"Utilities",
            "subcategory":"Telephone",
            "type":"Services"
        }
    ],
    "sg:phone":"+1 816 529 8685",
    "sg:postcode":"64158",
    "sg:province":"MO",
    "sg:tags":[
        "communications"
    ],
    "wof:name":"Show ME Hosting",
    "wof:placetype":"venue"
},
  "geometry": {"coordinates":[-94.49096900000001,39.228018],"type":"Point"}
}