{
  "type": "Feature",
  "properties": {
    "iso:country":"US",
    "sg:address":"2300 Locust St",
    "sg:city":"St Louis",
    "sg:classifiers":[
        {
            "category":"Professional",
            "subcategory":"Advertising",
            "type":"Services"
        }
    ],
    "sg:phone":"+1 314 241 8974",
    "sg:postcode":"63103",
    "sg:province":"MO",
    "sg:tags":[
        "counselor"
    ],
    "sg:website":"www.thenationalsystem.com",
    "wof:name":"1919 Agency",
    "wof:placetype":"venue"
},
  "geometry": {"coordinates":[-90.21375399999999,38.634119],"type":"Point"}
}