{
  "type": "Feature",
  "properties": {
    "iso:country":"US",
    "sg:address":"1221 Locust St Ste 1000",
    "sg:city":"Saint Louis",
    "sg:classifiers":[
        {
            "category":"Professional",
            "subcategory":"Lawyer & Legal Services",
            "type":"Services"
        }
    ],
    "sg:phone":"+1 314 621 4100",
    "sg:postcode":"63103",
    "sg:province":"MO",
    "wof:name":"Parrot James E Atty",
    "wof:placetype":"venue"
},
  "geometry": {"coordinates":[-90.197502,38.6306],"type":"Point"}
}