{
  "type": "Feature",
  "properties": {
    "iso:country":"US",
    "sg:address":"12310 Hibler Rd",
    "sg:city":"Saint Louis",
    "sg:classifiers":[
        {
            "category":"Wholesale",
            "subcategory":"Furniture",
            "type":"Manufacturing & Wholesale Goods"
        }
    ],
    "sg:phone":"+1 314 434 5360",
    "sg:postcode":"63141",
    "sg:province":"MO",
    "sg:tags":[
        "whole",
        "commercial"
    ],
    "wof:name":"Callisto Marketing LLC",
    "wof:placetype":"venue"
},
  "geometry": {"coordinates":[-90.457577,38.662022],"type":"Point"}
}