{
  "type": "Feature",
  "properties": {
    "iso:country":"US",
    "sg:address":"3617 State Hwy 30",
    "sg:city":"Lonedell",
    "sg:classifiers":[
        {
            "category":"Restaurant",
            "type":"Food & Drink"
        }
    ],
    "sg:phone":"+1 636 629 9988",
    "sg:postcode":"63060",
    "sg:province":"MO",
    "wof:name":"Linda's Snack Bar",
    "wof:placetype":"venue"
},
  "geometry": {"coordinates":[-90.83557,38.309069],"type":"Point"}
}