{
  "type": "Feature",
  "properties": {
    "iso:country":"US",
    "sg:address":"27775 E 220th Ave",
    "sg:city":"Bethany",
    "sg:classifiers":[
        {
            "category":"Retail",
            "subcategory":"Animal Services",
            "type":"Services"
        }
    ],
    "sg:phone":"+1 660 425 7510",
    "sg:postcode":"64424",
    "sg:province":"MO",
    "wof:name":"Hickory Hill Arena",
    "wof:placetype":"venue"
},
  "geometry": {"coordinates":[-94.011194,40.316688],"type":"Point"}
}