{
  "type": "Feature",
  "properties": {
    "iso:country":"US",
    "sg:address":"6450 Villa Ave",
    "sg:city":"Saint Louis",
    "sg:classifiers":[
        {
            "category":"Shopping",
            "subcategory":"Music",
            "type":"Retail Goods"
        }
    ],
    "sg:phone":"+1 314 645 5072",
    "sg:postcode":"63139",
    "sg:province":"MO",
    "wof:name":"Mt Record Copying",
    "wof:placetype":"venue"
},
  "geometry": {"coordinates":[-90.29494,38.624567],"type":"Point"}
}