{
  "type": "Feature",
  "properties": {
    "iso:country":"US",
    "sg:address":"518 Rockwood Ct",
    "sg:city":"St Joseph",
    "sg:classifiers":[
        {
            "category":"Insurance",
            "subcategory":"Insurance Agent",
            "type":"Services"
        }
    ],
    "sg:phone":"+1 816 233 5598",
    "sg:postcode":"64506",
    "sg:province":"MO",
    "wof:name":"Ken Glauser Insurance",
    "wof:placetype":"venue"
},
  "geometry": {"coordinates":[-94.77720100000001,39.771985],"type":"Point"}
}