{
  "type": "Feature",
  "properties": {
    "iso:country":"US",
    "sg:address":"1799 Pcr 944",
    "sg:city":"Perryville",
    "sg:classifiers":[
        {
            "category":"Shopping",
            "subcategory":"Pets & Pet Supplies",
            "type":"Retail Goods"
        }
    ],
    "sg:phone":"+1 573 543 2401",
    "sg:postcode":"63775",
    "sg:province":"MO",
    "sg:tags":[
        "feed"
    ],
    "wof:name":"Leonard Esselman",
    "wof:placetype":"venue"
},
  "geometry": {"coordinates":[-89.841652,37.892296],"type":"Point"}
}