{
  "type": "Feature",
  "properties": {
    "iso:country":"US",
    "sg:address":"705 Independence Ave",
    "sg:city":"Kennett",
    "sg:classifiers":[
        {
            "category":"Health Services",
            "subcategory":"Doctor",
            "type":"Services"
        }
    ],
    "sg:phone":"+1 573 888 4514",
    "sg:postcode":"63857",
    "sg:province":"MO",
    "sg:tags":[
        "physician",
        "surgeon"
    ],
    "wof:name":"Heartland Healthcare Inc",
    "wof:placetype":"venue"
},
  "geometry": {"coordinates":[-90.033186,36.243417],"type":"Point"}
}