{
  "type": "Feature",
  "properties": {
    "iso:country":"US",
    "sg:address":"18102 E 19 St N",
    "sg:city":"Independence",
    "sg:classifiers":[
        {
            "category":"Sports & Exercise",
            "subcategory":"Gym",
            "type":"Entertainment"
        }
    ],
    "sg:phone":"+1 816 796 8619",
    "sg:postcode":"64058",
    "sg:province":"MO",
    "sg:tags":[
        "consulting",
        "fitness"
    ],
    "wof:name":"Kathryn Delight Todd",
    "wof:placetype":"venue"
},
  "geometry": {"coordinates":[-94.36342999999999,39.137532],"type":"Point"}
}