{
  "type": "Feature",
  "properties": {
    "iso:country":"US",
    "sg:address":"5703 N Flora Ave",
    "sg:city":"Kansas City",
    "sg:classifiers":[
        {
            "category":"Social Services",
            "subcategory":"Child Care",
            "type":"Services"
        }
    ],
    "sg:phone":"+1 816 455 3364",
    "sg:postcode":"64118",
    "sg:province":"MO",
    "sg:tags":[
        "day"
    ],
    "wof:name":"Ican",
    "wof:placetype":"venue"
},
  "geometry": {"coordinates":[-94.562448,39.199398],"type":"Point"}
}