{
  "type": "Feature",
  "properties": {
    "iso:country":"US",
    "sg:address":"1419 N Belcrest Ave",
    "sg:city":"Springfield",
    "sg:classifiers":[
        {
            "category":"Shopping",
            "type":"Retail Goods"
        }
    ],
    "sg:phone":"+1 417 866 8989",
    "sg:postcode":"65802",
    "sg:province":"MO",
    "sg:tags":[
        "product",
        "promotional"
    ],
    "sg:website":"www.elitepromo.com",
    "wof:name":"Elite Promotions Inc",
    "wof:placetype":"venue"
},
  "geometry": {"coordinates":[-93.233098,37.223384],"type":"Point"}
}