{
  "type": "Feature",
  "properties": {
    "iso:country":"US",
    "sg:address":"12545 Olive Blvd",
    "sg:city":"Saint Louis",
    "sg:classifiers":[
        {
            "category":"Professional",
            "subcategory":"Art Services",
            "type":"Services"
        }
    ],
    "sg:phone":"+1 314 576 7752",
    "sg:postcode":"63141",
    "sg:province":"MO",
    "sg:tags":[
        "photography",
        "commercial"
    ],
    "wof:name":"Professional Photographic Svcs",
    "wof:placetype":"venue"
},
  "geometry": {"coordinates":[-90.465152,38.676639],"type":"Point"}
}