{
  "type": "Feature",
  "properties": {
    "iso:country":"US",
    "sg:address":"5509 Wornall Rd",
    "sg:city":"Kansas City",
    "sg:classifiers":[
        {
            "category":"Shopping",
            "type":"Retail Goods"
        }
    ],
    "sg:phone":"+1 816 361 1794",
    "sg:postcode":"64113",
    "sg:province":"MO",
    "sg:tags":[
        "telephone",
        "cellular"
    ],
    "wof:name":"Wireless Today Inc",
    "wof:placetype":"venue"
},
  "geometry": {"coordinates":[-94.592366,39.026605],"type":"Point"}
}