{
  "type": "Feature",
  "properties": {
    "iso:country":"US",
    "sg:address":"1231 Wildhorse Parkway Dr",
    "sg:city":"Chesterfield",
    "sg:classifiers":[
        {
            "category":"Real Estate",
            "subcategory":"Real Estate Agent",
            "type":"Services"
        }
    ],
    "sg:phone":"+1 636 532 2604",
    "sg:postcode":"63005",
    "sg:province":"MO",
    "wof:name":"Temporary VIP Suites",
    "wof:placetype":"venue"
},
  "geometry": {"coordinates":[-90.629475,38.649637],"type":"Point"}
}