{
  "type": "Feature",
  "properties": {
    "iso:country":"US",
    "sg:address":"281 Spring Garden Rd",
    "sg:city":"Olean",
    "sg:classifiers":[
        {
            "category":"Building & Trades",
            "subcategory":"Construction",
            "type":"Services"
        }
    ],
    "sg:phone":"+1 573 392 5149",
    "sg:postcode":"65064",
    "sg:province":"MO",
    "sg:tags":[
        "excavating",
        "contractor"
    ],
    "wof:name":"Everett Winters Excavating",
    "wof:placetype":"venue"
},
  "geometry": {"coordinates":[-92.446093,38.389752],"type":"Point"}
}