{
  "type": "Feature",
  "properties": {
    "iso:country":"US",
    "sg:address":"6614 Clayton Rd",
    "sg:city":"Saint Louis",
    "sg:classifiers":[
        {
            "category":"Real Estate",
            "subcategory":"Architect",
            "type":"Services"
        }
    ],
    "sg:phone":"+1 314 504 0405",
    "sg:postcode":"63117",
    "sg:province":"MO",
    "sg:tags":[
        "architectural"
    ],
    "wof:name":"Ray L Crader Architect",
    "wof:placetype":"venue"
},
  "geometry": {"coordinates":[-90.315546,38.634396],"type":"Point"}
}