{
  "type": "Feature",
  "properties": {
    "iso:country":"US",
    "sg:address":"4805 Theiss Rd",
    "sg:city":"St Louis",
    "sg:classifiers":[
        {
            "category":"Wholesale",
            "subcategory":"Machinery & Supplies",
            "type":"Manufacturing & Wholesale Goods"
        }
    ],
    "sg:phone":"+1 314 892 4431",
    "sg:postcode":"63128",
    "sg:province":"MO",
    "sg:tags":[
        "machine",
        "cutting",
        "paper",
        "drilling"
    ],
    "wof:name":"Tichacek Cutter & Drill",
    "wof:placetype":"venue"
},
  "geometry": {"coordinates":[-90.35099700000001,38.505238],"type":"Point"}
}