{
  "type": "Feature",
  "properties": {
    "iso:country":"US",
    "sg:address":"1823 State Hwy 114",
    "sg:city":"Dexter",
    "sg:classifiers":[
        {
            "category":"Retail",
            "subcategory":"Veterinary Services",
            "type":"Services"
        }
    ],
    "sg:phone":"+1 573 624 2140",
    "sg:postcode":"63841",
    "sg:province":"MO",
    "sg:tags":[
        "veterinarian"
    ],
    "wof:name":"Dexter Veterinary Clinic",
    "wof:placetype":"venue"
},
  "geometry": {"coordinates":[-89.934612,36.788226],"type":"Point"}
}