{
  "type": "Feature",
  "properties": {
    "iso:country":"US",
    "sg:address":"701 S Moffet Ave",
    "sg:city":"Joplin",
    "sg:classifiers":[
        {
            "category":"Retail",
            "subcategory":"Car Wash",
            "type":"Services"
        },
        {
            "category":"Retail",
            "subcategory":"Auto Repair",
            "type":"Services"
        }
    ],
    "sg:phone":"+1 417 782 3421",
    "sg:postcode":"64801",
    "sg:province":"MO",
    "sg:tags":[
        "automobile",
        "detailing"
    ],
    "wof:name":"Car Care",
    "wof:placetype":"venue"
},
  "geometry": {"coordinates":[-94.51929699999999,37.082007],"type":"Point"}
}