{
  "type": "Feature",
  "properties": {
    "iso:country":"US",
    "sg:address":"8138 Stratford Dr",
    "sg:city":"Saint Louis",
    "sg:classifiers":[
        {
            "category":"Manufacturing",
            "subcategory":"Lumber",
            "type":"Manufacturing & Wholesale Goods"
        }
    ],
    "sg:phone":"+1 314 725 9593",
    "sg:postcode":"63105",
    "sg:province":"MO",
    "sg:tags":[
        "forestry"
    ],
    "wof:name":"Nevinger Management LLC",
    "wof:placetype":"venue"
},
  "geometry": {"coordinates":[-90.342923,38.656544],"type":"Point"}
}