{
  "type": "Feature",
  "properties": {
    "iso:country":"US",
    "sg:address":"1408 Forum Blvd",
    "sg:city":"Columbia",
    "sg:classifiers":[
        {
            "category":"Banks & Credit Unions",
            "subcategory":"Bank",
            "type":"Services"
        }
    ],
    "sg:phone":"+1 573 446 6600",
    "sg:postcode":"65203",
    "sg:province":"MO",
    "wof:name":"US Bank",
    "wof:placetype":"venue"
},
  "geometry": {"coordinates":[-92.36047499999999,38.934854],"type":"Point"}
}