{
  "type": "Feature",
  "properties": {
    "iso:country":"US",
    "sg:address":"1104 Hampton Ave",
    "sg:city":"Saint Louis",
    "sg:classifiers":[
        {
            "category":"Autos & Motor Vehicles",
            "subcategory":"Fuel & Gas Station",
            "type":"Retail Goods"
        }
    ],
    "sg:phone":"+1 314 646 1600",
    "sg:postcode":"63139",
    "sg:province":"MO",
    "sg:tags":[
        "convenience",
        "oil",
        "store"
    ],
    "sg:website":"www.bp.com",
    "wof:name":"Hampton Bp",
    "wof:placetype":"venue"
},
  "geometry": {"coordinates":[-90.2873,38.629002],"type":"Point"}
}