{
  "type": "Feature",
  "properties": {
    "iso:country":"US",
    "sg:address":"2954 SW State Hwy D",
    "sg:city":"Polo",
    "sg:classifiers":[
        {
            "category":"Education",
            "subcategory":"Special Training",
            "type":"Public Place"
        }
    ],
    "sg:phone":"+1 816 586 4129",
    "sg:postcode":"64671",
    "sg:province":"MO",
    "sg:tags":[
        "information",
        "school",
        "college"
    ],
    "wof:name":"Mirabile C-1 School",
    "wof:placetype":"venue"
},
  "geometry": {"coordinates":[-94.141233,39.614311],"type":"Point"}
}