{
  "type": "Feature",
  "properties": {
    "iso:country":"US",
    "sg:address":"223 Ha Ha Tonka Rd",
    "sg:city":"Camdenton",
    "sg:classifiers":[
        {
            "category":"Shopping",
            "subcategory":"Florist",
            "type":"Retail Goods"
        }
    ],
    "sg:phone":"+1 573 346 3388",
    "sg:postcode":"65020",
    "sg:province":"MO",
    "wof:name":"Janine's Flowers & Gifts",
    "wof:placetype":"venue"
},
  "geometry": {"coordinates":[-92.747578,38.003509],"type":"Point"}
}