{
  "type": "Feature",
  "properties": {
    "iso:country":"US",
    "sg:address":"349 Eisenhower St",
    "sg:city":"Rolla",
    "sg:classifiers":[
        {
            "category":"Personal",
            "subcategory":"Beauty Salon",
            "type":"Services"
        }
    ],
    "sg:phone":"+1 573 762 3513",
    "sg:postcode":"65401",
    "sg:province":"MO",
    "sg:tags":[
        "shop"
    ],
    "wof:name":"A Shear Event",
    "wof:placetype":"venue"
},
  "geometry": {"coordinates":[-91.88103700000001,37.940179],"type":"Point"}
}