{
  "type": "Feature",
  "properties": {
    "iso:country":"US",
    "sg:address":"10212 Apke Ln",
    "sg:city":"Catawissa",
    "sg:classifiers":[
        {
            "category":"Professional",
            "subcategory":"Engineering",
            "type":"Services"
        }
    ],
    "sg:phone":"+1 314 330 3052",
    "sg:postcode":"63015",
    "sg:province":"MO",
    "wof:name":"Innovative Engineering",
    "wof:placetype":"venue"
},
  "geometry": {"coordinates":[-90.723767,38.400155],"type":"Point"}
}