{
  "type": "Feature",
  "properties": {
    "iso:country":"US",
    "sg:address":"1574 Fenpark Dr",
    "sg:city":"Fenton",
    "sg:classifiers":[
        {
            "category":"Professional",
            "subcategory":"Business Services",
            "type":"Services"
        }
    ],
    "sg:phone":"+1 636 343 3091",
    "sg:postcode":"63026",
    "sg:province":"MO",
    "sg:tags":[
        "lecture",
        "bureau",
        "seminar"
    ],
    "wof:name":"Achieve The Good Life",
    "wof:placetype":"venue"
},
  "geometry": {"coordinates":[-90.44895699999999,38.535404],"type":"Point"}
}