{
  "type": "Feature",
  "properties": {
    "iso:country":"US",
    "sg:address":"606 Sheridan Dr",
    "sg:city":"Cape Girardeau",
    "sg:classifiers":[
        {
            "category":"Professional",
            "subcategory":"Advertising",
            "type":"Services"
        }
    ],
    "sg:phone":"+1 573 651 1170",
    "sg:postcode":"63740",
    "sg:province":"MO",
    "wof:name":"See More Advertising",
    "wof:placetype":"venue"
},
  "geometry": {"coordinates":[-89.66488200000001,37.176539],"type":"Point"}
}