{
  "type": "Feature",
  "properties": {
    "iso:country":"US",
    "sg:address":"12606 Lusher Rd",
    "sg:city":"Florissant",
    "sg:classifiers":[
        {
            "category":"Social Services",
            "subcategory":"Child Care",
            "type":"Services"
        }
    ],
    "sg:phone":"+1 314 355 4014",
    "sg:postcode":"63033",
    "sg:province":"MO",
    "sg:tags":[
        "day"
    ],
    "wof:name":"Open Arms Preschool",
    "wof:placetype":"venue"
},
  "geometry": {"coordinates":[-90.227895,38.810666],"type":"Point"}
}