{
  "type": "Feature",
  "properties": {
    "iso:country":"US",
    "sg:address":"310 US Hwy 50",
    "sg:city":"Warrensburg",
    "sg:classifiers":[
        {
            "category":"Autos & Motor Vehicles",
            "subcategory":"Automobile Sales",
            "type":"Retail Goods"
        }
    ],
    "sg:phone":"+1 660 429 6887",
    "sg:postcode":"64093",
    "sg:province":"MO",
    "sg:tags":[
        "car",
        "dealer"
    ],
    "wof:name":"Goodrich Automotive",
    "wof:placetype":"venue"
},
  "geometry": {"coordinates":[-93.65892599999999,38.772164],"type":"Point"}
}