{
  "type": "Feature",
  "properties": {
    "iso:country":"US",
    "sg:address":"2929 Holmes St",
    "sg:city":"Kansas City",
    "sg:classifiers":[
        {
            "category":"Retail",
            "subcategory":"Repair Shop",
            "type":"Services"
        }
    ],
    "sg:phone":"+1 816 918 0135",
    "sg:postcode":"64109",
    "sg:province":"MO",
    "sg:tags":[
        "tile",
        "grout",
        "restoration",
        "cleaning"
    ],
    "wof:name":"Integrity Stone",
    "wof:placetype":"venue"
},
  "geometry": {"coordinates":[-94.576362,39.073022],"type":"Point"}
}