{
  "type": "Feature",
  "properties": {
    "iso:country":"US",
    "sg:address":"2233 Gravois Ave",
    "sg:city":"Saint Louis",
    "sg:classifiers":[
        {
            "category":"Wholesale",
            "subcategory":"Auto Parts",
            "type":"Manufacturing & Wholesale Goods"
        }
    ],
    "sg:phone":"+1 314 664 5650",
    "sg:postcode":"63104",
    "sg:province":"MO",
    "sg:tags":[
        "truck",
        "tire"
    ],
    "wof:name":"Industrial Tire Brokerage Inc",
    "wof:placetype":"venue"
},
  "geometry": {"coordinates":[-90.220596,38.605999],"type":"Point"}
}