{
  "type": "Feature",
  "properties": {
    "iso:country":"US",
    "sg:address":"47 Wester Bluff Rd",
    "sg:city":"Rogersville",
    "sg:classifiers":[
        {
            "category":"Farming",
            "subcategory":"Dairy Farm",
            "type":"Manufacturing & Wholesale Goods"
        }
    ],
    "sg:phone":"+1 417 753 2883",
    "sg:postcode":"65742",
    "sg:province":"MO",
    "wof:name":"At Valley Farm",
    "wof:placetype":"venue"
},
  "geometry": {"coordinates":[-93.004277,37.193463],"type":"Point"}
}