{
  "type": "Feature",
  "properties": {
    "iso:country":"US",
    "sg:address":"206 S Marietta St",
    "sg:city":"Excelsior Spgs",
    "sg:classifiers":[
        {
            "category":"Health Services",
            "subcategory":"Medical Lab",
            "type":"Services"
        }
    ],
    "sg:phone":"+1 816 630 4224",
    "sg:postcode":"64024",
    "sg:province":"MO",
    "sg:tags":[
        "laboratory",
        "dental",
        "restoration"
    ],
    "wof:name":"Excelsior Dental Lab",
    "wof:placetype":"venue"
},
  "geometry": {"coordinates":[-94.224116,39.341729],"type":"Point"}
}