{
  "type": "Feature",
  "properties": {
    "iso:country":"US",
    "sg:address":"2124 Lake Park Trl",
    "sg:city":"De Soto",
    "sg:classifiers":[
        {
            "category":"Freight",
            "type":"Transportation"
        }
    ],
    "sg:phone":"+1 636 337 7108",
    "sg:postcode":"63020",
    "sg:province":"MO",
    "sg:tags":[
        "operator",
        "local",
        "trucking"
    ],
    "wof:name":"PLM Hauling Inc",
    "wof:placetype":"venue"
},
  "geometry": {"coordinates":[-90.585835,38.07488],"type":"Point"}
}