{
  "type": "Feature",
  "properties": {
    "iso:country":"US",
    "sg:address":"1203 Johnson Dr",
    "sg:city":"Neosho",
    "sg:classifiers":[
        {
            "category":"Personal",
            "subcategory":"Beauty Salon",
            "type":"Services"
        }
    ],
    "sg:phone":"+1 417 451 6818",
    "sg:postcode":"64850",
    "sg:province":"MO",
    "sg:tags":[
        "shop"
    ],
    "wof:name":"Bungalow Beauty Salon",
    "wof:placetype":"venue"
},
  "geometry": {"coordinates":[-94.385655,36.85643],"type":"Point"}
}