{
  "type": "Feature",
  "properties": {
    "iso:country":"US",
    "sg:address":"7232 N Lindbergh Blvd",
    "sg:city":"Hazelwood",
    "sg:classifiers":[
        {
            "category":"Wholesale",
            "subcategory":"Auto Parts",
            "type":"Manufacturing & Wholesale Goods"
        }
    ],
    "sg:phone":"+1 314 731 1918",
    "sg:postcode":"63042",
    "sg:province":"MO",
    "wof:name":"Midnite Auto Paint",
    "wof:placetype":"venue"
},
  "geometry": {"coordinates":[-90.356846,38.782313],"type":"Point"}
}