{
  "type": "Feature",
  "properties": {
    "iso:country":"US",
    "sg:address":"14560 Manchester Rd",
    "sg:city":"Ballwin",
    "sg:classifiers":[
        {
            "category":"Shopping",
            "type":"Retail Goods"
        }
    ],
    "sg:phone":"+1 636 220 4279",
    "sg:postcode":"63011",
    "sg:province":"MO",
    "sg:tags":[
        "item",
        "boutique"
    ],
    "wof:name":"Hijab Boutique",
    "wof:placetype":"venue"
},
  "geometry": {"coordinates":[-90.52520800000001,38.593029],"type":"Point"}
}