{
  "type": "Feature",
  "properties": {
    "iso:country":"US",
    "sg:address":"221 Hoot Owl Hollow Rd",
    "sg:city":"Troy",
    "sg:classifiers":[
        {
            "category":"Organizations",
            "subcategory":"Religious Organization",
            "type":"Services"
        }
    ],
    "sg:phone":"+1 636 528 4070",
    "sg:postcode":"63379",
    "sg:province":"MO",
    "sg:tags":[
        "church"
    ],
    "wof:name":"Old Alexandria Methodist Chr",
    "wof:placetype":"venue"
},
  "geometry": {"coordinates":[-90.903002,38.991873],"type":"Point"}
}