{
  "type": "Feature",
  "properties": {
    "iso:country":"US",
    "sg:address":"20739 Liv 439",
    "sg:city":"Dawn",
    "sg:phone":"+1 660 745 3341",
    "sg:postcode":"64638",
    "sg:province":"MO",
    "sg:tags":[
        "farm"
    ],
    "wof:name":"Ireland Farms",
    "wof:placetype":"venue"
},
  "geometry": {"coordinates":[-93.572401,39.674756],"type":"Point"}
}