{
  "type": "Feature",
  "properties": {
    "iso:country":"US",
    "sg:address":"247 Ash St",
    "sg:city":"Morrison",
    "sg:classifiers":[
        {
            "category":"Building & Trades",
            "subcategory":"Construction",
            "type":"Services"
        }
    ],
    "sg:phone":"+1 573 294 6022",
    "sg:postcode":"65061",
    "sg:province":"MO",
    "sg:tags":[
        "handyman"
    ],
    "wof:name":"Voss Ag Repair",
    "wof:placetype":"venue"
},
  "geometry": {"coordinates":[-91.556439,38.666583],"type":"Point"}
}