{
  "type": "Feature",
  "properties": {
    "iso:country":"US",
    "sg:address":"103 State Hwy 7",
    "sg:city":"Blue Springs",
    "sg:classifiers":[
        {
            "category":"Personal",
            "type":"Services"
        }
    ],
    "sg:phone":"+1 816 228 8897",
    "sg:postcode":"64014",
    "sg:province":"MO",
    "wof:name":"Thompsons Tux and Tails",
    "wof:placetype":"venue"
},
  "geometry": {"coordinates":[-94.272532,39.015149],"type":"Point"}
}