{
  "type": "Feature",
  "properties": {
    "iso:country":"US",
    "sg:address":"4433 Woodson Rd",
    "sg:city":"St Louis",
    "sg:classifiers":[
        {
            "category":"Professional",
            "subcategory":"Computer Services",
            "type":"Services"
        }
    ],
    "sg:phone":"+1 314 429 7490",
    "sg:postcode":"63134",
    "sg:province":"MO",
    "sg:tags":[
        "internet"
    ],
    "wof:name":"Electrografix New Media",
    "wof:placetype":"venue"
},
  "geometry": {"coordinates":[-90.357478,38.730869],"type":"Point"}
}