{
  "type": "Feature",
  "properties": {
    "iso:country":"US",
    "sg:address":"611 W Fort Scott St",
    "sg:city":"Butler",
    "sg:classifiers":[
        {
            "category":"Professional",
            "subcategory":"Accounting & Tax Preparation",
            "type":"Services"
        }
    ],
    "sg:phone":"+1 660 679 6550",
    "sg:postcode":"64730",
    "sg:province":"MO",
    "sg:tags":[
        "accountant"
    ],
    "wof:name":"Troutt Beeman & Co",
    "wof:placetype":"venue"
},
  "geometry": {"coordinates":[-94.34195099999999,38.256736],"type":"Point"}
}