{
  "type": "Feature",
  "properties": {
    "iso:country":"US",
    "sg:address":"35155 160th St",
    "sg:city":"Hopkins",
    "sg:classifiers":[
        {
            "category":"Farming",
            "subcategory":"Livestock Farm",
            "type":"Manufacturing & Wholesale Goods"
        },
        {
            "category":"Farming",
            "subcategory":"Farm",
            "type":"Manufacturing & Wholesale Goods"
        }
    ],
    "sg:phone":"+1 660 986 3262",
    "sg:postcode":"64461",
    "sg:province":"MO",
    "sg:tags":[
        "ranch"
    ],
    "wof:name":"Brown Charolais",
    "wof:placetype":"venue"
},
  "geometry": {"coordinates":[-94.70932500000001,40.487716],"type":"Point"}
}