{
  "type": "Feature",
  "properties": {
    "iso:country":"US",
    "sg:address":"1440 State Highway 248",
    "sg:city":"Branson",
    "sg:classifiers":[
        {
            "category":"Real Estate",
            "subcategory":"Real Estate Services",
            "type":"Services"
        },
        {
            "category":"Real Estate",
            "subcategory":"Real Estate Agent",
            "type":"Services"
        }
    ],
    "sg:phone":"+1 417 335 8439",
    "sg:postcode":"65616",
    "sg:province":"MO",
    "sg:tags":[
        "buyer",
        "broker"
    ],
    "wof:name":"Mrc Commercial Group",
    "wof:placetype":"venue"
},
  "geometry": {"coordinates":[-93.238957,36.663724],"type":"Point"}
}