{
  "type": "Feature",
  "properties": {
    "iso:country":"US",
    "sg:address":"1137 Claycrest Cir",
    "sg:city":"Saint Charles",
    "sg:classifiers":[
        {
            "category":"Manufacturing",
            "subcategory":"Retail Goods",
            "type":"Manufacturing & Wholesale Goods"
        }
    ],
    "sg:phone":"+1 636 928 9810",
    "sg:postcode":"63304",
    "sg:province":"MO",
    "sg:tags":[
        "product",
        "mfg"
    ],
    "wof:name":"Barrett Mfg",
    "wof:placetype":"venue"
},
  "geometry": {"coordinates":[-90.620367,38.735226],"type":"Point"}
}