{
  "type": "Feature",
  "properties": {
    "iso:country":"US",
    "sg:address":"942 Hemsath Rd",
    "sg:city":"St Charles",
    "sg:classifiers":[
        {
            "category":"Building & Trades",
            "subcategory":"Construction",
            "type":"Services"
        }
    ],
    "sg:phone":"+1 636 443 0307",
    "sg:postcode":"63303",
    "sg:province":"MO",
    "sg:tags":[
        "dry wall",
        "contractor"
    ],
    "wof:name":"Independent Drywall Systems",
    "wof:placetype":"venue"
},
  "geometry": {"coordinates":[-90.535145,38.753202],"type":"Point"}
}