{
  "type": "Feature",
  "properties": {
    "iso:country":"US",
    "sg:address":"221 State Hwy 42",
    "sg:city":"Vienna",
    "sg:classifiers":[
        {
            "category":"Wholesale",
            "subcategory":"Farm Supplies",
            "type":"Manufacturing & Wholesale Goods"
        }
    ],
    "sg:phone":"+1 573 422 3674",
    "sg:postcode":"65582",
    "sg:province":"MO",
    "sg:tags":[
        "buyer",
        "livestock"
    ],
    "wof:name":"Missouri Department-Agrcltr",
    "wof:placetype":"venue"
},
  "geometry": {"coordinates":[-91.958163,38.186432],"type":"Point"}
}