{
  "type": "Feature",
  "properties": {
    "iso:country":"US",
    "sg:address":"510 E Prairie Ave",
    "sg:city":"Saint Louis",
    "sg:classifiers":[
        {
            "category":"Personal",
            "type":"Services"
        }
    ],
    "sg:phone":"+1 314 645 8888",
    "sg:postcode":"63147",
    "sg:province":"MO",
    "sg:tags":[
        "towing"
    ],
    "wof:name":"Bill's Wrecker Service Inc",
    "wof:placetype":"venue"
},
  "geometry": {"coordinates":[-90.2043,38.676998],"type":"Point"}
}