{
  "type": "Feature",
  "properties": {
    "iso:country":"US",
    "sg:address":"3338 S National Ave",
    "sg:city":"Springfield",
    "sg:classifiers":[
        {
            "category":"Banks & Credit Unions",
            "subcategory":"Bank",
            "type":"Services"
        }
    ],
    "sg:phone":"+1 417 799 3555",
    "sg:postcode":"65807",
    "sg:province":"MO",
    "sg:tags":[
        "loan",
        "real estate"
    ],
    "wof:name":"American Home Mortgage Corp",
    "wof:placetype":"venue"
},
  "geometry": {"coordinates":[-93.277507,37.154928],"type":"Point"}
}