{
  "type": "Feature",
  "properties": {
    "iso:country":"US",
    "sg:address":"1804 NW 9th Ct",
    "sg:city":"Blue Springs",
    "sg:classifiers":[
        {
            "category":"Wholesale",
            "subcategory":"Durable Goods & Equipment",
            "type":"Manufacturing & Wholesale Goods"
        }
    ],
    "sg:phone":"+1 816 228 4195",
    "sg:postcode":"64015",
    "sg:province":"MO",
    "sg:tags":[
        "representative",
        "manufacturer"
    ],
    "wof:name":"CCI Printing & Forms Source",
    "wof:placetype":"venue"
},
  "geometry": {"coordinates":[-94.27467,39.036805],"type":"Point"}
}