{
  "type": "Feature",
  "properties": {
    "iso:country":"US",
    "sg:address":"1707 W Battlefield Rd",
    "sg:city":"Springfield",
    "sg:classifiers":[
        {
            "category":"Banks & Credit Unions",
            "subcategory":"Bank",
            "type":"Services"
        }
    ],
    "sg:phone":"+1 417 889 8882",
    "sg:postcode":"65807",
    "sg:province":"MO",
    "sg:tags":[
        "federal"
    ],
    "wof:name":"Commercial Federal Bank",
    "wof:placetype":"venue"
},
  "geometry": {"coordinates":[-93.31393199999999,37.160142],"type":"Point"}
}