{
  "type": "Feature",
  "properties": {
    "iso:country":"US",
    "sg:address":"7700 S Bennett Dr",
    "sg:city":"Columbia",
    "sg:classifiers":[
        {
            "category":"Professional",
            "subcategory":"Management & Consulting",
            "type":"Services"
        }
    ],
    "sg:phone":"+1 573 449 3388",
    "sg:postcode":"65201",
    "sg:province":"MO",
    "wof:name":"Donald D Snyder",
    "wof:placetype":"venue"
},
  "geometry": {"coordinates":[-92.28688,38.863001],"type":"Point"}
}