{
  "type": "Feature",
  "properties": {
    "iso:country":"US",
    "sg:address":"705 NW Buckingham Pl",
    "sg:city":"Blue Springs",
    "sg:classifiers":[
        {
            "category":"Building & Trades",
            "subcategory":"Electrical",
            "type":"Services"
        }
    ],
    "sg:phone":"+1 816 228 4492",
    "sg:postcode":"64015",
    "sg:province":"MO",
    "sg:tags":[
        "electrical",
        "contractor"
    ],
    "wof:name":"Dave Brown Electric LLC",
    "wof:placetype":"venue"
},
  "geometry": {"coordinates":[-94.30385699999999,39.025623],"type":"Point"}
}