{
  "type": "Feature",
  "properties": {
    "iso:country":"US",
    "sg:address":"8833 N Broadway",
    "sg:city":"Saint Louis",
    "sg:classifiers":[
        {
            "category":"Autos & Motor Vehicles",
            "subcategory":"Automobile Sales",
            "type":"Retail Goods"
        }
    ],
    "sg:phone":"+1 314 867 7128",
    "sg:postcode":"63147",
    "sg:province":"MO",
    "sg:tags":[
        "used"
    ],
    "wof:name":"Drive By Auto Sale",
    "wof:placetype":"venue"
},
  "geometry": {"coordinates":[-90.228195,38.725191],"type":"Point"}
}