{
  "type": "Feature",
  "properties": {
    "iso:country":"US",
    "sg:address":"199 Clarkson Rd",
    "sg:city":"Ballwin",
    "sg:classifiers":[
        {
            "category":"Banks & Credit Unions",
            "subcategory":"Bank",
            "type":"Services"
        }
    ],
    "sg:phone":"+1 636 230 3500",
    "sg:postcode":"63011",
    "sg:province":"MO",
    "sg:tags":[
        "company",
        "holding",
        "for",
        "state"
    ],
    "wof:name":"Maramacket Valley Bank",
    "wof:placetype":"venue"
},
  "geometry": {"coordinates":[-90.585633,38.598358],"type":"Point"}
}