{
  "type": "Feature",
  "properties": {
    "iso:country":"US",
    "sg:address":"201 College Ave",
    "sg:city":"Kennett",
    "sg:classifiers":[
        {
            "category":"Professional",
            "subcategory":"Lawyer & Legal Services",
            "type":"Services"
        }
    ],
    "sg:phone":"+1 573 888 4636",
    "sg:postcode":"63857",
    "sg:province":"MO",
    "sg:tags":[
        "attorney",
        "practice"
    ],
    "wof:name":"Law Firm",
    "wof:placetype":"venue"
},
  "geometry": {"coordinates":[-90.055672,36.237831],"type":"Point"}
}