{
  "type": "Feature",
  "properties": {
    "iso:country":"US",
    "sg:address":"123 Frontenac Forest",
    "sg:city":"St Louis",
    "sg:classifiers":[
        {
            "category":"Professional",
            "subcategory":"Management & Consulting",
            "type":"Services"
        },
        {
            "category":"Insurance",
            "subcategory":"Insurance Agent",
            "type":"Services"
        }
    ],
    "sg:phone":"+1 314 993 5430",
    "sg:postcode":"63131",
    "sg:province":"MO",
    "sg:tags":[
        "personal"
    ],
    "wof:name":"Flotron G L & Assoc",
    "wof:placetype":"venue"
},
  "geometry": {"coordinates":[-90.43211599999999,38.624646],"type":"Point"}
}