{
  "type": "Feature",
  "properties": {
    "iso:country":"US",
    "sg:address":"10871 Chase Park Ln",
    "sg:city":"St Louis",
    "sg:classifiers":[
        {
            "category":"Real Estate",
            "subcategory":"Real Estate Operator",
            "type":"Services"
        }
    ],
    "sg:phone":"+1 314 432 3700",
    "sg:postcode":"63141",
    "sg:province":"MO",
    "sg:tags":[
        "apartment"
    ],
    "wof:name":"Camden Westchase",
    "wof:placetype":"venue"
},
  "geometry": {"coordinates":[-90.41996399999999,38.674185],"type":"Point"}
}