{
  "type": "Feature",
  "properties": {
    "iso:country":"US",
    "sg:address":"608 E Cora Ave",
    "sg:city":"California",
    "sg:classifiers":[
        {
            "category":"Social Services",
            "subcategory":"Child Care",
            "type":"Services"
        }
    ],
    "sg:phone":"+1 573 796 1917",
    "sg:postcode":"65018",
    "sg:province":"MO",
    "wof:name":"Kids' Depot Child Dev Ctr",
    "wof:placetype":"venue"
},
  "geometry": {"coordinates":[-92.561046,38.628233],"type":"Point"}
}