{
  "type": "Feature",
  "properties": {
    "iso:country":"US",
    "sg:address":"1150 Burgos St",
    "sg:city":"St Louis",
    "sg:classifiers":[
        {
            "category":"Wholesale",
            "subcategory":"Toys & Hobbies",
            "type":"Manufacturing & Wholesale Goods"
        }
    ],
    "sg:phone":"+1 314 741 4004",
    "sg:postcode":"63138",
    "sg:province":"MO",
    "sg:tags":[
        "wholesaler"
    ],
    "wof:name":"786 Y2k Inc",
    "wof:placetype":"venue"
},
  "geometry": {"coordinates":[-90.199867,38.790821],"type":"Point"}
}