{
  "type": "Feature",
  "properties": {
    "iso:country":"US",
    "sg:address":"222 S Bemiston Ave",
    "sg:city":"St Louis",
    "sg:classifiers":[
        {
            "category":"Real Estate",
            "subcategory":"Architect",
            "type":"Services"
        }
    ],
    "sg:phone":"+1 314 721 4050",
    "sg:postcode":"63105",
    "sg:province":"MO",
    "sg:website":"www.owh-inc.com",
    "wof:name":"Ottolino Winters Huebner",
    "wof:placetype":"venue"
},
  "geometry": {"coordinates":[-90.337309,38.646439],"type":"Point"}
}