{
  "type": "Feature",
  "properties": {
    "iso:country":"US",
    "sg:address":"69 Kelly Leaf Dr",
    "sg:city":"Saint Peters",
    "sg:classifiers":[
        {
            "category":"Wholesale",
            "subcategory":"Sporting Goods",
            "type":"Manufacturing & Wholesale Goods"
        }
    ],
    "sg:phone":"+1 636 441 1134",
    "sg:postcode":"63376",
    "sg:province":"MO",
    "wof:name":"Loubek & Associates",
    "wof:placetype":"venue"
},
  "geometry": {"coordinates":[-90.57655,38.771214],"type":"Point"}
}