{
  "type": "Feature",
  "properties": {
    "iso:country":"US",
    "sg:address":"23630 State Hwy 79",
    "sg:city":"Annada",
    "sg:phone":"+1 573 898 2130",
    "sg:postcode":"63330",
    "sg:province":"MO",
    "sg:tags":[
        "farm",
        "corn"
    ],
    "wof:name":"Phillip Lageman",
    "wof:placetype":"venue"
},
  "geometry": {"coordinates":[-90.820767,39.253674],"type":"Point"}
}