{
  "type": "Feature",
  "properties": {
    "iso:country":"US",
    "sg:address":"14838 Manchester Rd",
    "sg:city":"Ballwin",
    "sg:classifiers":[
        {
            "category":"Building & Trades",
            "subcategory":"Construction",
            "type":"Services"
        }
    ],
    "sg:phone":"+1 636 391 8177",
    "sg:postcode":"63011",
    "sg:province":"MO",
    "sg:tags":[
        "nonresidential"
    ],
    "wof:name":"S M Wilson Co",
    "wof:placetype":"venue"
},
  "geometry": {"coordinates":[-90.537527,38.592899],"type":"Point"}
}