{
  "type": "Feature",
  "properties": {
    "iso:country":"US",
    "sg:address":"161 N Arrowhead St",
    "sg:city":"Fair Grove",
    "sg:classifiers":[
        {
            "category":"Professional",
            "subcategory":"Art Services",
            "type":"Services"
        }
    ],
    "sg:phone":"+1 417 759 2766",
    "sg:postcode":"65648",
    "sg:province":"MO",
    "sg:tags":[
        "photography",
        "commercial"
    ],
    "wof:name":"Howard Photography",
    "wof:placetype":"venue"
},
  "geometry": {"coordinates":[-93.142839,37.386667],"type":"Point"}
}