{
  "type": "Feature",
  "properties": {
    "iso:country":"US",
    "sg:address":"1 S Memorial Dr",
    "sg:city":"St Louis",
    "sg:classifiers":[
        {
            "category":"Real Estate",
            "subcategory":"Real Estate Agent",
            "type":"Services"
        }
    ],
    "sg:phone":"+1 314 231 2945",
    "sg:postcode":"63102",
    "sg:province":"MO",
    "sg:tags":[
        "management"
    ],
    "wof:name":"C B Richard Ellis",
    "wof:placetype":"venue"
},
  "geometry": {"coordinates":[-90.187726,38.623926],"type":"Point"}
}