{
  "type": "Feature",
  "properties": {
    "iso:country":"US",
    "sg:address":"1705 S Baltimore St",
    "sg:city":"Kirksville",
    "sg:classifiers":[
        {
            "category":"Home & Garden",
            "subcategory":"Building Materials",
            "type":"Retail Goods"
        }
    ],
    "sg:phone":"+1 660 665 2796",
    "sg:postcode":"63501",
    "sg:province":"MO",
    "sg:tags":[
        "glass",
        "window",
        "plate"
    ],
    "wof:name":"Aladdin Glass",
    "wof:placetype":"venue"
},
  "geometry": {"coordinates":[-92.571838,40.180684],"type":"Point"}
}