{
  "type": "Feature",
  "properties": {
    "iso:country":"US",
    "sg:address":"210 Flora St",
    "sg:city":"Iberia",
    "sg:classifiers":[
        {
            "category":"Professional",
            "subcategory":"Accounting & Tax Preparation",
            "type":"Services"
        }
    ],
    "sg:phone":"+1 573 793 2342",
    "sg:postcode":"65486",
    "sg:province":"MO",
    "wof:name":"Colvin Tax Service",
    "wof:placetype":"venue"
},
  "geometry": {"coordinates":[-92.290279,38.083899],"type":"Point"}
}