{
  "type": "Feature",
  "properties": {
    "iso:country":"US",
    "sg:address":"741 W Leawood Dr",
    "sg:city":"Marshall",
    "sg:classifiers":[
        {
            "category":"Building & Trades",
            "subcategory":"Cleaning & Sanitation",
            "type":"Services"
        }
    ],
    "sg:phone":"+1 660 886 4303",
    "sg:postcode":"65340",
    "sg:province":"MO",
    "sg:tags":[
        "maintenance"
    ],
    "wof:name":"Pro Klean Cleaning Servic",
    "wof:placetype":"venue"
},
  "geometry": {"coordinates":[-93.207973,39.109218],"type":"Point"}
}