{
  "type": "Feature",
  "properties": {
    "iso:country":"US",
    "sg:address":"2047 Westport Center Dr",
    "sg:city":"Saint Louis",
    "sg:classifiers":[
        {
            "category":"Wholesale",
            "subcategory":"Durable Goods & Equipment",
            "type":"Manufacturing & Wholesale Goods"
        }
    ],
    "sg:phone":"+1 314 692 0717",
    "sg:postcode":"63146",
    "sg:province":"MO",
    "sg:tags":[
        "travel",
        "gear",
        "luggage"
    ],
    "wof:name":"Trg Group LLC",
    "wof:placetype":"venue"
},
  "geometry": {"coordinates":[-90.42158999999999,38.695277],"type":"Point"}
}