{
  "type": "Feature",
  "properties": {
    "iso:country":"US",
    "sg:address":"17225 E Kentucky Rd",
    "sg:city":"Independence",
    "sg:classifiers":[
        {
            "category":"Recreation",
            "type":"Entertainment"
        }
    ],
    "sg:phone":"+1 816 257 9548",
    "sg:postcode":"64058",
    "sg:province":"MO",
    "sg:tags":[
        "course",
        "golf"
    ],
    "wof:name":"Winterstone Golf Course",
    "wof:placetype":"venue"
},
  "geometry": {"coordinates":[-94.37213,39.128091],"type":"Point"}
}