{
  "type": "Feature",
  "properties": {
    "iso:country":"US",
    "sg:address":"1330 E Independence Ave",
    "sg:city":"Independence",
    "sg:classifiers":[
        {
            "category":"Manufacturing",
            "subcategory":"Jewelry",
            "type":"Manufacturing & Wholesale Goods"
        }
    ],
    "sg:phone":"+1 816 795 6775",
    "sg:postcode":"64050",
    "sg:province":"MO",
    "sg:tags":[
        "precious",
        "metal",
        "mfg"
    ],
    "wof:name":"Gold & Time",
    "wof:placetype":"venue"
},
  "geometry": {"coordinates":[-94.399056,39.102771],"type":"Point"}
}