{
  "type": "Feature",
  "properties": {
    "iso:country":"US",
    "sg:address":"2026 Grove Cir",
    "sg:city":"Independence",
    "sg:classifiers":[
        {
            "category":"Government",
            "subcategory":"Office",
            "type":"Public Place"
        }
    ],
    "sg:phone":"+1 816 796 0033",
    "sg:postcode":"64058",
    "sg:province":"MO",
    "sg:tags":[
        "mill",
        "management"
    ],
    "wof:name":"PTL Enterprises",
    "wof:placetype":"venue"
},
  "geometry": {"coordinates":[-94.354927,39.140874],"type":"Point"}
}