{
  "type": "Feature",
  "properties": {
    "iso:country":"US",
    "sg:address":"1240 S Brentwood Blvd",
    "sg:city":"Saint Louis",
    "sg:classifiers":[
        {
            "category":"Autos & Motor Vehicles",
            "subcategory":"Fuel & Gas Station",
            "type":"Retail Goods"
        }
    ],
    "sg:phone":"+1 314 725 9981",
    "sg:postcode":"63117",
    "sg:province":"MO",
    "sg:tags":[
        "station",
        "gasoline"
    ],
    "wof:name":"Shell",
    "wof:placetype":"venue"
},
  "geometry": {"coordinates":[-90.346166,38.632296],"type":"Point"}
}