{
  "type": "Feature",
  "properties": {
    "iso:country":"US",
    "sg:address":"112 Mariae Ln",
    "sg:city":"O Fallon",
    "sg:classifiers":[
        {
            "category":"Building & Trades",
            "subcategory":"Construction",
            "type":"Services"
        }
    ],
    "sg:phone":"+1 636 946 0711",
    "sg:postcode":"63366",
    "sg:province":"MO",
    "sg:tags":[
        "repairing",
        "house",
        "remodeling",
        "contractor"
    ],
    "wof:name":"Choice Remodeling Inc",
    "wof:placetype":"venue"
},
  "geometry": {"coordinates":[-90.70285199999999,38.803834],"type":"Point"}
}