{
  "type": "Feature",
  "properties": {
    "iso:country":"US",
    "sg:address":"16356 Harmony Ln",
    "sg:city":"Waynesville",
    "sg:classifiers":[
        {
            "category":"Real Estate",
            "subcategory":"Real Estate Agent",
            "type":"Services"
        }
    ],
    "sg:phone":"+1 573 336 4593",
    "sg:postcode":"65584",
    "sg:province":"MO",
    "wof:name":"Ladaca Enterprises LLC",
    "wof:placetype":"venue"
},
  "geometry": {"coordinates":[-92.13981099999999,37.845208],"type":"Point"}
}