{
  "type": "Feature",
  "properties": {
    "iso:country":"US",
    "sg:address":"509 N Jennings Rd",
    "sg:city":"Independence",
    "sg:classifiers":[
        {
            "category":"Education",
            "subcategory":"School",
            "type":"Public Place"
        }
    ],
    "sg:phone":"+1 816 257 4100",
    "sg:postcode":"64056",
    "sg:province":"MO",
    "wof:name":"Randall Elementary School",
    "wof:placetype":"venue"
},
  "geometry": {"coordinates":[-94.37472699999999,39.111946],"type":"Point"}
}