{
  "type": "Feature",
  "properties": {
    "addr:full":"3322 S Campbell Ave Springfield MO 65807",
    "addr:housenumber":"3322",
    "addr:postcode":"65807",
    "addr:street":"S Campbell Ave",
    "iso:country":"US",
    "sg:address":"3322 S Campbell Ave",
    "sg:city":"Springfield",
    "sg:classifiers":[
        {
            "category":"Banks & Credit Unions",
            "subcategory":"Bank",
            "type":"Services"
        }
    ],
    "sg:phone":"+1 417 881 7400",
    "sg:postcode":"65807",
    "sg:province":"MO",
    "sg:tags":[
        "financing"
    ],
    "wof:name":"American General Finance Inc",
    "wof:placetype":"venue"
},
  "geometry": {"coordinates":[-93.295596,37.153643],"type":"Point"}
}