{
  "type": "Feature",
  "properties": {
    "iso:country":"US",
    "sg:address":"1559 Smiley St",
    "sg:city":"Liberty",
    "sg:classifiers":[
        {
            "category":"Professional",
            "type":"Services"
        }
    ],
    "sg:phone":"+1 816 407 1536",
    "sg:postcode":"64068",
    "sg:province":"MO",
    "wof:name":"Woodworkers Services",
    "wof:placetype":"venue"
},
  "geometry": {"coordinates":[-94.44353099999999,39.220545],"type":"Point"}
}