{
  "type": "Feature",
  "properties": {
    "iso:country":"US",
    "sg:address":"1125 SW 701st Rd",
    "sg:city":"Chilhowee",
    "sg:classifiers":[
        {
            "category":"Farming",
            "subcategory":"Farm",
            "type":"Manufacturing & Wholesale Goods"
        }
    ],
    "sg:phone":"+1 660 678 2384",
    "sg:postcode":"64733",
    "sg:province":"MO",
    "sg:tags":[
        "crop",
        "general"
    ],
    "wof:name":"Raymond D Greene",
    "wof:placetype":"venue"
},
  "geometry": {"coordinates":[-93.878963,38.588603],"type":"Point"}
}