{
  "type": "Feature",
  "properties": {
    "iso:country":"US",
    "sg:address":"602 Sulphur Springs Rd",
    "sg:city":"Ballwin",
    "sg:classifiers":[
        {
            "category":"Food & Beverages",
            "subcategory":"Specialty",
            "type":"Retail Goods"
        }
    ],
    "sg:phone":"+1 636 527 0555",
    "sg:postcode":"63021",
    "sg:province":"MO",
    "sg:tags":[
        "health",
        "diet"
    ],
    "wof:name":"Monaco Labs",
    "wof:placetype":"venue"
},
  "geometry": {"coordinates":[-90.520008,38.58325],"type":"Point"}
}