{
  "type": "Feature",
  "properties": {
    "iso:country":"US",
    "sg:address":"19129 State Hwy 133",
    "sg:city":"Dixon",
    "sg:classifiers":[
        {
            "category":"Retail",
            "subcategory":"Repair Shop",
            "type":"Services"
        },
        {
            "category":"Manufacturing",
            "subcategory":"Tools & Machinery",
            "type":"Manufacturing & Wholesale Goods"
        }
    ],
    "sg:phone":"+1 573 759 2882",
    "sg:postcode":"65459",
    "sg:province":"MO",
    "sg:tags":[
        "engine",
        "power",
        "mfg"
    ],
    "wof:name":"Clark's Small Engines",
    "wof:placetype":"venue"
},
  "geometry": {"coordinates":[-92.112757,38.072797],"type":"Point"}
}