{
  "type": "Feature",
  "properties": {
    "iso:country":"US",
    "sg:address":"3209 Cross Keys Dr",
    "sg:city":"Florissant",
    "sg:phone":"+1 314 831 1366",
    "sg:postcode":"63033",
    "sg:province":"MO",
    "sg:website":"http://www.chrismill.com",
    "wof:name":"Cross Keys Apartments",
    "wof:placetype":"venue"
},
  "geometry": {"coordinates":[-90.296715,38.807577],"type":"Point"}
}