{
  "type": "Feature",
  "properties": {
    "iso:country":"US",
    "sg:address":"10327 Lime Kiln Dr",
    "sg:city":"Neosho",
    "sg:classifiers":[
        {
            "category":"Organizations",
            "subcategory":"Religious Organization",
            "type":"Services"
        }
    ],
    "sg:phone":"+1 417 451 7647",
    "sg:postcode":"64850",
    "sg:province":"MO",
    "wof:name":"Hilldale Baptist Church",
    "wof:placetype":"venue"
},
  "geometry": {"coordinates":[-94.37583600000001,36.921119],"type":"Point"}
}