{
  "type": "Feature",
  "properties": {
    "iso:country":"US",
    "sg:address":"3394 Mckelvey Rd Ste 108",
    "sg:city":"Bridgeton",
    "sg:classifiers":[
        {
            "category":"Health Services",
            "subcategory":"Chiropractor",
            "type":"Services"
        }
    ],
    "sg:phone":"+1 314 344 4438",
    "sg:postcode":"63044",
    "sg:province":"MO",
    "sg:tags":[
        "chiropractic"
    ],
    "wof:name":"Maryland Heights Chiropractic",
    "wof:placetype":"venue"
},
  "geometry": {"coordinates":[-90.432339,38.747533],"type":"Point"}
}