{
  "type": "Feature",
  "properties": {
    "iso:country":"US",
    "sg:address":"7118 N Hanley Rd",
    "sg:city":"Hazelwood",
    "sg:classifiers":[
        {
            "category":"Social Services",
            "subcategory":"Child Care",
            "type":"Services"
        }
    ],
    "sg:phone":"+1 314 521 9800",
    "sg:postcode":"63042",
    "sg:province":"MO",
    "sg:tags":[
        "day"
    ],
    "wof:name":"Educare In Hazelwood",
    "wof:placetype":"venue"
},
  "geometry": {"coordinates":[-90.335252,38.771617],"type":"Point"}
}