{
  "type": "Feature",
  "properties": {
    "iso:country":"US",
    "sg:address":"169 NE Cookingham Dr",
    "sg:city":"Kansas City",
    "sg:classifiers":[
        {
            "category":"Freight",
            "type":"Transportation"
        }
    ],
    "sg:phone":"+1 816 734 3989",
    "sg:postcode":"64155",
    "sg:province":"MO",
    "sg:tags":[
        "special"
    ],
    "wof:name":"Warburg Stragemart Partners LP",
    "wof:placetype":"venue"
},
  "geometry": {"coordinates":[-94.57713699999999,39.30372],"type":"Point"}
}