{
  "type": "Feature",
  "properties": {
    "iso:country":"US",
    "sg:address":"8120 Pershing Ave",
    "sg:city":"Saint Louis",
    "sg:classifiers":[
        {
            "category":"Retail",
            "subcategory":"Veterinary Services",
            "type":"Services"
        }
    ],
    "sg:phone":"+1 314 727 6235",
    "sg:postcode":"63105",
    "sg:province":"MO",
    "wof:name":"L Mc Daniel",
    "wof:placetype":"venue"
},
  "geometry": {"coordinates":[-90.342744,38.654887],"type":"Point"}
}