{
  "type": "Feature",
  "properties": {
    "iso:country":"US",
    "sg:address":"10921 Manchester Rd",
    "sg:city":"St Louis",
    "sg:classifiers":[
        {
            "category":"Autos & Motor Vehicles",
            "subcategory":"Fuel & Gas Station",
            "type":"Retail Goods"
        }
    ],
    "sg:phone":"+1 314 965 8020",
    "sg:postcode":"63122",
    "sg:province":"MO",
    "sg:tags":[
        "oil"
    ],
    "wof:name":"Citgo Kirkwood",
    "wof:placetype":"venue"
},
  "geometry": {"coordinates":[-90.408946,38.599761],"type":"Point"}
}