{
  "type": "Feature",
  "properties": {
    "iso:country":"US",
    "sg:address":"114 N Main St",
    "sg:city":"Huntsville",
    "sg:classifiers":[
        {
            "category":"Shopping",
            "subcategory":"Bicycles & Sporting Goods",
            "type":"Retail Goods"
        }
    ],
    "sg:phone":"+1 660 277 4690",
    "sg:postcode":"65259",
    "sg:province":"MO",
    "sg:tags":[
        "gun",
        "gunsmith"
    ],
    "wof:name":"Olari Gun Svc",
    "wof:placetype":"venue"
},
  "geometry": {"coordinates":[-92.54583100000001,39.441187],"type":"Point"}
}