{
  "type": "Feature",
  "properties": {
    "iso:country":"US",
    "sg:address":"7751 N Lindbergh Blvd",
    "sg:city":"Hazelwood",
    "sg:classifiers":[
        {
            "category":"Professional",
            "type":"Services"
        }
    ],
    "sg:phone":"+1 314 830 5400",
    "sg:postcode":"63042",
    "sg:province":"MO",
    "wof:name":"Sports Stats",
    "wof:placetype":"venue"
},
  "geometry": {"coordinates":[-90.350615,38.786898],"type":"Point"}
}