{
  "type": "Feature",
  "properties": {
    "iso:country":"US",
    "sg:address":"223 S Crittenden St",
    "sg:city":"Marshfield",
    "sg:classifiers":[
        {
            "category":"Home & Garden",
            "subcategory":"Household Appliances",
            "type":"Retail Goods"
        },
        {
            "category":"Retail",
            "subcategory":"Repair Shop",
            "type":"Services"
        }
    ],
    "sg:phone":"+1 417 468 7910",
    "sg:postcode":"65706",
    "sg:province":"MO",
    "sg:tags":[
        "cleaners",
        "parts",
        "electrical",
        "vacuum"
    ],
    "wof:name":"Sids Vac Shop & Sewing Center",
    "wof:placetype":"venue"
},
  "geometry": {"coordinates":[-92.906374,37.337912],"type":"Point"}
}