{
  "type": "Feature",
  "properties": {
    "iso:country":"US",
    "sg:address":"320 W Main St",
    "sg:city":"Jackson",
    "sg:classifiers":[
        {
            "category":"Banks & Credit Unions",
            "subcategory":"Bank",
            "type":"Services"
        }
    ],
    "sg:phone":"+1 573 339 6501",
    "sg:postcode":"63755",
    "sg:province":"MO",
    "sg:tags":[
        "national",
        "commercial",
        "security",
        "state"
    ],
    "wof:name":"Bank Of America",
    "wof:placetype":"venue"
},
  "geometry": {"coordinates":[-89.670507,37.382931],"type":"Point"}
}