{
  "type": "Feature",
  "properties": {
    "iso:country":"US",
    "sg:address":"1184 Old Rte 66",
    "sg:city":"Waynesville",
    "sg:phone":"+1 573 336 4821",
    "sg:postcode":"65584",
    "sg:province":"MO",
    "sg:tags":[
        "product",
        "petroleum"
    ],
    "wof:name":"All Star Gas Corporation",
    "wof:placetype":"venue"
},
  "geometry": {"coordinates":[-92.180004,37.828379],"type":"Point"}
}