{
  "type": "Feature",
  "properties": {
    "iso:country":"US",
    "sg:address":"1165 Sara Mathews Ln",
    "sg:city":"Chesterfield",
    "sg:classifiers":[
        {
            "category":"Professional",
            "subcategory":"Management & Consulting",
            "type":"Services"
        }
    ],
    "sg:phone":"+1 636 561 8008",
    "sg:postcode":"63005",
    "sg:province":"MO",
    "sg:tags":[
        "consultant"
    ],
    "wof:name":"Sheets Assoc Invstments Search",
    "wof:placetype":"venue"
},
  "geometry": {"coordinates":[-90.67273299999999,38.605653],"type":"Point"}
}