{
  "type": "Feature",
  "properties": {
    "iso:country":"US",
    "sg:address":"4110 McClay Rd",
    "sg:city":"Saint Charles",
    "sg:classifiers":[
        {
            "category":"Education",
            "subcategory":"School",
            "type":"Public Place"
        }
    ],
    "sg:phone":"+1 636 441 4835",
    "sg:postcode":"63304",
    "sg:province":"MO",
    "wof:name":"Notre Dame Ministry Inc",
    "wof:placetype":"venue"
},
  "geometry": {"coordinates":[-90.601034,38.755059],"type":"Point"}
}