{
  "type": "Feature",
  "properties": {
    "iso:country":"US",
    "sg:address":"417 E High St",
    "sg:city":"Potosi",
    "sg:classifiers":[
        {
            "category":"Health Services",
            "subcategory":"Chiropractor",
            "type":"Services"
        }
    ],
    "sg:phone":"+1 573 438 1999",
    "sg:postcode":"63664",
    "sg:province":"MO",
    "wof:name":"Greenlee Chiropractic",
    "wof:placetype":"venue"
},
  "geometry": {"coordinates":[-90.78205,37.932752],"type":"Point"}
}