{
  "type": "Feature",
  "properties": {
    "iso:country":"US",
    "sg:address":"9523 Lackland Rd",
    "sg:city":"Overland",
    "sg:classifiers":[
        {
            "category":"Education",
            "subcategory":"School",
            "type":"Public Place"
        },
        {
            "category":"Shopping",
            "subcategory":"Clothing, Apparel, & Fashions",
            "type":"Retail Goods"
        }
    ],
    "sg:phone":"+1 314 428 3446",
    "sg:postcode":"63114",
    "sg:province":"MO",
    "sg:tags":[
        "uniform"
    ],
    "wof:name":"School Fashions & More",
    "wof:placetype":"venue"
},
  "geometry": {"coordinates":[-90.36609199999999,38.700793],"type":"Point"}
}