{
  "type": "Feature",
  "properties": {
    "iso:country":"US",
    "sg:address":"14380 State Rte V",
    "sg:city":"St James",
    "sg:classifiers":[
        {
            "category":"Retail",
            "subcategory":"Repair Shop",
            "type":"Services"
        }
    ],
    "sg:phone":"+1 573 265 6106",
    "sg:postcode":"65559",
    "sg:province":"MO",
    "sg:tags":[
        "blacksmith"
    ],
    "wof:name":"Precision Farrier Service",
    "wof:placetype":"venue"
},
  "geometry": {"coordinates":[-91.667295,38.022584],"type":"Point"}
}