{
  "type": "Feature",
  "properties": {
    "iso:country":"US",
    "sg:address":"8132 NW Prairie View Rd",
    "sg:city":"Kansas City",
    "sg:classifiers":[
        {
            "category":"Restaurant",
            "type":"Food & Drink"
        },
        {
            "category":"Bars & Pubs",
            "type":"Food & Drink"
        }
    ],
    "sg:phone":"+1 816 587 3646",
    "sg:postcode":"64151",
    "sg:province":"MO",
    "sg:tags":[
        "drinking"
    ],
    "wof:name":"Dirks Sports Bar & Grill Inc",
    "wof:placetype":"venue"
},
  "geometry": {"coordinates":[-94.658934,39.243725],"type":"Point"}
}