{
  "type": "Feature",
  "properties": {
    "iso:country":"US",
    "sg:address":"8050 Watson Rd",
    "sg:city":"St Louis",
    "sg:classifiers":[
        {
            "category":"Real Estate",
            "subcategory":"Real Estate Agent",
            "type":"Services"
        }
    ],
    "sg:phone":"+1 314 849 9913",
    "sg:postcode":"63119",
    "sg:province":"MO",
    "sg:tags":[
        "appraiser"
    ],
    "wof:name":"St Louis Appraisal Co",
    "wof:placetype":"venue"
},
  "geometry": {"coordinates":[-90.34364100000001,38.567289],"type":"Point"}
}