{
  "type": "Feature",
  "properties": {
    "iso:country":"US",
    "sg:address":"120 S Main St",
    "sg:city":"Independence",
    "sg:classifiers":[
        {
            "category":"Restaurant",
            "type":"Food & Drink"
        }
    ],
    "sg:phone":"+1 816 252 0020",
    "sg:postcode":"64050",
    "sg:province":"MO",
    "sg:tags":[
        "caterer"
    ],
    "wof:name":"Penelope's Pastime",
    "wof:placetype":"venue"
},
  "geometry": {"coordinates":[-94.415825,39.09126],"type":"Point"}
}