{
  "type": "Feature",
  "properties": {
    "iso:country":"US",
    "sg:address":"86 S Highway Dr",
    "sg:city":"Valley Park",
    "sg:classifiers":[
        {
            "category":"Real Estate",
            "subcategory":"Real Estate Agent",
            "type":"Services"
        }
    ],
    "sg:phone":"+1 636 225 6446",
    "sg:postcode":"63088",
    "sg:province":"MO",
    "wof:name":"Sdk Investments Inc",
    "wof:placetype":"venue"
},
  "geometry": {"coordinates":[-90.493191,38.538503],"type":"Point"}
}