{
  "type": "Feature",
  "properties": {
    "iso:country":"US",
    "sg:address":"615 N Country Ave",
    "sg:city":"Kearney",
    "sg:classifiers":[
        {
            "category":"Home & Garden",
            "subcategory":"Carpets & Floor Coverings",
            "type":"Retail Goods"
        }
    ],
    "sg:phone":"+1 816 628 6669",
    "sg:postcode":"64060",
    "sg:province":"MO",
    "sg:tags":[
        "dealer",
        "rug"
    ],
    "wof:name":"Interior Motives",
    "wof:placetype":"venue"
},
  "geometry": {"coordinates":[-94.376329,39.367567],"type":"Point"}
}