{
  "type": "Feature",
  "properties": {
    "iso:country":"US",
    "sg:address":"410 W 37th St N",
    "sg:city":"Independence",
    "sg:classifiers":[
        {
            "category":"Banks & Credit Unions",
            "subcategory":"Bank",
            "type":"Services"
        }
    ],
    "sg:phone":"+1 816 461 8776",
    "sg:postcode":"64050",
    "sg:province":"MO",
    "sg:tags":[
        "bond",
        "broker",
        "stock"
    ],
    "wof:name":"Ace Flight Shares",
    "wof:placetype":"venue"
},
  "geometry": {"coordinates":[-94.41755999999999,39.128161],"type":"Point"}
}