{
  "type": "Feature",
  "properties": {
    "iso:country":"US",
    "sg:address":"23709 E 232nd St",
    "sg:city":"Harrisonville",
    "sg:classifiers":[
        {
            "category":"Building & Trades",
            "subcategory":"Construction",
            "type":"Services"
        }
    ],
    "sg:phone":"+1 816 380 2007",
    "sg:postcode":"64701",
    "sg:province":"MO",
    "sg:tags":[
        "contractor"
    ],
    "wof:name":"Jdv Construction",
    "wof:placetype":"venue"
},
  "geometry": {"coordinates":[-94.32228600000001,38.696265],"type":"Point"}
}