{
  "type": "Feature",
  "properties": {
    "iso:country":"US",
    "sg:address":"18577 Hwy K",
    "sg:city":"Versailles",
    "sg:classifiers":[
        {
            "category":"Wholesale",
            "subcategory":"Chemicals & Plastics",
            "type":"Manufacturing & Wholesale Goods"
        }
    ],
    "sg:phone":"+1 573 378 2432",
    "sg:postcode":"65084",
    "sg:province":"MO",
    "wof:name":"Loganbill Farm Chemicals",
    "wof:placetype":"venue"
},
  "geometry": {"coordinates":[-92.723601,38.477391],"type":"Point"}
}