{
  "type": "Feature",
  "properties": {
    "iso:country":"US",
    "sg:address":"6330 NW Kelly Dr",
    "sg:city":"Kansas City",
    "sg:classifiers":[
        {
            "category":"Building & Trades",
            "subcategory":"Construction",
            "type":"Services"
        }
    ],
    "sg:phone":"+1 816 741 6084",
    "sg:postcode":"64152",
    "sg:province":"MO",
    "sg:tags":[
        "waterproofing",
        "contractor"
    ],
    "wof:name":"Commercial Waterproofing",
    "wof:placetype":"venue"
},
  "geometry": {"coordinates":[-94.689656,39.209421],"type":"Point"}
}