{
  "type": "Feature",
  "properties": {
    "iso:country":"US",
    "sg:address":"64 State Hwy Uu",
    "sg:city":"Silex",
    "sg:classifiers":[
        {
            "category":"Education",
            "subcategory":"School",
            "type":"Public Place"
        }
    ],
    "sg:phone":"+1 573 384 5044",
    "sg:postcode":"63377",
    "sg:province":"MO",
    "wof:name":"Silex R-1 Elementary School",
    "wof:placetype":"venue"
},
  "geometry": {"coordinates":[-91.061813,39.125932],"type":"Point"}
}