{
  "type": "Feature",
  "properties": {
    "iso:country":"US",
    "sg:address":"1061 E Battlefield Rd",
    "sg:city":"Springfield",
    "sg:classifiers":[
        {
            "category":"Wholesale",
            "subcategory":"Apparel",
            "type":"Manufacturing & Wholesale Goods"
        }
    ],
    "sg:phone":"+1 417 889 5991",
    "sg:postcode":"65807",
    "sg:province":"MO",
    "sg:tags":[
        "textile"
    ],
    "wof:name":"Os International",
    "wof:placetype":"venue"
},
  "geometry": {"coordinates":[-93.279867,37.159745],"type":"Point"}
}