{
  "type": "Feature",
  "properties": {
    "iso:country":"US",
    "sg:address":"301 W Jefferson St",
    "sg:city":"Doniphan",
    "sg:classifiers":[
        {
            "category":"Home & Garden",
            "subcategory":"Hardware",
            "type":"Retail Goods"
        },
        {
            "category":"Shopping",
            "subcategory":"Pets & Pet Supplies",
            "type":"Retail Goods"
        }
    ],
    "sg:phone":"+1 573 996 2923",
    "sg:postcode":"63935",
    "sg:province":"MO",
    "sg:tags":[
        "feed",
        "concentrate",
        "supplement",
        "store"
    ],
    "wof:name":"Inman Feed & Fertilizer",
    "wof:placetype":"venue"
},
  "geometry": {"coordinates":[-90.830551,36.616749],"type":"Point"}
}