{
  "type": "Feature",
  "properties": {
    "iso:country":"US",
    "sg:address":"53 Crown Dr",
    "sg:city":"Camdenton",
    "sg:classifiers":[
        {
            "category":"Building & Trades",
            "subcategory":"Construction",
            "type":"Services"
        }
    ],
    "sg:phone":"+1 573 434 6771",
    "sg:postcode":"65020",
    "sg:province":"MO",
    "sg:tags":[
        "wallcoverings-installation",
        "wallpaper",
        "painting",
        "contractor"
    ],
    "wof:name":"Dave Osment Painting Dba",
    "wof:placetype":"venue"
},
  "geometry": {"coordinates":[-92.771232,38.059045],"type":"Point"}
}