{
  "type": "Feature",
  "properties": {
    "iso:country":"US",
    "sg:address":"209 Old Rte 66",
    "sg:city":"Waynesville",
    "sg:classifiers":[
        {
            "category":"Insurance",
            "subcategory":"Hazard Insurance",
            "type":"Services"
        },
        {
            "category":"Professional",
            "subcategory":"Business Services",
            "type":"Services"
        }
    ],
    "sg:phone":"+1 573 774 6951",
    "sg:postcode":"65583",
    "sg:province":"MO",
    "sg:tags":[
        "bond"
    ],
    "wof:name":"Missouri Bail Bonding",
    "wof:placetype":"venue"
},
  "geometry": {"coordinates":[-92.207725,37.8272],"type":"Point"}
}