{
  "type": "Feature",
  "properties": {
    "iso:country":"US",
    "sg:address":"5700 Old Hwy 21",
    "sg:city":"Antonia",
    "sg:classifiers":[
        {
            "category":"Shopping",
            "subcategory":"Hobbies, Toys, & Games",
            "type":"Retail Goods"
        }
    ],
    "sg:phone":"+1 636 942 1344",
    "sg:postcode":"63052",
    "sg:province":"MO",
    "sg:tags":[
        "product",
        "ceramic"
    ],
    "wof:name":"Ceramics Unlimited",
    "wof:placetype":"venue"
},
  "geometry": {"coordinates":[-90.497157,38.378081],"type":"Point"}
}