{
  "type": "Feature",
  "properties": {
    "iso:country":"US",
    "sg:address":"14465 US Hwy 169",
    "sg:city":"Smithville",
    "sg:classifiers":[
        {
            "category":"Home & Garden",
            "subcategory":"Garden Supply",
            "type":"Retail Goods"
        }
    ],
    "sg:phone":"+1 816 532 4241",
    "sg:postcode":"64089",
    "sg:province":"MO",
    "sg:tags":[
        "fountain",
        "display"
    ],
    "wof:name":"K & M Aquatic Gardens",
    "wof:placetype":"venue"
},
  "geometry": {"coordinates":[-94.583814,39.36034],"type":"Point"}
}