{
  "type": "Feature",
  "properties": {
    "iso:country":"US",
    "sg:address":"2600 Ensign Dr",
    "sg:city":"Platte City",
    "sg:classifiers":[
        {
            "category":"Deli",
            "type":"Food & Drink"
        }
    ],
    "sg:menulink":"http://www.allmenus.com/mo/carroll/10382-planet-sub/menu/",
    "sg:phone":"+1 816 431 2469",
    "sg:postcode":"64079",
    "sg:province":"MO",
    "sg:tags":[
        "wrap",
        "american",
        "sandwich"
    ],
    "wof:name":"Planet Sub",
    "wof:placetype":"venue"
},
  "geometry": {"coordinates":[-94.76858,39.348858],"type":"Point"}
}