{
  "type": "Feature",
  "properties": {
    "iso:country":"US",
    "sg:address":"25 S 4th St",
    "sg:city":"Columbia",
    "sg:classifiers":[
        {
            "category":"Building & Trades",
            "subcategory":"Construction",
            "type":"Services"
        }
    ],
    "sg:phone":"+1 573 442 6187",
    "sg:postcode":"65201",
    "sg:province":"MO",
    "sg:website":"www.septagon.com",
    "wof:name":"Septagon Construction Co",
    "wof:placetype":"venue"
},
  "geometry": {"coordinates":[-92.333065,38.950812],"type":"Point"}
}