{
  "type": "Feature",
  "properties": {
    "iso:country":"US",
    "sg:address":"114 Jackson St",
    "sg:city":"Jefferson City",
    "sg:classifiers":[
        {
            "category":"Real Estate",
            "subcategory":"Real Estate Agent",
            "type":"Services"
        }
    ],
    "sg:phone":"+1 573 635 4168",
    "sg:postcode":"65101",
    "sg:province":"MO",
    "wof:name":"William W Gratz Real Estate",
    "wof:placetype":"venue"
},
  "geometry": {"coordinates":[-92.16564,38.574835],"type":"Point"}
}