{
  "type": "Feature",
  "properties": {
    "iso:country":"US",
    "sg:address":"2885 Flameglow Dr",
    "sg:city":"St Louis",
    "sg:classifiers":[
        {
            "category":"Professional",
            "subcategory":"Business Services",
            "type":"Services"
        },
        {
            "category":"Professional",
            "subcategory":"Secretarial Services",
            "type":"Services"
        }
    ],
    "sg:phone":"+1 314 487 7750",
    "sg:postcode":"63129",
    "sg:province":"MO",
    "sg:tags":[
        "transcribing",
        "reporting",
        "disc"
    ],
    "wof:name":"Equitable Transcription",
    "wof:placetype":"venue"
},
  "geometry": {"coordinates":[-90.31907,38.483172],"type":"Point"}
}