{
  "type": "Feature",
  "properties": {
    "iso:country":"US",
    "sg:address":"6221 Wanda Ave",
    "sg:city":"St Louis",
    "sg:classifiers":[
        {
            "category":"Personal",
            "subcategory":"Beauty Salon",
            "type":"Services"
        }
    ],
    "sg:phone":"+1 314 352 1282",
    "sg:postcode":"63116",
    "sg:province":"MO",
    "sg:tags":[
        "shop"
    ],
    "wof:name":"Wand Beauty Salon",
    "wof:placetype":"venue"
},
  "geometry": {"coordinates":[-90.276014,38.571873],"type":"Point"}
}