{
  "type": "Feature",
  "properties": {
    "iso:country":"US",
    "sg:address":"800 Bittersweet Rd",
    "sg:city":"Lake Ozark",
    "sg:classifiers":[
        {
            "category":"Food & Beverages",
            "subcategory":"Groceries & Convenience Stores",
            "type":"Retail Goods"
        }
    ],
    "sg:phone":"+1 573 365 7225",
    "sg:postcode":"65049",
    "sg:province":"MO",
    "wof:name":"Carl Williams",
    "wof:placetype":"venue"
},
  "geometry": {"coordinates":[-92.72292899999999,38.195349],"type":"Point"}
}