{
  "type": "Feature",
  "properties": {
    "iso:country":"US",
    "sg:address":"2302 Main St",
    "sg:city":"Bethany",
    "sg:classifiers":[
        {
            "category":"Health Services",
            "subcategory":"Chiropractor",
            "type":"Services"
        }
    ],
    "sg:phone":"+1 660 425 3444",
    "sg:postcode":"64424",
    "sg:province":"MO",
    "sg:tags":[
        "chiropractic"
    ],
    "wof:name":"Guernsey Chiropractic",
    "wof:placetype":"venue"
},
  "geometry": {"coordinates":[-94.028722,40.2687],"type":"Point"}
}