{
  "type": "Feature",
  "properties": {
    "iso:country":"US",
    "sg:address":"11108 N Oak Trfy",
    "sg:city":"Kansas City",
    "sg:classifiers":[
        {
            "category":"Insurance",
            "subcategory":"Insurance Agent",
            "type":"Services"
        }
    ],
    "sg:phone":"+1 816 734 1901",
    "sg:postcode":"64155",
    "sg:province":"MO",
    "sg:tags":[
        "adjuster"
    ],
    "wof:name":"Central States Claims Service",
    "wof:placetype":"venue"
},
  "geometry": {"coordinates":[-94.575473,39.295328],"type":"Point"}
}