{
  "type": "Feature",
  "properties": {
    "iso:country":"US",
    "sg:address":"600 State Hwy 92",
    "sg:city":"Kearney",
    "sg:classifiers":[
        {
            "category":"Autos & Motor Vehicles",
            "subcategory":"Fuel & Gas Station",
            "type":"Retail Goods"
        }
    ],
    "sg:phone":"+1 816 628 6101",
    "sg:postcode":"64060",
    "sg:province":"MO",
    "sg:tags":[
        "plaza",
        "truck",
        "stops"
    ],
    "wof:name":"Kearney Truck Plaza",
    "wof:placetype":"venue"
},
  "geometry": {"coordinates":[-94.35436199999999,39.367805],"type":"Point"}
}