{
  "type": "Feature",
  "properties": {
    "iso:country":"US",
    "sg:address":"911 N Alanthus Ave",
    "sg:city":"Stanberry",
    "sg:classifiers":[
        {
            "category":"Social Services",
            "type":"Services"
        }
    ],
    "sg:phone":"+1 660 783 2315",
    "sg:postcode":"64489",
    "sg:province":"MO",
    "wof:name":"Gentry County Outreach",
    "wof:placetype":"venue"
},
  "geometry": {"coordinates":[-94.538513,40.221291],"type":"Point"}
}