{
  "type": "Feature",
  "properties": {
    "iso:country":"US",
    "sg:address":"40 Fenton Plz",
    "sg:city":"Fenton",
    "sg:classifiers":[
        {
            "category":"Education",
            "subcategory":"Special Training",
            "type":"Public Place"
        }
    ],
    "sg:phone":"+1 636 305 1117",
    "sg:postcode":"63026",
    "sg:province":"MO",
    "sg:tags":[
        "tutoring"
    ],
    "sg:website":"www.educate.com",
    "wof:name":"Sylvan Learning Ctr",
    "wof:placetype":"venue"
},
  "geometry": {"coordinates":[-90.443186,38.511734],"type":"Point"}
}