{
  "type": "Feature",
  "properties": {
    "iso:country":"US",
    "sg:address":"1103 W Pearce Blvd",
    "sg:city":"Wentzville",
    "sg:classifiers":[
        {
            "category":"Insurance",
            "subcategory":"Insurance Agent",
            "type":"Services"
        }
    ],
    "sg:phone":"+1 636 332 3400",
    "sg:postcode":"63385",
    "sg:province":"MO",
    "wof:name":"Greg Costello Ins",
    "wof:placetype":"venue"
},
  "geometry": {"coordinates":[-90.86573799999999,38.810334],"type":"Point"}
}