{
  "type": "Feature",
  "properties": {
    "iso:country":"US",
    "sg:address":"3746 Harvester Rd",
    "sg:city":"St Peters",
    "sg:classifiers":[
        {
            "category":"Food & Beverages",
            "subcategory":"Fruits & Vegetables",
            "type":"Retail Goods"
        }
    ],
    "sg:phone":"+1 636 936 8442",
    "sg:postcode":"63303",
    "sg:province":"MO",
    "sg:tags":[
        "produce"
    ],
    "wof:name":"Acme Produce",
    "wof:placetype":"venue"
},
  "geometry": {"coordinates":[-90.58395899999999,38.7434],"type":"Point"}
}