{
  "type": "Feature",
  "properties": {
    "iso:country":"US",
    "sg:address":"1555 NE Douglas St",
    "sg:city":"Lees Summit",
    "sg:classifiers":[
        {
            "category":"Restaurant",
            "type":"Food & Drink"
        }
    ],
    "sg:phone":"+1 816 525 9982",
    "sg:postcode":"64063",
    "sg:province":"MO",
    "sg:tags":[
        "eating"
    ],
    "wof:name":"Baskin-Robbins",
    "wof:placetype":"venue"
},
  "geometry": {"coordinates":[-94.378286,38.941856],"type":"Point"}
}