{
  "type": "Feature",
  "properties": {
    "iso:country":"US",
    "sg:address":"501 S Main St",
    "sg:city":"Carthage",
    "sg:classifiers":[
        {
            "category":"Shopping",
            "subcategory":"Gifts & Souvenirs",
            "type":"Retail Goods"
        }
    ],
    "sg:phone":"+1 417 358 0700",
    "sg:postcode":"64836",
    "sg:province":"MO",
    "sg:tags":[
        "repair"
    ],
    "wof:name":"Hosteen",
    "wof:placetype":"venue"
},
  "geometry": {"coordinates":[-94.310997,37.175382],"type":"Point"}
}