{
  "type": "Feature",
  "properties": {
    "iso:country":"US",
    "sg:address":"233 Dennis Weaver Dr",
    "sg:city":"Webb City",
    "sg:classifiers":[
        {
            "category":"Manufacturing",
            "subcategory":"Metals",
            "type":"Manufacturing & Wholesale Goods"
        }
    ],
    "sg:phone":"+1 417 623 7370",
    "sg:postcode":"64870",
    "sg:province":"MO",
    "sg:tags":[
        "product",
        "wire",
        "fabricated",
        "mfg"
    ],
    "wof:name":"Leggett & Platt Incorporated",
    "wof:placetype":"venue"
},
  "geometry": {"coordinates":[-94.503027,37.146865],"type":"Point"}
}