{
  "type": "Feature",
  "properties": {
    "iso:country":"US",
    "sg:address":"321 E 1st St",
    "sg:city":"West Plains",
    "sg:classifiers":[
        {
            "category":"Personal",
            "subcategory":"Beauty Salon",
            "type":"Services"
        }
    ],
    "sg:phone":"+1 417 926 7338",
    "sg:postcode":"65775",
    "sg:province":"MO",
    "wof:name":"Bj's Styles & Smiles",
    "wof:placetype":"venue"
},
  "geometry": {"coordinates":[-91.85029400000001,36.732081],"type":"Point"}
}