{
  "type": "Feature",
  "properties": {
    "iso:country":"US",
    "sg:address":"9081 Silver Ln",
    "sg:city":"Cedar Hill",
    "sg:classifiers":[
        {
            "category":"Farming",
            "subcategory":"Farm",
            "type":"Manufacturing & Wholesale Goods"
        }
    ],
    "sg:phone":"+1 636 285 7393",
    "sg:postcode":"63016",
    "sg:province":"MO",
    "sg:tags":[
        "crop",
        "general"
    ],
    "wof:name":"Lloyd H Linhorst",
    "wof:placetype":"venue"
},
  "geometry": {"coordinates":[-90.64613,38.374249],"type":"Point"}
}