{
  "type": "Feature",
  "properties": {
    "iso:country":"US",
    "sg:address":"16900 NW 136th St",
    "sg:city":"Platte City",
    "sg:classifiers":[
        {
            "category":"Building & Trades",
            "subcategory":"Construction",
            "type":"Services"
        }
    ],
    "sg:phone":"+1 816 858 2520",
    "sg:postcode":"64079",
    "sg:province":"MO",
    "sg:tags":[
        "excavation",
        "grading",
        "general",
        "contractor"
    ],
    "wof:name":"Stinnett Construction Company",
    "wof:placetype":"venue"
},
  "geometry": {"coordinates":[-94.775109,39.339357],"type":"Point"}
}