{
  "type": "Feature",
  "properties": {
    "iso:country":"US",
    "sg:address":"310 W Mercer St",
    "sg:city":"Jasper",
    "sg:classifiers":[
        {
            "category":"Wholesale",
            "subcategory":"Farm Supplies",
            "type":"Manufacturing & Wholesale Goods"
        }
    ],
    "sg:phone":"+1 417 394 2022",
    "sg:postcode":"64755",
    "sg:province":"MO",
    "sg:tags":[
        "fertilizer"
    ],
    "wof:name":"Metz Grain",
    "wof:placetype":"venue"
},
  "geometry": {"coordinates":[-94.304931,37.339833],"type":"Point"}
}