{
  "type": "Feature",
  "properties": {
    "iso:country":"US",
    "sg:address":"505 N Russell St",
    "sg:city":"Jackson",
    "sg:classifiers":[
        {
            "category":"Building & Trades",
            "subcategory":"Construction",
            "type":"Services"
        }
    ],
    "sg:phone":"+1 573 243 2512",
    "sg:postcode":"63755",
    "sg:province":"MO",
    "sg:tags":[
        "house"
    ],
    "wof:name":"Weber Construction",
    "wof:placetype":"venue"
},
  "geometry": {"coordinates":[-89.66974,37.388146],"type":"Point"}
}