{
  "type": "Feature",
  "properties": {
    "iso:country":"US",
    "sg:address":"17499 Private Drive 8194",
    "sg:city":"Newburg",
    "sg:classifiers":[
        {
            "category":"Building & Trades",
            "subcategory":"Construction",
            "type":"Services"
        },
        {
            "category":"Manufacturing",
            "subcategory":"Building Materials",
            "type":"Manufacturing & Wholesale Goods"
        }
    ],
    "sg:phone":"+1 573 762 2188",
    "sg:postcode":"65550",
    "sg:province":"MO",
    "sg:tags":[
        "roofing",
        "sheet",
        "work",
        "metal",
        "contractor",
        "siding"
    ],
    "wof:name":"Rick's Seamless Guttering",
    "wof:placetype":"venue"
},
  "geometry": {"coordinates":[-91.886726,37.95039],"type":"Point"}
}