{
  "type": "Feature",
  "properties": {
    "iso:country":"US",
    "sg:address":"1100 S Elliott Ave",
    "sg:city":"Aurora",
    "sg:classifiers":[
        {
            "category":"Banks & Credit Unions",
            "subcategory":"Bank",
            "type":"Services"
        }
    ],
    "sg:phone":"+1 417 678 3333",
    "sg:postcode":"65605",
    "sg:province":"MO",
    "wof:name":"First Independent Bank",
    "wof:placetype":"venue"
},
  "geometry": {"coordinates":[-93.718193,36.964079],"type":"Point"}
}