{
  "type": "Feature",
  "properties": {
    "iso:country":"US",
    "sg:address":"9601 E 82 Ter",
    "sg:city":"Kansas City",
    "sg:classifiers":[
        {
            "category":"Insurance",
            "subcategory":"Insurance Agent",
            "type":"Services"
        }
    ],
    "sg:phone":"+1 816 356 1760",
    "sg:postcode":"64138",
    "sg:province":"MO",
    "wof:name":"Homer A Radford",
    "wof:placetype":"venue"
},
  "geometry": {"coordinates":[-94.465025,38.973025],"type":"Point"}
}