{
  "type": "Feature",
  "properties": {
    "iso:country":"US",
    "sg:address":"6200 E Connecticut Ave",
    "sg:city":"Kansas City",
    "sg:classifiers":[
        {
            "category":"Organizations",
            "subcategory":"Labor Organization",
            "type":"Services"
        }
    ],
    "sg:phone":"+1 816 231 4530",
    "sg:postcode":"64120",
    "sg:province":"MO",
    "wof:name":"I B E W Local Union 412",
    "wof:placetype":"venue"
},
  "geometry": {"coordinates":[-94.509837,39.132794],"type":"Point"}
}