{
  "type": "Feature",
  "properties": {
    "iso:country":"US",
    "sg:address":"8301 NW 101st Ter",
    "sg:city":"Kansas City",
    "sg:classifiers":[
        {
            "category":"Manufacturing",
            "subcategory":"Printing",
            "type":"Manufacturing & Wholesale Goods"
        }
    ],
    "sg:phone":"+1 816 891 8717",
    "sg:postcode":"64153",
    "sg:province":"MO",
    "sg:tags":[
        "printer",
        "commercial"
    ],
    "sg:website":"www.kcdp.net",
    "wof:name":"Kansas City Digital Press Inc",
    "wof:placetype":"venue"
},
  "geometry": {"coordinates":[-94.674865,39.276872],"type":"Point"}
}