{
  "type": "Feature",
  "properties": {
    "iso:country":"US",
    "sg:address":"600 Emerson Rd",
    "sg:city":"St Louis",
    "sg:classifiers":[
        {
            "category":"Insurance",
            "subcategory":"Insurance Agent",
            "type":"Services"
        }
    ],
    "sg:phone":"+1 314 997 7510",
    "sg:postcode":"63141",
    "sg:province":"MO",
    "wof:name":"Greater St Louis Group",
    "wof:placetype":"venue"
},
  "geometry": {"coordinates":[-90.447277,38.667205],"type":"Point"}
}