{
  "type": "Feature",
  "properties": {
    "iso:country":"US",
    "sg:address":"1066 S Odell Ave",
    "sg:city":"Marshall",
    "sg:classifiers":[
        {
            "category":"Autos & Motor Vehicles",
            "subcategory":"Automobile Sales",
            "type":"Retail Goods"
        }
    ],
    "sg:phone":"+1 660 886 5101",
    "sg:postcode":"65340",
    "sg:province":"MO",
    "sg:tags":[
        "used"
    ],
    "wof:name":"Atomic Car",
    "wof:placetype":"venue"
},
  "geometry": {"coordinates":[-93.194906,39.110333],"type":"Point"}
}