{
  "type": "Feature",
  "properties": {
    "iso:country":"US",
    "sg:address":"2971 S Farm Rd 51",
    "sg:city":"Republic",
    "sg:classifiers":[
        {
            "category":"Home & Garden",
            "subcategory":"Garden Supply",
            "type":"Retail Goods"
        }
    ],
    "sg:phone":"+1 417 864 5210",
    "sg:postcode":"65738",
    "sg:province":"MO",
    "sg:tags":[
        "fertilizer",
        "spraying"
    ],
    "wof:name":"Custom AGR-Srvces of Ozark LLC",
    "wof:placetype":"venue"
},
  "geometry": {"coordinates":[-93.54239699999999,37.164227],"type":"Point"}
}