{
  "type": "Feature",
  "properties": {
    "iso:country":"US",
    "sg:address":"106 N Devasher Rd",
    "sg:city":"Warrensburg",
    "sg:classifiers":[
        {
            "category":"Building & Trades",
            "subcategory":"Construction",
            "type":"Services"
        }
    ],
    "sg:phone":"+1 660 747 8232",
    "sg:postcode":"64093",
    "sg:province":"MO",
    "sg:tags":[
        "manufactured",
        "housing-communities"
    ],
    "wof:name":"Grove Walnut Mobile Home Court",
    "wof:placetype":"venue"
},
  "geometry": {"coordinates":[-93.701618,38.762891],"type":"Point"}
}