{
  "type": "Feature",
  "properties": {
    "iso:country":"US",
    "sg:address":"10678 Hwy 185",
    "sg:city":"Sullivan",
    "sg:classifiers":[
        {
            "category":"Shopping",
            "subcategory":"Bicycles & Sporting Goods",
            "type":"Retail Goods"
        }
    ],
    "sg:phone":"+1 573 468 2366",
    "sg:postcode":"63080",
    "sg:province":"MO",
    "sg:tags":[
        "gun",
        "gunsmith"
    ],
    "wof:name":"Pro Guns",
    "wof:placetype":"venue"
},
  "geometry": {"coordinates":[-91.208765,38.219077],"type":"Point"}
}