{
  "type": "Feature",
  "properties": {
    "iso:country":"US",
    "sg:address":"4466 W Pine Blvd",
    "sg:city":"Saint Louis",
    "sg:classifiers":[
        {
            "category":"Real Estate",
            "subcategory":"Real Estate Operator",
            "type":"Services"
        }
    ],
    "sg:phone":"+1 314 534 4466",
    "sg:postcode":"63108",
    "sg:province":"MO",
    "sg:tags":[
        "apartment"
    ],
    "wof:name":"Executive House",
    "wof:placetype":"venue"
},
  "geometry": {"coordinates":[-90.257237,38.640671],"type":"Point"}
}