{
  "type": "Feature",
  "properties": {
    "iso:country":"US",
    "sg:address":"132 S Main St",
    "sg:city":"Carl Junction",
    "sg:classifiers":[
        {
            "category":"Retail",
            "subcategory":"Portrait Studio",
            "type":"Services"
        }
    ],
    "sg:phone":"+1 417 649 0194",
    "sg:postcode":"64834",
    "sg:province":"MO",
    "sg:tags":[
        "photographer"
    ],
    "wof:name":"Colonial Photography-Cynthia",
    "wof:placetype":"venue"
},
  "geometry": {"coordinates":[-94.565031,37.176466],"type":"Point"}
}