{
  "type": "Feature",
  "properties": {
    "iso:country":"US",
    "sg:address":"5013 Dover Dr",
    "sg:city":"House Springs",
    "sg:classifiers":[
        {
            "category":"Building & Trades",
            "subcategory":"Equipment Rental",
            "type":"Services"
        }
    ],
    "sg:phone":"+1 636 274 2901",
    "sg:postcode":"63051",
    "sg:province":"MO",
    "sg:tags":[
        "heavy",
        "crane"
    ],
    "wof:name":"Krausz Equipment Service",
    "wof:placetype":"venue"
},
  "geometry": {"coordinates":[-90.644448,38.393967],"type":"Point"}
}