{
  "type": "Feature",
  "properties": {
    "addr:full":"1810 Meadow Ct Rolla MO 65401",
    "addr:housenumber":"1810",
    "addr:postcode":"65401",
    "addr:street":"Meadow Ct",
    "iso:country":"US",
    "sg:address":"1810 Meadow Ct",
    "sg:city":"Rolla",
    "sg:classifiers":[
        {
            "category":"Organizations",
            "subcategory":"Religious Organization",
            "type":"Services"
        }
    ],
    "sg:phone":"+1 573 364 0811",
    "sg:postcode":"65401",
    "sg:province":"MO",
    "wof:name":"Corporation of President of Th",
    "wof:placetype":"venue"
},
  "geometry": {"coordinates":[-91.74104699999999,37.94193],"type":"Point"}
}