{
  "type": "Feature",
  "properties": {
    "iso:country":"US",
    "sg:address":"14 Park Charles Blvd S",
    "sg:city":"Saint Peters",
    "sg:classifiers":[
        {
            "category":"Professional",
            "subcategory":"Business Services",
            "type":"Services"
        }
    ],
    "sg:phone":"+1 636 939 2149",
    "sg:postcode":"63376",
    "sg:province":"MO",
    "wof:name":"Midwest Business Solutions",
    "wof:placetype":"venue"
},
  "geometry": {"coordinates":[-90.61923,38.753719],"type":"Point"}
}