{
  "type": "Feature",
  "properties": {
    "iso:country":"US",
    "sg:address":"1100 State Hwy 32",
    "sg:city":"Salem",
    "sg:classifiers":[
        {
            "category":"Shopping",
            "subcategory":"Florist",
            "type":"Retail Goods"
        }
    ],
    "sg:phone":"+1 573 729 6733",
    "sg:postcode":"65560",
    "sg:province":"MO",
    "wof:name":"That Special Touch",
    "wof:placetype":"venue"
},
  "geometry": {"coordinates":[-91.547225,37.636102],"type":"Point"}
}