{
  "type": "Feature",
  "properties": {
    "iso:country":"US",
    "sg:address":"2711 N Kansas Expy",
    "sg:city":"Springfield",
    "sg:classifiers":[
        {
            "category":"Cinema",
            "subcategory":"Movie Theater",
            "type":"Entertainment"
        }
    ],
    "sg:phone":"+1 417 864 4190",
    "sg:postcode":"65803",
    "sg:province":"MO",
    "sg:tags":[
        "motion",
        "picture"
    ],
    "wof:name":"Town & Country 6 Theater",
    "wof:placetype":"venue"
},
  "geometry": {"coordinates":[-93.31093,37.24567],"type":"Point"}
}