{
  "type": "Feature",
  "properties": {
    "iso:country":"US",
    "sg:address":"2709 Clara Ave",
    "sg:city":"St Louis",
    "sg:classifiers":[
        {
            "category":"Organizations",
            "subcategory":"Religious Organization",
            "type":"Services"
        }
    ],
    "sg:phone":"+1 314 385 9898",
    "sg:postcode":"63112",
    "sg:province":"MO",
    "sg:tags":[
        "church"
    ],
    "wof:name":"Perpetual Praise & Worship",
    "wof:placetype":"venue"
},
  "geometry": {"coordinates":[-90.271383,38.676052],"type":"Point"}
}