{
  "type": "Feature",
  "properties": {
    "iso:country":"US",
    "sg:address":"400 Ward Ave",
    "sg:city":"Caruthersville",
    "sg:classifiers":[
        {
            "category":"Social Services",
            "type":"Services"
        }
    ],
    "sg:phone":"+1 573 333 5433",
    "sg:postcode":"63830",
    "sg:province":"MO",
    "sg:tags":[
        "organization",
        "welfare"
    ],
    "wof:name":"Semo Options",
    "wof:placetype":"venue"
},
  "geometry": {"coordinates":[-89.654853,36.191599],"type":"Point"}
}