{
  "type": "Feature",
  "properties": {
    "iso:country":"US",
    "sg:address":"103 N McArthur Ave",
    "sg:city":"Salem",
    "sg:classifiers":[
        {
            "category":"Organizations",
            "subcategory":"Professional Association",
            "type":"Services"
        }
    ],
    "sg:phone":"+1 573 729 7663",
    "sg:postcode":"65560",
    "sg:province":"MO",
    "wof:name":"Dent County Baptist Assn",
    "wof:placetype":"venue"
},
  "geometry": {"coordinates":[-91.54042800000001,37.644281],"type":"Point"}
}