{
  "type": "Feature",
  "properties": {
    "iso:country":"US",
    "sg:address":"304 S 9th St Ste 100",
    "sg:city":"Columbia",
    "sg:classifiers":[
        {
            "category":"Bars & Pubs",
            "type":"Food & Drink"
        }
    ],
    "sg:menulink":"http://www.allmenus.com/mo/columbia/285432-campus-bar--grill/menu/",
    "sg:phone":"+1 573 449 3463",
    "sg:postcode":"65201",
    "sg:province":"MO",
    "sg:tags":[
        "burger",
        "american",
        "sandwich"
    ],
    "wof:name":"Campus Bar & Grill",
    "wof:placetype":"venue"
},
  "geometry": {"coordinates":[-92.327455,38.948365],"type":"Point"}
}