{
  "type": "Feature",
  "properties": {
    "iso:country":"US",
    "sg:address":"9721 Litzsinger Rd",
    "sg:city":"Saint Louis",
    "sg:classifiers":[
        {
            "category":"Real Estate",
            "subcategory":"Architect",
            "type":"Services"
        }
    ],
    "sg:phone":"+1 314 962 2560",
    "sg:postcode":"63124",
    "sg:province":"MO",
    "sg:tags":[
        "architectural"
    ],
    "wof:name":"Kwa",
    "wof:placetype":"venue"
},
  "geometry": {"coordinates":[-90.37757000000001,38.622786],"type":"Point"}
}