{
  "type": "Feature",
  "properties": {
    "iso:country":"US",
    "sg:address":"208 W North St",
    "sg:city":"Republic",
    "sg:classifiers":[
        {
            "category":"Freight",
            "type":"Transportation"
        }
    ],
    "sg:phone":"+1 417 732 1861",
    "sg:postcode":"65738",
    "sg:province":"MO",
    "sg:tags":[
        "over",
        "trucking"
    ],
    "wof:name":"Boatright Trucking Inc",
    "wof:placetype":"venue"
},
  "geometry": {"coordinates":[-93.481146,37.129368],"type":"Point"}
}