{
  "type": "Feature",
  "properties": {
    "iso:country":"US",
    "sg:address":"507 Francis St",
    "sg:city":"Saint Joseph",
    "sg:classifiers":[
        {
            "category":"Real Estate",
            "subcategory":"Real Estate Operator",
            "type":"Services"
        }
    ],
    "sg:phone":"+1 816 364 3020",
    "sg:postcode":"64501",
    "sg:province":"MO",
    "sg:tags":[
        "farm",
        "property",
        "crop",
        "lessor",
        "general"
    ],
    "wof:name":"Missouri River Farms Inc",
    "wof:placetype":"venue"
},
  "geometry": {"coordinates":[-94.853115,39.767466],"type":"Point"}
}