{
  "type": "Feature",
  "properties": {
    "iso:country":"US",
    "sg:address":"215 W Relief St",
    "sg:city":"Poplar Bluff",
    "sg:classifiers":[
        {
            "category":"Insurance",
            "subcategory":"Hazard Insurance",
            "type":"Services"
        }
    ],
    "sg:phone":"+1 573 776 7777",
    "sg:postcode":"63901",
    "sg:province":"MO",
    "sg:tags":[
        "bond"
    ],
    "wof:name":"Bail Bonds By Walter",
    "wof:placetype":"venue"
},
  "geometry": {"coordinates":[-90.39091500000001,36.76238],"type":"Point"}
}