{
  "type": "Feature",
  "properties": {
    "iso:country":"US",
    "sg:address":"1114 S Fuller St",
    "sg:city":"Independence",
    "sg:classifiers":[
        {
            "category":"Wholesale",
            "subcategory":"Auto Parts",
            "type":"Manufacturing & Wholesale Goods"
        }
    ],
    "sg:phone":"+1 816 836 4481",
    "sg:postcode":"64050",
    "sg:province":"MO",
    "sg:tags":[
        "automobile",
        "wrecking"
    ],
    "wof:name":"Dabney's Tow",
    "wof:placetype":"venue"
},
  "geometry": {"coordinates":[-94.4342,39.080193],"type":"Point"}
}