{
  "type": "Feature",
  "properties": {
    "iso:country":"US",
    "sg:address":"7870 Becker Rd",
    "sg:city":"Saint Louis",
    "sg:classifiers":[
        {
            "category":"Shopping",
            "subcategory":"Used Merchandise",
            "type":"Retail Goods"
        }
    ],
    "sg:phone":"+1 314 846 5110",
    "sg:postcode":"63129",
    "sg:province":"MO",
    "wof:name":"Southwest Designs By TEC",
    "wof:placetype":"venue"
},
  "geometry": {"coordinates":[-90.330669,38.414157],"type":"Point"}
}