{
  "type": "Feature",
  "properties": {
    "iso:country":"US",
    "sg:address":"3333 S Glenstone Ave",
    "sg:city":"Springfield",
    "sg:classifiers":[
        {
            "category":"Restaurant",
            "type":"Food & Drink"
        }
    ],
    "sg:phone":"+1 417 883 6550",
    "sg:postcode":"65804",
    "sg:province":"MO",
    "sg:tags":[
        "style",
        "family"
    ],
    "wof:name":"Glenstone Enterprises",
    "wof:placetype":"venue"
},
  "geometry": {"coordinates":[-93.263077,37.154388],"type":"Point"}
}