{
  "type": "Feature",
  "properties": {
    "iso:country":"US",
    "sg:address":"9706 Monitor Dr",
    "sg:city":"Hillsboro",
    "sg:classifiers":[
        {
            "category":"Real Estate",
            "subcategory":"Architect",
            "type":"Services"
        }
    ],
    "sg:phone":"+1 636 797 4433",
    "sg:postcode":"63050",
    "sg:province":"MO",
    "sg:tags":[
        "architectural",
        "business"
    ],
    "wof:name":"Creative Design Studio",
    "wof:placetype":"venue"
},
  "geometry": {"coordinates":[-90.61187700000001,38.265529],"type":"Point"}
}