{
  "type": "Feature",
  "properties": {
    "addr:full":"1978 Co Rd 156 Auxvasse MO 65231",
    "addr:housenumber":"1978",
    "addr:postcode":"65231",
    "addr:street":"Co Rd 156",
    "iso:country":"US",
    "sg:address":"1978 Co Rd 156",
    "sg:city":"Auxvasse",
    "sg:phone":"+1 573 386 5118",
    "sg:postcode":"65231",
    "sg:province":"MO",
    "sg:tags":[
        "farm",
        "grain",
        "cash"
    ],
    "wof:name":"Tim Lubbers",
    "wof:placetype":"venue"
},
  "geometry": {"coordinates":[-91.852964,38.970795],"type":"Point"}
}