{
  "type": "Feature",
  "properties": {
    "iso:country":"US",
    "sg:address":"1973 Hwy 52",
    "sg:city":"Tuscumbia",
    "sg:classifiers":[
        {
            "category":"Professional",
            "subcategory":"Business Services",
            "type":"Services"
        }
    ],
    "sg:phone":"+1 573 369 3923",
    "sg:postcode":"65082",
    "sg:province":"MO",
    "sg:tags":[
        "auctioneer"
    ],
    "wof:name":"Miller County Auction Co",
    "wof:placetype":"venue"
},
  "geometry": {"coordinates":[-92.461704,38.237118],"type":"Point"}
}