{
  "type": "Feature",
  "properties": {
    "iso:country":"US",
    "sg:address":"3 Industrial Dr",
    "sg:city":"Steelville",
    "sg:classifiers":[
        {
            "category":"Freight",
            "type":"Transportation"
        }
    ],
    "sg:phone":"+1 573 775 3355",
    "sg:postcode":"65565",
    "sg:province":"MO",
    "sg:tags":[
        "trucking"
    ],
    "wof:name":"Tucklisch Trucking Inc",
    "wof:placetype":"venue"
},
  "geometry": {"coordinates":[-91.341407,37.971967],"type":"Point"}
}