{
  "type": "Feature",
  "properties": {
    "iso:country":"US",
    "sg:address":"620 W Walnut St",
    "sg:city":"Blue Springs",
    "sg:classifiers":[
        {
            "category":"Building & Trades",
            "subcategory":"Construction",
            "type":"Services"
        }
    ],
    "sg:phone":"+1 816 373 3738",
    "sg:postcode":"64014",
    "sg:province":"MO",
    "sg:tags":[
        "contractor"
    ],
    "wof:name":"M R C Contracting Inc",
    "wof:placetype":"venue"
},
  "geometry": {"coordinates":[-94.270043,39.016358],"type":"Point"}
}