{
  "type": "Feature",
  "properties": {
    "iso:country":"US",
    "sg:address":"18931 E Valley View Pkwy",
    "sg:city":"Independence",
    "sg:classifiers":[
        {
            "category":"Restaurant",
            "type":"Food & Drink"
        }
    ],
    "sg:phone":"+1 816 795 8833",
    "sg:postcode":"64055",
    "sg:province":"MO",
    "sg:tags":[
        "eating"
    ],
    "wof:name":"Cheezteak Company",
    "wof:placetype":"venue"
},
  "geometry": {"coordinates":[-94.349114,39.038333],"type":"Point"}
}