{
  "type": "Feature",
  "properties": {
    "iso:country":"US",
    "sg:address":"7700 Irwin",
    "sg:city":"Kansas City",
    "sg:classifiers":[
        {
            "category":"Bus Charters",
            "type":"Transportation"
        }
    ],
    "sg:phone":"+1 816 356 5557",
    "sg:postcode":"64138",
    "sg:province":"MO",
    "wof:name":"Sunset Tours Inc",
    "wof:placetype":"venue"
},
  "geometry": {"coordinates":[-94.442476,38.981901],"type":"Point"}
}