{
  "type": "Feature",
  "properties": {
    "iso:country":"US",
    "sg:address":"310 N Locust St",
    "sg:city":"Sweet Springs",
    "sg:classifiers":[
        {
            "category":"Personal",
            "subcategory":"Beauty Salon",
            "type":"Services"
        }
    ],
    "sg:phone":"+1 660 335 4949",
    "sg:postcode":"65351",
    "sg:province":"MO",
    "sg:tags":[
        "shop"
    ],
    "wof:name":"Tina's Solution",
    "wof:placetype":"venue"
},
  "geometry": {"coordinates":[-93.41519599999999,38.96982],"type":"Point"}
}