{
  "type": "Feature",
  "properties": {
    "iso:country":"US",
    "sg:address":"3136 Watson Rd",
    "sg:city":"St Louis",
    "sg:classifiers":[
        {
            "category":"Home & Garden",
            "subcategory":"Building Materials",
            "type":"Retail Goods"
        },
        {
            "category":"Wholesale",
            "subcategory":"Painting Supplies",
            "type":"Manufacturing & Wholesale Goods"
        }
    ],
    "sg:phone":"+1 314 647 5055",
    "sg:postcode":"63139",
    "sg:province":"MO",
    "sg:tags":[
        "paint"
    ],
    "wof:name":"Frank Feagans Co Inc",
    "wof:placetype":"venue"
},
  "geometry": {"coordinates":[-90.29348899999999,38.606653],"type":"Point"}
}