{
  "type": "Feature",
  "properties": {
    "iso:country":"US",
    "sg:address":"9927 Markhall Ln",
    "sg:city":"St Louis",
    "sg:classifiers":[
        {
            "category":"Insurance",
            "subcategory":"Insurance Agent",
            "type":"Services"
        }
    ],
    "sg:phone":"+1 314 631 5057",
    "sg:postcode":"63123",
    "sg:province":"MO",
    "wof:name":"Dan May Insurance",
    "wof:placetype":"venue"
},
  "geometry": {"coordinates":[-90.33282199999999,38.537554],"type":"Point"}
}