{
  "type": "Feature",
  "properties": {
    "iso:country":"US",
    "sg:address":"100 W Boone St",
    "sg:city":"Ash Grove",
    "sg:classifiers":[
        {
            "category":"Manufacturing",
            "subcategory":"Printing",
            "type":"Manufacturing & Wholesale Goods"
        }
    ],
    "sg:phone":"+1 417 751 3183",
    "sg:postcode":"65604",
    "sg:province":"MO",
    "sg:tags":[
        "publisher"
    ],
    "wof:name":"Christ The Savior Brotherhood",
    "wof:placetype":"venue"
},
  "geometry": {"coordinates":[-93.58446000000001,37.31801],"type":"Point"}
}