{
  "type": "Feature",
  "properties": {
    "iso:country":"US",
    "sg:address":"346 Wilkerson Ave",
    "sg:city":"Camdenton",
    "sg:classifiers":[
        {
            "category":"Building & Trades",
            "subcategory":"Landscaping Services",
            "type":"Services"
        }
    ],
    "sg:phone":"+1 573 873 2284",
    "sg:postcode":"65020",
    "sg:province":"MO",
    "sg:tags":[
        "tree"
    ],
    "wof:name":"D & M Professional Tree Service",
    "wof:placetype":"venue"
},
  "geometry": {"coordinates":[-92.745317,38.015597],"type":"Point"}
}