{
  "type": "Feature",
  "properties": {
    "addr:full":"6027 Clearview Dr House Springs MO 63051",
    "addr:housenumber":"6027",
    "addr:postcode":"63051",
    "addr:street":"Clearview Dr House Springs",
    "iso:country":"US",
    "sg:address":"6027 Clearview Dr",
    "sg:city":"House Springs",
    "sg:classifiers":[
        {
            "category":"Professional",
            "type":"Services"
        }
    ],
    "sg:phone":"+1 636 677 7792",
    "sg:postcode":"63051",
    "sg:province":"MO",
    "wof:name":"Pampered Chef",
    "wof:placetype":"venue"
},
  "geometry": {"coordinates":[-90.5467,38.440239],"type":"Point"}
}