{
  "type": "Feature",
  "properties": {
    "iso:country":"US",
    "sg:address":"8705 Big Bend Blvd",
    "sg:city":"Saint Louis",
    "sg:classifiers":[
        {
            "category":"Home & Garden",
            "subcategory":"Building Materials",
            "type":"Retail Goods"
        },
        {
            "category":"Manufacturing",
            "subcategory":"Metals",
            "type":"Manufacturing & Wholesale Goods"
        }
    ],
    "sg:phone":"+1 314 961 2207",
    "sg:postcode":"63119",
    "sg:province":"MO",
    "sg:tags":[
        "coating"
    ],
    "wof:name":"PPG Porter Paints",
    "wof:placetype":"venue"
},
  "geometry": {"coordinates":[-90.359599,38.582367],"type":"Point"}
}