{
  "type": "Feature",
  "properties": {
    "iso:country":"US",
    "sg:address":"409 W Hickory St",
    "sg:city":"Kirksville",
    "sg:classifiers":[
        {
            "category":"Autos & Motor Vehicles",
            "subcategory":"Auto Supplies",
            "type":"Retail Goods"
        }
    ],
    "sg:phone":"+1 660 665 4100",
    "sg:postcode":"63501",
    "sg:province":"MO",
    "sg:tags":[
        "automobile",
        "stereo",
        "radio"
    ],
    "wof:name":"Sound Ideas",
    "wof:placetype":"venue"
},
  "geometry": {"coordinates":[-92.587542,40.19876],"type":"Point"}
}