{
  "type": "Feature",
  "properties": {
    "iso:country":"US",
    "sg:address":"8044 Manchester Rd",
    "sg:city":"St Louis",
    "sg:classifiers":[
        {
            "category":"Health Services",
            "subcategory":"Health Practitioner",
            "type":"Services"
        }
    ],
    "sg:phone":"+1 314 781 3848",
    "sg:postcode":"63144",
    "sg:province":"MO",
    "sg:tags":[
        "occupational",
        "safety"
    ],
    "wof:name":"SSM Corporate Health Svc",
    "wof:placetype":"venue"
},
  "geometry": {"coordinates":[-90.334515,38.612143],"type":"Point"}
}