{
  "type": "Feature",
  "properties": {
    "iso:country":"US",
    "sg:address":"121 N Benton St",
    "sg:city":"Waynesville",
    "sg:classifiers":[
        {
            "category":"Social Services",
            "type":"Services"
        }
    ],
    "sg:phone":"+1 573 774 6555",
    "sg:postcode":"65583",
    "sg:province":"MO",
    "sg:tags":[
        "individual",
        "emergency"
    ],
    "wof:name":"Birthright of Waynesville",
    "wof:placetype":"venue"
},
  "geometry": {"coordinates":[-92.20157500000001,37.829406],"type":"Point"}
}