{
  "type": "Feature",
  "properties": {
    "iso:country":"US",
    "sg:address":"626 E Russell Ave",
    "sg:city":"Warrensburg",
    "sg:classifiers":[
        {
            "category":"Travel",
            "subcategory":"Hotels & Motels",
            "type":"Entertainment"
        }
    ],
    "sg:phone":"+1 660 747 3000",
    "sg:postcode":"64093",
    "sg:province":"MO",
    "wof:name":"Holiday Inn Express Warrensbrg",
    "wof:placetype":"venue"
},
  "geometry": {"coordinates":[-93.72495600000001,38.772837],"type":"Point"}
}