{
  "type": "Feature",
  "properties": {
    "iso:country":"US",
    "sg:address":"811 Cherry St",
    "sg:city":"Columbia",
    "sg:classifiers":[
        {
            "category":"Restaurant",
            "type":"Food & Drink"
        }
    ],
    "sg:menulink":"http://www.allmenus.com/mo/columbia/261256-bangkok-gardens/menu/",
    "sg:phone":"+1 573 874 3284",
    "sg:postcode":"65201",
    "sg:province":"MO",
    "sg:tags":[
        "thai",
        "asian"
    ],
    "wof:name":"Bangkok Gardens",
    "wof:placetype":"venue"
},
  "geometry": {"coordinates":[-92.328514,38.950508],"type":"Point"}
}