{
  "type": "Feature",
  "properties": {
    "iso:country":"US",
    "sg:address":"5091 Baumgartner Rd",
    "sg:city":"Saint Louis",
    "sg:classifiers":[
        {
            "category":"Real Estate",
            "subcategory":"Real Estate Operator",
            "type":"Services"
        }
    ],
    "sg:phone":"+1 314 487 9400",
    "sg:postcode":"63129",
    "sg:province":"MO",
    "sg:tags":[
        "building",
        "nonresidential"
    ],
    "wof:name":"Terra Holding Co Inc",
    "wof:placetype":"venue"
},
  "geometry": {"coordinates":[-90.352694,38.463213],"type":"Point"}
}