{
  "type": "Feature",
  "properties": {
    "iso:country":"US",
    "sg:address":"1723 Black Twig Ln",
    "sg:city":"Saint Louis",
    "sg:classifiers":[
        {
            "category":"Professional",
            "subcategory":"Business Services",
            "type":"Services"
        }
    ],
    "sg:phone":"+1 314 965 7626",
    "sg:postcode":"63122",
    "sg:province":"MO",
    "wof:name":"Ideations",
    "wof:placetype":"venue"
},
  "geometry": {"coordinates":[-90.436491,38.595387],"type":"Point"}
}