{
  "type": "Feature",
  "properties": {
    "iso:country":"US",
    "sg:address":"925 Iron Gate Walk",
    "sg:city":"Ballwin",
    "sg:classifiers":[
        {
            "category":"Organizations",
            "subcategory":"Professional Association",
            "type":"Services"
        }
    ],
    "sg:phone":"+1 636 527 2690",
    "sg:postcode":"63011",
    "sg:province":"MO",
    "wof:name":"Grampion Group",
    "wof:placetype":"venue"
},
  "geometry": {"coordinates":[-90.513662,38.619622],"type":"Point"}
}