{
  "type": "Feature",
  "properties": {
    "addr:full":"12825 US Hwy 63 Rolla MO 65401",
    "addr:housenumber":"12825",
    "addr:postcode":"65401",
    "addr:street":"Us Hwy 63",
    "iso:country":"US",
    "sg:address":"12825 US Hwy 63",
    "sg:city":"Rolla",
    "sg:classifiers":[
        {
            "category":"Wholesale",
            "subcategory":"Machinery & Supplies",
            "type":"Manufacturing & Wholesale Goods"
        }
    ],
    "sg:phone":"+1 573 368 3299",
    "sg:postcode":"65401",
    "sg:province":"MO",
    "sg:tags":[
        "equipment",
        "welding"
    ],
    "wof:name":"Airgas",
    "wof:placetype":"venue"
},
  "geometry": {"coordinates":[-91.776385,37.913268],"type":"Point"}
}