{
  "type": "Feature",
  "properties": {
    "iso:country":"US",
    "sg:address":"13131 Tesson Ferry Rd",
    "sg:city":"Saint Louis",
    "sg:classifiers":[
        {
            "category":"Health Services",
            "subcategory":"Clinic",
            "type":"Services"
        }
    ],
    "sg:phone":"+1 314 849 8523",
    "sg:postcode":"63128",
    "sg:province":"MO",
    "sg:tags":[
        "specialty",
        "outpatient"
    ],
    "wof:name":"Jeanine Valleroy PHD",
    "wof:placetype":"venue"
},
  "geometry": {"coordinates":[-90.383655,38.486237],"type":"Point"}
}