{
  "type": "Feature",
  "properties": {
    "iso:country":"US",
    "sg:address":"900 N 1st St",
    "sg:city":"Saint Louis",
    "sg:classifiers":[
        {
            "category":"Restaurant",
            "type":"Food & Drink"
        }
    ],
    "sg:phone":"+1 314 241 5915",
    "sg:postcode":"63102",
    "sg:province":"MO",
    "sg:tags":[
        "traditional",
        "american"
    ],
    "wof:name":"Sundecker's Bar and Grill",
    "wof:placetype":"venue"
},
  "geometry": {"coordinates":[-90.1828,38.632198],"type":"Point"}
}