{
  "type": "Feature",
  "properties": {
    "iso:country":"US",
    "sg:address":"4305 S National Ave",
    "sg:city":"Springfield",
    "sg:classifiers":[
        {
            "category":"Personal",
            "subcategory":"Beauty Salon",
            "type":"Services"
        }
    ],
    "sg:phone":"+1 417 885 0077",
    "sg:postcode":"65810",
    "sg:province":"MO",
    "sg:tags":[
        "shop"
    ],
    "wof:name":"Mane Event",
    "wof:placetype":"venue"
},
  "geometry": {"coordinates":[-93.277505,37.133726],"type":"Point"}
}