{
  "type": "Feature",
  "properties": {
    "iso:country":"US",
    "sg:address":"1120 W Foxwood Dr",
    "sg:city":"Raymore",
    "sg:classifiers":[
        {
            "category":"Restaurant",
            "type":"Food & Drink"
        }
    ],
    "sg:menulink":"http://www.allmenus.com/mo/raymore/194281-mcdonalds/menu/",
    "sg:postcode":"64083",
    "sg:province":"MO",
    "sg:tags":[
        "burger",
        "american"
    ],
    "wof:name":"McDonald's",
    "wof:placetype":"venue"
},
  "geometry": {"coordinates":[-94.47292400000001,38.811987],"type":"Point"}
}