{
  "type": "Feature",
  "properties": {
    "iso:country":"US",
    "sg:address":"5616 US Hwy 54",
    "sg:city":"Osage Beach",
    "sg:classifiers":[
        {
            "category":"Shopping",
            "type":"Retail Goods"
        }
    ],
    "sg:phone":"+1 573 348 5958",
    "sg:postcode":"65065",
    "sg:province":"MO",
    "sg:tags":[
        "merchandise"
    ],
    "wof:name":"Trophy Art",
    "wof:placetype":"venue"
},
  "geometry": {"coordinates":[-92.666894,38.126683],"type":"Point"}
}