{
  "type": "Feature",
  "properties": {
    "iso:country":"US",
    "sg:address":"307 Market St",
    "sg:city":"Berger",
    "sg:classifiers":[
        {
            "category":"Professional",
            "type":"Services"
        }
    ],
    "sg:phone":"+1 573 834 5229",
    "sg:postcode":"63014",
    "sg:province":"MO",
    "wof:name":"Berger Firehouse",
    "wof:placetype":"venue"
},
  "geometry": {"coordinates":[-91.339457,38.674232],"type":"Point"}
}