{
  "type": "Feature",
  "properties": {
    "iso:country":"US",
    "sg:address":"614 S Brookside Ave",
    "sg:city":"Independence",
    "sg:classifiers":[
        {
            "category":"Real Estate",
            "subcategory":"Developer",
            "type":"Services"
        }
    ],
    "sg:phone":"+1 816 252 4141",
    "sg:postcode":"64052",
    "sg:province":"MO",
    "sg:tags":[
        "cemetery"
    ],
    "wof:name":"Mount Wash Forever Fnrl HM Ce",
    "wof:placetype":"venue"
},
  "geometry": {"coordinates":[-94.46775,39.095106],"type":"Point"}
}