{
  "type": "Feature",
  "properties": {
    "iso:country":"US",
    "sg:address":"6451 N Cosby Ave",
    "sg:city":"Kansas City",
    "sg:classifiers":[
        {
            "category":"Manufacturing",
            "subcategory":"Apparel",
            "type":"Manufacturing & Wholesale Goods"
        }
    ],
    "sg:phone":"+1 816 587 2020",
    "sg:postcode":"64151",
    "sg:province":"MO",
    "wof:name":"Embroider Shoppe",
    "wof:placetype":"venue"
},
  "geometry": {"coordinates":[-94.646627,39.21116],"type":"Point"}
}