{
  "type": "Feature",
  "properties": {
    "iso:country":"US",
    "sg:address":"7536 Forsyth Blvd",
    "sg:city":"Clayton",
    "sg:classifiers":[
        {
            "category":"Insurance",
            "subcategory":"Hazard Insurance",
            "type":"Services"
        }
    ],
    "sg:phone":"+1 314 863 4015",
    "sg:postcode":"63105",
    "sg:province":"MO",
    "sg:tags":[
        "profit",
        "sharing",
        "pension",
        "plan"
    ],
    "wof:name":"ABC Assoc",
    "wof:placetype":"venue"
},
  "geometry": {"coordinates":[-90.33033,38.6495],"type":"Point"}
}