{
  "type": "Feature",
  "properties": {
    "iso:country":"US",
    "sg:address":"109 N Main St",
    "sg:city":"Clarkton",
    "sg:classifiers":[
        {
            "category":"Government",
            "subcategory":"Police Station",
            "type":"Public Place"
        },
        {
            "category":"Government",
            "subcategory":"Office",
            "type":"Public Place"
        }
    ],
    "sg:phone":"+1 573 448 3500",
    "sg:postcode":"63837",
    "sg:province":"MO",
    "sg:tags":[
        "department",
        "township",
        "government-city",
        "village"
    ],
    "wof:name":"Gideon-City",
    "wof:placetype":"venue"
},
  "geometry": {"coordinates":[-89.96741400000001,36.451741],"type":"Point"}
}