{
  "type": "Feature",
  "properties": {
    "addr:full":"7100 Eastwood Trfy Kansas City MO 64129",
    "addr:housenumber":"7100",
    "addr:postcode":"64129",
    "addr:street":"Eastwood Trfy",
    "iso:country":"US",
    "sg:address":"7100 Eastwood Trfy",
    "sg:city":"Kansas City",
    "sg:classifiers":[
        {
            "category":"Autos & Motor Vehicles",
            "subcategory":"Fuel & Gas Station",
            "type":"Retail Goods"
        }
    ],
    "sg:phone":"+1 816 921 8284",
    "sg:postcode":"64129",
    "sg:province":"MO",
    "sg:tags":[
        "grocery",
        "station",
        "gasoline"
    ],
    "wof:name":"Quiktrip",
    "wof:placetype":"venue"
},
  "geometry": {"coordinates":[-94.501966,39.031151],"type":"Point"}
}