{
  "type": "Feature",
  "properties": {
    "iso:country":"US",
    "sg:address":"1323 Mitchell Ave",
    "sg:city":"St Joseph",
    "sg:classifiers":[
        {
            "category":"Building & Trades",
            "subcategory":"Construction",
            "type":"Services"
        }
    ],
    "sg:phone":"+1 816 279 3563",
    "sg:postcode":"64503",
    "sg:province":"MO",
    "sg:tags":[
        "repairing",
        "remodeling",
        "contractor"
    ],
    "wof:name":"Payne Construction",
    "wof:placetype":"venue"
},
  "geometry": {"coordinates":[-94.84365099999999,39.755257],"type":"Point"}
}