{
  "type": "Feature",
  "properties": {
    "iso:country":"US",
    "sg:address":"10 Barnes West Dr",
    "sg:city":"Saint Louis",
    "sg:classifiers":[
        {
            "category":"Health Services",
            "subcategory":"Health Practitioner",
            "type":"Services"
        }
    ],
    "sg:phone":"+1 314 205 2223",
    "sg:postcode":"63141",
    "sg:province":"MO",
    "sg:tags":[
        "medical"
    ],
    "wof:name":"David M Brown MD",
    "wof:placetype":"venue"
},
  "geometry": {"coordinates":[-90.46700300000001,38.675553],"type":"Point"}
}