{
  "type": "Feature",
  "properties": {
    "iso:country":"US",
    "sg:address":"2959 Antelope Rd",
    "sg:city":"Joplin",
    "sg:classifiers":[
        {
            "category":"Home & Garden",
            "subcategory":"Home Furnishings",
            "type":"Retail Goods"
        }
    ],
    "sg:phone":"+1 417 781 4305",
    "sg:postcode":"64804",
    "sg:province":"MO",
    "sg:tags":[
        "pottery"
    ],
    "wof:name":"Pottery Zone",
    "wof:placetype":"venue"
},
  "geometry": {"coordinates":[-94.58229300000001,37.028535],"type":"Point"}
}