{
  "type": "Feature",
  "properties": {
    "iso:country":"US",
    "sg:address":"11 Champion Dr",
    "sg:city":"Fenton",
    "sg:classifiers":[
        {
            "category":"Personal",
            "subcategory":"Massage",
            "type":"Services"
        }
    ],
    "sg:phone":"+1 636 600 4056",
    "sg:postcode":"63026",
    "sg:province":"MO",
    "sg:tags":[
        "therapist"
    ],
    "wof:name":"Massageluxe",
    "wof:placetype":"venue"
},
  "geometry": {"coordinates":[-90.461944,38.496354],"type":"Point"}
}