{
  "type": "Feature",
  "properties": {
    "iso:country":"US",
    "sg:address":"566 Co Rd 513",
    "sg:city":"Altenburg",
    "sg:classifiers":[
        {
            "category":"Farming",
            "subcategory":"Livestock Farm",
            "type":"Manufacturing & Wholesale Goods"
        }
    ],
    "sg:phone":"+1 573 833 6584",
    "sg:postcode":"63732",
    "sg:province":"MO",
    "sg:tags":[
        "beef",
        "feedlot",
        "cattle"
    ],
    "wof:name":"Ruben Haertling",
    "wof:placetype":"venue"
},
  "geometry": {"coordinates":[-89.62108600000001,37.582273],"type":"Point"}
}