{
  "type": "Feature",
  "properties": {
    "iso:country":"US",
    "sg:address":"4664 South Grand Blvd",
    "sg:city":"Saint Louis",
    "sg:classifiers":[
        {
            "category":"Home & Garden",
            "subcategory":"Building Materials",
            "type":"Retail Goods"
        }
    ],
    "sg:phone":"+1 314 494 4200",
    "sg:postcode":"63116",
    "sg:province":"MO",
    "sg:tags":[
        "supply"
    ],
    "sg:website":"www.stonepros.biz/",
    "wof:name":"Stone Pros",
    "wof:placetype":"venue"
},
  "geometry": {"coordinates":[-90.2489,38.575048],"type":"Point"}
}