{
  "type": "Feature",
  "properties": {
    "iso:country":"US",
    "sg:address":"103 W Steel St",
    "sg:city":"Seymour",
    "sg:classifiers":[
        {
            "category":"Shopping",
            "subcategory":"Discount & Variety Stores",
            "type":"Retail Goods"
        }
    ],
    "sg:phone":"+1 417 935 4348",
    "sg:postcode":"65746",
    "sg:province":"MO",
    "sg:tags":[
        "merchandise",
        "general"
    ],
    "wof:name":"Dollar General",
    "wof:placetype":"venue"
},
  "geometry": {"coordinates":[-92.769276,37.155582],"type":"Point"}
}