{
  "type": "Feature",
  "properties": {
    "iso:country":"US",
    "sg:address":"101 N Range Line Rd",
    "sg:city":"Joplin",
    "sg:classifiers":[
        {
            "category":"Food & Beverages",
            "subcategory":"Candy",
            "type":"Retail Goods"
        }
    ],
    "sg:phone":"+1 417 623 1299",
    "sg:postcode":"64801",
    "sg:province":"MO",
    "sg:tags":[
        "confectionery"
    ],
    "wof:name":"Tropik Sun Fruit & Nut",
    "wof:placetype":"venue"
},
  "geometry": {"coordinates":[-94.47687500000001,37.093661],"type":"Point"}
}