{
  "type": "Feature",
  "properties": {
    "iso:country":"US",
    "sg:address":"1205 Woodswether Rd",
    "sg:city":"Kansas City",
    "sg:classifiers":[
        {
            "category":"Professional",
            "subcategory":"Business Services",
            "type":"Services"
        }
    ],
    "sg:phone":"+1 816 472 5009",
    "sg:postcode":"64105",
    "sg:province":"MO",
    "sg:tags":[
        "liquidator"
    ],
    "wof:name":"International Asset Lqdtrs",
    "wof:placetype":"venue"
},
  "geometry": {"coordinates":[-94.599487,39.108058],"type":"Point"}
}