{
  "type": "Feature",
  "properties": {
    "iso:country":"US",
    "sg:address":"470 SW 701st Rd",
    "sg:city":"Centerview",
    "sg:phone":"+1 816 732 6682",
    "sg:postcode":"64019",
    "sg:province":"MO",
    "sg:tags":[
        "farm",
        "field",
        "corn",
        "crop",
        "soybean"
    ],
    "wof:name":"Morris Hamlin",
    "wof:placetype":"venue"
},
  "geometry": {"coordinates":[-93.880279,38.695791],"type":"Point"}
}