{
  "type": "Feature",
  "properties": {
    "iso:country":"US",
    "sg:address":"5500 Heege Rd",
    "sg:city":"St Louis",
    "sg:classifiers":[
        {
            "category":"Building & Trades",
            "subcategory":"Construction",
            "type":"Services"
        }
    ],
    "sg:phone":"+1 314 351 0445",
    "sg:postcode":"63123",
    "sg:province":"MO",
    "sg:tags":[
        "plastering",
        "contractor"
    ],
    "wof:name":"Gypsum Specialty Contractors",
    "wof:placetype":"venue"
},
  "geometry": {"coordinates":[-90.311538,38.564741],"type":"Point"}
}