{
  "type": "Feature",
  "properties": {
    "iso:country":"US",
    "sg:address":"24 E Main St",
    "sg:city":"Festus",
    "sg:classifiers":[
        {
            "category":"Shopping",
            "subcategory":"Used Merchandise",
            "type":"Retail Goods"
        }
    ],
    "sg:phone":"+1 636 931 5551",
    "sg:postcode":"63028",
    "sg:province":"MO",
    "sg:tags":[
        "appliance"
    ],
    "wof:name":"Second Chance Appliances",
    "wof:placetype":"venue"
},
  "geometry": {"coordinates":[-90.389037,38.219407],"type":"Point"}
}