{
  "type": "Feature",
  "properties": {
    "iso:country":"US",
    "sg:address":"4232 Wornall Rd",
    "sg:city":"Kansas City",
    "sg:classifiers":[
        {
            "category":"Social Services",
            "subcategory":"Child Care",
            "type":"Services"
        }
    ],
    "sg:phone":"+1 816 932 3832",
    "sg:postcode":"64111",
    "sg:province":"MO",
    "sg:tags":[
        "day"
    ],
    "wof:name":"The Childrens Spot",
    "wof:placetype":"venue"
},
  "geometry": {"coordinates":[-94.590549,39.049552],"type":"Point"}
}