{
  "type": "Feature",
  "properties": {
    "iso:country":"US",
    "sg:address":"964 Kehrs Mill Rd",
    "sg:city":"Ballwin",
    "sg:classifiers":[
        {
            "category":"Health Services",
            "subcategory":"Dentist",
            "type":"Services"
        }
    ],
    "sg:phone":"+1 888 533 5358",
    "sg:postcode":"63011",
    "sg:province":"MO",
    "sg:tags":[
        "product",
        "dentists-cosmetic",
        "teeth",
        "whitening",
        "dentistry",
        "dentists-orthodontists"
    ],
    "sg:website":"http://stlouis.citysearch.com/profile/external/653775460/ballwin_mo/dr_robert_o_brien_dds_pc.html?publisher=yellowpages&reference_id=7&placement=ypwebsitemip",
    "wof:name":"Dr. Robert O Brien DDS PC",
    "wof:placetype":"venue"
},
  "geometry": {"coordinates":[-90.56462500000001,38.606016],"type":"Point"}
}