{
  "type": "Feature",
  "properties": {
    "iso:country":"US",
    "sg:address":"2803 S McKnight Rd",
    "sg:city":"Webster Groves",
    "sg:classifiers":[
        {
            "category":"Manufacturing",
            "subcategory":"Signs",
            "type":"Manufacturing & Wholesale Goods"
        }
    ],
    "sg:phone":"+1 314 961 3118",
    "sg:postcode":"63119",
    "sg:province":"MO",
    "wof:name":"Sign Designs",
    "wof:placetype":"venue"
},
  "geometry": {"coordinates":[-90.363478,38.610254],"type":"Point"}
}