{
  "type": "Feature",
  "properties": {
    "iso:country":"US",
    "sg:address":"444 Chesterfield Center",
    "sg:city":"Chesterfield",
    "sg:classifiers":[
        {
            "category":"Insurance",
            "subcategory":"Insurance Agent",
            "type":"Services"
        }
    ],
    "sg:phone":"+1 636 519 7055",
    "sg:postcode":"63017",
    "sg:province":"MO",
    "wof:name":"Gardner & White",
    "wof:placetype":"venue"
},
  "geometry": {"coordinates":[-90.567893,38.650153],"type":"Point"}
}