{
  "type": "Feature",
  "properties": {
    "iso:country":"US",
    "sg:address":"120 Main St",
    "sg:city":"Belton",
    "sg:classifiers":[
        {
            "category":"Shopping",
            "subcategory":"Florist",
            "type":"Retail Goods"
        }
    ],
    "sg:phone":"+1 816 331 1992",
    "sg:postcode":"64012",
    "sg:province":"MO",
    "wof:name":"Plum Beautiful Florist",
    "wof:placetype":"venue"
},
  "geometry": {"coordinates":[-94.534206,38.813207],"type":"Point"}
}