{
  "type": "Feature",
  "properties": {
    "iso:country":"US",
    "sg:address":"243 Kaywin Ct",
    "sg:city":"Chesterfield",
    "sg:classifiers":[
        {
            "category":"Professional",
            "subcategory":"Lawyer & Legal Services",
            "type":"Services"
        }
    ],
    "sg:phone":"+1 314 434 8230",
    "sg:postcode":"63017",
    "sg:province":"MO",
    "wof:name":"Baron and Budd PC",
    "wof:placetype":"venue"
},
  "geometry": {"coordinates":[-90.526096,38.663017],"type":"Point"}
}