{
  "type": "Feature",
  "properties": {
    "iso:country":"US",
    "sg:address":"8011 Forest Park Dr",
    "sg:city":"Kansas City",
    "sg:classifiers":[
        {
            "category":"Restaurant",
            "type":"Food & Drink"
        }
    ],
    "sg:phone":"+1 816 505 0177",
    "sg:postcode":"64152",
    "sg:province":"MO",
    "sg:tags":[
        "eating"
    ],
    "wof:name":"Culinary Group Inc",
    "wof:placetype":"venue"
},
  "geometry": {"coordinates":[-94.66409299999999,39.201168],"type":"Point"}
}