{
  "type": "Feature",
  "properties": {
    "iso:country":"US",
    "sg:address":"1101 US Hwy 60 Bus",
    "sg:city":"Dexter",
    "sg:classifiers":[
        {
            "category":"Personal",
            "subcategory":"Beauty Salon",
            "type":"Services"
        }
    ],
    "sg:phone":"+1 573 624 3337",
    "sg:postcode":"63841",
    "sg:province":"MO",
    "wof:name":"Carpet Direct No II",
    "wof:placetype":"venue"
},
  "geometry": {"coordinates":[-89.97477600000001,36.803605],"type":"Point"}
}