{
  "type": "Feature",
  "properties": {
    "addr:full":"805 Clinic Rd Hannibal MO 63401",
    "addr:housenumber":"805",
    "addr:postcode":"63401",
    "addr:street":"Clinic Rd",
    "iso:country":"US",
    "sg:address":"805 Clinic Rd",
    "sg:city":"Hannibal",
    "sg:classifiers":[
        {
            "category":"Government",
            "subcategory":"Office",
            "type":"Public Place"
        }
    ],
    "sg:phone":"+1 573 248 2400",
    "sg:postcode":"63401",
    "sg:province":"MO",
    "sg:tags":[
        "state",
        "program",
        "health"
    ],
    "wof:name":"Mental Health Dept",
    "wof:placetype":"venue"
},
  "geometry": {"coordinates":[-91.395217,39.697738],"type":"Point"}
}