{
  "type": "Feature",
  "properties": {
    "iso:country":"US",
    "sg:address":"350 Village Square Dr",
    "sg:city":"Hazelwood",
    "sg:classifiers":[
        {
            "category":"Freight",
            "type":"Transportation"
        }
    ],
    "sg:phone":"+1 314 731 2293",
    "sg:postcode":"63042",
    "sg:province":"MO",
    "sg:tags":[
        "warehouse",
        "self",
        "storage"
    ],
    "wof:name":"Van's Hallmark Warehouse",
    "wof:placetype":"venue"
},
  "geometry": {"coordinates":[-90.361279,38.780186],"type":"Point"}
}