{
  "type": "Feature",
  "properties": {
    "iso:country":"US",
    "sg:address":"1322 Clarkson Clayton Center",
    "sg:city":"Ellisville",
    "sg:classifiers":[
        {
            "category":"Food & Beverages",
            "subcategory":"Groceries & Convenience Stores",
            "type":"Retail Goods"
        }
    ],
    "sg:phone":"+1 636 394 2254",
    "sg:postcode":"63011",
    "sg:province":"MO",
    "sg:tags":[
        "grocer"
    ],
    "sg:website":"www.dierbergs.com",
    "wof:name":"Dierbergs Markets",
    "wof:placetype":"venue"
},
  "geometry": {"coordinates":[-90.58650299999999,38.603729],"type":"Point"}
}