{
  "type": "Feature",
  "properties": {
    "iso:country":"US",
    "sg:address":"806 W Worley St",
    "sg:city":"Columbia",
    "sg:classifiers":[
        {
            "category":"Professional",
            "subcategory":"Accounting & Tax Preparation",
            "type":"Services"
        }
    ],
    "sg:phone":"+1 573 442 2588",
    "sg:postcode":"65203",
    "sg:province":"MO",
    "sg:tags":[
        "business"
    ],
    "wof:name":"Bottom Line Accounting Tax Svc",
    "wof:placetype":"venue"
},
  "geometry": {"coordinates":[-92.35074899999999,38.959153],"type":"Point"}
}