{
  "type": "Feature",
  "properties": {
    "iso:country":"US",
    "sg:address":"19 River Trl",
    "sg:city":"Saint Charles",
    "sg:classifiers":[
        {
            "category":"Building & Trades",
            "subcategory":"Construction",
            "type":"Services"
        }
    ],
    "sg:phone":"+1 636 926 0364",
    "sg:postcode":"63303",
    "sg:province":"MO",
    "sg:tags":[
        "concrete",
        "coating"
    ],
    "wof:name":"Show ME Industrial Service",
    "wof:placetype":"venue"
},
  "geometry": {"coordinates":[-90.539075,38.731121],"type":"Point"}
}