{
  "type": "Feature",
  "properties": {
    "iso:country":"US",
    "sg:address":"110 State Hwy 34",
    "sg:city":"Glenallen",
    "sg:classifiers":[
        {
            "category":"Food & Beverages",
            "subcategory":"Groceries & Convenience Stores",
            "type":"Retail Goods"
        }
    ],
    "sg:phone":"+1 573 238 3326",
    "sg:postcode":"63751",
    "sg:province":"MO",
    "sg:tags":[
        "grocer"
    ],
    "wof:name":"Barker's Grocery Store",
    "wof:placetype":"venue"
},
  "geometry": {"coordinates":[-89.97885599999999,37.302668],"type":"Point"}
}