{
  "type": "Feature",
  "properties": {
    "iso:country":"US",
    "sg:address":"610 Kinswood Ln",
    "sg:city":"St Louis",
    "sg:classifiers":[
        {
            "category":"Social Services",
            "subcategory":"Child Care",
            "type":"Services"
        }
    ],
    "sg:phone":"+1 314 892 4446",
    "sg:postcode":"63129",
    "sg:province":"MO",
    "sg:tags":[
        "day"
    ],
    "wof:name":"Casa Dia Montessori",
    "wof:placetype":"venue"
},
  "geometry": {"coordinates":[-90.307667,38.49673],"type":"Point"}
}