{
  "type": "Feature",
  "properties": {
    "iso:country":"US",
    "sg:address":"2207 S Westwood Blvd",
    "sg:city":"Poplar Bluff",
    "sg:classifiers":[
        {
            "category":"Recreation",
            "type":"Entertainment"
        }
    ],
    "sg:phone":"+1 573 686 4880",
    "sg:postcode":"63901",
    "sg:province":"MO",
    "sg:tags":[
        "parlor",
        "billiard"
    ],
    "wof:name":"Westwood Billiards Center",
    "wof:placetype":"venue"
},
  "geometry": {"coordinates":[-90.421296,36.738341],"type":"Point"}
}