{
  "type": "Feature",
  "properties": {
    "iso:country":"US",
    "sg:address":"5817 Sutherland Ave",
    "sg:city":"Saint Louis",
    "sg:classifiers":[
        {
            "category":"Wholesale",
            "subcategory":"Medical Equipment & Supplies",
            "type":"Manufacturing & Wholesale Goods"
        }
    ],
    "sg:phone":"+1 314 533 0828",
    "sg:postcode":"63109",
    "sg:province":"MO",
    "wof:name":"Surgical Dynamics",
    "wof:placetype":"venue"
},
  "geometry": {"coordinates":[-90.294459,38.590745],"type":"Point"}
}