{
  "type": "Feature",
  "properties": {
    "iso:country":"US",
    "sg:address":"15610 Cedarmill Dr",
    "sg:city":"Chesterfield",
    "sg:classifiers":[
        {
            "category":"Freight",
            "type":"Transportation"
        }
    ],
    "sg:phone":"+1 636 519 8142",
    "sg:postcode":"63017",
    "sg:province":"MO",
    "sg:tags":[
        "car",
        "railroad",
        "leasing"
    ],
    "wof:name":"CIT Rail Resources",
    "wof:placetype":"venue"
},
  "geometry": {"coordinates":[-90.559541,38.636009],"type":"Point"}
}