{
  "type": "Feature",
  "properties": {
    "iso:country":"US",
    "sg:address":"509 Belmont Dr",
    "sg:city":"Raymore",
    "sg:classifiers":[
        {
            "category":"Building & Trades",
            "subcategory":"Construction",
            "type":"Services"
        }
    ],
    "sg:phone":"+1 816 322 4130",
    "sg:postcode":"64083",
    "sg:province":"MO",
    "sg:tags":[
        "general",
        "contractor"
    ],
    "wof:name":"AMF Construction Inc",
    "wof:placetype":"venue"
},
  "geometry": {"coordinates":[-94.459378,38.796309],"type":"Point"}
}