{
  "type": "Feature",
  "properties": {
    "iso:country":"US",
    "sg:address":"3120 W 10th St",
    "sg:city":"Sedalia",
    "sg:classifiers":[
        {
            "category":"Banks & Credit Unions",
            "subcategory":"Bank",
            "type":"Services"
        }
    ],
    "sg:phone":"+1 660 826 6922",
    "sg:postcode":"65301",
    "sg:province":"MO",
    "sg:tags":[
        "commercial",
        "saving"
    ],
    "sg:website":"http://www.cmccreditunion.org",
    "wof:name":"Central Missouri Community Credit Union",
    "wof:placetype":"venue"
},
  "geometry": {"coordinates":[-93.269262,38.703907],"type":"Point"}
}