{
  "type": "Feature",
  "properties": {
    "iso:country":"US",
    "sg:address":"1016 Wilmer Rd",
    "sg:city":"Wentzville",
    "sg:classifiers":[
        {
            "category":"Manufacturing",
            "subcategory":"Chemicals & Compounds",
            "type":"Manufacturing & Wholesale Goods"
        }
    ],
    "sg:phone":"+1 636 327 4819",
    "sg:postcode":"63385",
    "sg:province":"MO",
    "sg:tags":[
        "fertilizer",
        "mixing",
        "only"
    ],
    "wof:name":"Mfa Inc",
    "wof:placetype":"venue"
},
  "geometry": {"coordinates":[-90.868965,38.806993],"type":"Point"}
}