{
  "type": "Feature",
  "properties": {
    "iso:country":"US",
    "sg:address":"161 E Lincoln St",
    "sg:city":"Hawk Point",
    "sg:classifiers":[
        {
            "category":"Government",
            "subcategory":"Office",
            "type":"Public Place"
        }
    ],
    "sg:phone":"+1 636 338 4377",
    "sg:postcode":"63349",
    "sg:province":"MO",
    "sg:tags":[
        "city"
    ],
    "wof:name":"Hawk Point City Hall",
    "wof:placetype":"venue"
},
  "geometry": {"coordinates":[-91.12438400000001,38.967876],"type":"Point"}
}