{
  "type": "Feature",
  "properties": {
    "iso:country":"US",
    "sg:address":"3425 Union Blvd",
    "sg:city":"Saint Louis",
    "sg:classifiers":[
        {
            "category":"Shopping",
            "subcategory":"Beauty & Cosmetics",
            "type":"Retail Goods"
        }
    ],
    "sg:phone":"+1 314 382 5477",
    "sg:postcode":"63115",
    "sg:province":"MO",
    "sg:tags":[
        "supply"
    ],
    "wof:name":"Nu Fashion Beauty Product Distributor",
    "wof:placetype":"venue"
},
  "geometry": {"coordinates":[-90.25885599999999,38.678444],"type":"Point"}
}