{
  "type": "Feature",
  "properties": {
    "iso:country":"US",
    "sg:address":"3230 Parker Rd",
    "sg:city":"Florissant",
    "sg:classifiers":[
        {
            "category":"Insurance",
            "subcategory":"Insurance Agent",
            "type":"Services"
        }
    ],
    "sg:phone":"+1 314 838 0600",
    "sg:postcode":"63033",
    "sg:province":"MO",
    "wof:name":"Statler Realty Company",
    "wof:placetype":"venue"
},
  "geometry": {"coordinates":[-90.293181,38.795169],"type":"Point"}
}