{
  "type": "Feature",
  "properties": {
    "iso:country":"US",
    "sg:address":"2648 E Stanford St",
    "sg:city":"Springfield",
    "sg:classifiers":[
        {
            "category":"Building & Trades",
            "subcategory":"Cleaning & Sanitation",
            "type":"Services"
        }
    ],
    "sg:phone":"+1 417 880 0588",
    "sg:postcode":"65804",
    "sg:province":"MO",
    "sg:tags":[
        "maintenance"
    ],
    "wof:name":"Dbr Services",
    "wof:placetype":"venue"
},
  "geometry": {"coordinates":[-93.241302,37.182586],"type":"Point"}
}