{
  "type": "Feature",
  "properties": {
    "iso:country":"US",
    "sg:address":"3350 Gravois Ave",
    "sg:city":"Saint Louis",
    "sg:classifiers":[
        {
            "category":"Restaurant",
            "type":"Food & Drink"
        }
    ],
    "sg:phone":"+1 314 771 8818",
    "sg:postcode":"63118",
    "sg:province":"MO",
    "sg:tags":[
        "chinese"
    ],
    "wof:name":"New China",
    "wof:placetype":"venue"
},
  "geometry": {"coordinates":[-90.239535,38.595654],"type":"Point"}
}