{
  "type": "Feature",
  "properties": {
    "iso:country":"US",
    "sg:address":"1941 Boone Villa Dr",
    "sg:city":"Boonville",
    "sg:classifiers":[
        {
            "category":"Health Services",
            "subcategory":"Doctor",
            "type":"Services"
        }
    ],
    "sg:phone":"+1 660 882 7522",
    "sg:postcode":"65233",
    "sg:province":"MO",
    "sg:tags":[
        "dentist"
    ],
    "wof:name":"Virginia E Dooley DDS",
    "wof:placetype":"venue"
},
  "geometry": {"coordinates":[-92.742422,38.955988],"type":"Point"}
}