{
  "type": "Feature",
  "properties": {
    "iso:country":"US",
    "sg:address":"5033 Rosa Ave",
    "sg:city":"St Louis",
    "sg:classifiers":[
        {
            "category":"Building & Trades",
            "subcategory":"Construction",
            "type":"Services"
        }
    ],
    "sg:phone":"+1 314 835 1025",
    "sg:postcode":"63109",
    "sg:province":"MO",
    "sg:tags":[
        "painter"
    ],
    "wof:name":"Donahue Paint & Paper",
    "wof:placetype":"venue"
},
  "geometry": {"coordinates":[-90.281888,38.580478],"type":"Point"}
}