{
  "type": "Feature",
  "properties": {
    "iso:country":"US",
    "sg:address":"406 E Missouri Ave",
    "sg:city":"Saint Joseph",
    "sg:classifiers":[
        {
            "category":"Building & Trades",
            "subcategory":"Construction",
            "type":"Services"
        }
    ],
    "sg:phone":"+1 816 238 4849",
    "sg:postcode":"64504",
    "sg:province":"MO",
    "sg:tags":[
        "contractor"
    ],
    "wof:name":"A1 Handyman Service",
    "wof:placetype":"venue"
},
  "geometry": {"coordinates":[-94.855971,39.722188],"type":"Point"}
}