{
  "type": "Feature",
  "properties": {
    "iso:country":"US",
    "sg:address":"1555 NE Douglas St",
    "sg:city":"Lees Summit",
    "sg:classifiers":[
        {
            "category":"Personal",
            "subcategory":"Beauty Salon",
            "type":"Services"
        }
    ],
    "sg:phone":"+1 816 347 1695",
    "sg:postcode":"64063",
    "sg:province":"MO",
    "sg:tags":[
        "manicuring"
    ],
    "wof:name":"For Nails",
    "wof:placetype":"venue"
},
  "geometry": {"coordinates":[-94.378286,38.941856],"type":"Point"}
}