{
  "type": "Feature",
  "properties": {
    "iso:country":"US",
    "sg:address":"812 E Main St",
    "sg:city":"California",
    "sg:classifiers":[
        {
            "category":"Shopping",
            "subcategory":"Gifts & Souvenirs",
            "type":"Retail Goods"
        }
    ],
    "sg:phone":"+1 573 796 3535",
    "sg:postcode":"65018",
    "sg:province":"MO",
    "wof:name":"Pekays Gift Shop",
    "wof:placetype":"venue"
},
  "geometry": {"coordinates":[-92.558071,38.636154],"type":"Point"}
}