{
  "type": "Feature",
  "properties": {
    "iso:country":"US",
    "sg:address":"811 N 3rd St",
    "sg:city":"Clinton",
    "sg:classifiers":[
        {
            "category":"Retail",
            "subcategory":"Repair Shop",
            "type":"Services"
        },
        {
            "category":"Shopping",
            "subcategory":"Bicycles & Sporting Goods",
            "type":"Retail Goods"
        }
    ],
    "sg:phone":"+1 660 885 5544",
    "sg:postcode":"64735",
    "sg:province":"MO",
    "sg:tags":[
        "equipment",
        "golf",
        "supply"
    ],
    "wof:name":"Custom Clubs & Repairs",
    "wof:placetype":"venue"
},
  "geometry": {"coordinates":[-93.772069,38.378855],"type":"Point"}
}