{
  "type": "Feature",
  "properties": {
    "iso:country":"US",
    "sg:address":"3550 W Clay St",
    "sg:city":"St Charles",
    "sg:classifiers":[
        {
            "category":"Autos & Motor Vehicles",
            "subcategory":"Boat Sales",
            "type":"Retail Goods"
        }
    ],
    "sg:phone":"+1 636 916 4411",
    "sg:postcode":"63301",
    "sg:province":"MO",
    "sg:tags":[
        "dealer",
        "sales"
    ],
    "sg:website":"www.budsplaceboats.com",
    "wof:name":"Bud's Place",
    "wof:placetype":"venue"
},
  "geometry": {"coordinates":[-90.554827,38.791329],"type":"Point"}
}