{
  "type": "Feature",
  "properties": {
    "iso:country":"US",
    "sg:address":"133 E 2nd St",
    "sg:city":"Hermann",
    "sg:classifiers":[
        {
            "category":"Professional",
            "subcategory":"Lawyer & Legal Services",
            "type":"Services"
        }
    ],
    "sg:phone":"+1 573 486 5039",
    "sg:postcode":"65041",
    "sg:province":"MO",
    "sg:tags":[
        "attorney"
    ],
    "wof:name":"Ferti-Sorb Co",
    "wof:placetype":"venue"
},
  "geometry": {"coordinates":[-91.436992,38.706122],"type":"Point"}
}