{
  "type": "Feature",
  "properties": {
    "iso:country":"US",
    "sg:address":"203 S Main St",
    "sg:city":"Hartville",
    "sg:classifiers":[
        {
            "category":"Autos & Motor Vehicles",
            "subcategory":"Fuel & Gas Station",
            "type":"Retail Goods"
        },
        {
            "category":"Food & Beverages",
            "subcategory":"Groceries & Convenience Stores",
            "type":"Retail Goods"
        }
    ],
    "sg:phone":"+1 417 741 7675",
    "sg:postcode":"65667",
    "sg:province":"MO",
    "wof:name":"Lazy Lee's One-Stop 4",
    "wof:placetype":"venue"
},
  "geometry": {"coordinates":[-92.510272,37.249335],"type":"Point"}
}