{
  "type": "Feature",
  "properties": {
    "iso:country":"US",
    "sg:address":"14001 Audrain Road 741",
    "sg:city":"Martinsburg",
    "sg:classifiers":[
        {
            "category":"Animal Shelter",
            "type":"Public Place"
        },
        {
            "category":"Retail",
            "subcategory":"Pet Boarding",
            "type":"Services"
        }
    ],
    "sg:phone":"+1 573 492 6299",
    "sg:postcode":"65264",
    "sg:province":"MO",
    "sg:tags":[
        "kennel"
    ],
    "wof:name":"Deimeke Kevin",
    "wof:placetype":"venue"
},
  "geometry": {"coordinates":[-91.668749,39.133771],"type":"Point"}
}