{
  "type": "Feature",
  "properties": {
    "iso:country":"US",
    "sg:address":"332 W 3rd St",
    "sg:city":"Mountain Grove",
    "sg:classifiers":[
        {
            "category":"Retail",
            "subcategory":"Auto Repair",
            "type":"Services"
        }
    ],
    "sg:phone":"+1 417 926 5278",
    "sg:postcode":"65711",
    "sg:province":"MO",
    "sg:tags":[
        "general"
    ],
    "wof:name":"Gould Garage",
    "wof:placetype":"venue"
},
  "geometry": {"coordinates":[-92.267032,37.130896],"type":"Point"}
}