{
  "type": "Feature",
  "properties": {
    "iso:country":"US",
    "sg:address":"4848 Orchard Dr",
    "sg:city":"Barnhart",
    "sg:phone":"+1 636 942 4219",
    "sg:postcode":"63012",
    "sg:province":"MO",
    "sg:tags":[
        "equipment",
        "commercial"
    ],
    "wof:name":"Slane International Inc",
    "wof:placetype":"venue"
},
  "geometry": {"coordinates":[-90.50303,38.357838],"type":"Point"}
}