{
  "type": "Feature",
  "properties": {
    "iso:country":"US",
    "sg:address":"1000 N Truman Blvd",
    "sg:city":"Crystal City",
    "sg:classifiers":[
        {
            "category":"Retail",
            "subcategory":"Veterinary Services",
            "type":"Services"
        }
    ],
    "sg:phone":"+1 636 937 9502",
    "sg:postcode":"63019",
    "sg:province":"MO",
    "sg:tags":[
        "veterinarian"
    ],
    "wof:name":"Dacus Veterinary Hospital",
    "wof:placetype":"venue"
},
  "geometry": {"coordinates":[-90.38682,38.22952],"type":"Point"}
}