{
  "type": "Feature",
  "properties": {
    "iso:country":"US",
    "sg:address":"1506 Westwinds Dr",
    "sg:city":"St Louis",
    "sg:classifiers":[
        {
            "category":"Real Estate",
            "subcategory":"Real Estate Agent",
            "type":"Services"
        }
    ],
    "sg:phone":"+1 314 966 6666",
    "sg:postcode":"63131",
    "sg:province":"MO",
    "wof:name":"ROPA Corp",
    "wof:placetype":"venue"
},
  "geometry": {"coordinates":[-90.438694,38.607926],"type":"Point"}
}