{
  "type": "Feature",
  "properties": {
    "iso:country":"US",
    "sg:address":"307 Christopher Pl",
    "sg:city":"Union",
    "sg:classifiers":[
        {
            "category":"Organizations",
            "subcategory":"Religious Organization",
            "type":"Services"
        }
    ],
    "sg:phone":"+1 636 583 9320",
    "sg:postcode":"63084",
    "sg:province":"MO",
    "wof:name":"McRae Murdoch Rev",
    "wof:placetype":"venue"
},
  "geometry": {"coordinates":[-91.018789,38.465112],"type":"Point"}
}