{
  "type": "Feature",
  "properties": {
    "iso:country":"US",
    "sg:address":"1491 Saint Louis Galleria",
    "sg:city":"St Louis",
    "sg:classifiers":[
        {
            "category":"Shopping",
            "subcategory":"Clothing, Apparel, & Fashions",
            "type":"Retail Goods"
        }
    ],
    "sg:phone":"+1 314 727 6262",
    "sg:postcode":"63117",
    "sg:province":"MO",
    "wof:name":"Urban Outfitters",
    "wof:placetype":"venue"
},
  "geometry": {"coordinates":[-90.34598099999999,38.637056],"type":"Point"}
}