{
  "type": "Feature",
  "properties": {
    "iso:country":"US",
    "sg:address":"505 Meadowmere Vw",
    "sg:city":"Ashland",
    "sg:classifiers":[
        {
            "category":"Organizations",
            "subcategory":"Community Association",
            "type":"Services"
        }
    ],
    "sg:phone":"+1 573 657 2869",
    "sg:postcode":"65010",
    "sg:province":"MO",
    "wof:name":"Veterans of Foreign Wars Inc",
    "wof:placetype":"venue"
},
  "geometry": {"coordinates":[-92.25563099999999,38.777684],"type":"Point"}
}