{
  "type": "Feature",
  "properties": {
    "iso:country":"US",
    "sg:address":"518 W Pearce Blvd",
    "sg:city":"Wentzville",
    "sg:classifiers":[
        {
            "category":"Shopping",
            "subcategory":"Gifts & Souvenirs",
            "type":"Retail Goods"
        }
    ],
    "sg:phone":"+1 636 327 5656",
    "sg:postcode":"63385",
    "sg:province":"MO",
    "sg:tags":[
        "novelty"
    ],
    "wof:name":"Vans Hallmark Shoppe",
    "wof:placetype":"venue"
},
  "geometry": {"coordinates":[-90.858362,38.810343],"type":"Point"}
}