{
  "type": "Feature",
  "properties": {
    "iso:country":"US",
    "sg:address":"1408 Pickford Pl",
    "sg:city":"Columbia",
    "sg:classifiers":[
        {
            "category":"Building & Trades",
            "subcategory":"Electrical",
            "type":"Services"
        }
    ],
    "sg:phone":"+1 573 446 6321",
    "sg:postcode":"65203",
    "sg:province":"MO",
    "sg:tags":[
        "electrical",
        "contractor"
    ],
    "wof:name":"Tcb Electric",
    "wof:placetype":"venue"
},
  "geometry": {"coordinates":[-92.40481200000001,38.938147],"type":"Point"}
}