{
  "type": "Feature",
  "properties": {
    "iso:country":"US",
    "sg:address":"6527 N Oak Fwy",
    "sg:city":"Gladstone",
    "sg:classifiers":[
        {
            "category":"Autos & Motor Vehicles",
            "subcategory":"Auto Supplies",
            "type":"Retail Goods"
        }
    ],
    "sg:phone":"+1 816 420 8137",
    "sg:postcode":"64118",
    "sg:province":"MO",
    "sg:tags":[
        "automobile",
        "parts"
    ],
    "wof:name":"Advance Auto Parts Inc",
    "wof:placetype":"venue"
},
  "geometry": {"coordinates":[-94.576095,39.212709],"type":"Point"}
}