{
  "type": "Feature",
  "properties": {
    "iso:country":"US",
    "sg:address":"1685 State Hwy 13",
    "sg:city":"Reeds Spring",
    "sg:classifiers":[
        {
            "category":"Home & Garden",
            "subcategory":"Home Furnishings",
            "type":"Retail Goods"
        }
    ],
    "sg:phone":"+1 417 272 8800",
    "sg:postcode":"65737",
    "sg:province":"MO",
    "sg:tags":[
        "lighting",
        "fixture"
    ],
    "wof:name":"Desi's Lighting Showroom",
    "wof:placetype":"venue"
},
  "geometry": {"coordinates":[-93.35118900000001,36.792222],"type":"Point"}
}