{
  "type": "Feature",
  "properties": {
    "iso:country":"US",
    "sg:address":"5025 Hwy P",
    "sg:city":"Flinthill",
    "sg:classifiers":[
        {
            "category":"Government",
            "subcategory":"Post Office",
            "type":"Public Place"
        }
    ],
    "sg:phone":"+1 636 327 3070",
    "sg:postcode":"63385",
    "sg:province":"MO",
    "wof:name":"US Post Office",
    "wof:placetype":"venue"
},
  "geometry": {"coordinates":[-90.86121,38.85532],"type":"Point"}
}