{
  "type": "Feature",
  "properties": {
    "iso:country":"US",
    "sg:address":"6802 Cherryvale Dr",
    "sg:city":"Hazelwood",
    "sg:classifiers":[
        {
            "category":"Building & Trades",
            "subcategory":"Construction",
            "type":"Services"
        }
    ],
    "sg:phone":"+1 314 895 4235",
    "sg:postcode":"63042",
    "sg:province":"MO",
    "sg:tags":[
        "house"
    ],
    "wof:name":"Scandinavian Renovations",
    "wof:placetype":"venue"
},
  "geometry": {"coordinates":[-90.37015700000001,38.782474],"type":"Point"}
}