{
  "type": "Feature",
  "properties": {
    "iso:country":"US",
    "sg:address":"310 Watson Pl",
    "sg:city":"Columbia",
    "sg:classifiers":[
        {
            "category":"Government",
            "subcategory":"Office",
            "type":"Public Place"
        }
    ],
    "sg:phone":"+1 573 875 5349",
    "sg:postcode":"65201",
    "sg:province":"MO",
    "sg:tags":[
        "federal",
        "program"
    ],
    "wof:name":"US Agricultural Dept",
    "wof:placetype":"venue"
},
  "geometry": {"coordinates":[-92.326595,38.947537],"type":"Point"}
}