{
  "type": "Feature",
  "properties": {
    "iso:country":"US",
    "sg:address":"208 Green Trail Dr",
    "sg:city":"Farmington",
    "sg:classifiers":[
        {
            "category":"Professional",
            "subcategory":"Business Services",
            "type":"Services"
        }
    ],
    "sg:phone":"+1 573 756 8198",
    "sg:postcode":"63640",
    "sg:province":"MO",
    "wof:name":"Skaggs Development Co",
    "wof:placetype":"venue"
},
  "geometry": {"coordinates":[-90.43082200000001,37.820836],"type":"Point"}
}