{
  "type": "Feature",
  "properties": {
    "iso:country":"US",
    "sg:address":"11370 Manchester Rd",
    "sg:city":"Kirkwood",
    "sg:classifiers":[
        {
            "category":"Professional",
            "subcategory":"Advertising",
            "type":"Services"
        }
    ],
    "sg:phone":"+1 314 821 1994",
    "sg:postcode":"63122",
    "sg:province":"MO",
    "sg:tags":[
        "mailing",
        "list"
    ],
    "sg:website":"www.crosslists.com",
    "wof:name":"Cross Co",
    "wof:placetype":"venue"
},
  "geometry": {"coordinates":[-90.421031,38.599087],"type":"Point"}
}