{
  "type": "Feature",
  "properties": {
    "iso:country":"US",
    "sg:address":"835 Hyde Park Dr",
    "sg:city":"Arnold",
    "sg:classifiers":[
        {
            "category":"Freight",
            "type":"Transportation"
        }
    ],
    "sg:phone":"+1 314 308 8276",
    "sg:postcode":"63010",
    "sg:province":"MO",
    "sg:tags":[
        "distance",
        "without",
        "storage",
        "long",
        "trucking"
    ],
    "wof:name":"Dark Horse Inc",
    "wof:placetype":"venue"
},
  "geometry": {"coordinates":[-90.367744,38.442453],"type":"Point"}
}