{
  "type": "Feature",
  "properties": {
    "iso:country":"US",
    "sg:address":"1104 Washington Square Shopping Ctr",
    "sg:city":"Washington",
    "sg:classifiers":[
        {
            "category":"Restaurant",
            "type":"Food & Drink"
        }
    ],
    "sg:menulink":"http://www.allmenus.com/mo/washington/86584-imos-pizza/menu/",
    "sg:phone":"+1 636 390 4667",
    "sg:postcode":"63090",
    "sg:province":"MO",
    "sg:tags":[
        "american",
        "pizza"
    ],
    "wof:name":"Imo's Pizza",
    "wof:placetype":"venue"
},
  "geometry": {"coordinates":[-91.00344200000001,38.536225],"type":"Point"}
}