{
  "type": "Feature",
  "properties": {
    "iso:country":"US",
    "sg:address":"7001 N Locust St",
    "sg:city":"Kansas City",
    "sg:classifiers":[
        {
            "category":"Real Estate",
            "subcategory":"Real Estate Services",
            "type":"Services"
        }
    ],
    "sg:phone":"+1 816 468 8268",
    "sg:postcode":"64118",
    "sg:province":"MO",
    "sg:tags":[
        "company",
        "title"
    ],
    "wof:name":"Community Land Title",
    "wof:placetype":"venue"
},
  "geometry": {"coordinates":[-94.574963,39.222242],"type":"Point"}
}