{
  "type": "Feature",
  "properties": {
    "addr:full":"7711 Carondelet Ave Saint Louis MO 63105",
    "addr:housenumber":"7711",
    "addr:postcode":"63105",
    "addr:street":"Carondelet Ave",
    "iso:country":"US",
    "sg:address":"7711 Carondelet Ave",
    "sg:city":"Saint Louis",
    "sg:classifiers":[
        {
            "category":"Insurance",
            "subcategory":"Life Insurance",
            "type":"Services"
        }
    ],
    "sg:phone":"+1 800 238 6225",
    "sg:postcode":"63105",
    "sg:province":"MO",
    "sg:tags":[
        "surety",
        "accident",
        "health",
        "casualty"
    ],
    "wof:name":"Travelers Insurance",
    "wof:placetype":"venue"
},
  "geometry": {"coordinates":[-90.33683000000001,38.648858],"type":"Point"}
}