{
  "type": "Feature",
  "properties": {
    "iso:country":"US",
    "sg:address":"2114 E Fairview Ave",
    "sg:city":"Carthage",
    "sg:classifiers":[
        {
            "category":"Building & Trades",
            "subcategory":"Construction",
            "type":"Services"
        }
    ],
    "sg:phone":"+1 417 358 7105",
    "sg:postcode":"64836",
    "sg:province":"MO",
    "sg:tags":[
        "contractor"
    ],
    "wof:name":"Master Blaster",
    "wof:placetype":"venue"
},
  "geometry": {"coordinates":[-94.275947,37.154592],"type":"Point"}
}