{
  "type": "Feature",
  "properties": {
    "iso:country":"US",
    "sg:address":"447 S New Ballas Rd",
    "sg:city":"Saint Louis",
    "sg:classifiers":[
        {
            "category":"Restaurant",
            "type":"Food & Drink"
        }
    ],
    "sg:menulink":"http://www.allmenus.com/mo/missouri-river/55105-st-louis-bread-co/menu/",
    "sg:phone":"+1 314 569 3031",
    "sg:postcode":"63141",
    "sg:province":"MO",
    "sg:tags":[
        "wrap",
        "american",
        "sandwich"
    ],
    "wof:name":"St. Louis Bread Co.",
    "wof:placetype":"venue"
},
  "geometry": {"coordinates":[-90.44341900000001,38.649235],"type":"Point"}
}