{
  "type": "Feature",
  "properties": {
    "iso:country":"US",
    "sg:address":"1818 Redbud Dr",
    "sg:city":"Joplin",
    "sg:classifiers":[
        {
            "category":"Building & Trades",
            "subcategory":"Construction",
            "type":"Services"
        }
    ],
    "sg:phone":"+1 417 206 6988",
    "sg:postcode":"64801",
    "sg:province":"MO",
    "sg:tags":[
        "house"
    ],
    "wof:name":"Royster Homes Inc",
    "wof:placetype":"venue"
},
  "geometry": {"coordinates":[-94.53815299999999,37.121165],"type":"Point"}
}