{
  "type": "Feature",
  "properties": {
    "iso:country":"US",
    "sg:address":"4097 State Hwy Aa",
    "sg:city":"Broseley",
    "sg:phone":"+1 573 785 9860",
    "sg:postcode":"63932",
    "sg:province":"MO",
    "sg:tags":[
        "farm",
        "corn"
    ],
    "wof:name":"Jim Ellsworth",
    "wof:placetype":"venue"
},
  "geometry": {"coordinates":[-90.334551,36.73227],"type":"Point"}
}