{
  "type": "Feature",
  "properties": {
    "iso:country":"US",
    "sg:address":"113 E Washington St",
    "sg:city":"Kearney",
    "sg:classifiers":[
        {
            "category":"Retail",
            "subcategory":"Photofinishing",
            "type":"Services"
        }
    ],
    "sg:phone":"+1 816 903 2000",
    "sg:postcode":"64060",
    "sg:province":"MO",
    "sg:tags":[
        "photo",
        "finishing"
    ],
    "wof:name":"Awesome Possum One Hour Photo",
    "wof:placetype":"venue"
},
  "geometry": {"coordinates":[-94.362196,39.372886],"type":"Point"}
}