{
  "type": "Feature",
  "properties": {
    "iso:country":"US",
    "sg:address":"1009 Vogel Estates Dr",
    "sg:city":"Arnold",
    "sg:classifiers":[
        {
            "category":"Building & Trades",
            "subcategory":"Construction",
            "type":"Services"
        }
    ],
    "sg:phone":"+1 636 461 2272",
    "sg:postcode":"63010",
    "sg:province":"MO",
    "sg:tags":[
        "contractor"
    ],
    "wof:name":"Sage Construction",
    "wof:placetype":"venue"
},
  "geometry": {"coordinates":[-90.402294,38.415664],"type":"Point"}
}