{
  "type": "Feature",
  "properties": {
    "iso:country":"US",
    "sg:address":"604 S Springfield Ave",
    "sg:city":"Bolivar",
    "sg:classifiers":[
        {
            "category":"Restaurant",
            "type":"Food & Drink"
        }
    ],
    "sg:menulink":"http://www.allmenus.com/mo/southeast-marion/83990-dominos-pizza/menu/",
    "sg:phone":"+1 417 777 7070",
    "sg:postcode":"65613",
    "sg:province":"MO",
    "sg:tags":[
        "american",
        "wing",
        "pizza"
    ],
    "wof:name":"Domino's Pizza",
    "wof:placetype":"venue"
},
  "geometry": {"coordinates":[-93.408506,37.60943],"type":"Point"}
}