{
  "type": "Feature",
  "properties": {
    "iso:country":"US",
    "sg:address":"4271 Delor St",
    "sg:city":"St Louis",
    "sg:classifiers":[
        {
            "category":"Organizations",
            "subcategory":"Community Association",
            "type":"Services"
        }
    ],
    "sg:phone":"+1 314 351 6137",
    "sg:postcode":"63116",
    "sg:province":"MO",
    "sg:tags":[
        "military"
    ],
    "wof:name":"Newport Heights Memorial Post",
    "wof:placetype":"venue"
},
  "geometry": {"coordinates":[-90.266406,38.581324],"type":"Point"}
}