{
  "type": "Feature",
  "properties": {
    "iso:country":"US",
    "sg:address":"7519 NW Prairie View Rd",
    "sg:city":"Kansas City",
    "sg:classifiers":[
        {
            "category":"Autos & Motor Vehicles",
            "subcategory":"Fuel & Gas Station",
            "type":"Retail Goods"
        }
    ],
    "sg:phone":"+1 816 741 0677",
    "sg:postcode":"64151",
    "sg:province":"MO",
    "sg:tags":[
        "oil"
    ],
    "wof:name":"Ray's Conoco & Auto Repair",
    "wof:placetype":"venue"
},
  "geometry": {"coordinates":[-94.65822199999999,39.23263],"type":"Point"}
}