{
  "type": "Feature",
  "properties": {
    "iso:country":"US",
    "sg:address":"14 Ladue Meadows",
    "sg:city":"St Louis",
    "sg:classifiers":[
        {
            "category":"Professional",
            "subcategory":"Management & Consulting",
            "type":"Services"
        }
    ],
    "sg:phone":"+1 314 993 4743",
    "sg:postcode":"63141",
    "sg:province":"MO",
    "sg:tags":[
        "consultant"
    ],
    "wof:name":"Lexco Group Inc",
    "wof:placetype":"venue"
},
  "geometry": {"coordinates":[-90.43294899999999,38.658258],"type":"Point"}
}