{
  "type": "Feature",
  "properties": {
    "iso:country":"US",
    "sg:address":"304 E Jackson St",
    "sg:city":"Willard",
    "sg:classifiers":[
        {
            "category":"Insurance",
            "subcategory":"Hazard Insurance",
            "type":"Services"
        }
    ],
    "sg:phone":"+1 417 742 3562",
    "sg:postcode":"65781",
    "sg:province":"MO",
    "sg:website":"http://statefarm.mqgroup.com/url.asp?usr=253375",
    "wof:name":"State Farm Insurance Agent-Jim Anderson",
    "wof:placetype":"venue"
},
  "geometry": {"coordinates":[-93.425804,37.303655],"type":"Point"}
}