{
  "type": "Feature",
  "properties": {
    "iso:country":"US",
    "sg:address":"137 Brown Rd",
    "sg:city":"St Peters",
    "sg:classifiers":[
        {
            "category":"Manufacturing",
            "subcategory":"Metals",
            "type":"Manufacturing & Wholesale Goods"
        }
    ],
    "sg:phone":"+1 636 397 3000",
    "sg:postcode":"63376",
    "sg:province":"MO",
    "wof:name":"West Co Glass Inc",
    "wof:placetype":"venue"
},
  "geometry": {"coordinates":[-90.634809,38.804427],"type":"Point"}
}