{
  "type": "Feature",
  "properties": {
    "iso:country":"US",
    "sg:address":"1012 Gutenberg St",
    "sg:city":"Hermann",
    "sg:classifiers":[
        {
            "category":"Manufacturing",
            "subcategory":"Rubber & Plastics",
            "type":"Manufacturing & Wholesale Goods"
        }
    ],
    "sg:phone":"+1 573 486 8025",
    "sg:postcode":"65041",
    "sg:province":"MO",
    "sg:tags":[
        "toy",
        "mfg"
    ],
    "wof:name":"Mac Molto USA Inc",
    "wof:placetype":"venue"
},
  "geometry": {"coordinates":[-91.433742,38.69874],"type":"Point"}
}