{
  "type": "Feature",
  "properties": {
    "iso:country":"US",
    "sg:address":"214 US Hwy 54",
    "sg:city":"Farber",
    "sg:classifiers":[
        {
            "category":"Government",
            "subcategory":"Office",
            "type":"Public Place"
        }
    ],
    "sg:phone":"+1 573 249 3652",
    "sg:postcode":"63345",
    "sg:province":"MO",
    "sg:tags":[
        "executive"
    ],
    "wof:name":"City Clerk",
    "wof:placetype":"venue"
},
  "geometry": {"coordinates":[-91.574269,39.279144],"type":"Point"}
}