{
  "type": "Feature",
  "properties": {
    "iso:country":"US",
    "sg:address":"335 Huron Ln",
    "sg:city":"Jackson",
    "sg:classifiers":[
        {
            "category":"Professional",
            "subcategory":"Accounting & Tax Preparation",
            "type":"Services"
        }
    ],
    "sg:phone":"+1 573 243 9810",
    "sg:postcode":"63755",
    "sg:province":"MO",
    "sg:tags":[
        "bookkeeping",
        "general"
    ],
    "wof:name":"Heartland Accounting Solutions",
    "wof:placetype":"venue"
},
  "geometry": {"coordinates":[-89.599704,37.43227],"type":"Point"}
}