{
  "type": "Feature",
  "properties": {
    "iso:country":"US",
    "sg:address":"753 Co Rd 212",
    "sg:city":"Portageville",
    "sg:classifiers":[
        {
            "category":"Farming",
            "subcategory":"Farm",
            "type":"Manufacturing & Wholesale Goods"
        }
    ],
    "sg:phone":"+1 573 628 3296",
    "sg:postcode":"63873",
    "sg:province":"MO",
    "sg:tags":[
        "crop",
        "general"
    ],
    "wof:name":"Blaine Martin Farms",
    "wof:placetype":"venue"
},
  "geometry": {"coordinates":[-89.728585,36.364171],"type":"Point"}
}