{
  "type": "Feature",
  "properties": {
    "iso:country":"US",
    "sg:address":"8990 Lawrence 2075",
    "sg:city":"Mount Vernon",
    "sg:classifiers":[
        {
            "category":"Professional",
            "type":"Services"
        }
    ],
    "sg:phone":"+1 417 452 3829",
    "sg:postcode":"65712",
    "sg:province":"MO",
    "wof:name":"Dorothy Frances Heisner",
    "wof:placetype":"venue"
},
  "geometry": {"coordinates":[-93.89466400000001,37.168312],"type":"Point"}
}