{
  "type": "Feature",
  "properties": {
    "iso:country":"US",
    "sg:address":"176 Clarkson Executive Park",
    "sg:city":"Ellisville",
    "sg:classifiers":[
        {
            "category":"Professional",
            "subcategory":"Accounting & Tax Preparation",
            "type":"Services"
        }
    ],
    "sg:phone":"+1 636 391 3080",
    "sg:postcode":"63011",
    "sg:province":"MO",
    "sg:tags":[
        "accountant"
    ],
    "wof:name":"West County Financial Svc",
    "wof:placetype":"venue"
},
  "geometry": {"coordinates":[-90.586737,38.600655],"type":"Point"}
}