{
  "type": "Feature",
  "properties": {
    "iso:country":"US",
    "sg:address":"730 State Hwy 7",
    "sg:city":"Blue Springs",
    "sg:classifiers":[
        {
            "category":"Shopping",
            "subcategory":"Tobacco",
            "type":"Retail Goods"
        }
    ],
    "sg:phone":"+1 816 224 9499",
    "sg:postcode":"64014",
    "sg:province":"MO",
    "sg:tags":[
        "cigarette",
        "cigar",
        "dealer"
    ],
    "wof:name":"Smokes 4 Less",
    "wof:placetype":"venue"
},
  "geometry": {"coordinates":[-94.27244899999999,39.012803],"type":"Point"}
}