{
  "type": "Feature",
  "properties": {
    "addr:full":"18775 Lober Rd Weston MO 64098",
    "addr:housenumber":"18775",
    "addr:postcode":"64098",
    "addr:street":"Lober Rd",
    "iso:country":"US",
    "sg:address":"18775 Lober Rd",
    "sg:city":"Weston",
    "sg:classifiers":[
        {
            "category":"Utilities",
            "subcategory":"Telephone",
            "type":"Services"
        }
    ],
    "sg:phone":"+1 816 640 5704",
    "sg:postcode":"64098",
    "sg:province":"MO",
    "sg:tags":[
        "communications"
    ],
    "wof:name":"Sprint",
    "wof:placetype":"venue"
},
  "geometry": {"coordinates":[-94.844767,39.429885],"type":"Point"}
}