{
  "type": "Feature",
  "properties": {
    "iso:country":"US",
    "sg:address":"515 E Cleveland Ave",
    "sg:city":"Monett",
    "sg:classifiers":[
        {
            "category":"Professional",
            "subcategory":"Business Services",
            "type":"Services"
        }
    ],
    "sg:phone":"+1 417 235 0111",
    "sg:postcode":"65708",
    "sg:province":"MO",
    "wof:name":"Missouri Telecom Inc",
    "wof:placetype":"venue"
},
  "geometry": {"coordinates":[-93.92340299999999,36.928667],"type":"Point"}
}