{
  "type": "Feature",
  "properties": {
    "addr:full":"1317 Frederick Ave Saint Joseph MO 64501",
    "addr:housenumber":"1317",
    "addr:postcode":"64501",
    "addr:street":"Frederick Ave",
    "iso:country":"US",
    "sg:address":"1317 Frederick Ave",
    "sg:city":"Saint Joseph",
    "sg:classifiers":[
        {
            "category":"Restaurant",
            "type":"Food & Drink"
        }
    ],
    "sg:menulink":"http://www.allmenus.com/mo/st-joseph/201669-sonic/menu/",
    "sg:phone":"+1 816 233 1211",
    "sg:postcode":"64501",
    "sg:province":"MO",
    "sg:tags":[
        "burger",
        "american"
    ],
    "wof:name":"Sonic",
    "wof:placetype":"venue"
},
  "geometry": {"coordinates":[-94.844055,39.770615],"type":"Point"}
}