{
  "type": "Feature",
  "properties": {
    "iso:country":"US",
    "sg:address":"12222 Blue Ridge Ext",
    "sg:city":"Grandview",
    "sg:classifiers":[
        {
            "category":"Social Services",
            "type":"Services"
        },
        {
            "category":"Place Of Worship",
            "subcategory":"Church",
            "type":"Public Place"
        },
        {
            "category":"Place Of Worship",
            "type":"Public Place"
        }
    ],
    "sg:phone":"+1 816 965 7141",
    "sg:postcode":"64030",
    "sg:province":"MO",
    "sg:tags":[
        "churches-non-denominational"
    ],
    "sg:website":"http://www.faithministrieskc.com",
    "wof:name":"Faith Ministries World Outreach Center",
    "wof:placetype":"venue"
},
  "geometry": {"coordinates":[-94.532431,38.902082],"type":"Point"}
}