{
  "type": "Feature",
  "properties": {
    "iso:country":"US",
    "sg:address":"2444 Pendleton Rd",
    "sg:city":"Farmington",
    "sg:classifiers":[
        {
            "category":"Insurance",
            "subcategory":"Hazard Insurance",
            "type":"Services"
        }
    ],
    "sg:phone":"+1 573 756 9072",
    "sg:postcode":"63640",
    "sg:province":"MO",
    "wof:name":"Craig A Duncan",
    "wof:placetype":"venue"
},
  "geometry": {"coordinates":[-90.480141,37.73372],"type":"Point"}
}