{
  "type": "Feature",
  "properties": {
    "iso:country":"US",
    "sg:address":"1209 Lake Rd",
    "sg:city":"Liberty",
    "sg:classifiers":[
        {
            "category":"Insurance",
            "subcategory":"Insurance Agent",
            "type":"Services"
        }
    ],
    "sg:phone":"+1 816 792 0864",
    "sg:postcode":"64068",
    "sg:province":"MO",
    "wof:name":"Marchand J S & Assoc",
    "wof:placetype":"venue"
},
  "geometry": {"coordinates":[-94.440822,39.26117],"type":"Point"}
}