{
  "type": "Feature",
  "properties": {
    "iso:country":"US",
    "sg:address":"14407 Manchester Rd",
    "sg:city":"Ballwin",
    "sg:classifiers":[
        {
            "category":"Personal",
            "subcategory":"Beauty Salon",
            "type":"Services"
        }
    ],
    "sg:phone":"+1 636 227 3026",
    "sg:postcode":"63011",
    "sg:province":"MO",
    "sg:tags":[
        "manicuring"
    ],
    "sg:website":"http://www.madaboutyou.com",
    "wof:name":"Mad About You Hair Salon",
    "wof:placetype":"venue"
},
  "geometry": {"coordinates":[-90.516463,38.593101],"type":"Point"}
}