{
  "type": "Feature",
  "properties": {
    "iso:country":"US",
    "sg:address":"110 S Main St",
    "sg:city":"Charleston",
    "sg:classifiers":[
        {
            "category":"Shopping",
            "subcategory":"Department Store",
            "type":"Retail Goods"
        }
    ],
    "sg:phone":"+1 573 683 4650",
    "sg:postcode":"63834",
    "sg:province":"MO",
    "sg:tags":[
        "shop"
    ],
    "wof:name":"Just A Buck",
    "wof:placetype":"venue"
},
  "geometry": {"coordinates":[-89.349992,36.923314],"type":"Point"}
}