{
  "type": "Feature",
  "properties": {
    "iso:country":"US",
    "sg:address":"124 E 4th St",
    "sg:city":"Hermann",
    "sg:classifiers":[
        {
            "category":"Food & Beverages",
            "subcategory":"Specialty",
            "type":"Retail Goods"
        }
    ],
    "sg:phone":"+1 573 486 5300",
    "sg:postcode":"65041",
    "sg:province":"MO",
    "sg:tags":[
        "gourmet",
        "shop"
    ],
    "sg:website":"www.tyandmore.com",
    "wof:name":"Tastefully Yours & More",
    "wof:placetype":"venue"
},
  "geometry": {"coordinates":[-91.437427,38.704236],"type":"Point"}
}