{
  "type": "Feature",
  "properties": {
    "addr:full":"4100 Snow St Saint Louis MO 63120",
    "addr:housenumber":"4100",
    "addr:postcode":"63120",
    "addr:street":"Snow St",
    "iso:country":"US",
    "sg:address":"4100 Snow St",
    "sg:city":"Saint Louis",
    "sg:classifiers":[
        {
            "category":"Social Services",
            "subcategory":"Child Care",
            "type":"Services"
        }
    ],
    "sg:phone":"+1 314 389 9293",
    "sg:postcode":"63120",
    "sg:province":"MO",
    "sg:tags":[
        "state",
        "day",
        "licensed"
    ],
    "wof:name":"Bond Head Start Center",
    "wof:placetype":"venue"
},
  "geometry": {"coordinates":[-90.271457,38.694471],"type":"Point"}
}