{
  "type": "Feature",
  "properties": {
    "iso:country":"US",
    "sg:address":"974 E Highway 8",
    "sg:city":"Steelville",
    "sg:classifiers":[
        {
            "category":"Restaurant",
            "type":"Food & Drink"
        }
    ],
    "sg:phone":"+1 573 786 7848",
    "sg:postcode":"65565",
    "sg:province":"MO",
    "sg:website":"http://www.huzzahvalley.com",
    "wof:name":"Huzzah Valley Dining Lodge",
    "wof:placetype":"venue"
},
  "geometry": {"coordinates":[-91.345332,37.968896],"type":"Point"}
}