{
  "type": "Feature",
  "properties": {
    "iso:country":"US",
    "sg:address":"1835 E Main St",
    "sg:city":"Warsaw",
    "sg:classifiers":[
        {
            "category":"Manufacturing",
            "subcategory":"Rubber & Plastics",
            "type":"Manufacturing & Wholesale Goods"
        },
        {
            "category":"Manufacturing",
            "subcategory":"Chemicals & Compounds",
            "type":"Manufacturing & Wholesale Goods"
        }
    ],
    "sg:phone":"+1 660 428 2333",
    "sg:postcode":"65355",
    "sg:province":"MO",
    "sg:tags":[
        "product",
        "compounds",
        "materials-colorants",
        "powders",
        "plastics-raw",
        "resins",
        "liquids"
    ],
    "wof:name":"Gemsafe Plastics, Inc.",
    "wof:placetype":"venue"
},
  "geometry": {"coordinates":[-93.36629499999999,38.262992],"type":"Point"}
}