{
  "type": "Feature",
  "properties": {
    "iso:country":"US",
    "sg:address":"212 N Kingshighway Blvd",
    "sg:city":"Saint Louis",
    "sg:classifiers":[
        {
            "category":"Shopping",
            "subcategory":"Florist",
            "type":"Retail Goods"
        }
    ],
    "sg:phone":"+1 314 633 3030",
    "sg:postcode":"63108",
    "sg:province":"MO",
    "wof:name":"Fiori Flowers",
    "wof:placetype":"venue"
},
  "geometry": {"coordinates":[-90.264536,38.644111],"type":"Point"}
}