{
  "type": "Feature",
  "properties": {
    "iso:country":"US",
    "sg:address":"1101 E Svc Rd Highway 61 S",
    "sg:city":"Wentzville",
    "sg:classifiers":[
        {
            "category":"Health Services",
            "subcategory":"Clinic",
            "type":"Services"
        }
    ],
    "sg:phone":"+1 636 332 5100",
    "sg:postcode":"63385",
    "sg:province":"MO",
    "sg:tags":[
        "agency",
        "social"
    ],
    "wof:name":"Unity Home Services",
    "wof:placetype":"venue"
},
  "geometry": {"coordinates":[-90.830348,38.80254],"type":"Point"}
}