{
  "type": "Feature",
  "properties": {
    "iso:country":"US",
    "sg:address":"16436 Andraes Dr",
    "sg:city":"Chesterfield",
    "sg:classifiers":[
        {
            "category":"Professional",
            "type":"Services"
        }
    ],
    "sg:phone":"+1 636 530 6018",
    "sg:postcode":"63005",
    "sg:province":"MO",
    "wof:name":"Pt Specialists Inc",
    "wof:placetype":"venue"
},
  "geometry": {"coordinates":[-90.594497,38.640664],"type":"Point"}
}