{
  "type": "Feature",
  "properties": {
    "iso:country":"US",
    "sg:address":"907 Harbor Oaks Ct",
    "sg:city":"Florissant",
    "sg:classifiers":[
        {
            "category":"Building & Trades",
            "subcategory":"Construction",
            "type":"Services"
        }
    ],
    "sg:phone":"+1 314 707 9776",
    "sg:postcode":"63031",
    "sg:province":"MO",
    "sg:tags":[
        "system",
        "contractor",
        "air conditioning"
    ],
    "wof:name":"Ace Heating, Cooling And",
    "wof:placetype":"venue"
},
  "geometry": {"coordinates":[-90.359033,38.799857],"type":"Point"}
}