{
  "type": "Feature",
  "properties": {
    "iso:country":"US",
    "sg:address":"334 NW 1201st Rd",
    "sg:city":"Holden",
    "sg:classifiers":[
        {
            "category":"Manufacturing",
            "subcategory":"Food",
            "type":"Manufacturing & Wholesale Goods"
        }
    ],
    "sg:phone":"+1 816 732 5765",
    "sg:postcode":"64040",
    "sg:province":"MO",
    "sg:tags":[
        "product"
    ],
    "wof:name":"Stoney Bluff Farm",
    "wof:placetype":"venue"
},
  "geometry": {"coordinates":[-93.968818,38.827868],"type":"Point"}
}