{
  "type": "Feature",
  "properties": {
    "iso:country":"US",
    "sg:address":"201 Northpark Ln",
    "sg:city":"Joplin",
    "sg:classifiers":[
        {
            "category":"Health Services",
            "subcategory":"Clinic",
            "type":"Services"
        }
    ],
    "sg:phone":"+1 417 206 0541",
    "sg:postcode":"64801",
    "sg:province":"MO",
    "sg:tags":[
        "specialty",
        "outpatient"
    ],
    "wof:name":"Rehab Care Group",
    "wof:placetype":"venue"
},
  "geometry": {"coordinates":[-94.470252,37.089402],"type":"Point"}
}