{
  "type": "Feature",
  "properties": {
    "iso:country":"US",
    "sg:address":"9538 Anchorage Ln",
    "sg:city":"Saint Louis",
    "sg:classifiers":[
        {
            "category":"Professional",
            "subcategory":"Business Services",
            "type":"Services"
        }
    ],
    "sg:phone":"+1 314 843 1802",
    "sg:postcode":"63126",
    "sg:province":"MO",
    "wof:name":"L E Olliges",
    "wof:placetype":"venue"
},
  "geometry": {"coordinates":[-90.377656,38.553763],"type":"Point"}
}