{
  "type": "Feature",
  "properties": {
    "iso:country":"US",
    "sg:address":"2812 W Maplewood St",
    "sg:city":"Springfield",
    "sg:classifiers":[
        {
            "category":"Social Services",
            "subcategory":"Child Care",
            "type":"Services"
        }
    ],
    "sg:phone":"+1 417 883 4294",
    "sg:postcode":"65807",
    "sg:province":"MO",
    "sg:tags":[
        "daycare"
    ],
    "wof:name":"Bean Michael Ray & Lyn",
    "wof:placetype":"venue"
},
  "geometry": {"coordinates":[-93.33448300000001,37.141531],"type":"Point"}
}