{
  "type": "Feature",
  "properties": {
    "iso:country":"US",
    "sg:address":"15487 Ashwood Ave",
    "sg:city":"Pattonsburg",
    "sg:phone":"+1 660 367 4644",
    "sg:postcode":"64670",
    "sg:province":"MO",
    "sg:tags":[
        "farm",
        "soybean"
    ],
    "wof:name":"Kris Lowery",
    "wof:placetype":"venue"
},
  "geometry": {"coordinates":[-94.122722,40.134817],"type":"Point"}
}