{
  "type": "Feature",
  "properties": {
    "iso:country":"US",
    "sg:address":"4555 Virginia Ave",
    "sg:city":"St Louis",
    "sg:classifiers":[
        {
            "category":"Organizations",
            "subcategory":"Religious Organization",
            "type":"Services"
        }
    ],
    "sg:phone":"+1 314 832 2142",
    "sg:postcode":"63111",
    "sg:province":"MO",
    "sg:tags":[
        "church"
    ],
    "wof:name":"New Journey Baptist Church",
    "wof:placetype":"venue"
},
  "geometry": {"coordinates":[-90.243139,38.574042],"type":"Point"}
}