{
  "type": "Feature",
  "properties": {
    "iso:country":"US",
    "sg:address":"1601 N Bishop Ave",
    "sg:city":"Rolla",
    "sg:classifiers":[
        {
            "category":"Health Services",
            "subcategory":"Doctor",
            "type":"Services"
        },
        {
            "category":"Health Services",
            "subcategory":"Clinic",
            "type":"Services"
        }
    ],
    "sg:phone":"+1 573 364 4226",
    "sg:postcode":"65401",
    "sg:province":"MO",
    "sg:tags":[
        "physician",
        "family",
        "practice",
        "surgeons",
        "osteopathic",
        "medicine"
    ],
    "wof:name":"Felts James Md",
    "wof:placetype":"venue"
},
  "geometry": {"coordinates":[-91.775543,37.957191],"type":"Point"}
}