{
  "type": "Feature",
  "properties": {
    "iso:country":"US",
    "sg:address":"2501 Guinotte Ave",
    "sg:city":"Kansas City",
    "sg:classifiers":[
        {
            "category":"Food & Beverages",
            "subcategory":"Meat & Fish",
            "type":"Retail Goods"
        }
    ],
    "sg:phone":"+1 816 472 8325",
    "sg:postcode":"64120",
    "sg:province":"MO",
    "sg:website":"www.hpsteaks.com",
    "wof:name":"Hitchin' Post Steak Co-Kansas",
    "wof:placetype":"venue"
},
  "geometry": {"coordinates":[-94.55138700000001,39.11876],"type":"Point"}
}