{
  "type": "Feature",
  "properties": {
    "iso:country":"US",
    "sg:address":"5285 US Hwy 54",
    "sg:city":"Osage Beach",
    "sg:classifiers":[
        {
            "category":"Building & Trades",
            "subcategory":"Construction",
            "type":"Services"
        }
    ],
    "sg:phone":"+1 573 348 3553",
    "sg:postcode":"65065",
    "sg:province":"MO",
    "sg:tags":[
        "residential",
        "commercial"
    ],
    "wof:name":"Ellerman Concrete Systems",
    "wof:placetype":"venue"
},
  "geometry": {"coordinates":[-92.655219,38.129491],"type":"Point"}
}