{
  "type": "Feature",
  "properties": {
    "iso:country":"US",
    "sg:address":"32 Portwest Ct",
    "sg:city":"St Charles",
    "sg:classifiers":[
        {
            "category":"Professional",
            "subcategory":"Engineering",
            "type":"Services"
        }
    ],
    "sg:phone":"+1 636 916 0444",
    "sg:postcode":"63303",
    "sg:province":"MO",
    "sg:tags":[
        "engineer"
    ],
    "wof:name":"Musler Engineering Co",
    "wof:placetype":"venue"
},
  "geometry": {"coordinates":[-90.534701,38.757594],"type":"Point"}
}