{
  "type": "Feature",
  "properties": {
    "iso:country":"US",
    "sg:address":"25701 E Blue Mills Rd",
    "sg:city":"Independence",
    "sg:classifiers":[
        {
            "category":"Professional",
            "subcategory":"Business Services",
            "type":"Services"
        }
    ],
    "sg:phone":"+1 816 726 1683",
    "sg:postcode":"64058",
    "sg:province":"MO",
    "wof:name":"Caruthers Interior",
    "wof:placetype":"venue"
},
  "geometry": {"coordinates":[-94.273788,39.159848],"type":"Point"}
}