{
  "type": "Feature",
  "properties": {
    "addr:full":"402 W Main St Jackson MO 63755",
    "addr:housenumber":"402",
    "addr:postcode":"63755",
    "addr:street":"W Main St",
    "iso:country":"US",
    "sg:address":"402 W Main St",
    "sg:city":"Jackson",
    "sg:classifiers":[
        {
            "category":"Restaurant",
            "type":"Food & Drink"
        }
    ],
    "sg:menulink":"http://www.allmenus.com/mo/byrd/148892-subway/menu/",
    "sg:phone":"+1 573 243 0055",
    "sg:postcode":"63755",
    "sg:province":"MO",
    "sg:tags":[
        "american",
        "sandwich"
    ],
    "wof:name":"Subway",
    "wof:placetype":"venue"
},
  "geometry": {"coordinates":[-89.671364,37.382893],"type":"Point"}
}