{
  "type": "Feature",
  "properties": {
    "iso:country":"US",
    "sg:address":"9345 Clayton Rd",
    "sg:city":"St Louis",
    "sg:classifiers":[
        {
            "category":"Government",
            "subcategory":"Office",
            "type":"Public Place"
        }
    ],
    "sg:phone":"+1 314 997 6308",
    "sg:postcode":"63124",
    "sg:province":"MO",
    "sg:tags":[
        "village"
    ],
    "wof:name":"Ladue City Building Dept",
    "wof:placetype":"venue"
},
  "geometry": {"coordinates":[-90.379099,38.640878],"type":"Point"}
}