{
  "type": "Feature",
  "properties": {
    "addr:full":"711 Pointe Basse Dr Sainte Genevieve MO 63670",
    "addr:housenumber":"711",
    "addr:postcode":"63670",
    "addr:street":"Pointe Basse Dr",
    "iso:country":"US",
    "sg:address":"711 Pointe Basse Dr",
    "sg:city":"Sainte Genevieve",
    "sg:classifiers":[
        {
            "category":"Government",
            "subcategory":"Office",
            "type":"Public Place"
        }
    ],
    "sg:phone":"+1 573 883 2703",
    "sg:postcode":"63670",
    "sg:province":"MO",
    "sg:tags":[
        "use",
        "land",
        "commodity",
        "related",
        "program",
        "administers"
    ],
    "wof:name":"Farm Service Agency",
    "wof:placetype":"venue"
},
  "geometry": {"coordinates":[-90.051362,37.966981],"type":"Point"}
}