{
  "type": "Feature",
  "properties": {
    "iso:country":"US",
    "sg:address":"401 State Hwy 32",
    "sg:city":"Salem",
    "sg:classifiers":[
        {
            "category":"Autos & Motor Vehicles",
            "subcategory":"Auto Supplies",
            "type":"Retail Goods"
        }
    ],
    "sg:phone":"+1 573 729 4942",
    "sg:postcode":"65560",
    "sg:province":"MO",
    "sg:tags":[
        "equipment",
        "air",
        "conditioning",
        "automobile"
    ],
    "wof:name":"Stricklin Radiator & Auto AC",
    "wof:placetype":"venue"
},
  "geometry": {"coordinates":[-91.53331300000001,37.635781],"type":"Point"}
}