{
  "type": "Feature",
  "properties": {
    "iso:country":"US",
    "sg:address":"611 E Fox Hollow Rd",
    "sg:city":"Ashland",
    "sg:classifiers":[
        {
            "category":"Manufacturing",
            "subcategory":"Wood Products",
            "type":"Manufacturing & Wholesale Goods"
        }
    ],
    "sg:phone":"+1 573 657 2215",
    "sg:postcode":"65010",
    "sg:province":"MO",
    "sg:tags":[
        "millwork-wholesale",
        "millwork",
        "manufacturer"
    ],
    "wof:name":"Speciality Woodworks",
    "wof:placetype":"venue"
},
  "geometry": {"coordinates":[-92.342293,38.784119],"type":"Point"}
}