{
  "type": "Feature",
  "properties": {
    "iso:country":"US",
    "sg:address":"507 NW 43 Ter",
    "sg:city":"Kansas City",
    "sg:classifiers":[
        {
            "category":"Wholesale",
            "subcategory":"Vending Machines",
            "type":"Manufacturing & Wholesale Goods"
        }
    ],
    "sg:phone":"+1 816 452 8617",
    "sg:postcode":"64116",
    "sg:province":"MO",
    "sg:tags":[
        "operator"
    ],
    "wof:name":"Ensley Vending & Distrg Co",
    "wof:placetype":"venue"
},
  "geometry": {"coordinates":[-94.5908,39.173247],"type":"Point"}
}