{
  "type": "Feature",
  "properties": {
    "iso:country":"US",
    "sg:address":"501 State Hwy 92",
    "sg:city":"Kearney",
    "sg:classifiers":[
        {
            "category":"Professional",
            "subcategory":"Business Services",
            "type":"Services"
        }
    ],
    "sg:phone":"+1 816 628 6290",
    "sg:postcode":"64060",
    "sg:province":"MO",
    "wof:name":"Mega Industries",
    "wof:placetype":"venue"
},
  "geometry": {"coordinates":[-94.356022,39.367827],"type":"Point"}
}