{
  "type": "Feature",
  "properties": {
    "iso:country":"US",
    "sg:address":"12530 Zufall Ln",
    "sg:city":"De Soto",
    "sg:classifiers":[
        {
            "category":"Building & Trades",
            "subcategory":"Construction",
            "type":"Services"
        }
    ],
    "sg:phone":"+1 636 586 8504",
    "sg:postcode":"63020",
    "sg:province":"MO",
    "sg:tags":[
        "house",
        "general",
        "contractor"
    ],
    "wof:name":"Rod Caldwell Construction Inc",
    "wof:placetype":"venue"
},
  "geometry": {"coordinates":[-90.557092,38.162685],"type":"Point"}
}