{
  "type": "Feature",
  "properties": {
    "iso:country":"US",
    "sg:address":"810 W Terra Ln",
    "sg:city":"O Fallon",
    "sg:classifiers":[
        {
            "category":"Autos & Motor Vehicles",
            "subcategory":"Auto Supplies",
            "type":"Retail Goods"
        }
    ],
    "sg:phone":"+1 636 272 6565",
    "sg:postcode":"63366",
    "sg:province":"MO",
    "sg:tags":[
        "wholesale",
        "tire"
    ],
    "wof:name":"Childs Tire Inc",
    "wof:placetype":"venue"
},
  "geometry": {"coordinates":[-90.721395,38.802799],"type":"Point"}
}