{
  "type": "Feature",
  "properties": {
    "iso:country":"US",
    "sg:address":"12422 Worthington Dr",
    "sg:city":"Saint Louis",
    "sg:classifiers":[
        {
            "category":"Food & Beverages",
            "subcategory":"Groceries & Convenience Stores",
            "type":"Retail Goods"
        }
    ],
    "sg:phone":"+1 314 772 4589",
    "sg:postcode":"63128",
    "sg:province":"MO",
    "wof:name":"Kristopfs Market",
    "wof:placetype":"venue"
},
  "geometry": {"coordinates":[-90.37136599999999,38.508154],"type":"Point"}
}