{
  "type": "Feature",
  "properties": {
    "iso:country":"US",
    "sg:address":"1009 Baxter St",
    "sg:city":"Neosho",
    "sg:classifiers":[
        {
            "category":"Freight",
            "type":"Transportation"
        }
    ],
    "sg:phone":"+1 417 451 5046",
    "sg:postcode":"64850",
    "sg:province":"MO",
    "sg:tags":[
        "operator",
        "local",
        "trucking"
    ],
    "wof:name":"Howard Trucking",
    "wof:placetype":"venue"
},
  "geometry": {"coordinates":[-94.39078499999999,36.880028],"type":"Point"}
}