{
  "type": "Feature",
  "properties": {
    "iso:country":"US",
    "sg:address":"3329 S Westwood Blvd",
    "sg:city":"Poplar Bluff",
    "sg:classifiers":[
        {
            "category":"Food & Beverages",
            "subcategory":"Liquor & Beverages",
            "type":"Retail Goods"
        }
    ],
    "sg:phone":"+1 573 686 5413",
    "sg:postcode":"63901",
    "sg:province":"MO",
    "sg:tags":[
        "alcoholic"
    ],
    "wof:name":"Villa Package Liquor Store",
    "wof:placetype":"venue"
},
  "geometry": {"coordinates":[-90.441011,36.732227],"type":"Point"}
}