{
  "type": "Feature",
  "properties": {
    "addr:full":"12109 Refuge Rd Sumner MO 64681",
    "addr:postcode":"12109;64681",
    "addr:street":"Refuge Rd",
    "iso:country":"US",
    "sg:address":"12109 Refuge Rd",
    "sg:city":"Sumner",
    "sg:classifiers":[
        {
            "category":"Building & Trades",
            "subcategory":"Plumbing",
            "type":"Services"
        }
    ],
    "sg:phone":"+1 660 856 3238",
    "sg:postcode":"64681",
    "sg:province":"MO",
    "sg:tags":[
        "pipe",
        "line",
        "contractor"
    ],
    "wof:name":"Grand River Construction, Inc.",
    "wof:placetype":"venue"
},
  "geometry": {"coordinates":[-93.237596,39.637614],"type":"Point"}
}