{
  "type": "Feature",
  "properties": {
    "iso:country":"US",
    "sg:address":"2005 E Kearney St",
    "sg:city":"Springfield",
    "sg:classifiers":[
        {
            "category":"Personal",
            "subcategory":"Tattoo Parlor",
            "type":"Services"
        }
    ],
    "sg:phone":"+1 417 831 5611",
    "sg:postcode":"65803",
    "sg:province":"MO",
    "sg:tags":[
        "tattooing"
    ],
    "wof:name":"Dragonfly",
    "wof:placetype":"venue"
},
  "geometry": {"coordinates":[-93.256387,37.239968],"type":"Point"}
}