{
  "type": "Feature",
  "properties": {
    "iso:country":"US",
    "sg:address":"451 NW 701st Rd",
    "sg:city":"Centerview",
    "sg:classifiers":[
        {
            "category":"Professional",
            "type":"Services"
        }
    ],
    "sg:phone":"+1 660 747 8624",
    "sg:postcode":"64019",
    "sg:province":"MO",
    "wof:name":"Grant E Matthews",
    "wof:placetype":"venue"
},
  "geometry": {"coordinates":[-93.873322,38.835187],"type":"Point"}
}