{
  "type": "Feature",
  "properties": {
    "iso:country":"US",
    "sg:address":"100 Twill Haven Dr",
    "sg:city":"St Charles",
    "sg:classifiers":[
        {
            "category":"Wholesale",
            "subcategory":"Vending Machines",
            "type":"Manufacturing & Wholesale Goods"
        }
    ],
    "sg:phone":"+1 636 926 8282",
    "sg:postcode":"63304",
    "sg:province":"MO",
    "wof:name":"Best Vending",
    "wof:placetype":"venue"
},
  "geometry": {"coordinates":[-90.66489,38.737719],"type":"Point"}
}