{
  "type": "Feature",
  "properties": {
    "iso:country":"US",
    "sg:address":"502 S Beckwith St",
    "sg:city":"Malden",
    "sg:classifiers":[
        {
            "category":"Retail",
            "subcategory":"Car Wash",
            "type":"Services"
        }
    ],
    "sg:phone":"+1 573 276 5704",
    "sg:postcode":"63863",
    "sg:province":"MO",
    "sg:tags":[
        "automobile",
        "detail",
        "clean"
    ],
    "wof:name":"Tacker Auto Detail",
    "wof:placetype":"venue"
},
  "geometry": {"coordinates":[-89.967715,36.553023],"type":"Point"}
}