{
  "type": "Feature",
  "properties": {
    "iso:country":"US",
    "sg:address":"101 Eastwood Ave",
    "sg:city":"Higginsville",
    "sg:classifiers":[
        {
            "category":"Professional",
            "type":"Services"
        }
    ],
    "sg:phone":"+1 660 584 7874",
    "sg:postcode":"64037",
    "sg:province":"MO",
    "wof:name":"Vincent Thompson",
    "wof:placetype":"venue"
},
  "geometry": {"coordinates":[-93.710171,39.068329],"type":"Point"}
}