{
  "type": "Feature",
  "properties": {
    "iso:country":"US",
    "sg:address":"603 Crabapple Ln",
    "sg:city":"Liberty",
    "sg:classifiers":[
        {
            "category":"Retail",
            "subcategory":"Veterinary Services",
            "type":"Services"
        }
    ],
    "sg:phone":"+1 816 415 4375",
    "sg:postcode":"64068",
    "sg:province":"MO",
    "sg:tags":[
        "veterinarian",
        "specialty"
    ],
    "wof:name":"Robert J Smith Dvm",
    "wof:placetype":"venue"
},
  "geometry": {"coordinates":[-94.40278600000001,39.237765],"type":"Point"}
}