{
  "type": "Feature",
  "properties": {
    "iso:country":"US",
    "sg:address":"9229 Robyn Rd",
    "sg:city":"St Louis",
    "sg:classifiers":[
        {
            "category":"Professional",
            "subcategory":"Advertising",
            "type":"Services"
        }
    ],
    "sg:phone":"+1 314 842 3222",
    "sg:postcode":"63127",
    "sg:province":"MO",
    "sg:tags":[
        "counselor"
    ],
    "wof:name":"Brand Bank",
    "wof:placetype":"venue"
},
  "geometry": {"coordinates":[-90.39706099999999,38.540781],"type":"Point"}
}