{
  "type": "Feature",
  "properties": {
    "iso:country":"US",
    "sg:address":"17 Flint Ridge Dr",
    "sg:city":"Wentzville",
    "sg:classifiers":[
        {
            "category":"Building & Trades",
            "subcategory":"Construction",
            "type":"Services"
        }
    ],
    "sg:phone":"+1 636 327 3559",
    "sg:postcode":"63385",
    "sg:province":"MO",
    "sg:tags":[
        "excavation",
        "contractor"
    ],
    "wof:name":"Custom Excavating & Grading",
    "wof:placetype":"venue"
},
  "geometry": {"coordinates":[-90.81882299999999,38.85385],"type":"Point"}
}