{
  "type": "Feature",
  "properties": {
    "iso:country":"US",
    "sg:address":"108 Southeast St",
    "sg:city":"Wellsville",
    "sg:classifiers":[
        {
            "category":"Farming",
            "subcategory":"Livestock Farm",
            "type":"Manufacturing & Wholesale Goods"
        }
    ],
    "sg:phone":"+1 573 684 3150",
    "sg:postcode":"63384",
    "sg:province":"MO",
    "sg:tags":[
        "equine"
    ],
    "wof:name":"TLC Stables",
    "wof:placetype":"venue"
},
  "geometry": {"coordinates":[-91.5664,39.067271],"type":"Point"}
}