{
  "type": "Feature",
  "properties": {
    "iso:country":"US",
    "sg:address":"556 Purdue Ave",
    "sg:city":"Saint Louis",
    "sg:classifiers":[
        {
            "category":"Real Estate",
            "subcategory":"Real Estate Agent",
            "type":"Services"
        }
    ],
    "sg:phone":"+1 314 727 2520",
    "sg:postcode":"63130",
    "sg:province":"MO",
    "wof:name":"Horowitz & Fahey",
    "wof:placetype":"venue"
},
  "geometry": {"coordinates":[-90.327282,38.655141],"type":"Point"}
}