{
  "type": "Feature",
  "properties": {
    "iso:country":"US",
    "sg:address":"718 S Mill St",
    "sg:city":"Festus",
    "sg:classifiers":[
        {
            "category":"Building & Trades",
            "subcategory":"Plumbing",
            "type":"Services"
        }
    ],
    "sg:phone":"+1 636 937 3406",
    "sg:postcode":"63028",
    "sg:province":"MO",
    "sg:tags":[
        "plumber",
        "industrial",
        "contractors-commercial"
    ],
    "wof:name":"Jim S Complete Plumbing S",
    "wof:placetype":"venue"
},
  "geometry": {"coordinates":[-90.397003,38.211271],"type":"Point"}
}