{
  "type": "Feature",
  "properties": {
    "iso:country":"US",
    "sg:address":"9904 E 82nd Ter",
    "sg:city":"Raytown",
    "sg:classifiers":[
        {
            "category":"Building & Trades",
            "subcategory":"Electrical",
            "type":"Services"
        }
    ],
    "sg:phone":"+1 816 588 6415",
    "sg:postcode":"64138",
    "sg:province":"MO",
    "sg:tags":[
        "electrician"
    ],
    "wof:name":"Allyn Electric",
    "wof:placetype":"venue"
},
  "geometry": {"coordinates":[-94.465586,38.973868],"type":"Point"}
}