{
  "type": "Feature",
  "properties": {
    "iso:country":"US",
    "sg:address":"5232 Oak St",
    "sg:city":"Kansas City",
    "sg:classifiers":[
        {
            "category":"Shopping",
            "subcategory":"Gifts & Souvenirs",
            "type":"Retail Goods"
        }
    ],
    "sg:phone":"+1 816 726 8087",
    "sg:postcode":"64112",
    "sg:province":"MO",
    "wof:name":"One of A Kind Friend",
    "wof:placetype":"venue"
},
  "geometry": {"coordinates":[-94.583032,39.029643],"type":"Point"}
}