{
  "type": "Feature",
  "properties": {
    "iso:country":"US",
    "sg:address":"645 W 3rd St",
    "sg:city":"Mountain Grove",
    "sg:classifiers":[
        {
            "category":"Personal",
            "type":"Services"
        }
    ],
    "sg:phone":"+1 417 926 3595",
    "sg:postcode":"65711",
    "sg:province":"MO",
    "wof:name":"Cosmetique House Of Style",
    "wof:placetype":"venue"
},
  "geometry": {"coordinates":[-92.269564,37.131022],"type":"Point"}
}