{
  "type": "Feature",
  "properties": {
    "addr:full":"3140 Mc Clelland Blvd Joplin MO 64804",
    "addr:housenumber":"3140",
    "addr:postcode":"64804",
    "addr:street":"Mc Clelland Blvd",
    "iso:country":"US",
    "sg:address":"3140 Mc Clelland Blvd",
    "sg:city":"Joplin",
    "sg:classifiers":[
        {
            "category":"Restaurant",
            "type":"Food & Drink"
        }
    ],
    "sg:menulink":"http://www.allmenus.com/mo/galena/194189-mcdonalds/menu/",
    "sg:postcode":"64804",
    "sg:province":"MO",
    "sg:tags":[
        "burger",
        "american"
    ],
    "wof:name":"McDonald's",
    "wof:placetype":"venue"
},
  "geometry": {"coordinates":[-94.53277799999999,37.055555],"type":"Point"}
}