{
  "type": "Feature",
  "properties": {
    "iso:country":"US",
    "sg:address":"281 Greenbriar Estates Dr",
    "sg:city":"Saint Louis",
    "sg:classifiers":[
        {
            "category":"Professional",
            "type":"Services"
        }
    ],
    "sg:phone":"+1 314 821 9362",
    "sg:postcode":"63122",
    "sg:province":"MO",
    "wof:name":"Vine Art",
    "wof:placetype":"venue"
},
  "geometry": {"coordinates":[-90.45773,38.573557],"type":"Point"}
}