{
  "type": "Feature",
  "properties": {
    "iso:country":"US",
    "sg:address":"21971 State Hwy 32",
    "sg:city":"Ste Genevieve",
    "sg:classifiers":[
        {
            "category":"Banks & Credit Unions",
            "subcategory":"Investment Brokerage",
            "type":"Services"
        }
    ],
    "sg:phone":"+1 573 883 7494",
    "sg:postcode":"63670",
    "sg:province":"MO",
    "sg:tags":[
        "stock",
        "bond"
    ],
    "wof:name":"Edward Jones Co",
    "wof:placetype":"venue"
},
  "geometry": {"coordinates":[-90.05635599999999,37.967785],"type":"Point"}
}