{
  "type": "Feature",
  "properties": {
    "iso:country":"US",
    "sg:address":"7813 W Old 66 Blvd",
    "sg:city":"Joplin",
    "sg:classifiers":[
        {
            "category":"Sports & Exercise",
            "subcategory":"Bowling",
            "type":"Entertainment"
        }
    ],
    "sg:phone":"+1 417 623 9431",
    "sg:postcode":"64804",
    "sg:province":"MO",
    "sg:tags":[
        "alley"
    ],
    "wof:name":"Crown Lanes",
    "wof:placetype":"venue"
},
  "geometry": {"coordinates":[-94.61548500000001,37.085865],"type":"Point"}
}