{
  "type": "Feature",
  "properties": {
    "iso:country":"US",
    "sg:address":"3401 Renick St",
    "sg:city":"St Joseph",
    "sg:classifiers":[
        {
            "category":"Education",
            "subcategory":"School",
            "type":"Public Place"
        }
    ],
    "sg:phone":"+1 816 671 4390",
    "sg:postcode":"64507",
    "sg:province":"MO",
    "sg:website":"www.sjsd.k12.mo.us",
    "wof:name":"Troester Media Center",
    "wof:placetype":"venue"
},
  "geometry": {"coordinates":[-94.808376,39.75428],"type":"Point"}
}