{
  "type": "Feature",
  "properties": {
    "iso:country":"US",
    "sg:address":"1005 W 41 St",
    "sg:city":"Kansas City",
    "sg:classifiers":[
        {
            "category":"Food & Beverages",
            "subcategory":"Bakery",
            "type":"Retail Goods"
        }
    ],
    "sg:phone":"+1 816 753 2486",
    "sg:postcode":"64111",
    "sg:province":"MO",
    "sg:tags":[
        "baker"
    ],
    "wof:name":"J H Baker Personal Svc",
    "wof:placetype":"venue"
},
  "geometry": {"coordinates":[-94.598553,39.054604],"type":"Point"}
}