{
  "type": "Feature",
  "properties": {
    "iso:country":"US",
    "sg:address":"2716 Telegraph Rd",
    "sg:city":"Saint Louis",
    "sg:classifiers":[
        {
            "category":"Health Services",
            "subcategory":"Podiatrist",
            "type":"Services"
        }
    ],
    "sg:phone":"+1 314 487 4055",
    "sg:postcode":"63125",
    "sg:province":"MO",
    "wof:name":"Donald Piekarski",
    "wof:placetype":"venue"
},
  "geometry": {"coordinates":[-90.29301599999999,38.509791],"type":"Point"}
}