{
  "type": "Feature",
  "properties": {
    "iso:country":"US",
    "sg:address":"100 Stadium Plz",
    "sg:city":"St Louis",
    "sg:classifiers":[
        {
            "category":"Shopping",
            "subcategory":"Gifts & Souvenirs",
            "type":"Retail Goods"
        }
    ],
    "sg:phone":"+1 314 421 3263",
    "sg:postcode":"63102",
    "sg:province":"MO",
    "sg:tags":[
        "shop"
    ],
    "sg:website":"www.fanzone.com",
    "wof:name":"Cardinals Team Store",
    "wof:placetype":"venue"
},
  "geometry": {"coordinates":[-90.19400899999999,38.624137],"type":"Point"}
}