{
  "type": "Feature",
  "properties": {
    "iso:country":"US",
    "sg:address":"1110 Jones Ave",
    "sg:city":"Eldon",
    "sg:classifiers":[
        {
            "category":"Social Services",
            "subcategory":"Child Care",
            "type":"Services"
        },
        {
            "category":"Education",
            "subcategory":"School",
            "type":"Public Place"
        }
    ],
    "sg:phone":"+1 573 392 3409",
    "sg:postcode":"65026",
    "sg:province":"MO",
    "sg:tags":[
        "kindergarten",
        "academic"
    ],
    "wof:name":"Montessori Children's House",
    "wof:placetype":"venue"
},
  "geometry": {"coordinates":[-92.564599,38.351991],"type":"Point"}
}