{
  "type": "Feature",
  "properties": {
    "iso:country":"US",
    "sg:address":"5785 Westwood Dr",
    "sg:city":"Saint Charles",
    "sg:classifiers":[
        {
            "category":"Manufacturing",
            "subcategory":"Chemicals & Compounds",
            "type":"Manufacturing & Wholesale Goods"
        }
    ],
    "sg:phone":"+1 636 441 8803",
    "sg:postcode":"63304",
    "sg:province":"MO",
    "sg:tags":[
        "preparation",
        "toilet",
        "so",
        "mfg"
    ],
    "wof:name":"Classic Lady Packaging Inc",
    "wof:placetype":"venue"
},
  "geometry": {"coordinates":[-90.668319,38.720995],"type":"Point"}
}