{
  "type": "Feature",
  "properties": {
    "iso:country":"US",
    "sg:address":"1809 N Kingshighway St",
    "sg:city":"Cape Girardeau",
    "sg:classifiers":[
        {
            "category":"Home & Garden",
            "subcategory":"Furniture",
            "type":"Retail Goods"
        }
    ],
    "sg:phone":"+1 573 334 7757",
    "sg:postcode":"63701",
    "sg:province":"MO",
    "wof:name":"Sleepy Hollow Home Ctr",
    "wof:placetype":"venue"
},
  "geometry": {"coordinates":[-89.572739,37.332353],"type":"Point"}
}