{
  "type": "Feature",
  "properties": {
    "iso:country":"US",
    "sg:address":"20745 Sedalia Rd",
    "sg:city":"Waynesville",
    "sg:classifiers":[
        {
            "category":"Professional",
            "subcategory":"Detective & Security Services",
            "type":"Services"
        }
    ],
    "sg:phone":"+1 573 528 5116",
    "sg:postcode":"65583",
    "sg:province":"MO",
    "sg:tags":[
        "information",
        "bureau"
    ],
    "wof:name":"Sergeant Darrell S. Cole Detachment 1195 Marine Corps League",
    "wof:placetype":"venue"
},
  "geometry": {"coordinates":[-92.22061600000001,37.782393],"type":"Point"}
}