{
  "type": "Feature",
  "properties": {
    "iso:country":"US",
    "sg:address":"29118 S Van Meter Rd",
    "sg:city":"Freeman",
    "sg:classifiers":[
        {
            "category":"Building & Trades",
            "subcategory":"Construction",
            "type":"Services"
        }
    ],
    "sg:phone":"+1 816 250 2473",
    "sg:postcode":"64746",
    "sg:province":"MO",
    "sg:tags":[
        "carpenter"
    ],
    "wof:name":"Carpentry Plus Inc",
    "wof:placetype":"venue"
},
  "geometry": {"coordinates":[-94.525267,38.588864],"type":"Point"}
}