{
  "type": "Feature",
  "properties": {
    "iso:country":"US",
    "sg:address":"5230 Spring Trail Dr",
    "sg:city":"Florissant",
    "sg:classifiers":[
        {
            "category":"Professional",
            "subcategory":"Management & Consulting",
            "type":"Services"
        }
    ],
    "sg:phone":"+1 314 355 5325",
    "sg:postcode":"63033",
    "sg:province":"MO",
    "sg:tags":[
        "training"
    ],
    "wof:name":"Self Management Communications",
    "wof:placetype":"venue"
},
  "geometry": {"coordinates":[-90.254946,38.801072],"type":"Point"}
}