{
  "type": "Feature",
  "properties": {
    "iso:country":"US",
    "sg:address":"500 N Main Ave",
    "sg:city":"Springfield",
    "sg:classifiers":[
        {
            "category":"Manufacturing",
            "subcategory":"Tools & Machinery",
            "type":"Manufacturing & Wholesale Goods"
        }
    ],
    "sg:phone":"+1 417 869 2060",
    "sg:postcode":"65806",
    "sg:province":"MO",
    "sg:tags":[
        "machine",
        "shop"
    ],
    "wof:name":"Precision Machining Of Ozark",
    "wof:placetype":"venue"
},
  "geometry": {"coordinates":[-93.48034,37.123889],"type":"Point"}
}