{
  "type": "Feature",
  "properties": {
    "iso:country":"US",
    "sg:address":"79 N Highway A",
    "sg:city":"Lamar",
    "sg:classifiers":[
        {
            "category":"Farming",
            "subcategory":"Livestock Farm",
            "type":"Manufacturing & Wholesale Goods"
        }
    ],
    "sg:phone":"+1 417 682 3583",
    "sg:postcode":"64759",
    "sg:province":"MO",
    "sg:tags":[
        "ranch"
    ],
    "wof:name":"Neil Robertson",
    "wof:placetype":"venue"
},
  "geometry": {"coordinates":[-94.18720399999999,37.513172],"type":"Point"}
}