{
  "type": "Feature",
  "properties": {
    "iso:country":"US",
    "sg:address":"1806 Stoddard St",
    "sg:city":"Cape Girardeau",
    "sg:classifiers":[
        {
            "category":"Shopping",
            "type":"Retail Goods"
        }
    ],
    "sg:phone":"+1 573 334 2393",
    "sg:postcode":"63701",
    "sg:province":"MO",
    "sg:tags":[
        "repair",
        "merchandise",
        "mfg"
    ],
    "wof:name":"R & R Awning Co",
    "wof:placetype":"venue"
},
  "geometry": {"coordinates":[-89.54441799999999,37.322666],"type":"Point"}
}