{
  "type": "Feature",
  "properties": {
    "iso:country":"US",
    "sg:address":"151 W Park Mall",
    "sg:city":"Cape Girardeau",
    "sg:classifiers":[
        {
            "category":"Recreation",
            "subcategory":"Amusement Park",
            "type":"Entertainment"
        }
    ],
    "sg:phone":"+1 573 334 5846",
    "sg:postcode":"63703",
    "sg:province":"MO",
    "wof:name":"Tilt",
    "wof:placetype":"venue"
},
  "geometry": {"coordinates":[-89.573898,37.298904],"type":"Point"}
}