{
  "type": "Feature",
  "properties": {
    "iso:country":"US",
    "sg:address":"231 S Main St",
    "sg:city":"Ironton",
    "sg:classifiers":[
        {
            "category":"Banks & Credit Unions",
            "subcategory":"Bank",
            "type":"Services"
        }
    ],
    "sg:phone":"+1 573 546 7431",
    "sg:postcode":"63650",
    "sg:province":"MO",
    "sg:website":"www.fscb.com",
    "wof:name":"First State Community Bank",
    "wof:placetype":"venue"
},
  "geometry": {"coordinates":[-90.627548,37.598023],"type":"Point"}
}