{
  "type": "Feature",
  "properties": {
    "iso:country":"US",
    "sg:address":"1300 Hampton Ave",
    "sg:city":"St Louis",
    "sg:classifiers":[
        {
            "category":"Health Services",
            "subcategory":"Nursing And Care Facility",
            "type":"Services"
        }
    ],
    "sg:phone":"+1 314 645 8648",
    "sg:postcode":"63139",
    "sg:province":"MO",
    "sg:tags":[
        "hospice",
        "skilled"
    ],
    "wof:name":"Unity Hospice",
    "wof:placetype":"venue"
},
  "geometry": {"coordinates":[-90.28768599999999,38.626218],"type":"Point"}
}