{
  "type": "Feature",
  "properties": {
    "iso:country":"US",
    "sg:address":"4211 S Hocker St",
    "sg:city":"Independence",
    "sg:classifiers":[
        {
            "category":"Professional",
            "subcategory":"Accounting & Tax Preparation",
            "type":"Services"
        }
    ],
    "sg:phone":"+1 816 478 0915",
    "sg:postcode":"64055",
    "sg:province":"MO",
    "sg:tags":[
        "accountant"
    ],
    "wof:name":"Trudy Beard CPA",
    "wof:placetype":"venue"
},
  "geometry": {"coordinates":[-94.410415,39.043811],"type":"Point"}
}