{
  "type": "Feature",
  "properties": {
    "iso:country":"US",
    "sg:address":"4720 NW Gateway Ave",
    "sg:city":"Kansas City",
    "sg:classifiers":[
        {
            "category":"Recreation",
            "type":"Entertainment"
        }
    ],
    "sg:phone":"+1 816 587 0131",
    "sg:postcode":"64150",
    "sg:province":"MO",
    "sg:tags":[
        "skating",
        "rink"
    ],
    "sg:website":"www.riverroll.com",
    "wof:name":"River Roll Skate Center",
    "wof:placetype":"venue"
},
  "geometry": {"coordinates":[-94.6134,39.182307],"type":"Point"}
}