{
  "type": "Feature",
  "properties": {
    "iso:country":"US",
    "sg:address":"127 Algana Ct",
    "sg:city":"St Peters",
    "sg:classifiers":[
        {
            "category":"Wholesale",
            "subcategory":"Office Equipment",
            "type":"Manufacturing & Wholesale Goods"
        },
        {
            "category":"Manufacturing",
            "subcategory":"Electronics",
            "type":"Manufacturing & Wholesale Goods"
        }
    ],
    "sg:phone":"+1 636 928 7770",
    "sg:postcode":"63376",
    "sg:province":"MO",
    "sg:tags":[
        "machine",
        "communication",
        "supply"
    ],
    "sg:website":"www.rbmcopysystems.com",
    "wof:name":"Rbm Copy Systems Inc",
    "wof:placetype":"venue"
},
  "geometry": {"coordinates":[-90.582581,38.801125],"type":"Point"}
}