{
  "type": "Feature",
  "properties": {
    "iso:country":"US",
    "sg:address":"122 NW 63 St",
    "sg:city":"Kansas City",
    "sg:classifiers":[
        {
            "category":"Real Estate",
            "subcategory":"Real Estate Operator",
            "type":"Services"
        }
    ],
    "sg:phone":"+1 816 453 3682",
    "sg:postcode":"64118",
    "sg:province":"MO",
    "sg:tags":[
        "apartment"
    ],
    "wof:name":"Rosemont Court Apartments",
    "wof:placetype":"venue"
},
  "geometry": {"coordinates":[-94.58314900000001,39.208461],"type":"Point"}
}