{
  "type": "Feature",
  "properties": {
    "iso:country":"US",
    "sg:address":"1706 S Big Bend Blvd",
    "sg:city":"Richmond Heights",
    "sg:classifiers":[
        {
            "category":"Personal",
            "type":"Services"
        },
        {
            "category":"Freight",
            "type":"Transportation"
        }
    ],
    "sg:phone":"+1 314 991 1320",
    "sg:postcode":"63117",
    "sg:province":"MO",
    "sg:tags":[
        "mover",
        "shipping"
    ],
    "sg:website":"www.gonavis.com/about/mo1049",
    "wof:name":"Navis Pack & Ship",
    "wof:placetype":"venue"
},
  "geometry": {"coordinates":[-90.320773,38.623628],"type":"Point"}
}