{
  "type": "Feature",
  "properties": {
    "iso:country":"US",
    "sg:address":"610 S Broad St",
    "sg:city":"Parma",
    "sg:classifiers":[
        {
            "category":"Manufacturing",
            "subcategory":"Tools & Machinery",
            "type":"Manufacturing & Wholesale Goods"
        }
    ],
    "sg:phone":"+1 573 357 4317",
    "sg:postcode":"63870",
    "sg:province":"MO",
    "sg:tags":[
        "ginning",
        "cotton",
        "supply"
    ],
    "wof:name":"Mahan Gin Co",
    "wof:placetype":"venue"
},
  "geometry": {"coordinates":[-89.81694400000001,36.612238],"type":"Point"}
}