{
  "type": "Feature",
  "properties": {
    "iso:country":"US",
    "sg:address":"8022 S Broadway",
    "sg:city":"St Louis",
    "sg:classifiers":[
        {
            "category":"Retail",
            "subcategory":"Auto Repair",
            "type":"Services"
        }
    ],
    "sg:phone":"+1 314 638 1103",
    "sg:postcode":"63111",
    "sg:province":"MO",
    "sg:tags":[
        "body",
        "automobile",
        "painting"
    ],
    "wof:name":"Faulstich Auto Body Repair",
    "wof:placetype":"venue"
},
  "geometry": {"coordinates":[-90.261152,38.544558],"type":"Point"}
}