{
  "type": "Feature",
  "properties": {
    "iso:country":"US",
    "sg:address":"950 Lamar St",
    "sg:city":"Avilla",
    "sg:classifiers":[
        {
            "category":"Retail",
            "subcategory":"Auto Repair",
            "type":"Services"
        }
    ],
    "sg:phone":"+1 417 246 5368",
    "sg:postcode":"64833",
    "sg:province":"MO",
    "sg:tags":[
        "body"
    ],
    "wof:name":"Avilla Body Shop",
    "wof:placetype":"venue"
},
  "geometry": {"coordinates":[-94.129698,37.197867],"type":"Point"}
}