{
  "type": "Feature",
  "properties": {
    "iso:country":"US",
    "sg:address":"10750 Midwest Industrial Blvd",
    "sg:city":"St Louis",
    "sg:classifiers":[
        {
            "category":"Building & Trades",
            "subcategory":"Cleaning & Sanitation",
            "type":"Services"
        }
    ],
    "sg:phone":"+1 314 423 0773",
    "sg:postcode":"63132",
    "sg:province":"MO",
    "sg:tags":[
        "flue"
    ],
    "sg:website":"www.commercialsteam.com",
    "wof:name":"Commercial Steam Cleaners",
    "wof:placetype":"venue"
},
  "geometry": {"coordinates":[-90.40203099999999,38.688366],"type":"Point"}
}