{
  "type": "Feature",
  "properties": {
    "iso:country":"US",
    "sg:address":"107 S Biltz Dr",
    "sg:city":"Concordia",
    "sg:classifiers":[
        {
            "category":"Farming",
            "subcategory":"Farm",
            "type":"Manufacturing & Wholesale Goods"
        }
    ],
    "sg:phone":"+1 660 463 7371",
    "sg:postcode":"64020",
    "sg:province":"MO",
    "sg:tags":[
        "crop",
        "general"
    ],
    "wof:name":"W C Nienhuese Farms Inc",
    "wof:placetype":"venue"
},
  "geometry": {"coordinates":[-93.556898,38.989006],"type":"Point"}
}