{
  "type": "Feature",
  "properties": {
    "iso:country":"US",
    "sg:address":"4621 NE Vivion Rd",
    "sg:city":"Kansas City",
    "sg:classifiers":[
        {
            "category":"Autos & Motor Vehicles",
            "subcategory":"Fuel & Gas Station",
            "type":"Retail Goods"
        }
    ],
    "sg:phone":"+1 816 452 5332",
    "sg:postcode":"64119",
    "sg:province":"MO",
    "sg:tags":[
        "station",
        "gasoline"
    ],
    "wof:name":"Total Gas Station 4409",
    "wof:placetype":"venue"
},
  "geometry": {"coordinates":[-94.524843,39.187919],"type":"Point"}
}