{
  "type": "Feature",
  "properties": {
    "iso:country":"US",
    "sg:address":"3818 Rock Bluff Ct",
    "sg:city":"St Louis",
    "sg:classifiers":[
        {
            "category":"Building & Trades",
            "subcategory":"Construction",
            "type":"Services"
        }
    ],
    "sg:phone":"+1 314 845 2171",
    "sg:postcode":"63129",
    "sg:province":"MO",
    "sg:tags":[
        "siding",
        "carpentry",
        "contractor"
    ],
    "wof:name":"Trade Mark Construction",
    "wof:placetype":"venue"
},
  "geometry": {"coordinates":[-90.34248700000001,38.471858],"type":"Point"}
}