{
  "type": "Feature",
  "properties": {
    "iso:country":"US",
    "sg:address":"910 Porter Wagoner Blvd",
    "sg:city":"West Plains",
    "sg:classifiers":[
        {
            "category":"Insurance",
            "subcategory":"Insurance Agent",
            "type":"Services"
        },
        {
            "category":"Insurance",
            "subcategory":"Life Insurance",
            "type":"Services"
        }
    ],
    "sg:phone":"+1 417 256 4800",
    "sg:postcode":"65775",
    "sg:province":"MO",
    "sg:tags":[
        "carrier",
        "market",
        "research"
    ],
    "wof:name":"Farm Bureau Insurance Services",
    "wof:placetype":"venue"
},
  "geometry": {"coordinates":[-91.865989,36.736327],"type":"Point"}
}