{
  "type": "Feature",
  "properties": {
    "iso:country":"US",
    "sg:address":"3800 Gravois Ave",
    "sg:city":"Saint Louis",
    "sg:classifiers":[
        {
            "category":"Professional",
            "type":"Services"
        }
    ],
    "sg:phone":"+1 314 772 6606",
    "sg:postcode":"63116",
    "sg:province":"MO",
    "wof:name":"Pacific Services Center",
    "wof:placetype":"venue"
},
  "geometry": {"coordinates":[-90.250118,38.591557],"type":"Point"}
}