{
  "type": "Feature",
  "properties": {
    "iso:country":"US",
    "sg:address":"8 Brewer Rd",
    "sg:city":"Charleston",
    "sg:phone":"+1 573 683 2230",
    "sg:postcode":"63834",
    "sg:province":"MO",
    "sg:tags":[
        "farm",
        "soybean"
    ],
    "wof:name":"Robert Graham",
    "wof:placetype":"venue"
},
  "geometry": {"coordinates":[-89.347966,36.935063],"type":"Point"}
}