{
  "type": "Feature",
  "properties": {
    "iso:country":"US",
    "sg:address":"20298 Moloney Dr",
    "sg:city":"Licking",
    "sg:phone":"+1 573 674 3565",
    "sg:postcode":"65542",
    "sg:province":"MO",
    "sg:tags":[
        "farm",
        "soybean"
    ],
    "wof:name":"Moloney Farms",
    "wof:placetype":"venue"
},
  "geometry": {"coordinates":[-91.795107,37.56238],"type":"Point"}
}