{
  "type": "Feature",
  "properties": {
    "iso:country":"US",
    "sg:address":"5976 Howdershell Rd",
    "sg:city":"Hazelwood",
    "sg:classifiers":[
        {
            "category":"Professional",
            "subcategory":"Management & Consulting",
            "type":"Services"
        },
        {
            "category":"Education",
            "subcategory":"Special Training",
            "type":"Public Place"
        },
        {
            "category":"Education",
            "subcategory":"Library",
            "type":"Public Place"
        }
    ],
    "sg:phone":"+1 877 655 7242",
    "sg:postcode":"63042",
    "sg:province":"MO",
    "sg:tags":[
        "educational",
        "consultant",
        "instruction",
        "system",
        "improvement",
        "preparation",
        "equipment",
        "adult",
        "test",
        "reading",
        "tutoring"
    ],
    "sg:website":"http://www.sylvanlearningcenter.com",
    "wof:name":"Sylvan Learning Center",
    "wof:placetype":"venue"
},
  "geometry": {"coordinates":[-90.388622,38.781635],"type":"Point"}
}