{
  "type": "Feature",
  "properties": {
    "iso:country":"US",
    "sg:address":"410 Redbud Ln",
    "sg:city":"Buffalo",
    "sg:classifiers":[
        {
            "category":"Retail",
            "subcategory":"Laundry & Dry Cleaning",
            "type":"Services"
        }
    ],
    "sg:phone":"+1 417 345 4962",
    "sg:postcode":"65622",
    "sg:province":"MO",
    "sg:tags":[
        "cleaners",
        "rug",
        "carpet"
    ],
    "wof:name":"Quality Cleaning Specialist",
    "wof:placetype":"venue"
},
  "geometry": {"coordinates":[-93.087778,37.647122],"type":"Point"}
}