{
  "type": "Feature",
  "properties": {
    "iso:country":"US",
    "sg:address":"1204 Sunset Dr",
    "sg:city":"Mountain Grove",
    "sg:classifiers":[
        {
            "category":"Professional",
            "subcategory":"Management & Consulting",
            "type":"Services"
        }
    ],
    "sg:phone":"+1 417 926 0817",
    "sg:postcode":"65711",
    "sg:province":"MO",
    "sg:tags":[
        "business"
    ],
    "wof:name":"Hr Solutions",
    "wof:placetype":"venue"
},
  "geometry": {"coordinates":[-92.25255300000001,37.137992],"type":"Point"}
}