{
  "type": "Feature",
  "properties": {
    "iso:country":"US",
    "sg:address":"946 S Campbell Ave",
    "sg:city":"Springfield",
    "sg:classifiers":[
        {
            "category":"Retail",
            "subcategory":"Repair Shop",
            "type":"Services"
        }
    ],
    "sg:phone":"+1 417 869 4738",
    "sg:postcode":"65806",
    "sg:province":"MO",
    "sg:tags":[
        "television",
        "radio"
    ],
    "wof:name":"Electronic Communications",
    "wof:placetype":"venue"
},
  "geometry": {"coordinates":[-93.29446299999999,37.197678],"type":"Point"}
}