{
  "type": "Feature",
  "properties": {
    "iso:country":"US",
    "sg:address":"16081 SW 42nd Rd",
    "sg:city":"De Kalb",
    "sg:classifiers":[
        {
            "category":"Autos & Motor Vehicles",
            "subcategory":"Automobile Sales",
            "type":"Retail Goods"
        }
    ],
    "sg:phone":"+1 816 685 7770",
    "sg:postcode":"64440",
    "sg:province":"MO",
    "sg:tags":[
        "used"
    ],
    "wof:name":"Bauer Pre Owned & Classic Auto",
    "wof:placetype":"venue"
},
  "geometry": {"coordinates":[-94.932844,39.576316],"type":"Point"}
}