{
  "type": "Feature",
  "properties": {
    "iso:country":"US",
    "sg:address":"1705 Prospect Dr",
    "sg:city":"Macon",
    "sg:classifiers":[
        {
            "category":"Health Services",
            "subcategory":"Optometrist",
            "type":"Services"
        },
        {
            "category":"Shopping",
            "subcategory":"Optical Goods",
            "type":"Retail Goods"
        }
    ],
    "sg:phone":"+1 660 385 5724",
    "sg:postcode":"63552",
    "sg:province":"MO",
    "sg:tags":[
        "lens",
        "contact"
    ],
    "wof:name":"Vision Care Associates",
    "wof:placetype":"venue"
},
  "geometry": {"coordinates":[-92.462429,39.752236],"type":"Point"}
}