{
  "type": "Feature",
  "properties": {
    "addr:full":"501 E Booneslick Rd Warrenton MO 63383",
    "addr:housenumber":"501",
    "addr:postcode":"63383",
    "addr:street":"E Booneslick Rd",
    "iso:country":"US",
    "sg:address":"501 E Booneslick Rd",
    "sg:city":"Warrenton",
    "sg:classifiers":[
        {
            "category":"Government",
            "subcategory":"Post Office",
            "type":"Public Place"
        }
    ],
    "sg:phone":"+1 636 456 3324",
    "sg:postcode":"63383",
    "sg:province":"MO",
    "sg:website":"www.usps.gov",
    "wof:name":"US Post Office",
    "wof:placetype":"venue"
},
  "geometry": {"coordinates":[-91.14151699999999,38.811371],"type":"Point"}
}