{
  "type": "Feature",
  "properties": {
    "iso:country":"US",
    "sg:address":"7925 NW 110th St",
    "sg:city":"Kansas City",
    "sg:classifiers":[
        {
            "category":"Social Services",
            "subcategory":"Child Care",
            "type":"Services"
        }
    ],
    "sg:phone":"+1 816 891 9400",
    "sg:postcode":"64153",
    "sg:province":"MO",
    "sg:website":"www.brighthorizons.com",
    "wof:name":"Citicorp Family Ctr",
    "wof:placetype":"venue"
},
  "geometry": {"coordinates":[-94.673379,39.292531],"type":"Point"}
}