{
  "type": "Feature",
  "properties": {
    "iso:country":"US",
    "sg:address":"1980 State Hwy V",
    "sg:city":"Harviell",
    "sg:classifiers":[
        {
            "category":"Organizations",
            "subcategory":"Non-profit Organization",
            "type":"Services"
        }
    ],
    "sg:phone":"+1 573 989 3919",
    "sg:postcode":"63945",
    "sg:province":"MO",
    "wof:name":"Project Wow Walk The Ozarks",
    "wof:placetype":"venue"
},
  "geometry": {"coordinates":[-90.549178,36.644066],"type":"Point"}
}