{
  "type": "Feature",
  "properties": {
    "iso:country":"US",
    "sg:address":"1512 Main St",
    "sg:city":"Grandview",
    "sg:classifiers":[
        {
            "category":"Personal",
            "subcategory":"Massage",
            "type":"Services"
        },
        {
            "category":"Health Services",
            "subcategory":"Clinic",
            "type":"Services"
        },
        {
            "category":"Health Services",
            "subcategory":"Health Practitioner",
            "type":"Services"
        }
    ],
    "sg:phone":"+1 816 966 0522",
    "sg:postcode":"64030",
    "sg:province":"MO",
    "sg:tags":[
        "therapist",
        "therapy",
        "physical"
    ],
    "wof:name":"Christina Waugh Lmt",
    "wof:placetype":"venue"
},
  "geometry": {"coordinates":[-94.527829,38.888993],"type":"Point"}
}