{
  "type": "Feature",
  "properties": {
    "iso:country":"US",
    "sg:address":"316 S Main St",
    "sg:city":"Peculiar",
    "sg:classifiers":[
        {
            "category":"Building & Trades",
            "subcategory":"Construction",
            "type":"Services"
        }
    ],
    "sg:phone":"+1 314 801 0268",
    "sg:postcode":"64078",
    "sg:province":"MO",
    "sg:tags":[
        "bathroom",
        "planning",
        "remodeling",
        "kitchen",
        "contractor"
    ],
    "wof:name":"Urban Renovation",
    "wof:placetype":"venue"
},
  "geometry": {"coordinates":[-94.46054599999999,38.714114],"type":"Point"}
}