{
  "type": "Feature",
  "properties": {
    "iso:country":"US",
    "sg:address":"100 W Horseshoe Dr",
    "sg:city":"Gallatin",
    "sg:classifiers":[
        {
            "category":"Wholesale",
            "subcategory":"Farm Supplies",
            "type":"Manufacturing & Wholesale Goods"
        },
        {
            "category":"Shopping",
            "subcategory":"Pets & Pet Supplies",
            "type":"Retail Goods"
        }
    ],
    "sg:phone":"+1 660 663 3687",
    "sg:postcode":"64640",
    "sg:province":"MO",
    "sg:tags":[
        "feed",
        "grain",
        "elevator"
    ],
    "wof:name":"Gallatin Grain Company Feed Div",
    "wof:placetype":"venue"
},
  "geometry": {"coordinates":[-93.979469,39.914207],"type":"Point"}
}