{
  "type": "Feature",
  "properties": {
    "iso:country":"US",
    "sg:address":"3350 S Scott Ave",
    "sg:city":"Independence",
    "sg:classifiers":[
        {
            "category":"Restaurant",
            "type":"Food & Drink"
        }
    ],
    "sg:phone":"+1 816 833 0624",
    "sg:postcode":"64052",
    "sg:province":"MO",
    "sg:tags":[
        "eating"
    ],
    "wof:name":"Johnny CS Deli and Pasta",
    "wof:placetype":"venue"
},
  "geometry": {"coordinates":[-94.440646,39.060111],"type":"Point"}
}