{
  "type": "Feature",
  "properties": {
    "iso:country":"US",
    "sg:address":"2312 Mueller Ln",
    "sg:city":"St Louis",
    "sg:classifiers":[
        {
            "category":"Building & Trades",
            "subcategory":"Landscaping Services",
            "type":"Services"
        }
    ],
    "sg:phone":"+1 314 989 1900",
    "sg:postcode":"63131",
    "sg:province":"MO",
    "sg:tags":[
        "landscape",
        "contractor"
    ],
    "wof:name":"Houlihan Land Concepts Inc",
    "wof:placetype":"venue"
},
  "geometry": {"coordinates":[-90.452949,38.625508],"type":"Point"}
}