{
  "type": "Feature",
  "properties": {
    "iso:country":"US",
    "sg:address":"320 W Walnut St",
    "sg:city":"Springfield",
    "sg:classifiers":[
        {
            "category":"Home & Garden",
            "subcategory":"Furniture",
            "type":"Retail Goods"
        }
    ],
    "sg:phone":"+1 417 865 2876",
    "sg:postcode":"65806",
    "sg:province":"MO",
    "sg:tags":[
        "interior",
        "design"
    ],
    "wof:name":"Thomas Brothers Office Furn",
    "wof:placetype":"venue"
},
  "geometry": {"coordinates":[-93.294101,37.207046],"type":"Point"}
}