{
  "type": "Feature",
  "properties": {
    "iso:country":"US",
    "sg:address":"9422 Hwy Yy",
    "sg:city":"New Haven",
    "sg:classifiers":[
        {
            "category":"Farming",
            "subcategory":"Farm",
            "type":"Manufacturing & Wholesale Goods"
        }
    ],
    "sg:phone":"+1 573 459 2260",
    "sg:postcode":"63068",
    "sg:province":"MO",
    "sg:tags":[
        "crop",
        "general"
    ],
    "wof:name":"Morhaus Farm",
    "wof:placetype":"venue"
},
  "geometry": {"coordinates":[-91.206429,38.500834],"type":"Point"}
}