{
  "type": "Feature",
  "properties": {
    "iso:country":"US",
    "sg:address":"123 W Walnut St",
    "sg:city":"Independence",
    "sg:classifiers":[
        {
            "category":"Shopping",
            "subcategory":"Clothing, Apparel, & Fashions",
            "type":"Retail Goods"
        }
    ],
    "sg:phone":"+1 816 461 3859",
    "sg:postcode":"64050",
    "sg:province":"MO",
    "sg:tags":[
        "item",
        "boutique"
    ],
    "wof:name":"Wee Wags Pet Boutique",
    "wof:placetype":"venue"
},
  "geometry": {"coordinates":[-94.41696899999999,39.089907],"type":"Point"}
}