{
  "type": "Feature",
  "properties": {
    "iso:country":"US",
    "sg:address":"14500 N Outer Rd",
    "sg:city":"Chesterfield",
    "sg:classifiers":[
        {
            "category":"Professional",
            "subcategory":"Engineering",
            "type":"Services"
        },
        {
            "category":"Real Estate",
            "subcategory":"Architect",
            "type":"Services"
        }
    ],
    "sg:phone":"+1 314 439 1944",
    "sg:postcode":"63017",
    "sg:province":"MO",
    "sg:tags":[
        "firm",
        "building",
        "consulting",
        "construction",
        "exterior",
        "enclosure"
    ],
    "sg:website":"www.heitmannassoc.com",
    "wof:name":"Heitmann & Associates Inc",
    "wof:placetype":"venue"
},
  "geometry": {"coordinates":[-90.55012600000001,38.651886],"type":"Point"}
}