{
  "type": "Feature",
  "properties": {
    "iso:country":"US",
    "sg:address":"1273 E Republic Rd",
    "sg:city":"Springfield",
    "sg:classifiers":[
        {
            "category":"Retail",
            "subcategory":"Car Wash",
            "type":"Services"
        },
        {
            "category":"Retail",
            "subcategory":"Auto Repair",
            "type":"Services"
        }
    ],
    "sg:phone":"+1 417 889 7878",
    "sg:postcode":"65804",
    "sg:province":"MO",
    "sg:tags":[
        "body",
        "automotive",
        "detail",
        "clean",
        "automobile"
    ],
    "wof:name":"Ming Auto Beauty Center",
    "wof:placetype":"venue"
},
  "geometry": {"coordinates":[-93.276729,37.137692],"type":"Point"}
}