{
  "type": "Feature",
  "properties": {
    "iso:country":"US",
    "sg:address":"2315 E Cynthia Ct",
    "sg:city":"Springfield",
    "sg:classifiers":[
        {
            "category":"Building & Trades",
            "subcategory":"Electrical",
            "type":"Services"
        }
    ],
    "sg:phone":"+1 417 865 8059",
    "sg:postcode":"65802",
    "sg:province":"MO",
    "sg:tags":[
        "electrical",
        "contractor"
    ],
    "wof:name":"Lawrence A Michael",
    "wof:placetype":"venue"
},
  "geometry": {"coordinates":[-93.250049,37.198726],"type":"Point"}
}