{
  "type": "Feature",
  "properties": {
    "iso:country":"US",
    "sg:address":"303 S Hunter St",
    "sg:city":"Versailles",
    "sg:classifiers":[
        {
            "category":"Building & Trades",
            "subcategory":"Construction",
            "type":"Services"
        }
    ],
    "sg:phone":"+1 573 378 5860",
    "sg:postcode":"65084",
    "sg:province":"MO",
    "sg:tags":[
        "siding",
        "contractor"
    ],
    "wof:name":"Bill's Siding & Insulation",
    "wof:placetype":"venue"
},
  "geometry": {"coordinates":[-92.84651599999999,38.429156],"type":"Point"}
}