{
  "type": "Feature",
  "properties": {
    "iso:country":"US",
    "sg:address":"16905 Old Jamestown Rd",
    "sg:city":"Florissant",
    "sg:classifiers":[
        {
            "category":"Wholesale",
            "subcategory":"Scrap",
            "type":"Manufacturing & Wholesale Goods"
        }
    ],
    "sg:phone":"+1 314 741 4284",
    "sg:postcode":"63034",
    "sg:province":"MO",
    "sg:tags":[
        "material"
    ],
    "wof:name":"Mad Auto Wrecking Inc",
    "wof:placetype":"venue"
},
  "geometry": {"coordinates":[-90.258348,38.847937],"type":"Point"}
}