{
  "type": "Feature",
  "properties": {
    "iso:country":"US",
    "sg:address":"W Hwy 76",
    "sg:city":"Branson",
    "sg:classifiers":[
        {
            "category":"Restaurant",
            "type":"Food & Drink"
        }
    ],
    "sg:menulink":"http://www.allmenus.com/mo/branson/184912-baldknobbers/menu/",
    "sg:phone":"+1 417 334 7202",
    "sg:postcode":"65616",
    "sg:province":"MO",
    "sg:tags":[
        "american"
    ],
    "wof:name":"Baldknobbers",
    "wof:placetype":"venue"
},
  "geometry": {"coordinates":[-93.26298199999999,36.641442],"type":"Point"}
}