{
  "type": "Feature",
  "properties": {
    "iso:country":"US",
    "sg:address":"209 W Highway St",
    "sg:city":"Doniphan",
    "sg:classifiers":[
        {
            "category":"Social Services",
            "type":"Services"
        }
    ],
    "sg:phone":"+1 573 996 5424",
    "sg:postcode":"63935",
    "sg:province":"MO",
    "sg:tags":[
        "counseling"
    ],
    "wof:name":"Family Counseling Ctr",
    "wof:placetype":"venue"
},
  "geometry": {"coordinates":[-90.82895000000001,36.625993],"type":"Point"}
}