{
  "type": "Feature",
  "properties": {
    "iso:country":"US",
    "sg:address":"3400 Buttonwood Dr",
    "sg:city":"Columbia",
    "sg:classifiers":[
        {
            "category":"Insurance",
            "subcategory":"Insurance Agent",
            "type":"Services"
        }
    ],
    "sg:phone":"+1 573 256 2221",
    "sg:postcode":"65201",
    "sg:province":"MO",
    "wof:name":"Falco Mike Insurance Agency",
    "wof:placetype":"venue"
},
  "geometry": {"coordinates":[-92.33426900000001,38.91541],"type":"Point"}
}