{
  "type": "Feature",
  "properties": {
    "iso:country":"US",
    "sg:address":"1053 E Broadway St",
    "sg:city":"Bolivar",
    "sg:classifiers":[
        {
            "category":"Insurance",
            "subcategory":"Hazard Insurance",
            "type":"Services"
        }
    ],
    "sg:phone":"+1 417 777 7570",
    "sg:postcode":"65613",
    "sg:province":"MO",
    "sg:tags":[
        "commercial",
        "business"
    ],
    "sg:website":"http://www.capstoneins.com",
    "wof:name":"Banner, Darin - Capstone Insurors",
    "wof:placetype":"venue"
},
  "geometry": {"coordinates":[-93.400238,37.61513],"type":"Point"}
}