{
  "type": "Feature",
  "properties": {
    "iso:country":"US",
    "sg:address":"75 Dogwood Ln",
    "sg:city":"Steelville",
    "sg:classifiers":[
        {
            "category":"Insurance",
            "subcategory":"Insurance Agent",
            "type":"Services"
        }
    ],
    "sg:phone":"+1 573 775 4077",
    "sg:postcode":"65565",
    "sg:province":"MO",
    "wof:name":"Integrity Financial Solutions",
    "wof:placetype":"venue"
},
  "geometry": {"coordinates":[-91.32898900000001,37.977299],"type":"Point"}
}