{
  "type": "Feature",
  "properties": {
    "iso:country":"US",
    "sg:address":"15855 Hardin Ln",
    "sg:city":"St Robert",
    "sg:classifiers":[
        {
            "category":"Retail",
            "subcategory":"Animal Services",
            "type":"Services"
        }
    ],
    "sg:phone":"+1 573 336 4138",
    "sg:postcode":"65584",
    "sg:province":"MO",
    "sg:tags":[
        "training",
        "dog"
    ],
    "wof:name":"All-Breed Canine Behavioral",
    "wof:placetype":"venue"
},
  "geometry": {"coordinates":[-92.129062,37.831228],"type":"Point"}
}