{
  "type": "Feature",
  "properties": {
    "iso:country":"US",
    "sg:address":"6115 Bradley Manor Pl",
    "sg:city":"Saint Louis",
    "sg:classifiers":[
        {
            "category":"Retail",
            "subcategory":"Auto Repair",
            "type":"Services"
        }
    ],
    "sg:phone":"+1 314 487 2280",
    "sg:postcode":"63129",
    "sg:province":"MO",
    "sg:tags":[
        "general"
    ],
    "wof:name":"Auto Care Engineers",
    "wof:placetype":"venue"
},
  "geometry": {"coordinates":[-90.34716299999999,38.458731],"type":"Point"}
}