{
  "type": "Feature",
  "properties": {
    "iso:country":"US",
    "sg:address":"4440 Deer Valley Dr",
    "sg:city":"Florissant",
    "sg:classifiers":[
        {
            "category":"Social Services",
            "subcategory":"Child Care",
            "type":"Services"
        }
    ],
    "sg:phone":"+1 314 438 1516",
    "sg:postcode":"63034",
    "sg:province":"MO",
    "sg:tags":[
        "day"
    ],
    "wof:name":"Pennington Playtime",
    "wof:placetype":"venue"
},
  "geometry": {"coordinates":[-90.270472,38.821727],"type":"Point"}
}