{
  "type": "Feature",
  "properties": {
    "iso:country":"US",
    "sg:address":"124 US Hwy 169",
    "sg:city":"Smithville",
    "sg:classifiers":[
        {
            "category":"Autos & Motor Vehicles",
            "subcategory":"Fuel & Gas Station",
            "type":"Retail Goods"
        }
    ],
    "sg:phone":"+1 816 532 4259",
    "sg:postcode":"64089",
    "sg:province":"MO",
    "sg:tags":[
        "oil"
    ],
    "wof:name":"Shell",
    "wof:placetype":"venue"
},
  "geometry": {"coordinates":[-94.584819,39.387728],"type":"Point"}
}