{
  "type": "Feature",
  "properties": {
    "iso:country":"US",
    "sg:address":"585 State Hwy A",
    "sg:city":"Moberly",
    "sg:phone":"+1 660 263 4196",
    "sg:postcode":"65231",
    "sg:province":"MO",
    "sg:tags":[
        "farm",
        "field",
        "crop"
    ],
    "wof:name":"Roscoe Turner",
    "wof:placetype":"venue"
},
  "geometry": {"coordinates":[-91.77523100000001,39.039042],"type":"Point"}
}