{
  "type": "Feature",
  "properties": {
    "iso:country":"US",
    "sg:address":"100 Piper Hills Dr",
    "sg:city":"St Peters",
    "sg:classifiers":[
        {
            "category":"Health Services",
            "subcategory":"Doctor",
            "type":"Services"
        }
    ],
    "sg:phone":"+1 636 936 8777",
    "sg:postcode":"63376",
    "sg:province":"MO",
    "sg:tags":[
        "physician",
        "surgeon"
    ],
    "wof:name":"Womens Care Specialists",
    "wof:placetype":"venue"
},
  "geometry": {"coordinates":[-90.58814,38.79474],"type":"Point"}
}