{
  "type": "Feature",
  "properties": {
    "iso:country":"US",
    "sg:address":"5449 State Hwy Pp",
    "sg:city":"Poplar Bluff",
    "sg:classifiers":[
        {
            "category":"Farming",
            "subcategory":"Livestock Farm",
            "type":"Manufacturing & Wholesale Goods"
        }
    ],
    "sg:phone":"+1 573 785 6180",
    "sg:postcode":"63901",
    "sg:province":"MO",
    "sg:tags":[
        "beef",
        "feedlot",
        "cattle"
    ],
    "wof:name":"West Livestock",
    "wof:placetype":"venue"
},
  "geometry": {"coordinates":[-90.47917700000001,36.778715],"type":"Point"}
}