{
  "type": "Feature",
  "properties": {
    "iso:country":"US",
    "sg:address":"552 Golfwood Dr",
    "sg:city":"Ballwin",
    "sg:classifiers":[
        {
            "category":"Professional",
            "type":"Services"
        }
    ],
    "sg:phone":"+1 636 527 0446",
    "sg:postcode":"63021",
    "sg:province":"MO",
    "sg:tags":[
        "establishment"
    ],
    "wof:name":"Parex Inc",
    "wof:placetype":"venue"
},
  "geometry": {"coordinates":[-90.549271,38.579494],"type":"Point"}
}