{
  "type": "Feature",
  "properties": {
    "iso:country":"US",
    "sg:address":"4914 Gravois Ave",
    "sg:city":"Saint Louis",
    "sg:classifiers":[
        {
            "category":"Banks & Credit Unions",
            "subcategory":"Bank",
            "type":"Services"
        }
    ],
    "sg:phone":"+1 314 481 3900",
    "sg:postcode":"63116",
    "sg:province":"MO",
    "sg:tags":[
        "saving",
        "institution"
    ],
    "sg:website":"www.southerncommercialbankstl.com",
    "wof:name":"Southern Commercial Bank",
    "wof:placetype":"venue"
},
  "geometry": {"coordinates":[-90.26709700000001,38.581501],"type":"Point"}
}