{
  "type": "Feature",
  "properties": {
    "iso:country":"US",
    "sg:address":"201 Cherry St",
    "sg:city":"Columbia",
    "sg:classifiers":[
        {
            "category":"Organizations",
            "subcategory":"Non-profit Organization",
            "type":"Services"
        }
    ],
    "sg:phone":"+1 573 443 0166",
    "sg:postcode":"65203",
    "sg:province":"MO",
    "wof:name":"Islamic American Relief Agency",
    "wof:placetype":"venue"
},
  "geometry": {"coordinates":[-92.33413899999999,38.95062],"type":"Point"}
}