{
  "type": "Feature",
  "properties": {
    "iso:country":"US",
    "sg:address":"5402 E 233rd St",
    "sg:city":"Peculiar",
    "sg:classifiers":[
        {
            "category":"Restaurant",
            "type":"Food & Drink"
        }
    ],
    "sg:phone":"+1 816 618 3427",
    "sg:postcode":"64078",
    "sg:province":"MO",
    "sg:tags":[
        "seafood"
    ],
    "wof:name":"Mad Jacks",
    "wof:placetype":"venue"
},
  "geometry": {"coordinates":[-94.53957800000001,38.70227],"type":"Point"}
}