{
  "type": "Feature",
  "properties": {
    "iso:country":"US",
    "sg:address":"15820 NE 178th St",
    "sg:city":"Holt",
    "sg:classifiers":[
        {
            "category":"Wholesale",
            "subcategory":"Drugs",
            "type":"Manufacturing & Wholesale Goods"
        }
    ],
    "sg:phone":"+1 816 320 3716",
    "sg:postcode":"64048",
    "sg:province":"MO",
    "wof:name":"Bach Tasha",
    "wof:placetype":"venue"
},
  "geometry": {"coordinates":[-94.38862399999999,39.415402],"type":"Point"}
}