{
  "type": "Feature",
  "properties": {
    "iso:country":"US",
    "sg:address":"4651 Roanoke Pkwy",
    "sg:city":"Kansas City",
    "sg:classifiers":[
        {
            "category":"Cinema",
            "subcategory":"Movie Rental",
            "type":"Entertainment"
        }
    ],
    "sg:phone":"+1 816 531 8866",
    "sg:postcode":"64112",
    "sg:province":"MO",
    "sg:tags":[
        "video",
        "tape"
    ],
    "wof:name":"Video Post Duplication",
    "wof:placetype":"venue"
},
  "geometry": {"coordinates":[-94.59783299999999,39.043082],"type":"Point"}
}