{
  "type": "Feature",
  "properties": {
    "addr:full":"901 E Ohio St Clinton MO 64735",
    "addr:housenumber":"901",
    "addr:postcode":"64735",
    "addr:street":"E Ohio St",
    "iso:country":"US",
    "sg:address":"901 E Ohio St",
    "sg:city":"Clinton",
    "sg:classifiers":[
        {
            "category":"Insurance",
            "subcategory":"Insurance Agent",
            "type":"Services"
        }
    ],
    "sg:phone":"+1 660 885 5575",
    "sg:postcode":"64735",
    "sg:province":"MO",
    "wof:name":"American Family Insurance",
    "wof:placetype":"venue"
},
  "geometry": {"coordinates":[-93.761197,38.366488],"type":"Point"}
}