{
  "type": "Feature",
  "properties": {
    "iso:country":"US",
    "sg:address":"13937 State Hwy 32",
    "sg:city":"Ste Genevieve",
    "sg:classifiers":[
        {
            "category":"Manufacturing",
            "subcategory":"Wood Products",
            "type":"Manufacturing & Wholesale Goods"
        }
    ],
    "sg:phone":"+1 573 883 3611",
    "sg:postcode":"63670",
    "sg:province":"MO",
    "sg:tags":[
        "pallet",
        "skid"
    ],
    "wof:name":"Schwartz Saw Mill",
    "wof:placetype":"venue"
},
  "geometry": {"coordinates":[-90.202853,37.909132],"type":"Point"}
}