{
  "type": "Feature",
  "properties": {
    "iso:country":"US",
    "sg:address":"423 W Karsch Blvd",
    "sg:city":"Farmington",
    "sg:classifiers":[
        {
            "category":"Personal",
            "subcategory":"Massage",
            "type":"Services"
        },
        {
            "category":"Personal",
            "subcategory":"Beauty Salon",
            "type":"Services"
        },
        {
            "category":"Personal",
            "subcategory":"Tanning Parlor",
            "type":"Services"
        },
        {
            "category":"Personal",
            "subcategory":"Day Spa",
            "type":"Services"
        },
        {
            "category":"Personal",
            "subcategory":"Nail Salon",
            "type":"Services"
        }
    ],
    "sg:phone":"+1 573 756 1327",
    "sg:postcode":"63640",
    "sg:province":"MO",
    "sg:tags":[
        "therapist"
    ],
    "sg:website":"http://www.theboulevardspa.com",
    "wof:name":"The Boulevard",
    "wof:placetype":"venue"
},
  "geometry": {"coordinates":[-90.424672,37.788158],"type":"Point"}
}