{
  "type": "Feature",
  "properties": {
    "iso:country":"US",
    "sg:address":"3660 S Geyer Rd",
    "sg:city":"Saint Louis",
    "sg:classifiers":[
        {
            "category":"Real Estate",
            "subcategory":"Real Estate Agent",
            "type":"Services"
        }
    ],
    "sg:phone":"+1 314 984 8911",
    "sg:postcode":"63127",
    "sg:province":"MO",
    "wof:name":"Real Estate Show",
    "wof:placetype":"venue"
},
  "geometry": {"coordinates":[-90.416319,38.553581],"type":"Point"}
}