{
  "type": "Feature",
  "properties": {
    "iso:country":"US",
    "sg:address":"300 Tanger Blvd Ste 303",
    "sg:city":"Branson",
    "sg:classifiers":[
        {
            "category":"Shopping",
            "subcategory":"Jewelry",
            "type":"Retail Goods"
        },
        {
            "category":"Manufacturing",
            "subcategory":"Jewelry",
            "type":"Manufacturing & Wholesale Goods"
        }
    ],
    "sg:phone":"+1 417 336 3899",
    "sg:postcode":"65616",
    "sg:province":"MO",
    "sg:tags":[
        "stone",
        "designer",
        "semi-precious",
        "precious",
        "jeweler"
    ],
    "sg:website":"http://www.zales.com",
    "wof:name":"Zales Jewelers Outlet",
    "wof:placetype":"venue"
},
  "geometry": {"coordinates":[-93.264456,36.643578],"type":"Point"}
}