{
  "type": "Feature",
  "properties": {
    "iso:country":"US",
    "sg:address":"3863 Tall Oaks Dr",
    "sg:city":"Bland",
    "sg:classifiers":[
        {
            "category":"Building & Trades",
            "subcategory":"Construction",
            "type":"Services"
        }
    ],
    "sg:phone":"+1 573 646 3684",
    "sg:postcode":"65014",
    "sg:province":"MO",
    "sg:tags":[
        "contractor"
    ],
    "wof:name":"Bill Krause Foundations Inc",
    "wof:placetype":"venue"
},
  "geometry": {"coordinates":[-91.60410299999999,38.285352],"type":"Point"}
}