{
  "type": "Feature",
  "properties": {
    "iso:country":"US",
    "sg:address":"1120 S 6th St",
    "sg:city":"St Louis",
    "sg:classifiers":[
        {
            "category":"Professional",
            "subcategory":"Engineering",
            "type":"Services"
        },
        {
            "category":"Professional",
            "subcategory":"Research",
            "type":"Services"
        }
    ],
    "sg:phone":"+1 314 678 1398",
    "sg:postcode":"63104",
    "sg:province":"MO",
    "sg:tags":[
        "environmental",
        "ecological"
    ],
    "sg:website":"www.react-env.com",
    "wof:name":"React Environmental Engineers",
    "wof:placetype":"venue"
},
  "geometry": {"coordinates":[-90.195211,38.61544],"type":"Point"}
}