{
  "type": "Feature",
  "properties": {
    "iso:country":"US",
    "sg:address":"3220 Greenwood Blvd",
    "sg:city":"St Louis",
    "sg:classifiers":[
        {
            "category":"Building & Trades",
            "subcategory":"Electrical",
            "type":"Services"
        }
    ],
    "sg:phone":"+1 314 647 5600",
    "sg:postcode":"63143",
    "sg:province":"MO",
    "sg:tags":[
        "electric",
        "contractor"
    ],
    "wof:name":"AAA Electrical Contractors",
    "wof:placetype":"venue"
},
  "geometry": {"coordinates":[-90.316216,38.608385],"type":"Point"}
}