{
  "type": "Feature",
  "properties": {
    "iso:country":"US",
    "sg:address":"7181 N Drake Ln",
    "sg:city":"Rocheport",
    "sg:classifiers":[
        {
            "category":"Wholesale",
            "subcategory":"Auto Parts",
            "type":"Manufacturing & Wholesale Goods"
        }
    ],
    "sg:phone":"+1 573 874 7181",
    "sg:postcode":"65279",
    "sg:province":"MO",
    "sg:tags":[
        "repair",
        "general",
        "automotive"
    ],
    "wof:name":"Bodeans Service Inc",
    "wof:placetype":"venue"
},
  "geometry": {"coordinates":[-92.526083,39.03982],"type":"Point"}
}