{
  "type": "Feature",
  "properties": {
    "iso:country":"US",
    "sg:address":"1423 Autumn Leaf Dr",
    "sg:city":"Ballwin",
    "sg:classifiers":[
        {
            "category":"Insurance",
            "subcategory":"Insurance Agent",
            "type":"Services"
        }
    ],
    "sg:phone":"+1 636 225 8778",
    "sg:postcode":"63021",
    "sg:province":"MO",
    "wof:name":"Innovative Financial Services",
    "wof:placetype":"venue"
},
  "geometry": {"coordinates":[-90.50412300000001,38.56379],"type":"Point"}
}