{
  "type": "Feature",
  "properties": {
    "iso:country":"US",
    "sg:address":"678 Stonehill Ln",
    "sg:city":"Altenburg",
    "sg:classifiers":[
        {
            "category":"Farming",
            "subcategory":"Livestock Farm",
            "type":"Manufacturing & Wholesale Goods"
        }
    ],
    "sg:phone":"+1 573 824 5434",
    "sg:postcode":"63748",
    "sg:province":"MO",
    "sg:tags":[
        "feedlot",
        "field",
        "crop",
        "beef",
        "cattle"
    ],
    "wof:name":"Harold Schilling",
    "wof:placetype":"venue"
},
  "geometry": {"coordinates":[-89.58249000000001,37.655032],"type":"Point"}
}