{
  "type": "Feature",
  "properties": {
    "iso:country":"US",
    "sg:address":"21224 Hwy Ww",
    "sg:city":"Bowling Green",
    "sg:classifiers":[
        {
            "category":"Organizations",
            "subcategory":"Religious Organization",
            "type":"Services"
        }
    ],
    "sg:phone":"+1 573 324 5065",
    "sg:postcode":"63334",
    "sg:province":"MO",
    "sg:tags":[
        "church"
    ],
    "wof:name":"Edgewood Baptist Church",
    "wof:placetype":"venue"
},
  "geometry": {"coordinates":[-91.080285,39.271912],"type":"Point"}
}