{
  "type": "Feature",
  "properties": {
    "iso:country":"US",
    "sg:address":"101 S Hanley Rd",
    "sg:city":"St Louis",
    "sg:classifiers":[
        {
            "category":"Banks & Credit Unions",
            "subcategory":"Investment Brokerage",
            "type":"Services"
        }
    ],
    "sg:phone":"+1 314 746 1600",
    "sg:postcode":"63105",
    "sg:province":"MO",
    "sg:tags":[
        "advisory",
        "financial"
    ],
    "wof:name":"Hammond Associates",
    "wof:placetype":"venue"
},
  "geometry": {"coordinates":[-90.334101,38.649863],"type":"Point"}
}