{
  "type": "Feature",
  "properties": {
    "addr:full":"19 W 1st St Eureka MO 63025",
    "addr:housenumber":"19",
    "addr:postcode":"63025",
    "addr:street":"W 1St St",
    "iso:country":"US",
    "sg:address":"19 W 1st St",
    "sg:city":"Eureka",
    "sg:classifiers":[
        {
            "category":"Organizations",
            "subcategory":"Community Association",
            "type":"Services"
        }
    ],
    "sg:phone":"+1 636 938 6720",
    "sg:postcode":"63025",
    "sg:province":"MO",
    "sg:tags":[
        "fraternal"
    ],
    "wof:name":"Elks Lodge",
    "wof:placetype":"venue"
},
  "geometry": {"coordinates":[-90.62909399999999,38.503333],"type":"Point"}
}