{
  "type": "Feature",
  "properties": {
    "iso:country":"US",
    "sg:address":"1578 Woodlake Dr",
    "sg:city":"Chesterfield",
    "sg:classifiers":[
        {
            "category":"Banks & Credit Unions",
            "subcategory":"Bank",
            "type":"Services"
        }
    ],
    "sg:phone":"+1 314 878 7272",
    "sg:postcode":"63017",
    "sg:province":"MO",
    "sg:tags":[
        "broker",
        "mortgage"
    ],
    "wof:name":"Elizabeth Fay Mortgage",
    "wof:placetype":"venue"
},
  "geometry": {"coordinates":[-90.516989,38.642075],"type":"Point"}
}