{
  "type": "Feature",
  "properties": {
    "addr:full":"4525 Central School Rd St Charles MO 63304",
    "addr:housenumber":"4525",
    "addr:postcode":"63304",
    "addr:street":"School Rd",
    "iso:country":"US",
    "sg:address":"4525 Central School Rd",
    "sg:city":"St Charles",
    "sg:classifiers":[
        {
            "category":"Education",
            "subcategory":"School",
            "type":"Public Place"
        }
    ],
    "sg:phone":"+1 636 441 5210",
    "sg:postcode":"63304",
    "sg:province":"MO",
    "wof:name":"Central Elementary School",
    "wof:placetype":"venue"
},
  "geometry": {"coordinates":[-90.614975,38.743067],"type":"Point"}
}