{
  "type": "Feature",
  "properties": {
    "iso:country":"US",
    "sg:address":"5841 State Hwy 19",
    "sg:city":"Cuba",
    "sg:classifiers":[
        {
            "category":"Restaurant",
            "type":"Food & Drink"
        }
    ],
    "sg:phone":"+1 573 885 0043",
    "sg:postcode":"65453",
    "sg:province":"MO",
    "wof:name":"Huddle House",
    "wof:placetype":"venue"
},
  "geometry": {"coordinates":[-91.408666,38.076295],"type":"Point"}
}