{
  "type": "Feature",
  "properties": {
    "iso:country":"US",
    "sg:address":"1100 N Morley St",
    "sg:city":"Moberly",
    "sg:classifiers":[
        {
            "category":"Banks & Credit Unions",
            "subcategory":"Bank",
            "type":"Services"
        }
    ],
    "sg:phone":"+1 660 263 0066",
    "sg:postcode":"65270",
    "sg:province":"MO",
    "sg:tags":[
        "cashing",
        "institution",
        "business",
        "check"
    ],
    "wof:name":"Payroll Advance",
    "wof:placetype":"venue"
},
  "geometry": {"coordinates":[-92.433189,39.430612],"type":"Point"}
}