{
  "type": "Feature",
  "properties": {
    "iso:country":"US",
    "sg:address":"610 State Hwy 80",
    "sg:city":"East Prairie",
    "sg:classifiers":[
        {
            "category":"Retail",
            "subcategory":"Auto Repair",
            "type":"Services"
        }
    ],
    "sg:phone":"+1 573 649 3880",
    "sg:postcode":"63845",
    "sg:province":"MO",
    "sg:tags":[
        "general"
    ],
    "wof:name":"Nunns Auto Service",
    "wof:placetype":"venue"
},
  "geometry": {"coordinates":[-89.375507,36.775649],"type":"Point"}
}