{
  "type": "Feature",
  "properties": {
    "iso:country":"US",
    "sg:address":"9629 Olive Blvd",
    "sg:city":"St Louis",
    "sg:classifiers":[
        {
            "category":"Banks & Credit Unions",
            "subcategory":"Bank",
            "type":"Services"
        }
    ],
    "sg:phone":"+1 314 994 9100",
    "sg:postcode":"63132",
    "sg:province":"MO",
    "sg:tags":[
        "state",
        "commercial"
    ],
    "wof:name":"Bank of America",
    "wof:placetype":"venue"
},
  "geometry": {"coordinates":[-90.389697,38.673048],"type":"Point"}
}