{
  "type": "Feature",
  "properties": {
    "iso:country":"US",
    "sg:address":"511 College St",
    "sg:city":"Clarence",
    "sg:classifiers":[
        {
            "category":"Personal",
            "subcategory":"Beauty Salon",
            "type":"Services"
        }
    ],
    "sg:phone":"+1 660 699 3546",
    "sg:postcode":"63437",
    "sg:province":"MO",
    "wof:name":"Beckys Beauty Salon",
    "wof:placetype":"venue"
},
  "geometry": {"coordinates":[-92.267183,39.738741],"type":"Point"}
}