{
  "type": "Feature",
  "properties": {
    "iso:country":"US",
    "sg:address":"701 Ridgeside Dr",
    "sg:city":"Ballwin",
    "sg:classifiers":[
        {
            "category":"Food & Beverages",
            "subcategory":"Groceries & Convenience Stores",
            "type":"Retail Goods"
        }
    ],
    "sg:phone":"+1 636 256 0322",
    "sg:postcode":"63021",
    "sg:province":"MO",
    "wof:name":"Food Packaging Broker",
    "wof:placetype":"venue"
},
  "geometry": {"coordinates":[-90.521461,38.563599],"type":"Point"}
}