{
  "type": "Feature",
  "properties": {
    "iso:country":"US",
    "sg:address":"406 W Lexington St",
    "sg:city":"Richmond",
    "sg:classifiers":[
        {
            "category":"Retail",
            "subcategory":"Auto Repair",
            "type":"Services"
        }
    ],
    "sg:phone":"+1 816 776 3476",
    "sg:postcode":"64085",
    "sg:province":"MO",
    "sg:tags":[
        "body",
        "automobile",
        "painting"
    ],
    "wof:name":"Allnutt Brothers",
    "wof:placetype":"venue"
},
  "geometry": {"coordinates":[-93.982274,39.276875],"type":"Point"}
}