{
  "type": "Feature",
  "properties": {
    "iso:country":"US",
    "sg:address":"18 Lakemont Dr",
    "sg:city":"Saint Charles",
    "sg:classifiers":[
        {
            "category":"Social Services",
            "type":"Services"
        }
    ],
    "sg:phone":"+1 636 441 3656",
    "sg:postcode":"63304",
    "sg:province":"MO",
    "wof:name":"Counseling For Women",
    "wof:placetype":"venue"
},
  "geometry": {"coordinates":[-90.599378,38.760111],"type":"Point"}
}