{
  "type": "Feature",
  "properties": {
    "iso:country":"US",
    "sg:address":"117 W Hwy 22",
    "sg:city":"Centralia",
    "sg:classifiers":[
        {
            "category":"Food & Beverages",
            "subcategory":"Groceries & Convenience Stores",
            "type":"Retail Goods"
        }
    ],
    "sg:phone":"+1 573 682 2222",
    "sg:postcode":"65240",
    "sg:province":"MO",
    "sg:tags":[
        "station",
        "gasoline"
    ],
    "wof:name":"Break Time 3012",
    "wof:placetype":"venue"
},
  "geometry": {"coordinates":[-92.13672,39.219057],"type":"Point"}
}