{
  "type": "Feature",
  "properties": {
    "iso:country":"US",
    "sg:address":"18405 S Gray Dr",
    "sg:city":"Pleasant Hill",
    "sg:classifiers":[
        {
            "category":"Building & Trades",
            "subcategory":"Construction",
            "type":"Services"
        }
    ],
    "sg:phone":"+1 816 540 2297",
    "sg:postcode":"64080",
    "sg:province":"MO",
    "sg:tags":[
        "excavation",
        "contractor"
    ],
    "wof:name":"Gray Co",
    "wof:placetype":"venue"
},
  "geometry": {"coordinates":[-94.337171,38.783411],"type":"Point"}
}