{
  "type": "Feature",
  "properties": {
    "iso:country":"US",
    "sg:address":"1510 Prospect Ave",
    "sg:city":"Kansas City",
    "sg:classifiers":[
        {
            "category":"Wholesale",
            "subcategory":"Machinery & Supplies",
            "type":"Manufacturing & Wholesale Goods"
        }
    ],
    "sg:phone":"+1 816 241 9742",
    "sg:postcode":"64127",
    "sg:province":"MO",
    "sg:tags":[
        "fire",
        "hose"
    ],
    "wof:name":"American Fire & Security",
    "wof:placetype":"venue"
},
  "geometry": {"coordinates":[-94.551743,39.093688],"type":"Point"}
}