{
  "type": "Feature",
  "properties": {
    "iso:country":"US",
    "sg:address":"401 S Market St",
    "sg:city":"Chamois",
    "sg:classifiers":[
        {
            "category":"Shopping",
            "subcategory":"Gifts & Souvenirs",
            "type":"Retail Goods"
        }
    ],
    "sg:phone":"+1 573 763 5131",
    "sg:postcode":"65024",
    "sg:province":"MO",
    "wof:name":"Just Around Corner Gift Shop",
    "wof:placetype":"venue"
},
  "geometry": {"coordinates":[-91.76982700000001,38.673235],"type":"Point"}
}