{
  "type": "Feature",
  "properties": {
    "iso:country":"US",
    "sg:address":"3628 S Campbell Ave",
    "sg:city":"Springfield",
    "sg:classifiers":[
        {
            "category":"Utilities",
            "subcategory":"Mobile Phone",
            "type":"Services"
        },
        {
            "category":"Coffee & Tea",
            "type":"Food & Drink"
        }
    ],
    "sg:phone":"+1 417 885 7069",
    "sg:postcode":"65807",
    "sg:province":"MO",
    "sg:tags":[
        "shop",
        "restaurant",
        "espresso",
        "hotspot",
        "wi-fi"
    ],
    "sg:website":"http://www.starbuckscoffee.com",
    "wof:name":"Starbucks Coffee",
    "wof:placetype":"venue"
},
  "geometry": {"coordinates":[-93.29592,37.147797],"type":"Point"}
}