{
  "type": "Feature",
  "properties": {
    "iso:country":"US",
    "sg:address":"1111 S Maguire St",
    "sg:city":"Warrensburg",
    "sg:classifiers":[
        {
            "category":"Autos & Motor Vehicles",
            "subcategory":"Auto Supplies",
            "type":"Retail Goods"
        }
    ],
    "sg:phone":"+1 660 747 2272",
    "sg:postcode":"64093",
    "sg:province":"MO",
    "sg:tags":[
        "automobile",
        "part"
    ],
    "wof:name":"A Castro Supply",
    "wof:placetype":"venue"
},
  "geometry": {"coordinates":[-93.736313,38.747524],"type":"Point"}
}