{
  "type": "Feature",
  "properties": {
    "iso:country":"US",
    "sg:address":"7238 Wornall Rd",
    "sg:city":"Kansas City",
    "sg:classifiers":[
        {
            "category":"Retail",
            "subcategory":"Animal Services",
            "type":"Services"
        }
    ],
    "sg:phone":"+1 816 333 2522",
    "sg:postcode":"64114",
    "sg:province":"MO",
    "sg:tags":[
        "pet",
        "grooming",
        "washing"
    ],
    "wof:name":"Pampered Paws Grooming",
    "wof:placetype":"venue"
},
  "geometry": {"coordinates":[-94.594099,38.996672],"type":"Point"}
}