{
  "type": "Feature",
  "properties": {
    "iso:country":"US",
    "sg:address":"2136 E Pythian St",
    "sg:city":"Springfield",
    "sg:classifiers":[
        {
            "category":"Building & Trades",
            "subcategory":"Plumbing",
            "type":"Services"
        }
    ],
    "sg:phone":"+1 417 865 3583",
    "sg:postcode":"65802",
    "sg:province":"MO",
    "sg:tags":[
        "heating",
        "contractor"
    ],
    "wof:name":"Rick's Heating & Air",
    "wof:placetype":"venue"
},
  "geometry": {"coordinates":[-93.253379,37.217865],"type":"Point"}
}