{
  "type": "Feature",
  "properties": {
    "iso:country":"US",
    "sg:address":"2638 Hwy 109",
    "sg:city":"Grover",
    "sg:classifiers":[
        {
            "category":"Real Estate",
            "subcategory":"Real Estate Agent",
            "type":"Services"
        }
    ],
    "sg:phone":"+1 636 273 0083",
    "sg:postcode":"63040",
    "sg:province":"MO",
    "wof:name":"Mc Clain Properties",
    "wof:placetype":"venue"
},
  "geometry": {"coordinates":[-90.64483799999999,38.575664],"type":"Point"}
}