{
  "type": "Feature",
  "properties": {
    "iso:country":"US",
    "sg:address":"7245 Maryland Ave",
    "sg:city":"Saint Louis",
    "sg:classifiers":[
        {
            "category":"Professional",
            "type":"Services"
        }
    ],
    "sg:phone":"+1 314 725 2122",
    "sg:postcode":"63130",
    "sg:province":"MO",
    "wof:name":"Charles A Redd PC",
    "wof:placetype":"venue"
},
  "geometry": {"coordinates":[-90.32312899999999,38.650267],"type":"Point"}
}