{
  "type": "Feature",
  "properties": {
    "iso:country":"US",
    "sg:address":"2715 N Sarah St",
    "sg:city":"Saint Louis",
    "sg:classifiers":[
        {
            "category":"Organizations",
            "subcategory":"Religious Organization",
            "type":"Services"
        }
    ],
    "sg:phone":"+1 314 531 6443",
    "sg:postcode":"63113",
    "sg:province":"MO",
    "sg:tags":[
        "church"
    ],
    "wof:name":"St Matthew the Apostle Catholic Church",
    "wof:placetype":"venue"
},
  "geometry": {"coordinates":[-90.232697,38.6586],"type":"Point"}
}