{
  "type": "Feature",
  "properties": {
    "iso:country":"US",
    "sg:address":"2491 Forest Shadows Dr",
    "sg:city":"Saint Louis",
    "sg:classifiers":[
        {
            "category":"Manufacturing",
            "subcategory":"Toys & Sporting Goods",
            "type":"Manufacturing & Wholesale Goods"
        }
    ],
    "sg:phone":"+1 314 741 4771",
    "sg:postcode":"63136",
    "sg:province":"MO",
    "sg:tags":[
        "mfg"
    ],
    "wof:name":"Angies Place",
    "wof:placetype":"venue"
},
  "geometry": {"coordinates":[-90.251234,38.77591],"type":"Point"}
}