{
  "type": "Feature",
  "properties": {
    "iso:country":"US",
    "sg:address":"5310 N Euclid Ave",
    "sg:city":"St Louis",
    "sg:classifiers":[
        {
            "category":"Health Services",
            "subcategory":"Nursing And Care Facility",
            "type":"Services"
        }
    ],
    "sg:phone":"+1 314 382 3570",
    "sg:postcode":"63115",
    "sg:province":"MO",
    "sg:tags":[
        "home",
        "retirement",
        "community"
    ],
    "wof:name":"Euclid Senior Developement Plz",
    "wof:placetype":"venue"
},
  "geometry": {"coordinates":[-90.239041,38.68665],"type":"Point"}
}