{
  "type": "Feature",
  "properties": {
    "iso:country":"US",
    "sg:address":"1522 Porter Wagoner Blvd",
    "sg:city":"West Plains",
    "sg:classifiers":[
        {
            "category":"Shopping",
            "subcategory":"Optical Goods",
            "type":"Retail Goods"
        }
    ],
    "sg:phone":"+1 417 256 6625",
    "sg:postcode":"65775",
    "sg:province":"MO",
    "wof:name":"Optical Shoppe",
    "wof:placetype":"venue"
},
  "geometry": {"coordinates":[-91.8724,36.743617],"type":"Point"}
}