{
  "type": "Feature",
  "properties": {
    "iso:country":"US",
    "sg:address":"213 Kelly St",
    "sg:city":"Dexter",
    "sg:classifiers":[
        {
            "category":"Insurance",
            "subcategory":"Insurance Agent",
            "type":"Services"
        }
    ],
    "sg:phone":"+1 573 624 1896",
    "sg:postcode":"63841",
    "sg:province":"MO",
    "wof:name":"Reid Adjusting Service",
    "wof:placetype":"venue"
},
  "geometry": {"coordinates":[-89.97686,36.791666],"type":"Point"}
}