{
  "type": "Feature",
  "properties": {
    "iso:country":"US",
    "sg:address":"921 1st St",
    "sg:city":"Kennett",
    "sg:classifiers":[
        {
            "category":"Retail",
            "subcategory":"Auto Repair",
            "type":"Services"
        }
    ],
    "sg:phone":"+1 573 888 2858",
    "sg:postcode":"63857",
    "sg:province":"MO",
    "sg:tags":[
        "automotive",
        "general"
    ],
    "wof:name":"McMahons Auto & Diesel Repair",
    "wof:placetype":"venue"
},
  "geometry": {"coordinates":[-90.047488,36.236499],"type":"Point"}
}