{
  "type": "Feature",
  "properties": {
    "iso:country":"US",
    "sg:address":"23610 Cleveland Ave",
    "sg:city":"Cleveland",
    "sg:classifiers":[
        {
            "category":"Place Of Worship",
            "type":"Public Place"
        }
    ],
    "sg:phone":"+1 816 658 3957",
    "sg:postcode":"64734",
    "sg:province":"MO",
    "sg:tags":[
        "church"
    ],
    "wof:name":"Temple B'nai Jehudah Retreat",
    "wof:placetype":"venue"
},
  "geometry": {"coordinates":[-94.554762,38.693122],"type":"Point"}
}