{
  "type": "Feature",
  "properties": {
    "iso:country":"US",
    "sg:address":"2925 W Republic Rd",
    "sg:city":"Springfield",
    "sg:classifiers":[
        {
            "category":"Personal",
            "subcategory":"Massage",
            "type":"Services"
        },
        {
            "category":"Personal",
            "subcategory":"Beauty Salon",
            "type":"Services"
        },
        {
            "category":"Personal",
            "subcategory":"Day Spa",
            "type":"Services"
        },
        {
            "category":"Personal",
            "subcategory":"Skin Care",
            "type":"Services"
        },
        {
            "category":"Personal",
            "subcategory":"Nail Salon",
            "type":"Services"
        }
    ],
    "sg:phone":"+1 417 889 1500",
    "sg:postcode":"65807",
    "sg:province":"MO",
    "sg:tags":[
        "therapist"
    ],
    "sg:website":"http://www.elitestylesalonandspa.com",
    "wof:name":"Elite Style Salon & Spa",
    "wof:placetype":"venue"
},
  "geometry": {"coordinates":[-93.337088,37.138442],"type":"Point"}
}