{
  "type": "Feature",
  "properties": {
    "iso:country":"US",
    "sg:address":"2570 Bradley Beach Rd",
    "sg:city":"Arnold",
    "sg:classifiers":[
        {
            "category":"Building & Trades",
            "subcategory":"Construction",
            "type":"Services"
        }
    ],
    "sg:phone":"+1 636 282 0085",
    "sg:postcode":"63010",
    "sg:province":"MO",
    "sg:tags":[
        "house"
    ],
    "wof:name":"Goodman Brothers Construction",
    "wof:placetype":"venue"
},
  "geometry": {"coordinates":[-90.340091,38.449933],"type":"Point"}
}