{
  "type": "Feature",
  "properties": {
    "iso:country":"US",
    "sg:address":"Forsyth & Skinker",
    "sg:city":"Saint Louis",
    "sg:classifiers":[
        {
            "category":"Sports & Exercise",
            "subcategory":"Gym",
            "type":"Entertainment"
        }
    ],
    "sg:phone":"+1 314 935 5010",
    "sg:postcode":"63130",
    "sg:province":"MO",
    "sg:tags":[
        "trainer"
    ],
    "wof:name":"YWCA of Metropolitan St Louis",
    "wof:placetype":"venue"
},
  "geometry": {"coordinates":[-90.324501,38.6637],"type":"Point"}
}