{
  "type": "Feature",
  "properties": {
    "iso:country":"US",
    "sg:address":"3030 S Grand Blvd",
    "sg:city":"St Louis",
    "sg:classifiers":[
        {
            "category":"Professional",
            "subcategory":"Lawyer & Legal Services",
            "type":"Services"
        }
    ],
    "sg:phone":"+1 314 773 8635",
    "sg:postcode":"63118",
    "sg:province":"MO",
    "sg:tags":[
        "attorney"
    ],
    "wof:name":"Clifford Faddis",
    "wof:placetype":"venue"
},
  "geometry": {"coordinates":[-90.242137,38.602958],"type":"Point"}
}