{
  "type": "Feature",
  "properties": {
    "iso:country":"US",
    "sg:address":"1211 Eaglecrest St",
    "sg:city":"Nixa",
    "sg:classifiers":[
        {
            "category":"Home & Garden",
            "subcategory":"Building Materials",
            "type":"Retail Goods"
        }
    ],
    "sg:phone":"+1 417 725 8090",
    "sg:postcode":"65714",
    "sg:province":"MO",
    "sg:tags":[
        "windows"
    ],
    "wof:name":"Showcase Builder's Supply",
    "wof:placetype":"venue"
},
  "geometry": {"coordinates":[-93.30862500000001,37.065571],"type":"Point"}
}