{
  "type": "Feature",
  "properties": {
    "iso:country":"US",
    "sg:address":"694 Walton Dr",
    "sg:city":"Farmington",
    "sg:classifiers":[
        {
            "category":"Military Area",
            "type":"Public Place"
        }
    ],
    "sg:phone":"+1 573 756 6426",
    "sg:postcode":"63640",
    "sg:province":"MO",
    "sg:tags":[
        "force",
        "armed",
        "recruiting"
    ],
    "wof:name":"Farmington Army Recruiting Station",
    "wof:placetype":"venue"
},
  "geometry": {"coordinates":[-90.434111,37.788879],"type":"Point"}
}