{
  "type": "Feature",
  "properties": {
    "iso:country":"US",
    "sg:address":"8160 Balson Ave",
    "sg:city":"St Louis",
    "sg:classifiers":[
        {
            "category":"Retail",
            "subcategory":"Veterinary Services",
            "type":"Services"
        }
    ],
    "sg:phone":"+1 314 863 3332",
    "sg:postcode":"63130",
    "sg:province":"MO",
    "sg:tags":[
        "veterinarian"
    ],
    "wof:name":"Leila R Redlich DVM",
    "wof:placetype":"venue"
},
  "geometry": {"coordinates":[-90.347418,38.664618],"type":"Point"}
}