{
  "type": "Feature",
  "properties": {
    "iso:country":"US",
    "sg:address":"29546 Holt 310",
    "sg:city":"Oregon",
    "sg:classifiers":[
        {
            "category":"Manufacturing",
            "subcategory":"Food",
            "type":"Manufacturing & Wholesale Goods"
        },
        {
            "category":"Farming",
            "subcategory":"Farm",
            "type":"Manufacturing & Wholesale Goods"
        }
    ],
    "sg:phone":"+1 660 446 2729",
    "sg:postcode":"64473",
    "sg:province":"MO",
    "sg:tags":[
        "corn",
        "product"
    ],
    "wof:name":"Weis Farms",
    "wof:placetype":"venue"
},
  "geometry": {"coordinates":[-95.08189900000001,39.957],"type":"Point"}
}