{
  "type": "Feature",
  "properties": {
    "iso:country":"US",
    "sg:address":"3232 S Grand Blvd",
    "sg:city":"Saint Louis",
    "sg:classifiers":[
        {
            "category":"Restaurant",
            "type":"Food & Drink"
        },
        {
            "category":"Food & Beverages",
            "subcategory":"Groceries & Convenience Stores",
            "type":"Retail Goods"
        }
    ],
    "sg:phone":"+1 314 664 8032",
    "sg:postcode":"63118",
    "sg:province":"MO",
    "sg:tags":[
        "deli",
        "delicatessen"
    ],
    "wof:name":"South Grand Deli and Grocery",
    "wof:placetype":"venue"
},
  "geometry": {"coordinates":[-90.243103,38.598],"type":"Point"}
}