{
  "type": "Feature",
  "properties": {
    "iso:country":"US",
    "sg:address":"348 Ozark Ave",
    "sg:city":"Cabool",
    "sg:classifiers":[
        {
            "category":"Insurance",
            "subcategory":"Insurance Agent",
            "type":"Services"
        },
        {
            "category":"Insurance",
            "subcategory":"Hazard Insurance",
            "type":"Services"
        },
        {
            "category":"Insurance",
            "subcategory":"Title Insurance",
            "type":"Services"
        }
    ],
    "sg:phone":"+1 417 962 3195",
    "sg:postcode":"65689",
    "sg:province":"MO",
    "sg:tags":[
        "auto",
        "homeowner"
    ],
    "sg:website":"http://apps.amfam.com/agentlocator/?sourceid=yp3",
    "wof:name":"American Family Insurance- Kathy Wells",
    "wof:placetype":"venue"
},
  "geometry": {"coordinates":[-92.097178,37.123747],"type":"Point"}
}