{
  "type": "Feature",
  "properties": {
    "iso:country":"US",
    "sg:address":"2629 Rock Hill Industrial Ct",
    "sg:city":"Saint Louis",
    "sg:classifiers":[
        {
            "category":"Wholesale",
            "subcategory":"Stationery",
            "type":"Manufacturing & Wholesale Goods"
        }
    ],
    "sg:phone":"+1 314 961 3522",
    "sg:postcode":"63144",
    "sg:province":"MO",
    "sg:tags":[
        "supply"
    ],
    "wof:name":"F R Distribution Center",
    "wof:placetype":"venue"
},
  "geometry": {"coordinates":[-90.359886,38.61166],"type":"Point"}
}