{
  "type": "Feature",
  "properties": {
    "iso:country":"US",
    "sg:address":"809 E Gordon St",
    "sg:city":"Marshall",
    "sg:classifiers":[
        {
            "category":"Health Services",
            "subcategory":"Nursing And Care Facility",
            "type":"Services"
        }
    ],
    "sg:phone":"+1 660 886 2247",
    "sg:postcode":"65340",
    "sg:province":"MO",
    "sg:tags":[
        "home",
        "convalescent"
    ],
    "wof:name":"MAR-Saline Manor Care Ctr",
    "wof:placetype":"venue"
},
  "geometry": {"coordinates":[-93.184741,39.110901],"type":"Point"}
}