{
  "type": "Feature",
  "properties": {
    "iso:country":"US",
    "sg:address":"707 NE Cookingham Dr",
    "sg:city":"Kansas City",
    "sg:classifiers":[
        {
            "category":"Professional",
            "subcategory":"Computer Services",
            "type":"Services"
        }
    ],
    "sg:phone":"+1 816 734 3735",
    "sg:postcode":"64155",
    "sg:province":"MO",
    "sg:tags":[
        "datum"
    ],
    "wof:name":"Wayne Metcalfe",
    "wof:placetype":"venue"
},
  "geometry": {"coordinates":[-94.57198099999999,39.303662],"type":"Point"}
}