{
  "type": "Feature",
  "properties": {
    "iso:country":"US",
    "sg:address":"1576 State Hwy Y",
    "sg:city":"Linn Creek",
    "sg:classifiers":[
        {
            "category":"Freight",
            "type":"Transportation"
        }
    ],
    "sg:phone":"+1 573 346 3733",
    "sg:postcode":"65052",
    "sg:province":"MO",
    "sg:tags":[
        "commercial",
        "storage"
    ],
    "wof:name":"Y Road Self Storage",
    "wof:placetype":"venue"
},
  "geometry": {"coordinates":[-92.71622000000001,38.076732],"type":"Point"}
}