{
  "type": "Feature",
  "properties": {
    "iso:country":"US",
    "sg:address":"4559 Von Talge Rd",
    "sg:city":"St Louis",
    "sg:classifiers":[
        {
            "category":"Building & Trades",
            "subcategory":"Landscaping Services",
            "type":"Services"
        }
    ],
    "sg:phone":"+1 314 894 7100",
    "sg:postcode":"63128",
    "sg:province":"MO",
    "sg:tags":[
        "tree"
    ],
    "wof:name":"Hazel Hammers Varnon",
    "wof:placetype":"venue"
},
  "geometry": {"coordinates":[-90.344415,38.505118],"type":"Point"}
}