{
  "type": "Feature",
  "properties": {
    "iso:country":"US",
    "sg:address":"9423 Burdella Ave",
    "sg:city":"Overland",
    "sg:classifiers":[
        {
            "category":"Building & Trades",
            "subcategory":"Landscaping Services",
            "type":"Services"
        }
    ],
    "sg:phone":"+1 314 427 1714",
    "sg:postcode":"63114",
    "sg:province":"MO",
    "sg:tags":[
        "landscape",
        "contractor"
    ],
    "wof:name":"Design Landscaping",
    "wof:placetype":"venue"
},
  "geometry": {"coordinates":[-90.363586,38.720951],"type":"Point"}
}