{
  "type": "Feature",
  "properties": {
    "iso:country":"US",
    "sg:address":"130 W Flier Dr",
    "sg:city":"Pacific",
    "sg:classifiers":[
        {
            "category":"Restaurant",
            "type":"Food & Drink"
        }
    ],
    "sg:phone":"+1 636 257 2200",
    "sg:postcode":"63069",
    "sg:province":"MO",
    "sg:tags":[
        "eating"
    ],
    "wof:name":"Flier Drive Estates",
    "wof:placetype":"venue"
},
  "geometry": {"coordinates":[-90.77452599999999,38.485463],"type":"Point"}
}