{
  "type": "Feature",
  "properties": {
    "iso:country":"US",
    "sg:address":"1101 S 4th St",
    "sg:city":"St Joseph",
    "sg:classifiers":[
        {
            "category":"Freight",
            "type":"Transportation"
        }
    ],
    "sg:phone":"+1 816 364 3110",
    "sg:postcode":"64501",
    "sg:province":"MO",
    "sg:tags":[
        "trucking"
    ],
    "wof:name":"Fender Trucking",
    "wof:placetype":"venue"
},
  "geometry": {"coordinates":[-94.855251,39.755902],"type":"Point"}
}