{
  "type": "Feature",
  "properties": {
    "iso:country":"US",
    "sg:address":"381 SW 40th Rd",
    "sg:city":"Lamar",
    "sg:phone":"+1 417 682 2336",
    "sg:postcode":"64759",
    "sg:province":"MO",
    "sg:tags":[
        "farm",
        "wheat",
        "corn",
        "grain",
        "cash"
    ],
    "wof:name":"Gail Miller",
    "wof:placetype":"venue"
},
  "geometry": {"coordinates":[-94.359054,37.443735],"type":"Point"}
}