{
  "type": "Feature",
  "properties": {
    "iso:country":"US",
    "sg:address":"12565 Co Rd 4031",
    "sg:city":"Holts Summit",
    "sg:classifiers":[
        {
            "category":"Building & Trades",
            "subcategory":"Landscaping Services",
            "type":"Services"
        }
    ],
    "sg:phone":"+1 573 295 6484",
    "sg:postcode":"65043",
    "sg:province":"MO",
    "wof:name":"Gene Mowing Service",
    "wof:placetype":"venue"
},
  "geometry": {"coordinates":[-92.07675,38.600451],"type":"Point"}
}