{
  "type": "Feature",
  "properties": {
    "iso:country":"US",
    "sg:address":"11701 SW Kerns Rd",
    "sg:city":"Stewartsville",
    "sg:classifiers":[
        {
            "category":"Building & Trades",
            "subcategory":"Plumbing",
            "type":"Services"
        },
        {
            "category":"Building & Trades",
            "subcategory":"Construction",
            "type":"Services"
        },
        {
            "category":"Utilities",
            "subcategory":"Sewage",
            "type":"Services"
        }
    ],
    "sg:phone":"+1 816 667 5464",
    "sg:postcode":"64490",
    "sg:province":"MO",
    "sg:tags":[
        "plumber",
        "tank",
        "septic",
        "excavation",
        "system",
        "contractor",
        "sewer",
        "demolition"
    ],
    "wof:name":"Wynes Excavation & Demolition",
    "wof:placetype":"venue"
},
  "geometry": {"coordinates":[-94.573967,39.75082],"type":"Point"}
}