{
  "type": "Feature",
  "properties": {
    "iso:country":"US",
    "sg:address":"4 E 5th St",
    "sg:city":"Gerald",
    "sg:classifiers":[
        {
            "category":"Place Of Worship",
            "subcategory":"Church",
            "type":"Public Place"
        },
        {
            "category":"Place Of Worship",
            "type":"Public Place"
        }
    ],
    "sg:phone":"+1 573 764 2941",
    "sg:postcode":"63037",
    "sg:province":"MO",
    "sg:tags":[
        "churches-interdenominational",
        "churches-various",
        "denomination"
    ],
    "wof:name":"St Pauls Women's Fellowship",
    "wof:placetype":"venue"
},
  "geometry": {"coordinates":[-91.330567,38.398861],"type":"Point"}
}