{
  "type": "Feature",
  "properties": {
    "iso:country":"US",
    "sg:address":"12507 US Hwy 71",
    "sg:city":"Grandview",
    "sg:classifiers":[
        {
            "category":"Autos & Motor Vehicles",
            "subcategory":"Motorcycle Sales",
            "type":"Retail Goods"
        }
    ],
    "sg:phone":"+1 816 777 3882",
    "sg:postcode":"64030",
    "sg:province":"MO",
    "sg:tags":[
        "scooter"
    ],
    "wof:name":"Freedom Suzuki Husqvarna Honda",
    "wof:placetype":"venue"
},
  "geometry": {"coordinates":[-94.524399,38.897797],"type":"Point"}
}