{
  "type": "Feature",
  "properties": {
    "iso:country":"US",
    "sg:address":"1312 E 9th St",
    "sg:city":"Trenton",
    "sg:classifiers":[
        {
            "category":"Wholesale",
            "subcategory":"Home Furnishings",
            "type":"Manufacturing & Wholesale Goods"
        }
    ],
    "sg:phone":"+1 660 359 3333",
    "sg:postcode":"64683",
    "sg:province":"MO",
    "wof:name":"Bryns Country Charm",
    "wof:placetype":"venue"
},
  "geometry": {"coordinates":[-93.605969,40.074225],"type":"Point"}
}