{
  "type": "Feature",
  "properties": {
    "iso:country":"US",
    "sg:address":"6500 Forsyth Blvd",
    "sg:city":"St Louis",
    "sg:classifiers":[
        {
            "category":"Education",
            "subcategory":"Library",
            "type":"Public Place"
        }
    ],
    "sg:phone":"+1 314 935 5563",
    "sg:postcode":"63105",
    "sg:province":"MO",
    "wof:name":"Gaylord Music",
    "wof:placetype":"venue"
},
  "geometry": {"coordinates":[-90.307039,38.646468],"type":"Point"}
}