{
  "type": "Feature",
  "properties": {
    "iso:country":"US",
    "sg:address":"4330 N Newstead Ave",
    "sg:city":"Saint Louis",
    "sg:classifiers":[
        {
            "category":"Bars & Pubs",
            "type":"Food & Drink"
        }
    ],
    "sg:phone":"+1 314 381 4144",
    "sg:postcode":"63115",
    "sg:province":"MO",
    "sg:tags":[
        "lounge",
        "drinking",
        "nightlife",
        "cocktail"
    ],
    "wof:name":"Brenda's Paris Lounge",
    "wof:placetype":"venue"
},
  "geometry": {"coordinates":[-90.230904,38.6772],"type":"Point"}
}