{
  "type": "Feature",
  "properties": {
    "iso:country":"US",
    "sg:address":"4224 Watson Rd",
    "sg:city":"Saint Louis",
    "sg:classifiers":[
        {
            "category":"Health Services",
            "subcategory":"Dentist",
            "type":"Services"
        }
    ],
    "sg:phone":"+1 314 353 5430",
    "sg:postcode":"63109",
    "sg:province":"MO",
    "sg:tags":[
        "orthodontist"
    ],
    "wof:name":"Tabash John W DDS Ms",
    "wof:placetype":"venue"
},
  "geometry": {"coordinates":[-90.302002,38.592899],"type":"Point"}
}