{
  "type": "Feature",
  "properties": {
    "iso:country":"US",
    "sg:address":"1028 Sinnock Ave",
    "sg:city":"Moberly",
    "sg:classifiers":[
        {
            "category":"Freight",
            "type":"Transportation"
        }
    ],
    "sg:phone":"+1 660 263 7239",
    "sg:postcode":"65270",
    "sg:province":"MO",
    "sg:tags":[
        "general"
    ],
    "wof:name":"Garber Inc",
    "wof:placetype":"venue"
},
  "geometry": {"coordinates":[-92.42208599999999,39.431183],"type":"Point"}
}