{
  "type": "Feature",
  "properties": {
    "iso:country":"US",
    "sg:address":"19225 State Rte M",
    "sg:city":"Edgar Springs",
    "sg:classifiers":[
        {
            "category":"Farming",
            "subcategory":"Livestock Farm",
            "type":"Manufacturing & Wholesale Goods"
        }
    ],
    "sg:phone":"+1 573 435 9345",
    "sg:postcode":"65462",
    "sg:province":"MO",
    "sg:tags":[
        "general"
    ],
    "wof:name":"Donald Sneed",
    "wof:placetype":"venue"
},
  "geometry": {"coordinates":[-91.918566,37.734269],"type":"Point"}
}