{
  "type": "Feature",
  "properties": {
    "iso:country":"US",
    "sg:address":"2702 Ashland Ave",
    "sg:city":"St Joseph",
    "sg:classifiers":[
        {
            "category":"Shopping",
            "subcategory":"Florist",
            "type":"Retail Goods"
        }
    ],
    "sg:phone":"+1 816 279 2200",
    "sg:postcode":"64506",
    "sg:province":"MO",
    "wof:name":"Sansone Floral Inc",
    "wof:placetype":"venue"
},
  "geometry": {"coordinates":[-94.82044500000001,39.793273],"type":"Point"}
}