{
  "type": "Feature",
  "properties": {
    "iso:country":"US",
    "sg:address":"4023 S Noland Rd",
    "sg:city":"Independence",
    "sg:classifiers":[
        {
            "category":"Shopping",
            "subcategory":"Shoes",
            "type":"Retail Goods"
        }
    ],
    "sg:phone":"+1 816 461 9000",
    "sg:postcode":"64055",
    "sg:province":"MO",
    "wof:name":"Payless Shoe Source",
    "wof:placetype":"venue"
},
  "geometry": {"coordinates":[-94.41507300000001,39.04694],"type":"Point"}
}