{
  "type": "Feature",
  "properties": {
    "iso:country":"US",
    "sg:address":"2701 Running Horse Rd",
    "sg:city":"Platte City",
    "sg:classifiers":[
        {
            "category":"Bars & Pubs",
            "type":"Food & Drink"
        }
    ],
    "sg:menulink":"http://www.allmenus.com/mo/carroll/229347-tanners-bar--grill/menu/",
    "sg:phone":"+1 816 858 7444",
    "sg:postcode":"64079",
    "sg:province":"MO",
    "sg:tags":[
        "american"
    ],
    "wof:name":"Tanner's Bar & Grill",
    "wof:placetype":"venue"
},
  "geometry": {"coordinates":[-94.762837,39.349088],"type":"Point"}
}