{
  "type": "Feature",
  "properties": {
    "iso:country":"US",
    "sg:address":"226 W Main St",
    "sg:city":"Sullivan",
    "sg:classifiers":[
        {
            "category":"Personal",
            "subcategory":"Beauty Salon",
            "type":"Services"
        }
    ],
    "sg:phone":"+1 573 468 5100",
    "sg:postcode":"63080",
    "sg:province":"MO",
    "wof:name":"Progressive Design Salon",
    "wof:placetype":"venue"
},
  "geometry": {"coordinates":[-91.161351,38.208756],"type":"Point"}
}