{
  "type": "Feature",
  "properties": {
    "iso:country":"US",
    "sg:address":"13090 Manchester Rd",
    "sg:city":"Saint Louis",
    "sg:classifiers":[
        {
            "category":"Restaurant",
            "type":"Food & Drink"
        }
    ],
    "sg:menulink":"http://www.allmenus.com/mo/missouri-river/185214-surf--sirloin/menu/",
    "sg:phone":"+1 314 822 3637",
    "sg:postcode":"63131",
    "sg:province":"MO",
    "sg:tags":[
        "sandwich",
        "salad",
        "seafood",
        "soup",
        "american",
        "pasta",
        "chicken"
    ],
    "wof:name":"Surf & Sirloin",
    "wof:placetype":"venue"
},
  "geometry": {"coordinates":[-90.460846,38.602043],"type":"Point"}
}