{
  "type": "Feature",
  "properties": {
    "iso:country":"US",
    "sg:address":"423 W Grand Ave",
    "sg:city":"Campbell",
    "sg:classifiers":[
        {
            "category":"Personal",
            "subcategory":"Beauty Salon",
            "type":"Services"
        }
    ],
    "sg:phone":"+1 573 246 3139",
    "sg:postcode":"63933",
    "sg:province":"MO",
    "wof:name":"Karen's Styling Salon",
    "wof:placetype":"venue"
},
  "geometry": {"coordinates":[-90.07675399999999,36.491953],"type":"Point"}
}