{
  "type": "Feature",
  "properties": {
    "iso:country":"US",
    "sg:address":"900 US Hwy 24",
    "sg:city":"Independence",
    "sg:classifiers":[
        {
            "category":"Wholesale",
            "subcategory":"Groceries",
            "type":"Manufacturing & Wholesale Goods"
        }
    ],
    "sg:phone":"+1 816 252 2748",
    "sg:postcode":"64050",
    "sg:province":"MO",
    "sg:tags":[
        "baker"
    ],
    "wof:name":"Wonder Bread/Hostess",
    "wof:placetype":"venue"
},
  "geometry": {"coordinates":[-94.402705,39.10237],"type":"Point"}
}