{
  "type": "Feature",
  "properties": {
    "iso:country":"US",
    "sg:address":"11252 Midland Blvd",
    "sg:city":"St Louis",
    "sg:classifiers":[
        {
            "category":"Autos & Motor Vehicles",
            "subcategory":"Auto Supplies",
            "type":"Retail Goods"
        }
    ],
    "sg:phone":"+1 314 427 4991",
    "sg:postcode":"63114",
    "sg:province":"MO",
    "sg:tags":[
        "automobile",
        "parts"
    ],
    "wof:name":"Corvettes & More",
    "wof:placetype":"venue"
},
  "geometry": {"coordinates":[-90.40645000000001,38.705796],"type":"Point"}
}