{
  "type": "Feature",
  "properties": {
    "iso:country":"US",
    "sg:address":"825 South St",
    "sg:city":"Warrenton",
    "sg:classifiers":[
        {
            "category":"Building & Trades",
            "subcategory":"Plumbing",
            "type":"Services"
        }
    ],
    "sg:phone":"+1 636 456 8323",
    "sg:postcode":"63383",
    "sg:province":"MO",
    "sg:tags":[
        "air",
        "heating",
        "refrigeration",
        "conditioning",
        "contractor"
    ],
    "wof:name":"Dames Air LLC",
    "wof:placetype":"venue"
},
  "geometry": {"coordinates":[-91.133106,38.810791],"type":"Point"}
}