{
  "type": "Feature",
  "properties": {
    "iso:country":"US",
    "sg:address":"701 S Maiden Ln",
    "sg:city":"Joplin",
    "sg:classifiers":[
        {
            "category":"Restaurant",
            "type":"Food & Drink"
        }
    ],
    "sg:menulink":"http://www.allmenus.com/mo/galena/182552-wendys/menu/",
    "sg:phone":"+1 471 782 1010",
    "sg:postcode":"64801",
    "sg:province":"MO",
    "sg:tags":[
        "burger",
        "american",
        "soup"
    ],
    "wof:name":"Wendy's",
    "wof:placetype":"venue"
},
  "geometry": {"coordinates":[-94.531147,37.084553],"type":"Point"}
}