{
  "type": "Feature",
  "properties": {
    "iso:country":"US",
    "sg:address":"1015 N Grand Blvd",
    "sg:city":"Saint Louis",
    "sg:classifiers":[
        {
            "category":"Shopping",
            "subcategory":"Beauty & Cosmetics",
            "type":"Retail Goods"
        }
    ],
    "sg:phone":"+1 314 533 2000",
    "sg:postcode":"63106",
    "sg:province":"MO",
    "sg:tags":[
        "supply"
    ],
    "wof:name":"Q & B Plus Beauty Supply",
    "wof:placetype":"venue"
},
  "geometry": {"coordinates":[-90.229235,38.642838],"type":"Point"}
}