{
  "type": "Feature",
  "properties": {
    "iso:country":"US",
    "sg:address":"101 N Main St",
    "sg:city":"Carl Junction",
    "sg:classifiers":[
        {
            "category":"Retail",
            "subcategory":"Funeral Services",
            "type":"Services"
        }
    ],
    "sg:phone":"+1 417 649 7201",
    "sg:postcode":"64834",
    "sg:province":"MO",
    "sg:tags":[
        "director"
    ],
    "wof:name":"Simpson Funeral Home Inc",
    "wof:placetype":"venue"
},
  "geometry": {"coordinates":[-94.56489000000001,37.17752],"type":"Point"}
}