{
  "type": "Feature",
  "properties": {
    "iso:country":"US",
    "sg:address":"545 State Hwy 13",
    "sg:city":"Lexington",
    "sg:classifiers":[
        {
            "category":"Professional",
            "subcategory":"Accounting & Tax Preparation",
            "type":"Services"
        }
    ],
    "sg:phone":"+1 660 259 3991",
    "sg:postcode":"64067",
    "sg:province":"MO",
    "sg:tags":[
        "accountant"
    ],
    "wof:name":"Donald R Wood CPA",
    "wof:placetype":"venue"
},
  "geometry": {"coordinates":[-93.87645999999999,39.176822],"type":"Point"}
}