{
  "type": "Feature",
  "properties": {
    "iso:country":"US",
    "sg:address":"2797 High Ridge Blvd",
    "sg:city":"High Ridge",
    "sg:classifiers":[
        {
            "category":"Professional",
            "subcategory":"Credit Reporting & Collection",
            "type":"Services"
        }
    ],
    "sg:phone":"+1 636 677 3000",
    "sg:postcode":"63049",
    "sg:province":"MO",
    "sg:tags":[
        "agency"
    ],
    "wof:name":"MCA Management Medical Coml",
    "wof:placetype":"venue"
},
  "geometry": {"coordinates":[-90.52949099999999,38.464335],"type":"Point"}
}