{
  "type": "Feature",
  "properties": {
    "iso:country":"US",
    "sg:address":"533 S State Hwy 5",
    "sg:city":"Camdenton",
    "sg:classifiers":[
        {
            "category":"Autos & Motor Vehicles",
            "subcategory":"Automobile Sales",
            "type":"Retail Goods"
        }
    ],
    "sg:phone":"+1 573 346 2700",
    "sg:postcode":"65020",
    "sg:province":"MO",
    "sg:tags":[
        "used"
    ],
    "wof:name":"Car Store",
    "wof:placetype":"venue"
},
  "geometry": {"coordinates":[-92.732011,37.99983],"type":"Point"}
}