{
  "type": "Feature",
  "properties": {
    "iso:country":"US",
    "sg:address":"16870 State Hwy A",
    "sg:city":"Martinsburg",
    "sg:phone":"+1 573 581 1528",
    "sg:postcode":"65264",
    "sg:province":"MO",
    "sg:tags":[
        "farm",
        "corn",
        "soybean"
    ],
    "wof:name":"Greg Fort",
    "wof:placetype":"venue"
},
  "geometry": {"coordinates":[-91.773111,39.091746],"type":"Point"}
}