{
  "type": "Feature",
  "properties": {
    "iso:country":"US",
    "sg:address":"102 N Truman Blvd",
    "sg:city":"Crystal City",
    "sg:classifiers":[
        {
            "category":"Building & Trades",
            "subcategory":"Construction",
            "type":"Services"
        }
    ],
    "sg:phone":"+1 636 931 2820",
    "sg:postcode":"63019",
    "sg:province":"MO",
    "sg:tags":[
        "roofing",
        "contractor"
    ],
    "wof:name":"Hux Co Inc",
    "wof:placetype":"venue"
},
  "geometry": {"coordinates":[-90.38487499999999,38.219814],"type":"Point"}
}