{
  "type": "Feature",
  "properties": {
    "iso:country":"US",
    "sg:address":"304 W Inman St",
    "sg:city":"Clever",
    "sg:classifiers":[
        {
            "category":"Farming",
            "subcategory":"Farm & Veterinary Services",
            "type":"Manufacturing & Wholesale Goods"
        }
    ],
    "sg:phone":"+1 417 743 2903",
    "sg:postcode":"65631",
    "sg:province":"MO",
    "sg:tags":[
        "livestock"
    ],
    "wof:name":"Vicki Plunkett",
    "wof:placetype":"venue"
},
  "geometry": {"coordinates":[-93.474627,37.028244],"type":"Point"}
}