{
  "type": "Feature",
  "properties": {
    "iso:country":"US",
    "sg:address":"12620 Lamplighter Square Shopping Center",
    "sg:city":"Saint Louis",
    "sg:classifiers":[
        {
            "category":"Professional",
            "subcategory":"Employment Agencies",
            "type":"Services"
        }
    ],
    "sg:phone":"+1 314 525 7110",
    "sg:postcode":"63128",
    "sg:province":"MO",
    "wof:name":"Saint Luis Area Nrses Calition",
    "wof:placetype":"venue"
},
  "geometry": {"coordinates":[-90.37824999999999,38.505494],"type":"Point"}
}