{
  "type": "Feature",
  "properties": {
    "iso:country":"US",
    "sg:address":"360 S Mount Auburn Rd",
    "sg:city":"Cape Girardeau",
    "sg:classifiers":[
        {
            "category":"Health Services",
            "subcategory":"Doctor",
            "type":"Services"
        }
    ],
    "sg:phone":"+1 573 335 3577",
    "sg:postcode":"63703",
    "sg:province":"MO",
    "sg:tags":[
        "physician",
        "surgeon"
    ],
    "wof:name":"Eye Care Specialists LLC",
    "wof:placetype":"venue"
},
  "geometry": {"coordinates":[-89.573042,37.294155],"type":"Point"}
}