{
  "type": "Feature",
  "properties": {
    "iso:country":"US",
    "sg:address":"1155 Maple St",
    "sg:city":"Farmington",
    "sg:classifiers":[
        {
            "category":"Home & Garden",
            "subcategory":"Building Materials",
            "type":"Retail Goods"
        }
    ],
    "sg:phone":"+1 573 701 0400",
    "sg:postcode":"63640",
    "sg:province":"MO",
    "sg:tags":[
        "mater"
    ],
    "wof:name":"Overhead Door Co Farmington",
    "wof:placetype":"venue"
},
  "geometry": {"coordinates":[-90.43598,37.786953],"type":"Point"}
}