{
  "type": "Feature",
  "properties": {
    "iso:country":"US",
    "sg:address":"710 Velvet Dr",
    "sg:city":"Camdenton",
    "sg:classifiers":[
        {
            "category":"Retail",
            "subcategory":"Repair Shop",
            "type":"Services"
        },
        {
            "category":"Professional",
            "subcategory":"Detective & Security Services",
            "type":"Services"
        }
    ],
    "sg:phone":"+1 573 346 4357",
    "sg:postcode":"65020",
    "sg:province":"MO",
    "sg:tags":[
        "skip",
        "tracing",
        "bail",
        "bond"
    ],
    "wof:name":"Dave Vinson's Bail Bonds",
    "wof:placetype":"venue"
},
  "geometry": {"coordinates":[-92.705157,37.987377],"type":"Point"}
}