{
  "type": "Feature",
  "properties": {
    "iso:country":"US",
    "sg:address":"288 Hanley Industrial Ct",
    "sg:city":"Saint Louis",
    "sg:classifiers":[
        {
            "category":"Professional",
            "subcategory":"Advertising",
            "type":"Services"
        }
    ],
    "sg:phone":"+1 314 645 5055",
    "sg:postcode":"63144",
    "sg:province":"MO",
    "sg:tags":[
        "mail"
    ],
    "wof:name":"Zip Mail Services Inc",
    "wof:placetype":"venue"
},
  "geometry": {"coordinates":[-90.337202,38.621529],"type":"Point"}
}