{
  "type": "Feature",
  "properties": {
    "iso:country":"US",
    "sg:address":"2331 S Business Highway 65",
    "sg:city":"Hollister",
    "sg:classifiers":[
        {
            "category":"Health Services",
            "subcategory":"Doctor",
            "type":"Services"
        }
    ],
    "sg:phone":"+1 417 339 3033",
    "sg:postcode":"65672",
    "sg:province":"MO",
    "sg:tags":[
        "physician",
        "family",
        "practice",
        "surgeons",
        "medicine",
        "surgeon"
    ],
    "wof:name":"Sukman R Randall MD",
    "wof:placetype":"venue"
},
  "geometry": {"coordinates":[-93.2173,36.620218],"type":"Point"}
}