{
  "type": "Feature",
  "properties": {
    "iso:country":"US",
    "sg:address":"2607 NE Industrial Dr",
    "sg:city":"Kansas City",
    "sg:classifiers":[
        {
            "category":"Building & Trades",
            "subcategory":"Plumbing",
            "type":"Services"
        }
    ],
    "sg:phone":"+1 816 471 7772",
    "sg:postcode":"64117",
    "sg:province":"MO",
    "sg:tags":[
        "contractor"
    ],
    "wof:name":"Temp Air",
    "wof:placetype":"venue"
},
  "geometry": {"coordinates":[-94.53370700000001,39.148797],"type":"Point"}
}