{
  "type": "Feature",
  "properties": {
    "iso:country":"US",
    "sg:address":"2308 Cypress Dr",
    "sg:city":"Marshall",
    "sg:classifiers":[
        {
            "category":"Farming",
            "subcategory":"Farm",
            "type":"Manufacturing & Wholesale Goods"
        }
    ],
    "sg:phone":"+1 660 886 6318",
    "sg:postcode":"65340",
    "sg:province":"MO",
    "sg:tags":[
        "livestock",
        "crop",
        "general"
    ],
    "wof:name":"William R Thiel Inc",
    "wof:placetype":"venue"
},
  "geometry": {"coordinates":[-93.19387399999999,39.089149],"type":"Point"}
}