{
  "type": "Feature",
  "properties": {
    "iso:country":"US",
    "sg:address":"1010 Main St",
    "sg:city":"Lexington",
    "sg:classifiers":[
        {
            "category":"Professional",
            "subcategory":"Art Services",
            "type":"Services"
        }
    ],
    "sg:phone":"+1 660 259 6750",
    "sg:postcode":"64067",
    "sg:province":"MO",
    "sg:tags":[
        "graphic",
        "designer"
    ],
    "wof:name":"Heisler Graphics Etc",
    "wof:placetype":"venue"
},
  "geometry": {"coordinates":[-93.882301,39.185578],"type":"Point"}
}