{
  "type": "Feature",
  "properties": {
    "iso:country":"US",
    "sg:address":"20891 Carriage Ln",
    "sg:city":"Barnett",
    "sg:classifiers":[
        {
            "category":"Real Estate",
            "subcategory":"Real Estate Services",
            "type":"Services"
        },
        {
            "category":"Building & Trades",
            "subcategory":"Cleaning & Sanitation",
            "type":"Services"
        },
        {
            "category":"Retail",
            "subcategory":"Laundry & Dry Cleaning",
            "type":"Services"
        }
    ],
    "sg:phone":"+1 573 392 4733",
    "sg:postcode":"65011",
    "sg:province":"MO",
    "sg:tags":[
        "cleaner",
        "rug",
        "maintenance",
        "cleaners-interior",
        "janitorial",
        "carpet"
    ],
    "wof:name":"B & D Services",
    "wof:placetype":"venue"
},
  "geometry": {"coordinates":[-92.691648,38.353443],"type":"Point"}
}