{
  "type": "Feature",
  "properties": {
    "iso:country":"US",
    "sg:address":"706 Williams St",
    "sg:city":"Richmond",
    "sg:classifiers":[
        {
            "category":"Home & Garden",
            "subcategory":"Building Materials",
            "type":"Retail Goods"
        }
    ],
    "sg:phone":"+1 816 470 5084",
    "sg:postcode":"64085",
    "sg:province":"MO",
    "wof:name":"Terry Sullard Siding & Window",
    "wof:placetype":"venue"
},
  "geometry": {"coordinates":[-93.981754,39.267546],"type":"Point"}
}