{
  "type": "Feature",
  "properties": {
    "iso:country":"US",
    "sg:address":"1805 W Highway 32",
    "sg:city":"Salem",
    "sg:classifiers":[
        {
            "category":"Wholesale",
            "subcategory":"Poultry",
            "type":"Manufacturing & Wholesale Goods"
        },
        {
            "category":"Farming",
            "subcategory":"Livestock Farm",
            "type":"Manufacturing & Wholesale Goods"
        }
    ],
    "sg:phone":"+1 573 729 8880",
    "sg:postcode":"65560",
    "sg:province":"MO",
    "sg:tags":[
        "buyer",
        "auction",
        "market"
    ],
    "wof:name":"Salem Livestock Market Inc",
    "wof:placetype":"venue"
},
  "geometry": {"coordinates":[-91.559724,37.636436],"type":"Point"}
}