{
  "type": "Feature",
  "properties": {
    "addr:full":"1500 State Hwy 7 Blue Springs MO 64014",
    "addr:housenumber":"1500",
    "addr:postcode":"64014",
    "addr:street":"State Hwy 7",
    "iso:country":"US",
    "sg:address":"1500 State Hwy 7",
    "sg:city":"Blue Springs",
    "sg:classifiers":[
        {
            "category":"Autos & Motor Vehicles",
            "subcategory":"Fuel & Gas Station",
            "type":"Retail Goods"
        }
    ],
    "sg:phone":"+1 816 228 0502",
    "sg:postcode":"64014",
    "sg:province":"MO",
    "sg:tags":[
        "grocery",
        "station",
        "gasoline"
    ],
    "wof:name":"Quiktrip",
    "wof:placetype":"venue"
},
  "geometry": {"coordinates":[-94.272893,39.0007],"type":"Point"}
}