{
  "type": "Feature",
  "properties": {
    "iso:country":"US",
    "sg:address":"948 E Snider St",
    "sg:city":"Springfield",
    "sg:classifiers":[
        {
            "category":"Retail",
            "subcategory":"Repair Shop",
            "type":"Services"
        }
    ],
    "sg:phone":"+1 417 844 4270",
    "sg:postcode":"65803",
    "sg:province":"MO",
    "sg:tags":[
        "water",
        "heater",
        "electrical"
    ],
    "wof:name":"Water Heater Specialists",
    "wof:placetype":"venue"
},
  "geometry": {"coordinates":[-93.27992399999999,37.258335],"type":"Point"}
}