{
  "type": "Feature",
  "properties": {
    "iso:country":"US",
    "sg:address":"2825 Kraus Dr",
    "sg:city":"Barnhart",
    "sg:classifiers":[
        {
            "category":"Farming",
            "subcategory":"Dairy Farm",
            "type":"Manufacturing & Wholesale Goods"
        }
    ],
    "sg:phone":"+1 636 948 3701",
    "sg:postcode":"63012",
    "sg:province":"MO",
    "sg:tags":[
        "chicken",
        "egg"
    ],
    "wof:name":"Kraus Dairy Farm and Corp",
    "wof:placetype":"venue"
},
  "geometry": {"coordinates":[-90.425764,38.355164],"type":"Point"}
}