{
  "type": "Feature",
  "properties": {
    "iso:country":"US",
    "sg:address":"12922 2 St",
    "sg:city":"Grandview",
    "sg:classifiers":[
        {
            "category":"Real Estate",
            "subcategory":"Real Estate Agent",
            "type":"Services"
        }
    ],
    "sg:phone":"+1 816 761 8513",
    "sg:postcode":"64030",
    "sg:province":"MO",
    "wof:name":"SMS Properties",
    "wof:placetype":"venue"
},
  "geometry": {"coordinates":[-94.543469,38.889756],"type":"Point"}
}