{
  "type": "Feature",
  "properties": {
    "iso:country":"US",
    "sg:address":"3441 William St",
    "sg:city":"Cape Girardeau",
    "sg:classifiers":[
        {
            "category":"Banks & Credit Unions",
            "subcategory":"Bank",
            "type":"Services"
        }
    ],
    "sg:phone":"+1 573 339 7888",
    "sg:postcode":"63701",
    "sg:province":"MO",
    "sg:tags":[
        "commercial",
        "financing",
        "consumer"
    ],
    "wof:name":"Citi Financial",
    "wof:placetype":"venue"
},
  "geometry": {"coordinates":[-89.58007600000001,37.302695],"type":"Point"}
}