{
  "type": "Feature",
  "properties": {
    "iso:country":"US",
    "sg:address":"2912 Lafayette Ave",
    "sg:city":"St Louis",
    "sg:classifiers":[
        {
            "category":"Real Estate",
            "subcategory":"Real Estate Operator",
            "type":"Services"
        }
    ],
    "sg:phone":"+1 314 664 3770",
    "sg:postcode":"63104",
    "sg:province":"MO",
    "sg:tags":[
        "apartment"
    ],
    "wof:name":"Lafayette Terrace Apartments",
    "wof:placetype":"venue"
},
  "geometry": {"coordinates":[-90.228713,38.615642],"type":"Point"}
}