{
  "type": "Feature",
  "properties": {
    "iso:country":"US",
    "sg:address":"9426 Manchester Rd",
    "sg:city":"St Louis",
    "sg:classifiers":[
        {
            "category":"Professional",
            "type":"Services"
        }
    ],
    "sg:phone":"+1 314 961 2424",
    "sg:postcode":"63119",
    "sg:province":"MO",
    "sg:tags":[
        "establishment"
    ],
    "wof:name":"Pure Pilates Plus",
    "wof:placetype":"venue"
},
  "geometry": {"coordinates":[-90.363024,38.609579],"type":"Point"}
}