{
  "type": "Feature",
  "properties": {
    "iso:country":"US",
    "sg:address":"706 S Washington St",
    "sg:city":"Chillicothe",
    "sg:classifiers":[
        {
            "category":"Professional",
            "subcategory":"Lawyer & Legal Services",
            "type":"Services"
        }
    ],
    "sg:phone":"+1 660 646 4446",
    "sg:postcode":"64601",
    "sg:province":"MO",
    "sg:tags":[
        "attorney",
        "plan"
    ],
    "wof:name":"Bosler Timothy H",
    "wof:placetype":"venue"
},
  "geometry": {"coordinates":[-93.552824,39.77969],"type":"Point"}
}