{
  "type": "Feature",
  "properties": {
    "iso:country":"US",
    "sg:address":"2919 Meyer Rd",
    "sg:city":"Foristell",
    "sg:classifiers":[
        {
            "category":"Shopping",
            "subcategory":"Hobbies, Toys, & Games",
            "type":"Retail Goods"
        }
    ],
    "sg:phone":"+1 636 463 1544",
    "sg:postcode":"63348",
    "sg:province":"MO",
    "wof:name":"Beltworks",
    "wof:placetype":"venue"
},
  "geometry": {"coordinates":[-90.934552,38.8256],"type":"Point"}
}