{
  "type": "Feature",
  "properties": {
    "iso:country":"US",
    "sg:address":"15528 Washington School Rd",
    "sg:city":"Excelsior Springs",
    "sg:classifiers":[
        {
            "category":"Organizations",
            "subcategory":"Religious Organization",
            "type":"Services"
        }
    ],
    "sg:phone":"+1 816 637 9698",
    "sg:postcode":"64024",
    "sg:province":"MO",
    "wof:name":"Washington Restoration Branch",
    "wof:placetype":"venue"
},
  "geometry": {"coordinates":[-94.237859,39.37094],"type":"Point"}
}