{
  "type": "Feature",
  "properties": {
    "iso:country":"US",
    "sg:address":"1417 N 2nd St",
    "sg:city":"St Charles",
    "sg:classifiers":[
        {
            "category":"Shopping",
            "subcategory":"Used Merchandise",
            "type":"Retail Goods"
        }
    ],
    "sg:phone":"+1 636 723 1665",
    "sg:postcode":"63301",
    "sg:province":"MO",
    "sg:tags":[
        "antique"
    ],
    "wof:name":"Mattie's Heritage Antiques",
    "wof:placetype":"venue"
},
  "geometry": {"coordinates":[-90.476677,38.792976],"type":"Point"}
}