{
  "type": "Feature",
  "properties": {
    "iso:country":"US",
    "sg:address":"906 N Ely St",
    "sg:city":"Carrollton",
    "sg:classifiers":[
        {
            "category":"Place Of Worship",
            "subcategory":"Church",
            "type":"Public Place"
        },
        {
            "category":"Place Of Worship",
            "type":"Public Place"
        },
        {
            "category":"Organizations",
            "subcategory":"Religious Organization",
            "type":"Services"
        }
    ],
    "sg:phone":"+1 660 542 1741",
    "sg:postcode":"64633",
    "sg:province":"MO",
    "sg:tags":[
        "god",
        "god-independent",
        "churches-assemblies",
        "denomination",
        "churches-interdenominational",
        "churches-various"
    ],
    "sg:website":"http://www.ag.org",
    "wof:name":"Assembly of God Church",
    "wof:placetype":"venue"
},
  "geometry": {"coordinates":[-93.503418,39.368644],"type":"Point"}
}