{
  "type": "Feature",
  "properties": {
    "iso:country":"US",
    "sg:address":"2 Willowyck Ct",
    "sg:city":"St Louis",
    "sg:classifiers":[
        {
            "category":"Banks & Credit Unions",
            "subcategory":"Financial Services",
            "type":"Services"
        }
    ],
    "sg:phone":"+1 314 404 2277",
    "sg:postcode":"63146",
    "sg:province":"MO",
    "sg:tags":[
        "company",
        "holding"
    ],
    "wof:name":"Sagen Corp",
    "wof:placetype":"venue"
},
  "geometry": {"coordinates":[-90.472032,38.693138],"type":"Point"}
}