{
  "type": "Feature",
  "properties": {
    "iso:country":"US",
    "sg:address":"510 W Main St",
    "sg:city":"Savannah",
    "sg:classifiers":[
        {
            "category":"Insurance",
            "subcategory":"Insurance Agent",
            "type":"Services"
        },
        {
            "category":"Insurance",
            "subcategory":"Hazard Insurance",
            "type":"Services"
        }
    ],
    "sg:phone":"+1 816 324 3133",
    "sg:postcode":"64485",
    "sg:province":"MO",
    "sg:tags":[
        "auto",
        "commercial",
        "business"
    ],
    "sg:website":"http://www.ingersollinsurance.com",
    "wof:name":"Ingersoll Insurance Agency",
    "wof:placetype":"venue"
},
  "geometry": {"coordinates":[-94.830366,39.941561],"type":"Point"}
}