{
  "type": "Feature",
  "properties": {
    "iso:country":"US",
    "sg:address":"559 S Malang Rd",
    "sg:city":"Joplin",
    "sg:classifiers":[
        {
            "category":"Professional",
            "type":"Services"
        }
    ],
    "sg:phone":"+1 417 624 0683",
    "sg:postcode":"64801",
    "sg:province":"MO",
    "wof:name":"Arthur Dykens",
    "wof:placetype":"venue"
},
  "geometry": {"coordinates":[-94.60141400000001,37.08781],"type":"Point"}
}