{
  "type": "Feature",
  "properties": {
    "iso:country":"US",
    "sg:address":"500 E Broadway",
    "sg:city":"Columbia",
    "sg:classifiers":[
        {
            "category":"Autos & Motor Vehicles",
            "subcategory":"Auto Supplies",
            "type":"Retail Goods"
        }
    ],
    "sg:phone":"+1 573 443 8765",
    "sg:postcode":"65201",
    "sg:province":"MO",
    "sg:tags":[
        "automobile",
        "parts"
    ],
    "wof:name":"Carquest Auto Parts",
    "wof:placetype":"venue"
},
  "geometry": {"coordinates":[-92.33076,38.951609],"type":"Point"}
}