{
  "type": "Feature",
  "properties": {
    "iso:country":"US",
    "sg:address":"2204 Main St",
    "sg:city":"Bethany",
    "sg:classifiers":[
        {
            "category":"Shopping",
            "subcategory":"Books",
            "type":"Retail Goods"
        }
    ],
    "sg:phone":"+1 660 425 8193",
    "sg:postcode":"64424",
    "sg:province":"MO",
    "wof:name":"Jos Book Barn",
    "wof:placetype":"venue"
},
  "geometry": {"coordinates":[-94.02879900000001,40.268547],"type":"Point"}
}