{
  "type": "Feature",
  "properties": {
    "iso:country":"US",
    "sg:address":"17324 Radcliffe Place Dr",
    "sg:city":"Eureka",
    "sg:classifiers":[
        {
            "category":"Freight",
            "type":"Transportation"
        }
    ],
    "sg:phone":"+1 636 938 5859",
    "sg:postcode":"63025",
    "sg:province":"MO",
    "sg:tags":[
        "general"
    ],
    "wof:name":"Dedicated Warehousing Inc",
    "wof:placetype":"venue"
},
  "geometry": {"coordinates":[-90.635107,38.541713],"type":"Point"}
}