{
  "type": "Feature",
  "properties": {
    "iso:country":"US",
    "sg:address":"1 Bauman Dr",
    "sg:city":"Festus",
    "sg:classifiers":[
        {
            "category":"Retail",
            "subcategory":"Storage",
            "type":"Services"
        }
    ],
    "sg:phone":"+1 636 937 7073",
    "sg:postcode":"63028",
    "sg:province":"MO",
    "sg:tags":[
        "self",
        "recreational",
        "campers-storage",
        "vehicle"
    ],
    "wof:name":"Crystal Self Storage",
    "wof:placetype":"venue"
},
  "geometry": {"coordinates":[-90.394333,38.234859],"type":"Point"}
}