{
  "type": "Feature",
  "properties": {
    "iso:country":"US",
    "sg:address":"117 W 4th St",
    "sg:city":"Salem",
    "sg:classifiers":[
        {
            "category":"Shopping",
            "subcategory":"Pharmacy",
            "type":"Retail Goods"
        }
    ],
    "sg:phone":"+1 573 729 4114",
    "sg:postcode":"65560",
    "sg:province":"MO",
    "wof:name":"Vandivort Drug Store",
    "wof:placetype":"venue"
},
  "geometry": {"coordinates":[-91.537273,37.645303],"type":"Point"}
}