{
  "type": "Feature",
  "properties": {
    "iso:country":"US",
    "sg:address":"6524 Liv 420",
    "sg:city":"Ludlow",
    "sg:phone":"+1 660 738 4748",
    "sg:postcode":"64656",
    "sg:province":"MO",
    "sg:tags":[
        "farm",
        "fertilizer",
        "soybean",
        "supply"
    ],
    "wof:name":"Davies Grain & Distributing",
    "wof:placetype":"venue"
},
  "geometry": {"coordinates":[-93.66582,39.684182],"type":"Point"}
}