{
  "type": "Feature",
  "properties": {
    "iso:country":"US",
    "sg:address":"1721 Tudor Ln",
    "sg:city":"Liberty",
    "sg:classifiers":[
        {
            "category":"Freight",
            "type":"Transportation"
        }
    ],
    "sg:phone":"+1 816 792 2667",
    "sg:postcode":"64068",
    "sg:province":"MO",
    "sg:tags":[
        "carrier"
    ],
    "wof:name":"J & S Express LLC",
    "wof:placetype":"venue"
},
  "geometry": {"coordinates":[-94.44857,39.227746],"type":"Point"}
}