{
  "type": "Feature",
  "properties": {
    "iso:country":"US",
    "sg:address":"1916 Woodson Rd",
    "sg:city":"St Louis",
    "sg:classifiers":[
        {
            "category":"Wholesale",
            "subcategory":"Machinery & Supplies",
            "type":"Manufacturing & Wholesale Goods"
        },
        {
            "category":"Retail",
            "subcategory":"Repair Shop",
            "type":"Services"
        }
    ],
    "sg:phone":"+1 314 423 4600",
    "sg:postcode":"63114",
    "sg:province":"MO",
    "sg:tags":[
        "equipment",
        "hydraulic"
    ],
    "wof:name":"Pirtek Overland",
    "wof:placetype":"venue"
},
  "geometry": {"coordinates":[-90.362184,38.688651],"type":"Point"}
}