{
  "type": "Feature",
  "properties": {
    "iso:country":"US",
    "sg:address":"260 Lamar Pkwy",
    "sg:city":"Pacific",
    "sg:classifiers":[
        {
            "category":"Shopping",
            "type":"Retail Goods"
        }
    ],
    "sg:phone":"+1 636 271 3200",
    "sg:postcode":"63069",
    "sg:province":"MO",
    "sg:tags":[
        "equipment",
        "telephone",
        "cellular"
    ],
    "wof:name":"Solutions2 Cellular LLC",
    "wof:placetype":"venue"
},
  "geometry": {"coordinates":[-90.76836299999999,38.482971],"type":"Point"}
}