{
  "type": "Feature",
  "properties": {
    "iso:country":"US",
    "sg:address":"129 State Hwy T",
    "sg:city":"Rosebud",
    "sg:classifiers":[
        {
            "category":"Autos & Motor Vehicles",
            "subcategory":"Motorcycle Sales",
            "type":"Retail Goods"
        }
    ],
    "sg:phone":"+1 573 764 2359",
    "sg:postcode":"63091",
    "sg:province":"MO",
    "sg:tags":[
        "scooter"
    ],
    "wof:name":"Outpost Motorcycles Sales",
    "wof:placetype":"venue"
},
  "geometry": {"coordinates":[-91.399761,38.386109],"type":"Point"}
}