{
  "type": "Feature",
  "properties": {
    "iso:country":"US",
    "sg:address":"11309 Midland Blvd",
    "sg:city":"Overland",
    "sg:classifiers":[
        {
            "category":"Wholesale",
            "subcategory":"Electrical",
            "type":"Manufacturing & Wholesale Goods"
        }
    ],
    "sg:phone":"+1 314 427 2181",
    "sg:postcode":"63114",
    "sg:province":"MO",
    "sg:tags":[
        "lighting",
        "fixture"
    ],
    "wof:name":"Lensmasters",
    "wof:placetype":"venue"
},
  "geometry": {"coordinates":[-90.407748,38.707707],"type":"Point"}
}