{
  "type": "Feature",
  "properties": {
    "iso:country":"US",
    "sg:address":"6106 Walnut St",
    "sg:city":"Kansas City",
    "sg:classifiers":[
        {
            "category":"Professional",
            "subcategory":"Management & Consulting",
            "type":"Services"
        }
    ],
    "sg:phone":"+1 816 523 9150",
    "sg:postcode":"64113",
    "sg:province":"MO",
    "sg:tags":[
        "business"
    ],
    "wof:name":"Develpment Dynamics Consulting",
    "wof:placetype":"venue"
},
  "geometry": {"coordinates":[-94.587202,39.015562],"type":"Point"}
}