{
  "type": "Feature",
  "properties": {
    "iso:country":"US",
    "sg:address":"201 State Hwy D",
    "sg:city":"Lilbourn",
    "sg:classifiers":[
        {
            "category":"Wholesale",
            "subcategory":"Chemicals & Plastics",
            "type":"Manufacturing & Wholesale Goods"
        }
    ],
    "sg:phone":"+1 573 688 2152",
    "sg:postcode":"63862",
    "sg:province":"MO",
    "wof:name":"Mfa Inc",
    "wof:placetype":"venue"
},
  "geometry": {"coordinates":[-89.615405,36.595183],"type":"Point"}
}