{
  "type": "Feature",
  "properties": {
    "iso:country":"US",
    "sg:address":"1997 S Pin Oak Dr",
    "sg:city":"Springfield",
    "sg:classifiers":[
        {
            "category":"Professional",
            "subcategory":"Lawyer & Legal Services",
            "type":"Services"
        }
    ],
    "sg:phone":"+1 417 877 0640",
    "sg:postcode":"65809",
    "sg:province":"MO",
    "wof:name":"David L Zerrer",
    "wof:placetype":"venue"
},
  "geometry": {"coordinates":[-93.193926,37.177705],"type":"Point"}
}