{
  "type": "Feature",
  "properties": {
    "iso:country":"US",
    "sg:address":"500 Armour Rd",
    "sg:city":"Kansas City",
    "sg:classifiers":[
        {
            "category":"Insurance",
            "subcategory":"Insurance Agent",
            "type":"Services"
        }
    ],
    "sg:phone":"+1 816 471 4200",
    "sg:postcode":"64116",
    "sg:province":"MO",
    "wof:name":"American Family Insurance",
    "wof:placetype":"venue"
},
  "geometry": {"coordinates":[-94.57376600000001,39.142607],"type":"Point"}
}