{
  "type": "Feature",
  "properties": {
    "iso:country":"US",
    "sg:address":"105 N Thornton St",
    "sg:city":"Richmond",
    "sg:classifiers":[
        {
            "category":"Banks & Credit Unions",
            "subcategory":"Investment Brokerage",
            "type":"Services"
        }
    ],
    "sg:phone":"+1 816 776 5458",
    "sg:postcode":"64085",
    "sg:province":"MO",
    "sg:tags":[
        "stock",
        "bond"
    ],
    "wof:name":"Edward Jones Co",
    "wof:placetype":"venue"
},
  "geometry": {"coordinates":[-93.97647000000001,39.278453],"type":"Point"}
}