{
  "type": "Feature",
  "properties": {
    "iso:country":"US",
    "sg:address":"1424 N Dewey St",
    "sg:city":"Maryville",
    "sg:classifiers":[
        {
            "category":"Organizations",
            "subcategory":"Religious Organization",
            "type":"Services"
        }
    ],
    "sg:phone":"+1 660 582 2926",
    "sg:postcode":"64468",
    "sg:province":"MO",
    "wof:name":"McKim Paul Rev",
    "wof:placetype":"venue"
},
  "geometry": {"coordinates":[-94.868488,40.358912],"type":"Point"}
}