{
  "type": "Feature",
  "properties": {
    "iso:country":"US",
    "sg:address":"127 Jamestown Mall",
    "sg:city":"Florissant",
    "sg:classifiers":[
        {
            "category":"Professional",
            "subcategory":"Business Services",
            "type":"Services"
        }
    ],
    "sg:phone":"+1 314 438 1582",
    "sg:postcode":"63034",
    "sg:province":"MO",
    "wof:name":"Mobile Solution Corp",
    "wof:placetype":"venue"
},
  "geometry": {"coordinates":[-90.249443,38.821015],"type":"Point"}
}