{
  "type": "Feature",
  "properties": {
    "iso:country":"US",
    "sg:address":"10114 N Central St",
    "sg:city":"Kansas City",
    "sg:classifiers":[
        {
            "category":"Professional",
            "subcategory":"Secretarial Services",
            "type":"Services"
        }
    ],
    "sg:phone":"+1 816 734 2500",
    "sg:postcode":"64155",
    "sg:province":"MO",
    "sg:tags":[
        "reporting"
    ],
    "wof:name":"McDaniel Secretarial Services",
    "wof:placetype":"venue"
},
  "geometry": {"coordinates":[-94.58383000000001,39.274903],"type":"Point"}
}