{
  "type": "Feature",
  "properties": {
    "iso:country":"US",
    "sg:address":"12262 Conway Rd",
    "sg:city":"Saint Louis",
    "sg:classifiers":[
        {
            "category":"Organizations",
            "subcategory":"Religious Organization",
            "type":"Services"
        }
    ],
    "sg:phone":"+1 314 878 3497",
    "sg:postcode":"63141",
    "sg:province":"MO",
    "wof:name":"Seminary Convenant Theological",
    "wof:placetype":"venue"
},
  "geometry": {"coordinates":[-90.450699,38.644244],"type":"Point"}
}