{
  "type": "Feature",
  "properties": {
    "iso:country":"US",
    "sg:address":"355 County Rd",
    "sg:city":"Festus",
    "sg:classifiers":[
        {
            "category":"Building & Trades",
            "subcategory":"Construction",
            "type":"Services"
        }
    ],
    "sg:phone":"+1 636 937 7444",
    "sg:postcode":"63019",
    "sg:province":"MO",
    "wof:name":"Water Waste Management",
    "wof:placetype":"venue"
},
  "geometry": {"coordinates":[-90.38838,38.206938],"type":"Point"}
}