{
  "type": "Feature",
  "properties": {
    "iso:country":"US",
    "sg:address":"3645 State Hwy 173",
    "sg:city":"Galena",
    "sg:classifiers":[
        {
            "category":"Building & Trades",
            "subcategory":"Construction",
            "type":"Services"
        }
    ],
    "sg:phone":"+1 417 357 6314",
    "sg:postcode":"65656",
    "sg:province":"MO",
    "sg:tags":[
        "nonresidential"
    ],
    "wof:name":"Double Eagle Contracting LLC",
    "wof:placetype":"venue"
},
  "geometry": {"coordinates":[-93.53351600000001,36.80391],"type":"Point"}
}