{
  "type": "Feature",
  "properties": {
    "iso:country":"US",
    "sg:address":"204 S Broadway St",
    "sg:city":"Oak Grove",
    "sg:classifiers":[
        {
            "category":"Food & Beverages",
            "subcategory":"Liquor & Beverages",
            "type":"Retail Goods"
        }
    ],
    "sg:phone":"+1 816 690 4725",
    "sg:postcode":"64075",
    "sg:province":"MO",
    "wof:name":"Oak Grove Liquors",
    "wof:placetype":"venue"
},
  "geometry": {"coordinates":[-94.12883600000001,39.013852],"type":"Point"}
}