{
  "type": "Feature",
  "properties": {
    "iso:country":"US",
    "sg:address":"7751 N Lindbergh Blvd",
    "sg:city":"Hazelwood",
    "sg:classifiers":[
        {
            "category":"Professional",
            "subcategory":"Business Services",
            "type":"Services"
        },
        {
            "category":"Wholesale",
            "subcategory":"Books, Periodicals, & Newspapers",
            "type":"Manufacturing & Wholesale Goods"
        }
    ],
    "sg:phone":"+1 314 972 1111",
    "sg:postcode":"63042",
    "sg:province":"MO",
    "sg:tags":[
        "publisher",
        "publishing",
        "consultant"
    ],
    "wof:name":"Suburban Journals",
    "wof:placetype":"venue"
},
  "geometry": {"coordinates":[-90.35110299999999,38.786557],"type":"Point"}
}