{
  "type": "Feature",
  "properties": {
    "iso:country":"US",
    "sg:address":"170 N Main Ave",
    "sg:city":"Summersville",
    "sg:classifiers":[
        {
            "category":"Manufacturing",
            "subcategory":"Furniture",
            "type":"Manufacturing & Wholesale Goods"
        }
    ],
    "sg:phone":"+1 417 932 1255",
    "sg:postcode":"65571",
    "sg:province":"MO",
    "sg:tags":[
        "builder",
        "designer",
        "custom"
    ],
    "wof:name":"Sister Act Furniture",
    "wof:placetype":"venue"
},
  "geometry": {"coordinates":[-91.656339,37.179347],"type":"Point"}
}