{
  "type": "Feature",
  "properties": {
    "iso:country":"US",
    "sg:address":"315 E Kansas Ave",
    "sg:city":"Independence",
    "sg:classifiers":[
        {
            "category":"Professional",
            "subcategory":"Lawyer & Legal Services",
            "type":"Services"
        }
    ],
    "sg:phone":"+1 816 836 1551",
    "sg:postcode":"64050",
    "sg:province":"MO",
    "sg:tags":[
        "attorney"
    ],
    "wof:name":"A Criminal Defense",
    "wof:placetype":"venue"
},
  "geometry": {"coordinates":[-94.411512,39.090885],"type":"Point"}
}