{
  "type": "Feature",
  "properties": {
    "iso:country":"US",
    "sg:address":"3108 State Hwy Kk",
    "sg:city":"Troy",
    "sg:classifiers":[
        {
            "category":"Personal",
            "type":"Services"
        }
    ],
    "sg:phone":"+1 636 528 6209",
    "sg:postcode":"63379",
    "sg:province":"MO",
    "wof:name":"Weddings Plus",
    "wof:placetype":"venue"
},
  "geometry": {"coordinates":[-90.911828,39.060843],"type":"Point"}
}