{
  "type": "Feature",
  "properties": {
    "iso:country":"US",
    "sg:address":"919 State Hwy 19",
    "sg:city":"Wellsville",
    "sg:classifiers":[
        {
            "category":"Farming",
            "subcategory":"Farm",
            "type":"Manufacturing & Wholesale Goods"
        }
    ],
    "sg:phone":"+1 573 684 2656",
    "sg:postcode":"63384",
    "sg:province":"MO",
    "sg:tags":[
        "crop",
        "general"
    ],
    "wof:name":"Gene Fort",
    "wof:placetype":"venue"
},
  "geometry": {"coordinates":[-91.551332,39.06451],"type":"Point"}
}