{
  "type": "Feature",
  "properties": {
    "iso:country":"US",
    "sg:address":"2957 Wentworth Dr",
    "sg:city":"Saint Charles",
    "sg:classifiers":[
        {
            "category":"Building & Trades",
            "subcategory":"Construction",
            "type":"Services"
        }
    ],
    "sg:phone":"+1 636 946 8822",
    "sg:postcode":"63301",
    "sg:province":"MO",
    "sg:tags":[
        "commercial",
        "drywall",
        "system"
    ],
    "wof:name":"Dhc Construction Inc",
    "wof:placetype":"venue"
},
  "geometry": {"coordinates":[-90.532212,38.804897],"type":"Point"}
}