{
  "type": "Feature",
  "properties": {
    "iso:country":"US",
    "sg:address":"508 State Hwy 72",
    "sg:city":"Rolla",
    "sg:classifiers":[
        {
            "category":"Shopping",
            "subcategory":"Discount & Variety Stores",
            "type":"Retail Goods"
        }
    ],
    "sg:phone":"+1 573 364 4332",
    "sg:postcode":"65401",
    "sg:province":"MO",
    "wof:name":"Dollar General",
    "wof:placetype":"venue"
},
  "geometry": {"coordinates":[-91.775612,37.942471],"type":"Point"}
}