{
  "type": "Feature",
  "properties": {
    "addr:full":"508 State Hwy 72 Rolla MO 65401",
    "addr:housenumber":"508",
    "addr:postcode":"65401",
    "addr:street":"State Hwy 72",
    "iso:country":"US",
    "sg:address":"508 State Hwy 72",
    "sg:city":"Rolla",
    "sg:classifiers":[
        {
            "category":"Shopping",
            "subcategory":"Discount & Variety Stores",
            "type":"Retail Goods"
        }
    ],
    "sg:phone":"+1 573 364 4332",
    "sg:postcode":"65401",
    "sg:province":"MO",
    "wof:name":"Dollar General",
    "wof:placetype":"venue"
},
  "geometry": {"coordinates":[-91.775612,37.942471],"type":"Point"}
}