{
  "type": "Feature",
  "properties": {
    "iso:country":"US",
    "sg:address":"6414 Hampton Ave Ste 4",
    "sg:city":"Saint Louis",
    "sg:classifiers":[
        {
            "category":"Communications",
            "type":"Services"
        }
    ],
    "sg:phone":"+1 314 752 3806",
    "sg:postcode":"63109",
    "sg:province":"MO",
    "sg:tags":[
        "web",
        "design"
    ],
    "sg:website":"www.mikesiers.com",
    "wof:name":"Mike Siers Website Design",
    "wof:placetype":"venue"
},
  "geometry": {"coordinates":[-90.29442899999999,38.575043],"type":"Point"}
}