{
  "type": "Feature",
  "properties": {
    "iso:country":"US",
    "sg:address":"2929 Terri Ln",
    "sg:city":"Joplin",
    "sg:classifiers":[
        {
            "category":"Building & Trades",
            "subcategory":"Construction",
            "type":"Services"
        }
    ],
    "sg:phone":"+1 417 782 9571",
    "sg:postcode":"64804",
    "sg:province":"MO",
    "sg:tags":[
        "hanging",
        "contractor"
    ],
    "wof:name":"Voss Painting",
    "wof:placetype":"venue"
},
  "geometry": {"coordinates":[-94.49632800000001,37.057558],"type":"Point"}
}