{
  "type": "Feature",
  "properties": {
    "iso:country":"US",
    "sg:address":"16230 Truman Rd",
    "sg:city":"Ellisville",
    "sg:classifiers":[
        {
            "category":"Freight",
            "type":"Transportation"
        }
    ],
    "sg:phone":"+1 636 273 4794",
    "sg:postcode":"63011",
    "sg:province":"MO",
    "sg:tags":[
        "commercial",
        "storage"
    ],
    "wof:name":"Public Storage",
    "wof:placetype":"venue"
},
  "geometry": {"coordinates":[-90.606949,38.587855],"type":"Point"}
}