{
  "type": "Feature",
  "properties": {
    "iso:country":"US",
    "sg:address":"1034 S Brentwood Blvd",
    "sg:city":"Saint Louis",
    "sg:classifiers":[
        {
            "category":"Professional",
            "subcategory":"Lawyer & Legal Services",
            "type":"Services"
        }
    ],
    "sg:phone":"+1 314 241 5353",
    "sg:postcode":"63117",
    "sg:province":"MO",
    "wof:name":"Robert A Samuels",
    "wof:placetype":"venue"
},
  "geometry": {"coordinates":[-90.345685,38.636034],"type":"Point"}
}