{
  "type": "Feature",
  "properties": {
    "iso:country":"US",
    "sg:address":"534 West St",
    "sg:city":"Stockton",
    "sg:classifiers":[
        {
            "category":"Insurance",
            "subcategory":"Insurance Agent",
            "type":"Services"
        },
        {
            "category":"Insurance",
            "subcategory":"Hazard Insurance",
            "type":"Services"
        }
    ],
    "sg:phone":"+1 417 276 5414",
    "sg:postcode":"65785",
    "sg:province":"MO",
    "sg:tags":[
        "consultant",
        "commercial",
        "analyst",
        "business"
    ],
    "wof:name":"Stockton Insurance Service",
    "wof:placetype":"venue"
},
  "geometry": {"coordinates":[-93.802471,37.701162],"type":"Point"}
}