{
  "type": "Feature",
  "properties": {
    "iso:country":"US",
    "sg:address":"303 Collier St",
    "sg:city":"Hannibal",
    "sg:classifiers":[
        {
            "category":"Bars & Pubs",
            "type":"Food & Drink"
        }
    ],
    "sg:phone":"+1 573 221 8236",
    "sg:postcode":"63401",
    "sg:province":"MO",
    "sg:tags":[
        "drinking"
    ],
    "wof:name":"Pops Club Inc",
    "wof:placetype":"venue"
},
  "geometry": {"coordinates":[-91.355161,39.706726],"type":"Point"}
}