{
  "type": "Feature",
  "properties": {
    "iso:country":"US",
    "sg:address":"421 Betty Ave",
    "sg:city":"Moberly",
    "sg:classifiers":[
        {
            "category":"Social Services",
            "subcategory":"Child Care",
            "type":"Services"
        }
    ],
    "sg:phone":"+1 660 263 9065",
    "sg:postcode":"65270",
    "sg:province":"MO",
    "sg:tags":[
        "day"
    ],
    "wof:name":"Alamo Learning Systems Inc",
    "wof:placetype":"venue"
},
  "geometry": {"coordinates":[-92.423266,39.415067],"type":"Point"}
}