{
  "type": "Feature",
  "properties": {
    "iso:country":"US",
    "sg:address":"5753 Impala Dr",
    "sg:city":"Joplin",
    "sg:classifiers":[
        {
            "category":"Building & Trades",
            "subcategory":"Construction",
            "type":"Services"
        }
    ],
    "sg:phone":"+1 417 781 7653",
    "sg:postcode":"64804",
    "sg:province":"MO",
    "sg:tags":[
        "house"
    ],
    "wof:name":"Bybee Const Co",
    "wof:placetype":"venue"
},
  "geometry": {"coordinates":[-94.444642,36.984069],"type":"Point"}
}