{
  "type": "Feature",
  "properties": {
    "iso:country":"US",
    "sg:address":"720 Lemay Ferry Rd",
    "sg:city":"St Louis",
    "sg:classifiers":[
        {
            "category":"Shopping",
            "subcategory":"Used Merchandise",
            "type":"Retail Goods"
        }
    ],
    "sg:phone":"+1 314 544 7366",
    "sg:postcode":"63125",
    "sg:province":"MO",
    "sg:tags":[
        "antique"
    ],
    "wof:name":"B Baggins Corner Antiques",
    "wof:placetype":"venue"
},
  "geometry": {"coordinates":[-90.28159100000001,38.539177],"type":"Point"}
}