{
  "type": "Feature",
  "properties": {
    "iso:country":"US",
    "sg:address":"523 Court St",
    "sg:city":"Fulton",
    "sg:classifiers":[
        {
            "category":"Shopping",
            "subcategory":"Crafts & Fabrics",
            "type":"Retail Goods"
        }
    ],
    "sg:phone":"+1 573 642 3143",
    "sg:postcode":"65251",
    "sg:province":"MO",
    "sg:tags":[
        "embroidery"
    ],
    "wof:name":"Center Custom Embroidery",
    "wof:placetype":"venue"
},
  "geometry": {"coordinates":[-91.947925,38.84768],"type":"Point"}
}