{
  "type": "Feature",
  "properties": {
    "iso:country":"US",
    "sg:address":"339 W State Hwy V",
    "sg:city":"Lamar",
    "sg:classifiers":[
        {
            "category":"Shopping",
            "subcategory":"Bicycles & Sporting Goods",
            "type":"Retail Goods"
        }
    ],
    "sg:phone":"+1 417 884 5143",
    "sg:postcode":"64759",
    "sg:province":"MO",
    "wof:name":"Pro Shooting",
    "wof:placetype":"venue"
},
  "geometry": {"coordinates":[-94.35500399999999,37.604504],"type":"Point"}
}