{
  "type": "Feature",
  "properties": {
    "iso:country":"US",
    "sg:address":"3434 S Range Line Rd",
    "sg:city":"Joplin",
    "sg:classifiers":[
        {
            "category":"Restaurant",
            "type":"Food & Drink"
        }
    ],
    "sg:phone":"+1 417 782 8574",
    "sg:postcode":"64804",
    "sg:province":"MO",
    "sg:tags":[
        "eating"
    ],
    "wof:name":"Tasteful Franchising Inc",
    "wof:placetype":"venue"
},
  "geometry": {"coordinates":[-94.478562,37.053006],"type":"Point"}
}