{
  "type": "Feature",
  "properties": {
    "iso:country":"US",
    "sg:address":"82 N Oaks Plz",
    "sg:city":"Saint Louis",
    "sg:classifiers":[
        {
            "category":"Shopping",
            "subcategory":"Beauty & Cosmetics",
            "type":"Retail Goods"
        }
    ],
    "sg:phone":"+1 314 389 0555",
    "sg:postcode":"63121",
    "sg:province":"MO",
    "sg:tags":[
        "supply"
    ],
    "wof:name":"Kings Beauty Distributor Corporation",
    "wof:placetype":"venue"
},
  "geometry": {"coordinates":[-90.290199,38.701],"type":"Point"}
}