{
  "type": "Feature",
  "properties": {
    "iso:country":"US",
    "sg:address":"46 4 Seasons Shopping Ctr",
    "sg:city":"Chesterfield",
    "sg:classifiers":[
        {
            "category":"Restaurant",
            "type":"Food & Drink"
        }
    ],
    "sg:menulink":"http://www.allmenus.com/mo/maryland-heights/55116-st-louis-bread-co/menu/",
    "sg:phone":"+1 314 878 7373",
    "sg:postcode":"63017",
    "sg:province":"MO",
    "sg:tags":[
        "wrap",
        "american",
        "sandwich"
    ],
    "wof:name":"St. Louis Bread Co.",
    "wof:placetype":"venue"
},
  "geometry": {"coordinates":[-90.501456,38.679098],"type":"Point"}
}