{
  "type": "Feature",
  "properties": {
    "iso:country":"US",
    "sg:address":"1804 NW Chipman Rd",
    "sg:city":"Lees Summit",
    "sg:classifiers":[
        {
            "category":"Personal",
            "subcategory":"Barber",
            "type":"Services"
        }
    ],
    "sg:phone":"+1 816 554 8630",
    "sg:postcode":"64081",
    "sg:province":"MO",
    "wof:name":"Sports Clips",
    "wof:placetype":"venue"
},
  "geometry": {"coordinates":[-94.407529,38.926089],"type":"Point"}
}