{
  "type": "Feature",
  "properties": {
    "iso:country":"US",
    "sg:address":"12151 Clayton Rd",
    "sg:city":"St Louis",
    "sg:classifiers":[
        {
            "category":"Autos & Motor Vehicles",
            "subcategory":"Fuel & Gas Station",
            "type":"Retail Goods"
        }
    ],
    "sg:phone":"+1 314 692 7052",
    "sg:postcode":"63131",
    "sg:province":"MO",
    "sg:tags":[
        "oil"
    ],
    "wof:name":"Ballas & Clayton Shell Svc",
    "wof:placetype":"venue"
},
  "geometry": {"coordinates":[-90.443321,38.631687],"type":"Point"}
}