{
  "type": "Feature",
  "properties": {
    "iso:country":"US",
    "sg:address":"1212 E North Ave",
    "sg:city":"Belton",
    "sg:classifiers":[
        {
            "category":"Restaurant",
            "type":"Food & Drink"
        }
    ],
    "sg:menulink":"http://www.allmenus.com/mo/mount-pleasant/98622-longhorn-steakhouse/menu/",
    "sg:phone":"+1 816 318 8300",
    "sg:postcode":"64012",
    "sg:province":"MO",
    "sg:tags":[
        "american",
        "steakhouse"
    ],
    "wof:name":"LongHorn Steakhouse",
    "wof:placetype":"venue"
},
  "geometry": {"coordinates":[-94.516063,38.813753],"type":"Point"}
}