{
  "type": "Feature",
  "properties": {
    "iso:country":"US",
    "sg:address":"2126 Prospect Ave",
    "sg:city":"Kansas City",
    "sg:classifiers":[
        {
            "category":"Organizations",
            "subcategory":"Religious Organization",
            "type":"Services"
        }
    ],
    "sg:phone":"+1 816 241 3719",
    "sg:postcode":"64127",
    "sg:province":"MO",
    "sg:tags":[
        "church"
    ],
    "wof:name":"Ward Chapel A M E Church",
    "wof:placetype":"venue"
},
  "geometry": {"coordinates":[-94.55215200000001,39.085829],"type":"Point"}
}