{
  "type": "Feature",
  "properties": {
    "iso:country":"US",
    "sg:address":"101 S Lincoln Dr",
    "sg:city":"Troy",
    "sg:classifiers":[
        {
            "category":"Restaurant",
            "type":"Food & Drink"
        }
    ],
    "sg:phone":"+1 636 462 8822",
    "sg:postcode":"63379",
    "sg:province":"MO",
    "wof:name":"Mike's Hickory Pit Barbecue",
    "wof:placetype":"venue"
},
  "geometry": {"coordinates":[-90.96961,38.983253],"type":"Point"}
}