{
  "type": "Feature",
  "properties": {
    "iso:country":"US",
    "sg:address":"1333 Fargo Dr",
    "sg:city":"Ferguson",
    "sg:classifiers":[
        {
            "category":"Building & Trades",
            "subcategory":"Construction",
            "type":"Services"
        }
    ],
    "sg:phone":"+1 314 521 7642",
    "sg:postcode":"63135",
    "sg:province":"MO",
    "sg:tags":[
        "general",
        "contractor"
    ],
    "wof:name":"Penson Construction",
    "wof:placetype":"venue"
},
  "geometry": {"coordinates":[-90.28077399999999,38.744169],"type":"Point"}
}