{
  "type": "Feature",
  "properties": {
    "iso:country":"US",
    "sg:address":"4521 Independence Ave",
    "sg:city":"Kansas City",
    "sg:classifiers":[
        {
            "category":"Personal",
            "subcategory":"Beauty Salon",
            "type":"Services"
        }
    ],
    "sg:phone":"+1 816 231 6610",
    "sg:postcode":"64124",
    "sg:province":"MO",
    "sg:tags":[
        "shop"
    ],
    "wof:name":"Eric Hair Salon",
    "wof:placetype":"venue"
},
  "geometry": {"coordinates":[-94.52932699999999,39.105507],"type":"Point"}
}