{
  "type": "Feature",
  "properties": {
    "iso:country":"US",
    "sg:address":"2012 N Deerborn Cir",
    "sg:city":"Columbia",
    "sg:classifiers":[
        {
            "category":"Insurance",
            "subcategory":"Insurance Agent",
            "type":"Services"
        }
    ],
    "sg:phone":"+1 573 446 0114",
    "sg:postcode":"65203",
    "sg:province":"MO",
    "wof:name":"Allied Insurance Claims",
    "wof:placetype":"venue"
},
  "geometry": {"coordinates":[-92.37181099999999,38.930207],"type":"Point"}
}