{
  "type": "Feature",
  "properties": {
    "iso:country":"US",
    "sg:address":"305 Saint Louis St",
    "sg:city":"Florissant",
    "sg:classifiers":[
        {
            "category":"Wholesale",
            "subcategory":"Machinery & Supplies",
            "type":"Manufacturing & Wholesale Goods"
        }
    ],
    "sg:phone":"+1 314 355 6666",
    "sg:postcode":"63031",
    "sg:province":"MO",
    "sg:tags":[
        "equipment",
        "welding"
    ],
    "wof:name":"Cee Kay Supply Inc",
    "wof:placetype":"venue"
},
  "geometry": {"coordinates":[-90.328323,38.795412],"type":"Point"}
}