{
  "type": "Feature",
  "properties": {
    "iso:country":"US",
    "sg:address":"2371 Rohlfing Rd",
    "sg:city":"Hermann",
    "sg:phone":"+1 573 486 2562",
    "sg:postcode":"65041",
    "sg:province":"MO",
    "sg:tags":[
        "farm",
        "corn",
        "soybean"
    ],
    "wof:name":"David Rohlfing",
    "wof:placetype":"venue"
},
  "geometry": {"coordinates":[-91.39786599999999,38.663232],"type":"Point"}
}