{
  "type": "Feature",
  "properties": {
    "iso:country":"US",
    "sg:address":"705 Corrington Dr",
    "sg:city":"Raymore",
    "sg:classifiers":[
        {
            "category":"Home & Garden",
            "subcategory":"Building Materials",
            "type":"Retail Goods"
        },
        {
            "category":"Building & Trades",
            "subcategory":"Construction",
            "type":"Services"
        }
    ],
    "sg:phone":"+1 816 935 1486",
    "sg:postcode":"64083",
    "sg:province":"MO",
    "sg:tags":[
        "concrete",
        "staining",
        "contractor"
    ],
    "wof:name":"Ddm Concrete Services",
    "wof:placetype":"venue"
},
  "geometry": {"coordinates":[-94.472183,38.795296],"type":"Point"}
}