{
  "type": "Feature",
  "properties": {
    "iso:country":"US",
    "sg:address":"1954 US Hwy 412",
    "sg:city":"Cardwell",
    "sg:classifiers":[
        {
            "category":"Wholesale",
            "subcategory":"Apparel",
            "type":"Manufacturing & Wholesale Goods"
        }
    ],
    "sg:phone":"+1 573 654 2273",
    "sg:postcode":"63829",
    "sg:province":"MO",
    "sg:tags":[
        "t"
    ],
    "wof:name":"Big Den's Transfer World",
    "wof:placetype":"venue"
},
  "geometry": {"coordinates":[-90.310126,36.039069],"type":"Point"}
}