{
  "type": "Feature",
  "properties": {
    "iso:country":"US",
    "sg:address":"901 Main St",
    "sg:city":"Cassville",
    "sg:classifiers":[
        {
            "category":"Insurance",
            "subcategory":"Hazard Insurance",
            "type":"Services"
        },
        {
            "category":"Banks & Credit Unions",
            "subcategory":"Financial Services",
            "type":"Services"
        }
    ],
    "sg:phone":"+1 417 847 3196",
    "sg:postcode":"65625",
    "sg:province":"MO",
    "sg:tags":[
        "consultant",
        "planning"
    ],
    "wof:name":"Bob Bishop Insurance Inc",
    "wof:placetype":"venue"
},
  "geometry": {"coordinates":[-93.868478,36.678357],"type":"Point"}
}