{
  "type": "Feature",
  "properties": {
    "iso:country":"US",
    "sg:address":"520 N High St",
    "sg:city":"Neosho",
    "sg:classifiers":[
        {
            "category":"Place Of Worship",
            "subcategory":"Church",
            "type":"Public Place"
        },
        {
            "category":"Place Of Worship",
            "type":"Public Place"
        },
        {
            "category":"Organizations",
            "subcategory":"Religious Organization",
            "type":"Services"
        }
    ],
    "sg:phone":"+1 417 451 1061",
    "sg:postcode":"64850",
    "sg:province":"MO",
    "sg:tags":[
        "god",
        "god-independent",
        "churches-assemblies"
    ],
    "wof:name":"Bible Holiness Press",
    "wof:placetype":"venue"
},
  "geometry": {"coordinates":[-94.373151,36.874145],"type":"Point"}
}