{
  "type": "Feature",
  "properties": {
    "iso:country":"US",
    "sg:address":"11105 NW 77 Ter",
    "sg:city":"Kansas City",
    "sg:classifiers":[
        {
            "category":"Professional",
            "type":"Services"
        }
    ],
    "sg:phone":"+1 816 587 6002",
    "sg:postcode":"64152",
    "sg:province":"MO",
    "sg:tags":[
        "establishment"
    ],
    "wof:name":"Mica Corp",
    "wof:placetype":"venue"
},
  "geometry": {"coordinates":[-94.710838,39.238925],"type":"Point"}
}