{
  "type": "Feature",
  "properties": {
    "iso:country":"US",
    "sg:address":"690 Rozier St",
    "sg:city":"Ste Genevieve",
    "sg:classifiers":[
        {
            "category":"Health Services",
            "subcategory":"Optometrist",
            "type":"Services"
        }
    ],
    "sg:phone":"+1 573 883 3030",
    "sg:postcode":"63670",
    "sg:province":"MO",
    "wof:name":"Mueller & Spray",
    "wof:placetype":"venue"
},
  "geometry": {"coordinates":[-90.046498,37.966734],"type":"Point"}
}