{
  "type": "Feature",
  "properties": {
    "iso:country":"US",
    "sg:address":"2111 McCausland Ave",
    "sg:city":"Saint Louis",
    "sg:classifiers":[
        {
            "category":"Organizations",
            "subcategory":"Religious Organization",
            "type":"Services"
        }
    ],
    "sg:phone":"+1 314 781 3064",
    "sg:postcode":"63143",
    "sg:province":"MO",
    "wof:name":"Immanuel Methodist Church",
    "wof:placetype":"venue"
},
  "geometry": {"coordinates":[-90.308708,38.619357],"type":"Point"}
}