{
  "type": "Feature",
  "properties": {
    "iso:country":"US",
    "sg:address":"4413 S Atherton Ct",
    "sg:city":"Independence",
    "sg:classifiers":[
        {
            "category":"Professional",
            "subcategory":"Management & Consulting",
            "type":"Services"
        }
    ],
    "sg:phone":"+1 816 373 5914",
    "sg:postcode":"64055",
    "sg:province":"MO",
    "sg:tags":[
        "consultant"
    ],
    "wof:name":"Gillette Consulting Group",
    "wof:placetype":"venue"
},
  "geometry": {"coordinates":[-94.374268,39.040852],"type":"Point"}
}