{
  "type": "Feature",
  "properties": {
    "iso:country":"US",
    "sg:address":"1900 Independence Ave",
    "sg:city":"Kansas City",
    "sg:classifiers":[
        {
            "category":"Autos & Motor Vehicles",
            "subcategory":"Fuel & Gas Station",
            "type":"Retail Goods"
        }
    ],
    "sg:phone":"+1 816 421 1255",
    "sg:postcode":"64124",
    "sg:province":"MO",
    "sg:tags":[
        "station",
        "gasoline",
        "oil"
    ],
    "wof:name":"Northeast Auto Service & Sales",
    "wof:placetype":"venue"
},
  "geometry": {"coordinates":[-94.557147,39.106528],"type":"Point"}
}