{
  "type": "Feature",
  "properties": {
    "iso:country":"US",
    "sg:address":"5544 Holmes St",
    "sg:city":"Kansas City",
    "sg:classifiers":[
        {
            "category":"Shopping",
            "subcategory":"Jewelry",
            "type":"Retail Goods"
        }
    ],
    "sg:phone":"+1 816 333 6182",
    "sg:postcode":"64110",
    "sg:province":"MO",
    "sg:tags":[
        "clocks"
    ],
    "wof:name":"Fred G Ramphal Co",
    "wof:placetype":"venue"
},
  "geometry": {"coordinates":[-94.57858400000001,39.026353],"type":"Point"}
}