{
  "type": "Feature",
  "properties": {
    "iso:country":"US",
    "sg:address":"1008 W Grand Ave",
    "sg:city":"Cameron",
    "sg:classifiers":[
        {
            "category":"Autos & Motor Vehicles",
            "subcategory":"Recreational Vehicle Sales",
            "type":"Retail Goods"
        }
    ],
    "sg:phone":"+1 816 632 5050",
    "sg:postcode":"64429",
    "sg:province":"MO",
    "wof:name":"Nw Missouri Recreational Vhcle",
    "wof:placetype":"venue"
},
  "geometry": {"coordinates":[-94.248104,39.752874],"type":"Point"}
}