{
  "type": "Feature",
  "properties": {
    "iso:country":"US",
    "sg:address":"312 Market St",
    "sg:city":"Fulton",
    "sg:classifiers":[
        {
            "category":"Banks & Credit Unions",
            "subcategory":"Financial Services",
            "type":"Services"
        }
    ],
    "sg:phone":"+1 573 592 4900",
    "sg:postcode":"65251",
    "sg:province":"MO",
    "sg:tags":[
        "cashing",
        "payday",
        "loan",
        "check"
    ],
    "sg:website":"http://www.pfglending.com",
    "wof:name":"America's Cash Advance Inc",
    "wof:placetype":"venue"
},
  "geometry": {"coordinates":[-91.94713400000001,38.845679],"type":"Point"}
}