{
  "type": "Feature",
  "properties": {
    "iso:country":"US",
    "sg:address":"4757 Lee Ave",
    "sg:city":"Saint Louis",
    "sg:classifiers":[
        {
            "category":"Shopping",
            "subcategory":"Clothing, Apparel, & Fashions",
            "type":"Retail Goods"
        }
    ],
    "sg:phone":"+1 314 389 5017",
    "sg:postcode":"63115",
    "sg:province":"MO",
    "wof:name":"R Life Inc",
    "wof:placetype":"venue"
},
  "geometry": {"coordinates":[-90.24137399999999,38.677883],"type":"Point"}
}