{
  "type": "Feature",
  "properties": {
    "iso:country":"US",
    "sg:address":"1201 W Broadway",
    "sg:city":"Columbia",
    "sg:classifiers":[
        {
            "category":"Professional",
            "subcategory":"Lawyer & Legal Services",
            "type":"Services"
        }
    ],
    "sg:phone":"+1 573 443 6003",
    "sg:postcode":"65203",
    "sg:province":"MO",
    "sg:tags":[
        "attorney"
    ],
    "wof:name":"Lori L Green",
    "wof:placetype":"venue"
},
  "geometry": {"coordinates":[-92.357586,38.952483],"type":"Point"}
}