{
  "type": "Feature",
  "properties": {
    "iso:country":"US",
    "sg:address":"4258 Finney Ave",
    "sg:city":"St Louis",
    "sg:classifiers":[
        {
            "category":"Restaurant",
            "type":"Food & Drink"
        }
    ],
    "sg:phone":"+1 314 535 0856",
    "sg:postcode":"63113",
    "sg:province":"MO",
    "sg:tags":[
        "banquet",
        "rooms"
    ],
    "wof:name":"Top Ten Banquet Studio",
    "wof:placetype":"venue"
},
  "geometry": {"coordinates":[-90.24477899999999,38.650878],"type":"Point"}
}