{
  "type": "Feature",
  "properties": {
    "iso:country":"US",
    "sg:address":"209 S Kirkwood Rd",
    "sg:city":"Kirkwood",
    "sg:classifiers":[
        {
            "category":"Health Services",
            "subcategory":"Doctor",
            "type":"Services"
        }
    ],
    "sg:phone":"+1 314 821 1101",
    "sg:postcode":"63122",
    "sg:province":"MO",
    "sg:tags":[
        "dentist"
    ],
    "wof:name":"Junction Orthodontics",
    "wof:placetype":"venue"
},
  "geometry": {"coordinates":[-90.406491,38.578934],"type":"Point"}
}