{
  "type": "Feature",
  "properties": {
    "iso:country":"US",
    "sg:address":"310 W Shawnee St",
    "sg:city":"Bloomfield",
    "sg:classifiers":[
        {
            "category":"Professional",
            "subcategory":"Lawyer & Legal Services",
            "type":"Services"
        }
    ],
    "sg:phone":"+1 573 568 2132",
    "sg:postcode":"63825",
    "sg:province":"MO",
    "sg:tags":[
        "attorney"
    ],
    "wof:name":"Don Rhodes Law Offices",
    "wof:placetype":"venue"
},
  "geometry": {"coordinates":[-89.931839,36.883505],"type":"Point"}
}