{
  "type": "Feature",
  "properties": {
    "iso:country":"US",
    "sg:address":"911 Alpine Ridge Dr",
    "sg:city":"Ballwin",
    "sg:classifiers":[
        {
            "category":"Banks & Credit Unions",
            "subcategory":"Investment Brokerage",
            "type":"Services"
        }
    ],
    "sg:phone":"+1 636 305 0330",
    "sg:postcode":"63021",
    "sg:province":"MO",
    "sg:tags":[
        "security"
    ],
    "wof:name":"Edward Jones 25652",
    "wof:placetype":"venue"
},
  "geometry": {"coordinates":[-90.510851,38.56562],"type":"Point"}
}