{
  "type": "Feature",
  "properties": {
    "iso:country":"US",
    "sg:address":"2201 Indiana Ave",
    "sg:city":"Kansas City",
    "sg:classifiers":[
        {
            "category":"Wholesale",
            "subcategory":"Electrical",
            "type":"Manufacturing & Wholesale Goods"
        }
    ],
    "sg:phone":"+1 816 241 5757",
    "sg:postcode":"64127",
    "sg:province":"MO",
    "sg:tags":[
        "resistant",
        "equipment",
        "burglar"
    ],
    "wof:name":"Ironcraft Ornamental Iron",
    "wof:placetype":"venue"
},
  "geometry": {"coordinates":[-94.54292100000001,39.084268],"type":"Point"}
}