{
  "type": "Feature",
  "properties": {
    "iso:country":"US",
    "sg:address":"1675 E Seminole St",
    "sg:city":"Springfield",
    "sg:classifiers":[
        {
            "category":"Professional",
            "subcategory":"Business Services",
            "type":"Services"
        }
    ],
    "sg:phone":"+1 417 882 5664",
    "sg:postcode":"65804",
    "sg:province":"MO",
    "sg:tags":[
        "real estate"
    ],
    "wof:name":"Bob Kollmeier C A I C A G A",
    "wof:placetype":"venue"
},
  "geometry": {"coordinates":[-93.26420899999999,37.17442],"type":"Point"}
}