{
  "type": "Feature",
  "properties": {
    "iso:country":"US",
    "sg:address":"2200 Potomac Dr",
    "sg:city":"Columbia",
    "sg:classifiers":[
        {
            "category":"Building & Trades",
            "subcategory":"Construction",
            "type":"Services"
        }
    ],
    "sg:phone":"+1 573 447 2054",
    "sg:postcode":"65203",
    "sg:province":"MO",
    "sg:tags":[
        "wallcoverings-installation",
        "wallpaper",
        "painting",
        "contractor"
    ],
    "wof:name":"Bill Green Painting Inc",
    "wof:placetype":"venue"
},
  "geometry": {"coordinates":[-92.39809200000001,38.930431],"type":"Point"}
}