{
  "type": "Feature",
  "properties": {
    "iso:country":"US",
    "sg:address":"3315 Berrywood Dr",
    "sg:city":"Columbia",
    "sg:classifiers":[
        {
            "category":"Organizations",
            "subcategory":"Professional Association",
            "type":"Services"
        }
    ],
    "sg:phone":"+1 573 875 0555",
    "sg:postcode":"65201",
    "sg:province":"MO",
    "sg:tags":[
        "home",
        "health"
    ],
    "wof:name":"Visiting Nrses Assn of Cntl MO",
    "wof:placetype":"venue"
},
  "geometry": {"coordinates":[-92.288724,38.95933],"type":"Point"}
}