{
  "type": "Feature",
  "properties": {
    "iso:country":"US",
    "sg:address":"1016 Motherhead Rd",
    "sg:city":"St Charles",
    "sg:classifiers":[
        {
            "category":"Building & Trades",
            "subcategory":"Construction",
            "type":"Services"
        },
        {
            "category":"Manufacturing",
            "subcategory":"Tools & Machinery",
            "type":"Manufacturing & Wholesale Goods"
        }
    ],
    "sg:phone":"+1 636 939 5919",
    "sg:postcode":"63304",
    "sg:province":"MO",
    "sg:tags":[
        "stairway",
        "house",
        "moving",
        "elevator",
        "nonresidential"
    ],
    "wof:name":"Petre Construction",
    "wof:placetype":"venue"
},
  "geometry": {"coordinates":[-90.64972899999999,38.728421],"type":"Point"}
}