{
  "type": "Feature",
  "properties": {
    "iso:country":"US",
    "sg:address":"14 Wydown Ter",
    "sg:city":"Saint Louis",
    "sg:classifiers":[
        {
            "category":"Building & Trades",
            "subcategory":"Construction",
            "type":"Services"
        }
    ],
    "sg:phone":"+1 314 862 9019",
    "sg:postcode":"63105",
    "sg:province":"MO",
    "sg:tags":[
        "industrial"
    ],
    "wof:name":"R D-Two Inc",
    "wof:placetype":"venue"
},
  "geometry": {"coordinates":[-90.309648,38.642205],"type":"Point"}
}