{
  "type": "Feature",
  "properties": {
    "iso:country":"US",
    "sg:address":"14025 N Robinhood Ln",
    "sg:city":"Kansas City",
    "sg:classifiers":[
        {
            "category":"Wholesale",
            "subcategory":"Machinery & Supplies",
            "type":"Manufacturing & Wholesale Goods"
        }
    ],
    "sg:phone":"+1 816 532 2610",
    "sg:postcode":"64164",
    "sg:province":"MO",
    "sg:tags":[
        "pump"
    ],
    "wof:name":"Summit Pump",
    "wof:placetype":"venue"
},
  "geometry": {"coordinates":[-94.610277,39.347416],"type":"Point"}
}