{
  "type": "Feature",
  "properties": {
    "iso:country":"US",
    "sg:address":"117 E Jefferson St",
    "sg:city":"Jackson",
    "sg:classifiers":[
        {
            "category":"Utilities",
            "subcategory":"Mobile Phone",
            "type":"Services"
        }
    ],
    "sg:phone":"+1 573 204 7100",
    "sg:postcode":"63755",
    "sg:province":"MO",
    "sg:tags":[
        "telephone",
        "cellular"
    ],
    "wof:name":"Heartland Wireless",
    "wof:placetype":"venue"
},
  "geometry": {"coordinates":[-89.667852,37.380545],"type":"Point"}
}