{
  "type": "Feature",
  "properties": {
    "iso:country":"US",
    "sg:address":"201 Enchanted Pkwy",
    "sg:city":"Ballwin",
    "sg:classifiers":[
        {
            "category":"Health Services",
            "subcategory":"Chiropractor",
            "type":"Services"
        }
    ],
    "sg:phone":"+1 636 227 4151",
    "sg:postcode":"63021",
    "sg:province":"MO",
    "sg:tags":[
        "chiropractic"
    ],
    "sg:website":"http://www.drmarquart.com",
    "wof:name":"Primary Care Chiropractic",
    "wof:placetype":"venue"
},
  "geometry": {"coordinates":[-90.501953,38.590111],"type":"Point"}
}