{
  "type": "Feature",
  "properties": {
    "iso:country":"US",
    "sg:address":"401 S Wells St",
    "sg:city":"Butler",
    "sg:classifiers":[
        {
            "category":"Manufacturing",
            "subcategory":"Buildings",
            "type":"Manufacturing & Wholesale Goods"
        },
        {
            "category":"Building & Trades",
            "subcategory":"Construction",
            "type":"Services"
        }
    ],
    "sg:phone":"+1 660 679 0820",
    "sg:postcode":"64730",
    "sg:province":"MO",
    "sg:tags":[
        "home",
        "builder",
        "contractor"
    ],
    "wof:name":"Straightline Custom Construction",
    "wof:placetype":"venue"
},
  "geometry": {"coordinates":[-94.325087,38.251943],"type":"Point"}
}