{
  "type": "Feature",
  "properties": {
    "iso:country":"US",
    "sg:address":"104 E Center St",
    "sg:city":"Salem",
    "sg:classifiers":[
        {
            "category":"Shopping",
            "subcategory":"Used Merchandise",
            "type":"Retail Goods"
        }
    ],
    "sg:phone":"+1 573 729 2862",
    "sg:postcode":"65560",
    "sg:province":"MO",
    "wof:name":"Teddy Bear Shop",
    "wof:placetype":"venue"
},
  "geometry": {"coordinates":[-91.536025,37.64327],"type":"Point"}
}