{
  "type": "Feature",
  "properties": {
    "iso:country":"US",
    "sg:address":"12697 W State Hwy Tt",
    "sg:city":"Republic",
    "sg:classifiers":[
        {
            "category":"Shopping",
            "subcategory":"Bicycles & Sporting Goods",
            "type":"Retail Goods"
        }
    ],
    "sg:phone":"+1 417 732 7302",
    "sg:postcode":"65738",
    "sg:province":"MO",
    "sg:tags":[
        "firearm"
    ],
    "wof:name":"Ernst Gun Co",
    "wof:placetype":"venue"
},
  "geometry": {"coordinates":[-93.553214,37.156341],"type":"Point"}
}