{
  "type": "Feature",
  "properties": {
    "iso:country":"US",
    "sg:address":"400 Frisco St",
    "sg:city":"Monett",
    "sg:classifiers":[
        {
            "category":"Retail",
            "subcategory":"Laundry & Dry Cleaning",
            "type":"Services"
        },
        {
            "category":"Building & Trades",
            "subcategory":"Cleaning & Sanitation",
            "type":"Services"
        }
    ],
    "sg:phone":"+1 417 489 4110",
    "sg:postcode":"65708",
    "sg:province":"MO",
    "sg:tags":[
        "cleaner",
        "house"
    ],
    "wof:name":"Executive Office Cleaning",
    "wof:placetype":"venue"
},
  "geometry": {"coordinates":[-93.92881,36.921612],"type":"Point"}
}