{
  "type": "Feature",
  "properties": {
    "iso:country":"US",
    "sg:address":"20 Goodwin Dr",
    "sg:city":"Crystal City",
    "sg:classifiers":[
        {
            "category":"Freight",
            "type":"Transportation"
        }
    ],
    "sg:phone":"+1 636 937 0130",
    "sg:postcode":"63028",
    "sg:province":"MO",
    "sg:tags":[
        "courier"
    ],
    "wof:name":"UPS",
    "wof:placetype":"venue"
},
  "geometry": {"coordinates":[-90.390837,38.19989],"type":"Point"}
}