{
  "type": "Feature",
  "properties": {
    "iso:country":"US",
    "sg:address":"1902 W Jesse James Rd",
    "sg:city":"Excelsior Springs",
    "sg:classifiers":[
        {
            "category":"Shopping",
            "subcategory":"Computers & Home Electronics",
            "type":"Retail Goods"
        }
    ],
    "sg:phone":"+1 816 630 4411",
    "sg:postcode":"64024",
    "sg:province":"MO",
    "wof:name":"Dish Ntwrk By Primetime Entrmt",
    "wof:placetype":"venue"
},
  "geometry": {"coordinates":[-94.252447,39.336801],"type":"Point"}
}