{
  "type": "Feature",
  "properties": {
    "iso:country":"US",
    "sg:address":"929 Hanley Industrial Ct",
    "sg:city":"St Louis",
    "sg:classifiers":[
        {
            "category":"Wholesale",
            "subcategory":"Electrical",
            "type":"Manufacturing & Wholesale Goods"
        }
    ],
    "sg:phone":"+1 314 961 6729",
    "sg:postcode":"63144",
    "sg:province":"MO",
    "sg:tags":[
        "equipment",
        "electric",
        "supply"
    ],
    "wof:name":"Metro Lighting",
    "wof:placetype":"venue"
},
  "geometry": {"coordinates":[-90.342562,38.624384],"type":"Point"}
}