{
  "type": "Feature",
  "properties": {
    "iso:country":"US",
    "sg:address":"4 Wycliffe Ct",
    "sg:city":"St Charles",
    "sg:classifiers":[
        {
            "category":"Real Estate",
            "subcategory":"Real Estate Operator",
            "type":"Services"
        }
    ],
    "sg:phone":"+1 636 329 8400",
    "sg:postcode":"63304",
    "sg:province":"MO",
    "sg:tags":[
        "mobile",
        "home",
        "community"
    ],
    "wof:name":"Fairview Manor Mobile Home Lot",
    "wof:placetype":"venue"
},
  "geometry": {"coordinates":[-90.67035199999999,38.70981],"type":"Point"}
}