{
  "type": "Feature",
  "properties": {
    "iso:country":"US",
    "sg:address":"217 N Main St",
    "sg:city":"Maryville",
    "sg:classifiers":[
        {
            "category":"Professional",
            "type":"Services"
        }
    ],
    "sg:phone":"+1 660 582 3286",
    "sg:postcode":"64468",
    "sg:province":"MO",
    "sg:tags":[
        "establishment"
    ],
    "wof:name":"Loucks & Assoc",
    "wof:placetype":"venue"
},
  "geometry": {"coordinates":[-94.872826,40.347754],"type":"Point"}
}