{
  "type": "Feature",
  "properties": {
    "iso:country":"US",
    "sg:address":"2144 Market St",
    "sg:city":"Saint Louis",
    "sg:classifiers":[
        {
            "category":"Building & Trades",
            "subcategory":"Locksmith",
            "type":"Services"
        }
    ],
    "sg:phone":"+1 314 735 0977",
    "sg:postcode":"63103",
    "sg:province":"MO",
    "sg:tags":[
        "key"
    ],
    "wof:name":"Locksmith & Locks-24 7 Emergency",
    "wof:placetype":"venue"
},
  "geometry": {"coordinates":[-90.211867,38.630263],"type":"Point"}
}