{
  "type": "Feature",
  "properties": {
    "iso:country":"US",
    "sg:address":"720 Lavinia Pl",
    "sg:city":"Kirkwood",
    "sg:classifiers":[
        {
            "category":"Professional",
            "subcategory":"Business Services",
            "type":"Services"
        }
    ],
    "sg:phone":"+1 314 835 1777",
    "sg:postcode":"63122",
    "sg:province":"MO",
    "sg:tags":[
        "appraiser"
    ],
    "wof:name":"Appraisemyhome Net",
    "wof:placetype":"venue"
},
  "geometry": {"coordinates":[-90.436291,38.571283],"type":"Point"}
}