{
  "type": "Feature",
  "properties": {
    "iso:country":"US",
    "sg:address":"1209 Mill St",
    "sg:city":"Cassville",
    "sg:classifiers":[
        {
            "category":"Building & Trades",
            "subcategory":"Construction",
            "type":"Services"
        }
    ],
    "sg:phone":"+1 417 847 4542",
    "sg:postcode":"65625",
    "sg:province":"MO",
    "sg:tags":[
        "downspouts",
        "gutter"
    ],
    "wof:name":"Cross Seamless Guttering",
    "wof:placetype":"venue"
},
  "geometry": {"coordinates":[-93.86412799999999,36.683433],"type":"Point"}
}