{
  "type": "Feature",
  "properties": {
    "iso:country":"US",
    "sg:address":"1041 S Vista Dr",
    "sg:city":"Independence",
    "sg:classifiers":[
        {
            "category":"Wholesale",
            "subcategory":"Machinery & Supplies",
            "type":"Manufacturing & Wholesale Goods"
        }
    ],
    "sg:phone":"+1 816 796 0909",
    "sg:postcode":"64056",
    "sg:province":"MO",
    "sg:tags":[
        "equipment",
        "industrial"
    ],
    "wof:name":"All Type Parts & Equip Inc",
    "wof:placetype":"venue"
},
  "geometry": {"coordinates":[-94.3653,39.094163],"type":"Point"}
}