{
  "type": "Feature",
  "properties": {
    "iso:country":"US",
    "sg:address":"2912 S Forest Ave",
    "sg:city":"Independence",
    "sg:classifiers":[
        {
            "category":"Retail",
            "subcategory":"Auto Repair",
            "type":"Services"
        }
    ],
    "sg:phone":"+1 816 716 9003",
    "sg:postcode":"64052",
    "sg:province":"MO",
    "sg:tags":[
        "body"
    ],
    "wof:name":"Advance Dent Repair",
    "wof:placetype":"venue"
},
  "geometry": {"coordinates":[-94.436944,39.067872],"type":"Point"}
}