{
  "type": "Feature",
  "properties": {
    "iso:country":"US",
    "sg:address":"1201 Pinewood Dr",
    "sg:city":"Pacific",
    "sg:classifiers":[
        {
            "category":"Manufacturing",
            "subcategory":"Buildings",
            "type":"Manufacturing & Wholesale Goods"
        },
        {
            "category":"Building & Trades",
            "subcategory":"Construction",
            "type":"Services"
        }
    ],
    "sg:phone":"+1 636 575 4115",
    "sg:postcode":"63069",
    "sg:province":"MO",
    "sg:tags":[
        "home",
        "builder",
        "contractor"
    ],
    "wof:name":"Hartupee Construction",
    "wof:placetype":"venue"
},
  "geometry": {"coordinates":[-90.75402099999999,38.476521],"type":"Point"}
}