{
  "type": "Feature",
  "properties": {
    "iso:country":"US",
    "sg:address":"431 Brown Rd",
    "sg:city":"Saint Peters",
    "sg:phone":"+1 636 970 6400",
    "sg:postcode":"63376",
    "sg:province":"MO",
    "sg:tags":[
        "food",
        "distributor",
        "importer",
        "specialty"
    ],
    "wof:name":"Eurogourmet",
    "wof:placetype":"venue"
},
  "geometry": {"coordinates":[-90.64676900000001,38.80375],"type":"Point"}
}