{
  "type": "Feature",
  "properties": {
    "iso:country":"US",
    "sg:address":"7632 N Oak Fwy",
    "sg:city":"Kansas City",
    "sg:classifiers":[
        {
            "category":"Bars & Pubs",
            "type":"Food & Drink"
        }
    ],
    "sg:phone":"+1 816 468 9611",
    "sg:postcode":"64118",
    "sg:province":"MO",
    "sg:tags":[
        "drinking"
    ],
    "wof:name":"End Zone The",
    "wof:placetype":"venue"
},
  "geometry": {"coordinates":[-94.57613000000001,39.233844],"type":"Point"}
}