{
  "type": "Feature",
  "properties": {
    "iso:country":"US",
    "sg:address":"5751 Goodfellow Pl",
    "sg:city":"Saint Louis",
    "sg:classifiers":[
        {
            "category":"Real Estate",
            "subcategory":"Real Estate Operator",
            "type":"Services"
        }
    ],
    "sg:phone":"+1 314 381 5780",
    "sg:postcode":"63120",
    "sg:province":"MO",
    "sg:tags":[
        "apartment"
    ],
    "wof:name":"Goodfellow Place Apartments",
    "wof:placetype":"venue"
},
  "geometry": {"coordinates":[-90.27220800000001,38.681799],"type":"Point"}
}