{
  "type": "Feature",
  "properties": {
    "iso:country":"US",
    "sg:address":"302 E Kearney St",
    "sg:city":"Springfield",
    "sg:classifiers":[
        {
            "category":"Autos & Motor Vehicles",
            "subcategory":"Auto Supplies",
            "type":"Retail Goods"
        }
    ],
    "sg:phone":"+1 417 866 6060",
    "sg:postcode":"65803",
    "sg:province":"MO",
    "sg:tags":[
        "upholstery-wholesale",
        "upholstery",
        "automobile",
        "top",
        "covers",
        "seat",
        "part",
        "manufacturer"
    ],
    "wof:name":"Bear Auto Trim",
    "wof:placetype":"venue"
},
  "geometry": {"coordinates":[-93.29236,37.240694],"type":"Point"}
}