{
  "type": "Feature",
  "properties": {
    "iso:country":"US",
    "sg:address":"410 S Belt Hwy",
    "sg:city":"Saint Joseph",
    "sg:classifiers":[
        {
            "category":"Building & Trades",
            "subcategory":"Equipment Rental",
            "type":"Services"
        }
    ],
    "sg:phone":"+1 816 233 8253",
    "sg:postcode":"64506",
    "sg:province":"MO",
    "sg:tags":[
        "heavy",
        "construction"
    ],
    "wof:name":"Belt Rental",
    "wof:placetype":"venue"
},
  "geometry": {"coordinates":[-94.80380700000001,39.763466],"type":"Point"}
}