{
  "type": "Feature",
  "properties": {
    "iso:country":"US",
    "sg:address":"116 Oak St",
    "sg:city":"Mountain View",
    "sg:classifiers":[
        {
            "category":"Home & Garden",
            "subcategory":"Home Furnishings",
            "type":"Retail Goods"
        }
    ],
    "sg:phone":"+1 417 934 6330",
    "sg:postcode":"65548",
    "sg:province":"MO",
    "sg:tags":[
        "quilting"
    ],
    "wof:name":"Calico Cupboard Quilt Shop",
    "wof:placetype":"venue"
},
  "geometry": {"coordinates":[-91.70275700000001,36.99573],"type":"Point"}
}