{
  "type": "Feature",
  "properties": {
    "iso:country":"US",
    "sg:address":"803 W Austin Blvd",
    "sg:city":"Nevada",
    "sg:classifiers":[
        {
            "category":"Utilities",
            "subcategory":"Telephone",
            "type":"Services"
        }
    ],
    "sg:phone":"+1 417 667 5598",
    "sg:postcode":"64772",
    "sg:province":"MO",
    "sg:tags":[
        "communications"
    ],
    "wof:name":"Kits Central Inc",
    "wof:placetype":"venue"
},
  "geometry": {"coordinates":[-94.36758,37.837359],"type":"Point"}
}