{
  "type": "Feature",
  "properties": {
    "iso:country":"US",
    "sg:address":"9899 Halls Ferry Rd",
    "sg:city":"St Louis",
    "sg:classifiers":[
        {
            "category":"Retail",
            "subcategory":"Auto Repair",
            "type":"Services"
        }
    ],
    "sg:phone":"+1 314 868 3131",
    "sg:postcode":"63136",
    "sg:province":"MO",
    "sg:tags":[
        "repairing",
        "automobile",
        "general"
    ],
    "wof:name":"Keane's Auto Repair",
    "wof:placetype":"venue"
},
  "geometry": {"coordinates":[-90.252195,38.742475],"type":"Point"}
}