{
  "type": "Feature",
  "properties": {
    "iso:country":"US",
    "sg:address":"19720 Farm Road 1065",
    "sg:city":"Exeter",
    "sg:classifiers":[
        {
            "category":"Transit Center",
            "subcategory":"Freight",
            "type":"Transportation"
        },
        {
            "category":"Freight",
            "type":"Transportation"
        }
    ],
    "sg:phone":"+1 417 835 2002",
    "sg:postcode":"65647",
    "sg:province":"MO",
    "sg:tags":[
        "local",
        "trucking-motor",
        "trucking"
    ],
    "wof:name":"Schreiner Trucking",
    "wof:placetype":"venue"
},
  "geometry": {"coordinates":[-93.954823,36.669846],"type":"Point"}
}