{
  "type": "Feature",
  "properties": {
    "iso:country":"US",
    "sg:address":"203 N Harrison St",
    "sg:city":"Freeman",
    "sg:classifiers":[
        {
            "category":"Professional",
            "subcategory":"Art Services",
            "type":"Services"
        }
    ],
    "sg:phone":"+1 816 442 4644",
    "sg:postcode":"64746",
    "sg:province":"MO",
    "sg:tags":[
        "designer",
        "display",
        "producer"
    ],
    "wof:name":"Insurance Concepts By Angie",
    "wof:placetype":"venue"
},
  "geometry": {"coordinates":[-94.50753,38.618277],"type":"Point"}
}