{
  "type": "Feature",
  "properties": {
    "iso:country":"US",
    "sg:address":"75 Fair Oaks",
    "sg:city":"Saint Louis",
    "sg:classifiers":[
        {
            "category":"Professional",
            "subcategory":"Management & Consulting",
            "type":"Services"
        }
    ],
    "sg:phone":"+1 314 994 1766",
    "sg:postcode":"63124",
    "sg:province":"MO",
    "wof:name":"Airway & Airport Consultants",
    "wof:placetype":"venue"
},
  "geometry": {"coordinates":[-90.36285599999999,38.63545],"type":"Point"}
}