{
  "type": "Feature",
  "properties": {
    "iso:country":"US",
    "sg:address":"11245 Hilltop Ln",
    "sg:city":"Joplin",
    "sg:classifiers":[
        {
            "category":"Building & Trades",
            "subcategory":"Construction",
            "type":"Services"
        }
    ],
    "sg:phone":"+1 417 659 8098",
    "sg:postcode":"64804",
    "sg:province":"MO",
    "sg:tags":[
        "carpentry",
        "contractor"
    ],
    "wof:name":"Spring City Cabinets",
    "wof:placetype":"venue"
},
  "geometry": {"coordinates":[-94.43697299999999,37.009409],"type":"Point"}
}