{
  "type": "Feature",
  "properties": {
    "iso:country":"US",
    "sg:address":"4406 NE 45 Ter",
    "sg:city":"Kansas City",
    "sg:classifiers":[
        {
            "category":"Organizations",
            "subcategory":"Religious Organization",
            "type":"Services"
        }
    ],
    "sg:phone":"+1 816 452 6181",
    "sg:postcode":"64117",
    "sg:province":"MO",
    "sg:tags":[
        "church"
    ],
    "wof:name":"Winnwood United Methodist Chr",
    "wof:placetype":"venue"
},
  "geometry": {"coordinates":[-94.527495,39.176491],"type":"Point"}
}