{
  "type": "Feature",
  "properties": {
    "iso:country":"US",
    "sg:address":"1695 SE Decker",
    "sg:city":"Lees Summit",
    "sg:classifiers":[
        {
            "category":"Manufacturing",
            "subcategory":"Metals",
            "type":"Manufacturing & Wholesale Goods"
        },
        {
            "category":"Manufacturing",
            "subcategory":"Tools & Machinery",
            "type":"Manufacturing & Wholesale Goods"
        }
    ],
    "sg:phone":"+1 816 524 8884",
    "sg:postcode":"64081",
    "sg:province":"MO",
    "sg:tags":[
        "machine",
        "shop",
        "machining",
        "fabrication"
    ],
    "sg:website":"www.heartlandfab.com",
    "wof:name":"Heartland Fabrication and Mch",
    "wof:placetype":"venue"
},
  "geometry": {"coordinates":[-94.371561,38.892387],"type":"Point"}
}