{
  "type": "Feature",
  "properties": {
    "iso:country":"US",
    "sg:address":"3548 S Campbell Ave",
    "sg:city":"Springfield",
    "sg:classifiers":[
        {
            "category":"Banks & Credit Unions",
            "subcategory":"Bank",
            "type":"Services"
        }
    ],
    "sg:phone":"+1 417 890 7624",
    "sg:postcode":"65807",
    "sg:province":"MO",
    "sg:tags":[
        "personal",
        "institution"
    ],
    "wof:name":"Advance America",
    "wof:placetype":"venue"
},
  "geometry": {"coordinates":[-93.29562799999999,37.152959],"type":"Point"}
}