{
  "type": "Feature",
  "properties": {
    "iso:country":"US",
    "sg:address":"510 N Missouri St Ste A",
    "sg:city":"Macon",
    "sg:classifiers":[
        {
            "category":"Insurance",
            "subcategory":"Hazard Insurance",
            "type":"Services"
        }
    ],
    "sg:phone":"+1 660 385 6461",
    "sg:postcode":"63552",
    "sg:province":"MO",
    "sg:website":"http://statefarm.mqgroup.com/url.asp?usr=253504",
    "wof:name":"State Farm Insurance Agent-Keith Morrissey",
    "wof:placetype":"venue"
},
  "geometry": {"coordinates":[-92.465158,39.742455],"type":"Point"}
}