{
  "type": "Feature",
  "properties": {
    "iso:country":"US",
    "sg:address":"2781 Co Rd 233",
    "sg:city":"Kingdom City",
    "sg:phone":"+1 573 642 4522",
    "sg:postcode":"65262",
    "sg:province":"MO",
    "sg:tags":[
        "farm",
        "grain",
        "cash"
    ],
    "wof:name":"George Lewis Trucking",
    "wof:placetype":"venue"
},
  "geometry": {"coordinates":[-91.994319,38.960431],"type":"Point"}
}