{
  "type": "Feature",
  "properties": {
    "iso:country":"US",
    "sg:address":"4210 S Noland Rd",
    "sg:city":"Independence",
    "sg:classifiers":[
        {
            "category":"Restaurant",
            "type":"Food & Drink"
        }
    ],
    "sg:menulink":"http://www.allmenus.com/mo/blue/183123-kfc---kentucky-fried-chicken/menu/",
    "sg:phone":"+1 816 373 4707",
    "sg:postcode":"64055",
    "sg:province":"MO",
    "sg:tags":[
        "american",
        "chicken"
    ],
    "wof:name":"KFC - Kentucky Fried Chicken",
    "wof:placetype":"venue"
},
  "geometry": {"coordinates":[-94.41552299999999,39.043683],"type":"Point"}
}