{
  "type": "Feature",
  "properties": {
    "addr:full":"1291 Banning St Marshfield MO 65706",
    "addr:housenumber":"1291",
    "addr:postcode":"65706",
    "addr:street":"Banning St",
    "iso:country":"US",
    "sg:address":"1291 Banning St",
    "sg:city":"Marshfield",
    "sg:classifiers":[
        {
            "category":"Restaurant",
            "type":"Food & Drink"
        }
    ],
    "sg:phone":"+1 417 859 2945",
    "sg:postcode":"65706",
    "sg:province":"MO",
    "wof:name":"Long John Silver's",
    "wof:placetype":"venue"
},
  "geometry": {"coordinates":[-92.92512499999999,37.346776],"type":"Point"}
}