{
  "type": "Feature",
  "properties": {
    "iso:country":"US",
    "sg:address":"1228 S Main St",
    "sg:city":"St Charles",
    "sg:classifiers":[
        {
            "category":"Professional",
            "type":"Services"
        }
    ],
    "sg:phone":"+1 636 940 4044",
    "sg:postcode":"63301",
    "sg:province":"MO",
    "sg:tags":[
        "establishment"
    ],
    "wof:name":"Hughes Tr Inc",
    "wof:placetype":"venue"
},
  "geometry": {"coordinates":[-90.487611,38.770285],"type":"Point"}
}