{
  "type": "Feature",
  "properties": {
    "iso:country":"US",
    "sg:address":"2520 Rte M",
    "sg:city":"Jefferson City",
    "sg:classifiers":[
        {
            "category":"Wholesale",
            "subcategory":"Scrap",
            "type":"Manufacturing & Wholesale Goods"
        }
    ],
    "sg:phone":"+1 573 395 4646",
    "sg:postcode":"65101",
    "sg:province":"MO",
    "sg:tags":[
        "material"
    ],
    "wof:name":"Lake Road Car Crushers Inc",
    "wof:placetype":"venue"
},
  "geometry": {"coordinates":[-92.157027,38.488244],"type":"Point"}
}