{
  "type": "Feature",
  "properties": {
    "iso:country":"US",
    "sg:address":"645 Union Rd",
    "sg:city":"Saint Louis",
    "sg:classifiers":[
        {
            "category":"Autos & Motor Vehicles",
            "subcategory":"Fuel & Gas Station",
            "type":"Retail Goods"
        }
    ],
    "sg:phone":"+1 314 631 8947",
    "sg:postcode":"63123",
    "sg:province":"MO",
    "sg:tags":[
        "station",
        "gasoline"
    ],
    "wof:name":"Union-Weber Shell",
    "wof:placetype":"venue"
},
  "geometry": {"coordinates":[-90.293291,38.549112],"type":"Point"}
}