{
  "type": "Feature",
  "properties": {
    "iso:country":"US",
    "sg:address":"1020 Van Dyke Dr",
    "sg:city":"Ballwin",
    "sg:classifiers":[
        {
            "category":"Farming",
            "subcategory":"Livestock Farm",
            "type":"Manufacturing & Wholesale Goods"
        }
    ],
    "sg:phone":"+1 636 227 7375",
    "sg:postcode":"63011",
    "sg:province":"MO",
    "sg:tags":[
        "beef",
        "equine",
        "feedlot",
        "cattle"
    ],
    "wof:name":"Calzone Aim",
    "wof:placetype":"venue"
},
  "geometry": {"coordinates":[-90.51017899999999,38.611701],"type":"Point"}
}