{
  "type": "Feature",
  "properties": {
    "addr:full":"200 S State Hwy 125 Strafford MO 65757",
    "addr:housenumber":"200",
    "addr:postcode":"65757",
    "addr:street":"S State Hwy 125",
    "iso:country":"US",
    "sg:address":"200 S State Hwy 125",
    "sg:city":"Strafford",
    "sg:classifiers":[
        {
            "category":"Personal",
            "subcategory":"Beauty Salon",
            "type":"Services"
        }
    ],
    "sg:phone":"+1 417 736 3353",
    "sg:postcode":"65757",
    "sg:province":"MO",
    "wof:name":"Cutting Room",
    "wof:placetype":"venue"
},
  "geometry": {"coordinates":[-93.11359,37.2694],"type":"Point"}
}