{
  "type": "Feature",
  "properties": {
    "iso:country":"US",
    "sg:address":"407 State Hwy J",
    "sg:city":"Malden",
    "sg:classifiers":[
        {
            "category":"Education",
            "subcategory":"School",
            "type":"Public Place"
        }
    ],
    "sg:phone":"+1 573 276 5794",
    "sg:postcode":"63863",
    "sg:province":"MO",
    "sg:tags":[
        "educational",
        "administrative"
    ],
    "wof:name":"Business Off",
    "wof:placetype":"venue"
},
  "geometry": {"coordinates":[-89.971383,36.563791],"type":"Point"}
}