{
  "type": "Feature",
  "properties": {
    "iso:country":"US",
    "sg:address":"828 E Franklin St",
    "sg:city":"Clinton",
    "sg:classifiers":[
        {
            "category":"Real Estate",
            "subcategory":"Real Estate Operator",
            "type":"Services"
        }
    ],
    "sg:phone":"+1 660 885 3984",
    "sg:postcode":"64735",
    "sg:province":"MO",
    "sg:tags":[
        "mobile",
        "home",
        "site"
    ],
    "wof:name":"Cee & Dee Mobile Court",
    "wof:placetype":"venue"
},
  "geometry": {"coordinates":[-93.762525,38.370186],"type":"Point"}
}