{
  "type": "Feature",
  "properties": {
    "iso:country":"US",
    "sg:address":"3652 State Hwy 123",
    "sg:city":"Dunnegan",
    "sg:classifiers":[
        {
            "category":"Farming",
            "subcategory":"Dairy Farm",
            "type":"Manufacturing & Wholesale Goods"
        }
    ],
    "sg:phone":"+1 417 754 2308",
    "sg:postcode":"65640",
    "sg:province":"MO",
    "wof:name":"Edgar Proctor",
    "wof:placetype":"venue"
},
  "geometry": {"coordinates":[-93.563152,37.729669],"type":"Point"}
}