{
  "type": "Feature",
  "properties": {
    "iso:country":"US",
    "sg:address":"1029 S Benton St",
    "sg:city":"Cape Girardeau",
    "sg:classifiers":[
        {
            "category":"Organizations",
            "subcategory":"Religious Organization",
            "type":"Services"
        }
    ],
    "sg:phone":"+1 573 335 3563",
    "sg:postcode":"63703",
    "sg:province":"MO",
    "sg:tags":[
        "church"
    ],
    "wof:name":"New Bethal Baptist Church",
    "wof:placetype":"venue"
},
  "geometry": {"coordinates":[-89.533038,37.290512],"type":"Point"}
}