{
  "type": "Feature",
  "properties": {
    "iso:country":"US",
    "sg:address":"4329 Manchester Ave",
    "sg:city":"Saint Louis",
    "sg:classifiers":[
        {
            "category":"Deli",
            "type":"Food & Drink"
        }
    ],
    "sg:phone":"+1 314 531 1833",
    "sg:postcode":"63110",
    "sg:province":"MO",
    "wof:name":"Sister Girls Deli",
    "wof:placetype":"venue"
},
  "geometry": {"coordinates":[-90.25749999999999,38.626801],"type":"Point"}
}