{
  "type": "Feature",
  "properties": {
    "iso:country":"US",
    "sg:address":"243 N Lindbergh Blvd",
    "sg:city":"St Louis",
    "sg:classifiers":[
        {
            "category":"Organizations",
            "subcategory":"Professional Association",
            "type":"Services"
        }
    ],
    "sg:phone":"+1 314 991 4007",
    "sg:postcode":"63141",
    "sg:province":"MO",
    "sg:website":"www.covd.org",
    "wof:name":"College-Optometrists In Vision",
    "wof:placetype":"venue"
},
  "geometry": {"coordinates":[-90.40531900000001,38.659933],"type":"Point"}
}