{
  "type": "Feature",
  "properties": {
    "addr:full":"450 Mill St New Madrid MO 63869",
    "addr:housenumber":"450",
    "addr:postcode":"63869",
    "addr:street":"Mill St",
    "iso:country":"US",
    "sg:address":"450 Mill St",
    "sg:city":"New Madrid",
    "sg:classifiers":[
        {
            "category":"Government",
            "subcategory":"Post Office",
            "type":"Public Place"
        }
    ],
    "sg:phone":"+1 573 748 5130",
    "sg:postcode":"63869",
    "sg:province":"MO",
    "sg:tags":[
        "postal",
        "us"
    ],
    "wof:name":"US Post Office",
    "wof:placetype":"venue"
},
  "geometry": {"coordinates":[-89.52614800000001,36.586156],"type":"Point"}
}