{
  "type": "Feature",
  "properties": {
    "iso:country":"US",
    "sg:address":"12209 Big Bend Rd",
    "sg:city":"Kirkwood",
    "sg:classifiers":[
        {
            "category":"Professional",
            "subcategory":"Lawyer & Legal Services",
            "type":"Services"
        }
    ],
    "sg:phone":"+1 314 909 7877",
    "sg:postcode":"63122",
    "sg:province":"MO",
    "sg:tags":[
        "attorney"
    ],
    "wof:name":"Hilton & Harford",
    "wof:placetype":"venue"
},
  "geometry": {"coordinates":[-90.435106,38.567338],"type":"Point"}
}