{
  "type": "Feature",
  "properties": {
    "iso:country":"US",
    "sg:address":"3115 Mitchell Ave",
    "sg:city":"Saint Joseph",
    "sg:classifiers":[
        {
            "category":"Freight",
            "type":"Transportation"
        }
    ],
    "sg:phone":"+1 816 279 4756",
    "sg:postcode":"64507",
    "sg:province":"MO",
    "sg:tags":[
        "operator",
        "local",
        "trucking"
    ],
    "wof:name":"R D Tracking",
    "wof:placetype":"venue"
},
  "geometry": {"coordinates":[-94.81553099999999,39.755335],"type":"Point"}
}