{
  "type": "Feature",
  "properties": {
    "iso:country":"US",
    "sg:address":"2627 Cherokee St",
    "sg:city":"Saint Louis",
    "sg:classifiers":[
        {
            "category":"Shopping",
            "subcategory":"Clothing, Apparel, & Fashions",
            "type":"Retail Goods"
        }
    ],
    "sg:phone":"+1 314 771 8252",
    "sg:postcode":"63118",
    "sg:province":"MO",
    "sg:tags":[
        "accessory",
        "clothing",
        "women's"
    ],
    "wof:name":"Touba Mbacke African Shop",
    "wof:placetype":"venue"
},
  "geometry": {"coordinates":[-90.226799,38.593399],"type":"Point"}
}