{
  "type": "Feature",
  "properties": {
    "iso:country":"US",
    "sg:address":"30192 State Hwy M",
    "sg:city":"Sedalia",
    "sg:classifiers":[
        {
            "category":"Wholesale",
            "subcategory":"Wine & Distilled Alcoholic Beverages",
            "type":"Manufacturing & Wholesale Goods"
        }
    ],
    "sg:phone":"+1 660 827 0151",
    "sg:postcode":"65301",
    "sg:province":"MO",
    "sg:tags":[
        "whole"
    ],
    "wof:name":"Tmw Wines LLC",
    "wof:placetype":"venue"
},
  "geometry": {"coordinates":[-93.163195,38.63036],"type":"Point"}
}