{
  "type": "Feature",
  "properties": {
    "iso:country":"US",
    "sg:address":"2708 Vermont Ave",
    "sg:city":"Joplin",
    "sg:classifiers":[
        {
            "category":"Organizations",
            "subcategory":"Membership Organization",
            "type":"Services"
        }
    ],
    "sg:phone":"+1 417 624 1257",
    "sg:postcode":"64804",
    "sg:province":"MO",
    "wof:name":"Julia Foundation",
    "wof:placetype":"venue"
},
  "geometry": {"coordinates":[-94.49810600000001,37.059407],"type":"Point"}
}