{
  "type": "Feature",
  "properties": {
    "iso:country":"US",
    "sg:address":"1700 Rainbow Blvd",
    "sg:city":"Excelsior Spgs",
    "sg:classifiers":[
        {
            "category":"Health Services",
            "subcategory":"Hospital",
            "type":"Services"
        }
    ],
    "sg:phone":"+1 816 630 6081",
    "sg:postcode":"64024",
    "sg:province":"MO",
    "sg:tags":[
        "home",
        "convalescent"
    ],
    "sg:website":"www.esmc.org",
    "wof:name":"Excelsior Springs Hospital Ctr",
    "wof:placetype":"venue"
},
  "geometry": {"coordinates":[-94.23666299999999,39.3636],"type":"Point"}
}