{
  "type": "Feature",
  "properties": {
    "iso:country":"US",
    "sg:address":"117 5th St",
    "sg:city":"Monett",
    "sg:classifiers":[
        {
            "category":"Professional",
            "subcategory":"Management & Consulting",
            "type":"Services"
        }
    ],
    "sg:phone":"+1 417 235 0919",
    "sg:postcode":"65708",
    "sg:province":"MO",
    "wof:name":"Therakare",
    "wof:placetype":"venue"
},
  "geometry": {"coordinates":[-93.921824,36.920554],"type":"Point"}
}