{
  "type": "Feature",
  "properties": {
    "iso:country":"US",
    "sg:address":"12031 McGee St",
    "sg:city":"Kansas City",
    "sg:classifiers":[
        {
            "category":"Professional",
            "subcategory":"Business Services",
            "type":"Services"
        }
    ],
    "sg:phone":"+1 816 943 8784",
    "sg:postcode":"64145",
    "sg:province":"MO",
    "wof:name":"S & S Partners",
    "wof:placetype":"venue"
},
  "geometry": {"coordinates":[-94.589865,38.908534],"type":"Point"}
}