{
  "type": "Feature",
  "properties": {
    "iso:country":"US",
    "sg:address":"300 Gunsmoke St",
    "sg:city":"Clinton",
    "sg:classifiers":[
        {
            "category":"Recreation",
            "type":"Entertainment"
        }
    ],
    "sg:phone":"+1 660 885 6556",
    "sg:postcode":"64735",
    "sg:province":"MO",
    "sg:tags":[
        "club",
        "membership",
        "operation"
    ],
    "wof:name":"Demming Duck Lodge Ltd",
    "wof:placetype":"venue"
},
  "geometry": {"coordinates":[-93.74928,38.372941],"type":"Point"}
}