{
  "type": "Feature",
  "properties": {
    "iso:country":"US",
    "sg:address":"1104 Main St",
    "sg:city":"Leadwood",
    "sg:classifiers":[
        {
            "category":"Banks & Credit Unions",
            "subcategory":"Financial Services",
            "type":"Services"
        }
    ],
    "sg:phone":"+1 573 431 2404",
    "sg:postcode":"63653",
    "sg:province":"MO",
    "sg:tags":[
        "consulting",
        "management",
        "age",
        "real estate",
        "investor"
    ],
    "wof:name":"M L S Investments",
    "wof:placetype":"venue"
},
  "geometry": {"coordinates":[-90.592085,37.861491],"type":"Point"}
}