{
  "type": "Feature",
  "properties": {
    "iso:country":"US",
    "sg:address":"111 Milwaukee Ave",
    "sg:city":"Lawson",
    "sg:classifiers":[
        {
            "category":"Building & Trades",
            "subcategory":"Electrical",
            "type":"Services"
        }
    ],
    "sg:phone":"+1 816 580 7964",
    "sg:postcode":"64062",
    "sg:province":"MO",
    "sg:tags":[
        "electrician"
    ],
    "wof:name":"Brothers In Christ Electric Inc.",
    "wof:placetype":"venue"
},
  "geometry": {"coordinates":[-94.204353,39.432072],"type":"Point"}
}