{
  "type": "Feature",
  "properties": {
    "iso:country":"US",
    "sg:address":"1001 S 12th St",
    "sg:city":"Bethany",
    "sg:classifiers":[
        {
            "category":"Personal",
            "subcategory":"Beauty Salon",
            "type":"Services"
        }
    ],
    "sg:phone":"+1 660 425 8222",
    "sg:postcode":"64424",
    "sg:province":"MO",
    "sg:tags":[
        "shop"
    ],
    "wof:name":"Gretchen's 12th Street Salon",
    "wof:placetype":"venue"
},
  "geometry": {"coordinates":[-94.038404,40.262772],"type":"Point"}
}