{
  "type": "Feature",
  "properties": {
    "iso:country":"US",
    "sg:address":"210 State Hwy 6",
    "sg:city":"Trenton",
    "sg:classifiers":[
        {
            "category":"Retail",
            "subcategory":"Veterinary Services",
            "type":"Services"
        }
    ],
    "sg:phone":"+1 660 359 9908",
    "sg:postcode":"64683",
    "sg:province":"MO",
    "wof:name":"Honey Creek Veterinary Hosp",
    "wof:placetype":"venue"
},
  "geometry": {"coordinates":[-93.616276,40.073637],"type":"Point"}
}