{
  "type": "Feature",
  "properties": {
    "iso:country":"US",
    "sg:address":"75 Village Square Shopping Center",
    "sg:city":"Hazelwood",
    "sg:classifiers":[
        {
            "category":"Education",
            "subcategory":"Vocational School",
            "type":"Public Place"
        }
    ],
    "sg:phone":"+1 314 731 5200",
    "sg:postcode":"63042",
    "sg:province":"MO",
    "sg:tags":[
        "secretarial"
    ],
    "wof:name":"Sanford-Brown College",
    "wof:placetype":"venue"
},
  "geometry": {"coordinates":[-90.360872,38.782468],"type":"Point"}
}