{
  "type": "Feature",
  "properties": {
    "iso:country":"US",
    "sg:address":"680 Crown Industrial Ct",
    "sg:city":"Chesterfield",
    "sg:classifiers":[
        {
            "category":"Home & Garden",
            "subcategory":"Furniture",
            "type":"Retail Goods"
        }
    ],
    "sg:phone":"+1 636 536 0100",
    "sg:postcode":"63005",
    "sg:province":"MO",
    "wof:name":"Global Heritage Inc",
    "wof:placetype":"venue"
},
  "geometry": {"coordinates":[-90.641272,38.668153],"type":"Point"}
}