{
  "type": "Feature",
  "properties": {
    "iso:country":"US",
    "sg:address":"465 N Taylor Ave",
    "sg:city":"Saint Louis",
    "sg:classifiers":[
        {
            "category":"Arena",
            "subcategory":"Sports Club",
            "type":"Entertainment"
        }
    ],
    "sg:phone":"+1 314 361 3600",
    "sg:postcode":"63108",
    "sg:province":"MO",
    "sg:tags":[
        "martial art"
    ],
    "wof:name":"The Martial Arts Institute",
    "wof:placetype":"venue"
},
  "geometry": {"coordinates":[-90.255441,38.647725],"type":"Point"}
}