{
  "type": "Feature",
  "properties": {
    "iso:country":"US",
    "sg:address":"1036 W Sunshine St",
    "sg:city":"Springfield",
    "sg:classifiers":[
        {
            "category":"Food & Beverages",
            "subcategory":"Groceries & Convenience Stores",
            "type":"Retail Goods"
        }
    ],
    "sg:phone":"+1 417 863 9968",
    "sg:postcode":"65807",
    "sg:province":"MO",
    "sg:tags":[
        "grocer"
    ],
    "wof:name":"LA Mexicana Tienda Latina",
    "wof:placetype":"venue"
},
  "geometry": {"coordinates":[-93.303934,37.182256],"type":"Point"}
}