{
  "type": "Feature",
  "properties": {
    "iso:country":"US",
    "sg:address":"35 Ross Rd",
    "sg:city":"Eldon",
    "sg:classifiers":[
        {
            "category":"Farming",
            "subcategory":"Farm",
            "type":"Manufacturing & Wholesale Goods"
        }
    ],
    "sg:phone":"+1 573 392 7379",
    "sg:postcode":"65026",
    "sg:province":"MO",
    "wof:name":"Lepper Farms",
    "wof:placetype":"venue"
},
  "geometry": {"coordinates":[-92.618222,38.352878],"type":"Point"}
}