{
  "type": "Feature",
  "properties": {
    "iso:country":"US",
    "sg:address":"15620 State Hwy 92",
    "sg:city":"Platte City",
    "sg:classifiers":[
        {
            "category":"Autos & Motor Vehicles",
            "subcategory":"Automobile Sales",
            "type":"Retail Goods"
        }
    ],
    "sg:phone":"+1 816 858 3420",
    "sg:postcode":"64079",
    "sg:province":"MO",
    "sg:tags":[
        "used"
    ],
    "wof:name":"Platte County Motors",
    "wof:placetype":"venue"
},
  "geometry": {"coordinates":[-94.79315099999999,39.375723],"type":"Point"}
}