{
  "type": "Feature",
  "properties": {
    "iso:country":"US",
    "sg:address":"235 Kerruish Pl",
    "sg:city":"Saint Louis",
    "sg:classifiers":[
        {
            "category":"Professional",
            "subcategory":"Engineering",
            "type":"Services"
        }
    ],
    "sg:phone":"+1 314 962 7267",
    "sg:postcode":"63119",
    "sg:province":"MO",
    "wof:name":"Paul F Probst Pe Service",
    "wof:placetype":"venue"
},
  "geometry": {"coordinates":[-90.35147000000001,38.589188],"type":"Point"}
}