{
  "type": "Feature",
  "properties": {
    "iso:country":"US",
    "sg:address":"4 Glaizeview Rd",
    "sg:city":"Chesterfield",
    "sg:classifiers":[
        {
            "category":"Arts & Performance",
            "subcategory":"Theater",
            "type":"Entertainment"
        }
    ],
    "sg:phone":"+1 314 362 6237",
    "sg:postcode":"63017",
    "sg:province":"MO",
    "sg:tags":[
        "group"
    ],
    "wof:name":"Skyfire Music",
    "wof:placetype":"venue"
},
  "geometry": {"coordinates":[-90.497895,38.628323],"type":"Point"}
}