{
  "type": "Feature",
  "properties": {
    "iso:country":"US",
    "sg:address":"1106 I- 70 Dr SW",
    "sg:city":"Columbia",
    "sg:classifiers":[
        {
            "category":"Autos & Motor Vehicles",
            "subcategory":"Automobile Sales",
            "type":"Retail Goods"
        }
    ],
    "sg:phone":"+1 573 441 1958",
    "sg:postcode":"65203",
    "sg:province":"MO",
    "sg:tags":[
        "car",
        "dealer"
    ],
    "wof:name":"Columbia Car Classics",
    "wof:placetype":"venue"
},
  "geometry": {"coordinates":[-92.35428400000001,38.964843],"type":"Point"}
}