{
  "type": "Feature",
  "properties": {
    "iso:country":"US",
    "sg:address":"9853 Richter Ln",
    "sg:city":"Saint Louis",
    "sg:classifiers":[
        {
            "category":"Utilities",
            "subcategory":"Telephone",
            "type":"Services"
        }
    ],
    "sg:phone":"+1 314 849 0919",
    "sg:postcode":"63126",
    "sg:province":"MO",
    "sg:tags":[
        "communications"
    ],
    "wof:name":"Christ Quest",
    "wof:placetype":"venue"
},
  "geometry": {"coordinates":[-90.385155,38.549874],"type":"Point"}
}