{
  "type": "Feature",
  "properties": {
    "iso:country":"US",
    "sg:address":"4014 S Lynn Court Dr",
    "sg:city":"Independence",
    "sg:classifiers":[
        {
            "category":"Insurance",
            "subcategory":"Insurance Agent",
            "type":"Services"
        }
    ],
    "sg:phone":"+1 816 478 1115",
    "sg:postcode":"64055",
    "sg:province":"MO",
    "wof:name":"American Family Insurance",
    "wof:placetype":"venue"
},
  "geometry": {"coordinates":[-94.415885,39.047911],"type":"Point"}
}