{
  "type": "Feature",
  "properties": {
    "iso:country":"US",
    "sg:address":"76 W Arrow St",
    "sg:city":"Marshall",
    "sg:classifiers":[
        {
            "category":"Shopping",
            "subcategory":"Jewelry",
            "type":"Retail Goods"
        }
    ],
    "sg:phone":"+1 660 886 3650",
    "sg:postcode":"65340",
    "sg:province":"MO",
    "sg:tags":[
        "repair"
    ],
    "wof:name":"Reid Jewelry",
    "wof:placetype":"venue"
},
  "geometry": {"coordinates":[-93.19710600000001,39.120275],"type":"Point"}
}