{
  "type": "Feature",
  "properties": {
    "iso:country":"US",
    "sg:address":"4311 McMillen Rd",
    "sg:city":"De Soto",
    "sg:classifiers":[
        {
            "category":"Organizations",
            "subcategory":"Religious Organization",
            "type":"Services"
        }
    ],
    "sg:phone":"+1 636 586 1800",
    "sg:postcode":"63020",
    "sg:province":"MO",
    "sg:tags":[
        "church"
    ],
    "wof:name":"Rose Of Sharon Full Gospel",
    "wof:placetype":"venue"
},
  "geometry": {"coordinates":[-90.55431,38.167601],"type":"Point"}
}