{
  "type": "Feature",
  "properties": {
    "iso:country":"US",
    "sg:address":"10741 W Florissant Ave",
    "sg:city":"St Louis",
    "sg:classifiers":[
        {
            "category":"Shopping",
            "subcategory":"Department Store",
            "type":"Retail Goods"
        }
    ],
    "sg:phone":"+1 314 521 3422",
    "sg:postcode":"63136",
    "sg:province":"MO",
    "sg:tags":[
        "automotive",
        "r",
        "repair"
    ],
    "wof:name":"Wal-Mart",
    "wof:placetype":"venue"
},
  "geometry": {"coordinates":[-90.280411,38.768322],"type":"Point"}
}