{
  "type": "Feature",
  "properties": {
    "iso:country":"US",
    "sg:address":"215 E Main St",
    "sg:city":"Sedalia",
    "sg:classifiers":[
        {
            "category":"Retail",
            "subcategory":"Repair Shop",
            "type":"Services"
        }
    ],
    "sg:phone":"+1 660 826 9211",
    "sg:postcode":"65301",
    "sg:province":"MO",
    "sg:tags":[
        "welding"
    ],
    "wof:name":"Al's Portable Welding Svc",
    "wof:placetype":"venue"
},
  "geometry": {"coordinates":[-93.22628400000001,38.710536],"type":"Point"}
}