{
  "type": "Feature",
  "properties": {
    "iso:country":"US",
    "sg:address":"1090 East Rd",
    "sg:city":"Goodman",
    "sg:classifiers":[
        {
            "category":"Insurance",
            "subcategory":"Hazard Insurance",
            "type":"Services"
        }
    ],
    "sg:phone":"+1 417 364 8289",
    "sg:postcode":"64843",
    "sg:province":"MO",
    "wof:name":"Larry Daniel Forcum",
    "wof:placetype":"venue"
},
  "geometry": {"coordinates":[-94.405769,36.699503],"type":"Point"}
}