{
  "type": "Feature",
  "properties": {
    "iso:country":"US",
    "sg:address":"31 New Sugar Creek Rd",
    "sg:city":"Fenton",
    "sg:classifiers":[
        {
            "category":"Building & Trades",
            "subcategory":"Construction",
            "type":"Services"
        }
    ],
    "sg:phone":"+1 636 343 1727",
    "sg:postcode":"63026",
    "sg:province":"MO",
    "sg:tags":[
        "heavy"
    ],
    "wof:name":"Don Rector Construction",
    "wof:placetype":"venue"
},
  "geometry": {"coordinates":[-90.49278,38.498],"type":"Point"}
}