{
  "type": "Feature",
  "properties": {
    "iso:country":"US",
    "sg:address":"432 Lancashire Rd",
    "sg:city":"St Louis",
    "sg:classifiers":[
        {
            "category":"Health Services",
            "subcategory":"Clinic",
            "type":"Services"
        }
    ],
    "sg:phone":"+1 314 869 7029",
    "sg:postcode":"63137",
    "sg:province":"MO",
    "sg:tags":[
        "home"
    ],
    "wof:name":"One On One Home Svc",
    "wof:placetype":"venue"
},
  "geometry": {"coordinates":[-90.203658,38.754601],"type":"Point"}
}