{
  "type": "Feature",
  "properties": {
    "iso:country":"US",
    "sg:address":"2914 Harper St",
    "sg:city":"St Louis",
    "sg:classifiers":[
        {
            "category":"Building & Trades",
            "subcategory":"Construction",
            "type":"Services"
        }
    ],
    "sg:phone":"+1 314 531 5632",
    "sg:postcode":"63107",
    "sg:province":"MO",
    "sg:tags":[
        "home",
        "improvement"
    ],
    "wof:name":"Express Home Maintenance",
    "wof:placetype":"venue"
},
  "geometry": {"coordinates":[-90.21394100000001,38.660825],"type":"Point"}
}