{
  "type": "Feature",
  "properties": {
    "iso:country":"US",
    "sg:address":"675 Barrett Rd",
    "sg:city":"Elsberry",
    "sg:classifiers":[
        {
            "category":"Professional",
            "subcategory":"Management & Consulting",
            "type":"Services"
        }
    ],
    "sg:phone":"+1 573 898 2116",
    "sg:postcode":"63343",
    "sg:province":"MO",
    "sg:tags":[
        "farm"
    ],
    "wof:name":"Karl Shannon",
    "wof:placetype":"venue"
},
  "geometry": {"coordinates":[-90.93056,39.115203],"type":"Point"}
}