{
  "type": "Feature",
  "properties": {
    "addr:full":"6240 McKissock Ave St Louis MO 63147",
    "addr:housenumber":"6240",
    "addr:postcode":"63147",
    "addr:street":"Mckissock Ave",
    "iso:country":"US",
    "sg:address":"6240 McKissock Ave",
    "sg:city":"St Louis",
    "sg:classifiers":[
        {
            "category":"Utilities",
            "subcategory":"Refuse",
            "type":"Services"
        }
    ],
    "sg:phone":"+1 314 381 0059",
    "sg:postcode":"63147",
    "sg:province":"MO",
    "sg:tags":[
        "waste",
        "removal"
    ],
    "wof:name":"BFI",
    "wof:placetype":"venue"
},
  "geometry": {"coordinates":[-90.221045,38.695376],"type":"Point"}
}