{
  "type": "Feature",
  "properties": {
    "iso:country":"US",
    "sg:address":"801 Plum St",
    "sg:city":"Doniphan",
    "sg:classifiers":[
        {
            "category":"Retail",
            "subcategory":"Laundry & Dry Cleaning",
            "type":"Services"
        },
        {
            "category":"Building & Trades",
            "subcategory":"Cleaning & Sanitation",
            "type":"Services"
        }
    ],
    "sg:phone":"+1 573 996 7572",
    "sg:postcode":"63935",
    "sg:province":"MO",
    "sg:tags":[
        "cleaner",
        "house",
        "rug",
        "contractor",
        "cleaning-industrial",
        "carpet"
    ],
    "wof:name":"Pro Steamers",
    "wof:placetype":"venue"
},
  "geometry": {"coordinates":[-90.815002,36.620892],"type":"Point"}
}