{
  "type": "Feature",
  "properties": {
    "iso:country":"US",
    "sg:address":"3206 Laclede Station Rd",
    "sg:city":"St Louis",
    "sg:classifiers":[
        {
            "category":"Restaurant",
            "type":"Food & Drink"
        }
    ],
    "sg:phone":"+1 314 781 2433",
    "sg:postcode":"63143",
    "sg:province":"MO",
    "sg:tags":[
        "eating"
    ],
    "wof:name":"Pizza World",
    "wof:placetype":"venue"
},
  "geometry": {"coordinates":[-90.331897,38.604805],"type":"Point"}
}