{
  "type": "Feature",
  "properties": {
    "iso:country":"US",
    "sg:address":"3207 Meramec St",
    "sg:city":"St Louis",
    "sg:classifiers":[
        {
            "category":"Banks & Credit Unions",
            "subcategory":"Bank",
            "type":"Services"
        }
    ],
    "sg:phone":"+1 314 481 6800",
    "sg:postcode":"63118",
    "sg:province":"MO",
    "sg:tags":[
        "savings",
        "institution"
    ],
    "wof:name":"Southern Commercial Bank",
    "wof:placetype":"venue"
},
  "geometry": {"coordinates":[-90.24031600000001,38.580512],"type":"Point"}
}