{
  "type": "Feature",
  "properties": {
    "iso:country":"US",
    "sg:address":"2338 Peters Ford Rd",
    "sg:city":"Leslie",
    "sg:classifiers":[
        {
            "category":"Professional",
            "subcategory":"Business Services",
            "type":"Services"
        }
    ],
    "sg:phone":"+1 573 484 3213",
    "sg:postcode":"63056",
    "sg:province":"MO",
    "wof:name":"Sn Design",
    "wof:placetype":"venue"
},
  "geometry": {"coordinates":[-91.209324,38.378058],"type":"Point"}
}