{
  "type": "Feature",
  "properties": {
    "iso:country":"US",
    "sg:address":"1807 Katherine Ave",
    "sg:city":"Joplin",
    "sg:classifiers":[
        {
            "category":"Retail",
            "subcategory":"Repair Shop",
            "type":"Services"
        }
    ],
    "sg:phone":"+1 417 206 2057",
    "sg:postcode":"64801",
    "sg:province":"MO",
    "sg:tags":[
        "refinishing",
        "furniture"
    ],
    "wof:name":"Furniture Rescue",
    "wof:placetype":"venue"
},
  "geometry": {"coordinates":[-94.46731699999999,37.071139],"type":"Point"}
}