{
  "type": "Feature",
  "properties": {
    "iso:country":"US",
    "sg:address":"900 W Washington",
    "sg:city":"Waverly",
    "sg:classifiers":[
        {
            "category":"Wholesale",
            "subcategory":"Machinery & Supplies",
            "type":"Manufacturing & Wholesale Goods"
        }
    ],
    "sg:phone":"+1 660 493 0220",
    "sg:postcode":"64096",
    "sg:province":"MO",
    "sg:tags":[
        "contractor"
    ],
    "wof:name":"L B Materials",
    "wof:placetype":"venue"
},
  "geometry": {"coordinates":[-93.52507199999999,39.205503],"type":"Point"}
}