{
  "type": "Feature",
  "properties": {
    "iso:country":"US",
    "sg:address":"1518 W Harper St",
    "sg:city":"Poplar Bluff",
    "sg:classifiers":[
        {
            "category":"Building & Trades",
            "subcategory":"Equipment Rental",
            "type":"Services"
        }
    ],
    "sg:phone":"+1 573 686 3405",
    "sg:postcode":"63901",
    "sg:province":"MO",
    "sg:tags":[
        "yard"
    ],
    "wof:name":"Bob's General Rental Ctr",
    "wof:placetype":"venue"
},
  "geometry": {"coordinates":[-90.412464,36.766481],"type":"Point"}
}