{
  "type": "Feature",
  "properties": {
    "iso:country":"US",
    "sg:address":"409 E Main St",
    "sg:city":"Warrenton",
    "sg:classifiers":[
        {
            "category":"Health Services",
            "subcategory":"Health Practitioner",
            "type":"Services"
        }
    ],
    "sg:phone":"+1 636 456 3326",
    "sg:postcode":"63383",
    "sg:province":"MO",
    "sg:tags":[
        "medical"
    ],
    "wof:name":"Philip Dean MD",
    "wof:placetype":"venue"
},
  "geometry": {"coordinates":[-91.143946,38.811294],"type":"Point"}
}