{
  "type": "Feature",
  "properties": {
    "iso:country":"US",
    "sg:address":"7520 Main St",
    "sg:city":"Sparta",
    "sg:classifiers":[
        {
            "category":"Shopping",
            "subcategory":"Used Merchandise",
            "type":"Retail Goods"
        }
    ],
    "sg:phone":"+1 417 634 4100",
    "sg:postcode":"65753",
    "sg:province":"MO",
    "sg:tags":[
        "furniture"
    ],
    "wof:name":"Maggard's Furniture",
    "wof:placetype":"venue"
},
  "geometry": {"coordinates":[-93.082655,37.001183],"type":"Point"}
}