{
  "type": "Feature",
  "properties": {
    "iso:country":"US",
    "sg:address":"3151 Olive St",
    "sg:city":"Kansas City",
    "sg:classifiers":[
        {
            "category":"Organizations",
            "subcategory":"Non-profit Organization",
            "type":"Services"
        }
    ],
    "sg:phone":"+1 816 861 6678",
    "sg:postcode":"64109",
    "sg:province":"MO",
    "sg:tags":[
        "information",
        "alcoholism",
        "treatment"
    ],
    "wof:name":"Alcoholics Anonymous",
    "wof:placetype":"venue"
},
  "geometry": {"coordinates":[-94.555125,39.069055],"type":"Point"}
}