{
  "type": "Feature",
  "properties": {
    "iso:country":"US",
    "sg:address":"958 S Highway Dr",
    "sg:city":"Fenton",
    "sg:classifiers":[
        {
            "category":"Manufacturing",
            "subcategory":"Wood Products",
            "type":"Manufacturing & Wholesale Goods"
        },
        {
            "category":"Home & Garden",
            "subcategory":"Carpets & Floor Coverings",
            "type":"Retail Goods"
        }
    ],
    "sg:phone":"+1 314 872 8400",
    "sg:postcode":"63026",
    "sg:province":"MO",
    "sg:tags":[
        "hardwood",
        "material"
    ],
    "sg:website":"http://www.lumberliquidators.com",
    "wof:name":"Lumber Liquidators",
    "wof:placetype":"venue"
},
  "geometry": {"coordinates":[-90.46238,38.542679],"type":"Point"}
}