{
  "type": "Feature",
  "properties": {
    "iso:country":"US",
    "sg:address":"215 N Rollins St",
    "sg:city":"Macon",
    "sg:classifiers":[
        {
            "category":"Restaurant",
            "type":"Food & Drink"
        }
    ],
    "sg:phone":"+1 660 395 7015",
    "sg:postcode":"63552",
    "sg:province":"MO",
    "wof:name":"Apple Basket",
    "wof:placetype":"venue"
},
  "geometry": {"coordinates":[-92.472988,39.738846],"type":"Point"}
}