{
  "type": "Feature",
  "properties": {
    "iso:country":"US",
    "sg:address":"3115 W 76 Country Blvd",
    "sg:city":"Branson",
    "sg:classifiers":[
        {
            "category":"Arts & Performance",
            "subcategory":"Theater",
            "type":"Entertainment"
        }
    ],
    "sg:phone":"+1 417 337 9333",
    "sg:postcode":"65616",
    "sg:province":"MO",
    "sg:tags":[
        "theatre"
    ],
    "wof:name":"Moe Bandy In Concert",
    "wof:placetype":"venue"
},
  "geometry": {"coordinates":[-93.27761,36.637951],"type":"Point"}
}