{
  "type": "Feature",
  "properties": {
    "iso:country":"US",
    "sg:address":"113 NE 72 St",
    "sg:city":"Kansas City",
    "sg:classifiers":[
        {
            "category":"Real Estate",
            "subcategory":"Real Estate Operator",
            "type":"Services"
        }
    ],
    "sg:phone":"+1 816 468 1830",
    "sg:postcode":"64118",
    "sg:province":"MO",
    "sg:tags":[
        "building",
        "nonresidential"
    ],
    "wof:name":"Judd Properties",
    "wof:placetype":"venue"
},
  "geometry": {"coordinates":[-94.57895499999999,39.224571],"type":"Point"}
}