{
  "type": "Feature",
  "properties": {
    "iso:country":"US",
    "sg:address":"514 N Orner St",
    "sg:city":"Carthage",
    "sg:classifiers":[
        {
            "category":"Railroad",
            "type":"Transportation"
        }
    ],
    "sg:phone":"+1 417 358 8800",
    "sg:postcode":"64836",
    "sg:province":"MO",
    "sg:website":"www.railamerica.com",
    "wof:name":"Missouri & Northern Arkansas",
    "wof:placetype":"venue"
},
  "geometry": {"coordinates":[-94.316953,37.183346],"type":"Point"}
}