{
  "type": "Feature",
  "properties": {
    "iso:country":"US",
    "sg:address":"530 Spring Creek Ct",
    "sg:city":"Branson",
    "sg:classifiers":[
        {
            "category":"Government",
            "subcategory":"Court House",
            "type":"Public Place"
        },
        {
            "category":"Recreation",
            "type":"Entertainment"
        },
        {
            "category":"Travel",
            "subcategory":"Resort",
            "type":"Entertainment"
        },
        {
            "category":"Travel",
            "subcategory":"Hotels & Motels",
            "type":"Entertainment"
        }
    ],
    "sg:phone":"+1 417 334 8650",
    "sg:postcode":"65616",
    "sg:province":"MO",
    "sg:tags":[
        "cottage",
        "chalet",
        "cabin",
        "camps-recreational"
    ],
    "wof:name":"Cleo H Wilkins",
    "wof:placetype":"venue"
},
  "geometry": {"coordinates":[-93.26914600000001,36.629546],"type":"Point"}
}