{
  "type": "Feature",
  "properties": {
    "iso:country":"US",
    "sg:address":"2021 Perryville Rd",
    "sg:city":"Cape Girardeau",
    "sg:classifiers":[
        {
            "category":"Food & Beverages",
            "subcategory":"Groceries & Convenience Stores",
            "type":"Retail Goods"
        }
    ],
    "sg:phone":"+1 573 335 0171",
    "sg:postcode":"63701",
    "sg:province":"MO",
    "wof:name":"Westside Convenience",
    "wof:placetype":"venue"
},
  "geometry": {"coordinates":[-89.554697,37.340509],"type":"Point"}
}