{
  "type": "Feature",
  "properties": {
    "iso:country":"US",
    "sg:address":"1725 Huntington Dr",
    "sg:city":"Cape Girardeau",
    "sg:classifiers":[
        {
            "category":"Wholesale",
            "subcategory":"Groceries",
            "type":"Manufacturing & Wholesale Goods"
        }
    ],
    "sg:phone":"+1 573 334 6532",
    "sg:postcode":"63701",
    "sg:province":"MO",
    "sg:tags":[
        "food",
        "broker"
    ],
    "wof:name":"Sales Force Inc",
    "wof:placetype":"venue"
},
  "geometry": {"coordinates":[-89.53974100000001,37.328345],"type":"Point"}
}