{
  "type": "Feature",
  "properties": {
    "iso:country":"US",
    "sg:address":"840 Lone Star Dr",
    "sg:city":"O Fallon",
    "sg:classifiers":[
        {
            "category":"Education",
            "subcategory":"School",
            "type":"Public Place"
        }
    ],
    "sg:phone":"+1 636 980 2337",
    "sg:postcode":"63366",
    "sg:province":"MO",
    "wof:name":"Fort Zumwalt School Dist Anx",
    "wof:placetype":"venue"
},
  "geometry": {"coordinates":[-90.749313,38.80697],"type":"Point"}
}