{
  "type": "Feature",
  "properties": {
    "iso:country":"US",
    "sg:address":"820 James S McDonnell Blvd",
    "sg:city":"Hazelwood",
    "sg:classifiers":[
        {
            "category":"Retail",
            "subcategory":"Auto Rental",
            "type":"Services"
        }
    ],
    "sg:phone":"+1 314 895 2650",
    "sg:postcode":"63042",
    "sg:province":"MO",
    "sg:tags":[
        "renting",
        "automobile",
        "passenger",
        "car"
    ],
    "wof:name":"Enterprise Rent-A-Car Company",
    "wof:placetype":"venue"
},
  "geometry": {"coordinates":[-90.390153,38.779578],"type":"Point"}
}