{
  "type": "Feature",
  "properties": {
    "iso:country":"US",
    "sg:address":"3725 N Oak Fwy",
    "sg:city":"Kansas City",
    "sg:classifiers":[
        {
            "category":"Real Estate",
            "subcategory":"Real Estate Agent",
            "type":"Services"
        }
    ],
    "sg:phone":"+1 816 459 7740",
    "sg:postcode":"64116",
    "sg:province":"MO",
    "wof:name":"Re/Max Mid-States Region",
    "wof:placetype":"venue"
},
  "geometry": {"coordinates":[-94.576764,39.163196],"type":"Point"}
}