{
  "type": "Feature",
  "properties": {
    "iso:country":"US",
    "sg:address":"1501 S Range Line Rd",
    "sg:city":"Joplin",
    "sg:classifiers":[
        {
            "category":"Professional",
            "subcategory":"Accounting & Tax Preparation",
            "type":"Services"
        }
    ],
    "sg:phone":"+1 417 623 7126",
    "sg:postcode":"64804",
    "sg:province":"MO",
    "sg:tags":[
        "return",
        "filing"
    ],
    "wof:name":"H & R Block Tax Svc",
    "wof:placetype":"venue"
},
  "geometry": {"coordinates":[-94.477738,37.072947],"type":"Point"}
}