{
  "type": "Feature",
  "properties": {
    "iso:country":"US",
    "sg:address":"7663 Watson Rd",
    "sg:city":"Saint Louis",
    "sg:classifiers":[
        {
            "category":"Real Estate",
            "subcategory":"Real Estate Operator",
            "type":"Services"
        }
    ],
    "sg:phone":"+1 314 962 7878",
    "sg:postcode":"63119",
    "sg:province":"MO",
    "sg:tags":[
        "building",
        "apartment"
    ],
    "wof:name":"Holy Infant Apartments",
    "wof:placetype":"venue"
},
  "geometry": {"coordinates":[-90.330653,38.575851],"type":"Point"}
}