{
  "type": "Feature",
  "properties": {
    "iso:country":"US",
    "sg:address":"11920 Old Ballas Rd",
    "sg:city":"St Louis",
    "sg:classifiers":[
        {
            "category":"Government",
            "subcategory":"Office",
            "type":"Public Place"
        }
    ],
    "sg:phone":"+1 314 991 0501",
    "sg:postcode":"63141",
    "sg:province":"MO",
    "sg:tags":[
        "village"
    ],
    "wof:name":"Trustees Of Woodridge",
    "wof:placetype":"venue"
},
  "geometry": {"coordinates":[-90.44718399999999,38.666387],"type":"Point"}
}