{
  "type": "Feature",
  "properties": {
    "iso:country":"US",
    "sg:address":"3501 Watson Rd",
    "sg:city":"Saint Louis",
    "sg:classifiers":[
        {
            "category":"Professional",
            "subcategory":"Management & Consulting",
            "type":"Services"
        }
    ],
    "sg:phone":"+1 314 645 2987",
    "sg:postcode":"63139",
    "sg:province":"MO",
    "sg:tags":[
        "food",
        "consultant",
        "facility"
    ],
    "wof:name":"Geiger Group The",
    "wof:placetype":"venue"
},
  "geometry": {"coordinates":[-90.30034999999999,38.598352],"type":"Point"}
}