{
  "type": "Feature",
  "properties": {
    "iso:country":"US",
    "sg:address":"9849 Manchester Rd",
    "sg:city":"Saint Louis",
    "sg:classifiers":[
        {
            "category":"Banks & Credit Unions",
            "subcategory":"Investment Brokerage",
            "type":"Services"
        }
    ],
    "sg:phone":"+1 314 968 1984",
    "sg:postcode":"63122",
    "sg:province":"MO",
    "sg:tags":[
        "security"
    ],
    "wof:name":"Edward Jones 15656",
    "wof:placetype":"venue"
},
  "geometry": {"coordinates":[-90.373682,38.606826],"type":"Point"}
}