{
  "type": "Feature",
  "properties": {
    "iso:country":"US",
    "sg:address":"411 E Broadway St",
    "sg:city":"Monett",
    "sg:classifiers":[
        {
            "category":"Home & Garden",
            "subcategory":"Furniture",
            "type":"Retail Goods"
        }
    ],
    "sg:phone":"+1 417 235 5921",
    "sg:postcode":"65708",
    "sg:province":"MO",
    "sg:tags":[
        "store"
    ],
    "wof:name":"Mitzi's",
    "wof:placetype":"venue"
},
  "geometry": {"coordinates":[-93.923272,36.920853],"type":"Point"}
}