{
  "type": "Feature",
  "properties": {
    "iso:country":"US",
    "sg:address":"5125 N Bellaire Ave",
    "sg:city":"Kansas City",
    "sg:classifiers":[
        {
            "category":"Organizations",
            "subcategory":"Community Association",
            "type":"Services"
        }
    ],
    "sg:phone":"+1 816 454 7570",
    "sg:postcode":"64119",
    "sg:province":"MO",
    "sg:tags":[
        "military"
    ],
    "wof:name":"American Legion",
    "wof:placetype":"venue"
},
  "geometry": {"coordinates":[-94.51072600000001,39.186901],"type":"Point"}
}