{
  "type": "Feature",
  "properties": {
    "iso:country":"US",
    "sg:address":"811 Crestland Dr",
    "sg:city":"Ballwin",
    "sg:classifiers":[
        {
            "category":"Professional",
            "subcategory":"Business Services",
            "type":"Services"
        }
    ],
    "sg:phone":"+1 636 391 7335",
    "sg:postcode":"63011",
    "sg:province":"MO",
    "wof:name":"Ramona Rossman Enterprises",
    "wof:placetype":"venue"
},
  "geometry": {"coordinates":[-90.566199,38.600104],"type":"Point"}
}