{
  "type": "Feature",
  "properties": {
    "iso:country":"US",
    "sg:address":"3613 Richardson Square Dr # 200",
    "sg:city":"Arnold",
    "sg:classifiers":[
        {
            "category":"Banks & Credit Unions",
            "subcategory":"Investment Brokerage",
            "type":"Services"
        }
    ],
    "sg:phone":"+1 636 461 2266",
    "sg:postcode":"63010",
    "sg:province":"MO",
    "sg:tags":[
        "security"
    ],
    "sg:website":"http://www.edwardjones.com",
    "wof:name":"Edward Jones 11596",
    "wof:placetype":"venue"
},
  "geometry": {"coordinates":[-90.384539,38.411577],"type":"Point"}
}