{
  "type": "Feature",
  "properties": {
    "iso:country":"US",
    "sg:address":"1940 Zumbehl Rd",
    "sg:city":"Saint Charles",
    "sg:classifiers":[
        {
            "category":"Shopping",
            "subcategory":"Music",
            "type":"Retail Goods"
        }
    ],
    "sg:phone":"+1 636 724 9645",
    "sg:postcode":"63303",
    "sg:province":"MO",
    "sg:tags":[
        "used",
        "merchandise"
    ],
    "wof:name":"Disc-Go-Round",
    "wof:placetype":"venue"
},
  "geometry": {"coordinates":[-90.532742,38.785728],"type":"Point"}
}