{
  "type": "Feature",
  "properties": {
    "iso:country":"US",
    "sg:address":"1200 Oak St",
    "sg:city":"Carthage",
    "sg:classifiers":[
        {
            "category":"Shopping",
            "subcategory":"Used Merchandise",
            "type":"Retail Goods"
        }
    ],
    "sg:phone":"+1 417 358 6104",
    "sg:postcode":"64836",
    "sg:province":"MO",
    "sg:tags":[
        "flea",
        "market"
    ],
    "wof:name":"Dean's Antique Mall",
    "wof:placetype":"venue"
},
  "geometry": {"coordinates":[-94.32744599999999,37.176563],"type":"Point"}
}