{
  "type": "Feature",
  "properties": {
    "iso:country":"US",
    "sg:address":"4010 Pennsylvania Ave",
    "sg:city":"Kansas City",
    "sg:classifiers":[
        {
            "category":"Restaurant",
            "type":"Food & Drink"
        }
    ],
    "sg:phone":"+1 816 756 3222",
    "sg:postcode":"64111",
    "sg:province":"MO",
    "sg:tags":[
        "eating"
    ],
    "sg:website":"www.westportcoffeehouse.com",
    "wof:name":"Westport Coffee House",
    "wof:placetype":"venue"
},
  "geometry": {"coordinates":[-94.59232799999999,39.053897],"type":"Point"}
}