{
  "type": "Feature",
  "properties": {
    "iso:country":"US",
    "sg:address":"1357 S Bishop Ave",
    "sg:city":"Rolla",
    "sg:classifiers":[
        {
            "category":"Wholesale",
            "subcategory":"Motor Vehicles",
            "type":"Manufacturing & Wholesale Goods"
        }
    ],
    "sg:phone":"+1 573 341 9984",
    "sg:postcode":"65401",
    "sg:province":"MO",
    "sg:tags":[
        "auction",
        "automobile"
    ],
    "wof:name":"Rolla Auto Auction",
    "wof:placetype":"venue"
},
  "geometry": {"coordinates":[-91.779983,37.924435],"type":"Point"}
}