{
  "type": "Feature",
  "properties": {
    "addr:full":"3423 S Noland Rd Independence MO 64055",
    "addr:housenumber":"3423",
    "addr:postcode":"64055",
    "addr:street":"S Noland Rd",
    "iso:country":"US",
    "sg:address":"3423 S Noland Rd",
    "sg:city":"Independence",
    "sg:classifiers":[
        {
            "category":"Banks & Credit Unions",
            "subcategory":"Bank",
            "type":"Services"
        }
    ],
    "sg:phone":"+1 816 252 8408",
    "sg:postcode":"64055",
    "sg:province":"MO",
    "sg:tags":[
        "depository",
        "banking"
    ],
    "wof:name":"Check Into Cash",
    "wof:placetype":"venue"
},
  "geometry": {"coordinates":[-94.414888,39.05842],"type":"Point"}
}