{
  "type": "Feature",
  "properties": {
    "iso:country":"US",
    "sg:address":"7705 NW Prairie View Rd",
    "sg:city":"Kansas City",
    "sg:classifiers":[
        {
            "category":"Banks & Credit Unions",
            "subcategory":"Investment Brokerage",
            "type":"Services"
        }
    ],
    "sg:phone":"+1 816 741 3088",
    "sg:postcode":"64151",
    "sg:province":"MO",
    "sg:tags":[
        "security"
    ],
    "wof:name":"Edward Jones 11842",
    "wof:placetype":"venue"
},
  "geometry": {"coordinates":[-94.658705,39.234187],"type":"Point"}
}