{
  "type": "Feature",
  "properties": {
    "iso:country":"US",
    "sg:address":"13558 NW Industrial Dr",
    "sg:city":"Bridgeton",
    "sg:classifiers":[
        {
            "category":"Building & Trades",
            "subcategory":"Construction",
            "type":"Services"
        }
    ],
    "sg:phone":"+1 314 770 2994",
    "sg:postcode":"63044",
    "sg:province":"MO",
    "sg:tags":[
        "general",
        "contractor"
    ],
    "wof:name":"Jamestown Constructors Inc",
    "wof:placetype":"venue"
},
  "geometry": {"coordinates":[-90.443899,38.775565],"type":"Point"}
}