{
  "type": "Feature",
  "properties": {
    "iso:country":"US",
    "sg:address":"12038 Red Lion Dr",
    "sg:city":"Florissant",
    "sg:classifiers":[
        {
            "category":"Professional",
            "subcategory":"Secretarial Services",
            "type":"Services"
        }
    ],
    "sg:phone":"+1 314 780 6889",
    "sg:postcode":"63033",
    "sg:province":"MO",
    "sg:tags":[
        "typing"
    ],
    "wof:name":"Professional Legal Forms",
    "wof:placetype":"venue"
},
  "geometry": {"coordinates":[-90.245774,38.794809],"type":"Point"}
}