{
  "type": "Feature",
  "properties": {
    "iso:country":"US",
    "sg:address":"17711 Birch Leaf Ct",
    "sg:city":"Chesterfield",
    "sg:classifiers":[
        {
            "category":"Real Estate",
            "subcategory":"Real Estate Agent",
            "type":"Services"
        }
    ],
    "sg:phone":"+1 636 530 9393",
    "sg:postcode":"63005",
    "sg:province":"MO",
    "sg:website":"www.firstmidwest.net",
    "wof:name":"First Midwest Inc",
    "wof:placetype":"venue"
},
  "geometry": {"coordinates":[-90.64316100000001,38.640653],"type":"Point"}
}