{
  "type": "Feature",
  "properties": {
    "iso:country":"US",
    "sg:address":"3620 Runnymede Dr",
    "sg:city":"St Charles",
    "sg:classifiers":[
        {
            "category":"Wholesale",
            "subcategory":"Fruits & Vegetables",
            "type":"Manufacturing & Wholesale Goods"
        }
    ],
    "sg:phone":"+1 636 946 4244",
    "sg:postcode":"63301",
    "sg:province":"MO",
    "wof:name":"Cardinal Delivery Redbird Prod",
    "wof:placetype":"venue"
},
  "geometry": {"coordinates":[-90.521456,38.814175],"type":"Point"}
}