{
  "type": "Feature",
  "properties": {
    "iso:country":"US",
    "sg:address":"8314 Wornall Rd",
    "sg:city":"Kansas City",
    "sg:classifiers":[
        {
            "category":"Restaurant",
            "type":"Food & Drink"
        }
    ],
    "sg:phone":"+1 816 531 8878",
    "sg:postcode":"64114",
    "sg:province":"KS",
    "wof:name":"Jake Edwards Bar-B-Que",
    "wof:placetype":"venue"
},
  "geometry": {"coordinates":[-94.594927,38.977398],"type":"Point"}
}