{
  "type": "Feature",
  "properties": {
    "iso:country":"US",
    "sg:address":"1257 E Kearney St",
    "sg:city":"Springfield",
    "sg:classifiers":[
        {
            "category":"Autos & Motor Vehicles",
            "subcategory":"Automobile Sales",
            "type":"Retail Goods"
        }
    ],
    "sg:phone":"+1 417 831 7751",
    "sg:postcode":"65803",
    "sg:province":"MO",
    "sg:tags":[
        "dealers-used",
        "used",
        "cars-wholesale",
        "car"
    ],
    "wof:name":"Route 66 Motor Sales",
    "wof:placetype":"venue"
},
  "geometry": {"coordinates":[-93.273088,37.240605],"type":"Point"}
}