{
  "type": "Feature",
  "properties": {
    "iso:country":"US",
    "sg:address":"11705 Baptist Church Rd",
    "sg:city":"St Louis",
    "sg:classifiers":[
        {
            "category":"Retail",
            "subcategory":"Veterinary Services",
            "type":"Services"
        }
    ],
    "sg:phone":"+1 314 843 9055",
    "sg:postcode":"63128",
    "sg:province":"MO",
    "sg:tags":[
        "hospital",
        "animal"
    ],
    "wof:name":"Concord Animal Hospital Inc",
    "wof:placetype":"venue"
},
  "geometry": {"coordinates":[-90.362444,38.520354],"type":"Point"}
}