{
  "type": "Feature",
  "properties": {
    "iso:country":"US",
    "sg:address":"359 Salem Rd",
    "sg:city":"Branson",
    "sg:classifiers":[
        {
            "category":"Transit Center",
            "subcategory":"Freight",
            "type":"Transportation"
        },
        {
            "category":"Freight",
            "type":"Transportation"
        }
    ],
    "sg:phone":"+1 417 239 3900",
    "sg:postcode":"65616",
    "sg:province":"MO",
    "sg:tags":[
        "local",
        "trucking-motor",
        "trucking"
    ],
    "wof:name":"Custer Enterprises Inc",
    "wof:placetype":"venue"
},
  "geometry": {"coordinates":[-93.282169,36.741846],"type":"Point"}
}