{
  "type": "Feature",
  "properties": {
    "iso:country":"US",
    "sg:address":"500 Walton Rd",
    "sg:city":"Kirbyville",
    "sg:classifiers":[
        {
            "category":"Place Of Worship",
            "type":"Public Place"
        },
        {
            "category":"Organizations",
            "subcategory":"Religious Organization",
            "type":"Services"
        }
    ],
    "sg:phone":"+1 417 336 4877",
    "sg:postcode":"65679",
    "sg:province":"MO",
    "sg:tags":[
        "church"
    ],
    "wof:name":"Prayer Mountain In The Ozarks",
    "wof:placetype":"venue"
},
  "geometry": {"coordinates":[-93.065169,36.506409],"type":"Point"}
}