{
  "type": "Feature",
  "properties": {
    "iso:country":"US",
    "sg:address":"3133 NE 59 Ter",
    "sg:city":"Kansas City",
    "sg:classifiers":[
        {
            "category":"Real Estate",
            "subcategory":"Real Estate Operator",
            "type":"Services"
        }
    ],
    "sg:phone":"+1 816 454 4422",
    "sg:postcode":"64119",
    "sg:province":"MO",
    "sg:tags":[
        "building",
        "apartment"
    ],
    "wof:name":"Kendallwood Aprtmnts Twnhouses",
    "wof:placetype":"venue"
},
  "geometry": {"coordinates":[-94.542151,39.201005],"type":"Point"}
}