{
  "type": "Feature",
  "properties": {
    "iso:country":"US",
    "sg:address":"1664 Cologna Rd",
    "sg:city":"Marshfield",
    "sg:classifiers":[
        {
            "category":"Wholesale",
            "subcategory":"Metals & Minerals",
            "type":"Manufacturing & Wholesale Goods"
        }
    ],
    "sg:phone":"+1 417 859 5961",
    "sg:postcode":"65706",
    "sg:province":"MO",
    "sg:tags":[
        "center"
    ],
    "wof:name":"Metal Strategies LLC",
    "wof:placetype":"venue"
},
  "geometry": {"coordinates":[-92.984364,37.317102],"type":"Point"}
}