{
  "type": "Feature",
  "properties": {
    "iso:country":"US",
    "sg:address":"9708 Natural Bridge Rd",
    "sg:city":"St Louis",
    "sg:classifiers":[
        {
            "category":"Autos & Motor Vehicles",
            "subcategory":"Fuel & Gas Station",
            "type":"Retail Goods"
        }
    ],
    "sg:phone":"+1 314 426 2436",
    "sg:postcode":"63134",
    "sg:province":"MO",
    "sg:tags":[
        "oil"
    ],
    "wof:name":"Shell",
    "wof:placetype":"venue"
},
  "geometry": {"coordinates":[-90.345752,38.729353],"type":"Point"}
}