{
  "type": "Feature",
  "properties": {
    "iso:country":"US",
    "sg:address":"2815 N. 14th Street",
    "sg:city":"St Louis",
    "sg:classifiers":[
        {
            "category":"Coffee & Tea",
            "type":"Food & Drink"
        }
    ],
    "sg:phone":"+1 314 601 3699",
    "sg:postcode":"63107",
    "sg:province":"MO",
    "sg:website":"www.urbanstudiocafe.org/",
    "wof:name":"Urban Studio Cafe",
    "wof:placetype":"venue"
},
  "geometry": {"coordinates":[-90.19775300000001,38.651388],"type":"Point"}
}