{
  "type": "Feature",
  "properties": {
    "iso:country":"US",
    "sg:address":"Ground Fl, The Village Washington University",
    "sg:city":"St Louis",
    "sg:classifiers":[
        {
            "category":"Fast Food",
            "type":"Food & Drink"
        },
        {
            "category":"Restaurant",
            "type":"Food & Drink"
        }
    ],
    "sg:postcode":"63130",
    "sg:province":"MO",
    "sg:tags":[
        "traditional",
        "burger",
        "american"
    ],
    "sg:website":"diningservices.wustl.edu/campus_...",
    "wof:name":"The Village Cafe",
    "wof:placetype":"venue"
},
  "geometry": {"coordinates":[-90.30477999999999,38.64797],"type":"Point"}
}