{
  "type": "Feature",
  "properties": {
    "iso:country":"US",
    "sg:address":"299 S Broadview St",
    "sg:city":"Cape Girardeau",
    "sg:classifiers":[
        {
            "category":"Personal",
            "subcategory":"Beauty Salon",
            "type":"Services"
        }
    ],
    "sg:phone":"+1 573 339 0333",
    "sg:postcode":"63703",
    "sg:province":"MO",
    "sg:tags":[
        "shop"
    ],
    "wof:name":"Amy Twidwell",
    "wof:placetype":"venue"
},
  "geometry": {"coordinates":[-89.55607999999999,37.300772],"type":"Point"}
}