{
  "type": "Feature",
  "properties": {
    "iso:country":"US",
    "sg:address":"902 Oxford Dr",
    "sg:city":"Rolla",
    "sg:classifiers":[
        {
            "category":"Building & Trades",
            "subcategory":"Construction",
            "type":"Services"
        }
    ],
    "sg:phone":"+1 573 368 2658",
    "sg:postcode":"65401",
    "sg:province":"MO",
    "sg:tags":[
        "home",
        "improvement"
    ],
    "wof:name":"Nita's Wallpaper",
    "wof:placetype":"venue"
},
  "geometry": {"coordinates":[-91.75791,37.933785],"type":"Point"}
}