{
  "type": "Feature",
  "properties": {
    "iso:country":"US",
    "sg:address":"801 Progress St",
    "sg:city":"Cape Girardeau",
    "sg:classifiers":[
        {
            "category":"Building & Trades",
            "subcategory":"Construction",
            "type":"Services"
        }
    ],
    "sg:phone":"+1 573 335 7033",
    "sg:postcode":"63703",
    "sg:province":"MO",
    "sg:tags":[
        "designer",
        "marine",
        "contractor"
    ],
    "wof:name":"Luhr Brothers Inc",
    "wof:placetype":"venue"
},
  "geometry": {"coordinates":[-89.557451,37.286733],"type":"Point"}
}