{
  "type": "Feature",
  "properties": {
    "iso:country":"US",
    "sg:address":"18120 Baxter Rd",
    "sg:city":"Lawson",
    "sg:classifiers":[
        {
            "category":"Building & Trades",
            "subcategory":"Plumbing",
            "type":"Services"
        }
    ],
    "sg:phone":"+1 816 580 3375",
    "sg:postcode":"64062",
    "sg:province":"MO",
    "sg:tags":[
        "contractor"
    ],
    "wof:name":"Barsco Mechanical",
    "wof:placetype":"venue"
},
  "geometry": {"coordinates":[-94.243746,39.41891],"type":"Point"}
}