{
  "type": "Feature",
  "properties": {
    "iso:country":"US",
    "sg:address":"7330 Dartmouth Ave",
    "sg:city":"St Louis",
    "sg:classifiers":[
        {
            "category":"Retail",
            "subcategory":"Portrait Studio",
            "type":"Services"
        }
    ],
    "sg:phone":"+1 314 726 3107",
    "sg:postcode":"63130",
    "sg:province":"MO",
    "sg:tags":[
        "photographer"
    ],
    "wof:name":"H R Imaging Partners",
    "wof:placetype":"venue"
},
  "geometry": {"coordinates":[-90.327426,38.663177],"type":"Point"}
}