{
  "type": "Feature",
  "properties": {
    "iso:country":"US",
    "sg:address":"1439 Elliot St",
    "sg:city":"Eureka",
    "sg:classifiers":[
        {
            "category":"Insurance",
            "subcategory":"Insurance Agent",
            "type":"Services"
        }
    ],
    "sg:phone":"+1 636 938 5656",
    "sg:postcode":"63025",
    "sg:province":"MO",
    "wof:name":"Weible Insurance Inc",
    "wof:placetype":"venue"
},
  "geometry": {"coordinates":[-90.65454800000001,38.505417],"type":"Point"}
}