{
  "type": "Feature",
  "properties": {
    "iso:country":"US",
    "sg:address":"4941 Waringford Dr",
    "sg:city":"Saint Louis",
    "sg:classifiers":[
        {
            "category":"Building & Trades",
            "subcategory":"Construction",
            "type":"Services"
        }
    ],
    "sg:phone":"+1 314 487 6739",
    "sg:postcode":"63128",
    "sg:province":"MO",
    "sg:tags":[
        "house"
    ],
    "wof:name":"Hamilton Home Improvement",
    "wof:placetype":"venue"
},
  "geometry": {"coordinates":[-90.36054,38.491156],"type":"Point"}
}