{
  "type": "Feature",
  "properties": {
    "iso:country":"US",
    "sg:address":"200 Walnut St",
    "sg:city":"Bunceton",
    "sg:classifiers":[
        {
            "category":"Organizations",
            "subcategory":"Community Association",
            "type":"Services"
        }
    ],
    "sg:phone":"+1 660 427 5451",
    "sg:postcode":"65237",
    "sg:province":"MO",
    "sg:tags":[
        "club"
    ],
    "wof:name":"Bunceton Lions Club",
    "wof:placetype":"venue"
},
  "geometry": {"coordinates":[-92.79802599999999,38.790171],"type":"Point"}
}