{
  "type": "Feature",
  "properties": {
    "iso:country":"US",
    "sg:address":"2044 Westbrook Dr",
    "sg:city":"Overland",
    "sg:classifiers":[
        {
            "category":"Personal",
            "type":"Services"
        }
    ],
    "sg:phone":"+1 314 283 8605",
    "sg:postcode":"63114",
    "sg:province":"MO",
    "sg:tags":[
        "control",
        "weight"
    ],
    "wof:name":"Herbalife Distributor",
    "wof:placetype":"venue"
},
  "geometry": {"coordinates":[-90.358028,38.69118],"type":"Point"}
}