{
  "type": "Feature",
  "properties": {
    "iso:country":"US",
    "sg:address":"340 E Georgie St",
    "sg:city":"Osborn",
    "sg:classifiers":[
        {
            "category":"Building & Trades",
            "subcategory":"Construction",
            "type":"Services"
        }
    ],
    "sg:phone":"+1 816 675 2595",
    "sg:postcode":"64474",
    "sg:province":"MO",
    "sg:tags":[
        "house"
    ],
    "wof:name":"Bob Bradford Construction",
    "wof:placetype":"venue"
},
  "geometry": {"coordinates":[-94.35362600000001,39.748478],"type":"Point"}
}