{
  "type": "Feature",
  "properties": {
    "iso:country":"US",
    "sg:address":"526 S Jefferson St",
    "sg:city":"Mexico",
    "sg:classifiers":[
        {
            "category":"Health Services",
            "subcategory":"Chiropractor",
            "type":"Services"
        }
    ],
    "sg:phone":"+1 573 581 2368",
    "sg:postcode":"65265",
    "sg:province":"MO",
    "sg:tags":[
        "chiropractic"
    ],
    "wof:name":"Manns, Scott",
    "wof:placetype":"venue"
},
  "geometry": {"coordinates":[-91.882817,39.167883],"type":"Point"}
}