{
  "type": "Feature",
  "properties": {
    "iso:country":"US",
    "sg:address":"108 Walnut St",
    "sg:city":"Doniphan",
    "sg:classifiers":[
        {
            "category":"Organizations",
            "subcategory":"Religious Organization",
            "type":"Services"
        }
    ],
    "sg:phone":"+1 573 996 4457",
    "sg:postcode":"63935",
    "sg:province":"MO",
    "sg:tags":[
        "church"
    ],
    "wof:name":"Bibleway Calvary Fellowship",
    "wof:placetype":"venue"
},
  "geometry": {"coordinates":[-90.82406400000001,36.617512],"type":"Point"}
}