{
  "type": "Feature",
  "properties": {
    "iso:country":"US",
    "sg:address":"60 Spring Way Dr",
    "sg:city":"Saint Peters",
    "sg:classifiers":[
        {
            "category":"Retail",
            "subcategory":"Repair Shop",
            "type":"Services"
        }
    ],
    "sg:phone":"+1 636 928 7728",
    "sg:postcode":"63376",
    "sg:province":"MO",
    "wof:name":"Turn Future Sowers Enterprise",
    "wof:placetype":"venue"
},
  "geometry": {"coordinates":[-90.59526,38.76918],"type":"Point"}
}