{
  "type": "Feature",
  "properties": {
    "iso:country":"US",
    "sg:address":"1627 Marriott Ln",
    "sg:city":"Barnhart",
    "sg:classifiers":[
        {
            "category":"Personal",
            "subcategory":"Beauty Salon",
            "type":"Services"
        }
    ],
    "sg:phone":"+1 636 464 1486",
    "sg:postcode":"63012",
    "sg:province":"MO",
    "sg:tags":[
        "shop"
    ],
    "wof:name":"Hair Inc Heads West",
    "wof:placetype":"venue"
},
  "geometry": {"coordinates":[-90.402148,38.347057],"type":"Point"}
}