{
  "type": "Feature",
  "properties": {
    "iso:country":"US",
    "sg:address":"53 NW Walnut St",
    "sg:city":"Trenton",
    "sg:classifiers":[
        {
            "category":"Wholesale",
            "subcategory":"Meat",
            "type":"Manufacturing & Wholesale Goods"
        }
    ],
    "sg:phone":"+1 660 789 2321",
    "sg:postcode":"64683",
    "sg:province":"MO",
    "sg:tags":[
        "butchering"
    ],
    "wof:name":"Bob White's Processing",
    "wof:placetype":"venue"
},
  "geometry": {"coordinates":[-93.688909,40.081436],"type":"Point"}
}