{
  "type": "Feature",
  "properties": {
    "iso:country":"US",
    "sg:address":"1733 Tudor Ln",
    "sg:city":"Liberty",
    "sg:classifiers":[
        {
            "category":"Professional",
            "subcategory":"Business Services",
            "type":"Services"
        }
    ],
    "sg:phone":"+1 816 792 3849",
    "sg:postcode":"64068",
    "sg:province":"MO",
    "wof:name":"K&G Enterprises Inc",
    "wof:placetype":"venue"
},
  "geometry": {"coordinates":[-94.448373,39.2279],"type":"Point"}
}