{
  "type": "Feature",
  "properties": {
    "iso:country":"US",
    "sg:address":"981 Mount Hawley Ct",
    "sg:city":"Wentzville",
    "sg:classifiers":[
        {
            "category":"Building & Trades",
            "subcategory":"Construction",
            "type":"Services"
        }
    ],
    "sg:phone":"+1 636 332 0754",
    "sg:postcode":"63385",
    "sg:province":"MO",
    "sg:tags":[
        "floor",
        "laying",
        "contractor"
    ],
    "wof:name":"Thornburgh Flooring Inc",
    "wof:placetype":"venue"
},
  "geometry": {"coordinates":[-90.896342,38.834881],"type":"Point"}
}