{
  "type": "Feature",
  "properties": {
    "iso:country":"US",
    "sg:address":"1418 W 23rd St S",
    "sg:city":"Independence",
    "sg:classifiers":[
        {
            "category":"Autos & Motor Vehicles",
            "subcategory":"Automobile Sales",
            "type":"Retail Goods"
        }
    ],
    "sg:phone":"+1 816 252 2100",
    "sg:postcode":"64050",
    "sg:province":"MO",
    "sg:tags":[
        "car",
        "dealer"
    ],
    "wof:name":"Street Dreams",
    "wof:placetype":"venue"
},
  "geometry": {"coordinates":[-94.43474999999999,39.079974],"type":"Point"}
}