{
  "type": "Feature",
  "properties": {
    "iso:country":"US",
    "sg:address":"1606 Burlington St",
    "sg:city":"Kansas City",
    "sg:classifiers":[
        {
            "category":"Wholesale",
            "subcategory":"Construction Materials",
            "type":"Manufacturing & Wholesale Goods"
        }
    ],
    "sg:phone":"+1 816 474 4500",
    "sg:postcode":"64116",
    "sg:province":"MO",
    "sg:tags":[
        "steel",
        "hardware",
        "frame",
        "door",
        "related"
    ],
    "wof:name":"Metal Doors & Frame Co",
    "wof:placetype":"venue"
},
  "geometry": {"coordinates":[-94.580609,39.140193],"type":"Point"}
}