{
  "type": "Feature",
  "properties": {
    "iso:country":"US",
    "sg:address":"2131 W Republic Rd",
    "sg:city":"Springfield",
    "sg:classifiers":[
        {
            "category":"Professional",
            "subcategory":"Computer Services",
            "type":"Services"
        }
    ],
    "sg:phone":"+1 417 886 8674",
    "sg:postcode":"65807",
    "sg:province":"MO",
    "sg:tags":[
        "programing",
        "custom"
    ],
    "wof:name":"Scherer Development Inc",
    "wof:placetype":"venue"
},
  "geometry": {"coordinates":[-93.321068,37.138454],"type":"Point"}
}