{
  "type": "Feature",
  "properties": {
    "iso:country":"US",
    "sg:address":"409 N Walnut St",
    "sg:city":"Cameron",
    "sg:classifiers":[
        {
            "category":"Personal",
            "subcategory":"Beauty Salon",
            "type":"Services"
        }
    ],
    "sg:phone":"+1 816 632 6527",
    "sg:postcode":"64429",
    "sg:province":"MO",
    "sg:tags":[
        "shop"
    ],
    "wof:name":"Ds House of Beauty",
    "wof:placetype":"venue"
},
  "geometry": {"coordinates":[-94.235817,39.742657],"type":"Point"}
}