{
  "type": "Feature",
  "properties": {
    "iso:country":"US",
    "sg:address":"7309 Boise Brule Rd",
    "sg:city":"Henley",
    "sg:phone":"+1 573 498 6686",
    "sg:postcode":"65040",
    "sg:province":"MO",
    "sg:tags":[
        "farm",
        "wheat"
    ],
    "wof:name":"Patrick Groose",
    "wof:placetype":"venue"
},
  "geometry": {"coordinates":[-92.34066300000001,38.379522],"type":"Point"}
}