{
  "type": "Feature",
  "properties": {
    "iso:country":"US",
    "sg:address":"1203 E 20th St",
    "sg:city":"Joplin",
    "sg:classifiers":[
        {
            "category":"Building & Trades",
            "subcategory":"Construction",
            "type":"Services"
        }
    ],
    "sg:phone":"+1 417 781 7372",
    "sg:postcode":"64804",
    "sg:province":"MO",
    "sg:tags":[
        "contractor"
    ],
    "wof:name":"Pella Window & Qulty Exteriors",
    "wof:placetype":"venue"
},
  "geometry": {"coordinates":[-94.50098199999999,37.069404],"type":"Point"}
}