{
  "type": "Feature",
  "properties": {
    "iso:country":"US",
    "sg:address":"609 NE 95th St",
    "sg:city":"Kansas City",
    "sg:classifiers":[
        {
            "category":"Professional",
            "subcategory":"Management & Consulting",
            "type":"Services"
        }
    ],
    "sg:phone":"+1 816 421 3040",
    "sg:postcode":"64155",
    "sg:province":"MO",
    "sg:tags":[
        "agricultural",
        "consultant"
    ],
    "wof:name":"Food & Livestock Planning Inc",
    "wof:placetype":"venue"
},
  "geometry": {"coordinates":[-94.570232,39.265556],"type":"Point"}
}