{
  "type": "Feature",
  "properties": {
    "iso:country":"US",
    "sg:address":"591 Old Rte 66",
    "sg:city":"Waynesville",
    "sg:classifiers":[
        {
            "category":"Organizations",
            "subcategory":"Religious Organization",
            "type":"Services"
        }
    ],
    "sg:phone":"+1 573 336 3393",
    "sg:postcode":"65584",
    "sg:province":"MO",
    "wof:name":"AG Full Gspl Love Christ Chrch",
    "wof:placetype":"venue"
},
  "geometry": {"coordinates":[-92.160803,37.821962],"type":"Point"}
}