{
  "type": "Feature",
  "properties": {
    "iso:country":"US",
    "sg:address":"9063 E 65th St",
    "sg:city":"Raytown",
    "sg:classifiers":[
        {
            "category":"Professional",
            "subcategory":"Business Services",
            "type":"Services"
        }
    ],
    "sg:phone":"+1 816 353 8323",
    "sg:postcode":"64133",
    "sg:province":"MO",
    "sg:tags":[
        "consultant",
        "coach"
    ],
    "wof:name":"Simpson's Estate Sales",
    "wof:placetype":"venue"
},
  "geometry": {"coordinates":[-94.476872,39.005792],"type":"Point"}
}