{
  "type": "Feature",
  "properties": {
    "addr:full":"1020 Kingsway Dr Cape Girardeau MO 63701",
    "addr:housenumber":"1020",
    "addr:postcode":"63701",
    "addr:street":"Kingsway Dr",
    "iso:country":"US",
    "sg:address":"1020 Kingsway Dr",
    "sg:city":"Cape Girardeau",
    "sg:classifiers":[
        {
            "category":"Insurance",
            "subcategory":"Insurance Agent",
            "type":"Services"
        }
    ],
    "sg:phone":"+1 573 334 2603",
    "sg:postcode":"63701",
    "sg:province":"MO",
    "wof:name":"Prudential",
    "wof:placetype":"venue"
},
  "geometry": {"coordinates":[-89.556558,37.320047],"type":"Point"}
}