{
  "type": "Feature",
  "properties": {
    "iso:country":"US",
    "sg:address":"906 Main St",
    "sg:city":"Boonville",
    "sg:classifiers":[
        {
            "category":"Personal",
            "subcategory":"Beauty Salon",
            "type":"Services"
        }
    ],
    "sg:phone":"+1 660 882 8333",
    "sg:postcode":"65233",
    "sg:province":"MO",
    "wof:name":"Hair Play",
    "wof:placetype":"venue"
},
  "geometry": {"coordinates":[-92.741952,38.969385],"type":"Point"}
}