{
  "type": "Feature",
  "properties": {
    "iso:country":"US",
    "sg:address":"1406 Forum Blvd",
    "sg:city":"Columbia",
    "sg:classifiers":[
        {
            "category":"Utilities",
            "subcategory":"Mobile Phone",
            "type":"Services"
        }
    ],
    "sg:phone":"+1 573 446 6680",
    "sg:postcode":"65203",
    "sg:province":"MO",
    "sg:tags":[
        "telephone",
        "cellular"
    ],
    "wof:name":"Cingular Wireless",
    "wof:placetype":"venue"
},
  "geometry": {"coordinates":[-92.360477,38.934878],"type":"Point"}
}