{
  "type": "Feature",
  "properties": {
    "iso:country":"US",
    "sg:address":"501 W Adamson St",
    "sg:city":"Miller",
    "sg:classifiers":[
        {
            "category":"Professional",
            "subcategory":"Detective & Security Services",
            "type":"Services"
        }
    ],
    "sg:phone":"+1 417 452 3324",
    "sg:postcode":"65707",
    "sg:province":"MO",
    "sg:tags":[
        "information",
        "bureau"
    ],
    "wof:name":"Jay Construction Services",
    "wof:placetype":"venue"
},
  "geometry": {"coordinates":[-93.846462,37.212334],"type":"Point"}
}