{
  "type": "Feature",
  "properties": {
    "iso:country":"US",
    "sg:address":"625 S Skinker Blvd Apt 503",
    "sg:city":"Saint Louis",
    "sg:classifiers":[
        {
            "category":"Health Services",
            "subcategory":"Doctor",
            "type":"Services"
        }
    ],
    "sg:phone":"+1 314 725 1137",
    "sg:postcode":"63105",
    "sg:province":"MO",
    "wof:name":"Shieber Wm MD",
    "wof:placetype":"venue"
},
  "geometry": {"coordinates":[-90.303398,38.638401],"type":"Point"}
}