{
  "type": "Feature",
  "properties": {
    "iso:country":"US",
    "sg:address":"5410 N Euclid Ave",
    "sg:city":"St Louis",
    "sg:classifiers":[
        {
            "category":"Manufacturing",
            "subcategory":"Tools & Machinery",
            "type":"Manufacturing & Wholesale Goods"
        }
    ],
    "sg:phone":"+1 314 381 0500",
    "sg:postcode":"63115",
    "sg:province":"MO",
    "sg:tags":[
        "door"
    ],
    "sg:website":"www.emsdoors.com",
    "wof:name":"EMS Group Inc",
    "wof:placetype":"venue"
},
  "geometry": {"coordinates":[-90.238685,38.686857],"type":"Point"}
}