{
  "type": "Feature",
  "properties": {
    "iso:country":"US",
    "sg:address":"1245 Little Missouri Rd",
    "sg:city":"Pineville",
    "sg:classifiers":[
        {
            "category":"Shopping",
            "subcategory":"Crafts & Fabrics",
            "type":"Retail Goods"
        }
    ],
    "sg:phone":"+1 417 226 4540",
    "sg:postcode":"64856",
    "sg:province":"MO",
    "sg:tags":[
        "art",
        "supply"
    ],
    "wof:name":"Oakcreek Woodworks",
    "wof:placetype":"venue"
},
  "geometry": {"coordinates":[-94.27666600000001,36.526332],"type":"Point"}
}