{
  "type": "Feature",
  "properties": {
    "iso:country":"US",
    "sg:address":"515 Burkarth Rd",
    "sg:city":"Warrensburg",
    "sg:classifiers":[
        {
            "category":"Health Services",
            "subcategory":"Doctor",
            "type":"Services"
        }
    ],
    "sg:phone":"+1 660 747 5444",
    "sg:postcode":"64093",
    "sg:province":"MO",
    "sg:tags":[
        "physician",
        "surgeon"
    ],
    "wof:name":"Ear Nose & Throat Plastic Srgr",
    "wof:placetype":"venue"
},
  "geometry": {"coordinates":[-93.723583,38.767487],"type":"Point"}
}