{
  "type": "Feature",
  "properties": {
    "iso:country":"US",
    "sg:address":"11277 US Hwy 61",
    "sg:city":"Frankford",
    "sg:classifiers":[
        {
            "category":"Building & Trades",
            "subcategory":"Construction",
            "type":"Services"
        }
    ],
    "sg:phone":"+1 573 324 2882",
    "sg:postcode":"63441",
    "sg:province":"MO",
    "sg:tags":[
        "cabinet",
        "carpentry",
        "maker",
        "contractor"
    ],
    "wof:name":"Greens Custom Cabinets",
    "wof:placetype":"venue"
},
  "geometry": {"coordinates":[-91.255683,39.428879],"type":"Point"}
}