{
  "type": "Feature",
  "properties": {
    "iso:country":"US",
    "sg:address":"1901 S Broadway St",
    "sg:city":"Poplar Bluff",
    "sg:classifiers":[
        {
            "category":"Retail",
            "subcategory":"Auto Repair",
            "type":"Services"
        }
    ],
    "sg:phone":"+1 573 686 3444",
    "sg:postcode":"63901",
    "sg:province":"MO",
    "sg:tags":[
        "muffler",
        "exhaust",
        "system"
    ],
    "wof:name":"Alan's Muffler & Speed Shop",
    "wof:placetype":"venue"
},
  "geometry": {"coordinates":[-90.395765,36.741434],"type":"Point"}
}