{
  "type": "Feature",
  "properties": {
    "iso:country":"US",
    "sg:address":"1031 Bellevue Ave Ste 280",
    "sg:city":"Saint Louis",
    "sg:classifiers":[
        {
            "category":"Health Services",
            "subcategory":"Doctor",
            "type":"Services"
        }
    ],
    "sg:phone":"+1 314 647 9444",
    "sg:postcode":"63117",
    "sg:province":"MO",
    "sg:website":"www.essehealth.com",
    "wof:name":"Esse Health",
    "wof:placetype":"venue"
},
  "geometry": {"coordinates":[-90.312209,38.632969],"type":"Point"}
}