{
  "type": "Feature",
  "properties": {
    "iso:country":"US",
    "sg:address":"206 N Harlem Ave",
    "sg:city":"Joplin",
    "sg:classifiers":[
        {
            "category":"Building & Trades",
            "subcategory":"Construction",
            "type":"Services"
        }
    ],
    "sg:phone":"+1 417 781 5700",
    "sg:postcode":"64801",
    "sg:province":"MO",
    "sg:tags":[
        "nonresidential"
    ],
    "wof:name":"Duff Construction",
    "wof:placetype":"venue"
},
  "geometry": {"coordinates":[-94.529481,37.092414],"type":"Point"}
}