{
  "type": "Feature",
  "properties": {
    "iso:country":"US",
    "sg:address":"1716 Ferry Rd",
    "sg:city":"Morrison",
    "sg:classifiers":[
        {
            "category":"Local Transit",
            "type":"Transportation"
        }
    ],
    "sg:phone":"+1 573 294 1114",
    "sg:postcode":"65061",
    "sg:province":"MO",
    "sg:tags":[
        "public"
    ],
    "wof:name":"Fredicksberg Ferry",
    "wof:placetype":"venue"
},
  "geometry": {"coordinates":[-91.64135,38.608309],"type":"Point"}
}