{
  "type": "Feature",
  "properties": {
    "iso:country":"US",
    "sg:address":"106 S 7th St",
    "sg:city":"St Joseph",
    "sg:classifiers":[
        {
            "category":"Professional",
            "subcategory":"Lawyer & Legal Services",
            "type":"Services"
        }
    ],
    "sg:phone":"+1 816 364 2325",
    "sg:postcode":"64501",
    "sg:province":"MO",
    "sg:tags":[
        "attorney"
    ],
    "wof:name":"Legal Aid Of Western Missouri",
    "wof:placetype":"venue"
},
  "geometry": {"coordinates":[-94.851973,39.765863],"type":"Point"}
}