{
  "type": "Feature",
  "properties": {
    "iso:country":"US",
    "sg:address":"225 S Meramec Ave",
    "sg:city":"Saint Louis",
    "sg:classifiers":[
        {
            "category":"Health Services",
            "subcategory":"Health Practitioner",
            "type":"Services"
        }
    ],
    "sg:phone":"+1 314 721 6555",
    "sg:postcode":"63105",
    "sg:province":"MO",
    "wof:name":"Eckelman C Cleary",
    "wof:placetype":"venue"
},
  "geometry": {"coordinates":[-90.340318,38.64624],"type":"Point"}
}