{
  "type": "Feature",
  "properties": {
    "iso:country":"US",
    "sg:address":"316 N Massey Blvd",
    "sg:city":"Nixa",
    "sg:classifiers":[
        {
            "category":"Utilities",
            "subcategory":"Mobile Phone",
            "type":"Services"
        }
    ],
    "sg:phone":"+1 417 725 1012",
    "sg:postcode":"65714",
    "sg:province":"MO",
    "sg:tags":[
        "telephone",
        "cellular"
    ],
    "wof:name":"Alltel Mobile",
    "wof:placetype":"venue"
},
  "geometry": {"coordinates":[-93.302902,37.046351],"type":"Point"}
}