{
  "type": "Feature",
  "properties": {
    "iso:country":"US",
    "sg:address":"2111 Smizer Mill Rd",
    "sg:city":"Fenton",
    "sg:classifiers":[
        {
            "category":"Banks & Credit Unions",
            "subcategory":"Bank",
            "type":"Services"
        }
    ],
    "sg:phone":"+1 636 225 9600",
    "sg:postcode":"63026",
    "sg:province":"MO",
    "sg:tags":[
        "loan",
        "real estate"
    ],
    "wof:name":"Allied Home Mortgage Capital",
    "wof:placetype":"venue"
},
  "geometry": {"coordinates":[-90.50202899999999,38.530299],"type":"Point"}
}