{
  "type": "Feature",
  "properties": {
    "iso:country":"US",
    "sg:address":"8131 N Oak Fwy",
    "sg:city":"Kansas City",
    "sg:classifiers":[
        {
            "category":"Autos & Motor Vehicles",
            "subcategory":"Automobile Sales",
            "type":"Retail Goods"
        }
    ],
    "sg:phone":"+1 816 436 7474",
    "sg:postcode":"64118",
    "sg:province":"MO",
    "sg:tags":[
        "car",
        "dealer"
    ],
    "wof:name":"Cascone's Used Cars Sales",
    "wof:placetype":"venue"
},
  "geometry": {"coordinates":[-94.575869,39.242759],"type":"Point"}
}