{
  "type": "Feature",
  "properties": {
    "iso:country":"US",
    "sg:address":"5471 Dr Martin Luther King Dr",
    "sg:city":"Saint Louis",
    "sg:classifiers":[
        {
            "category":"Health Services",
            "subcategory":"Clinic",
            "type":"Services"
        }
    ],
    "sg:phone":"+1 314 367 5820",
    "sg:postcode":"63112",
    "sg:province":"MO",
    "sg:tags":[
        "care"
    ],
    "wof:name":"St Louis Comp Health Center",
    "wof:placetype":"venue"
},
  "geometry": {"coordinates":[-90.27227499999999,38.668319],"type":"Point"}
}