{
  "type": "Feature",
  "properties": {
    "iso:country":"US",
    "sg:address":"7900 Forsyth Blvd",
    "sg:city":"Saint Louis",
    "sg:classifiers":[
        {
            "category":"Government",
            "subcategory":"Jail",
            "type":"Public Place"
        }
    ],
    "sg:phone":"+1 314 615 5699",
    "sg:postcode":"63105",
    "sg:province":"MO",
    "sg:tags":[
        "correctional",
        "institution"
    ],
    "wof:name":"Services",
    "wof:placetype":"venue"
},
  "geometry": {"coordinates":[-90.33963799999999,38.650366],"type":"Point"}
}