{
  "type": "Feature",
  "properties": {
    "iso:country":"US",
    "sg:address":"411 Shawnee Cir",
    "sg:city":"Jackson",
    "sg:classifiers":[
        {
            "category":"Real Estate",
            "subcategory":"Real Estate Agent",
            "type":"Services"
        }
    ],
    "sg:phone":"+1 573 243 7270",
    "sg:postcode":"63755",
    "sg:province":"MO",
    "sg:tags":[
        "appraiser"
    ],
    "wof:name":"1st Priority Home Inspections",
    "wof:placetype":"venue"
},
  "geometry": {"coordinates":[-89.65196400000001,37.37765],"type":"Point"}
}