{
  "type": "Feature",
  "properties": {
    "iso:country":"US",
    "sg:address":"11815 Rosary Ln",
    "sg:city":"St Louis",
    "sg:classifiers":[
        {
            "category":"Building & Trades",
            "subcategory":"Cleaning & Sanitation",
            "type":"Services"
        }
    ],
    "sg:phone":"+1 314 355 6567",
    "sg:postcode":"63138",
    "sg:province":"MO",
    "sg:tags":[
        "janitor"
    ],
    "wof:name":"Busy Bee Janitorial & Carpet",
    "wof:placetype":"venue"
},
  "geometry": {"coordinates":[-90.224422,38.787541],"type":"Point"}
}