{
  "type": "Feature",
  "properties": {
    "iso:country":"US",
    "sg:address":"601 Fairground Ave",
    "sg:city":"Higginsville",
    "sg:classifiers":[
        {
            "category":"Real Estate",
            "subcategory":"Real Estate Agent",
            "type":"Services"
        }
    ],
    "sg:phone":"+1 660 584 7991",
    "sg:postcode":"64037",
    "sg:province":"MO",
    "wof:name":"Action Realty",
    "wof:placetype":"venue"
},
  "geometry": {"coordinates":[-93.727701,39.069213],"type":"Point"}
}