{
  "type": "Feature",
  "properties": {
    "iso:country":"US",
    "sg:address":"8831 Cozens Ave",
    "sg:city":"Saint Louis",
    "sg:classifiers":[
        {
            "category":"Education",
            "subcategory":"School",
            "type":"Public Place"
        }
    ],
    "sg:phone":"+1 314 653 8150",
    "sg:postcode":"63136",
    "sg:province":"MO",
    "sg:tags":[
        "elementary",
        "secondary"
    ],
    "wof:name":"Jennings Jr High Sch",
    "wof:placetype":"venue"
},
  "geometry": {"coordinates":[-90.25783699999999,38.727148],"type":"Point"}
}