{
  "type": "Feature",
  "properties": {
    "iso:country":"US",
    "sg:address":"602 N Elm St",
    "sg:city":"Rolla",
    "sg:classifiers":[
        {
            "category":"Retail",
            "subcategory":"Repair Shop",
            "type":"Services"
        }
    ],
    "sg:phone":"+1 573 885 6078",
    "sg:postcode":"65401",
    "sg:province":"MO",
    "sg:tags":[
        "used",
        "merchandise"
    ],
    "wof:name":"Able Lock & Key",
    "wof:placetype":"venue"
},
  "geometry": {"coordinates":[-91.770504,37.949133],"type":"Point"}
}