{
  "type": "Feature",
  "properties": {
    "iso:country":"US",
    "sg:address":"7405 N Ava Ave",
    "sg:city":"Kansas City",
    "sg:classifiers":[
        {
            "category":"Professional",
            "subcategory":"Advertising",
            "type":"Services"
        }
    ],
    "sg:phone":"+1 816 584 1025",
    "sg:postcode":"64151",
    "sg:province":"MO",
    "sg:tags":[
        "graphic",
        "agency",
        "design"
    ],
    "wof:name":"Davis Design Group Inc",
    "wof:placetype":"venue"
},
  "geometry": {"coordinates":[-94.623361,39.229731],"type":"Point"}
}