{
  "type": "Feature",
  "properties": {
    "iso:country":"US",
    "sg:address":"26426 Georgetown Ave",
    "sg:city":"Warsaw",
    "sg:classifiers":[
        {
            "category":"Restaurant",
            "type":"Food & Drink"
        }
    ],
    "sg:phone":"+1 660 438 6564",
    "sg:postcode":"65355",
    "sg:province":"MO",
    "wof:name":"Rocky Top Cafe",
    "wof:placetype":"venue"
},
  "geometry": {"coordinates":[-93.391618,38.305856],"type":"Point"}
}