{
  "type": "Feature",
  "properties": {
    "iso:country":"US",
    "sg:address":"421 W Miller St",
    "sg:city":"Jefferson City",
    "sg:classifiers":[
        {
            "category":"Shopping",
            "subcategory":"Gifts & Souvenirs",
            "type":"Retail Goods"
        }
    ],
    "sg:phone":"+1 573 635 8278",
    "sg:postcode":"65101",
    "sg:province":"MO",
    "sg:tags":[
        "shop"
    ],
    "wof:name":"Tra-Art LTD",
    "wof:placetype":"venue"
},
  "geometry": {"coordinates":[-92.179726,38.578424],"type":"Point"}
}