{
  "type": "Feature",
  "properties": {
    "iso:country":"US",
    "sg:address":"20 Burl Dr",
    "sg:city":"St Peters",
    "sg:classifiers":[
        {
            "category":"Retail",
            "subcategory":"Repair Shop",
            "type":"Services"
        }
    ],
    "sg:phone":"+1 636 272 6308",
    "sg:postcode":"63376",
    "sg:province":"MO",
    "sg:tags":[
        "upholsterer"
    ],
    "wof:name":"Robin's Upholstery & Interiors",
    "wof:placetype":"venue"
},
  "geometry": {"coordinates":[-90.69464000000001,38.78875],"type":"Point"}
}