{
  "type": "Feature",
  "properties": {
    "iso:country":"US",
    "sg:address":"1246 Running Waters Dr",
    "sg:city":"St Charles",
    "sg:classifiers":[
        {
            "category":"Professional",
            "subcategory":"Business Services",
            "type":"Services"
        }
    ],
    "sg:phone":"+1 636 926 9144",
    "sg:postcode":"63304",
    "sg:province":"MO",
    "sg:tags":[
        "transcribing",
        "disc"
    ],
    "wof:name":"Transcripts To Go",
    "wof:placetype":"venue"
},
  "geometry": {"coordinates":[-90.675039,38.735633],"type":"Point"}
}