{
  "type": "Feature",
  "properties": {
    "iso:country":"US",
    "sg:address":"645 Leffingwell Ave",
    "sg:city":"St Louis",
    "sg:classifiers":[
        {
            "category":"Building & Trades",
            "subcategory":"Construction",
            "type":"Services"
        }
    ],
    "sg:phone":"+1 314 965 1212",
    "sg:postcode":"63122",
    "sg:province":"MO",
    "sg:tags":[
        "repairing",
        "carpentry",
        "remodeling",
        "contractor"
    ],
    "wof:name":"P K Construction Co",
    "wof:placetype":"venue"
},
  "geometry": {"coordinates":[-90.392173,38.570918],"type":"Point"}
}