{
  "type": "Feature",
  "properties": {
    "iso:country":"US",
    "sg:address":"306 Roanoake",
    "sg:city":"Warrenton",
    "sg:classifiers":[
        {
            "category":"Professional",
            "type":"Services"
        }
    ],
    "sg:phone":"+1 636 456 2737",
    "sg:postcode":"63383",
    "sg:province":"MO",
    "wof:name":"Boones Hollowcommerce Center",
    "wof:placetype":"venue"
},
  "geometry": {"coordinates":[-91.131264,38.822589],"type":"Point"}
}