{
  "type": "Feature",
  "properties": {
    "iso:country":"US",
    "sg:address":"5008 S Grand Blvd",
    "sg:city":"Saint Louis",
    "sg:classifiers":[
        {
            "category":"Food & Beverages",
            "subcategory":"Groceries & Convenience Stores",
            "type":"Retail Goods"
        }
    ],
    "sg:phone":"+1 314 752 8443",
    "sg:postcode":"63111",
    "sg:province":"MO",
    "wof:name":"Kaiser's Grand Mart",
    "wof:placetype":"venue"
},
  "geometry": {"coordinates":[-90.250849,38.572736],"type":"Point"}
}