{
  "type": "Feature",
  "properties": {
    "iso:country":"US",
    "sg:address":"1863 W Copper Creek Dr",
    "sg:city":"Nixa",
    "sg:classifiers":[
        {
            "category":"Professional",
            "type":"Services"
        }
    ],
    "sg:phone":"+1 417 724 2927",
    "sg:postcode":"65714",
    "sg:province":"MO",
    "wof:name":"Heartland Southwest",
    "wof:placetype":"venue"
},
  "geometry": {"coordinates":[-93.352299,37.036856],"type":"Point"}
}