{
  "type": "Feature",
  "properties": {
    "iso:country":"US",
    "sg:address":"4359 State Hwy 43",
    "sg:city":"Joplin",
    "sg:classifiers":[
        {
            "category":"Food & Beverages",
            "subcategory":"Groceries & Convenience Stores",
            "type":"Retail Goods"
        }
    ],
    "sg:phone":"+1 417 623 2246",
    "sg:postcode":"64804",
    "sg:province":"MO",
    "sg:tags":[
        "trailer"
    ],
    "wof:name":"Joplin KOA Campground",
    "wof:placetype":"venue"
},
  "geometry": {"coordinates":[-94.551832,37.004019],"type":"Point"}
}