{
  "type": "Feature",
  "properties": {
    "iso:country":"US",
    "sg:address":"500 E 13th St",
    "sg:city":"Mountain Grove",
    "sg:classifiers":[
        {
            "category":"Building & Trades",
            "subcategory":"Construction",
            "type":"Services"
        }
    ],
    "sg:phone":"+1 417 926 6285",
    "sg:postcode":"65711",
    "sg:province":"MO",
    "sg:tags":[
        "residential"
    ],
    "wof:name":"Keith Koehn",
    "wof:placetype":"venue"
},
  "geometry": {"coordinates":[-92.256879,37.139866],"type":"Point"}
}