{
  "type": "Feature",
  "properties": {
    "iso:country":"US",
    "sg:address":"4320 E Mcgee Rd",
    "sg:city":"Columbia",
    "sg:classifiers":[
        {
            "category":"Building & Trades",
            "subcategory":"Pest Control",
            "type":"Services"
        }
    ],
    "sg:phone":"+1 573 696 3830",
    "sg:postcode":"65202",
    "sg:province":"MO",
    "wof:name":"Otto's Termite & Pest Control",
    "wof:placetype":"venue"
},
  "geometry": {"coordinates":[-92.27095799999999,39.05883],"type":"Point"}
}