{
  "type": "Feature",
  "properties": {
    "iso:country":"US",
    "sg:address":"507 E Madison St",
    "sg:city":"Hayti",
    "sg:classifiers":[
        {
            "category":"Freight",
            "type":"Transportation"
        }
    ],
    "sg:phone":"+1 573 359 1370",
    "sg:postcode":"63851",
    "sg:province":"MO",
    "sg:tags":[
        "operator",
        "trucking"
    ],
    "wof:name":"Rwb SSS Inc",
    "wof:placetype":"venue"
},
  "geometry": {"coordinates":[-89.746711,36.234866],"type":"Point"}
}