{
  "type": "Feature",
  "properties": {
    "iso:country":"US",
    "sg:address":"676 NW 10th Ln",
    "sg:city":"Lamar",
    "sg:classifiers":[
        {
            "category":"Farming",
            "subcategory":"Livestock Farm",
            "type":"Manufacturing & Wholesale Goods"
        }
    ],
    "sg:phone":"+1 417 884 5129",
    "sg:postcode":"64759",
    "sg:province":"MO",
    "sg:tags":[
        "feedlot",
        "hog",
        "or",
        "beef",
        "cattle"
    ],
    "wof:name":"Rainbows Inn & Farm",
    "wof:placetype":"venue"
},
  "geometry": {"coordinates":[-94.31139400000001,37.597628],"type":"Point"}
}