{
  "type": "Feature",
  "properties": {
    "iso:country":"US",
    "sg:address":"14254 Manchester Rd",
    "sg:city":"Ballwin",
    "sg:classifiers":[
        {
            "category":"Shopping",
            "type":"Retail Goods"
        }
    ],
    "sg:phone":"+1 636 527 6663",
    "sg:postcode":"63011",
    "sg:province":"MO",
    "sg:tags":[
        "merchandise"
    ],
    "wof:name":"Art & Accents",
    "wof:placetype":"venue"
},
  "geometry": {"coordinates":[-90.504952,38.592605],"type":"Point"}
}