{
  "type": "Feature",
  "properties": {
    "iso:country":"US",
    "sg:address":"832 W Highway 42",
    "sg:city":"Iberia",
    "sg:classifiers":[
        {
            "category":"Banks & Credit Unions",
            "subcategory":"Financial Services",
            "type":"Services"
        }
    ],
    "sg:phone":"+1 573 793 3104",
    "sg:postcode":"65486",
    "sg:province":"MO",
    "sg:tags":[
        "marketing",
        "direct"
    ],
    "wof:name":"Rocktown Fresh Air",
    "wof:placetype":"venue"
},
  "geometry": {"coordinates":[-92.254623,38.111526],"type":"Point"}
}