{
  "type": "Feature",
  "properties": {
    "iso:country":"US",
    "sg:address":"2190 Mason Rd",
    "sg:city":"Saint Louis",
    "sg:classifiers":[
        {
            "category":"Education",
            "subcategory":"School",
            "type":"Public Place"
        }
    ],
    "sg:phone":"+1 314 821 0909",
    "sg:postcode":"63131",
    "sg:province":"MO",
    "wof:name":"Reading Enrichment & Developme",
    "wof:placetype":"venue"
},
  "geometry": {"coordinates":[-90.479462,38.596978],"type":"Point"}
}