{
  "type": "Feature",
  "properties": {
    "iso:country":"US",
    "sg:address":"802 US Hwy 40",
    "sg:city":"Blue Springs",
    "sg:classifiers":[
        {
            "category":"Banks & Credit Unions",
            "subcategory":"Bank",
            "type":"Services"
        }
    ],
    "sg:phone":"+1 816 228 2421",
    "sg:postcode":"64015",
    "sg:province":"MO",
    "sg:tags":[
        "cashing",
        "check"
    ],
    "wof:name":"National Cash Advance",
    "wof:placetype":"venue"
},
  "geometry": {"coordinates":[-94.27308600000001,39.009065],"type":"Point"}
}