{
  "type": "Feature",
  "properties": {
    "iso:country":"US",
    "sg:address":"6360 Clayton Rd",
    "sg:city":"Saint Louis",
    "sg:classifiers":[
        {
            "category":"Retail",
            "subcategory":"Laundry & Dry Cleaning",
            "type":"Services"
        }
    ],
    "sg:phone":"+1 314 644 4999",
    "sg:postcode":"63117",
    "sg:province":"MO",
    "wof:name":"Tip-Top Cleaners",
    "wof:placetype":"venue"
},
  "geometry": {"coordinates":[-90.3088,38.6339],"type":"Point"}
}