{
  "type": "Feature",
  "properties": {
    "iso:country":"US",
    "sg:address":"1209 SE Grand Dd Hwy",
    "sg:city":"Faucett",
    "sg:classifiers":[
        {
            "category":"Banks & Credit Unions",
            "subcategory":"Bank",
            "type":"Services"
        }
    ],
    "sg:phone":"+1 816 238 4564",
    "sg:postcode":"64448",
    "sg:province":"MO",
    "wof:name":"UMB Bank",
    "wof:placetype":"venue"
},
  "geometry": {"coordinates":[-94.796689,39.599695],"type":"Point"}
}