{
  "type": "Feature",
  "properties": {
    "iso:country":"US",
    "sg:address":"1201 W Davis St",
    "sg:city":"Fayette",
    "sg:phone":"+1 660 248 2478",
    "sg:postcode":"65248",
    "sg:province":"MO",
    "sg:tags":[
        "farm",
        "corn",
        "grain",
        "cash",
        "soybean"
    ],
    "wof:name":"Ray Kimmel",
    "wof:placetype":"venue"
},
  "geometry": {"coordinates":[-92.697451,39.146128],"type":"Point"}
}