{
  "type": "Feature",
  "properties": {
    "iso:country":"US",
    "sg:address":"202 E Main St",
    "sg:city":"Union",
    "sg:classifiers":[
        {
            "category":"Professional",
            "subcategory":"Engineering",
            "type":"Services"
        }
    ],
    "sg:phone":"+1 636 583 8885",
    "sg:postcode":"63084",
    "sg:province":"MO",
    "sg:tags":[
        "engineer"
    ],
    "wof:name":"Brunjes & Assoc Inc",
    "wof:placetype":"venue"
},
  "geometry": {"coordinates":[-91.007318,38.445413],"type":"Point"}
}