{
  "type": "Feature",
  "properties": {
    "iso:country":"US",
    "sg:address":"1949 Co Rd 474",
    "sg:city":"Steele",
    "sg:classifiers":[
        {
            "category":"Freight",
            "type":"Transportation"
        }
    ],
    "sg:phone":"+1 573 737 2871",
    "sg:postcode":"63877",
    "sg:province":"MO",
    "sg:tags":[
        "operator",
        "local",
        "trucking"
    ],
    "wof:name":"Jones Farm Trucking",
    "wof:placetype":"venue"
},
  "geometry": {"coordinates":[-89.959372,36.074389],"type":"Point"}
}