{
  "type": "Feature",
  "properties": {
    "iso:country":"US",
    "sg:address":"265 US Hwy 50",
    "sg:city":"Warrensburg",
    "sg:classifiers":[
        {
            "category":"Local Transit",
            "type":"Transportation"
        }
    ],
    "sg:phone":"+1 660 747 5309",
    "sg:postcode":"64093",
    "sg:province":"MO",
    "sg:tags":[
        "limousine"
    ],
    "wof:name":"Luxury Limousine-Warrensburg",
    "wof:placetype":"venue"
},
  "geometry": {"coordinates":[-93.665116,38.772821],"type":"Point"}
}