{
  "type": "Feature",
  "properties": {
    "iso:country":"US",
    "sg:address":"2 Saint Louis Ave",
    "sg:city":"Fulton",
    "sg:classifiers":[
        {
            "category":"Health Services",
            "subcategory":"Nursing And Care Facility",
            "type":"Services"
        }
    ],
    "sg:phone":"+1 573 642 0910",
    "sg:postcode":"65251",
    "sg:province":"MO",
    "sg:tags":[
        "intermediate"
    ],
    "wof:name":"Kingdom Hospice",
    "wof:placetype":"venue"
},
  "geometry": {"coordinates":[-91.947773,38.850525],"type":"Point"}
}