{
  "type": "Feature",
  "properties": {
    "iso:country":"US",
    "sg:address":"14780 Manchester Rd",
    "sg:city":"Ballwin",
    "sg:classifiers":[
        {
            "category":"Building & Trades",
            "subcategory":"Plumbing",
            "type":"Services"
        }
    ],
    "sg:phone":"+1 636 230 8916",
    "sg:postcode":"63011",
    "sg:province":"MO",
    "sg:tags":[
        "contractor"
    ],
    "wof:name":"Americas Choice Plumbing",
    "wof:placetype":"venue"
},
  "geometry": {"coordinates":[-90.53330099999999,38.592987],"type":"Point"}
}