{
  "type": "Feature",
  "properties": {
    "iso:country":"US",
    "sg:address":"81 Elaine Dr",
    "sg:city":"O Fallon",
    "sg:classifiers":[
        {
            "category":"Shopping",
            "type":"Retail Goods"
        }
    ],
    "sg:phone":"+1 636 379 8724",
    "sg:postcode":"63366",
    "sg:province":"MO",
    "sg:tags":[
        "factory",
        "outlet"
    ],
    "wof:name":"Outlet Store",
    "wof:placetype":"venue"
},
  "geometry": {"coordinates":[-90.723984,38.807761],"type":"Point"}
}