{
  "type": "Feature",
  "properties": {
    "iso:country":"US",
    "sg:address":"9889 Page Ave",
    "sg:city":"Saint Louis",
    "sg:classifiers":[
        {
            "category":"Building & Trades",
            "subcategory":"Construction",
            "type":"Services"
        }
    ],
    "sg:phone":"+1 314 428 6100",
    "sg:postcode":"63132",
    "sg:province":"MO",
    "sg:tags":[
        "roofing",
        "sheet",
        "work",
        "metal",
        "contractor",
        "siding",
        "or"
    ],
    "wof:name":"Statewide Restoration Services",
    "wof:placetype":"venue"
},
  "geometry": {"coordinates":[-90.37869000000001,38.689873],"type":"Point"}
}