{
  "type": "Feature",
  "properties": {
    "iso:country":"US",
    "sg:address":"2001 W Worley St",
    "sg:city":"Columbia",
    "sg:classifiers":[
        {
            "category":"Shopping",
            "subcategory":"Hobbies, Toys, & Games",
            "type":"Retail Goods"
        }
    ],
    "sg:phone":"+1 573 445 4443",
    "sg:postcode":"65203",
    "sg:province":"MO",
    "sg:tags":[
        "craft",
        "supply"
    ],
    "wof:name":"Hobby Lobby Creative Ctr",
    "wof:placetype":"venue"
},
  "geometry": {"coordinates":[-92.37002,38.96105],"type":"Point"}
}