{
  "type": "Feature",
  "properties": {
    "iso:country":"US",
    "sg:address":"302 E Harmon St",
    "sg:city":"Pineville",
    "sg:classifiers":[
        {
            "category":"Health Services",
            "subcategory":"Doctor",
            "type":"Services"
        }
    ],
    "sg:phone":"+1 417 223 2243",
    "sg:postcode":"64856",
    "sg:province":"MO",
    "sg:tags":[
        "dentist"
    ],
    "wof:name":"Area Community Health",
    "wof:placetype":"venue"
},
  "geometry": {"coordinates":[-94.383129,36.594007],"type":"Point"}
}