{
  "type": "Feature",
  "properties": {
    "iso:country":"US",
    "sg:address":"400 W Daugherty St",
    "sg:city":"Webb City",
    "sg:classifiers":[
        {
            "category":"Retail",
            "subcategory":"Funeral Services",
            "type":"Services"
        }
    ],
    "sg:phone":"+1 417 673 2411",
    "sg:postcode":"64870",
    "sg:province":"MO",
    "sg:tags":[
        "plan"
    ],
    "wof:name":"Simpson Funeral Home Inc",
    "wof:placetype":"venue"
},
  "geometry": {"coordinates":[-94.46742999999999,37.147386],"type":"Point"}
}