{
  "type": "Feature",
  "properties": {
    "iso:country":"US",
    "sg:address":"30212 S Hess Rd",
    "sg:city":"Harrisonville",
    "sg:classifiers":[
        {
            "category":"Wholesale",
            "subcategory":"Drugs",
            "type":"Manufacturing & Wholesale Goods"
        }
    ],
    "sg:phone":"+1 816 380 3215",
    "sg:postcode":"64701",
    "sg:province":"MO",
    "wof:name":"Arbonne",
    "wof:placetype":"venue"
},
  "geometry": {"coordinates":[-94.398641,38.568807],"type":"Point"}
}