{
  "type": "Feature",
  "properties": {
    "iso:country":"US",
    "sg:address":"1814 Eton Ln",
    "sg:city":"Saint Louis",
    "sg:classifiers":[
        {
            "category":"Social Services",
            "subcategory":"Child Care",
            "type":"Services"
        }
    ],
    "sg:phone":"+1 314 381 1102",
    "sg:postcode":"63147",
    "sg:province":"MO",
    "sg:tags":[
        "day"
    ],
    "wof:name":"Fullers Family Day Care",
    "wof:placetype":"venue"
},
  "geometry": {"coordinates":[-90.251672,38.715346],"type":"Point"}
}