{
  "type": "Feature",
  "properties": {
    "iso:country":"US",
    "sg:address":"9 Godfrey Ln",
    "sg:city":"Saint Louis",
    "sg:classifiers":[
        {
            "category":"Shopping",
            "subcategory":"Crafts & Fabrics",
            "type":"Retail Goods"
        }
    ],
    "sg:phone":"+1 314 521 6964",
    "sg:postcode":"63135",
    "sg:province":"MO",
    "sg:tags":[
        "sewing"
    ],
    "wof:name":"Little Stitches By Rose Mary",
    "wof:placetype":"venue"
},
  "geometry": {"coordinates":[-90.295174,38.740453],"type":"Point"}
}