{
  "type": "Feature",
  "properties": {
    "iso:country":"US",
    "sg:address":"612 E High St",
    "sg:city":"Potosi",
    "sg:classifiers":[
        {
            "category":"Health Services",
            "subcategory":"Doctor",
            "type":"Services"
        },
        {
            "category":"Health Services",
            "subcategory":"Clinic",
            "type":"Services"
        }
    ],
    "sg:phone":"+1 573 438 3660",
    "sg:postcode":"63664",
    "sg:province":"MO",
    "sg:tags":[
        "physician",
        "family",
        "practice",
        "surgeons",
        "osteopathic",
        "medicine"
    ],
    "wof:name":"Terpstra Gregory DO",
    "wof:placetype":"venue"
},
  "geometry": {"coordinates":[-90.780198,37.931728],"type":"Point"}
}