{
  "type": "Feature",
  "properties": {
    "iso:country":"US",
    "sg:address":"479 Airport Rd",
    "sg:city":"Ferguson",
    "sg:classifiers":[
        {
            "category":"Retail",
            "subcategory":"Auto Repair",
            "type":"Services"
        }
    ],
    "sg:phone":"+1 314 524 0120",
    "sg:postcode":"63135",
    "sg:province":"MO",
    "sg:tags":[
        "automobile",
        "inspection"
    ],
    "wof:name":"Kasper Automotive Svc Co Inc",
    "wof:placetype":"venue"
},
  "geometry": {"coordinates":[-90.311712,38.747164],"type":"Point"}
}