{
  "type": "Feature",
  "properties": {
    "iso:country":"US",
    "sg:address":"4107 Dr Martin Luther King Dr",
    "sg:city":"St Louis",
    "sg:classifiers":[
        {
            "category":"Autos & Motor Vehicles",
            "subcategory":"Auto Supplies",
            "type":"Retail Goods"
        }
    ],
    "sg:phone":"+1 314 652 8365",
    "sg:postcode":"63113",
    "sg:province":"MO",
    "sg:tags":[
        "tire"
    ],
    "wof:name":"M L King Tire",
    "wof:placetype":"venue"
},
  "geometry": {"coordinates":[-90.23680400000001,38.652937],"type":"Point"}
}