{
  "type": "Feature",
  "properties": {
    "iso:country":"US",
    "sg:address":"201 N Monroe St",
    "sg:city":"Versailles",
    "sg:classifiers":[
        {
            "category":"Health Services",
            "subcategory":"Doctor",
            "type":"Services"
        }
    ],
    "sg:phone":"+1 573 378 5767",
    "sg:postcode":"65084",
    "sg:province":"MO",
    "wof:name":"Wilson Eric S DDS PC",
    "wof:placetype":"venue"
},
  "geometry": {"coordinates":[-92.84173,38.43416],"type":"Point"}
}