{
  "type": "Feature",
  "properties": {
    "iso:country":"US",
    "sg:address":"456 Wright Dr",
    "sg:city":"Saint Charles",
    "sg:classifiers":[
        {
            "category":"Retail",
            "subcategory":"Laundry & Dry Cleaning",
            "type":"Services"
        }
    ],
    "sg:phone":"+1 636 443 0034",
    "sg:postcode":"63301",
    "sg:province":"MO",
    "wof:name":"Reylnolds Chem-Dry",
    "wof:placetype":"venue"
},
  "geometry": {"coordinates":[-90.47645199999999,38.810222],"type":"Point"}
}