{
  "type": "Feature",
  "properties": {
    "iso:country":"US",
    "sg:address":"10 Orchard Point Rd",
    "sg:city":"Hannibal",
    "sg:phone":"+1 573 221 0446",
    "sg:postcode":"63401",
    "sg:province":"MO",
    "sg:tags":[
        "farm",
        "wheat",
        "soybean"
    ],
    "wof:name":"William Craigmiles",
    "wof:placetype":"venue"
},
  "geometry": {"coordinates":[-91.378263,39.728393],"type":"Point"}
}