{
  "type": "Feature",
  "properties": {
    "iso:country":"US",
    "sg:address":"3719 Secretariat Dr",
    "sg:city":"Florissant",
    "sg:classifiers":[
        {
            "category":"Professional",
            "subcategory":"Management & Consulting",
            "type":"Services"
        }
    ],
    "sg:phone":"+1 314 831 1800",
    "sg:postcode":"63034",
    "sg:province":"MO",
    "sg:tags":[
        "business"
    ],
    "wof:name":"Paradigm Inc",
    "wof:placetype":"venue"
},
  "geometry": {"coordinates":[-90.31767600000001,38.843202],"type":"Point"}
}