{
  "type": "Feature",
  "properties": {
    "iso:country":"US",
    "sg:address":"412 Eagle Ridge Dr",
    "sg:city":"Saint Peters",
    "sg:classifiers":[
        {
            "category":"Professional",
            "subcategory":"Business Services",
            "type":"Services"
        }
    ],
    "sg:phone":"+1 636 281 3694",
    "sg:postcode":"63376",
    "sg:province":"MO",
    "wof:name":"Marketing Solutions",
    "wof:placetype":"venue"
},
  "geometry": {"coordinates":[-90.66172899999999,38.77887],"type":"Point"}
}