{
  "type": "Feature",
  "properties": {
    "iso:country":"US",
    "sg:address":"26 Webster Oaks Dr",
    "sg:city":"Saint Louis",
    "sg:classifiers":[
        {
            "category":"Communications",
            "subcategory":"Film & Video Production",
            "type":"Services"
        },
        {
            "category":"Education",
            "subcategory":"Special Training",
            "type":"Public Place"
        }
    ],
    "sg:phone":"+1 314 962 9204",
    "sg:postcode":"63119",
    "sg:province":"MO",
    "sg:tags":[
        "theatrical",
        "taping"
    ],
    "wof:name":"Saint James Productions",
    "wof:placetype":"venue"
},
  "geometry": {"coordinates":[-90.36009300000001,38.572415],"type":"Point"}
}