{
  "type": "Feature",
  "properties": {
    "iso:country":"US",
    "sg:address":"326 Orchard Ave",
    "sg:city":"Ballwin",
    "sg:classifiers":[
        {
            "category":"Shopping",
            "subcategory":"Computers & Home Electronics",
            "type":"Retail Goods"
        }
    ],
    "sg:phone":"+1 636 230 0130",
    "sg:postcode":"63021",
    "sg:province":"MO",
    "wof:name":"Faupel Computers and Upgrades",
    "wof:placetype":"venue"
},
  "geometry": {"coordinates":[-90.520368,38.590413],"type":"Point"}
}