{
  "type": "Feature",
  "properties": {
    "iso:country":"US",
    "sg:address":"100 W Center St",
    "sg:city":"Rogersville",
    "sg:classifiers":[
        {
            "category":"Retail",
            "subcategory":"Auto Repair",
            "type":"Services"
        }
    ],
    "sg:phone":"+1 417 753 3132",
    "sg:postcode":"65742",
    "sg:province":"MO",
    "sg:tags":[
        "general"
    ],
    "wof:name":"Rons Automotive & Body Shop",
    "wof:placetype":"venue"
},
  "geometry": {"coordinates":[-93.06010499999999,37.117825],"type":"Point"}
}