{
  "type": "Feature",
  "properties": {
    "iso:country":"US",
    "sg:address":"2649 Cherokee 2nd Fl",
    "sg:city":"St Louis",
    "sg:classifiers":[
        {
            "category":"Arts & Performance",
            "subcategory":"Art Gallery",
            "type":"Entertainment"
        }
    ],
    "sg:postcode":"63118",
    "sg:province":"MO",
    "sg:website":"www.loscaminosart.com",
    "wof:name":"Los Caminos",
    "wof:placetype":"venue"
},
  "geometry": {"coordinates":[-90.227522,38.593803],"type":"Point"}
}