{
  "type": "Feature",
  "properties": {
    "iso:country":"US",
    "sg:address":"9953 Lewis and Clark Blvd",
    "sg:city":"St Louis",
    "sg:classifiers":[
        {
            "category":"Health Services",
            "subcategory":"Clinic",
            "type":"Services"
        }
    ],
    "sg:phone":"+1 314 868 6400",
    "sg:postcode":"63136",
    "sg:province":"MO",
    "sg:tags":[
        "home"
    ],
    "wof:name":"Trinity Home Health Care Inc",
    "wof:placetype":"venue"
},
  "geometry": {"coordinates":[-90.239375,38.750628],"type":"Point"}
}