{
  "type": "Feature",
  "properties": {
    "iso:country":"US",
    "sg:address":"300 E 6th St",
    "sg:city":"Dixon",
    "sg:classifiers":[
        {
            "category":"Education",
            "subcategory":"School",
            "type":"Public Place"
        }
    ],
    "sg:phone":"+1 573 759 7428",
    "sg:postcode":"65459",
    "sg:province":"MO",
    "wof:name":"Dixon Alternative School",
    "wof:placetype":"venue"
},
  "geometry": {"coordinates":[-92.090571,37.997006],"type":"Point"}
}