{
  "type": "Feature",
  "properties": {
    "iso:country":"US",
    "sg:address":"564 State Hwy 6",
    "sg:city":"Trenton",
    "sg:classifiers":[
        {
            "category":"Building & Trades",
            "subcategory":"Construction",
            "type":"Services"
        }
    ],
    "sg:phone":"+1 660 359 6428",
    "sg:postcode":"64683",
    "sg:province":"MO",
    "sg:tags":[
        "excavation",
        "contractor"
    ],
    "wof:name":"Bill Stevens Backhoe Service",
    "wof:placetype":"venue"
},
  "geometry": {"coordinates":[-93.61324999999999,40.073695],"type":"Point"}
}