{
  "type": "Feature",
  "properties": {
    "iso:country":"US",
    "sg:address":"13305 Slabtown Rd",
    "sg:city":"Plato",
    "sg:classifiers":[
        {
            "category":"Freight",
            "type":"Transportation"
        }
    ],
    "sg:phone":"+1 417 458 3447",
    "sg:postcode":"65552",
    "sg:province":"MO",
    "sg:tags":[
        "operator",
        "trucking"
    ],
    "wof:name":"D&T Transport",
    "wof:placetype":"venue"
},
  "geometry": {"coordinates":[-92.09575599999999,37.554965],"type":"Point"}
}