{
  "type": "Feature",
  "properties": {
    "iso:country":"US",
    "sg:address":"1419 Sylvan Ln",
    "sg:city":"Cape Girardeau",
    "sg:classifiers":[
        {
            "category":"Real Estate",
            "subcategory":"Real Estate Operator",
            "type":"Services"
        }
    ],
    "sg:phone":"+1 573 334 5132",
    "sg:postcode":"63701",
    "sg:province":"MO",
    "sg:tags":[
        "building",
        "apartment"
    ],
    "wof:name":"Han M Kang",
    "wof:placetype":"venue"
},
  "geometry": {"coordinates":[-89.519423,37.325806],"type":"Point"}
}