{
  "type": "Feature",
  "properties": {
    "iso:country":"US",
    "sg:address":"895 E Walnut St",
    "sg:city":"Raymore",
    "sg:classifiers":[
        {
            "category":"Professional",
            "subcategory":"Lawyer & Legal Services",
            "type":"Services"
        }
    ],
    "sg:phone":"+1 816 322 7877",
    "sg:postcode":"64083",
    "sg:province":"MO",
    "sg:tags":[
        "attorney",
        "practice"
    ],
    "wof:name":"Law Offices Of Russell Little LLC The",
    "wof:placetype":"venue"
},
  "geometry": {"coordinates":[-94.456352,38.804119],"type":"Point"}
}