{
  "type": "Feature",
  "properties": {
    "iso:country":"US",
    "sg:address":"211 NW Executive Way",
    "sg:city":"Lees Summit",
    "sg:classifiers":[
        {
            "category":"Insurance",
            "subcategory":"Insurance Agent",
            "type":"Services"
        }
    ],
    "sg:phone":"+1 816 525 2333",
    "sg:postcode":"64063",
    "sg:province":"MO",
    "sg:website":"www.modernwoodmen.org",
    "wof:name":"Modern Woodmen of America",
    "wof:placetype":"venue"
},
  "geometry": {"coordinates":[-94.398313,38.915741],"type":"Point"}
}