{
  "type": "Feature",
  "properties": {
    "iso:country":"US",
    "sg:address":"100 N Main St",
    "sg:city":"Brookfield",
    "sg:classifiers":[
        {
            "category":"Personal",
            "subcategory":"Beauty Salon",
            "type":"Services"
        }
    ],
    "sg:phone":"+1 660 258 7993",
    "sg:postcode":"64628",
    "sg:province":"MO",
    "sg:tags":[
        "hair",
        "stylist"
    ],
    "wof:name":"Hair Teazerz",
    "wof:placetype":"venue"
},
  "geometry": {"coordinates":[-93.07421100000001,39.785789],"type":"Point"}
}