{
  "type": "Feature",
  "properties": {
    "iso:country":"US",
    "sg:address":"2700 Hebert St",
    "sg:city":"St Louis",
    "sg:classifiers":[
        {
            "category":"Food & Beverages",
            "subcategory":"Liquor & Beverages",
            "type":"Retail Goods"
        }
    ],
    "sg:phone":"+1 314 652 9411",
    "sg:postcode":"63107",
    "sg:province":"MO",
    "sg:tags":[
        "alcoholic"
    ],
    "wof:name":"Wainwright Confectionary",
    "wof:placetype":"venue"
},
  "geometry": {"coordinates":[-90.21455400000001,38.657675],"type":"Point"}
}