{
  "type": "Feature",
  "properties": {
    "iso:country":"US",
    "sg:address":"3318 Conway Rd",
    "sg:city":"Farmington",
    "sg:classifiers":[
        {
            "category":"Wholesale",
            "subcategory":"Meat",
            "type":"Manufacturing & Wholesale Goods"
        }
    ],
    "sg:phone":"+1 573 431 0198",
    "sg:postcode":"63640",
    "sg:province":"MO",
    "sg:tags":[
        "deli"
    ],
    "wof:name":"Smokey Valley Meats Inc",
    "wof:placetype":"venue"
},
  "geometry": {"coordinates":[-90.490489,37.860918],"type":"Point"}
}