{
  "type": "Feature",
  "properties": {
    "iso:country":"US",
    "sg:address":"732 State Hwy 7",
    "sg:city":"Blue Springs",
    "sg:classifiers":[
        {
            "category":"Restaurant",
            "type":"Food & Drink"
        }
    ],
    "sg:phone":"+1 816 229 3292",
    "sg:postcode":"64014",
    "sg:province":"MO",
    "wof:name":"Thai Place",
    "wof:placetype":"venue"
},
  "geometry": {"coordinates":[-94.27244899999999,39.012824],"type":"Point"}
}