{
  "type": "Feature",
  "properties": {
    "iso:country":"US",
    "sg:address":"211 NW Executive Way",
    "sg:city":"Lees Summit",
    "sg:classifiers":[
        {
            "category":"Professional",
            "type":"Services"
        }
    ],
    "sg:phone":"+1 816 554 0221",
    "sg:postcode":"64063",
    "sg:province":"MO",
    "sg:tags":[
        "establishment"
    ],
    "wof:name":"Codman",
    "wof:placetype":"venue"
},
  "geometry": {"coordinates":[-94.398313,38.915741],"type":"Point"}
}