{
  "type": "Feature",
  "properties": {
    "iso:country":"US",
    "sg:address":"100 S Main St",
    "sg:city":"Fair Grove",
    "sg:classifiers":[
        {
            "category":"Wholesale",
            "subcategory":"Machinery & Supplies",
            "type":"Manufacturing & Wholesale Goods"
        }
    ],
    "sg:phone":"+1 417 759 2250",
    "sg:postcode":"65648",
    "sg:province":"MO",
    "sg:tags":[
        "mason",
        "contractor"
    ],
    "wof:name":"Fair Grove Brick & Block",
    "wof:placetype":"venue"
},
  "geometry": {"coordinates":[-93.15115,37.382746],"type":"Point"}
}