{
  "type": "Feature",
  "properties": {
    "iso:country":"US",
    "sg:address":"746 E Eastwood St",
    "sg:city":"Marshall",
    "sg:classifiers":[
        {
            "category":"Organizations",
            "subcategory":"Community Association",
            "type":"Services"
        }
    ],
    "sg:phone":"+1 660 886 5871",
    "sg:postcode":"65340",
    "sg:province":"MO",
    "wof:name":"Rotary District 6080",
    "wof:placetype":"venue"
},
  "geometry": {"coordinates":[-93.18275,39.122634],"type":"Point"}
}