{
  "type": "Feature",
  "properties": {
    "iso:country":"US",
    "sg:address":"2114 Cherokee St",
    "sg:city":"Saint Louis",
    "sg:classifiers":[
        {
            "category":"Education",
            "subcategory":"Music School",
            "type":"Public Place"
        }
    ],
    "sg:phone":"+1 314 664 1234",
    "sg:postcode":"63118",
    "sg:province":"MO",
    "sg:tags":[
        "instrument",
        "teacher",
        "musical"
    ],
    "sg:website":"www.saxquest.com",
    "wof:name":"Saxquest",
    "wof:placetype":"venue"
},
  "geometry": {"coordinates":[-90.222231,38.592762],"type":"Point"}
}