{
  "type": "Feature",
  "properties": {
    "iso:country":"US",
    "sg:address":"2000 S River Rd",
    "sg:city":"St Charles",
    "sg:classifiers":[
        {
            "category":"Home & Garden",
            "subcategory":"Building Materials",
            "type":"Retail Goods"
        }
    ],
    "sg:phone":"+1 636 947 0100",
    "sg:postcode":"63303",
    "sg:province":"MO",
    "sg:tags":[
        "mixed",
        "concrete"
    ],
    "wof:name":"Concrete Resources",
    "wof:placetype":"venue"
},
  "geometry": {"coordinates":[-90.501693,38.755129],"type":"Point"}
}