{
  "type": "Feature",
  "properties": {
    "addr:full":"1520 Market St Saint Louis MO 63103",
    "addr:housenumber":"1520",
    "addr:postcode":"63103",
    "addr:street":"Market St",
    "iso:country":"US",
    "sg:address":"1520 Market St",
    "sg:city":"Saint Louis",
    "sg:classifiers":[
        {
            "category":"Government",
            "subcategory":"Office",
            "type":"Public Place"
        }
    ],
    "sg:phone":"+1 314 539 2404",
    "sg:postcode":"63103",
    "sg:province":"MO",
    "sg:tags":[
        "grant",
        "housing",
        "delivery",
        "program",
        "rural",
        "loan"
    ],
    "wof:name":"Rural Development",
    "wof:placetype":"venue"
},
  "geometry": {"coordinates":[-90.203504,38.628567],"type":"Point"}
}