{
  "type": "Feature",
  "properties": {
    "iso:country":"US",
    "sg:address":"1491 Kienlen Ave",
    "sg:city":"Saint Louis",
    "sg:classifiers":[
        {
            "category":"Autos & Motor Vehicles",
            "subcategory":"Fuel & Gas Station",
            "type":"Retail Goods"
        }
    ],
    "sg:phone":"+1 314 261 3500",
    "sg:postcode":"63133",
    "sg:province":"MO",
    "wof:name":"H R M Inc",
    "wof:placetype":"venue"
},
  "geometry": {"coordinates":[-90.287201,38.676201],"type":"Point"}
}