{
  "type": "Feature",
  "properties": {
    "iso:country":"US",
    "sg:address":"924 Hwy C",
    "sg:city":"Saint Peters",
    "sg:classifiers":[
        {
            "category":"Building & Trades",
            "subcategory":"Construction",
            "type":"Services"
        }
    ],
    "sg:phone":"+1 636 397 5161",
    "sg:postcode":"63376",
    "sg:province":"MO",
    "sg:tags":[
        "house"
    ],
    "wof:name":"Cape Construction",
    "wof:placetype":"venue"
},
  "geometry": {"coordinates":[-90.620642,38.827684],"type":"Point"}
}