{
  "type": "Feature",
  "properties": {
    "iso:country":"US",
    "sg:address":"2330 E Royal Ct",
    "sg:city":"Saint Louis",
    "sg:classifiers":[
        {
            "category":"Wholesale",
            "subcategory":"Non-durable Goods",
            "type":"Manufacturing & Wholesale Goods"
        }
    ],
    "sg:phone":"+1 314 835 9441",
    "sg:postcode":"63131",
    "sg:province":"MO",
    "wof:name":"Bokay Enterprises Inc",
    "wof:placetype":"venue"
},
  "geometry": {"coordinates":[-90.463283,38.58915],"type":"Point"}
}