{
  "type": "Feature",
  "properties": {
    "iso:country":"US",
    "sg:address":"3839 Mexico Rd",
    "sg:city":"Saint Charles",
    "sg:classifiers":[
        {
            "category":"Education",
            "subcategory":"Dance Studio",
            "type":"Public Place"
        }
    ],
    "sg:phone":"+1 636 939 0499",
    "sg:postcode":"63303",
    "sg:province":"MO",
    "wof:name":"Studio J Ltd Inc",
    "wof:placetype":"venue"
},
  "geometry": {"coordinates":[-90.56384300000001,38.791071],"type":"Point"}
}