{
  "type": "Feature",
  "properties": {
    "iso:country":"US",
    "sg:address":"5420 Liv 520",
    "sg:city":"Chillicothe",
    "sg:classifiers":[
        {
            "category":"Farming",
            "subcategory":"Farm",
            "type":"Manufacturing & Wholesale Goods"
        }
    ],
    "sg:phone":"+1 660 646 6983",
    "sg:postcode":"64601",
    "sg:province":"MO",
    "sg:tags":[
        "crop",
        "general"
    ],
    "wof:name":"Darrell Cooper",
    "wof:placetype":"venue"
},
  "geometry": {"coordinates":[-93.67460699999999,39.860001],"type":"Point"}
}