{
  "type": "Feature",
  "properties": {
    "iso:country":"US",
    "sg:address":"1709 S Campbell Ave",
    "sg:city":"Springfield",
    "sg:classifiers":[
        {
            "category":"Personal",
            "type":"Services"
        }
    ],
    "sg:phone":"+1 417 869 6338",
    "sg:postcode":"65807",
    "sg:province":"MO",
    "sg:tags":[
        "singles",
        "organization"
    ],
    "wof:name":"Singles Co",
    "wof:placetype":"venue"
},
  "geometry": {"coordinates":[-93.29499,37.184645],"type":"Point"}
}