{
  "type": "Feature",
  "properties": {
    "iso:country":"US",
    "sg:address":"246 Whiting Ln",
    "sg:city":"Chesterfield",
    "sg:classifiers":[
        {
            "category":"Health Services",
            "subcategory":"Dentist",
            "type":"Services"
        }
    ],
    "sg:phone":"+1 636 391 1912",
    "sg:postcode":"63005",
    "sg:province":"MO",
    "wof:name":"Ronald W Antoine",
    "wof:placetype":"venue"
},
  "geometry": {"coordinates":[-90.589998,38.610695],"type":"Point"}
}