{
  "type": "Feature",
  "properties": {
    "iso:country":"US",
    "sg:address":"3539 W Farm Rd 142",
    "sg:city":"Springfield",
    "sg:classifiers":[
        {
            "category":"Shopping",
            "subcategory":"Gifts & Souvenirs",
            "type":"Retail Goods"
        }
    ],
    "sg:phone":"+1 417 862 2737",
    "sg:postcode":"65807",
    "sg:province":"MO",
    "wof:name":"Anheuser-Busch",
    "wof:placetype":"venue"
},
  "geometry": {"coordinates":[-93.351054,37.194092],"type":"Point"}
}