{
  "type": "Feature",
  "properties": {
    "iso:country":"US",
    "sg:address":"14808 Clayton Rd",
    "sg:city":"Chesterfield",
    "sg:classifiers":[
        {
            "category":"Shopping",
            "subcategory":"Catalog Store",
            "type":"Retail Goods"
        }
    ],
    "sg:phone":"+1 636 386 4660",
    "sg:postcode":"63017",
    "sg:province":"MO",
    "sg:tags":[
        "house",
        "mail"
    ],
    "wof:name":"Home Decorators Catalog Outlet",
    "wof:placetype":"venue"
},
  "geometry": {"coordinates":[-90.539728,38.615358],"type":"Point"}
}