{
  "type": "Feature",
  "properties": {
    "iso:country":"US",
    "sg:address":"1305 W 49 St",
    "sg:city":"Kansas City",
    "sg:classifiers":[
        {
            "category":"Professional",
            "subcategory":"Business Services",
            "type":"Services"
        }
    ],
    "sg:phone":"+1 816 561 1876",
    "sg:postcode":"64112",
    "sg:province":"MO",
    "sg:tags":[
        "interior",
        "consultant",
        "design",
        "decorator"
    ],
    "wof:name":"Home Image",
    "wof:placetype":"venue"
},
  "geometry": {"coordinates":[-94.602149,39.039463],"type":"Point"}
}