{
  "type": "Feature",
  "properties": {
    "iso:country":"US",
    "sg:address":"1811 E Jackson Blvd Ste C",
    "sg:city":"Jackson",
    "sg:classifiers":[
        {
            "category":"Restaurant",
            "type":"Food & Drink"
        },
        {
            "category":"Bakery",
            "type":"Food & Drink"
        }
    ],
    "sg:phone":"+1 573 243 1952",
    "sg:postcode":"63755",
    "sg:province":"MO",
    "wof:name":"Meyers Bakery",
    "wof:placetype":"venue"
},
  "geometry": {"coordinates":[-89.649508,37.372035],"type":"Point"}
}