{
  "type": "Feature",
  "properties": {
    "iso:country":"US",
    "sg:address":"272 Siemers Dr",
    "sg:city":"Cape Girardeau",
    "sg:classifiers":[
        {
            "category":"Real Estate",
            "subcategory":"Real Estate Operator",
            "type":"Services"
        }
    ],
    "sg:phone":"+1 573 335 4200",
    "sg:postcode":"63701",
    "sg:province":"MO",
    "wof:name":"Drury Land Development Inc",
    "wof:placetype":"venue"
},
  "geometry": {"coordinates":[-89.579026,37.295213],"type":"Point"}
}