{
  "type": "Feature",
  "properties": {
    "iso:country":"US",
    "sg:address":"8732 Blue Ridge Blvd",
    "sg:city":"Raytown",
    "sg:classifiers":[
        {
            "category":"Personal",
            "subcategory":"Beauty Salon",
            "type":"Services"
        }
    ],
    "sg:phone":"+1 816 965 6770",
    "sg:postcode":"64138",
    "sg:province":"MO",
    "sg:tags":[
        "manicuring"
    ],
    "wof:name":"Nail Pro",
    "wof:placetype":"venue"
},
  "geometry": {"coordinates":[-94.499443,38.964687],"type":"Point"}
}