{
  "type": "Feature",
  "properties": {
    "iso:country":"US",
    "sg:address":"8378 Sumac Rd",
    "sg:city":"Jasper",
    "sg:classifiers":[
        {
            "category":"Personal",
            "subcategory":"Beauty Salon",
            "type":"Services"
        }
    ],
    "sg:phone":"+1 417 394 2886",
    "sg:postcode":"64755",
    "sg:province":"MO",
    "wof:name":"Karen's Kutting Korner",
    "wof:placetype":"venue"
},
  "geometry": {"coordinates":[-94.20392699999999,37.32274],"type":"Point"}
}