{
  "type": "Feature",
  "properties": {
    "iso:country":"US",
    "sg:address":"32 Fox Meadows Ln",
    "sg:city":"St Louis",
    "sg:classifiers":[
        {
            "category":"Professional",
            "type":"Services"
        }
    ],
    "sg:phone":"+1 314 842 1852",
    "sg:postcode":"63127",
    "sg:province":"MO",
    "sg:tags":[
        "establishment"
    ],
    "wof:name":"Rundquist F Wm",
    "wof:placetype":"venue"
},
  "geometry": {"coordinates":[-90.39228799999999,38.539203],"type":"Point"}
}