{
  "type": "Feature",
  "properties": {
    "iso:country":"US",
    "sg:address":"41 Park Charles Blvd N",
    "sg:city":"Saint Peters",
    "sg:classifiers":[
        {
            "category":"Manufacturing",
            "subcategory":"Food",
            "type":"Manufacturing & Wholesale Goods"
        }
    ],
    "sg:phone":"+1 636 441 0992",
    "sg:postcode":"63376",
    "sg:province":"MO",
    "sg:tags":[
        "frozen",
        "equipment",
        "commercial",
        "specialty",
        "mfg"
    ],
    "wof:name":"St Louis Julep",
    "wof:placetype":"venue"
},
  "geometry": {"coordinates":[-90.62102,38.7575],"type":"Point"}
}