{
  "type": "Feature",
  "properties": {
    "iso:country":"US",
    "sg:address":"8819 Stage Coach Rd",
    "sg:city":"Jefferson City",
    "sg:classifiers":[
        {
            "category":"Building & Trades",
            "subcategory":"Construction",
            "type":"Services"
        }
    ],
    "sg:phone":"+1 573 395 9993",
    "sg:postcode":"65101",
    "sg:province":"MO",
    "sg:tags":[
        "house"
    ],
    "wof:name":"Central Missouri Remodeling",
    "wof:placetype":"venue"
},
  "geometry": {"coordinates":[-92.043138,38.517802],"type":"Point"}
}