{
  "type": "Feature",
  "properties": {
    "iso:country":"US",
    "sg:address":"4604 NE 49 St",
    "sg:city":"Kansas City",
    "sg:classifiers":[
        {
            "category":"Professional",
            "type":"Services"
        }
    ],
    "sg:phone":"+1 816 454 1112",
    "sg:postcode":"64119",
    "sg:province":"MO",
    "wof:name":"Emerson Publications",
    "wof:placetype":"venue"
},
  "geometry": {"coordinates":[-94.52539400000001,39.183856],"type":"Point"}
}