{
  "type": "Feature",
  "properties": {
    "iso:country":"US",
    "sg:address":"8060 Rye Creek Rd",
    "sg:city":"Lonedell",
    "sg:classifiers":[
        {
            "category":"Building & Trades",
            "subcategory":"Landscaping Services",
            "type":"Services"
        }
    ],
    "sg:phone":"+1 636 629 2861",
    "sg:postcode":"63060",
    "sg:province":"MO",
    "wof:name":"Pewitt Lawn Service",
    "wof:placetype":"venue"
},
  "geometry": {"coordinates":[-90.880709,38.305724],"type":"Point"}
}