{
  "type": "Feature",
  "properties": {
    "iso:country":"US",
    "sg:address":"932 Ida St",
    "sg:city":"Poplar Bluff",
    "sg:classifiers":[
        {
            "category":"Health Services",
            "subcategory":"Doctor",
            "type":"Services"
        }
    ],
    "sg:phone":"+1 573 785 5100",
    "sg:postcode":"63901",
    "sg:province":"MO",
    "wof:name":"Michael B Price DDS",
    "wof:placetype":"venue"
},
  "geometry": {"coordinates":[-90.41094200000001,36.765831],"type":"Point"}
}