{
  "type": "Feature",
  "properties": {
    "iso:country":"US",
    "sg:address":"200 E 2nd St",
    "sg:city":"Kennett",
    "sg:classifiers":[
        {
            "category":"Government",
            "subcategory":"Police Station",
            "type":"Public Place"
        }
    ],
    "sg:phone":"+1 573 888 4622",
    "sg:postcode":"63857",
    "sg:province":"MO",
    "sg:tags":[
        "department"
    ],
    "wof:name":"Kennett Police Dept",
    "wof:placetype":"venue"
},
  "geometry": {"coordinates":[-90.054519,36.23567],"type":"Point"}
}