{
  "type": "Feature",
  "properties": {
    "iso:country":"US",
    "sg:address":"2108 NW 12 St",
    "sg:city":"Blue Springs",
    "sg:classifiers":[
        {
            "category":"Social Services",
            "subcategory":"Child Care",
            "type":"Services"
        }
    ],
    "sg:phone":"+1 816 229 7236",
    "sg:postcode":"64015",
    "sg:province":"MO",
    "sg:tags":[
        "day"
    ],
    "wof:name":"Demint Jewel Marie",
    "wof:placetype":"venue"
},
  "geometry": {"coordinates":[-94.276652,39.042453],"type":"Point"}
}