{
  "type": "Feature",
  "properties": {
    "iso:country":"US",
    "sg:address":"517 E Kirkwood Dr",
    "sg:city":"Aurora",
    "sg:classifiers":[
        {
            "category":"Organizations",
            "subcategory":"Religious Organization",
            "type":"Services"
        }
    ],
    "sg:phone":"+1 417 678 3883",
    "sg:postcode":"65605",
    "sg:province":"MO",
    "wof:name":"James R Lee Rev",
    "wof:placetype":"venue"
},
  "geometry": {"coordinates":[-93.71471200000001,36.959655],"type":"Point"}
}