{
  "type": "Feature",
  "properties": {
    "iso:country":"US",
    "sg:address":"15312 E Truman Rd",
    "sg:city":"Independence",
    "sg:classifiers":[
        {
            "category":"Building & Trades",
            "subcategory":"Construction",
            "type":"Services"
        }
    ],
    "sg:phone":"+1 816 833 4460",
    "sg:postcode":"64050",
    "sg:province":"MO",
    "sg:tags":[
        "downspouts",
        "gutter"
    ],
    "wof:name":"All Copper Inc",
    "wof:placetype":"venue"
},
  "geometry": {"coordinates":[-94.39446,39.093445],"type":"Point"}
}