{
  "type": "Feature",
  "properties": {
    "iso:country":"US",
    "sg:address":"11 Mabel Ln",
    "sg:city":"St Albans",
    "sg:classifiers":[
        {
            "category":"Building & Trades",
            "subcategory":"Construction",
            "type":"Services"
        }
    ],
    "sg:phone":"+1 636 458 4884",
    "sg:postcode":"63069",
    "sg:province":"MO",
    "sg:tags":[
        "general",
        "contractor"
    ],
    "wof:name":"St Albans Construction Co",
    "wof:placetype":"venue"
},
  "geometry": {"coordinates":[-90.769896,38.579944],"type":"Point"}
}