{
  "type": "Feature",
  "properties": {
    "iso:country":"US",
    "sg:address":"1108 W Edwards St",
    "sg:city":"Maryville",
    "sg:classifiers":[
        {
            "category":"Building & Trades",
            "subcategory":"Landscaping Services",
            "type":"Services"
        }
    ],
    "sg:phone":"+1 660 562 3621",
    "sg:postcode":"64468",
    "sg:province":"MO",
    "wof:name":"Complete Outdoor Services",
    "wof:placetype":"venue"
},
  "geometry": {"coordinates":[-94.88709299999999,40.341474],"type":"Point"}
}