{
  "type": "Feature",
  "properties": {
    "iso:country":"US",
    "sg:address":"13108 State Hwy C",
    "sg:city":"Russellville",
    "sg:classifiers":[
        {
            "category":"Food & Beverages",
            "subcategory":"Groceries & Convenience Stores",
            "type":"Retail Goods"
        }
    ],
    "sg:phone":"+1 573 782 4708",
    "sg:postcode":"65074",
    "sg:province":"MO",
    "wof:name":"Mertens Mini Mart",
    "wof:placetype":"venue"
},
  "geometry": {"coordinates":[-92.440145,38.509215],"type":"Point"}
}