{
  "type": "Feature",
  "properties": {
    "iso:country":"US",
    "sg:address":"13887 Co Rd 717",
    "sg:city":"Dexter",
    "sg:classifiers":[
        {
            "category":"Building & Trades",
            "subcategory":"Construction",
            "type":"Services"
        }
    ],
    "sg:phone":"+1 573 624 8519",
    "sg:postcode":"63841",
    "sg:province":"MO",
    "sg:tags":[
        "paving",
        "contractor"
    ],
    "wof:name":"Delta Asphalt Inc",
    "wof:placetype":"venue"
},
  "geometry": {"coordinates":[-89.93207099999999,36.816738],"type":"Point"}
}