{
  "type": "Feature",
  "properties": {
    "iso:country":"US",
    "sg:address":"1706 E Elm St",
    "sg:city":"Jefferson City",
    "sg:classifiers":[
        {
            "category":"Organizations",
            "subcategory":"Non-profit Organization",
            "type":"Services"
        }
    ],
    "sg:phone":"+1 573 751 8611",
    "sg:postcode":"65101",
    "sg:province":"MO",
    "sg:tags":[
        "human"
    ],
    "wof:name":"Missouri Planning Council",
    "wof:placetype":"venue"
},
  "geometry": {"coordinates":[-92.15172,38.552994],"type":"Point"}
}