{
  "type": "Feature",
  "properties": {
    "iso:country":"US",
    "sg:address":"105 W 259th St",
    "sg:city":"Cleveland",
    "sg:classifiers":[
        {
            "category":"Building & Trades",
            "subcategory":"Landscaping Services",
            "type":"Services"
        }
    ],
    "sg:phone":"+1 816 618 3200",
    "sg:postcode":"64734",
    "sg:province":"MO",
    "wof:name":"J & J Mowing",
    "wof:placetype":"venue"
},
  "geometry": {"coordinates":[-94.608845,38.652444],"type":"Point"}
}