{
  "type": "Feature",
  "properties": {
    "iso:country":"US",
    "sg:address":"5830 Natural Bridge Ave",
    "sg:city":"Saint Louis",
    "sg:classifiers":[
        {
            "category":"Professional",
            "subcategory":"Computer Services",
            "type":"Services"
        }
    ],
    "sg:phone":"+1 314 383 0600",
    "sg:postcode":"63120",
    "sg:province":"MO",
    "sg:tags":[
        "stereo",
        "installation"
    ],
    "wof:name":"Max AAA Automobile Service & Installation",
    "wof:placetype":"venue"
},
  "geometry": {"coordinates":[-90.272102,38.686699],"type":"Point"}
}