{
  "type": "Feature",
  "properties": {
    "iso:country":"US",
    "sg:address":"7303 Olive Blvd",
    "sg:city":"Saint Louis",
    "sg:classifiers":[
        {
            "category":"Restaurant",
            "type":"Food & Drink"
        }
    ],
    "sg:phone":"+1 314 721 5686",
    "sg:postcode":"63130",
    "sg:province":"MO",
    "wof:name":"La'chong Wah Restaurant",
    "wof:placetype":"venue"
},
  "geometry": {"coordinates":[-90.32620199999999,38.671101],"type":"Point"}
}