{
  "type": "Feature",
  "properties": {
    "iso:country":"US",
    "sg:address":"107 Main St",
    "sg:city":"St Peters",
    "sg:classifiers":[
        {
            "category":"Organizations",
            "subcategory":"Religious Organization",
            "type":"Services"
        },
        {
            "category":"Social Services",
            "type":"Services"
        }
    ],
    "sg:phone":"+1 636 278 1807",
    "sg:postcode":"63376",
    "sg:province":"MO",
    "sg:tags":[
        "church"
    ],
    "wof:name":"Saint Peters Jaycees",
    "wof:placetype":"venue"
},
  "geometry": {"coordinates":[-90.62561599999999,38.801856],"type":"Point"}
}