{
  "type": "Feature",
  "properties": {
    "iso:country":"US",
    "sg:address":"10759 State Hwy 32",
    "sg:city":"Plato",
    "sg:classifiers":[
        {
            "category":"Retail",
            "subcategory":"Auto Rental",
            "type":"Services"
        }
    ],
    "sg:phone":"+1 417 458 3789",
    "sg:postcode":"65552",
    "sg:province":"MO",
    "sg:tags":[
        "renting",
        "truck",
        "leasing"
    ],
    "wof:name":"U-Haul Co",
    "wof:placetype":"venue"
},
  "geometry": {"coordinates":[-92.214771,37.503539],"type":"Point"}
}