{
  "type": "Feature",
  "properties": {
    "iso:country":"US",
    "sg:address":"1921 S Glenstone Ave",
    "sg:city":"Springfield",
    "sg:classifiers":[
        {
            "category":"Personal",
            "subcategory":"Tanning Parlor",
            "type":"Services"
        }
    ],
    "sg:phone":"+1 417 823 0223",
    "sg:postcode":"65804",
    "sg:province":"MO",
    "sg:tags":[
        "salon"
    ],
    "wof:name":"Sun Source",
    "wof:placetype":"venue"
},
  "geometry": {"coordinates":[-93.262468,37.17935],"type":"Point"}
}