{
  "type": "Feature",
  "properties": {
    "iso:country":"US",
    "sg:address":"5314 NW Bluff Way",
    "sg:city":"Kansas City",
    "sg:classifiers":[
        {
            "category":"Professional",
            "subcategory":"Business Services",
            "type":"Services"
        }
    ],
    "sg:phone":"+1 816 741 2526",
    "sg:postcode":"64152",
    "sg:province":"MO",
    "sg:tags":[
        "packaging",
        "provides"
    ],
    "wof:name":"River City Products Inc",
    "wof:placetype":"venue"
},
  "geometry": {"coordinates":[-94.69540499999999,39.194584],"type":"Point"}
}