{
  "type": "Feature",
  "properties": {
    "iso:country":"US",
    "sg:address":"2414 State Hwy B",
    "sg:city":"Oak Ridge",
    "sg:classifiers":[
        {
            "category":"Personal",
            "subcategory":"Beauty Salon",
            "type":"Services"
        }
    ],
    "sg:phone":"+1 573 243 7963",
    "sg:postcode":"63769",
    "sg:province":"MO",
    "sg:tags":[
        "shop"
    ],
    "wof:name":"Sue Family Hair Care",
    "wof:placetype":"venue"
},
  "geometry": {"coordinates":[-89.778519,37.459276],"type":"Point"}
}