{
  "type": "Feature",
  "properties": {
    "iso:country":"US",
    "sg:address":"15289 Manchester Rd",
    "sg:city":"Ballwin",
    "sg:classifiers":[
        {
            "category":"Shopping",
            "subcategory":"Clothing, Apparel, & Fashions",
            "type":"Retail Goods"
        }
    ],
    "sg:phone":"+1 636 207 7396",
    "sg:postcode":"63011",
    "sg:province":"MO",
    "sg:tags":[
        "maternity"
    ],
    "wof:name":"Maternity Outlet",
    "wof:placetype":"venue"
},
  "geometry": {"coordinates":[-90.556673,38.592933],"type":"Point"}
}