{
  "type": "Feature",
  "properties": {
    "iso:country":"US",
    "sg:address":"809 Booth Rd",
    "sg:city":"Clinton",
    "sg:classifiers":[
        {
            "category":"Real Estate",
            "subcategory":"Real Estate Agent",
            "type":"Services"
        }
    ],
    "sg:phone":"+1 660 885 6684",
    "sg:postcode":"64735",
    "sg:province":"MO",
    "wof:name":"Golden Valley Real Estate",
    "wof:placetype":"venue"
},
  "geometry": {"coordinates":[-93.79290899999999,38.381754],"type":"Point"}
}