{
  "type": "Feature",
  "properties": {
    "iso:country":"US",
    "sg:address":"940 Oak Knoll Manor Dr",
    "sg:city":"Saint Louis",
    "sg:classifiers":[
        {
            "category":"Organizations",
            "subcategory":"Labor Organization",
            "type":"Services"
        }
    ],
    "sg:phone":"+1 314 968 5534",
    "sg:postcode":"63119",
    "sg:province":"MO",
    "wof:name":"New Directions Movement Inc",
    "wof:placetype":"venue"
},
  "geometry": {"coordinates":[-90.336102,38.572486],"type":"Point"}
}