{
  "type": "Feature",
  "properties": {
    "iso:country":"US",
    "sg:address":"4126 Lenox Ave",
    "sg:city":"Saint Louis",
    "sg:classifiers":[
        {
            "category":"Building & Trades",
            "subcategory":"Electrical",
            "type":"Services"
        }
    ],
    "sg:phone":"+1 314 647 5671",
    "sg:postcode":"63119",
    "sg:province":"MO",
    "sg:tags":[
        "electrical",
        "contractor"
    ],
    "wof:name":"Martin Keith",
    "wof:placetype":"venue"
},
  "geometry": {"coordinates":[-90.32861699999999,38.596306],"type":"Point"}
}