{
  "type": "Feature",
  "properties": {
    "iso:country":"US",
    "sg:address":"754 County Highway 459",
    "sg:city":"Sikeston",
    "sg:classifiers":[
        {
            "category":"Manufacturing",
            "subcategory":"Food",
            "type":"Manufacturing & Wholesale Goods"
        },
        {
            "category":"Farming",
            "subcategory":"Farm",
            "type":"Manufacturing & Wholesale Goods"
        }
    ],
    "sg:phone":"+1 573 471 4697",
    "sg:postcode":"63801",
    "sg:province":"MO",
    "sg:tags":[
        "corn",
        "product"
    ],
    "wof:name":"Chuck Pobst",
    "wof:placetype":"venue"
},
  "geometry": {"coordinates":[-89.676743,36.976251],"type":"Point"}
}