{
  "type": "Feature",
  "properties": {
    "iso:country":"US",
    "sg:address":"6418 Rte Y",
    "sg:city":"Jefferson City",
    "sg:classifiers":[
        {
            "category":"Retail",
            "subcategory":"Auto Repair",
            "type":"Services"
        }
    ],
    "sg:phone":"+1 573 395 4049",
    "sg:postcode":"65101",
    "sg:province":"MO",
    "sg:tags":[
        "repairing",
        "automobile",
        "general"
    ],
    "wof:name":"Curt's Automotive & Cycle Rpr",
    "wof:placetype":"venue"
},
  "geometry": {"coordinates":[-92.087238,38.492514],"type":"Point"}
}