{
  "type": "Feature",
  "properties": {
    "iso:country":"US",
    "sg:address":"101 N 17th St",
    "sg:city":"Sarcoxie",
    "sg:classifiers":[
        {
            "category":"Social Services",
            "subcategory":"Child Care",
            "type":"Services"
        }
    ],
    "sg:phone":"+1 417 548 6163",
    "sg:postcode":"64862",
    "sg:province":"MO",
    "wof:name":"Sonshine Center",
    "wof:placetype":"venue"
},
  "geometry": {"coordinates":[-94.13076,37.070492],"type":"Point"}
}