{
  "type": "Feature",
  "properties": {
    "iso:country":"US",
    "sg:address":"338 Brookes Dr",
    "sg:city":"Hazelwood",
    "sg:classifiers":[
        {
            "category":"Freight",
            "type":"Transportation"
        }
    ],
    "sg:phone":"+1 314 731 6666",
    "sg:postcode":"63042",
    "sg:province":"MO",
    "sg:tags":[
        "mover"
    ],
    "wof:name":"Apartment Movers",
    "wof:placetype":"venue"
},
  "geometry": {"coordinates":[-90.362195,38.777573],"type":"Point"}
}