{
  "type": "Feature",
  "properties": {
    "iso:country":"US",
    "sg:address":"664 Bayberry Ln",
    "sg:city":"Lees Summit",
    "sg:classifiers":[
        {
            "category":"Professional",
            "subcategory":"Management & Consulting",
            "type":"Services"
        }
    ],
    "sg:phone":"+1 816 246 1555",
    "sg:postcode":"64063",
    "sg:province":"MO",
    "sg:tags":[
        "small",
        "consultant",
        "business"
    ],
    "wof:name":"Mid America Taac",
    "wof:placetype":"venue"
},
  "geometry": {"coordinates":[-94.359533,38.907394],"type":"Point"}
}