{
  "type": "Feature",
  "properties": {
    "iso:country":"US",
    "sg:address":"333 First Capitol Dr",
    "sg:city":"Saint Charles",
    "sg:classifiers":[
        {
            "category":"Shopping",
            "subcategory":"Florist",
            "type":"Retail Goods"
        }
    ],
    "sg:phone":"+1 636 724 0148",
    "sg:postcode":"63301",
    "sg:province":"MO",
    "wof:name":"Kruses Flower Shop",
    "wof:placetype":"venue"
},
  "geometry": {"coordinates":[-90.485367,38.780552],"type":"Point"}
}