{
  "type": "Feature",
  "properties": {
    "iso:country":"US",
    "sg:address":"417 Beaton St",
    "sg:city":"Kennett",
    "sg:classifiers":[
        {
            "category":"Professional",
            "subcategory":"Business Services",
            "type":"Services"
        }
    ],
    "sg:phone":"+1 573 717 1653",
    "sg:postcode":"63857",
    "sg:province":"MO",
    "sg:tags":[
        "interior",
        "consultant",
        "design",
        "decorator"
    ],
    "wof:name":"Home Interiors",
    "wof:placetype":"venue"
},
  "geometry": {"coordinates":[-90.060363,36.234612],"type":"Point"}
}