{
  "type": "Feature",
  "properties": {
    "iso:country":"US",
    "sg:address":"336 Leffingwell Ave",
    "sg:city":"St Louis",
    "sg:classifiers":[
        {
            "category":"Professional",
            "subcategory":"Advertising",
            "type":"Services"
        }
    ],
    "sg:phone":"+1 314 909 1011",
    "sg:postcode":"63122",
    "sg:province":"MO",
    "sg:tags":[
        "distribution"
    ],
    "wof:name":"Jomico LLC",
    "wof:placetype":"venue"
},
  "geometry": {"coordinates":[-90.39877199999999,38.577352],"type":"Point"}
}