{
  "type": "Feature",
  "properties": {
    "iso:country":"US",
    "sg:address":"9341 Althea Ave",
    "sg:city":"St Louis",
    "sg:classifiers":[
        {
            "category":"Freight",
            "type":"Transportation"
        }
    ],
    "sg:phone":"+1 314 631 0125",
    "sg:postcode":"63123",
    "sg:province":"MO",
    "sg:tags":[
        "trucking"
    ],
    "wof:name":"EJA Trucking Inc",
    "wof:placetype":"venue"
},
  "geometry": {"coordinates":[-90.320795,38.549424],"type":"Point"}
}