{
  "type": "Feature",
  "properties": {
    "iso:country":"US",
    "sg:address":"17 E 69 St",
    "sg:city":"Kansas City",
    "sg:classifiers":[
        {
            "category":"Autos & Motor Vehicles",
            "subcategory":"Fuel & Gas Station",
            "type":"Retail Goods"
        }
    ],
    "sg:phone":"+1 816 452 8050",
    "sg:postcode":"64113",
    "sg:province":"MO",
    "sg:tags":[
        "grocery",
        "station",
        "gasoline"
    ],
    "wof:name":"King Super Store",
    "wof:placetype":"venue"
},
  "geometry": {"coordinates":[-94.586635,39.003095],"type":"Point"}
}