{
  "type": "Feature",
  "properties": {
    "iso:country":"US",
    "sg:address":"707 Clara Pl",
    "sg:city":"Montgomery City",
    "sg:classifiers":[
        {
            "category":"Organizations",
            "subcategory":"Community Association",
            "type":"Services"
        }
    ],
    "sg:phone":"+1 573 564 3624",
    "sg:postcode":"63361",
    "sg:province":"MO",
    "wof:name":"Interntnal Assn of Lions Clubs",
    "wof:placetype":"venue"
},
  "geometry": {"coordinates":[-91.515914,38.979149],"type":"Point"}
}