{
  "type": "Feature",
  "properties": {
    "iso:country":"US",
    "sg:address":"404 Prairie St",
    "sg:city":"Hornersville",
    "sg:classifiers":[
        {
            "category":"Place Of Worship",
            "subcategory":"Church",
            "type":"Public Place"
        },
        {
            "category":"Place Of Worship",
            "type":"Public Place"
        }
    ],
    "sg:phone":"+1 573 737 2611",
    "sg:postcode":"63855",
    "sg:province":"MO",
    "sg:tags":[
        "churches-baptist-general",
        "churches-baptist"
    ],
    "wof:name":"Hornersville Baptist Church",
    "wof:placetype":"venue"
},
  "geometry": {"coordinates":[-90.112465,36.038891],"type":"Point"}
}