{
  "type": "Feature",
  "properties": {
    "iso:country":"US",
    "sg:address":"29993 Beaman Rd",
    "sg:city":"Smithton",
    "sg:classifiers":[
        {
            "category":"Freight",
            "type":"Transportation"
        }
    ],
    "sg:phone":"+1 660 827 0477",
    "sg:postcode":"65350",
    "sg:province":"MO",
    "sg:tags":[
        "operator",
        "local",
        "trucking"
    ],
    "wof:name":"Dale Rhoads Trucking",
    "wof:placetype":"venue"
},
  "geometry": {"coordinates":[-93.134101,38.752634],"type":"Point"}
}