{
  "type": "Feature",
  "properties": {
    "iso:country":"US",
    "sg:address":"32583 Lamplighter Pl",
    "sg:city":"Atlanta",
    "sg:classifiers":[
        {
            "category":"Retail",
            "subcategory":"Repair Shop",
            "type":"Services"
        }
    ],
    "sg:phone":"+1 660 239 4233",
    "sg:postcode":"63530",
    "sg:province":"MO",
    "sg:tags":[
        "farm",
        "equipment",
        "parts"
    ],
    "wof:name":"Harrington's Garage",
    "wof:placetype":"venue"
},
  "geometry": {"coordinates":[-92.428352,39.889172],"type":"Point"}
}