{
  "type": "Feature",
  "properties": {
    "iso:country":"US",
    "sg:address":"4440 W Florissant Ave",
    "sg:city":"St Louis",
    "sg:classifiers":[
        {
            "category":"Utilities",
            "subcategory":"Telephone",
            "type":"Services"
        }
    ],
    "sg:phone":"+1 314 385 8770",
    "sg:postcode":"63115",
    "sg:province":"MO",
    "sg:tags":[
        "telecommunication"
    ],
    "wof:name":"A K Systems Inc",
    "wof:placetype":"venue"
},
  "geometry": {"coordinates":[-90.225792,38.682017],"type":"Point"}
}