{
  "type": "Feature",
  "properties": {
    "iso:country":"US",
    "sg:address":"32613 Van Dyke Rd",
    "sg:city":"Smithton",
    "sg:classifiers":[
        {
            "category":"Social Services",
            "subcategory":"Adult Care",
            "type":"Services"
        }
    ],
    "sg:phone":"+1 660 827 3032",
    "sg:postcode":"65350",
    "sg:province":"MO",
    "sg:tags":[
        "residential"
    ],
    "wof:name":"Park View Group Care Home",
    "wof:placetype":"venue"
},
  "geometry": {"coordinates":[-93.152574,38.599014],"type":"Point"}
}