{
  "type": "Feature",
  "properties": {
    "iso:country":"US",
    "sg:address":"114 E 4th St",
    "sg:city":"Hermann",
    "sg:classifiers":[
        {
            "category":"Travel",
            "subcategory":"Hotels & Motels",
            "type":"Entertainment"
        }
    ],
    "sg:phone":"+1 573 486 4444",
    "sg:postcode":"65041",
    "sg:province":"MO",
    "sg:tags":[
        "breakfast",
        "accommodation",
        "bed"
    ],
    "wof:name":"Stuff & Nonsense",
    "wof:placetype":"venue"
},
  "geometry": {"coordinates":[-91.437618,38.704248],"type":"Point"}
}