{
  "type": "Feature",
  "properties": {
    "iso:country":"US",
    "sg:address":"8800 NW Prairie View Rd",
    "sg:city":"Kansas City",
    "sg:classifiers":[
        {
            "category":"Restaurant",
            "type":"Food & Drink"
        }
    ],
    "sg:menulink":"http://www.allmenus.com/mo/may/10510-bo-lings/menu/",
    "sg:phone":"+1 816 587 7880",
    "sg:postcode":"64153",
    "sg:province":"MO",
    "sg:tags":[
        "asian",
        "chinese"
    ],
    "wof:name":"Bo Lings",
    "wof:placetype":"venue"
},
  "geometry": {"coordinates":[-94.66253399999999,39.25552],"type":"Point"}
}