{
  "type": "Feature",
  "properties": {
    "iso:country":"US",
    "sg:address":"38721 Van Slyke Rd",
    "sg:city":"Windsor",
    "sg:classifiers":[
        {
            "category":"Building & Trades",
            "subcategory":"Construction",
            "type":"Services"
        }
    ],
    "sg:phone":"+1 660 647 2277",
    "sg:postcode":"65360",
    "sg:province":"MO",
    "sg:tags":[
        "contractor"
    ],
    "wof:name":"Dons Custom Home Exteriors",
    "wof:placetype":"venue"
},
  "geometry": {"coordinates":[-93.50359899999999,38.512444],"type":"Point"}
}