{
  "type": "Feature",
  "properties": {
    "iso:country":"US",
    "sg:address":"278 Mervin St",
    "sg:city":"Sullivan",
    "sg:classifiers":[
        {
            "category":"Manufacturing",
            "subcategory":"Food",
            "type":"Manufacturing & Wholesale Goods"
        }
    ],
    "sg:phone":"+1 573 468 8779",
    "sg:postcode":"63080",
    "sg:province":"MO",
    "sg:tags":[
        "product",
        "grocery",
        "mfg"
    ],
    "wof:name":"Washington Street Bakery",
    "wof:placetype":"venue"
},
  "geometry": {"coordinates":[-91.16991,38.21958],"type":"Point"}
}