{
  "type": "Feature",
  "properties": {
    "iso:country":"US",
    "sg:address":"215 W Dartmouth Rd",
    "sg:city":"Kansas City",
    "sg:classifiers":[
        {
            "category":"Building & Trades",
            "subcategory":"Construction",
            "type":"Services"
        }
    ],
    "sg:phone":"+1 816 444 3948",
    "sg:postcode":"64113",
    "sg:province":"MO",
    "sg:tags":[
        "hanging",
        "contractor"
    ],
    "wof:name":"Crabtree Painting Inc",
    "wof:placetype":"venue"
},
  "geometry": {"coordinates":[-94.590293,39.000849],"type":"Point"}
}