{
  "type": "Feature",
  "properties": {
    "iso:country":"US",
    "sg:address":"105 E Charles St",
    "sg:city":"Doniphan",
    "sg:classifiers":[
        {
            "category":"Place Of Worship",
            "subcategory":"Church",
            "type":"Public Place"
        },
        {
            "category":"Place Of Worship",
            "type":"Public Place"
        },
        {
            "category":"Shopping",
            "subcategory":"Used Merchandise",
            "type":"Retail Goods"
        }
    ],
    "sg:phone":"+1 573 996 4541",
    "sg:postcode":"63935",
    "sg:province":"MO",
    "sg:tags":[
        "shop",
        "resale",
        "churches-interdenominational",
        "churches-various",
        "denomination"
    ],
    "wof:name":"Doniphan Gospel Rescue Mission",
    "wof:placetype":"venue"
},
  "geometry": {"coordinates":[-90.82738999999999,36.616612],"type":"Point"}
}