{
  "type": "Feature",
  "properties": {
    "iso:country":"US",
    "sg:address":"40 Old State Rd",
    "sg:city":"Ballwin",
    "sg:classifiers":[
        {
            "category":"Restaurant",
            "type":"Food & Drink"
        }
    ],
    "sg:phone":"+1 636 391 6154",
    "sg:postcode":"63021",
    "sg:province":"MO",
    "sg:tags":[
        "eating"
    ],
    "wof:name":"Clancy's Irish Pub & Grill",
    "wof:placetype":"venue"
},
  "geometry": {"coordinates":[-90.595421,38.588994],"type":"Point"}
}