{
  "type": "Feature",
  "properties": {
    "iso:country":"US",
    "sg:address":"3012 Apple Blossom Ct",
    "sg:city":"High Ridge",
    "sg:classifiers":[
        {
            "category":"Home & Garden",
            "subcategory":"Household Appliances",
            "type":"Retail Goods"
        },
        {
            "category":"Retail",
            "subcategory":"Repair Shop",
            "type":"Services"
        }
    ],
    "sg:phone":"+1 314 487 7400",
    "sg:postcode":"63049",
    "sg:province":"MO",
    "sg:tags":[
        "electrical"
    ],
    "wof:name":"A-1 Appliance",
    "wof:placetype":"venue"
},
  "geometry": {"coordinates":[-90.49079500000001,38.436594],"type":"Point"}
}