{
  "type": "Feature",
  "properties": {
    "iso:country":"US",
    "sg:address":"5756 N Anita Ave",
    "sg:city":"Kansas City",
    "sg:classifiers":[
        {
            "category":"Manufacturing",
            "subcategory":"Jewelry",
            "type":"Manufacturing & Wholesale Goods"
        }
    ],
    "sg:phone":"+1 816 587 5857",
    "sg:postcode":"64151",
    "sg:province":"MO",
    "sg:tags":[
        "precious",
        "metal",
        "mfg"
    ],
    "wof:name":"Galaxy Designs",
    "wof:placetype":"venue"
},
  "geometry": {"coordinates":[-94.63399800000001,39.200401],"type":"Point"}
}