{
  "type": "Feature",
  "properties": {
    "iso:country":"US",
    "sg:address":"213 W Main St",
    "sg:city":"Richland",
    "sg:classifiers":[
        {
            "category":"Local Transit",
            "type":"Transportation"
        }
    ],
    "sg:phone":"+1 573 765 5747",
    "sg:postcode":"65556",
    "sg:province":"MO",
    "sg:tags":[
        "ambulance"
    ],
    "wof:name":"Pulaski County Ambulance",
    "wof:placetype":"venue"
},
  "geometry": {"coordinates":[-92.406723,37.857511],"type":"Point"}
}