{
  "type": "Feature",
  "properties": {
    "iso:country":"US",
    "sg:address":"505 Strecker Rd",
    "sg:city":"Ballwin",
    "sg:classifiers":[
        {
            "category":"Restaurant",
            "type":"Food & Drink"
        }
    ],
    "sg:phone":"+1 636 405 0014",
    "sg:postcode":"63011",
    "sg:province":"MO",
    "wof:name":"Sarah's Cafe",
    "wof:placetype":"venue"
},
  "geometry": {"coordinates":[-90.61497799999999,38.60987],"type":"Point"}
}