{
  "type": "Feature",
  "properties": {
    "addr:full":"113 Schiller St Hermann MO 65041",
    "addr:housenumber":"113",
    "addr:postcode":"65041",
    "addr:street":"Schiller St",
    "iso:country":"US",
    "sg:address":"113 Schiller St",
    "sg:city":"Hermann",
    "sg:classifiers":[
        {
            "category":"Personal",
            "subcategory":"Beauty Salon",
            "type":"Services"
        }
    ],
    "sg:phone":"+1 573 486 0607",
    "sg:postcode":"65041",
    "sg:province":"MO",
    "sg:tags":[
        "shop"
    ],
    "wof:name":"Design Studio",
    "wof:placetype":"venue"
},
  "geometry": {"coordinates":[-91.43521699999999,38.706742],"type":"Point"}
}