{
  "type": "Feature",
  "properties": {
    "iso:country":"US",
    "sg:address":"13617 Route A",
    "sg:city":"Russellville",
    "sg:classifiers":[
        {
            "category":"Manufacturing",
            "subcategory":"Tools & Machinery",
            "type":"Manufacturing & Wholesale Goods"
        },
        {
            "category":"Retail",
            "subcategory":"Repair Shop",
            "type":"Services"
        },
        {
            "category":"Building & Trades",
            "subcategory":"Construction",
            "type":"Services"
        }
    ],
    "sg:phone":"+1 573 782 3441",
    "sg:postcode":"65074",
    "sg:province":"MO",
    "sg:tags":[
        "machine",
        "welder",
        "machinery-rebuild"
    ],
    "wof:name":"Voegeli Welding & Machine",
    "wof:placetype":"venue"
},
  "geometry": {"coordinates":[-92.453042,38.449686],"type":"Point"}
}