{
  "type": "Feature",
  "properties": {
    "iso:country":"US",
    "sg:address":"1628 Frederick Ave",
    "sg:city":"St Joseph",
    "sg:classifiers":[
        {
            "category":"Retail",
            "subcategory":"Auto Repair",
            "type":"Services"
        }
    ],
    "sg:phone":"+1 816 232 7083",
    "sg:postcode":"64501",
    "sg:province":"MO",
    "sg:tags":[
        "repairing",
        "automotive",
        "radiator",
        "automobile"
    ],
    "wof:name":"Acme Radiators Repair Shop",
    "wof:placetype":"venue"
},
  "geometry": {"coordinates":[-94.84020099999999,39.772583],"type":"Point"}
}