{
  "type": "Feature",
  "properties": {
    "iso:country":"US",
    "sg:address":"1105 W 49 St",
    "sg:city":"Kansas City",
    "sg:classifiers":[
        {
            "category":"Professional",
            "type":"Services"
        }
    ],
    "sg:phone":"+1 816 753 2266",
    "sg:postcode":"64112",
    "sg:province":"MO",
    "sg:tags":[
        "personal",
        "eating"
    ],
    "wof:name":"Arrangements LLC",
    "wof:placetype":"venue"
},
  "geometry": {"coordinates":[-94.600964,39.03935],"type":"Point"}
}