{
  "type": "Feature",
  "properties": {
    "iso:country":"US",
    "sg:address":"1221 Clay St",
    "sg:city":"Kansas City",
    "sg:classifiers":[
        {
            "category":"Retail",
            "subcategory":"Laundry & Dry Cleaning",
            "type":"Services"
        }
    ],
    "sg:phone":"+1 816 842 9444",
    "sg:postcode":"64116",
    "sg:province":"MO",
    "sg:tags":[
        "cleaners",
        "rug",
        "carpet"
    ],
    "wof:name":"Professional Carpet Systems",
    "wof:placetype":"venue"
},
  "geometry": {"coordinates":[-94.578547,39.131978],"type":"Point"}
}