{
  "type": "Feature",
  "properties": {
    "iso:country":"US",
    "sg:address":"6601 Executive Dr",
    "sg:city":"Kansas City",
    "sg:classifiers":[
        {
            "category":"Building & Trades",
            "subcategory":"Construction",
            "type":"Services"
        }
    ],
    "sg:phone":"+1 816 245 6000",
    "sg:postcode":"64120",
    "sg:province":"MO",
    "sg:tags":[
        "commercial",
        "contractor"
    ],
    "sg:website":"www.bucon.net",
    "wof:name":"Bucon Inc",
    "wof:placetype":"venue"
},
  "geometry": {"coordinates":[-94.50574400000001,39.140236],"type":"Point"}
}