{
  "type": "Feature",
  "properties": {
    "iso:country":"US",
    "sg:address":"1511 W College St",
    "sg:city":"Marshall",
    "sg:classifiers":[
        {
            "category":"Real Estate",
            "subcategory":"Real Estate Operator",
            "type":"Services"
        }
    ],
    "sg:phone":"+1 660 831 0030",
    "sg:postcode":"65340",
    "sg:province":"MO",
    "sg:tags":[
        "apartment"
    ],
    "wof:name":"Santa Fe Trail Apts",
    "wof:placetype":"venue"
},
  "geometry": {"coordinates":[-93.215886,39.108344],"type":"Point"}
}