{
  "type": "Feature",
  "properties": {
    "iso:country":"US",
    "sg:address":"1706 W Grand St",
    "sg:city":"Springfield",
    "sg:classifiers":[
        {
            "category":"Home & Garden",
            "subcategory":"Garden Supply",
            "type":"Retail Goods"
        }
    ],
    "sg:phone":"+1 417 869 1836",
    "sg:postcode":"65802",
    "sg:province":"MO",
    "sg:tags":[
        "renting",
        "equipment",
        "lawn",
        "lawnmowers",
        "accessory"
    ],
    "sg:website":"http://www.stihldealer.net/default-dealer-002795.aspx",
    "wof:name":"Vinton Supply Company",
    "wof:placetype":"venue"
},
  "geometry": {"coordinates":[-93.314232,37.197048],"type":"Point"}
}