{
  "type": "Feature",
  "properties": {
    "iso:country":"US",
    "sg:address":"5100 E 119th St",
    "sg:city":"Grandview",
    "sg:classifiers":[
        {
            "category":"Wholesale",
            "subcategory":"Photographic Equipment",
            "type":"Manufacturing & Wholesale Goods"
        },
        {
            "category":"Professional",
            "subcategory":"Business Services",
            "type":"Services"
        }
    ],
    "sg:phone":"+1 816 966 4529",
    "sg:postcode":"64030",
    "sg:province":"MO",
    "sg:tags":[
        "integrator",
        "audio",
        "video",
        "system"
    ],
    "wof:name":"Mis Technologies",
    "wof:placetype":"venue"
},
  "geometry": {"coordinates":[-94.52888799999999,38.909196],"type":"Point"}
}