{
  "type": "Feature",
  "properties": {
    "iso:country":"US",
    "sg:address":"106 W Washington St",
    "sg:city":"Kirksville",
    "sg:classifiers":[
        {
            "category":"Government",
            "subcategory":"Office",
            "type":"Public Place"
        }
    ],
    "sg:phone":"+1 660 665 4423",
    "sg:postcode":"63501",
    "sg:province":"MO",
    "sg:tags":[
        "county",
        "taxation"
    ],
    "wof:name":"Adair County Assessor",
    "wof:placetype":"venue"
},
  "geometry": {"coordinates":[-92.58320999999999,40.19479],"type":"Point"}
}