{
  "type": "Feature",
  "properties": {
    "iso:country":"US",
    "sg:address":"13371 Co Rd 3000",
    "sg:city":"Rolla",
    "sg:classifiers":[
        {
            "category":"Retail",
            "subcategory":"Repair Shop",
            "type":"Services"
        }
    ],
    "sg:phone":"+1 573 364 2915",
    "sg:postcode":"65401",
    "sg:province":"MO",
    "sg:tags":[
        "refinishing",
        "furniture"
    ],
    "wof:name":"Designs By Dills",
    "wof:placetype":"venue"
},
  "geometry": {"coordinates":[-91.706895,37.936278],"type":"Point"}
}