{
  "type": "Feature",
  "properties": {
    "iso:country":"US",
    "sg:address":"12212 Poggemoeller Rd",
    "sg:city":"Saint Louis",
    "sg:classifiers":[
        {
            "category":"Professional",
            "subcategory":"Business Services",
            "type":"Services"
        }
    ],
    "sg:phone":"+1 314 741 6565",
    "sg:postcode":"63138",
    "sg:province":"MO",
    "wof:name":"Courtney Appraisal Co",
    "wof:placetype":"venue"
},
  "geometry": {"coordinates":[-90.22782599999999,38.800543],"type":"Point"}
}