{
  "type": "Feature",
  "properties": {
    "iso:country":"US",
    "sg:address":"4509 Minor Hill Rd",
    "sg:city":"Ashland",
    "sg:classifiers":[
        {
            "category":"Professional",
            "subcategory":"Detective & Security Services",
            "type":"Services"
        }
    ],
    "sg:phone":"+1 573 657 0911",
    "sg:postcode":"65010",
    "sg:province":"MO",
    "sg:tags":[
        "information",
        "bureau"
    ],
    "wof:name":"Chore Services",
    "wof:placetype":"venue"
},
  "geometry": {"coordinates":[-92.278155,38.813801],"type":"Point"}
}