{
  "type": "Feature",
  "properties": {
    "iso:country":"US",
    "sg:address":"1960 E Blaine St",
    "sg:city":"Springfield",
    "sg:classifiers":[
        {
            "category":"Farming",
            "subcategory":"Dairy Farm",
            "type":"Manufacturing & Wholesale Goods"
        }
    ],
    "sg:phone":"+1 417 831 6931",
    "sg:postcode":"65803",
    "sg:province":"MO",
    "sg:website":"http://www.mid-southdairy.com",
    "wof:name":"Mid-South Dairy Records",
    "wof:placetype":"venue"
},
  "geometry": {"coordinates":[-93.257748,37.229086],"type":"Point"}
}