{
  "type": "Feature",
  "properties": {
    "iso:country":"US",
    "sg:address":"122 W 67 Ter",
    "sg:city":"Kansas City",
    "sg:classifiers":[
        {
            "category":"Professional",
            "subcategory":"Management & Consulting",
            "type":"Services"
        }
    ],
    "sg:phone":"+1 816 333 3986",
    "sg:postcode":"64113",
    "sg:province":"MO",
    "sg:tags":[
        "business"
    ],
    "wof:name":"State Arts Fine Art Consult",
    "wof:placetype":"venue"
},
  "geometry": {"coordinates":[-94.592502,39.006729],"type":"Point"}
}