{
  "type": "Feature",
  "properties": {
    "iso:country":"US",
    "sg:address":"13194 Maries Road 330",
    "sg:city":"Vienna",
    "sg:classifiers":[
        {
            "category":"Farming",
            "subcategory":"Livestock Farm",
            "type":"Manufacturing & Wholesale Goods"
        }
    ],
    "sg:phone":"+1 573 422 3578",
    "sg:postcode":"65582",
    "sg:province":"MO",
    "sg:tags":[
        "animal",
        "general"
    ],
    "wof:name":"Crossed Arrows Ranch",
    "wof:placetype":"venue"
},
  "geometry": {"coordinates":[-91.879107,38.205674],"type":"Point"}
}