{
  "type": "Feature",
  "properties": {
    "iso:country":"US",
    "sg:address":"749 W Torrance St",
    "sg:city":"Maryville",
    "sg:classifiers":[
        {
            "category":"Organizations",
            "subcategory":"Professional Association",
            "type":"Services"
        }
    ],
    "sg:phone":"+1 660 582 7620",
    "sg:postcode":"64468",
    "sg:province":"MO",
    "sg:tags":[
        "business"
    ],
    "wof:name":"Torrance Group Homes",
    "wof:placetype":"venue"
},
  "geometry": {"coordinates":[-94.882462,40.339817],"type":"Point"}
}