{
  "type": "Feature",
  "properties": {
    "iso:country":"US",
    "sg:address":"12440 Old Halls Ferry Rd",
    "sg:city":"Florissant",
    "sg:classifiers":[
        {
            "category":"Personal",
            "subcategory":"Barber",
            "type":"Services"
        }
    ],
    "sg:phone":"+1 314 741 7887",
    "sg:postcode":"63033",
    "sg:province":"MO",
    "sg:tags":[
        "shop"
    ],
    "wof:name":"Cross Roads Barber-Style Shop",
    "wof:placetype":"venue"
},
  "geometry": {"coordinates":[-90.26756399999999,38.795373],"type":"Point"}
}