{
  "type": "Feature",
  "properties": {
    "iso:country":"US",
    "sg:address":"561 N Scott Ave",
    "sg:city":"Belton",
    "sg:classifiers":[
        {
            "category":"Health Services",
            "subcategory":"Doctor",
            "type":"Services"
        }
    ],
    "sg:phone":"+1 816 331 4333",
    "sg:postcode":"64012",
    "sg:province":"MO",
    "sg:tags":[
        "dentist"
    ],
    "wof:name":"Steven D Dunning DDS",
    "wof:placetype":"venue"
},
  "geometry": {"coordinates":[-94.534099,38.823526],"type":"Point"}
}