{
  "type": "Feature",
  "properties": {
    "iso:country":"US",
    "sg:address":"3507 E 223rd St",
    "sg:city":"Peculiar",
    "sg:classifiers":[
        {
            "category":"Social Services",
            "subcategory":"Child Care",
            "type":"Services"
        }
    ],
    "sg:phone":"+1 816 618 3388",
    "sg:postcode":"64078",
    "sg:province":"MO",
    "sg:tags":[
        "day"
    ],
    "wof:name":"Kathys Daycare",
    "wof:placetype":"venue"
},
  "geometry": {"coordinates":[-94.56229500000001,38.721418],"type":"Point"}
}