{
  "type": "Feature",
  "properties": {
    "iso:country":"US",
    "sg:address":"300 Houston St",
    "sg:city":"St Charles",
    "sg:classifiers":[
        {
            "category":"Autos & Motor Vehicles",
            "subcategory":"Fuel & Gas Station",
            "type":"Retail Goods"
        }
    ],
    "sg:phone":"+1 636 925 2245",
    "sg:postcode":"63301",
    "sg:province":"MO",
    "sg:tags":[
        "petroleum",
        "product",
        "station",
        "gasoline",
        "grocery"
    ],
    "wof:name":"Citgo On Elm Street",
    "wof:placetype":"venue"
},
  "geometry": {"coordinates":[-90.49276999999999,38.78854],"type":"Point"}
}