{
  "type": "Feature",
  "properties": {
    "iso:country":"US",
    "sg:address":"972 Highway T",
    "sg:city":"Bolivar",
    "sg:classifiers":[
        {
            "category":"Farming",
            "subcategory":"Livestock Farm",
            "type":"Manufacturing & Wholesale Goods"
        }
    ],
    "sg:phone":"+1 417 326 5918",
    "sg:postcode":"65613",
    "sg:province":"MO",
    "sg:tags":[
        "ranch"
    ],
    "wof:name":"Billy Joe Neill",
    "wof:placetype":"venue"
},
  "geometry": {"coordinates":[-93.43534699999999,37.604894],"type":"Point"}
}