{
  "type": "Feature",
  "properties": {
    "iso:country":"US",
    "sg:address":"11855 Craig View Dr",
    "sg:city":"Saint Louis",
    "sg:classifiers":[
        {
            "category":"Professional",
            "subcategory":"Employment Agencies",
            "type":"Services"
        }
    ],
    "sg:phone":"+1 314 993 3391",
    "sg:postcode":"63146",
    "sg:province":"MO",
    "sg:tags":[
        "help",
        "supply"
    ],
    "wof:name":"Hillcrest Dev Agency",
    "wof:placetype":"venue"
},
  "geometry": {"coordinates":[-90.435109,38.68144],"type":"Point"}
}