{
  "type": "Feature",
  "properties": {
    "iso:country":"US",
    "sg:address":"1292 Poseidon Ct",
    "sg:city":"Saint Peters",
    "sg:classifiers":[
        {
            "category":"Professional",
            "subcategory":"Management & Consulting",
            "type":"Services"
        }
    ],
    "sg:phone":"+1 636 970 7904",
    "sg:postcode":"63376",
    "sg:province":"MO",
    "sg:tags":[
        "business"
    ],
    "wof:name":"Motorola",
    "wof:placetype":"venue"
},
  "geometry": {"coordinates":[-90.621152,38.769524],"type":"Point"}
}