{
  "type": "Feature",
  "properties": {
    "iso:country":"US",
    "sg:address":"7746 Delmont St",
    "sg:city":"Saint Louis",
    "sg:classifiers":[
        {
            "category":"Building & Trades",
            "subcategory":"Cleaning & Sanitation",
            "type":"Services"
        }
    ],
    "sg:phone":"+1 314 481 1327",
    "sg:postcode":"63123",
    "sg:province":"MO",
    "sg:tags":[
        "maintenance"
    ],
    "wof:name":"Correnti Air Duct Cleaning",
    "wof:placetype":"venue"
},
  "geometry": {"coordinates":[-90.306363,38.568624],"type":"Point"}
}