{
  "type": "Feature",
  "properties": {
    "iso:country":"US",
    "sg:address":"610 NE 76 Ter",
    "sg:city":"Kansas City",
    "sg:classifiers":[
        {
            "category":"Retail",
            "subcategory":"Auto Repair",
            "type":"Services"
        }
    ],
    "sg:phone":"+1 816 468 5150",
    "sg:postcode":"64118",
    "sg:province":"MO",
    "sg:tags":[
        "body",
        "automobile",
        "painting"
    ],
    "wof:name":"J R's Body & Paint",
    "wof:placetype":"venue"
},
  "geometry": {"coordinates":[-94.57358499999999,39.232861],"type":"Point"}
}