{
  "type": "Feature",
  "properties": {
    "iso:country":"US",
    "sg:address":"1003 S Pershing St",
    "sg:city":"Salem",
    "sg:classifiers":[
        {
            "category":"Shopping",
            "subcategory":"Used Merchandise",
            "type":"Retail Goods"
        }
    ],
    "sg:phone":"+1 573 729 3670",
    "sg:postcode":"65560",
    "sg:province":"MO",
    "wof:name":"Nu To U Shop",
    "wof:placetype":"venue"
},
  "geometry": {"coordinates":[-91.53102199999999,37.636342],"type":"Point"}
}