{
  "type": "Feature",
  "properties": {
    "iso:country":"US",
    "sg:address":"4039 S Kansas Expy",
    "sg:city":"Springfield",
    "sg:classifiers":[
        {
            "category":"Real Estate",
            "subcategory":"Real Estate Services",
            "type":"Services"
        },
        {
            "category":"Banks & Credit Unions",
            "subcategory":"Bank",
            "type":"Services"
        }
    ],
    "sg:phone":"+1 417 889 2600",
    "sg:postcode":"65807",
    "sg:province":"MO",
    "sg:tags":[
        "loan"
    ],
    "sg:website":"http://www.signaturebank.com",
    "wof:name":"The Signature Bank",
    "wof:placetype":"venue"
},
  "geometry": {"coordinates":[-93.319465,37.141135],"type":"Point"}
}