{
  "type": "Feature",
  "properties": {
    "iso:country":"US",
    "sg:address":"401 E North Main St",
    "sg:city":"Richmond",
    "sg:classifiers":[
        {
            "category":"Social Services",
            "type":"Services"
        }
    ],
    "sg:phone":"+1 816 776 8191",
    "sg:postcode":"64085",
    "sg:province":"MO",
    "sg:website":"http://www.salarmychicago.org",
    "wof:name":"Salvation Army",
    "wof:placetype":"venue"
},
  "geometry": {"coordinates":[-93.971588,39.279049],"type":"Point"}
}