{
  "type": "Feature",
  "properties": {
    "iso:country":"US",
    "sg:address":"2501 N Bishop Ave",
    "sg:city":"Rolla",
    "sg:classifiers":[
        {
            "category":"Wholesale",
            "subcategory":"Construction Materials",
            "type":"Manufacturing & Wholesale Goods"
        }
    ],
    "sg:phone":"+1 573 364 3820",
    "sg:postcode":"65401",
    "sg:province":"MO",
    "sg:tags":[
        "sand",
        "gravel"
    ],
    "wof:name":"Smith Sand & Gravel",
    "wof:placetype":"venue"
},
  "geometry": {"coordinates":[-91.765918,37.964609],"type":"Point"}
}