{
  "type": "Feature",
  "properties": {
    "iso:country":"US",
    "sg:address":"2138 Inman Rd",
    "sg:city":"Poplar Bluff",
    "sg:phone":"+1 573 785 5459",
    "sg:postcode":"63901",
    "sg:province":"MO",
    "sg:tags":[
        "farm",
        "rice"
    ],
    "wof:name":"Frank Waddell",
    "wof:placetype":"venue"
},
  "geometry": {"coordinates":[-90.426526,36.772658],"type":"Point"}
}