{
  "type": "Feature",
  "properties": {
    "iso:country":"US",
    "sg:address":"2333 Forest Ave",
    "sg:city":"Kansas City",
    "sg:classifiers":[
        {
            "category":"Professional",
            "subcategory":"Detective & Security Services",
            "type":"Services"
        }
    ],
    "sg:phone":"+1 816 421 1113",
    "sg:postcode":"64108",
    "sg:province":"MO",
    "sg:tags":[
        "car"
    ],
    "wof:name":"Dunbar Armored Inc",
    "wof:placetype":"venue"
},
  "geometry": {"coordinates":[-94.56925699999999,39.083832],"type":"Point"}
}