{
  "type": "Feature",
  "properties": {
    "iso:country":"US",
    "sg:address":"4520 Madison Ave",
    "sg:city":"Kansas City",
    "sg:classifiers":[
        {
            "category":"Building & Trades",
            "subcategory":"Cleaning & Sanitation",
            "type":"Services"
        }
    ],
    "sg:phone":"+1 816 531 3374",
    "sg:postcode":"64111",
    "sg:province":"MO",
    "sg:tags":[
        "support",
        "business"
    ],
    "wof:name":"Facility Support MGT Svcs",
    "wof:placetype":"venue"
},
  "geometry": {"coordinates":[-94.597343,39.044663],"type":"Point"}
}