{
  "type": "Feature",
  "properties": {
    "addr:full":"117 N 2nd St Odessa MO 64076",
    "addr:housenumber":"117",
    "addr:postcode":"64076",
    "addr:street":"N 2Nd St",
    "iso:country":"US",
    "sg:address":"117 N 2nd St",
    "sg:city":"Odessa",
    "sg:classifiers":[
        {
            "category":"Restaurant",
            "type":"Food & Drink"
        }
    ],
    "sg:phone":"+1 816 633 8828",
    "sg:postcode":"64076",
    "sg:province":"MO",
    "wof:name":"China Buffet",
    "wof:placetype":"venue"
},
  "geometry": {"coordinates":[-93.953633,39.000549],"type":"Point"}
}