{
  "type": "Feature",
  "properties": {
    "iso:country":"US",
    "sg:address":"1619 SE Decker",
    "sg:city":"Lees Summit",
    "sg:classifiers":[
        {
            "category":"Building & Trades",
            "subcategory":"Construction",
            "type":"Services"
        }
    ],
    "sg:phone":"+1 816 525 9460",
    "sg:postcode":"64081",
    "sg:province":"MO",
    "sg:tags":[
        "contractor"
    ],
    "wof:name":"Roy & Son Fencing",
    "wof:placetype":"venue"
},
  "geometry": {"coordinates":[-94.371612,38.891175],"type":"Point"}
}