{
  "type": "Feature",
  "properties": {
    "iso:country":"US",
    "sg:address":"902 E 4th St Ste 110",
    "sg:city":"Joplin",
    "sg:classifiers":[
        {
            "category":"Professional",
            "type":"Services"
        }
    ],
    "sg:phone":"+1 417 434 5295",
    "sg:postcode":"64801",
    "sg:province":"MO",
    "sg:tags":[
        "transportation"
    ],
    "wof:name":"Total Transportation Solutions Inc",
    "wof:placetype":"venue"
},
  "geometry": {"coordinates":[-94.503799,37.087478],"type":"Point"}
}