{
  "type": "Feature",
  "properties": {
    "iso:country":"US",
    "sg:address":"15464 Manchester Rd",
    "sg:city":"Ballwin",
    "sg:classifiers":[
        {
            "category":"Home & Garden",
            "subcategory":"Furniture",
            "type":"Retail Goods"
        }
    ],
    "sg:phone":"+1 636 386 3100",
    "sg:postcode":"63011",
    "sg:province":"MO",
    "wof:name":"Yotes Inc",
    "wof:placetype":"venue"
},
  "geometry": {"coordinates":[-90.564494,38.592839],"type":"Point"}
}