{
  "type": "Feature",
  "properties": {
    "iso:country":"US",
    "sg:address":"3919 Dr Martin Luther King Dr",
    "sg:city":"St Louis",
    "sg:classifiers":[
        {
            "category":"Retail",
            "subcategory":"Auto Repair",
            "type":"Services"
        }
    ],
    "sg:phone":"+1 314 534 1929",
    "sg:postcode":"63113",
    "sg:province":"MO",
    "sg:tags":[
        "repairing",
        "automobile",
        "general"
    ],
    "wof:name":"Martin Luther King Auto Repair",
    "wof:placetype":"venue"
},
  "geometry": {"coordinates":[-90.233949,38.651678],"type":"Point"}
}