{
  "type": "Feature",
  "properties": {
    "iso:country":"US",
    "sg:address":"119 N Main St",
    "sg:city":"Rogersville",
    "sg:classifiers":[
        {
            "category":"Banks & Credit Unions",
            "subcategory":"Bank",
            "type":"Services"
        }
    ],
    "sg:phone":"+1 417 753 5224",
    "sg:postcode":"65742",
    "sg:province":"MO",
    "sg:website":"http://www.theseymourbank.com",
    "wof:name":"Seymour Bank",
    "wof:placetype":"venue"
},
  "geometry": {"coordinates":[-93.057705,37.119678],"type":"Point"}
}