{
  "type": "Feature",
  "properties": {
    "iso:country":"US",
    "sg:address":"811A N 2nd St",
    "sg:city":"Saint Louis",
    "sg:classifiers":[
        {
            "category":"Professional",
            "subcategory":"Lawyer & Legal Services",
            "type":"Services"
        }
    ],
    "sg:phone":"+1 800 333 5297",
    "sg:postcode":"63102",
    "sg:province":"MO",
    "sg:tags":[
        "personal",
        "injury"
    ],
    "sg:website":"www.rexcarr.com",
    "wof:name":"Rex Carr Law Firm Llc the",
    "wof:placetype":"venue"
},
  "geometry": {"coordinates":[-90.184561,38.631075],"type":"Point"}
}