{
  "type": "Feature",
  "properties": {
    "iso:country":"US",
    "sg:address":"3600 S Jackson Dr",
    "sg:city":"Independence",
    "sg:classifiers":[
        {
            "category":"Professional",
            "subcategory":"Management & Consulting",
            "type":"Services"
        }
    ],
    "sg:phone":"+1 816 795 0832",
    "sg:postcode":"64057",
    "sg:province":"MO",
    "sg:tags":[
        "business"
    ],
    "wof:name":"Allen Enterprises",
    "wof:placetype":"venue"
},
  "geometry": {"coordinates":[-94.354758,39.05374],"type":"Point"}
}