{
  "type": "Feature",
  "properties": {
    "iso:country":"US",
    "sg:address":"803 E North Ave",
    "sg:city":"Belton",
    "sg:classifiers":[
        {
            "category":"Personal",
            "subcategory":"Tanning Parlor",
            "type":"Services"
        }
    ],
    "sg:phone":"+1 816 331 8267",
    "sg:postcode":"64012",
    "sg:province":"MO",
    "sg:tags":[
        "salon"
    ],
    "wof:name":"Nutri-Tan",
    "wof:placetype":"venue"
},
  "geometry": {"coordinates":[-94.520714,38.813961],"type":"Point"}
}