{
  "type": "Feature",
  "properties": {
    "iso:country":"US",
    "sg:address":"1040 SW Luttrell Rd",
    "sg:city":"Blue Springs",
    "sg:classifiers":[
        {
            "category":"Manufacturing",
            "subcategory":"Metals",
            "type":"Manufacturing & Wholesale Goods"
        }
    ],
    "sg:phone":"+1 816 229 1515",
    "sg:postcode":"64015",
    "sg:province":"MO",
    "sg:tags":[
        "lock",
        "industrial",
        "supply"
    ],
    "wof:name":"Best Access Systems",
    "wof:placetype":"venue"
},
  "geometry": {"coordinates":[-94.27723899999999,39.007924],"type":"Point"}
}