{
  "type": "Feature",
  "properties": {
    "iso:country":"US",
    "sg:address":"1004 E Commercial St",
    "sg:city":"Springfield",
    "sg:classifiers":[
        {
            "category":"Retail",
            "subcategory":"Repair Shop",
            "type":"Services"
        }
    ],
    "sg:phone":"+1 417 862 8670",
    "sg:postcode":"65803",
    "sg:province":"MO",
    "sg:tags":[
        "lawnmower",
        "r",
        "appliance",
        "electrical",
        "equipment"
    ],
    "wof:name":"Rays Repair Service Div Mwlc",
    "wof:placetype":"venue"
},
  "geometry": {"coordinates":[-93.27692500000001,37.230386],"type":"Point"}
}