{
  "type": "Feature",
  "properties": {
    "iso:country":"US",
    "sg:address":"312 Meadow Dr",
    "sg:city":"Washington",
    "sg:classifiers":[
        {
            "category":"Building & Trades",
            "subcategory":"Construction",
            "type":"Services"
        }
    ],
    "sg:phone":"+1 636 390 2227",
    "sg:postcode":"63090",
    "sg:province":"MO",
    "sg:tags":[
        "contractor"
    ],
    "wof:name":"Miller Contracting Co",
    "wof:placetype":"venue"
},
  "geometry": {"coordinates":[-91.010867,38.533161],"type":"Point"}
}