{
  "type": "Feature",
  "properties": {
    "iso:country":"US",
    "sg:address":"716 Thomas St",
    "sg:city":"Weston",
    "sg:classifiers":[
        {
            "category":"Social Services",
            "subcategory":"Child Care",
            "type":"Services"
        }
    ],
    "sg:phone":"+1 816 386 2273",
    "sg:postcode":"64098",
    "sg:province":"MO",
    "wof:name":"A Day At The Park Daycare",
    "wof:placetype":"venue"
},
  "geometry": {"coordinates":[-94.90259,39.411721],"type":"Point"}
}