{
  "type": "Feature",
  "properties": {
    "iso:country":"US",
    "sg:address":"60 Doctors Park",
    "sg:city":"Cape Girardeau",
    "sg:classifiers":[
        {
            "category":"Social Services",
            "type":"Services"
        }
    ],
    "sg:phone":"+1 573 339 1188",
    "sg:postcode":"63703",
    "sg:province":"MO",
    "sg:tags":[
        "clinic",
        "specialty",
        "outpatient"
    ],
    "wof:name":"Southeast Outpatient Rehab",
    "wof:placetype":"venue"
},
  "geometry": {"coordinates":[-89.57440200000001,37.29418],"type":"Point"}
}