{
  "type": "Feature",
  "properties": {
    "iso:country":"US",
    "sg:address":"14285 Clark Dr",
    "sg:city":"Purdin",
    "sg:classifiers":[
        {
            "category":"Farming",
            "subcategory":"Livestock Farm",
            "type":"Manufacturing & Wholesale Goods"
        }
    ],
    "sg:phone":"+1 660 244 5823",
    "sg:postcode":"64674",
    "sg:province":"MO",
    "sg:tags":[
        "beef",
        "feedlot",
        "cattle"
    ],
    "wof:name":"James Morris",
    "wof:placetype":"venue"
},
  "geometry": {"coordinates":[-93.285884,39.979386],"type":"Point"}
}