{
  "type": "Feature",
  "properties": {
    "iso:country":"US",
    "sg:address":"201 Clarkson Executive Park",
    "sg:city":"Ellisville",
    "sg:classifiers":[
        {
            "category":"Wholesale",
            "subcategory":"Farm Supplies",
            "type":"Manufacturing & Wholesale Goods"
        }
    ],
    "sg:phone":"+1 636 386 3377",
    "sg:postcode":"63011",
    "sg:province":"MO",
    "sg:tags":[
        "feed"
    ],
    "wof:name":"R F Southerland Co",
    "wof:placetype":"venue"
},
  "geometry": {"coordinates":[-90.587075,38.60053],"type":"Point"}
}