{
  "type": "Feature",
  "properties": {
    "iso:country":"US",
    "sg:address":"7381 E Southern Dr",
    "sg:city":"Columbia",
    "sg:classifiers":[
        {
            "category":"Professional",
            "subcategory":"Secretarial Services",
            "type":"Services"
        }
    ],
    "sg:phone":"+1 573 474 2533",
    "sg:postcode":"65201",
    "sg:province":"MO",
    "sg:tags":[
        "typing"
    ],
    "wof:name":"Staggs & Staggs",
    "wof:placetype":"venue"
},
  "geometry": {"coordinates":[-92.225756,38.95343],"type":"Point"}
}