{
  "type": "Feature",
  "properties": {
    "iso:country":"US",
    "sg:address":"1443 N Robberson Ave",
    "sg:city":"Springfield",
    "sg:classifiers":[
        {
            "category":"Health Services",
            "subcategory":"Clinic",
            "type":"Services"
        }
    ],
    "sg:phone":"+1 417 269 8061",
    "sg:postcode":"65802",
    "sg:province":"MO",
    "sg:tags":[
        "osteopathic"
    ],
    "wof:name":"Hakan Louis B DO",
    "wof:placetype":"venue"
},
  "geometry": {"coordinates":[-93.290672,37.224758],"type":"Point"}
}