{
  "type": "Feature",
  "properties": {
    "iso:country":"US",
    "sg:address":"1015 Sarcoxie Trl",
    "sg:city":"Joplin",
    "sg:classifiers":[
        {
            "category":"Education",
            "subcategory":"College",
            "type":"Public Place"
        }
    ],
    "sg:phone":"+1 417 624 2344",
    "sg:postcode":"64801",
    "sg:province":"MO",
    "wof:name":"Missouri Southern State Cllg",
    "wof:placetype":"venue"
},
  "geometry": {"coordinates":[-94.459152,37.100394],"type":"Point"}
}