{
  "type": "Feature",
  "properties": {
    "iso:country":"US",
    "sg:address":"3022 S Belt Hwy",
    "sg:city":"Saint Joseph",
    "sg:classifiers":[
        {
            "category":"Shopping",
            "subcategory":"Department Store",
            "type":"Retail Goods"
        }
    ],
    "sg:phone":"+1 816 232 9819",
    "sg:postcode":"64503",
    "sg:province":"MO",
    "sg:tags":[
        "grocery"
    ],
    "wof:name":"Wal-Mart",
    "wof:placetype":"venue"
},
  "geometry": {"coordinates":[-94.801243,39.740094],"type":"Point"}
}