{
  "type": "Feature",
  "properties": {
    "iso:country":"US",
    "sg:address":"126 Main St",
    "sg:city":"Noel",
    "sg:classifiers":[
        {
            "category":"Personal",
            "subcategory":"Beauty Salon",
            "type":"Services"
        }
    ],
    "sg:phone":"+1 417 475 3205",
    "sg:postcode":"64854",
    "sg:province":"MO",
    "wof:name":"Head Games Beauty Salon",
    "wof:placetype":"venue"
},
  "geometry": {"coordinates":[-94.489441,36.545467],"type":"Point"}
}