{
  "type": "Feature",
  "properties": {
    "iso:country":"US",
    "sg:address":"4530 N Lindbergh Blvd",
    "sg:city":"Bridgeton",
    "sg:classifiers":[
        {
            "category":"Travel",
            "subcategory":"Hotels & Motels",
            "type":"Entertainment"
        }
    ],
    "sg:phone":"+1 314 731 0191",
    "sg:postcode":"63044",
    "sg:province":"MO",
    "wof:name":"Airport Hotel Investors",
    "wof:placetype":"venue"
},
  "geometry": {"coordinates":[-90.39369600000001,38.74779],"type":"Point"}
}