{
  "type": "Feature",
  "properties": {
    "iso:country":"US",
    "sg:address":"4201 S Noland Rd",
    "sg:city":"Independence",
    "sg:classifiers":[
        {
            "category":"Shopping",
            "subcategory":"Stationery & Office Supplies",
            "type":"Retail Goods"
        }
    ],
    "sg:phone":"+1 816 478 8202",
    "sg:postcode":"64055",
    "sg:province":"MO",
    "sg:tags":[
        "professional"
    ],
    "wof:name":"Hammetts Teachers Store",
    "wof:placetype":"venue"
},
  "geometry": {"coordinates":[-94.415244,39.04396],"type":"Point"}
}