{
  "type": "Feature",
  "properties": {
    "iso:country":"US",
    "sg:address":"2323 N Bishop Ave",
    "sg:city":"Rolla",
    "sg:classifiers":[
        {
            "category":"Banks & Credit Unions",
            "subcategory":"Investment Brokerage",
            "type":"Services"
        }
    ],
    "sg:phone":"+1 573 426 8888",
    "sg:postcode":"65401",
    "sg:province":"MO",
    "sg:tags":[
        "advisory",
        "financial"
    ],
    "wof:name":"Phenix Financial Advisors",
    "wof:placetype":"venue"
},
  "geometry": {"coordinates":[-91.765497,37.965607],"type":"Point"}
}