{
  "type": "Feature",
  "properties": {
    "iso:country":"US",
    "sg:address":"1970 W Timber Ridge Dr",
    "sg:city":"Sedalia",
    "sg:classifiers":[
        {
            "category":"Organizations",
            "subcategory":"Community Association",
            "type":"Services"
        }
    ],
    "sg:phone":"+1 660 829 0628",
    "sg:postcode":"65301",
    "sg:province":"MO",
    "sg:tags":[
        "veteran",
        "fraternal"
    ],
    "wof:name":"Air Force Sergeants Assn",
    "wof:placetype":"venue"
},
  "geometry": {"coordinates":[-93.305296,38.703123],"type":"Point"}
}