{
  "type": "Feature",
  "properties": {
    "iso:country":"US",
    "sg:address":"300 E Sunshine St",
    "sg:city":"Springfield",
    "sg:classifiers":[
        {
            "category":"Professional",
            "subcategory":"Business Services",
            "type":"Services"
        }
    ],
    "sg:phone":"+1 417 862 8155",
    "sg:postcode":"65807",
    "sg:province":"MO",
    "wof:name":"E Business Solutions & Svc",
    "wof:placetype":"venue"
},
  "geometry": {"coordinates":[-93.29051,37.18217],"type":"Point"}
}