{
  "type": "Feature",
  "properties": {
    "iso:country":"US",
    "sg:address":"23138 Neon Rd",
    "sg:city":"Ravenwood",
    "sg:classifiers":[
        {
            "category":"Real Estate",
            "subcategory":"Real Estate Operator",
            "type":"Services"
        }
    ],
    "sg:phone":"+1 660 937 3358",
    "sg:postcode":"64479",
    "sg:province":"MO",
    "sg:tags":[
        "property",
        "lessor"
    ],
    "wof:name":"G Morin",
    "wof:placetype":"venue"
},
  "geometry": {"coordinates":[-94.702836,40.384281],"type":"Point"}
}