{
  "type": "Feature",
  "properties": {
    "iso:country":"US",
    "sg:address":"1725 SW Bethel Rd",
    "sg:city":"De Kalb",
    "sg:classifiers":[
        {
            "category":"Farming",
            "subcategory":"Farm",
            "type":"Manufacturing & Wholesale Goods"
        }
    ],
    "sg:phone":"+1 816 685 3333",
    "sg:postcode":"64440",
    "sg:province":"MO",
    "sg:tags":[
        "crop",
        "general"
    ],
    "wof:name":"Scotty Sharp",
    "wof:placetype":"venue"
},
  "geometry": {"coordinates":[-94.886965,39.632491],"type":"Point"}
}