{
  "type": "Feature",
  "properties": {
    "iso:country":"US",
    "sg:address":"328 N Boonville Ave",
    "sg:city":"Springfield",
    "sg:classifiers":[
        {
            "category":"Social Services",
            "type":"Services"
        }
    ],
    "sg:phone":"+1 417 869 8086",
    "sg:postcode":"65806",
    "sg:province":"MO",
    "sg:tags":[
        "organization",
        "welfare"
    ],
    "wof:name":"Pathways Support Svc",
    "wof:placetype":"venue"
},
  "geometry": {"coordinates":[-93.29226,37.209759],"type":"Point"}
}