{
  "type": "Feature",
  "properties": {
    "addr:full":"17406 Chesterfield Airport Rd Chesterfield MO 63005",
    "addr:housenumber":"17406",
    "addr:postcode":"63005",
    "addr:street":"Chesterfield Airport Rd",
    "iso:country":"US",
    "sg:address":"17406 Chesterfield Airport Rd",
    "sg:city":"Chesterfield",
    "sg:classifiers":[
        {
            "category":"Utilities",
            "subcategory":"Mobile Phone",
            "type":"Services"
        },
        {
            "category":"Communications",
            "type":"Services"
        }
    ],
    "sg:phone":"+1 866 430 5293",
    "sg:postcode":"63005",
    "sg:province":"MO",
    "sg:tags":[
        "telephone",
        "cellular"
    ],
    "sg:website":"http://stlouis.citysearch.com/profile/external/44231957/chesterfield_mo/u_s_cellular.html?publisher=yellowpages&reference_id=1&placement=ypwebsitemip",
    "wof:name":"U.S. Cellular",
    "wof:placetype":"venue"
},
  "geometry": {"coordinates":[-90.60704200000001,38.668343],"type":"Point"}
}