{
  "type": "Feature",
  "properties": {
    "iso:country":"US",
    "sg:address":"18505 Maple Rd",
    "sg:city":"Carthage",
    "sg:classifiers":[
        {
            "category":"Building & Trades",
            "subcategory":"Construction",
            "type":"Services"
        }
    ],
    "sg:phone":"+1 417 525 4718",
    "sg:postcode":"64836",
    "sg:province":"MO",
    "sg:tags":[
        "residential"
    ],
    "wof:name":"Rob Erwin Construction",
    "wof:placetype":"venue"
},
  "geometry": {"coordinates":[-94.399338,37.24207],"type":"Point"}
}