{
  "type": "Feature",
  "properties": {
    "iso:country":"US",
    "sg:address":"8816 Manchester Rd",
    "sg:city":"St Louis",
    "sg:classifiers":[
        {
            "category":"Professional",
            "subcategory":"Testing Lab",
            "type":"Services"
        }
    ],
    "sg:phone":"+1 314 664 4466",
    "sg:postcode":"63144",
    "sg:province":"MO",
    "sg:tags":[
        "correction",
        "radon"
    ],
    "wof:name":"Radon Solutions",
    "wof:placetype":"venue"
},
  "geometry": {"coordinates":[-90.350734,38.61251],"type":"Point"}
}