{
  "type": "Feature",
  "properties": {
    "iso:country":"US",
    "sg:address":"8514 Midland Blvd",
    "sg:city":"Saint Louis",
    "sg:classifiers":[
        {
            "category":"Freight",
            "type":"Transportation"
        }
    ],
    "sg:phone":"+1 314 426 8987",
    "sg:postcode":"63114",
    "sg:province":"MO",
    "sg:tags":[
        "operator",
        "local",
        "trucking"
    ],
    "wof:name":"Sammy Lane Trucking",
    "wof:placetype":"venue"
},
  "geometry": {"coordinates":[-90.34349400000001,38.697692],"type":"Point"}
}