{
  "type": "Feature",
  "properties": {
    "iso:country":"US",
    "sg:address":"1400 Brett Cir",
    "sg:city":"Kearney",
    "sg:classifiers":[
        {
            "category":"Building & Trades",
            "subcategory":"Construction",
            "type":"Services"
        }
    ],
    "sg:phone":"+1 816 628 6765",
    "sg:postcode":"64060",
    "sg:province":"MO",
    "sg:tags":[
        "house"
    ],
    "wof:name":"Laffey Brothers Firms Inc",
    "wof:placetype":"venue"
},
  "geometry": {"coordinates":[-94.36338499999999,39.358663],"type":"Point"}
}