{
  "type": "Feature",
  "properties": {
    "iso:country":"US",
    "sg:address":"1153 NE Rice Rd",
    "sg:city":"Lees Summit",
    "sg:classifiers":[
        {
            "category":"Insurance",
            "subcategory":"Title Insurance",
            "type":"Services"
        },
        {
            "category":"Real Estate",
            "subcategory":"Real Estate Services",
            "type":"Services"
        }
    ],
    "sg:phone":"+1 816 347 8429",
    "sg:postcode":"64086",
    "sg:province":"MO",
    "sg:tags":[
        "company",
        "carrier"
    ],
    "wof:name":"Chicago Title Co",
    "wof:placetype":"venue"
},
  "geometry": {"coordinates":[-94.359003,38.937986],"type":"Point"}
}