{
  "type": "Feature",
  "properties": {
    "addr:full":"521 W Karsch Blvd Farmington MO 63640",
    "addr:housenumber":"521",
    "addr:postcode":"63640",
    "addr:street":"W Karsch Blvd",
    "iso:country":"US",
    "sg:address":"521 W Karsch Blvd",
    "sg:city":"Farmington",
    "sg:classifiers":[
        {
            "category":"Restaurant",
            "type":"Food & Drink"
        }
    ],
    "sg:menulink":"http://www.allmenus.com/mo/st-francois/190908-burger-king/menu/",
    "sg:phone":"+1 314 756 6947",
    "sg:postcode":"63640",
    "sg:province":"MO",
    "sg:tags":[
        "burger",
        "american"
    ],
    "wof:name":"Burger King",
    "wof:placetype":"venue"
},
  "geometry": {"coordinates":[-90.431515,37.790056],"type":"Point"}
}