{
  "type": "Feature",
  "properties": {
    "iso:country":"US",
    "sg:address":"9107 Vaughn Ave",
    "sg:city":"Raytown",
    "sg:classifiers":[
        {
            "category":"Professional",
            "subcategory":"Business Services",
            "type":"Services"
        }
    ],
    "sg:phone":"+1 816 358 1503",
    "sg:postcode":"64133",
    "sg:province":"MO",
    "sg:tags":[
        "consultant",
        "coach"
    ],
    "wof:name":"Vaitl Consulting",
    "wof:placetype":"venue"
},
  "geometry": {"coordinates":[-94.478553,38.988182],"type":"Point"}
}