{
  "type": "Feature",
  "properties": {
    "iso:country":"US",
    "sg:address":"2141 Barrett Station Rd",
    "sg:city":"St Louis",
    "sg:classifiers":[
        {
            "category":"Personal",
            "subcategory":"Beauty Salon",
            "type":"Services"
        }
    ],
    "sg:phone":"+1 314 909 7721",
    "sg:postcode":"63131",
    "sg:province":"MO",
    "sg:tags":[
        "shop",
        "manicuring"
    ],
    "wof:name":"Nail Expo",
    "wof:placetype":"venue"
},
  "geometry": {"coordinates":[-90.474056,38.598579],"type":"Point"}
}