{
  "type": "Feature",
  "properties": {
    "iso:country":"US",
    "sg:address":"3561 S Davies Ct",
    "sg:city":"Springfield",
    "sg:classifiers":[
        {
            "category":"Wholesale",
            "subcategory":"Durable Goods & Equipment",
            "type":"Manufacturing & Wholesale Goods"
        }
    ],
    "sg:phone":"+1 417 886 6683",
    "sg:postcode":"65807",
    "sg:province":"MO",
    "wof:name":"Digiden",
    "wof:placetype":"venue"
},
  "geometry": {"coordinates":[-93.3262,37.149602],"type":"Point"}
}