{
  "type": "Feature",
  "properties": {
    "iso:country":"US",
    "sg:address":"1757 Old Highway 94 South",
    "sg:city":"St. Charles",
    "sg:classifiers":[
        {
            "category":"Professional",
            "subcategory":"Computer Services",
            "type":"Services"
        }
    ],
    "sg:phone":"+1 636 925 0770",
    "sg:postcode":"63303",
    "sg:province":"MO",
    "sg:tags":[
        "graphic-design",
        "artwork",
        "illustrations",
        "logos",
        "digital-scrapbooking",
        "marketplace",
        "sell-art",
        "buy-art"
    ],
    "sg:website":"http://graphicleftovers.com",
    "wof:name":"Graphic Leftovers",
    "wof:placetype":"venue"
},
  "geometry": {"coordinates":[-90.58100899999999,38.74489],"type":"Point"}
}