{
  "type": "Feature",
  "properties": {
    "iso:country":"US",
    "sg:address":"200 SE 2 St",
    "sg:city":"Lees Summit",
    "sg:classifiers":[
        {
            "category":"Professional",
            "subcategory":"Lawyer & Legal Services",
            "type":"Services"
        }
    ],
    "sg:phone":"+1 816 525 2400",
    "sg:postcode":"64063",
    "sg:province":"MO",
    "sg:tags":[
        "attorney"
    ],
    "wof:name":"Hugh H Ryan Law Office",
    "wof:placetype":"venue"
},
  "geometry": {"coordinates":[-94.374245,38.915268],"type":"Point"}
}