{
  "type": "Feature",
  "properties": {
    "iso:country":"US",
    "sg:address":"4008 Wicks Rd",
    "sg:city":"Arnold",
    "sg:classifiers":[
        {
            "category":"Personal",
            "subcategory":"Beauty Salon",
            "type":"Services"
        }
    ],
    "sg:phone":"+1 636 464 0855",
    "sg:postcode":"63010",
    "sg:province":"MO",
    "sg:tags":[
        "shop"
    ],
    "wof:name":"Posh Hair & Nail Studio Inc",
    "wof:placetype":"venue"
},
  "geometry": {"coordinates":[-90.362647,38.405731],"type":"Point"}
}