{
  "type": "Feature",
  "properties": {
    "iso:country":"US",
    "sg:address":"101 Riverside Dr",
    "sg:city":"New Madrid",
    "sg:classifiers":[
        {
            "category":"Personal",
            "subcategory":"Beauty Salon",
            "type":"Services"
        }
    ],
    "sg:phone":"+1 573 748 2040",
    "sg:postcode":"63869",
    "sg:province":"MO",
    "wof:name":"Catresa Beauty Shop",
    "wof:placetype":"venue"
},
  "geometry": {"coordinates":[-89.55155499999999,36.58339],"type":"Point"}
}