{
  "type": "Feature",
  "properties": {
    "iso:country":"US",
    "sg:address":"1145 N College Dr",
    "sg:city":"Maryville",
    "sg:classifiers":[
        {
            "category":"Real Estate",
            "subcategory":"Real Estate Operator",
            "type":"Services"
        }
    ],
    "sg:phone":"+1 660 582 3927",
    "sg:postcode":"64468",
    "sg:province":"MO",
    "sg:tags":[
        "building",
        "apartment"
    ],
    "wof:name":"Northridge Apartments",
    "wof:placetype":"venue"
},
  "geometry": {"coordinates":[-94.882644,40.355964],"type":"Point"}
}