{
  "type": "Feature",
  "properties": {
    "iso:country":"US",
    "sg:address":"427 2nd St",
    "sg:city":"Winfield",
    "sg:classifiers":[
        {
            "category":"Retail",
            "subcategory":"Auto Repair",
            "type":"Services"
        }
    ],
    "sg:phone":"+1 636 668 8062",
    "sg:postcode":"63389",
    "sg:province":"MO",
    "sg:tags":[
        "general"
    ],
    "wof:name":"Counts Muffler & Brakes",
    "wof:placetype":"venue"
},
  "geometry": {"coordinates":[-90.739642,38.997893],"type":"Point"}
}