{
  "type": "Feature",
  "properties": {
    "iso:country":"US",
    "sg:address":"5130 Manchester Ave",
    "sg:city":"St Louis",
    "sg:classifiers":[
        {
            "category":"Wholesale",
            "subcategory":"Construction Materials",
            "type":"Manufacturing & Wholesale Goods"
        },
        {
            "category":"Home & Garden",
            "subcategory":"Building Materials",
            "type":"Retail Goods"
        }
    ],
    "sg:phone":"+1 314 645 4640",
    "sg:postcode":"63110",
    "sg:province":"MO",
    "sg:tags":[
        "roofing"
    ],
    "sg:website":"www.crowncsupply.com",
    "wof:name":"Crown C Supply Company Inc",
    "wof:placetype":"venue"
},
  "geometry": {"coordinates":[-90.275569,38.623831],"type":"Point"}
}