{
  "type": "Feature",
  "properties": {
    "addr:full":"2009 Ely St Kennett MO 63857",
    "addr:housenumber":"2009",
    "addr:postcode":"63857",
    "addr:street":"Ely St",
    "iso:country":"US",
    "sg:address":"2009 Ely St",
    "sg:city":"Kennett",
    "sg:classifiers":[
        {
            "category":"Organizations",
            "subcategory":"Religious Organization",
            "type":"Services"
        }
    ],
    "sg:phone":"+1 573 888 6505",
    "sg:postcode":"63857",
    "sg:province":"MO",
    "sg:tags":[
        "church"
    ],
    "wof:name":"Jehovah's Witnesses Kingdom",
    "wof:placetype":"venue"
},
  "geometry": {"coordinates":[-90.030041,36.251171],"type":"Point"}
}