{
  "type": "Feature",
  "properties": {
    "iso:country":"US",
    "sg:address":"4518 Lee Ave",
    "sg:city":"St Louis",
    "sg:classifiers":[
        {
            "category":"Real Estate",
            "subcategory":"Real Estate Agent",
            "type":"Services"
        }
    ],
    "sg:phone":"+1 314 389 1911",
    "sg:postcode":"63115",
    "sg:province":"MO",
    "wof:name":"Crenshaw Enterprises",
    "wof:placetype":"venue"
},
  "geometry": {"coordinates":[-90.23761500000001,38.676323],"type":"Point"}
}