{
  "type": "Feature",
  "properties": {
    "iso:country":"US",
    "sg:address":"8015 Fawn Ct",
    "sg:city":"Saint Louis",
    "sg:classifiers":[
        {
            "category":"Organizations",
            "subcategory":"Religious Organization",
            "type":"Services"
        }
    ],
    "sg:phone":"+1 314 647 9548",
    "sg:postcode":"63144",
    "sg:province":"MO",
    "wof:name":"Episcopal Church",
    "wof:placetype":"venue"
},
  "geometry": {"coordinates":[-90.33540499999999,38.613166],"type":"Point"}
}