{
  "type": "Feature",
  "properties": {
    "iso:country":"US",
    "sg:address":"533 Jefferson St",
    "sg:city":"St Charles",
    "sg:classifiers":[
        {
            "category":"Health Services",
            "subcategory":"Doctor",
            "type":"Services"
        }
    ],
    "sg:phone":"+1 636 723 5116",
    "sg:postcode":"63301",
    "sg:province":"MO",
    "sg:tags":[
        "physician",
        "surgeon"
    ],
    "wof:name":"Gene P Roxas MD",
    "wof:placetype":"venue"
},
  "geometry": {"coordinates":[-90.48624599999999,38.782674],"type":"Point"}
}