{
  "type": "Feature",
  "properties": {
    "iso:country":"US",
    "sg:address":"3639 Dover Pl",
    "sg:city":"St Louis",
    "sg:classifiers":[
        {
            "category":"Shopping",
            "subcategory":"Florist",
            "type":"Retail Goods"
        }
    ],
    "sg:phone":"+1 314 481 5509",
    "sg:postcode":"63116",
    "sg:province":"MO",
    "wof:name":"Floral Jaz",
    "wof:placetype":"venue"
},
  "geometry": {"coordinates":[-90.258324,38.568033],"type":"Point"}
}