{
  "type": "Feature",
  "properties": {
    "iso:country":"US",
    "sg:address":"12134 Blue Ridge Exd",
    "sg:city":"Grandview",
    "sg:classifiers":[
        {
            "category":"Health Services",
            "subcategory":"Clinic",
            "type":"Services"
        }
    ],
    "sg:phone":"+1 816 728 2287",
    "sg:postcode":"64030",
    "sg:province":"MO",
    "sg:tags":[
        "nutrition"
    ],
    "wof:name":"Nutrition & Child Services",
    "wof:placetype":"venue"
},
  "geometry": {"coordinates":[-94.52681800000001,38.906436],"type":"Point"}
}