{
  "type": "Feature",
  "properties": {
    "iso:country":"US",
    "sg:address":"215 Woodbury Dr",
    "sg:city":"Grain Valley",
    "sg:classifiers":[
        {
            "category":"Building & Trades",
            "subcategory":"Construction",
            "type":"Services"
        }
    ],
    "sg:phone":"+1 816 228 8466",
    "sg:postcode":"64029",
    "sg:province":"MO",
    "sg:tags":[
        "contractor"
    ],
    "wof:name":"J N L Construction Co Inc",
    "wof:placetype":"venue"
},
  "geometry": {"coordinates":[-94.19925600000001,39.025982],"type":"Point"}
}