{
  "type": "Feature",
  "properties": {
    "iso:country":"US",
    "sg:address":"607 N 22nd St",
    "sg:city":"Saint Louis",
    "sg:classifiers":[
        {
            "category":"Social Services",
            "subcategory":"Child Care",
            "type":"Services"
        },
        {
            "category":"Education",
            "subcategory":"Preschool",
            "type":"Public Place"
        }
    ],
    "sg:phone":"+1 314 621 1131",
    "sg:postcode":"63103",
    "sg:province":"MO",
    "sg:tags":[
        "day"
    ],
    "sg:website":"www.dccstl.org",
    "wof:name":"Downtown Children's Center",
    "wof:placetype":"venue"
},
  "geometry": {"coordinates":[-90.210683,38.634709],"type":"Point"}
}