{
  "type": "Feature",
  "properties": {
    "iso:country":"US",
    "sg:address":"201 S Cherry St",
    "sg:city":"Keytesville",
    "sg:classifiers":[
        {
            "category":"Professional",
            "subcategory":"Lawyer & Legal Services",
            "type":"Services"
        }
    ],
    "sg:phone":"+1 660 288 3647",
    "sg:postcode":"65261",
    "sg:province":"MO",
    "sg:tags":[
        "attorney"
    ],
    "wof:name":"Dale L Linneman Law Office",
    "wof:placetype":"venue"
},
  "geometry": {"coordinates":[-92.941531,39.433952],"type":"Point"}
}