{
  "type": "Feature",
  "properties": {
    "iso:country":"US",
    "sg:address":"5700 Dutch Creek Rd",
    "sg:city":"Cedar Hill",
    "sg:classifiers":[
        {
            "category":"Building & Trades",
            "subcategory":"Construction",
            "type":"Services"
        }
    ],
    "sg:phone":"+1 636 274 5701",
    "sg:postcode":"63016",
    "sg:province":"MO",
    "sg:tags":[
        "gen",
        "contractor"
    ],
    "wof:name":"Dace Homes Inc",
    "wof:placetype":"venue"
},
  "geometry": {"coordinates":[-90.66620899999999,38.3697],"type":"Point"}
}