{
  "type": "Feature",
  "properties": {
    "iso:country":"US",
    "sg:address":"1309 Summerhawk Ln",
    "sg:city":"Fenton",
    "sg:classifiers":[
        {
            "category":"Building & Trades",
            "subcategory":"Construction",
            "type":"Services"
        }
    ],
    "sg:phone":"+1 636 225 7343",
    "sg:postcode":"63026",
    "sg:province":"MO",
    "sg:tags":[
        "repair",
        "handyman",
        "maintenance",
        "home"
    ],
    "wof:name":"Hellwigs Handymen",
    "wof:placetype":"venue"
},
  "geometry": {"coordinates":[-90.50029000000001,38.515003],"type":"Point"}
}