{
  "type": "Feature",
  "properties": {
    "iso:country":"US",
    "sg:address":"1508 Geronimo Dr",
    "sg:city":"Independence",
    "sg:classifiers":[
        {
            "category":"Organizations",
            "subcategory":"Religious Organization",
            "type":"Services"
        }
    ],
    "sg:phone":"+1 816 796 8198",
    "sg:postcode":"64058",
    "sg:province":"MO",
    "sg:tags":[
        "church"
    ],
    "wof:name":"Church Of The First Born In",
    "wof:placetype":"venue"
},
  "geometry": {"coordinates":[-94.35811099999999,39.128932],"type":"Point"}
}