{
  "type": "Feature",
  "properties": {
    "iso:country":"US",
    "sg:address":"1917 William St",
    "sg:city":"Cape Girardeau",
    "sg:classifiers":[
        {
            "category":"Freight",
            "type":"Transportation"
        }
    ],
    "sg:phone":"+1 573 334 7616",
    "sg:postcode":"63703",
    "sg:province":"MO",
    "sg:tags":[
        "operator",
        "trucking"
    ],
    "wof:name":"Retail Trucking",
    "wof:placetype":"venue"
},
  "geometry": {"coordinates":[-89.544926,37.302647],"type":"Point"}
}