{
  "type": "Feature",
  "properties": {
    "iso:country":"US",
    "sg:address":"3009 N Ballas Rd",
    "sg:city":"Saint Louis",
    "sg:classifiers":[
        {
            "category":"Health Services",
            "subcategory":"Doctor",
            "type":"Services"
        }
    ],
    "sg:phone":"+1 314 432 2880",
    "sg:postcode":"63131",
    "sg:province":"MO",
    "sg:tags":[
        "medical"
    ],
    "wof:name":"Saint Ann Ob Gyn",
    "wof:placetype":"venue"
},
  "geometry": {"coordinates":[-90.44364,38.63163],"type":"Point"}
}