{
  "type": "Feature",
  "properties": {
    "iso:country":"US",
    "sg:address":"12442 N Highway 51",
    "sg:city":"Perryville",
    "sg:classifiers":[
        {
            "category":"Autos & Motor Vehicles",
            "subcategory":"Fuel & Gas Station",
            "type":"Retail Goods"
        },
        {
            "category":"Food & Beverages",
            "subcategory":"Groceries & Convenience Stores",
            "type":"Retail Goods"
        }
    ],
    "sg:phone":"+1 573 543 2740",
    "sg:postcode":"63775",
    "sg:province":"MO",
    "wof:name":"Fisca Oil Co Inc",
    "wof:placetype":"venue"
},
  "geometry": {"coordinates":[-89.842583,37.895547],"type":"Point"}
}