{
  "type": "Feature",
  "properties": {
    "iso:country":"US",
    "sg:address":"101 S Main St",
    "sg:city":"Kennett",
    "sg:classifiers":[
        {
            "category":"Professional",
            "subcategory":"Management & Consulting",
            "type":"Services"
        }
    ],
    "sg:phone":"+1 573 888 4722",
    "sg:postcode":"63857",
    "sg:province":"MO",
    "sg:tags":[
        "agricultural",
        "consultant"
    ],
    "sg:website":"http://www.umsl.edu",
    "wof:name":"Missouri Co Op Extension",
    "wof:placetype":"venue"
},
  "geometry": {"coordinates":[-90.05682400000001,36.236691],"type":"Point"}
}