{
  "type": "Feature",
  "properties": {
    "iso:country":"US",
    "sg:address":"6167 Delmar Blvd",
    "sg:city":"Saint Louis",
    "sg:classifiers":[
        {
            "category":"Shopping",
            "subcategory":"Clothing, Apparel, & Fashions",
            "type":"Retail Goods"
        }
    ],
    "sg:phone":"+1 314 725 7313",
    "sg:postcode":"63112",
    "sg:province":"MO",
    "sg:tags":[
        "accessory",
        "clothing",
        "women's"
    ],
    "wof:name":"Peses Ladies Boutique",
    "wof:placetype":"venue"
},
  "geometry": {"coordinates":[-90.297401,38.655102],"type":"Point"}
}