{
  "type": "Feature",
  "properties": {
    "iso:country":"US",
    "sg:address":"533 SW 150th Rd",
    "sg:city":"Centerview",
    "sg:phone":"+1 660 656 3641",
    "sg:postcode":"64019",
    "sg:province":"MO",
    "sg:tags":[
        "oil"
    ],
    "wof:name":"Alternative Fuel Source Inc",
    "wof:placetype":"venue"
},
  "geometry": {"coordinates":[-93.851011,38.742251],"type":"Point"}
}