{
  "type": "Feature",
  "properties": {
    "iso:country":"US",
    "sg:address":"2340 Rusmar St",
    "sg:city":"Cape Girardeau",
    "sg:classifiers":[
        {
            "category":"Wholesale",
            "subcategory":"Construction Materials",
            "type":"Manufacturing & Wholesale Goods"
        }
    ],
    "sg:phone":"+1 573 335 7222",
    "sg:postcode":"63703",
    "sg:province":"MO",
    "sg:tags":[
        "carpentry",
        "contractor"
    ],
    "wof:name":"ABC",
    "wof:placetype":"venue"
},
  "geometry": {"coordinates":[-89.55256,37.287295],"type":"Point"}
}