{
  "type": "Feature",
  "properties": {
    "iso:country":"US",
    "sg:address":"1131 E Main St",
    "sg:city":"Linn",
    "sg:classifiers":[
        {
            "category":"Restaurant",
            "type":"Food & Drink"
        }
    ],
    "sg:phone":"+1 573 897 4088",
    "sg:postcode":"65051",
    "sg:province":"MO",
    "wof:name":"Vallarta Mexican Restaurant",
    "wof:placetype":"venue"
},
  "geometry": {"coordinates":[-91.839603,38.477182],"type":"Point"}
}