{
  "type": "Feature",
  "properties": {
    "iso:country":"US",
    "sg:address":"3516 Imperial Hills Dr",
    "sg:city":"Imperial",
    "sg:classifiers":[
        {
            "category":"Professional",
            "subcategory":"Computer Services",
            "type":"Services"
        }
    ],
    "sg:phone":"+1 314 308 2266",
    "sg:postcode":"63052",
    "sg:province":"MO",
    "sg:tags":[
        "information",
        "technology"
    ],
    "wof:name":"Software Testing & Tools Inc",
    "wof:placetype":"venue"
},
  "geometry": {"coordinates":[-90.46116600000001,38.371314],"type":"Point"}
}