{
  "type": "Feature",
  "properties": {
    "iso:country":"US",
    "sg:address":"135 Courtfield Dr",
    "sg:city":"O Fallon",
    "sg:classifiers":[
        {
            "category":"Building & Trades",
            "subcategory":"Landscaping Services",
            "type":"Services"
        }
    ],
    "sg:phone":"+1 636 978 6575",
    "sg:postcode":"63366",
    "sg:province":"MO",
    "wof:name":"Off Duty Lawn Care LLC",
    "wof:placetype":"venue"
},
  "geometry": {"coordinates":[-90.695835,38.834455],"type":"Point"}
}