{
  "type": "Feature",
  "properties": {
    "iso:country":"US",
    "sg:address":"204 S Broadway St",
    "sg:city":"Princeton",
    "sg:classifiers":[
        {
            "category":"Government",
            "subcategory":"Post Office",
            "type":"Public Place"
        }
    ],
    "sg:phone":"+1 660 748 4245",
    "sg:postcode":"64673",
    "sg:province":"MO",
    "wof:name":"US Post Office",
    "wof:placetype":"venue"
},
  "geometry": {"coordinates":[-93.586229,40.396517],"type":"Point"}
}