{
  "type": "Feature",
  "properties": {
    "iso:country":"US",
    "sg:address":"801 N 2nd St",
    "sg:city":"St Louis",
    "sg:classifiers":[
        {
            "category":"Professional",
            "type":"Services"
        },
        {
            "category":"Professional",
            "subcategory":"Management & Consulting",
            "type":"Services"
        }
    ],
    "sg:phone":"+1 314 621 8140",
    "sg:postcode":"63102",
    "sg:province":"MO",
    "sg:tags":[
        "consultant"
    ],
    "wof:name":"Weaver Boos Consultants",
    "wof:placetype":"venue"
},
  "geometry": {"coordinates":[-90.184308,38.631389],"type":"Point"}
}