{
  "type": "Feature",
  "properties": {
    "iso:country":"US",
    "sg:address":"1001 Golden Dr",
    "sg:city":"Clinton",
    "sg:phone":"+1 660 885 8151",
    "sg:postcode":"64735",
    "sg:province":"MO",
    "sg:tags":[
        "product",
        "petroleum"
    ],
    "sg:website":"www.championbrands.com",
    "wof:name":"Champion Brands LLC",
    "wof:placetype":"venue"
},
  "geometry": {"coordinates":[-93.76565100000001,38.383056],"type":"Point"}
}