{
  "type": "Feature",
  "properties": {
    "iso:country":"US",
    "sg:address":"3606 NE 50 St",
    "sg:city":"Kansas City",
    "sg:classifiers":[
        {
            "category":"Professional",
            "subcategory":"Computer Services",
            "type":"Services"
        }
    ],
    "sg:phone":"+1 816 455 8000",
    "sg:postcode":"64119",
    "sg:province":"MO",
    "sg:tags":[
        "related",
        "programing",
        "custom"
    ],
    "sg:website":"www.ibenterprises.com",
    "wof:name":"I B Enterprises",
    "wof:placetype":"venue"
},
  "geometry": {"coordinates":[-94.537183,39.185159],"type":"Point"}
}