{
  "type": "Feature",
  "properties": {
    "iso:country":"US",
    "sg:address":"2001 Corona Rd Ste 201",
    "sg:city":"Columbia",
    "sg:classifiers":[
        {
            "category":"Food & Beverages",
            "subcategory":"Liquor & Beverages",
            "type":"Retail Goods"
        },
        {
            "category":"Wholesale",
            "subcategory":"Wine & Distilled Alcoholic Beverages",
            "type":"Manufacturing & Wholesale Goods"
        }
    ],
    "sg:phone":"+1 573 447 5637",
    "sg:postcode":"65203",
    "sg:province":"MO",
    "sg:tags":[
        "broker",
        "store"
    ],
    "wof:name":"Joe's Wine & Spirits",
    "wof:placetype":"venue"
},
  "geometry": {"coordinates":[-92.398712,38.93359],"type":"Point"}
}