{
  "type": "Feature",
  "properties": {
    "iso:country":"US",
    "sg:address":"722 N 5th St",
    "sg:city":"Festus",
    "sg:classifiers":[
        {
            "category":"Real Estate",
            "subcategory":"Real Estate Agent",
            "type":"Services"
        }
    ],
    "sg:phone":"+1 636 931 0666",
    "sg:postcode":"63028",
    "sg:province":"MO",
    "sg:tags":[
        "finding",
        "apartment",
        "rental"
    ],
    "wof:name":"Laiben Investment Properties",
    "wof:placetype":"venue"
},
  "geometry": {"coordinates":[-90.400012,38.224013],"type":"Point"}
}