{
  "type": "Feature",
  "properties": {
    "iso:country":"US",
    "sg:address":"84 Co Rd 100",
    "sg:city":"Saint Charles",
    "sg:classifiers":[
        {
            "category":"Professional",
            "subcategory":"Engineering",
            "type":"Services"
        }
    ],
    "sg:phone":"+1 636 498 6400",
    "sg:postcode":"63333",
    "sg:province":"MO",
    "wof:name":"Clayton Engineering Co",
    "wof:placetype":"venue"
},
  "geometry": {"coordinates":[-91.315963,39.060466],"type":"Point"}
}