{
  "type": "Feature",
  "properties": {
    "iso:country":"US",
    "sg:address":"104 1/2 E Main St",
    "sg:city":"Branson",
    "sg:classifiers":[
        {
            "category":"Travel",
            "subcategory":"Hotels & Motels",
            "type":"Entertainment"
        }
    ],
    "sg:phone":"+1 417 335 8443",
    "sg:postcode":"65616",
    "sg:province":"MO",
    "wof:name":"Roark Vacation Resort",
    "wof:placetype":"venue"
},
  "geometry": {"coordinates":[-93.216953,36.644138],"type":"Point"}
}