{
  "type": "Feature",
  "properties": {
    "iso:country":"US",
    "sg:address":"2535 W Blossom Dr",
    "sg:city":"Springfield",
    "sg:classifiers":[
        {
            "category":"Professional",
            "subcategory":"Art Services",
            "type":"Services"
        }
    ],
    "sg:phone":"+1 417 890 7200",
    "sg:postcode":"65810",
    "sg:province":"MO",
    "sg:tags":[
        "commercial",
        "design"
    ],
    "wof:name":"Logos & Layouts",
    "wof:placetype":"venue"
},
  "geometry": {"coordinates":[-93.330001,37.112434],"type":"Point"}
}