{
  "type": "Feature",
  "properties": {
    "iso:country":"US",
    "sg:address":"408 N Jefferson St",
    "sg:city":"Mexico",
    "sg:classifiers":[
        {
            "category":"Social Services",
            "subcategory":"Child Care",
            "type":"Services"
        }
    ],
    "sg:phone":"+1 573 581 0900",
    "sg:postcode":"65265",
    "sg:province":"MO",
    "wof:name":"Bright Beginnings Child Care",
    "wof:placetype":"venue"
},
  "geometry": {"coordinates":[-91.882423,39.175411],"type":"Point"}
}