{
  "type": "Feature",
  "properties": {
    "iso:country":"US",
    "sg:address":"1012 Allen Ave",
    "sg:city":"St Louis",
    "sg:classifiers":[
        {
            "category":"Professional",
            "type":"Services"
        }
    ],
    "sg:phone":"+1 314 664 9744",
    "sg:postcode":"63104",
    "sg:province":"MO",
    "sg:tags":[
        "establishment"
    ],
    "wof:name":"Roseman & Assoc",
    "wof:placetype":"venue"
},
  "geometry": {"coordinates":[-90.206284,38.60779],"type":"Point"}
}