{
  "type": "Feature",
  "properties": {
    "iso:country":"US",
    "sg:address":"1401 Armour Rd",
    "sg:city":"Kansas City",
    "sg:classifiers":[
        {
            "category":"Health Services",
            "subcategory":"Health Practitioner",
            "type":"Services"
        }
    ],
    "sg:phone":"+1 816 842 4890",
    "sg:postcode":"64116",
    "sg:province":"MO",
    "sg:tags":[
        "therapist",
        "physical"
    ],
    "wof:name":"Healthsouth",
    "wof:placetype":"venue"
},
  "geometry": {"coordinates":[-94.564374,39.144276],"type":"Point"}
}