{
  "type": "Feature",
  "properties": {
    "iso:country":"US",
    "sg:address":"1520 N Leffingwell Ave",
    "sg:city":"Saint Louis",
    "sg:classifiers":[
        {
            "category":"Organizations",
            "subcategory":"Religious Organization",
            "type":"Services"
        }
    ],
    "sg:phone":"+1 314 535 0232",
    "sg:postcode":"63106",
    "sg:province":"MO",
    "wof:name":"Training Center For Service Inc",
    "wof:placetype":"venue"
},
  "geometry": {"coordinates":[-90.215896,38.646093],"type":"Point"}
}