{
  "type": "Feature",
  "properties": {
    "iso:country":"US",
    "sg:address":"170 Ste Genevieve Dr",
    "sg:city":"Ste Genevieve",
    "sg:classifiers":[
        {
            "category":"Banks & Credit Unions",
            "subcategory":"Bank",
            "type":"Services"
        }
    ],
    "sg:phone":"+1 573 883 9872",
    "sg:postcode":"63670",
    "sg:province":"MO",
    "wof:name":"Bank Of Bloomsdale",
    "wof:placetype":"venue"
},
  "geometry": {"coordinates":[-90.03848600000001,37.967238],"type":"Point"}
}