{
  "type": "Feature",
  "properties": {
    "iso:country":"US",
    "sg:address":"7200 Eastwood Trfy",
    "sg:city":"Kansas City",
    "sg:classifiers":[
        {
            "category":"Restaurant",
            "type":"Food & Drink"
        }
    ],
    "sg:phone":"+1 816 921 3839",
    "sg:postcode":"64129",
    "sg:province":"MO",
    "sg:tags":[
        "fast"
    ],
    "wof:name":"KFC",
    "wof:placetype":"venue"
},
  "geometry": {"coordinates":[-94.50137599999999,39.031137],"type":"Point"}
}