{
  "type": "Feature",
  "properties": {
    "iso:country":"US",
    "sg:address":"27423 Old Swiss Rd",
    "sg:city":"California",
    "sg:classifiers":[
        {
            "category":"Wholesale",
            "subcategory":"Vending Machines",
            "type":"Manufacturing & Wholesale Goods"
        }
    ],
    "sg:phone":"+1 573 796 3961",
    "sg:postcode":"65018",
    "sg:province":"MO",
    "sg:tags":[
        "operator"
    ],
    "wof:name":"Sweet Bits Vending",
    "wof:placetype":"venue"
},
  "geometry": {"coordinates":[-92.560847,38.671724],"type":"Point"}
}