{
  "type": "Feature",
  "properties": {
    "iso:country":"US",
    "sg:address":"828 Salem Way",
    "sg:city":"Ellisville",
    "sg:classifiers":[
        {
            "category":"Building & Trades",
            "subcategory":"Construction",
            "type":"Services"
        }
    ],
    "sg:phone":"+1 636 227 7335",
    "sg:postcode":"63021",
    "sg:province":"MO",
    "sg:tags":[
        "wallcoverings-installation",
        "wallpaper",
        "painting",
        "contractor"
    ],
    "wof:name":"David C Fuhremann Painting Co",
    "wof:placetype":"venue"
},
  "geometry": {"coordinates":[-90.56550300000001,38.588982],"type":"Point"}
}