{
  "type": "Feature",
  "properties": {
    "iso:country":"US",
    "sg:address":"750 Fountain Lakes Blvd",
    "sg:city":"St Charles",
    "sg:classifiers":[
        {
            "category":"Professional",
            "subcategory":"Engineering",
            "type":"Services"
        },
        {
            "category":"Building & Trades",
            "subcategory":"Plumbing",
            "type":"Services"
        }
    ],
    "sg:phone":"+1 636 940 1056",
    "sg:postcode":"63301",
    "sg:province":"MO",
    "sg:tags":[
        "contractor",
        "mfg",
        "sheet",
        "engineer"
    ],
    "sg:website":"www.wiegmann.com",
    "wof:name":"Wiegmann & Associates Inc",
    "wof:placetype":"venue"
},
  "geometry": {"coordinates":[-90.52721,38.827169],"type":"Point"}
}