{
  "type": "Feature",
  "properties": {
    "iso:country":"US",
    "sg:address":"330 First Capitol Dr",
    "sg:city":"Saint Charles",
    "sg:classifiers":[
        {
            "category":"Health Services",
            "subcategory":"Doctor",
            "type":"Services"
        }
    ],
    "sg:phone":"+1 636 946 1650",
    "sg:postcode":"63301",
    "sg:province":"MO",
    "sg:tags":[
        "medical"
    ],
    "wof:name":"Calandrino Frank S Jr MD",
    "wof:placetype":"venue"
},
  "geometry": {"coordinates":[-90.485331,38.780699],"type":"Point"}
}