{
  "type": "Feature",
  "properties": {
    "iso:country":"US",
    "sg:address":"5212 County Road 2002",
    "sg:city":"Auxvasse",
    "sg:classifiers":[
        {
            "category":"Health Services",
            "subcategory":"Doctor",
            "type":"Services"
        }
    ],
    "sg:phone":"+1 573 592 4991",
    "sg:postcode":"65231",
    "sg:province":"MO",
    "sg:tags":[
        "physician",
        "surgeon"
    ],
    "wof:name":"Dr H Marcus Price Iii",
    "wof:placetype":"venue"
},
  "geometry": {"coordinates":[-91.95248100000001,39.051266],"type":"Point"}
}