{
  "type": "Feature",
  "properties": {
    "iso:country":"US",
    "sg:address":"3618 Hopper Rd",
    "sg:city":"Cape Girardeau",
    "sg:classifiers":[
        {
            "category":"Building & Trades",
            "subcategory":"Construction",
            "type":"Services"
        }
    ],
    "sg:phone":"+1 573 334 0117",
    "sg:postcode":"63701",
    "sg:province":"MO",
    "sg:tags":[
        "house"
    ],
    "wof:name":"Legrand Construction",
    "wof:placetype":"venue"
},
  "geometry": {"coordinates":[-89.58101000000001,37.320323],"type":"Point"}
}