{
  "type": "Feature",
  "properties": {
    "addr:full":"875 US Hwy 60 Monett MO 65708",
    "addr:housenumber":"875",
    "addr:postcode":"65708",
    "addr:street":"Us Hwy 60",
    "iso:country":"US",
    "sg:address":"875 US Hwy 60",
    "sg:city":"Monett",
    "sg:classifiers":[
        {
            "category":"Restaurant",
            "type":"Food & Drink"
        }
    ],
    "sg:phone":"+1 417 235 7380",
    "sg:postcode":"65708",
    "sg:province":"MO",
    "sg:tags":[
        "eating"
    ],
    "wof:name":"Burger King",
    "wof:placetype":"venue"
},
  "geometry": {"coordinates":[-93.947215,36.915786],"type":"Point"}
}