{
  "type": "Feature",
  "properties": {
    "iso:country":"US",
    "sg:address":"603 State Hwy 7",
    "sg:city":"Pleasant Hill",
    "sg:classifiers":[
        {
            "category":"Freight",
            "type":"Transportation"
        }
    ],
    "sg:phone":"+1 816 540 5514",
    "sg:postcode":"64080",
    "sg:province":"MO",
    "sg:tags":[
        "commercial",
        "storage"
    ],
    "wof:name":"Yoder Mini Storage",
    "wof:placetype":"venue"
},
  "geometry": {"coordinates":[-94.261978,38.792189],"type":"Point"}
}