{
  "type": "Feature",
  "properties": {
    "addr:full":"2020 State Highway J Malden MO 63863",
    "addr:housenumber":"2020",
    "addr:postcode":"63863",
    "addr:street":"State Highway J Malden",
    "iso:country":"US",
    "sg:address":"2020 State Highway J",
    "sg:city":"Malden",
    "sg:classifiers":[
        {
            "category":"Place Of Worship",
            "subcategory":"Church",
            "type":"Public Place"
        },
        {
            "category":"Place Of Worship",
            "type":"Public Place"
        }
    ],
    "sg:phone":"+1 573 276 2488",
    "sg:postcode":"63863",
    "sg:province":"MO",
    "sg:tags":[
        "testament",
        "christ-new",
        "churches-church",
        "christ"
    ],
    "wof:name":"Church Of Christ",
    "wof:placetype":"venue"
},
  "geometry": {"coordinates":[-89.98855500000001,36.564246],"type":"Point"}
}