{
  "type": "Feature",
  "properties": {
    "iso:country":"US",
    "sg:address":"502 W 103rd St",
    "sg:city":"Kansas City",
    "sg:classifiers":[
        {
            "category":"Personal",
            "subcategory":"Beauty Salon",
            "type":"Services"
        }
    ],
    "sg:phone":"+1 816 942 6850",
    "sg:postcode":"64114",
    "sg:province":"MO",
    "sg:tags":[
        "shop"
    ],
    "wof:name":"Premiere Beauty",
    "wof:placetype":"venue"
},
  "geometry": {"coordinates":[-94.600003,38.941759],"type":"Point"}
}