{
  "type": "Feature",
  "properties": {
    "iso:country":"US",
    "sg:address":"11603 Hickman Mills Dr",
    "sg:city":"Kansas City",
    "sg:classifiers":[
        {
            "category":"Wholesale",
            "subcategory":"Machinery & Supplies",
            "type":"Manufacturing & Wholesale Goods"
        }
    ],
    "sg:phone":"+1 816 761 7977",
    "sg:postcode":"64134",
    "sg:province":"MO",
    "sg:tags":[
        "equipment",
        "establishment"
    ],
    "wof:name":"Belzer Carpet & Uphl Clg Supp",
    "wof:placetype":"venue"
},
  "geometry": {"coordinates":[-94.52385599999999,38.912792],"type":"Point"}
}