{
  "type": "Feature",
  "properties": {
    "iso:country":"US",
    "sg:address":"9410 Laverne Pl",
    "sg:city":"Saint Louis",
    "sg:classifiers":[
        {
            "category":"Personal",
            "subcategory":"Beauty Salon",
            "type":"Services"
        }
    ],
    "sg:phone":"+1 314 534 0368",
    "sg:postcode":"63123",
    "sg:province":"MO",
    "sg:tags":[
        "shop"
    ],
    "wof:name":"Normas Personal Touch",
    "wof:placetype":"venue"
},
  "geometry": {"coordinates":[-90.32094499999999,38.551597],"type":"Point"}
}