{
  "type": "Feature",
  "properties": {
    "iso:country":"US",
    "sg:address":"217 NE Independence Ave",
    "sg:city":"Lees Summit",
    "sg:classifiers":[
        {
            "category":"Real Estate",
            "subcategory":"Real Estate Operator",
            "type":"Services"
        }
    ],
    "sg:phone":"+1 816 524 8222",
    "sg:postcode":"64063",
    "sg:province":"MO",
    "sg:tags":[
        "building",
        "apartment"
    ],
    "wof:name":"Summit East Plaza Apartments",
    "wof:placetype":"venue"
},
  "geometry": {"coordinates":[-94.36512500000001,38.920559],"type":"Point"}
}