{
  "type": "Feature",
  "properties": {
    "iso:country":"US",
    "sg:address":"852 W State St",
    "sg:city":"Union",
    "sg:classifiers":[
        {
            "category":"Freight",
            "type":"Transportation"
        }
    ],
    "sg:phone":"+1 636 584 8849",
    "sg:postcode":"63084",
    "sg:province":"MO",
    "sg:tags":[
        "operator",
        "local",
        "trucking"
    ],
    "wof:name":"D & D Hauling",
    "wof:placetype":"venue"
},
  "geometry": {"coordinates":[-91.018855,38.446769],"type":"Point"}
}