{
  "type": "Feature",
  "properties": {
    "iso:country":"US",
    "sg:address":"200 Clover Ln",
    "sg:city":"Portageville",
    "sg:classifiers":[
        {
            "category":"Farming",
            "subcategory":"Farm",
            "type":"Manufacturing & Wholesale Goods"
        }
    ],
    "sg:phone":"+1 573 379 3268",
    "sg:postcode":"63873",
    "sg:province":"MO",
    "sg:tags":[
        "crop",
        "general"
    ],
    "wof:name":"Underwood Farms",
    "wof:placetype":"venue"
},
  "geometry": {"coordinates":[-89.70087599999999,36.435991],"type":"Point"}
}