{
  "type": "Feature",
  "properties": {
    "iso:country":"US",
    "sg:address":"7777 NE Birmingham Rd",
    "sg:city":"Randolph",
    "sg:classifiers":[
        {
            "category":"Government",
            "subcategory":"Office",
            "type":"Public Place"
        }
    ],
    "sg:phone":"+1 816 455 9323",
    "sg:postcode":"64161",
    "sg:province":"MO",
    "sg:tags":[
        "village"
    ],
    "wof:name":"Randolph City Office",
    "wof:placetype":"venue"
},
  "geometry": {"coordinates":[-94.486868,39.154673],"type":"Point"}
}