{
  "type": "Feature",
  "properties": {
    "iso:country":"US",
    "sg:address":"1105 Washington St",
    "sg:city":"Hermann",
    "sg:classifiers":[
        {
            "category":"Building & Trades",
            "subcategory":"Landscaping Services",
            "type":"Services"
        }
    ],
    "sg:phone":"+1 573 486 2839",
    "sg:postcode":"65041",
    "sg:province":"MO",
    "sg:tags":[
        "landscape"
    ],
    "wof:name":"C J B",
    "wof:placetype":"venue"
},
  "geometry": {"coordinates":[-91.44323799999999,38.698473],"type":"Point"}
}