{
  "type": "Feature",
  "properties": {
    "iso:country":"US",
    "sg:address":"308 S Main St",
    "sg:city":"St Charles",
    "sg:classifiers":[
        {
            "category":"Shopping",
            "subcategory":"Books",
            "type":"Retail Goods"
        }
    ],
    "sg:phone":"+1 636 949 9502",
    "sg:postcode":"63301",
    "sg:province":"MO",
    "sg:tags":[
        "dealer"
    ],
    "wof:name":"Enchanted Attic",
    "wof:placetype":"venue"
},
  "geometry": {"coordinates":[-90.482578,38.778745],"type":"Point"}
}