{
  "type": "Feature",
  "properties": {
    "iso:country":"US",
    "sg:address":"129 State St",
    "sg:city":"Doniphan",
    "sg:classifiers":[
        {
            "category":"Real Estate",
            "subcategory":"Real Estate Services",
            "type":"Services"
        }
    ],
    "sg:phone":"+1 573 996 2907",
    "sg:postcode":"63935",
    "sg:province":"MO",
    "sg:tags":[
        "company",
        "abstract",
        "title"
    ],
    "wof:name":"Current River Abstract & Title",
    "wof:placetype":"venue"
},
  "geometry": {"coordinates":[-90.825717,36.618187],"type":"Point"}
}