{
  "type": "Feature",
  "properties": {
    "iso:country":"US",
    "sg:address":"230 S Bemiston Ave",
    "sg:city":"St Louis",
    "sg:classifiers":[
        {
            "category":"Health Services",
            "subcategory":"Health Practitioner",
            "type":"Services"
        }
    ],
    "sg:phone":"+1 314 725 9668",
    "sg:postcode":"63105",
    "sg:province":"MO",
    "sg:tags":[
        "psychotherapist"
    ],
    "wof:name":"Gil Marsh",
    "wof:placetype":"venue"
},
  "geometry": {"coordinates":[-90.33729599999999,38.646552],"type":"Point"}
}