{
  "type": "Feature",
  "properties": {
    "iso:country":"US",
    "sg:address":"2926 Dover St",
    "sg:city":"St Joseph",
    "sg:classifiers":[
        {
            "category":"Building & Trades",
            "subcategory":"Electrical",
            "type":"Services"
        }
    ],
    "sg:phone":"+1 816 233 3501",
    "sg:postcode":"64506",
    "sg:province":"MO",
    "sg:tags":[
        "electrical",
        "electric",
        "contractor"
    ],
    "wof:name":"Sprague Electrical Service",
    "wof:placetype":"venue"
},
  "geometry": {"coordinates":[-94.822118,39.818651],"type":"Point"}
}