{
  "type": "Feature",
  "properties": {
    "iso:country":"US",
    "sg:address":"4015 Lemay Ferry Rd",
    "sg:city":"St Louis",
    "sg:classifiers":[
        {
            "category":"Restaurant",
            "type":"Food & Drink"
        }
    ],
    "sg:phone":"+1 314 892 0550",
    "sg:postcode":"63129",
    "sg:province":"MO",
    "wof:name":"Mc Donald's",
    "wof:placetype":"venue"
},
  "geometry": {"coordinates":[-90.32817,38.504268],"type":"Point"}
}