{
  "type": "Feature",
  "properties": {
    "iso:country":"US",
    "sg:address":"2625 N Range Line Rd",
    "sg:city":"Webb City",
    "sg:classifiers":[
        {
            "category":"Retail",
            "subcategory":"Auto Repair",
            "type":"Services"
        }
    ],
    "sg:phone":"+1 417 623 5344",
    "sg:postcode":"64870",
    "sg:province":"MO",
    "sg:tags":[
        "repairing",
        "automotive",
        "radiator",
        "automobile"
    ],
    "wof:name":"Joplin Radiator Repair",
    "wof:placetype":"venue"
},
  "geometry": {"coordinates":[-94.475881,37.116097],"type":"Point"}
}