{
  "type": "Feature",
  "properties": {
    "iso:country":"US",
    "sg:address":"705 Highway K",
    "sg:city":"O Fallon",
    "sg:classifiers":[
        {
            "category":"Restaurant",
            "type":"Food & Drink"
        }
    ],
    "sg:menulink":"http://www.allmenus.com/mo/dardenne/210941-arbys/menu/",
    "sg:phone":"+1 636 240 1004",
    "sg:postcode":"63366",
    "sg:province":"MO",
    "sg:tags":[
        "burger",
        "american"
    ],
    "wof:name":"Arby's",
    "wof:placetype":"venue"
},
  "geometry": {"coordinates":[-90.700198,38.80146],"type":"Point"}
}