{
  "type": "Feature",
  "properties": {
    "iso:country":"US",
    "sg:address":"1724 W Mount Vernon St",
    "sg:city":"Springfield",
    "sg:classifiers":[
        {
            "category":"Manufacturing",
            "subcategory":"Pet Food",
            "type":"Manufacturing & Wholesale Goods"
        }
    ],
    "sg:phone":"+1 417 866 4366",
    "sg:postcode":"65802",
    "sg:province":"MO",
    "sg:tags":[
        "feed"
    ],
    "wof:name":"Naremco Inc",
    "wof:placetype":"venue"
},
  "geometry": {"coordinates":[-93.314408,37.20429],"type":"Point"}
}