{
  "type": "Feature",
  "properties": {
    "iso:country":"US",
    "sg:address":"16584 Manchester Rd",
    "sg:city":"Grover",
    "sg:classifiers":[
        {
            "category":"Restaurant",
            "type":"Food & Drink"
        }
    ],
    "sg:phone":"+1 636 273 4727",
    "sg:postcode":"63040",
    "sg:province":"MO",
    "sg:tags":[
        "eating"
    ],
    "wof:name":"Quiznos Classic Subs",
    "wof:placetype":"venue"
},
  "geometry": {"coordinates":[-90.62069,38.580232],"type":"Point"}
}