{
  "type": "Feature",
  "properties": {
    "iso:country":"US",
    "sg:address":"1416 SW 19 St",
    "sg:city":"Blue Springs",
    "sg:classifiers":[
        {
            "category":"Organizations",
            "subcategory":"Religious Organization",
            "type":"Services"
        }
    ],
    "sg:phone":"+1 816 229 4344",
    "sg:postcode":"64015",
    "sg:province":"MO",
    "wof:name":"Blue Springs First Ward",
    "wof:placetype":"venue"
},
  "geometry": {"coordinates":[-94.28685900000001,39.001952],"type":"Point"}
}