{
  "type": "Feature",
  "properties": {
    "iso:country":"US",
    "sg:address":"102 Morgan St",
    "sg:city":"Slater",
    "sg:classifiers":[
        {
            "category":"Wholesale",
            "subcategory":"Machinery & Supplies",
            "type":"Manufacturing & Wholesale Goods"
        }
    ],
    "sg:phone":"+1 660 529 2600",
    "sg:postcode":"65349",
    "sg:province":"MO",
    "sg:tags":[
        "pressure",
        "washing",
        "equipment"
    ],
    "wof:name":"Morpower",
    "wof:placetype":"venue"
},
  "geometry": {"coordinates":[-93.063498,39.218215],"type":"Point"}
}