{
  "type": "Feature",
  "properties": {
    "iso:country":"US",
    "sg:address":"2600 Oakland Ave",
    "sg:city":"Bethany",
    "sg:classifiers":[
        {
            "category":"Social Services",
            "subcategory":"Child Care",
            "type":"Services"
        }
    ],
    "sg:phone":"+1 660 425 3184",
    "sg:postcode":"64424",
    "sg:province":"MO",
    "sg:tags":[
        "nursery",
        "day"
    ],
    "wof:name":"Mcdaniel's Day Care",
    "wof:placetype":"venue"
},
  "geometry": {"coordinates":[-94.027151,40.271595],"type":"Point"}
}