{
  "type": "Feature",
  "properties": {
    "iso:country":"US",
    "sg:address":"7516 Mulberry Rd",
    "sg:city":"Barnhart",
    "sg:classifiers":[
        {
            "category":"Professional",
            "subcategory":"Business Services",
            "type":"Services"
        }
    ],
    "sg:phone":"+1 636 464 1998",
    "sg:postcode":"63012",
    "sg:province":"MO",
    "sg:tags":[
        "consumer",
        "list",
        "brokerage"
    ],
    "wof:name":"Crosslists Company Inc",
    "wof:placetype":"venue"
},
  "geometry": {"coordinates":[-90.390535,38.324872],"type":"Point"}
}