{
  "type": "Feature",
  "properties": {
    "iso:country":"US",
    "sg:address":"1984 Congressional Dr",
    "sg:city":"St Louis",
    "sg:classifiers":[
        {
            "category":"Home & Garden",
            "subcategory":"Building Materials",
            "type":"Retail Goods"
        },
        {
            "category":"Wholesale",
            "subcategory":"Home Furnishings",
            "type":"Manufacturing & Wholesale Goods"
        }
    ],
    "sg:phone":"+1 314 989 1110",
    "sg:postcode":"63146",
    "sg:province":"MO",
    "sg:tags":[
        "closet",
        "accessory"
    ],
    "wof:name":"Closets & Storage Concepts",
    "wof:placetype":"venue"
},
  "geometry": {"coordinates":[-90.43856100000001,38.69632],"type":"Point"}
}