{
  "type": "Feature",
  "properties": {
    "iso:country":"US",
    "sg:address":"19004 E 18 Ter N",
    "sg:city":"Independence",
    "sg:classifiers":[
        {
            "category":"Professional",
            "type":"Services"
        }
    ],
    "sg:phone":"+1 816 796 4200",
    "sg:postcode":"64058",
    "sg:province":"MO",
    "wof:name":"Dreamchasers",
    "wof:placetype":"venue"
},
  "geometry": {"coordinates":[-94.352818,39.135343],"type":"Point"}
}