{
  "type": "Feature",
  "properties": {
    "iso:country":"US",
    "sg:address":"191 S Lincoln St",
    "sg:city":"Wardell",
    "sg:classifiers":[
        {
            "category":"Personal",
            "subcategory":"Beauty Salon",
            "type":"Services"
        }
    ],
    "sg:phone":"+1 573 628 3449",
    "sg:postcode":"63879",
    "sg:province":"MO",
    "wof:name":"Nan's Anointed Hands Beauty",
    "wof:placetype":"venue"
},
  "geometry": {"coordinates":[-89.823464,36.330109],"type":"Point"}
}