{
  "type": "Feature",
  "properties": {
    "iso:country":"US",
    "sg:address":"514 N Fremont Ave",
    "sg:city":"Springfield",
    "sg:classifiers":[
        {
            "category":"Manufacturing",
            "subcategory":"Tools & Machinery",
            "type":"Manufacturing & Wholesale Goods"
        }
    ],
    "sg:phone":"+1 417 869 5344",
    "sg:postcode":"65802",
    "sg:province":"MO",
    "sg:tags":[
        "machine",
        "shop"
    ],
    "wof:name":"Yarbrough's Machine Shop Inc",
    "wof:placetype":"venue"
},
  "geometry": {"coordinates":[-93.270847,37.212658],"type":"Point"}
}