{
  "type": "Feature",
  "properties": {
    "iso:country":"US",
    "sg:address":"1703 E Liberty St",
    "sg:city":"Mexico",
    "sg:classifiers":[
        {
            "category":"Building & Trades",
            "subcategory":"Construction",
            "type":"Services"
        }
    ],
    "sg:phone":"+1 573 582 7459",
    "sg:postcode":"65265",
    "sg:province":"MO",
    "sg:tags":[
        "general",
        "contractor"
    ],
    "wof:name":"Mid Missouri Directional",
    "wof:placetype":"venue"
},
  "geometry": {"coordinates":[-91.86256400000001,39.166326],"type":"Point"}
}