{
  "type": "Feature",
  "properties": {
    "iso:country":"US",
    "sg:address":"203 E 2nd St",
    "sg:city":"Norborne",
    "sg:classifiers":[
        {
            "category":"Food & Beverages",
            "subcategory":"Groceries & Convenience Stores",
            "type":"Retail Goods"
        }
    ],
    "sg:phone":"+1 660 593 3423",
    "sg:postcode":"64668",
    "sg:province":"MO",
    "sg:tags":[
        "grocer"
    ],
    "wof:name":"Norborne Supermarket",
    "wof:placetype":"venue"
},
  "geometry": {"coordinates":[-93.675439,39.302808],"type":"Point"}
}