{
  "type": "Feature",
  "properties": {
    "iso:country":"US",
    "sg:address":"447 South Ave",
    "sg:city":"Springfield",
    "sg:classifiers":[
        {
            "category":"Professional",
            "subcategory":"Management & Consulting",
            "type":"Services"
        }
    ],
    "sg:phone":"+1 417 831 9100",
    "sg:postcode":"65806",
    "sg:province":"MO",
    "sg:tags":[
        "personnel",
        "consultant"
    ],
    "sg:website":"www.penmacinc.com",
    "wof:name":"Penmac Personnel Svc",
    "wof:placetype":"venue"
},
  "geometry": {"coordinates":[-93.292441,37.205622],"type":"Point"}
}