{
  "type": "Feature",
  "properties": {
    "iso:country":"US",
    "sg:address":"101 NE 115th St",
    "sg:city":"Kansas City",
    "sg:classifiers":[
        {
            "category":"Retail",
            "subcategory":"Repair Shop",
            "type":"Services"
        }
    ],
    "sg:phone":"+1 816 734 3987",
    "sg:postcode":"64155",
    "sg:province":"MO",
    "sg:tags":[
        "welding"
    ],
    "wof:name":"Advance Welder Repair",
    "wof:placetype":"venue"
},
  "geometry": {"coordinates":[-94.576734,39.302192],"type":"Point"}
}