{
  "type": "Feature",
  "properties": {
    "iso:country":"US",
    "sg:address":"684 Bayberry Ln",
    "sg:city":"Lees Summit",
    "sg:classifiers":[
        {
            "category":"Professional",
            "subcategory":"Lawyer & Legal Services",
            "type":"Services"
        }
    ],
    "sg:phone":"+1 816 525 1500",
    "sg:postcode":"64063",
    "sg:province":"MO",
    "sg:tags":[
        "attorney"
    ],
    "wof:name":"David M Lurie Law Ofc",
    "wof:placetype":"venue"
},
  "geometry": {"coordinates":[-94.359504,38.907434],"type":"Point"}
}