{
  "type": "Feature",
  "properties": {
    "iso:country":"US",
    "sg:address":"7169 NW Lingley Dr",
    "sg:city":"Kansas City",
    "sg:classifiers":[
        {
            "category":"Shopping",
            "subcategory":"Hobbies, Toys, & Games",
            "type":"Retail Goods"
        }
    ],
    "sg:phone":"+1 816 746 4695",
    "sg:postcode":"64152",
    "sg:province":"MO",
    "sg:tags":[
        "craft",
        "supply"
    ],
    "sg:website":"www.windyhillwoods.com",
    "wof:name":"Windy Hill Woods",
    "wof:placetype":"venue"
},
  "geometry": {"coordinates":[-94.679023,39.226335],"type":"Point"}
}