{
  "type": "Feature",
  "properties": {
    "iso:country":"US",
    "sg:address":"10041 Lackland Rd",
    "sg:city":"Overland",
    "sg:classifiers":[
        {
            "category":"Wholesale",
            "subcategory":"Meat",
            "type":"Manufacturing & Wholesale Goods"
        }
    ],
    "sg:phone":"+1 314 428 8405",
    "sg:postcode":"63114",
    "sg:province":"MO",
    "sg:tags":[
        "product"
    ],
    "wof:name":"Gateway Beef Coop",
    "wof:placetype":"venue"
},
  "geometry": {"coordinates":[-90.379206,38.695706],"type":"Point"}
}