{
  "type": "Feature",
  "properties": {
    "iso:country":"US",
    "sg:address":"41 Meier Rd",
    "sg:city":"Old Monroe",
    "sg:classifiers":[
        {
            "category":"Wholesale",
            "subcategory":"Medical Equipment & Supplies",
            "type":"Manufacturing & Wholesale Goods"
        }
    ],
    "sg:phone":"+1 636 566 8010",
    "sg:postcode":"63369",
    "sg:province":"MO",
    "wof:name":"Advantage Marketing",
    "wof:placetype":"venue"
},
  "geometry": {"coordinates":[-90.764199,38.99008],"type":"Point"}
}