{
  "type": "Feature",
  "properties": {
    "iso:country":"US",
    "sg:address":"23 White River Ln",
    "sg:city":"Defiance",
    "sg:classifiers":[
        {
            "category":"Shopping",
            "subcategory":"Bicycles & Sporting Goods",
            "type":"Retail Goods"
        }
    ],
    "sg:phone":"+1 636 828 4550",
    "sg:postcode":"63341",
    "sg:province":"MO",
    "wof:name":"Palivodas Guns",
    "wof:placetype":"venue"
},
  "geometry": {"coordinates":[-90.864289,38.678643],"type":"Point"}
}