{
  "type": "Feature",
  "properties": {
    "iso:country":"US",
    "sg:address":"205 Mccormick Rd",
    "sg:city":"Chillicothe",
    "sg:classifiers":[
        {
            "category":"Building & Trades",
            "subcategory":"Cleaning & Sanitation",
            "type":"Services"
        },
        {
            "category":"Wholesale",
            "subcategory":"Construction Materials",
            "type":"Manufacturing & Wholesale Goods"
        }
    ],
    "sg:phone":"+1 660 646 6355",
    "sg:postcode":"64601",
    "sg:province":"MO",
    "sg:tags":[
        "coatings-protective",
        "sandblasting"
    ],
    "wof:name":"Superior Coating Co",
    "wof:placetype":"venue"
},
  "geometry": {"coordinates":[-93.544484,39.777999],"type":"Point"}
}