{
  "type": "Feature",
  "properties": {
    "iso:country":"US",
    "sg:address":"4634 Leduc St",
    "sg:city":"Saint Louis",
    "sg:classifiers":[
        {
            "category":"Professional",
            "subcategory":"Accounting & Tax Preparation",
            "type":"Services"
        }
    ],
    "sg:phone":"+1 314 371 0407",
    "sg:postcode":"63113",
    "sg:province":"MO",
    "wof:name":"Tree Life Bookkeeping Service",
    "wof:placetype":"venue"
},
  "geometry": {"coordinates":[-90.251622,38.662375],"type":"Point"}
}