{
  "type": "Feature",
  "properties": {
    "iso:country":"US",
    "sg:address":"201 Center St",
    "sg:city":"Columbia",
    "sg:classifiers":[
        {
            "category":"Education",
            "subcategory":"College",
            "type":"Public Place"
        }
    ],
    "sg:phone":"+1 573 882 1657",
    "sg:postcode":"65261",
    "sg:province":"MO",
    "wof:name":"Umc Career Center",
    "wof:placetype":"venue"
},
  "geometry": {"coordinates":[-92.933701,39.429888],"type":"Point"}
}