{
  "type": "Feature",
  "properties": {
    "iso:country":"US",
    "sg:address":"302 W Church St",
    "sg:city":"Palmyra",
    "sg:classifiers":[
        {
            "category":"Building & Trades",
            "subcategory":"Cleaning & Sanitation",
            "type":"Services"
        }
    ],
    "sg:phone":"+1 573 769 6209",
    "sg:postcode":"63461",
    "sg:province":"MO",
    "sg:tags":[
        "maintenance"
    ],
    "wof:name":"Roberts Stacy & Billy",
    "wof:placetype":"venue"
},
  "geometry": {"coordinates":[-91.52663,39.797085],"type":"Point"}
}