{
  "type": "Feature",
  "properties": {
    "iso:country":"US",
    "sg:address":"1940 Washington Xing",
    "sg:city":"Washington",
    "sg:classifiers":[
        {
            "category":"Restaurant",
            "type":"Food & Drink"
        }
    ],
    "sg:menulink":"http://www.allmenus.com/mo/washington/190878-burger-king/menu/",
    "sg:phone":"+1 636 390 3939",
    "sg:postcode":"63090",
    "sg:province":"MO",
    "sg:tags":[
        "burger",
        "american"
    ],
    "wof:name":"Burger King",
    "wof:placetype":"venue"
},
  "geometry": {"coordinates":[-91.006669,38.53617],"type":"Point"}
}