{
  "type": "Feature",
  "properties": {
    "iso:country":"US",
    "sg:address":"543 NW State Hwy 131",
    "sg:city":"Holden",
    "sg:classifiers":[
        {
            "category":"Organizations",
            "subcategory":"Religious Organization",
            "type":"Services"
        }
    ],
    "sg:phone":"+1 816 732 4561",
    "sg:postcode":"64040",
    "sg:province":"MO",
    "wof:name":"Enon Baptist Church",
    "wof:placetype":"venue"
},
  "geometry": {"coordinates":[-93.99073199999999,38.847198],"type":"Point"}
}