{
  "type": "Feature",
  "properties": {
    "iso:country":"US",
    "sg:address":"413 W Harrison St",
    "sg:city":"Kirksville",
    "sg:classifiers":[
        {
            "category":"Wholesale",
            "subcategory":"Hardware",
            "type":"Manufacturing & Wholesale Goods"
        }
    ],
    "sg:phone":"+1 660 665 7211",
    "sg:postcode":"63501",
    "sg:province":"MO",
    "sg:tags":[
        "plumbing",
        "fixture",
        "supply"
    ],
    "wof:name":"Kirksville Plumbing Supply Co",
    "wof:placetype":"venue"
},
  "geometry": {"coordinates":[-92.58723000000001,40.195547],"type":"Point"}
}