{
  "type": "Feature",
  "properties": {
    "iso:country":"US",
    "sg:address":"949 Romaine Creek Rd",
    "sg:city":"Fenton",
    "sg:classifiers":[
        {
            "category":"Building & Trades",
            "subcategory":"Plumbing",
            "type":"Services"
        }
    ],
    "sg:phone":"+1 636 343 9999",
    "sg:postcode":"63026",
    "sg:province":"MO",
    "sg:tags":[
        "conditioning",
        "air",
        "system",
        "contractor"
    ],
    "wof:name":"Bennett Mechanical Services",
    "wof:placetype":"venue"
},
  "geometry": {"coordinates":[-90.44699900000001,38.466698],"type":"Point"}
}