{
  "type": "Feature",
  "properties": {
    "iso:country":"US",
    "sg:address":"4600 J C Nichols Pkwy",
    "sg:city":"Kansas City",
    "sg:classifiers":[
        {
            "category":"Professional",
            "subcategory":"Art Services",
            "type":"Services"
        }
    ],
    "sg:phone":"+1 816 756 5723",
    "sg:postcode":"64112",
    "sg:province":"MO",
    "sg:tags":[
        "commercial",
        "design"
    ],
    "wof:name":"Joseph Lorusso",
    "wof:placetype":"venue"
},
  "geometry": {"coordinates":[-94.588212,39.043186],"type":"Point"}
}