{
  "type": "Feature",
  "properties": {
    "iso:country":"US",
    "sg:address":"200 S Main St",
    "sg:city":"St Charles",
    "sg:classifiers":[
        {
            "category":"Government",
            "subcategory":"Office",
            "type":"Public Place"
        }
    ],
    "sg:phone":"+1 636 940 3322",
    "sg:postcode":"63301",
    "sg:province":"MO",
    "wof:name":"First MO State Capitol",
    "wof:placetype":"venue"
},
  "geometry": {"coordinates":[-90.48219,38.77963],"type":"Point"}
}