{
  "type": "Feature",
  "properties": {
    "iso:country":"US",
    "sg:address":"10405 Olney Dr",
    "sg:city":"Saint Louis",
    "sg:classifiers":[
        {
            "category":"Building & Trades",
            "subcategory":"Cleaning & Sanitation",
            "type":"Services"
        }
    ],
    "sg:phone":"+1 314 388 4660",
    "sg:postcode":"63136",
    "sg:province":"MO",
    "sg:tags":[
        "maintenance"
    ],
    "wof:name":"Jam Janitorial Services",
    "wof:placetype":"venue"
},
  "geometry": {"coordinates":[-90.265021,38.761452],"type":"Point"}
}