{
  "type": "Feature",
  "properties": {
    "iso:country":"US",
    "sg:address":"1802 Union St",
    "sg:city":"St Joseph",
    "sg:classifiers":[
        {
            "category":"Personal",
            "subcategory":"Beauty Salon",
            "type":"Services"
        }
    ],
    "sg:phone":"+1 816 279 3777",
    "sg:postcode":"64501",
    "sg:province":"MO",
    "sg:tags":[
        "shop",
        "manicuring"
    ],
    "wof:name":"Peggy's Nails",
    "wof:placetype":"venue"
},
  "geometry": {"coordinates":[-94.838257,39.772809],"type":"Point"}
}