{
  "type": "Feature",
  "properties": {
    "iso:country":"US",
    "sg:address":"1923 N Main St",
    "sg:city":"Higginsville",
    "sg:classifiers":[
        {
            "category":"Communications",
            "subcategory":"Television Station",
            "type":"Services"
        },
        {
            "category":"Professional",
            "subcategory":"Computer Services",
            "type":"Services"
        }
    ],
    "sg:phone":"+1 866 611 6565",
    "sg:postcode":"64037",
    "sg:province":"MO",
    "sg:tags":[
        "satellite",
        "isp",
        "internet",
        "cable",
        "provider"
    ],
    "sg:website":"http://www.longviewcomm.com",
    "wof:name":"Longview Communications",
    "wof:placetype":"venue"
},
  "geometry": {"coordinates":[-93.717121,39.074875],"type":"Point"}
}