{
  "type": "Feature",
  "properties": {
    "iso:country":"US",
    "sg:address":"110 E Atchison St",
    "sg:city":"Jefferson City",
    "sg:classifiers":[
        {
            "category":"Social Services",
            "subcategory":"Adult Care",
            "type":"Services"
        }
    ],
    "sg:phone":"+1 573 634 7809",
    "sg:postcode":"65101",
    "sg:province":"MO",
    "sg:tags":[
        "home",
        "residential"
    ],
    "wof:name":"Pickett's Office",
    "wof:placetype":"venue"
},
  "geometry": {"coordinates":[-92.17943099999999,38.570773],"type":"Point"}
}