{
  "type": "Feature",
  "properties": {
    "iso:country":"US",
    "sg:address":"139 Concord Plaza Shopping Center",
    "sg:city":"St Louis",
    "sg:classifiers":[
        {
            "category":"Food & Beverages",
            "subcategory":"Specialty",
            "type":"Retail Goods"
        }
    ],
    "sg:phone":"+1 314 849 1050",
    "sg:postcode":"63128",
    "sg:province":"MO",
    "sg:tags":[
        "health",
        "diet"
    ],
    "wof:name":"Healthy Shopper",
    "wof:placetype":"venue"
},
  "geometry": {"coordinates":[-90.36212999999999,38.524434],"type":"Point"}
}