{
  "type": "Feature",
  "properties": {
    "iso:country":"US",
    "sg:address":"120 S 6th St",
    "sg:city":"Poplar Bluff",
    "sg:classifiers":[
        {
            "category":"Shopping",
            "type":"Retail Goods"
        }
    ],
    "sg:phone":"+1 573 686 1737",
    "sg:postcode":"63901",
    "sg:province":"MO",
    "sg:tags":[
        "equipment",
        "electrical",
        "merchandise"
    ],
    "wof:name":"Poplar Bluff Electric",
    "wof:placetype":"venue"
},
  "geometry": {"coordinates":[-90.397132,36.75678],"type":"Point"}
}