{
  "type": "Feature",
  "properties": {
    "iso:country":"US",
    "sg:address":"111 Split Rock Dr",
    "sg:city":"Hollister",
    "sg:classifiers":[
        {
            "category":"Real Estate",
            "subcategory":"Real Estate Services",
            "type":"Services"
        },
        {
            "category":"Real Estate",
            "subcategory":"Real Estate Agent",
            "type":"Services"
        }
    ],
    "sg:phone":"+1 417 336 4938",
    "sg:postcode":"65672",
    "sg:province":"MO",
    "sg:tags":[
        "buyer",
        "broker"
    ],
    "wof:name":"Sherrell Realty Associate",
    "wof:placetype":"venue"
},
  "geometry": {"coordinates":[-93.285357,36.562394],"type":"Point"}
}