{
  "type": "Feature",
  "properties": {
    "iso:country":"US",
    "sg:address":"1015 N Grand Ave",
    "sg:city":"Doniphan",
    "sg:classifiers":[
        {
            "category":"Health Services",
            "subcategory":"Nursing And Care Facility",
            "type":"Services"
        }
    ],
    "sg:phone":"+1 573 996 4239",
    "sg:postcode":"63935",
    "sg:province":"MO",
    "sg:tags":[
        "skilled",
        "homes-skilled"
    ],
    "wof:name":"Health Systems",
    "wof:placetype":"venue"
},
  "geometry": {"coordinates":[-90.82527899999999,36.625583],"type":"Point"}
}