{
  "type": "Feature",
  "properties": {
    "iso:country":"US",
    "sg:address":"1309 N Douglass St",
    "sg:city":"Malden",
    "sg:classifiers":[
        {
            "category":"Farming",
            "subcategory":"Farm",
            "type":"Manufacturing & Wholesale Goods"
        }
    ],
    "sg:phone":"+1 573 276 5917",
    "sg:postcode":"63863",
    "sg:province":"MO",
    "wof:name":"Lape Farms",
    "wof:placetype":"venue"
},
  "geometry": {"coordinates":[-89.970556,36.575267],"type":"Point"}
}