{
  "type": "Feature",
  "properties": {
    "iso:country":"US",
    "sg:address":"14008 Clayton Rd",
    "sg:city":"Chesterfield",
    "sg:classifiers":[
        {
            "category":"Personal",
            "subcategory":"Hair Removal",
            "type":"Services"
        }
    ],
    "sg:phone":"+1 636 207 1042",
    "sg:postcode":"63017",
    "sg:province":"MO",
    "sg:tags":[
        "removing"
    ],
    "wof:name":"Aesthetics & Electrologists",
    "wof:placetype":"venue"
},
  "geometry": {"coordinates":[-90.51143500000001,38.626953],"type":"Point"}
}