{
  "type": "Feature",
  "properties": {
    "iso:country":"US",
    "sg:address":"1631 Tyson Dr",
    "sg:city":"Joplin",
    "sg:classifiers":[
        {
            "category":"Building & Trades",
            "subcategory":"Construction",
            "type":"Services"
        }
    ],
    "sg:phone":"+1 417 623 2665",
    "sg:postcode":"64801",
    "sg:province":"MO",
    "sg:tags":[
        "contractor"
    ],
    "wof:name":"Win Tinting Overcast Prof",
    "wof:placetype":"venue"
},
  "geometry": {"coordinates":[-94.46185,37.107289],"type":"Point"}
}