{
  "type": "Feature",
  "properties": {
    "iso:country":"US",
    "sg:address":"208 N Jackson Ave",
    "sg:city":"Joplin",
    "sg:classifiers":[
        {
            "category":"Organizations",
            "subcategory":"Religious Organization",
            "type":"Services"
        }
    ],
    "sg:phone":"+1 417 782 6647",
    "sg:postcode":"64801",
    "sg:province":"MO",
    "sg:tags":[
        "church"
    ],
    "wof:name":"United Family Fellowship",
    "wof:placetype":"venue"
},
  "geometry": {"coordinates":[-94.521108,37.093024],"type":"Point"}
}