{
  "type": "Feature",
  "properties": {
    "iso:country":"US",
    "sg:address":"13595 US Hwy 63 S",
    "sg:city":"Ashland",
    "sg:phone":"+1 573 657 4626",
    "sg:postcode":"65010",
    "sg:province":"MO",
    "sg:tags":[
        "corn",
        "seed",
        "business"
    ],
    "wof:name":"Bullard Seed Company",
    "wof:placetype":"venue"
},
  "geometry": {"coordinates":[-92.25221500000001,38.781704],"type":"Point"}
}