{
  "type": "Feature",
  "properties": {
    "iso:country":"US",
    "sg:address":"1311 US Hwy 60 Bus",
    "sg:city":"Dexter",
    "sg:classifiers":[
        {
            "category":"Professional",
            "subcategory":"Accounting & Tax Preparation",
            "type":"Services"
        }
    ],
    "sg:phone":"+1 573 624 8890",
    "sg:postcode":"63841",
    "sg:province":"MO",
    "sg:tags":[
        "accountant"
    ],
    "wof:name":"Dexter Package",
    "wof:placetype":"venue"
},
  "geometry": {"coordinates":[-89.97858600000001,36.803608],"type":"Point"}
}