{
  "type": "Feature",
  "properties": {
    "iso:country":"US",
    "sg:address":"4905 Childrens Pl",
    "sg:city":"St Louis",
    "sg:classifiers":[
        {
            "category":"Shopping",
            "subcategory":"Books",
            "type":"Retail Goods"
        }
    ],
    "sg:phone":"+1 314 367 4793",
    "sg:postcode":"63110",
    "sg:province":"MO",
    "sg:tags":[
        "dealer"
    ],
    "wof:name":"Barnes Noble Washington Med",
    "wof:placetype":"venue"
},
  "geometry": {"coordinates":[-90.26390600000001,38.637234],"type":"Point"}
}