{
  "type": "Feature",
  "properties": {
    "iso:country":"US",
    "sg:address":"6036 State Hwy K",
    "sg:city":"Monroe City",
    "sg:classifiers":[
        {
            "category":"Farming",
            "subcategory":"Livestock Farm",
            "type":"Manufacturing & Wholesale Goods"
        }
    ],
    "sg:phone":"+1 573 983 2398",
    "sg:postcode":"63443",
    "sg:province":"MO",
    "sg:tags":[
        "beef",
        "feedlot",
        "cattle"
    ],
    "wof:name":"Donald Anderson",
    "wof:placetype":"venue"
},
  "geometry": {"coordinates":[-91.815946,39.730999],"type":"Point"}
}