{
  "type": "Feature",
  "properties": {
    "iso:country":"US",
    "sg:address":"201 S Campbell Ave",
    "sg:city":"Springfield",
    "sg:classifiers":[
        {
            "category":"Personal",
            "subcategory":"Beauty Salon",
            "type":"Services"
        }
    ],
    "sg:phone":"+1 417 831 1144",
    "sg:postcode":"65806",
    "sg:province":"MO",
    "sg:tags":[
        "shop"
    ],
    "wof:name":"West La Event Center LLC",
    "wof:placetype":"venue"
},
  "geometry": {"coordinates":[-93.29424899999999,37.20896],"type":"Point"}
}