{
  "type": "Feature",
  "properties": {
    "iso:country":"US",
    "sg:address":"915 Eastland Dr",
    "sg:city":"Jefferson City",
    "sg:classifiers":[
        {
            "category":"Personal",
            "subcategory":"Tanning Parlor",
            "type":"Services"
        }
    ],
    "sg:phone":"+1 573 893 8262",
    "sg:postcode":"65101",
    "sg:province":"MO",
    "sg:tags":[
        "salon"
    ],
    "wof:name":"Planet Sun Tanning Salon",
    "wof:placetype":"venue"
},
  "geometry": {"coordinates":[-92.150127,38.549274],"type":"Point"}
}