{
  "type": "Feature",
  "properties": {
    "iso:country":"US",
    "sg:address":"1712 Main St",
    "sg:city":"Unionville",
    "sg:classifiers":[
        {
            "category":"Insurance",
            "subcategory":"Insurance Agent",
            "type":"Services"
        }
    ],
    "sg:phone":"+1 660 947 7355",
    "sg:postcode":"63565",
    "sg:province":"MO",
    "wof:name":"Mccutchen & Son Inc",
    "wof:placetype":"venue"
},
  "geometry": {"coordinates":[-93.00408,40.477044],"type":"Point"}
}