{
  "type": "Feature",
  "properties": {
    "iso:country":"US",
    "sg:address":"1427 N Main St",
    "sg:city":"Cape Girardeau",
    "sg:classifiers":[
        {
            "category":"Personal",
            "subcategory":"Tattoo Parlor",
            "type":"Services"
        }
    ],
    "sg:phone":"+1 573 334 5500",
    "sg:postcode":"63701",
    "sg:province":"MO",
    "sg:tags":[
        "tattooing"
    ],
    "wof:name":"Tat 2000",
    "wof:placetype":"venue"
},
  "geometry": {"coordinates":[-89.513165,37.320961],"type":"Point"}
}