{
  "type": "Feature",
  "properties": {
    "iso:country":"US",
    "sg:address":"13902 Norby Rd",
    "sg:city":"Grandview",
    "sg:classifiers":[
        {
            "category":"Retail",
            "subcategory":"Repair Shop",
            "type":"Services"
        }
    ],
    "sg:phone":"+1 816 965 6700",
    "sg:postcode":"64030",
    "sg:province":"MO",
    "sg:tags":[
        "equipment",
        "hydraulic"
    ],
    "sg:website":"www.pitman.com",
    "wof:name":"Pitman Part Ctr",
    "wof:placetype":"venue"
},
  "geometry": {"coordinates":[-94.53873299999999,38.870379],"type":"Point"}
}