{
  "type": "Feature",
  "properties": {
    "iso:country":"US",
    "sg:address":"7220 N Oak Fwy",
    "sg:city":"Gladstone",
    "sg:classifiers":[
        {
            "category":"Social Services",
            "type":"Services"
        }
    ],
    "sg:phone":"+1 816 468 1861",
    "sg:postcode":"64118",
    "sg:province":"MO",
    "sg:tags":[
        "youth",
        "organization",
        "center"
    ],
    "sg:website":"www.missouriusawrestling.org",
    "wof:name":"MISSOURI-USA Wrestling",
    "wof:placetype":"venue"
},
  "geometry": {"coordinates":[-94.576173,39.226236],"type":"Point"}
}