{
  "type": "Feature",
  "properties": {
    "iso:country":"US",
    "sg:address":"9230 Watson Rd",
    "sg:city":"Saint Louis",
    "sg:classifiers":[
        {
            "category":"Social Services",
            "type":"Services"
        }
    ],
    "sg:phone":"+1 314 849 6811",
    "sg:postcode":"63126",
    "sg:province":"MO",
    "wof:name":"Red Cross",
    "wof:placetype":"venue"
},
  "geometry": {"coordinates":[-90.37550899999999,38.559356],"type":"Point"}
}