{
  "type": "Feature",
  "properties": {
    "iso:country":"US",
    "sg:address":"746 N Fairfax Ave",
    "sg:city":"Springfield",
    "sg:classifiers":[
        {
            "category":"Manufacturing",
            "subcategory":"Tools & Machinery",
            "type":"Manufacturing & Wholesale Goods"
        }
    ],
    "sg:phone":"+1 417 864 7718",
    "sg:postcode":"65802",
    "sg:province":"MO",
    "sg:tags":[
        "industrial",
        "mfg"
    ],
    "wof:name":"D & K Refrigerated Trnsp",
    "wof:placetype":"venue"
},
  "geometry": {"coordinates":[-93.245015,37.215775],"type":"Point"}
}