{
  "type": "Feature",
  "properties": {
    "iso:country":"US",
    "sg:address":"125 E Lockling St",
    "sg:city":"Brookfield",
    "sg:classifiers":[
        {
            "category":"Health Services",
            "subcategory":"Doctor",
            "type":"Services"
        },
        {
            "category":"Health Services",
            "subcategory":"Clinic",
            "type":"Services"
        },
        {
            "category":"Health Services",
            "subcategory":"Hospital",
            "type":"Services"
        }
    ],
    "sg:phone":"+1 660 258 8237",
    "sg:postcode":"64628",
    "sg:province":"MO",
    "sg:tags":[
        "physician",
        "family",
        "medical",
        "practice",
        "surgeons",
        "medicine"
    ],
    "wof:name":"Community Medical Associates",
    "wof:placetype":"venue"
},
  "geometry": {"coordinates":[-93.067383,39.775341],"type":"Point"}
}