{
  "type": "Feature",
  "properties": {
    "iso:country":"US",
    "sg:address":"5518 Kerth Rd",
    "sg:city":"Saint Louis",
    "sg:classifiers":[
        {
            "category":"Building & Trades",
            "subcategory":"Construction",
            "type":"Services"
        }
    ],
    "sg:phone":"+1 314 631 3131",
    "sg:postcode":"63128",
    "sg:province":"MO",
    "sg:tags":[
        "specializing",
        "residential",
        "general",
        "remodel",
        "contractor"
    ],
    "wof:name":"Kingdom Builders",
    "wof:placetype":"venue"
},
  "geometry": {"coordinates":[-90.371058,38.479297],"type":"Point"}
}