{
  "type": "Feature",
  "properties": {
    "iso:country":"US",
    "sg:address":"200 S Marvin Ave",
    "sg:city":"Sedalia",
    "sg:classifiers":[
        {
            "category":"Building & Trades",
            "subcategory":"Electrical",
            "type":"Services"
        }
    ],
    "sg:phone":"+1 660 826 7776",
    "sg:postcode":"65301",
    "sg:province":"MO",
    "sg:tags":[
        "electric",
        "contractor"
    ],
    "wof:name":"Maintenance Source",
    "wof:placetype":"venue"
},
  "geometry": {"coordinates":[-93.21780200000001,38.708721],"type":"Point"}
}