{
  "type": "Feature",
  "properties": {
    "iso:country":"US",
    "sg:address":"20 N 2nd St",
    "sg:city":"Columbia",
    "sg:classifiers":[
        {
            "category":"Personal",
            "subcategory":"Beauty Salon",
            "type":"Services"
        }
    ],
    "sg:phone":"+1 573 875 7930",
    "sg:postcode":"65203",
    "sg:province":"MO",
    "sg:tags":[
        "shop"
    ],
    "wof:name":"Off Broadway Hair Salon",
    "wof:placetype":"venue"
},
  "geometry": {"coordinates":[-92.335083,38.952605],"type":"Point"}
}