{
  "type": "Feature",
  "properties": {
    "iso:country":"US",
    "sg:address":"169 E Grand Ave",
    "sg:city":"Saint Louis",
    "sg:classifiers":[
        {
            "category":"Professional",
            "subcategory":"Employment Agencies",
            "type":"Services"
        }
    ],
    "sg:phone":"+1 314 621 5331",
    "sg:postcode":"63147",
    "sg:province":"MO",
    "wof:name":"Staff Management",
    "wof:placetype":"venue"
},
  "geometry": {"coordinates":[-90.200897,38.674599],"type":"Point"}
}