{
  "type": "Feature",
  "properties": {
    "iso:country":"US",
    "sg:address":"8450 Eager Rd",
    "sg:city":"Saint Louis",
    "sg:classifiers":[
        {
            "category":"Banks & Credit Unions",
            "subcategory":"Bank",
            "type":"Services"
        }
    ],
    "sg:phone":"+1 314 961 7727",
    "sg:postcode":"63144",
    "sg:province":"MO",
    "sg:tags":[
        "commercial"
    ],
    "wof:name":"First Banks Inc",
    "wof:placetype":"venue"
},
  "geometry": {"coordinates":[-90.340631,38.629161],"type":"Point"}
}