{
  "type": "Feature",
  "properties": {
    "iso:country":"US",
    "sg:address":"912 Glen Haven Cir",
    "sg:city":"Liberty",
    "sg:classifiers":[
        {
            "category":"Farming",
            "subcategory":"Livestock Farm",
            "type":"Manufacturing & Wholesale Goods"
        }
    ],
    "sg:phone":"+1 816 781 3985",
    "sg:postcode":"64068",
    "sg:province":"MO",
    "sg:tags":[
        "beef",
        "feedlot",
        "cattle"
    ],
    "wof:name":"Roger Neth",
    "wof:placetype":"venue"
},
  "geometry": {"coordinates":[-94.435822,39.259293],"type":"Point"}
}