{
  "type": "Feature",
  "properties": {
    "iso:country":"US",
    "sg:address":"8710 Manchester Rd",
    "sg:city":"St Louis",
    "sg:classifiers":[
        {
            "category":"Insurance",
            "subcategory":"Insurance Agent",
            "type":"Services"
        }
    ],
    "sg:phone":"+1 314 301 7799",
    "sg:postcode":"63144",
    "sg:province":"MO",
    "sg:website":"www.cbsstl.com",
    "wof:name":"Corporate Benefit Strategy",
    "wof:placetype":"venue"
},
  "geometry": {"coordinates":[-90.349029,38.612481],"type":"Point"}
}