{
  "type": "Feature",
  "properties": {
    "iso:country":"US",
    "sg:address":"422 Monroe St",
    "sg:city":"Jefferson City",
    "sg:classifiers":[
        {
            "category":"Travel",
            "subcategory":"Hotels & Motels",
            "type":"Entertainment"
        }
    ],
    "sg:phone":"+1 573 636 5101",
    "sg:postcode":"65101",
    "sg:province":"MO",
    "sg:tags":[
        "operation",
        "eating"
    ],
    "wof:name":"Monroe Plaza",
    "wof:placetype":"venue"
},
  "geometry": {"coordinates":[-92.171336,38.573953],"type":"Point"}
}