{
  "type": "Feature",
  "properties": {
    "iso:country":"US",
    "sg:address":"703 W Montcrew Dr",
    "sg:city":"Kansas City",
    "sg:classifiers":[
        {
            "category":"Professional",
            "subcategory":"Lawyer & Legal Services",
            "type":"Services"
        }
    ],
    "sg:phone":"+1 816 942 4436",
    "sg:postcode":"64114",
    "sg:province":"MO",
    "wof:name":"Law Office of Brett Schro",
    "wof:placetype":"venue"
},
  "geometry": {"coordinates":[-94.600352,38.928821],"type":"Point"}
}