{
  "type": "Feature",
  "properties": {
    "iso:country":"US",
    "sg:address":"525 Couch Ave",
    "sg:city":"Kirkwood",
    "sg:classifiers":[
        {
            "category":"Health Services",
            "subcategory":"Doctor",
            "type":"Services"
        }
    ],
    "sg:phone":"+1 314 966 1528",
    "sg:postcode":"63122",
    "sg:province":"MO",
    "sg:tags":[
        "physician",
        "surgeon"
    ],
    "wof:name":"Paul Evans Miller MD",
    "wof:placetype":"venue"
},
  "geometry": {"coordinates":[-90.425349,38.571688],"type":"Point"}
}