{
  "type": "Feature",
  "properties": {
    "iso:country":"US",
    "sg:address":"1236 Fox Rd",
    "sg:city":"Maryville",
    "sg:classifiers":[
        {
            "category":"Real Estate",
            "subcategory":"Real Estate Operator",
            "type":"Services"
        }
    ],
    "sg:phone":"+1 660 562 4800",
    "sg:postcode":"64468",
    "sg:province":"MO",
    "sg:tags":[
        "building",
        "apartment"
    ],
    "wof:name":"Fox Alley Apartments",
    "wof:placetype":"venue"
},
  "geometry": {"coordinates":[-94.887371,40.363611],"type":"Point"}
}