{
  "type": "Feature",
  "properties": {
    "iso:country":"US",
    "sg:address":"7915 E 103rd Ter",
    "sg:city":"Kansas City",
    "sg:classifiers":[
        {
            "category":"Building & Trades",
            "subcategory":"Construction",
            "type":"Services"
        }
    ],
    "sg:phone":"+1 816 200 3699",
    "sg:postcode":"64134",
    "sg:province":"MO",
    "sg:tags":[
        "concrete",
        "restoration",
        "cleaning",
        "repair"
    ],
    "wof:name":"Profile Coatings LLC",
    "wof:placetype":"venue"
},
  "geometry": {"coordinates":[-94.497568,38.936877],"type":"Point"}
}