{
  "type": "Feature",
  "properties": {
    "iso:country":"US",
    "sg:address":"125 E 16th St",
    "sg:city":"Sedalia",
    "sg:classifiers":[
        {
            "category":"Professional",
            "subcategory":"Accounting & Tax Preparation",
            "type":"Services"
        }
    ],
    "sg:phone":"+1 660 827 4142",
    "sg:postcode":"65301",
    "sg:province":"MO",
    "sg:tags":[
        "return"
    ],
    "wof:name":"Floyd Self CPA",
    "wof:placetype":"venue"
},
  "geometry": {"coordinates":[-93.22843399999999,38.697544],"type":"Point"}
}