{
  "type": "Feature",
  "properties": {
    "iso:country":"US",
    "sg:address":"13940 Manchester Rd",
    "sg:city":"Ballwin",
    "sg:classifiers":[
        {
            "category":"Shopping",
            "subcategory":"Hobbies, Toys, & Games",
            "type":"Retail Goods"
        }
    ],
    "sg:phone":"+1 636 532 5110",
    "sg:postcode":"63011",
    "sg:province":"MO",
    "sg:tags":[
        "store"
    ],
    "wof:name":"Learning Express",
    "wof:placetype":"venue"
},
  "geometry": {"coordinates":[-90.491066,38.595397],"type":"Point"}
}