{
  "type": "Feature",
  "properties": {
    "iso:country":"US",
    "sg:address":"4618 Wyoming St",
    "sg:city":"Kansas City",
    "sg:classifiers":[
        {
            "category":"Building & Trades",
            "subcategory":"Construction",
            "type":"Services"
        }
    ],
    "sg:phone":"+1 816 960 1552",
    "sg:postcode":"64112",
    "sg:province":"MO",
    "sg:tags":[
        "system",
        "drainage"
    ],
    "sg:website":"www.atlantisdrainage.com",
    "wof:name":"Atlantis Drainage Solutions",
    "wof:placetype":"venue"
},
  "geometry": {"coordinates":[-94.605289,39.043087],"type":"Point"}
}