{
  "type": "Feature",
  "properties": {
    "iso:country":"US",
    "sg:address":"705 Maple Valley Dr",
    "sg:city":"Farmington",
    "sg:classifiers":[
        {
            "category":"Insurance",
            "subcategory":"Hazard Insurance",
            "type":"Services"
        },
        {
            "category":"Insurance",
            "subcategory":"Insurance Agent",
            "type":"Services"
        },
        {
            "category":"Insurance",
            "subcategory":"Life Insurance",
            "type":"Services"
        },
        {
            "category":"Insurance",
            "subcategory":"Title Insurance",
            "type":"Services"
        }
    ],
    "sg:phone":"+1 573 756 1914",
    "sg:postcode":"63640",
    "sg:province":"MO",
    "sg:tags":[
        "auto",
        "renter",
        "homeowner"
    ],
    "sg:website":"http://www.ShelterInsurance.com/CA/agent/TIMSPEER",
    "wof:name":"Shelter Insurance - Tim Speer",
    "wof:placetype":"venue"
},
  "geometry": {"coordinates":[-90.437997,37.791779],"type":"Point"}
}