{
  "type": "Feature",
  "properties": {
    "iso:country":"US",
    "sg:address":"223 S Sturgeon St",
    "sg:city":"Montgomery City",
    "sg:classifiers":[
        {
            "category":"Real Estate",
            "subcategory":"Real Estate Agent",
            "type":"Services"
        }
    ],
    "sg:phone":"+1 573 564 2627",
    "sg:postcode":"63361",
    "sg:province":"MO",
    "wof:name":"Schlanker Realty",
    "wof:placetype":"venue"
},
  "geometry": {"coordinates":[-91.503418,38.975508],"type":"Point"}
}