{
  "type": "Feature",
  "properties": {
    "iso:country":"US",
    "sg:address":"934 Wyandotte St",
    "sg:city":"Kansas City",
    "sg:classifiers":[
        {
            "category":"Professional",
            "subcategory":"Employment Agencies",
            "type":"Services"
        }
    ],
    "sg:phone":"+1 816 472 5458",
    "sg:postcode":"64105",
    "sg:province":"MO",
    "sg:tags":[
        "help",
        "contractor"
    ],
    "wof:name":"Ace Personnel",
    "wof:placetype":"venue"
},
  "geometry": {"coordinates":[-94.58552,39.102768],"type":"Point"}
}