{
  "type": "Feature",
  "properties": {
    "iso:country":"US",
    "sg:address":"205 N Main St",
    "sg:city":"Paris",
    "sg:classifiers":[
        {
            "category":"Manufacturing",
            "subcategory":"Apparel",
            "type":"Manufacturing & Wholesale Goods"
        }
    ],
    "sg:phone":"+1 660 327 4113",
    "sg:postcode":"65275",
    "sg:province":"MO",
    "sg:tags":[
        "outerwear",
        "mfg"
    ],
    "wof:name":"Wee Ones Inc",
    "wof:placetype":"venue"
},
  "geometry": {"coordinates":[-92.000257,39.482449],"type":"Point"}
}