{
  "type": "Feature",
  "properties": {
    "iso:country":"US",
    "sg:address":"23 Southwest Ln",
    "sg:city":"Troy",
    "sg:classifiers":[
        {
            "category":"Professional",
            "subcategory":"Management & Consulting",
            "type":"Services"
        }
    ],
    "sg:phone":"+1 636 528 2895",
    "sg:postcode":"63379",
    "sg:province":"MO",
    "sg:tags":[
        "business"
    ],
    "wof:name":"Educational Edge",
    "wof:placetype":"venue"
},
  "geometry": {"coordinates":[-90.993667,38.967343],"type":"Point"}
}