{
  "type": "Feature",
  "properties": {
    "iso:country":"US",
    "sg:address":"1703 Hiawatha Dr",
    "sg:city":"Wentzville",
    "sg:classifiers":[
        {
            "category":"Building & Trades",
            "subcategory":"Construction",
            "type":"Services"
        }
    ],
    "sg:phone":"+1 636 327 6105",
    "sg:postcode":"63385",
    "sg:province":"MO",
    "sg:tags":[
        "supply",
        "wallcoverings-installation",
        "wallpaper",
        "painting",
        "contractor",
        "equipment",
        "drywall"
    ],
    "wof:name":"Custom Painting & Drywall Inc",
    "wof:placetype":"venue"
},
  "geometry": {"coordinates":[-90.886263,38.80803],"type":"Point"}
}