{
  "type": "Feature",
  "properties": {
    "iso:country":"US",
    "sg:address":"4266 E Natural Bridge Ave",
    "sg:city":"Saint Louis",
    "sg:classifiers":[
        {
            "category":"Bars & Pubs",
            "subcategory":"Nightclub",
            "type":"Food & Drink"
        }
    ],
    "sg:phone":"+1 314 534 1181",
    "sg:postcode":"63115",
    "sg:province":"MO",
    "sg:tags":[
        "nightlife"
    ],
    "wof:name":"Royal Palace",
    "wof:placetype":"venue"
},
  "geometry": {"coordinates":[-90.230003,38.664902],"type":"Point"}
}