{
  "type": "Feature",
  "properties": {
    "iso:country":"US",
    "sg:address":"4907 NE 60 Ter",
    "sg:city":"Kansas City",
    "sg:classifiers":[
        {
            "category":"Manufacturing",
            "subcategory":"Rubber & Plastics",
            "type":"Manufacturing & Wholesale Goods"
        }
    ],
    "sg:phone":"+1 816 413 7688",
    "sg:postcode":"64119",
    "sg:province":"MO",
    "sg:tags":[
        "automotive",
        "tube",
        "mfg"
    ],
    "wof:name":"B F Pettus & Associates",
    "wof:placetype":"venue"
},
  "geometry": {"coordinates":[-94.52305699999999,39.20308],"type":"Point"}
}