{
  "type": "Feature",
  "properties": {
    "iso:country":"US",
    "sg:address":"1302 Dewey Ave",
    "sg:city":"Saint Joseph",
    "sg:classifiers":[
        {
            "category":"Real Estate",
            "subcategory":"Real Estate Agent",
            "type":"Services"
        }
    ],
    "sg:phone":"+1 816 233 5686",
    "sg:postcode":"64501",
    "sg:province":"MO",
    "wof:name":"Barton Appraisal Services Inc",
    "wof:placetype":"venue"
},
  "geometry": {"coordinates":[-94.860944,39.776951],"type":"Point"}
}