{
  "type": "Feature",
  "properties": {
    "iso:country":"US",
    "sg:address":"1102 SE 5 Ter",
    "sg:city":"Lees Summit",
    "sg:classifiers":[
        {
            "category":"Professional",
            "subcategory":"Art Services",
            "type":"Services"
        }
    ],
    "sg:phone":"+1 816 246 0674",
    "sg:postcode":"64063",
    "sg:province":"MO",
    "sg:tags":[
        "commercial",
        "design"
    ],
    "wof:name":"Show Me Graphics",
    "wof:placetype":"venue"
},
  "geometry": {"coordinates":[-94.353336,38.909645],"type":"Point"}
}