{
  "type": "Feature",
  "properties": {
    "iso:country":"US",
    "sg:address":"10305 N Sunswept Dr",
    "sg:city":"St Louis",
    "sg:classifiers":[
        {
            "category":"Professional",
            "subcategory":"Management & Consulting",
            "type":"Services"
        }
    ],
    "sg:phone":"+1 314 726 1616",
    "sg:postcode":"63141",
    "sg:province":"MO",
    "sg:tags":[
        "marketing",
        "program"
    ],
    "wof:name":"Team",
    "wof:placetype":"venue"
},
  "geometry": {"coordinates":[-90.406237,38.665511],"type":"Point"}
}