{
  "type": "Feature",
  "properties": {
    "iso:country":"US",
    "sg:address":"7520 Florissant Rd",
    "sg:city":"St Louis",
    "sg:classifiers":[
        {
            "category":"Personal",
            "subcategory":"Beauty Salon",
            "type":"Services"
        }
    ],
    "sg:phone":"+1 314 389 5866",
    "sg:postcode":"63121",
    "sg:province":"MO",
    "sg:tags":[
        "shop"
    ],
    "wof:name":"G'Niva's Classique Hair Design",
    "wof:placetype":"venue"
},
  "geometry": {"coordinates":[-90.299161,38.708099],"type":"Point"}
}