{
  "type": "Feature",
  "properties": {
    "iso:country":"US",
    "sg:address":"405 N Franklin St",
    "sg:city":"Cuba",
    "sg:classifiers":[
        {
            "category":"Food & Beverages",
            "subcategory":"Groceries & Convenience Stores",
            "type":"Retail Goods"
        }
    ],
    "sg:phone":"+1 573 885 2268",
    "sg:postcode":"65453",
    "sg:province":"MO",
    "wof:name":"Delano Station Break",
    "wof:placetype":"venue"
},
  "geometry": {"coordinates":[-91.404633,38.067646],"type":"Point"}
}