{
  "type": "Feature",
  "properties": {
    "iso:country":"US",
    "sg:address":"2808 Schumacher Ln",
    "sg:city":"High Ridge",
    "sg:classifiers":[
        {
            "category":"Real Estate",
            "subcategory":"Real Estate Operator",
            "type":"Services"
        }
    ],
    "sg:phone":"+1 636 677 2880",
    "sg:postcode":"63049",
    "sg:province":"MO",
    "sg:tags":[
        "mobile",
        "home",
        "site"
    ],
    "wof:name":"Woodhurst Mobile Home Park",
    "wof:placetype":"venue"
},
  "geometry": {"coordinates":[-90.513245,38.464333],"type":"Point"}
}