{
  "type": "Feature",
  "properties": {
    "iso:country":"US",
    "sg:address":"20404 E Truman Rd",
    "sg:city":"Independence",
    "sg:classifiers":[
        {
            "category":"Education",
            "subcategory":"School",
            "type":"Public Place"
        }
    ],
    "sg:phone":"+1 816 521 5455",
    "sg:postcode":"64056",
    "sg:province":"MO",
    "sg:tags":[
        "elementary"
    ],
    "sg:website":"http://www.indep.k12.mo.us",
    "wof:name":"Spring Branch Elementary Schl",
    "wof:placetype":"venue"
},
  "geometry": {"coordinates":[-94.33843,39.091067],"type":"Point"}
}