{
  "type": "Feature",
  "properties": {
    "iso:country":"US",
    "sg:address":"1114 Greystone Manor Pkwy",
    "sg:city":"Chesterfield",
    "sg:classifiers":[
        {
            "category":"Real Estate",
            "subcategory":"Real Estate Agent",
            "type":"Services"
        }
    ],
    "sg:phone":"+1 636 532 3333",
    "sg:postcode":"63005",
    "sg:province":"MO",
    "wof:name":"Mark Scheller",
    "wof:placetype":"venue"
},
  "geometry": {"coordinates":[-90.63981,38.646411],"type":"Point"}
}