{
  "type": "Feature",
  "properties": {
    "iso:country":"US",
    "sg:address":"3806 Lemay Ferry Rd",
    "sg:city":"Saint Louis",
    "sg:classifiers":[
        {
            "category":"Building & Trades",
            "subcategory":"Construction",
            "type":"Services"
        }
    ],
    "sg:phone":"+1 314 892 1331",
    "sg:postcode":"63125",
    "sg:province":"MO",
    "sg:tags":[
        "roofing",
        "industrial",
        "commercial",
        "contractor"
    ],
    "wof:name":"Bade Roofing Company Inc",
    "wof:placetype":"venue"
},
  "geometry": {"coordinates":[-90.324174,38.507461],"type":"Point"}
}