{
  "type": "Feature",
  "properties": {
    "iso:country":"US",
    "sg:address":"3401 S Spring Ave",
    "sg:city":"Saint Louis",
    "sg:classifiers":[
        {
            "category":"Food & Beverages",
            "subcategory":"Groceries & Convenience Stores",
            "type":"Retail Goods"
        }
    ],
    "sg:phone":"+1 314 664 5555",
    "sg:postcode":"63116",
    "sg:province":"MO",
    "wof:name":"Lazeez Food Market",
    "wof:placetype":"venue"
},
  "geometry": {"coordinates":[-90.24700199999999,38.596298],"type":"Point"}
}