{
  "type": "Feature",
  "properties": {
    "iso:country":"US",
    "sg:address":"9074 Overland Plz",
    "sg:city":"Overland",
    "sg:classifiers":[
        {
            "category":"Banks & Credit Unions",
            "subcategory":"Bank",
            "type":"Services"
        }
    ],
    "sg:phone":"+1 314 284 1426",
    "sg:postcode":"63114",
    "sg:province":"MO",
    "wof:name":"Bank Of America",
    "wof:placetype":"venue"
},
  "geometry": {"coordinates":[-90.357613,38.686477],"type":"Point"}
}