{
  "type": "Feature",
  "properties": {
    "iso:country":"US",
    "sg:address":"701 S Joplin Ave",
    "sg:city":"Joplin",
    "sg:classifiers":[
        {
            "category":"Health Services",
            "subcategory":"Clinic",
            "type":"Services"
        }
    ],
    "sg:phone":"+1 417 624 3920",
    "sg:postcode":"64801",
    "sg:province":"MO",
    "sg:tags":[
        "physician",
        "surgeon",
        "bureau",
        "information"
    ],
    "wof:name":"Jasper-Newton Metro Med Scty",
    "wof:placetype":"venue"
},
  "geometry": {"coordinates":[-94.51465399999999,37.082809],"type":"Point"}
}