{
  "type": "Feature",
  "properties": {
    "iso:country":"US",
    "sg:address":"1420 Hale Mcginty Dr",
    "sg:city":"Neosho",
    "sg:classifiers":[
        {
            "category":"Education",
            "subcategory":"School",
            "type":"Public Place"
        }
    ],
    "sg:phone":"+1 417 451 8650",
    "sg:postcode":"64850",
    "sg:province":"MO",
    "sg:tags":[
        "middle"
    ],
    "sg:website":"http://www.neosho.k12.mo.us",
    "wof:name":"Middle School",
    "wof:placetype":"venue"
},
  "geometry": {"coordinates":[-94.399345,36.847147],"type":"Point"}
}