{
  "type": "Feature",
  "properties": {
    "iso:country":"US",
    "sg:address":"13695 State Hwy K",
    "sg:city":"Aurora",
    "sg:classifiers":[
        {
            "category":"Farming",
            "subcategory":"Livestock Farm",
            "type":"Manufacturing & Wholesale Goods"
        }
    ],
    "sg:phone":"+1 417 466 2855",
    "sg:postcode":"65605",
    "sg:province":"MO",
    "wof:name":"Twin Oaks Farm",
    "wof:placetype":"venue"
},
  "geometry": {"coordinates":[-93.715811,37.07624],"type":"Point"}
}