{
  "type": "Feature",
  "properties": {
    "iso:country":"US",
    "sg:address":"611 S Main St",
    "sg:city":"Maryville",
    "sg:classifiers":[
        {
            "category":"Restaurant",
            "type":"Food & Drink"
        }
    ],
    "sg:phone":"+1 660 582 5750",
    "sg:postcode":"64468",
    "sg:province":"MO",
    "sg:tags":[
        "pizza"
    ],
    "wof:name":"Pagliai's Pizza",
    "wof:placetype":"venue"
},
  "geometry": {"coordinates":[-94.87301600000001,40.341157],"type":"Point"}
}