{
  "type": "Feature",
  "properties": {
    "iso:country":"US",
    "sg:address":"101 S Locust St",
    "sg:city":"Meta",
    "sg:classifiers":[
        {
            "category":"Insurance",
            "subcategory":"Insurance Agent",
            "type":"Services"
        }
    ],
    "sg:phone":"+1 573 229 4211",
    "sg:postcode":"65026",
    "sg:province":"MO",
    "wof:name":"St Thomas-Babbtown Ins Co",
    "wof:placetype":"venue"
},
  "geometry": {"coordinates":[-92.585151,38.349748],"type":"Point"}
}