{
  "type": "Feature",
  "properties": {
    "iso:country":"US",
    "sg:address":"311 W College St",
    "sg:city":"Troy",
    "sg:classifiers":[
        {
            "category":"Real Estate",
            "subcategory":"Real Estate Services",
            "type":"Services"
        }
    ],
    "sg:phone":"+1 636 462 7575",
    "sg:postcode":"63379",
    "sg:province":"MO",
    "sg:tags":[
        "abstract",
        "title"
    ],
    "wof:name":"Heartland Title Services",
    "wof:placetype":"venue"
},
  "geometry": {"coordinates":[-90.98356,38.980249],"type":"Point"}
}