{
  "type": "Feature",
  "properties": {
    "iso:country":"US",
    "sg:address":"401 S Main St",
    "sg:city":"Sunrise Beach",
    "sg:classifiers":[
        {
            "category":"Restaurant",
            "type":"Food & Drink"
        }
    ],
    "sg:phone":"+1 573 374 1021",
    "sg:postcode":"65079",
    "sg:province":"MO",
    "wof:name":"Mom's Kitchen",
    "wof:placetype":"venue"
},
  "geometry": {"coordinates":[-92.81680900000001,38.19157],"type":"Point"}
}