{
  "type": "Feature",
  "properties": {
    "iso:country":"US",
    "sg:address":"1251 Forest Ave",
    "sg:city":"Saint Louis",
    "sg:classifiers":[
        {
            "category":"Professional",
            "type":"Services"
        }
    ],
    "sg:phone":"+1 314 821 2296",
    "sg:postcode":"63122",
    "sg:province":"MO",
    "wof:name":"Leslie J Beradino",
    "wof:placetype":"venue"
},
  "geometry": {"coordinates":[-90.422336,38.560029],"type":"Point"}
}