{
  "type": "Feature",
  "properties": {
    "iso:country":"US",
    "sg:address":"1060 S Odell Ave",
    "sg:city":"Marshall",
    "sg:classifiers":[
        {
            "category":"Banks & Credit Unions",
            "subcategory":"Bank",
            "type":"Services"
        }
    ],
    "sg:phone":"+1 660 886 4200",
    "sg:postcode":"65340",
    "sg:province":"MO",
    "sg:tags":[
        "loan",
        "broker"
    ],
    "wof:name":"Fast Cash",
    "wof:placetype":"venue"
},
  "geometry": {"coordinates":[-93.194906,39.110386],"type":"Point"}
}