{
  "type": "Feature",
  "properties": {
    "addr:full":"409 Folk Ave Bernie MO 63822",
    "addr:housenumber":"409",
    "addr:postcode":"63822",
    "addr:street":"Folk Ave",
    "iso:country":"US",
    "sg:address":"409 Folk Ave",
    "sg:city":"Bernie",
    "sg:classifiers":[
        {
            "category":"Organizations",
            "subcategory":"Religious Organization",
            "type":"Services"
        }
    ],
    "sg:phone":"+1 573 293 5949",
    "sg:postcode":"63822",
    "sg:province":"MO",
    "sg:tags":[
        "denomination",
        "churches-various",
        "church"
    ],
    "sg:website":"http://www.firstnlr.com/",
    "wof:name":"First Assembly Of God Church",
    "wof:placetype":"venue"
},
  "geometry": {"coordinates":[-89.97205,36.668043],"type":"Point"}
}