{
  "type": "Feature",
  "properties": {
    "iso:country":"US",
    "sg:address":"100 Cortney Ln",
    "sg:city":"Crane",
    "sg:classifiers":[
        {
            "category":"Personal",
            "subcategory":"Beauty Salon",
            "type":"Services"
        }
    ],
    "sg:phone":"+1 417 723 0338",
    "sg:postcode":"65633",
    "sg:province":"MO",
    "wof:name":"Spiffy Doos",
    "wof:placetype":"venue"
},
  "geometry": {"coordinates":[-93.574145,36.900214],"type":"Point"}
}