{
  "type": "Feature",
  "properties": {
    "iso:country":"US",
    "sg:address":"1200 NW S Outer Rd",
    "sg:city":"Blue Springs",
    "sg:classifiers":[
        {
            "category":"Retail",
            "subcategory":"Photofinishing",
            "type":"Services"
        }
    ],
    "sg:phone":"+1 816 229 6525",
    "sg:postcode":"64015",
    "sg:province":"MO",
    "sg:tags":[
        "laboratory"
    ],
    "wof:name":"Photo Doc",
    "wof:placetype":"venue"
},
  "geometry": {"coordinates":[-94.27601,39.030311],"type":"Point"}
}