{
  "type": "Feature",
  "properties": {
    "iso:country":"US",
    "sg:address":"722 E Broadway St",
    "sg:city":"Monett",
    "sg:classifiers":[
        {
            "category":"Wholesale",
            "subcategory":"Medical Equipment & Supplies",
            "type":"Manufacturing & Wholesale Goods"
        }
    ],
    "sg:phone":"+1 417 235 5588",
    "sg:postcode":"65708",
    "sg:province":"MO",
    "sg:tags":[
        "physician",
        "surgeon"
    ],
    "wof:name":"Tucker Medical Eqpt & Hm Hlth",
    "wof:placetype":"venue"
},
  "geometry": {"coordinates":[-93.918836,36.922049],"type":"Point"}
}