{
  "type": "Feature",
  "properties": {
    "iso:country":"US",
    "sg:address":"101 State Hwy 34",
    "sg:city":"Grassy",
    "sg:classifiers":[
        {
            "category":"Utilities",
            "subcategory":"Fuel Oil & Lpg",
            "type":"Services"
        }
    ],
    "sg:phone":"+1 573 238 2264",
    "sg:postcode":"63739",
    "sg:province":"MO",
    "sg:tags":[
        "bottled",
        "gas"
    ],
    "wof:name":"M & G Gas Company",
    "wof:placetype":"venue"
},
  "geometry": {"coordinates":[-89.726388,37.390713],"type":"Point"}
}