{
  "type": "Feature",
  "properties": {
    "iso:country":"US",
    "sg:address":"2400 Otter Creek Dr",
    "sg:city":"Otterville",
    "sg:classifiers":[
        {
            "category":"Farming",
            "subcategory":"Poultry Farm",
            "type":"Manufacturing & Wholesale Goods"
        }
    ],
    "sg:phone":"+1 660 366 4650",
    "sg:postcode":"65348",
    "sg:province":"MO",
    "sg:tags":[
        "egg"
    ],
    "wof:name":"Delbert",
    "wof:placetype":"venue"
},
  "geometry": {"coordinates":[-92.932395,38.729182],"type":"Point"}
}