{
  "type": "Feature",
  "properties": {
    "iso:country":"US",
    "sg:address":"18115 Manchester Rd",
    "sg:city":"Glencoe",
    "sg:classifiers":[
        {
            "category":"Building & Trades",
            "subcategory":"Construction",
            "type":"Services"
        }
    ],
    "sg:phone":"+1 636 458 2448",
    "sg:postcode":"63038",
    "sg:province":"MO",
    "sg:tags":[
        "contractor",
        "grading"
    ],
    "wof:name":"Harness Grading",
    "wof:placetype":"venue"
},
  "geometry": {"coordinates":[-90.687189,38.572385],"type":"Point"}
}