{
  "type": "Feature",
  "properties": {
    "iso:country":"US",
    "sg:address":"202 S 3rd St",
    "sg:city":"Hayti",
    "sg:classifiers":[
        {
            "category":"Real Estate",
            "subcategory":"Real Estate Services",
            "type":"Services"
        },
        {
            "category":"Professional",
            "subcategory":"Business Services",
            "type":"Services"
        },
        {
            "category":"Real Estate",
            "subcategory":"Real Estate Agent",
            "type":"Services"
        }
    ],
    "sg:phone":"+1 573 359 1788",
    "sg:postcode":"63851",
    "sg:province":"MO",
    "sg:tags":[
        "auction",
        "buyer",
        "broker"
    ],
    "sg:website":"http://www.yourauctionpage.com/TURNAGE",
    "wof:name":"Turnage Bob Auction & Real Estate",
    "wof:placetype":"venue"
},
  "geometry": {"coordinates":[-89.74915300000001,36.233031],"type":"Point"}
}