{
  "type": "Feature",
  "properties": {
    "iso:country":"US",
    "sg:address":"120 Long Rd",
    "sg:city":"Chesterfield",
    "sg:classifiers":[
        {
            "category":"Retail",
            "subcategory":"Auto Repair",
            "type":"Services"
        }
    ],
    "sg:phone":"+1 636 532 0837",
    "sg:postcode":"63005",
    "sg:province":"MO",
    "sg:tags":[
        "automobile",
        "lubrication",
        "automotive"
    ],
    "wof:name":"Valley Xpress Lube Inc",
    "wof:placetype":"venue"
},
  "geometry": {"coordinates":[-90.617672,38.665496],"type":"Point"}
}