{
  "type": "Feature",
  "properties": {
    "iso:country":"US",
    "sg:address":"496 SE 15th Ln",
    "sg:city":"Lamar",
    "sg:classifiers":[
        {
            "category":"Professional",
            "subcategory":"Computer Services",
            "type":"Services"
        }
    ],
    "sg:phone":"+1 417 681 0878",
    "sg:postcode":"64759",
    "sg:province":"MO",
    "sg:tags":[
        "isp",
        "provider",
        "internet"
    ],
    "wof:name":"Socket Internet",
    "wof:placetype":"venue"
},
  "geometry": {"coordinates":[-94.271469,37.426861],"type":"Point"}
}