{
  "type": "Feature",
  "properties": {
    "iso:country":"US",
    "sg:address":"1110 Millcreek Rd",
    "sg:city":"Lebanon",
    "sg:classifiers":[
        {
            "category":"Shopping",
            "subcategory":"Pets & Pet Supplies",
            "type":"Retail Goods"
        },
        {
            "category":"Retail",
            "subcategory":"Animal Services",
            "type":"Services"
        }
    ],
    "sg:phone":"+1 417 532 1944",
    "sg:postcode":"65536",
    "sg:province":"MO",
    "sg:tags":[
        "grooming",
        "dog",
        "cat"
    ],
    "wof:name":"Shaggy Shears Pet Grooming",
    "wof:placetype":"venue"
},
  "geometry": {"coordinates":[-92.636124,37.68018],"type":"Point"}
}