{
  "type": "Feature",
  "properties": {
    "iso:country":"US",
    "sg:address":"806 Jefferson St",
    "sg:city":"Washington",
    "sg:classifiers":[
        {
            "category":"Insurance",
            "subcategory":"Insurance Agent",
            "type":"Services"
        },
        {
            "category":"Insurance",
            "subcategory":"Hazard Insurance",
            "type":"Services"
        },
        {
            "category":"Insurance",
            "subcategory":"Title Insurance",
            "type":"Services"
        }
    ],
    "sg:phone":"+1 636 239 7823",
    "sg:postcode":"63090",
    "sg:province":"MO",
    "sg:tags":[
        "auto",
        "homeowner"
    ],
    "sg:website":"http://apps.amfam.com/agentlocator/RCOLEMAN?sourceid=yp3",
    "wof:name":"American Family Insurance- Robert E Coleman",
    "wof:placetype":"venue"
},
  "geometry": {"coordinates":[-91.014021,38.55271],"type":"Point"}
}