{
  "type": "Feature",
  "properties": {
    "iso:country":"US",
    "sg:address":"1600 S Brentwood Blvd",
    "sg:city":"St Louis",
    "sg:classifiers":[
        {
            "category":"Education",
            "subcategory":"Special Training",
            "type":"Public Place"
        },
        {
            "category":"Professional",
            "subcategory":"Computer Services",
            "type":"Services"
        }
    ],
    "sg:phone":"+1 314 961 4551",
    "sg:postcode":"63144",
    "sg:province":"MO",
    "sg:tags":[
        "datum",
        "tutoring"
    ],
    "wof:name":"Pearson Professional Centers",
    "wof:placetype":"venue"
},
  "geometry": {"coordinates":[-90.346542,38.626457],"type":"Point"}
}