{
  "type": "Feature",
  "properties": {
    "iso:country":"US",
    "sg:address":"400 US Hwy 61",
    "sg:city":"Kelso",
    "sg:classifiers":[
        {
            "category":"Retail",
            "subcategory":"Repair Shop",
            "type":"Services"
        }
    ],
    "sg:phone":"+1 573 264 2156",
    "sg:postcode":"63758",
    "sg:province":"MO",
    "sg:tags":[
        "appliance"
    ],
    "wof:name":"Kelso Sales & Svc",
    "wof:placetype":"venue"
},
  "geometry": {"coordinates":[-89.551068,37.191142],"type":"Point"}
}