{
  "type": "Feature",
  "properties": {
    "iso:country":"US",
    "sg:address":"1536D W Elm St",
    "sg:city":"Lebanon",
    "sg:classifiers":[
        {
            "category":"Personal",
            "subcategory":"Beauty Salon",
            "type":"Services"
        },
        {
            "category":"Personal",
            "subcategory":"Nail Salon",
            "type":"Services"
        }
    ],
    "sg:phone":"+1 417 532 6100",
    "sg:postcode":"65536",
    "sg:province":"MO",
    "wof:name":"Aphrodite's Hair And Nails",
    "wof:placetype":"venue"
},
  "geometry": {"coordinates":[-92.667604,37.657085],"type":"Point"}
}