{
  "type": "Feature",
  "properties": {
    "iso:country":"US",
    "sg:address":"606 Maple Valley Dr",
    "sg:city":"Farmington",
    "sg:classifiers":[
        {
            "category":"Health Services",
            "subcategory":"Health Practitioner",
            "type":"Services"
        }
    ],
    "sg:phone":"+1 573 756 9015",
    "sg:postcode":"63640",
    "sg:province":"MO",
    "wof:name":"Scott Vanness",
    "wof:placetype":"venue"
},
  "geometry": {"coordinates":[-90.438345,37.789295],"type":"Point"}
}