{
  "type": "Feature",
  "properties": {
    "iso:country":"US",
    "sg:address":"3057 Quail Run Ln",
    "sg:city":"Saint Charles",
    "sg:classifiers":[
        {
            "category":"Shopping",
            "subcategory":"Pharmacy",
            "type":"Retail Goods"
        }
    ],
    "sg:phone":"+1 636 926 0520",
    "sg:postcode":"63303",
    "sg:province":"MO",
    "wof:name":"Teresa Tilley",
    "wof:placetype":"venue"
},
  "geometry": {"coordinates":[-90.56167499999999,38.767201],"type":"Point"}
}