{
  "type": "Feature",
  "properties": {
    "iso:country":"US",
    "sg:address":"12663 Birch Dr",
    "sg:city":"Diamond",
    "sg:classifiers":[
        {
            "category":"Building & Trades",
            "subcategory":"Construction",
            "type":"Services"
        }
    ],
    "sg:phone":"+1 417 624 6172",
    "sg:postcode":"64840",
    "sg:province":"MO",
    "sg:tags":[
        "house"
    ],
    "wof:name":"T & M Quality Homes",
    "wof:placetype":"venue"
},
  "geometry": {"coordinates":[-94.414463,37.018079],"type":"Point"}
}