{
  "type": "Feature",
  "properties": {
    "iso:country":"US",
    "sg:address":"1489 Timberwood Ln",
    "sg:city":"St Louis",
    "sg:classifiers":[
        {
            "category":"Retail",
            "subcategory":"Portrait Studio",
            "type":"Services"
        }
    ],
    "sg:phone":"+1 314 432 1631",
    "sg:postcode":"63146",
    "sg:province":"MO",
    "sg:tags":[
        "photographer",
        "photo"
    ],
    "wof:name":"Pfeffer Photography",
    "wof:placetype":"venue"
},
  "geometry": {"coordinates":[-90.437214,38.68535],"type":"Point"}
}