{
  "type": "Feature",
  "properties": {
    "iso:country":"US",
    "sg:address":"6302 E 152nd Ter",
    "sg:city":"Grandview",
    "sg:classifiers":[
        {
            "category":"Building & Trades",
            "subcategory":"Landscaping Services",
            "type":"Services"
        }
    ],
    "sg:phone":"+1 816 318 0141",
    "sg:postcode":"64030",
    "sg:province":"MO",
    "wof:name":"Clark Fine Pruning",
    "wof:placetype":"venue"
},
  "geometry": {"coordinates":[-94.520252,38.848653],"type":"Point"}
}