{
  "type": "Feature",
  "properties": {
    "iso:country":"US",
    "sg:address":"2153 Bass Rd",
    "sg:city":"Cuba",
    "sg:classifiers":[
        {
            "category":"Insurance",
            "subcategory":"Insurance Agent",
            "type":"Services"
        }
    ],
    "sg:phone":"+1 573 775 3493",
    "sg:postcode":"65453",
    "sg:province":"MO",
    "wof:name":"US Bonding Insurance Svc",
    "wof:placetype":"venue"
},
  "geometry": {"coordinates":[-91.35617000000001,38.000024],"type":"Point"}
}