{
  "type": "Feature",
  "properties": {
    "iso:country":"US",
    "sg:address":"1000 Fairgrounds Rd",
    "sg:city":"St Charles",
    "sg:classifiers":[
        {
            "category":"Professional",
            "subcategory":"Accounting & Tax Preparation",
            "type":"Services"
        }
    ],
    "sg:phone":"+1 636 946 3100",
    "sg:postcode":"63301",
    "sg:province":"MO",
    "sg:tags":[
        "return",
        "filing"
    ],
    "wof:name":"Nangle & Associates Inc",
    "wof:placetype":"venue"
},
  "geometry": {"coordinates":[-90.49878,38.773849],"type":"Point"}
}