{
  "type": "Feature",
  "properties": {
    "iso:country":"US",
    "sg:address":"939 N Boonville Ave Ste F",
    "sg:city":"Springfield",
    "sg:classifiers":[
        {
            "category":"Professional",
            "subcategory":"Accounting & Tax Preparation",
            "type":"Services"
        },
        {
            "category":"Professional",
            "subcategory":"Lawyer & Legal Services",
            "type":"Services"
        }
    ],
    "sg:phone":"+1 417 865 4400",
    "sg:postcode":"65802",
    "sg:province":"MO",
    "sg:tags":[
        "attorney",
        "accident",
        "workers'",
        "automobile",
        "assistance",
        "practice",
        "personal",
        "compensation",
        "injury",
        "criminal",
        "law"
    ],
    "sg:website":"http://www.tadmorlan.com",
    "wof:name":"Tad Morlan",
    "wof:placetype":"venue"
},
  "geometry": {"coordinates":[-93.29234099999999,37.217961],"type":"Point"}
}