{
  "type": "Feature",
  "properties": {
    "iso:country":"US",
    "sg:address":"10221 US Hwy 24",
    "sg:city":"Independence",
    "sg:classifiers":[
        {
            "category":"Insurance",
            "subcategory":"Insurance Agent",
            "type":"Services"
        }
    ],
    "sg:phone":"+1 816 461 3888",
    "sg:postcode":"64053",
    "sg:province":"MO",
    "wof:name":"Action Auto Insurance",
    "wof:placetype":"venue"
},
  "geometry": {"coordinates":[-94.456706,39.102809],"type":"Point"}
}