{
  "type": "Feature",
  "properties": {
    "iso:country":"US",
    "sg:address":"304 W Springfield Ave",
    "sg:city":"Union",
    "sg:classifiers":[
        {
            "category":"Personal",
            "subcategory":"Beauty Salon",
            "type":"Services"
        }
    ],
    "sg:phone":"+1 636 583 3121",
    "sg:postcode":"63084",
    "sg:province":"MO",
    "sg:tags":[
        "shop"
    ],
    "wof:name":"Lillian's Beauty Shop",
    "wof:placetype":"venue"
},
  "geometry": {"coordinates":[-91.01119,38.443277],"type":"Point"}
}