{
  "type": "Feature",
  "properties": {
    "iso:country":"US",
    "sg:address":"625 E Russell Ave",
    "sg:city":"Warrensburg",
    "sg:classifiers":[
        {
            "category":"Real Estate",
            "subcategory":"Real Estate Services",
            "type":"Services"
        },
        {
            "category":"Real Estate",
            "subcategory":"Real Estate Agent",
            "type":"Services"
        }
    ],
    "sg:phone":"+1 660 747 5050",
    "sg:postcode":"64093",
    "sg:province":"MO",
    "sg:tags":[
        "buyer",
        "management",
        "broker"
    ],
    "wof:name":"Reece & Nichols",
    "wof:placetype":"venue"
},
  "geometry": {"coordinates":[-93.723179,38.772968],"type":"Point"}
}