{
  "type": "Feature",
  "properties": {
    "iso:country":"US",
    "sg:address":"21 Hillcrest Estates Ln",
    "sg:city":"St Peters",
    "sg:classifiers":[
        {
            "category":"Manufacturing",
            "subcategory":"Signs",
            "type":"Manufacturing & Wholesale Goods"
        }
    ],
    "sg:phone":"+1 636 240 5182",
    "sg:postcode":"63376",
    "sg:province":"MO",
    "sg:tags":[
        "specialty",
        "mfg"
    ],
    "wof:name":"Samson Signs",
    "wof:placetype":"venue"
},
  "geometry": {"coordinates":[-90.694232,38.780121],"type":"Point"}
}