{
  "type": "Feature",
  "properties": {
    "iso:country":"US",
    "sg:address":"3584 S Farm Rd 219",
    "sg:city":"Rogersville",
    "sg:classifiers":[
        {
            "category":"Professional",
            "subcategory":"Management & Consulting",
            "type":"Services"
        }
    ],
    "sg:phone":"+1 417 890 0699",
    "sg:postcode":"65742",
    "sg:province":"MO",
    "wof:name":"Equilon Pipe Line Co LLC",
    "wof:placetype":"venue"
},
  "geometry": {"coordinates":[-93.14606000000001,37.146636],"type":"Point"}
}