{
  "type": "Feature",
  "properties": {
    "iso:country":"US",
    "sg:address":"15060 State Hwy 13",
    "sg:city":"Reeds Spring",
    "sg:classifiers":[
        {
            "category":"Insurance",
            "subcategory":"Insurance Agent",
            "type":"Services"
        }
    ],
    "sg:phone":"+1 417 739 1243",
    "sg:postcode":"65737",
    "sg:province":"MO",
    "wof:name":"Bill Wagner Insurance",
    "wof:placetype":"venue"
},
  "geometry": {"coordinates":[-93.40870099999999,36.670653],"type":"Point"}
}