{
  "type": "Feature",
  "properties": {
    "iso:country":"US",
    "sg:address":"512 W Johnson St",
    "sg:city":"Sedalia",
    "sg:classifiers":[
        {
            "category":"Organizations",
            "subcategory":"Religious Organization",
            "type":"Services"
        }
    ],
    "sg:phone":"+1 660 826 1412",
    "sg:postcode":"65301",
    "sg:province":"MO",
    "wof:name":"Quinn Chapel AME Church",
    "wof:placetype":"venue"
},
  "geometry": {"coordinates":[-93.230334,38.717117],"type":"Point"}
}