{
  "type": "Feature",
  "properties": {
    "iso:country":"US",
    "sg:address":"9502 Co Ln 110",
    "sg:city":"Carthage",
    "sg:classifiers":[
        {
            "category":"Farming",
            "subcategory":"Livestock Farm",
            "type":"Manufacturing & Wholesale Goods"
        }
    ],
    "sg:phone":"+1 417 358 6455",
    "sg:postcode":"64836",
    "sg:province":"MO",
    "sg:tags":[
        "beef",
        "feedlot",
        "cattle"
    ],
    "wof:name":"S & S Farms",
    "wof:placetype":"venue"
},
  "geometry": {"coordinates":[-94.254268,37.198166],"type":"Point"}
}