{
  "type": "Feature",
  "properties": {
    "iso:country":"US",
    "sg:address":"649 W Webster St",
    "sg:city":"Springfield",
    "sg:classifiers":[
        {
            "category":"Building & Trades",
            "subcategory":"Electrical",
            "type":"Services"
        }
    ],
    "sg:phone":"+1 417 861 3892",
    "sg:postcode":"65802",
    "sg:province":"MO",
    "sg:tags":[
        "electric",
        "contractor"
    ],
    "wof:name":"Bonnie Wheeler Electrical",
    "wof:placetype":"venue"
},
  "geometry": {"coordinates":[-93.29827899999999,37.221184],"type":"Point"}
}