{
  "type": "Feature",
  "properties": {
    "iso:country":"US",
    "sg:address":"12300 Shoemaker Rd",
    "sg:city":"Excelsior Springs",
    "sg:classifiers":[
        {
            "category":"Farming",
            "subcategory":"Livestock Farm",
            "type":"Manufacturing & Wholesale Goods"
        }
    ],
    "sg:phone":"+1 816 637 3995",
    "sg:postcode":"64024",
    "sg:province":"MO",
    "sg:tags":[
        "beef",
        "feedlot",
        "cattle"
    ],
    "wof:name":"Grover Clevenger",
    "wof:placetype":"venue"
},
  "geometry": {"coordinates":[-94.145274,39.32985],"type":"Point"}
}