{
  "type": "Feature",
  "properties": {
    "iso:country":"US",
    "sg:address":"202 E Gay St",
    "sg:city":"Warrensburg",
    "sg:classifiers":[
        {
            "category":"Shopping",
            "type":"Retail Goods"
        }
    ],
    "sg:phone":"+1 660 429 1852",
    "sg:postcode":"64093",
    "sg:province":"MO",
    "sg:tags":[
        "pet",
        "shop"
    ],
    "wof:name":"Pet Lover's Lane",
    "wof:placetype":"venue"
},
  "geometry": {"coordinates":[-93.73788399999999,38.765834],"type":"Point"}
}