{
  "type": "Feature",
  "properties": {
    "iso:country":"US",
    "sg:address":"2601 Prairie Ave",
    "sg:city":"St Louis",
    "sg:classifiers":[
        {
            "category":"Organizations",
            "subcategory":"Religious Organization",
            "type":"Services"
        }
    ],
    "sg:phone":"+1 314 652 6552",
    "sg:postcode":"63113",
    "sg:province":"MO",
    "sg:tags":[
        "church"
    ],
    "wof:name":"New Age Missionary Baptist Chr",
    "wof:placetype":"venue"
},
  "geometry": {"coordinates":[-90.225899,38.654914],"type":"Point"}
}