{
  "type": "Feature",
  "properties": {
    "iso:country":"US",
    "sg:address":"525 Walnut St",
    "sg:city":"Kansas City",
    "sg:classifiers":[
        {
            "category":"Real Estate",
            "subcategory":"Real Estate Agent",
            "type":"Services"
        }
    ],
    "sg:phone":"+1 816 842 9813",
    "sg:postcode":"64106",
    "sg:province":"MO",
    "wof:name":"Markwest Realty LLC",
    "wof:placetype":"venue"
},
  "geometry": {"coordinates":[-94.581485,39.108428],"type":"Point"}
}