{
  "type": "Feature",
  "properties": {
    "iso:country":"US",
    "sg:address":"934 S Highway Dr",
    "sg:city":"Fenton",
    "sg:classifiers":[
        {
            "category":"Recreation",
            "subcategory":"Arcade",
            "type":"Entertainment"
        }
    ],
    "sg:phone":"+1 636 343 9171",
    "sg:postcode":"63026",
    "sg:province":"MO",
    "sg:tags":[
        "operator",
        "machine",
        "game",
        "coin"
    ],
    "wof:name":"Midwest Enterprises",
    "wof:placetype":"venue"
},
  "geometry": {"coordinates":[-90.46265699999999,38.542603],"type":"Point"}
}