{
  "type": "Feature",
  "properties": {
    "iso:country":"US",
    "sg:address":"2262 Castlegate Dr",
    "sg:city":"Imperial",
    "sg:classifiers":[
        {
            "category":"Professional",
            "subcategory":"Computer Services",
            "type":"Services"
        }
    ],
    "sg:phone":"+1 636 467 8089",
    "sg:postcode":"63052",
    "sg:province":"MO",
    "sg:tags":[
        "consulting",
        "co",
        "staffing"
    ],
    "wof:name":"Hartzell Consulting LLC",
    "wof:placetype":"venue"
},
  "geometry": {"coordinates":[-90.416714,38.359908],"type":"Point"}
}