{
  "type": "Feature",
  "properties": {
    "iso:country":"US",
    "sg:address":"418 W Pine St",
    "sg:city":"Raymore",
    "sg:classifiers":[
        {
            "category":"Freight",
            "type":"Transportation"
        }
    ],
    "sg:phone":"+1 816 561 9373",
    "sg:postcode":"64083",
    "sg:province":"MO",
    "sg:tags":[
        "trucking"
    ],
    "wof:name":"Maxon Moving",
    "wof:placetype":"venue"
},
  "geometry": {"coordinates":[-94.457801,38.8085],"type":"Point"}
}