{
  "type": "Feature",
  "properties": {
    "iso:country":"US",
    "sg:address":"905 Jeffco Executive Dr",
    "sg:city":"Imperial",
    "sg:classifiers":[
        {
            "category":"Shopping",
            "subcategory":"Department Store",
            "type":"Retail Goods"
        },
        {
            "category":"Building & Trades",
            "subcategory":"Cleaning & Sanitation",
            "type":"Services"
        },
        {
            "category":"Retail",
            "subcategory":"Laundry & Dry Cleaning",
            "type":"Services"
        }
    ],
    "sg:phone":"+1 636 464 6066",
    "sg:postcode":"63052",
    "sg:province":"MO",
    "sg:tags":[
        "equipment",
        "cleaner",
        "compound",
        "supply",
        "house"
    ],
    "wof:name":"Gateway Inc",
    "wof:placetype":"venue"
},
  "geometry": {"coordinates":[-90.37209799999999,38.384359],"type":"Point"}
}