{
  "type": "Feature",
  "properties": {
    "iso:country":"US",
    "sg:address":"2153 Sams Dr",
    "sg:city":"St Louis",
    "sg:classifiers":[
        {
            "category":"Organizations",
            "subcategory":"Religious Organization",
            "type":"Services"
        }
    ],
    "sg:phone":"+1 314 965 6131",
    "sg:postcode":"63131",
    "sg:province":"MO",
    "sg:tags":[
        "church"
    ],
    "wof:name":"Christian Family Worship Ctr",
    "wof:placetype":"venue"
},
  "geometry": {"coordinates":[-90.46953999999999,38.600616],"type":"Point"}
}