{
  "type": "Feature",
  "properties": {
    "iso:country":"US",
    "sg:address":"431 S Highway 65",
    "sg:city":"Trenton",
    "sg:classifiers":[
        {
            "category":"Building & Trades",
            "subcategory":"Landscaping Services",
            "type":"Services"
        }
    ],
    "sg:phone":"+1 660 359 6967",
    "sg:postcode":"64683",
    "sg:province":"MO",
    "sg:tags":[
        "lawn"
    ],
    "wof:name":"Landscape Sculpture",
    "wof:placetype":"venue"
},
  "geometry": {"coordinates":[-93.581079,40.064302],"type":"Point"}
}