{
  "type": "Feature",
  "properties": {
    "iso:country":"US",
    "sg:address":"2550 Lemay Ferry Rd",
    "sg:city":"St Louis",
    "sg:classifiers":[
        {
            "category":"Restaurant",
            "type":"Food & Drink"
        }
    ],
    "sg:phone":"+1 314 892 8636",
    "sg:postcode":"63125",
    "sg:province":"MO",
    "sg:tags":[
        "eating"
    ],
    "wof:name":"Lemay Garden",
    "wof:placetype":"venue"
},
  "geometry": {"coordinates":[-90.30478100000001,38.520126],"type":"Point"}
}