{
  "type": "Feature",
  "properties": {
    "iso:country":"US",
    "sg:address":"100 Main St",
    "sg:city":"Belton",
    "sg:classifiers":[
        {
            "category":"Personal",
            "subcategory":"Beauty Salon",
            "type":"Services"
        }
    ],
    "sg:phone":"+1 816 318 8332",
    "sg:postcode":"64012",
    "sg:province":"MO",
    "sg:tags":[
        "shop",
        "manicuring"
    ],
    "wof:name":"Nails Plus Hand & Foot Spa",
    "wof:placetype":"venue"
},
  "geometry": {"coordinates":[-94.53402199999999,38.813134],"type":"Point"}
}