{
  "type": "Feature",
  "properties": {
    "iso:country":"US",
    "sg:address":"799 S Western St",
    "sg:city":"Marionville",
    "sg:classifiers":[
        {
            "category":"Farming",
            "subcategory":"Dairy Farm",
            "type":"Manufacturing & Wholesale Goods"
        }
    ],
    "sg:phone":"+1 417 258 2597",
    "sg:postcode":"65705",
    "sg:province":"MO",
    "wof:name":"R Blevins",
    "wof:placetype":"venue"
},
  "geometry": {"coordinates":[-93.646332,36.990797],"type":"Point"}
}