{
  "type": "Feature",
  "properties": {
    "iso:country":"US",
    "sg:address":"136 State Hwy P",
    "sg:city":"Clever",
    "sg:classifiers":[
        {
            "category":"Wholesale",
            "subcategory":"Construction Materials",
            "type":"Manufacturing & Wholesale Goods"
        },
        {
            "category":"Building & Trades",
            "subcategory":"Construction",
            "type":"Services"
        }
    ],
    "sg:phone":"+1 417 743 2424",
    "sg:postcode":"65631",
    "sg:province":"MO",
    "sg:tags":[
        "insulation",
        "heat",
        "contractor"
    ],
    "wof:name":"L & E Cellulose Spray Insltn",
    "wof:placetype":"venue"
},
  "geometry": {"coordinates":[-93.472947,37.03821],"type":"Point"}
}