{
  "type": "Feature",
  "properties": {
    "iso:country":"US",
    "sg:address":"32 Walnut Creek Trl",
    "sg:city":"Defiance",
    "sg:classifiers":[
        {
            "category":"Building & Trades",
            "subcategory":"Construction",
            "type":"Services"
        }
    ],
    "sg:phone":"+1 636 798 2183",
    "sg:postcode":"63341",
    "sg:province":"MO",
    "sg:tags":[
        "system",
        "contractor",
        "air conditioning"
    ],
    "wof:name":"Am Rudroff Inc",
    "wof:placetype":"venue"
},
  "geometry": {"coordinates":[-90.788193,38.64909],"type":"Point"}
}