{
  "type": "Feature",
  "properties": {
    "iso:country":"US",
    "sg:address":"404 Portland St",
    "sg:city":"Columbia",
    "sg:classifiers":[
        {
            "category":"Health Services",
            "subcategory":"Doctor",
            "type":"Services"
        }
    ],
    "sg:phone":"+1 573 443 1479",
    "sg:postcode":"65201",
    "sg:province":"MO",
    "sg:tags":[
        "clinic"
    ],
    "wof:name":"Lions Eye Tissue Bank",
    "wof:placetype":"venue"
},
  "geometry": {"coordinates":[-92.28734900000001,38.956749],"type":"Point"}
}