{
  "type": "Feature",
  "properties": {
    "iso:country":"US",
    "sg:address":"31706 E Pink Hill Rd",
    "sg:city":"Grain Valley",
    "sg:classifiers":[
        {
            "category":"Home & Garden",
            "subcategory":"Garden Supply",
            "type":"Retail Goods"
        }
    ],
    "sg:phone":"+1 816 224 2852",
    "sg:postcode":"64029",
    "sg:province":"MO",
    "sg:tags":[
        "nurseryman"
    ],
    "sg:website":"www.americandaylily.com",
    "wof:name":"American Daylily & Perennials",
    "wof:placetype":"venue"
},
  "geometry": {"coordinates":[-94.207506,39.050663],"type":"Point"}
}