{
  "type": "Feature",
  "properties": {
    "iso:country":"US",
    "sg:address":"712 S Main St",
    "sg:city":"South West City",
    "sg:classifiers":[
        {
            "category":"Shopping",
            "subcategory":"Department Store",
            "type":"Retail Goods"
        }
    ],
    "sg:phone":"+1 417 762 4488",
    "sg:postcode":"64863",
    "sg:province":"MO",
    "sg:tags":[
        "shop"
    ],
    "wof:name":"Dollar General",
    "wof:placetype":"venue"
},
  "geometry": {"coordinates":[-94.61323,36.509305],"type":"Point"}
}