{
  "type": "Feature",
  "properties": {
    "iso:country":"US",
    "sg:address":"508 E US Hwy 136",
    "sg:city":"Albany",
    "sg:classifiers":[
        {
            "category":"Insurance",
            "subcategory":"Insurance Agent",
            "type":"Services"
        }
    ],
    "sg:phone":"+1 660 726 5264",
    "sg:postcode":"64402",
    "sg:province":"MO",
    "wof:name":"State Farm Insurance",
    "wof:placetype":"venue"
},
  "geometry": {"coordinates":[-94.327821,40.256785],"type":"Point"}
}