{
  "type": "Feature",
  "properties": {
    "iso:country":"US",
    "sg:address":"5922 McArthur Ave",
    "sg:city":"Saint Louis",
    "sg:classifiers":[
        {
            "category":"Building & Trades",
            "subcategory":"Cleaning & Sanitation",
            "type":"Services"
        }
    ],
    "sg:phone":"+1 314 382 6828",
    "sg:postcode":"63120",
    "sg:province":"MO",
    "sg:tags":[
        "maintenance"
    ],
    "wof:name":"Brenda H Allen",
    "wof:placetype":"venue"
},
  "geometry": {"coordinates":[-90.272426,38.689227],"type":"Point"}
}