{
  "type": "Feature",
  "properties": {
    "iso:country":"US",
    "sg:address":"1442 Hudson Lndg",
    "sg:city":"St Charles",
    "sg:classifiers":[
        {
            "category":"Building & Trades",
            "subcategory":"Plumbing",
            "type":"Services"
        },
        {
            "category":"Wholesale",
            "subcategory":"Metals & Minerals",
            "type":"Manufacturing & Wholesale Goods"
        }
    ],
    "sg:phone":"+1 636 928 1444",
    "sg:postcode":"63303",
    "sg:province":"MO",
    "sg:tags":[
        "steel",
        "work",
        "sheet",
        "piling",
        "contractor"
    ],
    "wof:name":"Piling Specialties Inc",
    "wof:placetype":"venue"
},
  "geometry": {"coordinates":[-90.551384,38.747484],"type":"Point"}
}