{
  "type": "Feature",
  "properties": {
    "iso:country":"US",
    "sg:address":"18724 Highway 59",
    "sg:city":"Neosho",
    "sg:classifiers":[
        {
            "category":"Autos & Motor Vehicles",
            "subcategory":"Automobile Sales",
            "type":"Retail Goods"
        },
        {
            "category":"Retail",
            "subcategory":"Auto Repair",
            "type":"Services"
        }
    ],
    "sg:phone":"+1 417 451 2158",
    "sg:postcode":"64850",
    "sg:province":"MO",
    "sg:tags":[
        "dealers-used",
        "car",
        "used",
        "cars-wholesale"
    ],
    "sg:website":"http://www.bandsauto.com",
    "wof:name":"B & S Auto Center",
    "wof:placetype":"venue"
},
  "geometry": {"coordinates":[-94.395767,36.807238],"type":"Point"}
}