{
  "type": "Feature",
  "properties": {
    "iso:country":"US",
    "sg:address":"1131 W Battlefield Rd",
    "sg:city":"Springfield",
    "sg:classifiers":[
        {
            "category":"Real Estate",
            "subcategory":"Real Estate Agent",
            "type":"Services"
        }
    ],
    "sg:phone":"+1 417 882 0690",
    "sg:postcode":"65807",
    "sg:province":"MO",
    "sg:tags":[
        "apartment",
        "property",
        "rental"
    ],
    "wof:name":"Matt-Ryan Properties LLC",
    "wof:placetype":"venue"
},
  "geometry": {"coordinates":[-93.30612600000001,37.160156],"type":"Point"}
}