{
  "type": "Feature",
  "properties": {
    "iso:country":"US",
    "sg:address":"827 N Kingshighway Blvd",
    "sg:city":"Saint Louis",
    "sg:classifiers":[
        {
            "category":"Restaurant",
            "type":"Food & Drink"
        }
    ],
    "sg:phone":"+1 314 361 6064",
    "sg:postcode":"63108",
    "sg:province":"MO",
    "sg:website":"www.captainds.com",
    "wof:name":"Captain D's Seafood Restaurants",
    "wof:placetype":"venue"
},
  "geometry": {"coordinates":[-90.26329800000001,38.653599],"type":"Point"}
}