{
  "type": "Feature",
  "properties": {
    "iso:country":"US",
    "sg:address":"29408 E Outer Belt Rd",
    "sg:city":"Greenwood",
    "sg:classifiers":[
        {
            "category":"Farming",
            "subcategory":"Farm",
            "type":"Manufacturing & Wholesale Goods"
        }
    ],
    "sg:phone":"+1 816 540 8983",
    "sg:postcode":"64034",
    "sg:province":"MO",
    "wof:name":"John W Bell",
    "wof:placetype":"venue"
},
  "geometry": {"coordinates":[-94.241255,38.863902],"type":"Point"}
}