{
  "type": "Feature",
  "properties": {
    "iso:country":"US",
    "sg:address":"40 Professional Pkwy",
    "sg:city":"Troy",
    "sg:classifiers":[
        {
            "category":"Retail",
            "subcategory":"Animal Services",
            "type":"Services"
        }
    ],
    "sg:phone":"+1 636 462 4831",
    "sg:postcode":"63379",
    "sg:province":"MO",
    "wof:name":"Jens Pet Grooming",
    "wof:placetype":"venue"
},
  "geometry": {"coordinates":[-90.961939,38.972134],"type":"Point"}
}