{
  "type": "Feature",
  "properties": {
    "iso:country":"US",
    "sg:address":"766 US Hwy 40",
    "sg:city":"Blue Springs",
    "sg:classifiers":[
        {
            "category":"Health Services",
            "subcategory":"Chiropractor",
            "type":"Services"
        }
    ],
    "sg:phone":"+1 816 229 6633",
    "sg:postcode":"64015",
    "sg:province":"MO",
    "wof:name":"Midwest Chiropractic & Sports",
    "wof:placetype":"venue"
},
  "geometry": {"coordinates":[-94.273263,39.00907],"type":"Point"}
}