{
  "type": "Feature",
  "properties": {
    "iso:country":"US",
    "sg:address":"4126 E Natural Bridge Ave",
    "sg:city":"Saint Louis",
    "sg:classifiers":[
        {
            "category":"Social Services",
            "subcategory":"Child Care",
            "type":"Services"
        }
    ],
    "sg:phone":"+1 314 533 4699",
    "sg:postcode":"63115",
    "sg:province":"MO",
    "sg:tags":[
        "day"
    ],
    "wof:name":"Cunningham Daycare",
    "wof:placetype":"venue"
},
  "geometry": {"coordinates":[-90.22796200000001,38.665907],"type":"Point"}
}