{
  "type": "Feature",
  "properties": {
    "iso:country":"US",
    "sg:address":"930 W Liberty Dr",
    "sg:city":"Liberty",
    "sg:classifiers":[
        {
            "category":"Banks & Credit Unions",
            "subcategory":"Bank",
            "type":"Services"
        }
    ],
    "sg:phone":"+1 816 792 3456",
    "sg:postcode":"64068",
    "sg:province":"MO",
    "wof:name":"Pony Express Bank",
    "wof:placetype":"venue"
},
  "geometry": {"coordinates":[-94.435777,39.23969],"type":"Point"}
}