{
  "type": "Feature",
  "properties": {
    "addr:full":"4900 Main St Kansas City MO 64112",
    "addr:housenumber":"4900",
    "addr:postcode":"64112",
    "addr:street":"Main St",
    "iso:country":"US",
    "sg:address":"4900 Main St",
    "sg:city":"Kansas City",
    "sg:classifiers":[
        {
            "category":"Banks & Credit Unions",
            "subcategory":"Bank",
            "type":"Services"
        }
    ],
    "sg:phone":"+1 816 860 7600",
    "sg:postcode":"64112",
    "sg:province":"MO",
    "wof:name":"UMB Bank",
    "wof:placetype":"venue"
},
  "geometry": {"coordinates":[-94.58718399999999,39.037541],"type":"Point"}
}