{
  "type": "Feature",
  "properties": {
    "iso:country":"US",
    "sg:address":"15045 Manchester Rd",
    "sg:city":"Ballwin",
    "sg:classifiers":[
        {
            "category":"Government",
            "subcategory":"Office",
            "type":"Public Place"
        }
    ],
    "sg:phone":"+1 636 527 8271",
    "sg:postcode":"63011",
    "sg:province":"MO",
    "sg:tags":[
        "force",
        "national",
        "recruiting",
        "guard",
        "state",
        "security",
        "armed"
    ],
    "sg:website":"http://www.mgc.dps.mo.gov",
    "wof:name":"National Guard",
    "wof:placetype":"venue"
},
  "geometry": {"coordinates":[-90.548019,38.59293],"type":"Point"}
}