{
  "type": "Feature",
  "properties": {
    "iso:country":"US",
    "sg:address":"803 Lemay Ferry Rd",
    "sg:city":"St Louis",
    "sg:classifiers":[
        {
            "category":"Real Estate",
            "subcategory":"Real Estate Agent",
            "type":"Services"
        }
    ],
    "sg:phone":"+1 314 638 8985",
    "sg:postcode":"63125",
    "sg:province":"MO",
    "sg:tags":[
        "management"
    ],
    "wof:name":"United Property Management",
    "wof:placetype":"venue"
},
  "geometry": {"coordinates":[-90.284052,38.536725],"type":"Point"}
}