{
  "type": "Feature",
  "properties": {
    "iso:country":"US",
    "sg:address":"2047 E Sunshine St",
    "sg:city":"Springfield",
    "sg:classifiers":[
        {
            "category":"Personal",
            "subcategory":"Shoe Repair & Shine",
            "type":"Services"
        }
    ],
    "sg:phone":"+1 417 886 3033",
    "sg:postcode":"65804",
    "sg:province":"MO",
    "sg:tags":[
        "shop"
    ],
    "wof:name":"Vogue Shoe Repair",
    "wof:placetype":"venue"
},
  "geometry": {"coordinates":[-93.256744,37.181458],"type":"Point"}
}