{
  "type": "Feature",
  "properties": {
    "iso:country":"US",
    "sg:address":"3202 Indiana Ave",
    "sg:city":"Joplin",
    "sg:classifiers":[
        {
            "category":"Shopping",
            "subcategory":"Pharmacy",
            "type":"Retail Goods"
        }
    ],
    "sg:phone":"+1 417 623 3800",
    "sg:postcode":"64804",
    "sg:province":"MO",
    "sg:tags":[
        "drug",
        "store"
    ],
    "wof:name":"Ken Reynolds Pharmacy",
    "wof:placetype":"venue"
},
  "geometry": {"coordinates":[-94.50538899999999,37.054168],"type":"Point"}
}