{
  "type": "Feature",
  "properties": {
    "iso:country":"US",
    "sg:address":"3981 W Outer Rd",
    "sg:city":"Arnold",
    "sg:classifiers":[
        {
            "category":"Retail",
            "subcategory":"Auto Repair",
            "type":"Services"
        }
    ],
    "sg:phone":"+1 636 461 0009",
    "sg:postcode":"63010",
    "sg:province":"MO",
    "sg:tags":[
        "body",
        "carwash"
    ],
    "wof:name":"Advanced Auto Detailing",
    "wof:placetype":"venue"
},
  "geometry": {"coordinates":[-90.38266900000001,38.398109],"type":"Point"}
}