{
  "type": "Feature",
  "properties": {
    "iso:country":"US",
    "sg:address":"1152 S Bruce Ave",
    "sg:city":"Springfield",
    "sg:classifiers":[
        {
            "category":"Building & Trades",
            "subcategory":"Construction",
            "type":"Services"
        }
    ],
    "sg:phone":"+1 417 882 6293",
    "sg:postcode":"65804",
    "sg:province":"MO",
    "sg:tags":[
        "general",
        "contractor"
    ],
    "wof:name":"M & K Construction",
    "wof:placetype":"venue"
},
  "geometry": {"coordinates":[-93.230577,37.194262],"type":"Point"}
}