{
  "type": "Feature",
  "properties": {
    "iso:country":"US",
    "sg:address":"1719 W 39 St",
    "sg:city":"Kansas City",
    "sg:classifiers":[
        {
            "category":"Education",
            "subcategory":"School",
            "type":"Public Place"
        }
    ],
    "sg:phone":"+1 816 753 8566",
    "sg:postcode":"64111",
    "sg:province":"MO",
    "wof:name":"Gamby Necia",
    "wof:placetype":"venue"
},
  "geometry": {"coordinates":[-94.60594500000001,39.057216],"type":"Point"}
}