{
  "type": "Feature",
  "properties": {
    "iso:country":"US",
    "sg:address":"162 Lakewood Dr",
    "sg:city":"Hollister",
    "sg:classifiers":[
        {
            "category":"Travel",
            "subcategory":"Hotels & Motels",
            "type":"Entertainment"
        },
        {
            "category":"Travel",
            "subcategory":"Bed & Breakfast",
            "type":"Entertainment"
        },
        {
            "category":"Travel",
            "subcategory":"Resort",
            "type":"Entertainment"
        }
    ],
    "sg:phone":"+1 417 334 7144",
    "sg:postcode":"65672",
    "sg:province":"MO",
    "sg:tags":[
        "inn",
        "lodging"
    ],
    "sg:website":"http://www.redbudcove.com",
    "wof:name":"Red Bud Cove Bed & Breakfast",
    "wof:placetype":"venue"
},
  "geometry": {"coordinates":[-93.288518,36.546623],"type":"Point"}
}