{
  "type": "Feature",
  "properties": {
    "iso:country":"US",
    "sg:address":"902 Buckeye Dr",
    "sg:city":"Saint Louis",
    "sg:classifiers":[
        {
            "category":"Communications",
            "subcategory":"Film & Video Production",
            "type":"Services"
        }
    ],
    "sg:phone":"+1 314 521 9951",
    "sg:postcode":"63135",
    "sg:province":"MO",
    "wof:name":"Creative Video Services",
    "wof:placetype":"venue"
},
  "geometry": {"coordinates":[-90.318173,38.761532],"type":"Point"}
}