{
  "type": "Feature",
  "properties": {
    "iso:country":"US",
    "sg:address":"102 S Maple St",
    "sg:city":"Eldon",
    "sg:classifiers":[
        {
            "category":"Personal",
            "subcategory":"Beauty Salon",
            "type":"Services"
        }
    ],
    "sg:phone":"+1 573 392 4437",
    "sg:postcode":"65026",
    "sg:province":"MO",
    "sg:tags":[
        "shop",
        "treatment",
        "skin"
    ],
    "wof:name":"Skin Sations",
    "wof:placetype":"venue"
},
  "geometry": {"coordinates":[-92.579188,38.349542],"type":"Point"}
}