{
  "type": "Feature",
  "properties": {
    "iso:country":"US",
    "sg:address":"1208 Locust St",
    "sg:city":"Columbia",
    "sg:classifiers":[
        {
            "category":"Education",
            "subcategory":"School",
            "type":"Public Place"
        }
    ],
    "sg:phone":"+1 573 886 2370",
    "sg:postcode":"65201",
    "sg:province":"MO",
    "wof:name":"Lee Elementary School",
    "wof:placetype":"venue"
},
  "geometry": {"coordinates":[-92.322031,38.949305],"type":"Point"}
}