{
  "type": "Feature",
  "properties": {
    "iso:country":"US",
    "sg:address":"103 W Franklin St",
    "sg:city":"Clinton",
    "sg:classifiers":[
        {
            "category":"Banks & Credit Unions",
            "subcategory":"Bank",
            "type":"Services"
        }
    ],
    "sg:phone":"+1 660 885 6106",
    "sg:postcode":"64735",
    "sg:province":"MO",
    "sg:tags":[
        "loan"
    ],
    "wof:name":"Security Loan & Finance Co",
    "wof:placetype":"venue"
},
  "geometry": {"coordinates":[-93.777756,38.370855],"type":"Point"}
}