{
  "type": "Feature",
  "properties": {
    "iso:country":"US",
    "sg:address":"1405 W Walnut St",
    "sg:city":"Springfield",
    "sg:classifiers":[
        {
            "category":"Wholesale",
            "subcategory":"Machinery & Supplies",
            "type":"Manufacturing & Wholesale Goods"
        }
    ],
    "sg:phone":"+1 417 862 1745",
    "sg:postcode":"65806",
    "sg:province":"MO",
    "sg:tags":[
        "equipment",
        "welding"
    ],
    "sg:website":"www.airgas.com",
    "wof:name":"Airgas Puritan Medical",
    "wof:placetype":"venue"
},
  "geometry": {"coordinates":[-93.31074,37.207383],"type":"Point"}
}