{
  "type": "Feature",
  "properties": {
    "iso:country":"US",
    "sg:address":"5400 Meramec Bottom Rd",
    "sg:city":"Sappington",
    "sg:classifiers":[
        {
            "category":"Recreation",
            "type":"Entertainment"
        }
    ],
    "sg:phone":"+1 314 849 8900",
    "sg:postcode":"63128",
    "sg:province":"MO",
    "sg:tags":[
        "club",
        "membership",
        "baseball"
    ],
    "wof:name":"Khoury League Intl Hdqtr",
    "wof:placetype":"venue"
},
  "geometry": {"coordinates":[-90.41304700000001,38.460395],"type":"Point"}
}