{
  "type": "Feature",
  "properties": {
    "iso:country":"US",
    "sg:address":"362 Mid Rivers Mall Dr",
    "sg:city":"St Peters",
    "sg:classifiers":[
        {
            "category":"Shopping",
            "subcategory":"Florist",
            "type":"Retail Goods"
        }
    ],
    "sg:phone":"+1 636 397 2525",
    "sg:postcode":"63376",
    "sg:province":"MO",
    "wof:name":"Simpley Roses & Such",
    "wof:placetype":"venue"
},
  "geometry": {"coordinates":[-90.625292,38.790431],"type":"Point"}
}