{
  "type": "Feature",
  "properties": {
    "iso:country":"US",
    "sg:address":"807 Lost Hills Dr",
    "sg:city":"Moberly",
    "sg:classifiers":[
        {
            "category":"Retail",
            "subcategory":"Car Wash",
            "type":"Services"
        }
    ],
    "sg:phone":"+1 660 269 9090",
    "sg:postcode":"65270",
    "sg:province":"MO",
    "sg:website":"http://www.mikesdetailingservice.com",
    "wof:name":"Mike's Detailing",
    "wof:placetype":"venue"
},
  "geometry": {"coordinates":[-92.458243,39.42564],"type":"Point"}
}