{
  "type": "Feature",
  "properties": {
    "iso:country":"US",
    "sg:address":"293 Broadway",
    "sg:city":"Herculaneum",
    "sg:classifiers":[
        {
            "category":"Building & Trades",
            "subcategory":"Landscaping Services",
            "type":"Services"
        }
    ],
    "sg:phone":"+1 636 475 9283",
    "sg:postcode":"63048",
    "sg:province":"MO",
    "sg:tags":[
        "lawn",
        "maintenance",
        "grounds"
    ],
    "wof:name":"Paramount Lawn & Land Co",
    "wof:placetype":"venue"
},
  "geometry": {"coordinates":[-90.377717,38.266285],"type":"Point"}
}