{
  "type": "Feature",
  "properties": {
    "iso:country":"US",
    "sg:address":"508 Strecker Rd",
    "sg:city":"Ballwin",
    "sg:classifiers":[
        {
            "category":"Health Services",
            "subcategory":"Doctor",
            "type":"Services"
        }
    ],
    "sg:phone":"+1 636 458 3223",
    "sg:postcode":"63011",
    "sg:province":"MO",
    "wof:name":"West County Family Dental",
    "wof:placetype":"venue"
},
  "geometry": {"coordinates":[-90.614597,38.609251],"type":"Point"}
}