{
  "type": "Feature",
  "properties": {
    "iso:country":"US",
    "sg:address":"1717 Roosevelt Ave",
    "sg:city":"Joplin",
    "sg:classifiers":[
        {
            "category":"Freight",
            "type":"Transportation"
        }
    ],
    "sg:phone":"+1 417 782 5233",
    "sg:postcode":"64801",
    "sg:province":"MO",
    "sg:tags":[
        "commercial",
        "storage",
        "general"
    ],
    "wof:name":"Westside Mini Storage",
    "wof:placetype":"venue"
},
  "geometry": {"coordinates":[-94.540992,37.073772],"type":"Point"}
}