{
  "type": "Feature",
  "properties": {
    "iso:country":"US",
    "sg:address":"13200 Christopher Dr",
    "sg:city":"Rolla",
    "sg:classifiers":[
        {
            "category":"Building & Trades",
            "subcategory":"Construction",
            "type":"Services"
        }
    ],
    "sg:phone":"+1 573 364 1076",
    "sg:postcode":"65401",
    "sg:province":"MO",
    "sg:tags":[
        "speculative",
        "builder"
    ],
    "wof:name":"Virgil Bartle Construction",
    "wof:placetype":"venue"
},
  "geometry": {"coordinates":[-91.78310999999999,37.902032],"type":"Point"}
}