{
  "type": "Feature",
  "properties": {
    "iso:country":"US",
    "sg:address":"1349 Laughlin Ridge Rd",
    "sg:city":"Pineville",
    "sg:classifiers":[
        {
            "category":"Farming",
            "subcategory":"Livestock Farm",
            "type":"Manufacturing & Wholesale Goods"
        }
    ],
    "sg:phone":"+1 417 435 2769",
    "sg:postcode":"64856",
    "sg:province":"MO",
    "sg:tags":[
        "feeding"
    ],
    "wof:name":"Dewayne Stephens",
    "wof:placetype":"venue"
},
  "geometry": {"coordinates":[-94.168609,36.570025],"type":"Point"}
}