{
  "type": "Feature",
  "properties": {
    "iso:country":"US",
    "sg:address":"620 Millstone Dr",
    "sg:city":"Florissant",
    "sg:classifiers":[
        {
            "category":"Shopping",
            "subcategory":"Bicycles & Sporting Goods",
            "type":"Retail Goods"
        }
    ],
    "sg:phone":"+1 314 830 3366",
    "sg:postcode":"63033",
    "sg:province":"MO",
    "sg:tags":[
        "equipment",
        "golf",
        "supply"
    ],
    "wof:name":"Three B's Golf Custom Clubs",
    "wof:placetype":"venue"
},
  "geometry": {"coordinates":[-90.292131,38.78926],"type":"Point"}
}