{
  "type": "Feature",
  "properties": {
    "iso:country":"US",
    "sg:address":"201 Main St",
    "sg:city":"Boonville",
    "sg:classifiers":[
        {
            "category":"Restaurant",
            "type":"Food & Drink"
        }
    ],
    "sg:phone":"+1 660 882 6333",
    "sg:postcode":"65233",
    "sg:province":"MO",
    "sg:tags":[
        "eating"
    ],
    "wof:name":"Riverside Diner",
    "wof:placetype":"venue"
},
  "geometry": {"coordinates":[-92.74440800000001,38.977589],"type":"Point"}
}