{
  "type": "Feature",
  "properties": {
    "iso:country":"US",
    "sg:address":"8515 Delmar Blvd",
    "sg:city":"Saint Louis",
    "sg:classifiers":[
        {
            "category":"Shopping",
            "subcategory":"Crafts & Fabrics",
            "type":"Retail Goods"
        }
    ],
    "sg:phone":"+1 314 432 5005",
    "sg:postcode":"63124",
    "sg:province":"MO",
    "sg:tags":[
        "household",
        "sewing",
        "appliance"
    ],
    "wof:name":"Winstons Fabrics",
    "wof:placetype":"venue"
},
  "geometry": {"coordinates":[-90.356274,38.660896],"type":"Point"}
}