{
  "type": "Feature",
  "properties": {
    "iso:country":"US",
    "sg:address":"11319 Highway Ff",
    "sg:city":"Joplin",
    "sg:classifiers":[
        {
            "category":"Building & Trades",
            "subcategory":"Construction",
            "type":"Services"
        }
    ],
    "sg:phone":"+1 417 781 7827",
    "sg:postcode":"64804",
    "sg:province":"MO",
    "sg:tags":[
        "manufactured",
        "housing-communities"
    ],
    "wof:name":"Bykota Estates",
    "wof:placetype":"venue"
},
  "geometry": {"coordinates":[-94.43734499999999,37.054572],"type":"Point"}
}