{
  "type": "Feature",
  "properties": {
    "iso:country":"US",
    "sg:address":"1714 Chestnut Farms Ct",
    "sg:city":"Fenton",
    "sg:classifiers":[
        {
            "category":"Real Estate",
            "subcategory":"Real Estate Services",
            "type":"Services"
        },
        {
            "category":"Real Estate",
            "subcategory":"Real Estate Agent",
            "type":"Services"
        }
    ],
    "sg:phone":"+1 314 720 4352",
    "sg:postcode":"63026",
    "sg:province":"MO",
    "sg:tags":[
        "buyer",
        "broker"
    ],
    "wof:name":"Edge Property Management Group",
    "wof:placetype":"venue"
},
  "geometry": {"coordinates":[-90.483497,38.526294],"type":"Point"}
}