{
  "type": "Feature",
  "properties": {
    "iso:country":"US",
    "sg:address":"17119 Manchester Rd",
    "sg:city":"Grover",
    "sg:classifiers":[
        {
            "category":"Manufacturing",
            "subcategory":"Building Materials",
            "type":"Manufacturing & Wholesale Goods"
        }
    ],
    "sg:phone":"+1 636 458 5956",
    "sg:postcode":"63040",
    "sg:province":"MO",
    "sg:tags":[
        "mfg",
        "wood",
        "kitchen",
        "cabinet"
    ],
    "wof:name":"Cabinets Crafts",
    "wof:placetype":"venue"
},
  "geometry": {"coordinates":[-90.654625,38.580383],"type":"Point"}
}