{
  "type": "Feature",
  "properties": {
    "iso:country":"US",
    "sg:address":"517 Fort St",
    "sg:city":"Moberly",
    "sg:classifiers":[
        {
            "category":"Wholesale",
            "subcategory":"Hardware",
            "type":"Manufacturing & Wholesale Goods"
        }
    ],
    "sg:phone":"+1 660 263 5746",
    "sg:postcode":"65270",
    "sg:province":"MO",
    "sg:tags":[
        "equipment",
        "heating",
        "system"
    ],
    "wof:name":"Show-Me Plumbing & Heating",
    "wof:placetype":"venue"
},
  "geometry": {"coordinates":[-92.445308,39.41425],"type":"Point"}
}