{
  "type": "Feature",
  "properties": {
    "iso:country":"US",
    "sg:address":"1319 Boland Pl",
    "sg:city":"Saint Louis",
    "sg:classifiers":[
        {
            "category":"Organizations",
            "subcategory":"Religious Organization",
            "type":"Services"
        }
    ],
    "sg:phone":"+1 314 644 0089",
    "sg:postcode":"63117",
    "sg:province":"MO",
    "wof:name":"Brentwood Church God In Christ",
    "wof:placetype":"venue"
},
  "geometry": {"coordinates":[-90.327851,38.627845],"type":"Point"}
}