{
  "type": "Feature",
  "properties": {
    "iso:country":"US",
    "sg:address":"3726 Wyoming St",
    "sg:city":"Saint Louis",
    "sg:classifiers":[
        {
            "category":"Building & Trades",
            "subcategory":"Plumbing",
            "type":"Services"
        }
    ],
    "sg:phone":"+1 314 772 7777",
    "sg:postcode":"63116",
    "sg:province":"MO",
    "wof:name":"Rabbit Timothy C Co",
    "wof:placetype":"venue"
},
  "geometry": {"coordinates":[-90.245251,38.599249],"type":"Point"}
}