{
  "type": "Feature",
  "properties": {
    "iso:country":"US",
    "sg:address":"7720 State Hwy Bb",
    "sg:city":"Rockville",
    "sg:phone":"+1 660 598 4132",
    "sg:postcode":"64780",
    "sg:province":"MO",
    "sg:tags":[
        "farm",
        "wheat",
        "grain",
        "cash",
        "soybean"
    ],
    "wof:name":"D Barger",
    "wof:placetype":"venue"
},
  "geometry": {"coordinates":[-93.925904,38.027249],"type":"Point"}
}