{
  "type": "Feature",
  "properties": {
    "iso:country":"US",
    "sg:address":"604 Lodwick Ln",
    "sg:city":"Excelsior Springs",
    "sg:classifiers":[
        {
            "category":"Farming",
            "subcategory":"Farm",
            "type":"Manufacturing & Wholesale Goods"
        }
    ],
    "sg:phone":"+1 816 630 7154",
    "sg:postcode":"64024",
    "sg:province":"MO",
    "sg:tags":[
        "crop",
        "general"
    ],
    "wof:name":"Richard Busick",
    "wof:placetype":"venue"
},
  "geometry": {"coordinates":[-94.253834,39.346201],"type":"Point"}
}