{
  "type": "Feature",
  "properties": {
    "iso:country":"US",
    "sg:address":"5201 N Belt Hwy",
    "sg:city":"Saint Joseph",
    "sg:classifiers":[
        {
            "category":"Coffee & Tea",
            "type":"Food & Drink"
        }
    ],
    "sg:menulink":"http://www.allmenus.com/mo/st-joseph/115340-starbucks-coffee/menu/",
    "sg:phone":"+1 816 279 4632",
    "sg:postcode":"64506",
    "sg:province":"MO",
    "sg:tags":[
        "american"
    ],
    "wof:name":"Starbucks Coffee",
    "wof:placetype":"venue"
},
  "geometry": {"coordinates":[-94.81331299999999,39.816801],"type":"Point"}
}