{
  "type": "Feature",
  "properties": {
    "iso:country":"US",
    "sg:address":"8845 State Hwy 86",
    "sg:city":"Shell Knob",
    "sg:classifiers":[
        {
            "category":"Food & Beverages",
            "subcategory":"Groceries & Convenience Stores",
            "type":"Retail Goods"
        }
    ],
    "sg:phone":"+1 417 858 6486",
    "sg:postcode":"65747",
    "sg:province":"MO",
    "wof:name":"Carr Lane Country Stop",
    "wof:placetype":"venue"
},
  "geometry": {"coordinates":[-93.565174,36.507914],"type":"Point"}
}