{
  "type": "Feature",
  "properties": {
    "iso:country":"US",
    "sg:address":"1410 E 7th St",
    "sg:city":"Joplin",
    "sg:classifiers":[
        {
            "category":"Shopping",
            "subcategory":"Pharmacy",
            "type":"Retail Goods"
        }
    ],
    "sg:phone":"+1 417 624 3270",
    "sg:postcode":"64801",
    "sg:province":"MO",
    "wof:name":"Drug Warehouse",
    "wof:placetype":"venue"
},
  "geometry": {"coordinates":[-94.49807199999999,37.083795],"type":"Point"}
}