{
  "type": "Feature",
  "properties": {
    "iso:country":"US",
    "sg:address":"314 W High St",
    "sg:city":"Jefferson City",
    "sg:classifiers":[
        {
            "category":"Education",
            "subcategory":"School",
            "type":"Public Place"
        }
    ],
    "sg:phone":"+1 573 636 8980",
    "sg:postcode":"65101",
    "sg:province":"MO",
    "sg:tags":[
        "organization",
        "religious"
    ],
    "wof:name":"St Peter Schl",
    "wof:placetype":"venue"
},
  "geometry": {"coordinates":[-92.176084,38.57972],"type":"Point"}
}