{
  "type": "Feature",
  "properties": {
    "addr:full":"120 Glenallen Dr St Peters MO 63376",
    "addr:housenumber":"120",
    "addr:postcode":"63376",
    "addr:street":"Glenallen Dr",
    "iso:country":"US",
    "sg:address":"120 Glenallen Dr",
    "sg:city":"St Peters",
    "sg:classifiers":[
        {
            "category":"Insurance",
            "subcategory":"Insurance Agent",
            "type":"Services"
        }
    ],
    "sg:phone":"+1 636 978 3655",
    "sg:postcode":"63376",
    "sg:province":"MO",
    "wof:name":"Federated Insurance Co",
    "wof:placetype":"venue"
},
  "geometry": {"coordinates":[-90.66576999999999,38.762209],"type":"Point"}
}