{
  "type": "Feature",
  "properties": {
    "iso:country":"US",
    "sg:address":"13220 Weatherfield Dr",
    "sg:city":"Saint Louis",
    "sg:classifiers":[
        {
            "category":"Organizations",
            "subcategory":"Community Association",
            "type":"Services"
        }
    ],
    "sg:phone":"+1 314 205 1881",
    "sg:postcode":"63146",
    "sg:province":"MO",
    "wof:name":"Homes of Distinction",
    "wof:placetype":"venue"
},
  "geometry": {"coordinates":[-90.48700599999999,38.699837],"type":"Point"}
}