{
  "type": "Feature",
  "properties": {
    "iso:country":"US",
    "sg:address":"576 NE 18th Ave",
    "sg:city":"Trenton",
    "sg:classifiers":[
        {
            "category":"Building & Trades",
            "subcategory":"Plumbing",
            "type":"Services"
        }
    ],
    "sg:phone":"+1 660 359 4289",
    "sg:postcode":"64683",
    "sg:province":"MO",
    "sg:tags":[
        "air",
        "heating",
        "contractor",
        "system",
        "conditioning"
    ],
    "wof:name":"Total Comfort Heating & Coolg",
    "wof:placetype":"venue"
},
  "geometry": {"coordinates":[-93.56150599999999,40.15327],"type":"Point"}
}