{
  "type": "Feature",
  "properties": {
    "iso:country":"US",
    "sg:address":"2435 Zagreb Rd",
    "sg:city":"Pacific",
    "sg:classifiers":[
        {
            "category":"Shopping",
            "subcategory":"Bicycles & Sporting Goods",
            "type":"Retail Goods"
        }
    ],
    "sg:phone":"+1 636 271 3336",
    "sg:postcode":"63069",
    "sg:province":"MO",
    "sg:tags":[
        "gun",
        "gunsmith"
    ],
    "wof:name":"Weatherby Collectors Assn",
    "wof:placetype":"venue"
},
  "geometry": {"coordinates":[-90.799378,38.445323],"type":"Point"}
}