{
  "type": "Feature",
  "properties": {
    "iso:country":"US",
    "sg:address":"6901 Manchester Ave",
    "sg:city":"Saint Louis",
    "sg:classifiers":[
        {
            "category":"Professional",
            "subcategory":"Lawyer & Legal Services",
            "type":"Services"
        }
    ],
    "sg:phone":"+1 314 781 4357",
    "sg:postcode":"63143",
    "sg:province":"MO",
    "wof:name":"Horan Law Office",
    "wof:placetype":"venue"
},
  "geometry": {"coordinates":[-90.306999,38.617001],"type":"Point"}
}