{
  "type": "Feature",
  "properties": {
    "iso:country":"US",
    "sg:address":"215 N Meramec Ave",
    "sg:city":"St Louis",
    "sg:classifiers":[
        {
            "category":"Real Estate",
            "subcategory":"Architect",
            "type":"Services"
        }
    ],
    "sg:phone":"+1 314 726 4858",
    "sg:postcode":"63105",
    "sg:province":"MO",
    "sg:tags":[
        "architectural"
    ],
    "sg:website":"www.schwetyearchitects.com",
    "wof:name":"Schwetye Architects Inc",
    "wof:placetype":"venue"
},
  "geometry": {"coordinates":[-90.33904800000001,38.655296],"type":"Point"}
}