{
  "type": "Feature",
  "properties": {
    "iso:country":"US",
    "sg:address":"6316 N Monroe Ave",
    "sg:city":"Kansas City",
    "sg:classifiers":[
        {
            "category":"Building & Trades",
            "subcategory":"Cleaning & Sanitation",
            "type":"Services"
        }
    ],
    "sg:phone":"+1 816 455 4443",
    "sg:postcode":"64119",
    "sg:province":"MO",
    "sg:tags":[
        "janitorial",
        "contract"
    ],
    "wof:name":"Carol Taylor",
    "wof:placetype":"venue"
},
  "geometry": {"coordinates":[-94.53686,39.209425],"type":"Point"}
}