{
  "type": "Feature",
  "properties": {
    "iso:country":"US",
    "sg:address":"8635 W Highway 86",
    "sg:city":"Joplin",
    "sg:classifiers":[
        {
            "category":"Insurance",
            "subcategory":"Hazard Insurance",
            "type":"Services"
        },
        {
            "category":"Banks & Credit Unions",
            "subcategory":"Financial Services",
            "type":"Services"
        }
    ],
    "sg:phone":"+1 417 782 5132",
    "sg:postcode":"64804",
    "sg:province":"MO",
    "sg:tags":[
        "commercial",
        "business"
    ],
    "wof:name":"Reed Financial Group",
    "wof:placetype":"venue"
},
  "geometry": {"coordinates":[-94.534721,36.944745],"type":"Point"}
}