{
  "type": "Feature",
  "properties": {
    "iso:country":"US",
    "sg:address":"231 Hibler Oaks Dr",
    "sg:city":"Saint Louis",
    "sg:classifiers":[
        {
            "category":"Manufacturing",
            "subcategory":"Printing",
            "type":"Manufacturing & Wholesale Goods"
        }
    ],
    "sg:phone":"+1 314 469 1042",
    "sg:postcode":"63141",
    "sg:province":"MO",
    "sg:tags":[
        "publishing"
    ],
    "wof:name":"Clean Edge Publications",
    "wof:placetype":"venue"
},
  "geometry": {"coordinates":[-90.458286,38.660332],"type":"Point"}
}