{
  "type": "Feature",
  "properties": {
    "iso:country":"US",
    "sg:address":"908 Hunts Rd",
    "sg:city":"Clinton",
    "sg:classifiers":[
        {
            "category":"Insurance",
            "subcategory":"Insurance Agent",
            "type":"Services"
        }
    ],
    "sg:phone":"+1 660 885 9920",
    "sg:postcode":"64735",
    "sg:province":"MO",
    "wof:name":"Americlaim Of Clinton",
    "wof:placetype":"venue"
},
  "geometry": {"coordinates":[-93.760319,38.359531],"type":"Point"}
}