{
  "type": "Feature",
  "properties": {
    "iso:country":"US",
    "sg:address":"1730 E Republic Rd",
    "sg:city":"Springfield",
    "sg:classifiers":[
        {
            "category":"Real Estate",
            "subcategory":"Real Estate Agent",
            "type":"Services"
        }
    ],
    "sg:phone":"+1 417 886 0533",
    "sg:postcode":"65804",
    "sg:province":"MO",
    "sg:tags":[
        "appraiser"
    ],
    "wof:name":"Ron Hawkins Appraisal",
    "wof:placetype":"venue"
},
  "geometry": {"coordinates":[-93.26514899999999,37.13738],"type":"Point"}
}