{
  "type": "Feature",
  "properties": {
    "iso:country":"US",
    "sg:address":"5114 S Walnut Hill Rd",
    "sg:city":"Springfield",
    "sg:classifiers":[
        {
            "category":"Shopping",
            "subcategory":"Hobbies, Toys, & Games",
            "type":"Retail Goods"
        },
        {
            "category":"Shopping",
            "subcategory":"Crafts & Fabrics",
            "type":"Retail Goods"
        }
    ],
    "sg:phone":"+1 417 882 7063",
    "sg:postcode":"65810",
    "sg:province":"MO",
    "sg:tags":[
        "shop",
        "model",
        "hobby",
        "supply"
    ],
    "wof:name":"Crafts Of Wood",
    "wof:placetype":"venue"
},
  "geometry": {"coordinates":[-93.339719,37.122788],"type":"Point"}
}