{
  "type": "Feature",
  "properties": {
    "iso:country":"US",
    "sg:address":"33 Stoddard Rd",
    "sg:city":"Olean",
    "sg:classifiers":[
        {
            "category":"Professional",
            "type":"Services"
        }
    ],
    "sg:phone":"+1 573 392 7390",
    "sg:postcode":"65064",
    "sg:province":"MO",
    "wof:name":"Doug Crouch",
    "wof:placetype":"venue"
},
  "geometry": {"coordinates":[-92.503922,38.402665],"type":"Point"}
}