{
  "type": "Feature",
  "properties": {
    "iso:country":"US",
    "sg:address":"2160 Lemay Ferry Rd",
    "sg:city":"St Louis",
    "sg:classifiers":[
        {
            "category":"Real Estate",
            "subcategory":"Developer",
            "type":"Services"
        }
    ],
    "sg:phone":"+1 314 892 3662",
    "sg:postcode":"63125",
    "sg:province":"MO",
    "sg:tags":[
        "cemetery"
    ],
    "wof:name":"St Trinity Cemetery",
    "wof:placetype":"venue"
},
  "geometry": {"coordinates":[-90.296637,38.525039],"type":"Point"}
}