{
  "type": "Feature",
  "properties": {
    "iso:country":"US",
    "sg:address":"1708 Hudson Rd",
    "sg:city":"Saint Louis",
    "sg:classifiers":[
        {
            "category":"Building & Trades",
            "subcategory":"Landscaping Services",
            "type":"Services"
        }
    ],
    "sg:phone":"+1 314 868 2100",
    "sg:postcode":"63136",
    "sg:province":"MO",
    "wof:name":"Woods Lawn Care",
    "wof:placetype":"venue"
},
  "geometry": {"coordinates":[-90.271575,38.761633],"type":"Point"}
}