{
  "type": "Feature",
  "properties": {
    "iso:country":"US",
    "sg:address":"6690 Clayton Rd",
    "sg:city":"Richmond Heights",
    "sg:classifiers":[
        {
            "category":"Fast Food",
            "type":"Food & Drink"
        },
        {
            "category":"Restaurant",
            "type":"Food & Drink"
        }
    ],
    "sg:phone":"+1 314 647 4500",
    "sg:postcode":"63117",
    "sg:province":"MO",
    "sg:tags":[
        "traditional",
        "american"
    ],
    "wof:name":"Boston Market",
    "wof:placetype":"venue"
},
  "geometry": {"coordinates":[-90.316002,38.634602],"type":"Point"}
}