{
  "type": "Feature",
  "properties": {
    "iso:country":"US",
    "sg:address":"3228 W 20th St",
    "sg:city":"Joplin",
    "sg:classifiers":[
        {
            "category":"Wholesale",
            "subcategory":"Construction Materials",
            "type":"Manufacturing & Wholesale Goods"
        }
    ],
    "sg:phone":"+1 417 781 8586",
    "sg:postcode":"64804",
    "sg:province":"MO",
    "wof:name":"Callender Window Tinting",
    "wof:placetype":"venue"
},
  "geometry": {"coordinates":[-94.555842,37.070158],"type":"Point"}
}