{
  "type": "Feature",
  "properties": {
    "iso:country":"US",
    "sg:address":"527 Mae Ct",
    "sg:city":"Fenton",
    "sg:classifiers":[
        {
            "category":"Wholesale",
            "subcategory":"Electrical",
            "type":"Manufacturing & Wholesale Goods"
        }
    ],
    "sg:phone":"+1 636 349 7722",
    "sg:postcode":"63026",
    "sg:province":"MO",
    "sg:tags":[
        "laboratory",
        "testing",
        "electronic"
    ],
    "sg:website":"www.islcorp.com",
    "wof:name":"Transcat",
    "wof:placetype":"venue"
},
  "geometry": {"coordinates":[-90.480527,38.491767],"type":"Point"}
}