{
  "type": "Feature",
  "properties": {
    "iso:country":"US",
    "sg:address":"1923 W Liberty St",
    "sg:city":"Mexico",
    "sg:classifiers":[
        {
            "category":"Freight",
            "type":"Transportation"
        }
    ],
    "sg:phone":"+1 573 581 6309",
    "sg:postcode":"65265",
    "sg:province":"MO",
    "sg:tags":[
        "commercial",
        "storage"
    ],
    "wof:name":"All Sizes Storage",
    "wof:placetype":"venue"
},
  "geometry": {"coordinates":[-91.907045,39.170767],"type":"Point"}
}