{
  "type": "Feature",
  "properties": {
    "iso:country":"US",
    "sg:address":"2019 S Elliott Ave",
    "sg:city":"Aurora",
    "sg:classifiers":[
        {
            "category":"Food & Beverages",
            "subcategory":"Groceries & Convenience Stores",
            "type":"Retail Goods"
        }
    ],
    "sg:phone":"+1 417 678 6660",
    "sg:postcode":"65605",
    "sg:province":"MO",
    "wof:name":"Rapid Roberts",
    "wof:placetype":"venue"
},
  "geometry": {"coordinates":[-93.71852,36.951998],"type":"Point"}
}