{
  "type": "Feature",
  "properties": {
    "iso:country":"US",
    "sg:address":"1112 E Dunklin St",
    "sg:city":"Jefferson City",
    "sg:classifiers":[
        {
            "category":"Social Services",
            "subcategory":"Child Care",
            "type":"Services"
        }
    ],
    "sg:phone":"+1 573 634 4561",
    "sg:postcode":"65101",
    "sg:province":"MO",
    "sg:tags":[
        "center",
        "day"
    ],
    "wof:name":"Janet D Khaleel",
    "wof:placetype":"venue"
},
  "geometry": {"coordinates":[-92.163926,38.563343],"type":"Point"}
}