{
  "type": "Feature",
  "properties": {
    "iso:country":"US",
    "sg:address":"5 Mesa Oaks",
    "sg:city":"Wright City",
    "sg:classifiers":[
        {
            "category":"Building & Trades",
            "subcategory":"Landscaping Services",
            "type":"Services"
        }
    ],
    "sg:phone":"+1 636 456 3463",
    "sg:postcode":"63390",
    "sg:province":"MO",
    "sg:tags":[
        "tree"
    ],
    "wof:name":"D-Tree Svc",
    "wof:placetype":"venue"
},
  "geometry": {"coordinates":[-91.00356600000001,38.848343],"type":"Point"}
}