{
  "type": "Feature",
  "properties": {
    "iso:country":"US",
    "sg:address":"7696 Jim Weber Rd",
    "sg:city":"Eureka",
    "sg:classifiers":[
        {
            "category":"Building & Trades",
            "subcategory":"Construction",
            "type":"Services"
        }
    ],
    "sg:phone":"+1 636 587 2266",
    "sg:postcode":"63025",
    "sg:province":"MO",
    "sg:tags":[
        "acoustical",
        "insulation",
        "contractor"
    ],
    "wof:name":"Friend Acoustical",
    "wof:placetype":"venue"
},
  "geometry": {"coordinates":[-90.599347,38.472964],"type":"Point"}
}