{
  "type": "Feature",
  "properties": {
    "iso:country":"US",
    "sg:address":"139 Blue Ridge Rd",
    "sg:city":"Kaiser",
    "sg:classifiers":[
        {
            "category":"Building & Trades",
            "subcategory":"Construction",
            "type":"Services"
        }
    ],
    "sg:phone":"+1 573 302 7307",
    "sg:postcode":"65047",
    "sg:province":"MO",
    "sg:tags":[
        "heavy"
    ],
    "wof:name":"Bam Dock Refoaming Inc",
    "wof:placetype":"venue"
},
  "geometry": {"coordinates":[-92.572889,38.15333],"type":"Point"}
}