{
  "type": "Feature",
  "properties": {
    "iso:country":"US",
    "sg:address":"106 N 4th St Ste 158",
    "sg:city":"Edina",
    "sg:classifiers":[
        {
            "category":"Professional",
            "subcategory":"Lawyer & Legal Services",
            "type":"Services"
        }
    ],
    "sg:phone":"+1 660 397 3356",
    "sg:postcode":"63537",
    "sg:province":"MO",
    "sg:tags":[
        "attorney",
        "practice"
    ],
    "wof:name":"Larry Phillips Law Office",
    "wof:placetype":"venue"
},
  "geometry": {"coordinates":[-92.17147799999999,40.167597],"type":"Point"}
}