{
  "type": "Feature",
  "properties": {
    "iso:country":"US",
    "sg:address":"15945 Manchester Rd",
    "sg:city":"Ellisville",
    "sg:classifiers":[
        {
            "category":"Banks & Credit Unions",
            "subcategory":"Bank",
            "type":"Services"
        }
    ],
    "sg:phone":"+1 636 227 2000",
    "sg:postcode":"63011",
    "sg:province":"MO",
    "sg:tags":[
        "loan"
    ],
    "wof:name":"Household Finance",
    "wof:placetype":"venue"
},
  "geometry": {"coordinates":[-90.591764,38.591604],"type":"Point"}
}