{
  "type": "Feature",
  "properties": {
    "iso:country":"US",
    "sg:address":"4909 N Northwood Rd",
    "sg:city":"Kansas City",
    "sg:classifiers":[
        {
            "category":"Building & Trades",
            "subcategory":"Landscaping Services",
            "type":"Services"
        }
    ],
    "sg:phone":"+1 816 509 2735",
    "sg:postcode":"64150",
    "sg:province":"MO",
    "sg:tags":[
        "landscape"
    ],
    "wof:name":"Soothing Surroundings",
    "wof:placetype":"venue"
},
  "geometry": {"coordinates":[-94.631614,39.188233],"type":"Point"}
}