{
  "type": "Feature",
  "properties": {
    "iso:country":"US",
    "sg:address":"1316 Country Club Dr",
    "sg:city":"Kirksville",
    "sg:classifiers":[
        {
            "category":"Health Services",
            "subcategory":"Doctor",
            "type":"Services"
        },
        {
            "category":"Health Services",
            "subcategory":"Dentist",
            "type":"Services"
        }
    ],
    "sg:phone":"+1 660 665 5653",
    "sg:postcode":"63501",
    "sg:province":"MO",
    "sg:tags":[
        "dentists-oral",
        "physician",
        "maxillofacial",
        "surgeons",
        "surgery",
        "oral"
    ],
    "sg:website":"http://www.asbarber.com",
    "wof:name":"A S Barber & Associates",
    "wof:placetype":"venue"
},
  "geometry": {"coordinates":[-92.569373,40.169561],"type":"Point"}
}