{
  "type": "Feature",
  "properties": {
    "iso:country":"US",
    "sg:address":"307 NE Castle Dr",
    "sg:city":"Lees Summit",
    "sg:classifiers":[
        {
            "category":"Professional",
            "subcategory":"Lawyer & Legal Services",
            "type":"Services"
        }
    ],
    "sg:phone":"+1 816 246 9994",
    "sg:postcode":"64086",
    "sg:province":"MO",
    "sg:tags":[
        "attorney"
    ],
    "wof:name":"Lee Willerton",
    "wof:placetype":"venue"
},
  "geometry": {"coordinates":[-94.35496999999999,38.921191],"type":"Point"}
}