{
  "type": "Feature",
  "properties": {
    "iso:country":"US",
    "sg:address":"278 Dartmoore Dr",
    "sg:city":"Rogersville",
    "sg:classifiers":[
        {
            "category":"Manufacturing",
            "subcategory":"Buildings",
            "type":"Manufacturing & Wholesale Goods"
        },
        {
            "category":"Building & Trades",
            "subcategory":"Construction",
            "type":"Services"
        }
    ],
    "sg:phone":"+1 417 859 0941",
    "sg:postcode":"65742",
    "sg:province":"MO",
    "sg:tags":[
        "home",
        "builder",
        "contractor"
    ],
    "wof:name":"Thornton Masonry Home Improv",
    "wof:placetype":"venue"
},
  "geometry": {"coordinates":[-92.995392,37.220597],"type":"Point"}
}