{
  "type": "Feature",
  "properties": {
    "iso:country":"US",
    "sg:address":"10950 Olive Blvd",
    "sg:city":"St Louis",
    "sg:classifiers":[
        {
            "category":"Banks & Credit Unions",
            "subcategory":"Bank",
            "type":"Services"
        }
    ],
    "sg:phone":"+1 314 432 1029",
    "sg:postcode":"63141",
    "sg:province":"MO",
    "sg:tags":[
        "state"
    ],
    "wof:name":"First Community Credit Union",
    "wof:placetype":"venue"
},
  "geometry": {"coordinates":[-90.420743,38.672973],"type":"Point"}
}