{
  "type": "Feature",
  "properties": {
    "iso:country":"US",
    "sg:address":"3646 Rouggly Rd",
    "sg:city":"Valles Mines",
    "sg:classifiers":[
        {
            "category":"Building & Trades",
            "subcategory":"Construction",
            "type":"Services"
        }
    ],
    "sg:phone":"+1 573 358 2367",
    "sg:postcode":"63087",
    "sg:province":"MO",
    "wof:name":"Farmer Grading",
    "wof:placetype":"venue"
},
  "geometry": {"coordinates":[-90.472656,38.01482],"type":"Point"}
}