{
  "type": "Feature",
  "properties": {
    "iso:country":"US",
    "sg:address":"710 N 2nd St",
    "sg:city":"Saint Louis",
    "sg:classifiers":[
        {
            "category":"Utilities",
            "subcategory":"Telephone",
            "type":"Services"
        }
    ],
    "sg:phone":"+1 314 588 9099",
    "sg:postcode":"63102",
    "sg:province":"MO",
    "wof:name":"Mindstep Corp",
    "wof:placetype":"venue"
},
  "geometry": {"coordinates":[-90.184375,38.630761],"type":"Point"}
}