{
  "type": "Feature",
  "properties": {
    "addr:full":"218 W Main St Sedalia MO 65301",
    "addr:housenumber":"218",
    "addr:postcode":"65301",
    "addr:street":"W Main St",
    "iso:country":"US",
    "sg:address":"218 W Main St",
    "sg:city":"Sedalia",
    "sg:classifiers":[
        {
            "category":"Retail",
            "subcategory":"Repair Shop",
            "type":"Services"
        }
    ],
    "sg:phone":"+1 660 826 7811",
    "sg:postcode":"65301",
    "sg:province":"MO",
    "sg:tags":[
        "scooter",
        "motorcycle",
        "motor"
    ],
    "wof:name":"Kust M Thunder",
    "wof:placetype":"venue"
},
  "geometry": {"coordinates":[-93.229406,38.711071],"type":"Point"}
}