{
  "type": "Feature",
  "properties": {
    "iso:country":"US",
    "sg:address":"2207 E 69 Ter",
    "sg:city":"Kansas City",
    "sg:classifiers":[
        {
            "category":"Professional",
            "subcategory":"Accounting & Tax Preparation",
            "type":"Services"
        }
    ],
    "sg:phone":"+1 816 363 8509",
    "sg:postcode":"64132",
    "sg:province":"MO",
    "wof:name":"Wrench & Associates",
    "wof:placetype":"venue"
},
  "geometry": {"coordinates":[-94.559173,39.000795],"type":"Point"}
}