{
  "type": "Feature",
  "properties": {
    "iso:country":"US",
    "sg:address":"1819 Zumbehl Rd",
    "sg:city":"Saint Charles",
    "sg:classifiers":[
        {
            "category":"Personal",
            "subcategory":"Beauty Salon",
            "type":"Services"
        }
    ],
    "sg:phone":"+1 636 724 1780",
    "sg:postcode":"63303",
    "sg:province":"MO",
    "sg:tags":[
        "shop"
    ],
    "wof:name":"US Nail",
    "wof:placetype":"venue"
},
  "geometry": {"coordinates":[-90.528828,38.77721],"type":"Point"}
}