{
  "type": "Feature",
  "properties": {
    "iso:country":"US",
    "sg:address":"3620 W Broadway Blvd",
    "sg:city":"Sedalia",
    "sg:classifiers":[
        {
            "category":"Autos & Motor Vehicles",
            "subcategory":"Automobile Sales",
            "type":"Retail Goods"
        }
    ],
    "sg:phone":"+1 660 826 9291",
    "sg:postcode":"65301",
    "sg:province":"MO",
    "sg:tags":[
        "used"
    ],
    "wof:name":"Marks Used Cars & Trucks",
    "wof:placetype":"venue"
},
  "geometry": {"coordinates":[-93.27660400000001,38.712613],"type":"Point"}
}