{
  "type": "Feature",
  "properties": {
    "iso:country":"US",
    "sg:address":"8820 Prospect Ave",
    "sg:city":"Kansas City",
    "sg:classifiers":[
        {
            "category":"Building & Trades",
            "subcategory":"Landscaping Services",
            "type":"Services"
        }
    ],
    "sg:phone":"+1 816 333 7220",
    "sg:postcode":"64132",
    "sg:province":"MO",
    "wof:name":"Country Club Tree Service Inc",
    "wof:placetype":"venue"
},
  "geometry": {"coordinates":[-94.556708,38.967586],"type":"Point"}
}