{
  "type": "Feature",
  "properties": {
    "iso:country":"US",
    "sg:address":"503 S McCleary Rd",
    "sg:city":"Excelsior Spgs",
    "sg:classifiers":[
        {
            "category":"Wholesale",
            "subcategory":"Electrical",
            "type":"Manufacturing & Wholesale Goods"
        }
    ],
    "sg:phone":"+1 816 630 6011",
    "sg:postcode":"64024",
    "sg:province":"MO",
    "sg:tags":[
        "appliance"
    ],
    "sg:website":"www.dragondistributing.com",
    "wof:name":"Dragon Distributing",
    "wof:placetype":"venue"
},
  "geometry": {"coordinates":[-94.263149,39.325289],"type":"Point"}
}