{
  "type": "Feature",
  "properties": {
    "iso:country":"US",
    "sg:address":"2902 N Baltimore St",
    "sg:city":"Kirksville",
    "sg:classifiers":[
        {
            "category":"Manufacturing",
            "subcategory":"Buildings",
            "type":"Manufacturing & Wholesale Goods"
        },
        {
            "category":"Building & Trades",
            "subcategory":"Construction",
            "type":"Services"
        }
    ],
    "sg:phone":"+1 660 665 8202",
    "sg:postcode":"63501",
    "sg:province":"MO",
    "sg:tags":[
        "home",
        "builder",
        "contractor"
    ],
    "wof:name":"Kilmer's Construction Incorporated",
    "wof:placetype":"venue"
},
  "geometry": {"coordinates":[-92.572145,40.169123],"type":"Point"}
}