{
  "type": "Feature",
  "properties": {
    "addr:full":"220 S Jefferson St Neosho MO 64850",
    "addr:housenumber":"220",
    "addr:postcode":"64850",
    "addr:street":"S Jefferson St",
    "iso:country":"US",
    "sg:address":"220 S Jefferson St",
    "sg:city":"Neosho",
    "sg:classifiers":[
        {
            "category":"Utilities",
            "subcategory":"Telephone",
            "type":"Services"
        }
    ],
    "sg:phone":"+1 800 235 9800",
    "sg:postcode":"64850",
    "sg:province":"MO",
    "wof:name":"Southwestern Bell Telephone LP",
    "wof:placetype":"venue"
},
  "geometry": {"coordinates":[-94.369888,36.868515],"type":"Point"}
}