{
  "type": "Feature",
  "properties": {
    "iso:country":"US",
    "sg:address":"3868 South Ave",
    "sg:city":"Springfield",
    "sg:classifiers":[
        {
            "category":"Banks & Credit Unions",
            "subcategory":"Bank",
            "type":"Services"
        }
    ],
    "sg:phone":"+1 417 887 3388",
    "sg:postcode":"65807",
    "sg:province":"MO",
    "wof:name":"Metro Credit Union",
    "wof:placetype":"venue"
},
  "geometry": {"coordinates":[-93.29298799999999,37.144432],"type":"Point"}
}