{
  "type": "Feature",
  "properties": {
    "iso:country":"US",
    "sg:address":"11121 Glen Arbor Rd",
    "sg:city":"Kansas City",
    "sg:classifiers":[
        {
            "category":"Professional",
            "subcategory":"Lawyer & Legal Services",
            "type":"Services"
        }
    ],
    "sg:phone":"+1 816 942 7880",
    "sg:postcode":"64114",
    "sg:province":"MO",
    "wof:name":"Partin Wm C",
    "wof:placetype":"venue"
},
  "geometry": {"coordinates":[-94.599163,38.925409],"type":"Point"}
}