{
  "type": "Feature",
  "properties": {
    "iso:country":"US",
    "sg:address":"403 S Prairie St",
    "sg:city":"Bloomfield",
    "sg:classifiers":[
        {
            "category":"Structure",
            "subcategory":"Office Building",
            "type":"Public Place"
        }
    ],
    "sg:phone":"+1 573 568 3150",
    "sg:postcode":"63825",
    "sg:province":"MO",
    "sg:tags":[
        "park"
    ],
    "wof:name":"Proscuting Attorney",
    "wof:placetype":"venue"
},
  "geometry": {"coordinates":[-89.928953,36.888379],"type":"Point"}
}