{
  "type": "Feature",
  "properties": {
    "iso:country":"US",
    "sg:address":"117 E Washington Ave",
    "sg:city":"Saint Louis",
    "sg:classifiers":[
        {
            "category":"Shopping",
            "subcategory":"Shoes",
            "type":"Retail Goods"
        }
    ],
    "sg:phone":"+1 314 965 8015",
    "sg:postcode":"63122",
    "sg:province":"MO",
    "sg:tags":[
        "athletic",
        "c",
        "footwear",
        "rug"
    ],
    "wof:name":"Daves Bargains",
    "wof:placetype":"venue"
},
  "geometry": {"coordinates":[-90.40427800000001,38.584365],"type":"Point"}
}