{
  "type": "Feature",
  "properties": {
    "iso:country":"US",
    "sg:address":"1640 E Liberty St",
    "sg:city":"Mexico",
    "sg:classifiers":[
        {
            "category":"Restaurant",
            "type":"Food & Drink"
        }
    ],
    "sg:phone":"+1 573 581 5442",
    "sg:postcode":"65265",
    "sg:province":"MO",
    "wof:name":"Porky's Smokehouse",
    "wof:placetype":"venue"
},
  "geometry": {"coordinates":[-91.864942,39.167892],"type":"Point"}
}