{
  "type": "Feature",
  "properties": {
    "iso:country":"US",
    "sg:address":"55 Patmos Ct",
    "sg:city":"St Peters",
    "sg:classifiers":[
        {
            "category":"Building & Trades",
            "subcategory":"Equipment Rental",
            "type":"Services"
        }
    ],
    "sg:phone":"+1 636 441 1289",
    "sg:postcode":"63376",
    "sg:province":"MO",
    "sg:tags":[
        "yard"
    ],
    "wof:name":"TNT Golf Car & Equipment Co",
    "wof:placetype":"venue"
},
  "geometry": {"coordinates":[-90.58683499999999,38.80075],"type":"Point"}
}