{
  "type": "Feature",
  "properties": {
    "iso:country":"US",
    "sg:address":"157 Hughes Ln",
    "sg:city":"St Charles",
    "sg:classifiers":[
        {
            "category":"Social Services",
            "subcategory":"Child Care",
            "type":"Services"
        }
    ],
    "sg:phone":"+1 636 916 3500",
    "sg:postcode":"63301",
    "sg:province":"MO",
    "sg:tags":[
        "day"
    ],
    "wof:name":"Bright Start Academy",
    "wof:placetype":"venue"
},
  "geometry": {"coordinates":[-90.47663900000001,38.812979],"type":"Point"}
}