{
  "type": "Feature",
  "properties": {
    "iso:country":"US",
    "sg:address":"1352 State Hwy 7",
    "sg:city":"Blue Springs",
    "sg:classifiers":[
        {
            "category":"Personal",
            "subcategory":"Beauty Salon",
            "type":"Services"
        }
    ],
    "sg:phone":"+1 816 220 7778",
    "sg:postcode":"64014",
    "sg:province":"MO",
    "sg:tags":[
        "manicuring"
    ],
    "wof:name":"Nails-N-Time",
    "wof:placetype":"venue"
},
  "geometry": {"coordinates":[-94.27286100000001,39.004711],"type":"Point"}
}