{
  "type": "Feature",
  "properties": {
    "iso:country":"US",
    "sg:address":"100 Isle of Capri Blvd",
    "sg:city":"Boonville",
    "sg:classifiers":[
        {
            "category":"Restaurant",
            "type":"Food & Drink"
        }
    ],
    "sg:phone":"+1 660 882 1226",
    "sg:postcode":"65233",
    "sg:province":"MO",
    "wof:name":"Calypso's",
    "wof:placetype":"venue"
},
  "geometry": {"coordinates":[-92.749083,38.976915],"type":"Point"}
}