{
  "type": "Feature",
  "properties": {
    "iso:country":"US",
    "sg:address":"9959 Manchester Rd",
    "sg:city":"St Louis",
    "sg:classifiers":[
        {
            "category":"Shopping",
            "subcategory":"Jewelry",
            "type":"Retail Goods"
        }
    ],
    "sg:phone":"+1 314 961 8010",
    "sg:postcode":"63122",
    "sg:province":"MO",
    "sg:tags":[
        "jeweler"
    ],
    "wof:name":"A F Noack Jeweler",
    "wof:placetype":"venue"
},
  "geometry": {"coordinates":[-90.382341,38.604079],"type":"Point"}
}