{
  "type": "Feature",
  "properties": {
    "iso:country":"US",
    "sg:address":"1829 Summitview Dr",
    "sg:city":"St Charles",
    "sg:classifiers":[
        {
            "category":"Arts & Performance",
            "subcategory":"Theater",
            "type":"Entertainment"
        }
    ],
    "sg:phone":"+1 636 244 9292",
    "sg:postcode":"63303",
    "sg:province":"MO",
    "sg:tags":[
        "live",
        "music"
    ],
    "wof:name":"Good Times DJ",
    "wof:placetype":"venue"
},
  "geometry": {"coordinates":[-90.52126800000001,38.759698],"type":"Point"}
}