{
  "type": "Feature",
  "properties": {
    "iso:country":"US",
    "sg:address":"5622 Natural Bridge Ave",
    "sg:city":"St Louis",
    "sg:classifiers":[
        {
            "category":"Wholesale",
            "subcategory":"Machinery & Supplies",
            "type":"Manufacturing & Wholesale Goods"
        }
    ],
    "sg:phone":"+1 314 381 9667",
    "sg:postcode":"63120",
    "sg:province":"MO",
    "sg:tags":[
        "equipment",
        "industrial",
        "used"
    ],
    "wof:name":"John Corder Equipment Co",
    "wof:placetype":"venue"
},
  "geometry": {"coordinates":[-90.267759,38.683604],"type":"Point"}
}