{
  "type": "Feature",
  "properties": {
    "iso:country":"US",
    "sg:address":"1229 Queens Trail Ln",
    "sg:city":"Fenton",
    "sg:classifiers":[
        {
            "category":"Retail",
            "subcategory":"Repair Shop",
            "type":"Services"
        },
        {
            "category":"Building & Trades",
            "subcategory":"Plumbing",
            "type":"Services"
        }
    ],
    "sg:phone":"+1 636 677 0070",
    "sg:postcode":"63026",
    "sg:province":"MO",
    "sg:tags":[
        "equipment",
        "medical",
        "contractor"
    ],
    "wof:name":"Med Tech Refrigeration Inc",
    "wof:placetype":"venue"
},
  "geometry": {"coordinates":[-90.502117,38.500549],"type":"Point"}
}