{
  "type": "Feature",
  "properties": {
    "iso:country":"US",
    "sg:address":"1215 Benton Blvd",
    "sg:city":"Kansas City",
    "sg:classifiers":[
        {
            "category":"Organizations",
            "subcategory":"Religious Organization",
            "type":"Services"
        }
    ],
    "sg:phone":"+1 816 231 0907",
    "sg:postcode":"64127",
    "sg:province":"MO",
    "wof:name":"Friendly Assembly of God",
    "wof:placetype":"venue"
},
  "geometry": {"coordinates":[-94.544453,39.097441],"type":"Point"}
}