{
  "type": "Feature",
  "properties": {
    "iso:country":"US",
    "sg:address":"22121 120th St",
    "sg:city":"Williamstown",
    "sg:classifiers":[
        {
            "category":"Building & Trades",
            "subcategory":"Plumbing",
            "type":"Services"
        }
    ],
    "sg:phone":"+1 573 853 4548",
    "sg:postcode":"63473",
    "sg:province":"MO",
    "sg:tags":[
        "conditioning",
        "contractor"
    ],
    "wof:name":"Hamilton Service",
    "wof:placetype":"venue"
},
  "geometry": {"coordinates":[-91.72095299999999,40.223918],"type":"Point"}
}