{
  "type": "Feature",
  "properties": {
    "iso:country":"US",
    "sg:address":"4525 Downs Dr",
    "sg:city":"Saint Joseph",
    "sg:classifiers":[
        {
            "category":"Restaurant",
            "type":"Food & Drink"
        }
    ],
    "sg:menulink":"http://www.allmenus.com/mo/st-joseph/122218-quiznos-sub/menu/",
    "sg:phone":"+1 816 271 4426",
    "sg:postcode":"64507",
    "sg:province":"MO",
    "sg:tags":[
        "wrap",
        "american",
        "sandwich"
    ],
    "wof:name":"Quiznos Sub",
    "wof:placetype":"venue"
},
  "geometry": {"coordinates":[-94.785826,39.759347],"type":"Point"}
}