{
  "type": "Feature",
  "properties": {
    "addr:full":"2808 N Kansas Expy Springfield MO 65803",
    "addr:housenumber":"2808",
    "addr:postcode":"65803",
    "addr:street":"N;Expy",
    "iso:country":"US",
    "sg:address":"2808 N Kansas Expy",
    "sg:city":"Springfield",
    "sg:classifiers":[
        {
            "category":"Travel",
            "subcategory":"Hotels & Motels",
            "type":"Entertainment"
        }
    ],
    "sg:phone":"+1 417 869 5600",
    "sg:postcode":"65803",
    "sg:province":"MO",
    "wof:name":"Econo Lodge",
    "wof:placetype":"venue"
},
  "geometry": {"coordinates":[-93.31081,37.246847],"type":"Point"}
}