{
  "type": "Feature",
  "properties": {
    "iso:country":"US",
    "sg:address":"11800 Old Halls Ferry Rd",
    "sg:city":"Florissant",
    "sg:classifiers":[
        {
            "category":"Organizations",
            "subcategory":"Religious Organization",
            "type":"Services"
        }
    ],
    "sg:phone":"+1 314 355 5046",
    "sg:postcode":"63033",
    "sg:province":"MO",
    "sg:tags":[
        "church"
    ],
    "wof:name":"Jehovah's Witnesses",
    "wof:placetype":"venue"
},
  "geometry": {"coordinates":[-90.270991,38.787501],"type":"Point"}
}