{
  "type": "Feature",
  "properties": {
    "iso:country":"US",
    "sg:address":"100 Chesterfield Business Pkwy",
    "sg:city":"Chesterfield",
    "sg:classifiers":[
        {
            "category":"Real Estate",
            "subcategory":"Architect",
            "type":"Services"
        }
    ],
    "sg:phone":"+1 636 519 1400",
    "sg:postcode":"63005",
    "sg:province":"MO",
    "sg:tags":[
        "architects'",
        "specification",
        "builders'",
        "construction",
        "architectural",
        "engineer"
    ],
    "sg:website":"http://www.mwweberarchitects.com",
    "wof:name":"Mw Weber Architects",
    "wof:placetype":"venue"
},
  "geometry": {"coordinates":[-90.619598,38.668251],"type":"Point"}
}