{
  "type": "Feature",
  "properties": {
    "iso:country":"US",
    "sg:address":"1104 E Ohio St",
    "sg:city":"Clinton",
    "sg:classifiers":[
        {
            "category":"Health Services",
            "subcategory":"Optometrist",
            "type":"Services"
        },
        {
            "category":"Shopping",
            "subcategory":"Optical Goods",
            "type":"Retail Goods"
        }
    ],
    "sg:phone":"+1 660 885 7116",
    "sg:postcode":"64735",
    "sg:province":"MO",
    "sg:tags":[
        "eyeglass",
        "repair"
    ],
    "sg:website":"http://www.eyecarespecialties.biz",
    "wof:name":"Eyecare Specialties",
    "wof:placetype":"venue"
},
  "geometry": {"coordinates":[-93.756364,38.36631],"type":"Point"}
}