{
  "type": "Feature",
  "properties": {
    "iso:country":"US",
    "sg:address":"1023 Parkwatch Dr",
    "sg:city":"Ballwin",
    "sg:classifiers":[
        {
            "category":"Retail",
            "subcategory":"Repair Shop",
            "type":"Services"
        }
    ],
    "sg:phone":"+1 636 227 3872",
    "sg:postcode":"63011",
    "sg:province":"MO",
    "wof:name":"CC Carpet & Upholstery Clg",
    "wof:placetype":"venue"
},
  "geometry": {"coordinates":[-90.50709500000001,38.616123],"type":"Point"}
}