{
  "type": "Feature",
  "properties": {
    "iso:country":"US",
    "sg:address":"1500 Thompson Blvd",
    "sg:city":"Sedalia",
    "sg:classifiers":[
        {
            "category":"Building & Trades",
            "subcategory":"Equipment Rental",
            "type":"Services"
        }
    ],
    "sg:phone":"+1 660 826 6409",
    "sg:postcode":"65301",
    "sg:province":"MO",
    "wof:name":"Heritage Village MBL HM Cmnty",
    "wof:placetype":"venue"
},
  "geometry": {"coordinates":[-93.265259,38.700052],"type":"Point"}
}