{
  "type": "Feature",
  "properties": {
    "iso:country":"US",
    "sg:address":"244 Strecker Farms Ct",
    "sg:city":"Ballwin",
    "sg:classifiers":[
        {
            "category":"Building & Trades",
            "subcategory":"Equipment Rental",
            "type":"Services"
        }
    ],
    "sg:phone":"+1 636 273 5990",
    "sg:postcode":"63011",
    "sg:province":"MO",
    "wof:name":"Ren Design & Sewing Co",
    "wof:placetype":"venue"
},
  "geometry": {"coordinates":[-90.606256,38.599789],"type":"Point"}
}