{
  "type": "Feature",
  "properties": {
    "iso:country":"US",
    "sg:address":"1800 W Hwy 116",
    "sg:city":"Plattsburg",
    "sg:classifiers":[
        {
            "category":"Government",
            "subcategory":"Office",
            "type":"Public Place"
        }
    ],
    "sg:phone":"+1 816 539 3741",
    "sg:postcode":"64477",
    "sg:province":"MO",
    "sg:tags":[
        "federal"
    ],
    "wof:name":"Natural Resources Conservation",
    "wof:placetype":"venue"
},
  "geometry": {"coordinates":[-94.475773,39.56509],"type":"Point"}
}