{
  "type": "Feature",
  "properties": {
    "iso:country":"US",
    "sg:address":"11611 E 139th St",
    "sg:city":"Kansas City",
    "sg:classifiers":[
        {
            "category":"Building & Trades",
            "subcategory":"Landscaping Services",
            "type":"Services"
        }
    ],
    "sg:phone":"+1 816 246 4031",
    "sg:postcode":"64149",
    "sg:province":"MO",
    "wof:name":"Obrien Lawn Care",
    "wof:placetype":"venue"
},
  "geometry": {"coordinates":[-94.44560799999999,38.869162],"type":"Point"}
}