{
  "type": "Feature",
  "properties": {
    "iso:country":"US",
    "sg:address":"131 US Hwy 54",
    "sg:city":"Camdenton",
    "sg:classifiers":[
        {
            "category":"Building & Trades",
            "subcategory":"Pest Control",
            "type":"Services"
        }
    ],
    "sg:phone":"+1 573 346 6660",
    "sg:postcode":"65020",
    "sg:province":"MO",
    "wof:name":"Time Pest Management",
    "wof:placetype":"venue"
},
  "geometry": {"coordinates":[-92.74589400000001,38.006826],"type":"Point"}
}