{
  "type": "Feature",
  "properties": {
    "iso:country":"US",
    "sg:address":"5550 US Hwy 63 S",
    "sg:city":"Columbia",
    "sg:classifiers":[
        {
            "category":"Professional",
            "subcategory":"Advertising",
            "type":"Services"
        }
    ],
    "sg:phone":"+1 573 882 8888",
    "sg:postcode":"65201",
    "sg:province":"MO",
    "wof:name":"KMOU",
    "wof:placetype":"venue"
},
  "geometry": {"coordinates":[-92.26463099999999,38.88697],"type":"Point"}
}