{
  "type": "Feature",
  "properties": {
    "iso:country":"US",
    "sg:address":"12401 Byars Rd",
    "sg:city":"Grandview",
    "sg:classifiers":[
        {
            "category":"Organizations",
            "subcategory":"Religious Organization",
            "type":"Services"
        }
    ],
    "sg:phone":"+1 816 966 2200",
    "sg:postcode":"64030",
    "sg:province":"MO",
    "sg:tags":[
        "school",
        "bible",
        "study"
    ],
    "wof:name":"Kairos Bible College",
    "wof:placetype":"venue"
},
  "geometry": {"coordinates":[-94.506434,38.898673],"type":"Point"}
}