{
  "type": "Feature",
  "properties": {
    "iso:country":"US",
    "sg:address":"2835 E Division St",
    "sg:city":"Springfield",
    "sg:classifiers":[
        {
            "category":"Home & Garden",
            "subcategory":"Home Furnishings",
            "type":"Retail Goods"
        }
    ],
    "sg:phone":"+1 417 831 1688",
    "sg:postcode":"65803",
    "sg:province":"MO",
    "sg:tags":[
        "stove",
        "fireplace"
    ],
    "wof:name":"Buck Stove & Spa",
    "wof:placetype":"venue"
},
  "geometry": {"coordinates":[-93.23768699999999,37.224663],"type":"Point"}
}