{
  "type": "Feature",
  "properties": {
    "iso:country":"US",
    "sg:address":"425 Hanley Industrial Ct",
    "sg:city":"Saint Louis",
    "sg:classifiers":[
        {
            "category":"Banks & Credit Unions",
            "subcategory":"Financial Services",
            "type":"Services"
        }
    ],
    "sg:phone":"+1 314 644 4300",
    "sg:postcode":"63144",
    "sg:province":"MO",
    "sg:tags":[
        "operate",
        "commercial",
        "real estate"
    ],
    "wof:name":"Lenor Properties & Inv Co",
    "wof:placetype":"venue"
},
  "geometry": {"coordinates":[-90.33764499999999,38.619198],"type":"Point"}
}