{
  "type": "Feature",
  "properties": {
    "iso:country":"US",
    "sg:address":"19095 Co Rd 483",
    "sg:city":"Puxico",
    "sg:classifiers":[
        {
            "category":"Real Estate",
            "subcategory":"Real Estate Agent",
            "type":"Services"
        }
    ],
    "sg:phone":"+1 573 222 9962",
    "sg:postcode":"63960",
    "sg:province":"MO",
    "sg:tags":[
        "management"
    ],
    "wof:name":"Robert's Property Management",
    "wof:placetype":"venue"
},
  "geometry": {"coordinates":[-90.13327700000001,36.899135],"type":"Point"}
}