{
  "type": "Feature",
  "properties": {
    "iso:country":"US",
    "sg:address":"9764 E Winner Rd",
    "sg:city":"Independence",
    "sg:classifiers":[
        {
            "category":"Building & Trades",
            "subcategory":"Construction",
            "type":"Services"
        }
    ],
    "sg:phone":"+1 816 833 3489",
    "sg:postcode":"64052",
    "sg:province":"MO",
    "sg:tags":[
        "house"
    ],
    "wof:name":"Pierce Jl Construction Inc",
    "wof:placetype":"venue"
},
  "geometry": {"coordinates":[-94.463779,39.093086],"type":"Point"}
}