{
  "type": "Feature",
  "properties": {
    "iso:country":"US",
    "sg:address":"800 Market St",
    "sg:city":"Saint Louis",
    "sg:classifiers":[
        {
            "category":"Banks & Credit Unions",
            "subcategory":"Investment Brokerage",
            "type":"Services"
        }
    ],
    "sg:phone":"+1 314 612 9000",
    "sg:postcode":"63103",
    "sg:province":"MO",
    "sg:tags":[
        "company",
        "management",
        "asset"
    ],
    "wof:name":"Conning Asset Management",
    "wof:placetype":"venue"
},
  "geometry": {"coordinates":[-90.194445,38.626506],"type":"Point"}
}