{
  "type": "Feature",
  "properties": {
    "iso:country":"US",
    "sg:address":"14964 Manor Ridge Dr",
    "sg:city":"Chesterfield",
    "sg:classifiers":[
        {
            "category":"Wholesale",
            "subcategory":"Groceries",
            "type":"Manufacturing & Wholesale Goods"
        }
    ],
    "sg:phone":"+1 636 537 9890",
    "sg:postcode":"63017",
    "sg:province":"MO",
    "sg:tags":[
        "food",
        "products-wholesale"
    ],
    "wof:name":"Public House Beverage",
    "wof:placetype":"venue"
},
  "geometry": {"coordinates":[-90.545111,38.628293],"type":"Point"}
}