{
  "type": "Feature",
  "properties": {
    "iso:country":"US",
    "sg:address":"1100 S 2nd St",
    "sg:city":"Clinton",
    "sg:classifiers":[
        {
            "category":"Banks & Credit Unions",
            "subcategory":"Bank",
            "type":"Services"
        }
    ],
    "sg:phone":"+1 660 885 6091",
    "sg:postcode":"64735",
    "sg:province":"MO",
    "wof:name":"Greater Iowa Credit Union",
    "wof:placetype":"venue"
},
  "geometry": {"coordinates":[-93.774512,38.358554],"type":"Point"}
}