{
  "type": "Feature",
  "properties": {
    "iso:country":"US",
    "sg:address":"11401 Olive Blvd",
    "sg:city":"St Louis",
    "sg:classifiers":[
        {
            "category":"Restaurant",
            "type":"Food & Drink"
        }
    ],
    "sg:phone":"+1 314 432 5454",
    "sg:postcode":"63141",
    "sg:province":"MO",
    "sg:tags":[
        "eating"
    ],
    "sg:website":"www.lonestar.com",
    "wof:name":"Lone Star Steakhouse & Saloon",
    "wof:placetype":"venue"
},
  "geometry": {"coordinates":[-90.43124299999999,38.671259],"type":"Point"}
}