{
  "type": "Feature",
  "properties": {
    "iso:country":"US",
    "sg:address":"231 E 1st St",
    "sg:city":"Hermann",
    "sg:classifiers":[
        {
            "category":"Bars & Pubs",
            "type":"Food & Drink"
        },
        {
            "category":"Restaurant",
            "type":"Food & Drink"
        }
    ],
    "sg:phone":"+1 573 486 5996",
    "sg:postcode":"65041",
    "sg:province":"MO",
    "sg:tags":[
        "tavern"
    ],
    "wof:name":"Mj's Bar & Grill",
    "wof:placetype":"venue"
},
  "geometry": {"coordinates":[-91.427498,38.70643],"type":"Point"}
}