{
  "type": "Feature",
  "properties": {
    "iso:country":"US",
    "sg:address":"1575 N Woodlawn Ave",
    "sg:city":"St Louis",
    "sg:classifiers":[
        {
            "category":"Organizations",
            "subcategory":"Religious Organization",
            "type":"Services"
        }
    ],
    "sg:phone":"+1 314 966 3780",
    "sg:postcode":"63122",
    "sg:province":"MO",
    "sg:tags":[
        "church"
    ],
    "wof:name":"St Genevieve Du Bois Church",
    "wof:placetype":"venue"
},
  "geometry": {"coordinates":[-90.39666099999999,38.609712],"type":"Point"}
}