{
  "type": "Feature",
  "properties": {
    "iso:country":"US",
    "sg:address":"12772 Boenker Ln",
    "sg:city":"Bridgeton",
    "sg:classifiers":[
        {
            "category":"Education",
            "subcategory":"Special Training",
            "type":"Public Place"
        }
    ],
    "sg:phone":"+1 317 739 4222",
    "sg:postcode":"63044",
    "sg:province":"MO",
    "sg:tags":[
        "arson",
        "awareness"
    ],
    "wof:name":"Iaai Eductl Foundation Inc",
    "wof:placetype":"venue"
},
  "geometry": {"coordinates":[-90.43844199999999,38.759939],"type":"Point"}
}