{
  "type": "Feature",
  "properties": {
    "iso:country":"US",
    "sg:address":"4500 E 31 St",
    "sg:city":"Kansas City",
    "sg:classifiers":[
        {
            "category":"Organizations",
            "subcategory":"Religious Organization",
            "type":"Services"
        }
    ],
    "sg:phone":"+1 816 921 6022",
    "sg:postcode":"64128",
    "sg:province":"MO",
    "sg:tags":[
        "church"
    ],
    "wof:name":"Blue Valley Missionary Baptist",
    "wof:placetype":"venue"
},
  "geometry": {"coordinates":[-94.529831,39.069125],"type":"Point"}
}