{
  "type": "Feature",
  "properties": {
    "iso:country":"US",
    "sg:address":"7005 Chalkstone Rd",
    "sg:city":"St Louis",
    "sg:classifiers":[
        {
            "category":"Building & Trades",
            "subcategory":"Plumbing",
            "type":"Services"
        }
    ],
    "sg:phone":"+1 314 293 4000",
    "sg:postcode":"63129",
    "sg:province":"MO",
    "sg:tags":[
        "plumbing",
        "contractor"
    ],
    "wof:name":"Joe's Plumbing Drain & Sewer",
    "wof:placetype":"venue"
},
  "geometry": {"coordinates":[-90.333158,38.438107],"type":"Point"}
}