{
  "type": "Feature",
  "properties": {
    "iso:country":"US",
    "sg:address":"12657 Fee Fee Rd",
    "sg:city":"St Louis",
    "sg:classifiers":[
        {
            "category":"Education",
            "subcategory":"School",
            "type":"Public Place"
        }
    ],
    "sg:phone":"+1 314 415 7000",
    "sg:postcode":"63146",
    "sg:province":"MO",
    "sg:website":"www.pkwy.org",
    "wof:name":"Parkway Instructional Svc Ctr",
    "wof:placetype":"venue"
},
  "geometry": {"coordinates":[-90.458907,38.693868],"type":"Point"}
}