{
  "type": "Feature",
  "properties": {
    "iso:country":"US",
    "sg:address":"5848 Hampton Ave",
    "sg:city":"St Louis",
    "sg:classifiers":[
        {
            "category":"Personal",
            "subcategory":"Beauty Salon",
            "type":"Services"
        }
    ],
    "sg:phone":"+1 314 481 1353",
    "sg:postcode":"63109",
    "sg:province":"MO",
    "sg:tags":[
        "shop"
    ],
    "wof:name":"Adriatic Beauty Salon",
    "wof:placetype":"venue"
},
  "geometry": {"coordinates":[-90.29383300000001,38.578804],"type":"Point"}
}