{
  "type": "Feature",
  "properties": {
    "iso:country":"US",
    "sg:address":"9091 State Line Rd",
    "sg:city":"Kansas City",
    "sg:classifiers":[
        {
            "category":"Real Estate",
            "subcategory":"Real Estate Services",
            "type":"Services"
        }
    ],
    "sg:phone":"+1 816 363 1800",
    "sg:postcode":"64114",
    "sg:province":"MO",
    "sg:tags":[
        "company",
        "title"
    ],
    "wof:name":"Title America",
    "wof:placetype":"venue"
},
  "geometry": {"coordinates":[-94.608023,38.963209],"type":"Point"}
}