{
  "type": "Feature",
  "properties": {
    "iso:country":"US",
    "sg:address":"826 E Prairie Ave",
    "sg:city":"Saint Louis",
    "sg:classifiers":[
        {
            "category":"Food & Beverages",
            "subcategory":"Groceries & Convenience Stores",
            "type":"Retail Goods"
        }
    ],
    "sg:phone":"+1 314 533 3336",
    "sg:postcode":"63107",
    "sg:province":"MO",
    "wof:name":"Tocco Frozen Foods",
    "wof:placetype":"venue"
},
  "geometry": {"coordinates":[-90.206902,38.675598],"type":"Point"}
}