{
  "type": "Feature",
  "properties": {
    "iso:country":"US",
    "sg:address":"4420 N Gretna Rd",
    "sg:city":"Branson",
    "sg:classifiers":[
        {
            "category":"Shopping",
            "subcategory":"Party Supplies",
            "type":"Retail Goods"
        },
        {
            "category":"Personal",
            "type":"Services"
        }
    ],
    "sg:phone":"+1 417 339 3899",
    "sg:postcode":"65616",
    "sg:province":"MO",
    "sg:tags":[
        "decoration",
        "favors",
        "planning",
        "event"
    ],
    "wof:name":"Paper Factory Outlet",
    "wof:placetype":"venue"
},
  "geometry": {"coordinates":[-93.259234,36.659152],"type":"Point"}
}