{
  "type": "Feature",
  "properties": {
    "iso:country":"US",
    "sg:address":"12613 Partridge Run Dr",
    "sg:city":"Florissant",
    "sg:classifiers":[
        {
            "category":"Organizations",
            "subcategory":"Religious Organization",
            "type":"Services"
        }
    ],
    "sg:phone":"+1 314 741 6568",
    "sg:postcode":"63033",
    "sg:province":"MO",
    "sg:tags":[
        "monastery",
        "convent"
    ],
    "wof:name":"Transfiguration Convent",
    "wof:placetype":"venue"
},
  "geometry": {"coordinates":[-90.238134,38.805186],"type":"Point"}
}