{
  "type": "Feature",
  "properties": {
    "iso:country":"US",
    "sg:address":"7 E Benton St",
    "sg:city":"Carrollton",
    "sg:classifiers":[
        {
            "category":"Professional",
            "subcategory":"Lawyer & Legal Services",
            "type":"Services"
        }
    ],
    "sg:phone":"+1 660 542 0306",
    "sg:postcode":"64633",
    "sg:province":"MO",
    "wof:name":"Wendel Law Office",
    "wof:placetype":"venue"
},
  "geometry": {"coordinates":[-93.495999,39.358596],"type":"Point"}
}