{
  "type": "Feature",
  "properties": {
    "iso:country":"US",
    "sg:address":"9807 NW 82 Ter",
    "sg:city":"Kansas City",
    "sg:classifiers":[
        {
            "category":"Retail",
            "subcategory":"Repair Shop",
            "type":"Services"
        }
    ],
    "sg:phone":"+1 816 587 0292",
    "sg:postcode":"64152",
    "sg:province":"MO",
    "wof:name":"Watsons Refinishing",
    "wof:placetype":"venue"
},
  "geometry": {"coordinates":[-94.69580499999999,39.244741],"type":"Point"}
}