{
  "type": "Feature",
  "properties": {
    "iso:country":"US",
    "sg:address":"11 Oak Tree Village St",
    "sg:city":"Doniphan",
    "sg:classifiers":[
        {
            "category":"Shopping",
            "subcategory":"Florist",
            "type":"Retail Goods"
        }
    ],
    "sg:phone":"+1 573 996 2412",
    "sg:postcode":"63935",
    "sg:province":"MO",
    "wof:name":"Bonnie's Flower Lane",
    "wof:placetype":"venue"
},
  "geometry": {"coordinates":[-90.820752,36.633093],"type":"Point"}
}