{
  "type": "Feature",
  "properties": {
    "iso:country":"US",
    "sg:address":"4001 E 137th Ter",
    "sg:city":"Grandview",
    "sg:classifiers":[
        {
            "category":"Retail",
            "subcategory":"Laundry & Dry Cleaning",
            "type":"Services"
        },
        {
            "category":"Building & Trades",
            "subcategory":"Cleaning & Sanitation",
            "type":"Services"
        },
        {
            "category":"Home & Garden",
            "subcategory":"Carpets & Floor Coverings",
            "type":"Retail Goods"
        }
    ],
    "sg:phone":"+1 816 761 6626",
    "sg:postcode":"64030",
    "sg:province":"MO",
    "sg:tags":[
        "cleaner",
        "upholstery",
        "rug"
    ],
    "sg:website":"http://www.certifiedcarpetsystems.com",
    "wof:name":"Certified Carpet Systems Inc",
    "wof:placetype":"venue"
},
  "geometry": {"coordinates":[-94.547892,38.876541],"type":"Point"}
}