{
  "type": "Feature",
  "properties": {
    "iso:country":"US",
    "sg:address":"1006 S Glenstone Ave",
    "sg:city":"Springfield",
    "sg:classifiers":[
        {
            "category":"Professional",
            "subcategory":"Accounting & Tax Preparation",
            "type":"Services"
        }
    ],
    "sg:phone":"+1 417 831 9326",
    "sg:postcode":"65804",
    "sg:province":"MO",
    "sg:tags":[
        "return"
    ],
    "wof:name":"A-1 Tax Service",
    "wof:placetype":"venue"
},
  "geometry": {"coordinates":[-93.262033,37.194617],"type":"Point"}
}