{
  "type": "Feature",
  "properties": {
    "iso:country":"US",
    "sg:address":"1507 Stone St",
    "sg:city":"Columbia",
    "sg:classifiers":[
        {
            "category":"Building & Trades",
            "subcategory":"Construction",
            "type":"Services"
        }
    ],
    "sg:phone":"+1 573 443 0953",
    "sg:postcode":"65201",
    "sg:province":"MO",
    "sg:tags":[
        "contractor"
    ],
    "wof:name":"PM Masonry",
    "wof:placetype":"venue"
},
  "geometry": {"coordinates":[-92.32127699999999,38.967717],"type":"Point"}
}