{
  "type": "Feature",
  "properties": {
    "iso:country":"US",
    "sg:address":"201 W Jackson St",
    "sg:city":"Gallatin",
    "sg:classifiers":[
        {
            "category":"Autos & Motor Vehicles",
            "subcategory":"Auto Supplies",
            "type":"Retail Goods"
        }
    ],
    "sg:phone":"+1 660 663 2622",
    "sg:postcode":"64640",
    "sg:province":"MO",
    "sg:tags":[
        "automobile",
        "parts"
    ],
    "wof:name":"T & D Auto Supply Inc",
    "wof:placetype":"venue"
},
  "geometry": {"coordinates":[-93.96304000000001,39.915467],"type":"Point"}
}