{
  "type": "Feature",
  "properties": {
    "iso:country":"US",
    "sg:address":"7509 Big Bend Blvd",
    "sg:city":"Saint Louis",
    "sg:classifiers":[
        {
            "category":"Health Services",
            "subcategory":"Doctor",
            "type":"Services"
        }
    ],
    "sg:phone":"+1 314 961 3113",
    "sg:postcode":"63119",
    "sg:province":"MO",
    "sg:tags":[
        "podiatrist"
    ],
    "wof:name":"Big Bend Foot Care Center",
    "wof:placetype":"venue"
},
  "geometry": {"coordinates":[-90.328102,38.5994],"type":"Point"}
}