{
  "type": "Feature",
  "properties": {
    "iso:country":"US",
    "sg:address":"211 N Woodlawn Ave",
    "sg:city":"Kirkwood",
    "sg:classifiers":[
        {
            "category":"Social Services",
            "subcategory":"Child Care",
            "type":"Services"
        }
    ],
    "sg:phone":"+1 314 822 5477",
    "sg:postcode":"63122",
    "sg:province":"MO",
    "sg:website":"www.kirkwoodbaptist.org",
    "wof:name":"Kirkwood Baptist Church",
    "wof:placetype":"venue"
},
  "geometry": {"coordinates":[-90.397299,38.583032],"type":"Point"}
}