{
  "type": "Feature",
  "properties": {
    "iso:country":"US",
    "sg:address":"2120 Hord Ave",
    "sg:city":"Saint Louis",
    "sg:classifiers":[
        {
            "category":"Government",
            "subcategory":"Office",
            "type":"Public Place"
        }
    ],
    "sg:phone":"+1 314 388 1164",
    "sg:postcode":"63136",
    "sg:province":"MO",
    "sg:tags":[
        "executive"
    ],
    "wof:name":"City of Jennings",
    "wof:placetype":"venue"
},
  "geometry": {"coordinates":[-90.255394,38.723379],"type":"Point"}
}