{
  "type": "Feature",
  "properties": {
    "addr:full":"1818 State Hwy 291 Harrisonville MO 64701",
    "addr:housenumber":"1818",
    "addr:postcode":"64701",
    "addr:street":"State Hwy 291",
    "iso:country":"US",
    "sg:address":"1818 State Hwy 291",
    "sg:city":"Harrisonville",
    "sg:classifiers":[
        {
            "category":"Shopping",
            "subcategory":"Clothing, Apparel, & Fashions",
            "type":"Retail Goods"
        }
    ],
    "sg:phone":"+1 816 884 1818",
    "sg:postcode":"64701",
    "sg:province":"MO",
    "wof:name":"Cato",
    "wof:placetype":"venue"
},
  "geometry": {"coordinates":[-94.366407,38.668468],"type":"Point"}
}