{
  "type": "Feature",
  "properties": {
    "iso:country":"US",
    "sg:address":"149 Main St",
    "sg:city":"St Elizabeth",
    "sg:classifiers":[
        {
            "category":"Home & Garden",
            "subcategory":"Hardware",
            "type":"Retail Goods"
        }
    ],
    "sg:phone":"+1 573 493 2315",
    "sg:postcode":"65075",
    "sg:province":"MO",
    "wof:name":"MFA Co-Op Assn",
    "wof:placetype":"venue"
},
  "geometry": {"coordinates":[-92.268692,38.255949],"type":"Point"}
}