{
  "type": "Feature",
  "properties": {
    "iso:country":"US",
    "sg:address":"200 NE 54 St",
    "sg:city":"Kansas City",
    "sg:classifiers":[
        {
            "category":"Health Services",
            "subcategory":"Doctor",
            "type":"Services"
        }
    ],
    "sg:phone":"+1 816 455 7400",
    "sg:postcode":"64118",
    "sg:province":"MO",
    "sg:tags":[
        "physician",
        "surgeon"
    ],
    "wof:name":"Creekwood Women's Care",
    "wof:placetype":"venue"
},
  "geometry": {"coordinates":[-94.576522,39.191673],"type":"Point"}
}