{
  "type": "Feature",
  "properties": {
    "iso:country":"US",
    "sg:address":"1436 Continental Dr",
    "sg:city":"Wentzville",
    "sg:classifiers":[
        {
            "category":"Freight",
            "type":"Transportation"
        }
    ],
    "sg:phone":"+1 636 281 2226",
    "sg:postcode":"63385",
    "sg:province":"MO",
    "sg:tags":[
        "mover"
    ],
    "wof:name":"Safe Lock Moving",
    "wof:placetype":"venue"
},
  "geometry": {"coordinates":[-90.83241099999999,38.806694],"type":"Point"}
}