{
  "type": "Feature",
  "properties": {
    "iso:country":"US",
    "sg:address":"3603 Faraon St",
    "sg:city":"St Joseph",
    "sg:classifiers":[
        {
            "category":"Retail",
            "subcategory":"Laundry & Dry Cleaning",
            "type":"Services"
        }
    ],
    "sg:phone":"+1 816 364 6141",
    "sg:postcode":"64506",
    "sg:province":"MO",
    "sg:tags":[
        "cleaners",
        "plant",
        "drycleaning"
    ],
    "wof:name":"East Hills Cleaners & Ldrers",
    "wof:placetype":"venue"
},
  "geometry": {"coordinates":[-94.8036,39.769732],"type":"Point"}
}