{
  "type": "Feature",
  "properties": {
    "iso:country":"US",
    "sg:address":"910 Kehrs Mill Rd",
    "sg:city":"Ballwin",
    "sg:classifiers":[
        {
            "category":"Building & Trades",
            "subcategory":"Cleaning & Sanitation",
            "type":"Services"
        }
    ],
    "sg:phone":"+1 636 527 6243",
    "sg:postcode":"63011",
    "sg:province":"MO",
    "sg:tags":[
        "house"
    ],
    "wof:name":"Manor Maids",
    "wof:placetype":"venue"
},
  "geometry": {"coordinates":[-90.56576200000001,38.607507],"type":"Point"}
}