{
  "type": "Feature",
  "properties": {
    "addr:full":"2351 S Highview Ave Joplin MO 64804",
    "addr:housenumber":"2351",
    "addr:postcode":"64804",
    "addr:street":"S Highview Ave",
    "iso:country":"US",
    "sg:address":"2351 S Highview Ave",
    "sg:city":"Joplin",
    "sg:classifiers":[
        {
            "category":"Banks & Credit Unions",
            "subcategory":"Bank",
            "type":"Services"
        }
    ],
    "sg:phone":"+1 417 659 9259",
    "sg:postcode":"64804",
    "sg:province":"MO",
    "wof:name":"Liberty Bank",
    "wof:placetype":"venue"
},
  "geometry": {"coordinates":[-94.480194,37.065596],"type":"Point"}
}