{
  "type": "Feature",
  "properties": {
    "addr:full":"115 W Pitman St O Fallon MO 63366",
    "addr:housenumber":"115",
    "addr:postcode":"63366",
    "addr:street":"W Pitman St",
    "iso:country":"US",
    "sg:address":"115 W Pitman St",
    "sg:city":"O Fallon",
    "sg:classifiers":[
        {
            "category":"Insurance",
            "subcategory":"Insurance Agent",
            "type":"Services"
        }
    ],
    "sg:phone":"+1 636 379 9170",
    "sg:postcode":"63366",
    "sg:province":"MO",
    "wof:name":"American Family Insurance",
    "wof:placetype":"venue"
},
  "geometry": {"coordinates":[-90.70132599999999,38.806946],"type":"Point"}
}