{
  "type": "Feature",
  "properties": {
    "iso:country":"US",
    "sg:address":"1468 S State Hwy T",
    "sg:city":"Springfield",
    "sg:classifiers":[
        {
            "category":"Wholesale",
            "subcategory":"Machinery & Supplies",
            "type":"Manufacturing & Wholesale Goods"
        }
    ],
    "sg:phone":"+1 417 732 9010",
    "sg:postcode":"65802",
    "sg:province":"MO",
    "wof:name":"Garys",
    "wof:placetype":"venue"
},
  "geometry": {"coordinates":[-93.478144,37.190902],"type":"Point"}
}