{
  "type": "Feature",
  "properties": {
    "iso:country":"US",
    "sg:address":"4583 Hunter Ln",
    "sg:city":"House Springs",
    "sg:classifiers":[
        {
            "category":"Building & Trades",
            "subcategory":"Construction",
            "type":"Services"
        }
    ],
    "sg:phone":"+1 636 375 3500",
    "sg:postcode":"63051",
    "sg:province":"MO",
    "sg:tags":[
        "contractor"
    ],
    "wof:name":"Premier Pool & Spa",
    "wof:placetype":"venue"
},
  "geometry": {"coordinates":[-90.58417799999999,38.411075],"type":"Point"}
}