{
  "type": "Feature",
  "properties": {
    "iso:country":"US",
    "sg:address":"140 Cherry Hill Dr",
    "sg:city":"Belton",
    "sg:classifiers":[
        {
            "category":"Real Estate",
            "subcategory":"Developer",
            "type":"Services"
        }
    ],
    "sg:phone":"+1 816 331 8141",
    "sg:postcode":"64012",
    "sg:province":"MO",
    "wof:name":"Maier Developments Inc",
    "wof:placetype":"venue"
},
  "geometry": {"coordinates":[-94.556309,38.817088],"type":"Point"}
}