{
  "type": "Feature",
  "properties": {
    "iso:country":"US",
    "sg:address":"1007 Jeffco Blvd",
    "sg:city":"Arnold",
    "sg:classifiers":[
        {
            "category":"Wholesale",
            "subcategory":"Petroleum",
            "type":"Manufacturing & Wholesale Goods"
        }
    ],
    "sg:phone":"+1 636 296 6766",
    "sg:postcode":"63010",
    "sg:province":"MO",
    "sg:tags":[
        "bulk",
        "station"
    ],
    "wof:name":"Sinclair Marketing",
    "wof:placetype":"venue"
},
  "geometry": {"coordinates":[-90.37321799999999,38.445492],"type":"Point"}
}