{
  "type": "Feature",
  "properties": {
    "iso:country":"US",
    "sg:address":"2410 Amesbury Dr",
    "sg:city":"Saint Louis",
    "sg:classifiers":[
        {
            "category":"Social Services",
            "subcategory":"Adult Care",
            "type":"Services"
        }
    ],
    "sg:phone":"+1 314 388 3994",
    "sg:postcode":"63136",
    "sg:province":"MO",
    "sg:tags":[
        "residential"
    ],
    "wof:name":"Greatness Is Serving",
    "wof:placetype":"venue"
},
  "geometry": {"coordinates":[-90.243966,38.738666],"type":"Point"}
}