{
  "type": "Feature",
  "properties": {
    "iso:country":"US",
    "sg:address":"132 High Point Dr",
    "sg:city":"Blue Eye",
    "sg:classifiers":[
        {
            "category":"Utilities",
            "subcategory":"Telephone",
            "type":"Services"
        }
    ],
    "sg:phone":"+1 417 779 1487",
    "sg:postcode":"65611",
    "sg:province":"AR",
    "sg:tags":[
        "communications"
    ],
    "wof:name":"B E Stevenson Enterprises",
    "wof:placetype":"venue"
},
  "geometry": {"coordinates":[-93.346598,36.566618],"type":"Point"}
}