{
  "type": "Feature",
  "properties": {
    "iso:country":"US",
    "sg:address":"8051 County Road 735",
    "sg:city":"Gobler",
    "sg:classifiers":[
        {
            "category":"Manufacturing",
            "subcategory":"Food",
            "type":"Manufacturing & Wholesale Goods"
        }
    ],
    "sg:phone":"+1 573 737 2391",
    "sg:postcode":"63849",
    "sg:province":"MO",
    "sg:tags":[
        "product"
    ],
    "wof:name":"Larry Payne",
    "wof:placetype":"venue"
},
  "geometry": {"coordinates":[-90.016137,36.098969],"type":"Point"}
}