{
  "type": "Feature",
  "properties": {
    "iso:country":"US",
    "sg:address":"12700 Southfork Rd",
    "sg:city":"St Louis",
    "sg:classifiers":[
        {
            "category":"Health Services",
            "subcategory":"Hospital",
            "type":"Services"
        }
    ],
    "sg:phone":"+1 314 842 3535",
    "sg:postcode":"63128",
    "sg:province":"MO",
    "wof:name":"South County Ctr",
    "wof:placetype":"venue"
},
  "geometry": {"coordinates":[-90.38267399999999,38.502719],"type":"Point"}
}