{
  "type": "Feature",
  "properties": {
    "iso:country":"US",
    "sg:address":"4618 State Hwy 72",
    "sg:city":"Jackson",
    "sg:classifiers":[
        {
            "category":"Autos & Motor Vehicles",
            "subcategory":"Automobile Sales",
            "type":"Retail Goods"
        }
    ],
    "sg:phone":"+1 573 243 3555",
    "sg:postcode":"63755",
    "sg:province":"MO",
    "sg:tags":[
        "used"
    ],
    "wof:name":"Keele Auto Sales",
    "wof:placetype":"venue"
},
  "geometry": {"coordinates":[-89.725024,37.389413],"type":"Point"}
}