{
  "type": "Feature",
  "properties": {
    "iso:country":"US",
    "sg:address":"4200 Snow",
    "sg:city":"Saint Louis",
    "sg:classifiers":[
        {
            "category":"Social Services",
            "subcategory":"Child Care",
            "type":"Services"
        }
    ],
    "sg:phone":"+1 314 382 9041",
    "sg:postcode":"63101",
    "sg:province":"MO",
    "sg:tags":[
        "day"
    ],
    "sg:website":"www.ywca.org",
    "wof:name":"YWCA",
    "wof:placetype":"venue"
},
  "geometry": {"coordinates":[-90.26960200000001,38.697116],"type":"Point"}
}