{
  "type": "Feature",
  "properties": {
    "iso:country":"US",
    "sg:address":"2502 NW Vivion Rd",
    "sg:city":"Northmoor",
    "sg:classifiers":[
        {
            "category":"Restaurant",
            "type":"Food & Drink"
        }
    ],
    "sg:phone":"+1 816 741 9548",
    "sg:postcode":"64150",
    "sg:province":"MO",
    "sg:tags":[
        "style",
        "family",
        "italian"
    ],
    "sg:website":"http://sorrentorestaurant.vpweb.com",
    "wof:name":"Sorrento's Italian Restaurant & Deli",
    "wof:placetype":"venue"
},
  "geometry": {"coordinates":[-94.608918,39.179387],"type":"Point"}
}