{
  "type": "Feature",
  "properties": {
    "iso:country":"US",
    "sg:address":"751 Sappington Bridge Rd",
    "sg:city":"Sullivan",
    "sg:classifiers":[
        {
            "category":"Health Services",
            "subcategory":"Doctor",
            "type":"Services"
        }
    ],
    "sg:phone":"+1 573 468 1352",
    "sg:postcode":"63080",
    "sg:province":"MO",
    "sg:tags":[
        "physician",
        "surgeon"
    ],
    "wof:name":"Peeples David M MD",
    "wof:placetype":"venue"
},
  "geometry": {"coordinates":[-91.16958099999999,38.194228],"type":"Point"}
}