{
  "type": "Feature",
  "properties": {
    "iso:country":"US",
    "sg:address":"3909 Harrison St",
    "sg:city":"Kansas City",
    "sg:classifiers":[
        {
            "category":"Organizations",
            "subcategory":"Religious Organization",
            "type":"Services"
        }
    ],
    "sg:phone":"+1 816 561 8512",
    "sg:postcode":"64110",
    "sg:province":"MO",
    "sg:website":"www.stjameskc.com",
    "wof:name":"St James Church",
    "wof:placetype":"venue"
},
  "geometry": {"coordinates":[-94.573329,39.054503],"type":"Point"}
}