{
  "type": "Feature",
  "properties": {
    "iso:country":"US",
    "sg:address":"3192 W Jackson Rd",
    "sg:city":"Nixa",
    "sg:classifiers":[
        {
            "category":"Autos & Motor Vehicles",
            "subcategory":"Auto Supplies",
            "type":"Retail Goods"
        },
        {
            "category":"Retail",
            "subcategory":"Auto Repair",
            "type":"Services"
        }
    ],
    "sg:phone":"+1 417 581 5103",
    "sg:postcode":"65714",
    "sg:province":"MO",
    "sg:tags":[
        "body",
        "lettering",
        "automobile",
        "truck",
        "painting",
        "repairing"
    ],
    "sg:website":"http://www.christiancountycollision.com",
    "wof:name":"Christian Co Collision Re",
    "wof:placetype":"venue"
},
  "geometry": {"coordinates":[-93.248217,37.025927],"type":"Point"}
}