{
  "type": "Feature",
  "properties": {
    "iso:country":"US",
    "sg:address":"1219 NE Rice Rd",
    "sg:city":"Lees Summit",
    "sg:classifiers":[
        {
            "category":"Personal",
            "subcategory":"Beauty Salon",
            "type":"Services"
        }
    ],
    "sg:phone":"+1 816 554 7673",
    "sg:postcode":"64086",
    "sg:province":"MO",
    "wof:name":"Untouchable Cuts Hair Salon",
    "wof:placetype":"venue"
},
  "geometry": {"coordinates":[-94.35919800000001,38.936825],"type":"Point"}
}