{
  "type": "Feature",
  "properties": {
    "iso:country":"US",
    "sg:address":"8907 Saint Charles Rock Rd",
    "sg:city":"Saint Louis",
    "sg:classifiers":[
        {
            "category":"Real Estate",
            "subcategory":"Developer",
            "type":"Services"
        }
    ],
    "sg:phone":"+1 314 428 4065",
    "sg:postcode":"63114",
    "sg:province":"MO",
    "sg:tags":[
        "cemetery"
    ],
    "wof:name":"Cemetery Sales Inc",
    "wof:placetype":"venue"
},
  "geometry": {"coordinates":[-90.351705,38.711551],"type":"Point"}
}