{
  "type": "Feature",
  "properties": {
    "iso:country":"US",
    "sg:address":"18772 State Hwy 51",
    "sg:city":"Qulin",
    "sg:classifiers":[
        {
            "category":"Farming",
            "subcategory":"Farm",
            "type":"Manufacturing & Wholesale Goods"
        }
    ],
    "sg:phone":"+1 573 328 4351",
    "sg:postcode":"63961",
    "sg:province":"MO",
    "sg:tags":[
        "crop",
        "general"
    ],
    "wof:name":"Louis Melton",
    "wof:placetype":"venue"
},
  "geometry": {"coordinates":[-90.248228,36.535368],"type":"Point"}
}