{
  "type": "Feature",
  "properties": {
    "iso:country":"US",
    "sg:address":"317 Barnes Rd",
    "sg:city":"Elsberry",
    "sg:phone":"+1 573 898 5346",
    "sg:postcode":"63343",
    "sg:province":"MO",
    "sg:tags":[
        "farm",
        "corn",
        "soybean"
    ],
    "wof:name":"Jimmy Barnes",
    "wof:placetype":"venue"
},
  "geometry": {"coordinates":[-90.848332,39.190209],"type":"Point"}
}