{
  "type": "Feature",
  "properties": {
    "iso:country":"US",
    "sg:address":"853 Mennemeyer Rd",
    "sg:city":"Troy",
    "sg:classifiers":[
        {
            "category":"Building & Trades",
            "subcategory":"Construction",
            "type":"Services"
        }
    ],
    "sg:phone":"+1 636 462 6776",
    "sg:postcode":"63379",
    "sg:province":"MO",
    "sg:tags":[
        "drywall",
        "contractor"
    ],
    "wof:name":"G G Drywall",
    "wof:placetype":"venue"
},
  "geometry": {"coordinates":[-91.01290899999999,38.93367],"type":"Point"}
}