{
  "type": "Feature",
  "properties": {
    "iso:country":"US",
    "sg:address":"1350 E Kingsley St",
    "sg:city":"Springfield",
    "sg:classifiers":[
        {
            "category":"Professional",
            "type":"Services"
        }
    ],
    "sg:phone":"+1 417 889 6800",
    "sg:postcode":"65804",
    "sg:province":"MO",
    "sg:tags":[
        "establishment"
    ],
    "wof:name":"Pba",
    "wof:placetype":"venue"
},
  "geometry": {"coordinates":[-93.273616,37.140222],"type":"Point"}
}