{
  "type": "Feature",
  "properties": {
    "iso:country":"US",
    "sg:address":"100 Grant Street",
    "sg:city":"Carthage",
    "sg:classifiers":[
        {
            "category":"Building & Trades",
            "subcategory":"Landscaping Services",
            "type":"Services"
        },
        {
            "category":"Manufacturing",
            "subcategory":"Buildings",
            "type":"Manufacturing & Wholesale Goods"
        },
        {
            "category":"Building & Trades",
            "subcategory":"Construction",
            "type":"Services"
        },
        {
            "category":"Community Center",
            "subcategory":"Social",
            "type":"Public Place"
        }
    ],
    "sg:phone":"+1 417 358 8778",
    "sg:postcode":"64836",
    "sg:province":"MO",
    "sg:tags":[
        "jacking",
        "roofing",
        "industrial",
        "leak",
        "metal",
        "contractor",
        "mud",
        "contractors-commercial",
        "detecting"
    ],
    "wof:name":"Henson Metal Building Supply",
    "wof:placetype":"venue"
},
  "geometry": {"coordinates":[-94.309647,37.178612],"type":"Point"}
}