{
  "type": "Feature",
  "properties": {
    "iso:country":"US",
    "sg:address":"456 Township Line Rd",
    "sg:city":"Poplar Bluff",
    "sg:classifiers":[
        {
            "category":"Organizations",
            "subcategory":"Religious Organization",
            "type":"Services"
        }
    ],
    "sg:phone":"+1 573 686 6119",
    "sg:postcode":"63901",
    "sg:province":"MO",
    "sg:tags":[
        "church"
    ],
    "wof:name":"Living Word Baptist Church",
    "wof:placetype":"venue"
},
  "geometry": {"coordinates":[-90.46528000000001,36.737305],"type":"Point"}
}