{
  "type": "Feature",
  "properties": {
    "iso:country":"US",
    "sg:address":"31768 Lake St",
    "sg:city":"Macon",
    "sg:classifiers":[
        {
            "category":"Farming",
            "subcategory":"Farm",
            "type":"Manufacturing & Wholesale Goods"
        }
    ],
    "sg:phone":"+1 660 385 4468",
    "sg:postcode":"63552",
    "sg:province":"MO",
    "wof:name":"Lakeside Farm",
    "wof:placetype":"venue"
},
  "geometry": {"coordinates":[-92.448155,39.769925],"type":"Point"}
}