{
  "type": "Feature",
  "properties": {
    "iso:country":"US",
    "sg:address":"201 Lynne Dr",
    "sg:city":"Willard",
    "sg:classifiers":[
        {
            "category":"Farming",
            "subcategory":"Nursery",
            "type":"Manufacturing & Wholesale Goods"
        }
    ],
    "sg:phone":"+1 417 742 0405",
    "sg:postcode":"65781",
    "sg:province":"MO",
    "sg:tags":[
        "greenhouse"
    ],
    "wof:name":"A Perfect Garden",
    "wof:placetype":"venue"
},
  "geometry": {"coordinates":[-93.43584,37.30531],"type":"Point"}
}