{
  "type": "Feature",
  "properties": {
    "iso:country":"US",
    "sg:address":"2214 Cherokee St",
    "sg:city":"Saint Louis",
    "sg:classifiers":[
        {
            "category":"Shopping",
            "subcategory":"Antiques",
            "type":"Retail Goods"
        }
    ],
    "sg:phone":"+1 314 664 2627",
    "sg:postcode":"63118",
    "sg:province":"MO",
    "wof:name":"Martin's Galleries",
    "wof:placetype":"venue"
},
  "geometry": {"coordinates":[-90.223356,38.592889],"type":"Point"}
}