{
  "type": "Feature",
  "properties": {
    "iso:country":"US",
    "sg:address":"20 SW Persels Rd",
    "sg:city":"Lees Summit",
    "sg:classifiers":[
        {
            "category":"Professional",
            "subcategory":"Art Services",
            "type":"Services"
        }
    ],
    "sg:phone":"+1 816 554 2718",
    "sg:postcode":"64081",
    "sg:province":"MO",
    "sg:tags":[
        "graphic",
        "commercial",
        "printing",
        "design",
        "screening",
        "silk"
    ],
    "wof:name":"Modern Systems Inc",
    "wof:placetype":"venue"
},
  "geometry": {"coordinates":[-94.37730000000001,38.89623],"type":"Point"}
}