{
  "type": "Feature",
  "properties": {
    "iso:country":"US",
    "sg:address":"8627 State Hwy 21",
    "sg:city":"Hillsboro",
    "sg:classifiers":[
        {
            "category":"Autos & Motor Vehicles",
            "subcategory":"Motorcycle Sales",
            "type":"Retail Goods"
        }
    ],
    "sg:phone":"+1 636 789 2190",
    "sg:postcode":"63050",
    "sg:province":"MO",
    "sg:tags":[
        "scooter"
    ],
    "wof:name":"Jireh",
    "wof:placetype":"venue"
},
  "geometry": {"coordinates":[-90.532697,38.309505],"type":"Point"}
}