{
  "type": "Feature",
  "properties": {
    "iso:country":"US",
    "sg:address":"7400 Pagedale Industrial Ct",
    "sg:city":"St Louis",
    "sg:classifiers":[
        {
            "category":"Building & Trades",
            "subcategory":"Construction",
            "type":"Services"
        }
    ],
    "sg:phone":"+1 314 863 2326",
    "sg:postcode":"63133",
    "sg:province":"MO",
    "sg:tags":[
        "concrete",
        "contractor"
    ],
    "sg:website":"www.cecoconcrete.com",
    "wof:name":"Ceco Corp",
    "wof:placetype":"venue"
},
  "geometry": {"coordinates":[-90.31495200000001,38.684289],"type":"Point"}
}