{
  "type": "Feature",
  "properties": {
    "iso:country":"US",
    "sg:address":"4484 S Noland Rd",
    "sg:city":"Independence",
    "sg:classifiers":[
        {
            "category":"Home & Garden",
            "subcategory":"Garden Supply",
            "type":"Retail Goods"
        },
        {
            "category":"Shopping",
            "subcategory":"Party Supplies",
            "type":"Retail Goods"
        },
        {
            "category":"Shopping",
            "subcategory":"Bridal",
            "type":"Retail Goods"
        },
        {
            "category":"Shopping",
            "subcategory":"Gifts & Souvenirs",
            "type":"Retail Goods"
        },
        {
            "category":"Shopping",
            "subcategory":"Florist",
            "type":"Retail Goods"
        }
    ],
    "sg:phone":"+1 816 478 7868",
    "sg:postcode":"64055",
    "sg:province":"MO",
    "sg:tags":[
        "shop",
        "plant",
        "delivery",
        "balloons-retail",
        "wedding",
        "basket"
    ],
    "sg:website":"http://www.cairnsflowers.com",
    "wof:name":"Cairns Flowers",
    "wof:placetype":"venue"
},
  "geometry": {"coordinates":[-94.41543900000001,39.039281],"type":"Point"}
}