{
  "type": "Feature",
  "properties": {
    "iso:country":"US",
    "sg:address":"719 S Main St",
    "sg:city":"Joplin",
    "sg:classifiers":[
        {
            "category":"Shopping",
            "subcategory":"Clothing, Apparel, & Fashions",
            "type":"Retail Goods"
        }
    ],
    "sg:phone":"+1 417 659 9913",
    "sg:postcode":"64801",
    "sg:province":"MO",
    "wof:name":"Day Dream & Night Things Btq",
    "wof:placetype":"venue"
},
  "geometry": {"coordinates":[-94.51346700000001,37.083008],"type":"Point"}
}