{
  "type": "Feature",
  "properties": {
    "iso:country":"US",
    "sg:address":"20158 Eisenbeis Bottom Rd",
    "sg:city":"Sainte Genevieve",
    "sg:classifiers":[
        {
            "category":"Farming",
            "subcategory":"Livestock Farm",
            "type":"Manufacturing & Wholesale Goods"
        }
    ],
    "sg:phone":"+1 573 883 2992",
    "sg:postcode":"63670",
    "sg:province":"MO",
    "sg:tags":[
        "beef",
        "feedlot",
        "cattle"
    ],
    "wof:name":"Oliver Gegg",
    "wof:placetype":"venue"
},
  "geometry": {"coordinates":[-90.086693,37.877353],"type":"Point"}
}