{
  "type": "Feature",
  "properties": {
    "iso:country":"US",
    "sg:address":"8030 Ward Parkway Plz",
    "sg:city":"Kansas City",
    "sg:classifiers":[
        {
            "category":"Education",
            "subcategory":"School",
            "type":"Public Place"
        }
    ],
    "sg:phone":"+1 816 361 1200",
    "sg:postcode":"64114",
    "sg:province":"MO",
    "sg:tags":[
        "organization",
        "religious"
    ],
    "wof:name":"Calvary Lutheran School",
    "wof:placetype":"venue"
},
  "geometry": {"coordinates":[-94.604078,38.982333],"type":"Point"}
}