{
  "type": "Feature",
  "properties": {
    "iso:country":"US",
    "sg:address":"14524 Tramore Dr",
    "sg:city":"Chesterfield",
    "sg:classifiers":[
        {
            "category":"Banks & Credit Unions",
            "subcategory":"Financial Services",
            "type":"Services"
        }
    ],
    "sg:phone":"+1 636 527 5811",
    "sg:postcode":"63017",
    "sg:province":"MO",
    "sg:tags":[
        "dry",
        "sugar",
        "co",
        "milk",
        "investment"
    ],
    "wof:name":"Firestone Investments Limited",
    "wof:placetype":"venue"
},
  "geometry": {"coordinates":[-90.52250100000001,38.626233],"type":"Point"}
}