{
  "type": "Feature",
  "properties": {
    "iso:country":"US",
    "sg:address":"3011 State Hwy 291",
    "sg:city":"Independence",
    "sg:classifiers":[
        {
            "category":"Wholesale",
            "subcategory":"Hardware",
            "type":"Manufacturing & Wholesale Goods"
        }
    ],
    "sg:phone":"+1 816 478 4166",
    "sg:postcode":"64057",
    "sg:province":"MO",
    "sg:tags":[
        "fastener"
    ],
    "wof:name":"Quality Fastners Inc",
    "wof:placetype":"venue"
},
  "geometry": {"coordinates":[-94.37585799999999,39.067012],"type":"Point"}
}