{
  "type": "Feature",
  "properties": {
    "iso:country":"US",
    "sg:address":"6811 Parker Rd",
    "sg:city":"Florissant",
    "sg:classifiers":[
        {
            "category":"Restaurant",
            "type":"Food & Drink"
        }
    ],
    "sg:phone":"+1 314 741 5544",
    "sg:postcode":"63033",
    "sg:province":"MO",
    "wof:name":"Potnars Fish & Grill",
    "wof:placetype":"venue"
},
  "geometry": {"coordinates":[-90.23437800000001,38.796317],"type":"Point"}
}