{
  "type": "Feature",
  "properties": {
    "iso:country":"US",
    "sg:address":"3874 E Jackson Blvd",
    "sg:city":"Jackson",
    "sg:classifiers":[
        {
            "category":"Health Services",
            "subcategory":"Chiropractor",
            "type":"Services"
        }
    ],
    "sg:phone":"+1 573 243 8983",
    "sg:postcode":"63755",
    "sg:province":"MO",
    "wof:name":"Andrews Chiropractic Center",
    "wof:placetype":"venue"
},
  "geometry": {"coordinates":[-89.62270700000001,37.359057],"type":"Point"}
}