{
  "type": "Feature",
  "properties": {
    "iso:country":"US",
    "sg:address":"214 Church St",
    "sg:city":"O Fallon",
    "sg:classifiers":[
        {
            "category":"Professional",
            "subcategory":"Lawyer & Legal Services",
            "type":"Services"
        }
    ],
    "sg:phone":"+1 636 978 1734",
    "sg:postcode":"63366",
    "sg:province":"MO",
    "wof:name":"Nesslage Larry D",
    "wof:placetype":"venue"
},
  "geometry": {"coordinates":[-90.70283499999999,38.808602],"type":"Point"}
}