{
  "type": "Feature",
  "properties": {
    "iso:country":"US",
    "sg:address":"5777 Westwood Dr",
    "sg:city":"Saint Charles",
    "sg:classifiers":[
        {
            "category":"Manufacturing",
            "subcategory":"Printing",
            "type":"Manufacturing & Wholesale Goods"
        }
    ],
    "sg:phone":"+1 636 329 1390",
    "sg:postcode":"63304",
    "sg:province":"MO",
    "wof:name":"Adhere Label Products LLC",
    "wof:placetype":"venue"
},
  "geometry": {"coordinates":[-90.668612,38.720805],"type":"Point"}
}