{
  "type": "Feature",
  "properties": {
    "iso:country":"US",
    "sg:address":"407 W Pine St",
    "sg:city":"Raymore",
    "sg:classifiers":[
        {
            "category":"Restaurant",
            "type":"Food & Drink"
        }
    ],
    "sg:phone":"+1 816 331 4528",
    "sg:postcode":"64083",
    "sg:province":"MO",
    "sg:tags":[
        "catering"
    ],
    "wof:name":"Affordable Elegance Inc",
    "wof:placetype":"venue"
},
  "geometry": {"coordinates":[-94.45683200000001,38.808456],"type":"Point"}
}