{
  "type": "Feature",
  "properties": {
    "iso:country":"US",
    "sg:address":"908 Woodridge Ln",
    "sg:city":"Liberty",
    "sg:classifiers":[
        {
            "category":"Professional",
            "subcategory":"Business Services",
            "type":"Services"
        }
    ],
    "sg:phone":"+1 816 792 8464",
    "sg:postcode":"64068",
    "sg:province":"MO",
    "wof:name":"Dacor Enterprises",
    "wof:placetype":"venue"
},
  "geometry": {"coordinates":[-94.431585,39.257075],"type":"Point"}
}