{
  "type": "Feature",
  "properties": {
    "iso:country":"US",
    "sg:address":"35 N Central Ave",
    "sg:city":"St Louis",
    "sg:classifiers":[
        {
            "category":"Shopping",
            "subcategory":"Computers & Home Electronics",
            "type":"Retail Goods"
        }
    ],
    "sg:phone":"+1 314 721 7210",
    "sg:postcode":"63105",
    "sg:province":"MO",
    "sg:tags":[
        "software"
    ],
    "sg:website":"www.primediam.com",
    "wof:name":"Prime Diam",
    "wof:placetype":"venue"
},
  "geometry": {"coordinates":[-90.33821399999999,38.651197],"type":"Point"}
}