{
  "type": "Feature",
  "properties": {
    "iso:country":"US",
    "sg:address":"166 W Main St",
    "sg:city":"Kahoka",
    "sg:classifiers":[
        {
            "category":"Health Services",
            "subcategory":"Clinic",
            "type":"Services"
        }
    ],
    "sg:phone":"+1 660 727 2388",
    "sg:postcode":"63445",
    "sg:province":"MO",
    "sg:tags":[
        "home"
    ],
    "wof:name":"Premier Home Health Care Inc",
    "wof:placetype":"venue"
},
  "geometry": {"coordinates":[-91.720868,40.420415],"type":"Point"}
}