{
  "type": "Feature",
  "properties": {
    "iso:country":"US",
    "sg:address":"232 NW Parkway Rd",
    "sg:city":"Kansas City",
    "sg:classifiers":[
        {
            "category":"Manufacturing",
            "subcategory":"Paper Products",
            "type":"Manufacturing & Wholesale Goods"
        }
    ],
    "sg:phone":"+1 816 746 0808",
    "sg:postcode":"64150",
    "sg:province":"MO",
    "sg:tags":[
        "converted",
        "mfg"
    ],
    "wof:name":"Green Bay Packaging Inc",
    "wof:placetype":"venue"
},
  "geometry": {"coordinates":[-94.628563,39.171196],"type":"Point"}
}