{
  "type": "Feature",
  "properties": {
    "iso:country":"US",
    "sg:address":"1287 Polo Lake Dr",
    "sg:city":"Ellisville",
    "sg:classifiers":[
        {
            "category":"Home & Garden",
            "subcategory":"Carpets & Floor Coverings",
            "type":"Retail Goods"
        }
    ],
    "sg:phone":"+1 636 527 3639",
    "sg:postcode":"63021",
    "sg:province":"MO",
    "sg:tags":[
        "hardwood"
    ],
    "sg:website":"http://www.nhance.com/der",
    "wof:name":"Nhance Wood Renewal",
    "wof:placetype":"venue"
},
  "geometry": {"coordinates":[-90.590019,38.584489],"type":"Point"}
}