{
  "type": "Feature",
  "properties": {
    "iso:country":"US",
    "sg:address":"9803 N Outer Rd",
    "sg:city":"Dudley",
    "sg:phone":"+1 573 624 2628",
    "sg:postcode":"63936",
    "sg:province":"MO",
    "sg:tags":[
        "farm",
        "grain",
        "cash"
    ],
    "wof:name":"D Cunningham",
    "wof:placetype":"venue"
},
  "geometry": {"coordinates":[-90.111114,36.795196],"type":"Point"}
}