{
  "type": "Feature",
  "properties": {
    "iso:country":"US",
    "sg:address":"1900 Main St",
    "sg:city":"Kansas City",
    "sg:classifiers":[
        {
            "category":"Restaurant",
            "type":"Food & Drink"
        }
    ],
    "sg:menulink":"http://www.allmenus.com/mo/kaw/10972-zin-restaurant/menu/",
    "sg:phone":"+1 816 527 0120",
    "sg:postcode":"64108",
    "sg:province":"MO",
    "sg:tags":[
        "american"
    ],
    "wof:name":"Zin Restaurant",
    "wof:placetype":"venue"
},
  "geometry": {"coordinates":[-94.583652,39.090323],"type":"Point"}
}