{
  "type": "Feature",
  "properties": {
    "iso:country":"US",
    "sg:address":"613 Hardwick St",
    "sg:city":"Kansas City",
    "sg:classifiers":[
        {
            "category":"Farming",
            "subcategory":"Farm",
            "type":"Manufacturing & Wholesale Goods"
        }
    ],
    "sg:phone":"+1 816 455 3060",
    "sg:postcode":"64161",
    "sg:province":"MO",
    "sg:tags":[
        "crop",
        "general"
    ],
    "wof:name":"Jajade Farms",
    "wof:placetype":"venue"
},
  "geometry": {"coordinates":[-94.451249,39.162354],"type":"Point"}
}