{
  "type": "Feature",
  "properties": {
    "iso:country":"US",
    "sg:address":"15 Willow Dr",
    "sg:city":"Charleston",
    "sg:classifiers":[
        {
            "category":"Professional",
            "subcategory":"Lawyer & Legal Services",
            "type":"Services"
        }
    ],
    "sg:phone":"+1 573 683 6413",
    "sg:postcode":"63834",
    "sg:province":"MO",
    "sg:tags":[
        "attorney",
        "practice"
    ],
    "wof:name":"Michael O'rourke Atty",
    "wof:placetype":"venue"
},
  "geometry": {"coordinates":[-89.349411,36.932298],"type":"Point"}
}