{
  "type": "Feature",
  "properties": {
    "iso:country":"US",
    "sg:address":"120 S Washington St",
    "sg:city":"Nevada",
    "sg:classifiers":[
        {
            "category":"Health Services",
            "subcategory":"Optometrist",
            "type":"Services"
        }
    ],
    "sg:phone":"+1 417 667 2560",
    "sg:postcode":"64772",
    "sg:province":"MO",
    "wof:name":"Nevada Optometric Ctr",
    "wof:placetype":"venue"
},
  "geometry": {"coordinates":[-94.35539,37.837939],"type":"Point"}
}