{
  "type": "Feature",
  "properties": {
    "iso:country":"US",
    "sg:address":"502 State Hwy 47",
    "sg:city":"Warrenton",
    "sg:classifiers":[
        {
            "category":"Insurance",
            "subcategory":"Insurance Agent",
            "type":"Services"
        }
    ],
    "sg:phone":"+1 636 456 2790",
    "sg:postcode":"63383",
    "sg:province":"MO",
    "wof:name":"Janet Bradshaw Financial Servi",
    "wof:placetype":"venue"
},
  "geometry": {"coordinates":[-91.14202299999999,38.816918],"type":"Point"}
}