{
  "type": "Feature",
  "properties": {
    "iso:country":"US",
    "sg:address":"402 S Washington St",
    "sg:city":"Chillicothe",
    "sg:classifiers":[
        {
            "category":"Government",
            "subcategory":"Office",
            "type":"Public Place"
        }
    ],
    "sg:phone":"+1 660 646 0902",
    "sg:postcode":"64601",
    "sg:province":"MO",
    "sg:tags":[
        "federal"
    ],
    "wof:name":"Natural Resources Conservation",
    "wof:placetype":"venue"
},
  "geometry": {"coordinates":[-93.55295599999999,39.783193],"type":"Point"}
}