{
  "type": "Feature",
  "properties": {
    "iso:country":"US",
    "sg:address":"611 Main St",
    "sg:city":"Troy",
    "sg:classifiers":[
        {
            "category":"Organizations",
            "subcategory":"Community Association",
            "type":"Services"
        }
    ],
    "sg:phone":"+1 636 528 6634",
    "sg:postcode":"63379",
    "sg:province":"MO",
    "sg:tags":[
        "fraternal"
    ],
    "wof:name":"Troy Masonic Lodge",
    "wof:placetype":"venue"
},
  "geometry": {"coordinates":[-90.980672,38.978279],"type":"Point"}
}