{
  "type": "Feature",
  "properties": {
    "iso:country":"US",
    "sg:address":"9012 Saint Charles Rock Rd",
    "sg:city":"St Louis",
    "sg:classifiers":[
        {
            "category":"Shopping",
            "subcategory":"Computers & Home Electronics",
            "type":"Retail Goods"
        }
    ],
    "sg:phone":"+1 314 733 0211",
    "sg:postcode":"63114",
    "sg:province":"MO",
    "sg:tags":[
        "game",
        "video"
    ],
    "wof:name":"EB Games",
    "wof:placetype":"venue"
},
  "geometry": {"coordinates":[-90.354287,38.712813],"type":"Point"}
}