{
  "type": "Feature",
  "properties": {
    "iso:country":"US",
    "sg:address":"70 Black Jack Ct",
    "sg:city":"Florissant",
    "sg:classifiers":[
        {
            "category":"Retail",
            "subcategory":"Veterinary Services",
            "type":"Services"
        }
    ],
    "sg:phone":"+1 314 741 7800",
    "sg:postcode":"63033",
    "sg:province":"MO",
    "sg:tags":[
        "pet",
        "clinic",
        "for"
    ],
    "wof:name":"North County Animal Clinic",
    "wof:placetype":"venue"
},
  "geometry": {"coordinates":[-90.26642,38.792512],"type":"Point"}
}