{
  "type": "Feature",
  "properties": {
    "iso:country":"US",
    "sg:address":"1116 N Vandeventer St",
    "sg:city":"Kennett",
    "sg:classifiers":[
        {
            "category":"Restaurant",
            "type":"Food & Drink"
        }
    ],
    "sg:phone":"+1 573 717 1559",
    "sg:postcode":"63857",
    "sg:province":"MO",
    "wof:name":"Murl's Diner",
    "wof:placetype":"venue"
},
  "geometry": {"coordinates":[-90.060211,36.248667],"type":"Point"}
}