{
  "type": "Feature",
  "properties": {
    "iso:country":"US",
    "sg:address":"1071 Dautel Ln",
    "sg:city":"St Louis",
    "sg:classifiers":[
        {
            "category":"Retail",
            "subcategory":"Portrait Studio",
            "type":"Services"
        }
    ],
    "sg:phone":"+1 314 995 7017",
    "sg:postcode":"63146",
    "sg:province":"MO",
    "sg:tags":[
        "photo",
        "photography",
        "commercial",
        "photographer"
    ],
    "wof:name":"Allen Weintrop Photography Inc",
    "wof:placetype":"venue"
},
  "geometry": {"coordinates":[-90.422027,38.67558],"type":"Point"}
}