{
  "type": "Feature",
  "properties": {
    "iso:country":"US",
    "sg:address":"14 Catfish Rd",
    "sg:city":"Tuscumbia",
    "sg:phone":"+1 573 369 2616",
    "sg:postcode":"65082",
    "sg:province":"MO",
    "sg:tags":[
        "farm",
        "soybean"
    ],
    "wof:name":"Greg Snodgrass",
    "wof:placetype":"venue"
},
  "geometry": {"coordinates":[-92.46469399999999,38.266046],"type":"Point"}
}