{
  "type": "Feature",
  "properties": {
    "iso:country":"US",
    "sg:address":"23378 Smasal Rd",
    "sg:city":"Sedalia",
    "sg:classifiers":[
        {
            "category":"Farming",
            "subcategory":"Dairy Farm",
            "type":"Manufacturing & Wholesale Goods"
        }
    ],
    "sg:phone":"+1 660 826 6838",
    "sg:postcode":"65301",
    "sg:province":"MO",
    "wof:name":"Wilken & Wilken",
    "wof:placetype":"venue"
},
  "geometry": {"coordinates":[-93.26146799999999,38.593029],"type":"Point"}
}