{
  "type": "Feature",
  "properties": {
    "iso:country":"US",
    "sg:address":"1002 N Mill St",
    "sg:city":"Festus",
    "sg:classifiers":[
        {
            "category":"Building & Trades",
            "subcategory":"Equipment Rental",
            "type":"Services"
        }
    ],
    "sg:phone":"+1 636 933 1783",
    "sg:postcode":"63028",
    "sg:province":"MO",
    "sg:tags":[
        "aircraft",
        "leasing",
        "charter"
    ],
    "wof:name":"Multi-Aero Inc",
    "wof:placetype":"venue"
},
  "geometry": {"coordinates":[-90.397977,38.23019],"type":"Point"}
}