{
  "type": "Feature",
  "properties": {
    "iso:country":"US",
    "sg:address":"139 Nall Rd",
    "sg:city":"Buffalo",
    "sg:classifiers":[
        {
            "category":"Retail",
            "subcategory":"Veterinary Services",
            "type":"Services"
        }
    ],
    "sg:phone":"+1 417 345 2579",
    "sg:postcode":"65672",
    "sg:province":"MO",
    "wof:name":"Neill Department Services PC",
    "wof:placetype":"venue"
},
  "geometry": {"coordinates":[-93.296059,36.577559],"type":"Point"}
}