{
  "type": "Feature",
  "properties": {
    "addr:full":"4579 Hunter Ln House Springs MO 63051",
    "addr:housenumber":"4579",
    "addr:postcode":"63051",
    "addr:street":"Hunter Ln",
    "iso:country":"US",
    "sg:address":"4579 Hunter Ln",
    "sg:city":"House Springs",
    "sg:classifiers":[
        {
            "category":"Sports & Exercise",
            "subcategory":"Gym",
            "type":"Entertainment"
        }
    ],
    "sg:phone":"+1 636 375 0051",
    "sg:postcode":"63051",
    "sg:province":"MO",
    "sg:tags":[
        "club",
        "health",
        "studio",
        "gymnasium"
    ],
    "wof:name":"Curves For Women",
    "wof:placetype":"venue"
},
  "geometry": {"coordinates":[-90.584127,38.411184],"type":"Point"}
}