{
  "type": "Feature",
  "properties": {
    "iso:country":"US",
    "sg:address":"231 E Union St",
    "sg:city":"Pacific",
    "sg:classifiers":[
        {
            "category":"Retail",
            "subcategory":"Funeral Services",
            "type":"Services"
        }
    ],
    "sg:phone":"+1 636 257 2730",
    "sg:postcode":"63069",
    "sg:province":"MO",
    "sg:tags":[
        "director"
    ],
    "wof:name":"Nieburg-Vitt Thiebes Fnrl Home",
    "wof:placetype":"venue"
},
  "geometry": {"coordinates":[-90.739852,38.483084],"type":"Point"}
}