{
  "type": "Feature",
  "properties": {
    "iso:country":"US",
    "sg:address":"3204 Thornbird Ave",
    "sg:city":"Blue Springs",
    "sg:classifiers":[
        {
            "category":"Arts & Performance",
            "subcategory":"Theater",
            "type":"Entertainment"
        }
    ],
    "sg:phone":"+1 816 228 3473",
    "sg:postcode":"64015",
    "sg:province":"MO",
    "sg:tags":[
        "magician"
    ],
    "wof:name":"Greg Lane Magical Productions",
    "wof:placetype":"venue"
},
  "geometry": {"coordinates":[-94.310447,39.057132],"type":"Point"}
}