{
  "type": "Feature",
  "properties": {
    "iso:country":"US",
    "sg:address":"4101 Burnett Ave",
    "sg:city":"St Louis",
    "sg:classifiers":[
        {
            "category":"Shopping",
            "subcategory":"Computers & Home Electronics",
            "type":"Retail Goods"
        }
    ],
    "sg:phone":"+1 314 638 0080",
    "sg:postcode":"63125",
    "sg:province":"MO",
    "sg:tags":[
        "equipment",
        "satellite",
        "system"
    ],
    "wof:name":"A & D Satellite",
    "wof:placetype":"venue"
},
  "geometry": {"coordinates":[-90.306237,38.530342],"type":"Point"}
}