{
  "type": "Feature",
  "properties": {
    "iso:country":"US",
    "sg:address":"26 Jonell Ct",
    "sg:city":"Saint Louis",
    "sg:classifiers":[
        {
            "category":"Retail",
            "subcategory":"Photofinishing",
            "type":"Services"
        }
    ],
    "sg:phone":"+1 314 429 4896",
    "sg:postcode":"63114",
    "sg:province":"MO",
    "sg:tags":[
        "laboratory"
    ],
    "wof:name":"Quality 1 Remodeling LLC",
    "wof:placetype":"venue"
},
  "geometry": {"coordinates":[-90.35701299999999,38.717277],"type":"Point"}
}