{
  "type": "Feature",
  "properties": {
    "iso:country":"US",
    "sg:address":"257 Clarkson Rd",
    "sg:city":"Ballwin",
    "sg:classifiers":[
        {
            "category":"Building & Trades",
            "subcategory":"Electrical",
            "type":"Services"
        }
    ],
    "sg:phone":"+1 636 230 0201",
    "sg:postcode":"63011",
    "sg:province":"MO",
    "sg:tags":[
        "electric",
        "contractor"
    ],
    "wof:name":"Hall Electrical Svc Inc",
    "wof:placetype":"venue"
},
  "geometry": {"coordinates":[-90.58559,38.599463],"type":"Point"}
}