{
  "type": "Feature",
  "properties": {
    "iso:country":"US",
    "sg:address":"5124 Natural Bridge Ave",
    "sg:city":"Saint Louis",
    "sg:classifiers":[
        {
            "category":"Restaurant",
            "type":"Food & Drink"
        }
    ],
    "sg:phone":"+1 314 381 1617",
    "sg:postcode":"63115",
    "sg:province":"MO",
    "wof:name":"Mammer Jammer Restaurant",
    "wof:placetype":"venue"
},
  "geometry": {"coordinates":[-90.255898,38.678299],"type":"Point"}
}