{
  "type": "Feature",
  "properties": {
    "iso:country":"US",
    "sg:address":"1522 Caulks Hill Rd",
    "sg:city":"Saint Charles",
    "sg:classifiers":[
        {
            "category":"Insurance",
            "subcategory":"Insurance Agent",
            "type":"Services"
        }
    ],
    "sg:phone":"+1 636 939 3993",
    "sg:postcode":"63304",
    "sg:province":"MO",
    "wof:name":"Bauer Insurance Agency",
    "wof:placetype":"venue"
},
  "geometry": {"coordinates":[-90.58095899999999,38.744628],"type":"Point"}
}