{
  "type": "Feature",
  "properties": {
    "iso:country":"US",
    "sg:address":"1220 Goldenrain Tree Cir",
    "sg:city":"Liberty",
    "sg:classifiers":[
        {
            "category":"Building & Trades",
            "subcategory":"Construction",
            "type":"Services"
        }
    ],
    "sg:phone":"+1 816 781 1634",
    "sg:postcode":"64068",
    "sg:province":"MO",
    "sg:tags":[
        "house"
    ],
    "wof:name":"Fjf Homes Inc",
    "wof:placetype":"venue"
},
  "geometry": {"coordinates":[-94.39903700000001,39.236873],"type":"Point"}
}