{
  "type": "Feature",
  "properties": {
    "iso:country":"US",
    "sg:address":"700 N 2nd St Ste 402",
    "sg:city":"Saint Louis",
    "sg:classifiers":[
        {
            "category":"Professional",
            "subcategory":"Lawyer & Legal Services",
            "type":"Services"
        }
    ],
    "sg:phone":"+1 314 542 9999",
    "sg:postcode":"63102",
    "sg:province":"MO",
    "sg:tags":[
        "divorce",
        "law",
        "family"
    ],
    "wof:name":"Cantor & Burger",
    "wof:placetype":"venue"
},
  "geometry": {"coordinates":[-90.184502,38.630501],"type":"Point"}
}