{
  "type": "Feature",
  "properties": {
    "iso:country":"US",
    "sg:address":"1920 Swift Ave",
    "sg:city":"Kansas City",
    "sg:classifiers":[
        {
            "category":"Professional",
            "subcategory":"Management & Consulting",
            "type":"Services"
        }
    ],
    "sg:phone":"+1 816 471 2323",
    "sg:postcode":"64116",
    "sg:province":"MO",
    "sg:tags":[
        "credit",
        "reporting",
        "business"
    ],
    "wof:name":"Midwest Regional Collections",
    "wof:placetype":"venue"
},
  "geometry": {"coordinates":[-94.577366,39.14252],"type":"Point"}
}