{
  "type": "Feature",
  "properties": {
    "iso:country":"US",
    "sg:address":"35220 E 240th Ave",
    "sg:city":"Bethany",
    "sg:classifiers":[
        {
            "category":"Organizations",
            "subcategory":"Religious Organization",
            "type":"Services"
        }
    ],
    "sg:phone":"+1 660 425 3888",
    "sg:postcode":"64424",
    "sg:province":"MO",
    "sg:tags":[
        "church"
    ],
    "wof:name":"Prairie Chapel Church",
    "wof:placetype":"venue"
},
  "geometry": {"coordinates":[-93.97289000000001,40.203382],"type":"Point"}
}