{
  "type": "Feature",
  "properties": {
    "iso:country":"US",
    "sg:address":"3 Westbury Dr",
    "sg:city":"St Charles",
    "sg:classifiers":[
        {
            "category":"Organizations",
            "subcategory":"Labor Organization",
            "type":"Services"
        }
    ],
    "sg:phone":"+1 636 946 4800",
    "sg:postcode":"63301",
    "sg:province":"MO",
    "wof:name":"Carpenter's Local 1987",
    "wof:placetype":"venue"
},
  "geometry": {"coordinates":[-90.51795,38.783549],"type":"Point"}
}