{
  "type": "Feature",
  "properties": {
    "iso:country":"US",
    "sg:address":"504 NE Wildplum Ct",
    "sg:city":"Lees Summit",
    "sg:classifiers":[
        {
            "category":"Professional",
            "subcategory":"Accounting & Tax Preparation",
            "type":"Services"
        }
    ],
    "sg:phone":"+1 816 554 9900",
    "sg:postcode":"64086",
    "sg:province":"MO",
    "sg:tags":[
        "accountant"
    ],
    "wof:name":"Mariane Watson CPA PC",
    "wof:placetype":"venue"
},
  "geometry": {"coordinates":[-94.35289899999999,38.920362],"type":"Point"}
}