{
  "type": "Feature",
  "properties": {
    "iso:country":"US",
    "sg:address":"1101 S Range Line Rd",
    "sg:city":"Joplin",
    "sg:classifiers":[
        {
            "category":"Restaurant",
            "type":"Food & Drink"
        }
    ],
    "sg:menulink":"http://www.allmenus.com/mo/joplin/66347-pizza-inn/menu/",
    "sg:phone":"+1 417 781 5000",
    "sg:postcode":"64801",
    "sg:province":"MO",
    "sg:tags":[
        "american",
        "pizza"
    ],
    "wof:name":"Pizza Inn",
    "wof:placetype":"venue"
},
  "geometry": {"coordinates":[-94.47747699999999,37.078499],"type":"Point"}
}