{
  "type": "Feature",
  "properties": {
    "iso:country":"US",
    "sg:address":"344 N Lafayette Ave",
    "sg:city":"Marshall",
    "sg:classifiers":[
        {
            "category":"Restaurant",
            "type":"Food & Drink"
        }
    ],
    "sg:phone":"+1 660 886 7600",
    "sg:postcode":"65340",
    "sg:province":"MO",
    "wof:name":"Mexico Lindo No 2",
    "wof:placetype":"venue"
},
  "geometry": {"coordinates":[-93.197229,39.123582],"type":"Point"}
}