{
  "type": "Feature",
  "properties": {
    "iso:country":"US",
    "sg:address":"4111 Goodfellow Blvd",
    "sg:city":"St Louis",
    "sg:classifiers":[
        {
            "category":"Organizations",
            "subcategory":"Religious Organization",
            "type":"Services"
        }
    ],
    "sg:phone":"+1 314 381 4558",
    "sg:postcode":"63120",
    "sg:province":"MO",
    "sg:tags":[
        "church"
    ],
    "wof:name":"Mt Ivory Missionary Baptist",
    "wof:placetype":"venue"
},
  "geometry": {"coordinates":[-90.26999000000001,38.689286],"type":"Point"}
}