{
  "type": "Feature",
  "properties": {
    "iso:country":"US",
    "sg:address":"4424 Remus Dr",
    "sg:city":"Florissant",
    "sg:classifiers":[
        {
            "category":"Food & Beverages",
            "subcategory":"Specialty",
            "type":"Retail Goods"
        }
    ],
    "sg:phone":"+1 314 830 0674",
    "sg:postcode":"63033",
    "sg:province":"MO",
    "wof:name":"Cakes Galore & Baskets 2",
    "wof:placetype":"venue"
},
  "geometry": {"coordinates":[-90.27148,38.780515],"type":"Point"}
}