{
  "type": "Feature",
  "properties": {
    "iso:country":"US",
    "sg:address":"105 W Washington St",
    "sg:city":"Kearney",
    "sg:classifiers":[
        {
            "category":"Home & Garden",
            "subcategory":"Household Appliances",
            "type":"Retail Goods"
        },
        {
            "category":"Retail",
            "subcategory":"Repair Shop",
            "type":"Services"
        },
        {
            "category":"Building & Trades",
            "subcategory":"Electrical",
            "type":"Services"
        }
    ],
    "sg:phone":"+1 816 628 6711",
    "sg:postcode":"64060",
    "sg:province":"MO",
    "sg:tags":[
        "major",
        "industrial",
        "electrician",
        "electric",
        "appliances-small",
        "contractors-commercial",
        "small",
        "refinishing"
    ],
    "wof:name":"Pence's Appliances & T V",
    "wof:placetype":"venue"
},
  "geometry": {"coordinates":[-94.362447,39.372941],"type":"Point"}
}