{
  "type": "Feature",
  "properties": {
    "iso:country":"US",
    "sg:address":"7511 Big Bend Blvd",
    "sg:city":"Saint Louis",
    "sg:classifiers":[
        {
            "category":"Health Services",
            "subcategory":"Doctor",
            "type":"Services"
        }
    ],
    "sg:phone":"+1 314 961 7064",
    "sg:postcode":"63119",
    "sg:province":"MO",
    "sg:tags":[
        "physician",
        "surgeon",
        "dermatologist"
    ],
    "wof:name":"Walters Richard C MD",
    "wof:placetype":"venue"
},
  "geometry": {"coordinates":[-90.32820100000001,38.5993],"type":"Point"}
}