{
  "type": "Feature",
  "properties": {
    "iso:country":"US",
    "sg:address":"708 Chatelet Ln",
    "sg:city":"Ballwin",
    "sg:classifiers":[
        {
            "category":"Building & Trades",
            "subcategory":"Construction",
            "type":"Services"
        }
    ],
    "sg:phone":"+1 636 391 2984",
    "sg:postcode":"63011",
    "sg:province":"MO",
    "sg:tags":[
        "handyman"
    ],
    "wof:name":"DNS Home Improvement Inc",
    "wof:placetype":"venue"
},
  "geometry": {"coordinates":[-90.50617,38.605587],"type":"Point"}
}