{
  "type": "Feature",
  "properties": {
    "iso:country":"US",
    "sg:address":"2409 Windy Hill Ln",
    "sg:city":"Cape Girardeau",
    "sg:classifiers":[
        {
            "category":"Food & Beverages",
            "subcategory":"Specialty",
            "type":"Retail Goods"
        }
    ],
    "sg:phone":"+1 573 335 7759",
    "sg:postcode":"63701",
    "sg:province":"MO",
    "wof:name":"Hawk Enterprises",
    "wof:placetype":"venue"
},
  "geometry": {"coordinates":[-89.529668,37.3529],"type":"Point"}
}