{
  "type": "Feature",
  "properties": {
    "iso:country":"US",
    "sg:address":"3540 Main St",
    "sg:city":"Kansas City",
    "sg:classifiers":[
        {
            "category":"Restaurant",
            "type":"Food & Drink"
        }
    ],
    "sg:phone":"+1 816 531 8070",
    "sg:postcode":"64111",
    "sg:province":"MO",
    "wof:name":"Poncho's Mexican Food",
    "wof:placetype":"venue"
},
  "geometry": {"coordinates":[-94.585826,39.062723],"type":"Point"}
}