{
  "type": "Feature",
  "properties": {
    "iso:country":"US",
    "sg:address":"208 W 4th St",
    "sg:city":"Fulton",
    "sg:classifiers":[
        {
            "category":"Insurance",
            "subcategory":"Hazard Insurance",
            "type":"Services"
        }
    ],
    "sg:phone":"+1 573 642 7283",
    "sg:postcode":"65251",
    "sg:province":"MO",
    "sg:website":"http://www.fultonmo.com",
    "wof:name":"Miller Real Estate",
    "wof:placetype":"venue"
},
  "geometry": {"coordinates":[-91.950176,38.846741],"type":"Point"}
}