{
  "type": "Feature",
  "properties": {
    "iso:country":"US",
    "sg:address":"3904 S Lynn Ct",
    "sg:city":"Independence",
    "sg:classifiers":[
        {
            "category":"Health Services",
            "subcategory":"Dentist",
            "type":"Services"
        }
    ],
    "sg:phone":"+1 816 252 0055",
    "sg:postcode":"64055",
    "sg:province":"MO",
    "sg:tags":[
        "dentists-oral",
        "maxillofacial",
        "denture",
        "dentists-prosthodontists",
        "dentists-orthodontists",
        "dentistry",
        "implant",
        "surgery",
        "dentists-implantology"
    ],
    "wof:name":"Schaefer David A",
    "wof:placetype":"venue"
},
  "geometry": {"coordinates":[-94.41709899999999,39.049871],"type":"Point"}
}