{
  "type": "Feature",
  "properties": {
    "addr:full":"3720 Arrowhead Ave Independence MO 64057",
    "addr:housenumber":"3720",
    "addr:postcode":"64057",
    "addr:street":"Arrowhead Ave",
    "iso:country":"US",
    "sg:address":"3720 Arrowhead Ave",
    "sg:city":"Independence",
    "sg:classifiers":[
        {
            "category":"Banks & Credit Unions",
            "subcategory":"Bank",
            "type":"Services"
        }
    ],
    "sg:phone":"+1 816 795 0051",
    "sg:postcode":"64057",
    "sg:province":"MO",
    "sg:tags":[
        "federal",
        "savings",
        "institution"
    ],
    "wof:name":"Washington Mutual Bank",
    "wof:placetype":"venue"
},
  "geometry": {"coordinates":[-94.359509,39.049029],"type":"Point"}
}