{
  "type": "Feature",
  "properties": {
    "iso:country":"US",
    "sg:address":"10198 W Florissant Ave",
    "sg:city":"St Louis",
    "sg:classifiers":[
        {
            "category":"Education",
            "subcategory":"Special Training",
            "type":"Public Place"
        }
    ],
    "sg:phone":"+1 314 867 0234",
    "sg:postcode":"63136",
    "sg:province":"MO",
    "sg:tags":[
        "tutoring"
    ],
    "sg:website":"www.sylvanlearningcenter.com",
    "wof:name":"Sylvan Learning Ctr",
    "wof:placetype":"venue"
},
  "geometry": {"coordinates":[-90.279657,38.755704],"type":"Point"}
}