{
  "type": "Feature",
  "properties": {
    "iso:country":"US",
    "sg:address":"1272 Jungermann Rd",
    "sg:city":"Saint Peters",
    "sg:classifiers":[
        {
            "category":"Banks & Credit Unions",
            "subcategory":"Investment Brokerage",
            "type":"Services"
        }
    ],
    "sg:phone":"+1 636 928 5151",
    "sg:postcode":"63376",
    "sg:province":"MO",
    "sg:tags":[
        "security"
    ],
    "wof:name":"Family Mortgage",
    "wof:placetype":"venue"
},
  "geometry": {"coordinates":[-90.578414,38.778437],"type":"Point"}
}