{
  "type": "Feature",
  "properties": {
    "iso:country":"US",
    "sg:address":"10 S Broadway",
    "sg:city":"St Louis",
    "sg:classifiers":[
        {
            "category":"Professional",
            "subcategory":"Printing & Photocopies",
            "type":"Services"
        }
    ],
    "sg:phone":"+1 314 446 0628",
    "sg:postcode":"63102",
    "sg:province":"MO",
    "sg:tags":[
        "duplicating",
        "copying"
    ],
    "wof:name":"DNT Inc",
    "wof:placetype":"venue"
},
  "geometry": {"coordinates":[-90.190271,38.6246],"type":"Point"}
}