{
  "type": "Feature",
  "properties": {
    "iso:country":"US",
    "sg:address":"1601 Olive St",
    "sg:city":"Saint Louis",
    "sg:classifiers":[
        {
            "category":"Professional",
            "subcategory":"Lawyer & Legal Services",
            "type":"Services"
        }
    ],
    "sg:phone":"+1 314 421 0077",
    "sg:postcode":"63103",
    "sg:province":"MO",
    "wof:name":"Caldwell & Singleton",
    "wof:placetype":"venue"
},
  "geometry": {"coordinates":[-90.203499,38.630798],"type":"Point"}
}