{
  "type": "Feature",
  "properties": {
    "iso:country":"US",
    "sg:address":"202 Fiddlecreek Ridge Rd",
    "sg:city":"Wentzville",
    "sg:classifiers":[
        {
            "category":"Building & Trades",
            "subcategory":"Construction",
            "type":"Services"
        }
    ],
    "sg:phone":"+1 636 398 6600",
    "sg:postcode":"63385",
    "sg:province":"MO",
    "sg:tags":[
        "home",
        "builder"
    ],
    "wof:name":"Fiddlestix",
    "wof:placetype":"venue"
},
  "geometry": {"coordinates":[-90.88431,38.72484],"type":"Point"}
}