{
  "type": "Feature",
  "properties": {
    "iso:country":"US",
    "sg:address":"12158 Lake Constance Dr",
    "sg:city":"Saint Louis",
    "sg:classifiers":[
        {
            "category":"Professional",
            "type":"Services"
        }
    ],
    "sg:phone":"+1 314 567 4330",
    "sg:postcode":"63146",
    "sg:province":"MO",
    "wof:name":"Alexsandr Rubinshteyn",
    "wof:placetype":"venue"
},
  "geometry": {"coordinates":[-90.447598,38.68321],"type":"Point"}
}