{
  "type": "Feature",
  "properties": {
    "iso:country":"US",
    "sg:address":"21364 Highway 42 E",
    "sg:city":"Belle",
    "sg:classifiers":[
        {
            "category":"Communications",
            "subcategory":"Television Station",
            "type":"Services"
        }
    ],
    "sg:phone":"+1 573 859 6523",
    "sg:postcode":"65013",
    "sg:province":"MO",
    "sg:tags":[
        "satellite",
        "antenna",
        "cable",
        "tv",
        "system",
        "equipment"
    ],
    "wof:name":"Antenna Works Plus Hcr",
    "wof:placetype":"venue"
},
  "geometry": {"coordinates":[-91.73281900000001,38.26355],"type":"Point"}
}