{
  "type": "Feature",
  "properties": {
    "iso:country":"US",
    "sg:address":"6201 Co Rd 125",
    "sg:city":"Fulton",
    "sg:phone":"+1 573 642 5437",
    "sg:postcode":"65251",
    "sg:province":"MO",
    "sg:tags":[
        "beef",
        "farm",
        "crop",
        "field",
        "cattle",
        "feedlot"
    ],
    "wof:name":"David Williamson",
    "wof:placetype":"venue"
},
  "geometry": {"coordinates":[-91.84311700000001,38.829622],"type":"Point"}
}