{
  "type": "Feature",
  "properties": {
    "iso:country":"US",
    "sg:address":"775 N Highway Cc",
    "sg:city":"Lamar",
    "sg:classifiers":[
        {
            "category":"Shopping",
            "subcategory":"Pets & Pet Supplies",
            "type":"Retail Goods"
        }
    ],
    "sg:phone":"+1 417 398 0012",
    "sg:postcode":"64759",
    "sg:province":"MO",
    "sg:tags":[
        "feed"
    ],
    "wof:name":"Vigortone Ag Products",
    "wof:placetype":"venue"
},
  "geometry": {"coordinates":[-94.151854,37.602912],"type":"Point"}
}