{
  "type": "Feature",
  "properties": {
    "iso:country":"US",
    "sg:address":"5046 S 38th St",
    "sg:city":"Saint Louis",
    "sg:classifiers":[
        {
            "category":"Building & Trades",
            "subcategory":"Construction",
            "type":"Services"
        }
    ],
    "sg:phone":"+1 314 752 4520",
    "sg:postcode":"63116",
    "sg:province":"MO",
    "sg:tags":[
        "warehouse"
    ],
    "wof:name":"Foundry Products Inc",
    "wof:placetype":"venue"
},
  "geometry": {"coordinates":[-90.255731,38.574048],"type":"Point"}
}