{
  "type": "Feature",
  "properties": {
    "iso:country":"US",
    "sg:address":"5792 State Hwy 72",
    "sg:city":"Jackson",
    "sg:classifiers":[
        {
            "category":"Retail",
            "subcategory":"Auto Repair",
            "type":"Services"
        }
    ],
    "sg:phone":"+1 573 243 8140",
    "sg:postcode":"63755",
    "sg:province":"MO",
    "sg:tags":[
        "general"
    ],
    "wof:name":"S & S Automotive",
    "wof:placetype":"venue"
},
  "geometry": {"coordinates":[-89.740228,37.399912],"type":"Point"}
}