{
  "type": "Feature",
  "properties": {
    "iso:country":"US",
    "sg:address":"625 Union St",
    "sg:city":"Hannibal",
    "sg:classifiers":[
        {
            "category":"Shopping",
            "subcategory":"Used Merchandise",
            "type":"Retail Goods"
        }
    ],
    "sg:phone":"+1 573 248 1610",
    "sg:postcode":"63401",
    "sg:province":"MO",
    "wof:name":"Second Chances",
    "wof:placetype":"venue"
},
  "geometry": {"coordinates":[-91.351403,39.702526],"type":"Point"}
}