{
  "type": "Feature",
  "properties": {
    "iso:country":"US",
    "sg:address":"11977 Saint Charles Rock Rd",
    "sg:city":"Bridgeton",
    "sg:classifiers":[
        {
            "category":"Personal",
            "subcategory":"Beauty Salon",
            "type":"Services"
        }
    ],
    "sg:phone":"+1 314 298 8804",
    "sg:postcode":"63044",
    "sg:province":"MO",
    "sg:tags":[
        "shop"
    ],
    "wof:name":"Academy of Beauty",
    "wof:placetype":"venue"
},
  "geometry": {"coordinates":[-90.422365,38.747738],"type":"Point"}
}