{
  "type": "Feature",
  "properties": {
    "iso:country":"US",
    "sg:address":"21903 Osage Ln",
    "sg:city":"Lebanon",
    "sg:classifiers":[
        {
            "category":"Building & Trades",
            "subcategory":"Construction",
            "type":"Services"
        }
    ],
    "sg:phone":"+1 417 531 1744",
    "sg:postcode":"65536",
    "sg:province":"MO",
    "sg:tags":[
        "masonry",
        "industrial",
        "contractors-commercial"
    ],
    "sg:website":"http://southwestveneers.com",
    "wof:name":"Southwest Veneers",
    "wof:placetype":"venue"
},
  "geometry": {"coordinates":[-92.697995,37.654393],"type":"Point"}
}