{
  "type": "Feature",
  "properties": {
    "iso:country":"US",
    "sg:address":"5376 Dr Martin Luther King Dr",
    "sg:city":"St Louis",
    "sg:classifiers":[
        {
            "category":"Building & Trades",
            "subcategory":"Construction",
            "type":"Services"
        }
    ],
    "sg:phone":"+1 314 361 2600",
    "sg:postcode":"63112",
    "sg:province":"MO",
    "sg:tags":[
        "roofing",
        "contractor"
    ],
    "wof:name":"Curtain Roofing Co",
    "wof:placetype":"venue"
},
  "geometry": {"coordinates":[-90.268781,38.666061],"type":"Point"}
}