{
  "type": "Feature",
  "properties": {
    "iso:country":"US",
    "sg:address":"1326 E Kearney St",
    "sg:city":"Springfield",
    "sg:classifiers":[
        {
            "category":"Banks & Credit Unions",
            "subcategory":"Bank",
            "type":"Services"
        }
    ],
    "sg:phone":"+1 417 868 0101",
    "sg:postcode":"65803",
    "sg:province":"MO",
    "sg:tags":[
        "cashing",
        "check"
    ],
    "wof:name":"Pay Day Today Inc",
    "wof:placetype":"venue"
},
  "geometry": {"coordinates":[-93.27209000000001,37.240492],"type":"Point"}
}