{
  "type": "Feature",
  "properties": {
    "iso:country":"US",
    "sg:address":"1020 N Taylor Ave",
    "sg:city":"Saint Louis",
    "sg:classifiers":[
        {
            "category":"Organizations",
            "subcategory":"Community Association",
            "type":"Services"
        }
    ],
    "sg:phone":"+1 713 738 0388",
    "sg:postcode":"63113",
    "sg:province":"MO",
    "sg:tags":[
        "fraternal"
    ],
    "wof:name":"International Black Fire Fight",
    "wof:placetype":"venue"
},
  "geometry": {"coordinates":[-90.2514,38.652958],"type":"Point"}
}