{
  "type": "Feature",
  "properties": {
    "iso:country":"US",
    "sg:address":"1520 Timberlake Manor Pkwy",
    "sg:city":"Chesterfield",
    "sg:classifiers":[
        {
            "category":"Insurance",
            "subcategory":"Insurance Agent",
            "type":"Services"
        }
    ],
    "sg:phone":"+1 636 537 8535",
    "sg:postcode":"63017",
    "sg:province":"MO",
    "wof:name":"Managed Employee Benefits Inc",
    "wof:placetype":"venue"
},
  "geometry": {"coordinates":[-90.531318,38.643017],"type":"Point"}
}