{
  "type": "Feature",
  "properties": {
    "iso:country":"US",
    "sg:address":"601 State Hwy 291",
    "sg:city":"Liberty",
    "sg:classifiers":[
        {
            "category":"Real Estate",
            "subcategory":"Real Estate Agent",
            "type":"Services"
        }
    ],
    "sg:phone":"+1 816 781 7800",
    "sg:postcode":"64068",
    "sg:province":"MO",
    "wof:name":"R N Ellis & Co-Realtors",
    "wof:placetype":"venue"
},
  "geometry": {"coordinates":[-94.43925,39.240249],"type":"Point"}
}