{
  "type": "Feature",
  "properties": {
    "iso:country":"US",
    "sg:address":"23200 State Hwy 25",
    "sg:city":"Advance",
    "sg:classifiers":[
        {
            "category":"Organizations",
            "subcategory":"Religious Organization",
            "type":"Services"
        }
    ],
    "sg:phone":"+1 573 722 5580",
    "sg:postcode":"63730",
    "sg:province":"MO",
    "wof:name":"Jehovahs Witnesses Advan",
    "wof:placetype":"venue"
},
  "geometry": {"coordinates":[-89.84189499999999,37.138928],"type":"Point"}
}