{
  "type": "Feature",
  "properties": {
    "iso:country":"US",
    "sg:address":"142 W Moniteau St",
    "sg:city":"Tipton",
    "sg:classifiers":[
        {
            "category":"Insurance",
            "subcategory":"Insurance Agent",
            "type":"Services"
        }
    ],
    "sg:phone":"+1 660 433 2141",
    "sg:postcode":"65081",
    "sg:province":"MO",
    "wof:name":"Insurance Associates America",
    "wof:placetype":"venue"
},
  "geometry": {"coordinates":[-92.779746,38.656748],"type":"Point"}
}