{
  "type": "Feature",
  "properties": {
    "iso:country":"US",
    "sg:address":"9930 Kennerly Rd",
    "sg:city":"Sappington",
    "sg:classifiers":[
        {
            "category":"Personal",
            "subcategory":"Beauty Salon",
            "type":"Services"
        }
    ],
    "sg:phone":"+1 314 842 0007",
    "sg:postcode":"63128",
    "sg:province":"MO",
    "sg:tags":[
        "shop"
    ],
    "wof:name":"Hair Perfection Inc",
    "wof:placetype":"venue"
},
  "geometry": {"coordinates":[-90.375623,38.507283],"type":"Point"}
}