{
  "type": "Feature",
  "properties": {
    "iso:country":"US",
    "sg:address":"224 N Main Ave",
    "sg:city":"Republic",
    "sg:classifiers":[
        {
            "category":"Home & Garden",
            "subcategory":"Carpets & Floor Coverings",
            "type":"Retail Goods"
        }
    ],
    "sg:phone":"+1 417 732 5445",
    "sg:postcode":"65738",
    "sg:province":"MO",
    "sg:tags":[
        "material"
    ],
    "wof:name":"E C Floor Covering",
    "wof:placetype":"venue"
},
  "geometry": {"coordinates":[-93.48042,37.12028],"type":"Point"}
}