{
  "type": "Feature",
  "properties": {
    "iso:country":"US",
    "sg:address":"8400 Ward Pkwy",
    "sg:city":"Kansas City",
    "sg:classifiers":[
        {
            "category":"Professional",
            "subcategory":"Engineering",
            "type":"Services"
        }
    ],
    "sg:phone":"+1 913 458 9600",
    "sg:postcode":"64114",
    "sg:province":"MO",
    "sg:tags":[
        "engineer"
    ],
    "wof:name":"Black & Veatch Corp",
    "wof:placetype":"venue"
},
  "geometry": {"coordinates":[-94.60691300000001,38.974658],"type":"Point"}
}