{
  "type": "Feature",
  "properties": {
    "iso:country":"US",
    "sg:address":"2024 Mckelvey Rd",
    "sg:city":"Maryland Heights",
    "sg:classifiers":[
        {
            "category":"Restaurant",
            "type":"Food & Drink"
        }
    ],
    "sg:menulink":"http://www.allmenus.com/mo/maryland-heights/195634-taco-bell/menu/",
    "sg:phone":"+1 314 576 3045",
    "sg:postcode":"63043",
    "sg:province":"MO",
    "sg:tags":[
        "mexican"
    ],
    "wof:name":"Taco Bell",
    "wof:placetype":"venue"
},
  "geometry": {"coordinates":[-90.452975,38.715528],"type":"Point"}
}