{
  "type": "Feature",
  "properties": {
    "iso:country":"US",
    "sg:address":"4653 S Campbell Ave",
    "sg:city":"Springfield",
    "sg:classifiers":[
        {
            "category":"Restaurant",
            "type":"Food & Drink"
        }
    ],
    "sg:phone":"+1 417 882 4122",
    "sg:postcode":"65810",
    "sg:province":"MO",
    "sg:tags":[
        "cafe"
    ],
    "wof:name":"Churchill Coffee International",
    "wof:placetype":"venue"
},
  "geometry": {"coordinates":[-93.29633699999999,37.131365],"type":"Point"}
}