{
  "type": "Feature",
  "properties": {
    "iso:country":"US",
    "sg:address":"1315 Nashua Rd",
    "sg:city":"Liberty",
    "sg:classifiers":[
        {
            "category":"Place Of Worship",
            "type":"Public Place"
        },
        {
            "category":"Social Services",
            "subcategory":"Child Care",
            "type":"Services"
        }
    ],
    "sg:phone":"+1 816 781 9689",
    "sg:postcode":"64068",
    "sg:province":"MO",
    "sg:tags":[
        "nursery",
        "day",
        "church"
    ],
    "wof:name":"Kiddie College Usa",
    "wof:placetype":"venue"
},
  "geometry": {"coordinates":[-94.44132500000001,39.263806],"type":"Point"}
}