{
  "type": "Feature",
  "properties": {
    "iso:country":"US",
    "sg:address":"8138 Westmoreland Ave",
    "sg:city":"Saint Louis",
    "sg:classifiers":[
        {
            "category":"Health Services",
            "subcategory":"Doctor",
            "type":"Services"
        }
    ],
    "sg:phone":"+1 314 721 2820",
    "sg:postcode":"63105",
    "sg:province":"MO",
    "sg:tags":[
        "medical"
    ],
    "wof:name":"Jerome Cohen MD",
    "wof:placetype":"venue"
},
  "geometry": {"coordinates":[-90.341235,38.653012],"type":"Point"}
}