{
  "type": "Feature",
  "properties": {
    "iso:country":"US",
    "sg:address":"9535 SW Sharp Rd",
    "sg:city":"Stewartsville",
    "sg:classifiers":[
        {
            "category":"Utilities",
            "subcategory":"Telephone",
            "type":"Services"
        }
    ],
    "sg:phone":"+1 816 669 3428",
    "sg:postcode":"64490",
    "sg:province":"MO",
    "sg:tags":[
        "telecommunication"
    ],
    "wof:name":"American Tower LP",
    "wof:placetype":"venue"
},
  "geometry": {"coordinates":[-94.508292,39.77019],"type":"Point"}
}