{
  "type": "Feature",
  "properties": {
    "iso:country":"US",
    "sg:address":"1034 W Valley St",
    "sg:city":"Granby",
    "sg:classifiers":[
        {
            "category":"Wholesale",
            "subcategory":"Machinery & Supplies",
            "type":"Manufacturing & Wholesale Goods"
        }
    ],
    "sg:phone":"+1 417 472 3611",
    "sg:postcode":"64844",
    "sg:province":"MO",
    "sg:tags":[
        "pump"
    ],
    "wof:name":"Tuggle Pump Svc",
    "wof:placetype":"venue"
},
  "geometry": {"coordinates":[-94.26896600000001,36.917058],"type":"Point"}
}