{
  "type": "Feature",
  "properties": {
    "iso:country":"US",
    "sg:address":"3737 Somerville Dr",
    "sg:city":"Saint Charles",
    "sg:classifiers":[
        {
            "category":"Retail",
            "subcategory":"Portrait Studio",
            "type":"Services"
        }
    ],
    "sg:phone":"+1 636 946 7530",
    "sg:postcode":"63303",
    "sg:province":"MO",
    "sg:tags":[
        "photo"
    ],
    "wof:name":"Gary Henricks Imaging Inc",
    "wof:placetype":"venue"
},
  "geometry": {"coordinates":[-90.555571,38.78427],"type":"Point"}
}