{
  "type": "Feature",
  "properties": {
    "iso:country":"US",
    "sg:address":"5876 Delmar Blvd",
    "sg:city":"Saint Louis",
    "sg:classifiers":[
        {
            "category":"Bars & Pubs",
            "subcategory":"Nightclub",
            "type":"Food & Drink"
        }
    ],
    "sg:phone":"+1 314 361 3099",
    "sg:postcode":"63112",
    "sg:province":"MO",
    "sg:tags":[
        "nightlife"
    ],
    "wof:name":"Palomino Lounge",
    "wof:placetype":"venue"
},
  "geometry": {"coordinates":[-90.28919999999999,38.654499],"type":"Point"}
}