{
  "type": "Feature",
  "properties": {
    "iso:country":"US",
    "sg:address":"12808 Pointe Dr",
    "sg:city":"Saint Louis",
    "sg:classifiers":[
        {
            "category":"Professional",
            "subcategory":"Management & Consulting",
            "type":"Services"
        }
    ],
    "sg:phone":"+1 314 849 4892",
    "sg:postcode":"63127",
    "sg:province":"MO",
    "wof:name":"Dinkins Consulting",
    "wof:placetype":"venue"
},
  "geometry": {"coordinates":[-90.411996,38.5199],"type":"Point"}
}