{
  "type": "Feature",
  "properties": {
    "addr:full":"328 Main St Boonville MO 65233",
    "addr:housenumber":"328",
    "addr:postcode":"65233",
    "addr:street":"Main St",
    "iso:country":"US",
    "sg:address":"328 Main St",
    "sg:city":"Boonville",
    "sg:classifiers":[
        {
            "category":"Professional",
            "subcategory":"Business Services",
            "type":"Services"
        }
    ],
    "sg:phone":"+1 660 882 7717",
    "sg:postcode":"65233",
    "sg:province":"MO",
    "sg:tags":[
        "interior",
        "decorating"
    ],
    "wof:name":"Ricmar Decorating Gallery",
    "wof:placetype":"venue"
},
  "geometry": {"coordinates":[-92.743954,38.976233],"type":"Point"}
}