{
  "type": "Feature",
  "properties": {
    "iso:country":"US",
    "sg:address":"710 Court St",
    "sg:city":"Fulton",
    "sg:classifiers":[
        {
            "category":"Education",
            "subcategory":"Library",
            "type":"Public Place"
        }
    ],
    "sg:phone":"+1 573 642 7261",
    "sg:postcode":"65251",
    "sg:province":"MO",
    "sg:website":"www.dbrl.library.missouri.com",
    "wof:name":"Callaway County Public Library",
    "wof:placetype":"venue"
},
  "geometry": {"coordinates":[-91.947706,38.850351],"type":"Point"}
}