{
  "type": "Feature",
  "properties": {
    "iso:country":"US",
    "sg:address":"917 S Kingshighway St",
    "sg:city":"Perryville",
    "sg:classifiers":[
        {
            "category":"Autos & Motor Vehicles",
            "subcategory":"Fuel & Gas Station",
            "type":"Retail Goods"
        },
        {
            "category":"Autos & Motor Vehicles",
            "subcategory":"Auto Supplies",
            "type":"Retail Goods"
        },
        {
            "category":"Retail",
            "subcategory":"Auto Repair",
            "type":"Services"
        }
    ],
    "sg:phone":"+1 573 547 8921",
    "sg:postcode":"63775",
    "sg:province":"MO",
    "sg:tags":[
        "exhaust",
        "automobile",
        "system",
        "accessory",
        "part",
        "brake",
        "muffler",
        "inspection"
    ],
    "wof:name":"Perryville Muffler & Automotive",
    "wof:placetype":"venue"
},
  "geometry": {"coordinates":[-89.854523,37.727252],"type":"Point"}
}