{
  "type": "Feature",
  "properties": {
    "iso:country":"US",
    "sg:address":"11228 Lone Eagle Dr",
    "sg:city":"Bridgeton",
    "sg:classifiers":[
        {
            "category":"Travel",
            "subcategory":"Hotels & Motels",
            "type":"Entertainment"
        },
        {
            "category":"Retail",
            "subcategory":"Event Space",
            "type":"Services"
        },
        {
            "category":"Travel",
            "subcategory":"Resort",
            "type":"Entertainment"
        }
    ],
    "sg:phone":"+1 877 270 1412",
    "sg:postcode":"63044",
    "sg:province":"MO",
    "sg:tags":[
        "hall",
        "lodging",
        "banquet",
        "reception",
        "facility"
    ],
    "sg:website":"http://ad.doubleclick.net/clk;222817048;46581824;l?http://www.crowneplaza.com/redirect?path=hd&brandCode=cp&hotelCode=stlap&_PMID=99601036&cm_mmc=mdpr-_-yellowpages-_-cp-_-stlap",
    "wof:name":"Crowne Plaza Hotel St. Louis Airport",
    "wof:placetype":"venue"
},
  "geometry": {"coordinates":[-90.398297,38.740694],"type":"Point"}
}