{
  "type": "Feature",
  "properties": {
    "iso:country":"US",
    "sg:address":"70 N Shore Dr",
    "sg:city":"Eldon",
    "sg:classifiers":[
        {
            "category":"Health Services",
            "subcategory":"Doctor",
            "type":"Services"
        }
    ],
    "sg:phone":"+1 573 365 1603",
    "sg:postcode":"65026",
    "sg:province":"MO",
    "sg:tags":[
        "dentist"
    ],
    "wof:name":"Dentures & Dental Svc",
    "wof:placetype":"venue"
},
  "geometry": {"coordinates":[-92.63091799999999,38.221063],"type":"Point"}
}