{
  "type": "Feature",
  "properties": {
    "iso:country":"US",
    "sg:address":"12924 Sycamore Ave",
    "sg:city":"Grandview",
    "sg:classifiers":[
        {
            "category":"Real Estate",
            "subcategory":"Real Estate Services",
            "type":"Services"
        },
        {
            "category":"Real Estate",
            "subcategory":"Real Estate Agent",
            "type":"Services"
        }
    ],
    "sg:phone":"+1 816 214 5627",
    "sg:postcode":"64030",
    "sg:province":"MO",
    "sg:tags":[
        "buyer",
        "broker"
    ],
    "wof:name":"Harding Realty",
    "wof:placetype":"venue"
},
  "geometry": {"coordinates":[-94.499397,38.888704],"type":"Point"}
}