{
  "type": "Feature",
  "properties": {
    "iso:country":"US",
    "sg:address":"201 E Central Ave",
    "sg:city":"Carthage",
    "sg:classifiers":[
        {
            "category":"Building & Trades",
            "subcategory":"Electrical",
            "type":"Services"
        }
    ],
    "sg:phone":"+1 417 359 9691",
    "sg:postcode":"64836",
    "sg:province":"MO",
    "sg:tags":[
        "booth",
        "equipment",
        "telephone",
        "pay"
    ],
    "wof:name":"Tele Connect Payphone",
    "wof:placetype":"venue"
},
  "geometry": {"coordinates":[-94.30964299999999,37.178584],"type":"Point"}
}