{
  "type": "Feature",
  "properties": {
    "iso:country":"US",
    "sg:address":"712 Porter Wagoner Blvd",
    "sg:city":"West Plains",
    "sg:classifiers":[
        {
            "category":"Shopping",
            "subcategory":"Used Merchandise",
            "type":"Retail Goods"
        }
    ],
    "sg:phone":"+1 417 256 8586",
    "sg:postcode":"65775",
    "sg:province":"MO",
    "sg:tags":[
        "antique"
    ],
    "wof:name":"Looking Back",
    "wof:placetype":"venue"
},
  "geometry": {"coordinates":[-91.86497900000001,36.735019],"type":"Point"}
}