{
  "type": "Feature",
  "properties": {
    "iso:country":"US",
    "sg:address":"1129 Birchgate Trl",
    "sg:city":"Ferguson",
    "sg:classifiers":[
        {
            "category":"Arts & Performance",
            "subcategory":"Theater",
            "type":"Entertainment"
        }
    ],
    "sg:phone":"+1 314 524 0737",
    "sg:postcode":"63135",
    "sg:province":"MO",
    "sg:tags":[
        "group",
        "clown"
    ],
    "wof:name":"Popsicle & Co",
    "wof:placetype":"venue"
},
  "geometry": {"coordinates":[-90.298011,38.761107],"type":"Point"}
}