{
  "type": "Feature",
  "properties": {
    "iso:country":"US",
    "sg:address":"330 E 14th Ave",
    "sg:city":"Kansas City",
    "sg:classifiers":[
        {
            "category":"Building & Trades",
            "subcategory":"Plumbing",
            "type":"Services"
        }
    ],
    "sg:phone":"+1 816 221 7878",
    "sg:postcode":"64116",
    "sg:province":"MO",
    "sg:tags":[
        "air",
        "heating",
        "contractor",
        "system",
        "conditioning"
    ],
    "wof:name":"Edwards Mc Dowell Incorporated",
    "wof:placetype":"venue"
},
  "geometry": {"coordinates":[-94.57643899999999,39.134237],"type":"Point"}
}