{
  "type": "Feature",
  "properties": {
    "iso:country":"US",
    "sg:address":"317 E Love St",
    "sg:city":"Mexico",
    "sg:classifiers":[
        {
            "category":"Building & Trades",
            "subcategory":"Cleaning & Sanitation",
            "type":"Services"
        }
    ],
    "sg:phone":"+1 573 581 6419",
    "sg:postcode":"65265",
    "sg:province":"MO",
    "sg:tags":[
        "venetian",
        "blind"
    ],
    "wof:name":"Darlene's Draperies & Interior",
    "wof:placetype":"venue"
},
  "geometry": {"coordinates":[-91.880334,39.173872],"type":"Point"}
}