{
  "type": "Feature",
  "properties": {
    "iso:country":"US",
    "sg:address":"909 S Range Line Rd",
    "sg:city":"Joplin",
    "sg:classifiers":[
        {
            "category":"Home & Garden",
            "subcategory":"Hardware",
            "type":"Retail Goods"
        },
        {
            "category":"Home & Garden",
            "subcategory":"Garden Supply",
            "type":"Retail Goods"
        }
    ],
    "sg:phone":"+1 417 623 1301",
    "sg:postcode":"64801",
    "sg:province":"MO",
    "sg:tags":[
        "saw"
    ],
    "wof:name":"Ron's Outdoor Power Equipment",
    "wof:placetype":"venue"
},
  "geometry": {"coordinates":[-94.477349,37.080625],"type":"Point"}
}