{
  "type": "Feature",
  "properties": {
    "iso:country":"US",
    "sg:address":"8600 N Boardwalk Ave",
    "sg:city":"Kansas City",
    "sg:classifiers":[
        {
            "category":"Restaurant",
            "type":"Food & Drink"
        }
    ],
    "sg:menulink":"http://www.allmenus.com/mo/may/221929-chipotle/menu/",
    "sg:phone":"+1 816 746 0050",
    "sg:postcode":"64154",
    "sg:province":"MO",
    "sg:tags":[
        "mexican"
    ],
    "wof:name":"Chipotle",
    "wof:placetype":"venue"
},
  "geometry": {"coordinates":[-94.65264000000001,39.252553],"type":"Point"}
}