{
  "type": "Feature",
  "properties": {
    "iso:country":"US",
    "sg:address":"180 Iffrig Rd",
    "sg:city":"Saint Peters",
    "sg:classifiers":[
        {
            "category":"Retail",
            "subcategory":"Repair Shop",
            "type":"Services"
        }
    ],
    "sg:phone":"+1 314 267 5014",
    "sg:postcode":"63376",
    "sg:province":"MO",
    "wof:name":"Bm Septic & Sewer Systems Inc",
    "wof:placetype":"venue"
},
  "geometry": {"coordinates":[-90.620693,38.806421],"type":"Point"}
}