{
  "type": "Feature",
  "properties": {
    "iso:country":"US",
    "sg:address":"11401 Conway Rd",
    "sg:city":"Saint Louis",
    "sg:classifiers":[
        {
            "category":"Banks & Credit Unions",
            "subcategory":"Investment Brokerage",
            "type":"Services"
        }
    ],
    "sg:phone":"+1 314 432 2374",
    "sg:postcode":"63131",
    "sg:province":"MO",
    "sg:tags":[
        "security"
    ],
    "wof:name":"Kolbrener",
    "wof:placetype":"venue"
},
  "geometry": {"coordinates":[-90.42671300000001,38.640692],"type":"Point"}
}