{
  "type": "Feature",
  "properties": {
    "iso:country":"US",
    "sg:address":"5684 County Road 420",
    "sg:city":"Puxico",
    "sg:classifiers":[
        {
            "category":"Manufacturing",
            "subcategory":"Food",
            "type":"Manufacturing & Wholesale Goods"
        },
        {
            "category":"Farming",
            "subcategory":"Farm",
            "type":"Manufacturing & Wholesale Goods"
        }
    ],
    "sg:phone":"+1 573 222 3020",
    "sg:postcode":"63960",
    "sg:province":"MO",
    "sg:tags":[
        "corn",
        "product"
    ],
    "wof:name":"Jerry Roberts Farms",
    "wof:placetype":"venue"
},
  "geometry": {"coordinates":[-90.18811599999999,36.878016],"type":"Point"}
}