{
  "type": "Feature",
  "properties": {
    "iso:country":"US",
    "sg:address":"1582 Clearview Rd",
    "sg:city":"Union",
    "sg:classifiers":[
        {
            "category":"Building & Trades",
            "subcategory":"Construction",
            "type":"Services"
        }
    ],
    "sg:phone":"+1 636 583 5455",
    "sg:postcode":"63084",
    "sg:province":"MO",
    "sg:tags":[
        "hanging",
        "contractor"
    ],
    "wof:name":"Pendleton Painting",
    "wof:placetype":"venue"
},
  "geometry": {"coordinates":[-91.010586,38.480418],"type":"Point"}
}