{
  "type": "Feature",
  "properties": {
    "iso:country":"US",
    "sg:address":"312 Co Rd 247",
    "sg:city":"Benton",
    "sg:classifiers":[
        {
            "category":"Wholesale",
            "subcategory":"Farm Supplies",
            "type":"Manufacturing & Wholesale Goods"
        }
    ],
    "sg:phone":"+1 573 545 3444",
    "sg:postcode":"63736",
    "sg:province":"MO",
    "sg:tags":[
        "livestock"
    ],
    "wof:name":"E & S Pork Inc",
    "wof:placetype":"venue"
},
  "geometry": {"coordinates":[-89.585936,37.110865],"type":"Point"}
}