{
  "type": "Feature",
  "properties": {
    "iso:country":"US",
    "sg:address":"11885 E Hwy 32",
    "sg:city":"Stockton",
    "sg:classifiers":[
        {
            "category":"Organizations",
            "subcategory":"Community Association",
            "type":"Services"
        }
    ],
    "sg:phone":"+1 417 276 3414",
    "sg:postcode":"65785",
    "sg:province":"MO",
    "sg:tags":[
        "club"
    ],
    "wof:name":"A M Vets",
    "wof:placetype":"venue"
},
  "geometry": {"coordinates":[-93.86284999999999,37.71814],"type":"Point"}
}