{
  "type": "Feature",
  "properties": {
    "iso:country":"US",
    "sg:address":"236 Shepherd Of The Hills Expy",
    "sg:city":"Branson",
    "sg:phone":"+1 417 336 4500",
    "sg:postcode":"65616",
    "sg:province":"MO",
    "sg:website":"http://www.danapointmarinainn.com",
    "wof:name":"Branson Powers Hotel",
    "wof:placetype":"venue"
},
  "geometry": {"coordinates":[-93.253561,36.668234],"type":"Point"}
}