{
  "type": "Feature",
  "properties": {
    "addr:full":"500 S Elson St Kirksville MO 63501",
    "addr:housenumber":"500",
    "addr:postcode":"63501",
    "addr:street":"S Elson St",
    "iso:country":"US",
    "sg:address":"500 S Elson St",
    "sg:city":"Kirksville",
    "sg:classifiers":[
        {
            "category":"Government",
            "subcategory":"Office",
            "type":"Public Place"
        }
    ],
    "sg:phone":"+1 660 665 9289",
    "sg:postcode":"63501",
    "sg:province":"MO",
    "sg:tags":[
        "state",
        "guard",
        "security",
        "national"
    ],
    "wof:name":"Army National Guard",
    "wof:placetype":"venue"
},
  "geometry": {"coordinates":[-92.58429099999999,40.191393],"type":"Point"}
}