{
  "type": "Feature",
  "properties": {
    "iso:country":"US",
    "sg:address":"5569 Page Blvd",
    "sg:city":"Saint Louis",
    "sg:classifiers":[
        {
            "category":"Social Services",
            "subcategory":"Child Care",
            "type":"Services"
        }
    ],
    "sg:phone":"+1 314 361 4466",
    "sg:postcode":"63112",
    "sg:province":"MO",
    "sg:tags":[
        "day"
    ],
    "wof:name":"Solomon's Temple Day Care Center",
    "wof:placetype":"venue"
},
  "geometry": {"coordinates":[-90.278,38.664001],"type":"Point"}
}