{
  "type": "Feature",
  "properties": {
    "iso:country":"US",
    "sg:address":"3504 Wakefield Dr",
    "sg:city":"Columbia",
    "sg:classifiers":[
        {
            "category":"Banks & Credit Unions",
            "subcategory":"Investment Brokerage",
            "type":"Services"
        }
    ],
    "sg:phone":"+1 573 875 6699",
    "sg:postcode":"65203",
    "sg:province":"MO",
    "sg:tags":[
        "advisory"
    ],
    "wof:name":"Ebusua Investment Club",
    "wof:placetype":"venue"
},
  "geometry": {"coordinates":[-92.350476,38.913772],"type":"Point"}
}