{
  "type": "Feature",
  "properties": {
    "iso:country":"US",
    "sg:address":"500 Park Rd",
    "sg:city":"Lexington",
    "sg:classifiers":[
        {
            "category":"Government",
            "subcategory":"Office",
            "type":"Public Place"
        }
    ],
    "sg:phone":"+1 660 259 2697",
    "sg:postcode":"64067",
    "sg:province":"MO",
    "sg:tags":[
        "township",
        "government-city",
        "village"
    ],
    "wof:name":"Parks Lexington & Recreation",
    "wof:placetype":"venue"
},
  "geometry": {"coordinates":[-93.864052,39.190689],"type":"Point"}
}