{
  "type": "Feature",
  "properties": {
    "iso:country":"US",
    "sg:address":"6840 NW Waukomis Dr",
    "sg:city":"Kansas City",
    "sg:classifiers":[
        {
            "category":"Professional",
            "subcategory":"Business Services",
            "type":"Services"
        }
    ],
    "sg:phone":"+1 816 741 3780",
    "sg:postcode":"64151",
    "sg:province":"MO",
    "wof:name":"Ladco Inspection Services",
    "wof:placetype":"venue"
},
  "geometry": {"coordinates":[-94.61894599999999,39.217544],"type":"Point"}
}