{
  "type": "Feature",
  "properties": {
    "iso:country":"US",
    "sg:address":"209 E 15th St",
    "sg:city":"Caruthersville",
    "sg:classifiers":[
        {
            "category":"Restaurant",
            "type":"Food & Drink"
        }
    ],
    "sg:phone":"+1 573 333 4670",
    "sg:postcode":"63830",
    "sg:province":"MO",
    "wof:name":"Momos Place",
    "wof:placetype":"venue"
},
  "geometry": {"coordinates":[-89.661576,36.181972],"type":"Point"}
}