{
  "type": "Feature",
  "properties": {
    "iso:country":"US",
    "sg:address":"3829 Main St",
    "sg:city":"Kansas City",
    "sg:classifiers":[
        {
            "category":"Professional",
            "subcategory":"Business Services",
            "type":"Services"
        }
    ],
    "sg:phone":"+1 816 756 1808",
    "sg:postcode":"64111",
    "sg:province":"MO",
    "wof:name":"Kemnitzer Design Inc",
    "wof:placetype":"venue"
},
  "geometry": {"coordinates":[-94.586006,39.057089],"type":"Point"}
}