{
  "type": "Feature",
  "properties": {
    "iso:country":"US",
    "sg:address":"500 W Olive St",
    "sg:city":"Aurora",
    "sg:classifiers":[
        {
            "category":"Education",
            "subcategory":"School",
            "type":"Public Place"
        }
    ],
    "sg:phone":"+1 417 678 3630",
    "sg:postcode":"65605",
    "sg:province":"MO",
    "wof:name":"Aurora Junior High School",
    "wof:placetype":"venue"
},
  "geometry": {"coordinates":[-93.728645,36.975735],"type":"Point"}
}