{
  "type": "Feature",
  "properties": {
    "iso:country":"US",
    "sg:address":"12451 Norma Ln",
    "sg:city":"Saint Louis",
    "sg:classifiers":[
        {
            "category":"Professional",
            "type":"Services"
        }
    ],
    "sg:phone":"+1 314 355 8653",
    "sg:postcode":"63138",
    "sg:province":"MO",
    "wof:name":"Viked Out Entertainment",
    "wof:placetype":"venue"
},
  "geometry": {"coordinates":[-90.22368,38.801431],"type":"Point"}
}