{
  "type": "Feature",
  "properties": {
    "iso:country":"US",
    "sg:address":"14507 Gammon Rd",
    "sg:city":"Greenwood",
    "sg:classifiers":[
        {
            "category":"Building & Trades",
            "subcategory":"Electrical",
            "type":"Services"
        }
    ],
    "sg:phone":"+1 816 540 5883",
    "sg:postcode":"64034",
    "sg:province":"MO",
    "sg:tags":[
        "electrical",
        "contractor"
    ],
    "wof:name":"Bright Ideas Electric Inc",
    "wof:placetype":"venue"
},
  "geometry": {"coordinates":[-94.239225,38.850393],"type":"Point"}
}