{
  "type": "Feature",
  "properties": {
    "iso:country":"US",
    "sg:address":"9816 E 87 St",
    "sg:city":"Raytown",
    "sg:classifiers":[
        {
            "category":"Professional",
            "subcategory":"Accounting & Tax Preparation",
            "type":"Services"
        }
    ],
    "sg:phone":"+1 816 737 3610",
    "sg:postcode":"64138",
    "sg:province":"MO",
    "sg:tags":[
        "bookkeeping",
        "general"
    ],
    "wof:name":"Accounting Xpress",
    "wof:placetype":"venue"
},
  "geometry": {"coordinates":[-94.466461,38.96528],"type":"Point"}
}