{
  "type": "Feature",
  "properties": {
    "iso:country":"US",
    "sg:address":"4663 S Forest Ave",
    "sg:city":"Springfield",
    "sg:classifiers":[
        {
            "category":"Shopping",
            "subcategory":"Hobbies, Toys, & Games",
            "type":"Retail Goods"
        }
    ],
    "sg:phone":"+1 417 883 8060",
    "sg:postcode":"65810",
    "sg:province":"MO",
    "sg:tags":[
        "basket"
    ],
    "wof:name":"Basket Express",
    "wof:placetype":"venue"
},
  "geometry": {"coordinates":[-93.32633300000001,37.130035],"type":"Point"}
}