{
  "type": "Feature",
  "properties": {
    "iso:country":"US",
    "sg:address":"205 S Barrett St",
    "sg:city":"Nevada",
    "sg:classifiers":[
        {
            "category":"Building & Trades",
            "subcategory":"Construction",
            "type":"Services"
        }
    ],
    "sg:phone":"+1 417 667 5884",
    "sg:postcode":"64772",
    "sg:province":"MO",
    "sg:tags":[
        "general"
    ],
    "wof:name":"Eaton Brothers Construction",
    "wof:placetype":"venue"
},
  "geometry": {"coordinates":[-94.327708,37.835948],"type":"Point"}
}