{
  "type": "Feature",
  "properties": {
    "iso:country":"US",
    "sg:address":"1221 Washington Ave",
    "sg:city":"Saint Louis",
    "sg:classifiers":[
        {
            "category":"Bars & Pubs",
            "type":"Food & Drink"
        }
    ],
    "sg:phone":"+1 314 231 2583",
    "sg:postcode":"63103",
    "sg:province":"MO",
    "sg:tags":[
        "drinking"
    ],
    "wof:name":"Kobal Nightclub",
    "wof:placetype":"venue"
},
  "geometry": {"coordinates":[-90.197441,38.631967],"type":"Point"}
}