{
  "type": "Feature",
  "properties": {
    "iso:country":"US",
    "sg:address":"108 S 16th St",
    "sg:city":"Bethany",
    "sg:classifiers":[
        {
            "category":"Social Services",
            "type":"Services"
        }
    ],
    "sg:phone":"+1 660 425 3755",
    "sg:postcode":"64424",
    "sg:province":"MO",
    "wof:name":"Harrison County Service Center",
    "wof:placetype":"venue"
},
  "geometry": {"coordinates":[-94.03475899999999,40.268634],"type":"Point"}
}