{
  "type": "Feature",
  "properties": {
    "addr:full":"4712 W Kearney St Springfield MO 65803",
    "addr:housenumber":"4712",
    "addr:postcode":"65803",
    "addr:street":"W Kearney St",
    "iso:country":"US",
    "sg:address":"4712 W Kearney St",
    "sg:city":"Springfield",
    "sg:classifiers":[
        {
            "category":"Retail",
            "subcategory":"Auto Rental",
            "type":"Services"
        }
    ],
    "sg:phone":"+1 417 865 9664",
    "sg:postcode":"65803",
    "sg:province":"MO",
    "sg:tags":[
        "passenger",
        "car"
    ],
    "wof:name":"Avis Rent A Car",
    "wof:placetype":"venue"
},
  "geometry": {"coordinates":[-93.37293,37.241656],"type":"Point"}
}