{
  "type": "Feature",
  "properties": {
    "iso:country":"US",
    "sg:address":"1819 Hobbs Rd",
    "sg:city":"Anderson",
    "sg:classifiers":[
        {
            "category":"Place Of Worship",
            "subcategory":"Church",
            "type":"Public Place"
        },
        {
            "category":"Place Of Worship",
            "type":"Public Place"
        }
    ],
    "sg:phone":"+1 417 845 8131",
    "sg:postcode":"64831",
    "sg:province":"MO",
    "sg:tags":[
        "churches-interdenominational",
        "churches-various",
        "denomination"
    ],
    "wof:name":"Jehovas Witness",
    "wof:placetype":"venue"
},
  "geometry": {"coordinates":[-94.477027,36.618215],"type":"Point"}
}