{
  "type": "Feature",
  "properties": {
    "iso:country":"US",
    "sg:address":"2319 Weldon Pkwy",
    "sg:city":"St Louis",
    "sg:classifiers":[
        {
            "category":"Utilities",
            "type":"Services"
        }
    ],
    "sg:phone":"+1 314 878 5787",
    "sg:postcode":"63146",
    "sg:province":"MO",
    "sg:tags":[
        "locating"
    ],
    "wof:name":"S M & P Utility Resources",
    "wof:placetype":"venue"
},
  "geometry": {"coordinates":[-90.440819,38.703154],"type":"Point"}
}