{
  "type": "Feature",
  "properties": {
    "iso:country":"US",
    "sg:address":"24355 Highway 20",
    "sg:city":"Corder",
    "sg:classifiers":[
        {
            "category":"Building & Trades",
            "subcategory":"Landscaping Services",
            "type":"Services"
        }
    ],
    "sg:phone":"+1 660 233 6201",
    "sg:postcode":"64021",
    "sg:province":"MO",
    "sg:tags":[
        "lawn",
        "maintenance"
    ],
    "wof:name":"King Lawn Care",
    "wof:placetype":"venue"
},
  "geometry": {"coordinates":[-93.643237,39.10852],"type":"Point"}
}