{
  "type": "Feature",
  "properties": {
    "iso:country":"US",
    "sg:address":"714 S Washington St",
    "sg:city":"Chillicothe",
    "sg:classifiers":[
        {
            "category":"Restaurant",
            "type":"Food & Drink"
        }
    ],
    "sg:menulink":"http://www.allmenus.com/mo/chillicothe/183097-kfc---kentucky-fried-chicken/menu/",
    "sg:phone":"+1 816 646 4001",
    "sg:postcode":"64601",
    "sg:province":"MO",
    "sg:tags":[
        "american",
        "chicken"
    ],
    "wof:name":"KFC - Kentucky Fried Chicken",
    "wof:placetype":"venue"
},
  "geometry": {"coordinates":[-93.55282,39.77936],"type":"Point"}
}