{
  "type": "Feature",
  "properties": {
    "iso:country":"US",
    "sg:address":"1217 N Jesse James Rd",
    "sg:city":"Excelsior Springs",
    "sg:classifiers":[
        {
            "category":"Food & Beverages",
            "subcategory":"Groceries & Convenience Stores",
            "type":"Retail Goods"
        }
    ],
    "sg:phone":"+1 816 637 7788",
    "sg:postcode":"64024",
    "sg:province":"MO",
    "sg:tags":[
        "station",
        "gasoline"
    ],
    "wof:name":"Q F C",
    "wof:placetype":"venue"
},
  "geometry": {"coordinates":[-94.235015,39.354413],"type":"Point"}
}