{
  "type": "Feature",
  "properties": {
    "iso:country":"US",
    "sg:address":"531 S Westwood Blvd",
    "sg:city":"Poplar Bluff",
    "sg:classifiers":[
        {
            "category":"Shopping",
            "subcategory":"Clothing, Apparel, & Fashions",
            "type":"Retail Goods"
        }
    ],
    "sg:phone":"+1 573 785 5154",
    "sg:postcode":"63901",
    "sg:province":"MO",
    "wof:name":"Cato",
    "wof:placetype":"venue"
},
  "geometry": {"coordinates":[-90.408946,36.75356],"type":"Point"}
}