{
  "type": "Feature",
  "properties": {
    "iso:country":"US",
    "sg:address":"1317 S Morley St",
    "sg:city":"Moberly",
    "sg:classifiers":[
        {
            "category":"Freight",
            "type":"Transportation"
        }
    ],
    "sg:phone":"+1 660 263 5100",
    "sg:postcode":"65270",
    "sg:province":"MO",
    "sg:tags":[
        "mover"
    ],
    "wof:name":"Mallory Van & Storage Inc",
    "wof:placetype":"venue"
},
  "geometry": {"coordinates":[-92.43414199999999,39.404976],"type":"Point"}
}