{
  "type": "Feature",
  "properties": {
    "iso:country":"US",
    "sg:address":"17733 Highway Hh",
    "sg:city":"Neosho",
    "sg:classifiers":[
        {
            "category":"Home & Garden",
            "subcategory":"Building Materials",
            "type":"Retail Goods"
        },
        {
            "category":"Building & Trades",
            "subcategory":"Construction",
            "type":"Services"
        }
    ],
    "sg:phone":"+1 417 451 3862",
    "sg:postcode":"64850",
    "sg:province":"MO",
    "sg:tags":[
        "roofing",
        "industrial",
        "altering",
        "improvement",
        "contractors-commercial",
        "contractor",
        "remodeling"
    ],
    "wof:name":"Thurman Roofing",
    "wof:placetype":"venue"
},
  "geometry": {"coordinates":[-94.32226199999999,36.836366],"type":"Point"}
}