{
  "type": "Feature",
  "properties": {
    "iso:country":"US",
    "sg:address":"220 W Battlefield Rd",
    "sg:city":"Springfield",
    "sg:classifiers":[
        {
            "category":"Shopping",
            "subcategory":"Hobbies, Toys, & Games",
            "type":"Retail Goods"
        }
    ],
    "sg:phone":"+1 417 887 5592",
    "sg:postcode":"65807",
    "sg:province":"MO",
    "sg:tags":[
        "model",
        "supply"
    ],
    "sg:website":"www.battlefieldstation.com",
    "wof:name":"Battlefield Station Family",
    "wof:placetype":"venue"
},
  "geometry": {"coordinates":[-93.29386100000001,37.159868],"type":"Point"}
}