{
  "type": "Feature",
  "properties": {
    "iso:country":"US",
    "sg:address":"17519 Country Lake Estates Ct",
    "sg:city":"Chesterfield",
    "sg:classifiers":[
        {
            "category":"Professional",
            "subcategory":"Business Services",
            "type":"Services"
        }
    ],
    "sg:phone":"+1 636 519 8998",
    "sg:postcode":"63005",
    "sg:province":"MO",
    "sg:tags":[
        "testing",
        "infrared"
    ],
    "wof:name":"Infrared Diagnostic Services",
    "wof:placetype":"venue"
},
  "geometry": {"coordinates":[-90.624673,38.652134],"type":"Point"}
}