{
  "type": "Feature",
  "properties": {
    "iso:country":"US",
    "sg:address":"1221 Illinois Ave",
    "sg:city":"Joplin",
    "sg:classifiers":[
        {
            "category":"Wholesale",
            "subcategory":"Painting Supplies",
            "type":"Manufacturing & Wholesale Goods"
        }
    ],
    "sg:phone":"+1 417 626 0488",
    "sg:postcode":"64801",
    "sg:province":"MO",
    "sg:tags":[
        "paint-wholesale",
        "manufacturer"
    ],
    "wof:name":"Spectrum Paint Company",
    "wof:placetype":"venue"
},
  "geometry": {"coordinates":[-94.50278,37.077801],"type":"Point"}
}