{
  "type": "Feature",
  "properties": {
    "iso:country":"US",
    "sg:address":"104 5th St",
    "sg:city":"Gerald",
    "sg:classifiers":[
        {
            "category":"Autos & Motor Vehicles",
            "subcategory":"Automobile Sales",
            "type":"Retail Goods"
        }
    ],
    "sg:phone":"+1 573 764 3636",
    "sg:postcode":"63037",
    "sg:province":"MO",
    "sg:tags":[
        "new",
        "used",
        "dealer",
        "car"
    ],
    "wof:name":"E L Auto Sales",
    "wof:placetype":"venue"
},
  "geometry": {"coordinates":[-91.33184799999999,38.398844],"type":"Point"}
}