{
  "type": "Feature",
  "properties": {
    "iso:country":"US",
    "sg:address":"7528 Florissant Rd",
    "sg:city":"Saint Louis",
    "sg:classifiers":[
        {
            "category":"Retail",
            "subcategory":"Car Wash",
            "type":"Services"
        }
    ],
    "sg:phone":"+1 314 389 3156",
    "sg:postcode":"63121",
    "sg:province":"MO",
    "wof:name":"S & S Hand Car Wash Normandy",
    "wof:placetype":"venue"
},
  "geometry": {"coordinates":[-90.297501,38.714401],"type":"Point"}
}