{
  "type": "Feature",
  "properties": {
    "iso:country":"US",
    "sg:address":"3325 Prospect Ave",
    "sg:city":"Kansas City",
    "sg:classifiers":[
        {
            "category":"Organizations",
            "subcategory":"Non-profit Organization",
            "type":"Services"
        }
    ],
    "sg:phone":"+1 816 921 1963",
    "sg:postcode":"64128",
    "sg:province":"MO",
    "wof:name":"Palestine Senior Citizens Ctr",
    "wof:placetype":"venue"
},
  "geometry": {"coordinates":[-94.553014,39.064877],"type":"Point"}
}