{
  "type": "Feature",
  "properties": {
    "iso:country":"US",
    "sg:address":"300 SW 15 St",
    "sg:city":"Blue Springs",
    "sg:classifiers":[
        {
            "category":"Professional",
            "subcategory":"Lawyer & Legal Services",
            "type":"Services"
        }
    ],
    "sg:phone":"+1 816 220 3086",
    "sg:postcode":"64015",
    "sg:province":"MO",
    "sg:tags":[
        "attorney"
    ],
    "wof:name":"Midland Professional Assoc",
    "wof:placetype":"venue"
},
  "geometry": {"coordinates":[-94.281633,39.015713],"type":"Point"}
}