{
  "type": "Feature",
  "properties": {
    "iso:country":"US",
    "sg:address":"10515 Watson Rd",
    "sg:city":"Saint Louis",
    "sg:classifiers":[
        {
            "category":"Wholesale",
            "subcategory":"Construction Materials",
            "type":"Manufacturing & Wholesale Goods"
        }
    ],
    "sg:phone":"+1 314 965 0300",
    "sg:postcode":"63127",
    "sg:province":"MO",
    "sg:tags":[
        "hardwood",
        "lumber"
    ],
    "wof:name":"Saint Louis Hardwood",
    "wof:placetype":"venue"
},
  "geometry": {"coordinates":[-90.406901,38.555567],"type":"Point"}
}