{
  "type": "Feature",
  "properties": {
    "iso:country":"US",
    "sg:address":"6960 Creekview Trl",
    "sg:city":"Affton",
    "sg:classifiers":[
        {
            "category":"Real Estate",
            "subcategory":"Real Estate Operator",
            "type":"Services"
        }
    ],
    "sg:phone":"+1 314 849 0515",
    "sg:postcode":"63123",
    "sg:province":"MO",
    "sg:tags":[
        "apartment"
    ],
    "wof:name":"Marlborough Trails Apartments",
    "wof:placetype":"venue"
},
  "geometry": {"coordinates":[-90.336804,38.565752],"type":"Point"}
}