{
  "type": "Feature",
  "properties": {
    "iso:country":"US",
    "sg:address":"967 Gardenview Office Pkwy",
    "sg:city":"Saint Louis",
    "sg:classifiers":[
        {
            "category":"Travel",
            "subcategory":"Campground",
            "type":"Entertainment"
        }
    ],
    "sg:phone":"+1 218 751 5171",
    "sg:postcode":"63141",
    "sg:province":"MO",
    "sg:tags":[
        "summer",
        "camp"
    ],
    "wof:name":"Camp Thunderbird For Girls",
    "wof:placetype":"venue"
},
  "geometry": {"coordinates":[-90.40702899999999,38.674793],"type":"Point"}
}