{
  "type": "Feature",
  "properties": {
    "iso:country":"US",
    "sg:address":"704 N Tucker Blvd",
    "sg:city":"Saint Louis",
    "sg:classifiers":[
        {
            "category":"Food & Beverages",
            "subcategory":"Groceries & Convenience Stores",
            "type":"Retail Goods"
        }
    ],
    "sg:phone":"+1 314 621 6511",
    "sg:postcode":"63101",
    "sg:province":"MO",
    "wof:name":"John's Market",
    "wof:placetype":"venue"
},
  "geometry": {"coordinates":[-90.196297,38.632401],"type":"Point"}
}