{
  "type": "Feature",
  "properties": {
    "iso:country":"US",
    "sg:address":"807 Brenda St",
    "sg:city":"New Florence",
    "sg:phone":"+1 573 835 2020",
    "sg:postcode":"63363",
    "sg:province":"MO",
    "sg:tags":[
        "farm",
        "soybean"
    ],
    "wof:name":"Larry Elflein",
    "wof:placetype":"venue"
},
  "geometry": {"coordinates":[-91.43991200000001,38.915107],"type":"Point"}
}