{
  "type": "Feature",
  "properties": {
    "iso:country":"US",
    "sg:address":"437 W State St",
    "sg:city":"Linneus",
    "sg:classifiers":[
        {
            "category":"Shopping",
            "subcategory":"Bicycles & Sporting Goods",
            "type":"Retail Goods"
        }
    ],
    "sg:phone":"+1 660 895 5164",
    "sg:postcode":"64653",
    "sg:province":"MO",
    "sg:tags":[
        "bait",
        "fishing"
    ],
    "wof:name":"North Missouri Bait Farm",
    "wof:placetype":"venue"
},
  "geometry": {"coordinates":[-93.19485299999999,39.879135],"type":"Point"}
}