{
  "type": "Feature",
  "properties": {
    "iso:country":"US",
    "sg:address":"512 N East St",
    "sg:city":"Albany",
    "sg:classifiers":[
        {
            "category":"Government",
            "subcategory":"Office",
            "type":"Public Place"
        }
    ],
    "sg:phone":"+1 660 726 5255",
    "sg:postcode":"64402",
    "sg:province":"MO",
    "sg:tags":[
        "agricultural",
        "regulation",
        "marketing"
    ],
    "wof:name":"Gentry County Swcd",
    "wof:placetype":"venue"
},
  "geometry": {"coordinates":[-94.32995,40.250021],"type":"Point"}
}