{
  "type": "Feature",
  "properties": {
    "iso:country":"US",
    "sg:address":"198 State Hwy 92",
    "sg:city":"Kearney",
    "sg:classifiers":[
        {
            "category":"Building & Trades",
            "subcategory":"Plumbing",
            "type":"Services"
        }
    ],
    "sg:phone":"+1 816 628 2254",
    "sg:postcode":"64060",
    "sg:province":"MO",
    "sg:tags":[
        "plumbing",
        "contractor"
    ],
    "wof:name":"Jamison Plumbing",
    "wof:placetype":"venue"
},
  "geometry": {"coordinates":[-94.36426299999999,39.367923],"type":"Point"}
}