{
  "type": "Feature",
  "properties": {
    "iso:country":"US",
    "sg:address":"143 W Yoakum Ave",
    "sg:city":"Chaffee",
    "sg:classifiers":[
        {
            "category":"Professional",
            "subcategory":"Business Services",
            "type":"Services"
        }
    ],
    "sg:phone":"+1 573 887 3400",
    "sg:postcode":"63740",
    "sg:province":"MO",
    "sg:tags":[
        "packaging"
    ],
    "wof:name":"Irydia Packaging Inc",
    "wof:placetype":"venue"
},
  "geometry": {"coordinates":[-89.656986,37.180658],"type":"Point"}
}