{
  "type": "Feature",
  "properties": {
    "iso:country":"US",
    "sg:address":"118 N Church St",
    "sg:city":"Silex",
    "sg:classifiers":[
        {
            "category":"Organizations",
            "subcategory":"Community Association",
            "type":"Services"
        }
    ],
    "sg:phone":"+1 573 384 5647",
    "sg:postcode":"63377",
    "sg:province":"MO",
    "sg:tags":[
        "fraternal"
    ],
    "wof:name":"Silex Masonic Lodge 75",
    "wof:placetype":"venue"
},
  "geometry": {"coordinates":[-91.057858,39.125961],"type":"Point"}
}