{
  "type": "Feature",
  "properties": {
    "iso:country":"US",
    "sg:address":"207 W Lee St",
    "sg:city":"Hayti",
    "sg:classifiers":[
        {
            "category":"Shopping",
            "subcategory":"Gifts & Souvenirs",
            "type":"Retail Goods"
        }
    ],
    "sg:phone":"+1 573 359 1302",
    "sg:postcode":"63851",
    "sg:province":"MO",
    "sg:tags":[
        "announcement",
        "invitation"
    ],
    "wof:name":"All In It For Him",
    "wof:placetype":"venue"
},
  "geometry": {"coordinates":[-89.75277800000001,36.236829],"type":"Point"}
}