{
  "type": "Feature",
  "properties": {
    "iso:country":"US",
    "sg:address":"2671 E Sunshine St",
    "sg:city":"Springfield",
    "sg:classifiers":[
        {
            "category":"Autos & Motor Vehicles",
            "subcategory":"Fuel & Gas Station",
            "type":"Retail Goods"
        }
    ],
    "sg:phone":"+1 417 881 1039",
    "sg:postcode":"65804",
    "sg:province":"MO",
    "sg:tags":[
        "station",
        "gasoline"
    ],
    "wof:name":"Clark Oil",
    "wof:placetype":"venue"
},
  "geometry": {"coordinates":[-93.242807,37.180921],"type":"Point"}
}