{
  "type": "Feature",
  "properties": {
    "iso:country":"US",
    "sg:address":"3500 Telegraph Rd",
    "sg:city":"Arnold",
    "sg:classifiers":[
        {
            "category":"Building & Trades",
            "subcategory":"Landscaping Services",
            "type":"Services"
        }
    ],
    "sg:phone":"+1 636 464 5181",
    "sg:postcode":"63010",
    "sg:province":"MO",
    "wof:name":"Declue Tree Service",
    "wof:placetype":"venue"
},
  "geometry": {"coordinates":[-90.36396999999999,38.40709],"type":"Point"}
}