{
  "type": "Feature",
  "properties": {
    "iso:country":"US",
    "sg:address":"11900 Jessica Ln",
    "sg:city":"Raytown",
    "sg:classifiers":[
        {
            "category":"Social Services",
            "subcategory":"Job Training",
            "type":"Services"
        }
    ],
    "sg:phone":"+1 816 353 1372",
    "sg:postcode":"64138",
    "sg:province":"MO",
    "sg:tags":[
        "rehabilitation"
    ],
    "wof:name":"Rehab Care Group",
    "wof:placetype":"venue"
},
  "geometry": {"coordinates":[-94.443557,38.976963],"type":"Point"}
}