{
  "type": "Feature",
  "properties": {
    "iso:country":"US",
    "sg:address":"109 W Fort Scott St",
    "sg:city":"Butler",
    "sg:classifiers":[
        {
            "category":"Banks & Credit Unions",
            "subcategory":"Bank",
            "type":"Services"
        }
    ],
    "sg:phone":"+1 660 200 2164",
    "sg:postcode":"64730",
    "sg:province":"MO",
    "sg:tags":[
        "federal"
    ],
    "wof:name":"Greater Iowa Credit Union",
    "wof:placetype":"venue"
},
  "geometry": {"coordinates":[-94.333653,38.256496],"type":"Point"}
}