{
  "type": "Feature",
  "properties": {
    "iso:country":"US",
    "sg:address":"9312 White Ave",
    "sg:city":"Saint Louis",
    "sg:classifiers":[
        {
            "category":"Health Services",
            "subcategory":"Clinic",
            "type":"Services"
        }
    ],
    "sg:phone":"+1 314 968 1112",
    "sg:postcode":"63144",
    "sg:province":"MO",
    "wof:name":"Premier Plasma",
    "wof:placetype":"venue"
},
  "geometry": {"coordinates":[-90.35743100000001,38.620909],"type":"Point"}
}