{
  "type": "Feature",
  "properties": {
    "iso:country":"US",
    "sg:address":"1050 Bittersweet Rd",
    "sg:city":"Lake Ozark",
    "sg:classifiers":[
        {
            "category":"Organizations",
            "subcategory":"Non-profit Organization",
            "type":"Services"
        }
    ],
    "sg:phone":"+1 573 365 2111",
    "sg:postcode":"65049",
    "sg:province":"MO",
    "sg:tags":[
        "information",
        "alcoholism",
        "treatment"
    ],
    "wof:name":"Clear Pointe",
    "wof:placetype":"venue"
},
  "geometry": {"coordinates":[-92.733822,38.200569],"type":"Point"}
}