{
  "type": "Feature",
  "properties": {
    "iso:country":"US",
    "sg:address":"4610 Mexico Rd",
    "sg:city":"Saint Peters",
    "sg:classifiers":[
        {
            "category":"Banks & Credit Unions",
            "subcategory":"Bank",
            "type":"Services"
        }
    ],
    "sg:phone":"+1 636 940 7827",
    "sg:postcode":"63376",
    "sg:province":"MO",
    "sg:tags":[
        "broker",
        "mortgage"
    ],
    "wof:name":"N-Star",
    "wof:placetype":"venue"
},
  "geometry": {"coordinates":[-90.580765,38.792036],"type":"Point"}
}