{
  "type": "Feature",
  "properties": {
    "iso:country":"US",
    "sg:address":"5299 E Farm Rd 142",
    "sg:city":"Springfield",
    "sg:classifiers":[
        {
            "category":"Recreation",
            "type":"Entertainment"
        }
    ],
    "sg:phone":"+1 417 866 0756",
    "sg:postcode":"65809",
    "sg:province":"MO",
    "sg:tags":[
        "stable"
    ],
    "wof:name":"High Prairie Stables",
    "wof:placetype":"venue"
},
  "geometry": {"coordinates":[-93.18322499999999,37.190022],"type":"Point"}
}