{
  "type": "Feature",
  "properties": {
    "iso:country":"US",
    "sg:address":"204 E Ash St",
    "sg:city":"Columbia",
    "sg:classifiers":[
        {
            "category":"Organizations",
            "subcategory":"Religious Organization",
            "type":"Services"
        }
    ],
    "sg:phone":"+1 573 443 5423",
    "sg:postcode":"65203",
    "sg:province":"MO",
    "sg:tags":[
        "church"
    ],
    "wof:name":"St Luke United Methodist Chr",
    "wof:placetype":"venue"
},
  "geometry": {"coordinates":[-92.335193,38.953626],"type":"Point"}
}