{
  "type": "Feature",
  "properties": {
    "iso:country":"US",
    "sg:address":"113 E Promenade St",
    "sg:city":"Mexico",
    "sg:classifiers":[
        {
            "category":"Health Services",
            "subcategory":"Optometrist",
            "type":"Services"
        }
    ],
    "sg:phone":"+1 573 581 3848",
    "sg:postcode":"65265",
    "sg:province":"MO",
    "sg:tags":[
        "optical",
        "good"
    ],
    "wof:name":"David J Luke O D",
    "wof:placetype":"venue"
},
  "geometry": {"coordinates":[-91.882498,39.171404],"type":"Point"}
}