{
  "type": "Feature",
  "properties": {
    "iso:country":"US",
    "sg:address":"1 W Olive St",
    "sg:city":"Aurora",
    "sg:classifiers":[
        {
            "category":"Bars & Pubs",
            "type":"Food & Drink"
        }
    ],
    "sg:phone":"+1 417 678 1115",
    "sg:postcode":"65605",
    "sg:province":"MO",
    "sg:tags":[
        "drinking"
    ],
    "wof:name":"Brothers Rest & Lounge",
    "wof:placetype":"venue"
},
  "geometry": {"coordinates":[-93.72271000000001,36.9754],"type":"Point"}
}