{
  "type": "Feature",
  "properties": {
    "iso:country":"US",
    "sg:address":"5354 Southwest Ave",
    "sg:city":"St Louis",
    "sg:classifiers":[
        {
            "category":"Retail",
            "subcategory":"Repair Shop",
            "type":"Services"
        }
    ],
    "sg:phone":"+1 314 772 5277",
    "sg:postcode":"63139",
    "sg:province":"MO",
    "sg:tags":[
        "equipment",
        "conditioning",
        "air"
    ],
    "wof:name":"Hi-Pointe Air Cond & Heating",
    "wof:placetype":"venue"
},
  "geometry": {"coordinates":[-90.27633,38.610769],"type":"Point"}
}