{
  "type": "Feature",
  "properties": {
    "iso:country":"US",
    "sg:address":"33 E Broadway",
    "sg:city":"Columbia",
    "sg:classifiers":[
        {
            "category":"Real Estate",
            "subcategory":"Real Estate Agent",
            "type":"Services"
        }
    ],
    "sg:phone":"+1 573 442 6121",
    "sg:postcode":"65201",
    "sg:province":"MO",
    "sg:tags":[
        "psychologist"
    ],
    "sg:website":"www.boone1.com",
    "wof:name":"Re/Max Boone Realty",
    "wof:placetype":"venue"
},
  "geometry": {"coordinates":[-92.338014,38.951698],"type":"Point"}
}