{
  "type": "Feature",
  "properties": {
    "iso:country":"US",
    "sg:address":"401 N Main St",
    "sg:city":"Gravois Mills",
    "sg:classifiers":[
        {
            "category":"Shopping",
            "subcategory":"Clothing, Apparel, & Fashions",
            "type":"Retail Goods"
        }
    ],
    "sg:phone":"+1 573 374 6522",
    "sg:postcode":"65037",
    "sg:province":"MO",
    "wof:name":"Twin Oaks Apparel",
    "wof:placetype":"venue"
},
  "geometry": {"coordinates":[-92.8389,38.203579],"type":"Point"}
}