{
  "type": "Feature",
  "properties": {
    "iso:country":"US",
    "sg:address":"1011 W 103rd St",
    "sg:city":"Kansas City",
    "sg:classifiers":[
        {
            "category":"Autos & Motor Vehicles",
            "subcategory":"Automobile Sales",
            "type":"Retail Goods"
        }
    ],
    "sg:phone":"+1 816 943 6060",
    "sg:postcode":"64114",
    "sg:province":"MO",
    "sg:tags":[
        "used"
    ],
    "wof:name":"Saturn",
    "wof:placetype":"venue"
},
  "geometry": {"coordinates":[-94.603264,38.941761],"type":"Point"}
}