{
  "type": "Feature",
  "properties": {
    "iso:country":"US",
    "sg:address":"1537 Orchard Lakes Dr",
    "sg:city":"Saint Louis",
    "sg:classifiers":[
        {
            "category":"Professional",
            "subcategory":"Business Services",
            "type":"Services"
        }
    ],
    "sg:phone":"+1 314 997 1083",
    "sg:postcode":"63146",
    "sg:province":"MO",
    "wof:name":"D L Coe",
    "wof:placetype":"venue"
},
  "geometry": {"coordinates":[-90.448896,38.685643],"type":"Point"}
}