{
  "type": "Feature",
  "properties": {
    "iso:country":"US",
    "sg:address":"1279 Autumn Wood Cir",
    "sg:city":"Ballwin",
    "sg:classifiers":[
        {
            "category":"Professional",
            "subcategory":"Computer Services",
            "type":"Services"
        }
    ],
    "sg:phone":"+1 636 391 6135",
    "sg:postcode":"63011",
    "sg:province":"MO",
    "sg:tags":[
        "programing",
        "custom"
    ],
    "wof:name":"Vsam Systems Inc",
    "wof:placetype":"venue"
},
  "geometry": {"coordinates":[-90.50256,38.610173],"type":"Point"}
}