{
  "type": "Feature",
  "properties": {
    "iso:country":"US",
    "sg:address":"1835 Jefferson St",
    "sg:city":"Kansas City",
    "sg:classifiers":[
        {
            "category":"Communications",
            "type":"Services"
        }
    ],
    "sg:phone":"+1 816 474 4591",
    "sg:postcode":"64108",
    "sg:province":"MO",
    "sg:tags":[
        "communication"
    ],
    "wof:name":"Alaniz Communications",
    "wof:placetype":"venue"
},
  "geometry": {"coordinates":[-94.592304,39.089675],"type":"Point"}
}