{
  "type": "Feature",
  "properties": {
    "iso:country":"US",
    "sg:address":"4635 Wyandotte St",
    "sg:city":"Kansas City",
    "sg:classifiers":[
        {
            "category":"Health Services",
            "subcategory":"Chiropractor",
            "type":"Services"
        }
    ],
    "sg:phone":"+1 816 753 0193",
    "sg:postcode":"64112",
    "sg:province":"MO",
    "wof:name":"Arete Chiropractic & Wellness",
    "wof:placetype":"venue"
},
  "geometry": {"coordinates":[-94.589281,39.042673],"type":"Point"}
}