{
  "type": "Feature",
  "properties": {
    "iso:country":"US",
    "sg:address":"1600 Main St",
    "sg:city":"Blue Springs",
    "sg:classifiers":[
        {
            "category":"Retail",
            "subcategory":"Funeral Services",
            "type":"Services"
        }
    ],
    "sg:phone":"+1 816 229 3276",
    "sg:postcode":"64015",
    "sg:province":"MO",
    "wof:name":"Newcomers D W Sons Fnrl Homes",
    "wof:placetype":"venue"
},
  "geometry": {"coordinates":[-94.28378600000001,39.018553],"type":"Point"}
}