{
  "type": "Feature",
  "properties": {
    "iso:country":"US",
    "sg:address":"1820 Market St Ste 107",
    "sg:city":"Saint Louis",
    "sg:classifiers":[
        {
            "category":"Arts & Performance",
            "subcategory":"Art Gallery",
            "type":"Entertainment"
        }
    ],
    "sg:phone":"+1 314 241 1113",
    "sg:postcode":"63103",
    "sg:province":"MO",
    "sg:website":"www.ceciuniquegallery.com",
    "wof:name":"Ceci Unique Gallery",
    "wof:placetype":"venue"
},
  "geometry": {"coordinates":[-90.206614,38.629333],"type":"Point"}
}