{
  "type": "Feature",
  "properties": {
    "iso:country":"US",
    "sg:address":"1274 Madison 447",
    "sg:city":"Des Arc",
    "sg:phone":"+1 573 856 4537",
    "sg:postcode":"63636",
    "sg:province":"MO",
    "sg:tags":[
        "farm",
        "soybean",
        "beef",
        "feedlot",
        "cattle"
    ],
    "wof:name":"Jerry Belmar",
    "wof:placetype":"venue"
},
  "geometry": {"coordinates":[-90.48069,37.346735],"type":"Point"}
}