{
  "type": "Feature",
  "properties": {
    "iso:country":"US",
    "sg:address":"1306 Hwy K",
    "sg:city":"O Fallon",
    "sg:classifiers":[
        {
            "category":"Personal",
            "subcategory":"Beauty Salon",
            "type":"Services"
        }
    ],
    "sg:phone":"+1 636 379 0670",
    "sg:postcode":"63366",
    "sg:province":"MO",
    "sg:tags":[
        "shop"
    ],
    "wof:name":"Supercuts",
    "wof:placetype":"venue"
},
  "geometry": {"coordinates":[-90.698516,38.792991],"type":"Point"}
}