{
  "type": "Feature",
  "properties": {
    "iso:country":"US",
    "sg:address":"52 E Arrow St",
    "sg:city":"Marshall",
    "sg:classifiers":[
        {
            "category":"Shopping",
            "subcategory":"Gifts & Souvenirs",
            "type":"Retail Goods"
        }
    ],
    "sg:phone":"+1 660 886 5535",
    "sg:postcode":"65340",
    "sg:province":"MO",
    "sg:tags":[
        "shop"
    ],
    "wof:name":"Jenni's Hallmark",
    "wof:placetype":"venue"
},
  "geometry": {"coordinates":[-93.196264,39.12026],"type":"Point"}
}