{
  "type": "Feature",
  "properties": {
    "iso:country":"US",
    "sg:address":"605 E Booneslick Rd Ste B",
    "sg:city":"Warrenton",
    "sg:classifiers":[
        {
            "category":"Health Services",
            "subcategory":"Doctor",
            "type":"Services"
        },
        {
            "category":"Health Services",
            "subcategory":"Clinic",
            "type":"Services"
        }
    ],
    "sg:phone":"+1 636 456 6103",
    "sg:postcode":"63383",
    "sg:province":"MO",
    "sg:tags":[
        "physician",
        "family",
        "practice",
        "surgeons",
        "osteopathic",
        "medicine"
    ],
    "wof:name":"Patients First Health Care",
    "wof:placetype":"venue"
},
  "geometry": {"coordinates":[-91.155674,38.812144],"type":"Point"}
}