{
  "type": "Feature",
  "properties": {
    "iso:country":"US",
    "sg:address":"16494 King Rd",
    "sg:city":"Lawson",
    "sg:classifiers":[
        {
            "category":"Shopping",
            "subcategory":"Clothing, Apparel, & Fashions",
            "type":"Retail Goods"
        }
    ],
    "sg:phone":"+1 816 630 7287",
    "sg:postcode":"64062",
    "sg:province":"MO",
    "sg:tags":[
        "personal"
    ],
    "wof:name":"Carolyns Wedding Wonderland",
    "wof:placetype":"venue"
},
  "geometry": {"coordinates":[-94.182573,39.389145],"type":"Point"}
}