{
  "type": "Feature",
  "properties": {
    "iso:country":"US",
    "sg:address":"12810 NE 136th St",
    "sg:city":"Kearney",
    "sg:classifiers":[
        {
            "category":"Personal",
            "subcategory":"Beauty Salon",
            "type":"Services"
        }
    ],
    "sg:phone":"+1 816 781 9379",
    "sg:postcode":"64060",
    "sg:province":"MO",
    "wof:name":"Musgrove Hair Styling",
    "wof:placetype":"venue"
},
  "geometry": {"coordinates":[-94.422191,39.338761],"type":"Point"}
}