{
  "type": "Feature",
  "properties": {
    "iso:country":"US",
    "sg:address":"1515 US Hwy 169",
    "sg:city":"Smithville",
    "sg:classifiers":[
        {
            "category":"Restaurant",
            "type":"Food & Drink"
        }
    ],
    "sg:phone":"+1 816 532 0014",
    "sg:postcode":"64089",
    "sg:province":"MO",
    "wof:name":"Mc Donald's",
    "wof:placetype":"venue"
},
  "geometry": {"coordinates":[-94.58361499999999,39.412194],"type":"Point"}
}