{
  "type": "Feature",
  "properties": {
    "iso:country":"US",
    "sg:address":"619 Lambert Pointe Dr",
    "sg:city":"Hazelwood",
    "sg:classifiers":[
        {
            "category":"Wholesale",
            "subcategory":"Hardware",
            "type":"Manufacturing & Wholesale Goods"
        }
    ],
    "sg:phone":"+1 314 291 4113",
    "sg:postcode":"63042",
    "sg:province":"MO",
    "sg:tags":[
        "water",
        "equipment",
        "purification"
    ],
    "wof:name":"U S Filter Iron/Pure Inc",
    "wof:placetype":"venue"
},
  "geometry": {"coordinates":[-90.37575,38.773628],"type":"Point"}
}