{
  "type": "Feature",
  "properties": {
    "iso:country":"US",
    "sg:address":"3509 S Spring Ave",
    "sg:city":"St Louis",
    "sg:classifiers":[
        {
            "category":"Communications",
            "subcategory":"Film & Video Production",
            "type":"Services"
        }
    ],
    "sg:phone":"+1 314 772 3205",
    "sg:postcode":"63116",
    "sg:province":"MO",
    "sg:tags":[
        "taping"
    ],
    "wof:name":"Everlasting Productions",
    "wof:placetype":"venue"
},
  "geometry": {"coordinates":[-90.247744,38.592101],"type":"Point"}
}