{
  "type": "Feature",
  "properties": {
    "iso:country":"US",
    "sg:address":"1341 Hamilton Ave",
    "sg:city":"Saint Louis",
    "sg:classifiers":[
        {
            "category":"Retail",
            "subcategory":"Laundry & Dry Cleaning",
            "type":"Services"
        }
    ],
    "sg:phone":"+1 314 721 8673",
    "sg:postcode":"63112",
    "sg:province":"MO",
    "sg:tags":[
        "cleaner"
    ],
    "wof:name":"Dorothy's Cleaners",
    "wof:placetype":"venue"
},
  "geometry": {"coordinates":[-90.2854,38.669601],"type":"Point"}
}