{
  "type": "Feature",
  "properties": {
    "iso:country":"US",
    "sg:address":"12375 Running Horse Rd",
    "sg:city":"Platte City",
    "sg:classifiers":[
        {
            "category":"Real Estate",
            "subcategory":"Real Estate Agent",
            "type":"Services"
        }
    ],
    "sg:phone":"+1 816 413 0147",
    "sg:postcode":"64079",
    "sg:province":"MO",
    "wof:name":"Reece & Nichols Running Horse",
    "wof:placetype":"venue"
},
  "geometry": {"coordinates":[-94.76099600000001,39.317308],"type":"Point"}
}