{
  "type": "Feature",
  "properties": {
    "iso:country":"US",
    "sg:address":"117 Locust St",
    "sg:city":"Barnett",
    "sg:classifiers":[
        {
            "category":"Autos & Motor Vehicles",
            "subcategory":"Automobile Sales",
            "type":"Retail Goods"
        }
    ],
    "sg:phone":"+1 573 392 5680",
    "sg:postcode":"65011",
    "sg:province":"MO",
    "sg:tags":[
        "used"
    ],
    "wof:name":"John Lapp Auto Sales",
    "wof:placetype":"venue"
},
  "geometry": {"coordinates":[-92.674209,38.380884],"type":"Point"}
}