{
  "type": "Feature",
  "properties": {
    "iso:country":"US",
    "sg:address":"8780 Big Bend Blvd",
    "sg:city":"St Louis",
    "sg:classifiers":[
        {
            "category":"Shopping",
            "subcategory":"Computers & Home Electronics",
            "type":"Retail Goods"
        }
    ],
    "sg:phone":"+1 314 918 7600",
    "sg:postcode":"63119",
    "sg:province":"MO",
    "sg:tags":[
        "equipment",
        "dealer"
    ],
    "sg:website":"www.compsolstl.com",
    "wof:name":"Computer Solutions",
    "wof:placetype":"venue"
},
  "geometry": {"coordinates":[-90.360028,38.58191],"type":"Point"}
}