{
  "type": "Feature",
  "properties": {
    "iso:country":"US",
    "sg:address":"1404 Old Cape Rd",
    "sg:city":"Jackson",
    "sg:classifiers":[
        {
            "category":"Real Estate",
            "subcategory":"Real Estate Agent",
            "type":"Services"
        }
    ],
    "sg:phone":"+1 573 204 1355",
    "sg:postcode":"63755",
    "sg:province":"MO",
    "sg:tags":[
        "appraiser"
    ],
    "wof:name":"Kinder Appraisal Co",
    "wof:placetype":"venue"
},
  "geometry": {"coordinates":[-89.65190800000001,37.374068],"type":"Point"}
}