{
  "type": "Feature",
  "properties": {
    "iso:country":"US",
    "sg:address":"312 Harold St",
    "sg:city":"Slater",
    "sg:classifiers":[
        {
            "category":"Restaurant",
            "type":"Food & Drink"
        }
    ],
    "sg:phone":"+1 660 529 2990",
    "sg:postcode":"65349",
    "sg:province":"MO",
    "sg:tags":[
        "eating",
        "caterer"
    ],
    "wof:name":"Maxine's Tea House & Catering",
    "wof:placetype":"venue"
},
  "geometry": {"coordinates":[-93.065997,39.222797],"type":"Point"}
}