{
  "type": "Feature",
  "properties": {
    "iso:country":"US",
    "sg:address":"2714 Plymouth Dr",
    "sg:city":"Cape Girardeau",
    "sg:classifiers":[
        {
            "category":"Professional",
            "type":"Services"
        }
    ],
    "sg:phone":"+1 573 651 3521",
    "sg:postcode":"63701",
    "sg:province":"MO",
    "wof:name":"Lifestyle Protection LLC",
    "wof:placetype":"venue"
},
  "geometry": {"coordinates":[-89.558283,37.325023],"type":"Point"}
}