{
  "type": "Feature",
  "properties": {
    "iso:country":"US",
    "sg:address":"5640 Gravois Ave",
    "sg:city":"St Louis",
    "sg:classifiers":[
        {
            "category":"Wholesale",
            "subcategory":"Machinery & Supplies",
            "type":"Manufacturing & Wholesale Goods"
        }
    ],
    "sg:phone":"+1 314 351 1751",
    "sg:postcode":"63116",
    "sg:province":"MO",
    "sg:tags":[
        "machine",
        "equipment",
        "commercial",
        "butcher"
    ],
    "sg:website":"www.hessmm.com",
    "wof:name":"Hess Meat Machines Inc",
    "wof:placetype":"venue"
},
  "geometry": {"coordinates":[-90.273143,38.577511],"type":"Point"}
}