{
  "type": "Feature",
  "properties": {
    "iso:country":"US",
    "sg:address":"2186 Hillsgate Ct",
    "sg:city":"Saint Louis",
    "sg:classifiers":[
        {
            "category":"Shopping",
            "subcategory":"Computers & Home Electronics",
            "type":"Retail Goods"
        }
    ],
    "sg:phone":"+1 314 878 7223",
    "sg:postcode":"63146",
    "sg:province":"MO",
    "wof:name":"S L K Computer Service",
    "wof:placetype":"venue"
},
  "geometry": {"coordinates":[-90.47478599999999,38.703128],"type":"Point"}
}