{
  "type": "Feature",
  "properties": {
    "iso:country":"US",
    "sg:address":"441 Sweetbriar Dr",
    "sg:city":"Marshfield",
    "sg:classifiers":[
        {
            "category":"Building & Trades",
            "subcategory":"Plumbing",
            "type":"Services"
        }
    ],
    "sg:phone":"+1 417 859 4815",
    "sg:postcode":"65706",
    "sg:province":"MO",
    "sg:tags":[
        "plumbing",
        "contractor"
    ],
    "wof:name":"Baker Plumbing",
    "wof:placetype":"venue"
},
  "geometry": {"coordinates":[-92.868058,37.345214],"type":"Point"}
}