{
  "type": "Feature",
  "properties": {
    "iso:country":"US",
    "sg:address":"124 Kroeck Ct",
    "sg:city":"Arnold",
    "sg:classifiers":[
        {
            "category":"Building & Trades",
            "subcategory":"Construction",
            "type":"Services"
        }
    ],
    "sg:phone":"+1 636 464 0700",
    "sg:postcode":"63010",
    "sg:province":"MO",
    "sg:tags":[
        "wallcoverings-installation",
        "wallpaper",
        "painting",
        "contractor"
    ],
    "wof:name":"Painting Solutions",
    "wof:placetype":"venue"
},
  "geometry": {"coordinates":[-90.390375,38.408217],"type":"Point"}
}