{
  "type": "Feature",
  "properties": {
    "iso:country":"US",
    "sg:address":"10545 Liv 525",
    "sg:city":"Chillicothe",
    "sg:classifiers":[
        {
            "category":"Farming",
            "subcategory":"Livestock Farm",
            "type":"Manufacturing & Wholesale Goods"
        }
    ],
    "sg:phone":"+1 660 646 2266",
    "sg:postcode":"64601",
    "sg:province":"MO",
    "sg:tags":[
        "wheat",
        "beef",
        "cash",
        "grain",
        "soybean",
        "cattle",
        "feedlot"
    ],
    "wof:name":"Morris Ora",
    "wof:placetype":"venue"
},
  "geometry": {"coordinates":[-93.648059,39.820474],"type":"Point"}
}