{
  "type": "Feature",
  "properties": {
    "iso:country":"US",
    "sg:address":"1316 Old 63 S",
    "sg:city":"Columbia",
    "sg:classifiers":[
        {
            "category":"Real Estate",
            "subcategory":"Real Estate Services",
            "type":"Services"
        },
        {
            "category":"Banks & Credit Unions",
            "subcategory":"Financial Services",
            "type":"Services"
        }
    ],
    "sg:phone":"+1 573 449 5910",
    "sg:postcode":"65201",
    "sg:province":"MO",
    "sg:tags":[
        "financing",
        "processing",
        "loan"
    ],
    "sg:website":"http://myfcsfinancial.com",
    "wof:name":"F C S Financial",
    "wof:placetype":"venue"
},
  "geometry": {"coordinates":[-92.31080300000001,38.932851],"type":"Point"}
}