{
  "type": "Feature",
  "properties": {
    "addr:full":"104 N 4th St Moberly MO 65270",
    "addr:housenumber":"104",
    "addr:postcode":"65270",
    "addr:street":"N 4Th St",
    "iso:country":"US",
    "sg:address":"104 N 4th St",
    "sg:city":"Moberly",
    "sg:classifiers":[
        {
            "category":"Social Services",
            "type":"Services"
        }
    ],
    "sg:phone":"+1 660 263 9298",
    "sg:postcode":"65270",
    "sg:province":"MO",
    "sg:tags":[
        "organization",
        "welfare"
    ],
    "wof:name":"Salvation Army Thrift Store",
    "wof:placetype":"venue"
},
  "geometry": {"coordinates":[-92.440224,39.419697],"type":"Point"}
}