{
  "type": "Feature",
  "properties": {
    "addr:full":"511 N Ridgeview Dr Warrensburg MO 64093",
    "addr:housenumber":"511",
    "addr:postcode":"64093",
    "addr:street":"N Ridgeview Dr",
    "iso:country":"US",
    "sg:address":"511 N Ridgeview Dr",
    "sg:city":"Warrensburg",
    "sg:classifiers":[
        {
            "category":"Government",
            "subcategory":"Office",
            "type":"Public Place"
        }
    ],
    "sg:phone":"+1 660 747 8879",
    "sg:postcode":"64093",
    "sg:province":"MO",
    "sg:tags":[
        "security",
        "administration",
        "social"
    ],
    "wof:name":"Social Security Administration",
    "wof:placetype":"venue"
},
  "geometry": {"coordinates":[-93.71029299999999,38.769529],"type":"Point"}
}