{
  "type": "Feature",
  "properties": {
    "iso:country":"US",
    "sg:address":"1018 Roseberry Ave",
    "sg:city":"Burlington Junction",
    "sg:phone":"+1 660 725 4634",
    "sg:postcode":"64428",
    "sg:province":"MO",
    "sg:tags":[
        "farm",
        "corn",
        "soybean"
    ],
    "wof:name":"Robert Hackett",
    "wof:placetype":"venue"
},
  "geometry": {"coordinates":[-95.055379,40.441876],"type":"Point"}
}