{
  "type": "Feature",
  "properties": {
    "iso:country":"US",
    "sg:address":"1159 Martin Manor Pl",
    "sg:city":"Florissant",
    "sg:classifiers":[
        {
            "category":"Retail",
            "subcategory":"Repair Shop",
            "type":"Services"
        }
    ],
    "sg:phone":"+1 314 921 7668",
    "sg:postcode":"63031",
    "sg:province":"MO",
    "wof:name":"Sercomp International LLC",
    "wof:placetype":"venue"
},
  "geometry": {"coordinates":[-90.376976,38.79582],"type":"Point"}
}