{
  "type": "Feature",
  "properties": {
    "iso:country":"US",
    "sg:address":"10826 Hallwood Dr",
    "sg:city":"Saint Louis",
    "sg:classifiers":[
        {
            "category":"Building & Trades",
            "subcategory":"Landscaping Services",
            "type":"Services"
        }
    ],
    "sg:phone":"+1 314 869 3919",
    "sg:postcode":"63136",
    "sg:province":"MO",
    "wof:name":"Batteast Son Lawn Service",
    "wof:placetype":"venue"
},
  "geometry": {"coordinates":[-90.251403,38.768248],"type":"Point"}
}