{
  "type": "Feature",
  "properties": {
    "iso:country":"US",
    "sg:address":"10 N Industrial Dr",
    "sg:city":"Monett",
    "sg:classifiers":[
        {
            "category":"Shopping",
            "subcategory":"Party Supplies",
            "type":"Retail Goods"
        }
    ],
    "sg:phone":"+1 800 798 0119",
    "sg:postcode":"65708",
    "sg:province":"MO",
    "sg:tags":[
        "tents-rental"
    ],
    "sg:website":"http://www.weisertent.com",
    "wof:name":"Weiser Tent Service",
    "wof:placetype":"venue"
},
  "geometry": {"coordinates":[-93.909484,36.915489],"type":"Point"}
}