{
  "type": "Feature",
  "properties": {
    "iso:country":"US",
    "sg:address":"101 Cresap St",
    "sg:city":"Sikeston",
    "sg:classifiers":[
        {
            "category":"Real Estate",
            "subcategory":"Real Estate Services",
            "type":"Services"
        },
        {
            "category":"Real Estate",
            "subcategory":"Real Estate Operator",
            "type":"Services"
        }
    ],
    "sg:phone":"+1 573 471 6021",
    "sg:postcode":"63801",
    "sg:province":"MO",
    "sg:tags":[
        "vacancy",
        "apartment",
        "rental",
        "listing"
    ],
    "wof:name":"Wendell Apartments",
    "wof:placetype":"venue"
},
  "geometry": {"coordinates":[-89.591347,36.879238],"type":"Point"}
}