{
  "type": "Feature",
  "properties": {
    "iso:country":"US",
    "sg:address":"114 W 3rd St",
    "sg:city":"Lamar",
    "sg:classifiers":[
        {
            "category":"Banks & Credit Unions",
            "subcategory":"Investment Brokerage",
            "type":"Services"
        }
    ],
    "sg:phone":"+1 417 358 1250",
    "sg:postcode":"64759",
    "sg:province":"MO",
    "sg:tags":[
        "consultant",
        "planning",
        "financial"
    ],
    "wof:name":"Dow Financial Svc Inc",
    "wof:placetype":"venue"
},
  "geometry": {"coordinates":[-94.277018,37.504189],"type":"Point"}
}