{
  "type": "Feature",
  "properties": {
    "iso:country":"US",
    "sg:address":"402 N Woodbine Rd",
    "sg:city":"St Joseph",
    "sg:classifiers":[
        {
            "category":"Retail",
            "subcategory":"Car Wash",
            "type":"Services"
        }
    ],
    "sg:phone":"+1 816 232 3666",
    "sg:postcode":"64506",
    "sg:province":"MO",
    "sg:tags":[
        "automobile",
        "detail",
        "clean"
    ],
    "wof:name":"Posh Cars Plus Detail Ctr",
    "wof:placetype":"venue"
},
  "geometry": {"coordinates":[-94.796758,39.770318],"type":"Point"}
}