{
  "type": "Feature",
  "properties": {
    "iso:country":"US",
    "sg:address":"133 State St",
    "sg:city":"Doniphan",
    "sg:classifiers":[
        {
            "category":"Banks & Credit Unions",
            "subcategory":"Bank",
            "type":"Services"
        }
    ],
    "sg:phone":"+1 573 996 2228",
    "sg:postcode":"63935",
    "sg:province":"MO",
    "sg:tags":[
        "depository",
        "banking"
    ],
    "wof:name":"Redi-Cash",
    "wof:placetype":"venue"
},
  "geometry": {"coordinates":[-90.82573499999999,36.618152],"type":"Point"}
}