{
  "type": "Feature",
  "properties": {
    "iso:country":"US",
    "sg:address":"300 W 3rd St",
    "sg:city":"Caruthersville",
    "sg:classifiers":[
        {
            "category":"Autos & Motor Vehicles",
            "subcategory":"Automobile Sales",
            "type":"Retail Goods"
        }
    ],
    "sg:phone":"+1 573 333 2828",
    "sg:postcode":"63830",
    "sg:province":"MO",
    "sg:tags":[
        "passenger",
        "leasing",
        "truck",
        "car",
        "re"
    ],
    "wof:name":"Bob Churchill Motors Inc",
    "wof:placetype":"venue"
},
  "geometry": {"coordinates":[-89.657721,36.194328],"type":"Point"}
}