{
  "type": "Feature",
  "properties": {
    "iso:country":"US",
    "sg:address":"6000 W Florissant Ave",
    "sg:city":"Saint Louis",
    "sg:classifiers":[
        {
            "category":"Building & Trades",
            "subcategory":"Construction",
            "type":"Services"
        }
    ],
    "sg:phone":"+1 314 382 9000",
    "sg:postcode":"63136",
    "sg:province":"MO",
    "sg:tags":[
        "contractor"
    ],
    "wof:name":"Riverview West Florissant Housing Corporation",
    "wof:placetype":"venue"
},
  "geometry": {"coordinates":[-90.25129699999999,38.708801],"type":"Point"}
}