{
  "type": "Feature",
  "properties": {
    "iso:country":"US",
    "sg:address":"10 W Nifong Blvd",
    "sg:city":"Columbia",
    "sg:classifiers":[
        {
            "category":"Shopping",
            "subcategory":"Florist",
            "type":"Retail Goods"
        }
    ],
    "sg:phone":"+1 573 442 2864",
    "sg:postcode":"65203",
    "sg:province":"MO",
    "wof:name":"Columbia Flowers",
    "wof:placetype":"venue"
},
  "geometry": {"coordinates":[-92.33832700000001,38.909165],"type":"Point"}
}