{
  "type": "Feature",
  "properties": {
    "iso:country":"US",
    "sg:address":"1201 Clinton St",
    "sg:city":"Golden City",
    "sg:classifiers":[
        {
            "category":"Personal",
            "subcategory":"Beauty Salon",
            "type":"Services"
        }
    ],
    "sg:phone":"+1 417 537 8723",
    "sg:postcode":"64748",
    "sg:province":"MO",
    "wof:name":"Magic Touch",
    "wof:placetype":"venue"
},
  "geometry": {"coordinates":[-94.091245,37.388147],"type":"Point"}
}