{
  "type": "Feature",
  "properties": {
    "iso:country":"US",
    "sg:address":"6164 State Hwy K",
    "sg:city":"Troy",
    "sg:classifiers":[
        {
            "category":"Organizations",
            "subcategory":"Religious Organization",
            "type":"Services"
        }
    ],
    "sg:phone":"+1 573 384 5953",
    "sg:postcode":"63379",
    "sg:province":"MO",
    "sg:tags":[
        "church"
    ],
    "wof:name":"Birscoe Holiness Church",
    "wof:placetype":"venue"
},
  "geometry": {"coordinates":[-90.982827,39.084256],"type":"Point"}
}