{
  "type": "Feature",
  "properties": {
    "iso:country":"US",
    "sg:address":"103 W Lockwood Ave",
    "sg:city":"Saint Louis",
    "sg:classifiers":[
        {
            "category":"Real Estate",
            "subcategory":"Architect",
            "type":"Services"
        },
        {
            "category":"Manufacturing",
            "subcategory":"Metals",
            "type":"Manufacturing & Wholesale Goods"
        }
    ],
    "sg:phone":"+1 314 918 1600",
    "sg:postcode":"63119",
    "sg:province":"MO",
    "sg:tags":[
        "metalwork",
        "architectural",
        "mfg"
    ],
    "wof:name":"Webster Design",
    "wof:placetype":"venue"
},
  "geometry": {"coordinates":[-90.36087499999999,38.593255],"type":"Point"}
}