{
  "type": "Feature",
  "properties": {
    "iso:country":"US",
    "sg:address":"936 Kiefer Hill Dr",
    "sg:city":"Ballwin",
    "sg:classifiers":[
        {
            "category":"Professional",
            "subcategory":"Research",
            "type":"Services"
        }
    ],
    "sg:phone":"+1 636 675 5243",
    "sg:postcode":"63021",
    "sg:province":"MO",
    "sg:tags":[
        "chemical"
    ],
    "wof:name":"Innova Specialties Inc",
    "wof:placetype":"venue"
},
  "geometry": {"coordinates":[-90.57087,38.565821],"type":"Point"}
}