{
  "type": "Feature",
  "properties": {
    "iso:country":"US",
    "sg:address":"2500 Raymond Dr",
    "sg:city":"St Charles",
    "sg:classifiers":[
        {
            "category":"Organizations",
            "subcategory":"Community Association",
            "type":"Services"
        }
    ],
    "sg:phone":"+1 636 947 7666",
    "sg:postcode":"63301",
    "sg:province":"MO",
    "sg:tags":[
        "military"
    ],
    "wof:name":"American Legion",
    "wof:placetype":"venue"
},
  "geometry": {"coordinates":[-90.51421000000001,38.786881],"type":"Point"}
}