{
  "type": "Feature",
  "properties": {
    "iso:country":"US",
    "sg:address":"23494 Co Rd 239",
    "sg:city":"Union Star",
    "sg:classifiers":[
        {
            "category":"Farming",
            "subcategory":"Farm",
            "type":"Manufacturing & Wholesale Goods"
        }
    ],
    "sg:phone":"+1 816 593 2236",
    "sg:postcode":"64494",
    "sg:province":"MO",
    "sg:tags":[
        "heavy",
        "construction",
        "crop",
        "general"
    ],
    "wof:name":"Schnitker Trenching and Tile",
    "wof:placetype":"venue"
},
  "geometry": {"coordinates":[-94.61215199999999,39.995218],"type":"Point"}
}