{
  "type": "Feature",
  "properties": {
    "iso:country":"US",
    "sg:address":"9157 Reavis Barracks Rd",
    "sg:city":"St Louis",
    "sg:classifiers":[
        {
            "category":"Insurance",
            "subcategory":"Insurance Agent",
            "type":"Services"
        }
    ],
    "sg:phone":"+1 314 638 9550",
    "sg:postcode":"63123",
    "sg:province":"MO",
    "wof:name":"Gipson Insurance",
    "wof:placetype":"venue"
},
  "geometry": {"coordinates":[-90.316287,38.536133],"type":"Point"}
}