{
  "type": "Feature",
  "properties": {
    "iso:country":"US",
    "sg:address":"804 Horan Dr",
    "sg:city":"Fenton",
    "sg:classifiers":[
        {
            "category":"Manufacturing",
            "subcategory":"Printing",
            "type":"Manufacturing & Wholesale Goods"
        }
    ],
    "sg:phone":"+1 636 343 2844",
    "sg:postcode":"63026",
    "sg:province":"MO",
    "sg:tags":[
        "commercial"
    ],
    "wof:name":"Klio Eterna",
    "wof:placetype":"venue"
},
  "geometry": {"coordinates":[-90.45761,38.537995],"type":"Point"}
}