{
  "type": "Feature",
  "properties": {
    "iso:country":"US",
    "sg:address":"1600 Genessee St",
    "sg:city":"Kansas City",
    "sg:phone":"+1 816 918 0511",
    "sg:postcode":"64102",
    "sg:province":"MO",
    "wof:name":"Leason Vending LLC",
    "wof:placetype":"venue"
},
  "geometry": {"coordinates":[-94.605063,39.093409],"type":"Point"}
}