{
  "type": "Feature",
  "properties": {
    "iso:country":"US",
    "sg:address":"2400 Frederick Ave",
    "sg:city":"St Joseph",
    "sg:classifiers":[
        {
            "category":"Wholesale",
            "subcategory":"Farm Supplies",
            "type":"Manufacturing & Wholesale Goods"
        }
    ],
    "sg:phone":"+1 816 233 5109",
    "sg:postcode":"64506",
    "sg:province":"MO",
    "sg:tags":[
        "grain"
    ],
    "wof:name":"Gumbert Exchange",
    "wof:placetype":"venue"
},
  "geometry": {"coordinates":[-94.830725,39.776782],"type":"Point"}
}