{
  "type": "Feature",
  "properties": {
    "iso:country":"US",
    "sg:address":"519 Locust St",
    "sg:city":"Chillicothe",
    "sg:classifiers":[
        {
            "category":"Shopping",
            "type":"Retail Goods"
        }
    ],
    "sg:phone":"+1 660 646 5300",
    "sg:postcode":"64601",
    "sg:province":"MO",
    "sg:tags":[
        "health",
        "merchandise"
    ],
    "wof:name":"Horizon Hearing Services",
    "wof:placetype":"venue"
},
  "geometry": {"coordinates":[-93.552419,39.793233],"type":"Point"}
}