{
  "type": "Feature",
  "properties": {
    "iso:country":"US",
    "sg:address":"28905 E 117th St",
    "sg:city":"Lees Summit",
    "sg:classifiers":[
        {
            "category":"Building & Trades",
            "subcategory":"Construction",
            "type":"Services"
        }
    ],
    "sg:phone":"+1 816 228 9670",
    "sg:postcode":"64086",
    "sg:province":"MO",
    "sg:tags":[
        "contractor"
    ],
    "wof:name":"Rainbow Water Proofing",
    "wof:placetype":"venue"
},
  "geometry": {"coordinates":[-94.2479,38.903998],"type":"Point"}
}