{
  "type": "Feature",
  "properties": {
    "iso:country":"US",
    "sg:address":"1517 E 7th St",
    "sg:city":"Sedalia",
    "sg:classifiers":[
        {
            "category":"Building & Trades",
            "subcategory":"Construction",
            "type":"Services"
        }
    ],
    "sg:phone":"+1 660 829 4468",
    "sg:postcode":"65301",
    "sg:province":"MO",
    "sg:tags":[
        "tile",
        "dealer"
    ],
    "wof:name":"Ronspiez Tile Co",
    "wof:placetype":"venue"
},
  "geometry": {"coordinates":[-93.209695,38.704499],"type":"Point"}
}