{
  "type": "Feature",
  "properties": {
    "iso:country":"US",
    "sg:address":"2104 W Chesterfield Blvd",
    "sg:city":"Springfield",
    "sg:classifiers":[
        {
            "category":"Health Services",
            "subcategory":"Doctor",
            "type":"Services"
        }
    ],
    "sg:phone":"+1 417 889 2880",
    "sg:postcode":"65807",
    "sg:province":"MO",
    "wof:name":"Buzbee Dental Clinic PC",
    "wof:placetype":"venue"
},
  "geometry": {"coordinates":[-93.321095,37.145917],"type":"Point"}
}