{
  "type": "Feature",
  "properties": {
    "iso:country":"US",
    "sg:address":"700 Plaza Dr",
    "sg:city":"Fredericktown",
    "sg:classifiers":[
        {
            "category":"Retail",
            "subcategory":"Funeral Services",
            "type":"Services"
        }
    ],
    "sg:phone":"+1 573 783 8336",
    "sg:postcode":"63645",
    "sg:province":"MO",
    "sg:tags":[
        "merchandise"
    ],
    "wof:name":"Follis-Sonderman Funeral Home",
    "wof:placetype":"venue"
},
  "geometry": {"coordinates":[-90.30462199999999,37.560297],"type":"Point"}
}