{
  "type": "Feature",
  "properties": {
    "iso:country":"US",
    "sg:address":"5684 US Hwy 54",
    "sg:city":"Osage Beach",
    "sg:classifiers":[
        {
            "category":"Autos & Motor Vehicles",
            "subcategory":"Automobile Sales",
            "type":"Retail Goods"
        }
    ],
    "sg:phone":"+1 573 348 1920",
    "sg:postcode":"65065",
    "sg:province":"MO",
    "sg:tags":[
        "car",
        "dealer"
    ],
    "wof:name":"Lakeway Motors",
    "wof:placetype":"venue"
},
  "geometry": {"coordinates":[-92.66703699999999,38.126653],"type":"Point"}
}