{
  "type": "Feature",
  "properties": {
    "iso:country":"US",
    "sg:address":"378 S Hwy 185",
    "sg:city":"Sullivan",
    "sg:classifiers":[
        {
            "category":"Organizations",
            "subcategory":"Community Association",
            "type":"Services"
        }
    ],
    "sg:phone":"+1 573 468 6321",
    "sg:postcode":"63080",
    "sg:province":"MO",
    "sg:tags":[
        "military"
    ],
    "wof:name":"Veterans Of Foreign Wars",
    "wof:placetype":"venue"
},
  "geometry": {"coordinates":[-91.149164,38.222739],"type":"Point"}
}