{
  "type": "Feature",
  "properties": {
    "iso:country":"US",
    "sg:address":"1118 Hampton Ave",
    "sg:city":"St Louis",
    "sg:classifiers":[
        {
            "category":"Organizations",
            "subcategory":"Professional Association",
            "type":"Services"
        }
    ],
    "sg:phone":"+1 314 645 5505",
    "sg:postcode":"63139",
    "sg:province":"MO",
    "sg:website":"www.lungusa.org",
    "wof:name":"American Lung Assn-Missouri",
    "wof:placetype":"venue"
},
  "geometry": {"coordinates":[-90.287126,38.629143],"type":"Point"}
}