{
  "type": "Feature",
  "properties": {
    "iso:country":"US",
    "sg:address":"18767 Terrier Rd",
    "sg:city":"Stella",
    "sg:classifiers":[
        {
            "category":"Farming",
            "subcategory":"Poultry Farm",
            "type":"Manufacturing & Wholesale Goods"
        }
    ],
    "sg:phone":"+1 417 638 5473",
    "sg:postcode":"64867",
    "sg:province":"MO",
    "sg:tags":[
        "egg"
    ],
    "wof:name":"Lou Mettlach",
    "wof:placetype":"venue"
},
  "geometry": {"coordinates":[-94.16414,36.79585],"type":"Point"}
}