{
  "type": "Feature",
  "properties": {
    "iso:country":"US",
    "sg:address":"107 E Hayward St",
    "sg:city":"Meadville",
    "sg:classifiers":[
        {
            "category":"Retail",
            "subcategory":"Funeral Services",
            "type":"Services"
        }
    ],
    "sg:phone":"+1 660 938 4313",
    "sg:postcode":"64659",
    "sg:province":"MO",
    "sg:tags":[
        "director"
    ],
    "wof:name":"Wright Baker Hill Funeral Home",
    "wof:placetype":"venue"
},
  "geometry": {"coordinates":[-93.301997,39.786267],"type":"Point"}
}