{
  "type": "Feature",
  "properties": {
    "iso:country":"US",
    "sg:address":"206 N Filmore St",
    "sg:city":"Cuba",
    "sg:classifiers":[
        {
            "category":"Professional",
            "subcategory":"Accounting & Tax Preparation",
            "type":"Services"
        }
    ],
    "sg:phone":"+1 573 885 2318",
    "sg:postcode":"65453",
    "sg:province":"MO",
    "wof:name":"Charles A Kolb CPA",
    "wof:placetype":"venue"
},
  "geometry": {"coordinates":[-91.406204,38.064067],"type":"Point"}
}