{
  "type": "Feature",
  "properties": {
    "iso:country":"US",
    "sg:address":"1735 S River Rd",
    "sg:city":"Saint Charles",
    "sg:classifiers":[
        {
            "category":"Manufacturing",
            "subcategory":"Tools & Machinery",
            "type":"Manufacturing & Wholesale Goods"
        }
    ],
    "sg:phone":"+1 636 949 9101",
    "sg:postcode":"63303",
    "sg:province":"MO",
    "sg:tags":[
        "manufacture",
        "control",
        "design",
        "electronic"
    ],
    "wof:name":"E2 E Squared",
    "wof:placetype":"venue"
},
  "geometry": {"coordinates":[-90.49637,38.7596],"type":"Point"}
}