{
  "type": "Feature",
  "properties": {
    "iso:country":"US",
    "sg:address":"627 N 25th St",
    "sg:city":"St Joseph",
    "sg:classifiers":[
        {
            "category":"Real Estate",
            "subcategory":"Real Estate Operator",
            "type":"Services"
        }
    ],
    "sg:phone":"+1 816 233 2248",
    "sg:postcode":"64506",
    "sg:province":"MO",
    "sg:tags":[
        "apartment"
    ],
    "wof:name":"Century Tower Apartments",
    "wof:placetype":"venue"
},
  "geometry": {"coordinates":[-94.830253,39.772503],"type":"Point"}
}