{
  "type": "Feature",
  "properties": {
    "iso:country":"US",
    "sg:address":"514 Earth City Plz",
    "sg:city":"Earth City",
    "sg:classifiers":[
        {
            "category":"Restaurant",
            "type":"Food & Drink"
        }
    ],
    "sg:phone":"+1 314 209 0055",
    "sg:postcode":"63044",
    "sg:province":"MO",
    "wof:name":"Ejg Enterprises Inc",
    "wof:placetype":"venue"
},
  "geometry": {"coordinates":[-90.45856999999999,38.765927],"type":"Point"}
}