{
  "type": "Feature",
  "properties": {
    "iso:country":"US",
    "sg:address":"26522 Cordes Rd",
    "sg:city":"Sedalia",
    "sg:classifiers":[
        {
            "category":"Farming",
            "subcategory":"Livestock Farm",
            "type":"Manufacturing & Wholesale Goods"
        }
    ],
    "sg:phone":"+1 660 668 4930",
    "sg:postcode":"65301",
    "sg:province":"MO",
    "sg:tags":[
        "animal",
        "general"
    ],
    "wof:name":"Johnson Farms",
    "wof:placetype":"venue"
},
  "geometry": {"coordinates":[-93.20878,38.556217],"type":"Point"}
}