{
  "type": "Feature",
  "properties": {
    "iso:country":"US",
    "sg:address":"1701 State Hwy 291",
    "sg:city":"Harrisonville",
    "sg:classifiers":[
        {
            "category":"Food & Beverages",
            "subcategory":"Groceries & Convenience Stores",
            "type":"Retail Goods"
        }
    ],
    "sg:phone":"+1 816 887 2822",
    "sg:postcode":"64701",
    "sg:province":"MO",
    "wof:name":"Sinclair",
    "wof:placetype":"venue"
},
  "geometry": {"coordinates":[-94.366277,38.669439],"type":"Point"}
}