{
  "type": "Feature",
  "properties": {
    "iso:country":"US",
    "sg:address":"1608 S el Chaparral Ave",
    "sg:city":"Columbia",
    "sg:classifiers":[
        {
            "category":"Shopping",
            "subcategory":"Gifts & Souvenirs",
            "type":"Retail Goods"
        }
    ],
    "sg:phone":"+1 573 874 5698",
    "sg:postcode":"65201",
    "sg:province":"MO",
    "wof:name":"Leland Stepney & Card",
    "wof:placetype":"venue"
},
  "geometry": {"coordinates":[-92.27748800000001,38.931855],"type":"Point"}
}