{
  "type": "Feature",
  "properties": {
    "iso:country":"US",
    "sg:address":"2438 N Bolivar Rd",
    "sg:city":"Springfield",
    "sg:classifiers":[
        {
            "category":"Organizations",
            "subcategory":"Non-profit Organization",
            "type":"Services"
        }
    ],
    "sg:phone":"+1 417 864 0086",
    "sg:postcode":"65803",
    "sg:province":"MO",
    "sg:tags":[
        "charitable",
        "institution"
    ],
    "wof:name":"Goodwill Industries",
    "wof:placetype":"venue"
},
  "geometry": {"coordinates":[-93.310834,37.243547],"type":"Point"}
}