{
  "type": "Feature",
  "properties": {
    "iso:country":"US",
    "sg:address":"207 Doerner St",
    "sg:city":"Steele",
    "sg:classifiers":[
        {
            "category":"Retail",
            "subcategory":"Auto Repair",
            "type":"Services"
        }
    ],
    "sg:phone":"+1 573 695 3796",
    "sg:postcode":"63877",
    "sg:province":"MO",
    "sg:tags":[
        "body",
        "automobile",
        "painting"
    ],
    "wof:name":"David House",
    "wof:placetype":"venue"
},
  "geometry": {"coordinates":[-89.83117300000001,36.086413],"type":"Point"}
}