{
  "type": "Feature",
  "properties": {
    "iso:country":"US",
    "sg:address":"6900 N Broadway",
    "sg:city":"St Louis",
    "sg:classifiers":[
        {
            "category":"Manufacturing",
            "subcategory":"Metals",
            "type":"Manufacturing & Wholesale Goods"
        }
    ],
    "sg:phone":"+1 314 389 7500",
    "sg:postcode":"63147",
    "sg:province":"MO",
    "sg:tags":[
        "nut",
        "bolt"
    ],
    "sg:website":"www.stlouisscrewbolt.com",
    "wof:name":"St Louis Screw & Bolt Co",
    "wof:placetype":"venue"
},
  "geometry": {"coordinates":[-90.22595699999999,38.695707],"type":"Point"}
}