{
  "type": "Feature",
  "properties": {
    "iso:country":"US",
    "sg:address":"2496 Starling Airport Rd",
    "sg:city":"Arnold",
    "sg:classifiers":[
        {
            "category":"Shopping",
            "subcategory":"Crafts & Fabrics",
            "type":"Retail Goods"
        }
    ],
    "sg:phone":"+1 636 287 9640",
    "sg:postcode":"63010",
    "sg:province":"MO",
    "sg:tags":[
        "embroidery"
    ],
    "wof:name":"Shoppers Rule Inc",
    "wof:placetype":"venue"
},
  "geometry": {"coordinates":[-90.351839,38.443059],"type":"Point"}
}