{
  "type": "Feature",
  "properties": {
    "iso:country":"US",
    "sg:address":"18598 Brady Ln",
    "sg:city":"Boonville",
    "sg:classifiers":[
        {
            "category":"Building & Trades",
            "subcategory":"Construction",
            "type":"Services"
        }
    ],
    "sg:phone":"+1 660 882 8229",
    "sg:postcode":"65233",
    "sg:province":"MO",
    "sg:tags":[
        "nonresidential"
    ],
    "wof:name":"Brady Buildings & Construction",
    "wof:placetype":"venue"
},
  "geometry": {"coordinates":[-92.60485199999999,38.951485],"type":"Point"}
}