{
  "type": "Feature",
  "properties": {
    "iso:country":"US",
    "sg:address":"523 Green St",
    "sg:city":"St Joseph",
    "sg:classifiers":[
        {
            "category":"Building & Trades",
            "subcategory":"Landscaping Services",
            "type":"Services"
        }
    ],
    "sg:phone":"+1 816 676 1878",
    "sg:postcode":"64505",
    "sg:province":"MO",
    "sg:tags":[
        "tree"
    ],
    "wof:name":"Tree Technicians",
    "wof:placetype":"venue"
},
  "geometry": {"coordinates":[-94.85248300000001,39.793312],"type":"Point"}
}