{
  "type": "Feature",
  "properties": {
    "iso:country":"US",
    "sg:address":"577 Old Rte 66",
    "sg:city":"St Robert",
    "sg:classifiers":[
        {
            "category":"Retail",
            "subcategory":"Auto Rental",
            "type":"Services"
        }
    ],
    "sg:phone":"+1 573 336 4317",
    "sg:postcode":"65584",
    "sg:province":"MO",
    "sg:tags":[
        "renting",
        "truck",
        "leasing"
    ],
    "wof:name":"U-Haul Co",
    "wof:placetype":"venue"
},
  "geometry": {"coordinates":[-92.162434,37.822506],"type":"Point"}
}