{
  "type": "Feature",
  "properties": {
    "iso:country":"US",
    "sg:address":"906 N Miami Ave",
    "sg:city":"Marshall",
    "sg:classifiers":[
        {
            "category":"Building & Trades",
            "subcategory":"Construction",
            "type":"Services"
        }
    ],
    "sg:phone":"+1 660 886 6854",
    "sg:postcode":"65340",
    "sg:province":"MO",
    "sg:tags":[
        "product",
        "asphalt"
    ],
    "wof:name":"Marshall Paving Co Inc",
    "wof:placetype":"venue"
},
  "geometry": {"coordinates":[-93.208219,39.131824],"type":"Point"}
}