{
  "type": "Feature",
  "properties": {
    "iso:country":"US",
    "sg:address":"2905 M 291 Frontage Rd",
    "sg:city":"Independence",
    "sg:classifiers":[
        {
            "category":"Building & Trades",
            "subcategory":"Plumbing",
            "type":"Services"
        }
    ],
    "sg:phone":"+1 816 373 6370",
    "sg:postcode":"64057",
    "sg:province":"MO",
    "sg:tags":[
        "sheet",
        "metal",
        "heating",
        "air",
        "conditioning",
        "contractor"
    ],
    "wof:name":"McDaniel Furnace & Sheet Metal",
    "wof:placetype":"venue"
},
  "geometry": {"coordinates":[-94.37477800000001,39.063156],"type":"Point"}
}