{
  "type": "Feature",
  "properties": {
    "addr:full":"1756 1st St Kennett MO 63857",
    "addr:housenumber":"1756",
    "addr:postcode":"63857",
    "addr:street":"1St St",
    "iso:country":"US",
    "sg:address":"1756 1st St",
    "sg:city":"Kennett",
    "sg:classifiers":[
        {
            "category":"Shopping",
            "subcategory":"Jewelry",
            "type":"Retail Goods"
        }
    ],
    "sg:phone":"+1 573 888 2711",
    "sg:postcode":"63857",
    "sg:province":"MO",
    "wof:name":"Friedmans Jewelers",
    "wof:placetype":"venue"
},
  "geometry": {"coordinates":[-90.037254,36.236731],"type":"Point"}
}