{
  "type": "Feature",
  "properties": {
    "iso:country":"US",
    "sg:address":"8495 Mid County Industrl Dr",
    "sg:city":"Saint Louis",
    "sg:classifiers":[
        {
            "category":"Freight",
            "type":"Transportation"
        }
    ],
    "sg:phone":"+1 314 426 7300",
    "sg:postcode":"63114",
    "sg:province":"MO",
    "sg:tags":[
        "company",
        "moving"
    ],
    "wof:name":"Office Moving Incorporated",
    "wof:placetype":"venue"
},
  "geometry": {"coordinates":[-90.341723,38.691954],"type":"Point"}
}