{
  "type": "Feature",
  "properties": {
    "iso:country":"US",
    "sg:address":"519 Cedar Ave",
    "sg:city":"Cabool",
    "sg:classifiers":[
        {
            "category":"Professional",
            "subcategory":"Business Services",
            "type":"Services"
        },
        {
            "category":"Government",
            "subcategory":"Post Office",
            "type":"Public Place"
        }
    ],
    "sg:phone":"+1 800 275 8777",
    "sg:postcode":"65689",
    "sg:province":"MO",
    "sg:tags":[
        "mail",
        "shipping"
    ],
    "sg:website":"http://www.usps.com",
    "wof:name":"USPS - United States Post Office - Cabool Main Office",
    "wof:placetype":"venue"
},
  "geometry": {"coordinates":[-92.100856,37.122498],"type":"Point"}
}