{
  "type": "Feature",
  "properties": {
    "iso:country":"US",
    "sg:address":"206 W Tilden St",
    "sg:city":"Humansville",
    "sg:classifiers":[
        {
            "category":"Retail",
            "subcategory":"Repair Shop",
            "type":"Services"
        }
    ],
    "sg:phone":"+1 417 754 2384",
    "sg:postcode":"65674",
    "sg:province":"MO",
    "sg:tags":[
        "plumbing",
        "drain",
        "cleaning",
        "sewer"
    ],
    "wof:name":"Garretson's Center",
    "wof:placetype":"venue"
},
  "geometry": {"coordinates":[-93.578441,37.794447],"type":"Point"}
}