{
  "type": "Feature",
  "properties": {
    "iso:country":"US",
    "sg:address":"1809 Clifford St",
    "sg:city":"Saint Joseph",
    "sg:classifiers":[
        {
            "category":"Organizations",
            "subcategory":"Membership Organization",
            "type":"Services"
        }
    ],
    "sg:phone":"+1 816 232 1998",
    "sg:postcode":"64505",
    "sg:province":"MO",
    "wof:name":"Royal Arch Masons of Miss",
    "wof:placetype":"venue"
},
  "geometry": {"coordinates":[-94.839073,39.813221],"type":"Point"}
}