{
  "type": "Feature",
  "properties": {
    "iso:country":"US",
    "sg:address":"13000 Kinsley Heights Dr",
    "sg:city":"Florissant",
    "sg:classifiers":[
        {
            "category":"Professional",
            "subcategory":"Management & Consulting",
            "type":"Services"
        }
    ],
    "sg:phone":"+1 314 495 7906",
    "sg:postcode":"63033",
    "sg:province":"MO",
    "sg:tags":[
        "consultant"
    ],
    "wof:name":"Ub2 Global Conortim",
    "wof:placetype":"venue"
},
  "geometry": {"coordinates":[-90.264488,38.803391],"type":"Point"}
}