{
  "type": "Feature",
  "properties": {
    "iso:country":"US",
    "sg:address":"6900 E 28 St",
    "sg:city":"Kansas City",
    "sg:classifiers":[
        {
            "category":"Building & Trades",
            "subcategory":"Construction",
            "type":"Services"
        }
    ],
    "sg:phone":"+1 816 795 1344",
    "sg:postcode":"64129",
    "sg:province":"MO",
    "sg:tags":[
        "house"
    ],
    "wof:name":"Four Seasons Mobile Home Svc",
    "wof:placetype":"venue"
},
  "geometry": {"coordinates":[-94.50094300000001,39.073589],"type":"Point"}
}