{
  "type": "Feature",
  "properties": {
    "iso:country":"US",
    "sg:address":"19606 S Hickory Grove Rd",
    "sg:city":"Pleasant Hill",
    "sg:classifiers":[
        {
            "category":"Building & Trades",
            "subcategory":"Construction",
            "type":"Services"
        }
    ],
    "sg:phone":"+1 816 540 5474",
    "sg:postcode":"64080",
    "sg:province":"MO",
    "sg:tags":[
        "hanging",
        "contractor"
    ],
    "wof:name":"Gross Bros Painting",
    "wof:placetype":"venue"
},
  "geometry": {"coordinates":[-94.319632,38.759457],"type":"Point"}
}