{
  "type": "Feature",
  "properties": {
    "iso:country":"US",
    "sg:address":"120 W 12 St",
    "sg:city":"Kansas City",
    "sg:classifiers":[
        {
            "category":"Banks & Credit Unions",
            "subcategory":"Bank",
            "type":"Services"
        }
    ],
    "sg:phone":"+1 816 871 2210",
    "sg:postcode":"64105",
    "sg:province":"MO",
    "wof:name":"Us Bank",
    "wof:placetype":"venue"
},
  "geometry": {"coordinates":[-94.58537699999999,39.100068],"type":"Point"}
}