{
  "type": "Feature",
  "properties": {
    "iso:country":"US",
    "sg:address":"6104 E Kneff Rd",
    "sg:city":"Imperial",
    "sg:classifiers":[
        {
            "category":"Building & Trades",
            "subcategory":"Construction",
            "type":"Services"
        }
    ],
    "sg:phone":"+1 636 942 4174",
    "sg:postcode":"63052",
    "sg:province":"MO",
    "wof:name":"Gudorp W Paving & Gen Contr",
    "wof:placetype":"venue"
},
  "geometry": {"coordinates":[-90.447213,38.373566],"type":"Point"}
}