{
  "type": "Feature",
  "properties": {
    "iso:country":"US",
    "sg:address":"130 SW 30th Ave",
    "sg:city":"Trenton",
    "sg:classifiers":[
        {
            "category":"Wholesale",
            "subcategory":"Construction Materials",
            "type":"Manufacturing & Wholesale Goods"
        }
    ],
    "sg:phone":"+1 660 359 6145",
    "sg:postcode":"64683",
    "sg:province":"MO",
    "sg:tags":[
        "sand",
        "gravel"
    ],
    "wof:name":"Trenton Sand Co",
    "wof:placetype":"venue"
},
  "geometry": {"coordinates":[-93.643367,40.043273],"type":"Point"}
}