{
  "type": "Feature",
  "properties": {
    "iso:country":"US",
    "sg:address":"1720 W Main St",
    "sg:city":"Sedalia",
    "sg:classifiers":[
        {
            "category":"Freight",
            "type":"Transportation"
        }
    ],
    "sg:phone":"+1 660 826 1600",
    "sg:postcode":"65301",
    "sg:province":"MO",
    "sg:tags":[
        "commercial",
        "storage"
    ],
    "wof:name":"ARCO LLC",
    "wof:placetype":"venue"
},
  "geometry": {"coordinates":[-93.24937799999999,38.713783],"type":"Point"}
}