{
  "type": "Feature",
  "properties": {
    "addr:full":"14636 Manchester Rd Ballwin MO 63011",
    "addr:housenumber":"14636",
    "addr:postcode":"63011",
    "addr:street":"Manchester Rd",
    "iso:country":"US",
    "sg:address":"14636 Manchester Rd",
    "sg:city":"Ballwin",
    "sg:classifiers":[
        {
            "category":"Banks & Credit Unions",
            "subcategory":"Bank",
            "type":"Services"
        }
    ],
    "sg:phone":"+1 636 227 7000",
    "sg:postcode":"63011",
    "sg:province":"MO",
    "sg:tags":[
        "depository",
        "banking"
    ],
    "wof:name":"ACE Cash Express",
    "wof:placetype":"venue"
},
  "geometry": {"coordinates":[-90.529669,38.592924],"type":"Point"}
}