{
  "type": "Feature",
  "properties": {
    "iso:country":"US",
    "sg:address":"11126 Woodale Dr",
    "sg:city":"Rolla",
    "sg:classifiers":[
        {
            "category":"Retail",
            "subcategory":"Repair Shop",
            "type":"Services"
        }
    ],
    "sg:phone":"+1 573 364 0826",
    "sg:postcode":"65401",
    "sg:province":"MO",
    "sg:tags":[
        "upholsterer"
    ],
    "wof:name":"Bill's Custom Upholstery",
    "wof:placetype":"venue"
},
  "geometry": {"coordinates":[-91.72331699999999,38.00336],"type":"Point"}
}