{
  "type": "Feature",
  "properties": {
    "iso:country":"US",
    "sg:address":"338 Jefferson Ave",
    "sg:city":"Valley Park",
    "sg:classifiers":[
        {
            "category":"Building & Trades",
            "subcategory":"Construction",
            "type":"Services"
        }
    ],
    "sg:phone":"+1 636 337 0966",
    "sg:postcode":"63088",
    "sg:province":"MO",
    "sg:tags":[
        "boring",
        "contractor"
    ],
    "wof:name":"St Louis Underground Inc",
    "wof:placetype":"venue"
},
  "geometry": {"coordinates":[-90.497382,38.559852],"type":"Point"}
}