{
  "type": "Feature",
  "properties": {
    "iso:country":"US",
    "sg:address":"5211 S Range Line Rd",
    "sg:city":"Joplin",
    "sg:classifiers":[
        {
            "category":"Shopping",
            "subcategory":"Tobacco",
            "type":"Retail Goods"
        },
        {
            "category":"Food & Beverages",
            "subcategory":"Liquor & Beverages",
            "type":"Retail Goods"
        }
    ],
    "sg:phone":"+1 417 206 4559",
    "sg:postcode":"64804",
    "sg:province":"MO",
    "sg:tags":[
        "cigarette",
        "cigar",
        "store"
    ],
    "wof:name":"Hi-Point Liquor & Smoke Shop",
    "wof:placetype":"venue"
},
  "geometry": {"coordinates":[-94.478928,37.036511],"type":"Point"}
}