{
  "type": "Feature",
  "properties": {
    "iso:country":"US",
    "sg:address":"1121 SE Scenic Dr",
    "sg:city":"Blue Springs",
    "sg:classifiers":[
        {
            "category":"Retail",
            "subcategory":"Repair Shop",
            "type":"Services"
        }
    ],
    "sg:phone":"+1 816 224 1005",
    "sg:postcode":"64014",
    "sg:province":"MO",
    "wof:name":"Westover Cleaning",
    "wof:placetype":"venue"
},
  "geometry": {"coordinates":[-94.24083,39.006242],"type":"Point"}
}