{
  "type": "Feature",
  "properties": {
    "addr:full":"310 SW Blue Pkwy Lees Summit MO 64063",
    "addr:housenumber":"310",
    "addr:postcode":"64063",
    "addr:street":"Sw Blue Pkwy",
    "iso:country":"US",
    "sg:address":"310 SW Blue Pkwy",
    "sg:city":"Lees Summit",
    "sg:classifiers":[
        {
            "category":"Shopping",
            "type":"Retail Goods"
        }
    ],
    "sg:phone":"+1 816 246 7450",
    "sg:postcode":"64063",
    "sg:province":"MO",
    "sg:tags":[
        "pet",
        "shop",
        "merchandise",
        "animal"
    ],
    "wof:name":"Pet Supermarket",
    "wof:placetype":"venue"
},
  "geometry": {"coordinates":[-94.381922,38.905113],"type":"Point"}
}