{
  "type": "Feature",
  "properties": {
    "iso:country":"US",
    "sg:address":"202 High St",
    "sg:city":"Alba",
    "sg:classifiers":[
        {
            "category":"Banks & Credit Unions",
            "subcategory":"Bank",
            "type":"Services"
        }
    ],
    "sg:phone":"+1 417 525 4218",
    "sg:postcode":"64830",
    "sg:province":"MO",
    "wof:name":"Southwest Missouri Bank",
    "wof:placetype":"venue"
},
  "geometry": {"coordinates":[-94.419482,37.238676],"type":"Point"}
}