{
  "type": "Feature",
  "properties": {
    "iso:country":"US",
    "sg:address":"5635 Locust St",
    "sg:city":"Kansas City",
    "sg:classifiers":[
        {
            "category":"Building & Trades",
            "subcategory":"Construction",
            "type":"Services"
        }
    ],
    "sg:phone":"+1 816 363 1862",
    "sg:postcode":"64110",
    "sg:province":"MO",
    "sg:tags":[
        "house"
    ],
    "wof:name":"C N N Updating",
    "wof:placetype":"venue"
},
  "geometry": {"coordinates":[-94.58197800000001,39.024473],"type":"Point"}
}