{
  "type": "Feature",
  "properties": {
    "iso:country":"US",
    "sg:address":"925 NE 231 Rd",
    "sg:city":"Clinton",
    "sg:classifiers":[
        {
            "category":"Building & Trades",
            "subcategory":"Construction",
            "type":"Services"
        }
    ],
    "sg:phone":"+1 660 885 6256",
    "sg:postcode":"64761",
    "sg:province":"MO",
    "sg:tags":[
        "general",
        "contractor"
    ],
    "wof:name":"Brian Kimzey Construction",
    "wof:placetype":"venue"
},
  "geometry": {"coordinates":[-93.71634,38.492752],"type":"Point"}
}