{
  "type": "Feature",
  "properties": {
    "iso:country":"US",
    "sg:address":"824 Union Rd",
    "sg:city":"Saint Louis",
    "sg:classifiers":[
        {
            "category":"Education",
            "subcategory":"School",
            "type":"Public Place"
        }
    ],
    "sg:phone":"+1 314 631 0991",
    "sg:postcode":"63123",
    "sg:province":"MO",
    "wof:name":"St Timothy School",
    "wof:placetype":"venue"
},
  "geometry": {"coordinates":[-90.295593,38.546549],"type":"Point"}
}