{
  "type": "Feature",
  "properties": {
    "iso:country":"US",
    "sg:address":"10262 Page Ave",
    "sg:city":"St Louis",
    "sg:classifiers":[
        {
            "category":"Recreation",
            "type":"Entertainment"
        }
    ],
    "sg:phone":"+1 314 429 4238",
    "sg:postcode":"63132",
    "sg:province":"MO",
    "sg:tags":[
        "karate",
        "judo",
        "instr"
    ],
    "wof:name":"CDT Personal & Family Train",
    "wof:placetype":"venue"
},
  "geometry": {"coordinates":[-90.386218,38.690979],"type":"Point"}
}