{
  "type": "Feature",
  "properties": {
    "iso:country":"US",
    "sg:address":"117 E Main St",
    "sg:city":"Smithville",
    "sg:classifiers":[
        {
            "category":"Shopping",
            "subcategory":"Florist",
            "type":"Retail Goods"
        }
    ],
    "sg:phone":"+1 816 532 4757",
    "sg:postcode":"64089",
    "sg:province":"MO",
    "wof:name":"Smithville Florist",
    "wof:placetype":"venue"
},
  "geometry": {"coordinates":[-94.580694,39.387128],"type":"Point"}
}