{
  "type": "Feature",
  "properties": {
    "iso:country":"US",
    "sg:address":"9911 Co Rd 371",
    "sg:city":"New Bloomfield",
    "sg:classifiers":[
        {
            "category":"Farming",
            "subcategory":"Livestock Farm",
            "type":"Manufacturing & Wholesale Goods"
        }
    ],
    "sg:phone":"+1 573 491 3494",
    "sg:postcode":"65063",
    "sg:province":"MO",
    "sg:tags":[
        "beef",
        "feedlot",
        "cattle"
    ],
    "wof:name":"L Kelsay",
    "wof:placetype":"venue"
},
  "geometry": {"coordinates":[-92.11797,38.70161],"type":"Point"}
}