{
  "type": "Feature",
  "properties": {
    "iso:country":"US",
    "sg:address":"1827 Sparks Ct",
    "sg:city":"Ballwin",
    "sg:classifiers":[
        {
            "category":"Health Services",
            "subcategory":"Doctor",
            "type":"Services"
        }
    ],
    "sg:phone":"+1 636 458 1827",
    "sg:postcode":"63011",
    "sg:province":"MO",
    "wof:name":"Charles Thornton DMD",
    "wof:placetype":"venue"
},
  "geometry": {"coordinates":[-90.619315,38.616336],"type":"Point"}
}