{
  "type": "Feature",
  "properties": {
    "iso:country":"US",
    "sg:address":"1866 State Hwy CC",
    "sg:city":"Elsberry",
    "sg:classifiers":[
        {
            "category":"Organizations",
            "subcategory":"Religious Organization",
            "type":"Services"
        }
    ],
    "sg:phone":"+1 573 898 3600",
    "sg:postcode":"63343",
    "sg:province":"MO",
    "wof:name":"Smith Chapel",
    "wof:placetype":"venue"
},
  "geometry": {"coordinates":[-90.854159,39.210091],"type":"Point"}
}