{
  "type": "Feature",
  "properties": {
    "iso:country":"US",
    "sg:address":"2142 W Chesterfield Blvd",
    "sg:city":"Springfield",
    "sg:classifiers":[
        {
            "category":"Banks & Credit Unions",
            "subcategory":"Investment Brokerage",
            "type":"Services"
        }
    ],
    "sg:phone":"+1 417 520 6324",
    "sg:postcode":"65807",
    "sg:province":"MO",
    "sg:tags":[
        "advisory",
        "financial",
        "stock"
    ],
    "wof:name":"Andrew Garrett Inc",
    "wof:placetype":"venue"
},
  "geometry": {"coordinates":[-93.32150799999999,37.145734],"type":"Point"}
}