{
  "type": "Feature",
  "properties": {
    "iso:country":"US",
    "sg:address":"722 Proctor Pl",
    "sg:city":"Independence",
    "sg:classifiers":[
        {
            "category":"Building & Trades",
            "subcategory":"Construction",
            "type":"Services"
        }
    ],
    "sg:phone":"+1 816 252 0700",
    "sg:postcode":"64052",
    "sg:province":"MO",
    "sg:tags":[
        "contractor"
    ],
    "wof:name":"Advance Seamless Guttering",
    "wof:placetype":"venue"
},
  "geometry": {"coordinates":[-94.43623599999999,39.085751],"type":"Point"}
}