{
  "type": "Feature",
  "properties": {
    "iso:country":"US",
    "sg:address":"109 Skyline Dr",
    "sg:city":"Joplin",
    "sg:classifiers":[
        {
            "category":"Manufacturing",
            "subcategory":"Metals",
            "type":"Manufacturing & Wholesale Goods"
        }
    ],
    "sg:phone":"+1 417 624 7774",
    "sg:postcode":"64804",
    "sg:province":"MO",
    "sg:tags":[
        "steel"
    ],
    "wof:name":"Doing Steel",
    "wof:placetype":"venue"
},
  "geometry": {"coordinates":[-94.47662800000001,37.033664],"type":"Point"}
}