{
  "type": "Feature",
  "properties": {
    "iso:country":"US",
    "sg:address":"3973 Humphrey St",
    "sg:city":"Saint Louis",
    "sg:classifiers":[
        {
            "category":"Retail",
            "subcategory":"Auto Repair",
            "type":"Services"
        }
    ],
    "sg:phone":"+1 314 776 5116",
    "sg:postcode":"63116",
    "sg:province":"MO",
    "wof:name":"Carl's 66 Serv Station",
    "wof:placetype":"venue"
},
  "geometry": {"coordinates":[-90.252998,38.5989],"type":"Point"}
}