{
  "type": "Feature",
  "properties": {
    "iso:country":"US",
    "sg:address":"9300 Blue Ridge Blvd",
    "sg:city":"Kansas City",
    "sg:classifiers":[
        {
            "category":"Banks & Credit Unions",
            "subcategory":"Bank",
            "type":"Services"
        }
    ],
    "sg:phone":"+1 816 221 3600",
    "sg:postcode":"64138",
    "sg:province":"MO",
    "wof:name":"Banister Bank",
    "wof:placetype":"venue"
},
  "geometry": {"coordinates":[-94.50784400000001,38.953775],"type":"Point"}
}