{
  "type": "Feature",
  "properties": {
    "iso:country":"US",
    "sg:address":"10216 Manchester Rd",
    "sg:city":"Kirkwood",
    "sg:classifiers":[
        {
            "category":"Professional",
            "type":"Services"
        },
        {
            "category":"Retail",
            "subcategory":"Animal Services",
            "type":"Services"
        }
    ],
    "sg:phone":"+1 314 966 5589",
    "sg:postcode":"63122",
    "sg:province":"MO",
    "sg:tags":[
        "pet"
    ],
    "wof:name":"Saint Louis Schnauzer Rescue",
    "wof:placetype":"venue"
},
  "geometry": {"coordinates":[-90.396615,38.600709],"type":"Point"}
}