{
  "type": "Feature",
  "properties": {
    "iso:country":"US",
    "sg:address":"4035 Shamrock Rd",
    "sg:city":"Jefferson City",
    "sg:classifiers":[
        {
            "category":"Social Services",
            "subcategory":"Child Care",
            "type":"Services"
        }
    ],
    "sg:phone":"+1 573 634 2360",
    "sg:postcode":"65101",
    "sg:province":"MO",
    "sg:tags":[
        "day"
    ],
    "wof:name":"Toebbens Day Care",
    "wof:placetype":"venue"
},
  "geometry": {"coordinates":[-92.089986,38.518336],"type":"Point"}
}