{
  "type": "Feature",
  "properties": {
    "iso:country":"US",
    "sg:address":"624 S Central St",
    "sg:city":"Buckner",
    "sg:classifiers":[
        {
            "category":"Retail",
            "subcategory":"Repair Shop",
            "type":"Services"
        }
    ],
    "sg:phone":"+1 816 650 6529",
    "sg:postcode":"64016",
    "sg:province":"MO",
    "sg:tags":[
        "electrical"
    ],
    "wof:name":"Mickeys Appliance Service",
    "wof:placetype":"venue"
},
  "geometry": {"coordinates":[-94.20038700000001,39.129955],"type":"Point"}
}