{
  "type": "Feature",
  "properties": {
    "iso:country":"US",
    "sg:address":"1282 Westside Blvd",
    "sg:city":"Nixa",
    "sg:classifiers":[
        {
            "category":"Retail",
            "subcategory":"Auto Repair",
            "type":"Services"
        }
    ],
    "sg:phone":"+1 417 724 1234",
    "sg:postcode":"65714",
    "sg:province":"MO",
    "sg:tags":[
        "general"
    ],
    "wof:name":"Advanced Auto Repair",
    "wof:placetype":"venue"
},
  "geometry": {"coordinates":[-93.326803,37.036294],"type":"Point"}
}