{
  "type": "Feature",
  "properties": {
    "iso:country":"US",
    "sg:address":"3660 W Clay St",
    "sg:city":"St Charles",
    "sg:classifiers":[
        {
            "category":"Professional",
            "subcategory":"Accounting & Tax Preparation",
            "type":"Services"
        }
    ],
    "sg:phone":"+1 636 946 3366",
    "sg:postcode":"63301",
    "sg:province":"MO",
    "sg:tags":[
        "accountant"
    ],
    "wof:name":"Bredensteiner & Assoc",
    "wof:placetype":"venue"
},
  "geometry": {"coordinates":[-90.556539,38.791596],"type":"Point"}
}