{
  "type": "Feature",
  "properties": {
    "iso:country":"US",
    "sg:address":"203 NE Englewood Rd",
    "sg:city":"Kansas City",
    "sg:classifiers":[
        {
            "category":"Professional",
            "subcategory":"Accounting & Tax Preparation",
            "type":"Services"
        }
    ],
    "sg:phone":"+1 816 455 5470",
    "sg:postcode":"64118",
    "sg:province":"MO",
    "wof:name":"H & R Block",
    "wof:placetype":"venue"
},
  "geometry": {"coordinates":[-94.57864600000001,39.195644],"type":"Point"}
}