{
  "type": "Feature",
  "properties": {
    "iso:country":"US",
    "sg:address":"2730 McNair Ave",
    "sg:city":"St Louis",
    "sg:classifiers":[
        {
            "category":"Bars & Pubs",
            "subcategory":"Wine Bar",
            "type":"Food & Drink"
        }
    ],
    "sg:phone":"+1 314 664 4511",
    "sg:postcode":"63118",
    "sg:province":"MO",
    "sg:website":"ernestoswinebar.com/",
    "wof:name":"Ernesto's",
    "wof:placetype":"venue"
},
  "geometry": {"coordinates":[-90.219309,38.60212],"type":"Point"}
}