{
  "type": "Feature",
  "properties": {
    "iso:country":"US",
    "sg:address":"33913 E Truman Rd",
    "sg:city":"Grain Valley",
    "sg:phone":"+1 816 650 3462",
    "sg:postcode":"64029",
    "sg:province":"MO",
    "sg:tags":[
        "farm",
        "corn"
    ],
    "wof:name":"Marvin Cuddy",
    "wof:placetype":"venue"
},
  "geometry": {"coordinates":[-94.18154199999999,39.064441],"type":"Point"}
}