{
  "type": "Feature",
  "properties": {
    "iso:country":"US",
    "sg:address":"6251 Mid Rivers Mall Dr",
    "sg:city":"Saint Charles",
    "sg:classifiers":[
        {
            "category":"Restaurant",
            "type":"Food & Drink"
        }
    ],
    "sg:menulink":"http://www.allmenus.com/mo/cottleville/194320-mcdonalds/menu/",
    "sg:postcode":"63304",
    "sg:province":"MO",
    "sg:tags":[
        "burger",
        "american"
    ],
    "wof:name":"McDonald's",
    "wof:placetype":"venue"
},
  "geometry": {"coordinates":[-90.63408099999999,38.73935],"type":"Point"}
}