{
  "type": "Feature",
  "properties": {
    "iso:country":"US",
    "sg:address":"208 Pearl St",
    "sg:city":"Nixa",
    "sg:classifiers":[
        {
            "category":"Organizations",
            "subcategory":"Membership Organization",
            "type":"Services"
        }
    ],
    "sg:phone":"+1 417 725 3524",
    "sg:postcode":"65714",
    "sg:province":"MO",
    "wof:name":"Ozarks Steam Engine Assoc",
    "wof:placetype":"venue"
},
  "geometry": {"coordinates":[-93.293471,37.050091],"type":"Point"}
}