{
  "type": "Feature",
  "properties": {
    "iso:country":"US",
    "sg:address":"508 S Hunter St",
    "sg:city":"Versailles",
    "sg:classifiers":[
        {
            "category":"Building & Trades",
            "subcategory":"Construction",
            "type":"Services"
        }
    ],
    "sg:phone":"+1 573 378 6368",
    "sg:postcode":"65084",
    "sg:province":"MO",
    "sg:tags":[
        "builder",
        "deck"
    ],
    "wof:name":"Barnes Construction",
    "wof:placetype":"venue"
},
  "geometry": {"coordinates":[-92.846521,38.426543],"type":"Point"}
}