{
  "type": "Feature",
  "properties": {
    "iso:country":"US",
    "sg:address":"211 S Central Ave",
    "sg:city":"Clayton",
    "sg:classifiers":[
        {
            "category":"Utilities",
            "subcategory":"Telephone",
            "type":"Services"
        },
        {
            "category":"Professional",
            "subcategory":"Computer Services",
            "type":"Services"
        }
    ],
    "sg:phone":"+1 314 727 6818",
    "sg:postcode":"63105",
    "sg:province":"MO",
    "sg:tags":[
        "communications",
        "internet"
    ],
    "wof:name":"Captiva Marketing",
    "wof:placetype":"venue"
},
  "geometry": {"coordinates":[-90.338936,38.646014],"type":"Point"}
}