{
  "type": "Feature",
  "properties": {
    "iso:country":"US",
    "sg:address":"126 Main St",
    "sg:city":"St Peters",
    "sg:classifiers":[
        {
            "category":"Bars & Pubs",
            "type":"Food & Drink"
        }
    ],
    "sg:phone":"+1 636 272 9205",
    "sg:postcode":"63376",
    "sg:province":"MO",
    "sg:tags":[
        "drinking"
    ],
    "wof:name":"Bert & Jim's Tavern",
    "wof:placetype":"venue"
},
  "geometry": {"coordinates":[-90.626018,38.801859],"type":"Point"}
}