{
  "type": "Feature",
  "properties": {
    "iso:country":"US",
    "sg:address":"21501 200th St",
    "sg:city":"Jameson",
    "sg:classifiers":[
        {
            "category":"Organizations",
            "subcategory":"Community Association",
            "type":"Services"
        }
    ],
    "sg:phone":"+1 660 663 3520",
    "sg:postcode":"64647",
    "sg:province":"MO",
    "wof:name":"International Assoc of LI",
    "wof:placetype":"venue"
},
  "geometry": {"coordinates":[-94.025172,39.970586],"type":"Point"}
}