{
  "type": "Feature",
  "properties": {
    "iso:country":"US",
    "sg:address":"187 Oak Hill Cluster",
    "sg:city":"Independence",
    "sg:classifiers":[
        {
            "category":"Building & Trades",
            "subcategory":"Construction",
            "type":"Services"
        }
    ],
    "sg:phone":"+1 816 228 2481",
    "sg:postcode":"64057",
    "sg:province":"MO",
    "sg:tags":[
        "commercial",
        "painting",
        "contractor"
    ],
    "wof:name":"Mid American Coating",
    "wof:placetype":"venue"
},
  "geometry": {"coordinates":[-94.2812,39.073497],"type":"Point"}
}