{
  "type": "Feature",
  "properties": {
    "iso:country":"US",
    "sg:address":"12458 Saint Charles Rock Rd",
    "sg:city":"Bridgeton",
    "sg:classifiers":[
        {
            "category":"Personal",
            "subcategory":"Nail Salon",
            "type":"Services"
        }
    ],
    "sg:phone":"+1 314 739 2855",
    "sg:postcode":"63044",
    "sg:province":"MO",
    "wof:name":"VI VI Nails",
    "wof:placetype":"venue"
},
  "geometry": {"coordinates":[-90.43164899999999,38.756082],"type":"Point"}
}