{
  "type": "Feature",
  "properties": {
    "iso:country":"US",
    "sg:address":"550 Sondern St",
    "sg:city":"O Fallon",
    "sg:classifiers":[
        {
            "category":"Restaurant",
            "type":"Food & Drink"
        }
    ],
    "sg:phone":"+1 636 281 2030",
    "sg:postcode":"63366",
    "sg:province":"MO",
    "wof:name":"Business Interest",
    "wof:placetype":"venue"
},
  "geometry": {"coordinates":[-90.695115,38.806293],"type":"Point"}
}