{
  "type": "Feature",
  "properties": {
    "iso:country":"US",
    "sg:address":"1007 N 5th St",
    "sg:city":"Tarkio",
    "sg:classifiers":[
        {
            "category":"Freight",
            "type":"Transportation"
        }
    ],
    "sg:phone":"+1 660 736 4408",
    "sg:postcode":"64491",
    "sg:province":"MO",
    "sg:tags":[
        "over",
        "road",
        "trucking"
    ],
    "wof:name":"Marvin McCartney Trucking",
    "wof:placetype":"venue"
},
  "geometry": {"coordinates":[-95.380167,40.449577],"type":"Point"}
}