{
  "type": "Feature",
  "properties": {
    "iso:country":"US",
    "sg:address":"10182 Old Hwy 60",
    "sg:city":"Dudley",
    "sg:classifiers":[
        {
            "category":"Manufacturing",
            "subcategory":"Building Materials",
            "type":"Manufacturing & Wholesale Goods"
        }
    ],
    "sg:phone":"+1 573 624 7090",
    "sg:postcode":"63936",
    "sg:province":"MO",
    "sg:tags":[
        "cabinet"
    ],
    "wof:name":"WW Wood Products Inc",
    "wof:placetype":"venue"
},
  "geometry": {"coordinates":[-90.097495,36.790745],"type":"Point"}
}