{
  "type": "Feature",
  "properties": {
    "iso:country":"US",
    "sg:address":"69 Fulkerson Cir",
    "sg:city":"Liberty",
    "sg:classifiers":[
        {
            "category":"Wholesale",
            "subcategory":"Home Furnishings",
            "type":"Manufacturing & Wholesale Goods"
        }
    ],
    "sg:phone":"+1 816 415 9540",
    "sg:postcode":"64068",
    "sg:province":"MO",
    "wof:name":"Wallpapers For Less",
    "wof:placetype":"venue"
},
  "geometry": {"coordinates":[-94.437343,39.236209],"type":"Point"}
}