{
  "type": "Feature",
  "properties": {
    "iso:country":"US",
    "sg:address":"901 NE Independence Ave",
    "sg:city":"Lees Summit",
    "sg:classifiers":[
        {
            "category":"Health Services",
            "subcategory":"Hospital",
            "type":"Services"
        },
        {
            "category":"Health Services",
            "subcategory":"Clinic",
            "type":"Services"
        }
    ],
    "sg:phone":"+1 816 246 8000",
    "sg:postcode":"64086",
    "sg:province":"MO",
    "sg:tags":[
        "mental",
        "outpatient",
        "specialty"
    ],
    "sg:website":"www.rediscovermh.org",
    "wof:name":"Rediscover Mental Health Svcs",
    "wof:placetype":"venue"
},
  "geometry": {"coordinates":[-94.364806,38.928312],"type":"Point"}
}