{
  "type": "Feature",
  "properties": {
    "iso:country":"US",
    "sg:address":"1501 S Williams St",
    "sg:city":"Moberly",
    "sg:classifiers":[
        {
            "category":"Place Of Worship",
            "type":"Public Place"
        }
    ],
    "sg:phone":"+1 660 263 3932",
    "sg:postcode":"65270",
    "sg:province":"MO",
    "sg:tags":[
        "church"
    ],
    "wof:name":"Franklin St Church Of God",
    "wof:placetype":"venue"
},
  "geometry": {"coordinates":[-92.43898,39.401659],"type":"Point"}
}