{
  "type": "Feature",
  "properties": {
    "iso:country":"US",
    "sg:address":"205 W Berry St",
    "sg:city":"Hamilton",
    "sg:classifiers":[
        {
            "category":"Health Services",
            "subcategory":"Chiropractor",
            "type":"Services"
        }
    ],
    "sg:phone":"+1 660 645 2011",
    "sg:postcode":"64644",
    "sg:province":"MO",
    "wof:name":"Terry Ross DC",
    "wof:placetype":"venue"
},
  "geometry": {"coordinates":[-94.00057700000001,39.742407],"type":"Point"}
}