{
  "type": "Feature",
  "properties": {
    "iso:country":"US",
    "sg:address":"15296 Falcon Rd",
    "sg:city":"Neosho",
    "sg:classifiers":[
        {
            "category":"Professional",
            "subcategory":"Detective & Security Services",
            "type":"Services"
        }
    ],
    "sg:phone":"+1 417 456 1978",
    "sg:postcode":"64850",
    "sg:province":"MO",
    "sg:tags":[
        "information",
        "bureau"
    ],
    "wof:name":"Jmh Dumpster Service",
    "wof:placetype":"venue"
},
  "geometry": {"coordinates":[-94.500205,36.847824],"type":"Point"}
}