{
  "type": "Feature",
  "properties": {
    "iso:country":"US",
    "sg:address":"358 Midway Cir",
    "sg:city":"Nixa",
    "sg:classifiers":[
        {
            "category":"Home & Garden",
            "subcategory":"Garden Supply",
            "type":"Retail Goods"
        }
    ],
    "sg:phone":"+1 417 725 8787",
    "sg:postcode":"65714",
    "sg:province":"MO",
    "sg:tags":[
        "statuary"
    ],
    "wof:name":"J H Creative",
    "wof:placetype":"venue"
},
  "geometry": {"coordinates":[-93.30383,37.093422],"type":"Point"}
}