{
  "type": "Feature",
  "properties": {
    "iso:country":"US",
    "sg:address":"902 Tyler Ave",
    "sg:city":"Warrensburg",
    "sg:classifiers":[
        {
            "category":"Freight",
            "type":"Transportation"
        }
    ],
    "sg:phone":"+1 660 747 2383",
    "sg:postcode":"64093",
    "sg:province":"MO",
    "sg:tags":[
        "broker",
        "agent"
    ],
    "wof:name":"A Truckers Dream",
    "wof:placetype":"venue"
},
  "geometry": {"coordinates":[-93.72416699999999,38.75722],"type":"Point"}
}