{
  "type": "Feature",
  "properties": {
    "iso:country":"US",
    "sg:address":"193 Jamestown Mall",
    "sg:city":"Florissant",
    "sg:classifiers":[
        {
            "category":"Restaurant",
            "type":"Food & Drink"
        }
    ],
    "sg:menulink":"http://www.allmenus.com/mo/spanish-lake/34131-kriegers/menu/",
    "sg:phone":"+1 314 653 6279",
    "sg:postcode":"63034",
    "sg:province":"MO",
    "sg:tags":[
        "american"
    ],
    "wof:name":"Krieger's",
    "wof:placetype":"venue"
},
  "geometry": {"coordinates":[-90.249503,38.818744],"type":"Point"}
}