{
  "type": "Feature",
  "properties": {
    "iso:country":"US",
    "sg:address":"3497 S 30th Rd",
    "sg:city":"Humansville",
    "sg:classifiers":[
        {
            "category":"Building & Trades",
            "subcategory":"Construction",
            "type":"Services"
        }
    ],
    "sg:phone":"+1 417 880 3750",
    "sg:postcode":"65674",
    "sg:province":"MO",
    "sg:tags":[
        "house"
    ],
    "wof:name":"R&R Enterprise",
    "wof:placetype":"venue"
},
  "geometry": {"coordinates":[-93.571692,37.757754],"type":"Point"}
}