{
  "type": "Feature",
  "properties": {
    "iso:country":"US",
    "sg:address":"3196 W Farm Rd 112",
    "sg:city":"Springfield",
    "sg:classifiers":[
        {
            "category":"Building & Trades",
            "subcategory":"Construction",
            "type":"Services"
        }
    ],
    "sg:phone":"+1 417 866 4802",
    "sg:postcode":"65803",
    "sg:province":"MO",
    "wof:name":"Ball Paving Inc",
    "wof:placetype":"venue"
},
  "geometry": {"coordinates":[-93.33908,37.248699],"type":"Point"}
}