{
  "type": "Feature",
  "properties": {
    "iso:country":"US",
    "sg:address":"35 Anderson Ln",
    "sg:city":"Sullivan",
    "sg:classifiers":[
        {
            "category":"Retail",
            "subcategory":"Repair Shop",
            "type":"Services"
        }
    ],
    "sg:phone":"+1 573 927 2121",
    "sg:postcode":"63080",
    "sg:province":"MO",
    "wof:name":"Furniture Doctor",
    "wof:placetype":"venue"
},
  "geometry": {"coordinates":[-91.122066,38.282886],"type":"Point"}
}