{
  "type": "Feature",
  "properties": {
    "iso:country":"US",
    "sg:address":"519 Ward Ave",
    "sg:city":"Caruthersville",
    "sg:classifiers":[
        {
            "category":"Shopping",
            "subcategory":"Catalog Store",
            "type":"Retail Goods"
        }
    ],
    "sg:phone":"+1 573 333 1430",
    "sg:postcode":"63830",
    "sg:province":"MO",
    "sg:tags":[
        "house",
        "mail"
    ],
    "wof:name":"Jean Keith & Theresa Whse",
    "wof:placetype":"venue"
},
  "geometry": {"coordinates":[-89.655557,36.190638],"type":"Point"}
}