{
  "type": "Feature",
  "properties": {
    "iso:country":"US",
    "sg:address":"1112 Westport Rd",
    "sg:city":"Kansas City",
    "sg:classifiers":[
        {
            "category":"Retail",
            "subcategory":"Auto Repair",
            "type":"Services"
        }
    ],
    "sg:phone":"+1 816 452 7490",
    "sg:postcode":"64111",
    "sg:province":"MO",
    "sg:tags":[
        "automotive",
        "general"
    ],
    "wof:name":"Westport Oil & Lube Inc",
    "wof:placetype":"venue"
},
  "geometry": {"coordinates":[-94.599954,39.049965],"type":"Point"}
}