{
  "type": "Feature",
  "properties": {
    "iso:country":"US",
    "sg:address":"813 SE 14 St",
    "sg:city":"Lees Summit",
    "sg:classifiers":[
        {
            "category":"Freight",
            "type":"Transportation"
        }
    ],
    "sg:phone":"+1 816 524 6071",
    "sg:postcode":"64081",
    "sg:province":"MO",
    "wof:name":"Fuller Transportation",
    "wof:placetype":"venue"
},
  "geometry": {"coordinates":[-94.353302,38.893039],"type":"Point"}
}