{
  "type": "Feature",
  "properties": {
    "iso:country":"US",
    "sg:address":"1231 W Liberty Ave",
    "sg:city":"Ozark",
    "sg:classifiers":[
        {
            "category":"Transit Center",
            "subcategory":"Freight",
            "type":"Transportation"
        },
        {
            "category":"Freight",
            "type":"Transportation"
        }
    ],
    "sg:phone":"+1 417 581 9815",
    "sg:postcode":"65721",
    "sg:province":"MO",
    "sg:tags":[
        "local",
        "trucking-motor",
        "trucking"
    ],
    "wof:name":"Jerry Swearengin Trucking, Inc.",
    "wof:placetype":"venue"
},
  "geometry": {"coordinates":[-93.215772,37.061579],"type":"Point"}
}