{
  "type": "Feature",
  "properties": {
    "iso:country":"US",
    "sg:address":"2761 Telegraph Rd",
    "sg:city":"Saint Louis",
    "sg:classifiers":[
        {
            "category":"Organizations",
            "subcategory":"Religious Organization",
            "type":"Services"
        }
    ],
    "sg:phone":"+1 314 892 5595",
    "sg:postcode":"63125",
    "sg:province":"MO",
    "wof:name":"St Lukes United Methdst Church",
    "wof:placetype":"venue"
},
  "geometry": {"coordinates":[-90.29399600000001,38.508966],"type":"Point"}
}