{
  "type": "Feature",
  "properties": {
    "iso:country":"US",
    "sg:address":"2602 Pear St",
    "sg:city":"St Joseph",
    "sg:classifiers":[
        {
            "category":"Wholesale",
            "subcategory":"Hardware",
            "type":"Manufacturing & Wholesale Goods"
        }
    ],
    "sg:phone":"+1 816 279 0084",
    "sg:postcode":"64503",
    "sg:province":"MO",
    "sg:tags":[
        "water",
        "cooler",
        "fountain",
        "filter"
    ],
    "wof:name":"CVB Inc",
    "wof:placetype":"venue"
},
  "geometry": {"coordinates":[-94.831098,39.733909],"type":"Point"}
}