{
  "type": "Feature",
  "properties": {
    "iso:country":"US",
    "sg:address":"228 W Main St",
    "sg:city":"Steele",
    "sg:classifiers":[
        {
            "category":"Home & Garden",
            "subcategory":"Garden Supply",
            "type":"Retail Goods"
        }
    ],
    "sg:phone":"+1 573 695 2233",
    "sg:postcode":"63877",
    "sg:province":"MO",
    "sg:tags":[
        "lawn",
        "mower"
    ],
    "wof:name":"Robertson Lawn & Garden",
    "wof:placetype":"venue"
},
  "geometry": {"coordinates":[-89.831512,36.085779],"type":"Point"}
}