{
  "type": "Feature",
  "properties": {
    "iso:country":"US",
    "sg:address":"1804 Wigwam Pl",
    "sg:city":"Blue Springs",
    "sg:classifiers":[
        {
            "category":"Professional",
            "type":"Services"
        }
    ],
    "sg:phone":"+1 816 228 4601",
    "sg:postcode":"64015",
    "sg:province":"MO",
    "sg:tags":[
        "establishment"
    ],
    "wof:name":"Michael Pfizer Griesbauer Inc",
    "wof:placetype":"venue"
},
  "geometry": {"coordinates":[-94.285774,39.000275],"type":"Point"}
}