{
  "type": "Feature",
  "properties": {
    "iso:country":"US",
    "sg:address":"144 N Harmon Ave",
    "sg:city":"Republic",
    "sg:classifiers":[
        {
            "category":"Building & Trades",
            "subcategory":"Construction",
            "type":"Services"
        }
    ],
    "sg:phone":"+1 417 732 8171",
    "sg:postcode":"65738",
    "sg:province":"MO",
    "sg:tags":[
        "house"
    ],
    "wof:name":"G & M Peterson Homes Inc",
    "wof:placetype":"venue"
},
  "geometry": {"coordinates":[-93.444397,37.119163],"type":"Point"}
}