{
  "type": "Feature",
  "properties": {
    "iso:country":"US",
    "sg:address":"94 State Rd Bb",
    "sg:city":"Montreal",
    "sg:classifiers":[
        {
            "category":"Shopping",
            "subcategory":"Bicycles & Sporting Goods",
            "type":"Retail Goods"
        }
    ],
    "sg:phone":"+1 573 346 7975",
    "sg:postcode":"65591",
    "sg:province":"MO",
    "sg:tags":[
        "gun",
        "gunsmith"
    ],
    "wof:name":"Eddie's Fin Feather & Fur",
    "wof:placetype":"venue"
},
  "geometry": {"coordinates":[-92.592495,37.959545],"type":"Point"}
}