{
  "type": "Feature",
  "properties": {
    "iso:country":"US",
    "sg:address":"1008 N Ponca Dr",
    "sg:city":"Independence",
    "sg:classifiers":[
        {
            "category":"Professional",
            "type":"Services"
        },
        {
            "category":"Personal",
            "type":"Services"
        }
    ],
    "sg:phone":"+1 816 796 9727",
    "sg:postcode":"64056",
    "sg:province":"MO",
    "sg:tags":[
        "consultant",
        "wedding"
    ],
    "wof:name":"Mommy's Rescue LLC",
    "wof:placetype":"venue"
},
  "geometry": {"coordinates":[-94.35932200000001,39.121762],"type":"Point"}
}