{
  "type": "Feature",
  "properties": {
    "iso:country":"US",
    "sg:address":"1120 N Missouri Ave",
    "sg:city":"Springfield",
    "sg:classifiers":[
        {
            "category":"Building & Trades",
            "subcategory":"Construction",
            "type":"Services"
        },
        {
            "category":"Manufacturing",
            "subcategory":"Building Materials",
            "type":"Manufacturing & Wholesale Goods"
        }
    ],
    "sg:phone":"+1 417 818 7458",
    "sg:postcode":"65802",
    "sg:province":"MO",
    "sg:tags":[
        "roofing",
        "industrial",
        "sheet",
        "altering",
        "work",
        "metal",
        "specialty",
        "contractor",
        "siding",
        "contractors-commercial",
        "remodeling"
    ],
    "wof:name":"Lampe Roofing & Contracting",
    "wof:placetype":"venue"
},
  "geometry": {"coordinates":[-93.301237,37.220268],"type":"Point"}
}