{
  "type": "Feature",
  "properties": {
    "iso:country":"US",
    "sg:address":"1146 Great Falls Ct",
    "sg:city":"Ballwin",
    "sg:classifiers":[
        {
            "category":"Health Services",
            "subcategory":"Doctor",
            "type":"Services"
        }
    ],
    "sg:phone":"+1 636 825 1228",
    "sg:postcode":"63021",
    "sg:province":"MO",
    "sg:tags":[
        "medical"
    ],
    "wof:name":"Agha Dr Irfan",
    "wof:placetype":"venue"
},
  "geometry": {"coordinates":[-90.50231100000001,38.572525],"type":"Point"}
}