{
  "type": "Feature",
  "properties": {
    "iso:country":"US",
    "sg:address":"17102 Hwy Ff",
    "sg:city":"Stover",
    "sg:classifiers":[
        {
            "category":"Farming",
            "subcategory":"Livestock Farm",
            "type":"Manufacturing & Wholesale Goods"
        }
    ],
    "sg:phone":"+1 573 377 4353",
    "sg:postcode":"65078",
    "sg:province":"MO",
    "sg:tags":[
        "beef",
        "feedlot",
        "cattle"
    ],
    "wof:name":"Myron Fischer",
    "wof:placetype":"venue"
},
  "geometry": {"coordinates":[-93.03146099999999,38.437214],"type":"Point"}
}