{
  "type": "Feature",
  "properties": {
    "iso:country":"US",
    "sg:address":"3341 Cottonwood Dr",
    "sg:city":"St Charles",
    "sg:classifiers":[
        {
            "category":"Cinema",
            "subcategory":"Movie Rental",
            "type":"Entertainment"
        }
    ],
    "sg:phone":"+1 636 724 7457",
    "sg:postcode":"63301",
    "sg:province":"MO",
    "sg:tags":[
        "leasing",
        "video",
        "disc",
        "tape"
    ],
    "wof:name":"Flix Plus LLC",
    "wof:placetype":"venue"
},
  "geometry": {"coordinates":[-90.47935699999999,38.821699],"type":"Point"}
}