{
  "type": "Feature",
  "properties": {
    "iso:country":"US",
    "sg:address":"1509 Bellevue Ave",
    "sg:city":"Saint Louis",
    "sg:classifiers":[
        {
            "category":"Shopping",
            "subcategory":"Crafts & Fabrics",
            "type":"Retail Goods"
        }
    ],
    "sg:phone":"+1 314 644 6871",
    "sg:postcode":"63117",
    "sg:province":"MO",
    "sg:tags":[
        "sewing"
    ],
    "wof:name":"Rope Yarn Music Inc",
    "wof:placetype":"venue"
},
  "geometry": {"coordinates":[-90.313005,38.625273],"type":"Point"}
}