{
  "type": "Feature",
  "properties": {
    "iso:country":"US",
    "sg:address":"22397 State Hwy 156",
    "sg:city":"La Plata",
    "sg:classifiers":[
        {
            "category":"Building & Trades",
            "subcategory":"Construction",
            "type":"Services"
        }
    ],
    "sg:phone":"+1 660 332 4176",
    "sg:postcode":"63549",
    "sg:province":"MO",
    "sg:tags":[
        "contractor",
        "carpenter",
        "carpentry"
    ],
    "wof:name":"Burkholder Construction",
    "wof:placetype":"venue"
},
  "geometry": {"coordinates":[-92.617974,40.022398],"type":"Point"}
}