{
  "type": "Feature",
  "properties": {
    "iso:country":"US",
    "sg:address":"604 Lambert Pointe Dr",
    "sg:city":"Hazelwood",
    "sg:classifiers":[
        {
            "category":"Wholesale",
            "subcategory":"Medical Equipment & Supplies",
            "type":"Manufacturing & Wholesale Goods"
        }
    ],
    "sg:phone":"+1 314 731 3555",
    "sg:postcode":"63042",
    "sg:province":"MO",
    "sg:tags":[
        "x",
        "apparatus"
    ],
    "wof:name":"Source One Health Care Tchnlgs",
    "wof:placetype":"venue"
},
  "geometry": {"coordinates":[-90.377798,38.774641],"type":"Point"}
}