{
  "type": "Feature",
  "properties": {
    "iso:country":"US",
    "sg:address":"1612 Main St",
    "sg:city":"Bethany",
    "sg:classifiers":[
        {
            "category":"Manufacturing",
            "subcategory":"Printing",
            "type":"Manufacturing & Wholesale Goods"
        }
    ],
    "sg:phone":"+1 660 425 6315",
    "sg:postcode":"64424",
    "sg:province":"MO",
    "sg:tags":[
        "commercial"
    ],
    "wof:name":"Printery",
    "wof:placetype":"venue"
},
  "geometry": {"coordinates":[-94.034598,40.268604],"type":"Point"}
}