{
  "type": "Feature",
  "properties": {
    "iso:country":"US",
    "sg:address":"310 Potosi St",
    "sg:city":"Farmington",
    "sg:classifiers":[
        {
            "category":"Professional",
            "subcategory":"Accounting & Tax Preparation",
            "type":"Services"
        }
    ],
    "sg:phone":"+1 573 747 0200",
    "sg:postcode":"63640",
    "sg:province":"MO",
    "sg:tags":[
        "accountant"
    ],
    "wof:name":"John P Stobbs CPA",
    "wof:placetype":"venue"
},
  "geometry": {"coordinates":[-90.42874,37.783977],"type":"Point"}
}