{
  "type": "Feature",
  "properties": {
    "iso:country":"US",
    "sg:address":"5514 Locust St",
    "sg:city":"Augusta",
    "sg:classifiers":[
        {
            "category":"Education",
            "subcategory":"School",
            "type":"Public Place"
        }
    ],
    "sg:phone":"+1 636 228 4375",
    "sg:postcode":"63332",
    "sg:province":"MO",
    "wof:name":"Augusta Elementary School",
    "wof:placetype":"venue"
},
  "geometry": {"coordinates":[-90.879746,38.574121],"type":"Point"}
}