{
  "type": "Feature",
  "properties": {
    "iso:country":"US",
    "sg:address":"502 S Main St",
    "sg:city":"De Soto",
    "sg:classifiers":[
        {
            "category":"Restaurant",
            "type":"Food & Drink"
        }
    ],
    "sg:phone":"+1 636 586 7687",
    "sg:postcode":"63020",
    "sg:province":"MO",
    "wof:name":"Jewel's Bread Soup Bowl",
    "wof:placetype":"venue"
},
  "geometry": {"coordinates":[-90.555278,38.135202],"type":"Point"}
}