{
  "type": "Feature",
  "properties": {
    "iso:country":"US",
    "sg:address":"702 E 1st St",
    "sg:city":"Concordia",
    "sg:classifiers":[
        {
            "category":"Wholesale",
            "subcategory":"Hardware",
            "type":"Manufacturing & Wholesale Goods"
        },
        {
            "category":"Home & Garden",
            "subcategory":"Garden Supply",
            "type":"Retail Goods"
        },
        {
            "category":"Retail",
            "subcategory":"Repair Shop",
            "type":"Services"
        }
    ],
    "sg:phone":"+1 660 463 2844",
    "sg:postcode":"64020",
    "sg:province":"MO",
    "sg:tags":[
        "renting",
        "lawn",
        "outdoor",
        "power",
        "landscaping",
        "equipment-sales",
        "equipment",
        "saw"
    ],
    "sg:website":"http://www.stihldealer.net/default-dealer-011111.aspx",
    "wof:name":"Concordia Implement",
    "wof:placetype":"venue"
},
  "geometry": {"coordinates":[-93.559008,38.989189],"type":"Point"}
}