{
  "type": "Feature",
  "properties": {
    "iso:country":"US",
    "sg:address":"811 E South St",
    "sg:city":"Richmond",
    "sg:classifiers":[
        {
            "category":"Professional",
            "subcategory":"Computer Services",
            "type":"Services"
        }
    ],
    "sg:phone":"+1 816 776 3310",
    "sg:postcode":"64085",
    "sg:province":"MO",
    "sg:tags":[
        "related"
    ],
    "wof:name":"3 D Corporation",
    "wof:placetype":"venue"
},
  "geometry": {"coordinates":[-93.963984,39.270687],"type":"Point"}
}