{
  "type": "Feature",
  "properties": {
    "iso:country":"US",
    "sg:address":"3646 Fairview Ave",
    "sg:city":"Saint Louis",
    "sg:classifiers":[
        {
            "category":"Health Services",
            "subcategory":"Doctor",
            "type":"Services"
        }
    ],
    "sg:phone":"+1 314 664 5565",
    "sg:postcode":"63116",
    "sg:province":"MO",
    "sg:tags":[
        "medical",
        "clinic"
    ],
    "wof:name":"La Clinica",
    "wof:placetype":"venue"
},
  "geometry": {"coordinates":[-90.245126,38.595],"type":"Point"}
}