{
  "type": "Feature",
  "properties": {
    "iso:country":"US",
    "sg:address":"121 S Main St",
    "sg:city":"Piedmont",
    "sg:classifiers":[
        {
            "category":"Personal",
            "subcategory":"Barber",
            "type":"Services"
        }
    ],
    "sg:phone":"+1 573 223 7277",
    "sg:postcode":"63957",
    "sg:province":"MO",
    "sg:tags":[
        "shop"
    ],
    "wof:name":"Sitze's Barber Shop",
    "wof:placetype":"venue"
},
  "geometry": {"coordinates":[-90.695992,37.154518],"type":"Point"}
}