{
  "type": "Feature",
  "properties": {
    "iso:country":"US",
    "sg:address":"308 Front St",
    "sg:city":"La Monte",
    "sg:classifiers":[
        {
            "category":"Autos & Motor Vehicles",
            "subcategory":"Automobile Sales",
            "type":"Retail Goods"
        }
    ],
    "sg:phone":"+1 660 347 5883",
    "sg:postcode":"65337",
    "sg:province":"MO",
    "sg:tags":[
        "car",
        "used",
        "dealer"
    ],
    "wof:name":"Tommy's Used Cars",
    "wof:placetype":"venue"
},
  "geometry": {"coordinates":[-93.4306,38.763845],"type":"Point"}
}