{
  "type": "Feature",
  "properties": {
    "iso:country":"US",
    "sg:address":"17931 Liv 228",
    "sg:city":"Chillicothe",
    "sg:classifiers":[
        {
            "category":"Real Estate",
            "subcategory":"Real Estate Agent",
            "type":"Services"
        }
    ],
    "sg:phone":"+1 660 646 5798",
    "sg:postcode":"64601",
    "sg:province":"MO",
    "wof:name":"Medicine Creek Realty",
    "wof:placetype":"venue"
},
  "geometry": {"coordinates":[-93.446704,39.834992],"type":"Point"}
}