{
  "type": "Feature",
  "properties": {
    "iso:country":"US",
    "sg:address":"17501 S Reynolds Rd",
    "sg:city":"Pleasant Hill",
    "sg:classifiers":[
        {
            "category":"Farming",
            "subcategory":"Livestock Farm",
            "type":"Manufacturing & Wholesale Goods"
        }
    ],
    "sg:phone":"+1 816 865 3234",
    "sg:postcode":"64080",
    "sg:province":"MO",
    "sg:tags":[
        "beef",
        "feedlot",
        "cattle"
    ],
    "wof:name":"Russell Reynolds",
    "wof:placetype":"venue"
},
  "geometry": {"coordinates":[-94.170243,38.797358],"type":"Point"}
}