{
  "type": "Feature",
  "properties": {
    "iso:country":"US",
    "sg:address":"34 Wild Horse Way",
    "sg:city":"Chesterfield",
    "sg:classifiers":[
        {
            "category":"Health Services",
            "subcategory":"Doctor",
            "type":"Services"
        }
    ],
    "sg:phone":"+1 636 532 5228",
    "sg:postcode":"63005",
    "sg:province":"MO",
    "sg:tags":[
        "dentist"
    ],
    "wof:name":"Thomas C Lease DDS",
    "wof:placetype":"venue"
},
  "geometry": {"coordinates":[-90.66752700000001,38.646431],"type":"Point"}
}