{
  "type": "Feature",
  "properties": {
    "iso:country":"US",
    "sg:address":"1215 S Business 54",
    "sg:city":"Fulton",
    "sg:classifiers":[
        {
            "category":"Building & Trades",
            "subcategory":"Plumbing",
            "type":"Services"
        }
    ],
    "sg:phone":"+1 573 592 0627",
    "sg:postcode":"65251",
    "sg:province":"MO",
    "sg:tags":[
        "conditioning",
        "air",
        "system",
        "contractor"
    ],
    "wof:name":"Kronk Heating & Air Conditioni",
    "wof:placetype":"venue"
},
  "geometry": {"coordinates":[-91.95928499999999,38.832535],"type":"Point"}
}