{
  "type": "Feature",
  "properties": {
    "iso:country":"US",
    "sg:address":"1619 Spring St",
    "sg:city":"Poplar Bluff",
    "sg:classifiers":[
        {
            "category":"Professional",
            "type":"Services"
        }
    ],
    "sg:phone":"+1 573 727 9191",
    "sg:postcode":"63901",
    "sg:province":"MO",
    "wof:name":"Adams Kacie",
    "wof:placetype":"venue"
},
  "geometry": {"coordinates":[-90.41289500000001,36.764481],"type":"Point"}
}