{
  "type": "Feature",
  "properties": {
    "iso:country":"US",
    "sg:address":"2700 Forum Blvd",
    "sg:city":"Columbia",
    "sg:classifiers":[
        {
            "category":"Insurance",
            "subcategory":"Insurance Agent",
            "type":"Services"
        }
    ],
    "sg:phone":"+1 573 445 1178",
    "sg:postcode":"65203",
    "sg:province":"MO",
    "wof:name":"Plaza Insurance Ctr",
    "wof:placetype":"venue"
},
  "geometry": {"coordinates":[-92.364992,38.921844],"type":"Point"}
}