{
  "type": "Feature",
  "properties": {
    "iso:country":"US",
    "sg:address":"13878 Parksted Dr",
    "sg:city":"Earth City",
    "sg:classifiers":[
        {
            "category":"Freight",
            "type":"Transportation"
        }
    ],
    "sg:phone":"+1 314 298 9911",
    "sg:postcode":"63044",
    "sg:province":"MO",
    "sg:tags":[
        "terminal",
        "truck",
        "facility"
    ],
    "wof:name":"Winwell Distribution Inc",
    "wof:placetype":"venue"
},
  "geometry": {"coordinates":[-90.471744,38.767282],"type":"Point"}
}