{
  "type": "Feature",
  "properties": {
    "iso:country":"US",
    "sg:address":"6252 Southwood Ave",
    "sg:city":"Saint Louis",
    "sg:classifiers":[
        {
            "category":"Retail",
            "subcategory":"Portrait Studio",
            "type":"Services"
        }
    ],
    "sg:phone":"+1 314 725 4925",
    "sg:postcode":"63105",
    "sg:province":"MO",
    "sg:tags":[
        "photo"
    ],
    "wof:name":"Douglas Garfield Photography",
    "wof:placetype":"venue"
},
  "geometry": {"coordinates":[-90.304722,38.636234],"type":"Point"}
}