{
  "type": "Feature",
  "properties": {
    "iso:country":"US",
    "sg:address":"1 Lincoln Way",
    "sg:city":"Saint Louis",
    "sg:classifiers":[
        {
            "category":"Manufacturing",
            "subcategory":"Tools & Machinery",
            "type":"Manufacturing & Wholesale Goods"
        }
    ],
    "sg:phone":"+1 314 679 4200",
    "sg:postcode":"63120",
    "sg:province":"MO",
    "sg:tags":[
        "equipment",
        "mfg",
        "system",
        "lubricating"
    ],
    "wof:name":"Ln Holdings Corp",
    "wof:placetype":"venue"
},
  "geometry": {"coordinates":[-90.27023699999999,38.688586],"type":"Point"}
}