{
  "type": "Feature",
  "properties": {
    "addr:full":"1464 Saint Louis Galleria St Louis MO 63117",
    "addr:housenumber":"1464",
    "addr:postcode":"63117",
    "addr:street":"Saint Louis Galleria",
    "iso:country":"US",
    "sg:address":"1464 Saint Louis Galleria",
    "sg:city":"St Louis",
    "sg:classifiers":[
        {
            "category":"Shopping",
            "subcategory":"Clothing, Apparel, & Fashions",
            "type":"Retail Goods"
        }
    ],
    "sg:phone":"+1 314 721 9800",
    "sg:postcode":"63117",
    "sg:province":"MO",
    "wof:name":"Coldwater Creek",
    "wof:placetype":"venue"
},
  "geometry": {"coordinates":[-90.34590900000001,38.637193],"type":"Point"}
}