{
  "type": "Feature",
  "properties": {
    "iso:country":"US",
    "sg:address":"269 Buzzard Hill Rd",
    "sg:city":"Jackson",
    "sg:classifiers":[
        {
            "category":"Shopping",
            "type":"Retail Goods"
        },
        {
            "category":"Manufacturing",
            "subcategory":"Paper Products",
            "type":"Manufacturing & Wholesale Goods"
        }
    ],
    "sg:phone":"+1 573 837 5199",
    "sg:postcode":"63755",
    "sg:province":"MO",
    "sg:tags":[
        "packaging",
        "materials-wholesale",
        "material",
        "manufacturer"
    ],
    "wof:name":"Total Package Productions",
    "wof:placetype":"venue"
},
  "geometry": {"coordinates":[-89.532214,37.460098],"type":"Point"}
}