{
  "type": "Feature",
  "properties": {
    "iso:country":"US",
    "sg:address":"116 N Main St",
    "sg:city":"De Soto",
    "sg:classifiers":[
        {
            "category":"Retail",
            "subcategory":"Photofinishing",
            "type":"Services"
        }
    ],
    "sg:phone":"+1 636 586 3372",
    "sg:postcode":"63020",
    "sg:province":"MO",
    "sg:tags":[
        "laboratory"
    ],
    "wof:name":"Milfeld Flix Phtgaphy DBA Fojo",
    "wof:placetype":"venue"
},
  "geometry": {"coordinates":[-90.55350900000001,38.139776],"type":"Point"}
}