{
  "type": "Feature",
  "properties": {
    "iso:country":"US",
    "sg:address":"2116 59th St",
    "sg:city":"St Louis",
    "sg:classifiers":[
        {
            "category":"Professional",
            "subcategory":"Advertising",
            "type":"Services"
        }
    ],
    "sg:phone":"+1 314 951 2100",
    "sg:postcode":"63110",
    "sg:province":"MO",
    "sg:tags":[
        "mail",
        "direct"
    ],
    "wof:name":"Impressions Direct Inc",
    "wof:placetype":"venue"
},
  "geometry": {"coordinates":[-90.284971,38.61507],"type":"Point"}
}