{
  "type": "Feature",
  "properties": {
    "iso:country":"US",
    "sg:address":"403 N Main St",
    "sg:city":"Elsberry",
    "sg:classifiers":[
        {
            "category":"Restaurant",
            "type":"Food & Drink"
        }
    ],
    "sg:phone":"+1 573 898 3131",
    "sg:postcode":"63343",
    "sg:province":"MO",
    "wof:name":"Cadillac Bill's",
    "wof:placetype":"venue"
},
  "geometry": {"coordinates":[-90.782527,39.169239],"type":"Point"}
}