{
  "type": "Feature",
  "properties": {
    "iso:country":"US",
    "sg:address":"1522 Clayton Woods Ct",
    "sg:city":"Ballwin",
    "sg:classifiers":[
        {
            "category":"Professional",
            "subcategory":"Business Services",
            "type":"Services"
        }
    ],
    "sg:phone":"+1 636 458 9364",
    "sg:postcode":"63011",
    "sg:province":"MO",
    "wof:name":"Interiors By Robin",
    "wof:placetype":"venue"
},
  "geometry": {"coordinates":[-90.609728,38.601754],"type":"Point"}
}