{
  "type": "Feature",
  "properties": {
    "iso:country":"US",
    "sg:address":"5201 Fox Chase Dr",
    "sg:city":"Saint Charles",
    "sg:classifiers":[
        {
            "category":"Insurance",
            "subcategory":"Insurance Agent",
            "type":"Services"
        }
    ],
    "sg:phone":"+1 314 276 3645",
    "sg:postcode":"63301",
    "sg:province":"MO",
    "wof:name":"Real Estate Property Investors",
    "wof:placetype":"venue"
},
  "geometry": {"coordinates":[-90.486209,38.815024],"type":"Point"}
}