{
  "type": "Feature",
  "properties": {
    "iso:country":"US",
    "sg:address":"700 N Alanthus Ave",
    "sg:city":"Stanberry",
    "sg:classifiers":[
        {
            "category":"Manufacturing",
            "subcategory":"Food",
            "type":"Manufacturing & Wholesale Goods"
        }
    ],
    "sg:phone":"+1 660 783 2911",
    "sg:postcode":"64489",
    "sg:province":"MO",
    "sg:tags":[
        "product"
    ],
    "wof:name":"Dean Johnson",
    "wof:placetype":"venue"
},
  "geometry": {"coordinates":[-94.538551,40.219318],"type":"Point"}
}