{
  "type": "Feature",
  "properties": {
    "iso:country":"US",
    "sg:address":"1186 Teson Rd",
    "sg:city":"Hazelwood",
    "sg:classifiers":[
        {
            "category":"Sports & Exercise",
            "subcategory":"Swimming Pool",
            "type":"Entertainment"
        },
        {
            "category":"Government",
            "subcategory":"Office",
            "type":"Public Place"
        }
    ],
    "sg:phone":"+1 314 895 4157",
    "sg:postcode":"63042",
    "sg:province":"MO",
    "sg:tags":[
        "pools-public",
        "township",
        "government-city",
        "village"
    ],
    "wof:name":"Village of Hazelwood Pool",
    "wof:placetype":"venue"
},
  "geometry": {"coordinates":[-90.380859,38.79306],"type":"Point"}
}