{
  "type": "Feature",
  "properties": {
    "iso:country":"US",
    "sg:address":"1335 W 76 Country Blvd",
    "sg:city":"Branson",
    "sg:classifiers":[
        {
            "category":"Arts & Performance",
            "subcategory":"Music",
            "type":"Entertainment"
        },
        {
            "category":"Manufacturing",
            "subcategory":"Musical Instruments",
            "type":"Manufacturing & Wholesale Goods"
        }
    ],
    "sg:phone":"+1 417 334 2100",
    "sg:postcode":"65616",
    "sg:province":"MO",
    "sg:tags":[
        "instruments-supplies",
        "accessory"
    ],
    "wof:name":"Art Folk Music & Wood",
    "wof:placetype":"venue"
},
  "geometry": {"coordinates":[-93.245366,36.64035],"type":"Point"}
}