{
  "type": "Feature",
  "properties": {
    "iso:country":"US",
    "sg:address":"901 N Case St",
    "sg:city":"Albany",
    "sg:classifiers":[
        {
            "category":"Social Services",
            "subcategory":"Job Training",
            "type":"Services"
        }
    ],
    "sg:phone":"+1 660 726 5280",
    "sg:postcode":"64402",
    "sg:province":"MO",
    "sg:tags":[
        "nursing",
        "homes-skilled",
        "facility"
    ],
    "wof:name":"Intermediate Care Facility",
    "wof:placetype":"venue"
},
  "geometry": {"coordinates":[-94.327927,40.253464],"type":"Point"}
}