{
  "type": "Feature",
  "properties": {
    "iso:country":"US",
    "sg:address":"211 S Ardinger St",
    "sg:city":"Hamilton",
    "sg:classifiers":[
        {
            "category":"Building & Trades",
            "subcategory":"Cleaning & Sanitation",
            "type":"Services"
        }
    ],
    "sg:phone":"+1 816 583 2531",
    "sg:postcode":"64644",
    "sg:province":"MO",
    "sg:tags":[
        "janitor"
    ],
    "wof:name":"Grillim House Cleaning",
    "wof:placetype":"venue"
},
  "geometry": {"coordinates":[-93.99927700000001,39.741219],"type":"Point"}
}