{
  "type": "Feature",
  "properties": {
    "iso:country":"US",
    "sg:address":"6900 Gravois Ave",
    "sg:city":"Saint Louis",
    "sg:classifiers":[
        {
            "category":"Retail",
            "subcategory":"Auto Repair",
            "type":"Services"
        }
    ],
    "sg:phone":"+1 314 351 9100",
    "sg:postcode":"63116",
    "sg:province":"MO",
    "wof:name":"Ace Transmission",
    "wof:placetype":"venue"
},
  "geometry": {"coordinates":[-90.285674,38.568824],"type":"Point"}
}