{
  "type": "Feature",
  "properties": {
    "iso:country":"US",
    "sg:address":"10733 Sunset Office Dr",
    "sg:city":"Saint Louis",
    "sg:classifiers":[
        {
            "category":"Professional",
            "subcategory":"Management & Consulting",
            "type":"Services"
        }
    ],
    "sg:phone":"+1 314 894 1245",
    "sg:postcode":"63127",
    "sg:province":"MO",
    "sg:tags":[
        "consultation",
        "pool",
        "swimming"
    ],
    "wof:name":"Counsilman Hunsaker & Assoc",
    "wof:placetype":"venue"
},
  "geometry": {"coordinates":[-90.409851,38.556957],"type":"Point"}
}