{
  "type": "Feature",
  "properties": {
    "iso:country":"US",
    "sg:address":"31 NW 525th Rd",
    "sg:city":"Warrensburg",
    "sg:classifiers":[
        {
            "category":"Personal",
            "subcategory":"Beauty Salon",
            "type":"Services"
        }
    ],
    "sg:phone":"+1 660 747 6905",
    "sg:postcode":"64093",
    "sg:province":"MO",
    "wof:name":"Short Cut Inc",
    "wof:placetype":"venue"
},
  "geometry": {"coordinates":[-93.741775,38.838702],"type":"Point"}
}