{
  "type": "Feature",
  "properties": {
    "iso:country":"US",
    "sg:address":"1600 S 39th St",
    "sg:city":"St Louis",
    "sg:classifiers":[
        {
            "category":"Shopping",
            "subcategory":"Used Merchandise",
            "type":"Retail Goods"
        }
    ],
    "sg:phone":"+1 314 773 2264",
    "sg:postcode":"63110",
    "sg:province":"MO",
    "sg:tags":[
        "antique"
    ],
    "wof:name":"St Louis Architectural Art Co",
    "wof:placetype":"venue"
},
  "geometry": {"coordinates":[-90.24475,38.61905],"type":"Point"}
}