{
  "type": "Feature",
  "properties": {
    "iso:country":"US",
    "sg:address":"247 Pillsbury Rd",
    "sg:city":"Winfield",
    "sg:classifiers":[
        {
            "category":"Wholesale",
            "subcategory":"Farm Supplies",
            "type":"Manufacturing & Wholesale Goods"
        }
    ],
    "sg:phone":"+1 636 668 8101",
    "sg:postcode":"63389",
    "sg:province":"MO",
    "sg:tags":[
        "bean"
    ],
    "wof:name":"Winfield Grain",
    "wof:placetype":"venue"
},
  "geometry": {"coordinates":[-90.683497,38.993233],"type":"Point"}
}