{
  "type": "Feature",
  "properties": {
    "iso:country":"US",
    "sg:address":"16 Ashton Oak Ct",
    "sg:city":"Florissant",
    "sg:classifiers":[
        {
            "category":"Professional",
            "type":"Services"
        }
    ],
    "sg:phone":"+1 314 837 6326",
    "sg:postcode":"63034",
    "sg:province":"MO",
    "wof:name":"Jireh Creative Services",
    "wof:placetype":"venue"
},
  "geometry": {"coordinates":[-90.293126,38.841274],"type":"Point"}
}