{
  "type": "Feature",
  "properties": {
    "iso:country":"US",
    "sg:address":"339 Clayton Oaks Dr",
    "sg:city":"Ballwin",
    "sg:classifiers":[
        {
            "category":"Building & Trades",
            "subcategory":"Construction",
            "type":"Services"
        }
    ],
    "sg:phone":"+1 636 227 8261",
    "sg:postcode":"63011",
    "sg:province":"MO",
    "sg:tags":[
        "house"
    ],
    "wof:name":"Sage Contracting",
    "wof:placetype":"venue"
},
  "geometry": {"coordinates":[-90.596495,38.602041],"type":"Point"}
}