{
  "type": "Feature",
  "properties": {
    "iso:country":"US",
    "sg:address":"625 N Euclid Ave Ste 150",
    "sg:city":"Saint Louis",
    "sg:classifiers":[
        {
            "category":"Shopping",
            "subcategory":"Pharmacy",
            "type":"Retail Goods"
        }
    ],
    "sg:phone":"+1 314 367 3009",
    "sg:postcode":"63108",
    "sg:province":"MO",
    "sg:tags":[
        "drugstore"
    ],
    "sg:website":"www.medicineshoppe.com",
    "wof:name":"Medicine Shoppe",
    "wof:placetype":"venue"
},
  "geometry": {"coordinates":[-90.26067,38.651075],"type":"Point"}
}