{
  "type": "Feature",
  "properties": {
    "iso:country":"US",
    "sg:address":"136 N Kingshighway St",
    "sg:city":"Saint Charles",
    "sg:classifiers":[
        {
            "category":"Personal",
            "subcategory":"Beauty Salon",
            "type":"Services"
        }
    ],
    "sg:phone":"+1 636 949 0025",
    "sg:postcode":"63301",
    "sg:province":"MO",
    "sg:tags":[
        "shop"
    ],
    "wof:name":"Janes Nails",
    "wof:placetype":"venue"
},
  "geometry": {"coordinates":[-90.49477,38.786254],"type":"Point"}
}