{
  "type": "Feature",
  "properties": {
    "iso:country":"US",
    "sg:address":"1810 N Oak St",
    "sg:city":"Rolla",
    "sg:classifiers":[
        {
            "category":"Professional",
            "subcategory":"Detective & Security Services",
            "type":"Services"
        }
    ],
    "sg:phone":"+1 573 368 4433",
    "sg:postcode":"65401",
    "sg:province":"MO",
    "sg:tags":[
        "guard",
        "patrol"
    ],
    "wof:name":"TGI Insigna",
    "wof:placetype":"venue"
},
  "geometry": {"coordinates":[-91.768818,37.958934],"type":"Point"}
}