{
  "type": "Feature",
  "properties": {
    "iso:country":"US",
    "sg:address":"401 Overland Dr",
    "sg:city":"Liberty",
    "sg:classifiers":[
        {
            "category":"Shopping",
            "subcategory":"Computers & Home Electronics",
            "type":"Retail Goods"
        }
    ],
    "sg:phone":"+1 816 781 7177",
    "sg:postcode":"64068",
    "sg:province":"MO",
    "wof:name":"Macany Computers",
    "wof:placetype":"venue"
},
  "geometry": {"coordinates":[-94.382227,39.24934],"type":"Point"}
}