{
  "type": "Feature",
  "properties": {
    "iso:country":"US",
    "sg:address":"10465 State Hwy Af",
    "sg:city":"Mountain Grove",
    "sg:phone":"+1 417 453 6263",
    "sg:postcode":"65711",
    "sg:province":"MO",
    "sg:tags":[
        "farm",
        "field",
        "dairy",
        "crop"
    ],
    "wof:name":"Gene Dowden",
    "wof:placetype":"venue"
},
  "geometry": {"coordinates":[-92.37062,37.429912],"type":"Point"}
}