{
  "type": "Feature",
  "properties": {
    "iso:country":"US",
    "sg:address":"8032 Joel Ave",
    "sg:city":"Saint Louis",
    "sg:classifiers":[
        {
            "category":"Retail",
            "subcategory":"Repair Shop",
            "type":"Services"
        }
    ],
    "sg:phone":"+1 314 481 1822",
    "sg:postcode":"63123",
    "sg:province":"MO",
    "sg:tags":[
        "electrical"
    ],
    "wof:name":"Richmeyer Electronics",
    "wof:placetype":"venue"
},
  "geometry": {"coordinates":[-90.313937,38.563042],"type":"Point"}
}