{
  "type": "Feature",
  "properties": {
    "iso:country":"US",
    "sg:address":"311 Main St",
    "sg:city":"Amsterdam",
    "sg:classifiers":[
        {
            "category":"Banks & Credit Unions",
            "subcategory":"Bank",
            "type":"Services"
        }
    ],
    "sg:phone":"+1 660 267 3211",
    "sg:postcode":"64788",
    "sg:province":"MO",
    "wof:name":"CITIZENS Bank",
    "wof:placetype":"venue"
},
  "geometry": {"coordinates":[-94.00120699999999,38.459418],"type":"Point"}
}