{
  "type": "Feature",
  "properties": {
    "iso:country":"US",
    "sg:address":"43 Monte Rosa Dr",
    "sg:city":"De Soto",
    "sg:classifiers":[
        {
            "category":"Real Estate",
            "subcategory":"Real Estate Agent",
            "type":"Services"
        },
        {
            "category":"Organizations",
            "subcategory":"Professional Association",
            "type":"Services"
        }
    ],
    "sg:phone":"+1 636 586 8705",
    "sg:postcode":"63020",
    "sg:province":"MO",
    "wof:name":"Summer Set Prperty Owners Assn",
    "wof:placetype":"venue"
},
  "geometry": {"coordinates":[-90.567511,38.095249],"type":"Point"}
}