{
  "type": "Feature",
  "properties": {
    "iso:country":"US",
    "sg:address":"12422 Lusher Rd",
    "sg:city":"St Louis",
    "sg:classifiers":[
        {
            "category":"Manufacturing",
            "subcategory":"Printing",
            "type":"Manufacturing & Wholesale Goods"
        }
    ],
    "sg:phone":"+1 314 438 0023",
    "sg:postcode":"63138",
    "sg:province":"MO",
    "sg:tags":[
        "multimedia"
    ],
    "wof:name":"Unified Soundzz",
    "wof:placetype":"venue"
},
  "geometry": {"coordinates":[-90.227621,38.801765],"type":"Point"}
}