{
  "type": "Feature",
  "properties": {
    "iso:country":"US",
    "sg:address":"214 W Main St",
    "sg:city":"Malden",
    "sg:classifiers":[
        {
            "category":"Banks & Credit Unions",
            "subcategory":"Bank",
            "type":"Services"
        }
    ],
    "sg:phone":"+1 573 276 1212",
    "sg:postcode":"63863",
    "sg:province":"MO",
    "sg:tags":[
        "loan"
    ],
    "wof:name":"Master Cash",
    "wof:placetype":"venue"
},
  "geometry": {"coordinates":[-89.96831,36.558354],"type":"Point"}
}