{
  "type": "Feature",
  "properties": {
    "iso:country":"US",
    "sg:address":"80 S County Centerway",
    "sg:city":"St Louis",
    "sg:classifiers":[
        {
            "category":"Real Estate",
            "subcategory":"Real Estate Operator",
            "type":"Services"
        }
    ],
    "sg:phone":"+1 314 288 2020",
    "sg:postcode":"63129",
    "sg:province":"MO",
    "sg:tags":[
        "mall",
        "shopping",
        "center"
    ],
    "sg:website":"www.westfield.com",
    "wof:name":"Westfield Shoppingtowns West",
    "wof:placetype":"venue"
},
  "geometry": {"coordinates":[-90.329195,38.504824],"type":"Point"}
}