{
  "type": "Feature",
  "properties": {
    "iso:country":"US",
    "sg:address":"11655 N Farm Rd 51",
    "sg:city":"Walnut Grove",
    "sg:classifiers":[
        {
            "category":"Organizations",
            "subcategory":"Religious Organization",
            "type":"Services"
        }
    ],
    "sg:phone":"+1 417 994 2324",
    "sg:postcode":"65770",
    "sg:province":"MO",
    "wof:name":"Harold Baptist Church",
    "wof:placetype":"venue"
},
  "geometry": {"coordinates":[-93.53285200000001,37.416697],"type":"Point"}
}