{
  "type": "Feature",
  "properties": {
    "iso:country":"US",
    "sg:address":"802 NW Vesper St",
    "sg:city":"Blue Springs",
    "sg:classifiers":[
        {
            "category":"Retail",
            "subcategory":"Portrait Studio",
            "type":"Services"
        }
    ],
    "sg:phone":"+1 816 313 7400",
    "sg:postcode":"64015",
    "sg:province":"MO",
    "sg:tags":[
        "photo"
    ],
    "wof:name":"Creative Gallery Photogra",
    "wof:placetype":"venue"
},
  "geometry": {"coordinates":[-94.27341199999999,39.020486],"type":"Point"}
}