{
  "type": "Feature",
  "properties": {
    "addr:full":"608 N Belishe Ave Willow Springs MO 65793",
    "addr:housenumber":"608",
    "addr:postcode":"65793",
    "addr:street":"N Belishe Ave",
    "iso:country":"US",
    "sg:address":"608 N Belishe Ave",
    "sg:city":"Willow Springs",
    "sg:classifiers":[
        {
            "category":"Freight",
            "type":"Transportation"
        }
    ],
    "sg:phone":"+1 417 469 4337",
    "sg:postcode":"65793",
    "sg:province":"MO",
    "sg:tags":[
        "operator",
        "trucking"
    ],
    "wof:name":"David W Collins Trucking",
    "wof:placetype":"venue"
},
  "geometry": {"coordinates":[-91.960187,36.994362],"type":"Point"}
}