{
  "type": "Feature",
  "properties": {
    "iso:country":"US",
    "sg:address":"115 S Main St",
    "sg:city":"Liberty",
    "sg:classifiers":[
        {
            "category":"Professional",
            "subcategory":"Business Services",
            "type":"Services"
        }
    ],
    "sg:phone":"+1 816 407 3320",
    "sg:postcode":"64068",
    "sg:province":"MO",
    "sg:tags":[
        "organizing",
        "services-household"
    ],
    "wof:name":"Clay Facilities Management",
    "wof:placetype":"venue"
},
  "geometry": {"coordinates":[-94.420349,39.243763],"type":"Point"}
}