{
  "type": "Feature",
  "properties": {
    "iso:country":"US",
    "sg:address":"11004 Rambling Oaks Dr",
    "sg:city":"St Louis",
    "sg:classifiers":[
        {
            "category":"Personal",
            "type":"Services"
        },
        {
            "category":"Professional",
            "subcategory":"Management & Consulting",
            "type":"Services"
        }
    ],
    "sg:phone":"+1 314 843 5110",
    "sg:postcode":"63128",
    "sg:province":"MO",
    "sg:tags":[
        "party",
        "planning"
    ],
    "wof:name":"Always & Forever Ltd",
    "wof:placetype":"venue"
},
  "geometry": {"coordinates":[-90.404521,38.518252],"type":"Point"}
}