{
  "type": "Feature",
  "properties": {
    "iso:country":"US",
    "sg:address":"122 Avondale St",
    "sg:city":"Liberty",
    "sg:classifiers":[
        {
            "category":"Shopping",
            "subcategory":"Discount & Variety Stores",
            "type":"Retail Goods"
        }
    ],
    "sg:phone":"+1 816 630 2590",
    "sg:postcode":"64068",
    "sg:province":"MO",
    "sg:tags":[
        "merchandise",
        "general"
    ],
    "wof:name":"Stretch-A-Buck Sales",
    "wof:placetype":"venue"
},
  "geometry": {"coordinates":[-94.456503,39.232044],"type":"Point"}
}