{
  "type": "Feature",
  "properties": {
    "iso:country":"US",
    "sg:address":"8415 E 116th St",
    "sg:city":"Kansas City",
    "sg:classifiers":[
        {
            "category":"Retail",
            "subcategory":"Repair Shop",
            "type":"Services"
        }
    ],
    "sg:phone":"+1 816 966 8850",
    "sg:postcode":"64134",
    "sg:province":"MO",
    "sg:tags":[
        "refrigeration",
        "electrical"
    ],
    "wof:name":"Longview Refrigeration",
    "wof:placetype":"venue"
},
  "geometry": {"coordinates":[-94.49608499999999,38.912789],"type":"Point"}
}