{
  "type": "Feature",
  "properties": {
    "iso:country":"US",
    "sg:address":"711 Old Frontenac Sq",
    "sg:city":"St Louis",
    "sg:classifiers":[
        {
            "category":"Education",
            "subcategory":"Special Training",
            "type":"Public Place"
        }
    ],
    "sg:phone":"+1 314 993 3097",
    "sg:postcode":"63131",
    "sg:province":"MO",
    "sg:tags":[
        "modeling",
        "school"
    ],
    "wof:name":"John Robert Powers Intl",
    "wof:placetype":"venue"
},
  "geometry": {"coordinates":[-90.406353,38.643826],"type":"Point"}
}