{
  "type": "Feature",
  "properties": {
    "iso:country":"US",
    "sg:address":"1501 S Truman Blvd",
    "sg:city":"Caruthersville",
    "sg:classifiers":[
        {
            "category":"Autos & Motor Vehicles",
            "subcategory":"Automobile Sales",
            "type":"Retail Goods"
        }
    ],
    "sg:phone":"+1 573 333 4226",
    "sg:postcode":"63830",
    "sg:province":"MO",
    "sg:tags":[
        "used"
    ],
    "wof:name":"Gunnels Autosales",
    "wof:placetype":"venue"
},
  "geometry": {"coordinates":[-89.66751499999999,36.182684],"type":"Point"}
}