{
  "type": "Feature",
  "properties": {
    "iso:country":"US",
    "sg:address":"407 Shelby St",
    "sg:city":"Shelbina",
    "sg:classifiers":[
        {
            "category":"Building & Trades",
            "subcategory":"Construction",
            "type":"Services"
        }
    ],
    "sg:phone":"+1 573 588 2458",
    "sg:postcode":"63468",
    "sg:province":"MO",
    "sg:tags":[
        "residential"
    ],
    "wof:name":"Simpson Contracting",
    "wof:placetype":"venue"
},
  "geometry": {"coordinates":[-92.044127,39.696824],"type":"Point"}
}