{
  "type": "Feature",
  "properties": {
    "iso:country":"US",
    "sg:address":"915 W 23rd St S",
    "sg:city":"Independence",
    "sg:classifiers":[
        {
            "category":"Professional",
            "subcategory":"Business Services",
            "type":"Services"
        }
    ],
    "sg:phone":"+1 816 252 4511",
    "sg:postcode":"64055",
    "sg:province":"MO",
    "sg:tags":[
        "hanger",
        "sign"
    ],
    "wof:name":"ABC Sign & Lighting Svc",
    "wof:placetype":"venue"
},
  "geometry": {"coordinates":[-94.42764099999999,39.07954],"type":"Point"}
}