{
  "type": "Feature",
  "properties": {
    "iso:country":"US",
    "sg:address":"5051 Riverview Blvd",
    "sg:city":"Saint Louis",
    "sg:classifiers":[
        {
            "category":"Restaurant",
            "type":"Food & Drink"
        }
    ],
    "sg:phone":"+1 314 389 3262",
    "sg:postcode":"63120",
    "sg:province":"MO",
    "sg:tags":[
        "eating"
    ],
    "wof:name":"Lewis Snack Shop",
    "wof:placetype":"venue"
},
  "geometry": {"coordinates":[-90.25760200000001,38.700604],"type":"Point"}
}