{
  "type": "Feature",
  "properties": {
    "iso:country":"US",
    "sg:address":"163 Orlando Rd",
    "sg:city":"Kirbyville",
    "sg:classifiers":[
        {
            "category":"Utilities",
            "subcategory":"Water",
            "type":"Services"
        }
    ],
    "sg:phone":"+1 417 546 3132",
    "sg:postcode":"65679",
    "sg:province":"MO",
    "sg:tags":[
        "equipment",
        "conditioning",
        "softening"
    ],
    "wof:name":"Liscum Water & Waste Water Services",
    "wof:placetype":"venue"
},
  "geometry": {"coordinates":[-93.101953,36.650758],"type":"Point"}
}