{
  "type": "Feature",
  "properties": {
    "iso:country":"US",
    "sg:address":"3155 Meramec St",
    "sg:city":"Saint Louis",
    "sg:classifiers":[
        {
            "category":"Bars & Pubs",
            "type":"Food & Drink"
        }
    ],
    "sg:phone":"+1 314 353 9626",
    "sg:postcode":"63118",
    "sg:province":"MO",
    "sg:tags":[
        "nightlife"
    ],
    "wof:name":"Behrmann's Tavern",
    "wof:placetype":"venue"
},
  "geometry": {"coordinates":[-90.2397,38.580299],"type":"Point"}
}