{
  "type": "Feature",
  "properties": {
    "iso:country":"US",
    "sg:address":"402 SW White Ridge Dr",
    "sg:city":"Lees Summit",
    "sg:classifiers":[
        {
            "category":"Utilities",
            "subcategory":"Telephone",
            "type":"Services"
        },
        {
            "category":"Professional",
            "subcategory":"Computer Services",
            "type":"Services"
        }
    ],
    "sg:phone":"+1 816 246 4117",
    "sg:postcode":"64081",
    "sg:province":"MO",
    "sg:tags":[
        "consulting",
        "dev",
        "communications",
        "internet",
        "home",
        "page"
    ],
    "wof:name":"Kalechi Designs Inc",
    "wof:placetype":"venue"
},
  "geometry": {"coordinates":[-94.400424,38.910237],"type":"Point"}
}