{
  "type": "Feature",
  "properties": {
    "iso:country":"US",
    "sg:address":"708 N Bishop Ave",
    "sg:city":"Rolla",
    "sg:classifiers":[
        {
            "category":"Professional",
            "type":"Services"
        }
    ],
    "sg:phone":"+1 573 368 2882",
    "sg:postcode":"65401",
    "sg:province":"MO",
    "sg:tags":[
        "establishment"
    ],
    "wof:name":"Team Orb",
    "wof:placetype":"venue"
},
  "geometry": {"coordinates":[-91.77716100000001,37.949933],"type":"Point"}
}