{
  "type": "Feature",
  "properties": {
    "iso:country":"US",
    "sg:address":"3421 S Grand Blvd",
    "sg:city":"St Louis",
    "sg:classifiers":[
        {
            "category":"Home & Garden",
            "subcategory":"Building Materials",
            "type":"Retail Goods"
        }
    ],
    "sg:phone":"+1 314 772 1900",
    "sg:postcode":"63118",
    "sg:province":"MO",
    "sg:tags":[
        "paint"
    ],
    "wof:name":"Brod-Dugan Co",
    "wof:placetype":"venue"
},
  "geometry": {"coordinates":[-90.243482,38.595231],"type":"Point"}
}