{
  "type": "Feature",
  "properties": {
    "iso:country":"US",
    "sg:address":"10440 Page Ave",
    "sg:city":"St Louis",
    "sg:classifiers":[
        {
            "category":"Restaurant",
            "type":"Food & Drink"
        }
    ],
    "sg:phone":"+1 314 428 1445",
    "sg:postcode":"63132",
    "sg:province":"MO",
    "sg:tags":[
        "pizza"
    ],
    "wof:name":"Pizza Hut",
    "wof:placetype":"venue"
},
  "geometry": {"coordinates":[-90.39168100000001,38.691642],"type":"Point"}
}