{
  "type": "Feature",
  "properties": {
    "iso:country":"US",
    "sg:address":"28719 State Hwy Dd",
    "sg:city":"Harrisonville",
    "sg:classifiers":[
        {
            "category":"Freight",
            "type":"Transportation"
        }
    ],
    "sg:phone":"+1 816 380 6028",
    "sg:postcode":"64701",
    "sg:province":"MO",
    "sg:tags":[
        "distance",
        "long",
        "trucking"
    ],
    "wof:name":"Gundels Grass Farms",
    "wof:placetype":"venue"
},
  "geometry": {"coordinates":[-94.404855,38.59656],"type":"Point"}
}