{
  "type": "Feature",
  "properties": {
    "iso:country":"US",
    "sg:address":"1401 Creekstone Ct",
    "sg:city":"Fenton",
    "sg:classifiers":[
        {
            "category":"Shopping",
            "subcategory":"Jewelry",
            "type":"Retail Goods"
        }
    ],
    "sg:phone":"+1 636 225 7541",
    "sg:postcode":"63026",
    "sg:province":"MO",
    "wof:name":"Jewelry By Melanie",
    "wof:placetype":"venue"
},
  "geometry": {"coordinates":[-90.49079999999999,38.50989],"type":"Point"}
}