{
  "type": "Feature",
  "properties": {
    "iso:country":"US",
    "sg:address":"2403 Erna St",
    "sg:city":"Cape Girardeau",
    "sg:classifiers":[
        {
            "category":"Building & Trades",
            "subcategory":"Electrical",
            "type":"Services"
        }
    ],
    "sg:phone":"+1 573 334 6465",
    "sg:postcode":"63701",
    "sg:province":"MO",
    "sg:tags":[
        "electric",
        "contractor"
    ],
    "wof:name":"Ron Hale Electric",
    "wof:placetype":"venue"
},
  "geometry": {"coordinates":[-89.550504,37.323072],"type":"Point"}
}