{
  "type": "Feature",
  "properties": {
    "iso:country":"US",
    "sg:address":"1200 E Woodhurst Dr",
    "sg:city":"Springfield",
    "sg:classifiers":[
        {
            "category":"Manufacturing",
            "subcategory":"Printing",
            "type":"Manufacturing & Wholesale Goods"
        },
        {
            "category":"Organizations",
            "subcategory":"Professional Association",
            "type":"Services"
        }
    ],
    "sg:phone":"+1 417 887 1017",
    "sg:postcode":"65804",
    "sg:province":"MO",
    "sg:tags":[
        "publisher",
        "medical"
    ],
    "wof:name":"Greene County Medical Society",
    "wof:placetype":"venue"
},
  "geometry": {"coordinates":[-93.27625999999999,37.157761],"type":"Point"}
}