{
  "type": "Feature",
  "properties": {
    "iso:country":"US",
    "sg:address":"335 Bell Rd",
    "sg:city":"Wright City",
    "sg:classifiers":[
        {
            "category":"Building & Trades",
            "subcategory":"Construction",
            "type":"Services"
        }
    ],
    "sg:phone":"+1 636 745 7752",
    "sg:postcode":"63390",
    "sg:province":"MO",
    "sg:tags":[
        "residential",
        "general",
        "contractor"
    ],
    "wof:name":"Telkamp Construction Inc",
    "wof:placetype":"venue"
},
  "geometry": {"coordinates":[-91.03913,38.867114],"type":"Point"}
}