{
  "type": "Feature",
  "properties": {
    "iso:country":"US",
    "sg:address":"6220 E 87 St",
    "sg:city":"Kansas City",
    "sg:classifiers":[
        {
            "category":"Restaurant",
            "type":"Food & Drink"
        }
    ],
    "sg:phone":"+1 816 523 4242",
    "sg:postcode":"64138",
    "sg:province":"MO",
    "sg:tags":[
        "eating"
    ],
    "wof:name":"Dennys",
    "wof:placetype":"venue"
},
  "geometry": {"coordinates":[-94.51935,38.967316],"type":"Point"}
}