{
  "type": "Feature",
  "properties": {
    "iso:country":"US",
    "sg:address":"2828 N National Ave",
    "sg:city":"Springfield",
    "sg:classifiers":[
        {
            "category":"Health Services",
            "subcategory":"Clinic",
            "type":"Services"
        }
    ],
    "sg:phone":"+1 417 837 4087",
    "sg:postcode":"65803",
    "sg:province":"MO",
    "sg:tags":[
        "osteopathic"
    ],
    "wof:name":"Mckay Family Clinic",
    "wof:placetype":"venue"
},
  "geometry": {"coordinates":[-93.27445,37.248689],"type":"Point"}
}