{
  "type": "Feature",
  "properties": {
    "iso:country":"US",
    "sg:address":"201 Orchard St",
    "sg:city":"Alba",
    "sg:classifiers":[
        {
            "category":"Organizations",
            "subcategory":"Religious Organization",
            "type":"Services"
        }
    ],
    "sg:phone":"+1 417 525 4900",
    "sg:postcode":"64830",
    "sg:province":"MO",
    "sg:tags":[
        "church"
    ],
    "wof:name":"Pathways United Methodist Chr",
    "wof:placetype":"venue"
},
  "geometry": {"coordinates":[-94.41656500000001,37.238423],"type":"Point"}
}