{
  "type": "Feature",
  "properties": {
    "iso:country":"US",
    "sg:address":"9741 Gravois Rd",
    "sg:city":"St Louis",
    "sg:classifiers":[
        {
            "category":"Home & Garden",
            "subcategory":"Building Materials",
            "type":"Retail Goods"
        }
    ],
    "sg:phone":"+1 314 631 4334",
    "sg:postcode":"63123",
    "sg:province":"MO",
    "sg:tags":[
        "door"
    ],
    "wof:name":"Cardinal Door Inc",
    "wof:placetype":"venue"
},
  "geometry": {"coordinates":[-90.326767,38.551827],"type":"Point"}
}