{
  "type": "Feature",
  "properties": {
    "iso:country":"US",
    "sg:address":"1123 E Austin Blvd",
    "sg:city":"Nevada",
    "sg:classifiers":[
        {
            "category":"Autos & Motor Vehicles",
            "subcategory":"Automobile Sales",
            "type":"Retail Goods"
        },
        {
            "category":"Wholesale",
            "subcategory":"Motor Vehicles",
            "type":"Manufacturing & Wholesale Goods"
        }
    ],
    "sg:phone":"+1 417 667 5958",
    "sg:postcode":"64772",
    "sg:province":"MO",
    "sg:tags":[
        "car",
        "used",
        "dealer"
    ],
    "wof:name":"Yockey's Motors",
    "wof:placetype":"venue"
},
  "geometry": {"coordinates":[-94.3439,37.836864],"type":"Point"}
}