{
  "type": "Feature",
  "properties": {
    "iso:country":"US",
    "sg:address":"3837 Brooklyn Ave",
    "sg:city":"Kansas City",
    "sg:classifiers":[
        {
            "category":"Building & Trades",
            "subcategory":"Construction",
            "type":"Services"
        }
    ],
    "sg:phone":"+1 816 921 4857",
    "sg:postcode":"64109",
    "sg:province":"MO",
    "sg:tags":[
        "house"
    ],
    "wof:name":"Real Reconstruction Builders",
    "wof:placetype":"venue"
},
  "geometry": {"coordinates":[-94.557999,39.055784],"type":"Point"}
}