{
  "type": "Feature",
  "properties": {
    "iso:country":"US",
    "sg:address":"3154 State Hwy Ff",
    "sg:city":"Jackson",
    "sg:classifiers":[
        {
            "category":"Building & Trades",
            "subcategory":"Cleaning & Sanitation",
            "type":"Services"
        }
    ],
    "sg:phone":"+1 573 243 3985",
    "sg:postcode":"63755",
    "sg:province":"MO",
    "sg:tags":[
        "flue"
    ],
    "wof:name":"Kitchen Exhaust Cleaning",
    "wof:placetype":"venue"
},
  "geometry": {"coordinates":[-89.644702,37.448339],"type":"Point"}
}