{
  "type": "Feature",
  "properties": {
    "iso:country":"US",
    "sg:address":"616 E Karsch Blvd",
    "sg:city":"Farmington",
    "sg:classifiers":[
        {
            "category":"Retail",
            "subcategory":"Auto Rental",
            "type":"Services"
        }
    ],
    "sg:phone":"+1 573 756 5587",
    "sg:postcode":"63640",
    "sg:province":"MO",
    "sg:tags":[
        "truck"
    ],
    "wof:name":"Ryder",
    "wof:placetype":"venue"
},
  "geometry": {"coordinates":[-90.41363699999999,37.785982],"type":"Point"}
}