{
  "type": "Feature",
  "properties": {
    "iso:country":"US",
    "sg:address":"32706 Byler Rd",
    "sg:city":"Creighton",
    "sg:classifiers":[
        {
            "category":"Professional",
            "type":"Services"
        }
    ],
    "sg:phone":"+1 816 773 7084",
    "sg:postcode":"64739",
    "sg:province":"MO",
    "sg:tags":[
        "establishment"
    ],
    "wof:name":"JAM",
    "wof:placetype":"venue"
},
  "geometry": {"coordinates":[-94.144429,38.523133],"type":"Point"}
}