{
  "type": "Feature",
  "properties": {
    "iso:country":"US",
    "sg:address":"108 W State Highway 174",
    "sg:city":"Republic",
    "sg:classifiers":[
        {
            "category":"Education",
            "subcategory":"Special Training",
            "type":"Public Place"
        },
        {
            "category":"Shopping",
            "subcategory":"Crafts & Fabrics",
            "type":"Retail Goods"
        }
    ],
    "sg:phone":"+1 417 732 2076",
    "sg:postcode":"65738",
    "sg:province":"MO",
    "sg:tags":[
        "school",
        "instruction",
        "art",
        "supply"
    ],
    "sg:website":"http://www.dorothydent.com",
    "wof:name":"Painter's Corner Inc",
    "wof:placetype":"venue"
},
  "geometry": {"coordinates":[-93.480367,37.126427],"type":"Point"}
}