{
  "type": "Feature",
  "properties": {
    "iso:country":"US",
    "sg:address":"14161 Olive Blvd",
    "sg:city":"Chesterfield",
    "sg:classifiers":[
        {
            "category":"Retail",
            "subcategory":"Veterinary Services",
            "type":"Services"
        }
    ],
    "sg:phone":"+1 314 469 1700",
    "sg:postcode":"63017",
    "sg:province":"MO",
    "sg:tags":[
        "veterinarian"
    ],
    "wof:name":"Chesterfield Veterinary Center",
    "wof:placetype":"venue"
},
  "geometry": {"coordinates":[-90.52054099999999,38.679167],"type":"Point"}
}