{
  "type": "Feature",
  "properties": {
    "iso:country":"US",
    "sg:address":"4401 McClay Rd",
    "sg:city":"Saint Charles",
    "sg:classifiers":[
        {
            "category":"Real Estate",
            "subcategory":"Real Estate Agent",
            "type":"Services"
        }
    ],
    "sg:phone":"+1 636 441 1234",
    "sg:postcode":"63304",
    "sg:province":"MO",
    "wof:name":"Roy Powell Realty",
    "wof:placetype":"venue"
},
  "geometry": {"coordinates":[-90.611662,38.750948],"type":"Point"}
}