{
  "type": "Feature",
  "properties": {
    "iso:country":"US",
    "sg:address":"3595 Tenbrook Rd",
    "sg:city":"Arnold",
    "sg:classifiers":[
        {
            "category":"Home & Garden",
            "subcategory":"Garden Supply",
            "type":"Retail Goods"
        }
    ],
    "sg:phone":"+1 636 464 5928",
    "sg:postcode":"63010",
    "sg:province":"MO",
    "sg:tags":[
        "nursery",
        "center"
    ],
    "wof:name":"Miller's Ground Covers & Ctr",
    "wof:placetype":"venue"
},
  "geometry": {"coordinates":[-90.36251900000001,38.41193],"type":"Point"}
}