{
  "type": "Feature",
  "properties": {
    "iso:country":"US",
    "sg:address":"96 SE Hwy Pp",
    "sg:city":"Clinton",
    "sg:classifiers":[
        {
            "category":"Recreation",
            "subcategory":"Marina",
            "type":"Entertainment"
        }
    ],
    "sg:phone":"+1 660 477 3351",
    "sg:postcode":"64735",
    "sg:province":"MO",
    "sg:tags":[
        "storage",
        "boat"
    ],
    "wof:name":"Tebo Creek Bait Stop",
    "wof:placetype":"venue"
},
  "geometry": {"coordinates":[-93.544753,38.346382],"type":"Point"}
}