{
  "type": "Feature",
  "properties": {
    "iso:country":"US",
    "sg:address":"5800 Natural Bridge Ave",
    "sg:city":"Saint Louis",
    "sg:classifiers":[
        {
            "category":"Shopping",
            "subcategory":"Optical Goods",
            "type":"Retail Goods"
        }
    ],
    "sg:phone":"+1 314 389 2425",
    "sg:postcode":"63120",
    "sg:province":"MO",
    "sg:tags":[
        "optician",
        "eyewear"
    ],
    "wof:name":"Eye Fashion Factory",
    "wof:placetype":"venue"
},
  "geometry": {"coordinates":[-90.27179700000001,38.686501],"type":"Point"}
}