{
  "type": "Feature",
  "properties": {
    "addr:full":"2133 Zumbehl Rd St Charles MO 63303",
    "addr:housenumber":"2133",
    "addr:postcode":"63303",
    "addr:street":"Zumbehl Rd St Charles",
    "iso:country":"US",
    "sg:address":"2133 Zumbehl Rd",
    "sg:city":"St Charles",
    "sg:classifiers":[
        {
            "category":"Shopping",
            "subcategory":"Clothing, Apparel, & Fashions",
            "type":"Retail Goods"
        }
    ],
    "sg:phone":"+1 636 723 0381",
    "sg:postcode":"63303",
    "sg:province":"MO",
    "sg:website":"www.dressbarn.com",
    "wof:name":"Dress Barn",
    "wof:placetype":"venue"
},
  "geometry": {"coordinates":[-90.532045,38.790116],"type":"Point"}
}