{
  "type": "Feature",
  "properties": {
    "iso:country":"US",
    "sg:address":"9312 Olive Blvd",
    "sg:city":"Saint Louis",
    "sg:classifiers":[
        {
            "category":"Health Services",
            "subcategory":"Clinic",
            "type":"Services"
        }
    ],
    "sg:phone":"+1 314 991 3355",
    "sg:postcode":"63132",
    "sg:province":"MO",
    "sg:tags":[
        "personal",
        "home",
        "care"
    ],
    "wof:name":"Auxi Health",
    "wof:placetype":"venue"
},
  "geometry": {"coordinates":[-90.369319,38.674026],"type":"Point"}
}