{
  "type": "Feature",
  "properties": {
    "iso:country":"US",
    "sg:address":"814 N 19th St",
    "sg:city":"Saint Louis",
    "sg:classifiers":[
        {
            "category":"Real Estate",
            "subcategory":"Real Estate Operator",
            "type":"Services"
        }
    ],
    "sg:phone":"+1 314 588 1100",
    "sg:postcode":"63106",
    "sg:province":"MO",
    "sg:tags":[
        "apartment"
    ],
    "wof:name":"Franklin School Apartments",
    "wof:placetype":"venue"
},
  "geometry": {"coordinates":[-90.205488,38.635389],"type":"Point"}
}