{
  "type": "Feature",
  "properties": {
    "iso:country":"US",
    "sg:address":"1204 S 2nd St",
    "sg:city":"Clinton",
    "sg:classifiers":[
        {
            "category":"Autos & Motor Vehicles",
            "subcategory":"Automobile Sales",
            "type":"Retail Goods"
        },
        {
            "category":"Autos & Motor Vehicles",
            "subcategory":"Recreational Vehicle Sales",
            "type":"Retail Goods"
        }
    ],
    "sg:phone":"+1 660 885 3894",
    "sg:postcode":"64735",
    "sg:province":"MO",
    "sg:tags":[
        "vehicles-sports",
        "atv's",
        "all-terrain",
        "utility"
    ],
    "wof:name":"C & D Yamaha And Power Pdts",
    "wof:placetype":"venue"
},
  "geometry": {"coordinates":[-93.77581000000001,38.343571],"type":"Point"}
}