{
  "type": "Feature",
  "properties": {
    "iso:country":"US",
    "sg:address":"8127 Olive Blvd",
    "sg:city":"St Louis",
    "sg:classifiers":[
        {
            "category":"Restaurant",
            "type":"Food & Drink"
        }
    ],
    "sg:phone":"+1 314 994 1435",
    "sg:postcode":"63130",
    "sg:province":"MO",
    "wof:name":"Mc Donald's",
    "wof:placetype":"venue"
},
  "geometry": {"coordinates":[-90.34797500000001,38.673658],"type":"Point"}
}