{
  "type": "Feature",
  "properties": {
    "iso:country":"US",
    "sg:address":"1312 S Commercial St",
    "sg:city":"Harrisonville",
    "sg:classifiers":[
        {
            "category":"Professional",
            "type":"Services"
        }
    ],
    "sg:phone":"+1 816 380 7626",
    "sg:postcode":"64701",
    "sg:province":"MO",
    "wof:name":"Johnson Moving Svc",
    "wof:placetype":"venue"
},
  "geometry": {"coordinates":[-94.356239,38.646807],"type":"Point"}
}