{
  "type": "Feature",
  "properties": {
    "iso:country":"US",
    "sg:address":"801 Dunn Rd",
    "sg:city":"St Louis",
    "sg:classifiers":[
        {
            "category":"Retail",
            "subcategory":"Repair Shop",
            "type":"Services"
        }
    ],
    "sg:phone":"+1 314 355 1500",
    "sg:postcode":"63138",
    "sg:province":"MO",
    "sg:tags":[
        "related"
    ],
    "wof:name":"Airfield Improvement & Repair",
    "wof:placetype":"venue"
},
  "geometry": {"coordinates":[-90.19376699999999,38.767983],"type":"Point"}
}