{
  "type": "Feature",
  "properties": {
    "iso:country":"US",
    "sg:address":"10807 State Hwy 350",
    "sg:city":"Kansas City",
    "sg:classifiers":[
        {
            "category":"Autos & Motor Vehicles",
            "subcategory":"Automobile Sales",
            "type":"Retail Goods"
        }
    ],
    "sg:phone":"+1 816 356 2192",
    "sg:postcode":"64138",
    "sg:province":"MO",
    "sg:tags":[
        "provide",
        "car",
        "polishing",
        "used",
        "dealer"
    ],
    "wof:name":"Wilson Auto Sales & Car Polish",
    "wof:placetype":"venue"
},
  "geometry": {"coordinates":[-94.45708500000001,38.981052],"type":"Point"}
}