{
  "type": "Feature",
  "properties": {
    "iso:country":"US",
    "sg:address":"9248 Kentucky Rd",
    "sg:city":"Neosho",
    "sg:classifiers":[
        {
            "category":"Insurance",
            "subcategory":"Hazard Insurance",
            "type":"Services"
        }
    ],
    "sg:phone":"+1 417 451 0788",
    "sg:postcode":"64850",
    "sg:province":"MO",
    "sg:tags":[
        "commercial",
        "business"
    ],
    "wof:name":"Carter Insurance",
    "wof:placetype":"venue"
},
  "geometry": {"coordinates":[-94.478223,36.89571],"type":"Point"}
}