{
  "type": "Feature",
  "properties": {
    "iso:country":"US",
    "sg:address":"1610 Des Peres Rd",
    "sg:city":"St Louis",
    "sg:classifiers":[
        {
            "category":"Professional",
            "subcategory":"Employment Agencies",
            "type":"Services"
        }
    ],
    "sg:phone":"+1 314 822 9700",
    "sg:postcode":"63131",
    "sg:province":"MO",
    "sg:tags":[
        "opportunity"
    ],
    "sg:website":"www.apexsystemsinc.com",
    "wof:name":"Apex Systems",
    "wof:placetype":"venue"
},
  "geometry": {"coordinates":[-90.45244,38.617677],"type":"Point"}
}