{
  "type": "Feature",
  "properties": {
    "iso:country":"US",
    "sg:address":"145 Calwood Dr",
    "sg:city":"St Peters",
    "sg:classifiers":[
        {
            "category":"Building & Trades",
            "subcategory":"Plumbing",
            "type":"Services"
        }
    ],
    "sg:phone":"+1 636 397 8250",
    "sg:postcode":"63376",
    "sg:province":"MO",
    "sg:tags":[
        "heating",
        "contractor"
    ],
    "wof:name":"Dan Brokaw",
    "wof:placetype":"venue"
},
  "geometry": {"coordinates":[-90.657786,38.790352],"type":"Point"}
}