{
  "type": "Feature",
  "properties": {
    "iso:country":"US",
    "sg:address":"2233 N Belt Hwy",
    "sg:city":"Saint Joseph",
    "sg:classifiers":[
        {
            "category":"Health Services",
            "subcategory":"Chiropractor",
            "type":"Services"
        }
    ],
    "sg:phone":"+1 816 233 9445",
    "sg:postcode":"64506",
    "sg:province":"MO",
    "wof:name":"Slayton J W",
    "wof:placetype":"venue"
},
  "geometry": {"coordinates":[-94.803714,39.78528],"type":"Point"}
}