{
  "type": "Feature",
  "properties": {
    "iso:country":"US",
    "sg:address":"202 NW 2nd St",
    "sg:city":"Concordia",
    "sg:classifiers":[
        {
            "category":"Retail",
            "subcategory":"Car Wash",
            "type":"Services"
        }
    ],
    "sg:phone":"+1 660 463 4015",
    "sg:postcode":"64020",
    "sg:province":"MO",
    "sg:tags":[
        "carwash"
    ],
    "wof:name":"D & P Carwash",
    "wof:placetype":"venue"
},
  "geometry": {"coordinates":[-93.569664,38.9904],"type":"Point"}
}