{
  "type": "Feature",
  "properties": {
    "iso:country":"US",
    "sg:address":"15490 Co Rd 2030",
    "sg:city":"Rolla",
    "sg:classifiers":[
        {
            "category":"Building & Trades",
            "subcategory":"Construction",
            "type":"Services"
        }
    ],
    "sg:phone":"+1 573 368 0225",
    "sg:postcode":"65401",
    "sg:province":"MO",
    "wof:name":"Havens & Associates LLC",
    "wof:placetype":"venue"
},
  "geometry": {"coordinates":[-91.747472,38.029824],"type":"Point"}
}