{
  "type": "Feature",
  "properties": {
    "iso:country":"US",
    "sg:address":"506 Oakwood St",
    "sg:city":"Harrisonville",
    "sg:classifiers":[
        {
            "category":"Wholesale",
            "subcategory":"Computers",
            "type":"Manufacturing & Wholesale Goods"
        }
    ],
    "sg:phone":"+1 816 985 2102",
    "sg:postcode":"64701",
    "sg:province":"MO",
    "sg:tags":[
        "equipment"
    ],
    "wof:name":"Sos Computers, Inc.",
    "wof:placetype":"venue"
},
  "geometry": {"coordinates":[-94.347969,38.642612],"type":"Point"}
}