{
  "type": "Feature",
  "properties": {
    "iso:country":"US",
    "sg:address":"603 S Elm St",
    "sg:city":"Mountain Grove",
    "sg:classifiers":[
        {
            "category":"Building & Trades",
            "subcategory":"Construction",
            "type":"Services"
        }
    ],
    "sg:phone":"+1 417 926 6147",
    "sg:postcode":"65711",
    "sg:province":"MO",
    "sg:tags":[
        "excavation",
        "contractor"
    ],
    "wof:name":"Pro-Construction",
    "wof:placetype":"venue"
},
  "geometry": {"coordinates":[-92.263339,37.123613],"type":"Point"}
}