{
  "type": "Feature",
  "properties": {
    "iso:country":"US",
    "sg:address":"1075 E Terra Ln",
    "sg:city":"O Fallon",
    "sg:classifiers":[
        {
            "category":"Banks & Credit Unions",
            "subcategory":"Bank",
            "type":"Services"
        }
    ],
    "sg:phone":"+1 636 978 1075",
    "sg:postcode":"63366",
    "sg:province":"MO",
    "sg:tags":[
        "financing"
    ],
    "wof:name":"American General Finance Inc",
    "wof:placetype":"venue"
},
  "geometry": {"coordinates":[-90.681639,38.803348],"type":"Point"}
}