{
  "type": "Feature",
  "properties": {
    "iso:country":"US",
    "sg:address":"406 Zinnia Ln",
    "sg:city":"Kirbyville",
    "sg:classifiers":[
        {
            "category":"Manufacturing",
            "subcategory":"Buildings",
            "type":"Manufacturing & Wholesale Goods"
        }
    ],
    "sg:phone":"+1 417 336 9711",
    "sg:postcode":"65679",
    "sg:province":"MO",
    "sg:tags":[
        "home",
        "builder"
    ],
    "wof:name":"Dwight B Shoopman",
    "wof:placetype":"venue"
},
  "geometry": {"coordinates":[-93.14954,36.6098],"type":"Point"}
}