{
  "type": "Feature",
  "properties": {
    "addr:full":"3896 Vogel Rd Arnold MO 63010",
    "addr:housenumber":"3896",
    "addr:postcode":"63010",
    "addr:street":"Vogel Rd",
    "iso:country":"US",
    "sg:address":"3896 Vogel Rd",
    "sg:city":"Arnold",
    "sg:classifiers":[
        {
            "category":"Retail",
            "subcategory":"Auto Repair",
            "type":"Services"
        }
    ],
    "sg:phone":"+1 636 282 0418",
    "sg:postcode":"63010",
    "sg:province":"MO",
    "sg:tags":[
        "automobile",
        "lubrication"
    ],
    "wof:name":"Valvoline Instant Oil Change",
    "wof:placetype":"venue"
},
  "geometry": {"coordinates":[-90.39115,38.416069],"type":"Point"}
}