{
  "type": "Feature",
  "properties": {
    "iso:country":"US",
    "sg:address":"937 Peace Haven Dr",
    "sg:city":"Saint Louis",
    "sg:classifiers":[
        {
            "category":"Real Estate",
            "subcategory":"Real Estate Agent",
            "type":"Services"
        }
    ],
    "sg:phone":"+1 314 487 9144",
    "sg:postcode":"63125",
    "sg:province":"MO",
    "wof:name":"Nestegg Enterprises",
    "wof:placetype":"venue"
},
  "geometry": {"coordinates":[-90.313315,38.50355],"type":"Point"}
}