{
  "type": "Feature",
  "properties": {
    "addr:full":"1800 Central St Kansas City MO 64108",
    "addr:housenumber":"1800",
    "addr:postcode":"64108",
    "addr:street":"Central St",
    "iso:country":"US",
    "sg:address":"1800 Central St",
    "sg:city":"Kansas City",
    "sg:classifiers":[
        {
            "category":"Professional",
            "subcategory":"Advertising",
            "type":"Services"
        }
    ],
    "sg:phone":"+1 816 421 4242",
    "sg:postcode":"64108",
    "sg:province":"MO",
    "sg:tags":[
        "agency"
    ],
    "wof:name":"Kellyrussell Advertising Inc",
    "wof:placetype":"venue"
},
  "geometry": {"coordinates":[-94.58743200000001,39.091006],"type":"Point"}
}