{
  "type": "Feature",
  "properties": {
    "iso:country":"US",
    "sg:address":"205 W Walnut St",
    "sg:city":"Springfield",
    "sg:classifiers":[
        {
            "category":"Health Services",
            "subcategory":"Health Practitioner",
            "type":"Services"
        }
    ],
    "sg:phone":"+1 417 831 5927",
    "sg:postcode":"65806",
    "sg:province":"MO",
    "wof:name":"Tranqlity Island Mssage Thrapy",
    "wof:placetype":"venue"
},
  "geometry": {"coordinates":[-93.293256,37.207174],"type":"Point"}
}