{
  "type": "Feature",
  "properties": {
    "iso:country":"US",
    "sg:address":"106 W McKinley St",
    "sg:city":"Poplar Bluff",
    "sg:classifiers":[
        {
            "category":"Personal",
            "subcategory":"Beauty Salon",
            "type":"Services"
        }
    ],
    "sg:phone":"+1 573 785 8455",
    "sg:postcode":"63901",
    "sg:province":"MO",
    "sg:tags":[
        "shop"
    ],
    "wof:name":"Pampered Lady Beauty Salon",
    "wof:placetype":"venue"
},
  "geometry": {"coordinates":[-90.39274500000001,36.744096],"type":"Point"}
}