{
  "type": "Feature",
  "properties": {
    "iso:country":"US",
    "sg:address":"1759 Scherer Pkwy",
    "sg:city":"Saint Charles",
    "sg:classifiers":[
        {
            "category":"Organizations",
            "subcategory":"Labor Organization",
            "type":"Services"
        }
    ],
    "sg:phone":"+1 636 281 4666",
    "sg:postcode":"63303",
    "sg:province":"MO",
    "wof:name":"Union Needletraders Local 1170",
    "wof:placetype":"venue"
},
  "geometry": {"coordinates":[-90.523183,38.765005],"type":"Point"}
}