{
  "type": "Feature",
  "properties": {
    "iso:country":"US",
    "sg:address":"4547 Green Park Rd",
    "sg:city":"St Louis",
    "sg:classifiers":[
        {
            "category":"Building & Trades",
            "subcategory":"Construction",
            "type":"Services"
        }
    ],
    "sg:phone":"+1 314 845 1554",
    "sg:postcode":"63123",
    "sg:province":"MO",
    "sg:tags":[
        "hanging",
        "painter",
        "contractor"
    ],
    "wof:name":"Runge Painting Company Inc",
    "wof:placetype":"venue"
},
  "geometry": {"coordinates":[-90.32205500000001,38.524201],"type":"Point"}
}