{
  "type": "Feature",
  "properties": {
    "iso:country":"US",
    "sg:address":"6301 NE Upper Wood Rd",
    "sg:city":"Lees Summit",
    "sg:classifiers":[
        {
            "category":"Professional",
            "subcategory":"Advertising",
            "type":"Services"
        }
    ],
    "sg:phone":"+1 816 795 1080",
    "sg:postcode":"64064",
    "sg:province":"MO",
    "sg:tags":[
        "agency"
    ],
    "wof:name":"Worth Smith Advertising",
    "wof:placetype":"venue"
},
  "geometry": {"coordinates":[-94.353044,39.02365],"type":"Point"}
}