{
  "type": "Feature",
  "properties": {
    "iso:country":"US",
    "sg:address":"238 State Hwy Y",
    "sg:city":"Jackson",
    "sg:classifiers":[
        {
            "category":"Building & Trades",
            "subcategory":"Construction",
            "type":"Services"
        }
    ],
    "sg:phone":"+1 573 243 3133",
    "sg:postcode":"63755",
    "sg:province":"MO",
    "sg:tags":[
        "television",
        "telephone",
        "cable",
        "contractor"
    ],
    "wof:name":"Eastern Missouri Industries",
    "wof:placetype":"venue"
},
  "geometry": {"coordinates":[-89.64880599999999,37.412808],"type":"Point"}
}