{
  "type": "Feature",
  "properties": {
    "iso:country":"US",
    "sg:address":"5708 King Hill Ave",
    "sg:city":"St Joseph",
    "sg:classifiers":[
        {
            "category":"Organizations",
            "subcategory":"Religious Organization",
            "type":"Services"
        }
    ],
    "sg:phone":"+1 816 238 1341",
    "sg:postcode":"64504",
    "sg:province":"MO",
    "sg:tags":[
        "church"
    ],
    "wof:name":"King Hill Baptist Church",
    "wof:placetype":"venue"
},
  "geometry": {"coordinates":[-94.86228800000001,39.7166],"type":"Point"}
}