{
  "type": "Feature",
  "properties": {
    "iso:country":"US",
    "sg:address":"2157 N Prospect Ave",
    "sg:city":"Springfield",
    "sg:classifiers":[
        {
            "category":"Organizations",
            "subcategory":"Religious Organization",
            "type":"Services"
        }
    ],
    "sg:phone":"+1 417 864 4338",
    "sg:postcode":"65803",
    "sg:province":"MO",
    "sg:tags":[
        "church"
    ],
    "wof:name":"Dayspring Worship Ctr",
    "wof:placetype":"venue"
},
  "geometry": {"coordinates":[-93.27258999999999,37.235762],"type":"Point"}
}