{
  "type": "Feature",
  "properties": {
    "iso:country":"US",
    "sg:address":"2301 Maguire Blvd",
    "sg:city":"Columbia",
    "sg:classifiers":[
        {
            "category":"Professional",
            "subcategory":"Computer Services",
            "type":"Services"
        }
    ],
    "sg:phone":"+1 573 874 0834",
    "sg:postcode":"65201",
    "sg:province":"MO",
    "sg:tags":[
        "information",
        "retrieval"
    ],
    "wof:name":"Carfax Inc",
    "wof:placetype":"venue"
},
  "geometry": {"coordinates":[-92.28985,38.92611],"type":"Point"}
}