{
  "type": "Feature",
  "properties": {
    "iso:country":"US",
    "sg:address":"337 E Kearney St",
    "sg:city":"Springfield",
    "sg:classifiers":[
        {
            "category":"Restaurant",
            "type":"Food & Drink"
        }
    ],
    "sg:phone":"+1 417 831 4133",
    "sg:postcode":"65803",
    "sg:province":"MO",
    "sg:tags":[
        "eating"
    ],
    "wof:name":"Lotus Inn",
    "wof:placetype":"venue"
},
  "geometry": {"coordinates":[-93.289179,37.240574],"type":"Point"}
}