{
  "type": "Feature",
  "properties": {
    "iso:country":"US",
    "sg:address":"3219 Paseo Blvd",
    "sg:city":"Kansas City",
    "sg:classifiers":[
        {
            "category":"Building & Trades",
            "subcategory":"Construction",
            "type":"Services"
        }
    ],
    "sg:phone":"+1 816 861 0059",
    "sg:postcode":"64109",
    "sg:province":"MO",
    "sg:tags":[
        "residential"
    ],
    "wof:name":"Alvarez Construction",
    "wof:placetype":"venue"
},
  "geometry": {"coordinates":[-94.56676899999999,39.067897],"type":"Point"}
}