{
  "type": "Feature",
  "properties": {
    "iso:country":"US",
    "sg:address":"4435 Harrison St",
    "sg:city":"Kansas City",
    "sg:classifiers":[
        {
            "category":"Home & Garden",
            "subcategory":"Building Materials",
            "type":"Retail Goods"
        }
    ],
    "sg:phone":"+1 816 960 1112",
    "sg:postcode":"64110",
    "sg:province":"MO",
    "sg:tags":[
        "screen",
        "window"
    ],
    "wof:name":"Casey Screen",
    "wof:placetype":"venue"
},
  "geometry": {"coordinates":[-94.57384,39.045962],"type":"Point"}
}