{
  "type": "Feature",
  "properties": {
    "iso:country":"US",
    "sg:address":"2837 Raritan Dr",
    "sg:city":"Saint Louis",
    "sg:classifiers":[
        {
            "category":"Insurance",
            "subcategory":"Insurance Agent",
            "type":"Services"
        }
    ],
    "sg:phone":"+1 314 962 1014",
    "sg:postcode":"63119",
    "sg:province":"MO",
    "sg:tags":[
        "broker"
    ],
    "wof:name":"Brokers Financial Trust",
    "wof:placetype":"venue"
},
  "geometry": {"coordinates":[-90.3604,38.609497],"type":"Point"}
}