{
  "type": "Feature",
  "properties": {
    "iso:country":"US",
    "sg:address":"2 Clayton Ter",
    "sg:city":"St Louis",
    "sg:classifiers":[
        {
            "category":"Building & Trades",
            "subcategory":"Construction",
            "type":"Services"
        }
    ],
    "sg:phone":"+1 314 692 2500",
    "sg:postcode":"63131",
    "sg:province":"MO",
    "sg:tags":[
        "house",
        "builder",
        "home"
    ],
    "wof:name":"American Dream Properties Inc",
    "wof:placetype":"venue"
},
  "geometry": {"coordinates":[-90.407876,38.636947],"type":"Point"}
}