{
  "type": "Feature",
  "properties": {
    "iso:country":"US",
    "sg:address":"1403 E 4th St",
    "sg:city":"Joplin",
    "sg:classifiers":[
        {
            "category":"Wholesale",
            "subcategory":"Hardware",
            "type":"Manufacturing & Wholesale Goods"
        }
    ],
    "sg:phone":"+1 417 782 0820",
    "sg:postcode":"64801",
    "sg:province":"MO",
    "sg:tags":[
        "plumbing",
        "fixture",
        "supply"
    ],
    "wof:name":"Locke Supply Co",
    "wof:placetype":"venue"
},
  "geometry": {"coordinates":[-94.497023,37.087485],"type":"Point"}
}