{
  "type": "Feature",
  "properties": {
    "iso:country":"US",
    "sg:address":"412 S Cedar St",
    "sg:city":"Gallatin",
    "sg:classifiers":[
        {
            "category":"Insurance",
            "subcategory":"Hazard Insurance",
            "type":"Services"
        }
    ],
    "sg:phone":"+1 660 663 3392",
    "sg:postcode":"64640",
    "sg:province":"MO",
    "wof:name":"Mfa Oil Co. Whitney Kenny Agent",
    "wof:placetype":"venue"
},
  "geometry": {"coordinates":[-93.966077,39.911517],"type":"Point"}
}