{
  "type": "Feature",
  "properties": {
    "iso:country":"US",
    "sg:address":"51 Sunset Dr",
    "sg:city":"Tunas",
    "sg:classifiers":[
        {
            "category":"Home & Garden",
            "subcategory":"Furniture",
            "type":"Retail Goods"
        }
    ],
    "sg:phone":"+1 417 993 4349",
    "sg:postcode":"65764",
    "sg:province":"MO",
    "sg:tags":[
        "store"
    ],
    "wof:name":"Country Lane Furniture Shop",
    "wof:placetype":"venue"
},
  "geometry": {"coordinates":[-92.972104,37.851197],"type":"Point"}
}