{
  "type": "Feature",
  "properties": {
    "iso:country":"US",
    "sg:address":"3200 Washington Ave",
    "sg:city":"St Louis",
    "sg:classifiers":[
        {
            "category":"Organizations",
            "subcategory":"Religious Organization",
            "type":"Services"
        }
    ],
    "sg:phone":"+1 314 533 8763",
    "sg:postcode":"63103",
    "sg:province":"MO",
    "sg:tags":[
        "church"
    ],
    "sg:website":"www.washingtontabmbc.org",
    "wof:name":"Washington Tabernacle Baptist",
    "wof:placetype":"venue"
},
  "geometry": {"coordinates":[-90.226219,38.637682],"type":"Point"}
}