{
  "type": "Feature",
  "properties": {
    "iso:country":"US",
    "sg:address":"222 S. Central Ave. Suite 400",
    "sg:city":"Clayton",
    "sg:classifiers":[
        {
            "category":"Professional",
            "subcategory":"Computer Services",
            "type":"Services"
        }
    ],
    "sg:phone":"+1 314 880 2900",
    "sg:postcode":"63105",
    "sg:province":"MO",
    "sg:website":"http://www.globalvelocity.com/",
    "wof:name":"Global Velocity",
    "wof:placetype":"venue"
},
  "geometry": {"coordinates":[-90.338752,38.646221],"type":"Point"}
}