{
  "type": "Feature",
  "properties": {
    "iso:country":"US",
    "sg:address":"1803 W Farm Rd 102",
    "sg:city":"Springfield",
    "sg:classifiers":[
        {
            "category":"Personal",
            "subcategory":"Beauty Salon",
            "type":"Services"
        }
    ],
    "sg:phone":"+1 417 833 8558",
    "sg:postcode":"65803",
    "sg:province":"MO",
    "sg:tags":[
        "shop"
    ],
    "wof:name":"A New Look Hair & Nail Salon",
    "wof:placetype":"venue"
},
  "geometry": {"coordinates":[-93.319774,37.263083],"type":"Point"}
}