{
  "type": "Feature",
  "properties": {
    "iso:country":"US",
    "sg:address":"133 E Jefferson St",
    "sg:city":"Clinton",
    "sg:classifiers":[
        {
            "category":"Shopping",
            "subcategory":"Computers & Home Electronics",
            "type":"Retail Goods"
        }
    ],
    "sg:phone":"+1 660 890 2541",
    "sg:postcode":"64735",
    "sg:province":"MO",
    "sg:tags":[
        "software"
    ],
    "wof:name":"Dynamic Computer Wurx",
    "wof:placetype":"venue"
},
  "geometry": {"coordinates":[-93.775661,38.369467],"type":"Point"}
}