{
  "type": "Feature",
  "properties": {
    "iso:country":"US",
    "sg:address":"2180 Hilltop Dr",
    "sg:city":"Warsaw",
    "sg:classifiers":[
        {
            "category":"Health Services",
            "subcategory":"Doctor",
            "type":"Services"
        },
        {
            "category":"Health Services",
            "subcategory":"Clinic",
            "type":"Services"
        }
    ],
    "sg:phone":"+1 660 438 6800",
    "sg:postcode":"65355",
    "sg:province":"MO",
    "sg:tags":[
        "physician",
        "family",
        "medical",
        "practice",
        "surgeons",
        "medicine"
    ],
    "wof:name":"Eye Clinic",
    "wof:placetype":"venue"
},
  "geometry": {"coordinates":[-93.367937,38.256053],"type":"Point"}
}