{
  "type": "Feature",
  "properties": {
    "iso:country":"US",
    "sg:address":"621 W Woodbine Ave",
    "sg:city":"St Louis",
    "sg:classifiers":[
        {
            "category":"Autos & Motor Vehicles",
            "subcategory":"Fuel & Gas Station",
            "type":"Retail Goods"
        }
    ],
    "sg:phone":"+1 314 822 0065",
    "sg:postcode":"63122",
    "sg:province":"MO",
    "sg:tags":[
        "oil"
    ],
    "wof:name":"TMP Enterprises Citgo",
    "wof:placetype":"venue"
},
  "geometry": {"coordinates":[-90.418598,38.574372],"type":"Point"}
}