{
  "type": "Feature",
  "properties": {
    "iso:country":"US",
    "sg:address":"3000 S Westwood Blvd",
    "sg:city":"Poplar Bluff",
    "sg:classifiers":[
        {
            "category":"Home & Garden",
            "subcategory":"Carpets & Floor Coverings",
            "type":"Retail Goods"
        }
    ],
    "sg:phone":"+1 573 785 5554",
    "sg:postcode":"63901",
    "sg:province":"MO",
    "sg:tags":[
        "dealer",
        "rug"
    ],
    "wof:name":"Semo Discount Carpet & Floor",
    "wof:placetype":"venue"
},
  "geometry": {"coordinates":[-90.432011,36.733699],"type":"Point"}
}