{
  "type": "Feature",
  "properties": {
    "iso:country":"US",
    "sg:address":"2219 S Garrison Ave",
    "sg:city":"Carthage",
    "sg:classifiers":[
        {
            "category":"Autos & Motor Vehicles",
            "subcategory":"Automobile Sales",
            "type":"Retail Goods"
        }
    ],
    "sg:phone":"+1 417 358 4878",
    "sg:postcode":"64836",
    "sg:province":"MO",
    "sg:tags":[
        "used"
    ],
    "wof:name":"Imperial Motor Co",
    "wof:placetype":"venue"
},
  "geometry": {"coordinates":[-94.31482099999999,37.15076],"type":"Point"}
}