{
  "type": "Feature",
  "properties": {
    "iso:country":"US",
    "sg:address":"2806 Cass Ave",
    "sg:city":"St Louis",
    "sg:classifiers":[
        {
            "category":"Organizations",
            "subcategory":"Religious Organization",
            "type":"Services"
        }
    ],
    "sg:phone":"+1 314 531 5211",
    "sg:postcode":"63106",
    "sg:province":"MO",
    "sg:tags":[
        "church"
    ],
    "wof:name":"Renaissance Temple",
    "wof:placetype":"venue"
},
  "geometry": {"coordinates":[-90.217573,38.645985],"type":"Point"}
}