{
  "type": "Feature",
  "properties": {
    "iso:country":"US",
    "sg:address":"1502 Marsh Ave",
    "sg:city":"Kansas City",
    "sg:classifiers":[
        {
            "category":"Autos & Motor Vehicles",
            "subcategory":"Automobile Sales",
            "type":"Retail Goods"
        }
    ],
    "sg:phone":"+1 816 254 0088",
    "sg:postcode":"64126",
    "sg:province":"MO",
    "sg:tags":[
        "used"
    ],
    "wof:name":"Truman Road Auto Sales",
    "wof:placetype":"venue"
},
  "geometry": {"coordinates":[-94.48617299999999,39.091664],"type":"Point"}
}