{
  "type": "Feature",
  "properties": {
    "addr:full":"12414 US Hwy 71 Grandview MO 64030",
    "addr:housenumber":"12414",
    "addr:postcode":"64030",
    "addr:street":"Us Hwy 71",
    "iso:country":"US",
    "sg:address":"12414 US Hwy 71",
    "sg:city":"Grandview",
    "sg:classifiers":[
        {
            "category":"Home & Garden",
            "subcategory":"Building Materials",
            "type":"Retail Goods"
        }
    ],
    "sg:phone":"+1 816 965 8419",
    "sg:postcode":"64030",
    "sg:province":"MO",
    "sg:tags":[
        "paint"
    ],
    "wof:name":"ICI Paints",
    "wof:placetype":"venue"
},
  "geometry": {"coordinates":[-94.52472,38.898135],"type":"Point"}
}