{
  "type": "Feature",
  "properties": {
    "iso:country":"US",
    "sg:address":"3302 W Broadway",
    "sg:city":"Columbia",
    "sg:classifiers":[
        {
            "category":"Retail",
            "subcategory":"Laundry & Dry Cleaning",
            "type":"Services"
        }
    ],
    "sg:phone":"+1 573 445 5657",
    "sg:postcode":"65203",
    "sg:province":"MO",
    "sg:tags":[
        "cleaners"
    ],
    "wof:name":"Sudden Service Cleaners",
    "wof:placetype":"venue"
},
  "geometry": {"coordinates":[-92.385002,38.95498],"type":"Point"}
}