{
  "type": "Feature",
  "properties": {
    "iso:country":"US",
    "sg:address":"1000 S 9th St",
    "sg:city":"Saint Joseph",
    "sg:classifiers":[
        {
            "category":"Food & Beverages",
            "subcategory":"Groceries & Convenience Stores",
            "type":"Retail Goods"
        }
    ],
    "sg:phone":"+1 816 671 4140",
    "sg:postcode":"64503",
    "sg:province":"MO",
    "wof:name":"Food Service",
    "wof:placetype":"venue"
},
  "geometry": {"coordinates":[-94.849333,39.757191],"type":"Point"}
}