{
  "type": "Feature",
  "properties": {
    "iso:country":"US",
    "sg:address":"6201 NW 48 St",
    "sg:city":"Kansas City",
    "sg:classifiers":[
        {
            "category":"Health Services",
            "subcategory":"Clinic",
            "type":"Services"
        }
    ],
    "sg:phone":"+1 816 505 2026",
    "sg:postcode":"64151",
    "sg:province":"MO",
    "sg:tags":[
        "home",
        "agency",
        "employment",
        "care"
    ],
    "sg:website":"www.conceptsincare.com",
    "wof:name":"Concepts In Care Inc",
    "wof:placetype":"venue"
},
  "geometry": {"coordinates":[-94.65409099999999,39.182407],"type":"Point"}
}