{
  "type": "Feature",
  "properties": {
    "iso:country":"US",
    "sg:address":"701 NW College Dr",
    "sg:city":"Saint Joseph",
    "sg:classifiers":[
        {
            "category":"Government",
            "subcategory":"Office",
            "type":"Public Place"
        }
    ],
    "sg:phone":"+1 816 271 3100",
    "sg:postcode":"64507",
    "sg:province":"MO",
    "sg:tags":[
        "conservation"
    ],
    "wof:name":"Northwest Regional Office",
    "wof:placetype":"venue"
},
  "geometry": {"coordinates":[-94.785218,39.759831],"type":"Point"}
}