{
  "type": "Feature",
  "properties": {
    "iso:country":"US",
    "sg:address":"11 Balcon Ests",
    "sg:city":"Saint Louis",
    "sg:classifiers":[
        {
            "category":"Professional",
            "subcategory":"Business Services",
            "type":"Services"
        }
    ],
    "sg:phone":"+1 314 434 3406",
    "sg:postcode":"63141",
    "sg:province":"MO",
    "sg:tags":[
        "furniture"
    ],
    "wof:name":"Jsi",
    "wof:placetype":"venue"
},
  "geometry": {"coordinates":[-90.45360700000001,38.643088],"type":"Point"}
}