{
  "type": "Feature",
  "properties": {
    "iso:country":"US",
    "sg:address":"24943 Demott Dr",
    "sg:city":"Webb City",
    "sg:classifiers":[
        {
            "category":"Professional",
            "subcategory":"Management & Consulting",
            "type":"Services"
        }
    ],
    "sg:phone":"+1 417 782 3515",
    "sg:postcode":"64870",
    "sg:province":"MO",
    "sg:tags":[
        "development",
        "economic",
        "agency"
    ],
    "wof:name":"Harry S Truman Coordinating",
    "wof:placetype":"venue"
},
  "geometry": {"coordinates":[-94.510682,37.142776],"type":"Point"}
}