{
  "type": "Feature",
  "properties": {
    "iso:country":"US",
    "sg:address":"9966 Odessa Cemetery Rd",
    "sg:city":"Odessa",
    "sg:classifiers":[
        {
            "category":"Building & Trades",
            "subcategory":"Plumbing",
            "type":"Services"
        }
    ],
    "sg:phone":"+1 816 633 8264",
    "sg:postcode":"64076",
    "sg:province":"MO",
    "sg:tags":[
        "plumbing",
        "contractor"
    ],
    "wof:name":"Direct Plumbing",
    "wof:placetype":"venue"
},
  "geometry": {"coordinates":[-93.92538999999999,39.00606],"type":"Point"}
}