{
  "type": "Feature",
  "properties": {
    "addr:full":"6301 N Michigan Ave Kansas City MO 64118",
    "addr:housenumber":"6301",
    "addr:postcode":"64118",
    "addr:street":"N Michigan Ave",
    "iso:country":"US",
    "sg:address":"6301 N Michigan Ave",
    "sg:city":"Kansas City",
    "sg:classifiers":[
        {
            "category":"Education",
            "subcategory":"School",
            "type":"Public Place"
        }
    ],
    "sg:phone":"+1 816 453 2120",
    "sg:postcode":"64118",
    "sg:province":"MO",
    "wof:name":"Meadowbrook Elementary School",
    "wof:placetype":"venue"
},
  "geometry": {"coordinates":[-94.55748800000001,39.207376],"type":"Point"}
}