{
  "type": "Feature",
  "properties": {
    "iso:country":"US",
    "sg:address":"104 S Maple St",
    "sg:city":"Cole Camp",
    "sg:classifiers":[
        {
            "category":"Restaurant",
            "type":"Food & Drink"
        }
    ],
    "sg:phone":"+1 660 668 4777",
    "sg:postcode":"65325",
    "sg:province":"MO",
    "sg:tags":[
        "pizza"
    ],
    "wof:name":"Calgaro's Family Pizzeria",
    "wof:placetype":"venue"
},
  "geometry": {"coordinates":[-93.20263,38.460003],"type":"Point"}
}