{
  "type": "Feature",
  "properties": {
    "iso:country":"US",
    "sg:address":"69 Wildwood Ter",
    "sg:city":"Sullivan",
    "sg:classifiers":[
        {
            "category":"Building & Trades",
            "subcategory":"Construction",
            "type":"Services"
        }
    ],
    "sg:phone":"+1 573 860 2131",
    "sg:postcode":"63080",
    "sg:province":"MO",
    "sg:tags":[
        "contractor"
    ],
    "wof:name":"Brads Roofing",
    "wof:placetype":"venue"
},
  "geometry": {"coordinates":[-91.148977,38.234802],"type":"Point"}
}