{
  "type": "Feature",
  "properties": {
    "iso:country":"US",
    "sg:address":"111 N Main St",
    "sg:city":"Auxvasse",
    "sg:classifiers":[
        {
            "category":"Professional",
            "subcategory":"Business Services",
            "type":"Services"
        }
    ],
    "sg:phone":"+1 573 386 2228",
    "sg:postcode":"65231",
    "sg:province":"MO",
    "sg:tags":[
        "auctioneer"
    ],
    "wof:name":"Graham Auction Service",
    "wof:placetype":"venue"
},
  "geometry": {"coordinates":[-91.89670599999999,39.029114],"type":"Point"}
}