{
  "type": "Feature",
  "properties": {
    "iso:country":"US",
    "sg:address":"375 NW 20 Ln",
    "sg:city":"Lamar",
    "sg:phone":"+1 417 682 2821",
    "sg:postcode":"64759",
    "sg:province":"MO",
    "sg:tags":[
        "farm",
        "corn",
        "soybean"
    ],
    "wof:name":"Donald Crockett",
    "wof:placetype":"venue"
},
  "geometry": {"coordinates":[-94.32923099999999,37.620927],"type":"Point"}
}