{
  "type": "Feature",
  "properties": {
    "iso:country":"US",
    "sg:address":"935 Keeneland Rd",
    "sg:city":"Florissant",
    "sg:classifiers":[
        {
            "category":"Building & Trades",
            "subcategory":"Plumbing",
            "type":"Services"
        }
    ],
    "sg:phone":"+1 314 537 7407",
    "sg:postcode":"63034",
    "sg:province":"MO",
    "sg:tags":[
        "plumber",
        "industrial",
        "contractors-commercial"
    ],
    "sg:website":"http://www.soldiersplumbing.com",
    "wof:name":"Soldiers Plumbing, Inc",
    "wof:placetype":"venue"
},
  "geometry": {"coordinates":[-90.30352000000001,38.835548],"type":"Point"}
}