{
  "type": "Feature",
  "properties": {
    "iso:country":"US",
    "sg:address":"5220 Spring Trail Dr",
    "sg:city":"Florissant",
    "sg:classifiers":[
        {
            "category":"Shopping",
            "subcategory":"Tobacco",
            "type":"Retail Goods"
        }
    ],
    "sg:phone":"+1 314 741 3300",
    "sg:postcode":"63033",
    "sg:province":"MO",
    "sg:tags":[
        "product"
    ],
    "wof:name":"Exclusive Cigars",
    "wof:placetype":"venue"
},
  "geometry": {"coordinates":[-90.25494399999999,38.801078],"type":"Point"}
}