{
  "type": "Feature",
  "properties": {
    "iso:country":"US",
    "sg:address":"11595 County Road 395",
    "sg:city":"Hartsburg",
    "sg:classifiers":[
        {
            "category":"Building & Trades",
            "subcategory":"Construction",
            "type":"Services"
        }
    ],
    "sg:phone":"+1 573 635 0141",
    "sg:postcode":"65039",
    "sg:province":"MO",
    "sg:tags":[
        "roofing",
        "contractor"
    ],
    "sg:website":"http://www.wcrfg.com",
    "wof:name":"Weathercraft Inc",
    "wof:placetype":"venue"
},
  "geometry": {"coordinates":[-92.200011,38.642864],"type":"Point"}
}