{
  "type": "Feature",
  "properties": {
    "iso:country":"US",
    "sg:address":"1501 E Ashland St",
    "sg:city":"Nevada",
    "sg:classifiers":[
        {
            "category":"Building & Trades",
            "subcategory":"Landscaping Services",
            "type":"Services"
        }
    ],
    "sg:phone":"+1 417 667 5953",
    "sg:postcode":"64772",
    "sg:province":"MO",
    "sg:tags":[
        "aged",
        "homes-institutional"
    ],
    "wof:name":"Maple Assisted Living & Memory Care Of Nevada",
    "wof:placetype":"venue"
},
  "geometry": {"coordinates":[-94.338644,37.844064],"type":"Point"}
}