{
  "type": "Feature",
  "properties": {
    "iso:country":"US",
    "sg:address":"9566 Indian Meadows Dr",
    "sg:city":"Saint Louis",
    "sg:classifiers":[
        {
            "category":"Professional",
            "subcategory":"Business Services",
            "type":"Services"
        }
    ],
    "sg:phone":"+1 314 432 3078",
    "sg:postcode":"63132",
    "sg:province":"MO",
    "sg:tags":[
        "apparel",
        "design"
    ],
    "wof:name":"Sweat Sports Inc",
    "wof:placetype":"venue"
},
  "geometry": {"coordinates":[-90.38288300000001,38.67718],"type":"Point"}
}