{
  "type": "Feature",
  "properties": {
    "iso:country":"US",
    "sg:address":"777 Schaper Rd",
    "sg:city":"Foristell",
    "sg:classifiers":[
        {
            "category":"Food & Beverages",
            "subcategory":"Farmers Market",
            "type":"Retail Goods"
        }
    ],
    "sg:phone":"+1 314 302 8705",
    "sg:postcode":"63348",
    "sg:province":"MO",
    "sg:tags":[
        "vegetable",
        "fruit",
        "shipper",
        "grower"
    ],
    "wof:name":"Zaathof Company, The",
    "wof:placetype":"venue"
},
  "geometry": {"coordinates":[-90.938682,38.787802],"type":"Point"}
}