{
  "type": "Feature",
  "properties": {
    "iso:country":"US",
    "sg:address":"803 Keen St",
    "sg:city":"Raymore",
    "sg:classifiers":[
        {
            "category":"Building & Trades",
            "subcategory":"Construction",
            "type":"Services"
        }
    ],
    "sg:phone":"+1 816 318 8230",
    "sg:postcode":"64083",
    "sg:province":"MO",
    "sg:tags":[
        "home",
        "builder"
    ],
    "wof:name":"Higgins Building Co",
    "wof:placetype":"venue"
},
  "geometry": {"coordinates":[-94.442222,38.806587],"type":"Point"}
}