{
  "type": "Feature",
  "properties": {
    "iso:country":"US",
    "sg:address":"513 Jefferson St",
    "sg:city":"Washington",
    "sg:classifiers":[
        {
            "category":"Home & Garden",
            "subcategory":"Household Appliances",
            "type":"Retail Goods"
        },
        {
            "category":"Retail",
            "subcategory":"Repair Shop",
            "type":"Services"
        }
    ],
    "sg:phone":"+1 636 239 3795",
    "sg:postcode":"63090",
    "sg:province":"MO",
    "sg:tags":[
        "equipment",
        "cleaners-repair",
        "system",
        "cleaners-household-dealers",
        "vacuum"
    ],
    "wof:name":"Franklin County Vacuums",
    "wof:placetype":"venue"
},
  "geometry": {"coordinates":[-91.013245,38.556319],"type":"Point"}
}