{
  "type": "Feature",
  "properties": {
    "iso:country":"US",
    "sg:address":"7445 Cornell Ave",
    "sg:city":"Saint Louis",
    "sg:classifiers":[
        {
            "category":"Professional",
            "type":"Services"
        }
    ],
    "sg:phone":"+1 314 863 4727",
    "sg:postcode":"63130",
    "sg:province":"MO",
    "wof:name":"Mid West Power Tools",
    "wof:placetype":"venue"
},
  "geometry": {"coordinates":[-90.32910200000001,38.660612],"type":"Point"}
}