{
  "type": "Feature",
  "properties": {
    "iso:country":"US",
    "sg:address":"310 S Scott Ave",
    "sg:city":"Belton",
    "sg:classifiers":[
        {
            "category":"Education",
            "subcategory":"School",
            "type":"Public Place"
        }
    ],
    "sg:phone":"+1 816 348 1005",
    "sg:postcode":"64012",
    "sg:province":"MO",
    "wof:name":"Belton Public Schools",
    "wof:placetype":"venue"
},
  "geometry": {"coordinates":[-94.534997,38.810949],"type":"Point"}
}