{
  "type": "Feature",
  "properties": {
    "iso:country":"US",
    "sg:address":"6425 State Hwy Zz",
    "sg:city":"West Plains",
    "sg:classifiers":[
        {
            "category":"Wholesale",
            "subcategory":"Non-durable Goods",
            "type":"Manufacturing & Wholesale Goods"
        }
    ],
    "sg:phone":"+1 417 256 2116",
    "sg:postcode":"65775",
    "sg:province":"MO",
    "sg:tags":[
        "charcoal"
    ],
    "wof:name":"Royal Oak Enterprises",
    "wof:placetype":"venue"
},
  "geometry": {"coordinates":[-91.819456,36.712268],"type":"Point"}
}