{
  "type": "Feature",
  "properties": {
    "iso:country":"US",
    "sg:address":"1220 N Jesse James Rd",
    "sg:city":"Excelsior Springs",
    "sg:classifiers":[
        {
            "category":"Shopping",
            "subcategory":"Used Merchandise",
            "type":"Retail Goods"
        }
    ],
    "sg:phone":"+1 816 630 8000",
    "sg:postcode":"64024",
    "sg:province":"MO",
    "wof:name":"Excelsior Trade Fair Mall",
    "wof:placetype":"venue"
},
  "geometry": {"coordinates":[-94.235164,39.354466],"type":"Point"}
}