{
  "type": "Feature",
  "properties": {
    "iso:country":"US",
    "sg:address":"3439 Prospect Ave",
    "sg:city":"Kansas City",
    "sg:classifiers":[
        {
            "category":"Manufacturing",
            "subcategory":"Metals",
            "type":"Manufacturing & Wholesale Goods"
        },
        {
            "category":"Manufacturing",
            "subcategory":"Apparel",
            "type":"Manufacturing & Wholesale Goods"
        }
    ],
    "sg:phone":"+1 816 924 4500",
    "sg:postcode":"64128",
    "sg:province":"MO",
    "sg:tags":[
        "trim",
        "door",
        "mfg",
        "frame",
        "work",
        "iron",
        "awning",
        "sash"
    ],
    "wof:name":"Advance Awning & Iron Works Co",
    "wof:placetype":"venue"
},
  "geometry": {"coordinates":[-94.553099,39.063327],"type":"Point"}
}