{
  "type": "Feature",
  "properties": {
    "iso:country":"US",
    "sg:address":"351 NW 75th St",
    "sg:city":"Spickard",
    "sg:classifiers":[
        {
            "category":"Building & Trades",
            "subcategory":"Construction",
            "type":"Services"
        }
    ],
    "sg:phone":"+1 660 485 6430",
    "sg:postcode":"64679",
    "sg:province":"MO",
    "sg:tags":[
        "house"
    ],
    "wof:name":"Devorss Construction",
    "wof:placetype":"venue"
},
  "geometry": {"coordinates":[-93.65611,40.183966],"type":"Point"}
}