{
  "type": "Feature",
  "properties": {
    "iso:country":"US",
    "sg:address":"4550 Belleview Ave",
    "sg:city":"Kansas City",
    "sg:classifiers":[
        {
            "category":"Professional",
            "subcategory":"Lawyer & Legal Services",
            "type":"Services"
        }
    ],
    "sg:phone":"+1 816 561 0123",
    "sg:postcode":"64111",
    "sg:province":"MO",
    "sg:tags":[
        "attorney"
    ],
    "wof:name":"Mc Roberts Roberts & Rainer",
    "wof:placetype":"venue"
},
  "geometry": {"coordinates":[-94.598461,39.04526],"type":"Point"}
}