{
  "type": "Feature",
  "properties": {
    "iso:country":"US",
    "sg:address":"110 N Douglass St",
    "sg:city":"Malden",
    "sg:classifiers":[
        {
            "category":"Shopping",
            "subcategory":"Department Store",
            "type":"Retail Goods"
        },
        {
            "category":"Shopping",
            "subcategory":"Discount & Variety Stores",
            "type":"Retail Goods"
        },
        {
            "category":"Shopping",
            "type":"Retail Goods"
        },
        {
            "category":"Food & Beverages",
            "subcategory":"Groceries & Convenience Stores",
            "type":"Retail Goods"
        }
    ],
    "sg:phone":"+1 573 276 3815",
    "sg:postcode":"63863",
    "sg:province":"MO",
    "sg:tags":[
        "merchandise"
    ],
    "sg:website":"http://www.dollargeneral.com",
    "wof:name":"Dollar General",
    "wof:placetype":"venue"
},
  "geometry": {"coordinates":[-89.97073399999999,36.558444],"type":"Point"}
}