{
  "type": "Feature",
  "properties": {
    "iso:country":"US",
    "sg:address":"2232 Hood Ave",
    "sg:city":"St Louis",
    "sg:classifiers":[
        {
            "category":"Building & Trades",
            "subcategory":"Construction",
            "type":"Services"
        }
    ],
    "sg:phone":"+1 314 429 1764",
    "sg:postcode":"63114",
    "sg:province":"MO",
    "sg:tags":[
        "layer",
        "carpet"
    ],
    "wof:name":"Steam Way Carpet Care Inc",
    "wof:placetype":"venue"
},
  "geometry": {"coordinates":[-90.368945,38.696461],"type":"Point"}
}