{
  "type": "Feature",
  "properties": {
    "iso:country":"US",
    "sg:address":"5103 N Belt Hwy",
    "sg:city":"Saint Joseph",
    "sg:classifiers":[
        {
            "category":"Restaurant",
            "type":"Food & Drink"
        }
    ],
    "sg:menulink":"http://www.allmenus.com/mo/st-joseph/11031-54th-street-grill/menu/",
    "sg:phone":"+1 816 233 5450",
    "sg:postcode":"64506",
    "sg:province":"MO",
    "sg:tags":[
        "american"
    ],
    "wof:name":"54th Street Grill",
    "wof:placetype":"venue"
},
  "geometry": {"coordinates":[-94.815039,39.814309],"type":"Point"}
}