{
  "type": "Feature",
  "properties": {
    "iso:country":"US",
    "sg:address":"3125 Lafayette Ave",
    "sg:city":"Saint Louis",
    "sg:classifiers":[
        {
            "category":"Retail",
            "subcategory":"Funeral Services",
            "type":"Services"
        }
    ],
    "sg:phone":"+1 314 771 7780",
    "sg:postcode":"63104",
    "sg:province":"MO",
    "sg:tags":[
        "cemetery"
    ],
    "wof:name":"Vollmer Theo F Funrl Dir",
    "wof:placetype":"venue"
},
  "geometry": {"coordinates":[-90.23139999999999,38.616001],"type":"Point"}
}