{
  "type": "Feature",
  "properties": {
    "iso:country":"US",
    "sg:address":"4403 Kensington Dr",
    "sg:city":"Saint Joseph",
    "sg:classifiers":[
        {
            "category":"Professional",
            "type":"Services"
        }
    ],
    "sg:phone":"+1 816 554 0378",
    "sg:postcode":"64506",
    "sg:province":"MO",
    "wof:name":"Noland Urban",
    "wof:placetype":"venue"
},
  "geometry": {"coordinates":[-94.79016799999999,39.803979],"type":"Point"}
}