{
  "type": "Feature",
  "properties": {
    "iso:country":"US",
    "sg:address":"125 W Main St",
    "sg:city":"Jackson",
    "sg:classifiers":[
        {
            "category":"Manufacturing",
            "subcategory":"Printing",
            "type":"Manufacturing & Wholesale Goods"
        }
    ],
    "sg:phone":"+1 573 243 0090",
    "sg:postcode":"63755",
    "sg:province":"MO",
    "sg:tags":[
        "screen"
    ],
    "wof:name":"Semo Specialties & Sports",
    "wof:placetype":"venue"
},
  "geometry": {"coordinates":[-89.667962,37.382499],"type":"Point"}
}