{
  "type": "Feature",
  "properties": {
    "iso:country":"US",
    "sg:address":"3890 Pershall Rd",
    "sg:city":"St Louis",
    "sg:classifiers":[
        {
            "category":"Retail",
            "subcategory":"Car Wash",
            "type":"Services"
        }
    ],
    "sg:phone":"+1 314 524 5803",
    "sg:postcode":"63135",
    "sg:province":"MO",
    "sg:tags":[
        "polishing",
        "carwash",
        "washing"
    ],
    "wof:name":"Pershall Carwash",
    "wof:placetype":"venue"
},
  "geometry": {"coordinates":[-90.30473499999999,38.771988],"type":"Point"}
}