{
  "type": "Feature",
  "properties": {
    "iso:country":"US",
    "sg:address":"15440 Manchester Rd",
    "sg:city":"Ballwin",
    "sg:classifiers":[
        {
            "category":"Cinema",
            "subcategory":"Movie Rental",
            "type":"Entertainment"
        }
    ],
    "sg:phone":"+1 636 527 7008",
    "sg:postcode":"63011",
    "sg:province":"MO",
    "sg:tags":[
        "video",
        "retail",
        "tape",
        "rent"
    ],
    "wof:name":"Hollywood Entertainment Corp",
    "wof:placetype":"venue"
},
  "geometry": {"coordinates":[-90.56506400000001,38.592833],"type":"Point"}
}