{
  "type": "Feature",
  "properties": {
    "addr:full":"50 S Plaza Way Cape Girardeau MO 63703",
    "addr:housenumber":"50",
    "addr:postcode":"63703",
    "addr:street":"S Plaza Way",
    "iso:country":"US",
    "sg:address":"50 S Plaza Way",
    "sg:city":"Cape Girardeau",
    "sg:classifiers":[
        {
            "category":"Shopping",
            "subcategory":"Used Merchandise",
            "type":"Retail Goods"
        },
        {
            "category":"Shopping",
            "subcategory":"Books",
            "type":"Retail Goods"
        }
    ],
    "sg:phone":"+1 573 334 2711",
    "sg:postcode":"63703",
    "sg:province":"MO",
    "sg:tags":[
        "rare",
        "dealer"
    ],
    "wof:name":"Book Rack",
    "wof:placetype":"venue"
},
  "geometry": {"coordinates":[-89.548028,37.305417],"type":"Point"}
}