{
  "type": "Feature",
  "properties": {
    "iso:country":"US",
    "sg:address":"521 SE 2 St",
    "sg:city":"Lees Summit",
    "sg:classifiers":[
        {
            "category":"Social Services",
            "type":"Services"
        }
    ],
    "sg:phone":"+1 816 554 0912",
    "sg:postcode":"64063",
    "sg:province":"MO",
    "wof:name":"Judith M Steffen PHD LPC",
    "wof:placetype":"venue"
},
  "geometry": {"coordinates":[-94.370085,38.915766],"type":"Point"}
}