{
  "type": "Feature",
  "properties": {
    "iso:country":"US",
    "sg:address":"1507 Heritage Hills Dr",
    "sg:city":"Washington",
    "sg:classifiers":[
        {
            "category":"Health Services",
            "subcategory":"Dentist",
            "type":"Services"
        }
    ],
    "sg:phone":"+1 636 239 5151",
    "sg:postcode":"63090",
    "sg:province":"MO",
    "sg:tags":[
        "dentists-orthodontists"
    ],
    "wof:name":"Walde, Kevin C Dds Ms Pc",
    "wof:placetype":"venue"
},
  "geometry": {"coordinates":[-91.006652,38.543496],"type":"Point"}
}