{
  "type": "Feature",
  "properties": {
    "iso:country":"US",
    "sg:address":"4337 Showplace Dr",
    "sg:city":"Farmington",
    "sg:classifiers":[
        {
            "category":"Building & Trades",
            "subcategory":"Construction",
            "type":"Services"
        },
        {
            "category":"Home & Garden",
            "subcategory":"Carpets & Floor Coverings",
            "type":"Retail Goods"
        }
    ],
    "sg:phone":"+1 800 394 3064",
    "sg:postcode":"63640",
    "sg:province":"MO",
    "sg:tags":[
        "material",
        "tile-contractors",
        "rug",
        "flooring",
        "contractor"
    ],
    "sg:website":"http://www.filitrac.com/Click.aspx?tid=BDEDC5D5EF8BAE3541B5938870DA3DDECE60F60FEE115906&FiliAff=15016&sid=99202&utm_source=YellowPages&utm_medium=ppc&utm_campaign=national&utm_term=63640",
    "wof:name":"Carpet One Floor & Home",
    "wof:placetype":"venue"
},
  "geometry": {"coordinates":[-90.44709899999999,37.80337],"type":"Point"}
}