{
  "type": "Feature",
  "properties": {
    "iso:country":"US",
    "sg:address":"512 Crest Ct",
    "sg:city":"Saint Louis",
    "sg:classifiers":[
        {
            "category":"Professional",
            "subcategory":"Management & Consulting",
            "type":"Services"
        }
    ],
    "sg:phone":"+1 314 821 7713",
    "sg:postcode":"63122",
    "sg:province":"MO",
    "sg:tags":[
        "business"
    ],
    "wof:name":"Gary Schmidt PTG Co",
    "wof:placetype":"venue"
},
  "geometry": {"coordinates":[-90.424115,38.573006],"type":"Point"}
}