{
  "type": "Feature",
  "properties": {
    "iso:country":"US",
    "sg:address":"611 Rollins Rd",
    "sg:city":"Columbia",
    "sg:classifiers":[
        {
            "category":"Personal",
            "type":"Services"
        }
    ],
    "sg:phone":"+1 573 443 2122",
    "sg:postcode":"65203",
    "sg:province":"MO",
    "wof:name":"A Matter of Style",
    "wof:placetype":"venue"
},
  "geometry": {"coordinates":[-92.34713499999999,38.944264],"type":"Point"}
}