{
  "type": "Feature",
  "properties": {
    "iso:country":"US",
    "sg:address":"298 County Highway 450",
    "sg:city":"Steele",
    "sg:classifiers":[
        {
            "category":"Farming",
            "subcategory":"Farm",
            "type":"Manufacturing & Wholesale Goods"
        }
    ],
    "sg:phone":"+1 573 333 4380",
    "sg:postcode":"63877",
    "sg:province":"MO",
    "wof:name":"Carter Farm",
    "wof:placetype":"venue"
},
  "geometry": {"coordinates":[-89.788612,36.1175],"type":"Point"}
}