{
  "type": "Feature",
  "properties": {
    "iso:country":"US",
    "sg:address":"123 W 2nd St",
    "sg:city":"Salisbury",
    "sg:classifiers":[
        {
            "category":"Local Transit",
            "type":"Transportation"
        }
    ],
    "sg:phone":"+1 660 388 5461",
    "sg:postcode":"65281",
    "sg:province":"MO",
    "sg:tags":[
        "ambulance"
    ],
    "wof:name":"Chariton Co Ambulance Dis",
    "wof:placetype":"venue"
},
  "geometry": {"coordinates":[-92.802868,39.423794],"type":"Point"}
}