{
  "type": "Feature",
  "properties": {
    "iso:country":"US",
    "sg:address":"4720 Oak St",
    "sg:city":"Kansas City",
    "sg:classifiers":[
        {
            "category":"Retail",
            "subcategory":"Repair Shop",
            "type":"Services"
        }
    ],
    "sg:phone":"+1 816 921 0501",
    "sg:postcode":"64112",
    "sg:province":"MO",
    "wof:name":"Paxson Communications Corp",
    "wof:placetype":"venue"
},
  "geometry": {"coordinates":[-94.58245599999999,39.04053],"type":"Point"}
}