{
  "type": "Feature",
  "properties": {
    "iso:country":"US",
    "sg:address":"907 Copper Oaks Dr",
    "sg:city":"Carl Junction",
    "sg:classifiers":[
        {
            "category":"Building & Trades",
            "subcategory":"Construction",
            "type":"Services"
        }
    ],
    "sg:phone":"+1 417 649 7771",
    "sg:postcode":"64834",
    "sg:province":"MO",
    "wof:name":"Burnison Construction Svc",
    "wof:placetype":"venue"
},
  "geometry": {"coordinates":[-94.54628200000001,37.151409],"type":"Point"}
}