{
  "type": "Feature",
  "properties": {
    "iso:country":"US",
    "sg:address":"4336 Natural Bridge Ave",
    "sg:city":"St Louis",
    "sg:classifiers":[
        {
            "category":"Shopping",
            "subcategory":"Clothing, Apparel, & Fashions",
            "type":"Retail Goods"
        }
    ],
    "sg:phone":"+1 314 535 2968",
    "sg:postcode":"63115",
    "sg:province":"MO",
    "sg:tags":[
        "hat"
    ],
    "wof:name":"Harris Hat Shop",
    "wof:placetype":"venue"
},
  "geometry": {"coordinates":[-90.235961,38.66945],"type":"Point"}
}