{
  "type": "Feature",
  "properties": {
    "iso:country":"US",
    "sg:address":"113 W 78 Ter",
    "sg:city":"Kansas City",
    "sg:classifiers":[
        {
            "category":"Professional",
            "type":"Services"
        }
    ],
    "sg:phone":"+1 816 523 4332",
    "sg:postcode":"64114",
    "sg:province":"MO",
    "wof:name":"Dee Services",
    "wof:placetype":"venue"
},
  "geometry": {"coordinates":[-94.59206399999999,38.985813],"type":"Point"}
}