{
  "type": "Feature",
  "properties": {
    "iso:country":"US",
    "sg:address":"5792 Bluebird Cir",
    "sg:city":"Lake Ozark",
    "sg:classifiers":[
        {
            "category":"Building & Trades",
            "subcategory":"Construction",
            "type":"Services"
        }
    ],
    "sg:phone":"+1 573 302 1053",
    "sg:postcode":"65065",
    "sg:province":"MO",
    "sg:tags":[
        "hanging",
        "wallpaper",
        "contractor"
    ],
    "wof:name":"Westwood Interprises Inc",
    "wof:placetype":"venue"
},
  "geometry": {"coordinates":[-92.688428,38.139003],"type":"Point"}
}