{
  "type": "Feature",
  "properties": {
    "iso:country":"US",
    "sg:address":"1245 Parmer Dr",
    "sg:city":"Florissant",
    "sg:classifiers":[
        {
            "category":"Professional",
            "subcategory":"Computer Services",
            "type":"Services"
        }
    ],
    "sg:phone":"+1 314 830 7936",
    "sg:postcode":"63031",
    "sg:province":"MO",
    "sg:tags":[
        "design",
        "system"
    ],
    "wof:name":"Web Store",
    "wof:placetype":"venue"
},
  "geometry": {"coordinates":[-90.329847,38.827135],"type":"Point"}
}