{
  "type": "Feature",
  "properties": {
    "iso:country":"US",
    "sg:address":"1867 Ironstone Rd",
    "sg:city":"Saint Louis",
    "sg:classifiers":[
        {
            "category":"Wholesale",
            "subcategory":"Durable Goods & Equipment",
            "type":"Manufacturing & Wholesale Goods"
        }
    ],
    "sg:phone":"+1 314 966 2633",
    "sg:postcode":"63131",
    "sg:province":"MO",
    "sg:tags":[
        "instrument",
        "musical"
    ],
    "wof:name":"Now Entertainment LLC",
    "wof:placetype":"venue"
},
  "geometry": {"coordinates":[-90.43944500000001,38.614062],"type":"Point"}
}