{
  "type": "Feature",
  "properties": {
    "iso:country":"US",
    "sg:address":"4469 State Hwy 33",
    "sg:city":"Maysville",
    "sg:classifiers":[
        {
            "category":"Travel",
            "subcategory":"Campground",
            "type":"Entertainment"
        }
    ],
    "sg:phone":"+1 816 449 2039",
    "sg:postcode":"64469",
    "sg:province":"MO",
    "wof:name":"Pony Express Rv Park",
    "wof:placetype":"venue"
},
  "geometry": {"coordinates":[-94.362341,39.840155],"type":"Point"}
}