{
  "type": "Feature",
  "properties": {
    "iso:country":"US",
    "sg:address":"2126 Lafayette Ave",
    "sg:city":"Saint Louis",
    "sg:classifiers":[
        {
            "category":"Professional",
            "type":"Services"
        }
    ],
    "sg:phone":"+1 314 771 3691",
    "sg:postcode":"63104",
    "sg:province":"MO",
    "wof:name":"Trace S Shaughnessy",
    "wof:placetype":"venue"
},
  "geometry": {"coordinates":[-90.216905,38.614224],"type":"Point"}
}