{
  "type": "Feature",
  "properties": {
    "iso:country":"US",
    "sg:address":"1411 W Sunshine St",
    "sg:city":"Springfield",
    "sg:classifiers":[
        {
            "category":"Restaurant",
            "type":"Food & Drink"
        }
    ],
    "sg:menulink":"http://www.allmenus.com/mo/springfield/54930-thai-peppers/menu/",
    "sg:phone":"+1 417 882 1979",
    "sg:postcode":"65807",
    "sg:province":"MO",
    "sg:tags":[
        "thai",
        "asian"
    ],
    "wof:name":"Thai Peppers",
    "wof:placetype":"venue"
},
  "geometry": {"coordinates":[-93.31052800000001,37.182418],"type":"Point"}
}