{
  "type": "Feature",
  "properties": {
    "iso:country":"US",
    "sg:address":"741 Forest Ave",
    "sg:city":"Cape Girardeau",
    "sg:classifiers":[
        {
            "category":"Organizations",
            "subcategory":"Religious Organization",
            "type":"Services"
        }
    ],
    "sg:phone":"+1 573 335 7667",
    "sg:postcode":"63701",
    "sg:province":"MO",
    "sg:tags":[
        "school"
    ],
    "wof:name":"St Vincent De Paul Church",
    "wof:placetype":"venue"
},
  "geometry": {"coordinates":[-89.545277,37.314871],"type":"Point"}
}