{
  "type": "Feature",
  "properties": {
    "iso:country":"US",
    "sg:address":"3800 NW Barry Rd",
    "sg:city":"Kansas City",
    "sg:classifiers":[
        {
            "category":"Real Estate",
            "subcategory":"Real Estate Operator",
            "type":"Services"
        }
    ],
    "sg:phone":"+1 816 436 2202",
    "sg:postcode":"64154",
    "sg:province":"MO",
    "sg:tags":[
        "building",
        "apartment"
    ],
    "wof:name":"Barclay Club Apartments",
    "wof:placetype":"venue"
},
  "geometry": {"coordinates":[-94.625428,39.246616],"type":"Point"}
}