{
  "type": "Feature",
  "properties": {
    "iso:country":"US",
    "sg:address":"701 E 3 St",
    "sg:city":"Kansas City",
    "sg:classifiers":[
        {
            "category":"Wholesale",
            "subcategory":"Construction Materials",
            "type":"Manufacturing & Wholesale Goods"
        }
    ],
    "sg:phone":"+1 816 842 0715",
    "sg:postcode":"64106",
    "sg:province":"MO",
    "sg:tags":[
        "building",
        "exterior"
    ],
    "wof:name":"C & W Siding & Window Material",
    "wof:placetype":"venue"
},
  "geometry": {"coordinates":[-94.575085,39.111522],"type":"Point"}
}