{
  "type": "Feature",
  "properties": {
    "iso:country":"US",
    "sg:address":"1720 E Timber Ridge Dr",
    "sg:city":"Sedalia",
    "sg:classifiers":[
        {
            "category":"Insurance",
            "subcategory":"Insurance Agent",
            "type":"Services"
        }
    ],
    "sg:phone":"+1 660 827 4705",
    "sg:postcode":"65301",
    "sg:province":"MO",
    "wof:name":"Thrivent Fincl For Lutherans",
    "wof:placetype":"venue"
},
  "geometry": {"coordinates":[-93.302059,38.703363],"type":"Point"}
}