{
  "type": "Feature",
  "properties": {
    "iso:country":"US",
    "sg:address":"6370 Devonshire Ave",
    "sg:city":"Saint Louis",
    "sg:classifiers":[
        {
            "category":"Professional",
            "subcategory":"Lawyer & Legal Services",
            "type":"Services"
        }
    ],
    "sg:phone":"+1 314 353 5690",
    "sg:postcode":"63109",
    "sg:province":"MO",
    "wof:name":"James F Shrewsbury Atty",
    "wof:placetype":"venue"
},
  "geometry": {"coordinates":[-90.29853300000001,38.589179],"type":"Point"}
}