{
  "type": "Feature",
  "properties": {
    "iso:country":"US",
    "sg:address":"106 N Pearl Ave",
    "sg:city":"Joplin",
    "sg:classifiers":[
        {
            "category":"Retail",
            "subcategory":"Laundry & Dry Cleaning",
            "type":"Services"
        }
    ],
    "sg:phone":"+1 417 781 8031",
    "sg:postcode":"64801",
    "sg:province":"MO",
    "wof:name":"Stitch Witch",
    "wof:placetype":"venue"
},
  "geometry": {"coordinates":[-94.516514,37.091678],"type":"Point"}
}