{
  "type": "Feature",
  "properties": {
    "iso:country":"US",
    "sg:address":"22318 Shelton Rd",
    "sg:city":"Polo",
    "sg:classifiers":[
        {
            "category":"Professional",
            "type":"Services"
        }
    ],
    "sg:phone":"+1 660 352 6010",
    "sg:postcode":"64671",
    "sg:province":"MO",
    "sg:tags":[
        "establishment"
    ],
    "wof:name":"Aimco Klemp",
    "wof:placetype":"venue"
},
  "geometry": {"coordinates":[-94.00332400000001,39.495876],"type":"Point"}
}