{
  "type": "Feature",
  "properties": {
    "iso:country":"US",
    "sg:address":"1227 S Maryland Ave",
    "sg:city":"Springfield",
    "sg:classifiers":[
        {
            "category":"Building & Trades",
            "subcategory":"Construction",
            "type":"Services"
        }
    ],
    "sg:phone":"+1 417 864 7585",
    "sg:postcode":"65807",
    "sg:province":"MO",
    "sg:tags":[
        "contractor"
    ],
    "wof:name":"Branson Lake Dev",
    "wof:placetype":"venue"
},
  "geometry": {"coordinates":[-93.280439,37.191349],"type":"Point"}
}