{
  "type": "Feature",
  "properties": {
    "iso:country":"US",
    "sg:address":"1447 Shelby 420",
    "sg:city":"Clarence",
    "sg:classifiers":[
        {
            "category":"Home & Garden",
            "subcategory":"Building Materials",
            "type":"Retail Goods"
        }
    ],
    "sg:phone":"+1 660 699 3811",
    "sg:postcode":"63437",
    "sg:province":"MO",
    "sg:tags":[
        "lumber-used"
    ],
    "wof:name":"Kelly D Wood",
    "wof:placetype":"venue"
},
  "geometry": {"coordinates":[-92.25206799999999,39.720988],"type":"Point"}
}