{
  "type": "Feature",
  "properties": {
    "iso:country":"US",
    "sg:address":"25480 CR 160",
    "sg:city":"Tina",
    "sg:classifiers":[
        {
            "category":"Insurance",
            "subcategory":"Hazard Insurance",
            "type":"Services"
        }
    ],
    "sg:phone":"+1 660 622 4434",
    "sg:postcode":"64682",
    "sg:province":"MO",
    "wof:name":"Nancy Kay Maasdam",
    "wof:placetype":"venue"
},
  "geometry": {"coordinates":[-93.46947,39.528827],"type":"Point"}
}