{
  "type": "Feature",
  "properties": {
    "iso:country":"US",
    "sg:address":"801 W College St",
    "sg:city":"Springfield",
    "sg:classifiers":[
        {
            "category":"Shopping",
            "subcategory":"Used Merchandise",
            "type":"Retail Goods"
        }
    ],
    "sg:phone":"+1 417 869 7743",
    "sg:postcode":"65806",
    "sg:province":"MO",
    "sg:tags":[
        "pawnbroker"
    ],
    "wof:name":"Square Deal Pawn Inc",
    "wof:placetype":"venue"
},
  "geometry": {"coordinates":[-93.30109899999999,37.20829],"type":"Point"}
}