{
  "type": "Feature",
  "properties": {
    "iso:country":"US",
    "sg:address":"11150 Lindbergh Business Ct",
    "sg:city":"Saint Louis",
    "sg:classifiers":[
        {
            "category":"Insurance",
            "subcategory":"Insurance Agent",
            "type":"Services"
        }
    ],
    "sg:phone":"+1 314 892 6005",
    "sg:postcode":"63123",
    "sg:province":"MO",
    "wof:name":"McM Financial Service Inc",
    "wof:placetype":"venue"
},
  "geometry": {"coordinates":[-90.337209,38.516495],"type":"Point"}
}