{
  "type": "Feature",
  "properties": {
    "iso:country":"US",
    "sg:address":"416 S Main St",
    "sg:city":"St Charles",
    "sg:classifiers":[
        {
            "category":"Food & Beverages",
            "subcategory":"Candy",
            "type":"Retail Goods"
        }
    ],
    "sg:phone":"+1 636 724 4131",
    "sg:postcode":"63301",
    "sg:province":"MO",
    "sg:tags":[
        "confectionery"
    ],
    "wof:name":"Riverside Sweets",
    "wof:placetype":"venue"
},
  "geometry": {"coordinates":[-90.48295299999999,38.777977],"type":"Point"}
}