{
  "type": "Feature",
  "properties": {
    "iso:country":"US",
    "sg:address":"1844 Highgrove Dr",
    "sg:city":"O Fallon",
    "sg:classifiers":[
        {
            "category":"Food & Beverages",
            "subcategory":"Groceries & Convenience Stores",
            "type":"Retail Goods"
        }
    ],
    "sg:phone":"+1 636 379 8449",
    "sg:postcode":"63366",
    "sg:province":"MO",
    "sg:tags":[
        "product"
    ],
    "wof:name":"Bunge Foods",
    "wof:placetype":"venue"
},
  "geometry": {"coordinates":[-90.68943899999999,38.83432],"type":"Point"}
}