{
  "type": "Feature",
  "properties": {
    "iso:country":"US",
    "sg:address":"3568 Manhattan Ave",
    "sg:city":"Saint Louis",
    "sg:classifiers":[
        {
            "category":"Building & Trades",
            "subcategory":"Construction",
            "type":"Services"
        }
    ],
    "sg:phone":"+1 314 645 8400",
    "sg:postcode":"63143",
    "sg:province":"MO",
    "sg:tags":[
        "hanging",
        "contractor"
    ],
    "wof:name":"Hang-Tite Wallcoverings",
    "wof:placetype":"venue"
},
  "geometry": {"coordinates":[-90.31938700000001,38.601744],"type":"Point"}
}