{
  "type": "Feature",
  "properties": {
    "iso:country":"US",
    "sg:address":"299 Parkland Ave",
    "sg:city":"Saint Louis",
    "sg:classifiers":[
        {
            "category":"Professional",
            "subcategory":"Management & Consulting",
            "type":"Services"
        }
    ],
    "sg:phone":"+1 314 822 4572",
    "sg:postcode":"63122",
    "sg:province":"MO",
    "wof:name":"Heller Capital Resources",
    "wof:placetype":"venue"
},
  "geometry": {"coordinates":[-90.382491,38.586714],"type":"Point"}
}