{
  "type": "Feature",
  "properties": {
    "iso:country":"US",
    "sg:address":"904 Clearview Dr",
    "sg:city":"Union",
    "sg:classifiers":[
        {
            "category":"Transit Center",
            "subcategory":"Freight",
            "type":"Transportation"
        },
        {
            "category":"Professional",
            "subcategory":"Advertising",
            "type":"Services"
        }
    ],
    "sg:phone":"+1 636 583 2405",
    "sg:postcode":"63084",
    "sg:province":"MO",
    "sg:tags":[
        "outdoor"
    ],
    "wof:name":"Bailey Outdoor Advertising",
    "wof:placetype":"venue"
},
  "geometry": {"coordinates":[-91.020175,38.433782],"type":"Point"}
}