{
  "type": "Feature",
  "properties": {
    "iso:country":"US",
    "sg:address":"9 Sunset Ln",
    "sg:city":"Saint Peters",
    "sg:classifiers":[
        {
            "category":"Building & Trades",
            "subcategory":"Construction",
            "type":"Services"
        }
    ],
    "sg:phone":"+1 636 240 8087",
    "sg:postcode":"63376",
    "sg:province":"MO",
    "sg:tags":[
        "hanging",
        "contractor"
    ],
    "wof:name":"Professional Painting Ser",
    "wof:placetype":"venue"
},
  "geometry": {"coordinates":[-90.691079,38.786647],"type":"Point"}
}