{
  "type": "Feature",
  "properties": {
    "iso:country":"US",
    "sg:address":"1302 Poplar St",
    "sg:city":"Lamar",
    "sg:classifiers":[
        {
            "category":"Organizations",
            "subcategory":"Religious Organization",
            "type":"Services"
        }
    ],
    "sg:phone":"+1 417 682 3147",
    "sg:postcode":"64759",
    "sg:province":"MO",
    "sg:tags":[
        "church"
    ],
    "wof:name":"Forest Grove Baptist Church",
    "wof:placetype":"venue"
},
  "geometry": {"coordinates":[-94.27468500000001,37.492103],"type":"Point"}
}