{
  "type": "Feature",
  "properties": {
    "iso:country":"US",
    "sg:address":"3838 Vogel Rd",
    "sg:city":"Arnold",
    "sg:classifiers":[
        {
            "category":"Government",
            "subcategory":"Office",
            "type":"Public Place"
        }
    ],
    "sg:phone":"+1 314 260 5077",
    "sg:postcode":"63010",
    "sg:province":"MO",
    "sg:tags":[
        "map",
        "making"
    ],
    "wof:name":"Dma Aerospace Center",
    "wof:placetype":"venue"
},
  "geometry": {"coordinates":[-90.39060000000001,38.416492],"type":"Point"}
}