{
  "type": "Feature",
  "properties": {
    "iso:country":"US",
    "sg:address":"30200 Utica Dr",
    "sg:city":"Richland",
    "sg:classifiers":[
        {
            "category":"Health Services",
            "subcategory":"Doctor",
            "type":"Services"
        },
        {
            "category":"Health Services",
            "subcategory":"Clinic",
            "type":"Services"
        },
        {
            "category":"Health Services",
            "subcategory":"Chiropractor",
            "type":"Services"
        }
    ],
    "sg:phone":"+1 573 765 4010",
    "sg:postcode":"65556",
    "sg:province":"MO",
    "sg:tags":[
        "physician",
        "medical",
        "surgeon",
        "chiropractic"
    ],
    "wof:name":"Morter Chiropractic Clini",
    "wof:placetype":"venue"
},
  "geometry": {"coordinates":[-92.417713,37.771508],"type":"Point"}
}