{
  "type": "Feature",
  "properties": {
    "iso:country":"US",
    "sg:address":"100 Chestnut St",
    "sg:city":"Oregon",
    "sg:classifiers":[
        {
            "category":"Government",
            "subcategory":"Office",
            "type":"Public Place"
        }
    ],
    "sg:phone":"+1 660 446 2346",
    "sg:postcode":"64473",
    "sg:province":"MO",
    "sg:tags":[
        "city"
    ],
    "wof:name":"Forest City City Hall",
    "wof:placetype":"venue"
},
  "geometry": {"coordinates":[-95.148505,39.988321],"type":"Point"}
}