{
  "type": "Feature",
  "properties": {
    "iso:country":"US",
    "sg:address":"1301 E Myrtle St",
    "sg:city":"Pleasant Hill",
    "sg:classifiers":[
        {
            "category":"Education",
            "subcategory":"School",
            "type":"Public Place"
        }
    ],
    "sg:phone":"+1 816 540 2149",
    "sg:postcode":"64080",
    "sg:province":"MO",
    "sg:website":"www.pleasanthillschools.com",
    "wof:name":"Pleasant Hill Middle School",
    "wof:placetype":"venue"
},
  "geometry": {"coordinates":[-94.25932299999999,38.788571],"type":"Point"}
}