{
  "type": "Feature",
  "properties": {
    "iso:country":"US",
    "sg:address":"3125 Boschertown Rd",
    "sg:city":"St Charles",
    "sg:classifiers":[
        {
            "category":"Manufacturing",
            "subcategory":"Metals",
            "type":"Manufacturing & Wholesale Goods"
        },
        {
            "category":"Manufacturing",
            "subcategory":"Tools & Machinery",
            "type":"Manufacturing & Wholesale Goods"
        }
    ],
    "sg:phone":"+1 636 947 3800",
    "sg:postcode":"63301",
    "sg:province":"MO",
    "sg:tags":[
        "repair",
        "shopping",
        "mfg",
        "cart",
        "bag",
        "fab",
        "w",
        "basket"
    ],
    "wof:name":"National Cart Co Inc",
    "wof:placetype":"venue"
},
  "geometry": {"coordinates":[-90.482783,38.825761],"type":"Point"}
}