{
  "type": "Feature",
  "properties": {
    "iso:country":"US",
    "sg:address":"3864 Mexico Rd",
    "sg:city":"Saint Charles",
    "sg:classifiers":[
        {
            "category":"Health Services",
            "subcategory":"Chiropractor",
            "type":"Services"
        }
    ],
    "sg:phone":"+1 636 477 8818",
    "sg:postcode":"63303",
    "sg:province":"MO",
    "wof:name":"Hoffman Chiopractic Center",
    "wof:placetype":"venue"
},
  "geometry": {"coordinates":[-90.56394899999999,38.791],"type":"Point"}
}