{
  "type": "Feature",
  "properties": {
    "iso:country":"US",
    "sg:address":"2633 Antler Ct",
    "sg:city":"Imperial",
    "sg:classifiers":[
        {
            "category":"Manufacturing",
            "subcategory":"Buildings",
            "type":"Manufacturing & Wholesale Goods"
        },
        {
            "category":"Building & Trades",
            "subcategory":"Construction",
            "type":"Services"
        }
    ],
    "sg:phone":"+1 636 464 8159",
    "sg:postcode":"63052",
    "sg:province":"MO",
    "sg:tags":[
        "home",
        "builder",
        "contractor"
    ],
    "wof:name":"Everett Hahn",
    "wof:placetype":"venue"
},
  "geometry": {"coordinates":[-90.426176,38.387771],"type":"Point"}
}