{
  "type": "Feature",
  "properties": {
    "iso:country":"US",
    "sg:address":"381 Highway W",
    "sg:city":"Eldon",
    "sg:classifiers":[
        {
            "category":"Shopping",
            "type":"Retail Goods"
        }
    ],
    "sg:phone":"+1 573 964 0365",
    "sg:postcode":"65026",
    "sg:province":"MO",
    "sg:tags":[
        "merchandise"
    ],
    "wof:name":"Hwy Wc Store Gas More LL",
    "wof:placetype":"venue"
},
  "geometry": {"coordinates":[-92.672364,38.245853],"type":"Point"}
}