{
  "type": "Feature",
  "properties": {
    "iso:country":"US",
    "sg:address":"3810 Robinson Pike Rd",
    "sg:city":"Grandview",
    "sg:classifiers":[
        {
            "category":"Building & Trades",
            "subcategory":"Landscaping Services",
            "type":"Services"
        }
    ],
    "sg:phone":"+1 816 763 2999",
    "sg:postcode":"64030",
    "sg:province":"MO",
    "wof:name":"Perfect Finish",
    "wof:placetype":"venue"
},
  "geometry": {"coordinates":[-94.54886,38.888311],"type":"Point"}
}