{
  "type": "Feature",
  "properties": {
    "iso:country":"US",
    "sg:address":"1401 S Boyle Ave",
    "sg:city":"St Louis",
    "sg:classifiers":[
        {
            "category":"Professional",
            "subcategory":"Advertising",
            "type":"Services"
        },
        {
            "category":"Professional",
            "subcategory":"Business Services",
            "type":"Services"
        }
    ],
    "sg:phone":"+1 314 968 7712",
    "sg:postcode":"63110",
    "sg:province":"MO",
    "sg:tags":[
        "marketing",
        "relation",
        "public"
    ],
    "sg:website":"www.traffic-prm.com",
    "wof:name":"TrafficPRM",
    "wof:placetype":"venue"
},
  "geometry": {"coordinates":[-90.253817,38.624532],"type":"Point"}
}