{
  "type": "Feature",
  "properties": {
    "iso:country":"US",
    "sg:address":"1017 W 1st St",
    "sg:city":"West Plains",
    "sg:classifiers":[
        {
            "category":"Autos & Motor Vehicles",
            "subcategory":"Automobile Sales",
            "type":"Retail Goods"
        }
    ],
    "sg:phone":"+1 417 257 0746",
    "sg:postcode":"65775",
    "sg:province":"MO",
    "sg:tags":[
        "car",
        "dealer"
    ],
    "wof:name":"Mike's Auto Sales",
    "wof:placetype":"venue"
},
  "geometry": {"coordinates":[-91.861947,36.732347],"type":"Point"}
}