{
  "type": "Feature",
  "properties": {
    "iso:country":"US",
    "sg:address":"1419 W Austin Blvd",
    "sg:city":"Nevada",
    "sg:classifiers":[
        {
            "category":"Banks & Credit Unions",
            "subcategory":"Investment Brokerage",
            "type":"Services"
        }
    ],
    "sg:phone":"+1 417 667 5555",
    "sg:postcode":"64772",
    "sg:province":"MO",
    "sg:tags":[
        "commodity"
    ],
    "wof:name":"Drywood Financial Svc Inc",
    "wof:placetype":"venue"
},
  "geometry": {"coordinates":[-94.375512,37.837643],"type":"Point"}
}