{
  "type": "Feature",
  "properties": {
    "iso:country":"US",
    "sg:address":"501 Hardwick Cir",
    "sg:city":"Liberty",
    "sg:classifiers":[
        {
            "category":"Shopping",
            "subcategory":"Hobbies, Toys, & Games",
            "type":"Retail Goods"
        }
    ],
    "sg:phone":"+1 816 407 7967",
    "sg:postcode":"64068",
    "sg:province":"MO",
    "sg:tags":[
        "product",
        "ceramic"
    ],
    "wof:name":"Ceramica On The Square",
    "wof:placetype":"venue"
},
  "geometry": {"coordinates":[-94.42643700000001,39.265117],"type":"Point"}
}