{
  "type": "Feature",
  "properties": {
    "iso:country":"US",
    "sg:address":"642 E 46 St",
    "sg:city":"Kansas City",
    "sg:classifiers":[
        {
            "category":"Professional",
            "subcategory":"Business Services",
            "type":"Services"
        }
    ],
    "sg:phone":"+1 816 753 4093",
    "sg:postcode":"64110",
    "sg:province":"MO",
    "wof:name":"Rheinfrank Foundation Inc",
    "wof:placetype":"venue"
},
  "geometry": {"coordinates":[-94.57887599999999,39.043754],"type":"Point"}
}