{
  "type": "Feature",
  "properties": {
    "iso:country":"US",
    "sg:address":"107 Church St",
    "sg:city":"Fredericktown",
    "sg:classifiers":[
        {
            "category":"Retail",
            "subcategory":"Car Wash",
            "type":"Services"
        }
    ],
    "sg:phone":"+1 573 783 7870",
    "sg:postcode":"63645",
    "sg:province":"MO",
    "sg:tags":[
        "carwash"
    ],
    "wof:name":"Darren Detail Shop",
    "wof:placetype":"venue"
},
  "geometry": {"coordinates":[-90.29422,37.5635],"type":"Point"}
}