{
  "type": "Feature",
  "properties": {
    "iso:country":"US",
    "sg:address":"2389 Vixen Rd",
    "sg:city":"Sarcoxie",
    "sg:classifiers":[
        {
            "category":"Building & Trades",
            "subcategory":"Construction",
            "type":"Services"
        }
    ],
    "sg:phone":"+1 417 548 2519",
    "sg:postcode":"64862",
    "sg:province":"MO",
    "sg:tags":[
        "house",
        "carpentry",
        "contractor"
    ],
    "wof:name":"Carpenter Shop",
    "wof:placetype":"venue"
},
  "geometry": {"coordinates":[-94.113795,37.033114],"type":"Point"}
}