{
  "type": "Feature",
  "properties": {
    "iso:country":"US",
    "sg:address":"100 Saint Elizabeth Ln",
    "sg:city":"New Madrid",
    "sg:classifiers":[
        {
            "category":"Shopping",
            "subcategory":"Florist",
            "type":"Retail Goods"
        }
    ],
    "sg:phone":"+1 573 748 5263",
    "sg:postcode":"63869",
    "sg:province":"MO",
    "wof:name":"Candys Sunshine & Smiles",
    "wof:placetype":"venue"
},
  "geometry": {"coordinates":[-89.545717,36.596032],"type":"Point"}
}