{
  "type": "Feature",
  "properties": {
    "iso:country":"US",
    "sg:address":"2060 Wealdwood Ct",
    "sg:city":"Saint Louis",
    "sg:classifiers":[
        {
            "category":"Manufacturing",
            "subcategory":"Printing",
            "type":"Manufacturing & Wholesale Goods"
        }
    ],
    "sg:phone":"+1 314 965 1413",
    "sg:postcode":"63122",
    "sg:province":"MO",
    "sg:tags":[
        "publishing"
    ],
    "wof:name":"Ltc Expert Publications LLC",
    "wof:placetype":"venue"
},
  "geometry": {"coordinates":[-90.44442600000001,38.56199],"type":"Point"}
}