{
  "type": "Feature",
  "properties": {
    "iso:country":"US",
    "sg:address":"6670 E Mutton Hollow Ln",
    "sg:city":"Columbia",
    "sg:classifiers":[
        {
            "category":"Manufacturing",
            "subcategory":"Building Materials",
            "type":"Manufacturing & Wholesale Goods"
        }
    ],
    "sg:phone":"+1 573 443 2095",
    "sg:postcode":"65201",
    "sg:province":"MO",
    "sg:tags":[
        "member",
        "mfg",
        "wood",
        "structural"
    ],
    "wof:name":"C J Truss Inc",
    "wof:placetype":"venue"
},
  "geometry": {"coordinates":[-92.240551,38.872044],"type":"Point"}
}