{
  "type": "Feature",
  "properties": {
    "iso:country":"US",
    "sg:address":"11556 Concord Village Ave",
    "sg:city":"Sappington",
    "sg:classifiers":[
        {
            "category":"Building & Trades",
            "subcategory":"Landscaping Services",
            "type":"Services"
        }
    ],
    "sg:phone":"+1 314 843 4500",
    "sg:postcode":"63128",
    "sg:province":"MO",
    "sg:tags":[
        "lawn",
        "maintenance",
        "grounds"
    ],
    "wof:name":"Kissel Bros Pro Cutting System",
    "wof:placetype":"venue"
},
  "geometry": {"coordinates":[-90.36136,38.521866],"type":"Point"}
}