{
  "type": "Feature",
  "properties": {
    "iso:country":"US",
    "sg:address":"10215 State Hwy 350",
    "sg:city":"Kansas City",
    "sg:classifiers":[
        {
            "category":"Retail",
            "subcategory":"Laundry & Dry Cleaning",
            "type":"Services"
        }
    ],
    "sg:phone":"+1 816 313 6367",
    "sg:postcode":"64138",
    "sg:province":"MO",
    "wof:name":"Certified Carpet Care",
    "wof:placetype":"venue"
},
  "geometry": {"coordinates":[-94.461495,38.983342],"type":"Point"}
}