{
  "type": "Feature",
  "properties": {
    "iso:country":"US",
    "sg:address":"6701 Memorial Hwy",
    "sg:city":"St Joseph",
    "sg:classifiers":[
        {
            "category":"Shopping",
            "subcategory":"Used Merchandise",
            "type":"Retail Goods"
        }
    ],
    "sg:phone":"+1 816 238 4698",
    "sg:postcode":"64504",
    "sg:province":"MO",
    "sg:tags":[
        "pawnbroker"
    ],
    "wof:name":"Southside Pawn",
    "wof:placetype":"venue"
},
  "geometry": {"coordinates":[-94.879394,39.706617],"type":"Point"}
}