{
  "type": "Feature",
  "properties": {
    "iso:country":"US",
    "sg:address":"107 Adams St",
    "sg:city":"Jefferson City",
    "sg:classifiers":[
        {
            "category":"Organizations",
            "subcategory":"Professional Association",
            "type":"Services"
        }
    ],
    "sg:phone":"+1 573 634 2922",
    "sg:postcode":"65101",
    "sg:province":"MO",
    "sg:website":"www.aimo.com",
    "wof:name":"Missouri Transportation & Dev",
    "wof:placetype":"venue"
},
  "geometry": {"coordinates":[-92.166262,38.57613],"type":"Point"}
}