{
  "type": "Feature",
  "properties": {
    "iso:country":"US",
    "sg:address":"510 Lake Ave",
    "sg:city":"Saint Louis",
    "sg:classifiers":[
        {
            "category":"Shopping",
            "subcategory":"Crafts & Fabrics",
            "type":"Retail Goods"
        }
    ],
    "sg:phone":"+1 314 961 0909",
    "sg:postcode":"63119",
    "sg:province":"MO",
    "sg:tags":[
        "quilting"
    ],
    "wof:name":"Prestige Corner",
    "wof:placetype":"venue"
},
  "geometry": {"coordinates":[-90.341542,38.592129],"type":"Point"}
}