{
  "type": "Feature",
  "properties": {
    "iso:country":"US",
    "sg:address":"1208 Chambers Rd",
    "sg:city":"Ferguson",
    "sg:classifiers":[
        {
            "category":"Home & Garden",
            "subcategory":"Household Appliances",
            "type":"Retail Goods"
        },
        {
            "category":"Wholesale",
            "subcategory":"Electrical",
            "type":"Manufacturing & Wholesale Goods"
        }
    ],
    "sg:phone":"+1 314 524 7605",
    "sg:postcode":"63135",
    "sg:province":"MO",
    "sg:tags":[
        "repair"
    ],
    "wof:name":"Dellwood Washer-Dryer Parts Co",
    "wof:placetype":"venue"
},
  "geometry": {"coordinates":[-90.28682999999999,38.749347],"type":"Point"}
}