{
  "type": "Feature",
  "properties": {
    "iso:country":"US",
    "sg:address":"6500 Chippewa St",
    "sg:city":"St Louis",
    "sg:classifiers":[
        {
            "category":"Health Services",
            "subcategory":"Chiropractor",
            "type":"Services"
        }
    ],
    "sg:phone":"+1 314 352 0834",
    "sg:postcode":"63109",
    "sg:province":"MO",
    "wof:name":"Chiro Health",
    "wof:placetype":"venue"
},
  "geometry": {"coordinates":[-90.303057,38.591872],"type":"Point"}
}