{
  "type": "Feature",
  "properties": {
    "iso:country":"US",
    "sg:address":"100 N Court Sq",
    "sg:city":"Kennett",
    "sg:classifiers":[
        {
            "category":"Government",
            "subcategory":"Office",
            "type":"Public Place"
        }
    ],
    "sg:phone":"+1 573 888 1374",
    "sg:postcode":"63857",
    "sg:province":"MO",
    "sg:tags":[
        "county"
    ],
    "wof:name":"Dunklin County Clerk",
    "wof:placetype":"venue"
},
  "geometry": {"coordinates":[-90.0568,36.237089],"type":"Point"}
}