{
  "type": "Feature",
  "properties": {
    "iso:country":"US",
    "sg:address":"1813 E 390th Rd",
    "sg:city":"Bolivar",
    "sg:classifiers":[
        {
            "category":"Farming",
            "subcategory":"Farm",
            "type":"Manufacturing & Wholesale Goods"
        }
    ],
    "sg:phone":"+1 417 326 5979",
    "sg:postcode":"65613",
    "sg:province":"MO",
    "wof:name":"Flying S Farm",
    "wof:placetype":"venue"
},
  "geometry": {"coordinates":[-93.488728,37.68631],"type":"Point"}
}