{
  "type": "Feature",
  "properties": {
    "iso:country":"US",
    "sg:address":"8624 N Boardwalk Ave",
    "sg:city":"Kansas City",
    "sg:classifiers":[
        {
            "category":"Shopping",
            "type":"Retail Goods"
        }
    ],
    "sg:phone":"+1 816 587 7200",
    "sg:postcode":"64154",
    "sg:province":"MO",
    "sg:tags":[
        "educational",
        "toy",
        "supply"
    ],
    "wof:name":"Noggin Noodle",
    "wof:placetype":"venue"
},
  "geometry": {"coordinates":[-94.65258799999999,39.252542],"type":"Point"}
}