{
  "type": "Feature",
  "properties": {
    "iso:country":"US",
    "sg:address":"209 W 6th St",
    "sg:city":"Joplin",
    "sg:classifiers":[
        {
            "category":"Professional",
            "subcategory":"Management & Consulting",
            "type":"Services"
        }
    ],
    "sg:phone":"+1 417 782 7966",
    "sg:postcode":"64801",
    "sg:province":"MO",
    "sg:tags":[
        "consultant",
        "business"
    ],
    "wof:name":"Joplin Business Forms",
    "wof:placetype":"venue"
},
  "geometry": {"coordinates":[-94.515558,37.085622],"type":"Point"}
}