{
  "type": "Feature",
  "properties": {
    "iso:country":"US",
    "sg:address":"15472 Manchester Rd",
    "sg:city":"Ballwin",
    "sg:classifiers":[
        {
            "category":"Shopping",
            "type":"Retail Goods"
        }
    ],
    "sg:phone":"+1 636 227 7363",
    "sg:postcode":"63011",
    "sg:province":"MO",
    "sg:tags":[
        "merchandise"
    ],
    "wof:name":"Award Associates of America",
    "wof:placetype":"venue"
},
  "geometry": {"coordinates":[-90.56430400000001,38.592841],"type":"Point"}
}