{
  "type": "Feature",
  "properties": {
    "iso:country":"US",
    "sg:address":"5489 Clarksburg Dr",
    "sg:city":"Prairie Home",
    "sg:classifiers":[
        {
            "category":"Farming",
            "subcategory":"Farm",
            "type":"Manufacturing & Wholesale Goods"
        }
    ],
    "sg:phone":"+1 660 841 5491",
    "sg:postcode":"65068",
    "sg:province":"MO",
    "sg:tags":[
        "crop",
        "general"
    ],
    "wof:name":"Carol Ernst",
    "wof:placetype":"venue"
},
  "geometry": {"coordinates":[-92.605537,38.752778],"type":"Point"}
}