{
  "type": "Feature",
  "properties": {
    "iso:country":"US",
    "sg:address":"5822 Macklind Avenue",
    "sg:city":"St Louis",
    "sg:classifiers":[
        {
            "category":"Personal",
            "subcategory":"Beauty Salon",
            "type":"Services"
        }
    ],
    "sg:phone":"+1 314 353 5580",
    "sg:postcode":"63109",
    "sg:province":"MO",
    "sg:tags":[
        "hair"
    ],
    "wof:name":"Salon Soha",
    "wof:placetype":"venue"
},
  "geometry": {"coordinates":[-90.285725,38.57839],"type":"Point"}
}