{
  "type": "Feature",
  "properties": {
    "iso:country":"US",
    "sg:address":"7751 NW Prairie View Rd",
    "sg:city":"Kansas City",
    "sg:classifiers":[
        {
            "category":"Food & Beverages",
            "subcategory":"Liquor & Beverages",
            "type":"Retail Goods"
        }
    ],
    "sg:phone":"+1 816 741 1588",
    "sg:postcode":"64151",
    "sg:province":"MO",
    "sg:tags":[
        "alcoholic"
    ],
    "wof:name":"Berbiglia Wine & Spirits",
    "wof:placetype":"venue"
},
  "geometry": {"coordinates":[-94.65876900000001,39.237532],"type":"Point"}
}