{
  "type": "Feature",
  "properties": {
    "iso:country":"US",
    "sg:address":"201 S Orange St",
    "sg:city":"Butler",
    "sg:classifiers":[
        {
            "category":"Shopping",
            "subcategory":"Gifts & Souvenirs",
            "type":"Retail Goods"
        },
        {
            "category":"Shopping",
            "subcategory":"Florist",
            "type":"Retail Goods"
        }
    ],
    "sg:phone":"+1 660 679 9988",
    "sg:postcode":"64730",
    "sg:province":"MO",
    "sg:tags":[
        "shop"
    ],
    "wof:name":"Westward Gifts",
    "wof:placetype":"venue"
},
  "geometry": {"coordinates":[-94.343763,38.254646],"type":"Point"}
}