{
  "type": "Feature",
  "properties": {
    "iso:country":"US",
    "sg:address":"1691 E Morgan St",
    "sg:city":"Boonville",
    "sg:classifiers":[
        {
            "category":"Government",
            "subcategory":"Office",
            "type":"Public Place"
        }
    ],
    "sg:phone":"+1 660 882 2335",
    "sg:postcode":"65233",
    "sg:province":"MO",
    "sg:tags":[
        "village"
    ],
    "sg:website":"www.boonville-mo.org",
    "wof:name":"Booneville City Animal Shelter",
    "wof:placetype":"venue"
},
  "geometry": {"coordinates":[-92.72677400000001,38.977774],"type":"Point"}
}