{
  "type": "Feature",
  "properties": {
    "iso:country":"US",
    "sg:address":"1010 N State Hwy 47",
    "sg:city":"Warrenton",
    "sg:classifiers":[
        {
            "category":"Food & Beverages",
            "subcategory":"Groceries & Convenience Stores",
            "type":"Retail Goods"
        }
    ],
    "sg:phone":"+1 636 456 3722",
    "sg:postcode":"63383",
    "sg:province":"MO",
    "wof:name":"Warrenton Fast Lane North",
    "wof:placetype":"venue"
},
  "geometry": {"coordinates":[-91.138386,38.822429],"type":"Point"}
}