{
  "type": "Feature",
  "properties": {
    "iso:country":"US",
    "sg:address":"2372 Goodale Ave",
    "sg:city":"St Louis",
    "sg:classifiers":[
        {
            "category":"Wholesale",
            "subcategory":"Non-durable Goods",
            "type":"Manufacturing & Wholesale Goods"
        },
        {
            "category":"Manufacturing",
            "subcategory":"Toys & Sporting Goods",
            "type":"Manufacturing & Wholesale Goods"
        }
    ],
    "sg:phone":"+1 314 423 5660",
    "sg:postcode":"63114",
    "sg:province":"MO",
    "sg:tags":[
        "stuffed",
        "doll"
    ],
    "wof:name":"Jody's Stitch N Stuff Bears",
    "wof:placetype":"venue"
},
  "geometry": {"coordinates":[-90.359157,38.699419],"type":"Point"}
}