{
  "type": "Feature",
  "properties": {
    "iso:country":"US",
    "sg:address":"5436 State Hwy 17",
    "sg:city":"Eunice",
    "sg:classifiers":[
        {
            "category":"Government",
            "subcategory":"Office",
            "type":"Public Place"
        }
    ],
    "sg:phone":"+1 417 932 5345",
    "sg:postcode":"65468",
    "sg:province":"MO",
    "sg:tags":[
        "management"
    ],
    "wof:name":"South Central Solid Waste",
    "wof:placetype":"venue"
},
  "geometry": {"coordinates":[-91.804875,37.247578],"type":"Point"}
}