{
  "type": "Feature",
  "properties": {
    "iso:country":"US",
    "sg:address":"28150 State Hwy Mm",
    "sg:city":"Ravenwood",
    "sg:classifiers":[
        {
            "category":"Shopping",
            "subcategory":"Hobbies, Toys, & Games",
            "type":"Retail Goods"
        }
    ],
    "sg:phone":"+1 660 937 3737",
    "sg:postcode":"64479",
    "sg:province":"MO",
    "wof:name":"Rainin Dolls & Treasures",
    "wof:placetype":"venue"
},
  "geometry": {"coordinates":[-94.718749,40.31467],"type":"Point"}
}