{
  "type": "Feature",
  "properties": {
    "iso:country":"US",
    "sg:address":"4226 E Woodland St",
    "sg:city":"Springfield",
    "sg:classifiers":[
        {
            "category":"Real Estate",
            "subcategory":"Developer",
            "type":"Services"
        }
    ],
    "sg:phone":"+1 417 883 3868",
    "sg:postcode":"65809",
    "sg:province":"MO",
    "sg:tags":[
        "development",
        "brokerage"
    ],
    "wof:name":"S L Stinnett Co Inc",
    "wof:placetype":"venue"
},
  "geometry": {"coordinates":[-93.20734899999999,37.162315],"type":"Point"}
}