{
  "type": "Feature",
  "properties": {
    "iso:country":"US",
    "sg:address":"36 N Franklin St",
    "sg:city":"Kingston",
    "sg:classifiers":[
        {
            "category":"Government",
            "subcategory":"Post Office",
            "type":"Public Place"
        }
    ],
    "sg:phone":"+1 816 586 2071",
    "sg:postcode":"64650",
    "sg:province":"MO",
    "wof:name":"US Post Office",
    "wof:placetype":"venue"
},
  "geometry": {"coordinates":[-94.0377,39.64307],"type":"Point"}
}