{
  "type": "Feature",
  "properties": {
    "iso:country":"US",
    "sg:address":"2336 State Rd Nn",
    "sg:city":"Climax Springs",
    "sg:classifiers":[
        {
            "category":"Manufacturing",
            "subcategory":"Tools & Machinery",
            "type":"Manufacturing & Wholesale Goods"
        }
    ],
    "sg:phone":"+1 573 347 2516",
    "sg:postcode":"65324",
    "sg:province":"MO",
    "sg:tags":[
        "lift",
        "boat"
    ],
    "wof:name":"Mo-Zark Steel Fabricators",
    "wof:placetype":"venue"
},
  "geometry": {"coordinates":[-93.051221,38.084604],"type":"Point"}
}