{
  "type": "Feature",
  "properties": {
    "iso:country":"US",
    "sg:address":"1534 Burlington St",
    "sg:city":"Kansas City",
    "sg:classifiers":[
        {
            "category":"Wholesale",
            "subcategory":"Farm Supplies",
            "type":"Manufacturing & Wholesale Goods"
        }
    ],
    "sg:phone":"+1 816 221 1080",
    "sg:postcode":"64116",
    "sg:province":"MO",
    "wof:name":"Pest Management Sup Mid-West",
    "wof:placetype":"venue"
},
  "geometry": {"coordinates":[-94.58064,39.13722],"type":"Point"}
}