{
  "type": "Feature",
  "properties": {
    "iso:country":"US",
    "sg:address":"3325 S Westwood Blvd",
    "sg:city":"Poplar Bluff",
    "sg:classifiers":[
        {
            "category":"Retail",
            "subcategory":"Auto Repair",
            "type":"Services"
        }
    ],
    "sg:phone":"+1 573 785 4450",
    "sg:postcode":"63901",
    "sg:province":"MO",
    "sg:tags":[
        "repairing",
        "automobile"
    ],
    "wof:name":"Jack's Auto Repair",
    "wof:placetype":"venue"
},
  "geometry": {"coordinates":[-90.440995,36.73223],"type":"Point"}
}