{
  "type": "Feature",
  "properties": {
    "iso:country":"US",
    "sg:address":"201 Mortimer St",
    "sg:city":"New Florence",
    "sg:classifiers":[
        {
            "category":"Government",
            "subcategory":"Fire Station",
            "type":"Public Place"
        }
    ],
    "sg:phone":"+1 573 835 2424",
    "sg:postcode":"63363",
    "sg:province":"MO",
    "sg:tags":[
        "department"
    ],
    "wof:name":"New Florence Fire Protection",
    "wof:placetype":"venue"
},
  "geometry": {"coordinates":[-91.452009,38.908802],"type":"Point"}
}