{
  "type": "Feature",
  "properties": {
    "iso:country":"US",
    "sg:address":"10166 W Florissant Ave",
    "sg:city":"St Louis",
    "sg:classifiers":[
        {
            "category":"Health Services",
            "subcategory":"Doctor",
            "type":"Services"
        }
    ],
    "sg:phone":"+1 314 867 5650",
    "sg:postcode":"63136",
    "sg:province":"MO",
    "sg:tags":[
        "dentist"
    ],
    "wof:name":"Children Dental Zone",
    "wof:placetype":"venue"
},
  "geometry": {"coordinates":[-90.279653,38.755861],"type":"Point"}
}