{
  "type": "Feature",
  "properties": {
    "iso:country":"US",
    "sg:address":"7204 Maywood Ave",
    "sg:city":"Raytown",
    "sg:classifiers":[
        {
            "category":"Professional",
            "subcategory":"Business Services",
            "type":"Services"
        }
    ],
    "sg:phone":"+1 816 743 0208",
    "sg:postcode":"64133",
    "sg:province":"MO",
    "sg:tags":[
        "consultant",
        "coach"
    ],
    "wof:name":"Environmental Const Consult",
    "wof:placetype":"venue"
},
  "geometry": {"coordinates":[-94.461912,38.991485],"type":"Point"}
}