{
  "type": "Feature",
  "properties": {
    "iso:country":"US",
    "sg:address":"205 Warren St",
    "sg:city":"Richland",
    "sg:classifiers":[
        {
            "category":"Retail",
            "subcategory":"Repair Shop",
            "type":"Services"
        }
    ],
    "sg:phone":"+1 573 765 5575",
    "sg:postcode":"65556",
    "sg:province":"MO",
    "sg:tags":[
        "bathtub",
        "sink",
        "refinishing"
    ],
    "wof:name":"American Tub & Tile",
    "wof:placetype":"venue"
},
  "geometry": {"coordinates":[-92.405823,37.862607],"type":"Point"}
}