{
  "type": "Feature",
  "properties": {
    "iso:country":"US",
    "sg:address":"1024 NE 175",
    "sg:city":"Knob Noster",
    "sg:classifiers":[
        {
            "category":"Manufacturing",
            "subcategory":"Metals",
            "type":"Manufacturing & Wholesale Goods"
        }
    ],
    "sg:phone":"+1 660 563 2131",
    "sg:postcode":"65336",
    "sg:province":"MO",
    "sg:tags":[
        "mfg",
        "mirror"
    ],
    "wof:name":"SMS Manufacturing",
    "wof:placetype":"venue"
},
  "geometry": {"coordinates":[-93.548644,38.779177],"type":"Point"}
}