{
  "type": "Feature",
  "properties": {
    "iso:country":"US",
    "sg:address":"2508 SE Nottingham Dr",
    "sg:city":"Lees Summit",
    "sg:classifiers":[
        {
            "category":"Building & Trades",
            "subcategory":"Construction",
            "type":"Services"
        }
    ],
    "sg:phone":"+1 816 524 6304",
    "sg:postcode":"64063",
    "sg:province":"MO",
    "sg:tags":[
        "house"
    ],
    "wof:name":"Stone Construction",
    "wof:placetype":"venue"
},
  "geometry": {"coordinates":[-94.320014,38.914223],"type":"Point"}
}