{
  "type": "Feature",
  "properties": {
    "iso:country":"US",
    "sg:address":"4553 McCausland Ave",
    "sg:city":"St Louis",
    "sg:classifiers":[
        {
            "category":"Building & Trades",
            "subcategory":"Construction",
            "type":"Services"
        }
    ],
    "sg:phone":"+1 314 842 9208",
    "sg:postcode":"63109",
    "sg:province":"MO",
    "sg:tags":[
        "contractor"
    ],
    "wof:name":"K T Freund Contracting",
    "wof:placetype":"venue"
},
  "geometry": {"coordinates":[-90.31321,38.589781],"type":"Point"}
}