{
  "type": "Feature",
  "properties": {
    "iso:country":"US",
    "sg:address":"875 Rampart Dr",
    "sg:city":"St Louis",
    "sg:classifiers":[
        {
            "category":"Health Services",
            "subcategory":"Doctor",
            "type":"Services"
        }
    ],
    "sg:phone":"+1 314 862 2311",
    "sg:postcode":"63122",
    "sg:province":"MO",
    "sg:tags":[
        "dentist"
    ],
    "wof:name":"R D Kloetzer DDS",
    "wof:placetype":"venue"
},
  "geometry": {"coordinates":[-90.38908000000001,38.609106],"type":"Point"}
}