{
  "type": "Feature",
  "properties": {
    "iso:country":"US",
    "sg:address":"1400 Ferguson Ave",
    "sg:city":"St Louis",
    "sg:classifiers":[
        {
            "category":"Manufacturing",
            "subcategory":"Electronics",
            "type":"Manufacturing & Wholesale Goods"
        }
    ],
    "sg:phone":"+1 314 569 0141",
    "sg:postcode":"63133",
    "sg:province":"MO",
    "sg:tags":[
        "equipment",
        "household"
    ],
    "wof:name":"SLM Electronics",
    "wof:placetype":"venue"
},
  "geometry": {"coordinates":[-90.30705399999999,38.683617],"type":"Point"}
}