{
  "type": "Feature",
  "properties": {
    "iso:country":"US",
    "sg:address":"8500 NW River Park Dr",
    "sg:city":"Parkville",
    "sg:classifiers":[
        {
            "category":"Professional",
            "type":"Services"
        }
    ],
    "sg:phone":"+1 816 741 2816",
    "sg:postcode":"64152",
    "sg:province":"MO",
    "sg:tags":[
        "purchasing"
    ],
    "wof:name":"Kansas City Higher Education",
    "wof:placetype":"venue"
},
  "geometry": {"coordinates":[-94.67901500000001,39.187722],"type":"Point"}
}