{
  "type": "Feature",
  "properties": {
    "iso:country":"US",
    "sg:address":"1850 S Glenstone Ave",
    "sg:city":"Springfield",
    "sg:classifiers":[
        {
            "category":"Professional",
            "subcategory":"Accounting & Tax Preparation",
            "type":"Services"
        }
    ],
    "sg:phone":"+1 417 823 7228",
    "sg:postcode":"65804",
    "sg:province":"MO",
    "wof:name":"William Glover CPA",
    "wof:placetype":"venue"
},
  "geometry": {"coordinates":[-93.262231,37.180648],"type":"Point"}
}