{
  "type": "Feature",
  "properties": {
    "iso:country":"US",
    "sg:address":"900 Kennett St",
    "sg:city":"Kennett",
    "sg:classifiers":[
        {
            "category":"Government",
            "subcategory":"Office",
            "type":"Public Place"
        }
    ],
    "sg:phone":"+1 573 888 4612",
    "sg:postcode":"63857",
    "sg:province":"MO",
    "sg:tags":[
        "township",
        "government-city",
        "village"
    ],
    "wof:name":"Kennett Housing Authority",
    "wof:placetype":"venue"
},
  "geometry": {"coordinates":[-90.05555699999999,36.229279],"type":"Point"}
}