{
  "type": "Feature",
  "properties": {
    "iso:country":"US",
    "sg:address":"1155 Wentzville Pkwy",
    "sg:city":"Wentzville",
    "sg:classifiers":[
        {
            "category":"Professional",
            "type":"Services"
        },
        {
            "category":"Restaurant",
            "type":"Food & Drink"
        },
        {
            "category":"Retail",
            "subcategory":"Event Space",
            "type":"Services"
        }
    ],
    "sg:phone":"+1 636 332 6757",
    "sg:postcode":"63385",
    "sg:province":"MO",
    "sg:tags":[
        "grill",
        "bar",
        "facility",
        "hall",
        "reception",
        "caterer",
        "banquet"
    ],
    "sg:website":"http://www.rizzosbarandgrill.com",
    "wof:name":"Rizzo's Bar & Grill",
    "wof:placetype":"venue"
},
  "geometry": {"coordinates":[-90.86381299999999,38.824969],"type":"Point"}
}