{
  "type": "Feature",
  "properties": {
    "iso:country":"US",
    "sg:address":"1330 Copper Dr",
    "sg:city":"Cape Girardeau",
    "sg:classifiers":[
        {
            "category":"Wholesale",
            "subcategory":"Poultry",
            "type":"Manufacturing & Wholesale Goods"
        }
    ],
    "sg:phone":"+1 573 651 3940",
    "sg:postcode":"63701",
    "sg:province":"MO",
    "wof:name":"Midwest Food & Poultry Inc",
    "wof:placetype":"venue"
},
  "geometry": {"coordinates":[-89.573566,37.325092],"type":"Point"}
}