{
  "type": "Feature",
  "properties": {
    "iso:country":"US",
    "sg:address":"4231 S Hocker St",
    "sg:city":"Independence",
    "sg:classifiers":[
        {
            "category":"Real Estate",
            "subcategory":"Real Estate Agent",
            "type":"Services"
        }
    ],
    "sg:phone":"+1 816 303 5300",
    "sg:postcode":"64055",
    "sg:province":"MO",
    "sg:tags":[
        "consultant"
    ],
    "sg:website":"www.xceligent.com",
    "wof:name":"Xceligent",
    "wof:placetype":"venue"
},
  "geometry": {"coordinates":[-94.410408,39.043962],"type":"Point"}
}