{
  "type": "Feature",
  "properties": {
    "iso:country":"US",
    "sg:address":"61 Sunset Ln",
    "sg:city":"Winfield",
    "sg:classifiers":[
        {
            "category":"Building & Trades",
            "subcategory":"Landscaping Services",
            "type":"Services"
        }
    ],
    "sg:phone":"+1 636 462 2817",
    "sg:postcode":"63389",
    "sg:province":"MO",
    "sg:tags":[
        "tree"
    ],
    "wof:name":"Lentz Tree Service",
    "wof:placetype":"venue"
},
  "geometry": {"coordinates":[-90.864093,39.008462],"type":"Point"}
}