{
  "type": "Feature",
  "properties": {
    "iso:country":"US",
    "sg:address":"85 Jason Ct",
    "sg:city":"Saint Charles",
    "sg:classifiers":[
        {
            "category":"Building & Trades",
            "subcategory":"Equipment Rental",
            "type":"Services"
        }
    ],
    "sg:phone":"+1 319 622 6473",
    "sg:postcode":"63304",
    "sg:province":"MO",
    "sg:tags":[
        "medical"
    ],
    "wof:name":"Medical Perceptions",
    "wof:placetype":"venue"
},
  "geometry": {"coordinates":[-90.655378,38.725885],"type":"Point"}
}