{
  "type": "Feature",
  "properties": {
    "iso:country":"US",
    "sg:address":"302 S Spruce St",
    "sg:city":"Bonne Terre",
    "sg:classifiers":[
        {
            "category":"Building & Trades",
            "subcategory":"Construction",
            "type":"Services"
        }
    ],
    "sg:phone":"+1 573 358 4026",
    "sg:postcode":"63628",
    "sg:province":"MO",
    "sg:tags":[
        "house"
    ],
    "wof:name":"Vaughn Home Improvement",
    "wof:placetype":"venue"
},
  "geometry": {"coordinates":[-90.560254,37.92086],"type":"Point"}
}