{
  "type": "Feature",
  "properties": {
    "iso:country":"US",
    "sg:address":"221 N Olive St",
    "sg:city":"Pacific",
    "sg:classifiers":[
        {
            "category":"Travel",
            "subcategory":"Travel Agent",
            "type":"Entertainment"
        }
    ],
    "sg:phone":"+1 636 271 2300",
    "sg:postcode":"63069",
    "sg:province":"MO",
    "sg:tags":[
        "operator",
        "tour",
        "agency",
        "bureau"
    ],
    "wof:name":"Saint Louis Group Travel",
    "wof:placetype":"venue"
},
  "geometry": {"coordinates":[-90.738179,38.483388],"type":"Point"}
}