{
  "type": "Feature",
  "properties": {
    "iso:country":"US",
    "sg:address":"5601 Telegraph Rd",
    "sg:city":"Saint Louis",
    "sg:classifiers":[
        {
            "category":"Restaurant",
            "type":"Food & Drink"
        }
    ],
    "sg:menulink":"http://www.allmenus.com/mo/oakville/190911-burger-king/menu/",
    "sg:phone":"+1 614 894 6987",
    "sg:postcode":"63129",
    "sg:province":"MO",
    "sg:tags":[
        "burger",
        "american"
    ],
    "wof:name":"Burger King",
    "wof:placetype":"venue"
},
  "geometry": {"coordinates":[-90.305514,38.469707],"type":"Point"}
}