{
  "type": "Feature",
  "properties": {
    "iso:country":"US",
    "sg:address":"336 Front St",
    "sg:city":"Thayer",
    "sg:classifiers":[
        {
            "category":"Home & Garden",
            "subcategory":"Garden Supply",
            "type":"Retail Goods"
        }
    ],
    "sg:phone":"+1 417 264 3025",
    "sg:postcode":"65791",
    "sg:province":"MO",
    "sg:tags":[
        "fertilizer"
    ],
    "wof:name":"Thayer Plant Food Inc",
    "wof:placetype":"venue"
},
  "geometry": {"coordinates":[-91.5402,36.527333],"type":"Point"}
}