{
  "type": "Feature",
  "properties": {
    "iso:country":"US",
    "sg:address":"6125 Brookside Blvd",
    "sg:city":"Kansas City",
    "sg:classifiers":[
        {
            "category":"Wholesale",
            "subcategory":"Electrical",
            "type":"Manufacturing & Wholesale Goods"
        }
    ],
    "sg:phone":"+1 816 333 0527",
    "sg:postcode":"64113",
    "sg:province":"MO",
    "sg:tags":[
        "supply"
    ],
    "wof:name":"Graham Electric Supply Co",
    "wof:placetype":"venue"
},
  "geometry": {"coordinates":[-94.589917,39.017383],"type":"Point"}
}