{
  "type": "Feature",
  "properties": {
    "iso:country":"US",
    "sg:address":"4109 Cook Rd",
    "sg:city":"Saint Joseph",
    "sg:classifiers":[
        {
            "category":"Professional",
            "subcategory":"Business Services",
            "type":"Services"
        }
    ],
    "sg:phone":"+1 816 279 8079",
    "sg:postcode":"64505",
    "sg:province":"MO",
    "wof:name":"Critchfield Crane Service",
    "wof:placetype":"venue"
},
  "geometry": {"coordinates":[-94.795993,39.806799],"type":"Point"}
}