{
  "type": "Feature",
  "properties": {
    "iso:country":"US",
    "sg:address":"12125 Woodcrest Executive Dr",
    "sg:city":"Saint Louis",
    "sg:classifiers":[
        {
            "category":"Health Services",
            "subcategory":"Health Practitioner",
            "type":"Services"
        }
    ],
    "sg:phone":"+1 314 275 8599",
    "sg:postcode":"63141",
    "sg:province":"MO",
    "wof:name":"Mary Fitzgibbons",
    "wof:placetype":"venue"
},
  "geometry": {"coordinates":[-90.452589,38.675015],"type":"Point"}
}