{
  "type": "Feature",
  "properties": {
    "iso:country":"US",
    "sg:address":"12425 Liv 224",
    "sg:city":"Chillicothe",
    "sg:classifiers":[
        {
            "category":"Farming",
            "subcategory":"Farm & Veterinary Services",
            "type":"Manufacturing & Wholesale Goods"
        }
    ],
    "sg:phone":"+1 660 646 5165",
    "sg:postcode":"64601",
    "sg:province":"MO",
    "sg:tags":[
        "breeder",
        "livestock"
    ],
    "wof:name":"Trans Ova Genetics",
    "wof:placetype":"venue"
},
  "geometry": {"coordinates":[-93.54789700000001,39.84798],"type":"Point"}
}