{
  "type": "Feature",
  "properties": {
    "iso:country":"US",
    "sg:address":"305 State Hwy 39",
    "sg:city":"Aurora",
    "sg:classifiers":[
        {
            "category":"Government",
            "subcategory":"Office",
            "type":"Public Place"
        }
    ],
    "sg:phone":"+1 417 678 3050",
    "sg:postcode":"65605",
    "sg:province":"MO",
    "sg:tags":[
        "village"
    ],
    "wof:name":"Aurora Sewer Treatment Plant",
    "wof:placetype":"venue"
},
  "geometry": {"coordinates":[-93.72700500000001,36.97571],"type":"Point"}
}