{
  "type": "Feature",
  "properties": {
    "iso:country":"US",
    "sg:address":"416 E Walnut St",
    "sg:city":"Columbia",
    "sg:classifiers":[
        {
            "category":"Professional",
            "type":"Services"
        }
    ],
    "sg:phone":"+1 573 441 1030",
    "sg:postcode":"65201",
    "sg:province":"MO",
    "sg:tags":[
        "establishment"
    ],
    "wof:name":"Tc A Inc Voice & Data Cmmnctns",
    "wof:placetype":"venue"
},
  "geometry": {"coordinates":[-92.331936,38.952575],"type":"Point"}
}