{
  "type": "Feature",
  "properties": {
    "iso:country":"US",
    "sg:address":"2456 N Kansas Expy",
    "sg:city":"Springfield",
    "sg:classifiers":[
        {
            "category":"Restaurant",
            "type":"Food & Drink"
        }
    ],
    "sg:menulink":"http://www.allmenus.com/mo/springfield/54937-papa-murphys/menu/",
    "sg:phone":"+1 417 831 0313",
    "sg:postcode":"65803",
    "sg:province":"MO",
    "sg:tags":[
        "american",
        "pizza"
    ],
    "wof:name":"Papa Murphy's",
    "wof:placetype":"venue"
},
  "geometry": {"coordinates":[-93.31104499999999,37.244766],"type":"Point"}
}