{
  "type": "Feature",
  "properties": {
    "addr:full":"504 E Mount Vernon St Nixa MO 65714",
    "addr:housenumber":"504",
    "addr:postcode":"65714",
    "addr:street":"E Mount Vernon St",
    "iso:country":"US",
    "sg:address":"504 E Mount Vernon St",
    "sg:city":"Nixa",
    "sg:classifiers":[
        {
            "category":"Insurance",
            "subcategory":"Insurance Agent",
            "type":"Services"
        }
    ],
    "sg:phone":"+1 417 725 2621",
    "sg:postcode":"65714",
    "sg:province":"MO",
    "wof:name":"State Farm Insurance",
    "wof:placetype":"venue"
},
  "geometry": {"coordinates":[-93.28787,37.043224],"type":"Point"}
}