{
  "type": "Feature",
  "properties": {
    "iso:country":"US",
    "sg:address":"605 N Valley Dr",
    "sg:city":"Boonville",
    "sg:phone":"+1 660 882 6718",
    "sg:postcode":"65233",
    "sg:province":"MO",
    "sg:tags":[
        "beef",
        "farm",
        "corn",
        "soybean",
        "cattle",
        "feedlot"
    ],
    "wof:name":"James Vieth",
    "wof:placetype":"venue"
},
  "geometry": {"coordinates":[-92.736198,38.962979],"type":"Point"}
}