{
  "type": "Feature",
  "properties": {
    "iso:country":"US",
    "sg:address":"1112 W Aylor St",
    "sg:city":"Webb City",
    "sg:classifiers":[
        {
            "category":"Organizations",
            "subcategory":"Religious Organization",
            "type":"Services"
        }
    ],
    "sg:phone":"+1 417 673 0477",
    "sg:postcode":"64870",
    "sg:province":"MO",
    "wof:name":"Kings Way Full Gospel Church",
    "wof:placetype":"venue"
},
  "geometry": {"coordinates":[-94.476129,37.152404],"type":"Point"}
}