{
  "type": "Feature",
  "properties": {
    "iso:country":"US",
    "sg:address":"3101 Broadway St",
    "sg:city":"Kansas City",
    "sg:classifiers":[
        {
            "category":"Building & Trades",
            "subcategory":"Cleaning & Sanitation",
            "type":"Services"
        }
    ],
    "sg:phone":"+1 816 931 1134",
    "sg:postcode":"64111",
    "sg:province":"MO",
    "sg:tags":[
        "janitor"
    ],
    "wof:name":"H & M Inc",
    "wof:placetype":"venue"
},
  "geometry": {"coordinates":[-94.59004,39.069382],"type":"Point"}
}