{
  "type": "Feature",
  "properties": {
    "iso:country":"US",
    "sg:address":"431 Mill St",
    "sg:city":"New Madrid",
    "sg:classifiers":[
        {
            "category":"Education",
            "subcategory":"Library",
            "type":"Public Place"
        }
    ],
    "sg:phone":"+1 573 748 2378",
    "sg:postcode":"63869",
    "sg:province":"MO",
    "wof:name":"New Madrid Memorial Library",
    "wof:placetype":"venue"
},
  "geometry": {"coordinates":[-89.525884,36.586306],"type":"Point"}
}