{
  "type": "Feature",
  "properties": {
    "iso:country":"US",
    "sg:address":"136 Aspencade Cir",
    "sg:city":"St Peters",
    "sg:classifiers":[
        {
            "category":"Professional",
            "subcategory":"Management & Consulting",
            "type":"Services"
        }
    ],
    "sg:phone":"+1 314 235 1763",
    "sg:postcode":"63376",
    "sg:province":"MO",
    "sg:tags":[
        "promotion",
        "sales"
    ],
    "wof:name":"Saving Cents",
    "wof:placetype":"venue"
},
  "geometry": {"coordinates":[-90.68113,38.78812],"type":"Point"}
}