{
  "type": "Feature",
  "properties": {
    "iso:country":"US",
    "sg:address":"150 Jungermann Rd",
    "sg:city":"St Peters",
    "sg:classifiers":[
        {
            "category":"Personal",
            "type":"Services"
        },
        {
            "category":"Recreation",
            "type":"Entertainment"
        }
    ],
    "sg:phone":"+1 636 939 3397",
    "sg:postcode":"63376",
    "sg:province":"MO",
    "sg:tags":[
        "therapist",
        "massage"
    ],
    "wof:name":"Nirvana Thrapeutic Massage Ctr",
    "wof:placetype":"venue"
},
  "geometry": {"coordinates":[-90.576319,38.793206],"type":"Point"}
}