{
  "type": "Feature",
  "properties": {
    "iso:country":"US",
    "sg:address":"115 Bus Loop 70 W",
    "sg:city":"Columbia",
    "sg:classifiers":[
        {
            "category":"Health Services",
            "subcategory":"Doctor",
            "type":"Services"
        }
    ],
    "sg:phone":"+1 573 882 8545",
    "sg:postcode":"65203",
    "sg:province":"MO",
    "sg:tags":[
        "medical"
    ],
    "wof:name":"Kuvshinoff II Boris W MD",
    "wof:placetype":"venue"
},
  "geometry": {"coordinates":[-92.34023000000001,38.965386],"type":"Point"}
}