{
  "type": "Feature",
  "properties": {
    "iso:country":"US",
    "sg:address":"251 Old Sulphur Spring Rd",
    "sg:city":"Ballwin",
    "sg:classifiers":[
        {
            "category":"Professional",
            "subcategory":"Management & Consulting",
            "type":"Services"
        }
    ],
    "sg:phone":"+1 314 272 0252",
    "sg:postcode":"63021",
    "sg:province":"MO",
    "sg:tags":[
        "science",
        "consultant",
        "academic"
    ],
    "wof:name":"Customized Consulting Linda Goodwin",
    "wof:placetype":"venue"
},
  "geometry": {"coordinates":[-90.514697,38.590693],"type":"Point"}
}