{
  "type": "Feature",
  "properties": {
    "iso:country":"US",
    "sg:address":"803 NE Lakewood Blvd",
    "sg:city":"Lees Summit",
    "sg:classifiers":[
        {
            "category":"Shopping",
            "subcategory":"Florist",
            "type":"Retail Goods"
        }
    ],
    "sg:phone":"+1 816 373 3937",
    "sg:postcode":"64064",
    "sg:province":"MO",
    "wof:name":"Lakewood Floral",
    "wof:placetype":"venue"
},
  "geometry": {"coordinates":[-94.359208,39.004325],"type":"Point"}
}