{
  "type": "Feature",
  "properties": {
    "iso:country":"US",
    "sg:address":"2100 E Grand Blvd",
    "sg:city":"Saint Louis",
    "sg:classifiers":[
        {
            "category":"Home & Garden",
            "subcategory":"Household Appliances",
            "type":"Retail Goods"
        },
        {
            "category":"Home & Garden",
            "subcategory":"Furniture",
            "type":"Retail Goods"
        }
    ],
    "sg:phone":"+1 314 534 4800",
    "sg:postcode":"63107",
    "sg:province":"MO",
    "sg:tags":[
        "repair",
        "store"
    ],
    "wof:name":"Watson Furniture",
    "wof:placetype":"venue"
},
  "geometry": {"coordinates":[-90.20970199999999,38.669998],"type":"Point"}
}