{
  "type": "Feature",
  "properties": {
    "iso:country":"US",
    "sg:address":"930 Hwy Y",
    "sg:city":"O Fallon",
    "sg:classifiers":[
        {
            "category":"Building & Trades",
            "subcategory":"Landscaping Services",
            "type":"Services"
        }
    ],
    "sg:phone":"+1 636 272 8622",
    "sg:postcode":"63366",
    "sg:province":"MO",
    "sg:tags":[
        "lawn",
        "maintenance",
        "grounds"
    ],
    "wof:name":"Custom Cut Lawn Care Inc",
    "wof:placetype":"venue"
},
  "geometry": {"coordinates":[-90.72747,38.868969],"type":"Point"}
}