{
  "type": "Feature",
  "properties": {
    "iso:country":"US",
    "sg:address":"36485 Mcdonald Rd",
    "sg:city":"Salisbury",
    "sg:classifiers":[
        {
            "category":"Professional",
            "subcategory":"Management & Consulting",
            "type":"Services"
        }
    ],
    "sg:phone":"+1 660 777 3373",
    "sg:postcode":"65281",
    "sg:province":"MO",
    "sg:tags":[
        "farm"
    ],
    "wof:name":"Carl Boss",
    "wof:placetype":"venue"
},
  "geometry": {"coordinates":[-92.78064,39.489735],"type":"Point"}
}