{
  "type": "Feature",
  "properties": {
    "iso:country":"US",
    "sg:address":"7010 E 136th St",
    "sg:city":"Grandview",
    "sg:classifiers":[
        {
            "category":"Education",
            "subcategory":"School",
            "type":"Public Place"
        }
    ],
    "sg:phone":"+1 816 316 5525",
    "sg:postcode":"64030",
    "sg:province":"MO",
    "wof:name":"Meadowmere Elem Sch",
    "wof:placetype":"venue"
},
  "geometry": {"coordinates":[-94.51249,38.877755],"type":"Point"}
}