{
  "type": "Feature",
  "properties": {
    "iso:country":"US",
    "sg:address":"509 Olive St",
    "sg:city":"St Louis",
    "sg:classifiers":[
        {
            "category":"Restaurant",
            "type":"Food & Drink"
        }
    ],
    "sg:phone":"+1 314 241 9800",
    "sg:postcode":"63101",
    "sg:province":"MO",
    "sg:tags":[
        "eating"
    ],
    "wof:name":"Mid-America Chili's",
    "wof:placetype":"venue"
},
  "geometry": {"coordinates":[-90.190185,38.627978],"type":"Point"}
}