{
  "type": "Feature",
  "properties": {
    "iso:country":"US",
    "sg:address":"550 Co Rd 105",
    "sg:city":"Fayette",
    "sg:classifiers":[
        {
            "category":"Retail",
            "subcategory":"Auto Repair",
            "type":"Services"
        }
    ],
    "sg:phone":"+1 660 248 3190",
    "sg:postcode":"65248",
    "sg:province":"MO",
    "sg:tags":[
        "body"
    ],
    "wof:name":"B TS Auto Bdy Pnt Refinishing",
    "wof:placetype":"venue"
},
  "geometry": {"coordinates":[-92.58778599999999,39.160269],"type":"Point"}
}