{
  "type": "Feature",
  "properties": {
    "iso:country":"US",
    "sg:address":"1 Ashley St",
    "sg:city":"Saint Louis",
    "sg:classifiers":[
        {
            "category":"Building & Trades",
            "subcategory":"Cleaning & Sanitation",
            "type":"Services"
        }
    ],
    "sg:phone":"+1 314 621 3550",
    "sg:postcode":"63102",
    "sg:province":"MO",
    "sg:tags":[
        "generation",
        "steam",
        "sales"
    ],
    "wof:name":"St Louis 620",
    "wof:placetype":"venue"
},
  "geometry": {"coordinates":[-90.18280300000001,38.63635],"type":"Point"}
}