{
  "type": "Feature",
  "properties": {
    "iso:country":"US",
    "sg:address":"3628 Antonia Woods Dr",
    "sg:city":"Imperial",
    "sg:classifiers":[
        {
            "category":"Manufacturing",
            "subcategory":"Printing",
            "type":"Manufacturing & Wholesale Goods"
        }
    ],
    "sg:phone":"+1 636 942 2788",
    "sg:postcode":"63052",
    "sg:province":"MO",
    "sg:tags":[
        "commercial"
    ],
    "wof:name":"Jennemann Enterprise",
    "wof:placetype":"venue"
},
  "geometry": {"coordinates":[-90.479556,38.354339],"type":"Point"}
}