{
  "type": "Feature",
  "properties": {
    "iso:country":"US",
    "sg:address":"660 Washam Rd",
    "sg:city":"Clever",
    "sg:classifiers":[
        {
            "category":"Structure",
            "subcategory":"Office Building",
            "type":"Public Place"
        }
    ],
    "sg:phone":"+1 417 743 3340",
    "sg:postcode":"65631",
    "sg:province":"MO",
    "sg:tags":[
        "park"
    ],
    "wof:name":"Hedge Stone Properties",
    "wof:placetype":"venue"
},
  "geometry": {"coordinates":[-93.48791900000001,37.000558],"type":"Point"}
}