{
  "type": "Feature",
  "properties": {
    "iso:country":"US",
    "sg:address":"204 Main St",
    "sg:city":"Noel",
    "sg:classifiers":[
        {
            "category":"Food & Beverages",
            "subcategory":"Groceries & Convenience Stores",
            "type":"Retail Goods"
        }
    ],
    "sg:phone":"+1 417 475 3434",
    "sg:postcode":"64854",
    "sg:province":"MO",
    "sg:tags":[
        "grocer"
    ],
    "wof:name":"Harp's Food Stores",
    "wof:placetype":"venue"
},
  "geometry": {"coordinates":[-94.48760900000001,36.545605],"type":"Point"}
}