{
  "type": "Feature",
  "properties": {
    "iso:country":"US",
    "sg:address":"304 Old 40 Hwy",
    "sg:city":"Bates City",
    "sg:classifiers":[
        {
            "category":"Shopping",
            "subcategory":"Tobacco",
            "type":"Retail Goods"
        }
    ],
    "sg:phone":"+1 816 690 4646",
    "sg:postcode":"64011",
    "sg:province":"MO",
    "sg:tags":[
        "cigarette",
        "cigar",
        "dealer"
    ],
    "wof:name":"Tobacco House",
    "wof:placetype":"venue"
},
  "geometry": {"coordinates":[-94.072119,39.010942],"type":"Point"}
}