{
  "type": "Feature",
  "properties": {
    "iso:country":"US",
    "sg:address":"1845 E 9th St",
    "sg:city":"Trenton",
    "sg:classifiers":[
        {
            "category":"Retail",
            "subcategory":"Auto Repair",
            "type":"Services"
        }
    ],
    "sg:phone":"+1 660 359 6260",
    "sg:postcode":"64683",
    "sg:province":"MO",
    "sg:tags":[
        "glass",
        "replacement"
    ],
    "wof:name":"G&G Auto Glass Service",
    "wof:placetype":"venue"
},
  "geometry": {"coordinates":[-93.598296,40.074405],"type":"Point"}
}