{
  "type": "Feature",
  "properties": {
    "iso:country":"US",
    "sg:address":"809 E Pearce Blvd",
    "sg:city":"Wentzville",
    "sg:classifiers":[
        {
            "category":"Real Estate",
            "subcategory":"Real Estate Agent",
            "type":"Services"
        }
    ],
    "sg:phone":"+1 636 327 4971",
    "sg:postcode":"63385",
    "sg:province":"MO",
    "wof:name":"Rothermich Real Estate",
    "wof:placetype":"venue"
},
  "geometry": {"coordinates":[-90.84620099999999,38.813325],"type":"Point"}
}