{
  "type": "Feature",
  "properties": {
    "iso:country":"US",
    "sg:address":"13894 Manchester Rd",
    "sg:city":"Ballwin",
    "sg:classifiers":[
        {
            "category":"Retail",
            "subcategory":"Car Wash",
            "type":"Services"
        }
    ],
    "sg:phone":"+1 636 227 9274",
    "sg:postcode":"63011",
    "sg:province":"MO",
    "sg:website":"http://www.mickeyscarwash.com",
    "wof:name":"Mickeys West County Car Wash",
    "wof:placetype":"venue"
},
  "geometry": {"coordinates":[-90.485058,38.59656],"type":"Point"}
}