{
  "type": "Feature",
  "properties": {
    "iso:country":"US",
    "sg:address":"523 N Walnut St Ste A",
    "sg:city":"Dexter",
    "sg:classifiers":[
        {
            "category":"Personal",
            "subcategory":"Massage",
            "type":"Services"
        },
        {
            "category":"Personal",
            "subcategory":"Beauty Salon",
            "type":"Services"
        },
        {
            "category":"Personal",
            "subcategory":"Day Spa",
            "type":"Services"
        }
    ],
    "sg:phone":"+1 573 624 4070",
    "sg:postcode":"63841",
    "sg:province":"MO",
    "sg:tags":[
        "therapist"
    ],
    "wof:name":"Designs On You",
    "wof:placetype":"venue"
},
  "geometry": {"coordinates":[-89.957686,36.798423],"type":"Point"}
}