{
  "type": "Feature",
  "properties": {
    "iso:country":"US",
    "sg:address":"15243 Lochcrest Ct",
    "sg:city":"Chesterfield",
    "sg:classifiers":[
        {
            "category":"Health Services",
            "subcategory":"Doctor",
            "type":"Services"
        }
    ],
    "sg:phone":"+1 636 530 7824",
    "sg:postcode":"63017",
    "sg:province":"MO",
    "sg:tags":[
        "medical"
    ],
    "wof:name":"David Carr MD",
    "wof:placetype":"venue"
},
  "geometry": {"coordinates":[-90.557507,38.621934],"type":"Point"}
}