{
  "type": "Feature",
  "properties": {
    "iso:country":"US",
    "sg:address":"6309 Natural Bridge Rd",
    "sg:city":"St Louis",
    "sg:classifiers":[
        {
            "category":"Personal",
            "subcategory":"Beauty Salon",
            "type":"Services"
        }
    ],
    "sg:phone":"+1 314 385 5583",
    "sg:postcode":"63121",
    "sg:province":"MO",
    "wof:name":"N Tha Cut Salon & Carwash",
    "wof:placetype":"venue"
},
  "geometry": {"coordinates":[-90.279456,38.692967],"type":"Point"}
}