{
  "type": "Feature",
  "properties": {
    "iso:country":"US",
    "sg:address":"4449 S Davidson Dr",
    "sg:city":"Independence",
    "sg:classifiers":[
        {
            "category":"Retail",
            "subcategory":"Laundry & Dry Cleaning",
            "type":"Services"
        }
    ],
    "sg:phone":"+1 816 350 3197",
    "sg:postcode":"64055",
    "sg:province":"MO",
    "wof:name":"Sewing By Sandy",
    "wof:placetype":"venue"
},
  "geometry": {"coordinates":[-94.37648,39.041518],"type":"Point"}
}