{
  "type": "Feature",
  "properties": {
    "iso:country":"US",
    "sg:address":"2024 E 32nd St",
    "sg:city":"Joplin",
    "sg:classifiers":[
        {
            "category":"Banks & Credit Unions",
            "subcategory":"Investment Brokerage",
            "type":"Services"
        },
        {
            "category":"Banks & Credit Unions",
            "subcategory":"Financial Services",
            "type":"Services"
        }
    ],
    "sg:phone":"+1 417 623 4030",
    "sg:postcode":"64804",
    "sg:province":"MO",
    "sg:tags":[
        "advisory",
        "security",
        "planner"
    ],
    "sg:website":"http://www.donoradvisedfunds.com",
    "wof:name":"Raymond James Financial Services",
    "wof:placetype":"venue"
},
  "geometry": {"coordinates":[-94.535214,37.055383],"type":"Point"}
}