{
  "type": "Feature",
  "properties": {
    "iso:country":"US",
    "sg:address":"2406 Edmond St",
    "sg:city":"Saint Joseph",
    "sg:classifiers":[
        {
            "category":"Building & Trades",
            "subcategory":"Landscaping Services",
            "type":"Services"
        }
    ],
    "sg:phone":"+1 816 232 7851",
    "sg:postcode":"64501",
    "sg:province":"MO",
    "wof:name":"Turf Works",
    "wof:placetype":"venue"
},
  "geometry": {"coordinates":[-94.83036800000001,39.765824],"type":"Point"}
}