{
  "type": "Feature",
  "properties": {
    "iso:country":"US",
    "sg:address":"100 South St",
    "sg:city":"Bethany",
    "sg:classifiers":[
        {
            "category":"Social Services",
            "subcategory":"Adult Care",
            "type":"Services"
        }
    ],
    "sg:phone":"+1 660 425 3244",
    "sg:postcode":"64424",
    "sg:province":"MO",
    "sg:tags":[
        "retardation",
        "home",
        "dev",
        "disabled"
    ],
    "wof:name":"Harrison County Group Home",
    "wof:placetype":"venue"
},
  "geometry": {"coordinates":[-94.056107,40.257963],"type":"Point"}
}