{
  "type": "Feature",
  "properties": {
    "iso:country":"US",
    "sg:address":"4005 Ripa Ave",
    "sg:city":"Saint Louis",
    "sg:classifiers":[
        {
            "category":"Health Services",
            "subcategory":"Nursing And Care Facility",
            "type":"Services"
        }
    ],
    "sg:phone":"+1 314 544 1111",
    "sg:postcode":"63125",
    "sg:province":"MO",
    "sg:tags":[
        "int",
        "skilled"
    ],
    "wof:name":"Alexian Bros Sherbrooke Vlg",
    "wof:placetype":"venue"
},
  "geometry": {"coordinates":[-90.303077,38.533682],"type":"Point"}
}