{
  "type": "Feature",
  "properties": {
    "iso:country":"US",
    "sg:address":"1606 E Kansas Ave",
    "sg:city":"Independence",
    "sg:classifiers":[
        {
            "category":"Personal",
            "subcategory":"Beauty Salon",
            "type":"Services"
        }
    ],
    "sg:phone":"+1 816 461 1991",
    "sg:postcode":"64050",
    "sg:province":"MO",
    "sg:tags":[
        "shop"
    ],
    "wof:name":"Styles By Donna",
    "wof:placetype":"venue"
},
  "geometry": {"coordinates":[-94.38778000000001,39.090245],"type":"Point"}
}