{
  "type": "Feature",
  "properties": {
    "iso:country":"US",
    "sg:address":"411 Northview Rd",
    "sg:city":"Nixa",
    "sg:classifiers":[
        {
            "category":"Restaurant",
            "type":"Food & Drink"
        }
    ],
    "sg:menulink":"http://www.allmenus.com/mo/union-chapel/60389-cashew-inn-cashew-out/menu/",
    "sg:phone":"+1 417 725 2699",
    "sg:postcode":"65714",
    "sg:province":"MO",
    "sg:tags":[
        "asian",
        "chinese"
    ],
    "wof:name":"Cashew Inn Cashew Out",
    "wof:placetype":"venue"
},
  "geometry": {"coordinates":[-93.301574,37.054606],"type":"Point"}
}