{
  "type": "Feature",
  "properties": {
    "iso:country":"US",
    "sg:address":"413 Main St",
    "sg:city":"Polo",
    "sg:classifiers":[
        {
            "category":"Restaurant",
            "type":"Food & Drink"
        }
    ],
    "sg:phone":"+1 660 354 2500",
    "sg:postcode":"64671",
    "sg:province":"MO",
    "wof:name":"Cookin' From Scratch",
    "wof:placetype":"venue"
},
  "geometry": {"coordinates":[-94.039599,39.554079],"type":"Point"}
}