{
  "type": "Feature",
  "properties": {
    "iso:country":"US",
    "sg:address":"325 McDonnell Blvd",
    "sg:city":"Hazelwood",
    "sg:classifiers":[
        {
            "category":"Real Estate",
            "subcategory":"Real Estate Agent",
            "type":"Services"
        }
    ],
    "sg:phone":"+1 314 232 7000",
    "sg:postcode":"63042",
    "sg:province":"MO",
    "wof:name":"Cushman & Wakefield of MO",
    "wof:placetype":"venue"
},
  "geometry": {"coordinates":[-90.374514,38.76774],"type":"Point"}
}