{
  "type": "Feature",
  "properties": {
    "addr:full":"1414 E Primrose St Springfield MO 65804",
    "addr:housenumber":"1414",
    "addr:postcode":"65804",
    "addr:street":"E Primrose St",
    "iso:country":"US",
    "sg:address":"1414 E Primrose St",
    "sg:city":"Springfield",
    "sg:classifiers":[
        {
            "category":"Banks & Credit Unions",
            "subcategory":"Investment Brokerage",
            "type":"Services"
        }
    ],
    "sg:phone":"+1 417 875 6700",
    "sg:postcode":"65804",
    "sg:province":"MO",
    "sg:tags":[
        "advisory",
        "financial"
    ],
    "wof:name":"Raymond James Financial Svc",
    "wof:placetype":"venue"
},
  "geometry": {"coordinates":[-93.27127299999999,37.14777],"type":"Point"}
}