{
  "type": "Feature",
  "properties": {
    "iso:country":"US",
    "sg:address":"233 E Douglas St",
    "sg:city":"Clinton",
    "sg:classifiers":[
        {
            "category":"Manufacturing",
            "subcategory":"Printing",
            "type":"Manufacturing & Wholesale Goods"
        },
        {
            "category":"Manufacturing",
            "subcategory":"Motor Vehicles & Parts",
            "type":"Manufacturing & Wholesale Goods"
        }
    ],
    "sg:phone":"+1 660 885 6181",
    "sg:postcode":"64735",
    "sg:province":"MO",
    "sg:tags":[
        "screen",
        "mfg",
        "trimming"
    ],
    "wof:name":"Creative Screen Prtg Embrdring",
    "wof:placetype":"venue"
},
  "geometry": {"coordinates":[-93.773155,38.380544],"type":"Point"}
}