{
  "type": "Feature",
  "properties": {
    "iso:country":"US",
    "sg:address":"7728 Augusta Ave",
    "sg:city":"Saint Louis",
    "sg:classifiers":[
        {
            "category":"Building & Trades",
            "subcategory":"Construction",
            "type":"Services"
        }
    ],
    "sg:phone":"+1 314 369 8218",
    "sg:postcode":"63121",
    "sg:province":"MO",
    "sg:tags":[
        "carpentry",
        "contractor"
    ],
    "wof:name":"Doug Aikin",
    "wof:placetype":"venue"
},
  "geometry": {"coordinates":[-90.304688,38.708178],"type":"Point"}
}