{
  "type": "Feature",
  "properties": {
    "iso:country":"US",
    "sg:address":"1615 Grant St",
    "sg:city":"Unionville",
    "sg:classifiers":[
        {
            "category":"Health Services",
            "subcategory":"Chiropractor",
            "type":"Services"
        }
    ],
    "sg:phone":"+1 660 947 2116",
    "sg:postcode":"63565",
    "sg:province":"MO",
    "wof:name":"A R Hammett III DC",
    "wof:placetype":"venue"
},
  "geometry": {"coordinates":[-93.002944,40.476025],"type":"Point"}
}