{
  "type": "Feature",
  "properties": {
    "iso:country":"US",
    "sg:address":"405 S White Oak Rd",
    "sg:city":"Marshfield",
    "sg:classifiers":[
        {
            "category":"Building & Trades",
            "subcategory":"Plumbing",
            "type":"Services"
        }
    ],
    "sg:phone":"+1 417 859 4504",
    "sg:postcode":"65706",
    "sg:province":"MO",
    "sg:tags":[
        "plumbing",
        "repair"
    ],
    "wof:name":"Dr Plumber",
    "wof:placetype":"venue"
},
  "geometry": {"coordinates":[-92.91171199999999,37.335868],"type":"Point"}
}