{
  "type": "Feature",
  "properties": {
    "iso:country":"US",
    "sg:address":"13642 Bonanza Rd",
    "sg:city":"Higginsville",
    "sg:phone":"+1 660 584 7032",
    "sg:postcode":"64037",
    "sg:province":"MO",
    "sg:tags":[
        "farm",
        "corn",
        "grain",
        "cash"
    ],
    "wof:name":"Scott Cretzmeyer",
    "wof:placetype":"venue"
},
  "geometry": {"coordinates":[-93.678099,39.10131],"type":"Point"}
}