{
  "type": "Feature",
  "properties": {
    "iso:country":"US",
    "sg:address":"4175 Chippewa St",
    "sg:city":"St Louis",
    "sg:classifiers":[
        {
            "category":"Retail",
            "subcategory":"Storage",
            "type":"Services"
        }
    ],
    "sg:phone":"+1 314 773 8600",
    "sg:postcode":"63116",
    "sg:province":"MO",
    "sg:tags":[
        "self"
    ],
    "sg:website":"ezmini.com",
    "wof:name":"EZ Storage",
    "wof:placetype":"venue"
},
  "geometry": {"coordinates":[-90.259894,38.59062],"type":"Point"}
}