{
  "type": "Feature",
  "properties": {
    "iso:country":"US",
    "sg:address":"733 N New Ballas Rd",
    "sg:city":"Saint Louis",
    "sg:classifiers":[
        {
            "category":"Restaurant",
            "type":"Food & Drink"
        }
    ],
    "sg:phone":"+1 314 993 3387",
    "sg:postcode":"63141",
    "sg:province":"MO",
    "sg:tags":[
        "eating"
    ],
    "wof:name":"Zang CHI",
    "wof:placetype":"venue"
},
  "geometry": {"coordinates":[-90.44336800000001,38.669886],"type":"Point"}
}