{
  "type": "Feature",
  "properties": {
    "iso:country":"US",
    "sg:address":"6903 Lansdown Ave",
    "sg:city":"St Louis",
    "sg:classifiers":[
        {
            "category":"Shopping",
            "subcategory":"Pharmacy",
            "type":"Retail Goods"
        }
    ],
    "sg:phone":"+1 314 781 2445",
    "sg:postcode":"63109",
    "sg:province":"MO",
    "sg:tags":[
        "drugstore"
    ],
    "wof:name":"Lindenwood Drugs",
    "wof:placetype":"venue"
},
  "geometry": {"coordinates":[-90.310058,38.591596],"type":"Point"}
}