{
  "type": "Feature",
  "properties": {
    "iso:country":"US",
    "sg:address":"1466 Blackwell Ferry Rd",
    "sg:city":"Kirbyville",
    "sg:classifiers":[
        {
            "category":"Place Of Worship",
            "type":"Public Place"
        }
    ],
    "sg:phone":"+1 417 334 2618",
    "sg:postcode":"65679",
    "sg:province":"MO",
    "sg:tags":[
        "church"
    ],
    "wof:name":"Future Men For God",
    "wof:placetype":"venue"
},
  "geometry": {"coordinates":[-93.054921,36.633311],"type":"Point"}
}