{
  "type": "Feature",
  "properties": {
    "iso:country":"US",
    "sg:address":"101 S Prospect Ave",
    "sg:city":"Sedalia",
    "sg:classifiers":[
        {
            "category":"Health Services",
            "subcategory":"Medical Lab",
            "type":"Services"
        }
    ],
    "sg:phone":"+1 660 826 3775",
    "sg:postcode":"65301",
    "sg:province":"MO",
    "sg:tags":[
        "laboratory"
    ],
    "wof:name":"Downtown Dental Lab",
    "wof:placetype":"venue"
},
  "geometry": {"coordinates":[-93.237364,38.712382],"type":"Point"}
}