{
  "type": "Feature",
  "properties": {
    "iso:country":"US",
    "sg:address":"436 N Brunswick Ave",
    "sg:city":"Marshall",
    "sg:classifiers":[
        {
            "category":"Farming",
            "subcategory":"Farm",
            "type":"Manufacturing & Wholesale Goods"
        }
    ],
    "sg:phone":"+1 660 886 9225",
    "sg:postcode":"65340",
    "sg:province":"MO",
    "wof:name":"R And C Farm Services",
    "wof:placetype":"venue"
},
  "geometry": {"coordinates":[-93.190004,39.124612],"type":"Point"}
}