{
  "type": "Feature",
  "properties": {
    "iso:country":"US",
    "sg:address":"2247 S Grand Blvd",
    "sg:city":"Saint Louis",
    "sg:classifiers":[
        {
            "category":"Retail",
            "subcategory":"Veterinary Services",
            "type":"Services"
        }
    ],
    "sg:phone":"+1 314 772 4413",
    "sg:postcode":"63104",
    "sg:province":"MO",
    "wof:name":"Philip Wagenknecht",
    "wof:placetype":"venue"
},
  "geometry": {"coordinates":[-90.24087900000001,38.609669],"type":"Point"}
}