{
  "type": "Feature",
  "properties": {
    "iso:country":"US",
    "sg:address":"107 S Main St",
    "sg:city":"Webb City",
    "sg:classifiers":[
        {
            "category":"Home & Garden",
            "subcategory":"Building Materials",
            "type":"Retail Goods"
        }
    ],
    "sg:phone":"+1 417 673 5627",
    "sg:postcode":"64870",
    "sg:province":"MO",
    "wof:name":"Burrington Window & Glass Co",
    "wof:placetype":"venue"
},
  "geometry": {"coordinates":[-94.46315199999999,37.143843],"type":"Point"}
}