{
  "type": "Feature",
  "properties": {
    "iso:country":"US",
    "sg:address":"10214 Manchester Rd",
    "sg:city":"Saint Louis",
    "sg:classifiers":[
        {
            "category":"Restaurant",
            "type":"Food & Drink"
        }
    ],
    "sg:phone":"+1 314 966 2433",
    "sg:postcode":"63122",
    "sg:province":"MO",
    "wof:name":"Pizza World",
    "wof:placetype":"venue"
},
  "geometry": {"coordinates":[-90.396642,38.600709],"type":"Point"}
}