{
  "type": "Feature",
  "properties": {
    "iso:country":"US",
    "sg:address":"15722 Co Rd 55",
    "sg:city":"Jasper",
    "sg:classifiers":[
        {
            "category":"Farming",
            "subcategory":"Farm",
            "type":"Manufacturing & Wholesale Goods"
        }
    ],
    "sg:phone":"+1 417 537 4298",
    "sg:postcode":"64755",
    "sg:province":"MO",
    "sg:tags":[
        "crop",
        "general"
    ],
    "wof:name":"E J Brinkhoff",
    "wof:placetype":"venue"
},
  "geometry": {"coordinates":[-94.151313,37.287074],"type":"Point"}
}