{
  "type": "Feature",
  "properties": {
    "iso:country":"US",
    "sg:address":"568 Old Smizer Mill Rd",
    "sg:city":"Fenton",
    "sg:classifiers":[
        {
            "category":"Restaurant",
            "type":"Food & Drink"
        }
    ],
    "sg:phone":"+1 636 343 9268",
    "sg:postcode":"63026",
    "sg:province":"MO",
    "sg:tags":[
        "eating"
    ],
    "wof:name":"B Donovan's St Louis Grill",
    "wof:placetype":"venue"
},
  "geometry": {"coordinates":[-90.45193999999999,38.516287],"type":"Point"}
}