{
  "type": "Feature",
  "properties": {
    "iso:country":"US",
    "sg:address":"4001 E 4 Ridge Rd",
    "sg:city":"Imperial",
    "sg:classifiers":[
        {
            "category":"Manufacturing",
            "subcategory":"Pet Food",
            "type":"Manufacturing & Wholesale Goods"
        },
        {
            "category":"Farming",
            "subcategory":"Farm",
            "type":"Manufacturing & Wholesale Goods"
        }
    ],
    "sg:phone":"+1 636 948 3473",
    "sg:postcode":"63052",
    "sg:province":"MO",
    "sg:tags":[
        "hay"
    ],
    "wof:name":"Ralph Lammert",
    "wof:placetype":"venue"
},
  "geometry": {"coordinates":[-90.480553,38.396294],"type":"Point"}
}