{
  "type": "Feature",
  "properties": {
    "iso:country":"US",
    "sg:address":"111 S 10th St",
    "sg:city":"Saint Louis",
    "sg:classifiers":[
        {
            "category":"Organizations",
            "subcategory":"Non-profit Organization",
            "type":"Services"
        }
    ],
    "sg:phone":"+1 314 539 2773",
    "sg:postcode":"63102",
    "sg:province":"MO",
    "sg:tags":[
        "program",
        "prevention",
        "crime"
    ],
    "wof:name":"Operation Weed & Seed St Louis",
    "wof:placetype":"venue"
},
  "geometry": {"coordinates":[-90.19645800000001,38.624622],"type":"Point"}
}