{
  "type": "Feature",
  "properties": {
    "addr:full":"1600 Heritage Lndg St Peters MO 63303",
    "addr:housenumber":"1600",
    "addr:postcode":"63303",
    "addr:street":"Heritage Lndg",
    "iso:country":"US",
    "sg:address":"1600 Heritage Lndg",
    "sg:city":"St Peters",
    "sg:classifiers":[
        {
            "category":"Personal",
            "type":"Services"
        }
    ],
    "sg:phone":"+1 636 441 9107",
    "sg:postcode":"63303",
    "sg:province":"MO",
    "sg:tags":[
        "credit",
        "debt",
        "counseling"
    ],
    "wof:name":"Consumer Credit Counseling Svc",
    "wof:placetype":"venue"
},
  "geometry": {"coordinates":[-90.549791,38.750351],"type":"Point"}
}