{
  "type": "Feature",
  "properties": {
    "iso:country":"US",
    "sg:address":"2228 S Maiden Ln",
    "sg:city":"Joplin",
    "sg:classifiers":[
        {
            "category":"Health Services",
            "subcategory":"Doctor",
            "type":"Services"
        }
    ],
    "sg:phone":"+1 417 624 1069",
    "sg:postcode":"64804",
    "sg:province":"MO",
    "wof:name":"Mark Woodin DDS",
    "wof:placetype":"venue"
},
  "geometry": {"coordinates":[-94.531949,37.066602],"type":"Point"}
}