{
  "type": "Feature",
  "properties": {
    "iso:country":"US",
    "sg:address":"113 Dockside Dr",
    "sg:city":"Blue Springs",
    "sg:classifiers":[
        {
            "category":"Professional",
            "subcategory":"Management & Consulting",
            "type":"Services"
        }
    ],
    "sg:phone":"+1 816 228 5748",
    "sg:postcode":"64015",
    "sg:province":"MO",
    "sg:tags":[
        "business"
    ],
    "wof:name":"Phillips Keynote Consulting",
    "wof:placetype":"venue"
},
  "geometry": {"coordinates":[-94.311448,39.021448],"type":"Point"}
}