{
  "type": "Feature",
  "properties": {
    "iso:country":"US",
    "sg:address":"226 River Valley Dr",
    "sg:city":"Chesterfield",
    "sg:classifiers":[
        {
            "category":"Professional",
            "subcategory":"Engineering",
            "type":"Services"
        },
        {
            "category":"Building & Trades",
            "subcategory":"Construction",
            "type":"Services"
        }
    ],
    "sg:phone":"+1 314 469 1190",
    "sg:postcode":"63017",
    "sg:province":"MO",
    "sg:tags":[
        "control",
        "corrosion"
    ],
    "wof:name":"Robert B Puyear Pe",
    "wof:placetype":"venue"
},
  "geometry": {"coordinates":[-90.50321099999999,38.685768],"type":"Point"}
}