{
  "type": "Feature",
  "properties": {
    "iso:country":"US",
    "sg:address":"1170 State Hwy B",
    "sg:city":"Liberty",
    "sg:classifiers":[
        {
            "category":"Insurance",
            "subcategory":"Insurance Agent",
            "type":"Services"
        }
    ],
    "sg:phone":"+1 816 792 2999",
    "sg:postcode":"64068",
    "sg:province":"MO",
    "wof:name":"AFLAC",
    "wof:placetype":"venue"
},
  "geometry": {"coordinates":[-94.399208,39.258873],"type":"Point"}
}