{
  "type": "Feature",
  "properties": {
    "iso:country":"US",
    "sg:address":"82 S Main St",
    "sg:city":"Fair Grove",
    "sg:classifiers":[
        {
            "category":"Shopping",
            "subcategory":"Used Merchandise",
            "type":"Retail Goods"
        }
    ],
    "sg:phone":"+1 417 759 1122",
    "sg:postcode":"65648",
    "sg:province":"MO",
    "sg:tags":[
        "clothing"
    ],
    "wof:name":"Growin Like A Weed",
    "wof:placetype":"venue"
},
  "geometry": {"coordinates":[-93.151145,37.382971],"type":"Point"}
}