{
  "type": "Feature",
  "properties": {
    "iso:country":"US",
    "sg:address":"213 N Jefferson St",
    "sg:city":"Vandalia",
    "sg:classifiers":[
        {
            "category":"Retail",
            "subcategory":"Repair Shop",
            "type":"Services"
        }
    ],
    "sg:phone":"+1 573 594 3258",
    "sg:postcode":"63382",
    "sg:province":"MO",
    "sg:tags":[
        "electrical"
    ],
    "wof:name":"Smittys Electronic Repair Ser",
    "wof:placetype":"venue"
},
  "geometry": {"coordinates":[-91.489929,39.309484],"type":"Point"}
}