{
  "type": "Feature",
  "properties": {
    "iso:country":"US",
    "sg:address":"2906 Union Blvd",
    "sg:city":"Saint Louis",
    "sg:classifiers":[
        {
            "category":"Shopping",
            "subcategory":"Used Merchandise",
            "type":"Retail Goods"
        }
    ],
    "sg:phone":"+1 314 385 8083",
    "sg:postcode":"63115",
    "sg:province":"MO",
    "sg:tags":[
        "shop",
        "pawn"
    ],
    "wof:name":"Four-M's Pawn Shop",
    "wof:placetype":"venue"
},
  "geometry": {"coordinates":[-90.261398,38.674599],"type":"Point"}
}