{
  "type": "Feature",
  "properties": {
    "iso:country":"US",
    "sg:address":"1000 Huntington Rd",
    "sg:city":"Kansas City",
    "sg:classifiers":[
        {
            "category":"Professional",
            "subcategory":"Lawyer & Legal Services",
            "type":"Services"
        }
    ],
    "sg:phone":"+1 816 333 3222",
    "sg:postcode":"64113",
    "sg:province":"MO",
    "wof:name":"Dietrich William G Atty R",
    "wof:placetype":"venue"
},
  "geometry": {"coordinates":[-94.5996,39.019132],"type":"Point"}
}