{
  "type": "Feature",
  "properties": {
    "iso:country":"US",
    "sg:address":"1122 Oklahoma Ave",
    "sg:city":"Trenton",
    "sg:classifiers":[
        {
            "category":"Wholesale",
            "subcategory":"Farm Supplies",
            "type":"Manufacturing & Wholesale Goods"
        }
    ],
    "sg:phone":"+1 660 359 3608",
    "sg:postcode":"64683",
    "sg:province":"MO",
    "sg:tags":[
        "livestock"
    ],
    "wof:name":"Swift & Company",
    "wof:placetype":"venue"
},
  "geometry": {"coordinates":[-93.59708000000001,40.07659],"type":"Point"}
}