{
  "type": "Feature",
  "properties": {
    "iso:country":"US",
    "sg:address":"3861 South Ave",
    "sg:city":"Springfield",
    "sg:classifiers":[
        {
            "category":"Home & Garden",
            "subcategory":"Furniture",
            "type":"Retail Goods"
        }
    ],
    "sg:phone":"+1 417 889 3200",
    "sg:postcode":"65807",
    "sg:province":"MO",
    "sg:tags":[
        "store"
    ],
    "wof:name":"Wheeler's Furniture Downtown",
    "wof:placetype":"venue"
},
  "geometry": {"coordinates":[-93.292936,37.143817],"type":"Point"}
}