{
  "type": "Feature",
  "properties": {
    "iso:country":"US",
    "sg:address":"1880 Little Brennan Rd",
    "sg:city":"High Ridge",
    "sg:classifiers":[
        {
            "category":"Autos & Motor Vehicles",
            "subcategory":"Fuel & Gas Station",
            "type":"Retail Goods"
        }
    ],
    "sg:phone":"+1 636 677 2883",
    "sg:postcode":"63049",
    "sg:province":"MO",
    "sg:tags":[
        "oil"
    ],
    "sg:website":"www.u-gas.com",
    "wof:name":"U-Gas Carwash & Food Mart",
    "wof:placetype":"venue"
},
  "geometry": {"coordinates":[-90.50224799999999,38.490223],"type":"Point"}
}