{
  "type": "Feature",
  "properties": {
    "iso:country":"US",
    "sg:address":"3508 S Range Line Rd",
    "sg:city":"Joplin",
    "sg:classifiers":[
        {
            "category":"Travel",
            "subcategory":"Hotels & Motels",
            "type":"Entertainment"
        }
    ],
    "sg:phone":"+1 877 574 2464",
    "sg:postcode":"64804",
    "sg:province":"MO",
    "sg:tags":[
        "lodging"
    ],
    "sg:website":"http://book.bestwestern.com/bestwestern/priceAvail.do?propertyCode=26153&cm_mmc=IYP-_-YP-_-property-_-26153",
    "wof:name":"Best Western Oasis Inn & Suites",
    "wof:placetype":"venue"
},
  "geometry": {"coordinates":[-94.47851,37.051792],"type":"Point"}
}