{
  "type": "Feature",
  "properties": {
    "iso:country":"US",
    "sg:address":"18401 Edison Ave",
    "sg:city":"Chesterfield",
    "sg:classifiers":[
        {
            "category":"Real Estate",
            "subcategory":"Developer",
            "type":"Services"
        }
    ],
    "sg:phone":"+1 636 537 0016",
    "sg:postcode":"63005",
    "sg:province":"MO",
    "wof:name":"Pott & Phenie Foundation",
    "wof:placetype":"venue"
},
  "geometry": {"coordinates":[-90.646519,38.66391],"type":"Point"}
}