{
  "type": "Feature",
  "properties": {
    "iso:country":"US",
    "sg:address":"2712 N 10th St",
    "sg:city":"Saint Louis",
    "sg:classifiers":[
        {
            "category":"Building & Trades",
            "subcategory":"Construction",
            "type":"Services"
        }
    ],
    "sg:phone":"+1 314 482 2396",
    "sg:postcode":"63102",
    "sg:province":"MO",
    "sg:tags":[
        "roofing"
    ],
    "wof:name":"Gipson Home Improvement",
    "wof:placetype":"venue"
},
  "geometry": {"coordinates":[-90.19280500000001,38.652368],"type":"Point"}
}