{
  "type": "Feature",
  "properties": {
    "iso:country":"US",
    "sg:address":"4009 Gene Field Rd",
    "sg:city":"St Joseph",
    "sg:classifiers":[
        {
            "category":"Health Services",
            "subcategory":"Nursing And Care Facility",
            "type":"Services"
        }
    ],
    "sg:phone":"+1 816 364 1526",
    "sg:postcode":"64506",
    "sg:province":"MO",
    "sg:tags":[
        "skilled",
        "home",
        "convalescent"
    ],
    "wof:name":"Carriage Square Hlth Care Ctr",
    "wof:placetype":"venue"
},
  "geometry": {"coordinates":[-94.792749,39.792128],"type":"Point"}
}