{
  "type": "Feature",
  "properties": {
    "iso:country":"US",
    "sg:address":"5731 Pebble Acres",
    "sg:city":"High Ridge",
    "sg:classifiers":[
        {
            "category":"Shopping",
            "subcategory":"Hobbies, Toys, & Games",
            "type":"Retail Goods"
        }
    ],
    "sg:phone":"+1 636 458 1989",
    "sg:postcode":"63049",
    "sg:province":"MO",
    "wof:name":"Crafty Cupboard Inc",
    "wof:placetype":"venue"
},
  "geometry": {"coordinates":[-90.53900899999999,38.476733],"type":"Point"}
}