{
  "type": "Feature",
  "properties": {
    "iso:country":"US",
    "sg:address":"6076 S Farm Rd 67",
    "sg:city":"Republic",
    "sg:classifiers":[
        {
            "category":"Building & Trades",
            "subcategory":"Construction",
            "type":"Services"
        }
    ],
    "sg:phone":"+1 417 732 5665",
    "sg:postcode":"65738",
    "sg:province":"MO",
    "sg:tags":[
        "repairing",
        "remodeling",
        "contractor"
    ],
    "wof:name":"Vauble Construction",
    "wof:placetype":"venue"
},
  "geometry": {"coordinates":[-93.50724099999999,37.105877],"type":"Point"}
}