{
  "type": "Feature",
  "properties": {
    "iso:country":"US",
    "sg:address":"1726 Annie Malone Dr",
    "sg:city":"St Louis",
    "sg:classifiers":[
        {
            "category":"Organizations",
            "subcategory":"Religious Organization",
            "type":"Services"
        }
    ],
    "sg:phone":"+1 314 531 1102",
    "sg:postcode":"63113",
    "sg:province":"MO",
    "sg:tags":[
        "church"
    ],
    "wof:name":"Great Day Missionary Baptist",
    "wof:placetype":"venue"
},
  "geometry": {"coordinates":[-90.239418,38.655825],"type":"Point"}
}