{
  "type": "Feature",
  "properties": {
    "iso:country":"US",
    "sg:address":"11899 New Halls Ferry Rd",
    "sg:city":"Florissant",
    "sg:classifiers":[
        {
            "category":"Banks & Credit Unions",
            "subcategory":"Bank",
            "type":"Services"
        }
    ],
    "sg:phone":"+1 314 838 4666",
    "sg:postcode":"63033",
    "sg:province":"MO",
    "wof:name":"St Louis Postal Credit Union",
    "wof:placetype":"venue"
},
  "geometry": {"coordinates":[-90.278541,38.781628],"type":"Point"}
}