{
  "type": "Feature",
  "properties": {
    "iso:country":"US",
    "sg:address":"6304 N Oak Trfy",
    "sg:city":"Kansas City",
    "sg:classifiers":[
        {
            "category":"Bars & Pubs",
            "type":"Food & Drink"
        }
    ],
    "sg:menulink":"http://www.allmenus.com/mo/gallatin/10302-smokehouse-bar-b-que/menu/",
    "sg:phone":"+1 816 454 4500",
    "sg:postcode":"64118",
    "sg:province":"MO",
    "sg:tags":[
        "american"
    ],
    "wof:name":"Smokehouse Bar-B-Que",
    "wof:placetype":"venue"
},
  "geometry": {"coordinates":[-94.57627599999999,39.208698],"type":"Point"}
}