{
  "type": "Feature",
  "properties": {
    "iso:country":"US",
    "sg:address":"4313 S Oak Ave",
    "sg:city":"Springfield",
    "sg:classifiers":[
        {
            "category":"Professional",
            "subcategory":"Advertising",
            "type":"Services"
        }
    ],
    "sg:phone":"+1 417 864 8336",
    "sg:postcode":"65804",
    "sg:province":"MO",
    "sg:tags":[
        "distribution"
    ],
    "wof:name":"Youngs Innovations",
    "wof:placetype":"venue"
},
  "geometry": {"coordinates":[-93.23269999999999,37.134838],"type":"Point"}
}