{
  "type": "Feature",
  "properties": {
    "iso:country":"US",
    "sg:address":"705 Lexington Park",
    "sg:city":"Florissant",
    "sg:classifiers":[
        {
            "category":"Building & Trades",
            "subcategory":"Construction",
            "type":"Services"
        }
    ],
    "sg:phone":"+1 314 830 4349",
    "sg:postcode":"63031",
    "sg:province":"MO",
    "sg:tags":[
        "company"
    ],
    "wof:name":"Mark Lee Construction",
    "wof:placetype":"venue"
},
  "geometry": {"coordinates":[-90.32589299999999,38.816199],"type":"Point"}
}