{
  "type": "Feature",
  "properties": {
    "iso:country":"US",
    "sg:address":"2958A E Division St",
    "sg:city":"Springfield",
    "sg:classifiers":[
        {
            "category":"Manufacturing",
            "subcategory":"Tools & Machinery",
            "type":"Manufacturing & Wholesale Goods"
        },
        {
            "category":"Manufacturing",
            "subcategory":"Metals",
            "type":"Manufacturing & Wholesale Goods"
        },
        {
            "category":"Building & Trades",
            "subcategory":"Plumbing",
            "type":"Services"
        }
    ],
    "sg:phone":"+1 417 831 7182",
    "sg:postcode":"65803",
    "sg:province":"MO",
    "sg:tags":[
        "jig",
        "stamping",
        "fixture",
        "maker",
        "die"
    ],
    "wof:name":"C&M Tool",
    "wof:placetype":"venue"
},
  "geometry": {"coordinates":[-93.23436100000001,37.224481],"type":"Point"}
}