{
  "type": "Feature",
  "properties": {
    "iso:country":"US",
    "sg:address":"1600 N Missouri Ave",
    "sg:city":"Marceline",
    "sg:classifiers":[
        {
            "category":"Shopping",
            "subcategory":"Stationery & Office Supplies",
            "type":"Retail Goods"
        }
    ],
    "sg:phone":"+1 660 376 2755",
    "sg:postcode":"64658",
    "sg:province":"MO",
    "sg:tags":[
        "map"
    ],
    "sg:website":"www.marcelinemapping.com",
    "wof:name":"Marceline Mapping",
    "wof:placetype":"venue"
},
  "geometry": {"coordinates":[-92.94197200000001,39.728683],"type":"Point"}
}