{
  "type": "Feature",
  "properties": {
    "iso:country":"US",
    "sg:address":"208 S 3rd St",
    "sg:city":"King City",
    "sg:classifiers":[
        {
            "category":"Farming",
            "subcategory":"Livestock Farm",
            "type":"Manufacturing & Wholesale Goods"
        }
    ],
    "sg:phone":"+1 660 535 6285",
    "sg:postcode":"64463",
    "sg:province":"MO",
    "sg:tags":[
        "beef",
        "feedlot",
        "cattle"
    ],
    "wof:name":"Jim Black",
    "wof:placetype":"venue"
},
  "geometry": {"coordinates":[-94.517197,40.049966],"type":"Point"}
}