{
  "type": "Feature",
  "properties": {
    "iso:country":"US",
    "sg:address":"11405 Anderson St",
    "sg:city":"Independence",
    "sg:classifiers":[
        {
            "category":"Health Services",
            "subcategory":"Doctor",
            "type":"Services"
        }
    ],
    "sg:phone":"+1 816 252 1860",
    "sg:postcode":"64054",
    "sg:province":"MO",
    "wof:name":"John W Hellstein",
    "wof:placetype":"venue"
},
  "geometry": {"coordinates":[-94.441532,39.107705],"type":"Point"}
}