{
  "type": "Feature",
  "properties": {
    "iso:country":"US",
    "sg:address":"6281 Cedar Oaks Dr",
    "sg:city":"Fulton",
    "sg:classifiers":[
        {
            "category":"Professional",
            "subcategory":"Detective & Security Services",
            "type":"Services"
        }
    ],
    "sg:phone":"+1 573 642 5318",
    "sg:postcode":"65251",
    "sg:province":"MO",
    "sg:tags":[
        "system"
    ],
    "wof:name":"F G Baysinger",
    "wof:placetype":"venue"
},
  "geometry": {"coordinates":[-92.020965,38.837168],"type":"Point"}
}