{
  "type": "Feature",
  "properties": {
    "iso:country":"US",
    "sg:address":"4200 US Hwy 54",
    "sg:city":"Osage Beach",
    "sg:classifiers":[
        {
            "category":"Shopping",
            "subcategory":"Bicycles & Sporting Goods",
            "type":"Retail Goods"
        }
    ],
    "sg:phone":"+1 573 348 5770",
    "sg:postcode":"65065",
    "sg:province":"MO",
    "sg:tags":[
        "equipment",
        "golf"
    ],
    "wof:name":"Golf USA",
    "wof:placetype":"venue"
},
  "geometry": {"coordinates":[-92.619936,38.148424],"type":"Point"}
}