{
  "type": "Feature",
  "properties": {
    "addr:full":"410 S Madison St Webb City MO 64870",
    "addr:housenumber":"410",
    "addr:postcode":"64870",
    "addr:street":"S Madison St",
    "iso:country":"US",
    "sg:address":"410 S Madison St",
    "sg:city":"Webb City",
    "sg:classifiers":[
        {
            "category":"Restaurant",
            "type":"Food & Drink"
        }
    ],
    "sg:menulink":"http://www.allmenus.com/mo/joplin/194368-mcdonalds/menu/",
    "sg:postcode":"64870",
    "sg:province":"MO",
    "sg:tags":[
        "burger",
        "american"
    ],
    "wof:name":"McDonald's",
    "wof:placetype":"venue"
},
  "geometry": {"coordinates":[-94.47472999999999,37.141687],"type":"Point"}
}