{
  "type": "Feature",
  "properties": {
    "iso:country":"US",
    "sg:address":"225 Turner St",
    "sg:city":"Chillicothe",
    "sg:classifiers":[
        {
            "category":"Wholesale",
            "subcategory":"Scrap",
            "type":"Manufacturing & Wholesale Goods"
        }
    ],
    "sg:phone":"+1 660 646 3665",
    "sg:postcode":"64601",
    "sg:province":"MO",
    "sg:tags":[
        "material"
    ],
    "wof:name":"Knouse Iron Metal",
    "wof:placetype":"venue"
},
  "geometry": {"coordinates":[-93.541516,39.791065],"type":"Point"}
}