{
  "type": "Feature",
  "properties": {
    "iso:country":"US",
    "sg:address":"808 Madison St",
    "sg:city":"Pleasant Hill",
    "sg:classifiers":[
        {
            "category":"Professional",
            "subcategory":"Management & Consulting",
            "type":"Services"
        }
    ],
    "sg:phone":"+1 816 540 4156",
    "sg:postcode":"64080",
    "sg:province":"MO",
    "sg:tags":[
        "fire",
        "consultant",
        "protection"
    ],
    "wof:name":"U S Exhaust",
    "wof:placetype":"venue"
},
  "geometry": {"coordinates":[-94.258045,38.795708],"type":"Point"}
}