{
  "type": "Feature",
  "properties": {
    "iso:country":"US",
    "sg:address":"4800 Old Cape Rd E",
    "sg:city":"Jackson",
    "sg:classifiers":[
        {
            "category":"Autos & Motor Vehicles",
            "subcategory":"Fuel & Gas Station",
            "type":"Retail Goods"
        }
    ],
    "sg:phone":"+1 573 243 6449",
    "sg:postcode":"63755",
    "sg:province":"MO",
    "sg:tags":[
        "equipment",
        "supply"
    ],
    "sg:website":"http://www.neumayerequipment.com",
    "wof:name":"Neumayer Equipment Co Inc",
    "wof:placetype":"venue"
},
  "geometry": {"coordinates":[-89.61017,37.350035],"type":"Point"}
}