{
  "type": "Feature",
  "properties": {
    "iso:country":"US",
    "sg:address":"2275 Rivoli Pl",
    "sg:city":"Florissant",
    "sg:classifiers":[
        {
            "category":"Wholesale",
            "subcategory":"Machinery & Supplies",
            "type":"Manufacturing & Wholesale Goods"
        }
    ],
    "sg:phone":"+1 314 830 3253",
    "sg:postcode":"63031",
    "sg:province":"MO",
    "sg:tags":[
        "janitor"
    ],
    "wof:name":"Housekeeping Solutions",
    "wof:placetype":"venue"
},
  "geometry": {"coordinates":[-90.32514399999999,38.810696],"type":"Point"}
}