{
  "type": "Feature",
  "properties": {
    "iso:country":"US",
    "sg:address":"214 W F St",
    "sg:city":"Joplin",
    "sg:classifiers":[
        {
            "category":"Shopping",
            "subcategory":"Gifts & Souvenirs",
            "type":"Retail Goods"
        }
    ],
    "sg:phone":"+1 417 624 1798",
    "sg:postcode":"64801",
    "sg:province":"MO",
    "sg:tags":[
        "porcelain",
        "product"
    ],
    "wof:name":"Danish Porcelain Imports",
    "wof:placetype":"venue"
},
  "geometry": {"coordinates":[-94.514914,37.0985],"type":"Point"}
}