{
  "type": "Feature",
  "properties": {
    "iso:country":"US",
    "sg:address":"608 Jefferson St",
    "sg:city":"Saint Charles",
    "sg:classifiers":[
        {
            "category":"Autos & Motor Vehicles",
            "subcategory":"Automobile Sales",
            "type":"Retail Goods"
        }
    ],
    "sg:phone":"+1 636 946 6340",
    "sg:postcode":"63301",
    "sg:province":"MO",
    "wof:name":"Baue Funeral Home",
    "wof:placetype":"venue"
},
  "geometry": {"coordinates":[-90.489513,38.783925],"type":"Point"}
}