{
  "type": "Feature",
  "properties": {
    "iso:country":"US",
    "sg:address":"2600 Clark Ave",
    "sg:city":"St Louis",
    "sg:classifiers":[
        {
            "category":"Professional",
            "subcategory":"Computer Services",
            "type":"Services"
        }
    ],
    "sg:phone":"+1 314 535 5900",
    "sg:postcode":"63103",
    "sg:province":"MO",
    "sg:tags":[
        "processing",
        "datum"
    ],
    "sg:website":"www.datasciencecorp.com",
    "wof:name":"Data Science Corp",
    "wof:placetype":"venue"
},
  "geometry": {"coordinates":[-90.22013800000001,38.629369],"type":"Point"}
}