{
  "type": "Feature",
  "properties": {
    "iso:country":"US",
    "sg:address":"9620 Midland Blvd",
    "sg:city":"Overland",
    "sg:classifiers":[
        {
            "category":"Building & Trades",
            "subcategory":"Construction",
            "type":"Services"
        }
    ],
    "sg:phone":"+1 314 428 6170",
    "sg:postcode":"63114",
    "sg:province":"MO",
    "sg:tags":[
        "contractor"
    ],
    "wof:name":"Robinson Quality Constructors",
    "wof:placetype":"venue"
},
  "geometry": {"coordinates":[-90.369264,38.708069],"type":"Point"}
}