{
  "type": "Feature",
  "properties": {
    "iso:country":"US",
    "sg:address":"12529 Olive Blvd",
    "sg:city":"St Louis",
    "sg:classifiers":[
        {
            "category":"Restaurant",
            "type":"Food & Drink"
        }
    ],
    "sg:phone":"+1 314 469 9111",
    "sg:postcode":"63141",
    "sg:province":"MO",
    "sg:tags":[
        "eating"
    ],
    "wof:name":"Cecil Whittakers Pizzeria",
    "wof:placetype":"venue"
},
  "geometry": {"coordinates":[-90.46243699999999,38.675477],"type":"Point"}
}