{
  "type": "Feature",
  "properties": {
    "iso:country":"US",
    "sg:address":"217 S Denton St",
    "sg:city":"Centralia",
    "sg:classifiers":[
        {
            "category":"Building & Trades",
            "subcategory":"Construction",
            "type":"Services"
        }
    ],
    "sg:phone":"+1 573 682 9903",
    "sg:postcode":"65240",
    "sg:province":"MO",
    "sg:tags":[
        "home",
        "improvement"
    ],
    "wof:name":"Quality Home Improvements",
    "wof:placetype":"venue"
},
  "geometry": {"coordinates":[-92.14573300000001,39.209723],"type":"Point"}
}