{
  "type": "Feature",
  "properties": {
    "iso:country":"US",
    "sg:address":"305 Countryside Dr",
    "sg:city":"Florissant",
    "sg:classifiers":[
        {
            "category":"Building & Trades",
            "subcategory":"Construction",
            "type":"Services"
        }
    ],
    "sg:phone":"+1 314 839 8749",
    "sg:postcode":"63033",
    "sg:province":"MO",
    "sg:tags":[
        "house"
    ],
    "wof:name":"Rains Remodeling",
    "wof:placetype":"venue"
},
  "geometry": {"coordinates":[-90.306346,38.783835],"type":"Point"}
}