{
  "type": "Feature",
  "properties": {
    "iso:country":"US",
    "sg:address":"1009 N Osteopathy",
    "sg:city":"Kirksville",
    "sg:classifiers":[
        {
            "category":"Banks & Credit Unions",
            "subcategory":"Bank",
            "type":"Services"
        }
    ],
    "sg:phone":"+1 660 627 5614",
    "sg:postcode":"63501",
    "sg:province":"MO",
    "wof:name":"Greater Iowa Credit Union",
    "wof:placetype":"venue"
},
  "geometry": {"coordinates":[-92.590864,40.202425],"type":"Point"}
}