{
  "type": "Feature",
  "properties": {
    "iso:country":"US",
    "sg:address":"2800 Cherokee St",
    "sg:city":"Saint Louis",
    "sg:classifiers":[
        {
            "category":"Food & Beverages",
            "subcategory":"Groceries & Convenience Stores",
            "type":"Retail Goods"
        }
    ],
    "sg:phone":"+1 314 773 1707",
    "sg:postcode":"63118",
    "sg:province":"MO",
    "wof:name":"Carniceria Latino Americana",
    "wof:placetype":"venue"
},
  "geometry": {"coordinates":[-90.230202,38.594002],"type":"Point"}
}