{
  "type": "Feature",
  "properties": {
    "iso:country":"US",
    "sg:address":"1107 Hinkson Ave",
    "sg:city":"Columbia",
    "sg:classifiers":[
        {
            "category":"Wholesale",
            "subcategory":"Machinery & Supplies",
            "type":"Manufacturing & Wholesale Goods"
        }
    ],
    "sg:phone":"+1 573 874 1375",
    "sg:postcode":"65201",
    "sg:province":"MO",
    "sg:tags":[
        "equipment",
        "industrial"
    ],
    "wof:name":"Diggs Packing",
    "wof:placetype":"venue"
},
  "geometry": {"coordinates":[-92.32279,38.957014],"type":"Point"}
}