{
  "type": "Feature",
  "properties": {
    "iso:country":"US",
    "sg:address":"324 S Buckner Tarsney Rd",
    "sg:city":"Buckner",
    "sg:classifiers":[
        {
            "category":"Autos & Motor Vehicles",
            "subcategory":"Auto Supplies",
            "type":"Retail Goods"
        }
    ],
    "sg:phone":"+1 816 650 5063",
    "sg:postcode":"64016",
    "sg:province":"MO",
    "sg:tags":[
        "equipment",
        "racing",
        "car",
        "automobile"
    ],
    "wof:name":"MLRA",
    "wof:placetype":"venue"
},
  "geometry": {"coordinates":[-94.19966599999999,39.100836],"type":"Point"}
}