{
  "type": "Feature",
  "properties": {
    "iso:country":"US",
    "sg:address":"2387 W Jackson Blvd",
    "sg:city":"Jackson",
    "sg:classifiers":[
        {
            "category":"Health Services",
            "subcategory":"Doctor",
            "type":"Services"
        }
    ],
    "sg:phone":"+1 573 651 1882",
    "sg:postcode":"63755",
    "sg:province":"MO",
    "sg:tags":[
        "physician",
        "surgeon"
    ],
    "wof:name":"J Thomas Critchlow MD",
    "wof:placetype":"venue"
},
  "geometry": {"coordinates":[-89.69444300000001,37.383793],"type":"Point"}
}