{
  "type": "Feature",
  "properties": {
    "iso:country":"US",
    "sg:address":"1545 Boonslick Rd",
    "sg:city":"St Charles",
    "sg:classifiers":[
        {
            "category":"Freight",
            "type":"Transportation"
        }
    ],
    "sg:phone":"+1 636 925 1311",
    "sg:postcode":"63301",
    "sg:province":"MO",
    "sg:tags":[
        "local",
        "broker",
        "trucking"
    ],
    "wof:name":"Ira Transportation",
    "wof:placetype":"venue"
},
  "geometry": {"coordinates":[-90.504991,38.773879],"type":"Point"}
}