{
  "type": "Feature",
  "properties": {
    "iso:country":"US",
    "sg:address":"12818 US Hwy 71",
    "sg:city":"Grandview",
    "sg:classifiers":[
        {
            "category":"Food & Beverages",
            "subcategory":"Liquor & Beverages",
            "type":"Retail Goods"
        }
    ],
    "sg:phone":"+1 816 761 7337",
    "sg:postcode":"64030",
    "sg:province":"MO",
    "sg:tags":[
        "beer",
        "ale",
        "store"
    ],
    "wof:name":"Bi-Rite Liquors 1",
    "wof:placetype":"venue"
},
  "geometry": {"coordinates":[-94.525251,38.890914],"type":"Point"}
}