{
  "type": "Feature",
  "properties": {
    "iso:country":"US",
    "sg:address":"640 E College St",
    "sg:city":"Troy",
    "sg:classifiers":[
        {
            "category":"Retail",
            "subcategory":"Portrait Studio",
            "type":"Services"
        }
    ],
    "sg:phone":"+1 636 528 6918",
    "sg:postcode":"63379",
    "sg:province":"MO",
    "sg:tags":[
        "photographer"
    ],
    "wof:name":"My Camera & Eye",
    "wof:placetype":"venue"
},
  "geometry": {"coordinates":[-90.974906,38.982558],"type":"Point"}
}