{
  "type": "Feature",
  "properties": {
    "iso:country":"US",
    "sg:address":"104 Trade Center Dr",
    "sg:city":"St Peters",
    "sg:classifiers":[
        {
            "category":"Wholesale",
            "subcategory":"Groceries",
            "type":"Manufacturing & Wholesale Goods"
        }
    ],
    "sg:phone":"+1 636 379 8401",
    "sg:postcode":"63376",
    "sg:province":"MO",
    "sg:tags":[
        "food",
        "product"
    ],
    "wof:name":"Hays Food Systems Inc",
    "wof:placetype":"venue"
},
  "geometry": {"coordinates":[-90.66561900000001,38.80251],"type":"Point"}
}