{
  "type": "Feature",
  "properties": {
    "iso:country":"US",
    "sg:address":"581 Co Rd 432",
    "sg:city":"Fayette",
    "sg:classifiers":[
        {
            "category":"Freight",
            "type":"Transportation"
        }
    ],
    "sg:phone":"+1 660 248 5126",
    "sg:postcode":"65248",
    "sg:province":"MO",
    "sg:tags":[
        "operator",
        "trucking",
        "local",
        "hauling",
        "livestock"
    ],
    "wof:name":"Johnmeyer Cattle Co Inc",
    "wof:placetype":"venue"
},
  "geometry": {"coordinates":[-92.631989,39.056964],"type":"Point"}
}