{
  "type": "Feature",
  "properties": {
    "iso:country":"US",
    "sg:address":"6877 Parker Rd",
    "sg:city":"Florissant",
    "sg:classifiers":[
        {
            "category":"Recreation",
            "type":"Entertainment"
        }
    ],
    "sg:phone":"+1 314 355 9629",
    "sg:postcode":"63033",
    "sg:province":"MO",
    "wof:name":"World Martial Arts Academy",
    "wof:placetype":"venue"
},
  "geometry": {"coordinates":[-90.23268400000001,38.796089],"type":"Point"}
}