{
  "type": "Feature",
  "properties": {
    "iso:country":"US",
    "sg:address":"2049 Rose Ln",
    "sg:city":"Pacific",
    "sg:classifiers":[
        {
            "category":"Social Services",
            "subcategory":"Adult Care",
            "type":"Services"
        }
    ],
    "sg:phone":"+1 636 257 8020",
    "sg:postcode":"63069",
    "sg:province":"MO",
    "sg:tags":[
        "residential"
    ],
    "wof:name":"Bristol Manor of Pacific",
    "wof:placetype":"venue"
},
  "geometry": {"coordinates":[-90.76332499999999,38.481711],"type":"Point"}
}