{
  "type": "Feature",
  "properties": {
    "iso:country":"US",
    "sg:address":"4543 Magnolia Ave",
    "sg:city":"St Louis",
    "sg:classifiers":[
        {
            "category":"Organizations",
            "subcategory":"Religious Organization",
            "type":"Services"
        }
    ],
    "sg:phone":"+1 314 771 6215",
    "sg:postcode":"63110",
    "sg:province":"MO",
    "sg:tags":[
        "church"
    ],
    "wof:name":"Southwest Church of Nazarene",
    "wof:placetype":"venue"
},
  "geometry": {"coordinates":[-90.265208,38.609584],"type":"Point"}
}