{
  "type": "Feature",
  "properties": {
    "iso:country":"US",
    "sg:address":"328 State Rd Ae",
    "sg:city":"New Bloomfield",
    "sg:classifiers":[
        {
            "category":"Social Services",
            "subcategory":"Child Care",
            "type":"Services"
        }
    ],
    "sg:phone":"+1 573 491 3799",
    "sg:postcode":"65063",
    "sg:province":"MO",
    "wof:name":"Little Flowers School",
    "wof:placetype":"venue"
},
  "geometry": {"coordinates":[-92.08636,38.71252],"type":"Point"}
}