{
  "type": "Feature",
  "properties": {
    "iso:country":"US",
    "sg:address":"607 S 12th St",
    "sg:city":"Bethany",
    "sg:classifiers":[
        {
            "category":"Farming",
            "subcategory":"Farm",
            "type":"Manufacturing & Wholesale Goods"
        }
    ],
    "sg:phone":"+1 660 425 6794",
    "sg:postcode":"64424",
    "sg:province":"MO",
    "wof:name":"Cripple Creek Farms",
    "wof:placetype":"venue"
},
  "geometry": {"coordinates":[-94.038362,40.265492],"type":"Point"}
}