{
  "type": "Feature",
  "properties": {
    "addr:full":"36 Ofallon Sq O Fallon MO 63366",
    "addr:housenumber":"36",
    "addr:postcode":"63366",
    "addr:street":"Ofallon Sq O",
    "iso:country":"US",
    "sg:address":"36 Ofallon Sq",
    "sg:city":"O Fallon",
    "sg:classifiers":[
        {
            "category":"Personal",
            "subcategory":"Beauty Salon",
            "type":"Services"
        }
    ],
    "sg:phone":"+1 636 240 8047",
    "sg:postcode":"63366",
    "sg:province":"MO",
    "sg:tags":[
        "shop"
    ],
    "wof:name":"Fantastic Sam's",
    "wof:placetype":"venue"
},
  "geometry": {"coordinates":[-90.701336,38.80131],"type":"Point"}
}