{
  "type": "Feature",
  "properties": {
    "iso:country":"US",
    "sg:address":"1645 W Republic Rd",
    "sg:city":"Springfield",
    "sg:classifiers":[
        {
            "category":"Restaurant",
            "type":"Food & Drink"
        }
    ],
    "sg:menulink":"http://www.allmenus.com/mo/springfield/60397-longhorn-grill/menu/",
    "sg:phone":"+1 417 447 1064",
    "sg:postcode":"65807",
    "sg:province":"MO",
    "sg:tags":[
        "american",
        "steakhouse"
    ],
    "wof:name":"Longhorn Grill",
    "wof:placetype":"venue"
},
  "geometry": {"coordinates":[-93.31536,37.138302],"type":"Point"}
}