{
  "type": "Feature",
  "properties": {
    "iso:country":"US",
    "sg:address":"2991 Highway A",
    "sg:city":"Mansfield",
    "sg:classifiers":[
        {
            "category":"Fast Food",
            "type":"Food & Drink"
        },
        {
            "category":"Restaurant",
            "type":"Food & Drink"
        }
    ],
    "sg:phone":"+1 417 924 2332",
    "sg:postcode":"65704",
    "sg:province":"MO",
    "sg:tags":[
        "hot",
        "hamburger",
        "dog"
    ],
    "wof:name":"Burger Barn & Bakery",
    "wof:placetype":"venue"
},
  "geometry": {"coordinates":[-92.570168,37.098927],"type":"Point"}
}