{
  "type": "Feature",
  "properties": {
    "iso:country":"US",
    "sg:address":"2301 Cherokee St",
    "sg:city":"St Louis",
    "sg:classifiers":[
        {
            "category":"Shopping",
            "subcategory":"Jewelry",
            "type":"Retail Goods"
        },
        {
            "category":"Shopping",
            "subcategory":"Crafts & Fabrics",
            "type":"Retail Goods"
        }
    ],
    "sg:phone":"+1 314 771 6353",
    "sg:postcode":"63118",
    "sg:province":"MO",
    "sg:tags":[
        "art"
    ],
    "sg:website":"www.stlcurioshoppe.com",
    "wof:name":"St. Louis Curio Shoppe",
    "wof:placetype":"venue"
},
  "geometry": {"coordinates":[-90.224368,38.593356],"type":"Point"}
}