{
  "type": "Feature",
  "properties": {
    "iso:country":"US",
    "sg:address":"30703 Arrowhead Rd",
    "sg:city":"Stover",
    "sg:classifiers":[
        {
            "category":"Building & Trades",
            "subcategory":"Construction",
            "type":"Services"
        }
    ],
    "sg:phone":"+1 573 372 0121",
    "sg:postcode":"65078",
    "sg:province":"MO",
    "sg:tags":[
        "system",
        "contractor",
        "air conditioning"
    ],
    "wof:name":"Danner Mobile Hm Serv & Const",
    "wof:placetype":"venue"
},
  "geometry": {"coordinates":[-92.97300799999999,38.246145],"type":"Point"}
}