{
  "type": "Feature",
  "properties": {
    "iso:country":"US",
    "sg:address":"839 Autumn Grove Dr",
    "sg:city":"O Fallon",
    "sg:classifiers":[
        {
            "category":"Manufacturing",
            "subcategory":"Apparel",
            "type":"Manufacturing & Wholesale Goods"
        }
    ],
    "sg:phone":"+1 636 978 6977",
    "sg:postcode":"63366",
    "sg:province":"MO",
    "wof:name":"Sweat Tyme",
    "wof:placetype":"venue"
},
  "geometry": {"coordinates":[-90.713618,38.811743],"type":"Point"}
}