{
  "type": "Feature",
  "properties": {
    "iso:country":"US",
    "sg:address":"600 E 14th St",
    "sg:city":"Sedalia",
    "sg:classifiers":[
        {
            "category":"Health Services",
            "subcategory":"Nursing And Care Facility",
            "type":"Services"
        }
    ],
    "sg:phone":"+1 660 826 4400",
    "sg:postcode":"65301",
    "sg:province":"MO",
    "sg:tags":[
        "home",
        "group"
    ],
    "wof:name":"Center For Human Services",
    "wof:placetype":"venue"
},
  "geometry": {"coordinates":[-93.22273800000001,38.699062],"type":"Point"}
}