{
  "type": "Feature",
  "properties": {
    "iso:country":"US",
    "sg:address":"703 1st St",
    "sg:city":"Warrenton",
    "sg:classifiers":[
        {
            "category":"Social Services",
            "type":"Services"
        },
        {
            "category":"Health Services",
            "subcategory":"Clinic",
            "type":"Services"
        }
    ],
    "sg:phone":"+1 636 456 7518",
    "sg:postcode":"63383",
    "sg:province":"MO",
    "sg:tags":[
        "welfare"
    ],
    "wof:name":"Warren County Development Disa",
    "wof:placetype":"venue"
},
  "geometry": {"coordinates":[-91.143283,38.803577],"type":"Point"}
}