{
  "type": "Feature",
  "properties": {
    "iso:country":"US",
    "sg:address":"11830 E Concord Rd",
    "sg:city":"Saint Louis",
    "sg:classifiers":[
        {
            "category":"Freight",
            "type":"Transportation"
        }
    ],
    "sg:phone":"+1 314 892 2572",
    "sg:postcode":"63128",
    "sg:province":"MO",
    "sg:tags":[
        "broker"
    ],
    "wof:name":"Spectrum Transportation",
    "wof:placetype":"venue"
},
  "geometry": {"coordinates":[-90.35745799999999,38.515887],"type":"Point"}
}