{
  "type": "Feature",
  "properties": {
    "iso:country":"US",
    "sg:address":"2122 Madison 504",
    "sg:city":"Fredericktown",
    "sg:classifiers":[
        {
            "category":"Organizations",
            "subcategory":"Religious Organization",
            "type":"Services"
        }
    ],
    "sg:phone":"+1 573 547 6796",
    "sg:postcode":"63645",
    "sg:province":"MO",
    "sg:tags":[
        "church"
    ],
    "wof:name":"Bethlehem Baptist Church",
    "wof:placetype":"venue"
},
  "geometry": {"coordinates":[-90.34912799999999,37.564157],"type":"Point"}
}