{
  "type": "Feature",
  "properties": {
    "iso:country":"US",
    "sg:address":"318 W Broadway Blvd",
    "sg:city":"Sedalia",
    "sg:classifiers":[
        {
            "category":"Autos & Motor Vehicles",
            "subcategory":"Auto Supplies",
            "type":"Retail Goods"
        }
    ],
    "sg:phone":"+1 660 827 2370",
    "sg:postcode":"65301",
    "sg:province":"MO",
    "wof:name":"Break Time 3084",
    "wof:placetype":"venue"
},
  "geometry": {"coordinates":[-93.231492,38.704391],"type":"Point"}
}