{
  "type": "Feature",
  "properties": {
    "addr:full":"125 S Main St Independence MO 64050",
    "addr:housenumber":"125",
    "addr:postcode":"64050",
    "addr:street":"S Main St",
    "iso:country":"US",
    "sg:address":"125 S Main St",
    "sg:city":"Independence",
    "sg:classifiers":[
        {
            "category":"Retail",
            "subcategory":"Auto Repair",
            "type":"Services"
        }
    ],
    "sg:phone":"+1 816 252 9300",
    "sg:postcode":"64050",
    "sg:province":"MO",
    "sg:tags":[
        "tire",
        "general"
    ],
    "wof:name":"Firestone",
    "wof:placetype":"venue"
},
  "geometry": {"coordinates":[-94.415674,39.091299],"type":"Point"}
}