{
  "type": "Feature",
  "properties": {
    "iso:country":"US",
    "sg:address":"110 NW 1221st Rd",
    "sg:city":"Holden",
    "sg:classifiers":[
        {
            "category":"Professional",
            "subcategory":"Detective & Security Services",
            "type":"Services"
        }
    ],
    "sg:phone":"+1 816 732 4014",
    "sg:postcode":"64040",
    "sg:province":"MO",
    "sg:tags":[
        "information",
        "bureau"
    ],
    "wof:name":"C&M Services",
    "wof:placetype":"venue"
},
  "geometry": {"coordinates":[-93.97438,38.786387],"type":"Point"}
}