{
  "type": "Feature",
  "properties": {
    "iso:country":"US",
    "sg:address":"3696 State Hwy 53",
    "sg:city":"Poplar Bluff",
    "sg:classifiers":[
        {
            "category":"Shopping",
            "subcategory":"Bicycles & Sporting Goods",
            "type":"Retail Goods"
        }
    ],
    "sg:phone":"+1 573 776 7484",
    "sg:postcode":"63901",
    "sg:province":"MO",
    "wof:name":"Tack-N-More",
    "wof:placetype":"venue"
},
  "geometry": {"coordinates":[-90.36412300000001,36.70416],"type":"Point"}
}