{
  "type": "Feature",
  "properties": {
    "iso:country":"US",
    "sg:address":"2408 S Grand Ave",
    "sg:city":"Carthage",
    "sg:classifiers":[
        {
            "category":"Food & Beverages",
            "subcategory":"Candy",
            "type":"Retail Goods"
        }
    ],
    "sg:phone":"+1 417 237 0900",
    "sg:postcode":"64836",
    "sg:province":"MO",
    "sg:tags":[
        "confectionery"
    ],
    "wof:name":"Richardson's Candy House",
    "wof:placetype":"venue"
},
  "geometry": {"coordinates":[-94.310276,37.146844],"type":"Point"}
}