{
  "type": "Feature",
  "properties": {
    "iso:country":"US",
    "sg:address":"4378 Lindell Blvd",
    "sg:city":"Saint Louis",
    "sg:classifiers":[
        {
            "category":"Professional",
            "subcategory":"Lawyer & Legal Services",
            "type":"Services"
        }
    ],
    "sg:phone":"+1 314 652 7481",
    "sg:postcode":"63108",
    "sg:province":"MO",
    "wof:name":"Sorrell Darin W Atty",
    "wof:placetype":"venue"
},
  "geometry": {"coordinates":[-90.253304,38.641602],"type":"Point"}
}