{
  "type": "Feature",
  "properties": {
    "iso:country":"US",
    "sg:address":"4262 Norfolk Ave",
    "sg:city":"Saint Louis",
    "sg:classifiers":[
        {
            "category":"Building & Trades",
            "subcategory":"Construction",
            "type":"Services"
        }
    ],
    "sg:phone":"+1 314 541 0864",
    "sg:postcode":"63110",
    "sg:province":"MO",
    "sg:tags":[
        "handyman"
    ],
    "sg:website":"www.brosch-handyman.net",
    "wof:name":"Alan's Handyman",
    "wof:placetype":"venue"
},
  "geometry": {"coordinates":[-90.255975,38.625033],"type":"Point"}
}