{
  "type": "Feature",
  "properties": {
    "iso:country":"US",
    "sg:address":"202 Austin Ave",
    "sg:city":"Columbia",
    "sg:classifiers":[
        {
            "category":"Shopping",
            "subcategory":"Discount & Variety Stores",
            "type":"Retail Goods"
        },
        {
            "category":"Autos & Motor Vehicles",
            "subcategory":"Automobile Sales",
            "type":"Retail Goods"
        }
    ],
    "sg:phone":"+1 573 449 1216",
    "sg:postcode":"65203",
    "sg:province":"MO",
    "sg:tags":[
        "used",
        "merchandise",
        "general"
    ],
    "wof:name":"Tee N Gee Auto Sales",
    "wof:placetype":"venue"
},
  "geometry": {"coordinates":[-92.33490399999999,38.963819],"type":"Point"}
}