{
  "type": "Feature",
  "properties": {
    "iso:country":"US",
    "sg:address":"6642 NE Silvius Rd",
    "sg:city":"Turney",
    "sg:classifiers":[
        {
            "category":"Real Estate",
            "subcategory":"Real Estate Agent",
            "type":"Services"
        }
    ],
    "sg:phone":"+1 816 664 2961",
    "sg:postcode":"64493",
    "sg:province":"MO",
    "wof:name":"David A Scrivens",
    "wof:placetype":"venue"
},
  "geometry": {"coordinates":[-94.35596,39.648309],"type":"Point"}
}