{
  "type": "Feature",
  "properties": {
    "iso:country":"US",
    "sg:address":"9628 Midland Blvd",
    "sg:city":"Overland",
    "sg:classifiers":[
        {
            "category":"Shopping",
            "subcategory":"Pharmacy",
            "type":"Retail Goods"
        }
    ],
    "sg:phone":"+1 314 423 2000",
    "sg:postcode":"63114",
    "sg:province":"MO",
    "sg:tags":[
        "drug",
        "store"
    ],
    "wof:name":"Midland Pharmacy",
    "wof:placetype":"venue"
},
  "geometry": {"coordinates":[-90.367778,38.708118],"type":"Point"}
}