{
  "type": "Feature",
  "properties": {
    "iso:country":"US",
    "sg:address":"700 Spirit of St Louis Blvd",
    "sg:city":"Chesterfield",
    "sg:classifiers":[
        {
            "category":"Building & Trades",
            "subcategory":"Construction",
            "type":"Services"
        }
    ],
    "sg:phone":"+1 636 532 9611",
    "sg:postcode":"63005",
    "sg:province":"MO",
    "sg:tags":[
        "house",
        "general",
        "contractor"
    ],
    "wof:name":"Kehr Construction Co",
    "wof:placetype":"venue"
},
  "geometry": {"coordinates":[-90.645296,38.668797],"type":"Point"}
}