{
  "type": "Feature",
  "properties": {
    "iso:country":"US",
    "sg:address":"100 W Berry St",
    "sg:city":"Hamilton",
    "sg:classifiers":[
        {
            "category":"Insurance",
            "subcategory":"Insurance Agent",
            "type":"Services"
        }
    ],
    "sg:phone":"+1 816 583 2178",
    "sg:postcode":"64644",
    "sg:province":"MO",
    "wof:name":"State Farm Insurance",
    "wof:placetype":"venue"
},
  "geometry": {"coordinates":[-93.99874800000001,39.742349],"type":"Point"}
}