{
  "type": "Feature",
  "properties": {
    "iso:country":"US",
    "sg:address":"415 N Hanley Rd",
    "sg:city":"Saint Louis",
    "sg:classifiers":[
        {
            "category":"Professional",
            "type":"Services"
        }
    ],
    "sg:phone":"+1 314 727 4413",
    "sg:postcode":"63130",
    "sg:province":"MO",
    "wof:name":"Gardeners Showcase Inc",
    "wof:placetype":"venue"
},
  "geometry": {"coordinates":[-90.33348100000001,38.654722],"type":"Point"}
}