{
  "type": "Feature",
  "properties": {
    "iso:country":"US",
    "sg:address":"5864 US Hwy 24",
    "sg:city":"Hannibal",
    "sg:classifiers":[
        {
            "category":"Banks & Credit Unions",
            "subcategory":"Investment Brokerage",
            "type":"Services"
        }
    ],
    "sg:phone":"+1 573 769 4193",
    "sg:postcode":"63401",
    "sg:province":"MO",
    "sg:tags":[
        "commodity"
    ],
    "wof:name":"Allen Dale Inc",
    "wof:placetype":"venue"
},
  "geometry": {"coordinates":[-91.514408,39.744895],"type":"Point"}
}