{
  "type": "Feature",
  "properties": {
    "iso:country":"US",
    "sg:address":"2625 E 11th St",
    "sg:city":"Joplin",
    "sg:classifiers":[
        {
            "category":"Building & Trades",
            "subcategory":"Construction",
            "type":"Services"
        }
    ],
    "sg:phone":"+1 417 623 6527",
    "sg:postcode":"64801",
    "sg:province":"MO",
    "sg:tags":[
        "contractor"
    ],
    "wof:name":"Frank Warden Portable Welding",
    "wof:placetype":"venue"
},
  "geometry": {"coordinates":[-94.484525,37.078799],"type":"Point"}
}