{
  "type": "Feature",
  "properties": {
    "iso:country":"US",
    "sg:address":"14824 Clayton Rd",
    "sg:city":"Chesterfield",
    "sg:classifiers":[
        {
            "category":"Health Services",
            "subcategory":"Chiropractor",
            "type":"Services"
        }
    ],
    "sg:phone":"+1 636 391 9494",
    "sg:postcode":"63017",
    "sg:province":"MO",
    "wof:name":"Sturmer Chiropractic",
    "wof:placetype":"venue"
},
  "geometry": {"coordinates":[-90.53925099999999,38.615718],"type":"Point"}
}