{
  "type": "Feature",
  "properties": {
    "iso:country":"US",
    "sg:address":"101 S Fairview Rd",
    "sg:city":"Columbia",
    "sg:classifiers":[
        {
            "category":"Health Services",
            "subcategory":"Doctor",
            "type":"Services"
        }
    ],
    "sg:phone":"+1 573 882 2124",
    "sg:postcode":"65203",
    "sg:province":"MO",
    "sg:tags":[
        "physician",
        "surgeon"
    ],
    "wof:name":"Chelmar Barrow Jr DO",
    "wof:placetype":"venue"
},
  "geometry": {"coordinates":[-92.380831,38.953359],"type":"Point"}
}