{
  "type": "Feature",
  "properties": {
    "iso:country":"US",
    "sg:address":"1300 W Harmony St",
    "sg:city":"Neosho",
    "sg:classifiers":[
        {
            "category":"Retail",
            "subcategory":"Auto Rental",
            "type":"Services"
        }
    ],
    "sg:phone":"+1 417 451 0328",
    "sg:postcode":"64850",
    "sg:province":"MO",
    "sg:tags":[
        "renting",
        "automobile"
    ],
    "wof:name":"Enterprise Rent-A-Car",
    "wof:placetype":"venue"
},
  "geometry": {"coordinates":[-94.388245,36.868412],"type":"Point"}
}