{
  "type": "Feature",
  "properties": {
    "iso:country":"US",
    "sg:address":"316 W Cherry St",
    "sg:city":"Nevada",
    "sg:classifiers":[
        {
            "category":"Personal",
            "subcategory":"Beauty Salon",
            "type":"Services"
        }
    ],
    "sg:phone":"+1 417 667 5259",
    "sg:postcode":"64772",
    "sg:province":"MO",
    "sg:tags":[
        "shop"
    ],
    "wof:name":"Double Take Hair Design",
    "wof:placetype":"venue"
},
  "geometry": {"coordinates":[-94.360434,37.838352],"type":"Point"}
}