{
  "type": "Feature",
  "properties": {
    "iso:country":"US",
    "sg:address":"10866 Lilac Ave",
    "sg:city":"Saint Louis",
    "sg:classifiers":[
        {
            "category":"Autos & Motor Vehicles",
            "subcategory":"Fuel & Gas Station",
            "type":"Retail Goods"
        }
    ],
    "sg:phone":"+1 314 869 3957",
    "sg:postcode":"63137",
    "sg:province":"MO",
    "sg:tags":[
        "filling",
        "station",
        "gasoline"
    ],
    "wof:name":"Conocophillips Company",
    "wof:placetype":"venue"
},
  "geometry": {"coordinates":[-90.203182,38.764964],"type":"Point"}
}