{
  "type": "Feature",
  "properties": {
    "iso:country":"US",
    "sg:address":"3416 Wilshire Dr",
    "sg:city":"Saint Charles",
    "sg:classifiers":[
        {
            "category":"Building & Trades",
            "subcategory":"Construction",
            "type":"Services"
        }
    ],
    "sg:phone":"+1 636 916 0598",
    "sg:postcode":"63301",
    "sg:province":"MO",
    "sg:tags":[
        "house"
    ],
    "wof:name":"Hoffman Construction",
    "wof:placetype":"venue"
},
  "geometry": {"coordinates":[-90.51383,38.809874],"type":"Point"}
}