{
  "type": "Feature",
  "properties": {
    "iso:country":"US",
    "sg:address":"422 S Neosho Blvd",
    "sg:city":"Neosho",
    "sg:classifiers":[
        {
            "category":"Building & Trades",
            "subcategory":"Equipment Rental",
            "type":"Services"
        }
    ],
    "sg:phone":"+1 417 451 6545",
    "sg:postcode":"64850",
    "sg:province":"MO",
    "sg:tags":[
        "yard"
    ],
    "wof:name":"Scott's Equipment Rental",
    "wof:placetype":"venue"
},
  "geometry": {"coordinates":[-94.38102600000001,36.866134],"type":"Point"}
}