{
  "type": "Feature",
  "properties": {
    "iso:country":"US",
    "sg:address":"120 Willow Creek Rd",
    "sg:city":"Union",
    "sg:classifiers":[
        {
            "category":"Building & Trades",
            "subcategory":"Construction",
            "type":"Services"
        }
    ],
    "sg:phone":"+1 636 583 5113",
    "sg:postcode":"63084",
    "sg:province":"MO",
    "sg:tags":[
        "contractor"
    ],
    "wof:name":"Quality Masonry Inc",
    "wof:placetype":"venue"
},
  "geometry": {"coordinates":[-91.02286100000001,38.49132],"type":"Point"}
}