{
  "type": "Feature",
  "properties": {
    "iso:country":"US",
    "sg:address":"3311 Pennsylvania Ave",
    "sg:city":"St Louis",
    "sg:classifiers":[
        {
            "category":"Organizations",
            "subcategory":"Religious Organization",
            "type":"Services"
        }
    ],
    "sg:phone":"+1 314 771 6310",
    "sg:postcode":"63118",
    "sg:province":"MO",
    "sg:tags":[
        "church"
    ],
    "wof:name":"Last Days Apostolic Church",
    "wof:placetype":"venue"
},
  "geometry": {"coordinates":[-90.233396,38.594922],"type":"Point"}
}