{
  "type": "Feature",
  "properties": {
    "addr:full":"1010 S Noland Rd Independence MO 64050",
    "addr:housenumber":"1010",
    "addr:postcode":"64050",
    "addr:street":"S Noland Rd",
    "iso:country":"US",
    "sg:address":"1010 S Noland Rd",
    "sg:city":"Independence",
    "sg:classifiers":[
        {
            "category":"Education",
            "subcategory":"Special Training",
            "type":"Public Place"
        }
    ],
    "sg:phone":"+1 816 252 1416",
    "sg:postcode":"64050",
    "sg:province":"MO",
    "wof:name":"International Reading Assn",
    "wof:placetype":"venue"
},
  "geometry": {"coordinates":[-94.413963,39.079226],"type":"Point"}
}