{
  "type": "Feature",
  "properties": {
    "iso:country":"US",
    "sg:address":"204 N Madison St",
    "sg:city":"Raymore",
    "sg:classifiers":[
        {
            "category":"Autos & Motor Vehicles",
            "subcategory":"Automobile Sales",
            "type":"Retail Goods"
        }
    ],
    "sg:phone":"+1 816 331 1300",
    "sg:postcode":"64083",
    "sg:province":"MO",
    "sg:tags":[
        "used",
        "boat"
    ],
    "wof:name":"Lake Land Auto Sales",
    "wof:placetype":"venue"
},
  "geometry": {"coordinates":[-94.456906,38.807488],"type":"Point"}
}