{
  "type": "Feature",
  "properties": {
    "iso:country":"US",
    "sg:address":"219 N Main St",
    "sg:city":"Palmyra",
    "sg:classifiers":[
        {
            "category":"Wholesale",
            "subcategory":"Machinery & Supplies",
            "type":"Manufacturing & Wholesale Goods"
        }
    ],
    "sg:phone":"+1 573 769 3117",
    "sg:postcode":"63461",
    "sg:province":"MO",
    "sg:tags":[
        "equipment",
        "establishment"
    ],
    "wof:name":"Country Cover Upholstery",
    "wof:placetype":"venue"
},
  "geometry": {"coordinates":[-91.522929,39.801402],"type":"Point"}
}