{
  "type": "Feature",
  "properties": {
    "iso:country":"US",
    "sg:address":"300 E 8th St",
    "sg:city":"Lockwood",
    "sg:classifiers":[
        {
            "category":"Manufacturing",
            "subcategory":"Wood Products",
            "type":"Manufacturing & Wholesale Goods"
        }
    ],
    "sg:phone":"+1 417 232 4555",
    "sg:postcode":"65682",
    "sg:province":"MO",
    "sg:tags":[
        "millwork-wholesale",
        "millwork",
        "manufacturer"
    ],
    "wof:name":"Wholesale Supply Company",
    "wof:placetype":"venue"
},
  "geometry": {"coordinates":[-93.951157,37.385761],"type":"Point"}
}