{
  "type": "Feature",
  "properties": {
    "iso:country":"US",
    "sg:address":"16 Lake Forest Dr",
    "sg:city":"Saint Charles",
    "sg:classifiers":[
        {
            "category":"Professional",
            "subcategory":"Business Services",
            "type":"Services"
        }
    ],
    "sg:phone":"+1 636 947 3141",
    "sg:postcode":"63301",
    "sg:province":"MO",
    "wof:name":"We Design",
    "wof:placetype":"venue"
},
  "geometry": {"coordinates":[-90.520039,38.806081],"type":"Point"}
}