{
  "type": "Feature",
  "properties": {
    "iso:country":"US",
    "sg:address":"1616 Fairview Ave",
    "sg:city":"Saint Louis",
    "sg:classifiers":[
        {
            "category":"Real Estate",
            "subcategory":"Real Estate Agent",
            "type":"Services"
        }
    ],
    "sg:phone":"+1 314 890 0100",
    "sg:postcode":"63132",
    "sg:province":"MO",
    "sg:tags":[
        "broker"
    ],
    "wof:name":"American Mortgage Corporation",
    "wof:placetype":"venue"
},
  "geometry": {"coordinates":[-90.388864,38.691316],"type":"Point"}
}