{
  "type": "Feature",
  "properties": {
    "iso:country":"US",
    "sg:address":"1301 W Webster St",
    "sg:city":"Springfield",
    "sg:classifiers":[
        {
            "category":"Wholesale",
            "subcategory":"Vending Machines",
            "type":"Manufacturing & Wholesale Goods"
        }
    ],
    "sg:phone":"+1 417 862 4389",
    "sg:postcode":"65802",
    "sg:province":"MO",
    "wof:name":"Jackson Brothers Vending",
    "wof:placetype":"venue"
},
  "geometry": {"coordinates":[-93.30837,37.221189],"type":"Point"}
}