{
  "type": "Feature",
  "properties": {
    "iso:country":"US",
    "sg:address":"15213 US Hwy 71",
    "sg:city":"Grandview",
    "sg:classifiers":[
        {
            "category":"Manufacturing",
            "subcategory":"Metals",
            "type":"Manufacturing & Wholesale Goods"
        },
        {
            "category":"Building & Trades",
            "subcategory":"Construction",
            "type":"Services"
        }
    ],
    "sg:phone":"+1 816 322 6663",
    "sg:postcode":"64030",
    "sg:province":"MO",
    "sg:tags":[
        "product",
        "wire",
        "fence",
        "mfg",
        "fabricated",
        "contractor",
        "fitting",
        "post"
    ],
    "wof:name":"American Fence Co",
    "wof:placetype":"venue"
},
  "geometry": {"coordinates":[-94.528749,38.851407],"type":"Point"}
}