{
  "type": "Feature",
  "properties": {
    "iso:country":"US",
    "sg:address":"1715 Old Eatherton Rd",
    "sg:city":"Glencoe",
    "sg:classifiers":[
        {
            "category":"Farming",
            "subcategory":"Farm",
            "type":"Manufacturing & Wholesale Goods"
        }
    ],
    "sg:phone":"+1 636 458 3224",
    "sg:postcode":"63038",
    "sg:province":"MO",
    "sg:tags":[
        "crop",
        "general"
    ],
    "wof:name":"Burkhardt Farms",
    "wof:placetype":"venue"
},
  "geometry": {"coordinates":[-90.644975,38.599241],"type":"Point"}
}