{
  "type": "Feature",
  "properties": {
    "iso:country":"US",
    "sg:address":"411 2nd St",
    "sg:city":"Mountain View",
    "sg:classifiers":[
        {
            "category":"Personal",
            "subcategory":"Beauty Salon",
            "type":"Services"
        }
    ],
    "sg:phone":"+1 417 934 2228",
    "sg:postcode":"65548",
    "sg:province":"MO",
    "wof:name":"Draztic Changes & More",
    "wof:placetype":"venue"
},
  "geometry": {"coordinates":[-91.69804999999999,36.997077],"type":"Point"}
}