{
  "type": "Feature",
  "properties": {
    "iso:country":"US",
    "sg:address":"13251 Mc Donald Rd",
    "sg:city":"Centralia",
    "sg:phone":"+1 573 682 2599",
    "sg:postcode":"65240",
    "sg:province":"MO",
    "sg:tags":[
        "farm",
        "field",
        "wheat",
        "crop",
        "soybean"
    ],
    "wof:name":"Swanson Farm",
    "wof:placetype":"venue"
},
  "geometry": {"coordinates":[-92.11865899999999,39.108829],"type":"Point"}
}