{
  "type": "Feature",
  "properties": {
    "iso:country":"US",
    "sg:address":"566 Brasilia Ave",
    "sg:city":"Kansas City",
    "sg:classifiers":[
        {
            "category":"Restaurant",
            "type":"Food & Drink"
        }
    ],
    "sg:phone":"+1 816 243 5745",
    "sg:postcode":"64153",
    "sg:province":"MO",
    "sg:tags":[
        "caterer"
    ],
    "sg:website":"www.lsgskychefs.com",
    "wof:name":"LSG-Sky Chefs",
    "wof:placetype":"venue"
},
  "geometry": {"coordinates":[-94.715082,39.310426],"type":"Point"}
}