{
  "type": "Feature",
  "properties": {
    "iso:country":"US",
    "sg:address":"1414 S Big Bend Blvd",
    "sg:city":"Saint Louis",
    "sg:classifiers":[
        {
            "category":"Building & Trades",
            "subcategory":"Plumbing",
            "type":"Services"
        }
    ],
    "sg:phone":"+1 314 644 2818",
    "sg:postcode":"63117",
    "sg:province":"MO",
    "wof:name":"Gloeckner-Melville Plumbing Co",
    "wof:placetype":"venue"
},
  "geometry": {"coordinates":[-90.320198,38.627499],"type":"Point"}
}