{
  "type": "Feature",
  "properties": {
    "iso:country":"US",
    "sg:address":"101 S Oak St",
    "sg:city":"Eldon",
    "sg:classifiers":[
        {
            "category":"Government",
            "subcategory":"Office",
            "type":"Public Place"
        }
    ],
    "sg:phone":"+1 573 392 3129",
    "sg:postcode":"65026",
    "sg:province":"MO",
    "sg:tags":[
        "township",
        "government-city",
        "village"
    ],
    "wof:name":"City Of Eldon",
    "wof:placetype":"venue"
},
  "geometry": {"coordinates":[-92.580254,38.349609],"type":"Point"}
}