{
  "type": "Feature",
  "properties": {
    "iso:country":"US",
    "sg:address":"42325 Hwy U",
    "sg:city":"Plato",
    "sg:classifiers":[
        {
            "category":"Farming",
            "subcategory":"Livestock Farm",
            "type":"Manufacturing & Wholesale Goods"
        }
    ],
    "sg:phone":"+1 417 453 6578",
    "sg:postcode":"65552",
    "sg:province":"MO",
    "sg:tags":[
        "beef",
        "feedlot",
        "cattle"
    ],
    "wof:name":"Dieman Poor Farm",
    "wof:placetype":"venue"
},
  "geometry": {"coordinates":[-92.28193400000001,37.568092],"type":"Point"}
}