{
  "type": "Feature",
  "properties": {
    "iso:country":"US",
    "sg:address":"836 Holiday Ave",
    "sg:city":"Hazelwood",
    "sg:classifiers":[
        {
            "category":"Building & Trades",
            "subcategory":"Construction",
            "type":"Services"
        }
    ],
    "sg:phone":"+1 314 895 5800",
    "sg:postcode":"63042",
    "sg:province":"MO",
    "sg:tags":[
        "roofing",
        "contractor"
    ],
    "wof:name":"Hanson Exteriors",
    "wof:placetype":"venue"
},
  "geometry": {"coordinates":[-90.373412,38.790814],"type":"Point"}
}