{
  "type": "Feature",
  "properties": {
    "iso:country":"US",
    "sg:address":"4403 Lemay Ferry Rd",
    "sg:city":"St Louis",
    "sg:classifiers":[
        {
            "category":"Manufacturing",
            "subcategory":"Petroleum Products",
            "type":"Manufacturing & Wholesale Goods"
        }
    ],
    "sg:phone":"+1 314 845 9892",
    "sg:postcode":"63129",
    "sg:province":"MO",
    "wof:name":"Midwest Petroleum Co",
    "wof:placetype":"venue"
},
  "geometry": {"coordinates":[-90.335356,38.499343],"type":"Point"}
}