{
  "type": "Feature",
  "properties": {
    "iso:country":"US",
    "sg:address":"27670 High Ridge Ln",
    "sg:city":"Carl Junction",
    "sg:classifiers":[
        {
            "category":"Retail",
            "subcategory":"Auto Repair",
            "type":"Services"
        }
    ],
    "sg:phone":"+1 417 325 7126",
    "sg:postcode":"64834",
    "sg:province":"MO",
    "sg:tags":[
        "body",
        "automobile",
        "painting"
    ],
    "wof:name":"Advanced Automotive",
    "wof:placetype":"venue"
},
  "geometry": {"coordinates":[-94.55689,37.159772],"type":"Point"}
}