{
  "type": "Feature",
  "properties": {
    "iso:country":"US",
    "sg:address":"8974 Watson Rd",
    "sg:city":"St Louis",
    "sg:classifiers":[
        {
            "category":"Shopping",
            "subcategory":"Jewelry",
            "type":"Retail Goods"
        }
    ],
    "sg:phone":"+1 314 849 5219",
    "sg:postcode":"63119",
    "sg:province":"MO",
    "sg:tags":[
        "jeweler"
    ],
    "wof:name":"Johnstone Jewelers",
    "wof:placetype":"venue"
},
  "geometry": {"coordinates":[-90.367001,38.562806],"type":"Point"}
}