{
  "type": "Feature",
  "properties": {
    "iso:country":"US",
    "sg:address":"17650 Highway 64",
    "sg:city":"Lebanon",
    "sg:classifiers":[
        {
            "category":"Retail",
            "subcategory":"Auto Repair",
            "type":"Services"
        }
    ],
    "sg:phone":"+1 417 588 1313",
    "sg:postcode":"65536",
    "sg:province":"MO",
    "sg:tags":[
        "body",
        "automobile",
        "painting",
        "repairing"
    ],
    "wof:name":"Hash, Harold Auto Body & Glass",
    "wof:placetype":"venue"
},
  "geometry": {"coordinates":[-92.713525,37.692705],"type":"Point"}
}