{
  "type": "Feature",
  "properties": {
    "iso:country":"US",
    "sg:address":"502 Westchester Ave",
    "sg:city":"Harrisonville",
    "sg:classifiers":[
        {
            "category":"Manufacturing",
            "subcategory":"Buildings",
            "type":"Manufacturing & Wholesale Goods"
        },
        {
            "category":"Real Estate",
            "subcategory":"Developer",
            "type":"Services"
        },
        {
            "category":"Building & Trades",
            "subcategory":"Construction",
            "type":"Services"
        }
    ],
    "sg:phone":"+1 816 380 6575",
    "sg:postcode":"64701",
    "sg:province":"MO",
    "sg:tags":[
        "home",
        "builder",
        "contractor"
    ],
    "wof:name":"Dpf Devlopment Corp",
    "wof:placetype":"venue"
},
  "geometry": {"coordinates":[-94.362995,38.652539],"type":"Point"}
}