{
  "type": "Feature",
  "properties": {
    "iso:country":"US",
    "sg:address":"334 W 9th St",
    "sg:city":"Hermann",
    "sg:classifiers":[
        {
            "category":"Social Services",
            "subcategory":"Child Care",
            "type":"Services"
        }
    ],
    "sg:phone":"+1 573 486 2845",
    "sg:postcode":"65041",
    "sg:province":"MO",
    "sg:tags":[
        "day"
    ],
    "wof:name":"Little Bearcat Day Care",
    "wof:placetype":"venue"
},
  "geometry": {"coordinates":[-91.44473499999999,38.700278],"type":"Point"}
}