{
  "type": "Feature",
  "properties": {
    "iso:country":"US",
    "sg:address":"1475 Golfview Ln",
    "sg:city":"Osage Beach",
    "sg:classifiers":[
        {
            "category":"Building & Trades",
            "subcategory":"Construction",
            "type":"Services"
        }
    ],
    "sg:phone":"+1 573 348 1405",
    "sg:postcode":"65065",
    "sg:province":"MO",
    "sg:tags":[
        "hanging",
        "contractor"
    ],
    "wof:name":"Steves Total Paint Co",
    "wof:placetype":"venue"
},
  "geometry": {"coordinates":[-92.68793100000001,38.136497],"type":"Point"}
}