{
  "type": "Feature",
  "properties": {
    "iso:country":"US",
    "sg:address":"301 SE Douglas St",
    "sg:city":"Lees Summit",
    "sg:classifiers":[
        {
            "category":"Home & Garden",
            "subcategory":"Furniture",
            "type":"Retail Goods"
        }
    ],
    "sg:phone":"+1 816 524 3377",
    "sg:postcode":"64063",
    "sg:province":"MO",
    "sg:tags":[
        "appliance"
    ],
    "wof:name":"Hartleys Home Furniture Inc",
    "wof:placetype":"venue"
},
  "geometry": {"coordinates":[-94.375726,38.911879],"type":"Point"}
}