{
  "type": "Feature",
  "properties": {
    "iso:country":"US",
    "sg:address":"6075 W Cabanne Pl",
    "sg:city":"St Louis",
    "sg:classifiers":[
        {
            "category":"Professional",
            "subcategory":"Art Services",
            "type":"Services"
        }
    ],
    "sg:phone":"+1 314 725 4523",
    "sg:postcode":"63112",
    "sg:province":"MO",
    "sg:tags":[
        "photographer"
    ],
    "wof:name":"Scott Henry Creative Phtgrphy",
    "wof:placetype":"venue"
},
  "geometry": {"coordinates":[-90.294911,38.659808],"type":"Point"}
}