{
  "type": "Feature",
  "properties": {
    "iso:country":"US",
    "sg:address":"2020 E 7th St",
    "sg:city":"Joplin",
    "sg:classifiers":[
        {
            "category":"Shopping",
            "subcategory":"Bicycles & Sporting Goods",
            "type":"Retail Goods"
        }
    ],
    "sg:phone":"+1 417 207 7765",
    "sg:postcode":"64801",
    "sg:province":"MO",
    "wof:name":"Spokes & Spandex Bike Shop LLC",
    "wof:placetype":"venue"
},
  "geometry": {"coordinates":[-94.491865,37.083745],"type":"Point"}
}