{
  "type": "Feature",
  "properties": {
    "iso:country":"US",
    "sg:address":"1706 Main St",
    "sg:city":"Bethany",
    "sg:classifiers":[
        {
            "category":"Health Services",
            "subcategory":"Clinic",
            "type":"Services"
        },
        {
            "category":"Social Services",
            "type":"Services"
        }
    ],
    "sg:phone":"+1 660 425 7227",
    "sg:postcode":"64424",
    "sg:province":"MO",
    "sg:tags":[
        "information",
        "center",
        "family",
        "outpatient",
        "specialty",
        "planning"
    ],
    "wof:name":"Youth Resource Center",
    "wof:placetype":"venue"
},
  "geometry": {"coordinates":[-94.03286,40.268599],"type":"Point"}
}