{
  "type": "Feature",
  "properties": {
    "iso:country":"US",
    "sg:address":"201 W Jackson St",
    "sg:city":"Willard",
    "sg:classifiers":[
        {
            "category":"Organizations",
            "subcategory":"Religious Organization",
            "type":"Services"
        }
    ],
    "sg:phone":"+1 417 742 0318",
    "sg:postcode":"65781",
    "sg:province":"MO",
    "wof:name":"Lighthouse Gospel Center Inc",
    "wof:placetype":"venue"
},
  "geometry": {"coordinates":[-93.42907599999999,37.305542],"type":"Point"}
}