{
  "type": "Feature",
  "properties": {
    "iso:country":"US",
    "sg:address":"1598 US Hwy 63 Bus",
    "sg:city":"West Plains",
    "sg:classifiers":[
        {
            "category":"Autos & Motor Vehicles",
            "subcategory":"Automobile Sales",
            "type":"Retail Goods"
        }
    ],
    "sg:phone":"+1 417 256 0973",
    "sg:postcode":"65775",
    "sg:province":"MO",
    "sg:tags":[
        "car",
        "used",
        "dealer"
    ],
    "wof:name":"Morgans Auto Sales",
    "wof:placetype":"venue"
},
  "geometry": {"coordinates":[-91.872135,36.742582],"type":"Point"}
}