{
  "type": "Feature",
  "properties": {
    "iso:country":"US",
    "sg:address":"1 Snow Creek Dr",
    "sg:city":"Weston",
    "sg:classifiers":[
        {
            "category":"Travel",
            "subcategory":"Hotels & Motels",
            "type":"Entertainment"
        }
    ],
    "sg:phone":"+1 816 640 2200",
    "sg:postcode":"64098",
    "sg:province":"MO",
    "sg:tags":[
        "resort",
        "center",
        "skiing"
    ],
    "wof:name":"Snow Creek Ski Area",
    "wof:placetype":"venue"
},
  "geometry": {"coordinates":[-94.971452,39.470499],"type":"Point"}
}