{
  "type": "Feature",
  "properties": {
    "iso:country":"US",
    "sg:address":"3901 N Belt Hwy",
    "sg:city":"St Joseph",
    "sg:classifiers":[
        {
            "category":"Professional",
            "type":"Services"
        }
    ],
    "sg:phone":"+1 816 676 0724",
    "sg:postcode":"64506",
    "sg:province":"MO",
    "sg:tags":[
        "establishment"
    ],
    "wof:name":"Huffy",
    "wof:placetype":"venue"
},
  "geometry": {"coordinates":[-94.814949,39.800401],"type":"Point"}
}