{
  "type": "Feature",
  "properties": {
    "iso:country":"US",
    "sg:address":"3345 S Kingshighway Blvd",
    "sg:city":"Saint Louis",
    "sg:classifiers":[
        {
            "category":"Shopping",
            "subcategory":"Computers & Home Electronics",
            "type":"Retail Goods"
        }
    ],
    "sg:phone":"+1 314 481 6666",
    "sg:postcode":"63139",
    "sg:province":"MO",
    "wof:name":"National Rent To Own",
    "wof:placetype":"venue"
},
  "geometry": {"coordinates":[-90.271674,38.597092],"type":"Point"}
}