{
  "type": "Feature",
  "properties": {
    "iso:country":"US",
    "sg:address":"3708 Mueller Rd",
    "sg:city":"St Charles",
    "sg:classifiers":[
        {
            "category":"Arts & Performance",
            "subcategory":"Theater",
            "type":"Entertainment"
        }
    ],
    "sg:phone":"+1 636 947 0050",
    "sg:postcode":"63301",
    "sg:province":"MO",
    "sg:tags":[
        "bureau"
    ],
    "sg:website":"www.ceo1.com",
    "wof:name":"Ceo Corporate Entertainments",
    "wof:placetype":"venue"
},
  "geometry": {"coordinates":[-90.502036,38.822018],"type":"Point"}
}