{
  "type": "Feature",
  "properties": {
    "iso:country":"US",
    "sg:address":"4444 Belleview Ave",
    "sg:city":"Kansas City",
    "sg:classifiers":[
        {
            "category":"Social Services",
            "type":"Services"
        }
    ],
    "sg:phone":"+1 816 453 2600",
    "sg:postcode":"64111",
    "sg:province":"MO",
    "sg:tags":[
        "counselor",
        "marriage",
        "family"
    ],
    "wof:name":"Northland Counseling Ctr",
    "wof:placetype":"venue"
},
  "geometry": {"coordinates":[-94.59836799999999,39.046993],"type":"Point"}
}