{
  "type": "Feature",
  "properties": {
    "iso:country":"US",
    "sg:address":"144 Rock Industrial Park Dr",
    "sg:city":"Bridgeton",
    "sg:classifiers":[
        {
            "category":"Manufacturing",
            "subcategory":"Tools & Machinery",
            "type":"Manufacturing & Wholesale Goods"
        }
    ],
    "sg:phone":"+1 314 739 6669",
    "sg:postcode":"63044",
    "sg:province":"MO",
    "sg:tags":[
        "machine",
        "shop"
    ],
    "wof:name":"Rec Valve Automation Svc",
    "wof:placetype":"venue"
},
  "geometry": {"coordinates":[-90.450675,38.778409],"type":"Point"}
}