{
  "type": "Feature",
  "properties": {
    "iso:country":"US",
    "sg:address":"40 Hillvale Dr",
    "sg:city":"Saint Louis",
    "sg:classifiers":[
        {
            "category":"Health Services",
            "subcategory":"Doctor",
            "type":"Services"
        }
    ],
    "sg:phone":"+1 314 863 1749",
    "sg:postcode":"63105",
    "sg:province":"MO",
    "sg:tags":[
        "surgeon",
        "oral"
    ],
    "wof:name":"Nissen Richard J DDS",
    "wof:placetype":"venue"
},
  "geometry": {"coordinates":[-90.323402,38.639],"type":"Point"}
}