{
  "type": "Feature",
  "properties": {
    "iso:country":"US",
    "sg:address":"1064 Regency Pkwy",
    "sg:city":"Saint Charles",
    "sg:classifiers":[
        {
            "category":"Restaurant",
            "type":"Food & Drink"
        }
    ],
    "sg:menulink":"http://www.allmenus.com/mo/zumbehl/148802-subway/menu/",
    "sg:phone":"+1 636 949 2681",
    "sg:postcode":"63303",
    "sg:province":"MO",
    "sg:tags":[
        "american",
        "sandwich"
    ],
    "wof:name":"Subway",
    "wof:placetype":"venue"
},
  "geometry": {"coordinates":[-90.52821299999999,38.783791],"type":"Point"}
}