{
  "type": "Feature",
  "properties": {
    "iso:country":"US",
    "sg:address":"6307 E 152nd Ter",
    "sg:city":"Grandview",
    "sg:classifiers":[
        {
            "category":"Professional",
            "subcategory":"Computer Services",
            "type":"Services"
        }
    ],
    "sg:phone":"+1 816 331 3754",
    "sg:postcode":"64030",
    "sg:province":"MO",
    "sg:tags":[
        "design",
        "system",
        "cu"
    ],
    "wof:name":"Vollmer Engineering",
    "wof:placetype":"venue"
},
  "geometry": {"coordinates":[-94.520267,38.848498],"type":"Point"}
}