{
  "type": "Feature",
  "properties": {
    "iso:country":"US",
    "sg:address":"6205 US Hwy 54 W",
    "sg:city":"Eugene",
    "sg:classifiers":[
        {
            "category":"Shopping",
            "subcategory":"Used Merchandise",
            "type":"Retail Goods"
        }
    ],
    "sg:phone":"+1 573 496 9973",
    "sg:postcode":"65032",
    "sg:province":"MO",
    "sg:tags":[
        "antique"
    ],
    "wof:name":"Tiny's Antique Mall",
    "wof:placetype":"venue"
},
  "geometry": {"coordinates":[-92.32498200000001,38.42814],"type":"Point"}
}