{
  "type": "Feature",
  "properties": {
    "iso:country":"US",
    "sg:address":"203 E 3rd St",
    "sg:city":"Portageville",
    "sg:classifiers":[
        {
            "category":"Health Services",
            "subcategory":"Doctor",
            "type":"Services"
        }
    ],
    "sg:phone":"+1 573 379 2100",
    "sg:postcode":"63873",
    "sg:province":"MO",
    "sg:tags":[
        "clinic"
    ],
    "wof:name":"A Plus Family Clinic",
    "wof:placetype":"venue"
},
  "geometry": {"coordinates":[-89.700568,36.426371],"type":"Point"}
}