{
  "type": "Feature",
  "properties": {
    "iso:country":"US",
    "sg:address":"3637 S Fort Ave",
    "sg:city":"Springfield",
    "sg:classifiers":[
        {
            "category":"Retail",
            "subcategory":"Portrait Studio",
            "type":"Services"
        }
    ],
    "sg:phone":"+1 417 889 2345",
    "sg:postcode":"65807",
    "sg:province":"MO",
    "sg:tags":[
        "photographer"
    ],
    "wof:name":"Mirror Image",
    "wof:placetype":"venue"
},
  "geometry": {"coordinates":[-93.310304,37.147357],"type":"Point"}
}