{
  "type": "Feature",
  "properties": {
    "iso:country":"US",
    "sg:address":"16612 Ellison Way",
    "sg:city":"Independence",
    "sg:classifiers":[
        {
            "category":"Shopping",
            "subcategory":"Computers & Home Electronics",
            "type":"Retail Goods"
        }
    ],
    "sg:phone":"+1 816 350 3100",
    "sg:postcode":"64055",
    "sg:province":"MO",
    "sg:tags":[
        "software"
    ],
    "wof:name":"CSI Inc",
    "wof:placetype":"venue"
},
  "geometry": {"coordinates":[-94.38043999999999,39.060832],"type":"Point"}
}