{
  "type": "Feature",
  "properties": {
    "iso:country":"US",
    "sg:address":"83 Florissant Park Dr",
    "sg:city":"Florissant",
    "sg:classifiers":[
        {
            "category":"Restaurant",
            "type":"Food & Drink"
        }
    ],
    "sg:menulink":"http://www.allmenus.com/mo/lewis-and-clark/34107-old-st-louis-chop-suey/menu/",
    "sg:phone":"+1 314 831 7337",
    "sg:postcode":"63031",
    "sg:province":"MO",
    "sg:tags":[
        "asian",
        "chinese"
    ],
    "wof:name":"Old St. Louis Chop Suey",
    "wof:placetype":"venue"
},
  "geometry": {"coordinates":[-90.334621,38.805062],"type":"Point"}
}