{
  "type": "Feature",
  "properties": {
    "iso:country":"US",
    "sg:address":"8430 Pershall Rd",
    "sg:city":"Hazelwood",
    "sg:classifiers":[
        {
            "category":"Health Services",
            "subcategory":"Dentist",
            "type":"Services"
        }
    ],
    "sg:phone":"+1 314 521 5678",
    "sg:postcode":"63042",
    "sg:province":"MO",
    "sg:tags":[
        "product",
        "whitening",
        "teeth"
    ],
    "sg:website":"http://www.lifesmiledentalcare.com",
    "wof:name":"LifeSmile Dental Care",
    "wof:placetype":"venue"
},
  "geometry": {"coordinates":[-90.330757,38.77475],"type":"Point"}
}