{
  "type": "Feature",
  "properties": {
    "iso:country":"US",
    "sg:address":"8635 Olive Blvd",
    "sg:city":"Saint Louis",
    "sg:classifiers":[
        {
            "category":"Professional",
            "subcategory":"Accounting & Tax Preparation",
            "type":"Services"
        }
    ],
    "sg:phone":"+1 314 432 1040",
    "sg:postcode":"63132",
    "sg:province":"MO",
    "sg:tags":[
        "return"
    ],
    "wof:name":"H & R Block",
    "wof:placetype":"venue"
},
  "geometry": {"coordinates":[-90.35764,38.674168],"type":"Point"}
}