{
  "type": "Feature",
  "properties": {
    "iso:country":"US",
    "sg:address":"9301 Gravois Rd",
    "sg:city":"Saint Louis",
    "sg:classifiers":[
        {
            "category":"Restaurant",
            "type":"Food & Drink"
        }
    ],
    "sg:menulink":"http://www.allmenus.com/mo/gravois/83958-dominos-pizza/menu/",
    "sg:phone":"+1 314 631 2100",
    "sg:postcode":"63123",
    "sg:province":"MO",
    "sg:tags":[
        "american",
        "wing",
        "pizza"
    ],
    "wof:name":"Domino's Pizza",
    "wof:placetype":"venue"
},
  "geometry": {"coordinates":[-90.31840200000001,38.554129],"type":"Point"}
}