{
  "type": "Feature",
  "properties": {
    "addr:full":"404 Maple St Lathrop MO 64465",
    "addr:housenumber":"404",
    "addr:postcode":"64465",
    "addr:street":"Maple St",
    "iso:country":"US",
    "sg:address":"404 Maple St",
    "sg:city":"Lathrop",
    "sg:classifiers":[
        {
            "category":"Organizations",
            "subcategory":"Religious Organization",
            "type":"Services"
        }
    ],
    "sg:phone":"+1 816 528 4280",
    "sg:postcode":"64465",
    "sg:province":"MO",
    "sg:tags":[
        "church"
    ],
    "wof:name":"United Methodist Church",
    "wof:placetype":"venue"
},
  "geometry": {"coordinates":[-94.327629,39.549999],"type":"Point"}
}