{
  "type": "Feature",
  "properties": {
    "iso:country":"US",
    "sg:address":"6703 S Broadway",
    "sg:city":"St Louis",
    "sg:classifiers":[
        {
            "category":"Food & Beverages",
            "subcategory":"Groceries & Convenience Stores",
            "type":"Retail Goods"
        }
    ],
    "sg:phone":"+1 314 832 4310",
    "sg:postcode":"63111",
    "sg:province":"MO",
    "wof:name":"7-Eleven",
    "wof:placetype":"venue"
},
  "geometry": {"coordinates":[-90.251403,38.553259],"type":"Point"}
}