{
  "type": "Feature",
  "properties": {
    "iso:country":"US",
    "sg:address":"882 S Hwy 47",
    "sg:city":"Union",
    "sg:classifiers":[
        {
            "category":"Organizations",
            "subcategory":"Religious Organization",
            "type":"Services"
        }
    ],
    "sg:phone":"+1 636 583 6923",
    "sg:postcode":"63084",
    "sg:province":"MO",
    "sg:tags":[
        "church"
    ],
    "wof:name":"Jehovah's Witnesses",
    "wof:placetype":"venue"
},
  "geometry": {"coordinates":[-90.99096299999999,38.433758],"type":"Point"}
}