{
  "type": "Feature",
  "properties": {
    "iso:country":"US",
    "sg:address":"18700 E 37 Ter S",
    "sg:city":"Independence",
    "sg:classifiers":[
        {
            "category":"Travel",
            "subcategory":"Hotels & Motels",
            "type":"Entertainment"
        }
    ],
    "sg:phone":"+1 816 795 1616",
    "sg:postcode":"64057",
    "sg:province":"MO",
    "sg:tags":[
        "operation"
    ],
    "wof:name":"Marriott",
    "wof:placetype":"venue"
},
  "geometry": {"coordinates":[-94.35976700000001,39.050463],"type":"Point"}
}