{
  "type": "Feature",
  "properties": {
    "iso:country":"US",
    "sg:address":"912 Baltimore Ave",
    "sg:city":"Kansas City",
    "sg:classifiers":[
        {
            "category":"Banks & Credit Unions",
            "subcategory":"Investment Brokerage",
            "type":"Services"
        }
    ],
    "sg:phone":"+1 816 472 5459",
    "sg:postcode":"64105",
    "sg:province":"MO",
    "sg:tags":[
        "stock",
        "bond"
    ],
    "wof:name":"Securities Consulting Svc",
    "wof:placetype":"venue"
},
  "geometry": {"coordinates":[-94.584265,39.103059],"type":"Point"}
}