{
  "type": "Feature",
  "properties": {
    "iso:country":"US",
    "sg:address":"200 S Main St",
    "sg:city":"Clinton",
    "sg:classifiers":[
        {
            "category":"Professional",
            "subcategory":"Employment Agencies",
            "type":"Services"
        },
        {
            "category":"Organizations",
            "subcategory":"Community Association",
            "type":"Services"
        }
    ],
    "sg:phone":"+1 660 885 2121",
    "sg:postcode":"64735",
    "sg:province":"MO",
    "sg:tags":[
        "employer"
    ],
    "wof:name":"Clinton Main Street Inc",
    "wof:placetype":"venue"
},
  "geometry": {"coordinates":[-93.77619199999999,38.369431],"type":"Point"}
}