{
  "type": "Feature",
  "properties": {
    "iso:country":"US",
    "sg:address":"492 W Tracker Rd",
    "sg:city":"Nixa",
    "sg:classifiers":[
        {
            "category":"Manufacturing",
            "subcategory":"Signs",
            "type":"Manufacturing & Wholesale Goods"
        }
    ],
    "sg:phone":"+1 417 724 9966",
    "sg:postcode":"65714",
    "sg:province":"MO",
    "sg:tags":[
        "specialty",
        "mfg"
    ],
    "wof:name":"Nixa Sign Crafters",
    "wof:placetype":"venue"
},
  "geometry": {"coordinates":[-93.302516,37.065505],"type":"Point"}
}