{
  "type": "Feature",
  "properties": {
    "iso:country":"US",
    "sg:address":"3806 E 18 Ct",
    "sg:city":"Kansas City",
    "sg:classifiers":[
        {
            "category":"Home & Garden",
            "subcategory":"Building Materials",
            "type":"Retail Goods"
        },
        {
            "category":"Building & Trades",
            "subcategory":"Construction",
            "type":"Services"
        }
    ],
    "sg:phone":"+1 816 231 7722",
    "sg:postcode":"64127",
    "sg:province":"MO",
    "sg:tags":[
        "painter",
        "furniture"
    ],
    "wof:name":"Paint Shop",
    "wof:placetype":"venue"
},
  "geometry": {"coordinates":[-94.537431,39.089633],"type":"Point"}
}