{
  "type": "Feature",
  "properties": {
    "iso:country":"US",
    "sg:address":"1 Detjen Dr",
    "sg:city":"St Louis",
    "sg:classifiers":[
        {
            "category":"Government",
            "subcategory":"Police Station",
            "type":"Public Place"
        }
    ],
    "sg:phone":"+1 314 729 4800",
    "sg:postcode":"63126",
    "sg:province":"MO",
    "sg:tags":[
        "department"
    ],
    "sg:website":"www.ci.crestwood.mo.us",
    "wof:name":"Crestwood Police Dept",
    "wof:placetype":"venue"
},
  "geometry": {"coordinates":[-90.38669,38.55905],"type":"Point"}
}