{
  "type": "Feature",
  "properties": {
    "iso:country":"US",
    "sg:address":"10 W 36 St",
    "sg:city":"Kansas City",
    "sg:classifiers":[
        {
            "category":"Personal",
            "type":"Services"
        }
    ],
    "sg:phone":"+1 816 931 2403",
    "sg:postcode":"64111",
    "sg:province":"MO",
    "sg:tags":[
        "hair",
        "weaving"
    ],
    "wof:name":"J C's Head To Toe",
    "wof:placetype":"venue"
},
  "geometry": {"coordinates":[-94.586918,39.062096],"type":"Point"}
}