{
  "type": "Feature",
  "properties": {
    "iso:country":"US",
    "sg:address":"141 Jeffery Dr",
    "sg:city":"Jackson",
    "sg:classifiers":[
        {
            "category":"Building & Trades",
            "subcategory":"Construction",
            "type":"Services"
        }
    ],
    "sg:phone":"+1 573 243 2811",
    "sg:postcode":"63755",
    "sg:province":"MO",
    "sg:tags":[
        "hanging",
        "contractor"
    ],
    "wof:name":"Mitchell Services",
    "wof:placetype":"venue"
},
  "geometry": {"coordinates":[-89.624894,37.44378],"type":"Point"}
}