{
  "type": "Feature",
  "properties": {
    "iso:country":"US",
    "sg:address":"2800 SW Twincreek Ct",
    "sg:city":"Blue Springs",
    "sg:classifiers":[
        {
            "category":"Professional",
            "subcategory":"Management & Consulting",
            "type":"Services"
        }
    ],
    "sg:phone":"+1 816 228 0011",
    "sg:postcode":"64015",
    "sg:province":"MO",
    "sg:tags":[
        "marketing",
        "consultant"
    ],
    "wof:name":"Texas Merchandising Inc",
    "wof:placetype":"venue"
},
  "geometry": {"coordinates":[-94.285134,38.989796],"type":"Point"}
}