{
  "type": "Feature",
  "properties": {
    "iso:country":"US",
    "sg:address":"1750 Ofallon Rd",
    "sg:city":"Saint Charles",
    "sg:classifiers":[
        {
            "category":"Autos & Motor Vehicles",
            "subcategory":"Fuel & Gas Station",
            "type":"Retail Goods"
        }
    ],
    "sg:phone":"+1 636 498 5552",
    "sg:postcode":"63304",
    "sg:province":"MO",
    "sg:tags":[
        "station",
        "gasoline"
    ],
    "wof:name":"Convenient Food Mart",
    "wof:placetype":"venue"
},
  "geometry": {"coordinates":[-90.688378,38.73438],"type":"Point"}
}