{
  "type": "Feature",
  "properties": {
    "iso:country":"US",
    "sg:address":"10835 Old Halls Ferry Rd",
    "sg:city":"Saint Louis",
    "sg:classifiers":[
        {
            "category":"Restaurant",
            "type":"Food & Drink"
        }
    ],
    "sg:menulink":"http://www.allmenus.com/mo/ferguson/51456-china-wok/menu/",
    "sg:phone":"+1 314 869 7993",
    "sg:postcode":"63136",
    "sg:province":"MO",
    "sg:tags":[
        "asian",
        "chinese"
    ],
    "wof:name":"China Wok",
    "wof:placetype":"venue"
},
  "geometry": {"coordinates":[-90.260103,38.767772],"type":"Point"}
}