{
  "type": "Feature",
  "properties": {
    "iso:country":"US",
    "sg:address":"15003 Claymont Estates Dr",
    "sg:city":"Chesterfield",
    "sg:classifiers":[
        {
            "category":"Building & Trades",
            "subcategory":"Electrical",
            "type":"Services"
        }
    ],
    "sg:phone":"+1 636 519 1855",
    "sg:postcode":"63017",
    "sg:province":"MO",
    "sg:tags":[
        "electrical",
        "contractor"
    ],
    "wof:name":"Treiber Electric Inc",
    "wof:placetype":"venue"
},
  "geometry": {"coordinates":[-90.547617,38.623731],"type":"Point"}
}