{
  "type": "Feature",
  "properties": {
    "iso:country":"US",
    "sg:address":"4121 S Fremont Ave",
    "sg:city":"Springfield",
    "sg:classifiers":[
        {
            "category":"Fast Food",
            "type":"Food & Drink"
        },
        {
            "category":"Restaurant",
            "type":"Food & Drink"
        },
        {
            "category":"Food & Beverages",
            "subcategory":"Groceries & Convenience Stores",
            "type":"Retail Goods"
        }
    ],
    "sg:phone":"+1 417 890 0008",
    "sg:postcode":"65804",
    "sg:province":"MO",
    "sg:tags":[
        "shop",
        "american",
        "sandwich"
    ],
    "sg:website":"http://www.lennyssubshop.com/",
    "wof:name":"Lenny's Sub Shop",
    "wof:placetype":"venue"
},
  "geometry": {"coordinates":[-93.272014,37.138964],"type":"Point"}
}