{
  "type": "Feature",
  "properties": {
    "iso:country":"US",
    "sg:address":"5190 US Hwy 54",
    "sg:city":"Osage Beach",
    "sg:classifiers":[
        {
            "category":"Real Estate",
            "subcategory":"Real Estate Operator",
            "type":"Services"
        }
    ],
    "sg:phone":"+1 573 348 3782",
    "sg:postcode":"65065",
    "sg:province":"MO",
    "sg:tags":[
        "condominium"
    ],
    "wof:name":"Lake Condo Connection RE Co",
    "wof:placetype":"venue"
},
  "geometry": {"coordinates":[-92.646585,38.133257],"type":"Point"}
}