{
  "type": "Feature",
  "properties": {
    "iso:country":"US",
    "sg:address":"1103 S Henderson St",
    "sg:city":"Salem",
    "sg:classifiers":[
        {
            "category":"Retail",
            "subcategory":"Auto Repair",
            "type":"Services"
        }
    ],
    "sg:phone":"+1 573 729 4162",
    "sg:postcode":"65560",
    "sg:province":"MO",
    "sg:tags":[
        "general"
    ],
    "wof:name":"Rons Pro Auto Detail/Small En",
    "wof:placetype":"venue"
},
  "geometry": {"coordinates":[-91.539129,37.632133],"type":"Point"}
}