{
  "type": "Feature",
  "properties": {
    "iso:country":"US",
    "sg:address":"202 N Cedar St",
    "sg:city":"Nevada",
    "sg:classifiers":[
        {
            "category":"Shopping",
            "subcategory":"Computers & Home Electronics",
            "type":"Retail Goods"
        }
    ],
    "sg:phone":"+1 417 667 4529",
    "sg:postcode":"64772",
    "sg:province":"MO",
    "wof:name":"James Wilson",
    "wof:placetype":"venue"
},
  "geometry": {"coordinates":[-94.356461,37.840252],"type":"Point"}
}