{
  "type": "Feature",
  "properties": {
    "iso:country":"US",
    "sg:address":"3520 N Peace Church Ave",
    "sg:city":"Joplin",
    "sg:classifiers":[
        {
            "category":"Building & Trades",
            "subcategory":"Construction",
            "type":"Services"
        }
    ],
    "sg:phone":"+1 417 623 1279",
    "sg:postcode":"64801",
    "sg:province":"MO",
    "sg:tags":[
        "carpentry",
        "general",
        "contractor"
    ],
    "wof:name":"Zak Construction Inc",
    "wof:placetype":"venue"
},
  "geometry": {"coordinates":[-94.547833,37.124534],"type":"Point"}
}