{
  "type": "Feature",
  "properties": {
    "iso:country":"US",
    "sg:address":"1416 Hathman Pl",
    "sg:city":"Columbia",
    "sg:classifiers":[
        {
            "category":"Restaurant",
            "type":"Food & Drink"
        }
    ],
    "sg:phone":"+1 573 874 8126",
    "sg:postcode":"65201",
    "sg:province":"MO",
    "sg:tags":[
        "eating"
    ],
    "wof:name":"Captain Ds",
    "wof:placetype":"venue"
},
  "geometry": {"coordinates":[-92.30663300000001,38.965402],"type":"Point"}
}