{
  "type": "Feature",
  "properties": {
    "iso:country":"US",
    "sg:address":"20657 State Hwy O",
    "sg:city":"Sedalia",
    "sg:classifiers":[
        {
            "category":"Organizations",
            "subcategory":"Religious Organization",
            "type":"Services"
        }
    ],
    "sg:phone":"+1 660 827 4529",
    "sg:postcode":"65301",
    "sg:province":"MO",
    "wof:name":"Olive Branch Baptist Church",
    "wof:placetype":"venue"
},
  "geometry": {"coordinates":[-93.37637100000001,38.242833],"type":"Point"}
}