{
  "type": "Feature",
  "properties": {
    "iso:country":"US",
    "sg:address":"2540 Granite Rd Unit 22",
    "sg:city":"Lebanon",
    "sg:classifiers":[
        {
            "category":"Restaurant",
            "type":"Food & Drink"
        }
    ],
    "sg:phone":"+1 417 532 4227",
    "sg:postcode":"65536",
    "sg:province":"MO",
    "sg:tags":[
        "house",
        "steak",
        "barbecue"
    ],
    "wof:name":"Dickeys Bbq 06",
    "wof:placetype":"venue"
},
  "geometry": {"coordinates":[-92.724056,37.685291],"type":"Point"}
}