{
  "type": "Feature",
  "properties": {
    "iso:country":"US",
    "sg:address":"Mackenzie Pointe Shopping Center 7253 Watson Road",
    "sg:city":"St Louis",
    "sg:classifiers":[
        {
            "category":"Freight",
            "type":"Transportation"
        },
        {
            "category":"Professional",
            "subcategory":"Lawyer & Legal Services",
            "type":"Services"
        },
        {
            "category":"Professional",
            "subcategory":"Printing & Photocopies",
            "type":"Services"
        }
    ],
    "sg:phone":"+1 314 395 8422",
    "sg:postcode":"63119",
    "sg:province":"MO",
    "sg:tags":[
        "notary",
        "shipping"
    ],
    "sg:website":"www.postnet.com/mo114/",
    "wof:name":"PostNet Printing, Shipping & Business Services",
    "wof:placetype":"venue"
},
  "geometry": {"coordinates":[-90.317587,38.583823],"type":"Point"}
}