{
  "type": "Feature",
  "properties": {
    "iso:country":"US",
    "sg:address":"101 N Grand St",
    "sg:city":"Clarence",
    "sg:classifiers":[
        {
            "category":"Government",
            "subcategory":"Post Office",
            "type":"Public Place"
        }
    ],
    "sg:phone":"+1 660 699 2440",
    "sg:postcode":"63437",
    "sg:province":"MO",
    "sg:tags":[
        "postal",
        "us"
    ],
    "wof:name":"US Post Office",
    "wof:placetype":"venue"
},
  "geometry": {"coordinates":[-92.262479,39.743014],"type":"Point"}
}