{
  "type": "Feature",
  "properties": {
    "iso:country":"US",
    "sg:address":"15251 Fleener Dr",
    "sg:city":"Gravois Mills",
    "sg:classifiers":[
        {
            "category":"Restaurant",
            "type":"Food & Drink"
        }
    ],
    "sg:phone":"+1 573 372 5415",
    "sg:postcode":"65037",
    "sg:province":"MO",
    "wof:name":"Frogs Restaurant",
    "wof:placetype":"venue"
},
  "geometry": {"coordinates":[-92.79825,38.302627],"type":"Point"}
}