{
  "type": "Feature",
  "properties": {
    "iso:country":"US",
    "sg:address":"12652 Co Rd 4039",
    "sg:city":"Holts Summit",
    "sg:classifiers":[
        {
            "category":"Shopping",
            "subcategory":"Gifts & Souvenirs",
            "type":"Retail Goods"
        }
    ],
    "sg:phone":"+1 573 896 4195",
    "sg:postcode":"65043",
    "sg:province":"MO",
    "wof:name":"Home Interior Gifts",
    "wof:placetype":"venue"
},
  "geometry": {"coordinates":[-92.122203,38.597008],"type":"Point"}
}