{
  "type": "Feature",
  "properties": {
    "iso:country":"US",
    "sg:address":"14535 Manchester Rd",
    "sg:city":"Ballwin",
    "sg:classifiers":[
        {
            "category":"Social Services",
            "subcategory":"Adult Care",
            "type":"Services"
        },
        {
            "category":"Social Services",
            "type":"Services"
        }
    ],
    "sg:phone":"+1 636 207 0847",
    "sg:postcode":"63011",
    "sg:province":"MO",
    "sg:tags":[
        "organization",
        "assistance",
        "senior",
        "elderly",
        "citizen"
    ],
    "wof:name":"Mid East Area Agency Of Aging",
    "wof:placetype":"venue"
},
  "geometry": {"coordinates":[-90.521629,38.593176],"type":"Point"}
}