{
  "type": "Feature",
  "properties": {
    "iso:country":"US",
    "sg:address":"7354 Manchester Rd Loft 6 at Salon Lofts",
    "sg:city":"Maplewood",
    "sg:classifiers":[
        {
            "category":"Personal",
            "subcategory":"Beauty Salon",
            "type":"Services"
        }
    ],
    "sg:phone":"+1 314 973 3252",
    "sg:postcode":"63143",
    "sg:province":"MO",
    "sg:tags":[
        "hair"
    ],
    "sg:website":"joshnicholsstudio.com/",
    "wof:name":"Josh Nichols Studio",
    "wof:placetype":"venue"
},
  "geometry": {"coordinates":[-90.319012,38.612786],"type":"Point"}
}