{
  "type": "Feature",
  "properties": {
    "iso:country":"US",
    "sg:address":"129 Chesterfield Towne Ctr",
    "sg:city":"Chesterfield",
    "sg:classifiers":[
        {
            "category":"Sports & Exercise",
            "subcategory":"Gym",
            "type":"Entertainment"
        }
    ],
    "sg:phone":"+1 636 590 2727",
    "sg:postcode":"63005",
    "sg:province":"MO",
    "sg:tags":[
        "fitness",
        "program",
        "physical"
    ],
    "wof:name":"ATA Martial Arts",
    "wof:placetype":"venue"
},
  "geometry": {"coordinates":[-90.6202,38.663015],"type":"Point"}
}