{
  "type": "Feature",
  "properties": {
    "iso:country":"US",
    "sg:address":"8523 Olive Blvd",
    "sg:city":"Saint Louis",
    "sg:classifiers":[
        {
            "category":"Personal",
            "type":"Services"
        }
    ],
    "sg:phone":"+1 314 993 5552",
    "sg:postcode":"63132",
    "sg:province":"MO",
    "wof:name":"Horizon Muscle Therapy Center",
    "wof:placetype":"venue"
},
  "geometry": {"coordinates":[-90.356302,38.674152],"type":"Point"}
}