{
  "type": "Feature",
  "properties": {
    "iso:country":"US",
    "sg:address":"3100 Twin Pines Dr",
    "sg:city":"Harrisonville",
    "sg:classifiers":[
        {
            "category":"Professional",
            "subcategory":"Management & Consulting",
            "type":"Services"
        }
    ],
    "sg:phone":"+1 816 380 5277",
    "sg:postcode":"64701",
    "sg:province":"MO",
    "sg:tags":[
        "business"
    ],
    "wof:name":"Beth Mulvey Consultant",
    "wof:placetype":"venue"
},
  "geometry": {"coordinates":[-94.318215,38.668906],"type":"Point"}
}