{
  "type": "Feature",
  "properties": {
    "iso:country":"US",
    "sg:address":"10110 N Farm Rd 51",
    "sg:city":"Walnut Grove",
    "sg:classifiers":[
        {
            "category":"Organizations",
            "subcategory":"Religious Organization",
            "type":"Services"
        }
    ],
    "sg:phone":"+1 417 994 2324",
    "sg:postcode":"65770",
    "sg:province":"MO",
    "sg:tags":[
        "church"
    ],
    "wof:name":"Harold Baptist Church",
    "wof:placetype":"venue"
},
  "geometry": {"coordinates":[-93.526672,37.383845],"type":"Point"}
}