{
  "type": "Feature",
  "properties": {
    "iso:country":"US",
    "sg:address":"2631 E Delmar St",
    "sg:city":"Springfield",
    "sg:classifiers":[
        {
            "category":"Building & Trades",
            "subcategory":"Landscaping Services",
            "type":"Services"
        }
    ],
    "sg:phone":"+1 417 886 6044",
    "sg:postcode":"65804",
    "sg:province":"MO",
    "wof:name":"Rare Earth Landscaping",
    "wof:placetype":"venue"
},
  "geometry": {"coordinates":[-93.24092,37.19363],"type":"Point"}
}