{
  "type": "Feature",
  "properties": {
    "iso:country":"US",
    "sg:address":"707 US Hwy 60",
    "sg:city":"Monett",
    "sg:classifiers":[
        {
            "category":"Wholesale",
            "subcategory":"Construction Materials",
            "type":"Manufacturing & Wholesale Goods"
        }
    ],
    "sg:phone":"+1 417 235 5003",
    "sg:postcode":"65708",
    "sg:province":"MO",
    "sg:tags":[
        "building"
    ],
    "sg:website":"www.architecturalsystemsinc.com",
    "wof:name":"Architectural Systems Inc",
    "wof:placetype":"venue"
},
  "geometry": {"coordinates":[-93.93651300000001,36.914375],"type":"Point"}
}