{
  "type": "Feature",
  "properties": {
    "iso:country":"US",
    "sg:address":"1531 E 23rd St S",
    "sg:city":"Independence",
    "sg:classifiers":[
        {
            "category":"Fast Food",
            "type":"Food & Drink"
        },
        {
            "category":"Restaurant",
            "type":"Food & Drink"
        }
    ],
    "sg:phone":"+1 816 252 4500",
    "sg:postcode":"64055",
    "sg:province":"MO",
    "sg:tags":[
        "take",
        "pizza"
    ],
    "sg:website":"http://www.papamurphys.com",
    "wof:name":"Papa Murphy's Take 'N' Bake",
    "wof:placetype":"venue"
},
  "geometry": {"coordinates":[-94.394599,39.078468],"type":"Point"}
}