{
  "type": "Feature",
  "properties": {
    "iso:country":"US",
    "sg:address":"1840 N Wharf St",
    "sg:city":"Saint Louis",
    "sg:classifiers":[
        {
            "category":"Freight",
            "type":"Transportation"
        }
    ],
    "sg:phone":"+1 314 436 3096",
    "sg:postcode":"63102",
    "sg:province":"MO",
    "sg:tags":[
        "loading",
        "unloading",
        "barge"
    ],
    "wof:name":"Bulk Service",
    "wof:placetype":"venue"
},
  "geometry": {"coordinates":[-90.181341,38.641531],"type":"Point"}
}