{
  "type": "Feature",
  "properties": {
    "iso:country":"US",
    "sg:address":"718 W 3rd St",
    "sg:city":"Caruthersville",
    "sg:classifiers":[
        {
            "category":"Bars & Pubs",
            "type":"Food & Drink"
        }
    ],
    "sg:phone":"+1 573 333 9932",
    "sg:postcode":"63830",
    "sg:province":"MO",
    "sg:tags":[
        "lounge",
        "cocktail"
    ],
    "wof:name":"Woody's Lounge",
    "wof:placetype":"venue"
},
  "geometry": {"coordinates":[-89.66072800000001,36.196189],"type":"Point"}
}