{
  "type": "Feature",
  "properties": {
    "iso:country":"US",
    "sg:address":"629 Broadway St",
    "sg:city":"Cape Girardeau",
    "sg:classifiers":[
        {
            "category":"Personal",
            "subcategory":"Beauty Salon",
            "type":"Services"
        }
    ],
    "sg:phone":"+1 573 334 6411",
    "sg:postcode":"63701",
    "sg:province":"MO",
    "sg:tags":[
        "shop"
    ],
    "wof:name":"Nail Design",
    "wof:placetype":"venue"
},
  "geometry": {"coordinates":[-89.52625399999999,37.30659],"type":"Point"}
}