{
  "type": "Feature",
  "properties": {
    "iso:country":"US",
    "sg:address":"601 Watkins Glen Dr",
    "sg:city":"Saint Charles",
    "sg:classifiers":[
        {
            "category":"Manufacturing",
            "subcategory":"Apparel",
            "type":"Manufacturing & Wholesale Goods"
        }
    ],
    "sg:phone":"+1 636 922 9661",
    "sg:postcode":"63304",
    "sg:province":"MO",
    "wof:name":"Creations By Lisa McGrath",
    "wof:placetype":"venue"
},
  "geometry": {"coordinates":[-90.60212,38.755199],"type":"Point"}
}