{
  "type": "Feature",
  "properties": {
    "iso:country":"US",
    "sg:address":"7777 Bonhomme Ave",
    "sg:city":"St Louis",
    "sg:classifiers":[
        {
            "category":"Manufacturing",
            "subcategory":"Printing",
            "type":"Manufacturing & Wholesale Goods"
        }
    ],
    "sg:phone":"+1 314 727 6111",
    "sg:postcode":"63105",
    "sg:province":"MO",
    "sg:tags":[
        "newspaper"
    ],
    "wof:name":"St Louis Countian The",
    "wof:placetype":"venue"
},
  "geometry": {"coordinates":[-90.335427,38.647405],"type":"Point"}
}