{
  "type": "Feature",
  "properties": {
    "iso:country":"US",
    "sg:address":"1127 S Hope St",
    "sg:city":"Jackson",
    "sg:classifiers":[
        {
            "category":"Autos & Motor Vehicles",
            "subcategory":"Automobile Sales",
            "type":"Retail Goods"
        }
    ],
    "sg:phone":"+1 573 243 7860",
    "sg:postcode":"63755",
    "sg:province":"MO",
    "sg:tags":[
        "car",
        "dealer"
    ],
    "wof:name":"Brugger Auto Sales",
    "wof:placetype":"venue"
},
  "geometry": {"coordinates":[-89.66543799999999,37.372986],"type":"Point"}
}