{
  "type": "Feature",
  "properties": {
    "iso:country":"US",
    "sg:address":"208 Washington St",
    "sg:city":"Holcomb",
    "sg:classifiers":[
        {
            "category":"Professional",
            "subcategory":"Detective & Security Services",
            "type":"Services"
        }
    ],
    "sg:phone":"+1 573 792 3262",
    "sg:postcode":"63852",
    "sg:province":"MO",
    "sg:tags":[
        "information",
        "bureau"
    ],
    "wof:name":"Holcomb Assembly Of God Church",
    "wof:placetype":"venue"
},
  "geometry": {"coordinates":[-90.02634,36.406315],"type":"Point"}
}