{
  "type": "Feature",
  "properties": {
    "iso:country":"US",
    "sg:address":"1526 US Hwy 60 Bus",
    "sg:city":"Dexter",
    "sg:classifiers":[
        {
            "category":"Social Services",
            "type":"Services"
        }
    ],
    "sg:phone":"+1 573 624 6786",
    "sg:postcode":"63841",
    "sg:province":"MO",
    "sg:tags":[
        "organization",
        "welfare"
    ],
    "wof:name":"VNA Community Svc Inc",
    "wof:placetype":"venue"
},
  "geometry": {"coordinates":[-89.981308,36.803759],"type":"Point"}
}