{
  "type": "Feature",
  "properties": {
    "iso:country":"US",
    "sg:address":"116 Chestnut St",
    "sg:city":"Thayer",
    "sg:classifiers":[
        {
            "category":"Banks & Credit Unions",
            "subcategory":"Bank",
            "type":"Services"
        }
    ],
    "sg:phone":"+1 417 264 7217",
    "sg:postcode":"65791",
    "sg:province":"MO",
    "sg:tags":[
        "saving",
        "commercial"
    ],
    "sg:website":"http://www.bankofthayer.com",
    "wof:name":"Howell County Bank",
    "wof:placetype":"venue"
},
  "geometry": {"coordinates":[-91.53849,36.524672],"type":"Point"}
}