{
  "type": "Feature",
  "properties": {
    "iso:country":"US",
    "sg:address":"1138 Vinetta Dr",
    "sg:city":"Des Peres",
    "sg:classifiers":[
        {
            "category":"Restaurant",
            "type":"Food & Drink"
        }
    ],
    "sg:phone":"+1 314 965 2526",
    "sg:postcode":"63131",
    "sg:province":"MO",
    "wof:name":"Topper Productions",
    "wof:placetype":"venue"
},
  "geometry": {"coordinates":[-90.43084500000001,38.602695],"type":"Point"}
}