{
  "type": "Feature",
  "properties": {
    "iso:country":"US",
    "sg:address":"114 E Main St",
    "sg:city":"Steele",
    "sg:classifiers":[
        {
            "category":"Insurance",
            "subcategory":"Hazard Insurance",
            "type":"Services"
        },
        {
            "category":"Insurance",
            "subcategory":"Insurance Agent",
            "type":"Services"
        },
        {
            "category":"Insurance",
            "subcategory":"Life Insurance",
            "type":"Services"
        },
        {
            "category":"Insurance",
            "subcategory":"Title Insurance",
            "type":"Services"
        }
    ],
    "sg:phone":"+1 573 695 3346",
    "sg:postcode":"63877",
    "sg:province":"MO",
    "sg:tags":[
        "auto",
        "renter",
        "homeowner"
    ],
    "sg:website":"http://www.ShelterInsurance.com/CA/agent/VICKIEPARROTT",
    "wof:name":"Shelter Insurance - Vickie Parrott",
    "wof:placetype":"venue"
},
  "geometry": {"coordinates":[-89.82942799999999,36.083834],"type":"Point"}
}