{
  "type": "Feature",
  "properties": {
    "iso:country":"US",
    "sg:address":"508 E 9th St",
    "sg:city":"Joplin",
    "sg:classifiers":[
        {
            "category":"Autos & Motor Vehicles",
            "subcategory":"Auto Supplies",
            "type":"Retail Goods"
        }
    ],
    "sg:phone":"+1 417 624 3637",
    "sg:postcode":"64801",
    "sg:province":"MO",
    "sg:tags":[
        "filter",
        "gas"
    ],
    "wof:name":"Red Bud Air Filter",
    "wof:placetype":"venue"
},
  "geometry": {"coordinates":[-94.508185,37.081315],"type":"Point"}
}