{
  "type": "Feature",
  "properties": {
    "iso:country":"US",
    "sg:address":"830 Barwick Pl",
    "sg:city":"Willard",
    "sg:classifiers":[
        {
            "category":"Professional",
            "subcategory":"Accounting & Tax Preparation",
            "type":"Services"
        }
    ],
    "sg:phone":"+1 417 742 5154",
    "sg:postcode":"65781",
    "sg:province":"MO",
    "wof:name":"H Jarvis Kassie",
    "wof:placetype":"venue"
},
  "geometry": {"coordinates":[-93.428282,37.285827],"type":"Point"}
}