{
  "type": "Feature",
  "properties": {
    "iso:country":"US",
    "sg:address":"1001 Washington Ave",
    "sg:city":"Saint Louis",
    "sg:classifiers":[
        {
            "category":"Professional",
            "subcategory":"Lawyer & Legal Services",
            "type":"Services"
        }
    ],
    "sg:phone":"+1 314 725 5353",
    "sg:postcode":"63101",
    "sg:province":"MO",
    "wof:name":"Teasdale Douglass S",
    "wof:placetype":"venue"
},
  "geometry": {"coordinates":[-90.193764,38.631304],"type":"Point"}
}