{
  "type": "Feature",
  "properties": {
    "iso:country":"US",
    "sg:address":"1112 W 4th St",
    "sg:city":"Joplin",
    "sg:classifiers":[
        {
            "category":"Freight",
            "type":"Transportation"
        }
    ],
    "sg:phone":"+1 417 782 9496",
    "sg:postcode":"64801",
    "sg:province":"MO",
    "sg:tags":[
        "distance",
        "long",
        "trucking"
    ],
    "wof:name":"REA Trucking",
    "wof:placetype":"venue"
},
  "geometry": {"coordinates":[-94.52606299999999,37.087947],"type":"Point"}
}