{
  "type": "Feature",
  "properties": {
    "iso:country":"US",
    "sg:address":"511 S Ohio Ave",
    "sg:city":"Sedalia",
    "sg:classifiers":[
        {
            "category":"Professional",
            "subcategory":"Computer Services",
            "type":"Services"
        }
    ],
    "sg:phone":"+1 660 827 3056",
    "sg:postcode":"65301",
    "sg:province":"MO",
    "sg:tags":[
        "graphics"
    ],
    "sg:website":"www.305spin.com",
    "wof:name":"305 Spin",
    "wof:placetype":"venue"
},
  "geometry": {"coordinates":[-93.22820400000001,38.706797],"type":"Point"}
}