{
  "type": "Feature",
  "properties": {
    "iso:country":"US",
    "sg:address":"73313 Koerkenmeier Rd",
    "sg:city":"Tipton",
    "sg:classifiers":[
        {
            "category":"Farming",
            "subcategory":"Livestock Farm",
            "type":"Manufacturing & Wholesale Goods"
        }
    ],
    "sg:phone":"+1 660 433 2477",
    "sg:postcode":"65081",
    "sg:province":"MO",
    "sg:tags":[
        "beef",
        "feedlot",
        "cattle"
    ],
    "wof:name":"Norman Koerkenmeier",
    "wof:placetype":"venue"
},
  "geometry": {"coordinates":[-92.819592,38.654032],"type":"Point"}
}