{
  "type": "Feature",
  "properties": {
    "iso:country":"US",
    "sg:address":"1416 S Main St",
    "sg:city":"Joplin",
    "sg:classifiers":[
        {
            "category":"Shopping",
            "type":"Retail Goods"
        }
    ],
    "sg:phone":"+1 417 782 2146",
    "sg:postcode":"64801",
    "sg:province":"MO",
    "sg:tags":[
        "machine",
        "adding",
        "calculator",
        "copier"
    ],
    "wof:name":"Office Concepts",
    "wof:placetype":"venue"
},
  "geometry": {"coordinates":[-94.51396099999999,37.075218],"type":"Point"}
}