{
  "type": "Feature",
  "properties": {
    "iso:country":"US",
    "sg:address":"104 W 2nd St",
    "sg:city":"Holden",
    "sg:classifiers":[
        {
            "category":"Health Services",
            "subcategory":"Chiropractor",
            "type":"Services"
        }
    ],
    "sg:phone":"+1 816 732 4122",
    "sg:postcode":"64040",
    "sg:province":"MO",
    "wof:name":"Joseph D Tirk DC",
    "wof:placetype":"venue"
},
  "geometry": {"coordinates":[-93.99091300000001,38.718066],"type":"Point"}
}