{
  "type": "Feature",
  "properties": {
    "iso:country":"US",
    "sg:address":"3300 N Gretna Rd",
    "sg:city":"Branson",
    "sg:classifiers":[
        {
            "category":"Shopping",
            "subcategory":"Jewelry",
            "type":"Retail Goods"
        }
    ],
    "sg:phone":"+1 417 231 1966",
    "sg:postcode":"65616",
    "sg:province":"MO",
    "sg:tags":[
        "jeweler"
    ],
    "wof:name":"Jewelry Repair Center",
    "wof:placetype":"venue"
},
  "geometry": {"coordinates":[-93.259632,36.654408],"type":"Point"}
}