{
  "type": "Feature",
  "properties": {
    "iso:country":"US",
    "sg:address":"3500 Prospect Ave",
    "sg:city":"Kansas City",
    "sg:classifiers":[
        {
            "category":"Food & Beverages",
            "subcategory":"Groceries & Convenience Stores",
            "type":"Retail Goods"
        }
    ],
    "sg:phone":"+1 816 923 0112",
    "sg:postcode":"64128",
    "sg:province":"MO",
    "wof:name":"U S Fuel LLC",
    "wof:placetype":"venue"
},
  "geometry": {"coordinates":[-94.553291,39.06095],"type":"Point"}
}