{
  "type": "Feature",
  "properties": {
    "iso:country":"US",
    "sg:address":"4412 Woodson Rd",
    "sg:city":"Saint Louis",
    "sg:classifiers":[
        {
            "category":"Restaurant",
            "type":"Food & Drink"
        }
    ],
    "sg:menulink":"http://www.allmenus.com/mo/airport/43806-yesterdays/menu/",
    "sg:phone":"+1 314 423 5677",
    "sg:postcode":"63134",
    "sg:province":"MO",
    "sg:tags":[
        "american"
    ],
    "wof:name":"Yesterday's",
    "wof:placetype":"venue"
},
  "geometry": {"coordinates":[-90.357564,38.729986],"type":"Point"}
}