{
  "type": "Feature",
  "properties": {
    "iso:country":"US",
    "sg:address":"4161 Bethel Dr",
    "sg:city":"Summersville",
    "sg:classifiers":[
        {
            "category":"Shopping",
            "subcategory":"Books",
            "type":"Retail Goods"
        }
    ],
    "sg:phone":"+1 417 932 4407",
    "sg:postcode":"65571",
    "sg:province":"MO",
    "wof:name":"Harbor Lights Publishing",
    "wof:placetype":"venue"
},
  "geometry": {"coordinates":[-91.708163,37.180771],"type":"Point"}
}