{
  "type": "Feature",
  "properties": {
    "iso:country":"US",
    "sg:address":"501 S Main St",
    "sg:city":"Saint Charles",
    "sg:classifiers":[
        {
            "category":"Restaurant",
            "type":"Food & Drink"
        }
    ],
    "sg:menulink":"http://www.allmenus.com/mo/rivers/185174-little-hills-winery--restaurant/menu/",
    "sg:phone":"+1 636 946 9339",
    "sg:postcode":"63301",
    "sg:province":"MO",
    "sg:tags":[
        "american"
    ],
    "wof:name":"Little Hills Winery & Restaurant",
    "wof:placetype":"venue"
},
  "geometry": {"coordinates":[-90.48312199999999,38.77787],"type":"Point"}
}