{
  "type": "Feature",
  "properties": {
    "iso:country":"US",
    "sg:address":"2931 W Broadway Blvd",
    "sg:city":"Sedalia",
    "sg:classifiers":[
        {
            "category":"Utilities",
            "subcategory":"Mobile Phone",
            "type":"Services"
        }
    ],
    "sg:phone":"+1 660 826 1200",
    "sg:postcode":"65301",
    "sg:province":"MO",
    "sg:tags":[
        "telephone",
        "cellular"
    ],
    "wof:name":"Affordable Cellular Systems",
    "wof:placetype":"venue"
},
  "geometry": {"coordinates":[-93.26188,38.70718],"type":"Point"}
}