{
  "type": "Feature",
  "properties": {
    "iso:country":"US",
    "sg:address":"5865 Hampton Ave",
    "sg:city":"Saint Louis",
    "sg:classifiers":[
        {
            "category":"Organizations",
            "subcategory":"Membership Organization",
            "type":"Services"
        }
    ],
    "sg:phone":"+1 314 832 9345",
    "sg:postcode":"63109",
    "sg:province":"MO",
    "wof:name":"Hampton Chippew Business Assn",
    "wof:placetype":"venue"
},
  "geometry": {"coordinates":[-90.293859,38.579017],"type":"Point"}
}