{
  "type": "Feature",
  "properties": {
    "iso:country":"US",
    "sg:address":"502 W Columbia St",
    "sg:city":"Farmington",
    "sg:classifiers":[
        {
            "category":"Farming",
            "subcategory":"Farm",
            "type":"Manufacturing & Wholesale Goods"
        }
    ],
    "sg:phone":"+1 573 756 4576",
    "sg:postcode":"63640",
    "sg:province":"MO",
    "sg:tags":[
        "crop",
        "general"
    ],
    "wof:name":"Green Tree Farm Inc",
    "wof:placetype":"venue"
},
  "geometry": {"coordinates":[-90.42786700000001,37.779828],"type":"Point"}
}