{
  "type": "Feature",
  "properties": {
    "iso:country":"US",
    "sg:address":"1925 Cherokee St",
    "sg:city":"Saint Louis",
    "sg:classifiers":[
        {
            "category":"Shopping",
            "subcategory":"Used Merchandise",
            "type":"Retail Goods"
        }
    ],
    "sg:phone":"+1 314 772 8007",
    "sg:postcode":"63118",
    "sg:province":"MO",
    "sg:tags":[
        "antique"
    ],
    "sg:website":"www.panoramafolkart.com/",
    "wof:name":"Panorama Antiques & Collectables",
    "wof:placetype":"venue"
},
  "geometry": {"coordinates":[-90.219498,38.5924],"type":"Point"}
}