{
  "type": "Feature",
  "properties": {
    "iso:country":"US",
    "sg:address":"1853 Schoettler Valley Dr",
    "sg:city":"Chesterfield",
    "sg:classifiers":[
        {
            "category":"Wholesale",
            "subcategory":"Office Equipment",
            "type":"Manufacturing & Wholesale Goods"
        }
    ],
    "sg:phone":"+1 314 994 0262",
    "sg:postcode":"63017",
    "sg:province":"MO",
    "wof:name":"Integrated Business Tech Group",
    "wof:placetype":"venue"
},
  "geometry": {"coordinates":[-90.55049200000001,38.63993],"type":"Point"}
}