{
  "type": "Feature",
  "properties": {
    "iso:country":"US",
    "sg:address":"1104 State Hwy 7",
    "sg:city":"Blue Springs",
    "sg:classifiers":[
        {
            "category":"Banks & Credit Unions",
            "subcategory":"Bank",
            "type":"Services"
        }
    ],
    "sg:phone":"+1 816 979 6160",
    "sg:postcode":"64014",
    "sg:province":"MO",
    "sg:tags":[
        "mortgage"
    ],
    "wof:name":"Bank Of America",
    "wof:placetype":"venue"
},
  "geometry": {"coordinates":[-94.272594,39.007815],"type":"Point"}
}