{
  "type": "Feature",
  "properties": {
    "iso:country":"US",
    "sg:address":"1781 State Hwy Nn",
    "sg:city":"Kennett",
    "sg:classifiers":[
        {
            "category":"Shopping",
            "type":"Retail Goods"
        }
    ],
    "sg:phone":"+1 573 888 9429",
    "sg:postcode":"63857",
    "sg:province":"MO",
    "sg:tags":[
        "merchandise"
    ],
    "wof:name":"Saturn Fireworks",
    "wof:placetype":"venue"
},
  "geometry": {"coordinates":[-89.961203,36.228072],"type":"Point"}
}