{
  "type": "Feature",
  "properties": {
    "iso:country":"US",
    "sg:address":"7825 N Oak Fwy",
    "sg:city":"Kansas City",
    "sg:classifiers":[
        {
            "category":"Restaurant",
            "type":"Food & Drink"
        }
    ],
    "sg:phone":"+1 816 436 0037",
    "sg:postcode":"64118",
    "sg:province":"MO",
    "sg:tags":[
        "shop",
        "coffee",
        "eating"
    ],
    "wof:name":"Perfect Cup",
    "wof:placetype":"venue"
},
  "geometry": {"coordinates":[-94.575986,39.23491],"type":"Point"}
}