{
  "type": "Feature",
  "properties": {
    "iso:country":"US",
    "sg:address":"506 S 4th St",
    "sg:city":"Ste Genevieve",
    "sg:classifiers":[
        {
            "category":"Retail",
            "subcategory":"Auto Repair",
            "type":"Services"
        }
    ],
    "sg:phone":"+1 573 883 3815",
    "sg:postcode":"63670",
    "sg:province":"MO",
    "sg:tags":[
        "repairing",
        "automobile"
    ],
    "wof:name":"Mueller's Tire Svc Inc",
    "wof:placetype":"venue"
},
  "geometry": {"coordinates":[-90.04680999999999,37.972023],"type":"Point"}
}