{
  "type": "Feature",
  "properties": {
    "iso:country":"US",
    "sg:address":"80 Rue Terre Bonne",
    "sg:city":"Bonne Terre",
    "sg:classifiers":[
        {
            "category":"Personal",
            "subcategory":"Beauty Salon",
            "type":"Services"
        }
    ],
    "sg:phone":"+1 573 358 3385",
    "sg:postcode":"63628",
    "sg:province":"MO",
    "sg:tags":[
        "shop"
    ],
    "wof:name":"Salon De Coiffure",
    "wof:placetype":"venue"
},
  "geometry": {"coordinates":[-90.61793400000001,37.920547],"type":"Point"}
}