{
  "type": "Feature",
  "properties": {
    "iso:country":"US",
    "sg:address":"13038 Oregon Ln",
    "sg:city":"Neosho",
    "sg:classifiers":[
        {
            "category":"Home & Garden",
            "subcategory":"Mobile Homes",
            "type":"Retail Goods"
        }
    ],
    "sg:phone":"+1 417 451 2609",
    "sg:postcode":"64850",
    "sg:province":"MO",
    "wof:name":"Southwest Mobile Home Sales",
    "wof:placetype":"venue"
},
  "geometry": {"coordinates":[-94.314746,36.8784],"type":"Point"}
}