{
  "type": "Feature",
  "properties": {
    "iso:country":"US",
    "sg:address":"304 S Market St",
    "sg:city":"Holden",
    "sg:classifiers":[
        {
            "category":"Utilities",
            "subcategory":"Telephone",
            "type":"Services"
        }
    ],
    "sg:phone":"+1 816 732 2220",
    "sg:postcode":"64040",
    "sg:province":"MO",
    "sg:tags":[
        "providing",
        "internet"
    ],
    "wof:name":"Knoxynet",
    "wof:placetype":"venue"
},
  "geometry": {"coordinates":[-93.991105,38.716952],"type":"Point"}
}