{
  "type": "Feature",
  "properties": {
    "iso:country":"US",
    "sg:address":"413 N Weber Ave",
    "sg:city":"Salisbury",
    "sg:classifiers":[
        {
            "category":"Food & Beverages",
            "subcategory":"Groceries & Convenience Stores",
            "type":"Retail Goods"
        }
    ],
    "sg:phone":"+1 660 388 6600",
    "sg:postcode":"65281",
    "sg:province":"MO",
    "sg:tags":[
        "grocer"
    ],
    "wof:name":"Salisbury Foods Inc",
    "wof:placetype":"venue"
},
  "geometry": {"coordinates":[-92.798276,39.427979],"type":"Point"}
}