{
  "type": "Feature",
  "properties": {
    "iso:country":"US",
    "sg:address":"11831 Saint Charles Rock Rd",
    "sg:city":"Bridgeton",
    "sg:classifiers":[
        {
            "category":"Manufacturing",
            "subcategory":"Rubber & Plastics",
            "type":"Manufacturing & Wholesale Goods"
        },
        {
            "category":"Autos & Motor Vehicles",
            "subcategory":"Auto Supplies",
            "type":"Retail Goods"
        },
        {
            "category":"Retail",
            "subcategory":"Auto Repair",
            "type":"Services"
        }
    ],
    "sg:phone":"+1 314 298 0887",
    "sg:postcode":"63044",
    "sg:province":"MO",
    "sg:tags":[
        "tires-wholesale",
        "tire",
        "retread",
        "recap",
        "manufacturer"
    ],
    "sg:website":"http://www.coopertire.com/html/",
    "wof:name":"Meineke - Bridgton",
    "wof:placetype":"venue"
},
  "geometry": {"coordinates":[-90.41639600000001,38.745265],"type":"Point"}
}