{
  "type": "Feature",
  "properties": {
    "iso:country":"US",
    "sg:address":"2800 N Sarah St",
    "sg:city":"Saint Louis",
    "sg:classifiers":[
        {
            "category":"Food & Beverages",
            "subcategory":"Groceries & Convenience Stores",
            "type":"Retail Goods"
        }
    ],
    "sg:phone":"+1 314 652 1635",
    "sg:postcode":"63115",
    "sg:province":"MO",
    "wof:name":"Regal Mkt",
    "wof:placetype":"venue"
},
  "geometry": {"coordinates":[-90.231697,38.6595],"type":"Point"}
}