{
  "type": "Feature",
  "properties": {
    "iso:country":"US",
    "sg:address":"501 S Lamine Ave",
    "sg:city":"Sedalia",
    "sg:classifiers":[
        {
            "category":"Professional",
            "subcategory":"Accounting & Tax Preparation",
            "type":"Services"
        }
    ],
    "sg:phone":"+1 660 829 4046",
    "sg:postcode":"65301",
    "sg:province":"MO",
    "wof:name":"National Billing & Collections",
    "wof:placetype":"venue"
},
  "geometry": {"coordinates":[-93.227057,38.70684],"type":"Point"}
}