{
  "type": "Feature",
  "properties": {
    "iso:country":"US",
    "sg:address":"100 Westwoods Dr",
    "sg:city":"Liberty",
    "sg:classifiers":[
        {
            "category":"Professional",
            "type":"Services"
        }
    ],
    "sg:phone":"+1 816 407 7148",
    "sg:postcode":"64068",
    "sg:province":"MO",
    "sg:tags":[
        "establishment"
    ],
    "wof:name":"Professional Anesthetic Care",
    "wof:placetype":"venue"
},
  "geometry": {"coordinates":[-94.436441,39.248286],"type":"Point"}
}