{
  "type": "Feature",
  "properties": {
    "iso:country":"US",
    "sg:address":"27152 200th St",
    "sg:city":"Maryville",
    "sg:classifiers":[
        {
            "category":"Farming",
            "subcategory":"Livestock Farm",
            "type":"Manufacturing & Wholesale Goods"
        }
    ],
    "sg:phone":"+1 660 927 3600",
    "sg:postcode":"64468",
    "sg:province":"MO",
    "sg:tags":[
        "beef",
        "feedlot",
        "cattle"
    ],
    "wof:name":"David Frueh",
    "wof:placetype":"venue"
},
  "geometry": {"coordinates":[-94.87024599999999,40.432104],"type":"Point"}
}