{
  "type": "Feature",
  "properties": {
    "iso:country":"US",
    "sg:address":"8399 E 7th St",
    "sg:city":"Joplin",
    "sg:classifiers":[
        {
            "category":"Wholesale",
            "subcategory":"Auto Parts",
            "type":"Manufacturing & Wholesale Goods"
        }
    ],
    "sg:phone":"+1 417 781 9232",
    "sg:postcode":"64801",
    "sg:province":"MO",
    "sg:tags":[
        "used"
    ],
    "wof:name":"Fit N Finish",
    "wof:placetype":"venue"
},
  "geometry": {"coordinates":[-94.39963299999999,37.083056],"type":"Point"}
}