{
  "type": "Feature",
  "properties": {
    "iso:country":"US",
    "sg:address":"17202 US Hwy 67",
    "sg:city":"Neelyville",
    "sg:classifiers":[
        {
            "category":"Autos & Motor Vehicles",
            "subcategory":"Automobile Sales",
            "type":"Retail Goods"
        }
    ],
    "sg:phone":"+1 573 989 3317",
    "sg:postcode":"63954",
    "sg:province":"MO",
    "sg:tags":[
        "car",
        "used",
        "dealer"
    ],
    "wof:name":"D & D Auto Sales",
    "wof:placetype":"venue"
},
  "geometry": {"coordinates":[-90.521472,36.548409],"type":"Point"}
}