{
  "type": "Feature",
  "properties": {
    "iso:country":"US",
    "sg:address":"1414 Broadway St",
    "sg:city":"Joplin",
    "sg:classifiers":[
        {
            "category":"Retail",
            "subcategory":"Auto Repair",
            "type":"Services"
        }
    ],
    "sg:phone":"+1 417 781 9548",
    "sg:postcode":"64801",
    "sg:province":"MO",
    "sg:tags":[
        "body",
        "automobile",
        "painting",
        "repairing"
    ],
    "wof:name":"Big B Body Shop",
    "wof:placetype":"venue"
},
  "geometry": {"coordinates":[-94.497734,37.09178],"type":"Point"}
}