{
  "type": "Feature",
  "properties": {
    "iso:country":"US",
    "sg:address":"3016 S National Ave",
    "sg:city":"Springfield",
    "sg:classifiers":[
        {
            "category":"Professional",
            "type":"Services"
        }
    ],
    "sg:phone":"+1 417 887 5196",
    "sg:postcode":"65804",
    "sg:province":"MO",
    "wof:name":"Infuuz",
    "wof:placetype":"venue"
},
  "geometry": {"coordinates":[-93.277186,37.159399],"type":"Point"}
}