{
  "type": "Feature",
  "properties": {
    "iso:country":"US",
    "sg:address":"417 S Main St",
    "sg:city":"Palmyra",
    "sg:classifiers":[
        {
            "category":"Professional",
            "subcategory":"Business Services",
            "type":"Services"
        }
    ],
    "sg:phone":"+1 573 769 3076",
    "sg:postcode":"63461",
    "sg:province":"MO",
    "wof:name":"Gardner House",
    "wof:placetype":"venue"
},
  "geometry": {"coordinates":[-91.523025,39.796797],"type":"Point"}
}