{
  "type": "Feature",
  "properties": {
    "iso:country":"US",
    "sg:address":"3730 Goodfellow Blvd",
    "sg:city":"Saint Louis",
    "sg:classifiers":[
        {
            "category":"Restaurant",
            "type":"Food & Drink"
        }
    ],
    "sg:phone":"+1 314 382 4143",
    "sg:postcode":"63120",
    "sg:province":"MO",
    "sg:website":"www.rallyburger.com",
    "wof:name":"Rally's Drive Thru",
    "wof:placetype":"venue"
},
  "geometry": {"coordinates":[-90.271103,38.686401],"type":"Point"}
}