{
  "type": "Feature",
  "properties": {
    "iso:country":"US",
    "sg:address":"707 Ottawa St",
    "sg:city":"Seneca",
    "sg:classifiers":[
        {
            "category":"Social Services",
            "subcategory":"Child Care",
            "type":"Services"
        }
    ],
    "sg:phone":"+1 417 776 8375",
    "sg:postcode":"64865",
    "sg:province":"MO",
    "sg:tags":[
        "day"
    ],
    "wof:name":"Kids Korner Inc",
    "wof:placetype":"venue"
},
  "geometry": {"coordinates":[-94.611402,36.839848],"type":"Point"}
}