{
  "type": "Feature",
  "properties": {
    "iso:country":"US",
    "sg:address":"310 E Hewitt Ave",
    "sg:city":"Greenfield",
    "sg:classifiers":[
        {
            "category":"Health Services",
            "subcategory":"Clinic",
            "type":"Services"
        }
    ],
    "sg:phone":"+1 417 637 0505",
    "sg:postcode":"65661",
    "sg:province":"MO",
    "sg:tags":[
        "medical"
    ],
    "wof:name":"Allied Mental Health Assoc Inc",
    "wof:placetype":"venue"
},
  "geometry": {"coordinates":[-93.840649,37.422451],"type":"Point"}
}