{
  "type": "Feature",
  "properties": {
    "iso:country":"US",
    "sg:address":"701 Westwood Ave",
    "sg:city":"Columbia",
    "sg:classifiers":[
        {
            "category":"Real Estate",
            "subcategory":"Real Estate Agent",
            "type":"Services"
        }
    ],
    "sg:phone":"+1 573 449 4663",
    "sg:postcode":"65203",
    "sg:province":"MO",
    "wof:name":"Show ME Properties LLC",
    "wof:placetype":"venue"
},
  "geometry": {"coordinates":[-92.345431,38.944812],"type":"Point"}
}