{
  "type": "Feature",
  "properties": {
    "iso:country":"US",
    "sg:address":"30040 Blackoak Rd",
    "sg:city":"Richland",
    "sg:classifiers":[
        {
            "category":"Professional",
            "subcategory":"Management & Consulting",
            "type":"Services"
        }
    ],
    "sg:phone":"+1 573 736 5119",
    "sg:postcode":"65556",
    "sg:province":"MO",
    "sg:tags":[
        "farm"
    ],
    "wof:name":"C E Thornsberry",
    "wof:placetype":"venue"
},
  "geometry": {"coordinates":[-92.389895,37.97413],"type":"Point"}
}