{
  "type": "Feature",
  "properties": {
    "iso:country":"US",
    "sg:address":"5300 Butler Hill Rd",
    "sg:city":"Saint Louis",
    "sg:classifiers":[
        {
            "category":"Professional",
            "subcategory":"Management & Consulting",
            "type":"Services"
        }
    ],
    "sg:phone":"+1 314 842 0588",
    "sg:postcode":"63128",
    "sg:province":"MO",
    "wof:name":"Delmar Gardens of South County",
    "wof:placetype":"venue"
},
  "geometry": {"coordinates":[-90.392319,38.480414],"type":"Point"}
}