{
  "type": "Feature",
  "properties": {
    "iso:country":"US",
    "sg:address":"6269 Delmar Blvd",
    "sg:city":"Saint Louis",
    "sg:classifiers":[
        {
            "category":"Travel",
            "subcategory":"Travel Agent",
            "type":"Entertainment"
        }
    ],
    "sg:phone":"+1 314 863 8885",
    "sg:postcode":"63130",
    "sg:province":"MO",
    "sg:tags":[
        "agency"
    ],
    "wof:name":"Ethopian Omo Adventure Travel",
    "wof:placetype":"venue"
},
  "geometry": {"coordinates":[-90.30366100000001,38.655914],"type":"Point"}
}