{
  "type": "Feature",
  "properties": {
    "iso:country":"US",
    "sg:address":"5400 Natural Bridge Ave",
    "sg:city":"St Louis",
    "sg:classifiers":[
        {
            "category":"Autos & Motor Vehicles",
            "subcategory":"Automobile Sales",
            "type":"Retail Goods"
        }
    ],
    "sg:phone":"+1 314 389 5551",
    "sg:postcode":"63120",
    "sg:province":"MO",
    "sg:tags":[
        "car",
        "dealer"
    ],
    "wof:name":"Drive Buy Auto Sales",
    "wof:placetype":"venue"
},
  "geometry": {"coordinates":[-90.261827,38.680809],"type":"Point"}
}