{
  "type": "Feature",
  "properties": {
    "iso:country":"US",
    "sg:address":"20602 Laramie Rd",
    "sg:city":"St Robert",
    "sg:classifiers":[
        {
            "category":"Building & Trades",
            "subcategory":"Landscaping Services",
            "type":"Services"
        }
    ],
    "sg:phone":"+1 573 336 8717",
    "sg:postcode":"65584",
    "sg:province":"MO",
    "sg:tags":[
        "nurseryman",
        "landscape"
    ],
    "wof:name":"Living Touch Landscaping",
    "wof:placetype":"venue"
},
  "geometry": {"coordinates":[-92.15093,37.860299],"type":"Point"}
}