{
  "type": "Feature",
  "properties": {
    "addr:full":"506 N Jackson St Salem MO 65560",
    "addr:housenumber":"506",
    "addr:postcode":"65560",
    "addr:street":"N Jackson St",
    "iso:country":"US",
    "sg:address":"506 N Jackson St",
    "sg:city":"Salem",
    "sg:classifiers":[
        {
            "category":"Government",
            "subcategory":"Police Station",
            "type":"Public Place"
        }
    ],
    "sg:phone":"+1 573 729 6550",
    "sg:postcode":"65560",
    "sg:province":"MO",
    "sg:tags":[
        "department"
    ],
    "wof:name":"Salem Police Chief",
    "wof:placetype":"venue"
},
  "geometry": {"coordinates":[-91.53829399999999,37.646697],"type":"Point"}
}