{
  "type": "Feature",
  "properties": {
    "iso:country":"US",
    "sg:address":"41 S Spanish St",
    "sg:city":"Cape Girardeau",
    "sg:classifiers":[
        {
            "category":"Real Estate",
            "subcategory":"Real Estate Agent",
            "type":"Services"
        }
    ],
    "sg:phone":"+1 573 651 4363",
    "sg:postcode":"63703",
    "sg:province":"MO",
    "wof:name":"Mc Clanahan Realty",
    "wof:placetype":"venue"
},
  "geometry": {"coordinates":[-89.51964099999999,37.302872],"type":"Point"}
}