{
  "type": "Feature",
  "properties": {
    "iso:country":"US",
    "sg:address":"2605 Jere Ln",
    "sg:city":"Arnold",
    "sg:classifiers":[
        {
            "category":"Building & Trades",
            "subcategory":"Construction",
            "type":"Services"
        }
    ],
    "sg:phone":"+1 636 296 9369",
    "sg:postcode":"63010",
    "sg:province":"MO",
    "sg:tags":[
        "wallcoverings-installation",
        "wallpaper",
        "painting",
        "contractor"
    ],
    "wof:name":"Hertel Painting",
    "wof:placetype":"venue"
},
  "geometry": {"coordinates":[-90.36721799999999,38.435347],"type":"Point"}
}