{
  "type": "Feature",
  "properties": {
    "iso:country":"US",
    "sg:address":"106 Elbring Dr",
    "sg:city":"St Louis",
    "sg:classifiers":[
        {
            "category":"Building & Trades",
            "subcategory":"Construction",
            "type":"Services"
        }
    ],
    "sg:phone":"+1 314 521 2368",
    "sg:postcode":"63135",
    "sg:province":"MO",
    "sg:tags":[
        "downspouts",
        "gutter"
    ],
    "wof:name":"Martin Exteriors",
    "wof:placetype":"venue"
},
  "geometry": {"coordinates":[-90.317915,38.766041],"type":"Point"}
}