{
  "type": "Feature",
  "properties": {
    "iso:country":"US",
    "sg:address":"3930 S Providence Rd Suite A",
    "sg:city":"Columbia",
    "sg:classifiers":[
        {
            "category":"Professional",
            "type":"Services"
        },
        {
            "category":"Shopping",
            "subcategory":"Bicycles & Sporting Goods",
            "type":"Retail Goods"
        },
        {
            "category":"Wholesale",
            "subcategory":"Chemicals & Plastics",
            "type":"Manufacturing & Wholesale Goods"
        }
    ],
    "sg:phone":"+1 573 443 8738",
    "sg:postcode":"65203",
    "sg:province":"MO",
    "sg:tags":[
        "supply",
        "tubs-repair",
        "equipment",
        "hot",
        "spa",
        "manufacturer",
        "supplies-wholesale",
        "pool",
        "swimming"
    ],
    "sg:website":"http://www.vaughanpools.com",
    "wof:name":"Vaughan Pools & Spas - A BioGuard Platinum Dealer",
    "wof:placetype":"venue"
},
  "geometry": {"coordinates":[-92.335484,38.906944],"type":"Point"}
}