{
  "type": "Feature",
  "properties": {
    "iso:country":"US",
    "sg:address":"13002 US Hwy 40",
    "sg:city":"Independence",
    "sg:classifiers":[
        {
            "category":"Restaurant",
            "type":"Food & Drink"
        }
    ],
    "sg:phone":"+1 816 358 5520",
    "sg:postcode":"64055",
    "sg:province":"MO",
    "wof:name":"Fun House Pizza & Pub",
    "wof:placetype":"venue"
},
  "geometry": {"coordinates":[-94.427306,39.037604],"type":"Point"}
}