{
  "type": "Feature",
  "properties": {
    "iso:country":"US",
    "sg:address":"3450 SW Hook Rd",
    "sg:city":"Lees Summit",
    "sg:classifiers":[
        {
            "category":"Recreation",
            "type":"Entertainment"
        }
    ],
    "sg:phone":"+1 816 246 4660",
    "sg:postcode":"64082",
    "sg:province":"MO",
    "sg:tags":[
        "stable"
    ],
    "wof:name":"Green Gate Stables",
    "wof:placetype":"venue"
},
  "geometry": {"coordinates":[-94.46254500000001,38.873497],"type":"Point"}
}