{
  "type": "Feature",
  "properties": {
    "iso:country":"US",
    "sg:address":"3483 Coyote Dr",
    "sg:city":"Joplin",
    "sg:classifiers":[
        {
            "category":"Recreation",
            "type":"Entertainment"
        }
    ],
    "sg:phone":"+1 417 781 7703",
    "sg:postcode":"64804",
    "sg:province":"MO",
    "sg:tags":[
        "paint",
        "ball",
        "sport"
    ],
    "wof:name":"Paintball Ridge",
    "wof:placetype":"venue"
},
  "geometry": {"coordinates":[-94.550186,37.020504],"type":"Point"}
}