{
  "type": "Feature",
  "properties": {
    "addr:full":"1000 NE Sam Walton Ln Lees Summit MO 64086",
    "addr:housenumber":"1000",
    "addr:postcode":"64086",
    "addr:street":"Ne Sam Walton Ln",
    "iso:country":"US",
    "sg:address":"1000 NE Sam Walton Ln",
    "sg:city":"Lees Summit",
    "sg:classifiers":[
        {
            "category":"Shopping",
            "subcategory":"Department Store",
            "type":"Retail Goods"
        }
    ],
    "sg:phone":"+1 816 246 4555",
    "sg:postcode":"64086",
    "sg:province":"MO",
    "sg:website":"www.walmart.com",
    "wof:name":"Wal-Mart Supercenter",
    "wof:placetype":"venue"
},
  "geometry": {"coordinates":[-94.36248500000001,38.931145],"type":"Point"}
}