{
  "type": "Feature",
  "properties": {
    "iso:country":"US",
    "sg:address":"4501 Telegraph Rd",
    "sg:city":"St Louis",
    "sg:classifiers":[
        {
            "category":"Professional",
            "subcategory":"Accounting & Tax Preparation",
            "type":"Services"
        }
    ],
    "sg:phone":"+1 314 487 4000",
    "sg:postcode":"63129",
    "sg:province":"MO",
    "sg:tags":[
        "accountant"
    ],
    "wof:name":"Maixner Maixner & Co",
    "wof:placetype":"venue"
},
  "geometry": {"coordinates":[-90.304464,38.480083],"type":"Point"}
}