{
  "type": "Feature",
  "properties": {
    "iso:country":"US",
    "sg:address":"6203 Cote Brilliante Ave",
    "sg:city":"St Louis",
    "sg:classifiers":[
        {
            "category":"Real Estate",
            "subcategory":"Real Estate Agent",
            "type":"Services"
        }
    ],
    "sg:phone":"+1 314 385 4089",
    "sg:postcode":"63133",
    "sg:province":"MO",
    "sg:tags":[
        "authorities",
        "housing"
    ],
    "wof:name":"Wellston Housing Authority",
    "wof:placetype":"venue"
},
  "geometry": {"coordinates":[-90.286136,38.677526],"type":"Point"}
}