{
  "type": "Feature",
  "properties": {
    "iso:country":"US",
    "sg:address":"903 Main St",
    "sg:city":"Trenton",
    "sg:classifiers":[
        {
            "category":"Professional",
            "subcategory":"Accounting & Tax Preparation",
            "type":"Services"
        }
    ],
    "sg:phone":"+1 660 359 4477",
    "sg:postcode":"64683",
    "sg:province":"MO",
    "sg:tags":[
        "bookkeeping",
        "return",
        "accountants-certified",
        "preparation-business",
        "public"
    ],
    "wof:name":"Segrist & Associates Pc",
    "wof:placetype":"venue"
},
  "geometry": {"coordinates":[-93.618171,40.074763],"type":"Point"}
}