{
  "type": "Feature",
  "properties": {
    "iso:country":"US",
    "sg:address":"2637 S Farm Rd 45",
    "sg:city":"Republic",
    "sg:classifiers":[
        {
            "category":"Building & Trades",
            "subcategory":"Construction",
            "type":"Services"
        }
    ],
    "sg:phone":"+1 417 732 8796",
    "sg:postcode":"65738",
    "sg:province":"MO",
    "sg:tags":[
        "excavation",
        "contractor"
    ],
    "wof:name":"Hamilton & Dad",
    "wof:placetype":"venue"
},
  "geometry": {"coordinates":[-93.55131900000001,37.170706],"type":"Point"}
}