{
  "type": "Feature",
  "properties": {
    "iso:country":"US",
    "sg:address":"12048 Tesson Ferry Rd",
    "sg:city":"Saint Louis",
    "sg:classifiers":[
        {
            "category":"Professional",
            "subcategory":"Accounting & Tax Preparation",
            "type":"Services"
        }
    ],
    "sg:phone":"+1 314 843 0307",
    "sg:postcode":"63128",
    "sg:province":"MO",
    "wof:name":"James J Tabor",
    "wof:placetype":"venue"
},
  "geometry": {"coordinates":[-90.365207,38.517972],"type":"Point"}
}