{
  "type": "Feature",
  "properties": {
    "iso:country":"US",
    "sg:address":"3001 Mercier St",
    "sg:city":"Kansas City",
    "sg:classifiers":[
        {
            "category":"Wholesale",
            "subcategory":"Vending Machines",
            "type":"Manufacturing & Wholesale Goods"
        }
    ],
    "sg:phone":"+1 816 931 0726",
    "sg:postcode":"64108",
    "sg:province":"MO",
    "sg:tags":[
        "automatic"
    ],
    "wof:name":"Vend-All Inc",
    "wof:placetype":"venue"
},
  "geometry": {"coordinates":[-94.600234,39.07158],"type":"Point"}
}