{
  "type": "Feature",
  "properties": {
    "iso:country":"US",
    "sg:address":"5823 Wilson Ave",
    "sg:city":"St Louis",
    "sg:classifiers":[
        {
            "category":"Travel",
            "subcategory":"Hotels & Motels",
            "type":"Entertainment"
        }
    ],
    "sg:phone":"+1 314 645 0101",
    "sg:postcode":"63110",
    "sg:province":"MO",
    "wof:name":"Red Roof Inn",
    "wof:placetype":"venue"
},
  "geometry": {"coordinates":[-90.286267,38.617932],"type":"Point"}
}