{
  "type": "Feature",
  "properties": {
    "iso:country":"US",
    "sg:address":"9706 Twincrest Dr",
    "sg:city":"Saint Louis",
    "sg:classifiers":[
        {
            "category":"Wholesale",
            "subcategory":"Non-durable Goods",
            "type":"Manufacturing & Wholesale Goods"
        }
    ],
    "sg:phone":"+1 314 968 7991",
    "sg:postcode":"63126",
    "sg:province":"MO",
    "wof:name":"Mk Distributing",
    "wof:placetype":"venue"
},
  "geometry": {"coordinates":[-90.38261900000001,38.560705],"type":"Point"}
}