{
  "type": "Feature",
  "properties": {
    "iso:country":"US",
    "sg:address":"3156 S Campbell Ave",
    "sg:city":"Springfield",
    "sg:classifiers":[
        {
            "category":"Personal",
            "subcategory":"Barber",
            "type":"Services"
        }
    ],
    "sg:phone":"+1 417 886 7600",
    "sg:postcode":"65807",
    "sg:province":"MO",
    "sg:tags":[
        "shop"
    ],
    "wof:name":"All Star Barber Shop",
    "wof:placetype":"venue"
},
  "geometry": {"coordinates":[-93.295462,37.157763],"type":"Point"}
}