{
  "type": "Feature",
  "properties": {
    "iso:country":"US",
    "sg:address":"1000 Prairie Ln",
    "sg:city":"Oak Grove",
    "sg:classifiers":[
        {
            "category":"Real Estate",
            "subcategory":"Real Estate Operator",
            "type":"Services"
        }
    ],
    "sg:phone":"+1 816 625 7567",
    "sg:postcode":"64075",
    "sg:province":"MO",
    "sg:tags":[
        "apartment"
    ],
    "wof:name":"Heather Oak Grove",
    "wof:placetype":"venue"
},
  "geometry": {"coordinates":[-94.1161,39.007103],"type":"Point"}
}