{
  "type": "Feature",
  "properties": {
    "iso:country":"US",
    "sg:address":"1262 W Foxwood Dr",
    "sg:city":"Raymore",
    "sg:classifiers":[
        {
            "category":"Shopping",
            "subcategory":"Computers & Home Electronics",
            "type":"Retail Goods"
        }
    ],
    "sg:phone":"+1 816 348 7660",
    "sg:postcode":"64083",
    "sg:province":"MO",
    "sg:tags":[
        "equipment",
        "dealer"
    ],
    "wof:name":"Computer Shoppe",
    "wof:placetype":"venue"
},
  "geometry": {"coordinates":[-94.47794,38.812267],"type":"Point"}
}