{
  "type": "Feature",
  "properties": {
    "iso:country":"US",
    "sg:address":"1 Mcbride And Son Center Dr",
    "sg:city":"Chesterfield",
    "sg:phone":"+1 636 537 2000",
    "sg:postcode":"63005",
    "sg:province":"MO",
    "sg:website":"http://www.mcbridehomes.com",
    "wof:name":"J & E Mc Bride Char Fdn, Inc.",
    "wof:placetype":"venue"
},
  "geometry": {"coordinates":[-90.601944,38.668381],"type":"Point"}
}