{
  "type": "Feature",
  "properties": {
    "iso:country":"US",
    "sg:address":"1363 Shepley Dr",
    "sg:city":"Saint Louis",
    "sg:classifiers":[
        {
            "category":"Professional",
            "type":"Services"
        }
    ],
    "sg:phone":"+1 314 869 0547",
    "sg:postcode":"63137",
    "sg:province":"MO",
    "wof:name":"Allan M Ellis",
    "wof:placetype":"venue"
},
  "geometry": {"coordinates":[-90.216865,38.758053],"type":"Point"}
}