{
  "type": "Feature",
  "properties": {
    "iso:country":"US",
    "sg:address":"4954 Lindell Blvd Apt 8W",
    "sg:city":"Saint Louis",
    "sg:classifiers":[
        {
            "category":"Professional",
            "subcategory":"Lawyer & Legal Services",
            "type":"Services"
        }
    ],
    "sg:phone":"+1 314 367 5301",
    "sg:postcode":"63108",
    "sg:province":"MO",
    "wof:name":"Newburger David J Atty",
    "wof:placetype":"venue"
},
  "geometry": {"coordinates":[-90.26300000000001,38.643501],"type":"Point"}
}