{
  "type": "Feature",
  "properties": {
    "iso:country":"US",
    "sg:address":"523 W Lake St",
    "sg:city":"Marceline",
    "sg:classifiers":[
        {
            "category":"Banks & Credit Unions",
            "subcategory":"Investment Brokerage",
            "type":"Services"
        }
    ],
    "sg:phone":"+1 660 376 2099",
    "sg:postcode":"64658",
    "sg:province":"MO",
    "sg:tags":[
        "security"
    ],
    "wof:name":"Edward Jones 22807",
    "wof:placetype":"venue"
},
  "geometry": {"coordinates":[-92.958696,39.715565],"type":"Point"}
}