{
  "type": "Feature",
  "properties": {
    "iso:country":"US",
    "sg:address":"250 Co Rd 209",
    "sg:city":"Fayette",
    "sg:classifiers":[
        {
            "category":"Retail",
            "subcategory":"Auto Repair",
            "type":"Services"
        }
    ],
    "sg:phone":"+1 660 248 3554",
    "sg:postcode":"65248",
    "sg:province":"MO",
    "sg:tags":[
        "repairing",
        "automobile"
    ],
    "wof:name":"Westhues Automotive",
    "wof:placetype":"venue"
},
  "geometry": {"coordinates":[-92.695994,39.176935],"type":"Point"}
}