{
  "type": "Feature",
  "properties": {
    "iso:country":"US",
    "sg:address":"149 Hwy 5",
    "sg:city":"Gravois Mills",
    "sg:classifiers":[
        {
            "category":"Shopping",
            "subcategory":"Used Merchandise",
            "type":"Retail Goods"
        }
    ],
    "sg:phone":"+1 573 372 2201",
    "sg:postcode":"65037",
    "sg:province":"MO",
    "sg:tags":[
        "operation"
    ],
    "wof:name":"Waters Edge Motel",
    "wof:placetype":"venue"
},
  "geometry": {"coordinates":[-92.83576100000001,38.200287],"type":"Point"}
}