{
  "type": "Feature",
  "properties": {
    "iso:country":"US",
    "sg:address":"107 W 2nd St",
    "sg:city":"Montgomery City",
    "sg:classifiers":[
        {
            "category":"Shopping",
            "subcategory":"Florist",
            "type":"Retail Goods"
        }
    ],
    "sg:phone":"+1 573 564 2235",
    "sg:postcode":"63361",
    "sg:province":"MO",
    "sg:tags":[
        "personal",
        "clothing"
    ],
    "wof:name":"Montgomery City Florist",
    "wof:placetype":"venue"
},
  "geometry": {"coordinates":[-91.505078,38.977516],"type":"Point"}
}