{
  "type": "Feature",
  "properties": {
    "iso:country":"US",
    "sg:address":"4225 Wildwood Ct",
    "sg:city":"Hannibal",
    "sg:classifiers":[
        {
            "category":"Banks & Credit Unions",
            "subcategory":"Bank",
            "type":"Services"
        },
        {
            "category":"Shopping",
            "subcategory":"Used Merchandise",
            "type":"Retail Goods"
        }
    ],
    "sg:phone":"+1 573 221 6345",
    "sg:postcode":"63401",
    "sg:province":"MO",
    "sg:tags":[
        "resale",
        "shop",
        "second",
        "hand"
    ],
    "wof:name":"De La Porte Auction Service",
    "wof:placetype":"venue"
},
  "geometry": {"coordinates":[-91.41086199999999,39.72451],"type":"Point"}
}