{
  "type": "Feature",
  "properties": {
    "iso:country":"US",
    "sg:address":"109 W Young St",
    "sg:city":"Warrensburg",
    "sg:classifiers":[
        {
            "category":"Autos & Motor Vehicles",
            "subcategory":"Automobile Sales",
            "type":"Retail Goods"
        }
    ],
    "sg:phone":"+1 660 429 2257",
    "sg:postcode":"64093",
    "sg:province":"MO",
    "sg:tags":[
        "used"
    ],
    "wof:name":"Lotspeich Motors Used Cars",
    "wof:placetype":"venue"
},
  "geometry": {"coordinates":[-93.74216300000001,38.771305],"type":"Point"}
}