{
  "type": "Feature",
  "properties": {
    "iso:country":"US",
    "sg:address":"505 Washington St",
    "sg:city":"Fulton",
    "sg:classifiers":[
        {
            "category":"Social Services",
            "subcategory":"Child Care",
            "type":"Services"
        }
    ],
    "sg:phone":"+1 573 642 8696",
    "sg:postcode":"65251",
    "sg:province":"MO",
    "sg:tags":[
        "day"
    ],
    "wof:name":"House Full of Kids",
    "wof:placetype":"venue"
},
  "geometry": {"coordinates":[-91.950265,38.839496],"type":"Point"}
}