{
  "type": "Feature",
  "properties": {
    "iso:country":"US",
    "sg:address":"8509 Greenwood Rd",
    "sg:city":"Raytown",
    "sg:classifiers":[
        {
            "category":"Structure",
            "subcategory":"Office Building",
            "type":"Public Place"
        }
    ],
    "sg:phone":"+1 816 737 1881",
    "sg:postcode":"64138",
    "sg:province":"MO",
    "sg:tags":[
        "park"
    ],
    "wof:name":"Crowe Home And Property",
    "wof:placetype":"venue"
},
  "geometry": {"coordinates":[-94.49468,38.969051],"type":"Point"}
}