{
  "type": "Feature",
  "properties": {
    "iso:country":"US",
    "sg:address":"303 W State Hwy 174",
    "sg:city":"Republic",
    "sg:classifiers":[
        {
            "category":"Organizations",
            "subcategory":"Religious Organization",
            "type":"Services"
        }
    ],
    "sg:phone":"+1 417 732 7823",
    "sg:postcode":"65738",
    "sg:province":"MO",
    "sg:tags":[
        "church"
    ],
    "wof:name":"United Pentecostal Ch Republic",
    "wof:placetype":"venue"
},
  "geometry": {"coordinates":[-93.48577299999999,37.123142],"type":"Point"}
}