{
  "type": "Feature",
  "properties": {
    "iso:country":"US",
    "sg:address":"14945 Co Rd 6260",
    "sg:city":"Edgar Springs",
    "sg:classifiers":[
        {
            "category":"Building & Trades",
            "subcategory":"Construction",
            "type":"Services"
        }
    ],
    "sg:phone":"+1 573 435 6726",
    "sg:postcode":"65462",
    "sg:province":"MO",
    "sg:tags":[
        "contractor"
    ],
    "wof:name":"Independent Masonry",
    "wof:placetype":"venue"
},
  "geometry": {"coordinates":[-91.843317,37.639213],"type":"Point"}
}