{
  "type": "Feature",
  "properties": {
    "iso:country":"US",
    "sg:address":"1557 Missouri State Rd",
    "sg:city":"Arnold",
    "sg:classifiers":[
        {
            "category":"Insurance",
            "subcategory":"Insurance Agent",
            "type":"Services"
        }
    ],
    "sg:phone":"+1 636 296 9094",
    "sg:postcode":"63010",
    "sg:province":"MO",
    "wof:name":"Newsome Phil Insurance Agency",
    "wof:placetype":"venue"
},
  "geometry": {"coordinates":[-90.40545299999999,38.443615],"type":"Point"}
}