{
  "type": "Feature",
  "properties": {
    "iso:country":"US",
    "sg:address":"524 N Scott Ave",
    "sg:city":"Belton",
    "sg:classifiers":[
        {
            "category":"Food & Beverages",
            "subcategory":"Groceries & Convenience Stores",
            "type":"Retail Goods"
        }
    ],
    "sg:phone":"+1 816 331 5677",
    "sg:postcode":"64012",
    "sg:province":"MO",
    "sg:tags":[
        "grocer"
    ],
    "wof:name":"Jose Luis Bencomo Grocery",
    "wof:placetype":"venue"
},
  "geometry": {"coordinates":[-94.534311,38.822818],"type":"Point"}
}