{
  "type": "Feature",
  "properties": {
    "iso:country":"US",
    "sg:address":"16962 Manchester Rd",
    "sg:city":"Grover",
    "sg:classifiers":[
        {
            "category":"Government",
            "subcategory":"Office",
            "type":"Public Place"
        }
    ],
    "sg:phone":"+1 636 458 4886",
    "sg:postcode":"63040",
    "sg:province":"MO",
    "sg:tags":[
        "village"
    ],
    "wof:name":"City Of Wildwood",
    "wof:placetype":"venue"
},
  "geometry": {"coordinates":[-90.64004799999999,38.576043],"type":"Point"}
}