{
  "type": "Feature",
  "properties": {
    "iso:country":"US",
    "sg:address":"1674 S Catalina Ave",
    "sg:city":"Springfield",
    "sg:classifiers":[
        {
            "category":"Health Services",
            "subcategory":"Clinic",
            "type":"Services"
        }
    ],
    "sg:phone":"+1 417 887 7783",
    "sg:postcode":"65804",
    "sg:province":"MO",
    "sg:tags":[
        "information",
        "alcoholism",
        "treatment"
    ],
    "wof:name":"Oxford House",
    "wof:placetype":"venue"
},
  "geometry": {"coordinates":[-93.231087,37.181626],"type":"Point"}
}