{
  "type": "Feature",
  "properties": {
    "iso:country":"US",
    "sg:address":"251 Scott Joplin Ct",
    "sg:city":"Sedalia",
    "sg:classifiers":[
        {
            "category":"Social Services",
            "subcategory":"Child Care",
            "type":"Services"
        }
    ],
    "sg:phone":"+1 660 827 6969",
    "sg:postcode":"65301",
    "sg:province":"MO",
    "wof:name":"Aunt B's Daycare",
    "wof:placetype":"venue"
},
  "geometry": {"coordinates":[-93.215868,38.710579],"type":"Point"}
}