{
  "type": "Feature",
  "properties": {
    "iso:country":"US",
    "sg:address":"20 S Ridge Rd",
    "sg:city":"St Charles",
    "sg:classifiers":[
        {
            "category":"Shopping",
            "subcategory":"Computers & Home Electronics",
            "type":"Retail Goods"
        }
    ],
    "sg:phone":"+1 636 274 9100",
    "sg:postcode":"63379",
    "sg:province":"MO",
    "sg:tags":[
        "equipment",
        "dealer"
    ],
    "wof:name":"Friendly Computers",
    "wof:placetype":"venue"
},
  "geometry": {"coordinates":[-90.889009,38.986641],"type":"Point"}
}