{
  "type": "Feature",
  "properties": {
    "iso:country":"US",
    "sg:address":"1801 Katherine Ave",
    "sg:city":"Joplin",
    "sg:classifiers":[
        {
            "category":"Wholesale",
            "subcategory":"Drugs",
            "type":"Manufacturing & Wholesale Goods"
        }
    ],
    "sg:phone":"+1 417 843 5001",
    "sg:postcode":"64801",
    "sg:province":"MO",
    "wof:name":"Allan Medical Company & Design",
    "wof:placetype":"venue"
},
  "geometry": {"coordinates":[-94.46731699999999,37.071089],"type":"Point"}
}