{
  "type": "Feature",
  "properties": {
    "iso:country":"US",
    "sg:address":"1406 Broadway St",
    "sg:city":"Joplin",
    "sg:classifiers":[
        {
            "category":"Social Services",
            "type":"Services"
        }
    ],
    "sg:phone":"+1 417 782 6660",
    "sg:postcode":"64801",
    "sg:province":"MO",
    "sg:tags":[
        "counseling"
    ],
    "wof:name":"Route 66 Counseling Ctr",
    "wof:placetype":"venue"
},
  "geometry": {"coordinates":[-94.49682799999999,37.091672],"type":"Point"}
}