{
  "type": "Feature",
  "properties": {
    "iso:country":"US",
    "sg:address":"1821 N Jefferson St",
    "sg:city":"Mexico",
    "sg:classifiers":[
        {
            "category":"Retail",
            "subcategory":"Portrait Studio",
            "type":"Services"
        }
    ],
    "sg:phone":"+1 573 581 2818",
    "sg:postcode":"65265",
    "sg:province":"MO",
    "sg:tags":[
        "photo"
    ],
    "wof:name":"Unger Photographic Designs",
    "wof:placetype":"venue"
},
  "geometry": {"coordinates":[-91.88229200000001,39.186815],"type":"Point"}
}