{
  "type": "Feature",
  "properties": {
    "iso:country":"US",
    "sg:address":"1909 N Commercial St",
    "sg:city":"Harrisonville",
    "sg:classifiers":[
        {
            "category":"Professional",
            "subcategory":"Accounting & Tax Preparation",
            "type":"Services"
        }
    ],
    "sg:phone":"+1 816 380 3548",
    "sg:postcode":"64701",
    "sg:province":"MO",
    "sg:tags":[
        "accountant"
    ],
    "wof:name":"CTN Tax & Bookkeeping",
    "wof:placetype":"venue"
},
  "geometry": {"coordinates":[-94.359861,38.662258],"type":"Point"}
}