{
  "type": "Feature",
  "properties": {
    "iso:country":"US",
    "sg:address":"900 E Battlefield Rd",
    "sg:city":"Springfield",
    "sg:classifiers":[
        {
            "category":"Shopping",
            "subcategory":"Clothing, Apparel, & Fashions",
            "type":"Retail Goods"
        }
    ],
    "sg:phone":"+1 417 889 2117",
    "sg:postcode":"65804",
    "sg:province":"MO",
    "sg:tags":[
        "shoes"
    ],
    "wof:name":"Jellybean Childrens Wear",
    "wof:placetype":"venue"
},
  "geometry": {"coordinates":[-93.28320600000001,37.159625],"type":"Point"}
}