{
  "type": "Feature",
  "properties": {
    "iso:country":"US",
    "sg:address":"3737 W Chestnut Expy",
    "sg:city":"Springfield",
    "sg:classifiers":[
        {
            "category":"Building & Trades",
            "subcategory":"Construction",
            "type":"Services"
        }
    ],
    "sg:phone":"+1 417 862 9120",
    "sg:postcode":"65802",
    "sg:province":"MO",
    "sg:tags":[
        "roofing",
        "contractor"
    ],
    "wof:name":"Larry's Roofing Svc",
    "wof:placetype":"venue"
},
  "geometry": {"coordinates":[-93.353421,37.212345],"type":"Point"}
}