{
  "type": "Feature",
  "properties": {
    "iso:country":"US",
    "sg:address":"8204 NW Forest Dr",
    "sg:city":"Parkville",
    "sg:classifiers":[
        {
            "category":"Manufacturing",
            "subcategory":"Printing",
            "type":"Manufacturing & Wholesale Goods"
        }
    ],
    "sg:phone":"+1 816 505 9566",
    "sg:postcode":"64152",
    "sg:province":"MO",
    "sg:tags":[
        "publisher"
    ],
    "sg:website":"www.performingartspub.com",
    "wof:name":"Spotlight Magazine",
    "wof:placetype":"venue"
},
  "geometry": {"coordinates":[-94.687698,39.24553],"type":"Point"}
}