{
  "type": "Feature",
  "properties": {
    "iso:country":"US",
    "sg:address":"3737 S Elizabeth St Suite 103",
    "sg:city":"Independence",
    "sg:classifiers":[
        {
            "category":"Banks & Credit Unions",
            "subcategory":"Financial Services",
            "type":"Services"
        }
    ],
    "sg:phone":"+1 816 753 0535",
    "sg:postcode":"64057",
    "sg:province":"MO",
    "sg:tags":[
        "information",
        "adjuster",
        "plan",
        "counseling",
        "debt",
        "consumer"
    ],
    "sg:website":"http://www.apprisen.com",
    "wof:name":"CCCS of Greater Kansas City & Mid-Missouri - A Division Of Apprisen Financial Advocates",
    "wof:placetype":"venue"
},
  "geometry": {"coordinates":[-94.360856,39.049837],"type":"Point"}
}