{
  "type": "Feature",
  "properties": {
    "iso:country":"US",
    "sg:address":"111 E Cherry St",
    "sg:city":"Nevada",
    "sg:classifiers":[
        {
            "category":"Shopping",
            "subcategory":"Bicycles & Sporting Goods",
            "type":"Retail Goods"
        }
    ],
    "sg:phone":"+1 417 667 6703",
    "sg:postcode":"64772",
    "sg:province":"MO",
    "wof:name":"G&M Gun Pawn Collectables",
    "wof:placetype":"venue"
},
  "geometry": {"coordinates":[-94.356515,37.838251],"type":"Point"}
}