{
  "type": "Feature",
  "properties": {
    "iso:country":"US",
    "sg:address":"1029 SE Country Ln",
    "sg:city":"Lees Summit",
    "sg:classifiers":[
        {
            "category":"Banks & Credit Unions",
            "subcategory":"Financial Services",
            "type":"Services"
        }
    ],
    "sg:phone":"+1 816 220 7413",
    "sg:postcode":"64081",
    "sg:province":"MO",
    "sg:tags":[
        "trust"
    ],
    "wof:name":"John E Stone Trust",
    "wof:placetype":"venue"
},
  "geometry": {"coordinates":[-94.347368,38.899622],"type":"Point"}
}