{
  "type": "Feature",
  "properties": {
    "iso:country":"US",
    "sg:address":"5811 Kenwood Ave",
    "sg:city":"Kansas City",
    "sg:phone":"+1 816 523 1323",
    "sg:postcode":"64110",
    "sg:province":"MO",
    "sg:tags":[
        "product",
        "petroleum"
    ],
    "wof:name":"Pats Customized Oil Dist Ctr",
    "wof:placetype":"venue"
},
  "geometry": {"coordinates":[-94.579894,39.020339],"type":"Point"}
}