{
  "type": "Feature",
  "properties": {
    "iso:country":"US",
    "sg:address":"412 State Hwy 53",
    "sg:city":"Campbell",
    "sg:classifiers":[
        {
            "category":"Retail",
            "subcategory":"Auto Repair",
            "type":"Services"
        }
    ],
    "sg:phone":"+1 573 246 2140",
    "sg:postcode":"63933",
    "sg:province":"MO",
    "sg:tags":[
        "automotive",
        "station",
        "gasoline"
    ],
    "wof:name":"Davis Service Station",
    "wof:placetype":"venue"
},
  "geometry": {"coordinates":[-90.072489,36.499555],"type":"Point"}
}