{
  "type": "Feature",
  "properties": {
    "iso:country":"US",
    "sg:address":"7511 Olive Blvd",
    "sg:city":"St Louis",
    "sg:classifiers":[
        {
            "category":"Shopping",
            "type":"Retail Goods"
        }
    ],
    "sg:phone":"+1 314 721 5070",
    "sg:postcode":"63130",
    "sg:province":"MO",
    "sg:tags":[
        "grave",
        "monument"
    ],
    "wof:name":"Rosenbloom Monument Co",
    "wof:placetype":"venue"
},
  "geometry": {"coordinates":[-90.33506199999999,38.672112],"type":"Point"}
}