{
  "type": "Feature",
  "properties": {
    "iso:country":"US",
    "sg:address":"1398 Clarkson Clayton Ctr",
    "sg:city":"Ellisville",
    "sg:classifiers":[
        {
            "category":"Shopping",
            "subcategory":"Pets & Pet Supplies",
            "type":"Retail Goods"
        },
        {
            "category":"Retail",
            "subcategory":"Veterinary Services",
            "type":"Services"
        }
    ],
    "sg:phone":"+1 636 227 9600",
    "sg:postcode":"63011",
    "sg:province":"MO",
    "sg:tags":[
        "hospital",
        "specialty",
        "dog",
        "clinic",
        "veterinarian",
        "furnishing",
        "cat",
        "store"
    ],
    "wof:name":"Ark Pet Center",
    "wof:placetype":"venue"
},
  "geometry": {"coordinates":[-90.587997,38.604858],"type":"Point"}
}