{
  "type": "Feature",
  "properties": {
    "iso:country":"US",
    "sg:address":"8403 Sunbury Ave",
    "sg:city":"St Louis",
    "sg:classifiers":[
        {
            "category":"Shopping",
            "subcategory":"Clothing, Apparel, & Fashions",
            "type":"Retail Goods"
        }
    ],
    "sg:phone":"+1 314 383 9838",
    "sg:postcode":"63136",
    "sg:province":"MO",
    "sg:tags":[
        "t"
    ],
    "wof:name":"Unique Designs One Of A Kind",
    "wof:placetype":"venue"
},
  "geometry": {"coordinates":[-90.27197099999999,38.724678],"type":"Point"}
}