{
  "type": "Feature",
  "properties": {
    "iso:country":"US",
    "sg:address":"6849 Julian Ave",
    "sg:city":"Saint Louis",
    "sg:classifiers":[
        {
            "category":"Professional",
            "type":"Services"
        }
    ],
    "sg:phone":"+1 314 725 9793",
    "sg:postcode":"63130",
    "sg:province":"MO",
    "wof:name":"Community Response",
    "wof:placetype":"venue"
},
  "geometry": {"coordinates":[-90.31191099999999,38.670259],"type":"Point"}
}