{
  "type": "Feature",
  "properties": {
    "iso:country":"US",
    "sg:address":"707 Cedar Dr",
    "sg:city":"Warrensburg",
    "sg:classifiers":[
        {
            "category":"Professional",
            "subcategory":"Art Services",
            "type":"Services"
        }
    ],
    "sg:phone":"+1 660 238 7769",
    "sg:postcode":"64093",
    "sg:province":"MO",
    "sg:tags":[
        "designer",
        "display",
        "producer"
    ],
    "wof:name":"Fairyturtle Designs",
    "wof:placetype":"venue"
},
  "geometry": {"coordinates":[-93.726741,38.748047],"type":"Point"}
}