{
  "type": "Feature",
  "properties": {
    "iso:country":"US",
    "sg:address":"9870 Big Bend Blvd",
    "sg:city":"Saint Louis",
    "sg:classifiers":[
        {
            "category":"Professional",
            "subcategory":"Computer Services",
            "type":"Services"
        }
    ],
    "sg:phone":"+1 314 822 0860",
    "sg:postcode":"63122",
    "sg:province":"MO",
    "sg:tags":[
        "c",
        "audio",
        "rom",
        "disc",
        "duplication",
        "d"
    ],
    "wof:name":"Arca CD Inc",
    "wof:placetype":"venue"
},
  "geometry": {"coordinates":[-90.38761,38.570057],"type":"Point"}
}