{
  "type": "Feature",
  "properties": {
    "iso:country":"US",
    "sg:address":"814 S Kickapoo Ave",
    "sg:city":"Springfield",
    "sg:classifiers":[
        {
            "category":"Recreation",
            "type":"Entertainment"
        }
    ],
    "sg:phone":"+1 417 882 2799",
    "sg:postcode":"65804",
    "sg:province":"MO",
    "sg:tags":[
        "camps-recreational"
    ],
    "wof:name":"Mickey Owen Baseball School",
    "wof:placetype":"venue"
},
  "geometry": {"coordinates":[-93.273776,37.199657],"type":"Point"}
}