{
  "type": "Feature",
  "properties": {
    "iso:country":"US",
    "sg:address":"3027 S Belt Hwy",
    "sg:city":"St Joseph",
    "sg:classifiers":[
        {
            "category":"Wholesale",
            "subcategory":"Farm Supplies",
            "type":"Manufacturing & Wholesale Goods"
        },
        {
            "category":"Shopping",
            "type":"Retail Goods"
        }
    ],
    "sg:phone":"+1 816 279 2741",
    "sg:postcode":"64503",
    "sg:province":"MO",
    "sg:tags":[
        "store"
    ],
    "wof:name":"Tractor Supply Co 345",
    "wof:placetype":"venue"
},
  "geometry": {"coordinates":[-94.801103,39.740139],"type":"Point"}
}