{
  "type": "Feature",
  "properties": {
    "iso:country":"US",
    "sg:address":"3105 Goodes Mill Rd",
    "sg:city":"Villa Ridge",
    "sg:classifiers":[
        {
            "category":"Building & Trades",
            "subcategory":"Equipment Rental",
            "type":"Services"
        },
        {
            "category":"Recreation",
            "type":"Entertainment"
        }
    ],
    "sg:phone":"+1 636 583 3142",
    "sg:postcode":"63089",
    "sg:province":"MO",
    "sg:tags":[
        "party",
        "supply"
    ],
    "wof:name":"Air Adventures LLC",
    "wof:placetype":"venue"
},
  "geometry": {"coordinates":[-90.96844900000001,38.470649],"type":"Point"}
}