{
  "type": "Feature",
  "properties": {
    "iso:country":"US",
    "sg:address":"31484 Warsaw Ave",
    "sg:city":"Warsaw",
    "sg:classifiers":[
        {
            "category":"Retail",
            "subcategory":"Auto Rental",
            "type":"Services"
        }
    ],
    "sg:phone":"+1 660 723 5466",
    "sg:postcode":"65355",
    "sg:province":"MO",
    "sg:tags":[
        "limousine"
    ],
    "wof:name":"Only Way To Go",
    "wof:placetype":"venue"
},
  "geometry": {"coordinates":[-93.356246,38.233771],"type":"Point"}
}