{
  "type": "Feature",
  "properties": {
    "iso:country":"US",
    "sg:address":"22 Willow Oak Ln",
    "sg:city":"Saint Louis",
    "sg:classifiers":[
        {
            "category":"Professional",
            "type":"Services"
        }
    ],
    "sg:phone":"+1 314 984 8600",
    "sg:postcode":"63122",
    "sg:province":"MO",
    "wof:name":"G&P Foundation",
    "wof:placetype":"venue"
},
  "geometry": {"coordinates":[-90.37813800000001,38.587936],"type":"Point"}
}