{
  "type": "Feature",
  "properties": {
    "iso:country":"US",
    "sg:address":"44 Sycamore Green Acres",
    "sg:city":"Dittmer",
    "sg:classifiers":[
        {
            "category":"Real Estate",
            "subcategory":"Real Estate Operator",
            "type":"Services"
        }
    ],
    "sg:phone":"+1 636 285 2768",
    "sg:postcode":"63023",
    "sg:province":"MO",
    "sg:tags":[
        "mobile",
        "home",
        "site"
    ],
    "wof:name":"Sycamore Green Acres",
    "wof:placetype":"venue"
},
  "geometry": {"coordinates":[-90.67019999999999,38.33374],"type":"Point"}
}