{
  "type": "Feature",
  "properties": {
    "iso:country":"US",
    "sg:address":"4581 N Square Dr",
    "sg:city":"High Ridge",
    "sg:classifiers":[
        {
            "category":"Professional",
            "subcategory":"Business Services",
            "type":"Services"
        }
    ],
    "sg:phone":"+1 636 376 3333",
    "sg:postcode":"63049",
    "sg:province":"MO",
    "wof:name":"Flexible Cutting Systems",
    "wof:placetype":"venue"
},
  "geometry": {"coordinates":[-90.49882100000001,38.490125],"type":"Point"}
}