{
  "type": "Feature",
  "properties": {
    "iso:country":"US",
    "sg:address":"1200 Clark Ave",
    "sg:city":"Saint Louis",
    "sg:classifiers":[
        {
            "category":"Professional",
            "subcategory":"Secretarial Services",
            "type":"Services"
        }
    ],
    "sg:phone":"+1 314 241 9435",
    "sg:postcode":"63103",
    "sg:province":"MO",
    "sg:tags":[
        "reporting"
    ],
    "wof:name":"Reporters Room",
    "wof:placetype":"venue"
},
  "geometry": {"coordinates":[-90.20089299999999,38.625686],"type":"Point"}
}