{
  "type": "Feature",
  "properties": {
    "iso:country":"US",
    "sg:address":"736 E McKinney St",
    "sg:city":"Neosho",
    "sg:classifiers":[
        {
            "category":"Retail",
            "subcategory":"Self-service Laundry",
            "type":"Services"
        }
    ],
    "sg:phone":"+1 417 451 0355",
    "sg:postcode":"64850",
    "sg:province":"MO",
    "sg:tags":[
        "coin"
    ],
    "wof:name":"Hickory Creek Laundromat",
    "wof:placetype":"venue"
},
  "geometry": {"coordinates":[-94.361009,36.865359],"type":"Point"}
}