{
  "type": "Feature",
  "properties": {
    "iso:country":"US",
    "sg:address":"24007 S State Route C",
    "sg:city":"Peculiar",
    "sg:classifiers":[
        {
            "category":"Real Estate",
            "subcategory":"Real Estate Services",
            "type":"Services"
        }
    ],
    "sg:phone":"+1 816 779 7439",
    "sg:postcode":"64078",
    "sg:province":"MO",
    "sg:tags":[
        "management"
    ],
    "wof:name":"Homes Assoc Management In",
    "wof:placetype":"venue"
},
  "geometry": {"coordinates":[-94.46178,38.687654],"type":"Point"}
}