{
  "type": "Feature",
  "properties": {
    "iso:country":"US",
    "sg:address":"2190 Mason Rd",
    "sg:city":"Saint Louis",
    "sg:classifiers":[
        {
            "category":"Professional",
            "subcategory":"Accounting & Tax Preparation",
            "type":"Services"
        }
    ],
    "sg:phone":"+1 314 909 1882",
    "sg:postcode":"63131",
    "sg:province":"MO",
    "wof:name":"Hoops & Associates PC",
    "wof:placetype":"venue"
},
  "geometry": {"coordinates":[-90.479462,38.596978],"type":"Point"}
}