{
  "type": "Feature",
  "properties": {
    "iso:country":"US",
    "sg:address":"3307 NW Norton Rd",
    "sg:city":"Plattsburg",
    "sg:classifiers":[
        {
            "category":"Farming",
            "subcategory":"Livestock Farm",
            "type":"Manufacturing & Wholesale Goods"
        }
    ],
    "sg:phone":"+1 816 539 2263",
    "sg:postcode":"64477",
    "sg:province":"MO",
    "wof:name":"Rea Norton",
    "wof:placetype":"venue"
},
  "geometry": {"coordinates":[-94.421982,39.614743],"type":"Point"}
}