{
  "type": "Feature",
  "properties": {
    "iso:country":"US",
    "sg:address":"7115 N Stewart Rd",
    "sg:city":"Liberty",
    "sg:classifiers":[
        {
            "category":"Professional",
            "subcategory":"Management & Consulting",
            "type":"Services"
        }
    ],
    "sg:phone":"+1 816 407 1213",
    "sg:postcode":"64068",
    "sg:province":"MO",
    "sg:tags":[
        "business"
    ],
    "wof:name":"Creative Concepts Co",
    "wof:placetype":"venue"
},
  "geometry": {"coordinates":[-94.46931499999999,39.224294],"type":"Point"}
}