{
  "type": "Feature",
  "properties": {
    "iso:country":"US",
    "sg:address":"1708 Olive St",
    "sg:city":"Saint Louis",
    "sg:classifiers":[
        {
            "category":"Professional",
            "subcategory":"Lawyer & Legal Services",
            "type":"Services"
        }
    ],
    "sg:phone":"+1 314 678 3824",
    "sg:postcode":"63103",
    "sg:province":"MO",
    "wof:name":"Law Offices of Derald Gab",
    "wof:placetype":"venue"
},
  "geometry": {"coordinates":[-90.204503,38.630988],"type":"Point"}
}