{
  "type": "Feature",
  "properties": {
    "iso:country":"US",
    "sg:address":"927 Quince Dr",
    "sg:city":"St Charles",
    "sg:classifiers":[
        {
            "category":"Building & Trades",
            "subcategory":"Cleaning & Sanitation",
            "type":"Services"
        }
    ],
    "sg:phone":"+1 636 916 1393",
    "sg:postcode":"63301",
    "sg:province":"MO",
    "sg:tags":[
        "window"
    ],
    "wof:name":"Before & After Cleaning Svc",
    "wof:placetype":"venue"
},
  "geometry": {"coordinates":[-90.48784999999999,38.818889],"type":"Point"}
}