{
  "type": "Feature",
  "properties": {
    "iso:country":"US",
    "sg:address":"124 S Main St",
    "sg:city":"Eminence",
    "sg:classifiers":[
        {
            "category":"Real Estate",
            "subcategory":"Real Estate Services",
            "type":"Services"
        },
        {
            "category":"Real Estate",
            "subcategory":"Real Estate Agent",
            "type":"Services"
        }
    ],
    "sg:phone":"+1 573 226 3702",
    "sg:postcode":"65466",
    "sg:province":"MO",
    "sg:tags":[
        "buyer",
        "broker"
    ],
    "wof:name":"Howard E Dixon",
    "wof:placetype":"venue"
},
  "geometry": {"coordinates":[-91.357936,37.145095],"type":"Point"}
}