{
  "type": "Feature",
  "properties": {
    "iso:country":"US",
    "sg:address":"1516 SW Hook Rd",
    "sg:city":"Lees Summit",
    "sg:classifiers":[
        {
            "category":"Building & Trades",
            "subcategory":"Construction",
            "type":"Services"
        }
    ],
    "sg:phone":"+1 816 525 1219",
    "sg:postcode":"64082",
    "sg:province":"MO",
    "sg:tags":[
        "residential"
    ],
    "wof:name":"Rainey Construction Inc",
    "wof:placetype":"venue"
},
  "geometry": {"coordinates":[-94.407985,38.86826],"type":"Point"}
}