{
  "type": "Feature",
  "properties": {
    "iso:country":"US",
    "sg:address":"7309 Natural Bridge Rd",
    "sg:city":"Saint Louis",
    "sg:classifiers":[
        {
            "category":"Education",
            "subcategory":"School",
            "type":"Public Place"
        }
    ],
    "sg:phone":"+1 314 385 6754",
    "sg:postcode":"63121",
    "sg:province":"MO",
    "wof:name":"Missouri In Protocol School",
    "wof:placetype":"venue"
},
  "geometry": {"coordinates":[-90.297308,38.704324],"type":"Point"}
}