{
  "type": "Feature",
  "properties": {
    "iso:country":"US",
    "sg:address":"5923 Summit Dr",
    "sg:city":"Imperial",
    "sg:classifiers":[
        {
            "category":"Shopping",
            "subcategory":"Musical Instruments",
            "type":"Retail Goods"
        }
    ],
    "sg:phone":"+1 636 464 1535",
    "sg:postcode":"63052",
    "sg:province":"MO",
    "wof:name":"Guitars & More Music",
    "wof:placetype":"venue"
},
  "geometry": {"coordinates":[-90.36609799999999,38.370742],"type":"Point"}
}