{
  "type": "Feature",
  "properties": {
    "iso:country":"US",
    "sg:address":"3203 S Grand Blvd",
    "sg:city":"Saint Louis",
    "sg:classifiers":[
        {
            "category":"Professional",
            "subcategory":"Detective & Security Services",
            "type":"Services"
        }
    ],
    "sg:phone":"+1 314 768 9741",
    "sg:postcode":"63118",
    "sg:province":"MO",
    "sg:tags":[
        "investigative"
    ],
    "wof:name":"Roberson & Henderson Svcs Inc",
    "wof:placetype":"venue"
},
  "geometry": {"coordinates":[-90.242919,38.598758],"type":"Point"}
}