{
  "type": "Feature",
  "properties": {
    "iso:country":"US",
    "sg:address":"5635 Gravois Ave",
    "sg:city":"Saint Louis",
    "sg:classifiers":[
        {
            "category":"Building & Trades",
            "subcategory":"Construction",
            "type":"Services"
        }
    ],
    "sg:phone":"+1 314 353 2100",
    "sg:postcode":"63116",
    "sg:province":"MO",
    "sg:tags":[
        "contractor"
    ],
    "wof:name":"Mastis",
    "wof:placetype":"venue"
},
  "geometry": {"coordinates":[-90.272301,38.577702],"type":"Point"}
}