{
  "type": "Feature",
  "properties": {
    "iso:country":"US",
    "sg:address":"121 N Washington St",
    "sg:city":"Neosho",
    "sg:classifiers":[
        {
            "category":"Museum",
            "type":"Entertainment"
        }
    ],
    "sg:phone":"+1 417 451 4940",
    "sg:postcode":"64850",
    "sg:province":"MO",
    "wof:name":"Newton Co Historical Museum",
    "wof:placetype":"venue"
},
  "geometry": {"coordinates":[-94.367193,36.870463],"type":"Point"}
}