{
  "type": "Feature",
  "properties": {
    "iso:country":"US",
    "sg:address":"4350 Hartford St",
    "sg:city":"St Louis",
    "sg:classifiers":[
        {
            "category":"Manufacturing",
            "subcategory":"Furniture",
            "type":"Manufacturing & Wholesale Goods"
        }
    ],
    "sg:phone":"+1 314 776 7759",
    "sg:postcode":"63116",
    "sg:province":"MO",
    "sg:tags":[
        "equipment",
        "supply"
    ],
    "sg:website":"www.moldedproco.com",
    "wof:name":"Molded Products Co",
    "wof:placetype":"venue"
},
  "geometry": {"coordinates":[-90.262856,38.603649],"type":"Point"}
}