{
  "type": "Feature",
  "properties": {
    "iso:country":"US",
    "sg:address":"524 Vine St",
    "sg:city":"Poplar Bluff",
    "sg:classifiers":[
        {
            "category":"Professional",
            "subcategory":"Employment Agencies",
            "type":"Services"
        }
    ],
    "sg:phone":"+1 573 686 3200",
    "sg:postcode":"63901",
    "sg:province":"MO",
    "sg:tags":[
        "opportunity"
    ],
    "wof:name":"Genesis Employment",
    "wof:placetype":"venue"
},
  "geometry": {"coordinates":[-90.396107,36.75668],"type":"Point"}
}