{
  "type": "Feature",
  "properties": {
    "iso:country":"US",
    "sg:address":"71 Angelica St",
    "sg:city":"Saint Louis",
    "sg:classifiers":[
        {
            "category":"Utilities",
            "subcategory":"Refuse",
            "type":"Services"
        }
    ],
    "sg:phone":"+1 314 436 7690",
    "sg:postcode":"63147",
    "sg:province":"MO",
    "wof:name":"BFI",
    "wof:placetype":"venue"
},
  "geometry": {"coordinates":[-90.19596300000001,38.668871],"type":"Point"}
}