{
  "type": "Feature",
  "properties": {
    "iso:country":"US",
    "sg:address":"3002 E Division St",
    "sg:city":"Springfield",
    "sg:classifiers":[
        {
            "category":"Professional",
            "subcategory":"Detective & Security Services",
            "type":"Services"
        }
    ],
    "sg:phone":"+1 417 865 8876",
    "sg:postcode":"65802",
    "sg:province":"MO",
    "sg:tags":[
        "system"
    ],
    "wof:name":"ADT Security Services Inc",
    "wof:placetype":"venue"
},
  "geometry": {"coordinates":[-93.233131,37.224385],"type":"Point"}
}