{
  "type": "Feature",
  "properties": {
    "iso:country":"US",
    "sg:address":"1335 Pegasus Trl",
    "sg:city":"St Peters",
    "sg:classifiers":[
        {
            "category":"Professional",
            "subcategory":"Management & Consulting",
            "type":"Services"
        }
    ],
    "sg:phone":"+1 636 397 5534",
    "sg:postcode":"63376",
    "sg:province":"MO",
    "sg:tags":[
        "party",
        "planning"
    ],
    "wof:name":"Tea Pleasures & Pirate Trsrs",
    "wof:placetype":"venue"
},
  "geometry": {"coordinates":[-90.62024,38.76922],"type":"Point"}
}