{
  "type": "Feature",
  "properties": {
    "iso:country":"US",
    "sg:address":"3854 South Ave",
    "sg:city":"Springfield",
    "sg:classifiers":[
        {
            "category":"Real Estate",
            "subcategory":"Real Estate Services",
            "type":"Services"
        },
        {
            "category":"Real Estate",
            "subcategory":"Real Estate Agent",
            "type":"Services"
        }
    ],
    "sg:phone":"+1 417 889 2138",
    "sg:postcode":"65807",
    "sg:province":"MO",
    "sg:tags":[
        "buyer",
        "management",
        "broker"
    ],
    "sg:website":"http://www.hiltonrealtors.com",
    "wof:name":"Hilton Realty & Investment",
    "wof:placetype":"venue"
},
  "geometry": {"coordinates":[-93.29293800000001,37.143838],"type":"Point"}
}