{
  "type": "Feature",
  "properties": {
    "iso:country":"US",
    "sg:address":"205 Sandpiper St",
    "sg:city":"Raymore",
    "sg:classifiers":[
        {
            "category":"Shopping",
            "subcategory":"Gifts & Souvenirs",
            "type":"Retail Goods"
        }
    ],
    "sg:phone":"+1 816 331 9057",
    "sg:postcode":"64083",
    "sg:province":"MO",
    "wof:name":"Deer Antler Gifts By Steve Hat",
    "wof:placetype":"venue"
},
  "geometry": {"coordinates":[-94.450413,38.795902],"type":"Point"}
}