{
  "type": "Feature",
  "properties": {
    "iso:country":"US",
    "sg:address":"1335 N Stewart Ave",
    "sg:city":"Springfield",
    "sg:classifiers":[
        {
            "category":"Home & Garden",
            "subcategory":"Building Materials",
            "type":"Retail Goods"
        },
        {
            "category":"Building & Trades",
            "subcategory":"Construction",
            "type":"Services"
        }
    ],
    "sg:phone":"+1 417 865 7005",
    "sg:postcode":"65802",
    "sg:province":"MO",
    "sg:tags":[
        "sell",
        "installs",
        "repair",
        "door",
        "garage"
    ],
    "wof:name":"Midwest Door Co",
    "wof:placetype":"venue"
},
  "geometry": {"coordinates":[-93.25987000000001,37.223024],"type":"Point"}
}