{
  "type": "Feature",
  "properties": {
    "iso:country":"US",
    "sg:address":"12125 Blue Ridge Exd",
    "sg:city":"Grandview",
    "sg:classifiers":[
        {
            "category":"Wholesale",
            "subcategory":"Machinery & Supplies",
            "type":"Manufacturing & Wholesale Goods"
        }
    ],
    "sg:phone":"+1 816 761 9898",
    "sg:postcode":"64030",
    "sg:province":"MO",
    "sg:tags":[
        "car"
    ],
    "wof:name":"Carver Svc Etc",
    "wof:placetype":"venue"
},
  "geometry": {"coordinates":[-94.52691,38.906153],"type":"Point"}
}