{
  "type": "Feature",
  "properties": {
    "iso:country":"US",
    "sg:address":"115 W Newton St",
    "sg:city":"Versailles",
    "sg:classifiers":[
        {
            "category":"Professional",
            "subcategory":"Computer Services",
            "type":"Services"
        }
    ],
    "sg:phone":"+1 573 378 2722",
    "sg:postcode":"65084",
    "sg:province":"MO",
    "sg:tags":[
        "internet"
    ],
    "wof:name":"Versailles Computers",
    "wof:placetype":"venue"
},
  "geometry": {"coordinates":[-92.84298800000001,38.431699],"type":"Point"}
}