{
  "type": "Feature",
  "properties": {
    "iso:country":"US",
    "sg:address":"3707 Main St",
    "sg:city":"Kansas City",
    "sg:classifiers":[
        {
            "category":"Bars & Pubs",
            "type":"Food & Drink"
        }
    ],
    "sg:phone":"+1 816 931 1430",
    "sg:postcode":"64111",
    "sg:province":"MO",
    "sg:tags":[
        "lounge",
        "drinking",
        "cocktail"
    ],
    "wof:name":"Side Kicks Saloon",
    "wof:placetype":"venue"
},
  "geometry": {"coordinates":[-94.585919,39.058489],"type":"Point"}
}