{
  "type": "Feature",
  "properties": {
    "iso:country":"US",
    "sg:address":"6327 Lemay Ferry Rd",
    "sg:city":"St Louis",
    "sg:classifiers":[
        {
            "category":"Organizations",
            "subcategory":"Community Association",
            "type":"Services"
        }
    ],
    "sg:phone":"+1 314 416 8877",
    "sg:postcode":"63129",
    "sg:province":"MO",
    "sg:tags":[
        "military"
    ],
    "wof:name":"Veterans Of Foreign Wars",
    "wof:placetype":"venue"
},
  "geometry": {"coordinates":[-90.35931100000001,38.461249],"type":"Point"}
}