{
  "type": "Feature",
  "properties": {
    "iso:country":"US",
    "sg:address":"1101 Lemay Ferry Rd",
    "sg:city":"St Louis",
    "sg:classifiers":[
        {
            "category":"Food & Beverages",
            "subcategory":"Bakery",
            "type":"Retail Goods"
        }
    ],
    "sg:phone":"+1 314 631 3333",
    "sg:postcode":"63125",
    "sg:province":"MO",
    "sg:tags":[
        "doughnut"
    ],
    "wof:name":"Donut Stop",
    "wof:placetype":"venue"
},
  "geometry": {"coordinates":[-90.287121,38.533457],"type":"Point"}
}