{
  "type": "Feature",
  "properties": {
    "iso:country":"US",
    "sg:address":"2019 S Main St",
    "sg:city":"Higginsville",
    "sg:classifiers":[
        {
            "category":"Shopping",
            "subcategory":"Pharmacy",
            "type":"Retail Goods"
        }
    ],
    "sg:phone":"+1 660 584 2110",
    "sg:postcode":"64037",
    "sg:province":"MO",
    "wof:name":"Services In Preferred Pharmacy",
    "wof:placetype":"venue"
},
  "geometry": {"coordinates":[-93.717005,39.074197],"type":"Point"}
}