{
  "type": "Feature",
  "properties": {
    "iso:country":"US",
    "sg:address":"440 Tumulty Dr",
    "sg:city":"Ballwin",
    "sg:classifiers":[
        {
            "category":"Professional",
            "type":"Services"
        }
    ],
    "sg:phone":"+1 636 256 6739",
    "sg:postcode":"63021",
    "sg:province":"MO",
    "wof:name":"Eye On Lake",
    "wof:placetype":"venue"
},
  "geometry": {"coordinates":[-90.52506,38.575154],"type":"Point"}
}