{
  "type": "Feature",
  "properties": {
    "iso:country":"US",
    "sg:address":"1051 Maple Dr",
    "sg:city":"Sainte Genevieve",
    "sg:classifiers":[
        {
            "category":"Social Services",
            "subcategory":"Child Care",
            "type":"Services"
        }
    ],
    "sg:phone":"+1 573 883 3045",
    "sg:postcode":"63670",
    "sg:province":"MO",
    "sg:tags":[
        "day"
    ],
    "wof:name":"Almost Home",
    "wof:placetype":"venue"
},
  "geometry": {"coordinates":[-90.056618,37.98065],"type":"Point"}
}