{
  "type": "Feature",
  "properties": {
    "iso:country":"US",
    "sg:address":"452 Jungs Station Rd",
    "sg:city":"St Charles",
    "sg:classifiers":[
        {
            "category":"Real Estate",
            "subcategory":"Architect",
            "type":"Services"
        }
    ],
    "sg:phone":"+1 636 441 7878",
    "sg:postcode":"63303",
    "sg:province":"MO",
    "wof:name":"Thompson Design Group LLC",
    "wof:placetype":"venue"
},
  "geometry": {"coordinates":[-90.554632,38.732501],"type":"Point"}
}