{
  "type": "Feature",
  "properties": {
    "iso:country":"US",
    "sg:address":"15009 Manchester Rd",
    "sg:city":"Ballwin",
    "sg:classifiers":[
        {
            "category":"Building & Trades",
            "subcategory":"Construction",
            "type":"Services"
        }
    ],
    "sg:phone":"+1 636 591 0099",
    "sg:postcode":"63011",
    "sg:province":"MO",
    "sg:tags":[
        "altering",
        "remodeling",
        "contractor"
    ],
    "wof:name":"Sigala Winder Contracting",
    "wof:placetype":"venue"
},
  "geometry": {"coordinates":[-90.546627,38.592955],"type":"Point"}
}