{
  "type": "Feature",
  "properties": {
    "iso:country":"US",
    "sg:address":"16479 State Hwy 19",
    "sg:city":"Steelville",
    "sg:classifiers":[
        {
            "category":"Real Estate",
            "subcategory":"Architect",
            "type":"Services"
        }
    ],
    "sg:phone":"+1 573 775 3729",
    "sg:postcode":"65565",
    "sg:province":"MO",
    "sg:tags":[
        "home",
        "planning",
        "design"
    ],
    "wof:name":"Brock Home Design & Constr LLC",
    "wof:placetype":"venue"
},
  "geometry": {"coordinates":[-91.343084,37.950677],"type":"Point"}
}