{
  "type": "Feature",
  "properties": {
    "iso:country":"US",
    "sg:address":"4533 Gravois Ave",
    "sg:city":"Saint Louis",
    "sg:classifiers":[
        {
            "category":"Personal",
            "subcategory":"Barber",
            "type":"Services"
        }
    ],
    "sg:phone":"+1 314 352 1519",
    "sg:postcode":"63116",
    "sg:province":"MO",
    "wof:name":"Slam Town Barber & Beauty Salon",
    "wof:placetype":"venue"
},
  "geometry": {"coordinates":[-90.262907,38.584786],"type":"Point"}
}