{
  "type": "Feature",
  "properties": {
    "iso:country":"US",
    "sg:address":"4120 Glendale Rd",
    "sg:city":"House Springs",
    "sg:classifiers":[
        {
            "category":"Professional",
            "type":"Services"
        }
    ],
    "sg:phone":"+1 636 671 0815",
    "sg:postcode":"63051",
    "sg:province":"MO",
    "wof:name":"Teresa Wallach",
    "wof:placetype":"venue"
},
  "geometry": {"coordinates":[-90.557873,38.425331],"type":"Point"}
}