{
  "type": "Feature",
  "properties": {
    "iso:country":"US",
    "sg:address":"6612 County Road 523",
    "sg:city":"Williamsville",
    "sg:classifiers":[
        {
            "category":"Manufacturing",
            "subcategory":"Buildings",
            "type":"Manufacturing & Wholesale Goods"
        },
        {
            "category":"Building & Trades",
            "subcategory":"Construction",
            "type":"Services"
        }
    ],
    "sg:phone":"+1 573 785 2515",
    "sg:postcode":"63967",
    "sg:province":"MO",
    "sg:tags":[
        "home",
        "builder",
        "contractor"
    ],
    "wof:name":"Russell Construction Co",
    "wof:placetype":"venue"
},
  "geometry": {"coordinates":[-90.468453,36.884842],"type":"Point"}
}