{
  "type": "Feature",
  "properties": {
    "iso:country":"US",
    "sg:address":"105 N Clay St",
    "sg:city":"Marshfield",
    "sg:classifiers":[
        {
            "category":"Personal",
            "subcategory":"Beauty Salon",
            "type":"Services"
        },
        {
            "category":"Personal",
            "subcategory":"Tanning Parlor",
            "type":"Services"
        }
    ],
    "sg:phone":"+1 417 859 4593",
    "sg:postcode":"65706",
    "sg:province":"MO",
    "wof:name":"Nina's Hair & Tropical Tans",
    "wof:placetype":"venue"
},
  "geometry": {"coordinates":[-92.907478,37.338631],"type":"Point"}
}