{
  "type": "Feature",
  "properties": {
    "iso:country":"US",
    "sg:address":"12260 Bellefontaine Rd",
    "sg:city":"St Louis",
    "sg:classifiers":[
        {
            "category":"Restaurant",
            "type":"Food & Drink"
        }
    ],
    "sg:phone":"+1 314 741 3637",
    "sg:postcode":"63138",
    "sg:province":"MO",
    "sg:tags":[
        "bar",
        "italian"
    ],
    "wof:name":"Ponticello's Restaurant",
    "wof:placetype":"venue"
},
  "geometry": {"coordinates":[-90.213213,38.795142],"type":"Point"}
}