{
  "type": "Feature",
  "properties": {
    "iso:country":"US",
    "sg:address":"215 N 1st St",
    "sg:city":"Owensville",
    "sg:classifiers":[
        {
            "category":"Personal",
            "subcategory":"Beauty Salon",
            "type":"Services"
        }
    ],
    "sg:phone":"+1 573 437 7722",
    "sg:postcode":"65066",
    "sg:province":"MO",
    "sg:tags":[
        "hair",
        "stylist"
    ],
    "wof:name":"Hair Force",
    "wof:placetype":"venue"
},
  "geometry": {"coordinates":[-91.50048099999999,38.348201],"type":"Point"}
}