{
  "type": "Feature",
  "properties": {
    "iso:country":"US",
    "sg:address":"12661 Countrybrook Dr",
    "sg:city":"Saint Louis",
    "sg:classifiers":[
        {
            "category":"Professional",
            "subcategory":"Detective & Security Services",
            "type":"Services"
        }
    ],
    "sg:phone":"+1 314 355 2110",
    "sg:postcode":"63138",
    "sg:province":"MO",
    "sg:tags":[
        "system"
    ],
    "wof:name":"Unlimited Security",
    "wof:placetype":"venue"
},
  "geometry": {"coordinates":[-90.21396900000001,38.806635],"type":"Point"}
}