{
  "type": "Feature",
  "properties": {
    "iso:country":"US",
    "sg:address":"18218 Cameron Rd",
    "sg:city":"Kearney",
    "sg:classifiers":[
        {
            "category":"Farming",
            "subcategory":"Farm",
            "type":"Manufacturing & Wholesale Goods"
        }
    ],
    "sg:phone":"+1 816 320 3640",
    "sg:postcode":"64060",
    "sg:province":"MO",
    "wof:name":"Leroy G Ellison",
    "wof:placetype":"venue"
},
  "geometry": {"coordinates":[-94.296542,39.424886],"type":"Point"}
}