{
  "type": "Feature",
  "properties": {
    "iso:country":"US",
    "sg:address":"1990 W Timber Ridge Dr",
    "sg:city":"Sedalia",
    "sg:classifiers":[
        {
            "category":"Home & Garden",
            "subcategory":"Hardware",
            "type":"Retail Goods"
        },
        {
            "category":"Wholesale",
            "subcategory":"Home Furnishings",
            "type":"Manufacturing & Wholesale Goods"
        }
    ],
    "sg:phone":"+1 660 221 5446",
    "sg:postcode":"65301",
    "sg:province":"MO",
    "sg:tags":[
        "equipment",
        "fixtures-wholesale",
        "lighting",
        "system",
        "manufacturer"
    ],
    "wof:name":"Zemos Led International",
    "wof:placetype":"venue"
},
  "geometry": {"coordinates":[-93.30410999999999,38.702127],"type":"Point"}
}