{
  "type": "Feature",
  "properties": {
    "iso:country":"US",
    "sg:address":"215 E High St",
    "sg:city":"Potosi",
    "sg:classifiers":[
        {
            "category":"Shopping",
            "subcategory":"Florist",
            "type":"Retail Goods"
        }
    ],
    "sg:phone":"+1 573 438 6433",
    "sg:postcode":"63664",
    "sg:province":"MO",
    "wof:name":"Twigs & Ivy Boutique",
    "wof:placetype":"venue"
},
  "geometry": {"coordinates":[-90.78625700000001,37.935197],"type":"Point"}
}