{
  "type": "Feature",
  "properties": {
    "iso:country":"US",
    "sg:address":"5025 Cote Brilliante Ave",
    "sg:city":"Saint Louis",
    "sg:classifiers":[
        {
            "category":"Organizations",
            "subcategory":"Religious Organization",
            "type":"Services"
        }
    ],
    "sg:phone":"+1 314 361 2802",
    "sg:postcode":"63113",
    "sg:province":"MO",
    "wof:name":"Dismas House of St Louis the",
    "wof:placetype":"venue"
},
  "geometry": {"coordinates":[-90.260002,38.665501],"type":"Point"}
}