{
  "type": "Feature",
  "properties": {
    "iso:country":"US",
    "sg:address":"3832 Blue Ridge Cut Off",
    "sg:city":"Kansas City",
    "sg:classifiers":[
        {
            "category":"Restaurant",
            "type":"Food & Drink"
        }
    ],
    "sg:menulink":"http://www.allmenus.com/mo/blue/11611-dennys/menu/",
    "sg:phone":"+1 816 923 2790",
    "sg:postcode":"64133",
    "sg:province":"MO",
    "sg:tags":[
        "american",
        "diner"
    ],
    "wof:name":"Denny's",
    "wof:placetype":"venue"
},
  "geometry": {"coordinates":[-94.473612,39.053252],"type":"Point"}
}