{
  "type": "Feature",
  "properties": {
    "iso:country":"US",
    "sg:address":"1602 S Range Line Rd",
    "sg:city":"Joplin",
    "sg:classifiers":[
        {
            "category":"Real Estate",
            "subcategory":"Real Estate Services",
            "type":"Services"
        }
    ],
    "sg:phone":"+1 417 623 7877",
    "sg:postcode":"64804",
    "sg:province":"MO",
    "sg:tags":[
        "company",
        "title"
    ],
    "wof:name":"Mid-America Title Loan Inc",
    "wof:placetype":"venue"
},
  "geometry": {"coordinates":[-94.477853,37.071941],"type":"Point"}
}