{
  "type": "Feature",
  "properties": {
    "iso:country":"US",
    "sg:address":"1801 S Commercial St",
    "sg:city":"Harrisonville",
    "sg:classifiers":[
        {
            "category":"Professional",
            "type":"Services"
        }
    ],
    "sg:phone":"+1 816 380 6040",
    "sg:postcode":"64701",
    "sg:province":"MO",
    "wof:name":"Khushi Petroleum Inc",
    "wof:placetype":"venue"
},
  "geometry": {"coordinates":[-94.35198699999999,38.643105],"type":"Point"}
}