{
  "type": "Feature",
  "properties": {
    "addr:full":"213 King Ave Portageville MO 63873",
    "addr:housenumber":"213",
    "addr:postcode":"63873",
    "addr:street":"King Ave",
    "iso:country":"US",
    "sg:address":"213 King Ave",
    "sg:city":"Portageville",
    "sg:classifiers":[
        {
            "category":"Personal",
            "subcategory":"Beauty Salon",
            "type":"Services"
        }
    ],
    "sg:phone":"+1 573 379 5523",
    "sg:postcode":"63873",
    "sg:province":"MO",
    "wof:name":"First Impressions",
    "wof:placetype":"venue"
},
  "geometry": {"coordinates":[-89.69936199999999,36.425508],"type":"Point"}
}