{
  "type": "Feature",
  "properties": {
    "iso:country":"US",
    "sg:address":"1355 S Country Club Rd",
    "sg:city":"Carthage",
    "sg:classifiers":[
        {
            "category":"Manufacturing",
            "subcategory":"Tools & Machinery",
            "type":"Manufacturing & Wholesale Goods"
        }
    ],
    "sg:phone":"+1 417 358 5599",
    "sg:postcode":"64836",
    "sg:province":"MO",
    "sg:tags":[
        "repair",
        "laser"
    ],
    "wof:name":"H B Laser Services",
    "wof:placetype":"venue"
},
  "geometry": {"coordinates":[-94.346039,37.16352],"type":"Point"}
}