{
  "type": "Feature",
  "properties": {
    "iso:country":"US",
    "sg:address":"404 Caroline Ave",
    "sg:city":"St Louis",
    "sg:classifiers":[
        {
            "category":"Building & Trades",
            "subcategory":"Construction",
            "type":"Services"
        }
    ],
    "sg:phone":"+1 314 965 9900",
    "sg:postcode":"63122",
    "sg:province":"MO",
    "sg:tags":[
        "general",
        "contractor"
    ],
    "wof:name":"Kirkwood Construction Svc Inc",
    "wof:placetype":"venue"
},
  "geometry": {"coordinates":[-90.422431,38.574356],"type":"Point"}
}