{
  "type": "Feature",
  "properties": {
    "iso:country":"US",
    "sg:address":"12735 Carrollton Industrl Ct",
    "sg:city":"Bridgeton",
    "sg:classifiers":[
        {
            "category":"Wholesale",
            "subcategory":"Machinery & Supplies",
            "type":"Manufacturing & Wholesale Goods"
        }
    ],
    "sg:phone":"+1 314 770 9300",
    "sg:postcode":"63044",
    "sg:province":"MO",
    "sg:tags":[
        "equipment",
        "printing",
        "trade"
    ],
    "wof:name":"Independent Printing Services",
    "wof:placetype":"venue"
},
  "geometry": {"coordinates":[-90.430745,38.762786],"type":"Point"}
}