{
  "type": "Feature",
  "properties": {
    "iso:country":"US",
    "sg:address":"207 N Truman Blvd",
    "sg:city":"Crystal City",
    "sg:classifiers":[
        {
            "category":"Shopping",
            "subcategory":"Shoes",
            "type":"Retail Goods"
        }
    ],
    "sg:phone":"+1 636 937 0300",
    "sg:postcode":"63019",
    "sg:province":"MO",
    "wof:name":"Shoe Warehouse",
    "wof:placetype":"venue"
},
  "geometry": {"coordinates":[-90.384209,38.221328],"type":"Point"}
}