{
  "type": "Feature",
  "properties": {
    "iso:country":"US",
    "sg:address":"103 S 4th St",
    "sg:city":"Shelbina",
    "sg:classifiers":[
        {
            "category":"Organizations",
            "subcategory":"Religious Organization",
            "type":"Services"
        }
    ],
    "sg:phone":"+1 573 588 4540",
    "sg:postcode":"63468",
    "sg:province":"MO",
    "wof:name":"Saint Marys Church",
    "wof:placetype":"venue"
},
  "geometry": {"coordinates":[-92.03566499999999,39.69185],"type":"Point"}
}