{
  "type": "Feature",
  "properties": {
    "iso:country":"US",
    "sg:address":"10036 NW Executive Hills Blvd",
    "sg:city":"Kansas City",
    "sg:classifiers":[
        {
            "category":"Banks & Credit Unions",
            "subcategory":"Investment Brokerage",
            "type":"Services"
        }
    ],
    "sg:phone":"+1 816 880 0100",
    "sg:postcode":"64153",
    "sg:province":"MO",
    "sg:tags":[
        "consultant",
        "planning",
        "financial"
    ],
    "wof:name":"New England Financial",
    "wof:placetype":"venue"
},
  "geometry": {"coordinates":[-94.668001,39.274944],"type":"Point"}
}