{
  "type": "Feature",
  "properties": {
    "iso:country":"US",
    "sg:address":"2012 Cleopatra Dr",
    "sg:city":"Fenton",
    "sg:classifiers":[
        {
            "category":"Building & Trades",
            "subcategory":"Construction",
            "type":"Services"
        }
    ],
    "sg:phone":"+1 636 225 4707",
    "sg:postcode":"63026",
    "sg:province":"MO",
    "sg:tags":[
        "nonresidential"
    ],
    "wof:name":"River City Construction",
    "wof:placetype":"venue"
},
  "geometry": {"coordinates":[-90.48992200000001,38.535326],"type":"Point"}
}