{
  "type": "Feature",
  "properties": {
    "iso:country":"US",
    "sg:address":"3917 Castleman Ave",
    "sg:city":"St Louis",
    "sg:classifiers":[
        {
            "category":"Building & Trades",
            "subcategory":"Construction",
            "type":"Services"
        }
    ],
    "sg:phone":"+1 314 772 5215",
    "sg:postcode":"63110",
    "sg:province":"MO",
    "sg:tags":[
        "general",
        "contractor"
    ],
    "wof:name":"Big Man Construction Co",
    "wof:placetype":"venue"
},
  "geometry": {"coordinates":[-90.247153,38.615034],"type":"Point"}
}