{
  "type": "Feature",
  "properties": {
    "addr:full":"102 Community Bank Plz Troy MO 63379",
    "addr:housenumber":"102",
    "addr:postcode":"63379",
    "addr:street":"Community Bank Plz",
    "iso:country":"US",
    "sg:address":"102 Community Bank Plz",
    "sg:city":"Troy",
    "sg:classifiers":[
        {
            "category":"Banks & Credit Unions",
            "subcategory":"Investment Brokerage",
            "type":"Services"
        }
    ],
    "sg:phone":"+1 636 528 4900",
    "sg:postcode":"63379",
    "sg:province":"MO",
    "sg:tags":[
        "consultant",
        "planning",
        "financial"
    ],
    "wof:name":"American Express Financial Adv",
    "wof:placetype":"venue"
},
  "geometry": {"coordinates":[-90.98071899999999,38.989165],"type":"Point"}
}