{
  "type": "Feature",
  "properties": {
    "iso:country":"US",
    "sg:address":"1350 Willowbrook Dr",
    "sg:city":"Florissant",
    "sg:classifiers":[
        {
            "category":"Building & Trades",
            "subcategory":"Cleaning & Sanitation",
            "type":"Services"
        }
    ],
    "sg:phone":"+1 314 838 6904",
    "sg:postcode":"63033",
    "sg:province":"MO",
    "sg:tags":[
        "maintenance"
    ],
    "wof:name":"Ceiling Pro of St Louis",
    "wof:placetype":"venue"
},
  "geometry": {"coordinates":[-90.313203,38.798097],"type":"Point"}
}