{
  "type": "Feature",
  "properties": {
    "iso:country":"US",
    "sg:address":"530 S Hope St",
    "sg:city":"Jackson",
    "sg:classifiers":[
        {
            "category":"Restaurant",
            "type":"Food & Drink"
        }
    ],
    "sg:menulink":"http://www.allmenus.com/mo/byrd/201599-sonic/menu/",
    "sg:phone":"+1 573 243 6211",
    "sg:postcode":"63755",
    "sg:province":"MO",
    "sg:tags":[
        "burger",
        "american"
    ],
    "wof:name":"Sonic",
    "wof:placetype":"venue"
},
  "geometry": {"coordinates":[-89.667169,37.378613],"type":"Point"}
}