{
  "type": "Feature",
  "properties": {
    "iso:country":"US",
    "sg:address":"4479 Paris Gravel Rd",
    "sg:city":"Hannibal",
    "sg:classifiers":[
        {
            "category":"Building & Trades",
            "subcategory":"Construction",
            "type":"Services"
        }
    ],
    "sg:phone":"+1 573 406 1507",
    "sg:postcode":"63401",
    "sg:province":"MO",
    "sg:tags":[
        "general"
    ],
    "wof:name":"Mikes Constructions LLC",
    "wof:placetype":"venue"
},
  "geometry": {"coordinates":[-91.412083,39.6854],"type":"Point"}
}