{
  "type": "Feature",
  "properties": {
    "iso:country":"US",
    "sg:address":"34137 W 108th St",
    "sg:city":"Orrick",
    "sg:classifiers":[
        {
            "category":"Manufacturing",
            "subcategory":"Buildings",
            "type":"Manufacturing & Wholesale Goods"
        },
        {
            "category":"Building & Trades",
            "subcategory":"Construction",
            "type":"Services"
        }
    ],
    "sg:phone":"+1 816 770 2377",
    "sg:postcode":"64077",
    "sg:province":"MO",
    "sg:tags":[
        "home",
        "builder",
        "contractor"
    ],
    "wof:name":"Senciboy Construction",
    "wof:placetype":"venue"
},
  "geometry": {"coordinates":[-94.127901,39.28621],"type":"Point"}
}