{
  "type": "Feature",
  "properties": {
    "iso:country":"US",
    "sg:address":"7338 Manchester Rd",
    "sg:city":"Saint Louis",
    "sg:classifiers":[
        {
            "category":"Food & Beverages",
            "subcategory":"Specialty",
            "type":"Retail Goods"
        }
    ],
    "sg:phone":"+1 314 781 7177",
    "sg:postcode":"63143",
    "sg:province":"MO",
    "sg:website":"www.penzeys.com",
    "wof:name":"Penzeys Spices",
    "wof:placetype":"venue"
},
  "geometry": {"coordinates":[-90.318298,38.613098],"type":"Point"}
}