{
  "type": "Feature",
  "properties": {
    "iso:country":"US",
    "sg:address":"8645 Red Oak Rd",
    "sg:city":"Gerald",
    "sg:classifiers":[
        {
            "category":"Building & Trades",
            "subcategory":"Construction",
            "type":"Services"
        }
    ],
    "sg:phone":"+1 573 764 5525",
    "sg:postcode":"63037",
    "sg:province":"MO",
    "sg:tags":[
        "house"
    ],
    "wof:name":"Dierker Home Improvement",
    "wof:placetype":"venue"
},
  "geometry": {"coordinates":[-91.319249,38.332136],"type":"Point"}
}