{
  "type": "Feature",
  "properties": {
    "iso:country":"US",
    "sg:address":"1500 3rd St",
    "sg:city":"Chillicothe",
    "sg:classifiers":[
        {
            "category":"Social Services",
            "type":"Services"
        }
    ],
    "sg:phone":"+1 660 646 6462",
    "sg:postcode":"64601",
    "sg:province":"MO",
    "sg:tags":[
        "organization",
        "welfare"
    ],
    "wof:name":"Prison Patch",
    "wof:placetype":"venue"
},
  "geometry": {"coordinates":[-93.562617,39.789421],"type":"Point"}
}