{
  "type": "Feature",
  "properties": {
    "iso:country":"US",
    "sg:address":"413 Lewis St",
    "sg:city":"Canton",
    "sg:classifiers":[
        {
            "category":"Home & Garden",
            "subcategory":"Building Materials",
            "type":"Retail Goods"
        }
    ],
    "sg:phone":"+1 573 288 3462",
    "sg:postcode":"63435",
    "sg:province":"MO",
    "sg:tags":[
        "paint",
        "contractor",
        "re"
    ],
    "wof:name":"Janney Builders Supply & Cnstr",
    "wof:placetype":"venue"
},
  "geometry": {"coordinates":[-91.51885900000001,40.13026],"type":"Point"}
}