{
  "type": "Feature",
  "properties": {
    "iso:country":"US",
    "sg:address":"4642 Shenandoah Ave",
    "sg:city":"St Louis",
    "sg:classifiers":[
        {
            "category":"Manufacturing",
            "subcategory":"Signs",
            "type":"Manufacturing & Wholesale Goods"
        }
    ],
    "sg:phone":"+1 314 822 3015",
    "sg:postcode":"63110",
    "sg:province":"MO",
    "wof:name":"Signs Now",
    "wof:placetype":"venue"
},
  "geometry": {"coordinates":[-90.266666,38.612397],"type":"Point"}
}