{
  "type": "Feature",
  "properties": {
    "iso:country":"US",
    "sg:address":"1835 San Pedro Ln",
    "sg:city":"Fenton",
    "sg:classifiers":[
        {
            "category":"Health Services",
            "subcategory":"Chiropractor",
            "type":"Services"
        }
    ],
    "sg:phone":"+1 636 225 6779",
    "sg:postcode":"63026",
    "sg:province":"MO",
    "sg:tags":[
        "chiropractic"
    ],
    "wof:name":"Einertson Chiropractic Center",
    "wof:placetype":"venue"
},
  "geometry": {"coordinates":[-90.484917,38.513649],"type":"Point"}
}