{
  "type": "Feature",
  "properties": {
    "iso:country":"US",
    "sg:address":"360 S Kingshighway",
    "sg:city":"Cape Girardeau",
    "sg:classifiers":[
        {
            "category":"Professional",
            "subcategory":"Business Services",
            "type":"Services"
        },
        {
            "category":"Manufacturing",
            "subcategory":"Printing",
            "type":"Manufacturing & Wholesale Goods"
        }
    ],
    "sg:phone":"+1 573 335 1909",
    "sg:postcode":"63703",
    "sg:province":"MO",
    "sg:tags":[
        "painter",
        "sign"
    ],
    "wof:name":"Sign Master Instant Signs",
    "wof:placetype":"venue"
},
  "geometry": {"coordinates":[-89.553479,37.299094],"type":"Point"}
}