{
  "type": "Feature",
  "properties": {
    "iso:country":"US",
    "sg:address":"6200 N Broadway",
    "sg:city":"St Louis",
    "sg:classifiers":[
        {
            "category":"Building & Trades",
            "subcategory":"Construction",
            "type":"Services"
        },
        {
            "category":"Manufacturing",
            "subcategory":"Tools & Machinery",
            "type":"Manufacturing & Wholesale Goods"
        }
    ],
    "sg:phone":"+1 314 383 5249",
    "sg:postcode":"63147",
    "sg:province":"MO",
    "sg:tags":[
        "conveying",
        "installation",
        "conveyor",
        "mfg",
        "equipment",
        "she"
    ],
    "wof:name":"Arch Conveying Corp",
    "wof:placetype":"venue"
},
  "geometry": {"coordinates":[-90.22053099999999,38.686319],"type":"Point"}
}