{
  "type": "Feature",
  "properties": {
    "iso:country":"US",
    "sg:address":"5614 Pinehurst Ln",
    "sg:city":"Columbia",
    "sg:classifiers":[
        {
            "category":"Real Estate",
            "subcategory":"Real Estate Services",
            "type":"Services"
        }
    ],
    "sg:phone":"+1 573 474 9810",
    "sg:postcode":"65202",
    "sg:province":"MO",
    "sg:tags":[
        "buyer",
        "broker"
    ],
    "wof:name":"Mounter Enterprises",
    "wof:placetype":"venue"
},
  "geometry": {"coordinates":[-92.251778,38.965592],"type":"Point"}
}