{
  "type": "Feature",
  "properties": {
    "iso:country":"US",
    "sg:address":"1067 Regency Pkwy",
    "sg:city":"St Charles",
    "sg:classifiers":[
        {
            "category":"Shopping",
            "subcategory":"Department Store",
            "type":"Retail Goods"
        }
    ],
    "sg:phone":"+1 636 916 3159",
    "sg:postcode":"63303",
    "sg:province":"MO",
    "sg:tags":[
        "shop"
    ],
    "wof:name":"Dollar Tree",
    "wof:placetype":"venue"
},
  "geometry": {"coordinates":[-90.528554,38.783529],"type":"Point"}
}