{
  "type": "Feature",
  "properties": {
    "iso:country":"US",
    "sg:address":"280 Williams Blvd",
    "sg:city":"Saint Louis",
    "sg:classifiers":[
        {
            "category":"Professional",
            "type":"Services"
        }
    ],
    "sg:phone":"+1 314 521 5914",
    "sg:postcode":"63135",
    "sg:province":"MO",
    "wof:name":"Laura A Mahoney",
    "wof:placetype":"venue"
},
  "geometry": {"coordinates":[-90.324305,38.764582],"type":"Point"}
}