{
  "type": "Feature",
  "properties": {
    "iso:country":"US",
    "sg:address":"4087 Highway 83",
    "sg:city":"Bolivar",
    "sg:classifiers":[
        {
            "category":"Food & Beverages",
            "subcategory":"Specialty",
            "type":"Retail Goods"
        }
    ],
    "sg:phone":"+1 417 777 8425",
    "sg:postcode":"65613",
    "sg:province":"MO",
    "sg:tags":[
        "product",
        "health",
        "diet"
    ],
    "wof:name":"Lewis Parsons",
    "wof:placetype":"venue"
},
  "geometry": {"coordinates":[-93.420556,37.641133],"type":"Point"}
}