{
  "type": "Feature",
  "properties": {
    "iso:country":"US",
    "sg:address":"1037 W South St",
    "sg:city":"Neosho",
    "sg:classifiers":[
        {
            "category":"Organizations",
            "subcategory":"Religious Organization",
            "type":"Services"
        }
    ],
    "sg:phone":"+1 417 451 2724",
    "sg:postcode":"64850",
    "sg:province":"MO",
    "sg:tags":[
        "testament",
        "churches-church",
        "christ-new"
    ],
    "wof:name":"Hillcrest Church Of Christ",
    "wof:placetype":"venue"
},
  "geometry": {"coordinates":[-94.385605,36.858185],"type":"Point"}
}