{
  "type": "Feature",
  "properties": {
    "iso:country":"US",
    "sg:address":"3010 Pershall Rd",
    "sg:city":"St Louis",
    "sg:classifiers":[
        {
            "category":"Personal",
            "subcategory":"Beauty Salon",
            "type":"Services"
        }
    ],
    "sg:phone":"+1 314 522 1900",
    "sg:postcode":"63136",
    "sg:province":"MO",
    "wof:name":"Hair Illusions Prosthesis Ctr",
    "wof:placetype":"venue"
},
  "geometry": {"coordinates":[-90.27886100000001,38.769818],"type":"Point"}
}