{
  "type": "Feature",
  "properties": {
    "iso:country":"US",
    "sg:address":"5600 Main St",
    "sg:city":"Kansas City",
    "sg:classifiers":[
        {
            "category":"Education",
            "subcategory":"School",
            "type":"Public Place"
        }
    ],
    "sg:phone":"+1 816 501 0011",
    "sg:postcode":"64113",
    "sg:province":"MO",
    "sg:tags":[
        "child",
        "day",
        "care"
    ],
    "sg:website":"www.stteresasacademy.org",
    "wof:name":"St Teresa's Academy",
    "wof:placetype":"venue"
},
  "geometry": {"coordinates":[-94.587816,39.027524],"type":"Point"}
}