{
  "type": "Feature",
  "properties": {
    "iso:country":"US",
    "sg:address":"700 E Cleveland Ave",
    "sg:city":"Monett",
    "sg:classifiers":[
        {
            "category":"Health Services",
            "subcategory":"Doctor",
            "type":"Services"
        }
    ],
    "sg:phone":"+1 417 354 1520",
    "sg:postcode":"65708",
    "sg:province":"MO",
    "sg:tags":[
        "physician",
        "surgeon",
        "orthopedics",
        "surgeons"
    ],
    "wof:name":"Monett Orthopedics",
    "wof:placetype":"venue"
},
  "geometry": {"coordinates":[-93.920738,36.928711],"type":"Point"}
}