{
  "type": "Feature",
  "properties": {
    "iso:country":"US",
    "sg:address":"3642 S Lindbergh Blvd",
    "sg:city":"Saint Louis",
    "sg:classifiers":[
        {
            "category":"Restaurant",
            "type":"Food & Drink"
        }
    ],
    "sg:menulink":"http://www.allmenus.com/mo/gravois/98628-longhorn-steakhouse/menu/",
    "sg:phone":"+1 314 821 7797",
    "sg:postcode":"63127",
    "sg:province":"MO",
    "sg:tags":[
        "american",
        "steakhouse"
    ],
    "wof:name":"LongHorn Steakhouse",
    "wof:placetype":"venue"
},
  "geometry": {"coordinates":[-90.406316,38.553796],"type":"Point"}
}