{
  "type": "Feature",
  "properties": {
    "iso:country":"US",
    "sg:address":"2120A N Bishop Ave",
    "sg:city":"Rolla",
    "sg:classifiers":[
        {
            "category":"Autos & Motor Vehicles",
            "subcategory":"Auto Supplies",
            "type":"Retail Goods"
        },
        {
            "category":"Retail",
            "subcategory":"Auto Repair",
            "type":"Services"
        }
    ],
    "sg:phone":"+1 573 426 5599",
    "sg:postcode":"65401",
    "sg:province":"MO",
    "sg:tags":[
        "wheel",
        "tire",
        "retread",
        "balancing",
        "wheels-aligning",
        "recap",
        "brake"
    ],
    "sg:website":"http://www.bigotires.com",
    "wof:name":"Big O Tires",
    "wof:placetype":"venue"
},
  "geometry": {"coordinates":[-91.765839,37.964197],"type":"Point"}
}