{
  "type": "Feature",
  "properties": {
    "iso:country":"US",
    "sg:address":"611 NW Timberbrooke Dr",
    "sg:city":"Lees Summit",
    "sg:classifiers":[
        {
            "category":"Shopping",
            "subcategory":"Shoes",
            "type":"Retail Goods"
        }
    ],
    "sg:phone":"+1 816 347 0482",
    "sg:postcode":"64081",
    "sg:province":"MO",
    "wof:name":"AR Custom Leasing",
    "wof:placetype":"venue"
},
  "geometry": {"coordinates":[-94.423862,38.924925],"type":"Point"}
}