{
  "type": "Feature",
  "properties": {
    "iso:country":"US",
    "sg:address":"1000 Sainte Genevieve Ave",
    "sg:city":"Farmington",
    "sg:classifiers":[
        {
            "category":"Food & Beverages",
            "subcategory":"Groceries & Convenience Stores",
            "type":"Retail Goods"
        }
    ],
    "sg:phone":"+1 573 756 1330",
    "sg:postcode":"63640",
    "sg:province":"MO",
    "wof:name":"Cbarn Inc",
    "wof:placetype":"venue"
},
  "geometry": {"coordinates":[-90.409294,37.777962],"type":"Point"}
}