{
  "type": "Feature",
  "properties": {
    "iso:country":"US",
    "sg:address":"2202 Walnut St",
    "sg:city":"Saint Joseph",
    "sg:classifiers":[
        {
            "category":"Autos & Motor Vehicles",
            "subcategory":"Automobile Sales",
            "type":"Retail Goods"
        }
    ],
    "sg:phone":"+1 816 279 8660",
    "sg:postcode":"64503",
    "sg:province":"MO",
    "sg:tags":[
        "used"
    ],
    "wof:name":"Action Auto Sales",
    "wof:placetype":"venue"
},
  "geometry": {"coordinates":[-94.83272100000001,39.74388],"type":"Point"}
}