{
  "type": "Feature",
  "properties": {
    "iso:country":"US",
    "sg:address":"12255 de Paul Dr",
    "sg:city":"Bridgeton",
    "sg:classifiers":[
        {
            "category":"Health Services",
            "subcategory":"Doctor",
            "type":"Services"
        }
    ],
    "sg:phone":"+1 636 946 5559",
    "sg:postcode":"63044",
    "sg:province":"MO",
    "sg:tags":[
        "physician",
        "surgeon"
    ],
    "wof:name":"St Louis Heart Institute",
    "wof:placetype":"venue"
},
  "geometry": {"coordinates":[-90.430239,38.749631],"type":"Point"}
}