{
  "type": "Feature",
  "properties": {
    "iso:country":"US",
    "sg:address":"9515 Lackland Rd",
    "sg:city":"Overland",
    "sg:classifiers":[
        {
            "category":"Bars & Pubs",
            "type":"Food & Drink"
        }
    ],
    "sg:phone":"+1 314 429 0794",
    "sg:postcode":"63114",
    "sg:province":"MO",
    "wof:name":"Kookie's Korner Saloon",
    "wof:placetype":"venue"
},
  "geometry": {"coordinates":[-90.366332,38.700795],"type":"Point"}
}