{
  "type": "Feature",
  "properties": {
    "iso:country":"US",
    "sg:address":"1600 S Brentwood Blvd",
    "sg:city":"Saint Louis",
    "sg:classifiers":[
        {
            "category":"Health Services",
            "subcategory":"Doctor",
            "type":"Services"
        }
    ],
    "sg:phone":"+1 314 367 1181",
    "sg:postcode":"63144",
    "sg:province":"MO",
    "sg:tags":[
        "medical"
    ],
    "wof:name":"Gerald S Shah",
    "wof:placetype":"venue"
},
  "geometry": {"coordinates":[-90.346542,38.626457],"type":"Point"}
}