{
  "type": "Feature",
  "properties": {
    "iso:country":"US",
    "sg:address":"5454 Elmira",
    "sg:city":"Springfield",
    "sg:classifiers":[
        {
            "category":"Professional",
            "type":"Services"
        }
    ],
    "sg:phone":"+1 417 882 8749",
    "sg:postcode":"65810",
    "sg:province":"MO",
    "wof:name":"John A White",
    "wof:placetype":"venue"
},
  "geometry": {"coordinates":[-93.290581,37.114804],"type":"Point"}
}