{
  "type": "Feature",
  "properties": {
    "iso:country":"US",
    "sg:address":"14650 Manchester Rd",
    "sg:city":"Ballwin",
    "sg:classifiers":[
        {
            "category":"Shopping",
            "subcategory":"Department Store",
            "type":"Retail Goods"
        }
    ],
    "sg:phone":"+1 636 227 8600",
    "sg:postcode":"63011",
    "sg:province":"MO",
    "wof:name":"Value City",
    "wof:placetype":"venue"
},
  "geometry": {"coordinates":[-90.53102,38.592913],"type":"Point"}
}