{
  "type": "Feature",
  "properties": {
    "iso:country":"US",
    "sg:address":"1512 State Hwy A",
    "sg:city":"Liberty",
    "sg:classifiers":[
        {
            "category":"Professional",
            "subcategory":"Lawyer & Legal Services",
            "type":"Services"
        }
    ],
    "sg:phone":"+1 816 471 7466",
    "sg:postcode":"64068",
    "sg:province":"MO",
    "sg:tags":[
        "attorney"
    ],
    "wof:name":"Heavner Jarrett & Kimball",
    "wof:placetype":"venue"
},
  "geometry": {"coordinates":[-94.447593,39.266538],"type":"Point"}
}