{
  "type": "Feature",
  "properties": {
    "iso:country":"US",
    "sg:address":"145 Dale St",
    "sg:city":"Fordland",
    "sg:classifiers":[
        {
            "category":"Place Of Worship",
            "type":"Public Place"
        }
    ],
    "sg:phone":"+1 417 767 4543",
    "sg:postcode":"65652",
    "sg:province":"MO",
    "sg:tags":[
        "church"
    ],
    "wof:name":"Ozark Primitive Church",
    "wof:placetype":"venue"
},
  "geometry": {"coordinates":[-92.951194,37.156716],"type":"Point"}
}