{
  "type": "Feature",
  "properties": {
    "iso:country":"US",
    "sg:address":"5402 Wren Ave",
    "sg:city":"St Louis",
    "sg:classifiers":[
        {
            "category":"Organizations",
            "subcategory":"Religious Organization",
            "type":"Services"
        }
    ],
    "sg:phone":"+1 314 261 7765",
    "sg:postcode":"63120",
    "sg:province":"MO",
    "sg:tags":[
        "church"
    ],
    "wof:name":"Saint Matthew Lutheran Church",
    "wof:placetype":"venue"
},
  "geometry": {"coordinates":[-90.247517,38.701281],"type":"Point"}
}