{
  "type": "Feature",
  "properties": {
    "iso:country":"US",
    "sg:address":"3558 S Grand Blvd",
    "sg:city":"St Louis",
    "sg:classifiers":[
        {
            "category":"Food & Beverages",
            "subcategory":"Groceries & Convenience Stores",
            "type":"Retail Goods"
        }
    ],
    "sg:phone":"+1 314 664 6010",
    "sg:postcode":"63118",
    "sg:province":"MO",
    "sg:tags":[
        "grocer"
    ],
    "wof:name":"African Grocery Store",
    "wof:placetype":"venue"
},
  "geometry": {"coordinates":[-90.243816,38.592104],"type":"Point"}
}