{
  "type": "Feature",
  "properties": {
    "iso:country":"US",
    "sg:address":"18 Surrey Hills Rd",
    "sg:city":"Hannibal",
    "sg:classifiers":[
        {
            "category":"Professional",
            "subcategory":"Management & Consulting",
            "type":"Services"
        },
        {
            "category":"Building & Trades",
            "subcategory":"Construction",
            "type":"Services"
        }
    ],
    "sg:phone":"+1 573 248 8278",
    "sg:postcode":"63401",
    "sg:province":"MO",
    "sg:tags":[
        "well",
        "drilling"
    ],
    "wof:name":"Schwanke's Directional Drill",
    "wof:placetype":"venue"
},
  "geometry": {"coordinates":[-91.395128,39.711644],"type":"Point"}
}