{
  "type": "Feature",
  "properties": {
    "iso:country":"US",
    "sg:address":"3600 Blue Ridge Ext",
    "sg:city":"Grandview",
    "sg:classifiers":[
        {
            "category":"Health Services",
            "subcategory":"Medical Lab",
            "type":"Services"
        }
    ],
    "sg:phone":"+1 816 761 9428",
    "sg:postcode":"64030",
    "sg:province":"MO",
    "sg:website":"http://www.mdsupport.org",
    "wof:name":"Md Support",
    "wof:placetype":"venue"
},
  "geometry": {"coordinates":[-94.550063,38.895501],"type":"Point"}
}