{
  "type": "Feature",
  "properties": {
    "iso:country":"US",
    "sg:address":"639 Kyle St",
    "sg:city":"Saint James",
    "sg:classifiers":[
        {
            "category":"Building & Trades",
            "subcategory":"Construction",
            "type":"Services"
        }
    ],
    "sg:phone":"+1 573 647 9619",
    "sg:postcode":"65559",
    "sg:province":"MO",
    "wof:name":"Dnd Construction",
    "wof:placetype":"venue"
},
  "geometry": {"coordinates":[-91.60882700000001,38.007798],"type":"Point"}
}