{
  "type": "Feature",
  "properties": {
    "iso:country":"US",
    "sg:address":"8515 Airport Rd",
    "sg:city":"St Louis",
    "sg:classifiers":[
        {
            "category":"Wholesale",
            "subcategory":"Construction Materials",
            "type":"Manufacturing & Wholesale Goods"
        },
        {
            "category":"Home & Garden",
            "subcategory":"Building Materials",
            "type":"Retail Goods"
        }
    ],
    "sg:phone":"+1 314 522 0738",
    "sg:postcode":"63134",
    "sg:province":"MO",
    "wof:name":"Behle Materials",
    "wof:placetype":"venue"
},
  "geometry": {"coordinates":[-90.332015,38.750115],"type":"Point"}
}