{
  "type": "Feature",
  "properties": {
    "iso:country":"US",
    "sg:address":"605 White Oak Ln",
    "sg:city":"Kansas City",
    "sg:classifiers":[
        {
            "category":"Health Services",
            "subcategory":"Doctor",
            "type":"Services"
        }
    ],
    "sg:phone":"+1 913 709 0304",
    "sg:postcode":"64116",
    "sg:province":"MO",
    "sg:tags":[
        "medical"
    ],
    "wof:name":"Iap Inc",
    "wof:placetype":"venue"
},
  "geometry": {"coordinates":[-94.588205,39.17848],"type":"Point"}
}