{
  "type": "Feature",
  "properties": {
    "iso:country":"US",
    "sg:address":"3325 Olive St",
    "sg:city":"St Louis",
    "sg:classifiers":[
        {
            "category":"Organizations",
            "subcategory":"Professional Association",
            "type":"Services"
        },
        {
            "category":"Social Services",
            "type":"Services"
        }
    ],
    "sg:phone":"+1 314 533 9104",
    "sg:postcode":"63103",
    "sg:province":"MO",
    "sg:tags":[
        "business",
        "welfare"
    ],
    "sg:website":"www.slaco.org",
    "wof:name":"Slaco",
    "wof:placetype":"venue"
},
  "geometry": {"coordinates":[-90.22794500000001,38.636299],"type":"Point"}
}