{
  "type": "Feature",
  "properties": {
    "iso:country":"US",
    "sg:address":"5133 S Campbell Ave",
    "sg:city":"Springfield",
    "sg:classifiers":[
        {
            "category":"Retail",
            "subcategory":"Storage",
            "type":"Services"
        }
    ],
    "sg:phone":"+1 417 883 6707",
    "sg:postcode":"65810",
    "sg:province":"MO",
    "sg:tags":[
        "automobile",
        "household",
        "recreational",
        "commercial",
        "campers-storage",
        "vehicle",
        "self",
        "boat"
    ],
    "sg:website":"http://www.swmostorage.com",
    "wof:name":"Cherokee Mini Storage & Aarons E-Z Store",
    "wof:placetype":"venue"
},
  "geometry": {"coordinates":[-93.296869,37.121357],"type":"Point"}
}