{
  "type": "Feature",
  "properties": {
    "iso:country":"US",
    "sg:address":"1203 Drury Ln",
    "sg:city":"Arnold",
    "sg:classifiers":[
        {
            "category":"Restaurant",
            "type":"Food & Drink"
        }
    ],
    "sg:menulink":"http://www.allmenus.com/mo/arnold/11484-dennys/menu/",
    "sg:phone":"+1 636 296 9477",
    "sg:postcode":"63010",
    "sg:province":"MO",
    "sg:tags":[
        "american",
        "diner"
    ],
    "wof:name":"Denny's",
    "wof:placetype":"venue"
},
  "geometry": {"coordinates":[-90.375834,38.445149],"type":"Point"}
}