{
  "type": "Feature",
  "properties": {
    "iso:country":"US",
    "sg:address":"25187 Collins Dr",
    "sg:city":"Milan",
    "sg:classifiers":[
        {
            "category":"Manufacturing",
            "subcategory":"Buildings",
            "type":"Manufacturing & Wholesale Goods"
        },
        {
            "category":"Building & Trades",
            "subcategory":"Construction",
            "type":"Services"
        }
    ],
    "sg:phone":"+1 660 292 1206",
    "sg:postcode":"63556",
    "sg:province":"MO",
    "sg:tags":[
        "home",
        "builder",
        "contractor"
    ],
    "wof:name":"Richard E Davis Construction",
    "wof:placetype":"venue"
},
  "geometry": {"coordinates":[-93.236318,40.164],"type":"Point"}
}