{
  "type": "Feature",
  "properties": {
    "iso:country":"US",
    "sg:address":"1800 Gravois Rd",
    "sg:city":"High Ridge",
    "sg:classifiers":[
        {
            "category":"Professional",
            "subcategory":"Management & Consulting",
            "type":"Services"
        }
    ],
    "sg:phone":"+1 636 677 8191",
    "sg:postcode":"63049",
    "sg:province":"MO",
    "sg:tags":[
        "business"
    ],
    "wof:name":"Alter Management Co",
    "wof:placetype":"venue"
},
  "geometry": {"coordinates":[-90.50314899999999,38.481999],"type":"Point"}
}