{
  "type": "Feature",
  "properties": {
    "iso:country":"US",
    "sg:address":"2310 Southwest Dr Ee",
    "sg:city":"Kennett",
    "sg:classifiers":[
        {
            "category":"Building & Trades",
            "subcategory":"Equipment Rental",
            "type":"Services"
        }
    ],
    "sg:phone":"+1 573 888 1980",
    "sg:postcode":"63857",
    "sg:province":"MO",
    "sg:tags":[
        "yard",
        "leasing",
        "store"
    ],
    "wof:name":"Baker Mills Trailer Park",
    "wof:placetype":"venue"
},
  "geometry": {"coordinates":[-90.074343,36.212183],"type":"Point"}
}