{
  "type": "Feature",
  "properties": {
    "iso:country":"US",
    "sg:address":"14145 Old Jamestown Rd",
    "sg:city":"Florissant",
    "sg:classifiers":[
        {
            "category":"Shopping",
            "subcategory":"Gifts & Souvenirs",
            "type":"Retail Goods"
        }
    ],
    "sg:phone":"+1 314 355 2187",
    "sg:postcode":"63033",
    "sg:province":"MO",
    "wof:name":"Good Time Party Stop Inc",
    "wof:placetype":"venue"
},
  "geometry": {"coordinates":[-90.25431500000001,38.812744],"type":"Point"}
}