{
  "type": "Feature",
  "properties": {
    "iso:country":"US",
    "sg:address":"297 N Broadview St",
    "sg:city":"Cape Girardeau",
    "sg:classifiers":[
        {
            "category":"Autos & Motor Vehicles",
            "subcategory":"Auto Supplies",
            "type":"Retail Goods"
        }
    ],
    "sg:phone":"+1 573 335 6399",
    "sg:postcode":"63701",
    "sg:province":"MO",
    "sg:tags":[
        "equipment",
        "electrical"
    ],
    "wof:name":"Exide Corporation",
    "wof:placetype":"venue"
},
  "geometry": {"coordinates":[-89.55522999999999,37.309253],"type":"Point"}
}