{
  "type": "Feature",
  "properties": {
    "addr:full":"500 W Business 36 Chillicothe MO 64601",
    "addr:housenumber":"500;36",
    "addr:postcode":"64601",
    "addr:street":"W Business",
    "iso:country":"US",
    "sg:address":"500 W Business 36",
    "sg:city":"Chillicothe",
    "sg:classifiers":[
        {
            "category":"Restaurant",
            "type":"Food & Drink"
        }
    ],
    "sg:menulink":"http://www.allmenus.com/mo/chillicothe/89807-applebees/menu/",
    "sg:phone":"+1 660 707 1222",
    "sg:postcode":"64601",
    "sg:province":"MO",
    "sg:tags":[
        "burger",
        "american",
        "sandwich",
        "soup"
    ],
    "wof:name":"Applebee's",
    "wof:placetype":"venue"
},
  "geometry": {"coordinates":[-93.54902199999999,39.775044],"type":"Point"}
}