{
  "type": "Feature",
  "properties": {
    "iso:country":"US",
    "sg:address":"206 S 2nd St",
    "sg:city":"Owensville",
    "sg:classifiers":[
        {
            "category":"Retail",
            "subcategory":"Animal Services",
            "type":"Services"
        }
    ],
    "sg:phone":"+1 573 437 5865",
    "sg:postcode":"65066",
    "sg:province":"MO",
    "sg:tags":[
        "pet"
    ],
    "wof:name":"Wagging Tails",
    "wof:placetype":"venue"
},
  "geometry": {"coordinates":[-91.501721,38.346007],"type":"Point"}
}