{
  "type": "Feature",
  "properties": {
    "iso:country":"US",
    "sg:address":"3 NE 1st Ln",
    "sg:city":"Lamar",
    "sg:classifiers":[
        {
            "category":"Autos & Motor Vehicles",
            "subcategory":"Automobile Sales",
            "type":"Retail Goods"
        }
    ],
    "sg:phone":"+1 417 682 2834",
    "sg:postcode":"64759",
    "sg:province":"MO",
    "sg:tags":[
        "used"
    ],
    "wof:name":"Marti Used Cars",
    "wof:placetype":"venue"
},
  "geometry": {"coordinates":[-94.297445,37.508285],"type":"Point"}
}