{
  "type": "Feature",
  "properties": {
    "iso:country":"US",
    "sg:address":"19750 E Valleyview Pkwy",
    "sg:city":"Independence",
    "sg:classifiers":[
        {
            "category":"Restaurant",
            "type":"Food & Drink"
        }
    ],
    "sg:menulink":"http://www.allmenus.com/mo/sni-a-bar/105545-bds-mongolian-bbq/menu/",
    "sg:phone":"+1 816 795 5430",
    "sg:postcode":"64057",
    "sg:province":"MO",
    "sg:tags":[
        "mongolian",
        "asian"
    ],
    "wof:name":"Bd's Mongolian BBQ",
    "wof:placetype":"venue"
},
  "geometry": {"coordinates":[-94.347437,39.038503],"type":"Point"}
}