{
  "type": "Feature",
  "properties": {
    "iso:country":"US",
    "sg:address":"2123 Newport Rd",
    "sg:city":"Saint Joseph",
    "sg:classifiers":[
        {
            "category":"Professional",
            "subcategory":"Management & Consulting",
            "type":"Services"
        }
    ],
    "sg:phone":"+1 816 232 0746",
    "sg:postcode":"64505",
    "sg:province":"MO",
    "sg:tags":[
        "establishment",
        "business"
    ],
    "wof:name":"Olympus Center",
    "wof:placetype":"venue"
},
  "geometry": {"coordinates":[-94.837599,39.792636],"type":"Point"}
}