{
  "type": "Feature",
  "properties": {
    "iso:country":"US",
    "sg:address":"700 North Byp",
    "sg:city":"Kennett",
    "sg:classifiers":[
        {
            "category":"Communications",
            "subcategory":"Radio Station",
            "type":"Services"
        }
    ],
    "sg:phone":"+1 573 686 3700",
    "sg:postcode":"63857",
    "sg:province":"MO",
    "sg:tags":[
        "company",
        "broadcasting"
    ],
    "wof:name":"KXOQ",
    "wof:placetype":"venue"
},
  "geometry": {"coordinates":[-90.050015,36.251332],"type":"Point"}
}