{
  "type": "Feature",
  "properties": {
    "iso:country":"US",
    "sg:address":"1601 Highway W",
    "sg:city":"Foristell",
    "sg:classifiers":[
        {
            "category":"Retail",
            "subcategory":"Animal Services",
            "type":"Services"
        }
    ],
    "sg:phone":"+1 636 327 6434",
    "sg:postcode":"63348",
    "sg:province":"MO",
    "sg:tags":[
        "pet",
        "boarding",
        "sitting"
    ],
    "wof:name":"Abel Country Aire Kennel",
    "wof:placetype":"venue"
},
  "geometry": {"coordinates":[-90.916417,38.769604],"type":"Point"}
}