{
  "type": "Feature",
  "properties": {
    "iso:country":"US",
    "sg:address":"20538 Lawrence 2145",
    "sg:city":"Aurora",
    "sg:classifiers":[
        {
            "category":"Retail",
            "subcategory":"Animal Services",
            "type":"Services"
        }
    ],
    "sg:phone":"+1 417 463 2717",
    "sg:postcode":"65605",
    "sg:province":"MO",
    "wof:name":"Jim Conran",
    "wof:placetype":"venue"
},
  "geometry": {"coordinates":[-93.687787,37.06633],"type":"Point"}
}