{
  "type": "Feature",
  "properties": {
    "iso:country":"US",
    "sg:address":"17 Sheppard St",
    "sg:city":"Fort Leonard Wood",
    "sg:classifiers":[
        {
            "category":"Wholesale",
            "subcategory":"Apparel",
            "type":"Manufacturing & Wholesale Goods"
        }
    ],
    "sg:phone":"+1 573 329 5672",
    "sg:postcode":"65473",
    "sg:province":"MO",
    "sg:tags":[
        "clothing"
    ],
    "wof:name":"Flappies",
    "wof:placetype":"venue"
},
  "geometry": {"coordinates":[-92.11873799999999,37.774433],"type":"Point"}
}