{
  "type": "Feature",
  "properties": {
    "iso:country":"US",
    "sg:address":"1025 Country Club Rd",
    "sg:city":"Saint Charles",
    "sg:classifiers":[
        {
            "category":"Professional",
            "subcategory":"Management & Consulting",
            "type":"Services"
        }
    ],
    "sg:phone":"+1 636 947 0822",
    "sg:postcode":"63303",
    "sg:province":"MO",
    "sg:tags":[
        "business"
    ],
    "wof:name":"Adult Edcatn Cstmized Training",
    "wof:placetype":"venue"
},
  "geometry": {"coordinates":[-90.53533400000001,38.786295],"type":"Point"}
}