{
  "type": "Feature",
  "properties": {
    "iso:country":"US",
    "sg:address":"402 W 1st St",
    "sg:city":"Mountain View",
    "sg:classifiers":[
        {
            "category":"Retail",
            "subcategory":"Repair Shop",
            "type":"Services"
        }
    ],
    "sg:phone":"+1 417 934 6871",
    "sg:postcode":"65548",
    "sg:province":"MO",
    "wof:name":"Dent Specialist",
    "wof:placetype":"venue"
},
  "geometry": {"coordinates":[-91.706659,36.995002],"type":"Point"}
}