{
  "type": "Feature",
  "properties": {
    "iso:country":"US",
    "sg:address":"163 Merchant St",
    "sg:city":"Ste Genevieve",
    "sg:classifiers":[
        {
            "category":"Restaurant",
            "type":"Food & Drink"
        }
    ],
    "sg:phone":"+1 573 883 7902",
    "sg:postcode":"63670",
    "sg:province":"MO",
    "wof:name":"Doc Bogy's Restaurant",
    "wof:placetype":"venue"
},
  "geometry": {"coordinates":[-90.043846,37.980172],"type":"Point"}
}