{
  "type": "Feature",
  "properties": {
    "iso:country":"US",
    "sg:address":"389 Wilson Rd",
    "sg:city":"Branson",
    "sg:classifiers":[
        {
            "category":"Shopping",
            "subcategory":"Jewelry",
            "type":"Retail Goods"
        },
        {
            "category":"Manufacturing",
            "subcategory":"Jewelry",
            "type":"Manufacturing & Wholesale Goods"
        }
    ],
    "sg:phone":"+1 417 334 1115",
    "sg:postcode":"65616",
    "sg:province":"MO",
    "sg:tags":[
        "designer",
        "jeweler"
    ],
    "wof:name":"Timline Lab / Classic Cut",
    "wof:placetype":"venue"
},
  "geometry": {"coordinates":[-93.208787,36.678442],"type":"Point"}
}