{
  "type": "Feature",
  "properties": {
    "iso:country":"US",
    "sg:address":"8503 Mid County Industrl Dr",
    "sg:city":"Saint Louis",
    "sg:classifiers":[
        {
            "category":"Professional",
            "subcategory":"Advertising",
            "type":"Services"
        }
    ],
    "sg:phone":"+1 314 426 6245",
    "sg:postcode":"63114",
    "sg:province":"MO",
    "sg:tags":[
        "mail",
        "lithographic",
        "direct"
    ],
    "wof:name":"All Mail USA Inc",
    "wof:placetype":"venue"
},
  "geometry": {"coordinates":[-90.34150099999999,38.691924],"type":"Point"}
}