{
  "type": "Feature",
  "properties": {
    "iso:country":"US",
    "sg:address":"101 W Main St",
    "sg:city":"Bunceton",
    "sg:classifiers":[
        {
            "category":"Banks & Credit Unions",
            "subcategory":"Bank",
            "type":"Services"
        }
    ],
    "sg:phone":"+1 660 427 5201",
    "sg:postcode":"65237",
    "sg:province":"MO",
    "sg:tags":[
        "state",
        "commercial"
    ],
    "wof:name":"Mainstreet Bank",
    "wof:placetype":"venue"
},
  "geometry": {"coordinates":[-92.800372,38.788135],"type":"Point"}
}