{
  "type": "Feature",
  "properties": {
    "iso:country":"US",
    "sg:address":"3500 E Kearney St",
    "sg:city":"Springfield",
    "sg:classifiers":[
        {
            "category":"Home & Garden",
            "subcategory":"Building Materials",
            "type":"Retail Goods"
        },
        {
            "category":"Retail",
            "subcategory":"Repair Shop",
            "type":"Services"
        },
        {
            "category":"Building & Trades",
            "subcategory":"Equipment Rental",
            "type":"Services"
        },
        {
            "category":"Home & Garden",
            "subcategory":"Garden Supply",
            "type":"Retail Goods"
        }
    ],
    "sg:phone":"+1 417 865 8665",
    "sg:postcode":"65803",
    "sg:province":"MO",
    "sg:tags":[
        "renting",
        "lawn",
        "yard",
        "improvement",
        "tools-renting",
        "store",
        "contractors'"
    ],
    "sg:website":"http://www.superiorrents.com",
    "wof:name":"Superior Rents",
    "wof:placetype":"venue"
},
  "geometry": {"coordinates":[-93.222641,37.238789],"type":"Point"}
}