{
  "type": "Feature",
  "properties": {
    "iso:country":"US",
    "sg:address":"712 N Everett St",
    "sg:city":"Kennett",
    "sg:classifiers":[
        {
            "category":"Manufacturing",
            "subcategory":"Food",
            "type":"Manufacturing & Wholesale Goods"
        }
    ],
    "sg:phone":"+1 573 888 0917",
    "sg:postcode":"63857",
    "sg:province":"MO",
    "sg:tags":[
        "product"
    ],
    "wof:name":"Leon Pulley",
    "wof:placetype":"venue"
},
  "geometry": {"coordinates":[-90.061684,36.243884],"type":"Point"}
}