{
  "type": "Feature",
  "properties": {
    "iso:country":"US",
    "sg:address":"13004 13th St",
    "sg:city":"Grandview",
    "sg:classifiers":[
        {
            "category":"Autos & Motor Vehicles",
            "subcategory":"Auto Supplies",
            "type":"Retail Goods"
        },
        {
            "category":"Retail",
            "subcategory":"Auto Repair",
            "type":"Services"
        }
    ],
    "sg:phone":"+1 816 761 4140",
    "sg:postcode":"64030",
    "sg:province":"MO",
    "sg:tags":[
        "body",
        "lettering",
        "automobile",
        "truck",
        "painting",
        "repairing"
    ],
    "wof:name":"Pro Built Body Repair",
    "wof:placetype":"venue"
},
  "geometry": {"coordinates":[-94.530294,38.889043],"type":"Point"}
}