{
  "type": "Feature",
  "properties": {
    "iso:country":"US",
    "sg:address":"1465 S Grand Blvd",
    "sg:city":"St Louis",
    "sg:classifiers":[
        {
            "category":"Health Services",
            "subcategory":"Doctor",
            "type":"Services"
        }
    ],
    "sg:phone":"+1 314 977 4440",
    "sg:postcode":"63104",
    "sg:province":"MO",
    "sg:tags":[
        "physician",
        "surgeon"
    ],
    "wof:name":"Slucare-Pediatric Surgery",
    "wof:placetype":"venue"
},
  "geometry": {"coordinates":[-90.238542,38.62101],"type":"Point"}
}