{
  "type": "Feature",
  "properties": {
    "iso:country":"US",
    "sg:address":"920 Scott Ave",
    "sg:city":"Dexter",
    "sg:classifiers":[
        {
            "category":"Manufacturing",
            "subcategory":"Metals",
            "type":"Manufacturing & Wholesale Goods"
        },
        {
            "category":"Retail",
            "subcategory":"Auto Repair",
            "type":"Services"
        }
    ],
    "sg:phone":"+1 573 624 8415",
    "sg:postcode":"63841",
    "sg:province":"MO",
    "sg:tags":[
        "machine",
        "die",
        "tool",
        "shop",
        "mfg"
    ],
    "wof:name":"Boot Heel Tool & Machine",
    "wof:placetype":"venue"
},
  "geometry": {"coordinates":[-89.980317,36.805627],"type":"Point"}
}