{
  "type": "Feature",
  "properties": {
    "iso:country":"US",
    "sg:address":"1135 Erie St",
    "sg:city":"Kansas City",
    "sg:classifiers":[
        {
            "category":"Home & Garden",
            "subcategory":"Building Materials",
            "type":"Retail Goods"
        },
        {
            "category":"Building & Trades",
            "subcategory":"Construction",
            "type":"Services"
        }
    ],
    "sg:phone":"+1 816 842 0770",
    "sg:postcode":"64116",
    "sg:province":"MO",
    "sg:tags":[
        "house",
        "planning",
        "remodeling",
        "kitchen"
    ],
    "wof:name":"Hartis Kitchen Center Inc",
    "wof:placetype":"venue"
},
  "geometry": {"coordinates":[-94.576126,39.129342],"type":"Point"}
}