{
  "type": "Feature",
  "properties": {
    "iso:country":"US",
    "sg:address":"320 E Railroad St",
    "sg:city":"Centralia",
    "sg:classifiers":[
        {
            "category":"Personal",
            "subcategory":"Beauty Salon",
            "type":"Services"
        }
    ],
    "sg:phone":"+1 573 682 1039",
    "sg:postcode":"65240",
    "sg:province":"MO",
    "sg:tags":[
        "shop"
    ],
    "wof:name":"Shear Illusions",
    "wof:placetype":"venue"
},
  "geometry": {"coordinates":[-92.134776,39.212159],"type":"Point"}
}