{
  "type": "Feature",
  "properties": {
    "iso:country":"US",
    "sg:address":"102 Tom White St",
    "sg:city":"Charleston",
    "sg:classifiers":[
        {
            "category":"Insurance",
            "subcategory":"Insurance Agent",
            "type":"Services"
        }
    ],
    "sg:phone":"+1 573 683 6382",
    "sg:postcode":"63834",
    "sg:province":"MO",
    "wof:name":"Farm Bureau Insurance",
    "wof:placetype":"venue"
},
  "geometry": {"coordinates":[-89.34970300000001,36.91035],"type":"Point"}
}