{
  "type": "Feature",
  "properties": {
    "iso:country":"US",
    "sg:address":"1107 S 25th St",
    "sg:city":"Bethany",
    "sg:classifiers":[
        {
            "category":"Retail",
            "subcategory":"Funeral Services",
            "type":"Services"
        }
    ],
    "sg:phone":"+1 660 425 3315",
    "sg:postcode":"64424",
    "sg:province":"MO",
    "sg:tags":[
        "director"
    ],
    "wof:name":"Roberson Funeral Homes",
    "wof:placetype":"venue"
},
  "geometry": {"coordinates":[-94.026989,40.257163],"type":"Point"}
}