{
  "type": "Feature",
  "properties": {
    "iso:country":"US",
    "sg:address":"116 N Range Line Rd",
    "sg:city":"Joplin",
    "sg:classifiers":[
        {
            "category":"Professional",
            "subcategory":"Advertising",
            "type":"Services"
        }
    ],
    "sg:phone":"+1 417 206 6999",
    "sg:postcode":"64801",
    "sg:province":"MO",
    "sg:tags":[
        "publishing"
    ],
    "wof:name":"Yellowbook",
    "wof:placetype":"venue"
},
  "geometry": {"coordinates":[-94.476957,37.093458],"type":"Point"}
}