{
  "type": "Feature",
  "properties": {
    "iso:country":"US",
    "sg:address":"1502 N 11th St",
    "sg:city":"Saint Joseph",
    "sg:classifiers":[
        {
            "category":"Wholesale",
            "subcategory":"Machinery & Supplies",
            "type":"Manufacturing & Wholesale Goods"
        }
    ],
    "sg:phone":"+1 816 232 8100",
    "sg:postcode":"64501",
    "sg:province":"MO",
    "sg:tags":[
        "equipment",
        "industrial"
    ],
    "wof:name":"Arch Environmental Equipment",
    "wof:placetype":"venue"
},
  "geometry": {"coordinates":[-94.846261,39.781214],"type":"Point"}
}