{
  "type": "Feature",
  "properties": {
    "iso:country":"US",
    "sg:address":"601 Illinois Ave",
    "sg:city":"St Joseph",
    "sg:classifiers":[
        {
            "category":"Wholesale",
            "subcategory":"Farm Supplies",
            "type":"Manufacturing & Wholesale Goods"
        }
    ],
    "sg:phone":"+1 816 238 0618",
    "sg:postcode":"64504",
    "sg:province":"MO",
    "sg:tags":[
        "commission",
        "livestock"
    ],
    "wof:name":"Boos & Penny",
    "wof:placetype":"venue"
},
  "geometry": {"coordinates":[-94.868674,39.719716],"type":"Point"}
}