{
  "type": "Feature",
  "properties": {
    "iso:country":"US",
    "sg:address":"103 E North St",
    "sg:city":"Warrensburg",
    "sg:classifiers":[
        {
            "category":"Restaurant",
            "type":"Food & Drink"
        }
    ],
    "sg:phone":"+1 660 747 9111",
    "sg:postcode":"64093",
    "sg:province":"MO",
    "sg:website":"http://www.sodexo.com",
    "wof:name":"Sodexo, Inc.",
    "wof:placetype":"venue"
},
  "geometry": {"coordinates":[-93.74009599999999,38.767577],"type":"Point"}
}