{
  "type": "Feature",
  "properties": {
    "iso:country":"US",
    "sg:address":"2125 Gravois Ave",
    "sg:city":"Saint Louis",
    "sg:classifiers":[
        {
            "category":"Building & Trades",
            "subcategory":"Cleaning & Sanitation",
            "type":"Services"
        }
    ],
    "sg:phone":"+1 314 771 3221",
    "sg:postcode":"63104",
    "sg:province":"MO",
    "sg:tags":[
        "carpet"
    ],
    "sg:website":"www.abbcoserv.com",
    "wof:name":"Abbco Service Corporation",
    "wof:placetype":"venue"
},
  "geometry": {"coordinates":[-90.219101,38.606499],"type":"Point"}
}