{
  "type": "Feature",
  "properties": {
    "iso:country":"US",
    "sg:address":"1376 E 525th Rd",
    "sg:city":"Brighton",
    "sg:classifiers":[
        {
            "category":"Farming",
            "subcategory":"Farm",
            "type":"Manufacturing & Wholesale Goods"
        }
    ],
    "sg:phone":"+1 417 376 2220",
    "sg:postcode":"65617",
    "sg:province":"MO",
    "wof:name":"Simmons Farm",
    "wof:placetype":"venue"
},
  "geometry": {"coordinates":[-93.380771,37.490671],"type":"Point"}
}