{
  "type": "Feature",
  "properties": {
    "iso:country":"US",
    "sg:address":"702 S Connor St",
    "sg:city":"Odessa",
    "sg:classifiers":[
        {
            "category":"Farming",
            "subcategory":"Farm",
            "type":"Manufacturing & Wholesale Goods"
        }
    ],
    "sg:phone":"+1 816 230 4198",
    "sg:postcode":"64076",
    "sg:province":"MO",
    "sg:tags":[
        "crop",
        "general"
    ],
    "wof:name":"Pinson Geraline",
    "wof:placetype":"venue"
},
  "geometry": {"coordinates":[-93.95021,38.989154],"type":"Point"}
}