{
  "type": "Feature",
  "properties": {
    "iso:country":"US",
    "sg:address":"428 Midlothian Rd",
    "sg:city":"St Louis",
    "sg:classifiers":[
        {
            "category":"Restaurant",
            "type":"Food & Drink"
        }
    ],
    "sg:phone":"+1 314 867 8998",
    "sg:postcode":"63137",
    "sg:province":"MO",
    "sg:tags":[
        "caterer"
    ],
    "wof:name":"Vickers Catering",
    "wof:placetype":"venue"
},
  "geometry": {"coordinates":[-90.20542,38.755425],"type":"Point"}
}