{
  "type": "Feature",
  "properties": {
    "iso:country":"US",
    "sg:address":"13935 New Halls Ferry Rd",
    "sg:city":"Florissant",
    "sg:classifiers":[
        {
            "category":"Shopping",
            "subcategory":"Clothing, Apparel, & Fashions",
            "type":"Retail Goods"
        }
    ],
    "sg:phone":"+1 314 355 0523",
    "sg:postcode":"63033",
    "sg:province":"MO",
    "wof:name":"Lane Bryant",
    "wof:placetype":"venue"
},
  "geometry": {"coordinates":[-90.298306,38.808061],"type":"Point"}
}