{
  "type": "Feature",
  "properties": {
    "iso:country":"US",
    "sg:address":"8244 Hwy Ae",
    "sg:city":"Sullivan",
    "sg:classifiers":[
        {
            "category":"Organizations",
            "subcategory":"Religious Organization",
            "type":"Services"
        }
    ],
    "sg:phone":"+1 573 627 3378",
    "sg:postcode":"63080",
    "sg:province":"MO",
    "wof:name":"Holy Martyrs Of Japan Church",
    "wof:placetype":"venue"
},
  "geometry": {"coordinates":[-91.315397,38.240478],"type":"Point"}
}