{
  "type": "Feature",
  "properties": {
    "iso:country":"US",
    "sg:address":"4026 Magnolia Pl",
    "sg:city":"Saint Louis",
    "sg:classifiers":[
        {
            "category":"Health Services",
            "subcategory":"Doctor",
            "type":"Services"
        }
    ],
    "sg:phone":"+1 314 772 7274",
    "sg:postcode":"63110",
    "sg:province":"MO",
    "sg:tags":[
        "surgeon",
        "oral"
    ],
    "wof:name":"Oleskevich Jas M DDS",
    "wof:placetype":"venue"
},
  "geometry": {"coordinates":[-90.25009900000001,38.608898],"type":"Point"}
}