{
  "type": "Feature",
  "properties": {
    "iso:country":"US",
    "sg:address":"500 W Sunshine St",
    "sg:city":"Springfield",
    "sg:classifiers":[
        {
            "category":"Museum",
            "subcategory":"Botanical Garden",
            "type":"Entertainment"
        }
    ],
    "sg:phone":"+1 417 890 9453",
    "sg:postcode":"65807",
    "sg:province":"MO",
    "sg:website":"www.wondersofwildlife.org",
    "wof:name":"Wonders Of Wildlife",
    "wof:placetype":"venue"
},
  "geometry": {"coordinates":[-93.29765999999999,37.18228],"type":"Point"}
}