{
  "type": "Feature",
  "properties": {
    "iso:country":"US",
    "sg:address":"3001 W 13th St",
    "sg:city":"Joplin",
    "sg:classifiers":[
        {
            "category":"Communications",
            "subcategory":"Radio Station",
            "type":"Services"
        }
    ],
    "sg:phone":"+1 417 781 1100",
    "sg:postcode":"64801",
    "sg:province":"MO",
    "sg:tags":[
        "broadcast"
    ],
    "wof:name":"Kkll 1100 Am Christian Radio",
    "wof:placetype":"venue"
},
  "geometry": {"coordinates":[-94.550612,37.077441],"type":"Point"}
}