{
  "type": "Feature",
  "properties": {
    "iso:country":"US",
    "sg:address":"8971 Halls Ferry Rd",
    "sg:city":"Saint Louis",
    "sg:classifiers":[
        {
            "category":"Shopping",
            "subcategory":"Beauty & Cosmetics",
            "type":"Retail Goods"
        }
    ],
    "sg:phone":"+1 314 867 8777",
    "sg:postcode":"63147",
    "sg:province":"MO",
    "sg:tags":[
        "supply"
    ],
    "wof:name":"Kings Beauty Distributor Corporation",
    "wof:placetype":"venue"
},
  "geometry": {"coordinates":[-90.239502,38.713902],"type":"Point"}
}