{
  "type": "Feature",
  "properties": {
    "iso:country":"US",
    "sg:address":"20312 East 17th Street North",
    "sg:city":"Independence",
    "sg:classifiers":[
        {
            "category":"Building & Trades",
            "subcategory":"Construction",
            "type":"Services"
        }
    ],
    "sg:phone":"+1 816 394 5943",
    "sg:postcode":"64056",
    "sg:province":"MO",
    "sg:tags":[
        "roofing",
        "consultant",
        "contractor"
    ],
    "wof:name":"Treece Roofing and Construction",
    "wof:placetype":"venue"
},
  "geometry": {"coordinates":[-94.338004,39.132882],"type":"Point"}
}