{
  "type": "Feature",
  "properties": {
    "iso:country":"US",
    "sg:address":"306 Mexico Rd",
    "sg:city":"Wentzville",
    "sg:classifiers":[
        {
            "category":"Farming",
            "subcategory":"Livestock Farm",
            "type":"Manufacturing & Wholesale Goods"
        }
    ],
    "sg:phone":"+1 636 327 6138",
    "sg:postcode":"63385",
    "sg:province":"MO",
    "sg:tags":[
        "beef",
        "feedlot",
        "cattle"
    ],
    "wof:name":"Elroy Rufkahr",
    "wof:placetype":"venue"
},
  "geometry": {"coordinates":[-90.85539799999999,38.850103],"type":"Point"}
}