{
  "type": "Feature",
  "properties": {
    "iso:country":"US",
    "sg:address":"7549 Huntley Dr",
    "sg:city":"Saint Louis",
    "sg:classifiers":[
        {
            "category":"Real Estate",
            "subcategory":"Real Estate Operator",
            "type":"Services"
        },
        {
            "category":"Organizations",
            "subcategory":"Community Association",
            "type":"Services"
        }
    ],
    "sg:phone":"+1 314 962 1959",
    "sg:postcode":"63119",
    "sg:province":"MO",
    "sg:tags":[
        "condominium"
    ],
    "wof:name":"Kenrick Park Condominium Assn",
    "wof:placetype":"venue"
},
  "geometry": {"coordinates":[-90.33198899999999,38.580374],"type":"Point"}
}