{
  "type": "Feature",
  "properties": {
    "iso:country":"US",
    "sg:address":"1693 Fenpark Dr",
    "sg:city":"Fenton",
    "sg:classifiers":[
        {
            "category":"Wholesale",
            "subcategory":"Hardware",
            "type":"Manufacturing & Wholesale Goods"
        }
    ],
    "sg:phone":"+1 636 343 6520",
    "sg:postcode":"63026",
    "sg:province":"MO",
    "sg:tags":[
        "a",
        "wholesaler",
        "as",
        "operates"
    ],
    "sg:website":"www.baerco.com",
    "wof:name":"Baer Supply Co",
    "wof:placetype":"venue"
},
  "geometry": {"coordinates":[-90.44916499999999,38.533053],"type":"Point"}
}