{
  "type": "Feature",
  "properties": {
    "iso:country":"US",
    "sg:address":"13354 Manchester Rd",
    "sg:city":"St Louis",
    "sg:classifiers":[
        {
            "category":"Social Services",
            "type":"Services"
        }
    ],
    "sg:phone":"+1 314 835 9311",
    "sg:postcode":"63131",
    "sg:province":"MO",
    "sg:tags":[
        "instruction",
        "health",
        "care"
    ],
    "sg:website":"www.g2n.org",
    "wof:name":"G2N Inc",
    "wof:placetype":"venue"
},
  "geometry": {"coordinates":[-90.46720000000001,38.60026],"type":"Point"}
}