{
  "type": "Feature",
  "properties": {
    "iso:country":"US",
    "sg:address":"4035 State Rd E",
    "sg:city":"Auxvasse",
    "sg:classifiers":[
        {
            "category":"Place Of Worship",
            "subcategory":"Church",
            "type":"Public Place"
        },
        {
            "category":"Place Of Worship",
            "type":"Public Place"
        }
    ],
    "sg:phone":"+1 573 387 4548",
    "sg:postcode":"65231",
    "sg:province":"MO",
    "sg:tags":[
        "churches-baptist-general",
        "churches-baptist"
    ],
    "wof:name":"Rising Sun Baptist Church",
    "wof:placetype":"venue"
},
  "geometry": {"coordinates":[-92.001127,39.026201],"type":"Point"}
}