{
  "type": "Feature",
  "properties": {
    "iso:country":"US",
    "sg:address":"149 N Meramec Ave",
    "sg:city":"Saint Louis",
    "sg:classifiers":[
        {
            "category":"Real Estate",
            "subcategory":"Real Estate Agent",
            "type":"Services"
        }
    ],
    "sg:phone":"+1 314 206 4600",
    "sg:postcode":"63105",
    "sg:province":"MO",
    "sg:tags":[
        "management",
        "operate"
    ],
    "wof:name":"Coldwell Banker",
    "wof:placetype":"venue"
},
  "geometry": {"coordinates":[-90.339189,38.654249],"type":"Point"}
}