{
  "type": "Feature",
  "properties": {
    "iso:country":"US",
    "sg:address":"6 Cedar Trail Ct",
    "sg:city":"Fenton",
    "sg:classifiers":[
        {
            "category":"Wholesale",
            "subcategory":"Vending Machines",
            "type":"Manufacturing & Wholesale Goods"
        }
    ],
    "sg:phone":"+1 636 677 6635",
    "sg:postcode":"63026",
    "sg:province":"MO",
    "sg:tags":[
        "operator"
    ],
    "wof:name":"D & W Innovations",
    "wof:placetype":"venue"
},
  "geometry": {"coordinates":[-90.501632,38.499104],"type":"Point"}
}