{
  "type": "Feature",
  "properties": {
    "iso:country":"US",
    "sg:address":"899 Sainte Genevieve Ave",
    "sg:city":"Sainte Genevieve",
    "sg:classifiers":[
        {
            "category":"Organizations",
            "subcategory":"Labor Organization",
            "type":"Services"
        }
    ],
    "sg:phone":"+1 573 883 2202",
    "sg:postcode":"63640",
    "sg:province":"MO",
    "wof:name":"Quarry & Allied Workers 830",
    "wof:placetype":"venue"
},
  "geometry": {"coordinates":[-90.41049599999999,37.778081],"type":"Point"}
}