{
  "type": "Feature",
  "properties": {
    "iso:country":"US",
    "sg:address":"141 N Meramec Ave",
    "sg:city":"St Louis",
    "sg:classifiers":[
        {
            "category":"Health Services",
            "subcategory":"Doctor",
            "type":"Services"
        }
    ],
    "sg:phone":"+1 314 726 1666",
    "sg:postcode":"63105",
    "sg:province":"MO",
    "sg:tags":[
        "physician",
        "medical",
        "surgeon"
    ],
    "wof:name":"James Mikolajczak MD",
    "wof:placetype":"venue"
},
  "geometry": {"coordinates":[-90.339499,38.651926],"type":"Point"}
}