{
  "type": "Feature",
  "properties": {
    "iso:country":"US",
    "sg:address":"1415 Carriage Bridge Trl",
    "sg:city":"Ballwin",
    "sg:classifiers":[
        {
            "category":"Building & Trades",
            "subcategory":"Construction",
            "type":"Services"
        }
    ],
    "sg:phone":"+1 636 861 4508",
    "sg:postcode":"63021",
    "sg:province":"MO",
    "sg:tags":[
        "altering",
        "remodeling",
        "contractor"
    ],
    "wof:name":"B & D Joker",
    "wof:placetype":"venue"
},
  "geometry": {"coordinates":[-90.515275,38.55937],"type":"Point"}
}