{
  "type": "Feature",
  "properties": {
    "addr:full":"8800 S Raytown Rd Kansas City MO 64138",
    "addr:housenumber":"8800",
    "addr:postcode":"64138",
    "addr:street":"S Raytown Rd",
    "iso:country":"US",
    "sg:address":"8800 S Raytown Rd",
    "sg:city":"Kansas City",
    "sg:classifiers":[
        {
            "category":"Government",
            "subcategory":"Post Office",
            "type":"Public Place"
        }
    ],
    "sg:phone":"+1 816 737 3255",
    "sg:postcode":"64138",
    "sg:province":"MO",
    "sg:tags":[
        "postal",
        "us"
    ],
    "wof:name":"US Post Office",
    "wof:placetype":"venue"
},
  "geometry": {"coordinates":[-94.46560700000001,38.962706],"type":"Point"}
}