{
  "type": "Feature",
  "properties": {
    "iso:country":"US",
    "sg:address":"404 Harvest Hill Ct",
    "sg:city":"Ballwin",
    "sg:classifiers":[
        {
            "category":"Building & Trades",
            "subcategory":"Construction",
            "type":"Services"
        }
    ],
    "sg:phone":"+1 314 846 3920",
    "sg:postcode":"63021",
    "sg:province":"MO",
    "sg:tags":[
        "nonresidential"
    ],
    "wof:name":"Spann General Contracting",
    "wof:placetype":"venue"
},
  "geometry": {"coordinates":[-90.55127299999999,38.574652],"type":"Point"}
}