{
  "type": "Feature",
  "properties": {
    "iso:country":"US",
    "sg:address":"9423 Muriel Ave",
    "sg:city":"Saint Louis",
    "sg:classifiers":[
        {
            "category":"Freight",
            "type":"Transportation"
        }
    ],
    "sg:phone":"+1 314 427 4306",
    "sg:postcode":"63114",
    "sg:province":"MO",
    "sg:tags":[
        "operator",
        "local",
        "trucking"
    ],
    "wof:name":"Mick Hollis Trucking",
    "wof:placetype":"venue"
},
  "geometry": {"coordinates":[-90.36338600000001,38.723134],"type":"Point"}
}