{
  "type": "Feature",
  "properties": {
    "iso:country":"US",
    "sg:address":"6421 N Cosby Ave",
    "sg:city":"Kansas City",
    "sg:classifiers":[
        {
            "category":"Shopping",
            "subcategory":"Gifts & Souvenirs",
            "type":"Retail Goods"
        }
    ],
    "sg:phone":"+1 816 746 4222",
    "sg:postcode":"64151",
    "sg:province":"MO",
    "wof:name":"Kiln Inc",
    "wof:placetype":"venue"
},
  "geometry": {"coordinates":[-94.64664,39.210769],"type":"Point"}
}