{
  "type": "Feature",
  "properties": {
    "iso:country":"US",
    "sg:address":"21752 Pike 312",
    "sg:city":"Bowling Green",
    "sg:classifiers":[
        {
            "category":"Building & Trades",
            "subcategory":"Construction",
            "type":"Services"
        }
    ],
    "sg:phone":"+1 573 324 3052",
    "sg:postcode":"63334",
    "sg:province":"MO",
    "sg:tags":[
        "hanging",
        "contractor"
    ],
    "wof:name":"Kneiss Painting Mark",
    "wof:placetype":"venue"
},
  "geometry": {"coordinates":[-91.181462,39.276638],"type":"Point"}
}