{
  "type": "Feature",
  "properties": {
    "iso:country":"US",
    "sg:address":"1326 Washington Ave",
    "sg:city":"St Louis",
    "sg:classifiers":[
        {
            "category":"Shopping",
            "subcategory":"Shoes",
            "type":"Retail Goods"
        }
    ],
    "sg:phone":"+1 314 231 2432",
    "sg:postcode":"63103",
    "sg:province":"MO",
    "wof:name":"Marte Shoes",
    "wof:placetype":"venue"
},
  "geometry": {"coordinates":[-90.199242,38.632211],"type":"Point"}
}