{
  "type": "Feature",
  "properties": {
    "iso:country":"US",
    "sg:address":"305 S Main St",
    "sg:city":"Concordia",
    "sg:classifiers":[
        {
            "category":"Autos & Motor Vehicles",
            "subcategory":"Automobile Sales",
            "type":"Retail Goods"
        }
    ],
    "sg:phone":"+1 660 463 2284",
    "sg:postcode":"64020",
    "sg:province":"MO",
    "sg:tags":[
        "car",
        "dealer"
    ],
    "wof:name":"Lew's Automart",
    "wof:placetype":"venue"
},
  "geometry": {"coordinates":[-93.567954,38.986651],"type":"Point"}
}