{
  "type": "Feature",
  "properties": {
    "iso:country":"US",
    "sg:address":"6072 US Hwy 54",
    "sg:city":"Osage Beach",
    "sg:classifiers":[
        {
            "category":"Shopping",
            "subcategory":"Gifts & Souvenirs",
            "type":"Retail Goods"
        }
    ],
    "sg:phone":"+1 573 348 6775",
    "sg:postcode":"65065",
    "sg:province":"MO",
    "sg:tags":[
        "shop"
    ],
    "wof:name":"Forever Friends",
    "wof:placetype":"venue"
},
  "geometry": {"coordinates":[-92.66587800000001,38.126975],"type":"Point"}
}