{
  "type": "Feature",
  "properties": {
    "iso:country":"US",
    "sg:address":"1723 W 4th St",
    "sg:city":"Sedalia",
    "sg:classifiers":[
        {
            "category":"Professional",
            "subcategory":"Business Services",
            "type":"Services"
        }
    ],
    "sg:phone":"+1 660 827 2656",
    "sg:postcode":"65301",
    "sg:province":"MO",
    "sg:tags":[
        "auction",
        "auctioneer"
    ],
    "wof:name":"Glen Glidewell Auction Service",
    "wof:placetype":"venue"
},
  "geometry": {"coordinates":[-93.246113,38.708256],"type":"Point"}
}