{
  "type": "Feature",
  "properties": {
    "iso:country":"US",
    "sg:address":"18777 E 39th St S",
    "sg:city":"Independence",
    "sg:classifiers":[
        {
            "category":"Shopping",
            "type":"Retail Goods"
        }
    ],
    "sg:phone":"+1 816 795 1888",
    "sg:postcode":"64057",
    "sg:province":"MO",
    "sg:tags":[
        "aids",
        "hearing"
    ],
    "wof:name":"Miracle-Ear",
    "wof:placetype":"venue"
},
  "geometry": {"coordinates":[-94.354277,39.047785],"type":"Point"}
}