{
  "type": "Feature",
  "properties": {
    "iso:country":"US",
    "sg:address":"303 Cedar St",
    "sg:city":"Anderson",
    "sg:classifiers":[
        {
            "category":"Personal",
            "subcategory":"Massage",
            "type":"Services"
        },
        {
            "category":"Health Services",
            "subcategory":"Clinic",
            "type":"Services"
        },
        {
            "category":"Health Services",
            "subcategory":"Health Practitioner",
            "type":"Services"
        }
    ],
    "sg:phone":"+1 417 845 0170",
    "sg:postcode":"64831",
    "sg:province":"MO",
    "sg:tags":[
        "therapist",
        "therapy",
        "physical"
    ],
    "wof:name":"Mollycoddle Massage Clinic",
    "wof:placetype":"venue"
},
  "geometry": {"coordinates":[-94.441795,36.649375],"type":"Point"}
}