{
  "type": "Feature",
  "properties": {
    "iso:country":"US",
    "sg:address":"5954 S Farm Rd 67",
    "sg:city":"Republic",
    "sg:classifiers":[
        {
            "category":"Retail",
            "subcategory":"Auto Repair",
            "type":"Services"
        }
    ],
    "sg:phone":"+1 417 732 6093",
    "sg:postcode":"65738",
    "sg:province":"MO",
    "sg:tags":[
        "body",
        "automobile",
        "painting"
    ],
    "wof:name":"Loveland Auto Body",
    "wof:placetype":"venue"
},
  "geometry": {"coordinates":[-93.507171,37.108909],"type":"Point"}
}