{
  "type": "Feature",
  "properties": {
    "iso:country":"US",
    "sg:address":"218 E Pine St",
    "sg:city":"Bourbon",
    "sg:classifiers":[
        {
            "category":"Professional",
            "subcategory":"Business Services",
            "type":"Services"
        },
        {
            "category":"Government",
            "subcategory":"Post Office",
            "type":"Public Place"
        }
    ],
    "sg:phone":"+1 573 732 4600",
    "sg:postcode":"65441",
    "sg:province":"MO",
    "sg:tags":[
        "mail",
        "shipping"
    ],
    "sg:website":"http://www.usps.com",
    "wof:name":"USPS - United States Post Office - Bourbon",
    "wof:placetype":"venue"
},
  "geometry": {"coordinates":[-91.24632699999999,38.152621],"type":"Point"}
}