{
  "type": "Feature",
  "properties": {
    "iso:country":"US",
    "sg:address":"11805 E 76 Ter",
    "sg:city":"Kansas City",
    "sg:classifiers":[
        {
            "category":"Professional",
            "subcategory":"Printing & Photocopies",
            "type":"Services"
        }
    ],
    "sg:phone":"+1 816 356 5341",
    "sg:postcode":"64138",
    "sg:province":"MO",
    "sg:tags":[
        "photocopying"
    ],
    "wof:name":"Copymed Inc",
    "wof:placetype":"venue"
},
  "geometry": {"coordinates":[-94.442826,38.98358],"type":"Point"}
}