{
  "type": "Feature",
  "properties": {
    "iso:country":"US",
    "sg:address":"501 W Central Ave",
    "sg:city":"Carthage",
    "sg:classifiers":[
        {
            "category":"Retail",
            "subcategory":"Auto Rental",
            "type":"Services"
        }
    ],
    "sg:phone":"+1 417 358 3276",
    "sg:postcode":"64836",
    "sg:province":"MO",
    "sg:tags":[
        "transportation"
    ],
    "wof:name":"Ryder",
    "wof:placetype":"venue"
},
  "geometry": {"coordinates":[-94.31732599999999,37.178763],"type":"Point"}
}