{
  "type": "Feature",
  "properties": {
    "iso:country":"US",
    "sg:address":"1263 Cypress Point Dr",
    "sg:city":"O Fallon",
    "sg:classifiers":[
        {
            "category":"Wholesale",
            "subcategory":"Office Equipment",
            "type":"Manufacturing & Wholesale Goods"
        }
    ],
    "sg:phone":"+1 636 240 0596",
    "sg:postcode":"63366",
    "sg:province":"MO",
    "wof:name":"Fmbs of MO",
    "wof:placetype":"venue"
},
  "geometry": {"coordinates":[-90.720506,38.791146],"type":"Point"}
}