{
  "type": "Feature",
  "properties": {
    "iso:country":"US",
    "sg:address":"11 Hill Side Ct",
    "sg:city":"Wentzville",
    "sg:classifiers":[
        {
            "category":"Shopping",
            "subcategory":"Clothing, Apparel, & Fashions",
            "type":"Retail Goods"
        }
    ],
    "sg:phone":"+1 636 327 5095",
    "sg:postcode":"63385",
    "sg:province":"MO",
    "wof:name":"The Square Dance Caller",
    "wof:placetype":"venue"
},
  "geometry": {"coordinates":[-90.8094,38.851717],"type":"Point"}
}