{
  "type": "Feature",
  "properties": {
    "iso:country":"US",
    "sg:address":"2019 S Main St",
    "sg:city":"Higginsville",
    "sg:classifiers":[
        {
            "category":"Wholesale",
            "subcategory":"Computers",
            "type":"Manufacturing & Wholesale Goods"
        },
        {
            "category":"Professional",
            "subcategory":"Computer Services",
            "type":"Services"
        }
    ],
    "sg:phone":"+1 660 584 5540",
    "sg:postcode":"64037",
    "sg:province":"MO",
    "sg:tags":[
        "repair",
        "internet",
        "technical",
        "assistance",
        "isp",
        "provider",
        "equipment",
        "equipment-service",
        "support"
    ],
    "sg:website":"http://www.tech-medics.com",
    "wof:name":"Tech Medics",
    "wof:placetype":"venue"
},
  "geometry": {"coordinates":[-93.717147,39.073968],"type":"Point"}
}