{
  "type": "Feature",
  "properties": {
    "iso:country":"US",
    "sg:address":"218 Delaware St",
    "sg:city":"Kansas City",
    "sg:classifiers":[
        {
            "category":"Professional",
            "subcategory":"Management & Consulting",
            "type":"Services"
        }
    ],
    "sg:phone":"+1 816 283 8300",
    "sg:postcode":"64105",
    "sg:province":"MO",
    "sg:tags":[
        "marketing",
        "consultant"
    ],
    "wof:name":"Puente Marketing Comm LLC",
    "wof:placetype":"venue"
},
  "geometry": {"coordinates":[-94.585379,39.111994],"type":"Point"}
}