{
  "type": "Feature",
  "properties": {
    "iso:country":"US",
    "sg:address":"219 N Mullen Rd",
    "sg:city":"Belton",
    "sg:classifiers":[
        {
            "category":"Autos & Motor Vehicles",
            "subcategory":"Fuel & Gas Station",
            "type":"Retail Goods"
        },
        {
            "category":"Autos & Motor Vehicles",
            "subcategory":"Auto Supplies",
            "type":"Retail Goods"
        },
        {
            "category":"Retail",
            "subcategory":"Auto Repair",
            "type":"Services"
        }
    ],
    "sg:phone":"+1 816 322 6878",
    "sg:postcode":"64012",
    "sg:province":"MO",
    "sg:tags":[
        "wheel",
        "tire",
        "automobile",
        "servicing-automotive",
        "brake",
        "axle",
        "alignment-frame",
        "inspection"
    ],
    "sg:website":"http://www.proalignmentandtire.com",
    "wof:name":"Pro Alignment & Tire Inc",
    "wof:placetype":"venue"
},
  "geometry": {"coordinates":[-94.512085,38.816273],"type":"Point"}
}