{
  "type": "Feature",
  "properties": {
    "iso:country":"US",
    "sg:address":"4457 Gravois Ave.",
    "sg:city":"St. Louis",
    "sg:classifiers":[
        {
            "category":"Bars & Pubs",
            "type":"Food & Drink"
        },
        {
            "category":"Restaurant",
            "type":"Food & Drink"
        }
    ],
    "sg:phone":"+1 314 457 1428",
    "sg:postcode":"63116",
    "sg:province":"MO",
    "wof:name":"Taft Street Restaurant and Bar",
    "wof:placetype":"venue"
},
  "geometry": {"coordinates":[-90.262001,38.585602],"type":"Point"}
}