{
  "type": "Feature",
  "properties": {
    "iso:country":"US",
    "sg:address":"2 Oak Knoll Park",
    "sg:city":"Saint Louis",
    "sg:classifiers":[
        {
            "category":"Arts & Performance",
            "subcategory":"Art Gallery",
            "type":"Entertainment"
        },
        {
            "category":"Organizations",
            "subcategory":"Non-profit Organization",
            "type":"Services"
        }
    ],
    "sg:phone":"+1 314 727 6266",
    "sg:postcode":"63105",
    "sg:province":"MO",
    "sg:tags":[
        "service/non-profit",
        "community"
    ],
    "sg:website":"www.stlouisartistsguild.org",
    "wof:name":"St. Louis Artists' Guild",
    "wof:placetype":"venue"
},
  "geometry": {"coordinates":[-90.31788299999999,38.63826],"type":"Point"}
}