{
  "type": "Feature",
  "properties": {
    "iso:country":"US",
    "sg:address":"5555 Saint Louis Mills Blvd",
    "sg:city":"Hazelwood",
    "sg:classifiers":[
        {
            "category":"Restaurant",
            "type":"Food & Drink"
        }
    ],
    "sg:menulink":"http://www.allmenus.com/mo/northwest/40829-panda-express/menu/",
    "sg:phone":"+1 314 227 5318",
    "sg:postcode":"63042",
    "sg:province":"MO",
    "sg:tags":[
        "asian",
        "chinese"
    ],
    "wof:name":"Panda Express",
    "wof:placetype":"venue"
},
  "geometry": {"coordinates":[-90.415548,38.786097],"type":"Point"}
}