{
  "type": "Feature",
  "properties": {
    "addr:full":"301 W High St Jefferson City MO 65101",
    "addr:housenumber":"301",
    "addr:postcode":"65101",
    "addr:street":"W High St",
    "iso:country":"US",
    "sg:address":"301 W High St",
    "sg:city":"Jefferson City",
    "sg:classifiers":[
        {
            "category":"Restaurant",
            "type":"Food & Drink"
        }
    ],
    "sg:phone":"+1 573 636 5411",
    "sg:postcode":"65101",
    "sg:province":"MO",
    "sg:tags":[
        "cafeteria"
    ],
    "wof:name":"Sidney's",
    "wof:placetype":"venue"
},
  "geometry": {"coordinates":[-92.176333,38.579815],"type":"Point"}
}