{
  "type": "Feature",
  "properties": {
    "iso:country":"US",
    "sg:address":"14559 Old 79",
    "sg:city":"New London",
    "sg:classifiers":[
        {
            "category":"Real Estate",
            "subcategory":"Real Estate Operator",
            "type":"Services"
        }
    ],
    "sg:phone":"+1 573 221 8527",
    "sg:postcode":"63459",
    "sg:province":"MO",
    "sg:tags":[
        "property",
        "lessor"
    ],
    "wof:name":"H Parham",
    "wof:placetype":"venue"
},
  "geometry": {"coordinates":[-91.339078,39.632371],"type":"Point"}
}