{
  "type": "Feature",
  "properties": {
    "iso:country":"US",
    "sg:address":"503 Osage Rd",
    "sg:city":"Willard",
    "sg:classifiers":[
        {
            "category":"Building & Trades",
            "subcategory":"Construction",
            "type":"Services"
        }
    ],
    "sg:phone":"+1 417 766 9068",
    "sg:postcode":"65781",
    "sg:province":"MO",
    "sg:tags":[
        "wallcoverings-installation",
        "wallpaper",
        "painting",
        "contractor"
    ],
    "wof:name":"Dc Painting",
    "wof:placetype":"venue"
},
  "geometry": {"coordinates":[-93.414447,37.286829],"type":"Point"}
}