{
  "type": "Feature",
  "properties": {
    "iso:country":"US",
    "sg:address":"7000 State Highway 13",
    "sg:city":"Lampe",
    "sg:classifiers":[
        {
            "category":"Travel",
            "subcategory":"Hotels & Motels",
            "type":"Entertainment"
        }
    ],
    "sg:phone":"+1 417 779 4345",
    "sg:postcode":"65681",
    "sg:province":"MO",
    "wof:name":"Hallelujah Resort Motel",
    "wof:placetype":"venue"
},
  "geometry": {"coordinates":[-93.428551,36.595081],"type":"Point"}
}