{
  "type": "Feature",
  "properties": {
    "iso:country":"US",
    "sg:address":"419 Riverside St",
    "sg:city":"Hannibal",
    "sg:classifiers":[
        {
            "category":"Retail",
            "subcategory":"Repair Shop",
            "type":"Services"
        }
    ],
    "sg:phone":"+1 573 221 1286",
    "sg:postcode":"63401",
    "sg:province":"MO",
    "sg:tags":[
        "appliance"
    ],
    "wof:name":"Larry's Household Refrig",
    "wof:placetype":"venue"
},
  "geometry": {"coordinates":[-91.349087,39.701909],"type":"Point"}
}