{
  "type": "Feature",
  "properties": {
    "iso:country":"US",
    "sg:address":"12208 Missouri Bottom Rd",
    "sg:city":"Hazelwood",
    "sg:classifiers":[
        {
            "category":"Retail",
            "subcategory":"Auto Rental",
            "type":"Services"
        },
        {
            "category":"Local Transit",
            "type":"Transportation"
        }
    ],
    "sg:phone":"+1 314 731 0505",
    "sg:postcode":"63042",
    "sg:province":"MO",
    "sg:tags":[
        "shuttle",
        "limousine"
    ],
    "wof:name":"Top Limousines",
    "wof:placetype":"venue"
},
  "geometry": {"coordinates":[-90.39646,38.770402],"type":"Point"}
}