{
  "type": "Feature",
  "properties": {
    "iso:country":"US",
    "sg:address":"11640 Forest Lake Dr",
    "sg:city":"Rolla",
    "sg:classifiers":[
        {
            "category":"Shopping",
            "subcategory":"Hobbies, Toys, & Games",
            "type":"Retail Goods"
        }
    ],
    "sg:phone":"+1 573 364 7117",
    "sg:postcode":"65401",
    "sg:province":"MO",
    "wof:name":"Oaky Doaky Inc",
    "wof:placetype":"venue"
},
  "geometry": {"coordinates":[-91.71378199999999,37.9689],"type":"Point"}
}