{
  "type": "Feature",
  "properties": {
    "iso:country":"US",
    "sg:address":"15 Quail Ridge Dr",
    "sg:city":"Joplin",
    "sg:classifiers":[
        {
            "category":"Banks & Credit Unions",
            "subcategory":"Investment Brokerage",
            "type":"Services"
        },
        {
            "category":"Banks & Credit Unions",
            "subcategory":"Financial Services",
            "type":"Services"
        }
    ],
    "sg:phone":"+1 417 626 2234",
    "sg:postcode":"64804",
    "sg:province":"MO",
    "sg:tags":[
        "advisory",
        "planner"
    ],
    "wof:name":"J And Investments",
    "wof:placetype":"venue"
},
  "geometry": {"coordinates":[-94.48475999999999,37.025372],"type":"Point"}
}