{
  "type": "Feature",
  "properties": {
    "iso:country":"US",
    "sg:address":"808 N Elm Ave",
    "sg:city":"Saint Louis",
    "sg:classifiers":[
        {
            "category":"Organizations",
            "subcategory":"Non-profit Organization",
            "type":"Services"
        }
    ],
    "sg:phone":"+1 314 968 8123",
    "sg:postcode":"63119",
    "sg:province":"MO",
    "sg:tags":[
        "social"
    ],
    "wof:name":"N Webster Neighborhood Ctr",
    "wof:placetype":"venue"
},
  "geometry": {"coordinates":[-90.355582,38.606559],"type":"Point"}
}