{
  "type": "Feature",
  "properties": {
    "iso:country":"US",
    "sg:address":"1517 Union Ave Ste A",
    "sg:city":"Moberly",
    "sg:classifiers":[
        {
            "category":"Health Services",
            "subcategory":"Doctor",
            "type":"Services"
        },
        {
            "category":"Health Services",
            "subcategory":"Clinic",
            "type":"Services"
        }
    ],
    "sg:phone":"+1 660 263 7201",
    "sg:postcode":"65270",
    "sg:province":"MO",
    "sg:tags":[
        "physician",
        "family",
        "practice",
        "surgeons",
        "osteopathic",
        "medicine"
    ],
    "wof:name":"Bragg Thomas A DO",
    "wof:placetype":"venue"
},
  "geometry": {"coordinates":[-92.415568,39.423871],"type":"Point"}
}