{
  "type": "Feature",
  "properties": {
    "iso:country":"US",
    "sg:address":"1612 W Business US Highway 60",
    "sg:city":"Dexter",
    "sg:classifiers":[
        {
            "category":"Restaurant",
            "type":"Food & Drink"
        }
    ],
    "sg:phone":"+1 573 624 8662",
    "sg:postcode":"63841",
    "sg:province":"MO",
    "sg:tags":[
        "mexican"
    ],
    "wof:name":"Los Portales Mexican Restaurant",
    "wof:placetype":"venue"
},
  "geometry": {"coordinates":[-89.98484000000001,36.803681],"type":"Point"}
}