{
  "type": "Feature",
  "properties": {
    "iso:country":"US",
    "sg:address":"2105 Burlington St",
    "sg:city":"Kansas City",
    "sg:classifiers":[
        {
            "category":"Shopping",
            "type":"Retail Goods"
        }
    ],
    "sg:phone":"+1 816 421 4848",
    "sg:postcode":"64116",
    "sg:province":"MO",
    "sg:tags":[
        "art",
        "gallery",
        "dealer"
    ],
    "wof:name":"Corporate Art Svc",
    "wof:placetype":"venue"
},
  "geometry": {"coordinates":[-94.580186,39.145138],"type":"Point"}
}