{
  "type": "Feature",
  "properties": {
    "iso:country":"US",
    "sg:address":"13208 US Hwy 40",
    "sg:city":"Independence",
    "sg:classifiers":[
        {
            "category":"Wholesale",
            "subcategory":"Auto Parts",
            "type":"Manufacturing & Wholesale Goods"
        }
    ],
    "sg:phone":"+1 816 373 8789",
    "sg:postcode":"64055",
    "sg:province":"MO",
    "sg:tags":[
        "truck",
        "accessory"
    ],
    "sg:website":"www.chuxtrux.com",
    "wof:name":"Chuck's Trucks",
    "wof:placetype":"venue"
},
  "geometry": {"coordinates":[-94.422692,39.035986],"type":"Point"}
}