{
  "type": "Feature",
  "properties": {
    "iso:country":"US",
    "sg:address":"2345 W Cynthia St",
    "sg:city":"Springfield",
    "sg:classifiers":[
        {
            "category":"Freight",
            "type":"Transportation"
        }
    ],
    "sg:phone":"+1 417 886 2007",
    "sg:postcode":"65810",
    "sg:province":"MO",
    "sg:tags":[
        "operator",
        "trucking"
    ],
    "wof:name":"Jones Auto Transport",
    "wof:placetype":"venue"
},
  "geometry": {"coordinates":[-93.326009,37.127037],"type":"Point"}
}