{
  "type": "Feature",
  "properties": {
    "iso:country":"US",
    "sg:address":"1201 Oakmont Dr",
    "sg:city":"Joplin",
    "sg:classifiers":[
        {
            "category":"Farming",
            "subcategory":"Livestock Farm",
            "type":"Manufacturing & Wholesale Goods"
        }
    ],
    "sg:phone":"+1 417 782 0144",
    "sg:postcode":"64804",
    "sg:province":"MO",
    "sg:tags":[
        "animal",
        "general"
    ],
    "wof:name":"Whitetail Ridge Ranch",
    "wof:placetype":"venue"
},
  "geometry": {"coordinates":[-94.53176000000001,37.045219],"type":"Point"}
}