{
  "type": "Feature",
  "properties": {
    "addr:full":"202 Commerce Dr Cuba MO 65453",
    "addr:housenumber":"202",
    "addr:postcode":"65453",
    "addr:street":"Commerce Dr",
    "iso:country":"US",
    "sg:address":"202 Commerce Dr",
    "sg:city":"Cuba",
    "sg:classifiers":[
        {
            "category":"Wholesale",
            "subcategory":"Electrical",
            "type":"Manufacturing & Wholesale Goods"
        },
        {
            "category":"Manufacturing",
            "subcategory":"Tools & Machinery",
            "type":"Manufacturing & Wholesale Goods"
        }
    ],
    "sg:phone":"+1 573 885 4866",
    "sg:postcode":"65453",
    "sg:province":"MO",
    "sg:tags":[
        "control",
        "equipment"
    ],
    "wof:name":"Johnson Controls Inc",
    "wof:placetype":"venue"
},
  "geometry": {"coordinates":[-91.396047,38.055002],"type":"Point"}
}