{
  "type": "Feature",
  "properties": {
    "iso:country":"US",
    "sg:address":"2520 Southwest Blvd",
    "sg:city":"Sedalia",
    "sg:classifiers":[
        {
            "category":"Autos & Motor Vehicles",
            "subcategory":"Automobile Sales",
            "type":"Retail Goods"
        }
    ],
    "sg:phone":"+1 660 826 7863",
    "sg:postcode":"65301",
    "sg:province":"MO",
    "sg:tags":[
        "dealers-used",
        "used",
        "cars-wholesale",
        "car"
    ],
    "wof:name":"Gill Campbell Used Cars",
    "wof:placetype":"venue"
},
  "geometry": {"coordinates":[-93.257745,38.689186],"type":"Point"}
}