{
  "type": "Feature",
  "properties": {
    "iso:country":"US",
    "sg:address":"614 Autumn Creek Dr",
    "sg:city":"Wentzville",
    "sg:classifiers":[
        {
            "category":"Manufacturing",
            "subcategory":"Buildings",
            "type":"Manufacturing & Wholesale Goods"
        },
        {
            "category":"Home & Garden",
            "subcategory":"Building Materials",
            "type":"Retail Goods"
        },
        {
            "category":"Building & Trades",
            "subcategory":"Construction",
            "type":"Services"
        }
    ],
    "sg:phone":"+1 636 887 1571",
    "sg:postcode":"63385",
    "sg:province":"MO",
    "sg:tags":[
        "builder",
        "improvement",
        "handyman",
        "carpenter",
        "contractor"
    ],
    "sg:website":"http://www.rent-a-carpenter.com",
    "wof:name":"Rent-A-Carpenter",
    "wof:placetype":"venue"
},
  "geometry": {"coordinates":[-90.899529,38.835481],"type":"Point"}
}