{
  "type": "Feature",
  "properties": {
    "iso:country":"US",
    "sg:address":"318 Dusty Rd",
    "sg:city":"Sparta",
    "sg:classifiers":[
        {
            "category":"Building & Trades",
            "subcategory":"Construction",
            "type":"Services"
        }
    ],
    "sg:phone":"+1 417 634 5207",
    "sg:postcode":"65753",
    "sg:province":"MO",
    "sg:tags":[
        "home",
        "residential",
        "improvement"
    ],
    "wof:name":"Bill's Home Maintenance Repair",
    "wof:placetype":"venue"
},
  "geometry": {"coordinates":[-93.05977799999999,36.98305],"type":"Point"}
}