{
  "type": "Feature",
  "properties": {
    "iso:country":"US",
    "sg:address":"8835 Greenbrook Dr",
    "sg:city":"Saint Louis",
    "sg:classifiers":[
        {
            "category":"Building & Trades",
            "subcategory":"Landscaping Services",
            "type":"Services"
        }
    ],
    "sg:phone":"+1 314 869 5755",
    "sg:postcode":"63136",
    "sg:province":"MO",
    "wof:name":"Divine Cuts Lawn Service",
    "wof:placetype":"venue"
},
  "geometry": {"coordinates":[-90.253512,38.723223],"type":"Point"}
}