{
  "type": "Feature",
  "properties": {
    "iso:country":"US",
    "sg:address":"701 Market St",
    "sg:city":"St Louis",
    "sg:classifiers":[
        {
            "category":"Professional",
            "subcategory":"Lawyer & Legal Services",
            "type":"Services"
        }
    ],
    "sg:phone":"+1 314 621 4002",
    "sg:postcode":"63101",
    "sg:province":"MO",
    "sg:tags":[
        "attorney"
    ],
    "wof:name":"Swedlow & King",
    "wof:placetype":"venue"
},
  "geometry": {"coordinates":[-90.193308,38.626232],"type":"Point"}
}