{
  "type": "Feature",
  "properties": {
    "iso:country":"US",
    "sg:address":"1448 Hodiamont Ave",
    "sg:city":"St Louis",
    "sg:classifiers":[
        {
            "category":"Organizations",
            "subcategory":"Religious Organization",
            "type":"Services"
        }
    ],
    "sg:phone":"+1 314 261 3766",
    "sg:postcode":"63112",
    "sg:province":"MO",
    "sg:tags":[
        "church"
    ],
    "wof:name":"Bostick Temple Church Of God",
    "wof:placetype":"venue"
},
  "geometry": {"coordinates":[-90.28668999999999,38.673172],"type":"Point"}
}