{
  "type": "Feature",
  "properties": {
    "iso:country":"US",
    "sg:address":"605 W Main St",
    "sg:city":"Greenwood",
    "sg:classifiers":[
        {
            "category":"Home & Garden",
            "subcategory":"Home Furnishings",
            "type":"Retail Goods"
        }
    ],
    "sg:phone":"+1 816 537 4420",
    "sg:postcode":"64034",
    "sg:province":"MO",
    "sg:tags":[
        "shop",
        "gift"
    ],
    "wof:name":"Neat Ideas LTD",
    "wof:placetype":"venue"
},
  "geometry": {"coordinates":[-94.342642,38.851343],"type":"Point"}
}