{
  "type": "Feature",
  "properties": {
    "iso:country":"US",
    "sg:address":"201 Elm St",
    "sg:city":"Bunceton",
    "sg:classifiers":[
        {
            "category":"Personal",
            "subcategory":"Beauty Salon",
            "type":"Services"
        }
    ],
    "sg:phone":"+1 660 427 5529",
    "sg:postcode":"65237",
    "sg:province":"MO",
    "wof:name":"Debbie's Snip & Clip",
    "wof:placetype":"venue"
},
  "geometry": {"coordinates":[-92.79934799999999,38.790169],"type":"Point"}
}