{
  "type": "Feature",
  "properties": {
    "iso:country":"US",
    "sg:address":"661 Jeffco Blvd",
    "sg:city":"Arnold",
    "sg:classifiers":[
        {
            "category":"Building & Trades",
            "subcategory":"Equipment Rental",
            "type":"Services"
        }
    ],
    "sg:phone":"+1 636 296 7009",
    "sg:postcode":"63010",
    "sg:province":"MO",
    "wof:name":"HFC",
    "wof:placetype":"venue"
},
  "geometry": {"coordinates":[-90.365622,38.450755],"type":"Point"}
}