{
  "type": "Feature",
  "properties": {
    "iso:country":"US",
    "sg:address":"1645 N Glenstone Ave",
    "sg:city":"Springfield",
    "sg:classifiers":[
        {
            "category":"Restaurant",
            "type":"Food & Drink"
        }
    ],
    "sg:phone":"+1 417 866 3382",
    "sg:postcode":"65803",
    "sg:province":"MO",
    "sg:tags":[
        "asian",
        "chinese",
        "pan"
    ],
    "sg:website":"http://hkirestaurant.com",
    "wof:name":"Hong Kong Inn",
    "wof:placetype":"venue"
},
  "geometry": {"coordinates":[-93.261353,37.228121],"type":"Point"}
}