{
  "type": "Feature",
  "properties": {
    "iso:country":"US",
    "sg:address":"4 Industrial Dr",
    "sg:city":"St James",
    "sg:classifiers":[
        {
            "category":"Government",
            "subcategory":"Office",
            "type":"Public Place"
        }
    ],
    "sg:phone":"+1 573 265 4200",
    "sg:postcode":"65565",
    "sg:province":"MO",
    "sg:tags":[
        "county",
        "housing",
        "agency"
    ],
    "wof:name":"Phelps County Pha",
    "wof:placetype":"venue"
},
  "geometry": {"coordinates":[-91.341511,37.971859],"type":"Point"}
}