{
  "type": "Feature",
  "properties": {
    "iso:country":"US",
    "sg:address":"713 S 3rd St",
    "sg:city":"Odessa",
    "sg:classifiers":[
        {
            "category":"Education",
            "subcategory":"School",
            "type":"Public Place"
        }
    ],
    "sg:phone":"+1 816 633 5533",
    "sg:postcode":"64076",
    "sg:province":"MO",
    "sg:tags":[
        "high"
    ],
    "wof:name":"Odessa High School",
    "wof:placetype":"venue"
},
  "geometry": {"coordinates":[-93.956239,38.989258],"type":"Point"}
}