{
  "type": "Feature",
  "properties": {
    "iso:country":"US",
    "sg:address":"2108 Macklind Ave",
    "sg:city":"Saint Louis",
    "sg:classifiers":[
        {
            "category":"Social Services",
            "subcategory":"Child Care",
            "type":"Services"
        }
    ],
    "sg:phone":"+1 314 771 2224",
    "sg:postcode":"63110",
    "sg:province":"MO",
    "sg:tags":[
        "kindergarten",
        "academic",
        "school",
        "nursery",
        "elementary"
    ],
    "wof:name":"Sacred Heart Villa",
    "wof:placetype":"venue"
},
  "geometry": {"coordinates":[-90.277298,38.616199],"type":"Point"}
}