{
  "type": "Feature",
  "properties": {
    "iso:country":"US",
    "sg:address":"112 N Main St",
    "sg:city":"Cardwell",
    "sg:classifiers":[
        {
            "category":"Personal",
            "subcategory":"Beauty Salon",
            "type":"Services"
        }
    ],
    "sg:phone":"+1 573 654 3878",
    "sg:postcode":"63829",
    "sg:province":"MO",
    "wof:name":"New Image Beauty Shop",
    "wof:placetype":"venue"
},
  "geometry": {"coordinates":[-90.29328,36.048278],"type":"Point"}
}