{
  "type": "Feature",
  "properties": {
    "iso:country":"US",
    "sg:address":"535 Holshire Way",
    "sg:city":"Ballwin",
    "sg:classifiers":[
        {
            "category":"Professional",
            "subcategory":"Business Services",
            "type":"Services"
        }
    ],
    "sg:phone":"+1 636 394 0869",
    "sg:postcode":"63017",
    "sg:province":"MO",
    "wof:name":"Gateway Residential Inspection",
    "wof:placetype":"venue"
},
  "geometry": {"coordinates":[-90.55238300000001,38.610451],"type":"Point"}
}