{
  "type": "Feature",
  "properties": {
    "addr:full":"101 W Center St Rogersville MO 65742",
    "addr:housenumber":"101",
    "addr:postcode":"65742",
    "addr:street":"W Center St",
    "iso:country":"US",
    "sg:address":"101 W Center St",
    "sg:city":"Rogersville",
    "sg:classifiers":[
        {
            "category":"Organizations",
            "subcategory":"Religious Organization",
            "type":"Services"
        }
    ],
    "sg:phone":"+1 417 753 2926",
    "sg:postcode":"65742",
    "sg:province":"MO",
    "sg:tags":[
        "church"
    ],
    "wof:name":"First Baptist Church",
    "wof:placetype":"venue"
},
  "geometry": {"coordinates":[-93.059091,37.117805],"type":"Point"}
}