{
  "type": "Feature",
  "properties": {
    "iso:country":"US",
    "sg:address":"45 Broadway Village Dr",
    "sg:city":"Columbia",
    "sg:classifiers":[
        {
            "category":"Building & Trades",
            "subcategory":"Construction",
            "type":"Services"
        }
    ],
    "sg:phone":"+1 573 817 0927",
    "sg:postcode":"65201",
    "sg:province":"MO",
    "sg:tags":[
        "repair",
        "handyman",
        "maintenance",
        "home"
    ],
    "wof:name":"Karl Handyman",
    "wof:placetype":"venue"
},
  "geometry": {"coordinates":[-92.30204,38.942558],"type":"Point"}
}