{
  "type": "Feature",
  "properties": {
    "iso:country":"US",
    "sg:address":"748 Stoney Creek Dr",
    "sg:city":"Ballwin",
    "sg:classifiers":[
        {
            "category":"Professional",
            "type":"Services"
        }
    ],
    "sg:phone":"+1 636 230 7495",
    "sg:postcode":"63021",
    "sg:province":"MO",
    "wof:name":"Athletic Enhncment Sltions LLC",
    "wof:placetype":"venue"
},
  "geometry": {"coordinates":[-90.559434,38.584488],"type":"Point"}
}