{
  "type": "Feature",
  "properties": {
    "iso:country":"US",
    "sg:address":"420 Forest Hills Dr",
    "sg:city":"Louisiana",
    "sg:classifiers":[
        {
            "category":"Professional",
            "subcategory":"Lawyer & Legal Services",
            "type":"Services"
        }
    ],
    "sg:phone":"+1 573 754 6878",
    "sg:postcode":"63353",
    "sg:province":"MO",
    "sg:tags":[
        "attorney",
        "practice"
    ],
    "wof:name":"Bradley Law Firm",
    "wof:placetype":"venue"
},
  "geometry": {"coordinates":[-91.067892,39.442068],"type":"Point"}
}