{
  "type": "Feature",
  "properties": {
    "iso:country":"US",
    "sg:address":"75 W Lockwood Ave",
    "sg:city":"St Louis",
    "sg:classifiers":[
        {
            "category":"Professional",
            "subcategory":"Lawyer & Legal Services",
            "type":"Services"
        }
    ],
    "sg:phone":"+1 314 446 0800",
    "sg:postcode":"63119",
    "sg:province":"MO",
    "sg:tags":[
        "attorney"
    ],
    "sg:website":"www.municipalfirm.com",
    "wof:name":"Cunningham Vogel & Rost",
    "wof:placetype":"venue"
},
  "geometry": {"coordinates":[-90.35918700000001,38.593059],"type":"Point"}
}