{
  "type": "Feature",
  "properties": {
    "iso:country":"US",
    "sg:address":"8615 Pardee Ln",
    "sg:city":"Sappington",
    "sg:classifiers":[
        {
            "category":"Banks & Credit Unions",
            "subcategory":"Investment Brokerage",
            "type":"Services"
        }
    ],
    "sg:phone":"+1 314 842 2220",
    "sg:postcode":"63126",
    "sg:province":"MO",
    "sg:tags":[
        "consultant",
        "planning",
        "financial"
    ],
    "wof:name":"Equity Financial Svc",
    "wof:placetype":"venue"
},
  "geometry": {"coordinates":[-90.368788,38.560188],"type":"Point"}
}