{
  "type": "Feature",
  "properties": {
    "iso:country":"US",
    "sg:address":"410 Deer Crossing Dr",
    "sg:city":"Festus",
    "sg:classifiers":[
        {
            "category":"Building & Trades",
            "subcategory":"Plumbing",
            "type":"Services"
        }
    ],
    "sg:phone":"+1 636 933 2468",
    "sg:postcode":"63028",
    "sg:province":"MO",
    "sg:tags":[
        "plumbing",
        "contractor"
    ],
    "wof:name":"A J's Plumbing Inc",
    "wof:placetype":"venue"
},
  "geometry": {"coordinates":[-90.42145600000001,38.227029],"type":"Point"}
}