{
  "type": "Feature",
  "properties": {
    "iso:country":"US",
    "sg:address":"2110 de Soto Ave",
    "sg:city":"St Louis",
    "sg:classifiers":[
        {
            "category":"Wholesale",
            "subcategory":"Groceries",
            "type":"Manufacturing & Wholesale Goods"
        },
        {
            "category":"Wholesale",
            "subcategory":"Meat",
            "type":"Manufacturing & Wholesale Goods"
        }
    ],
    "sg:phone":"+1 314 371 6644",
    "sg:postcode":"63107",
    "sg:province":"MO",
    "sg:tags":[
        "mfg",
        "frozen",
        "packaged",
        "prepared",
        "prod",
        "pack"
    ],
    "wof:name":"Schneemann Fred & Son",
    "wof:placetype":"venue"
},
  "geometry": {"coordinates":[-90.215023,38.672065],"type":"Point"}
}