{
  "type": "Feature",
  "properties": {
    "iso:country":"US",
    "sg:address":"9414 Lewis Ave",
    "sg:city":"Kansas City",
    "sg:classifiers":[
        {
            "category":"Communications",
            "subcategory":"Film & Video Production",
            "type":"Services"
        }
    ],
    "sg:phone":"+1 816 761 0297",
    "sg:postcode":"64138",
    "sg:province":"MO",
    "sg:tags":[
        "motion"
    ],
    "wof:name":"Godspeed Productions",
    "wof:placetype":"venue"
},
  "geometry": {"coordinates":[-94.486216,38.954207],"type":"Point"}
}