{
  "type": "Feature",
  "properties": {
    "iso:country":"US",
    "sg:address":"1825 Lemay Ferry Rd",
    "sg:city":"St Louis",
    "sg:classifiers":[
        {
            "category":"Shopping",
            "type":"Retail Goods"
        }
    ],
    "sg:phone":"+1 314 638 1112",
    "sg:postcode":"63125",
    "sg:province":"MO",
    "sg:tags":[
        "hearing",
        "equipment",
        "supply",
        "impaired"
    ],
    "wof:name":"Hearing System 2000",
    "wof:placetype":"venue"
},
  "geometry": {"coordinates":[-90.295607,38.52584],"type":"Point"}
}