{
  "type": "Feature",
  "properties": {
    "iso:country":"US",
    "sg:address":"503 N Maguire St",
    "sg:city":"Warrensburg",
    "sg:classifiers":[
        {
            "category":"Shopping",
            "subcategory":"Computers & Home Electronics",
            "type":"Retail Goods"
        }
    ],
    "sg:phone":"+1 660 747 1200",
    "sg:postcode":"64093",
    "sg:province":"MO",
    "sg:tags":[
        "equipment",
        "electronic",
        "supply"
    ],
    "wof:name":"Hunt's Electronics",
    "wof:placetype":"venue"
},
  "geometry": {"coordinates":[-93.73555399999999,38.76834],"type":"Point"}
}