{
  "type": "Feature",
  "properties": {
    "iso:country":"US",
    "sg:address":"4312 S Wall Ave",
    "sg:city":"Joplin",
    "sg:classifiers":[
        {
            "category":"Building & Trades",
            "subcategory":"Construction",
            "type":"Services"
        }
    ],
    "sg:phone":"+1 417 627 0604",
    "sg:postcode":"64804",
    "sg:province":"MO",
    "sg:tags":[
        "house"
    ],
    "wof:name":"Tates Remodeling",
    "wof:placetype":"venue"
},
  "geometry": {"coordinates":[-94.518006,37.040878],"type":"Point"}
}