{
  "type": "Feature",
  "properties": {
    "iso:country":"US",
    "sg:address":"7043 Flower Ln",
    "sg:city":"Saint Louis",
    "sg:classifiers":[
        {
            "category":"Building & Trades",
            "subcategory":"Equipment Rental",
            "type":"Services"
        }
    ],
    "sg:phone":"+1 314 846 7919",
    "sg:postcode":"63129",
    "sg:province":"MO",
    "wof:name":"Slushies Unlimited LLC",
    "wof:placetype":"venue"
},
  "geometry": {"coordinates":[-90.32477799999999,38.432691],"type":"Point"}
}