{
  "type": "Feature",
  "properties": {
    "iso:country":"US",
    "sg:address":"3520 S Culpepper Cir",
    "sg:city":"Springfield",
    "sg:classifiers":[
        {
            "category":"Education",
            "subcategory":"School",
            "type":"Public Place"
        }
    ],
    "sg:phone":"+1 417 865 5567",
    "sg:postcode":"65804",
    "sg:province":"MO",
    "sg:tags":[
        "organization",
        "religious"
    ],
    "wof:name":"Springfeld Cthlic Schl Systems",
    "wof:placetype":"venue"
},
  "geometry": {"coordinates":[-93.276573,37.150494],"type":"Point"}
}