{
  "type": "Feature",
  "properties": {
    "iso:country":"US",
    "sg:address":"518 Kraft Rd",
    "sg:city":"Warsaw",
    "sg:classifiers":[
        {
            "category":"Shopping",
            "subcategory":"Musical Instruments",
            "type":"Retail Goods"
        }
    ],
    "sg:phone":"+1 660 438 3115",
    "sg:postcode":"65355",
    "sg:province":"MO",
    "sg:tags":[
        "guitar"
    ],
    "wof:name":"House Of Guitars",
    "wof:placetype":"venue"
},
  "geometry": {"coordinates":[-93.371661,38.239484],"type":"Point"}
}