{
  "type": "Feature",
  "properties": {
    "iso:country":"US",
    "sg:address":"33409 Ivy Bend Rd",
    "sg:city":"Stover",
    "sg:classifiers":[
        {
            "category":"Real Estate",
            "subcategory":"Real Estate Services",
            "type":"Services"
        },
        {
            "category":"Real Estate",
            "subcategory":"Real Estate Agent",
            "type":"Services"
        }
    ],
    "sg:phone":"+1 573 372 6769",
    "sg:postcode":"65078",
    "sg:province":"MO",
    "sg:tags":[
        "buyer",
        "management",
        "broker"
    ],
    "sg:website":"http://www.pambrown.com",
    "wof:name":"Brown Pam Realty",
    "wof:placetype":"venue"
},
  "geometry": {"coordinates":[-93.003479,38.204609],"type":"Point"}
}