{
  "type": "Feature",
  "properties": {
    "iso:country":"US",
    "sg:address":"18787 State Hwy 13",
    "sg:city":"Reeds Spring",
    "sg:classifiers":[
        {
            "category":"Professional",
            "subcategory":"Business Services",
            "type":"Services"
        }
    ],
    "sg:phone":"+1 417 272 9817",
    "sg:postcode":"65737",
    "sg:province":"MO",
    "wof:name":"Regis Corporation",
    "wof:placetype":"venue"
},
  "geometry": {"coordinates":[-93.370501,36.703768],"type":"Point"}
}