{
  "type": "Feature",
  "properties": {
    "iso:country":"US",
    "sg:address":"801 N Morley St",
    "sg:city":"Moberly",
    "sg:classifiers":[
        {
            "category":"Banks & Credit Unions",
            "subcategory":"Bank",
            "type":"Services"
        }
    ],
    "sg:phone":"+1 660 263 6231",
    "sg:postcode":"65270",
    "sg:province":"MO",
    "sg:tags":[
        "savings",
        "commercial",
        "institution",
        "national"
    ],
    "wof:name":"Citizens Bank & Trust",
    "wof:placetype":"venue"
},
  "geometry": {"coordinates":[-92.43325900000001,39.427983],"type":"Point"}
}