{
  "type": "Feature",
  "properties": {
    "iso:country":"US",
    "sg:address":"6602 E 135th St",
    "sg:city":"Grandview",
    "sg:classifiers":[
        {
            "category":"Personal",
            "subcategory":"Beauty Salon",
            "type":"Services"
        }
    ],
    "sg:phone":"+1 816 966 0655",
    "sg:postcode":"64030",
    "sg:province":"MO",
    "sg:tags":[
        "shop"
    ],
    "wof:name":"Nail Salon",
    "wof:placetype":"venue"
},
  "geometry": {"coordinates":[-94.513102,38.878648],"type":"Point"}
}