{
  "type": "Feature",
  "properties": {
    "iso:country":"US",
    "sg:address":"2410 W 76 Country Blvd",
    "sg:city":"Branson",
    "sg:classifiers":[
        {
            "category":"Real Estate",
            "subcategory":"Real Estate Operator",
            "type":"Services"
        }
    ],
    "sg:phone":"+1 417 335 4710",
    "sg:postcode":"65616",
    "sg:province":"MO",
    "sg:tags":[
        "apartment"
    ],
    "wof:name":"Fairfield Communities",
    "wof:placetype":"venue"
},
  "geometry": {"coordinates":[-93.264537,36.641251],"type":"Point"}
}