{
  "type": "Feature",
  "properties": {
    "iso:country":"US",
    "sg:address":"5118 Natural Bridge Ave",
    "sg:city":"St Louis",
    "sg:classifiers":[
        {
            "category":"Professional",
            "subcategory":"Lawyer & Legal Services",
            "type":"Services"
        }
    ],
    "sg:phone":"+1 314 381 6357",
    "sg:postcode":"63115",
    "sg:province":"MO",
    "wof:name":"Northside Legal Ctr",
    "wof:placetype":"venue"
},
  "geometry": {"coordinates":[-90.254756,38.677423],"type":"Point"}
}