{
  "type": "Feature",
  "properties": {
    "iso:country":"US",
    "sg:address":"32 Sanke Rd",
    "sg:city":"Steelville",
    "sg:classifiers":[
        {
            "category":"Professional",
            "subcategory":"Art Services",
            "type":"Services"
        }
    ],
    "sg:phone":"+1 573 775 4217",
    "sg:postcode":"65565",
    "sg:province":"MO",
    "sg:tags":[
        "silk",
        "screen",
        "printing"
    ],
    "wof:name":"Pam's Silkscreening",
    "wof:placetype":"venue"
},
  "geometry": {"coordinates":[-91.33137000000001,37.986434],"type":"Point"}
}