{
  "type": "Feature",
  "properties": {
    "iso:country":"US",
    "sg:address":"2727 McClelland Blvd",
    "sg:city":"Joplin",
    "sg:classifiers":[
        {
            "category":"Health Services",
            "subcategory":"Doctor",
            "type":"Services"
        }
    ],
    "sg:phone":"+1 417 625 2808",
    "sg:postcode":"64804",
    "sg:province":"MO",
    "sg:tags":[
        "medical"
    ],
    "wof:name":"Amy Meoli MD",
    "wof:placetype":"venue"
},
  "geometry": {"coordinates":[-94.532048,37.06109],"type":"Point"}
}