{
  "type": "Feature",
  "properties": {
    "iso:country":"US",
    "sg:address":"902 Highway Oo",
    "sg:city":"Fredericktown",
    "sg:classifiers":[
        {
            "category":"Building & Trades",
            "subcategory":"Landscaping Services",
            "type":"Services"
        }
    ],
    "sg:phone":"+1 573 944 1131",
    "sg:postcode":"63645",
    "sg:province":"MO",
    "sg:tags":[
        "tree"
    ],
    "wof:name":"Cooper And Robbins Tree Serv.",
    "wof:placetype":"venue"
},
  "geometry": {"coordinates":[-90.290894,37.588875],"type":"Point"}
}