{
  "type": "Feature",
  "properties": {
    "iso:country":"US",
    "sg:address":"407 Dickinson Rd",
    "sg:city":"Independence",
    "sg:classifiers":[
        {
            "category":"Wholesale",
            "subcategory":"Vending Machines",
            "type":"Manufacturing & Wholesale Goods"
        }
    ],
    "sg:phone":"+1 816 833 3568",
    "sg:postcode":"64050",
    "sg:province":"MO",
    "sg:tags":[
        "operator"
    ],
    "wof:name":"Quick Snack Vending Inc",
    "wof:placetype":"venue"
},
  "geometry": {"coordinates":[-94.403218,39.104566],"type":"Point"}
}