{
  "type": "Feature",
  "properties": {
    "iso:country":"US",
    "sg:address":"27244 Meadow Rd",
    "sg:city":"Ravenwood",
    "sg:classifiers":[
        {
            "category":"Manufacturing",
            "subcategory":"Food",
            "type":"Manufacturing & Wholesale Goods"
        },
        {
            "category":"Farming",
            "subcategory":"Farm",
            "type":"Manufacturing & Wholesale Goods"
        }
    ],
    "sg:phone":"+1 660 937 2267",
    "sg:postcode":"64479",
    "sg:province":"MO",
    "sg:tags":[
        "corn",
        "product"
    ],
    "wof:name":"John Gallagher Jr",
    "wof:placetype":"venue"
},
  "geometry": {"coordinates":[-94.73771000000001,40.317702],"type":"Point"}
}