{
  "type": "Feature",
  "properties": {
    "iso:country":"US",
    "sg:address":"1620 W 14 St",
    "sg:city":"Kansas City",
    "sg:classifiers":[
        {
            "category":"Autos & Motor Vehicles",
            "subcategory":"Fuel & Gas Station",
            "type":"Retail Goods"
        }
    ],
    "sg:phone":"+1 816 471 8011",
    "sg:postcode":"64102",
    "sg:province":"MO",
    "sg:tags":[
        "oil"
    ],
    "wof:name":"Fisca Oil Co",
    "wof:placetype":"venue"
},
  "geometry": {"coordinates":[-94.60460999999999,39.098075],"type":"Point"}
}