{
  "type": "Feature",
  "properties": {
    "iso:country":"US",
    "sg:address":"428 N Kentucky St",
    "sg:city":"Mexico",
    "sg:classifiers":[
        {
            "category":"Utilities",
            "subcategory":"Cable",
            "type":"Services"
        }
    ],
    "sg:phone":"+1 573 581 6666",
    "sg:postcode":"65265",
    "sg:province":"MO",
    "sg:tags":[
        "television"
    ],
    "wof:name":"TCI Cablevision of MO",
    "wof:placetype":"venue"
},
  "geometry": {"coordinates":[-91.89845800000001,39.175281],"type":"Point"}
}