{
  "type": "Feature",
  "properties": {
    "iso:country":"US",
    "sg:address":"1915 State Hwy 161",
    "sg:city":"Montgomery City",
    "sg:classifiers":[
        {
            "category":"Freight",
            "type":"Transportation"
        }
    ],
    "sg:phone":"+1 573 564 2673",
    "sg:postcode":"63361",
    "sg:province":"MO",
    "sg:tags":[
        "commercial",
        "storage"
    ],
    "wof:name":"Knoepflein & Son's Storage",
    "wof:placetype":"venue"
},
  "geometry": {"coordinates":[-91.53371,38.925575],"type":"Point"}
}