{
  "type": "Feature",
  "properties": {
    "iso:country":"US",
    "sg:address":"38644 W Co Rd Tt",
    "sg:city":"Mc Fall",
    "sg:classifiers":[
        {
            "category":"Retail",
            "subcategory":"Repair Shop",
            "type":"Services"
        }
    ],
    "sg:phone":"+1 660 439 2921",
    "sg:postcode":"64657",
    "sg:province":"MO",
    "sg:tags":[
        "television",
        "radio",
        "sales"
    ],
    "wof:name":"Rouners Joe Radio & TV Service",
    "wof:placetype":"venue"
},
  "geometry": {"coordinates":[-94.160342,40.155045],"type":"Point"}
}