{
  "type": "Feature",
  "properties": {
    "iso:country":"US",
    "sg:address":"107 N Washington St",
    "sg:city":"Mexico",
    "sg:classifiers":[
        {
            "category":"Travel",
            "subcategory":"Travel Agent",
            "type":"Entertainment"
        }
    ],
    "sg:phone":"+1 573 581 8400",
    "sg:postcode":"65265",
    "sg:province":"MO",
    "sg:tags":[
        "agency",
        "bureau"
    ],
    "wof:name":"Capitol Comm",
    "wof:placetype":"venue"
},
  "geometry": {"coordinates":[-91.88369,39.172947],"type":"Point"}
}