{
  "type": "Feature",
  "properties": {
    "iso:country":"US",
    "sg:address":"5431 S Kingshighway Blvd",
    "sg:city":"Saint Louis",
    "sg:classifiers":[
        {
            "category":"Professional",
            "subcategory":"Advertising",
            "type":"Services"
        }
    ],
    "sg:phone":"+1 314 352 0033",
    "sg:postcode":"63109",
    "sg:province":"MO",
    "sg:tags":[
        "mail",
        "commercial",
        "direct"
    ],
    "wof:name":"MC Graphics",
    "wof:placetype":"venue"
},
  "geometry": {"coordinates":[-90.279838,38.579947],"type":"Point"}
}