{
  "type": "Feature",
  "properties": {
    "iso:country":"US",
    "sg:address":"19405 E 28 Ter S",
    "sg:city":"Independence",
    "sg:classifiers":[
        {
            "category":"Shopping",
            "subcategory":"Jewelry",
            "type":"Retail Goods"
        }
    ],
    "sg:phone":"+1 816 795 6645",
    "sg:postcode":"64057",
    "sg:province":"MO",
    "wof:name":"Silver Creations By Kriz",
    "wof:placetype":"venue"
},
  "geometry": {"coordinates":[-94.350195,39.066309],"type":"Point"}
}