{
  "type": "Feature",
  "properties": {
    "iso:country":"US",
    "sg:address":"303 N Market St",
    "sg:city":"Maryville",
    "sg:classifiers":[
        {
            "category":"Government",
            "subcategory":"Court House",
            "type":"Public Place"
        }
    ],
    "sg:phone":"+1 660 582 4221",
    "sg:postcode":"64468",
    "sg:province":"MO",
    "sg:tags":[
        "county"
    ],
    "wof:name":"Nodaway Circuit Court Div II",
    "wof:placetype":"venue"
},
  "geometry": {"coordinates":[-94.871658,40.348766],"type":"Point"}
}