{
  "type": "Feature",
  "properties": {
    "iso:country":"US",
    "sg:address":"1901 Pine St",
    "sg:city":"Saint Louis",
    "sg:classifiers":[
        {
            "category":"Wholesale",
            "subcategory":"Machinery & Supplies",
            "type":"Manufacturing & Wholesale Goods"
        }
    ],
    "sg:phone":"+1 314 231 7120",
    "sg:postcode":"63103",
    "sg:province":"MO",
    "sg:tags":[
        "mfg",
        "shoe",
        "findings",
        "representative"
    ],
    "wof:name":"Hayne-Sunridge",
    "wof:placetype":"venue"
},
  "geometry": {"coordinates":[-90.20866599999999,38.631239],"type":"Point"}
}