{
  "type": "Feature",
  "properties": {
    "iso:country":"US",
    "sg:address":"104 Friendship Dr",
    "sg:city":"Clinton",
    "sg:classifiers":[
        {
            "category":"Professional",
            "subcategory":"Business Services",
            "type":"Services"
        }
    ],
    "sg:phone":"+1 660 885 3725",
    "sg:postcode":"64735",
    "sg:province":"MO",
    "sg:tags":[
        "auction",
        "auctioneer"
    ],
    "wof:name":"Jim Wells Auctioneer",
    "wof:placetype":"venue"
},
  "geometry": {"coordinates":[-93.758277,38.370062],"type":"Point"}
}