{
  "type": "Feature",
  "properties": {
    "iso:country":"US",
    "sg:address":"1424 State Hwy 7",
    "sg:city":"Blue Springs",
    "sg:classifiers":[
        {
            "category":"Food & Beverages",
            "subcategory":"Liquor & Beverages",
            "type":"Retail Goods"
        }
    ],
    "sg:phone":"+1 816 229 3550",
    "sg:postcode":"64014",
    "sg:province":"MO",
    "wof:name":"Joy Liquors",
    "wof:placetype":"venue"
},
  "geometry": {"coordinates":[-94.272909,39.000302],"type":"Point"}
}