{
  "type": "Feature",
  "properties": {
    "iso:country":"US",
    "sg:address":"1448 Jeffco Blvd",
    "sg:city":"Arnold",
    "sg:classifiers":[
        {
            "category":"Retail",
            "subcategory":"Repair Shop",
            "type":"Services"
        }
    ],
    "sg:phone":"+1 636 296 7070",
    "sg:postcode":"63010",
    "sg:province":"MO",
    "sg:tags":[
        "television",
        "radio"
    ],
    "wof:name":"Zepp's Electronic Sales & Svc",
    "wof:placetype":"venue"
},
  "geometry": {"coordinates":[-90.375907,38.434354],"type":"Point"}
}