{
  "type": "Feature",
  "properties": {
    "iso:country":"US",
    "sg:address":"23861 Lumber Loop",
    "sg:city":"Atlanta",
    "sg:classifiers":[
        {
            "category":"Building & Trades",
            "subcategory":"Construction",
            "type":"Services"
        },
        {
            "category":"Building & Trades",
            "subcategory":"Plumbing",
            "type":"Services"
        }
    ],
    "sg:phone":"+1 660 239 4843",
    "sg:postcode":"63530",
    "sg:province":"MO",
    "sg:tags":[
        "concrete",
        "contractor"
    ],
    "wof:name":"Anderson & Sons Concrete Cnstr",
    "wof:placetype":"venue"
},
  "geometry": {"coordinates":[-92.417407,39.839071],"type":"Point"}
}