{
  "type": "Feature",
  "properties": {
    "iso:country":"US",
    "sg:address":"5438 Southfield Center",
    "sg:city":"Saint Louis",
    "sg:classifiers":[
        {
            "category":"Home & Garden",
            "subcategory":"Garden Supply",
            "type":"Retail Goods"
        }
    ],
    "sg:phone":"+1 314 605 4543",
    "sg:postcode":"63123",
    "sg:province":"MO",
    "wof:name":"Wild Bird Center",
    "wof:placetype":"venue"
},
  "geometry": {"coordinates":[-90.35924,38.525934],"type":"Point"}
}