{
  "type": "Feature",
  "properties": {
    "iso:country":"US",
    "sg:address":"8954 Drew Ln",
    "sg:city":"Joplin",
    "sg:classifiers":[
        {
            "category":"Building & Trades",
            "subcategory":"Cleaning & Sanitation",
            "type":"Services"
        }
    ],
    "sg:phone":"+1 417 624 3168",
    "sg:postcode":"64804",
    "sg:province":"MO",
    "sg:tags":[
        "maintenance"
    ],
    "wof:name":"Clean Rite",
    "wof:placetype":"venue"
},
  "geometry": {"coordinates":[-94.48282399999999,36.991492],"type":"Point"}
}