{
  "type": "Feature",
  "properties": {
    "addr:full":"1930 E Kearney St Springfield MO 65803",
    "addr:housenumber":"1930",
    "addr:postcode":"65803",
    "addr:street":"E Kearney St",
    "iso:country":"US",
    "sg:address":"1930 E Kearney St",
    "sg:city":"Springfield",
    "sg:classifiers":[
        {
            "category":"Shopping",
            "subcategory":"Department Store",
            "type":"Retail Goods"
        }
    ],
    "sg:phone":"+1 417 862 6689",
    "sg:postcode":"65803",
    "sg:province":"MO",
    "wof:name":"Kmart",
    "wof:placetype":"venue"
},
  "geometry": {"coordinates":[-93.257389,37.239839],"type":"Point"}
}