{
  "type": "Feature",
  "properties": {
    "iso:country":"US",
    "sg:address":"4689 W Farm Rd 54",
    "sg:city":"Willard",
    "sg:classifiers":[
        {
            "category":"Farming",
            "subcategory":"Farm & Veterinary Services",
            "type":"Manufacturing & Wholesale Goods"
        }
    ],
    "sg:phone":"+1 417 742 0916",
    "sg:postcode":"65781",
    "sg:province":"MO",
    "sg:tags":[
        "livestock",
        "animal"
    ],
    "wof:name":"Sho-ME Embryos",
    "wof:placetype":"venue"
},
  "geometry": {"coordinates":[-93.371387,37.345463],"type":"Point"}
}