{
  "type": "Feature",
  "properties": {
    "iso:country":"US",
    "sg:address":"1701 Wynbrick Dr",
    "sg:city":"Liberty",
    "sg:classifiers":[
        {
            "category":"Personal",
            "type":"Services"
        }
    ],
    "sg:phone":"+1 816 792 4325",
    "sg:postcode":"64068",
    "sg:province":"MO",
    "sg:tags":[
        "therapist",
        "massage"
    ],
    "sg:website":"www.wynbrickhealingarts.com",
    "wof:name":"Wynbrick Healing Arts Ctr",
    "wof:placetype":"venue"
},
  "geometry": {"coordinates":[-94.448052,39.23703],"type":"Point"}
}