{
  "type": "Feature",
  "properties": {
    "iso:country":"US",
    "sg:address":"801 1st St",
    "sg:city":"Glasgow",
    "sg:classifiers":[
        {
            "category":"Government",
            "subcategory":"Office",
            "type":"Public Place"
        }
    ],
    "sg:phone":"+1 660 338 2148",
    "sg:postcode":"65254",
    "sg:province":"MO",
    "sg:tags":[
        "village"
    ],
    "wof:name":"Glasgow Water Plant",
    "wof:placetype":"venue"
},
  "geometry": {"coordinates":[-92.846604,39.228769],"type":"Point"}
}