{
  "type": "Feature",
  "properties": {
    "iso:country":"US",
    "sg:address":"401 E School St",
    "sg:city":"Hamilton",
    "sg:classifiers":[
        {
            "category":"Farming",
            "subcategory":"Livestock Farm",
            "type":"Manufacturing & Wholesale Goods"
        }
    ],
    "sg:phone":"+1 816 583 2232",
    "sg:postcode":"64644",
    "sg:province":"MO",
    "sg:tags":[
        "beef",
        "feedlot",
        "cattle"
    ],
    "wof:name":"Tapp Cattle Inc",
    "wof:placetype":"venue"
},
  "geometry": {"coordinates":[-93.995212,39.7415],"type":"Point"}
}