{
  "type": "Feature",
  "properties": {
    "iso:country":"US",
    "sg:address":"4650 World Parkway Cir",
    "sg:city":"Saint Louis",
    "sg:classifiers":[
        {
            "category":"Building & Trades",
            "subcategory":"Pest Control",
            "type":"Services"
        }
    ],
    "sg:phone":"+1 314 426 7020",
    "sg:postcode":"63134",
    "sg:province":"MO",
    "wof:name":"Orkin Pest Control 818",
    "wof:placetype":"venue"
},
  "geometry": {"coordinates":[-90.334503,38.728152],"type":"Point"}
}