{
  "type": "Feature",
  "properties": {
    "iso:country":"US",
    "sg:address":"510 E 32nd St",
    "sg:city":"Joplin",
    "sg:classifiers":[
        {
            "category":"Professional",
            "subcategory":"Lawyer & Legal Services",
            "type":"Services"
        }
    ],
    "sg:phone":"+1 417 782 0004",
    "sg:postcode":"64804",
    "sg:province":"MO",
    "sg:tags":[
        "attorney",
        "family",
        "divorce",
        "child",
        "law",
        "custody",
        "bankruptcy"
    ],
    "sg:website":"http://nutzlaw.net",
    "wof:name":"Nutz Law Office",
    "wof:placetype":"venue"
},
  "geometry": {"coordinates":[-94.520081,37.05518],"type":"Point"}
}