{
  "type": "Feature",
  "properties": {
    "iso:country":"US",
    "sg:address":"1702 W 45 St",
    "sg:city":"Kansas City",
    "sg:classifiers":[
        {
            "category":"Professional",
            "type":"Services"
        }
    ],
    "sg:phone":"+1 816 753 5944",
    "sg:postcode":"64111",
    "sg:province":"MO",
    "wof:name":"Gallery Namaste",
    "wof:placetype":"venue"
},
  "geometry": {"coordinates":[-94.605695,39.046397],"type":"Point"}
}