{
  "type": "Feature",
  "properties": {
    "iso:country":"US",
    "sg:address":"5024 290th St",
    "sg:city":"Gentry",
    "sg:classifiers":[
        {
            "category":"Farming",
            "subcategory":"Farm",
            "type":"Manufacturing & Wholesale Goods"
        }
    ],
    "sg:phone":"+1 660 448 2292",
    "sg:postcode":"64453",
    "sg:province":"MO",
    "wof:name":"Daryl & Penny Woods",
    "wof:placetype":"venue"
},
  "geometry": {"coordinates":[-94.436504,40.297617],"type":"Point"}
}