{
  "type": "Feature",
  "properties": {
    "iso:country":"US",
    "sg:address":"305 N Central Ave",
    "sg:city":"Monett",
    "sg:classifiers":[
        {
            "category":"Building & Trades",
            "subcategory":"Plumbing",
            "type":"Services"
        }
    ],
    "sg:phone":"+1 417 235 6688",
    "sg:postcode":"65708",
    "sg:province":"MO",
    "sg:tags":[
        "heating",
        "contract",
        "air",
        "electrical",
        "conditioning",
        "plumbing"
    ],
    "wof:name":"Davis & Son Plumbing & Heating",
    "wof:placetype":"venue"
},
  "geometry": {"coordinates":[-93.927542,36.921838],"type":"Point"}
}