{
  "type": "Feature",
  "properties": {
    "iso:country":"US",
    "sg:address":"240 Bon Aire Dr",
    "sg:city":"Florissant",
    "sg:classifiers":[
        {
            "category":"Health Services",
            "subcategory":"Nursing And Care Facility",
            "type":"Services"
        }
    ],
    "sg:phone":"+1 314 569 5634",
    "sg:postcode":"63033",
    "sg:province":"MO",
    "sg:tags":[
        "skilled"
    ],
    "wof:name":"Superior Lawn Home Care",
    "wof:placetype":"venue"
},
  "geometry": {"coordinates":[-90.293601,38.782144],"type":"Point"}
}