{
  "type": "Feature",
  "properties": {
    "iso:country":"US",
    "sg:address":"7610 N Euclid Ave",
    "sg:city":"Gladstone",
    "sg:classifiers":[
        {
            "category":"Real Estate",
            "subcategory":"Real Estate Operator",
            "type":"Services"
        }
    ],
    "sg:phone":"+1 816 436 4851",
    "sg:postcode":"64118",
    "sg:province":"MO",
    "sg:tags":[
        "building",
        "apartment"
    ],
    "wof:name":"Continental Apartments",
    "wof:placetype":"venue"
},
  "geometry": {"coordinates":[-94.555542,39.232387],"type":"Point"}
}