{
  "type": "Feature",
  "properties": {
    "iso:country":"US",
    "sg:address":"4260 Gravois Rd",
    "sg:city":"House Springs",
    "sg:classifiers":[
        {
            "category":"Bus Charters",
            "type":"Transportation"
        }
    ],
    "sg:phone":"+1 636 671 0033",
    "sg:postcode":"63051",
    "sg:province":"MO",
    "sg:tags":[
        "rental"
    ],
    "wof:name":"Durham School Svc",
    "wof:placetype":"venue"
},
  "geometry": {"coordinates":[-90.55785,38.421929],"type":"Point"}
}