{
  "type": "Feature",
  "properties": {
    "iso:country":"US",
    "sg:address":"90 James St",
    "sg:city":"Poplar Bluff",
    "sg:classifiers":[
        {
            "category":"Personal",
            "subcategory":"Beauty Salon",
            "type":"Services"
        }
    ],
    "sg:phone":"+1 573 778 1582",
    "sg:postcode":"63901",
    "sg:province":"MO",
    "sg:tags":[
        "shop"
    ],
    "wof:name":"Kuntry Kreations Bath & Body",
    "wof:placetype":"venue"
},
  "geometry": {"coordinates":[-90.35489699999999,36.769236],"type":"Point"}
}