{
  "type": "Feature",
  "properties": {
    "iso:country":"US",
    "sg:address":"102 W 5th St",
    "sg:city":"Eldon",
    "sg:classifiers":[
        {
            "category":"Professional",
            "type":"Services"
        }
    ],
    "sg:phone":"+1 573 392 8383",
    "sg:postcode":"65026",
    "sg:province":"MO",
    "wof:name":"Penmac Personnel Service Inc",
    "wof:placetype":"venue"
},
  "geometry": {"coordinates":[-92.582303,38.34604],"type":"Point"}
}