{
  "type": "Feature",
  "properties": {
    "iso:country":"US",
    "sg:address":"1335 W Vest St",
    "sg:city":"Marshall",
    "sg:classifiers":[
        {
            "category":"Travel",
            "subcategory":"Hotels & Motels",
            "type":"Entertainment"
        }
    ],
    "sg:phone":"+1 660 886 2326",
    "sg:postcode":"65340",
    "sg:province":"MO",
    "wof:name":"Marshall Lodging",
    "wof:placetype":"venue"
},
  "geometry": {"coordinates":[-93.215237,39.115768],"type":"Point"}
}