{
  "type": "Feature",
  "properties": {
    "iso:country":"US",
    "sg:address":"531 E Sexton St",
    "sg:city":"Harrisburg",
    "sg:classifiers":[
        {
            "category":"Building & Trades",
            "subcategory":"Cleaning & Sanitation",
            "type":"Services"
        }
    ],
    "sg:phone":"+1 573 443 8887",
    "sg:postcode":"65256",
    "sg:province":"MO",
    "sg:tags":[
        "house"
    ],
    "wof:name":"Miracle Maids",
    "wof:placetype":"venue"
},
  "geometry": {"coordinates":[-92.456941,39.141487],"type":"Point"}
}