{
  "type": "Feature",
  "properties": {
    "iso:country":"US",
    "sg:address":"14750 Fairway Ln",
    "sg:city":"Platte City",
    "sg:classifiers":[
        {
            "category":"Sports & Exercise",
            "subcategory":"Golf",
            "type":"Entertainment"
        }
    ],
    "sg:phone":"+1 816 270 2582",
    "sg:postcode":"64079",
    "sg:province":"MO",
    "sg:tags":[
        "course"
    ],
    "wof:name":"Platte County Golf Course",
    "wof:placetype":"venue"
},
  "geometry": {"coordinates":[-94.731264,39.358754],"type":"Point"}
}