{
  "type": "Feature",
  "properties": {
    "iso:country":"US",
    "sg:address":"12724 State Line Rd",
    "sg:city":"Leawood",
    "sg:classifiers":[
        {
            "category":"Social Services",
            "type":"Services"
        }
    ],
    "sg:phone":"+1 913 345 8808",
    "sg:postcode":"64145",
    "sg:province":"MO",
    "sg:tags":[
        "senior",
        "citizen"
    ],
    "sg:website":"www.assisted.com",
    "wof:name":"Alterra Clare Bridge",
    "wof:placetype":"venue"
},
  "geometry": {"coordinates":[-94.608057,38.898492],"type":"Point"}
}