{
  "type": "Feature",
  "properties": {
    "iso:country":"US",
    "sg:address":"5002 Main St",
    "sg:city":"Kansas City",
    "sg:classifiers":[
        {
            "category":"Retail",
            "subcategory":"Veterinary Services",
            "type":"Services"
        }
    ],
    "sg:phone":"+1 816 931 6636",
    "sg:postcode":"64112",
    "sg:province":"MO",
    "wof:name":"Plaza Animal Clinic Inc",
    "wof:placetype":"venue"
},
  "geometry": {"coordinates":[-94.587388,39.03494],"type":"Point"}
}