{
  "type": "Feature",
  "properties": {
    "iso:country":"US",
    "sg:address":"7 Lampkin Ln",
    "sg:city":"Hermann",
    "sg:classifiers":[
        {
            "category":"Building & Trades",
            "subcategory":"Construction",
            "type":"Services"
        }
    ],
    "sg:phone":"+1 573 236 4655",
    "sg:postcode":"65041",
    "sg:province":"MO",
    "sg:tags":[
        "mason",
        "masonry",
        "industrial",
        "contractors-commercial",
        "contractor"
    ],
    "wof:name":"Lampkin Masonry Inc",
    "wof:placetype":"venue"
},
  "geometry": {"coordinates":[-91.515439,38.731041],"type":"Point"}
}