{
  "type": "Feature",
  "properties": {
    "iso:country":"US",
    "sg:address":"7401 Parkdale Ave",
    "sg:city":"Saint Louis",
    "sg:classifiers":[
        {
            "category":"Manufacturing",
            "subcategory":"Glass & Minerals",
            "type":"Manufacturing & Wholesale Goods"
        }
    ],
    "sg:phone":"+1 314 725 5831",
    "sg:postcode":"63105",
    "sg:province":"MO",
    "sg:tags":[
        "metal",
        "fabricated",
        "mfg"
    ],
    "wof:name":"Leigh Butler Designs",
    "wof:placetype":"venue"
},
  "geometry": {"coordinates":[-90.329741,38.64139],"type":"Point"}
}