{
  "type": "Feature",
  "properties": {
    "iso:country":"US",
    "sg:address":"505 Malinmor Dr",
    "sg:city":"Saint Charles",
    "sg:classifiers":[
        {
            "category":"Building & Trades",
            "subcategory":"Construction",
            "type":"Services"
        }
    ],
    "sg:phone":"+1 636 939 4013",
    "sg:postcode":"63304",
    "sg:province":"MO",
    "sg:tags":[
        "contractor",
        "dwelling",
        "carpentry"
    ],
    "wof:name":"Steve Giancola Construction",
    "wof:placetype":"venue"
},
  "geometry": {"coordinates":[-90.63485,38.71245],"type":"Point"}
}