{
  "type": "Feature",
  "properties": {
    "iso:country":"US",
    "sg:address":"3975 NE 63 Ter",
    "sg:city":"Kansas City",
    "sg:classifiers":[
        {
            "category":"Manufacturing",
            "subcategory":"Tools & Machinery",
            "type":"Manufacturing & Wholesale Goods"
        }
    ],
    "sg:phone":"+1 816 584 0088",
    "sg:postcode":"64119",
    "sg:province":"MO",
    "sg:tags":[
        "equipment",
        "motel",
        "hotel",
        "supply"
    ],
    "wof:name":"Allegiant",
    "wof:placetype":"venue"
},
  "geometry": {"coordinates":[-94.53339699999999,39.208554],"type":"Point"}
}