{
  "type": "Feature",
  "properties": {
    "iso:country":"US",
    "sg:address":"7280 Ellington Dr",
    "sg:city":"Saint Charles",
    "sg:classifiers":[
        {
            "category":"Building & Trades",
            "subcategory":"Construction",
            "type":"Services"
        }
    ],
    "sg:phone":"+1 636 939 5510",
    "sg:postcode":"63368",
    "sg:province":"MO",
    "sg:tags":[
        "house"
    ],
    "wof:name":"Hayden Homes Inc",
    "wof:placetype":"venue"
},
  "geometry": {"coordinates":[-90.716787,38.727378],"type":"Point"}
}