{
  "type": "Feature",
  "properties": {
    "iso:country":"US",
    "sg:address":"1267 S Odell Ave",
    "sg:city":"Marshall",
    "sg:classifiers":[
        {
            "category":"Food & Beverages",
            "subcategory":"Groceries & Convenience Stores",
            "type":"Retail Goods"
        }
    ],
    "sg:phone":"+1 660 886 8935",
    "sg:postcode":"65340",
    "sg:province":"MO",
    "sg:tags":[
        "station",
        "gasoline"
    ],
    "wof:name":"Caseys 1240",
    "wof:placetype":"venue"
},
  "geometry": {"coordinates":[-93.19505599999999,39.108304],"type":"Point"}
}