{
  "type": "Feature",
  "properties": {
    "iso:country":"US",
    "sg:address":"10443 State Hwy 5",
    "sg:city":"Camdenton",
    "sg:classifiers":[
        {
            "category":"Food & Beverages",
            "subcategory":"Groceries & Convenience Stores",
            "type":"Retail Goods"
        }
    ],
    "sg:phone":"+1 573 374 4331",
    "sg:postcode":"65020",
    "sg:province":"MO",
    "wof:name":"Joni's General Store",
    "wof:placetype":"venue"
},
  "geometry": {"coordinates":[-92.794552,38.130763],"type":"Point"}
}