{
  "type": "Feature",
  "properties": {
    "iso:country":"US",
    "sg:address":"10406 Odessa Cemetery Rd",
    "sg:city":"Odessa",
    "sg:classifiers":[
        {
            "category":"Organizations",
            "subcategory":"Religious Organization",
            "type":"Services"
        }
    ],
    "sg:phone":"+1 816 633 5711",
    "sg:postcode":"64076",
    "sg:province":"MO",
    "sg:tags":[
        "church"
    ],
    "wof:name":"Rolling Meadows Christn Church",
    "wof:placetype":"venue"
},
  "geometry": {"coordinates":[-93.92470299999999,38.995777],"type":"Point"}
}