{
  "type": "Feature",
  "properties": {
    "iso:country":"US",
    "sg:address":"2902 S Campbell Ave",
    "sg:city":"Springfield",
    "sg:classifiers":[
        {
            "category":"Banks & Credit Unions",
            "subcategory":"Investment Brokerage",
            "type":"Services"
        }
    ],
    "sg:phone":"+1 417 863 7838",
    "sg:postcode":"65807",
    "sg:province":"MO",
    "sg:tags":[
        "security"
    ],
    "wof:name":"Edward Jones Co",
    "wof:placetype":"venue"
},
  "geometry": {"coordinates":[-93.29526199999999,37.16266],"type":"Point"}
}