{
  "type": "Feature",
  "properties": {
    "iso:country":"US",
    "sg:address":"309 S Martin Ave",
    "sg:city":"East Prairie",
    "sg:classifiers":[
        {
            "category":"Organizations",
            "subcategory":"Religious Organization",
            "type":"Services"
        }
    ],
    "sg:phone":"+1 573 649 3427",
    "sg:postcode":"63845",
    "sg:province":"MO",
    "sg:tags":[
        "church"
    ],
    "wof:name":"East Prairie Church Of Christ",
    "wof:placetype":"venue"
},
  "geometry": {"coordinates":[-89.382976,36.774626],"type":"Point"}
}