{
  "type": "Feature",
  "properties": {
    "iso:country":"US",
    "sg:address":"750 W Dallas St",
    "sg:city":"Buffalo",
    "sg:classifiers":[
        {
            "category":"Social Services",
            "type":"Services"
        }
    ],
    "sg:phone":"+1 417 345 1776",
    "sg:postcode":"65622",
    "sg:province":"MO",
    "sg:tags":[
        "individual",
        "family",
        "therapist",
        "marriage",
        "child",
        "counselor"
    ],
    "wof:name":"Bowers Center For Children & Families The",
    "wof:placetype":"venue"
},
  "geometry": {"coordinates":[-93.098772,37.640375],"type":"Point"}
}