{
  "type": "Feature",
  "properties": {
    "iso:country":"US",
    "sg:address":"117 1st St",
    "sg:city":"Kennett",
    "sg:classifiers":[
        {
            "category":"Wholesale",
            "subcategory":"Hardware",
            "type":"Manufacturing & Wholesale Goods"
        },
        {
            "category":"Home & Garden",
            "subcategory":"Garden Supply",
            "type":"Retail Goods"
        },
        {
            "category":"Retail",
            "subcategory":"Repair Shop",
            "type":"Services"
        }
    ],
    "sg:phone":"+1 573 888 5358",
    "sg:postcode":"63857",
    "sg:province":"MO",
    "sg:tags":[
        "renting",
        "lawn",
        "outdoor",
        "power",
        "landscaping",
        "equipment-sales",
        "equipment",
        "saw"
    ],
    "sg:website":"http://www.stihldealer.net/default-dealer-011536.aspx",
    "wof:name":"McDaniel Firestone Store",
    "wof:placetype":"venue"
},
  "geometry": {"coordinates":[-89.969414,36.235889],"type":"Point"}
}