{
  "type": "Feature",
  "properties": {
    "iso:country":"US",
    "sg:address":"614 Lewis St",
    "sg:city":"St Charles",
    "sg:classifiers":[
        {
            "category":"Building & Trades",
            "subcategory":"Construction",
            "type":"Services"
        }
    ],
    "sg:phone":"+1 636 724 1995",
    "sg:postcode":"63301",
    "sg:province":"MO",
    "sg:tags":[
        "concrete",
        "product",
        "asphalt",
        "contractor"
    ],
    "wof:name":"Schnarre Contractors Inc",
    "wof:placetype":"venue"
},
  "geometry": {"coordinates":[-90.487043,38.788504],"type":"Point"}
}