{
  "type": "Feature",
  "properties": {
    "iso:country":"US",
    "sg:address":"1731 N 2nd St",
    "sg:city":"St Charles",
    "sg:classifiers":[
        {
            "category":"Autos & Motor Vehicles",
            "subcategory":"Automobile Sales",
            "type":"Retail Goods"
        }
    ],
    "sg:phone":"+1 636 947 2323",
    "sg:postcode":"63301",
    "sg:province":"MO",
    "sg:tags":[
        "car",
        "dealer"
    ],
    "wof:name":"Mylenbusch Auto Sales",
    "wof:placetype":"venue"
},
  "geometry": {"coordinates":[-90.47580000000001,38.794704],"type":"Point"}
}