{
  "type": "Feature",
  "properties": {
    "iso:country":"US",
    "sg:address":"2623 N Kansas Expy",
    "sg:city":"Springfield",
    "sg:classifiers":[
        {
            "category":"Insurance",
            "subcategory":"Insurance Agent",
            "type":"Services"
        }
    ],
    "sg:phone":"+1 417 862 0018",
    "sg:postcode":"65803",
    "sg:province":"MO",
    "wof:name":"A Bargain Insurance",
    "wof:placetype":"venue"
},
  "geometry": {"coordinates":[-93.31106,37.244038],"type":"Point"}
}