{
  "type": "Feature",
  "properties": {
    "iso:country":"US",
    "sg:address":"1504 Walnut St",
    "sg:city":"Higginsville",
    "sg:classifiers":[
        {
            "category":"Retail",
            "subcategory":"Animal Services",
            "type":"Services"
        }
    ],
    "sg:phone":"+1 660 584 2022",
    "sg:postcode":"64037",
    "sg:province":"MO",
    "wof:name":"K & L Kennel",
    "wof:placetype":"venue"
},
  "geometry": {"coordinates":[-93.7183,39.079034],"type":"Point"}
}