{
  "type": "Feature",
  "properties": {
    "iso:country":"US",
    "sg:address":"127 NE 20th St",
    "sg:city":"Trenton",
    "sg:classifiers":[
        {
            "category":"Farming",
            "subcategory":"Livestock Farm",
            "type":"Manufacturing & Wholesale Goods"
        }
    ],
    "sg:phone":"+1 660 359 6942",
    "sg:postcode":"64683",
    "sg:province":"MO",
    "sg:tags":[
        "real",
        "beef",
        "lessor",
        "cattle",
        "property",
        "feedlot"
    ],
    "wof:name":"Jack Derry",
    "wof:placetype":"venue"
},
  "geometry": {"coordinates":[-93.56965700000001,40.104757],"type":"Point"}
}