{
  "type": "Feature",
  "properties": {
    "iso:country":"US",
    "sg:address":"305 Market St",
    "sg:city":"Hermann",
    "sg:classifiers":[
        {
            "category":"Restaurant",
            "type":"Food & Drink"
        }
    ],
    "sg:menulink":"http://www.allmenus.com/mo/roark/148570-subway/menu/",
    "sg:phone":"+1 573 486 8821",
    "sg:postcode":"65041",
    "sg:province":"MO",
    "sg:tags":[
        "american",
        "sandwich"
    ],
    "wof:name":"Subway",
    "wof:placetype":"venue"
},
  "geometry": {"coordinates":[-91.437828,38.70578],"type":"Point"}
}