{
  "type": "Feature",
  "properties": {
    "iso:country":"US",
    "sg:address":"2235 W Old 66 Blvd",
    "sg:city":"Carthage",
    "sg:classifiers":[
        {
            "category":"Wholesale",
            "subcategory":"Auto Parts",
            "type":"Manufacturing & Wholesale Goods"
        }
    ],
    "sg:phone":"+1 417 358 9876",
    "sg:postcode":"64836",
    "sg:province":"MO",
    "sg:tags":[
        "automobile",
        "rebuilt"
    ],
    "wof:name":"Schrader's Salvage & Wrckr Svc",
    "wof:placetype":"venue"
},
  "geometry": {"coordinates":[-94.349479,37.173435],"type":"Point"}
}