{
  "type": "Feature",
  "properties": {
    "iso:country":"US",
    "sg:address":"123 E Moore St",
    "sg:city":"La Plata",
    "sg:classifiers":[
        {
            "category":"Insurance",
            "subcategory":"Insurance Agent",
            "type":"Services"
        }
    ],
    "sg:phone":"+1 660 332 7421",
    "sg:postcode":"63549",
    "sg:province":"MO",
    "wof:name":"Belfield Insurance & Realty",
    "wof:placetype":"venue"
},
  "geometry": {"coordinates":[-92.491321,40.023478],"type":"Point"}
}