{
  "type": "Feature",
  "properties": {
    "iso:country":"US",
    "sg:address":"801 Madeline Ct",
    "sg:city":"Ballwin",
    "sg:classifiers":[
        {
            "category":"Building & Trades",
            "subcategory":"Construction",
            "type":"Services"
        }
    ],
    "sg:phone":"+1 636 391 0295",
    "sg:postcode":"63011",
    "sg:province":"MO",
    "sg:tags":[
        "hanging",
        "contractor"
    ],
    "wof:name":"Boltas Painting",
    "wof:placetype":"venue"
},
  "geometry": {"coordinates":[-90.50793899999999,38.60648],"type":"Point"}
}