{
  "type": "Feature",
  "properties": {
    "iso:country":"US",
    "sg:address":"30261 Kansas Rd",
    "sg:city":"Marceline",
    "sg:classifiers":[
        {
            "category":"Autos & Motor Vehicles",
            "subcategory":"Motorcycle Sales",
            "type":"Retail Goods"
        }
    ],
    "sg:phone":"+1 660 376 2553",
    "sg:postcode":"64658",
    "sg:province":"MO",
    "sg:tags":[
        "all",
        "terrain"
    ],
    "wof:name":"Little Outdoor Adventures",
    "wof:placetype":"venue"
},
  "geometry": {"coordinates":[-92.989796,39.703159],"type":"Point"}
}