{
  "type": "Feature",
  "properties": {
    "iso:country":"US",
    "sg:address":"308 S County Center Way",
    "sg:city":"Saint Louis",
    "sg:classifiers":[
        {
            "category":"Shopping",
            "subcategory":"Computers & Home Electronics",
            "type":"Retail Goods"
        }
    ],
    "sg:phone":"+1 314 487 9035",
    "sg:postcode":"63129",
    "sg:province":"MO",
    "sg:tags":[
        "game",
        "video",
        "software"
    ],
    "wof:name":"Gamestop",
    "wof:placetype":"venue"
},
  "geometry": {"coordinates":[-90.329674,38.5054],"type":"Point"}
}