{
  "type": "Feature",
  "properties": {
    "iso:country":"US",
    "sg:address":"6314 Brookside Plz",
    "sg:city":"Kansas City",
    "sg:classifiers":[
        {
            "category":"Manufacturing",
            "subcategory":"Printing",
            "type":"Manufacturing & Wholesale Goods"
        }
    ],
    "sg:phone":"+1 816 523 8566",
    "sg:postcode":"64113",
    "sg:province":"MO",
    "sg:tags":[
        "multimedia"
    ],
    "wof:name":"Media Venture Partners",
    "wof:placetype":"venue"
},
  "geometry": {"coordinates":[-94.590807,39.012446],"type":"Point"}
}