{
  "type": "Feature",
  "properties": {
    "iso:country":"US",
    "sg:address":"951 Oakfield Dr",
    "sg:city":"Ballwin",
    "sg:classifiers":[
        {
            "category":"Real Estate",
            "subcategory":"Real Estate Agent",
            "type":"Services"
        }
    ],
    "sg:phone":"+1 636 394 2022",
    "sg:postcode":"63021",
    "sg:province":"MO",
    "sg:tags":[
        "appraiser"
    ],
    "wof:name":"Benchmark Appraisal Svc",
    "wof:placetype":"venue"
},
  "geometry": {"coordinates":[-90.53094400000001,38.573002],"type":"Point"}
}