{
  "type": "Feature",
  "properties": {
    "iso:country":"US",
    "sg:address":"606 Walnut St",
    "sg:city":"Doniphan",
    "sg:classifiers":[
        {
            "category":"Retail",
            "subcategory":"Funeral Services",
            "type":"Services"
        }
    ],
    "sg:phone":"+1 573 996 2121",
    "sg:postcode":"63935",
    "sg:province":"MO",
    "sg:tags":[
        "merchandise"
    ],
    "wof:name":"Edwards Funeral Home Inc",
    "wof:placetype":"venue"
},
  "geometry": {"coordinates":[-90.823916,36.622608],"type":"Point"}
}