{
  "type": "Feature",
  "properties": {
    "iso:country":"US",
    "sg:address":"6505 NW Caney Creek Dr",
    "sg:city":"Kansas City",
    "sg:classifiers":[
        {
            "category":"Organizations",
            "subcategory":"Professional Association",
            "type":"Services"
        }
    ],
    "sg:phone":"+1 816 587 3380",
    "sg:postcode":"64151",
    "sg:province":"MO",
    "wof:name":"University Spirit Of America",
    "wof:placetype":"venue"
},
  "geometry": {"coordinates":[-94.656972,39.2172],"type":"Point"}
}