{
  "type": "Feature",
  "properties": {
    "iso:country":"US",
    "sg:address":"802 Minnesota Ave",
    "sg:city":"Joplin",
    "sg:classifiers":[
        {
            "category":"Retail",
            "subcategory":"Auto Repair",
            "type":"Services"
        }
    ],
    "sg:phone":"+1 417 623 8830",
    "sg:postcode":"64801",
    "sg:province":"MO",
    "sg:tags":[
        "body",
        "automobile",
        "painting",
        "repairing"
    ],
    "wof:name":"Central Auto Body",
    "wof:placetype":"venue"
},
  "geometry": {"coordinates":[-94.505883,37.082525],"type":"Point"}
}