{
  "type": "Feature",
  "properties": {
    "iso:country":"US",
    "sg:address":"720 Medical Park Dr",
    "sg:city":"Mexico",
    "sg:classifiers":[
        {
            "category":"Health Services",
            "subcategory":"Doctor",
            "type":"Services"
        }
    ],
    "sg:phone":"+1 573 581 6831",
    "sg:postcode":"65265",
    "sg:province":"MO",
    "sg:tags":[
        "medical"
    ],
    "wof:name":"Ben Lee Jolly MD",
    "wof:placetype":"venue"
},
  "geometry": {"coordinates":[-91.878349,39.15874],"type":"Point"}
}