{
  "type": "Feature",
  "properties": {
    "iso:country":"US",
    "sg:address":"30 Patmos Ct",
    "sg:city":"St Peters",
    "sg:classifiers":[
        {
            "category":"Manufacturing",
            "subcategory":"Metals",
            "type":"Manufacturing & Wholesale Goods"
        }
    ],
    "sg:phone":"+1 636 928 7288",
    "sg:postcode":"63376",
    "sg:province":"MO",
    "sg:tags":[
        "casting"
    ],
    "wof:name":"Precision Components & Asmbls",
    "wof:placetype":"venue"
},
  "geometry": {"coordinates":[-90.586685,38.801137],"type":"Point"}
}