{
  "type": "Feature",
  "properties": {
    "iso:country":"US",
    "sg:address":"12702 Orley Dr",
    "sg:city":"Florissant",
    "sg:classifiers":[
        {
            "category":"Building & Trades",
            "subcategory":"Plumbing",
            "type":"Services"
        }
    ],
    "sg:phone":"+1 314 653 6909",
    "sg:postcode":"63033",
    "sg:province":"MO",
    "sg:tags":[
        "plumbing",
        "contractor"
    ],
    "wof:name":"Beck Sam Plumbing & Design",
    "wof:placetype":"venue"
},
  "geometry": {"coordinates":[-90.26428199999999,38.797616],"type":"Point"}
}