{
  "type": "Feature",
  "properties": {
    "iso:country":"US",
    "sg:address":"625 Cherry St",
    "sg:city":"Columbia",
    "sg:classifiers":[
        {
            "category":"Professional",
            "subcategory":"Management & Consulting",
            "type":"Services"
        }
    ],
    "sg:phone":"+1 573 499 0722",
    "sg:postcode":"65201",
    "sg:province":"MO",
    "sg:tags":[
        "consultant"
    ],
    "wof:name":"Gridnet International",
    "wof:placetype":"venue"
},
  "geometry": {"coordinates":[-92.330539,38.950534],"type":"Point"}
}