{
  "type": "Feature",
  "properties": {
    "addr:full":"25 S County Center Way Saint Louis MO 63129",
    "addr:housenumber":"25",
    "addr:postcode":"63129",
    "addr:street":"S County Center Way",
    "iso:country":"US",
    "sg:address":"25 S County Center Way",
    "sg:city":"Saint Louis",
    "sg:classifiers":[
        {
            "category":"Shopping",
            "subcategory":"Clothing, Apparel, & Fashions",
            "type":"Retail Goods"
        }
    ],
    "sg:phone":"+1 314 416 0084",
    "sg:postcode":"63129",
    "sg:province":"MO",
    "wof:name":"Toys r US",
    "wof:placetype":"venue"
},
  "geometry": {"coordinates":[-90.32949000000001,38.505311],"type":"Point"}
}