{
  "type": "Feature",
  "properties": {
    "iso:country":"US",
    "sg:address":"8736 Goodfellow Blvd",
    "sg:city":"Saint Louis",
    "sg:classifiers":[
        {
            "category":"Professional",
            "type":"Services"
        }
    ],
    "sg:phone":"+1 314 868 3755",
    "sg:postcode":"63147",
    "sg:province":"MO",
    "wof:name":"T Semirg Inc",
    "wof:placetype":"venue"
},
  "geometry": {"coordinates":[-90.250441,38.718841],"type":"Point"}
}