{
  "type": "Feature",
  "properties": {
    "iso:country":"US",
    "sg:address":"1340 W Battlefield Rd",
    "sg:city":"Springfield",
    "sg:classifiers":[
        {
            "category":"Professional",
            "subcategory":"Management & Consulting",
            "type":"Services"
        }
    ],
    "sg:phone":"+1 417 891 9971",
    "sg:postcode":"65807",
    "sg:province":"MO",
    "sg:tags":[
        "business"
    ],
    "wof:name":"Source Group",
    "wof:placetype":"venue"
},
  "geometry": {"coordinates":[-93.310807,37.160082],"type":"Point"}
}