{
  "type": "Feature",
  "properties": {
    "iso:country":"US",
    "sg:address":"34 Camden Ct SW",
    "sg:city":"Camdenton",
    "sg:phone":"+1 573 346 1399",
    "sg:postcode":"65020",
    "sg:province":"MO",
    "wof:name":"All That Jazz",
    "wof:placetype":"venue"
},
  "geometry": {"coordinates":[-92.7451,38.008358],"type":"Point"}
}