{
  "type": "Feature",
  "properties": {
    "iso:country":"US",
    "sg:address":"301 S Main St",
    "sg:city":"O Fallon",
    "sg:classifiers":[
        {
            "category":"Personal",
            "subcategory":"Tanning Parlor",
            "type":"Services"
        }
    ],
    "sg:phone":"+1 636 978 2071",
    "sg:postcode":"63366",
    "sg:province":"MO",
    "sg:tags":[
        "salon"
    ],
    "wof:name":"Pacific Beach Tanning Studios",
    "wof:placetype":"venue"
},
  "geometry": {"coordinates":[-90.69996999999999,38.80684],"type":"Point"}
}