{
  "type": "Feature",
  "properties": {
    "iso:country":"US",
    "sg:address":"760 NE Anderson Ln",
    "sg:city":"Lees Summit",
    "sg:classifiers":[
        {
            "category":"Banks & Credit Unions",
            "subcategory":"Bank",
            "type":"Services"
        }
    ],
    "sg:phone":"+1 816 348 6925",
    "sg:postcode":"64064",
    "sg:province":"MO",
    "sg:tags":[
        "state",
        "commercial"
    ],
    "wof:name":"Bank of Belton",
    "wof:placetype":"venue"
},
  "geometry": {"coordinates":[-94.36031,39.003364],"type":"Point"}
}