{
  "type": "Feature",
  "properties": {
    "iso:country":"US",
    "sg:address":"1000 S Main St",
    "sg:city":"Salem",
    "sg:classifiers":[
        {
            "category":"Coffee & Tea",
            "type":"Food & Drink"
        },
        {
            "category":"Restaurant",
            "type":"Food & Drink"
        }
    ],
    "sg:phone":"+1 573 729 7944",
    "sg:postcode":"65560",
    "sg:province":"MO",
    "sg:tags":[
        "espresso"
    ],
    "wof:name":"Red Hen Breakfast Cafe",
    "wof:placetype":"venue"
},
  "geometry": {"coordinates":[-91.535629,37.635834],"type":"Point"}
}