{
  "type": "Feature",
  "properties": {
    "iso:country":"US",
    "sg:address":"304 Way Ave",
    "sg:city":"St Louis",
    "sg:classifiers":[
        {
            "category":"Organizations",
            "subcategory":"Religious Organization",
            "type":"Services"
        }
    ],
    "sg:phone":"+1 314 965 6975",
    "sg:postcode":"63122",
    "sg:province":"MO",
    "sg:tags":[
        "monastery",
        "convent"
    ],
    "wof:name":"Sisters Of Mercy",
    "wof:placetype":"venue"
},
  "geometry": {"coordinates":[-90.41301199999999,38.586763],"type":"Point"}
}