{
  "type": "Feature",
  "properties": {
    "iso:country":"US",
    "sg:address":"9965 Watson Rd",
    "sg:city":"St Louis",
    "sg:classifiers":[
        {
            "category":"Retail",
            "subcategory":"Auto Repair",
            "type":"Services"
        }
    ],
    "sg:phone":"+1 314 984 9963",
    "sg:postcode":"63126",
    "sg:province":"MO",
    "sg:tags":[
        "repairing",
        "automobile"
    ],
    "wof:name":"Car-X Auto Svc",
    "wof:placetype":"venue"
},
  "geometry": {"coordinates":[-90.395957,38.556333],"type":"Point"}
}