{
  "type": "Feature",
  "properties": {
    "iso:country":"US",
    "sg:address":"616 SW Jefferson St",
    "sg:city":"Lees Summit",
    "sg:classifiers":[
        {
            "category":"Food & Beverages",
            "subcategory":"Groceries & Convenience Stores",
            "type":"Retail Goods"
        },
        {
            "category":"Autos & Motor Vehicles",
            "subcategory":"Fuel & Gas Station",
            "type":"Retail Goods"
        }
    ],
    "sg:phone":"+1 816 524 3555",
    "sg:postcode":"64063",
    "sg:province":"MO",
    "sg:tags":[
        "station",
        "gasoline"
    ],
    "wof:name":"Traffik Jam Convenience Stores",
    "wof:placetype":"venue"
},
  "geometry": {"coordinates":[-94.378134,38.907681],"type":"Point"}
}