{
  "type": "Feature",
  "properties": {
    "iso:country":"US",
    "sg:address":"5869 Bartmer Ave",
    "sg:city":"Saint Louis",
    "sg:classifiers":[
        {
            "category":"Social Services",
            "subcategory":"Child Care",
            "type":"Services"
        }
    ],
    "sg:phone":"+1 314 361 6104",
    "sg:postcode":"63112",
    "sg:province":"MO",
    "sg:tags":[
        "day"
    ],
    "wof:name":"West Mount Carmel Community Center",
    "wof:placetype":"venue"
},
  "geometry": {"coordinates":[-90.287697,38.663101],"type":"Point"}
}