{
  "type": "Feature",
  "properties": {
    "iso:country":"US",
    "sg:address":"2117 Seven Oaks Dr",
    "sg:city":"Saint Charles",
    "sg:classifiers":[
        {
            "category":"Freight",
            "type":"Transportation"
        }
    ],
    "sg:phone":"+1 314 280 3289",
    "sg:postcode":"63303",
    "sg:province":"MO",
    "sg:tags":[
        "company",
        "regional",
        "hauling",
        "trucking"
    ],
    "wof:name":"Martin Transport LLC",
    "wof:placetype":"venue"
},
  "geometry": {"coordinates":[-90.55279299999999,38.775054],"type":"Point"}
}