{
  "type": "Feature",
  "properties": {
    "addr:full":"3150 Telegraph Rd St Louis MO 63125",
    "addr:housenumber":"3150",
    "addr:postcode":"63125",
    "addr:street":"Telegraph Rd",
    "iso:country":"US",
    "sg:address":"3150 Telegraph Rd",
    "sg:city":"St Louis",
    "sg:classifiers":[
        {
            "category":"Autos & Motor Vehicles",
            "subcategory":"Fuel & Gas Station",
            "type":"Retail Goods"
        }
    ],
    "sg:phone":"+1 314 845 9536",
    "sg:postcode":"63125",
    "sg:province":"MO",
    "sg:tags":[
        "oil"
    ],
    "wof:name":"BP",
    "wof:placetype":"venue"
},
  "geometry": {"coordinates":[-90.29992799999999,38.49853],"type":"Point"}
}