{
  "type": "Feature",
  "properties": {
    "iso:country":"US",
    "sg:address":"709 SW 29 St",
    "sg:city":"Blue Springs",
    "sg:classifiers":[
        {
            "category":"Professional",
            "subcategory":"Accounting & Tax Preparation",
            "type":"Services"
        }
    ],
    "sg:phone":"+1 816 304 4398",
    "sg:postcode":"64015",
    "sg:province":"MO",
    "sg:tags":[
        "bookkeeping",
        "general"
    ],
    "wof:name":"RPPC Inc",
    "wof:placetype":"venue"
},
  "geometry": {"coordinates":[-94.296392,39.012367],"type":"Point"}
}