{
  "type": "Feature",
  "properties": {
    "iso:country":"US",
    "sg:address":"13523 Barrett Parkway Dr",
    "sg:city":"Ballwin",
    "sg:classifiers":[
        {
            "category":"Insurance",
            "subcategory":"Insurance Agent",
            "type":"Services"
        }
    ],
    "sg:phone":"+1 314 821 8330",
    "sg:postcode":"63021",
    "sg:province":"MO",
    "wof:name":"Provident",
    "wof:placetype":"venue"
},
  "geometry": {"coordinates":[-90.46927100000001,38.595634],"type":"Point"}
}