{
  "type": "Feature",
  "properties": {
    "addr:full":"1976 Hwy 52 Tuscumbia MO 65082",
    "addr:housenumber":"1976",
    "addr:postcode":"65082",
    "addr:street":"Hwy 52",
    "iso:country":"US",
    "sg:address":"1976 Hwy 52",
    "sg:city":"Tuscumbia",
    "sg:classifiers":[
        {
            "category":"Insurance",
            "subcategory":"Insurance Agent",
            "type":"Services"
        }
    ],
    "sg:phone":"+1 573 369 2213",
    "sg:postcode":"65082",
    "sg:province":"MO",
    "wof:name":"Shelter Insurance",
    "wof:placetype":"venue"
},
  "geometry": {"coordinates":[-92.462107,38.237615],"type":"Point"}
}