{
  "type": "Feature",
  "properties": {
    "iso:country":"US",
    "sg:address":"69 Sherwood Dr",
    "sg:city":"Washington",
    "sg:classifiers":[
        {
            "category":"Professional",
            "subcategory":"Computer Services",
            "type":"Services"
        }
    ],
    "sg:phone":"+1 636 583 0771",
    "sg:postcode":"63090",
    "sg:province":"MO",
    "sg:tags":[
        "web",
        "design",
        "hosting",
        "site"
    ],
    "wof:name":"One Stop Cyber Shop",
    "wof:placetype":"venue"
},
  "geometry": {"coordinates":[-90.996918,38.49176],"type":"Point"}
}