{
  "type": "Feature",
  "properties": {
    "iso:country":"US",
    "sg:address":"25091 Walnut St",
    "sg:city":"Bell City",
    "sg:classifiers":[
        {
            "category":"Organizations",
            "subcategory":"Religious Organization",
            "type":"Services"
        }
    ],
    "sg:phone":"+1 573 733 9003",
    "sg:postcode":"63735",
    "sg:province":"MO",
    "sg:tags":[
        "church"
    ],
    "wof:name":"New Life Tabernacle",
    "wof:placetype":"venue"
},
  "geometry": {"coordinates":[-89.82364699999999,37.021669],"type":"Point"}
}