{
  "type": "Feature",
  "properties": {
    "addr:full":"1081 Jeffco Blvd Arnold MO 63010",
    "addr:housenumber":"1081",
    "addr:postcode":"63010",
    "addr:street":"Jeffco Blvd",
    "iso:country":"US",
    "sg:address":"1081 Jeffco Blvd",
    "sg:city":"Arnold",
    "sg:classifiers":[
        {
            "category":"Retail",
            "subcategory":"Funeral Services",
            "type":"Services"
        }
    ],
    "sg:phone":"+1 636 296 5102",
    "sg:postcode":"63010",
    "sg:province":"MO",
    "sg:tags":[
        "home"
    ],
    "wof:name":"SCI",
    "wof:placetype":"venue"
},
  "geometry": {"coordinates":[-90.374347,38.442489],"type":"Point"}
}