{
  "type": "Feature",
  "properties": {
    "iso:country":"US",
    "sg:address":"46 N Elizabeth Ave",
    "sg:city":"Saint Louis",
    "sg:classifiers":[
        {
            "category":"Wholesale",
            "subcategory":"Vending Machines",
            "type":"Manufacturing & Wholesale Goods"
        }
    ],
    "sg:phone":"+1 314 521 3736",
    "sg:postcode":"63135",
    "sg:province":"MO",
    "sg:tags":[
        "operator"
    ],
    "wof:name":"Duncan Wn Business Service",
    "wof:placetype":"venue"
},
  "geometry": {"coordinates":[-90.298333,38.74626],"type":"Point"}
}