{
  "type": "Feature",
  "properties": {
    "iso:country":"US",
    "sg:address":"1525 S Vandeventer Ave",
    "sg:city":"St Louis",
    "sg:classifiers":[
        {
            "category":"Professional",
            "subcategory":"Business Services",
            "type":"Services"
        },
        {
            "category":"Professional",
            "subcategory":"Advertising",
            "type":"Services"
        }
    ],
    "sg:phone":"+1 314 664 0455",
    "sg:postcode":"63110",
    "sg:province":"MO",
    "sg:tags":[
        "consultant"
    ],
    "wof:name":"R W Communications",
    "wof:placetype":"venue"
},
  "geometry": {"coordinates":[-90.256066,38.622024],"type":"Point"}
}