{
  "type": "Feature",
  "properties": {
    "iso:country":"US",
    "sg:address":"505 E Martin St",
    "sg:city":"Campbell",
    "sg:classifiers":[
        {
            "category":"Organizations",
            "subcategory":"Religious Organization",
            "type":"Services"
        }
    ],
    "sg:phone":"+1 573 246 2795",
    "sg:postcode":"63933",
    "sg:province":"MO",
    "sg:tags":[
        "church"
    ],
    "wof:name":"Campbell United Methodist Chr",
    "wof:placetype":"venue"
},
  "geometry": {"coordinates":[-90.072647,36.495703],"type":"Point"}
}