{
  "type": "Feature",
  "properties": {
    "iso:country":"US",
    "sg:address":"3 Shady Moss Ct",
    "sg:city":"Saint Charles",
    "sg:classifiers":[
        {
            "category":"Professional",
            "subcategory":"Accounting & Tax Preparation",
            "type":"Services"
        }
    ],
    "sg:phone":"+1 636 498 6517",
    "sg:postcode":"63304",
    "sg:province":"MO",
    "sg:tags":[
        "return"
    ],
    "wof:name":"Phoenix Tax Service",
    "wof:placetype":"venue"
},
  "geometry": {"coordinates":[-90.650873,38.73215],"type":"Point"}
}