{
  "type": "Feature",
  "properties": {
    "iso:country":"US",
    "sg:address":"609 W Newton St",
    "sg:city":"Versailles",
    "sg:classifiers":[
        {
            "category":"Autos & Motor Vehicles",
            "subcategory":"Automobile Sales",
            "type":"Retail Goods"
        }
    ],
    "sg:phone":"+1 573 378 5456",
    "sg:postcode":"65084",
    "sg:province":"MO",
    "sg:tags":[
        "car",
        "dealer"
    ],
    "wof:name":"Ozark Wheels",
    "wof:placetype":"venue"
},
  "geometry": {"coordinates":[-92.848204,38.431796],"type":"Point"}
}