{
  "type": "Feature",
  "properties": {
    "iso:country":"US",
    "sg:address":"215 N Osage Blvd",
    "sg:city":"Nevada",
    "sg:classifiers":[
        {
            "category":"Autos & Motor Vehicles",
            "subcategory":"Automobile Sales",
            "type":"Retail Goods"
        }
    ],
    "sg:phone":"+1 417 667 5253",
    "sg:postcode":"64772",
    "sg:province":"MO",
    "sg:tags":[
        "car",
        "dealer"
    ],
    "wof:name":"Ketter Motors",
    "wof:placetype":"venue"
},
  "geometry": {"coordinates":[-94.349979,37.839236],"type":"Point"}
}