{
  "type": "Feature",
  "properties": {
    "iso:country":"US",
    "sg:address":"50 W 73 St",
    "sg:city":"Kansas City",
    "sg:classifiers":[
        {
            "category":"Retail",
            "subcategory":"Portrait Studio",
            "type":"Services"
        }
    ],
    "sg:phone":"+1 816 363 6374",
    "sg:postcode":"64114",
    "sg:province":"MO",
    "sg:tags":[
        "photographer"
    ],
    "wof:name":"Amphoto",
    "wof:placetype":"venue"
},
  "geometry": {"coordinates":[-94.59004299999999,38.995871],"type":"Point"}
}