{
  "type": "Feature",
  "properties": {
    "iso:country":"US",
    "sg:address":"7964 Amanda Dr",
    "sg:city":"Auxvasse",
    "sg:classifiers":[
        {
            "category":"Farming",
            "subcategory":"Farm",
            "type":"Manufacturing & Wholesale Goods"
        }
    ],
    "sg:phone":"+1 573 386 2010",
    "sg:postcode":"65231",
    "sg:province":"MO",
    "sg:tags":[
        "crop",
        "general"
    ],
    "wof:name":"Harrison Creek Farms",
    "wof:placetype":"venue"
},
  "geometry": {"coordinates":[-91.817876,39.001961],"type":"Point"}
}