{
  "type": "Feature",
  "properties": {
    "iso:country":"US",
    "sg:address":"9600 NE 112th St",
    "sg:city":"Kansas City",
    "sg:classifiers":[
        {
            "category":"Organizations",
            "subcategory":"Labor Organization",
            "type":"Services"
        }
    ],
    "sg:phone":"+1 816 792 2125",
    "sg:postcode":"64157",
    "sg:province":"MO",
    "wof:name":"Brotherhood of Locomotive",
    "wof:placetype":"venue"
},
  "geometry": {"coordinates":[-94.46822899999999,39.295643],"type":"Point"}
}