{
  "type": "Feature",
  "properties": {
    "iso:country":"US",
    "sg:address":"507 S Main St",
    "sg:city":"Maryville",
    "sg:classifiers":[
        {
            "category":"Health Services",
            "subcategory":"Doctor",
            "type":"Services"
        }
    ],
    "sg:phone":"+1 660 582 8516",
    "sg:postcode":"64468",
    "sg:province":"MO",
    "wof:name":"Poynter Phillip M DDS",
    "wof:placetype":"venue"
},
  "geometry": {"coordinates":[-94.87299,40.342076],"type":"Point"}
}