{
  "type": "Feature",
  "properties": {
    "iso:country":"US",
    "sg:address":"2829 S Scenic Ave",
    "sg:city":"Springfield",
    "sg:classifiers":[
        {
            "category":"Autos & Motor Vehicles",
            "subcategory":"Auto Supplies",
            "type":"Retail Goods"
        },
        {
            "category":"Manufacturing",
            "subcategory":"Petroleum Products",
            "type":"Manufacturing & Wholesale Goods"
        }
    ],
    "sg:phone":"+1 417 882 8844",
    "sg:postcode":"65807",
    "sg:province":"MO",
    "sg:tags":[
        "lubricating",
        "part",
        "oil",
        "lubricant",
        "automobile"
    ],
    "wof:name":"Keltner Distribution",
    "wof:placetype":"venue"
},
  "geometry": {"coordinates":[-93.331909,37.16407],"type":"Point"}
}