{
  "type": "Feature",
  "properties": {
    "iso:country":"US",
    "sg:address":"5000 NE 501 Rd",
    "sg:city":"Osceola",
    "sg:classifiers":[
        {
            "category":"Autos & Motor Vehicles",
            "subcategory":"Automobile Sales",
            "type":"Retail Goods"
        }
    ],
    "sg:phone":"+1 417 646 1310",
    "sg:postcode":"64776",
    "sg:province":"MO",
    "sg:tags":[
        "car",
        "dealer"
    ],
    "wof:name":"D & G Truck Trailer & Auto",
    "wof:placetype":"venue"
},
  "geometry": {"coordinates":[-93.689116,38.093286],"type":"Point"}
}