{
  "type": "Feature",
  "properties": {
    "iso:country":"US",
    "sg:address":"801 Pennsylvania Ave",
    "sg:city":"Kansas City",
    "sg:classifiers":[
        {
            "category":"Banks & Credit Unions",
            "subcategory":"Financial Services",
            "type":"Services"
        }
    ],
    "sg:phone":"+1 816 871 4226",
    "sg:postcode":"64105",
    "sg:province":"MO",
    "sg:tags":[
        "investor"
    ],
    "wof:name":"Investors Trust Co",
    "wof:placetype":"venue"
},
  "geometry": {"coordinates":[-94.59088800000001,39.104138],"type":"Point"}
}