{
  "type": "Feature",
  "properties": {
    "iso:country":"US",
    "sg:address":"11016 E 35th St S",
    "sg:city":"Independence",
    "sg:classifiers":[
        {
            "category":"Professional",
            "subcategory":"Business Services",
            "type":"Services"
        }
    ],
    "sg:phone":"+1 816 254 7530",
    "sg:postcode":"64052",
    "sg:province":"MO",
    "wof:name":"Tiffany Enterprise",
    "wof:placetype":"venue"
},
  "geometry": {"coordinates":[-94.447491,39.058663],"type":"Point"}
}