{
  "type": "Feature",
  "properties": {
    "iso:country":"US",
    "sg:address":"6955 State Road B",
    "sg:city":"Dittmer",
    "sg:classifiers":[
        {
            "category":"Place Of Worship",
            "subcategory":"Church",
            "type":"Public Place"
        },
        {
            "category":"Place Of Worship",
            "type":"Public Place"
        }
    ],
    "sg:phone":"+1 636 285 2411",
    "sg:postcode":"63023",
    "sg:province":"MO",
    "sg:tags":[
        "churches-baptist-general",
        "churches-baptist"
    ],
    "sg:website":"http://www.mmbc.net",
    "wof:name":"Morse Mill Baptist Church",
    "wof:placetype":"venue"
},
  "geometry": {"coordinates":[-90.648003,38.279034],"type":"Point"}
}