{
  "type": "Feature",
  "properties": {
    "iso:country":"US",
    "sg:address":"1040 Quisenberry Rd",
    "sg:city":"Sedalia",
    "sg:classifiers":[
        {
            "category":"Farming",
            "subcategory":"Livestock Farm",
            "type":"Manufacturing & Wholesale Goods"
        }
    ],
    "sg:phone":"+1 660 827 5141",
    "sg:postcode":"65301",
    "sg:province":"MO",
    "sg:tags":[
        "feedlot",
        "hog",
        "or",
        "beef",
        "cattle"
    ],
    "wof:name":"Rissler John",
    "wof:placetype":"venue"
},
  "geometry": {"coordinates":[-93.31052099999999,38.707764],"type":"Point"}
}