{
  "type": "Feature",
  "properties": {
    "iso:country":"US",
    "sg:address":"1451 Chambers Rd",
    "sg:city":"Saint Louis",
    "sg:classifiers":[
        {
            "category":"Personal",
            "subcategory":"Beauty Salon",
            "type":"Services"
        }
    ],
    "sg:phone":"+1 314 522 9293",
    "sg:postcode":"63135",
    "sg:province":"MO",
    "sg:tags":[
        "shop"
    ],
    "wof:name":"Styles Platinum",
    "wof:placetype":"venue"
},
  "geometry": {"coordinates":[-90.27994099999999,38.749425],"type":"Point"}
}