{
  "type": "Feature",
  "properties": {
    "iso:country":"US",
    "sg:address":"2003 Senate St",
    "sg:city":"Saint Louis",
    "sg:classifiers":[
        {
            "category":"Wholesale",
            "subcategory":"Home Furnishings",
            "type":"Manufacturing & Wholesale Goods"
        }
    ],
    "sg:phone":"+1 314 773 5300",
    "sg:postcode":"63118",
    "sg:province":"MO",
    "sg:tags":[
        "fixture",
        "range",
        "lighting",
        "grill"
    ],
    "wof:name":"Triad Sales & Service L L C",
    "wof:placetype":"venue"
},
  "geometry": {"coordinates":[-90.218672,38.603127],"type":"Point"}
}