{
  "type": "Feature",
  "properties": {
    "iso:country":"US",
    "sg:address":"8202 E 87 St",
    "sg:city":"Kansas City",
    "sg:classifiers":[
        {
            "category":"Utilities",
            "subcategory":"Telephone",
            "type":"Services"
        }
    ],
    "sg:phone":"+1 816 313 1232",
    "sg:postcode":"64138",
    "sg:province":"MO",
    "sg:tags":[
        "communications"
    ],
    "wof:name":"Deezhostcom",
    "wof:placetype":"venue"
},
  "geometry": {"coordinates":[-94.48833500000001,38.966223],"type":"Point"}
}