{
  "type": "Feature",
  "properties": {
    "iso:country":"US",
    "sg:address":"113 E Wall St",
    "sg:city":"Harrisonville",
    "sg:classifiers":[
        {
            "category":"Professional",
            "subcategory":"Lawyer & Legal Services",
            "type":"Services"
        }
    ],
    "sg:phone":"+1 816 380 2122",
    "sg:postcode":"64701",
    "sg:province":"MO",
    "sg:tags":[
        "attorney"
    ],
    "wof:name":"Cathleen A Shine Law Offices",
    "wof:placetype":"venue"
},
  "geometry": {"coordinates":[-94.34870600000001,38.65419],"type":"Point"}
}