{
  "type": "Feature",
  "properties": {
    "iso:country":"US",
    "sg:address":"320 Railroad Ave",
    "sg:city":"Gower",
    "sg:classifiers":[
        {
            "category":"Building & Trades",
            "subcategory":"Construction",
            "type":"Services"
        }
    ],
    "sg:phone":"+1 816 424 3249",
    "sg:postcode":"64454",
    "sg:province":"MO",
    "sg:tags":[
        "steel"
    ],
    "wof:name":"True Demensions",
    "wof:placetype":"venue"
},
  "geometry": {"coordinates":[-94.599951,39.612349],"type":"Point"}
}