{
  "type": "Feature",
  "properties": {
    "addr:full":"1101 Sulphur Spring Rd Ballwin MO 63021",
    "addr:housenumber":"1101",
    "addr:postcode":"63021",
    "addr:street":"Sulphur Spring Rd",
    "iso:country":"US",
    "sg:address":"1101 Sulphur Spring Rd",
    "sg:city":"Ballwin",
    "sg:classifiers":[
        {
            "category":"Place Of Worship",
            "subcategory":"Church",
            "type":"Public Place"
        },
        {
            "category":"Place Of Worship",
            "type":"Public Place"
        }
    ],
    "sg:phone":"+1 636 227 1227",
    "sg:postcode":"63021",
    "sg:province":"MO",
    "sg:tags":[
        "churches-episcopal"
    ],
    "sg:website":"http://www.stlukesec.org",
    "wof:name":"St Luke's Episcopal Church",
    "wof:placetype":"venue"
},
  "geometry": {"coordinates":[-90.52497099999999,38.5721],"type":"Point"}
}