{
  "type": "Feature",
  "properties": {
    "iso:country":"US",
    "sg:address":"2 N Delaware St",
    "sg:city":"Butler",
    "sg:classifiers":[
        {
            "category":"Manufacturing",
            "subcategory":"Tools & Machinery",
            "type":"Manufacturing & Wholesale Goods"
        }
    ],
    "sg:phone":"+1 660 679 5396",
    "sg:postcode":"64730",
    "sg:province":"MO",
    "sg:tags":[
        "mfg",
        "computer",
        "software"
    ],
    "wof:name":"Computer Shop The",
    "wof:placetype":"venue"
},
  "geometry": {"coordinates":[-94.33311999999999,38.258516],"type":"Point"}
}