{
  "type": "Feature",
  "properties": {
    "iso:country":"US",
    "sg:address":"404 State Hwy 25",
    "sg:city":"Dexter",
    "sg:classifiers":[
        {
            "category":"Autos & Motor Vehicles",
            "subcategory":"Auto Supplies",
            "type":"Retail Goods"
        }
    ],
    "sg:phone":"+1 573 624 1656",
    "sg:postcode":"63841",
    "sg:province":"MO",
    "sg:tags":[
        "alternator",
        "generator"
    ],
    "wof:name":"Semo Starter & Alternator",
    "wof:placetype":"venue"
},
  "geometry": {"coordinates":[-89.952084,36.788635],"type":"Point"}
}