{
  "type": "Feature",
  "properties": {
    "iso:country":"US",
    "sg:address":"1670 Kessler Pl",
    "sg:city":"Festus",
    "sg:classifiers":[
        {
            "category":"Retail",
            "subcategory":"Animal Services",
            "type":"Services"
        }
    ],
    "sg:phone":"+1 636 931 5754",
    "sg:postcode":"63028",
    "sg:province":"MO",
    "sg:tags":[
        "security",
        "system"
    ],
    "wof:name":"Canine Security Inc",
    "wof:placetype":"venue"
},
  "geometry": {"coordinates":[-90.321596,38.099785],"type":"Point"}
}