{
  "type": "Feature",
  "properties": {
    "iso:country":"US",
    "sg:address":"4025 S Old Hwy 94",
    "sg:city":"St Peters",
    "sg:classifiers":[
        {
            "category":"Building & Trades",
            "subcategory":"Construction",
            "type":"Services"
        }
    ],
    "sg:phone":"+1 636 928 6675",
    "sg:postcode":"63304",
    "sg:province":"MO",
    "sg:tags":[
        "painter"
    ],
    "wof:name":"St John Painting Inc",
    "wof:placetype":"venue"
},
  "geometry": {"coordinates":[-90.589906,38.742622],"type":"Point"}
}