{
  "type": "Feature",
  "properties": {
    "iso:country":"US",
    "sg:address":"1873 State Hwy K",
    "sg:city":"Kirbyville",
    "sg:classifiers":[
        {
            "category":"Parking",
            "type":"Transportation"
        },
        {
            "category":"Building & Trades",
            "subcategory":"Construction",
            "type":"Services"
        }
    ],
    "sg:phone":"+1 417 339 3089",
    "sg:postcode":"65631",
    "sg:province":"MO",
    "sg:tags":[
        "automobile",
        "paving",
        "contractor"
    ],
    "wof:name":"Tri-Lake Sealing and Striping",
    "wof:placetype":"venue"
},
  "geometry": {"coordinates":[-93.465024,37.004874],"type":"Point"}
}