{
  "type": "Feature",
  "properties": {
    "iso:country":"US",
    "sg:address":"120 Old Meramec Station Rd",
    "sg:city":"Ballwin",
    "sg:classifiers":[
        {
            "category":"Wholesale",
            "subcategory":"Construction Materials",
            "type":"Manufacturing & Wholesale Goods"
        },
        {
            "category":"Building & Trades",
            "subcategory":"Construction",
            "type":"Services"
        }
    ],
    "sg:phone":"+1 636 394 7227",
    "sg:postcode":"63021",
    "sg:province":"MO",
    "sg:tags":[
        "granite",
        "stonework",
        "contractor"
    ],
    "wof:name":"Midwest Marble & Granite Corp",
    "wof:placetype":"venue"
},
  "geometry": {"coordinates":[-90.51163099999999,38.592481],"type":"Point"}
}