{
  "type": "Feature",
  "properties": {
    "iso:country":"US",
    "sg:address":"6150 Oakland Ave",
    "sg:city":"Saint Louis",
    "sg:classifiers":[
        {
            "category":"Health Services",
            "subcategory":"Doctor",
            "type":"Services"
        }
    ],
    "sg:phone":"+1 314 768 3090",
    "sg:postcode":"63139",
    "sg:province":"MO",
    "sg:tags":[
        "podiatrist"
    ],
    "wof:name":"Ambulatory Care Center",
    "wof:placetype":"venue"
},
  "geometry": {"coordinates":[-90.287903,38.6311],"type":"Point"}
}