{
  "type": "Feature",
  "properties": {
    "iso:country":"US",
    "sg:address":"HC 86",
    "sg:city":"Steelville",
    "sg:classifiers":[
        {
            "category":"Organizations",
            "subcategory":"Religious Organization",
            "type":"Services"
        }
    ],
    "sg:phone":"+1 573 743 6399",
    "sg:postcode":"65565",
    "sg:province":"MO",
    "wof:name":"Center Ridge Pentecostal Churc",
    "wof:placetype":"venue"
},
  "geometry": {"coordinates":[-91.322655,37.916756],"type":"Point"}
}