{
  "type": "Feature",
  "properties": {
    "iso:country":"US",
    "sg:address":"100 N US Hwy 67",
    "sg:city":"Florissant",
    "sg:classifiers":[
        {
            "category":"Autos & Motor Vehicles",
            "subcategory":"Automobile Sales",
            "type":"Retail Goods"
        }
    ],
    "sg:phone":"+1 314 972 7000",
    "sg:postcode":"63031",
    "sg:province":"MO",
    "sg:tags":[
        "used"
    ],
    "wof:name":"Auto King Inc",
    "wof:placetype":"venue"
},
  "geometry": {"coordinates":[-90.338849,38.796808],"type":"Point"}
}