{
  "type": "Feature",
  "properties": {
    "iso:country":"US",
    "sg:address":"13995 New Halls Ferry Rd",
    "sg:city":"Florissant",
    "sg:classifiers":[
        {
            "category":"Banks & Credit Unions",
            "subcategory":"Investment Brokerage",
            "type":"Services"
        },
        {
            "category":"Shopping",
            "subcategory":"Music",
            "type":"Retail Goods"
        },
        {
            "category":"Shopping",
            "subcategory":"Computers & Home Electronics",
            "type":"Retail Goods"
        },
        {
            "category":"Shopping",
            "subcategory":"Gifts & Souvenirs",
            "type":"Retail Goods"
        },
        {
            "category":"Utilities",
            "subcategory":"Mobile Phone",
            "type":"Services"
        },
        {
            "category":"Communications",
            "subcategory":"Film & Video Production",
            "type":"Services"
        },
        {
            "category":"Shopping",
            "subcategory":"Books",
            "type":"Retail Goods"
        },
        {
            "category":"Wholesale",
            "subcategory":"Books, Periodicals, & Newspapers",
            "type":"Manufacturing & Wholesale Goods"
        }
    ],
    "sg:phone":"+1 314 830 3550",
    "sg:postcode":"63033",
    "sg:province":"MO",
    "sg:tags":[
        "shop",
        "educational",
        "dvd",
        "material",
        "sale",
        "hotspot",
        "dvds-rental",
        "record",
        "magazine",
        "tapes-wholesale",
        "tape",
        "cd's",
        "wi-fi",
        "store",
        "manufacturer"
    ],
    "sg:website":"http://store-locator.barnesandnoble.com/store/2163",
    "wof:name":"Barnes & Noble Booksellers",
    "wof:placetype":"venue"
},
  "geometry": {"coordinates":[-90.296835,38.805888],"type":"Point"}
}