{
  "type": "Feature",
  "properties": {
    "iso:country":"US",
    "sg:address":"1337 Carriage Crossing Ln",
    "sg:city":"Chesterfield",
    "sg:classifiers":[
        {
            "category":"Wholesale",
            "subcategory":"Construction Materials",
            "type":"Manufacturing & Wholesale Goods"
        }
    ],
    "sg:phone":"+1 636 441 2275",
    "sg:postcode":"63005",
    "sg:province":"MO",
    "sg:tags":[
        "glass"
    ],
    "wof:name":"BBS & Assoc Inc",
    "wof:placetype":"venue"
},
  "geometry": {"coordinates":[-90.610654,38.647823],"type":"Point"}
}