{
  "type": "Feature",
  "properties": {
    "iso:country":"US",
    "sg:address":"6000 N Oneal Rd",
    "sg:city":"Columbia",
    "sg:classifiers":[
        {
            "category":"Recreation",
            "type":"Entertainment"
        },
        {
            "category":"Community Center",
            "subcategory":"Youth",
            "type":"Public Place"
        },
        {
            "category":"Recreation",
            "subcategory":"Campground",
            "type":"Entertainment"
        }
    ],
    "sg:phone":"+1 573 445 7536",
    "sg:postcode":"65202",
    "sg:province":"MO",
    "sg:tags":[
        "recreational",
        "park",
        "camps-recreational",
        "vehicle"
    ],
    "wof:name":"Camp Fire Usa Missouri Trails",
    "wof:placetype":"venue"
},
  "geometry": {"coordinates":[-92.372581,39.019833],"type":"Point"}
}