{
  "type": "Feature",
  "properties": {
    "iso:country":"US",
    "sg:address":"1 Midway Rd",
    "sg:city":"Sunrise Beach",
    "sg:classifiers":[
        {
            "category":"Professional",
            "subcategory":"Advertising",
            "type":"Services"
        }
    ],
    "sg:phone":"+1 573 374 7799",
    "sg:postcode":"65026",
    "sg:province":"MO",
    "wof:name":"Medical Magnet",
    "wof:placetype":"venue"
},
  "geometry": {"coordinates":[-92.576382,38.306288],"type":"Point"}
}