{
  "type": "Feature",
  "properties": {
    "iso:country":"US",
    "sg:address":"22025 Rattan Dr",
    "sg:city":"Waynesville",
    "sg:classifiers":[
        {
            "category":"Building & Trades",
            "subcategory":"Cleaning & Sanitation",
            "type":"Services"
        }
    ],
    "sg:phone":"+1 573 855 0112",
    "sg:postcode":"65583",
    "sg:province":"MO",
    "sg:tags":[
        "control",
        "hazardous",
        "material",
        "removal"
    ],
    "wof:name":"Energetic Enterprises",
    "wof:placetype":"venue"
},
  "geometry": {"coordinates":[-92.246371,37.800579],"type":"Point"}
}