{
  "type": "Feature",
  "properties": {
    "iso:country":"US",
    "sg:address":"16620 Hemphill Dr",
    "sg:city":"Waynesville",
    "sg:classifiers":[
        {
            "category":"Arts & Performance",
            "subcategory":"Theater",
            "type":"Entertainment"
        }
    ],
    "sg:phone":"+1 573 336 0227",
    "sg:postcode":"65584",
    "sg:province":"MO",
    "sg:tags":[
        "piano",
        "organist"
    ],
    "wof:name":"Evelyn Horine",
    "wof:placetype":"venue"
},
  "geometry": {"coordinates":[-92.143986,37.833933],"type":"Point"}
}