{
  "type": "Feature",
  "properties": {
    "iso:country":"US",
    "sg:address":"714 E Green St",
    "sg:city":"Clinton",
    "sg:classifiers":[
        {
            "category":"Social Services",
            "subcategory":"Child Care",
            "type":"Services"
        }
    ],
    "sg:phone":"+1 660 885 5215",
    "sg:postcode":"64735",
    "sg:province":"MO",
    "sg:tags":[
        "state",
        "licensed",
        "day",
        "provider"
    ],
    "wof:name":"Shirley J Sutton",
    "wof:placetype":"venue"
},
  "geometry": {"coordinates":[-93.765343,38.371634],"type":"Point"}
}