{
  "type": "Feature",
  "properties": {
    "iso:country":"US",
    "sg:address":"4911 Union Blvd",
    "sg:city":"St Louis",
    "sg:classifiers":[
        {
            "category":"Professional",
            "type":"Services"
        },
        {
            "category":"Professional",
            "subcategory":"Management & Consulting",
            "type":"Services"
        }
    ],
    "sg:phone":"+1 314 385 8999",
    "sg:postcode":"63115",
    "sg:province":"MO",
    "sg:tags":[
        "consultant"
    ],
    "wof:name":"A L J Consultants",
    "wof:placetype":"venue"
},
  "geometry": {"coordinates":[-90.24993499999999,38.689035],"type":"Point"}
}