{
  "type": "Feature",
  "properties": {
    "iso:country":"US",
    "sg:address":"4024 Butler Hill Rd",
    "sg:city":"St Louis",
    "sg:classifiers":[
        {
            "category":"Professional",
            "subcategory":"Credit Reporting & Collection",
            "type":"Services"
        }
    ],
    "sg:phone":"+1 314 845 5995",
    "sg:postcode":"63129",
    "sg:province":"MO",
    "sg:tags":[
        "agency"
    ],
    "sg:website":"www.misource.com",
    "wof:name":"Mortgage Information Source",
    "wof:placetype":"venue"
},
  "geometry": {"coordinates":[-90.350568,38.485771],"type":"Point"}
}