{
  "type": "Feature",
  "properties": {
    "iso:country":"US",
    "sg:address":"1224 Harvestowne Ind Dr",
    "sg:city":"Saint Charles",
    "sg:classifiers":[
        {
            "category":"Freight",
            "type":"Transportation"
        }
    ],
    "sg:phone":"+1 636 926 8433",
    "sg:postcode":"63304",
    "sg:province":"MO",
    "sg:tags":[
        "broker"
    ],
    "wof:name":"Mid Rivers Marine Service",
    "wof:placetype":"venue"
},
  "geometry": {"coordinates":[-90.607028,38.739313],"type":"Point"}
}