{
  "type": "Feature",
  "properties": {
    "iso:country":"US",
    "sg:address":"12513 Olive Blvd",
    "sg:city":"Saint Louis",
    "sg:classifiers":[
        {
            "category":"Restaurant",
            "type":"Food & Drink"
        }
    ],
    "sg:phone":"+1 314 878 5858",
    "sg:postcode":"63141",
    "sg:province":"MO",
    "sg:tags":[
        "eating"
    ],
    "wof:name":"Candiccis West County",
    "wof:placetype":"venue"
},
  "geometry": {"coordinates":[-90.463077,38.675757],"type":"Point"}
}