{
  "type": "Feature",
  "properties": {
    "iso:country":"US",
    "sg:address":"7421 Mexico Rd",
    "sg:city":"St Peters",
    "sg:classifiers":[
        {
            "category":"Banks & Credit Unions",
            "subcategory":"Bank",
            "type":"Services"
        }
    ],
    "sg:phone":"+1 636 940 1009",
    "sg:postcode":"63376",
    "sg:province":"MO",
    "sg:tags":[
        "loan",
        "real estate"
    ],
    "wof:name":"Universal Mortgage Corp",
    "wof:placetype":"venue"
},
  "geometry": {"coordinates":[-90.604598,38.790598],"type":"Point"}
}