{
  "type": "Feature",
  "properties": {
    "iso:country":"US",
    "sg:address":"134 W Pine St",
    "sg:city":"Warrensburg",
    "sg:classifiers":[
        {
            "category":"Organizations",
            "subcategory":"Religious Organization",
            "type":"Services"
        }
    ],
    "sg:phone":"+1 660 747 0780",
    "sg:postcode":"64093",
    "sg:province":"MO",
    "wof:name":"Restoration Campus Ministries",
    "wof:placetype":"venue"
},
  "geometry": {"coordinates":[-93.742104,38.76336],"type":"Point"}
}