{
  "type": "Feature",
  "properties": {
    "iso:country":"US",
    "sg:address":"229 S Broadview St",
    "sg:city":"Cape Girardeau",
    "sg:classifiers":[
        {
            "category":"Personal",
            "subcategory":"Beauty Salon",
            "type":"Services"
        }
    ],
    "sg:phone":"+1 573 335 1597",
    "sg:postcode":"63703",
    "sg:province":"MO",
    "wof:name":"O'Haira",
    "wof:placetype":"venue"
},
  "geometry": {"coordinates":[-89.556906,37.302704],"type":"Point"}
}