{
  "type": "Feature",
  "properties": {
    "iso:country":"US",
    "sg:address":"121 N 1st St",
    "sg:city":"Owensville",
    "sg:classifiers":[
        {
            "category":"Shopping",
            "subcategory":"Used Merchandise",
            "type":"Retail Goods"
        }
    ],
    "sg:phone":"+1 573 437 8181",
    "sg:postcode":"65066",
    "sg:province":"MO",
    "sg:tags":[
        "shop",
        "consignment"
    ],
    "wof:name":"Kids Kottage",
    "wof:placetype":"venue"
},
  "geometry": {"coordinates":[-91.500556,38.347851],"type":"Point"}
}