{
  "type": "Feature",
  "properties": {
    "iso:country":"US",
    "sg:address":"5082 S Elizabeth Ave",
    "sg:city":"Springfield",
    "sg:classifiers":[
        {
            "category":"Insurance",
            "subcategory":"Hazard Insurance",
            "type":"Services"
        }
    ],
    "sg:phone":"+1 417 889 8143",
    "sg:postcode":"65810",
    "sg:province":"MO",
    "wof:name":"Deborah J Johnson",
    "wof:placetype":"venue"
},
  "geometry": {"coordinates":[-93.320284,37.122247],"type":"Point"}
}