{
  "type": "Feature",
  "properties": {
    "iso:country":"US",
    "sg:address":"207 Gum Rd",
    "sg:city":"Carl Junction",
    "sg:classifiers":[
        {
            "category":"Professional",
            "type":"Services"
        }
    ],
    "sg:phone":"+1 417 624 8553",
    "sg:postcode":"64834",
    "sg:province":"MO",
    "wof:name":"Luis Boyer",
    "wof:placetype":"venue"
},
  "geometry": {"coordinates":[-94.51040500000001,37.157286],"type":"Point"}
}