{
  "type": "Feature",
  "properties": {
    "iso:country":"US",
    "sg:address":"13992 Manchester Rd",
    "sg:city":"Ballwin",
    "sg:classifiers":[
        {
            "category":"Shopping",
            "subcategory":"Pharmacy",
            "type":"Retail Goods"
        }
    ],
    "sg:phone":"+1 636 227 9169",
    "sg:postcode":"63011",
    "sg:province":"MO",
    "sg:tags":[
        "photofinishing",
        "laboratory"
    ],
    "wof:name":"Walgreens",
    "wof:placetype":"venue"
},
  "geometry": {"coordinates":[-90.489985,38.595758],"type":"Point"}
}