{
  "type": "Feature",
  "properties": {
    "iso:country":"US",
    "sg:address":"300 Main St",
    "sg:city":"Saint Peters",
    "sg:classifiers":[
        {
            "category":"Professional",
            "subcategory":"Accounting & Tax Preparation",
            "type":"Services"
        }
    ],
    "sg:phone":"+1 636 946 3111",
    "sg:postcode":"63376",
    "sg:province":"MO",
    "wof:name":"Century Small Business Sltns",
    "wof:placetype":"venue"
},
  "geometry": {"coordinates":[-90.61958,38.80148],"type":"Point"}
}