{
  "type": "Feature",
  "properties": {
    "iso:country":"US",
    "sg:address":"104 S McKinley Ave",
    "sg:city":"Union",
    "sg:classifiers":[
        {
            "category":"Social Services",
            "type":"Services"
        }
    ],
    "sg:phone":"+1 636 583 6745",
    "sg:postcode":"63084",
    "sg:province":"MO",
    "wof:name":"Monica Houttuin",
    "wof:placetype":"venue"
},
  "geometry": {"coordinates":[-91.00383100000001,38.444726],"type":"Point"}
}