{
  "type": "Feature",
  "properties": {
    "iso:country":"US",
    "sg:address":"3023 S Joplin Ave",
    "sg:city":"Joplin",
    "sg:classifiers":[
        {
            "category":"Taxi",
            "type":"Transportation"
        },
        {
            "category":"Professional",
            "subcategory":"Business Services",
            "type":"Services"
        },
        {
            "category":"Government",
            "subcategory":"Post Office",
            "type":"Public Place"
        }
    ],
    "sg:phone":"+1 417 624 4080",
    "sg:postcode":"64804",
    "sg:province":"MO",
    "sg:tags":[
        "delivery",
        "messenger",
        "courier"
    ],
    "wof:name":"4-0-8 Courier",
    "wof:placetype":"venue"
},
  "geometry": {"coordinates":[-94.515816,37.057128],"type":"Point"}
}