{
  "type": "Feature",
  "properties": {
    "iso:country":"US",
    "sg:address":"409 W Bock St",
    "sg:city":"Pilot Grove",
    "sg:classifiers":[
        {
            "category":"Professional",
            "subcategory":"Accounting & Tax Preparation",
            "type":"Services"
        }
    ],
    "sg:phone":"+1 660 834 3300",
    "sg:postcode":"65276",
    "sg:province":"MO",
    "sg:tags":[
        "return"
    ],
    "wof:name":"Double B Bookkeeping & Tax Svc",
    "wof:placetype":"venue"
},
  "geometry": {"coordinates":[-92.91893899999999,38.869461],"type":"Point"}
}