{
  "type": "Feature",
  "properties": {
    "addr:full":"409 E Dakota St Butler MO 64730",
    "addr:housenumber":"409",
    "addr:postcode":"64730",
    "addr:street":"E Dakota St",
    "iso:country":"US",
    "sg:address":"409 E Dakota St",
    "sg:city":"Butler",
    "sg:classifiers":[
        {
            "category":"Organizations",
            "subcategory":"Religious Organization",
            "type":"Services"
        }
    ],
    "sg:phone":"+1 660 679 3682",
    "sg:postcode":"64730",
    "sg:province":"MO",
    "wof:name":"Corporation of President of Th",
    "wof:placetype":"venue"
},
  "geometry": {"coordinates":[-94.32834699999999,38.257307],"type":"Point"}
}