{
  "type": "Feature",
  "properties": {
    "iso:country":"US",
    "sg:address":"850 Cap au Gris St",
    "sg:city":"Troy",
    "sg:classifiers":[
        {
            "category":"Autos & Motor Vehicles",
            "subcategory":"Automobile Sales",
            "type":"Retail Goods"
        }
    ],
    "sg:phone":"+1 636 528 4786",
    "sg:postcode":"63379",
    "sg:province":"MO",
    "sg:tags":[
        "used"
    ],
    "wof:name":"Mcmurtrey Auto Co",
    "wof:placetype":"venue"
},
  "geometry": {"coordinates":[-90.974042,38.978857],"type":"Point"}
}