{
  "type": "Feature",
  "properties": {
    "iso:country":"US",
    "sg:address":"159 S Lafayette Ave",
    "sg:city":"Marshall",
    "sg:classifiers":[
        {
            "category":"Personal",
            "subcategory":"Beauty Salon",
            "type":"Services"
        }
    ],
    "sg:phone":"+1 660 886 3045",
    "sg:postcode":"65340",
    "sg:province":"MO",
    "sg:tags":[
        "shop"
    ],
    "wof:name":"Magic Mirror Beauty Salon",
    "wof:placetype":"venue"
},
  "geometry": {"coordinates":[-93.19738099999999,39.119999],"type":"Point"}
}