{
  "type": "Feature",
  "properties": {
    "addr:full":"1321 Spur Dr Marshfield MO 65706",
    "addr:housenumber":"1321",
    "addr:postcode":"65706",
    "addr:street":"Spur Dr",
    "iso:country":"US",
    "sg:address":"1321 Spur Dr",
    "sg:city":"Marshfield",
    "sg:classifiers":[
        {
            "category":"Restaurant",
            "type":"Food & Drink"
        }
    ],
    "sg:menulink":"http://www.allmenus.com/mo/marshfield/68984-breadeaux-pizza/menu/",
    "sg:phone":"+1 417 859 7929",
    "sg:postcode":"65706",
    "sg:province":"MO",
    "sg:tags":[
        "american",
        "pizza"
    ],
    "wof:name":"Breadeaux Pizza",
    "wof:placetype":"venue"
},
  "geometry": {"coordinates":[-92.93124899999999,37.343239],"type":"Point"}
}