{
  "type": "Feature",
  "properties": {
    "iso:country":"US",
    "sg:address":"1312 Eagles Way Ct",
    "sg:city":"Hazelwood",
    "sg:classifiers":[
        {
            "category":"Building & Trades",
            "subcategory":"Plumbing",
            "type":"Services"
        }
    ],
    "sg:phone":"+1 314 486 4541",
    "sg:postcode":"63042",
    "sg:province":"MO",
    "sg:tags":[
        "conditioning",
        "air",
        "system",
        "contractor"
    ],
    "wof:name":"Lograsso Services LLC",
    "wof:placetype":"venue"
},
  "geometry": {"coordinates":[-90.389852,38.785387],"type":"Point"}
}