{
  "type": "Feature",
  "properties": {
    "iso:country":"US",
    "sg:address":"3219 Wind River Cir",
    "sg:city":"Columbia",
    "sg:classifiers":[
        {
            "category":"Professional",
            "type":"Services"
        }
    ],
    "sg:phone":"+1 573 447 3990",
    "sg:postcode":"65203",
    "sg:province":"MO",
    "sg:tags":[
        "establishment"
    ],
    "wof:name":"First Alert",
    "wof:placetype":"venue"
},
  "geometry": {"coordinates":[-92.385862,38.952754],"type":"Point"}
}