{
  "type": "Feature",
  "properties": {
    "iso:country":"US",
    "sg:address":"2882 S Elm Rd",
    "sg:city":"Marshfield",
    "sg:classifiers":[
        {
            "category":"Building & Trades",
            "subcategory":"Landscaping Services",
            "type":"Services"
        }
    ],
    "sg:phone":"+1 417 859 4397",
    "sg:postcode":"65706",
    "sg:province":"MO",
    "wof:name":"Ladies Of Landscaping",
    "wof:placetype":"venue"
},
  "geometry": {"coordinates":[-92.893739,37.299463],"type":"Point"}
}