{
  "type": "Feature",
  "properties": {
    "iso:country":"US",
    "sg:address":"4135 Shreve Ave",
    "sg:city":"Saint Louis",
    "sg:classifiers":[
        {
            "category":"Wholesale",
            "subcategory":"Hardware",
            "type":"Manufacturing & Wholesale Goods"
        }
    ],
    "sg:phone":"+1 314 385 6499",
    "sg:postcode":"63115",
    "sg:province":"MO",
    "sg:tags":[
        "plumbing"
    ],
    "wof:name":"Luthers Enterprise",
    "wof:placetype":"venue"
},
  "geometry": {"coordinates":[-90.241981,38.679135],"type":"Point"}
}