{
  "type": "Feature",
  "properties": {
    "iso:country":"US",
    "sg:address":"4534 S Grand Blvd",
    "sg:city":"Saint Louis",
    "sg:classifiers":[
        {
            "category":"Building & Trades",
            "subcategory":"Electrical",
            "type":"Services"
        }
    ],
    "sg:phone":"+1 314 832 3070",
    "sg:postcode":"63111",
    "sg:province":"MO",
    "sg:tags":[
        "electrician"
    ],
    "wof:name":"Volz Electric Inc",
    "wof:placetype":"venue"
},
  "geometry": {"coordinates":[-90.24749799999999,38.5769],"type":"Point"}
}