{
  "type": "Feature",
  "properties": {
    "iso:country":"US",
    "sg:address":"214 S Grand Ave",
    "sg:city":"Jasper",
    "sg:classifiers":[
        {
            "category":"Retail",
            "subcategory":"Repair Shop",
            "type":"Services"
        }
    ],
    "sg:phone":"+1 417 394 2055",
    "sg:postcode":"64755",
    "sg:province":"MO",
    "sg:tags":[
        "rep",
        "industrial",
        "electrical",
        "machinery",
        "mfg"
    ],
    "wof:name":"Modern Mechanistics",
    "wof:placetype":"venue"
},
  "geometry": {"coordinates":[-94.44482499999999,37.24411],"type":"Point"}
}