{
  "type": "Feature",
  "properties": {
    "iso:country":"US",
    "sg:address":"25070 Highway 17",
    "sg:city":"Waynesville",
    "sg:classifiers":[
        {
            "category":"Place Of Worship",
            "subcategory":"Church",
            "type":"Public Place"
        },
        {
            "category":"Place Of Worship",
            "type":"Public Place"
        }
    ],
    "sg:phone":"+1 573 774 5423",
    "sg:postcode":"65583",
    "sg:province":"MO",
    "sg:tags":[
        "churches-pentecostal-independent",
        "churches-pentecostal"
    ],
    "wof:name":"Apostolic Faith United Pentecostal Church",
    "wof:placetype":"venue"
},
  "geometry": {"coordinates":[-92.26418,37.785481],"type":"Point"}
}