{
  "type": "Feature",
  "properties": {
    "iso:country":"US",
    "sg:address":"1205 Candlewax Dr",
    "sg:city":"St Louis",
    "sg:classifiers":[
        {
            "category":"Real Estate",
            "subcategory":"Surveying",
            "type":"Services"
        }
    ],
    "sg:phone":"+1 314 892 0077",
    "sg:postcode":"63129",
    "sg:province":"MO",
    "sg:tags":[
        "surveyor"
    ],
    "wof:name":"Moore Surveying Inc",
    "wof:placetype":"venue"
},
  "geometry": {"coordinates":[-90.329269,38.496021],"type":"Point"}
}