{
  "type": "Feature",
  "properties": {
    "iso:country":"US",
    "sg:address":"1701 Zachary Ct",
    "sg:city":"Nixa",
    "sg:classifiers":[
        {
            "category":"Banks & Credit Unions",
            "subcategory":"Bank",
            "type":"Services"
        }
    ],
    "sg:phone":"+1 417 724 1091",
    "sg:postcode":"65714",
    "sg:province":"MO",
    "sg:tags":[
        "other",
        "plan",
        "card"
    ],
    "wof:name":"American Express",
    "wof:placetype":"venue"
},
  "geometry": {"coordinates":[-93.305188,37.074738],"type":"Point"}
}