{
  "type": "Feature",
  "properties": {
    "iso:country":"US",
    "sg:address":"RR 1 Box 1965",
    "sg:city":"Patton",
    "sg:classifiers":[
        {
            "category":"Home & Garden",
            "subcategory":"Building Materials",
            "type":"Retail Goods"
        },
        {
            "category":"Building & Trades",
            "subcategory":"Construction",
            "type":"Services"
        }
    ],
    "sg:phone":"+1 573 866 2046",
    "sg:postcode":"63662",
    "sg:province":"MO",
    "sg:tags":[
        "concrete",
        "staining",
        "contractor"
    ],
    "wof:name":"Rich Shoemaker",
    "wof:placetype":"venue"
},
  "geometry": {"coordinates":[-90.035187,37.560528],"type":"Point"}
}