{
  "type": "Feature",
  "properties": {
    "iso:country":"US",
    "sg:address":"24110 E 90 Ter",
    "sg:city":"Lees Summit",
    "sg:classifiers":[
        {
            "category":"Building & Trades",
            "subcategory":"Construction",
            "type":"Services"
        }
    ],
    "sg:phone":"+1 816 224 8885",
    "sg:postcode":"64064",
    "sg:province":"MO",
    "sg:tags":[
        "hanging",
        "contractor"
    ],
    "wof:name":"Hayton Painting",
    "wof:placetype":"venue"
},
  "geometry": {"coordinates":[-94.302877,38.9532],"type":"Point"}
}