{
  "type": "Feature",
  "properties": {
    "iso:country":"US",
    "sg:address":"1010 N Kingshighway Blvd",
    "sg:city":"Saint Louis",
    "sg:classifiers":[
        {
            "category":"Autos & Motor Vehicles",
            "subcategory":"Auto Supplies",
            "type":"Retail Goods"
        }
    ],
    "sg:phone":"+1 314 367 9662",
    "sg:postcode":"63113",
    "sg:province":"MO",
    "sg:tags":[
        "tire"
    ],
    "wof:name":"Kersa Inc",
    "wof:placetype":"venue"
},
  "geometry": {"coordinates":[-90.262664,38.655448],"type":"Point"}
}