{
  "type": "Feature",
  "properties": {
    "iso:country":"US",
    "sg:address":"150 Shirley Cove",
    "sg:city":"Hollister",
    "sg:classifiers":[
        {
            "category":"Professional",
            "type":"Services"
        }
    ],
    "sg:phone":"+1 417 335 2121",
    "sg:postcode":"65672",
    "sg:province":"MO",
    "sg:tags":[
        "establishment"
    ],
    "wof:name":"Hollister Education Foundation",
    "wof:placetype":"venue"
},
  "geometry": {"coordinates":[-93.196029,36.621147],"type":"Point"}
}