{
  "type": "Feature",
  "properties": {
    "iso:country":"US",
    "sg:address":"1401 Frederick Ave",
    "sg:city":"St Joseph",
    "sg:classifiers":[
        {
            "category":"Health Services",
            "subcategory":"Chiropractor",
            "type":"Services"
        }
    ],
    "sg:phone":"+1 816 676 2225",
    "sg:postcode":"64501",
    "sg:province":"MO",
    "wof:name":"Schmidt Chiropractic Clinic",
    "wof:placetype":"venue"
},
  "geometry": {"coordinates":[-94.842581,39.771342],"type":"Point"}
}