{
  "type": "Feature",
  "properties": {
    "iso:country":"US",
    "sg:address":"9853 Arv Ellen Dr",
    "sg:city":"Saint Louis",
    "sg:classifiers":[
        {
            "category":"Arts & Performance",
            "subcategory":"Theater",
            "type":"Entertainment"
        }
    ],
    "sg:phone":"+1 314 283 6669",
    "sg:postcode":"63123",
    "sg:province":"MO",
    "sg:tags":[
        "theatrical"
    ],
    "wof:name":"John Sennott IV",
    "wof:placetype":"venue"
},
  "geometry": {"coordinates":[-90.32960199999999,38.540448],"type":"Point"}
}