{
  "type": "Feature",
  "properties": {
    "iso:country":"US",
    "sg:address":"653 S Odell Ave",
    "sg:city":"Marshall",
    "sg:classifiers":[
        {
            "category":"Retail",
            "subcategory":"Laundry & Dry Cleaning",
            "type":"Services"
        }
    ],
    "sg:phone":"+1 660 831 1344",
    "sg:postcode":"65340",
    "sg:province":"MO",
    "sg:tags":[
        "drycleaning",
        "plant",
        "power"
    ],
    "wof:name":"Viking Cleaners",
    "wof:placetype":"venue"
},
  "geometry": {"coordinates":[-93.195013,39.115145],"type":"Point"}
}