{
  "type": "Feature",
  "properties": {
    "iso:country":"US",
    "sg:address":"109 S State St",
    "sg:city":"Knob Noster",
    "sg:classifiers":[
        {
            "category":"Professional",
            "subcategory":"Lawyer & Legal Services",
            "type":"Services"
        }
    ],
    "sg:phone":"+1 660 563 5436",
    "sg:postcode":"65336",
    "sg:province":"MO",
    "sg:tags":[
        "attorney"
    ],
    "wof:name":"W Christopher Hodge Law Office",
    "wof:placetype":"venue"
},
  "geometry": {"coordinates":[-93.55661499999999,38.764935],"type":"Point"}
}