{
  "type": "Feature",
  "properties": {
    "iso:country":"US",
    "sg:address":"3566 Broadway St",
    "sg:city":"Kansas City",
    "sg:classifiers":[
        {
            "category":"Health Services",
            "subcategory":"Chiropractor",
            "type":"Services"
        }
    ],
    "sg:phone":"+1 816 561 4444",
    "sg:postcode":"64111",
    "sg:province":"MO",
    "wof:name":"Chiromed Family Health",
    "wof:placetype":"venue"
},
  "geometry": {"coordinates":[-94.59053299999999,39.062315],"type":"Point"}
}