{
  "type": "Feature",
  "properties": {
    "iso:country":"US",
    "sg:address":"10786 Old Hwy 190",
    "sg:city":"Chillicothe",
    "sg:classifiers":[
        {
            "category":"Insurance",
            "subcategory":"Hazard Insurance",
            "type":"Services"
        }
    ],
    "sg:phone":"+1 660 646 9750",
    "sg:postcode":"64601",
    "sg:province":"MO",
    "sg:tags":[
        "bond"
    ],
    "wof:name":"24-8 Bail Bonds",
    "wof:placetype":"venue"
},
  "geometry": {"coordinates":[-93.58091,39.812539],"type":"Point"}
}