{
  "type": "Feature",
  "properties": {
    "iso:country":"US",
    "sg:address":"3326 S 1st Rd",
    "sg:city":"Humansville",
    "sg:classifiers":[
        {
            "category":"Farming",
            "subcategory":"Farm & Veterinary Services",
            "type":"Manufacturing & Wholesale Goods"
        }
    ],
    "sg:phone":"+1 417 754 1155",
    "sg:postcode":"65674",
    "sg:province":"MO",
    "sg:tags":[
        "livestock"
    ],
    "sg:website":"www.pedigreeinternational.com",
    "wof:name":"Pedigree International",
    "wof:placetype":"venue"
},
  "geometry": {"coordinates":[-93.63015300000001,37.785894],"type":"Point"}
}