{
  "type": "Feature",
  "properties": {
    "iso:country":"US",
    "sg:address":"16808 S State Route D",
    "sg:city":"Belton",
    "sg:classifiers":[
        {
            "category":"Place Of Worship",
            "subcategory":"Church",
            "type":"Public Place"
        },
        {
            "category":"Place Of Worship",
            "type":"Public Place"
        }
    ],
    "sg:phone":"+1 816 331 2222",
    "sg:postcode":"64012",
    "sg:province":"MO",
    "sg:tags":[
        "churches-episcopal-anglican",
        "churches-episcopal"
    ],
    "wof:name":"Magdalene St Mary Episcopal Church",
    "wof:placetype":"venue"
},
  "geometry": {"coordinates":[-94.585269,38.824893],"type":"Point"}
}