{
  "type": "Feature",
  "properties": {
    "iso:country":"US",
    "sg:address":"7713 Clayton Rd",
    "sg:city":"Saint Louis",
    "sg:classifiers":[
        {
            "category":"Professional",
            "subcategory":"Management & Consulting",
            "type":"Services"
        }
    ],
    "sg:phone":"+1 314 726 1300",
    "sg:postcode":"63117",
    "sg:province":"MO",
    "sg:tags":[
        "agency",
        "advertising"
    ],
    "wof:name":"Bream Marketing Group",
    "wof:placetype":"venue"
},
  "geometry": {"coordinates":[-90.337931,38.637775],"type":"Point"}
}