{
  "type": "Feature",
  "properties": {
    "iso:country":"US",
    "sg:address":"217 5th St",
    "sg:city":"Monett",
    "sg:classifiers":[
        {
            "category":"Government",
            "subcategory":"Office",
            "type":"Public Place"
        }
    ],
    "sg:phone":"+1 417 235 5306",
    "sg:postcode":"65708",
    "sg:province":"MO",
    "sg:tags":[
        "village"
    ],
    "wof:name":"Monett Building Inspector",
    "wof:placetype":"venue"
},
  "geometry": {"coordinates":[-93.92212499999999,36.921158],"type":"Point"}
}