{
  "type": "Feature",
  "properties": {
    "iso:country":"US",
    "sg:address":"7918 Gracemore Dr",
    "sg:city":"Kansas City",
    "sg:classifiers":[
        {
            "category":"Building & Trades",
            "subcategory":"Construction",
            "type":"Services"
        }
    ],
    "sg:phone":"+1 816 454 2743",
    "sg:postcode":"64119",
    "sg:province":"MO",
    "sg:tags":[
        "contractor"
    ],
    "wof:name":"Jim Dishmans Installions",
    "wof:placetype":"venue"
},
  "geometry": {"coordinates":[-94.487199,39.192033],"type":"Point"}
}