{
  "type": "Feature",
  "properties": {
    "iso:country":"US",
    "sg:address":"103 Ichord Ave",
    "sg:city":"Waynesville",
    "sg:classifiers":[
        {
            "category":"Health Services",
            "subcategory":"Doctor",
            "type":"Services"
        }
    ],
    "sg:phone":"+1 573 774 6988",
    "sg:postcode":"65583",
    "sg:province":"MO",
    "sg:tags":[
        "medical"
    ],
    "wof:name":"Boys & Girls Town of Missouri",
    "wof:placetype":"venue"
},
  "geometry": {"coordinates":[-92.223468,37.813163],"type":"Point"}
}