{
  "type": "Feature",
  "properties": {
    "iso:country":"US",
    "sg:address":"1901 S Market St",
    "sg:city":"Holden",
    "sg:classifiers":[
        {
            "category":"Education",
            "subcategory":"School",
            "type":"Public Place"
        }
    ],
    "sg:phone":"+1 816 732 4136",
    "sg:postcode":"64040",
    "sg:province":"MO",
    "wof:name":"Holden Elementary School",
    "wof:placetype":"venue"
},
  "geometry": {"coordinates":[-93.991766,38.703517],"type":"Point"}
}