{
  "type": "Feature",
  "properties": {
    "iso:country":"US",
    "sg:address":"9015 Kings Chapel Rd",
    "sg:city":"Centertown",
    "sg:classifiers":[
        {
            "category":"Real Estate",
            "subcategory":"Real Estate Operator",
            "type":"Services"
        }
    ],
    "sg:phone":"+1 573 584 3365",
    "sg:postcode":"65023",
    "sg:province":"MO",
    "sg:tags":[
        "property",
        "lessor"
    ],
    "wof:name":"Rosemary Wolken",
    "wof:placetype":"venue"
},
  "geometry": {"coordinates":[-92.36114000000001,38.630966],"type":"Point"}
}