{
  "type": "Feature",
  "properties": {
    "addr:full":"1900 S Range Line Rd Joplin MO 64804",
    "addr:housenumber":"1900",
    "addr:postcode":"64804",
    "addr:street":"S Range Line Rd",
    "iso:country":"US",
    "sg:address":"1900 S Range Line Rd",
    "sg:city":"Joplin",
    "sg:classifiers":[
        {
            "category":"Shopping",
            "subcategory":"Clothing, Apparel, & Fashions",
            "type":"Retail Goods"
        }
    ],
    "sg:phone":"+1 417 206 4365",
    "sg:postcode":"64804",
    "sg:province":"MO",
    "wof:name":"Catherines",
    "wof:placetype":"venue"
},
  "geometry": {"coordinates":[-94.47788,37.069244],"type":"Point"}
}