{
  "type": "Feature",
  "properties": {
    "iso:country":"US",
    "sg:address":"1405 W Ridgecrest St",
    "sg:city":"Ozark",
    "sg:classifiers":[
        {
            "category":"Transit Center",
            "subcategory":"Freight",
            "type":"Transportation"
        },
        {
            "category":"Freight",
            "type":"Transportation"
        }
    ],
    "sg:phone":"+1 417 581 3304",
    "sg:postcode":"65721",
    "sg:province":"MO",
    "sg:tags":[
        "local",
        "trucking-motor",
        "trucking"
    ],
    "wof:name":"C & J Trucking",
    "wof:placetype":"venue"
},
  "geometry": {"coordinates":[-93.21709,36.99577],"type":"Point"}
}