{
  "type": "Feature",
  "properties": {
    "iso:country":"US",
    "sg:address":"520 W 75th St",
    "sg:city":"Kansas City",
    "sg:classifiers":[
        {
            "category":"Restaurant",
            "type":"Food & Drink"
        },
        {
            "category":"Brewery",
            "type":"Food & Drink"
        }
    ],
    "sg:menulink":"http://www.allmenus.com/mo/kaw/9870-75th-street-brewery/menu/",
    "sg:phone":"+1 816 523 4677",
    "sg:postcode":"64114",
    "sg:province":"MO",
    "sg:tags":[
        "american"
    ],
    "wof:name":"75th Street Brewery",
    "wof:placetype":"venue"
},
  "geometry": {"coordinates":[-94.59605999999999,38.992563],"type":"Point"}
}