{
  "type": "Feature",
  "properties": {
    "iso:country":"US",
    "sg:address":"6358 Delmar Blvd",
    "sg:city":"Saint Louis",
    "sg:classifiers":[
        {
            "category":"Communications",
            "subcategory":"Newspaper",
            "type":"Services"
        }
    ],
    "sg:phone":"+1 314 754 5966",
    "sg:postcode":"63130",
    "sg:province":"MO",
    "sg:tags":[
        "print",
        "medium"
    ],
    "wof:name":"River Front Times",
    "wof:placetype":"venue"
},
  "geometry": {"coordinates":[-90.303325,38.655675],"type":"Point"}
}