{
  "type": "Feature",
  "properties": {
    "iso:country":"US",
    "sg:address":"325 W Burnam Rd",
    "sg:city":"Columbia",
    "sg:classifiers":[
        {
            "category":"Professional",
            "subcategory":"Management & Consulting",
            "type":"Services"
        }
    ],
    "sg:phone":"+1 573 449 0154",
    "sg:postcode":"65203",
    "sg:province":"MO",
    "sg:tags":[
        "farm"
    ],
    "wof:name":"Mohatt Properties Inc",
    "wof:placetype":"venue"
},
  "geometry": {"coordinates":[-92.343407,38.940705],"type":"Point"}
}