{
  "type": "Feature",
  "properties": {
    "addr:full":"3330 S National Ave Springfield MO 65807",
    "addr:housenumber":"3330",
    "addr:postcode":"65807",
    "addr:street":"S National Ave",
    "iso:country":"US",
    "sg:address":"3330 S National Ave",
    "sg:city":"Springfield",
    "sg:classifiers":[
        {
            "category":"Government",
            "subcategory":"Office",
            "type":"Public Place"
        },
        {
            "category":"Education",
            "subcategory":"Vocational School",
            "type":"Public Place"
        }
    ],
    "sg:phone":"+1 417 823 7300",
    "sg:postcode":"65807",
    "sg:province":"MO",
    "sg:tags":[
        "training",
        "computer",
        "national",
        "security"
    ],
    "sg:website":"www.nhsgf.com",
    "wof:name":"New Horizons Computer Learning",
    "wof:placetype":"venue"
},
  "geometry": {"coordinates":[-93.277508,37.154799],"type":"Point"}
}