{
  "type": "Feature",
  "properties": {
    "iso:country":"US",
    "sg:address":"146 Payday Hill Rd",
    "sg:city":"Protem",
    "sg:classifiers":[
        {
            "category":"Professional",
            "subcategory":"Detective & Security Services",
            "type":"Services"
        }
    ],
    "sg:phone":"+1 417 785 4543",
    "sg:postcode":"65733",
    "sg:province":"MO",
    "sg:tags":[
        "information",
        "bureau"
    ],
    "wof:name":"L K Transcription Service",
    "wof:placetype":"venue"
},
  "geometry": {"coordinates":[-92.801086,36.549783],"type":"Point"}
}