{
  "type": "Feature",
  "properties": {
    "iso:country":"US",
    "sg:address":"828 N Scott Ave",
    "sg:city":"Belton",
    "sg:classifiers":[
        {
            "category":"Retail",
            "subcategory":"Self-service Laundry",
            "type":"Services"
        }
    ],
    "sg:phone":"+1 816 322 3115",
    "sg:postcode":"64012",
    "sg:province":"MO",
    "sg:tags":[
        "coin"
    ],
    "wof:name":"Belton Happy Wash Laundry",
    "wof:placetype":"venue"
},
  "geometry": {"coordinates":[-94.534042,38.826477],"type":"Point"}
}