{
  "type": "Feature",
  "properties": {
    "iso:country":"US",
    "sg:address":"18077 Crow Rd",
    "sg:city":"Seneca",
    "sg:classifiers":[
        {
            "category":"Retail",
            "subcategory":"Auto Repair",
            "type":"Services"
        }
    ],
    "sg:phone":"+1 417 776 3679",
    "sg:postcode":"64865",
    "sg:province":"MO",
    "sg:tags":[
        "wrecker"
    ],
    "wof:name":"Lankford's Garage",
    "wof:placetype":"venue"
},
  "geometry": {"coordinates":[-94.556949,36.818763],"type":"Point"}
}