{
  "type": "Feature",
  "properties": {
    "iso:country":"US",
    "sg:address":"102 N Range Line Rd",
    "sg:city":"Joplin",
    "sg:classifiers":[
        {
            "category":"Personal",
            "subcategory":"Beauty Salon",
            "type":"Services"
        }
    ],
    "sg:phone":"+1 417 206 7376",
    "sg:postcode":"64801",
    "sg:province":"MO",
    "sg:tags":[
        "shop"
    ],
    "wof:name":"Robyn Paul Salon",
    "wof:placetype":"venue"
},
  "geometry": {"coordinates":[-94.476951,37.093638],"type":"Point"}
}