{
  "type": "Feature",
  "properties": {
    "iso:country":"US",
    "sg:address":"1053 Washington Square Shopping Ctr",
    "sg:city":"Washington",
    "sg:classifiers":[
        {
            "category":"Insurance",
            "subcategory":"Hazard Insurance",
            "type":"Services"
        },
        {
            "category":"Travel",
            "subcategory":"Travel Agent",
            "type":"Entertainment"
        }
    ],
    "sg:phone":"+1 636 239 6791",
    "sg:postcode":"63090",
    "sg:province":"MO",
    "sg:tags":[
        "commercial",
        "agency",
        "services-commercial",
        "business"
    ],
    "sg:website":"http://aaa.com",
    "wof:name":"Aaa",
    "wof:placetype":"venue"
},
  "geometry": {"coordinates":[-91.00411,38.536111],"type":"Point"}
}