{
  "type": "Feature",
  "properties": {
    "iso:country":"US",
    "sg:address":"214 S Main St",
    "sg:city":"Joplin",
    "sg:classifiers":[
        {
            "category":"Real Estate",
            "subcategory":"Real Estate Agent",
            "type":"Services"
        }
    ],
    "sg:phone":"+1 417 781 7171",
    "sg:postcode":"64801",
    "sg:province":"MO",
    "wof:name":"J A Britt Real Estate",
    "wof:placetype":"venue"
},
  "geometry": {"coordinates":[-94.513362,37.088787],"type":"Point"}
}