{
  "type": "Feature",
  "properties": {
    "iso:country":"US",
    "sg:address":"2733 Howard St",
    "sg:city":"St Louis",
    "sg:classifiers":[
        {
            "category":"Shopping",
            "subcategory":"Gifts & Souvenirs",
            "type":"Retail Goods"
        }
    ],
    "sg:phone":"+1 314 535 7989",
    "sg:postcode":"63106",
    "sg:province":"MO",
    "sg:tags":[
        "collectible"
    ],
    "wof:name":"Mamma Lo's Collectibles",
    "wof:placetype":"venue"
},
  "geometry": {"coordinates":[-90.21539300000001,38.64667],"type":"Point"}
}