{
  "type": "Feature",
  "properties": {
    "iso:country":"US",
    "sg:address":"130 W Jefferson St",
    "sg:city":"Clinton",
    "sg:classifiers":[
        {
            "category":"Banks & Credit Unions",
            "subcategory":"Investment Brokerage",
            "type":"Services"
        }
    ],
    "sg:phone":"+1 660 885 6148",
    "sg:postcode":"64735",
    "sg:province":"MO",
    "sg:tags":[
        "stock",
        "bond"
    ],
    "wof:name":"Edward Jones Co",
    "wof:placetype":"venue"
},
  "geometry": {"coordinates":[-93.776668,38.369352],"type":"Point"}
}