{
  "type": "Feature",
  "properties": {
    "iso:country":"US",
    "sg:address":"214 S Lincoln Dr",
    "sg:city":"Troy",
    "sg:classifiers":[
        {
            "category":"Professional",
            "subcategory":"Art Services",
            "type":"Services"
        },
        {
            "category":"Personal",
            "type":"Services"
        },
        {
            "category":"Retail",
            "subcategory":"Event Space",
            "type":"Services"
        }
    ],
    "sg:phone":"+1 636 734 4373",
    "sg:postcode":"63379",
    "sg:province":"MO",
    "sg:tags":[
        "videography",
        "facility",
        "photography",
        "hall",
        "planning",
        "reception",
        "wedding",
        "party",
        "banquet"
    ],
    "wof:name":"Debis Digital Photography",
    "wof:placetype":"venue"
},
  "geometry": {"coordinates":[-90.968782,38.97815],"type":"Point"}
}