{
  "type": "Feature",
  "properties": {
    "iso:country":"US",
    "sg:address":"37045 W 63rd St",
    "sg:city":"Camden",
    "sg:classifiers":[
        {
            "category":"Wholesale",
            "subcategory":"Computers",
            "type":"Manufacturing & Wholesale Goods"
        },
        {
            "category":"Professional",
            "subcategory":"Computer Services",
            "type":"Services"
        },
        {
            "category":"Internet Cafe",
            "subcategory":"None",
            "type":"Food & Drink"
        }
    ],
    "sg:phone":"+1 816 770 5509",
    "sg:postcode":"64017",
    "sg:province":"MO",
    "sg:tags":[
        "equipment",
        "product",
        "software"
    ],
    "wof:name":"C M R, Inc",
    "wof:placetype":"venue"
},
  "geometry": {"coordinates":[-94.059421,39.205104],"type":"Point"}
}