{
  "type": "Feature",
  "properties": {
    "iso:country":"US",
    "sg:address":"24 Plz 94",
    "sg:city":"St Peters",
    "sg:classifiers":[
        {
            "category":"Communications",
            "type":"Services"
        }
    ],
    "sg:phone":"+1 636 922 2940",
    "sg:postcode":"63376",
    "sg:province":"MO",
    "wof:name":"ABS Communications",
    "wof:placetype":"venue"
},
  "geometry": {"coordinates":[-90.591015,38.749746],"type":"Point"}
}