{
  "type": "Feature",
  "properties": {
    "iso:country":"US",
    "sg:address":"160 E State Hwy CC",
    "sg:city":"Nixa",
    "sg:classifiers":[
        {
            "category":"Retail",
            "subcategory":"Auto Repair",
            "type":"Services"
        }
    ],
    "sg:phone":"+1 417 725 3586",
    "sg:postcode":"65714",
    "sg:province":"MO",
    "sg:tags":[
        "repairing",
        "automobile"
    ],
    "wof:name":"Vaughan's Car Care Ctr",
    "wof:placetype":"venue"
},
  "geometry": {"coordinates":[-93.293708,37.07281],"type":"Point"}
}