{
  "type": "Feature",
  "properties": {
    "iso:country":"US",
    "sg:address":"1016 N Willis St",
    "sg:city":"Independence",
    "sg:classifiers":[
        {
            "category":"Retail",
            "subcategory":"Auto Repair",
            "type":"Services"
        }
    ],
    "sg:phone":"+1 816 254 2305",
    "sg:postcode":"64050",
    "sg:province":"MO",
    "sg:tags":[
        "shop",
        "automotive"
    ],
    "wof:name":"Carls Radiator Service",
    "wof:placetype":"venue"
},
  "geometry": {"coordinates":[-94.429277,39.102506],"type":"Point"}
}