{
  "type": "Feature",
  "properties": {
    "iso:country":"US",
    "sg:address":"3616 Frann Lynn Ct",
    "sg:city":"St Louis",
    "sg:classifiers":[
        {
            "category":"Restaurant",
            "type":"Food & Drink"
        }
    ],
    "sg:phone":"+1 314 428 1947",
    "sg:postcode":"63114",
    "sg:province":"MO",
    "sg:tags":[
        "caterer"
    ],
    "wof:name":"Corrine's Catering",
    "wof:placetype":"venue"
},
  "geometry": {"coordinates":[-90.356235,38.720422],"type":"Point"}
}