{
  "type": "Feature",
  "properties": {
    "iso:country":"US",
    "sg:address":"3718 S Spring Ave",
    "sg:city":"St Louis",
    "sg:classifiers":[
        {
            "category":"Retail",
            "subcategory":"Repair Shop",
            "type":"Services"
        }
    ],
    "sg:phone":"+1 314 771 1914",
    "sg:postcode":"63116",
    "sg:province":"MO",
    "sg:tags":[
        "upholsterer"
    ],
    "wof:name":"Limmany Upholstery",
    "wof:placetype":"venue"
},
  "geometry": {"coordinates":[-90.248195,38.589746],"type":"Point"}
}