{
  "type": "Feature",
  "properties": {
    "iso:country":"US",
    "sg:address":"309 N Ash St Ste 101",
    "sg:city":"Buffalo",
    "sg:classifiers":[
        {
            "category":"Wholesale",
            "subcategory":"Medical Equipment & Supplies",
            "type":"Manufacturing & Wholesale Goods"
        },
        {
            "category":"Health Services",
            "subcategory":"Hospital",
            "type":"Services"
        },
        {
            "category":"Health Services",
            "subcategory":"Nursing And Care Facility",
            "type":"Services"
        },
        {
            "category":"Health Services",
            "subcategory":"Health Practitioner",
            "type":"Services"
        },
        {
            "category":"Shopping",
            "subcategory":"Pharmacy",
            "type":"Retail Goods"
        }
    ],
    "sg:phone":"+1 417 345 2244",
    "sg:postcode":"65622",
    "sg:province":"MO",
    "sg:tags":[
        "physician",
        "refinishing",
        "home",
        "surgeon",
        "eldercare-home",
        "equipment-repairing"
    ],
    "sg:website":"http://www.citizensmemorial.com",
    "wof:name":"Citizens Memorial Hm Hlth Eqp",
    "wof:placetype":"venue"
},
  "geometry": {"coordinates":[-93.104079,37.646017],"type":"Point"}
}