{
  "type": "Feature",
  "properties": {
    "iso:country":"US",
    "sg:address":"5703 N Flora Ave",
    "sg:city":"Kansas City",
    "sg:classifiers":[
        {
            "category":"Organizations",
            "subcategory":"Religious Organization",
            "type":"Services"
        }
    ],
    "sg:phone":"+1 816 452 2077",
    "sg:postcode":"64118",
    "sg:province":"MO",
    "wof:name":"Gladstone Church of Christ",
    "wof:placetype":"venue"
},
  "geometry": {"coordinates":[-94.562448,39.199398],"type":"Point"}
}