{
  "type": "Feature",
  "properties": {
    "iso:country":"US",
    "sg:address":"6803 Longview Rd",
    "sg:city":"Kansas City",
    "sg:classifiers":[
        {
            "category":"Professional",
            "subcategory":"Accounting & Tax Preparation",
            "type":"Services"
        }
    ],
    "sg:phone":"+1 816 765 6480",
    "sg:postcode":"64134",
    "sg:province":"MO",
    "sg:tags":[
        "billing"
    ],
    "wof:name":"Connect For Less",
    "wof:placetype":"venue"
},
  "geometry": {"coordinates":[-94.511543,38.91529],"type":"Point"}
}