{
  "type": "Feature",
  "properties": {
    "iso:country":"US",
    "sg:address":"1100 S Roache St",
    "sg:city":"California",
    "sg:classifiers":[
        {
            "category":"Retail",
            "subcategory":"Auto Repair",
            "type":"Services"
        }
    ],
    "sg:phone":"+1 573 796 2625",
    "sg:postcode":"65018",
    "sg:province":"MO",
    "sg:tags":[
        "exchanging",
        "engine",
        "general"
    ],
    "wof:name":"Fischers Auto Repair Inc",
    "wof:placetype":"venue"
},
  "geometry": {"coordinates":[-92.569357,38.622727],"type":"Point"}
}