{
  "type": "Feature",
  "properties": {
    "iso:country":"US",
    "sg:address":"9004 Saint Charles Rock Rd",
    "sg:city":"Overland",
    "sg:classifiers":[
        {
            "category":"Personal",
            "subcategory":"Tattoo Parlor",
            "type":"Services"
        }
    ],
    "sg:phone":"+1 314 423 1179",
    "sg:postcode":"63114",
    "sg:province":"MO",
    "sg:tags":[
        "tattooing"
    ],
    "wof:name":"Tattoo Hotline",
    "wof:placetype":"venue"
},
  "geometry": {"coordinates":[-90.354512,38.712932],"type":"Point"}
}