{
  "type": "Feature",
  "properties": {
    "iso:country":"US",
    "sg:address":"12 Co Rd 465",
    "sg:city":"Poplar Bluff",
    "sg:classifiers":[
        {
            "category":"Manufacturing",
            "subcategory":"Tools & Machinery",
            "type":"Manufacturing & Wholesale Goods"
        }
    ],
    "sg:phone":"+1 314 785 9223",
    "sg:postcode":"63901",
    "sg:province":"MO",
    "sg:tags":[
        "machine",
        "shop",
        "metal"
    ],
    "wof:name":"Central Machine Company",
    "wof:placetype":"venue"
},
  "geometry": {"coordinates":[-90.436284,36.744876],"type":"Point"}
}