{
  "type": "Feature",
  "properties": {
    "iso:country":"US",
    "sg:address":"2662 Stone Rd",
    "sg:city":"Noel",
    "sg:classifiers":[
        {
            "category":"Building & Trades",
            "subcategory":"Construction",
            "type":"Services"
        }
    ],
    "sg:phone":"+1 417 762 4001",
    "sg:postcode":"64854",
    "sg:province":"MO",
    "sg:tags":[
        "wallcoverings-installation",
        "wallpaper",
        "painting",
        "contractor"
    ],
    "wof:name":"Rozell Painting",
    "wof:placetype":"venue"
},
  "geometry": {"coordinates":[-94.54731200000001,36.568032],"type":"Point"}
}