{
  "type": "Feature",
  "properties": {
    "iso:country":"US",
    "sg:address":"810 N Water St",
    "sg:city":"Butler",
    "sg:classifiers":[
        {
            "category":"Mining & Drilling",
            "type":"Manufacturing & Wholesale Goods"
        }
    ],
    "sg:phone":"+1 660 679 4327",
    "sg:postcode":"64730",
    "sg:province":"MO",
    "sg:tags":[
        "development",
        "gas",
        "oil",
        "exploration"
    ],
    "wof:name":"Spendex",
    "wof:placetype":"venue"
},
  "geometry": {"coordinates":[-94.337069,38.265641],"type":"Point"}
}