{
  "type": "Feature",
  "properties": {
    "iso:country":"US",
    "sg:address":"709 Mikel St",
    "sg:city":"Columbia",
    "sg:classifiers":[
        {
            "category":"Building & Trades",
            "subcategory":"Cleaning & Sanitation",
            "type":"Services"
        }
    ],
    "sg:phone":"+1 573 499 3872",
    "sg:postcode":"65203",
    "sg:province":"MO",
    "sg:tags":[
        "help",
        "maintenance",
        "supply"
    ],
    "wof:name":"Throwers Cleaning",
    "wof:placetype":"venue"
},
  "geometry": {"coordinates":[-92.34856499999999,38.962671],"type":"Point"}
}