{
  "type": "Feature",
  "properties": {
    "iso:country":"US",
    "sg:address":"711 N Pine St",
    "sg:city":"Rolla",
    "sg:classifiers":[
        {
            "category":"Personal",
            "subcategory":"Tattoo Parlor",
            "type":"Services"
        },
        {
            "category":"Personal",
            "subcategory":"Piercing",
            "type":"Services"
        }
    ],
    "sg:phone":"+1 573 341 2800",
    "sg:postcode":"65401",
    "sg:province":"MO",
    "sg:tags":[
        "body"
    ],
    "wof:name":"Bloodlines Body Art",
    "wof:placetype":"venue"
},
  "geometry": {"coordinates":[-91.77160600000001,37.949183],"type":"Point"}
}