{
  "type": "Feature",
  "properties": {
    "iso:country":"US",
    "sg:address":"105 SW 12 St",
    "sg:city":"Oak Grove",
    "sg:classifiers":[
        {
            "category":"Health Services",
            "subcategory":"Chiropractor",
            "type":"Services"
        }
    ],
    "sg:phone":"+1 816 625 4580",
    "sg:postcode":"64075",
    "sg:province":"MO",
    "wof:name":"Wilkinson Robert E",
    "wof:placetype":"venue"
},
  "geometry": {"coordinates":[-94.13100799999999,39.004832],"type":"Point"}
}