{
  "type": "Feature",
  "properties": {
    "iso:country":"US",
    "sg:address":"405 N Main St",
    "sg:city":"Liberty",
    "sg:classifiers":[
        {
            "category":"Professional",
            "subcategory":"Detective & Security Services",
            "type":"Services"
        }
    ],
    "sg:phone":"+1 816 407 7500",
    "sg:postcode":"64068",
    "sg:province":"MO",
    "sg:tags":[
        "system"
    ],
    "wof:name":"Tree Frog Surveillance",
    "wof:placetype":"venue"
},
  "geometry": {"coordinates":[-94.42043200000001,39.250165],"type":"Point"}
}