{
  "type": "Feature",
  "properties": {
    "iso:country":"US",
    "sg:address":"1537 Grand Blvd",
    "sg:city":"Kansas City",
    "sg:classifiers":[
        {
            "category":"Personal",
            "subcategory":"Beauty Salon",
            "type":"Services"
        }
    ],
    "sg:phone":"+1 816 842 3555",
    "sg:postcode":"64108",
    "sg:province":"MO",
    "sg:tags":[
        "shop"
    ],
    "wof:name":"Starr Image Beauty Studio",
    "wof:placetype":"venue"
},
  "geometry": {"coordinates":[-94.581097,39.094888],"type":"Point"}
}