{
  "type": "Feature",
  "properties": {
    "iso:country":"US",
    "sg:address":"701 N 5th St",
    "sg:city":"Saint Charles",
    "sg:classifiers":[
        {
            "category":"Social Services",
            "subcategory":"Child Care",
            "type":"Services"
        }
    ],
    "sg:phone":"+1 636 255 0800",
    "sg:postcode":"63301",
    "sg:province":"MO",
    "sg:tags":[
        "day"
    ],
    "wof:name":"Shining Stars Learning Center",
    "wof:placetype":"venue"
},
  "geometry": {"coordinates":[-90.48281,38.789069],"type":"Point"}
}