{
  "type": "Feature",
  "properties": {
    "iso:country":"US",
    "sg:address":"2010 Bernadette Dr",
    "sg:city":"Columbia",
    "sg:classifiers":[
        {
            "category":"Restaurant",
            "type":"Food & Drink"
        }
    ],
    "sg:menulink":"http://www.allmenus.com/mo/missouri/103715-ruby-tuesdays/menu/",
    "sg:phone":"+1 573 446 8212",
    "sg:postcode":"65203",
    "sg:province":"MO",
    "sg:tags":[
        "burger",
        "american"
    ],
    "wof:name":"Ruby Tuesdays",
    "wof:placetype":"venue"
},
  "geometry": {"coordinates":[-92.370778,38.965375],"type":"Point"}
}