{
  "type": "Feature",
  "properties": {
    "iso:country":"US",
    "sg:address":"64 Gravois Rd",
    "sg:city":"Fenton",
    "sg:classifiers":[
        {
            "category":"Autos & Motor Vehicles",
            "subcategory":"Boat Sales",
            "type":"Retail Goods"
        }
    ],
    "sg:phone":"+1 636 305 0405",
    "sg:postcode":"63026",
    "sg:province":"MO",
    "sg:tags":[
        "dealer",
        "sales"
    ],
    "wof:name":"Brannan's Marine & Motorsports",
    "wof:placetype":"venue"
},
  "geometry": {"coordinates":[-90.43371999999999,38.511143],"type":"Point"}
}