{
  "type": "Feature",
  "properties": {
    "iso:country":"US",
    "sg:address":"5706 S Michigan Ave",
    "sg:city":"Springfield",
    "sg:classifiers":[
        {
            "category":"Health Services",
            "subcategory":"Health Practitioner",
            "type":"Services"
        }
    ],
    "sg:phone":"+1 417 848 4667",
    "sg:postcode":"65810",
    "sg:province":"MO",
    "sg:tags":[
        "psychologist"
    ],
    "wof:name":"Karen E Lee",
    "wof:placetype":"venue"
},
  "geometry": {"coordinates":[-93.30211199999999,37.110363],"type":"Point"}
}