{
  "type": "Feature",
  "properties": {
    "iso:country":"US",
    "sg:address":"7606 Alicia Ave",
    "sg:city":"Saint Louis",
    "sg:classifiers":[
        {
            "category":"Health Services",
            "subcategory":"Chiropractor",
            "type":"Services"
        }
    ],
    "sg:phone":"+1 314 645 4268",
    "sg:postcode":"63143",
    "sg:province":"MO",
    "wof:name":"Wilkinson Nancy A DC",
    "wof:placetype":"venue"
},
  "geometry": {"coordinates":[-90.324303,38.620499],"type":"Point"}
}