{
  "type": "Feature",
  "properties": {
    "iso:country":"US",
    "sg:address":"600 N Boonville Ave",
    "sg:city":"Springfield",
    "sg:classifiers":[
        {
            "category":"Real Estate",
            "subcategory":"Real Estate Operator",
            "type":"Services"
        }
    ],
    "sg:phone":"+1 417 831 6665",
    "sg:postcode":"65806",
    "sg:province":"MO",
    "sg:tags":[
        "building",
        "nonresidential"
    ],
    "wof:name":"Olde Towne Antique Mall",
    "wof:placetype":"venue"
},
  "geometry": {"coordinates":[-93.29236899999999,37.21505],"type":"Point"}
}