{
  "type": "Feature",
  "properties": {
    "iso:country":"US",
    "sg:address":"4 N Central Ave",
    "sg:city":"St Louis",
    "sg:classifiers":[
        {
            "category":"Shopping",
            "subcategory":"Tobacco",
            "type":"Retail Goods"
        }
    ],
    "sg:phone":"+1 314 727 5667",
    "sg:postcode":"63105",
    "sg:province":"MO",
    "sg:tags":[
        "cigarette",
        "cigar",
        "dealer"
    ],
    "wof:name":"J R Cigars & Fragrances",
    "wof:placetype":"venue"
},
  "geometry": {"coordinates":[-90.338007,38.651648],"type":"Point"}
}