{
  "type": "Feature",
  "properties": {
    "iso:country":"US",
    "sg:address":"6 N Iron St",
    "sg:city":"Salem",
    "sg:classifiers":[
        {
            "category":"Real Estate",
            "subcategory":"Real Estate Agent",
            "type":"Services"
        }
    ],
    "sg:phone":"+1 573 729 2255",
    "sg:postcode":"65560",
    "sg:province":"MO",
    "wof:name":"Carl Hale Real Estate Co",
    "wof:placetype":"venue"
},
  "geometry": {"coordinates":[-91.535117,37.643709],"type":"Point"}
}