{
  "type": "Feature",
  "properties": {
    "iso:country":"US",
    "sg:address":"1455 Triad Center Dr",
    "sg:city":"Saint Peters",
    "sg:classifiers":[
        {
            "category":"Health Services",
            "subcategory":"Doctor",
            "type":"Services"
        }
    ],
    "sg:phone":"+1 636 928 5550",
    "sg:postcode":"63376",
    "sg:province":"MO",
    "wof:name":"Burns W Paul",
    "wof:placetype":"venue"
},
  "geometry": {"coordinates":[-90.587383,38.756235],"type":"Point"}
}