{
  "type": "Feature",
  "properties": {
    "iso:country":"US",
    "sg:address":"13595 SW US Hwy 59 W",
    "sg:city":"Rushville",
    "sg:classifiers":[
        {
            "category":"Food & Beverages",
            "subcategory":"Groceries & Convenience Stores",
            "type":"Retail Goods"
        }
    ],
    "sg:phone":"+1 816 579 5661",
    "sg:postcode":"64484",
    "sg:province":"MO",
    "wof:name":"Fisca Oil Co",
    "wof:placetype":"venue"
},
  "geometry": {"coordinates":[-95.10135,39.557398],"type":"Point"}
}