{
  "type": "Feature",
  "properties": {
    "iso:country":"US",
    "sg:address":"2109 Smizer Station Rd",
    "sg:city":"Valley Park",
    "sg:classifiers":[
        {
            "category":"Restaurant",
            "type":"Food & Drink"
        }
    ],
    "sg:menulink":"http://www.allmenus.com/mo/meramec/194270-mcdonalds/menu/",
    "sg:postcode":"63088",
    "sg:province":"MO",
    "sg:tags":[
        "burger",
        "american"
    ],
    "wof:name":"McDonald's",
    "wof:placetype":"venue"
},
  "geometry": {"coordinates":[-90.494131,38.537654],"type":"Point"}
}