{
  "type": "Feature",
  "properties": {
    "addr:full":"1907 Locust St St Louis MO 63103",
    "addr:housenumber":"1907",
    "addr:postcode":"63103",
    "addr:street":"Locust St",
    "iso:country":"US",
    "sg:address":"1907 Locust St",
    "sg:city":"St Louis",
    "sg:classifiers":[
        {
            "category":"Organizations",
            "subcategory":"Labor Organization",
            "type":"Services"
        }
    ],
    "sg:phone":"+1 314 231 7665",
    "sg:postcode":"63103",
    "sg:province":"MO",
    "wof:name":"American Postal Workers Union",
    "wof:placetype":"venue"
},
  "geometry": {"coordinates":[-90.208001,38.632994],"type":"Point"}
}