{
  "type": "Feature",
  "properties": {
    "iso:country":"US",
    "sg:address":"1907 Locust St",
    "sg:city":"St Louis",
    "sg:classifiers":[
        {
            "category":"Organizations",
            "subcategory":"Labor Organization",
            "type":"Services"
        }
    ],
    "sg:phone":"+1 314 231 7665",
    "sg:postcode":"63103",
    "sg:province":"MO",
    "wof:name":"American Postal Workers Union",
    "wof:placetype":"venue"
},
  "geometry": {"coordinates":[-90.208001,38.632994],"type":"Point"}
}