{
  "type": "Feature",
  "properties": {
    "iso:country":"US",
    "sg:address":"1237 Craig Rd",
    "sg:city":"St Louis",
    "sg:classifiers":[
        {
            "category":"Retail",
            "subcategory":"Laundry & Dry Cleaning",
            "type":"Services"
        }
    ],
    "sg:phone":"+1 314 993 1011",
    "sg:postcode":"63146",
    "sg:province":"MO",
    "sg:tags":[
        "cleaners",
        "upholstery",
        "rug",
        "carpet"
    ],
    "wof:name":"Duraclean",
    "wof:placetype":"venue"
},
  "geometry": {"coordinates":[-90.43798200000001,38.678211],"type":"Point"}
}