{
  "type": "Feature",
  "properties": {
    "iso:country":"US",
    "sg:address":"4139 Shreve Ave",
    "sg:city":"Saint Louis",
    "sg:classifiers":[
        {
            "category":"Professional",
            "subcategory":"Business Services",
            "type":"Services"
        }
    ],
    "sg:phone":"+1 314 385 7029",
    "sg:postcode":"63115",
    "sg:province":"MO",
    "wof:name":"Lachelle Fullilove",
    "wof:placetype":"venue"
},
  "geometry": {"coordinates":[-90.242008,38.679089],"type":"Point"}
}