{
  "type": "Feature",
  "properties": {
    "addr:full":"1841 N Bluff St Fulton MO 65251",
    "addr:housenumber":"1841",
    "addr:postcode":"65251",
    "addr:street":"N Bluff St",
    "iso:country":"US",
    "sg:address":"1841 N Bluff St",
    "sg:city":"Fulton",
    "sg:classifiers":[
        {
            "category":"Restaurant",
            "type":"Food & Drink"
        }
    ],
    "sg:menulink":"http://www.allmenus.com/mo/east-fulton/182230-wendys/menu/",
    "sg:phone":"+1 573 592 7714",
    "sg:postcode":"65251",
    "sg:province":"MO",
    "sg:tags":[
        "burger",
        "american",
        "soup"
    ],
    "wof:name":"Wendy's",
    "wof:placetype":"venue"
},
  "geometry": {"coordinates":[-91.94387,38.864979],"type":"Point"}
}