{
  "type": "Feature",
  "properties": {
    "iso:country":"US",
    "sg:address":"2825 S Glenstone Ave",
    "sg:city":"Springfield",
    "sg:classifiers":[
        {
            "category":"Shopping",
            "type":"Retail Goods"
        }
    ],
    "sg:phone":"+1 888 673 9649",
    "sg:postcode":"65804",
    "sg:province":"MO",
    "sg:tags":[
        "merchandise"
    ],
    "wof:name":"Successries of Bttlefield Mall",
    "wof:placetype":"venue"
},
  "geometry": {"coordinates":[-93.262649,37.160053],"type":"Point"}
}