{
  "type": "Feature",
  "properties": {
    "iso:country":"US",
    "sg:address":"8135 N Stoddard Ave",
    "sg:city":"Kansas City",
    "sg:classifiers":[
        {
            "category":"Building & Trades",
            "subcategory":"Construction",
            "type":"Services"
        }
    ],
    "sg:phone":"+1 816 741 1692",
    "sg:postcode":"64152",
    "sg:province":"MO",
    "sg:tags":[
        "contractor"
    ],
    "wof:name":"Acv Decorative Con Restoration",
    "wof:placetype":"venue"
},
  "geometry": {"coordinates":[-94.665541,39.241302],"type":"Point"}
}