{
  "type": "Feature",
  "properties": {
    "iso:country":"US",
    "sg:address":"10150 Morgan Rd",
    "sg:city":"Festus",
    "sg:classifiers":[
        {
            "category":"Real Estate",
            "subcategory":"Real Estate Agent",
            "type":"Services"
        }
    ],
    "sg:phone":"+1 636 931 4455",
    "sg:postcode":"63028",
    "sg:province":"MO",
    "wof:name":"Lighthouse Real Estate & Assoc",
    "wof:placetype":"venue"
},
  "geometry": {"coordinates":[-90.49092899999999,38.24599],"type":"Point"}
}