{
  "type": "Feature",
  "properties": {
    "iso:country":"US",
    "sg:address":"4404 McPherson Ave",
    "sg:city":"St Louis",
    "sg:classifiers":[
        {
            "category":"Building & Trades",
            "subcategory":"Construction",
            "type":"Services"
        }
    ],
    "sg:phone":"+1 314 266 3749",
    "sg:postcode":"63108",
    "sg:province":"MO",
    "sg:tags":[
        "interior",
        "design"
    ],
    "sg:website":"www.stlouisinteriordesign.biz/",
    "wof:name":"Selection Masters LLC",
    "wof:placetype":"venue"
},
  "geometry": {"coordinates":[-90.253354,38.645074],"type":"Point"}
}