{
  "type": "Feature",
  "properties": {
    "iso:country":"US",
    "sg:address":"798 Market St",
    "sg:city":"Farmington",
    "sg:classifiers":[
        {
            "category":"Restaurant",
            "type":"Food & Drink"
        }
    ],
    "sg:menulink":"http://www.allmenus.com/mo/st-francois/65446-cicis-pizza-buffet/menu/",
    "sg:phone":"+1 573 756 9998",
    "sg:postcode":"63640",
    "sg:province":"MO",
    "sg:tags":[
        "american",
        "pizza"
    ],
    "wof:name":"CiCi's Pizza Buffet",
    "wof:placetype":"venue"
},
  "geometry": {"coordinates":[-90.438042,37.791685],"type":"Point"}
}