{
  "type": "Feature",
  "properties": {
    "iso:country":"US",
    "sg:address":"2922 Hwy K",
    "sg:city":"O Fallon",
    "sg:classifiers":[
        {
            "category":"Real Estate",
            "subcategory":"Real Estate Agent",
            "type":"Services"
        }
    ],
    "sg:phone":"+1 636 397 7770",
    "sg:postcode":"63368",
    "sg:province":"MO",
    "wof:name":"Re/Max",
    "wof:placetype":"venue"
},
  "geometry": {"coordinates":[-90.70011,38.76555],"type":"Point"}
}