{
  "type": "Feature",
  "properties": {
    "iso:country":"US",
    "sg:address":"801 Chouteau Ave",
    "sg:city":"Saint Louis",
    "sg:classifiers":[
        {
            "category":"Banks & Credit Unions",
            "subcategory":"Bank",
            "type":"Services"
        }
    ],
    "sg:phone":"+1 314 982 2888",
    "sg:postcode":"63102",
    "sg:province":"MO",
    "sg:website":"www.purinacu.org",
    "wof:name":"Purina Credit Union",
    "wof:placetype":"venue"
},
  "geometry": {"coordinates":[-90.196999,38.617699],"type":"Point"}
}