{
  "type": "Feature",
  "properties": {
    "iso:country":"US",
    "sg:address":"7234 W Florissant Ave",
    "sg:city":"St Louis",
    "sg:classifiers":[
        {
            "category":"Personal",
            "subcategory":"Beauty Salon",
            "type":"Services"
        }
    ],
    "sg:phone":"+1 314 381 5115",
    "sg:postcode":"63136",
    "sg:province":"MO",
    "sg:tags":[
        "shop"
    ],
    "wof:name":"Budget Beauty Salon",
    "wof:placetype":"venue"
},
  "geometry": {"coordinates":[-90.267847,38.721143],"type":"Point"}
}