{
  "type": "Feature",
  "properties": {
    "iso:country":"US",
    "sg:address":"508 US Hwy 54",
    "sg:city":"Camdenton",
    "sg:classifiers":[
        {
            "category":"Autos & Motor Vehicles",
            "subcategory":"Automobile Sales",
            "type":"Retail Goods"
        }
    ],
    "sg:phone":"+1 573 346 7722",
    "sg:postcode":"65020",
    "sg:province":"MO",
    "sg:tags":[
        "car",
        "dealer"
    ],
    "wof:name":"Beckett Motor Co",
    "wof:placetype":"venue"
},
  "geometry": {"coordinates":[-92.732449,38.016089],"type":"Point"}
}