{
  "type": "Feature",
  "properties": {
    "iso:country":"US",
    "sg:address":"1405 SW Mission Rd",
    "sg:city":"Lees Summit",
    "sg:classifiers":[
        {
            "category":"Building & Trades",
            "subcategory":"Construction",
            "type":"Services"
        }
    ],
    "sg:phone":"+1 816 537 7232",
    "sg:postcode":"64081",
    "sg:province":"MO",
    "sg:tags":[
        "house",
        "family"
    ],
    "wof:name":"David N Cooper Signature Homes",
    "wof:placetype":"venue"
},
  "geometry": {"coordinates":[-94.38258999999999,38.896251],"type":"Point"}
}