{
  "type": "Feature",
  "properties": {
    "iso:country":"US",
    "sg:address":"1202 E Hubach Hill Rd",
    "sg:city":"Raymore",
    "sg:classifiers":[
        {
            "category":"Shopping",
            "subcategory":"Clothing, Apparel, & Fashions",
            "type":"Retail Goods"
        }
    ],
    "sg:phone":"+1 816 322 2200",
    "sg:postcode":"64083",
    "sg:province":"MO",
    "sg:tags":[
        "riding",
        "equipment"
    ],
    "wof:name":"Sophisti-Gaited Fashions",
    "wof:placetype":"venue"
},
  "geometry": {"coordinates":[-94.43284199999999,38.781605],"type":"Point"}
}