{
  "type": "Feature",
  "properties": {
    "iso:country":"US",
    "sg:address":"462 S County Center Way",
    "sg:city":"Saint Louis",
    "sg:classifiers":[
        {
            "category":"Shopping",
            "subcategory":"Gifts & Souvenirs",
            "type":"Retail Goods"
        }
    ],
    "sg:phone":"+1 314 487 0632",
    "sg:postcode":"63129",
    "sg:province":"MO",
    "wof:name":"American Greetings",
    "wof:placetype":"venue"
},
  "geometry": {"coordinates":[-90.333016,38.505701],"type":"Point"}
}