{
  "type": "Feature",
  "properties": {
    "iso:country":"US",
    "sg:address":"810 E 63 St",
    "sg:city":"Kansas City",
    "sg:classifiers":[
        {
            "category":"Professional",
            "subcategory":"Lawyer & Legal Services",
            "type":"Services"
        }
    ],
    "sg:phone":"+1 816 523 2166",
    "sg:postcode":"64110",
    "sg:province":"MO",
    "sg:tags":[
        "attorney"
    ],
    "wof:name":"Londa Shabazz",
    "wof:placetype":"venue"
},
  "geometry": {"coordinates":[-94.57713200000001,39.013443],"type":"Point"}
}