{
  "type": "Feature",
  "properties": {
    "iso:country":"US",
    "sg:address":"311 Main St",
    "sg:city":"Noel",
    "sg:classifiers":[
        {
            "category":"Building & Trades",
            "subcategory":"Equipment Rental",
            "type":"Services"
        }
    ],
    "sg:phone":"+1 417 475 6178",
    "sg:postcode":"64854",
    "sg:province":"MO",
    "sg:tags":[
        "television"
    ],
    "wof:name":"National TV Sales & Rental",
    "wof:placetype":"venue"
},
  "geometry": {"coordinates":[-94.485733,36.545283],"type":"Point"}
}