{
  "type": "Feature",
  "properties": {
    "iso:country":"US",
    "sg:address":"10 Belleau Lake Ct",
    "sg:city":"O Fallon",
    "sg:classifiers":[
        {
            "category":"Wholesale",
            "subcategory":"Hardware",
            "type":"Manufacturing & Wholesale Goods"
        }
    ],
    "sg:phone":"+1 636 240 3489",
    "sg:postcode":"63366",
    "sg:province":"MO",
    "sg:tags":[
        "plumbing"
    ],
    "wof:name":"Montgomery Supply Inc",
    "wof:placetype":"venue"
},
  "geometry": {"coordinates":[-90.67800800000001,38.798329],"type":"Point"}
}