{
  "type": "Feature",
  "properties": {
    "iso:country":"US",
    "sg:address":"706 W 4th St",
    "sg:city":"Stover",
    "sg:classifiers":[
        {
            "category":"Shopping",
            "subcategory":"Florist",
            "type":"Retail Goods"
        }
    ],
    "sg:phone":"+1 573 377 2822",
    "sg:postcode":"65078",
    "sg:province":"MO",
    "wof:name":"Room To Bloom",
    "wof:placetype":"venue"
},
  "geometry": {"coordinates":[-92.994635,38.443025],"type":"Point"}
}