{
  "type": "Feature",
  "properties": {
    "iso:country":"US",
    "sg:address":"3637 Broadway St",
    "sg:city":"Kansas City",
    "sg:classifiers":[
        {
            "category":"Social Services",
            "type":"Services"
        }
    ],
    "sg:phone":"+1 816 756 2769",
    "sg:postcode":"64111",
    "sg:province":"MO",
    "sg:tags":[
        "organization",
        "welfare"
    ],
    "wof:name":"Metro Social Svc",
    "wof:placetype":"venue"
},
  "geometry": {"coordinates":[-94.590492,39.060474],"type":"Point"}
}