{
  "type": "Feature",
  "properties": {
    "iso:country":"US",
    "sg:address":"211 W 3rd St",
    "sg:city":"Cameron",
    "sg:classifiers":[
        {
            "category":"Personal",
            "subcategory":"Beauty Salon",
            "type":"Services"
        }
    ],
    "sg:phone":"+1 816 632 6741",
    "sg:postcode":"64429",
    "sg:province":"MO",
    "sg:tags":[
        "shop"
    ],
    "wof:name":"Old Fashinoned Beauty Spot",
    "wof:placetype":"venue"
},
  "geometry": {"coordinates":[-94.24103599999999,39.741319],"type":"Point"}
}