{
  "type": "Feature",
  "properties": {
    "iso:country":"US",
    "sg:address":"95 Bear Hollow Rd",
    "sg:city":"Pineville",
    "sg:classifiers":[
        {
            "category":"Health Services",
            "subcategory":"Chiropractor",
            "type":"Services"
        }
    ],
    "sg:phone":"+1 479 855 7374",
    "sg:postcode":"64856",
    "sg:province":"MO",
    "sg:tags":[
        "chiropractic"
    ],
    "wof:name":"Gil Morgan",
    "wof:placetype":"venue"
},
  "geometry": {"coordinates":[-94.268872,36.499347],"type":"Point"}
}