{
  "type": "Feature",
  "properties": {
    "iso:country":"US",
    "sg:address":"225 S Meramec Ave",
    "sg:city":"St Louis",
    "sg:classifiers":[
        {
            "category":"Health Services",
            "subcategory":"Doctor",
            "type":"Services"
        }
    ],
    "sg:phone":"+1 314 721 7550",
    "sg:postcode":"63105",
    "sg:province":"MO",
    "sg:tags":[
        "physician",
        "surgeon",
        "medical"
    ],
    "wof:name":"Mary L Nielsen MD",
    "wof:placetype":"venue"
},
  "geometry": {"coordinates":[-90.340318,38.64624],"type":"Point"}
}