{
  "type": "Feature",
  "properties": {
    "iso:country":"US",
    "sg:address":"18512 E 8 St N",
    "sg:city":"Independence",
    "sg:classifiers":[
        {
            "category":"Utilities",
            "subcategory":"Refuse",
            "type":"Services"
        }
    ],
    "sg:phone":"+1 816 796 8489",
    "sg:postcode":"64056",
    "sg:province":"MO",
    "sg:tags":[
        "garbage",
        "collection"
    ],
    "wof:name":"Bill's Hauling",
    "wof:placetype":"venue"
},
  "geometry": {"coordinates":[-94.358114,39.115759],"type":"Point"}
}