{
  "type": "Feature",
  "properties": {
    "iso:country":"US",
    "sg:address":"3161 Lupine Dr",
    "sg:city":"Arnold",
    "sg:classifiers":[
        {
            "category":"Building & Trades",
            "subcategory":"Construction",
            "type":"Services"
        }
    ],
    "sg:phone":"+1 636 296 5772",
    "sg:postcode":"63010",
    "sg:province":"MO",
    "sg:tags":[
        "roofing",
        "contractor"
    ],
    "wof:name":"Hill A & R Roofing & Siding",
    "wof:placetype":"venue"
},
  "geometry": {"coordinates":[-90.409284,38.413715],"type":"Point"}
}