{
  "type": "Feature",
  "properties": {
    "iso:country":"US",
    "sg:address":"800 First Capitol Dr",
    "sg:city":"Saint Charles",
    "sg:classifiers":[
        {
            "category":"Professional",
            "subcategory":"Computer Services",
            "type":"Services"
        }
    ],
    "sg:phone":"+1 636 946 5334",
    "sg:postcode":"63301",
    "sg:province":"MO",
    "sg:tags":[
        "programing",
        "custom"
    ],
    "wof:name":"Richard W Blalock",
    "wof:placetype":"venue"
},
  "geometry": {"coordinates":[-90.49283200000001,38.783114],"type":"Point"}
}