{
  "type": "Feature",
  "properties": {
    "iso:country":"US",
    "sg:address":"4612 S Forest Ave",
    "sg:city":"Springfield",
    "sg:classifiers":[
        {
            "category":"Building & Trades",
            "subcategory":"Construction",
            "type":"Services"
        }
    ],
    "sg:phone":"+1 417 887 6800",
    "sg:postcode":"65810",
    "sg:province":"MO",
    "sg:tags":[
        "contractor"
    ],
    "wof:name":"Gw Walton Acoustics Inc",
    "wof:placetype":"venue"
},
  "geometry": {"coordinates":[-93.326913,37.131114],"type":"Point"}
}