{
  "type": "Feature",
  "properties": {
    "iso:country":"US",
    "sg:address":"16100 Chesterfield Pkwy W",
    "sg:city":"Chesterfield",
    "sg:classifiers":[
        {
            "category":"Health Services",
            "subcategory":"Doctor",
            "type":"Services"
        },
        {
            "category":"Health Services",
            "subcategory":"Dentist",
            "type":"Services"
        }
    ],
    "sg:phone":"+1 636 532 3208",
    "sg:postcode":"63017",
    "sg:province":"MO",
    "sg:tags":[
        "dentists-oral",
        "physician",
        "dental",
        "maxillofacial",
        "surgeons",
        "clinic",
        "surgery",
        "oral"
    ],
    "sg:website":"http://www.chesterfielddentalassoc.com",
    "wof:name":"Johnson Charles E",
    "wof:placetype":"venue"
},
  "geometry": {"coordinates":[-90.563461,38.647572],"type":"Point"}
}