{
  "type": "Feature",
  "properties": {
    "iso:country":"US",
    "sg:address":"1003 W Bain St",
    "sg:city":"Dexter",
    "sg:classifiers":[
        {
            "category":"Real Estate",
            "subcategory":"Real Estate Services",
            "type":"Services"
        }
    ],
    "sg:phone":"+1 573 624 6373",
    "sg:postcode":"63841",
    "sg:province":"MO",
    "sg:tags":[
        "vacancy",
        "rental",
        "listing"
    ],
    "wof:name":"Swallows Rental Properties",
    "wof:placetype":"venue"
},
  "geometry": {"coordinates":[-89.974441,36.791551],"type":"Point"}
}