{
  "type": "Feature",
  "properties": {
    "iso:country":"US",
    "sg:address":"3832 SW Evergreen Ln",
    "sg:city":"Lees Summit",
    "sg:classifiers":[
        {
            "category":"Building & Trades",
            "subcategory":"Construction",
            "type":"Services"
        }
    ],
    "sg:phone":"+1 816 537 8201",
    "sg:postcode":"64082",
    "sg:province":"MO",
    "sg:tags":[
        "house"
    ],
    "wof:name":"Spacemakers",
    "wof:placetype":"venue"
},
  "geometry": {"coordinates":[-94.38506,38.85245],"type":"Point"}
}