{
  "type": "Feature",
  "properties": {
    "iso:country":"US",
    "sg:address":"449 W Newton St",
    "sg:city":"Eldon",
    "sg:classifiers":[
        {
            "category":"Shopping",
            "type":"Retail Goods"
        }
    ],
    "sg:phone":"+1 573 480 3155",
    "sg:postcode":"65026",
    "sg:province":"MO",
    "sg:tags":[
        "equipment",
        "telephone",
        "supply"
    ],
    "wof:name":"Best Tech Communications",
    "wof:placetype":"venue"
},
  "geometry": {"coordinates":[-92.58835999999999,38.353075],"type":"Point"}
}