{
  "type": "Feature",
  "properties": {
    "iso:country":"US",
    "sg:address":"1001 N Truman Blvd",
    "sg:city":"Caruthersville",
    "sg:classifiers":[
        {
            "category":"Personal",
            "subcategory":"Barber",
            "type":"Services"
        }
    ],
    "sg:phone":"+1 573 333 1387",
    "sg:postcode":"63830",
    "sg:province":"MO",
    "sg:tags":[
        "shop"
    ],
    "wof:name":"Ralph's Barber Shop",
    "wof:placetype":"venue"
},
  "geometry": {"coordinates":[-89.66707700000001,36.188047],"type":"Point"}
}