{
  "type": "Feature",
  "properties": {
    "iso:country":"US",
    "sg:address":"1870 Ridgeview Circle Dr",
    "sg:city":"Ballwin",
    "sg:classifiers":[
        {
            "category":"Professional",
            "subcategory":"Advertising",
            "type":"Services"
        }
    ],
    "sg:phone":"+1 636 394 3130",
    "sg:postcode":"63021",
    "sg:province":"MO",
    "sg:tags":[
        "agency"
    ],
    "wof:name":"Sugar Creek Productions",
    "wof:placetype":"venue"
},
  "geometry": {"coordinates":[-90.476373,38.582471],"type":"Point"}
}