{
  "type": "Feature",
  "properties": {
    "iso:country":"US",
    "sg:address":"624 W 44 St",
    "sg:city":"Kansas City",
    "sg:classifiers":[
        {
            "category":"Real Estate",
            "subcategory":"Real Estate Operator",
            "type":"Services"
        }
    ],
    "sg:phone":"+1 816 931 9056",
    "sg:postcode":"64111",
    "sg:province":"MO",
    "sg:tags":[
        "building",
        "apartment"
    ],
    "wof:name":"Casa Royale Apartments",
    "wof:placetype":"venue"
},
  "geometry": {"coordinates":[-94.594661,39.047988],"type":"Point"}
}