{
  "type": "Feature",
  "properties": {
    "iso:country":"US",
    "sg:address":"9807 E 20th St",
    "sg:city":"Mountain Grove",
    "sg:classifiers":[
        {
            "category":"Wholesale",
            "subcategory":"Farm Supplies",
            "type":"Manufacturing & Wholesale Goods"
        }
    ],
    "sg:phone":"+1 417 926 1015",
    "sg:postcode":"65711",
    "sg:province":"MO",
    "sg:tags":[
        "feed"
    ],
    "wof:name":"Noble Hudson & Sons Feeds",
    "wof:placetype":"venue"
},
  "geometry": {"coordinates":[-92.262638,37.149451],"type":"Point"}
}