{
  "type": "Feature",
  "properties": {
    "iso:country":"US",
    "sg:address":"6085 Pasadena Ln",
    "sg:city":"Granby",
    "sg:classifiers":[
        {
            "category":"Freight",
            "type":"Transportation"
        }
    ],
    "sg:phone":"+1 417 472 6352",
    "sg:postcode":"64844",
    "sg:province":"MO",
    "sg:tags":[
        "trucking"
    ],
    "wof:name":"T Jennings Trucking Computer",
    "wof:placetype":"venue"
},
  "geometry": {"coordinates":[-94.262215,36.980098],"type":"Point"}
}