{
  "type": "Feature",
  "properties": {
    "iso:country":"US",
    "sg:address":"1891 N Bluff St",
    "sg:city":"Fulton",
    "sg:classifiers":[
        {
            "category":"Restaurant",
            "type":"Food & Drink"
        }
    ],
    "sg:phone":"+1 573 592 8888",
    "sg:postcode":"65251",
    "sg:province":"MO",
    "sg:tags":[
        "eating"
    ],
    "wof:name":"Dragon Kitchen",
    "wof:placetype":"venue"
},
  "geometry": {"coordinates":[-91.94395400000001,38.864394],"type":"Point"}
}