{
  "type": "Feature",
  "properties": {
    "iso:country":"US",
    "sg:address":"4399 Forest Park Ave Ofc",
    "sg:city":"Saint Louis",
    "sg:classifiers":[
        {
            "category":"Real Estate",
            "subcategory":"Real Estate Operator",
            "type":"Services"
        }
    ],
    "sg:phone":"+1 314 535 3330",
    "sg:postcode":"63108",
    "sg:province":"MO",
    "sg:tags":[
        "apartment"
    ],
    "wof:name":"Park Place Apartments",
    "wof:placetype":"venue"
},
  "geometry": {"coordinates":[-90.255798,38.637699],"type":"Point"}
}