{
  "type": "Feature",
  "properties": {
    "iso:country":"US",
    "sg:address":"807 Jefferson St",
    "sg:city":"Jefferson City",
    "sg:classifiers":[
        {
            "category":"Building & Trades",
            "subcategory":"Cleaning & Sanitation",
            "type":"Services"
        }
    ],
    "sg:phone":"+1 573 635 8183",
    "sg:postcode":"65101",
    "sg:province":"MO",
    "sg:tags":[
        "janitor",
        "maintenance"
    ],
    "wof:name":"River City Janitorial Service",
    "wof:placetype":"venue"
},
  "geometry": {"coordinates":[-92.178314,38.571809],"type":"Point"}
}