{
  "type": "Feature",
  "properties": {
    "iso:country":"US",
    "sg:address":"1110 N Truman Blvd",
    "sg:city":"Crystal City",
    "sg:classifiers":[
        {
            "category":"Retail",
            "subcategory":"Auto Repair",
            "type":"Services"
        }
    ],
    "sg:phone":"+1 636 933 9999",
    "sg:postcode":"63019",
    "sg:province":"MO",
    "sg:tags":[
        "motorcycle"
    ],
    "wof:name":"P C Custom Cycles",
    "wof:placetype":"venue"
},
  "geometry": {"coordinates":[-90.387506,38.230293],"type":"Point"}
}