{
  "type": "Feature",
  "properties": {
    "iso:country":"US",
    "sg:address":"468 Kayla Dr",
    "sg:city":"Peculiar",
    "sg:classifiers":[
        {
            "category":"Building & Trades",
            "subcategory":"Construction",
            "type":"Services"
        }
    ],
    "sg:phone":"+1 816 380 2931",
    "sg:postcode":"64078",
    "sg:province":"MO",
    "sg:tags":[
        "general",
        "contractor"
    ],
    "wof:name":"Parks Construction",
    "wof:placetype":"venue"
},
  "geometry": {"coordinates":[-94.452299,38.728836],"type":"Point"}
}