{
  "type": "Feature",
  "properties": {
    "iso:country":"US",
    "sg:address":"8318 N Farm Rd 77",
    "sg:city":"Walnut Grove",
    "sg:classifiers":[
        {
            "category":"Retail",
            "subcategory":"Auto Repair",
            "type":"Services"
        }
    ],
    "sg:phone":"+1 417 742 3027",
    "sg:postcode":"65770",
    "sg:province":"MO",
    "sg:tags":[
        "automotive"
    ],
    "wof:name":"Pearl Auto Works",
    "wof:placetype":"venue"
},
  "geometry": {"coordinates":[-93.485427,37.352949],"type":"Point"}
}