{
  "type": "Feature",
  "properties": {
    "iso:country":"US",
    "sg:address":"22740 King Rd",
    "sg:city":"Weston",
    "sg:classifiers":[
        {
            "category":"Building & Trades",
            "subcategory":"Construction",
            "type":"Services"
        }
    ],
    "sg:phone":"+1 816 283 3105",
    "sg:postcode":"64098",
    "sg:province":"MO",
    "sg:website":"www.parkline-ma.com",
    "wof:name":"Parkline Mid-America",
    "wof:placetype":"venue"
},
  "geometry": {"coordinates":[-94.89111800000001,39.514773],"type":"Point"}
}