{
  "type": "Feature",
  "properties": {
    "iso:country":"US",
    "sg:address":"3400 S Kingshighway Blvd",
    "sg:city":"Saint Louis",
    "sg:classifiers":[
        {
            "category":"Retail",
            "subcategory":"Auto Repair",
            "type":"Services"
        }
    ],
    "sg:phone":"+1 314 752 0400",
    "sg:postcode":"63139",
    "sg:province":"MO",
    "sg:tags":[
        "body",
        "shop"
    ],
    "wof:name":"Ernie Patti Daewoo",
    "wof:placetype":"venue"
},
  "geometry": {"coordinates":[-90.270798,38.597401],"type":"Point"}
}