{
  "type": "Feature",
  "properties": {
    "iso:country":"US",
    "sg:address":"7199 Natural Bridge Rd",
    "sg:city":"Saint Louis",
    "sg:classifiers":[
        {
            "category":"Autos & Motor Vehicles",
            "subcategory":"Fuel & Gas Station",
            "type":"Retail Goods"
        }
    ],
    "sg:phone":"+1 314 381 5050",
    "sg:postcode":"63121",
    "sg:province":"MO",
    "sg:tags":[
        "station",
        "gasoline"
    ],
    "wof:name":"Lyon Petroleum Inc",
    "wof:placetype":"venue"
},
  "geometry": {"coordinates":[-90.29060699999999,38.700093],"type":"Point"}
}