{
  "type": "Feature",
  "properties": {
    "iso:country":"US",
    "sg:address":"214 Linn St",
    "sg:city":"Graham",
    "sg:classifiers":[
        {
            "category":"Farming",
            "subcategory":"Livestock Farm",
            "type":"Manufacturing & Wholesale Goods"
        },
        {
            "category":"Farming",
            "subcategory":"Farm",
            "type":"Manufacturing & Wholesale Goods"
        }
    ],
    "sg:phone":"+1 660 939 2655",
    "sg:postcode":"64455",
    "sg:province":"MO",
    "sg:tags":[
        "feeding"
    ],
    "wof:name":"John Barrett",
    "wof:placetype":"venue"
},
  "geometry": {"coordinates":[-95.040806,40.201773],"type":"Point"}
}