{
  "type": "Feature",
  "properties": {
    "iso:country":"US",
    "sg:address":"1882 James River Rd",
    "sg:city":"Ozark",
    "sg:classifiers":[
        {
            "category":"Restaurant",
            "type":"Food & Drink"
        }
    ],
    "sg:phone":"+1 417 582 2600",
    "sg:postcode":"65721",
    "sg:province":"MO",
    "sg:tags":[
        "style",
        "family"
    ],
    "wof:name":"Bric's Belguim Waffle & Pancake House",
    "wof:placetype":"venue"
},
  "geometry": {"coordinates":[-93.228005,37.072897],"type":"Point"}
}