{
  "type": "Feature",
  "properties": {
    "iso:country":"US",
    "sg:address":"180 Basswood Cir",
    "sg:city":"Lees Summit",
    "sg:classifiers":[
        {
            "category":"Professional",
            "type":"Services"
        }
    ],
    "sg:phone":"+1 816 350 2687",
    "sg:postcode":"64064",
    "sg:province":"MO",
    "wof:name":"Houses Hearts & Hands Inc",
    "wof:placetype":"venue"
},
  "geometry": {"coordinates":[-94.37932000000001,38.979972],"type":"Point"}
}