{
  "type": "Feature",
  "properties": {
    "iso:country":"US",
    "sg:address":"104 Gunston Hall Dr",
    "sg:city":"Saint Charles",
    "sg:classifiers":[
        {
            "category":"Professional",
            "subcategory":"Business Services",
            "type":"Services"
        }
    ],
    "sg:phone":"+1 636 300 1467",
    "sg:postcode":"63304",
    "sg:province":"MO",
    "wof:name":"Insight Capital Group",
    "wof:placetype":"venue"
},
  "geometry": {"coordinates":[-90.6863,38.733509],"type":"Point"}
}