{
  "type": "Feature",
  "properties": {
    "iso:country":"US",
    "sg:address":"4703 NE 47 Ter",
    "sg:city":"Kansas City",
    "sg:classifiers":[
        {
            "category":"Home & Garden",
            "subcategory":"Carpets & Floor Coverings",
            "type":"Retail Goods"
        }
    ],
    "sg:phone":"+1 816 459 8396",
    "sg:postcode":"64117",
    "sg:province":"MO",
    "wof:name":"Swanson Floors Inc",
    "wof:placetype":"venue"
},
  "geometry": {"coordinates":[-94.52466,39.179827],"type":"Point"}
}