{
  "type": "Feature",
  "properties": {
    "iso:country":"US",
    "sg:address":"9910 Gravois Rd",
    "sg:city":"St Louis",
    "sg:classifiers":[
        {
            "category":"Retail",
            "subcategory":"Portrait Studio",
            "type":"Services"
        },
        {
            "category":"Professional",
            "subcategory":"Art Services",
            "type":"Services"
        }
    ],
    "sg:phone":"+1 314 631 4170",
    "sg:postcode":"63123",
    "sg:province":"MO",
    "sg:tags":[
        "photographer",
        "photography",
        "commercial"
    ],
    "wof:name":"Denash Photography",
    "wof:placetype":"venue"
},
  "geometry": {"coordinates":[-90.32987300000001,38.550843],"type":"Point"}
}