{
  "type": "Feature",
  "properties": {
    "iso:country":"US",
    "sg:address":"600 W 67 Ter",
    "sg:city":"Kansas City",
    "sg:classifiers":[
        {
            "category":"Real Estate",
            "subcategory":"Real Estate Agent",
            "type":"Services"
        }
    ],
    "sg:phone":"+1 816 523 1039",
    "sg:postcode":"64113",
    "sg:province":"MO",
    "wof:name":"Re/Max First Realtors",
    "wof:placetype":"venue"
},
  "geometry": {"coordinates":[-94.59912,39.006589],"type":"Point"}
}