{
  "type": "Feature",
  "properties": {
    "iso:country":"US",
    "sg:address":"911 S 13th St",
    "sg:city":"Saint Louis",
    "sg:classifiers":[
        {
            "category":"Professional",
            "subcategory":"Lawyer & Legal Services",
            "type":"Services"
        }
    ],
    "sg:phone":"+1 314 241 6014",
    "sg:postcode":"63103",
    "sg:province":"MO",
    "wof:name":"Kehr Kent & Associates PC",
    "wof:placetype":"venue"
},
  "geometry": {"coordinates":[-90.202872,38.619925],"type":"Point"}
}