{
  "type": "Feature",
  "properties": {
    "addr:full":"3511 Shepherd of The Hills Expy Marvel Cave Park MO 65616",
    "addr:housenumber":"3511",
    "addr:postcode":"65616",
    "addr:street":"Shepherd Of The;Expy Marvel Cave Park",
    "iso:country":"US",
    "sg:address":"3511 Shepherd of The Hills Expy",
    "sg:city":"Marvel Cave Park",
    "sg:classifiers":[
        {
            "category":"Restaurant",
            "type":"Food & Drink"
        }
    ],
    "sg:menulink":"http://www.allmenus.com/mo/branson/195560-taco-bell/menu/",
    "sg:phone":"+1 417 336 5394",
    "sg:postcode":"65616",
    "sg:province":"MO",
    "sg:tags":[
        "mexican"
    ],
    "wof:name":"Taco Bell",
    "wof:placetype":"venue"
},
  "geometry": {"coordinates":[-93.28681400000001,36.652544],"type":"Point"}
}