{
  "type": "Feature",
  "properties": {
    "iso:country":"US",
    "sg:address":"4013 N Johnson Rd",
    "sg:city":"Sibley",
    "sg:classifiers":[
        {
            "category":"Farming",
            "subcategory":"Orchard",
            "type":"Manufacturing & Wholesale Goods"
        }
    ],
    "sg:phone":"+1 816 650 9339",
    "sg:postcode":"64088",
    "sg:province":"MO",
    "sg:tags":[
        "fruit",
        "tree"
    ],
    "wof:name":"Dobsons Happy Apple Orchard",
    "wof:placetype":"venue"
},
  "geometry": {"coordinates":[-94.175669,39.170875],"type":"Point"}
}