{
  "type": "Feature",
  "properties": {
    "iso:country":"US",
    "sg:address":"18702 Highway 59",
    "sg:city":"Neosho",
    "sg:classifiers":[
        {
            "category":"Utilities",
            "subcategory":"Fuel Oil & Lpg",
            "type":"Services"
        },
        {
            "category":"Utilities",
            "subcategory":"Natural Gas",
            "type":"Services"
        }
    ],
    "sg:phone":"+1 417 466 4050",
    "sg:postcode":"64850",
    "sg:province":"MO",
    "sg:tags":[
        "propane",
        "bulk",
        "petroleum-bottled",
        "gas-liquefied"
    ],
    "sg:website":"http://www.amerigas.com",
    "wof:name":"Amerigas",
    "wof:placetype":"venue"
},
  "geometry": {"coordinates":[-94.395751,36.807504],"type":"Point"}
}