{
  "type": "Feature",
  "properties": {
    "iso:country":"US",
    "sg:address":"315 Oakwood Ave",
    "sg:city":"Saint Louis",
    "sg:classifiers":[
        {
            "category":"Travel",
            "subcategory":"Travel Agent",
            "type":"Entertainment"
        }
    ],
    "sg:phone":"+1 314 962 7264",
    "sg:postcode":"63119",
    "sg:province":"MO",
    "sg:tags":[
        "operator",
        "tour"
    ],
    "wof:name":"Shirley Mercadal Dooley",
    "wof:placetype":"venue"
},
  "geometry": {"coordinates":[-90.349261,38.59515],"type":"Point"}
}