{
  "type": "Feature",
  "properties": {
    "iso:country":"US",
    "sg:address":"1415 E University St",
    "sg:city":"Springfield",
    "sg:classifiers":[
        {
            "category":"Professional",
            "subcategory":"Art Services",
            "type":"Services"
        }
    ],
    "sg:phone":"+1 417 890 9447",
    "sg:postcode":"65804",
    "sg:province":"MO",
    "sg:tags":[
        "photographer"
    ],
    "wof:name":"Zone Five Photography",
    "wof:placetype":"venue"
},
  "geometry": {"coordinates":[-93.267167,37.18297],"type":"Point"}
}