{
  "type": "Feature",
  "properties": {
    "iso:country":"US",
    "sg:address":"6001 Hartford St",
    "sg:city":"St Louis",
    "sg:classifiers":[
        {
            "category":"Personal",
            "subcategory":"Beauty Salon",
            "type":"Services"
        }
    ],
    "sg:phone":"+1 314 647 2837",
    "sg:postcode":"63139",
    "sg:province":"MO",
    "sg:tags":[
        "shop"
    ],
    "wof:name":"Clifton Heights Beauty Shop",
    "wof:placetype":"venue"
},
  "geometry": {"coordinates":[-90.29014599999999,38.606197],"type":"Point"}
}