{
  "type": "Feature",
  "properties": {
    "iso:country":"US",
    "sg:address":"12361 Merrick Dr",
    "sg:city":"St Louis",
    "sg:classifiers":[
        {
            "category":"Professional",
            "subcategory":"Engineering",
            "type":"Services"
        }
    ],
    "sg:phone":"+1 314 878 0123",
    "sg:postcode":"63146",
    "sg:province":"MO",
    "sg:tags":[
        "engineer"
    ],
    "wof:name":"Penta Engineering Corp",
    "wof:placetype":"venue"
},
  "geometry": {"coordinates":[-90.45187199999999,38.687508],"type":"Point"}
}