{
  "type": "Feature",
  "properties": {
    "iso:country":"US",
    "sg:address":"9475 Lawrence 2077",
    "sg:city":"Mount Vernon",
    "sg:classifiers":[
        {
            "category":"Building & Trades",
            "subcategory":"Construction",
            "type":"Services"
        }
    ],
    "sg:phone":"+1 417 452 2226",
    "sg:postcode":"65712",
    "sg:province":"MO",
    "sg:tags":[
        "concrete",
        "work"
    ],
    "wof:name":"Meeks Dan Construction",
    "wof:placetype":"venue"
},
  "geometry": {"coordinates":[-93.887778,37.164451],"type":"Point"}
}