{
  "type": "Feature",
  "properties": {
    "iso:country":"US",
    "sg:address":"905 E 5 St",
    "sg:city":"Kansas City",
    "sg:classifiers":[
        {
            "category":"Professional",
            "subcategory":"Art Services",
            "type":"Services"
        }
    ],
    "sg:phone":"+1 816 474 5501",
    "sg:postcode":"64106",
    "sg:province":"MO",
    "sg:tags":[
        "photographer",
        "photography",
        "commercial"
    ],
    "wof:name":"Hollis Officer Studios Inc",
    "wof:placetype":"venue"
},
  "geometry": {"coordinates":[-94.57220100000001,39.110363],"type":"Point"}
}