{
  "type": "Feature",
  "properties": {
    "iso:country":"US",
    "sg:address":"232 Grand Ave",
    "sg:city":"Kirkwood",
    "sg:classifiers":[
        {
            "category":"Wholesale",
            "subcategory":"Construction Materials",
            "type":"Manufacturing & Wholesale Goods"
        },
        {
            "category":"Home & Garden",
            "subcategory":"Building Materials",
            "type":"Retail Goods"
        }
    ],
    "sg:phone":"+1 314 821 2855",
    "sg:postcode":"63122",
    "sg:province":"MO",
    "sg:tags":[
        "roofing"
    ],
    "wof:name":"AAA Roofing Supply Co",
    "wof:placetype":"venue"
},
  "geometry": {"coordinates":[-90.40664599999999,38.569407],"type":"Point"}
}