{
  "type": "Feature",
  "properties": {
    "iso:country":"US",
    "sg:address":"12400 Olive Blvd",
    "sg:city":"Saint Louis",
    "sg:classifiers":[
        {
            "category":"Wholesale",
            "subcategory":"Electrical",
            "type":"Manufacturing & Wholesale Goods"
        }
    ],
    "sg:phone":"+1 314 621 4007",
    "sg:postcode":"63141",
    "sg:province":"MO",
    "sg:tags":[
        "r",
        "electronic",
        "contractor"
    ],
    "wof:name":"Alcatel-Itt",
    "wof:placetype":"venue"
},
  "geometry": {"coordinates":[-90.46194,38.67546],"type":"Point"}
}