{
  "type": "Feature",
  "properties": {
    "iso:country":"US",
    "sg:address":"207 NW Englewood Rd",
    "sg:city":"Kansas City",
    "sg:classifiers":[
        {
            "category":"Building & Trades",
            "subcategory":"Construction",
            "type":"Services"
        }
    ],
    "sg:phone":"+1 816 454 7704",
    "sg:postcode":"64118",
    "sg:province":"MO",
    "sg:tags":[
        "concrete",
        "contractor"
    ],
    "wof:name":"All Ssons Fndtion RPR Wtrprfng",
    "wof:placetype":"venue"
},
  "geometry": {"coordinates":[-94.584917,39.19644],"type":"Point"}
}