{
  "type": "Feature",
  "properties": {
    "iso:country":"US",
    "sg:address":"1816 Linn Ave",
    "sg:city":"Marshall",
    "sg:classifiers":[
        {
            "category":"Farming",
            "subcategory":"Farm",
            "type":"Manufacturing & Wholesale Goods"
        }
    ],
    "sg:phone":"+1 660 886 4406",
    "sg:postcode":"65340",
    "sg:province":"MO",
    "sg:tags":[
        "crop",
        "general"
    ],
    "wof:name":"Chevalier Farms",
    "wof:placetype":"venue"
},
  "geometry": {"coordinates":[-93.202476,39.101229],"type":"Point"}
}