{
  "type": "Feature",
  "properties": {
    "iso:country":"US",
    "sg:address":"754 E Young St",
    "sg:city":"Warrensburg",
    "sg:classifiers":[
        {
            "category":"Building & Trades",
            "subcategory":"Equipment Rental",
            "type":"Services"
        }
    ],
    "sg:phone":"+1 660 747 9159",
    "sg:postcode":"64093",
    "sg:province":"MO",
    "sg:tags":[
        "contractor"
    ],
    "sg:website":"www.rentalservice.com",
    "wof:name":"Atlas Copco Rental Svc Corp",
    "wof:placetype":"venue"
},
  "geometry": {"coordinates":[-93.720448,38.77187],"type":"Point"}
}