{
  "type": "Feature",
  "properties": {
    "addr:full":"1602 Country Club Plaza Dr St Charles MO 63303",
    "addr:housenumber":"1602",
    "addr:postcode":"63303",
    "addr:street":"Country Club Plaza Dr",
    "iso:country":"US",
    "sg:address":"1602 Country Club Plaza Dr",
    "sg:city":"St Charles",
    "sg:classifiers":[
        {
            "category":"Shopping",
            "type":"Retail Goods"
        }
    ],
    "sg:phone":"+1 636 949 2200",
    "sg:postcode":"63303",
    "sg:province":"MO",
    "sg:tags":[
        "cosmetic",
        "perfume"
    ],
    "wof:name":"Merle Norman Cosmetics",
    "wof:placetype":"venue"
},
  "geometry": {"coordinates":[-90.52225799999999,38.769293],"type":"Point"}
}