{
  "type": "Feature",
  "properties": {
    "iso:country":"US",
    "sg:address":"918 W Cherry St",
    "sg:city":"Nevada",
    "sg:classifiers":[
        {
            "category":"Building & Trades",
            "subcategory":"Cleaning & Sanitation",
            "type":"Services"
        }
    ],
    "sg:phone":"+1 417 667 2884",
    "sg:postcode":"64772",
    "sg:province":"MO",
    "sg:tags":[
        "maintenance"
    ],
    "wof:name":"Service Concepts",
    "wof:placetype":"venue"
},
  "geometry": {"coordinates":[-94.368824,37.838588],"type":"Point"}
}