{
  "type": "Feature",
  "properties": {
    "iso:country":"US",
    "sg:address":"168 Parsons Ave",
    "sg:city":"St Louis",
    "sg:classifiers":[
        {
            "category":"Professional",
            "subcategory":"Business Services",
            "type":"Services"
        }
    ],
    "sg:phone":"+1 314 962 8580",
    "sg:postcode":"63119",
    "sg:province":"MO",
    "sg:tags":[
        "trade",
        "fair",
        "show"
    ],
    "wof:name":"Hunkins Group Inc",
    "wof:placetype":"venue"
},
  "geometry": {"coordinates":[-90.36760099999999,38.595906],"type":"Point"}
}