{
  "type": "Feature",
  "properties": {
    "iso:country":"US",
    "sg:address":"713 Shirewood Rd",
    "sg:city":"Excelsior Spgs",
    "sg:classifiers":[
        {
            "category":"Professional",
            "subcategory":"Business Services",
            "type":"Services"
        }
    ],
    "sg:phone":"+1 816 616 3322",
    "sg:postcode":"64024",
    "sg:province":"MO",
    "wof:name":"Metropolitan Safety Inc",
    "wof:placetype":"venue"
},
  "geometry": {"coordinates":[-94.230582,39.330766],"type":"Point"}
}