{
  "type": "Feature",
  "properties": {
    "iso:country":"US",
    "sg:address":"1909 W 15th St",
    "sg:city":"Joplin",
    "sg:classifiers":[
        {
            "category":"Wholesale",
            "subcategory":"Construction Materials",
            "type":"Manufacturing & Wholesale Goods"
        },
        {
            "category":"Building & Trades",
            "subcategory":"Construction",
            "type":"Services"
        }
    ],
    "sg:phone":"+1 417 782 1843",
    "sg:postcode":"64801",
    "sg:province":"MO",
    "sg:tags":[
        "fence",
        "contractor"
    ],
    "wof:name":"A-1 Fence Installation",
    "wof:placetype":"venue"
},
  "geometry": {"coordinates":[-94.53962900000001,37.075807],"type":"Point"}
}