{
  "type": "Feature",
  "properties": {
    "iso:country":"US",
    "sg:address":"7731 Clayton Rd",
    "sg:city":"Saint Louis",
    "sg:classifiers":[
        {
            "category":"Shopping",
            "subcategory":"Used Merchandise",
            "type":"Retail Goods"
        }
    ],
    "sg:phone":"+1 314 727 9850",
    "sg:postcode":"63117",
    "sg:province":"MO",
    "wof:name":"Davis Pl Antq & Consignments",
    "wof:placetype":"venue"
},
  "geometry": {"coordinates":[-90.337419,38.637788],"type":"Point"}
}