{
  "type": "Feature",
  "properties": {
    "iso:country":"US",
    "sg:address":"6101 Government Dr",
    "sg:city":"Saint Louis",
    "sg:classifiers":[
        {
            "category":"Restaurant",
            "type":"Food & Drink"
        }
    ],
    "sg:menulink":"http://www.allmenus.com/mo/st-louis/269952-boathouse-forest-park/menu/",
    "sg:phone":"+1 314 367 2224",
    "sg:postcode":"63110",
    "sg:province":"MO",
    "sg:tags":[
        "american"
    ],
    "wof:name":"Boathouse Forest Park",
    "wof:placetype":"venue"
},
  "geometry": {"coordinates":[-90.290712,38.636988],"type":"Point"}
}