{
  "type": "Feature",
  "properties": {
    "addr:full":"631 S Ozark Ave Joplin MO 64801",
    "addr:housenumber":"631",
    "addr:postcode":"64801",
    "addr:street":"S Ozark Ave",
    "iso:country":"US",
    "sg:address":"631 S Ozark Ave",
    "sg:city":"Joplin",
    "sg:classifiers":[
        {
            "category":"Retail",
            "subcategory":"Laundry & Dry Cleaning",
            "type":"Services"
        }
    ],
    "sg:phone":"+1 417 624 7020",
    "sg:postcode":"64801",
    "sg:province":"MO",
    "sg:tags":[
        "drycleaning",
        "plant"
    ],
    "wof:name":"One Hour Cleaners",
    "wof:placetype":"venue"
},
  "geometry": {"coordinates":[-94.483549,37.084131],"type":"Point"}
}