{
  "type": "Feature",
  "properties": {
    "iso:country":"US",
    "sg:address":"1232 Washington Ave. Suite 220",
    "sg:city":"Saint Louis",
    "sg:classifiers":[
        {
            "category":"Professional",
            "subcategory":"Lawyer & Legal Services",
            "type":"Services"
        }
    ],
    "sg:phone":"+1 314 322 8515",
    "sg:postcode":"63103",
    "sg:province":"MO",
    "sg:tags":[
        "personal",
        "injury"
    ],
    "sg:website":"www.injuredclient.com/",
    "wof:name":"Page Law, LLC",
    "wof:placetype":"venue"
},
  "geometry": {"coordinates":[-90.198041,38.632029],"type":"Point"}
}