{
  "type": "Feature",
  "properties": {
    "iso:country":"US",
    "sg:address":"3000 Hatherly Dr",
    "sg:city":"St Louis",
    "sg:classifiers":[
        {
            "category":"Professional",
            "subcategory":"Lawyer & Legal Services",
            "type":"Services"
        }
    ],
    "sg:phone":"+1 314 389 4006",
    "sg:postcode":"63121",
    "sg:province":"MO",
    "sg:tags":[
        "attorney"
    ],
    "wof:name":"Clayton Law Ctr",
    "wof:placetype":"venue"
},
  "geometry": {"coordinates":[-90.315361,38.70311],"type":"Point"}
}