{
  "type": "Feature",
  "properties": {
    "iso:country":"US",
    "sg:address":"859 US Hwy 60",
    "sg:city":"Monett",
    "sg:classifiers":[
        {
            "category":"Autos & Motor Vehicles",
            "subcategory":"Automobile Sales",
            "type":"Retail Goods"
        }
    ],
    "sg:phone":"+1 417 235 3622",
    "sg:postcode":"65708",
    "sg:province":"MO",
    "sg:tags":[
        "car",
        "dealer"
    ],
    "wof:name":"Spradling Motors Inc",
    "wof:placetype":"venue"
},
  "geometry": {"coordinates":[-93.94743800000001,36.915862],"type":"Point"}
}