{
  "type": "Feature",
  "properties": {
    "iso:country":"US",
    "sg:address":"1200 NW Jefferson Ct",
    "sg:city":"Blue Springs",
    "sg:classifiers":[
        {
            "category":"Professional",
            "subcategory":"Lawyer & Legal Services",
            "type":"Services"
        }
    ],
    "sg:phone":"+1 816 224 1100",
    "sg:postcode":"64015",
    "sg:province":"MO",
    "wof:name":"Mitchell David R",
    "wof:placetype":"venue"
},
  "geometry": {"coordinates":[-94.286717,39.033596],"type":"Point"}
}