{
  "type": "Feature",
  "properties": {
    "iso:country":"US",
    "sg:address":"923 Waples St",
    "sg:city":"Chillicothe",
    "sg:classifiers":[
        {
            "category":"Organizations",
            "subcategory":"Religious Organization",
            "type":"Services"
        }
    ],
    "sg:phone":"+1 660 707 0850",
    "sg:postcode":"64601",
    "sg:province":"MO",
    "sg:tags":[
        "church"
    ],
    "wof:name":"Seventh Day Adventist",
    "wof:placetype":"venue"
},
  "geometry": {"coordinates":[-93.554406,39.785074],"type":"Point"}
}