{
  "type": "Feature",
  "properties": {
    "iso:country":"US",
    "sg:address":"2601 Independence St",
    "sg:city":"Cape Girardeau",
    "sg:classifiers":[
        {
            "category":"Organizations",
            "subcategory":"Religious Organization",
            "type":"Services"
        }
    ],
    "sg:phone":"+1 573 979 1490",
    "sg:postcode":"63703",
    "sg:province":"MO",
    "sg:website":"www.intervarsity.org",
    "wof:name":"Intervarsity Christian Fllwshp",
    "wof:placetype":"venue"
},
  "geometry": {"coordinates":[-89.55879,37.307518],"type":"Point"}
}