{
  "type": "Feature",
  "properties": {
    "iso:country":"US",
    "sg:address":"7590 Olive Blvd",
    "sg:city":"Saint Louis",
    "sg:classifiers":[
        {
            "category":"Wholesale",
            "subcategory":"Non-durable Goods",
            "type":"Manufacturing & Wholesale Goods"
        }
    ],
    "sg:phone":"+1 314 994 9301",
    "sg:postcode":"63130",
    "sg:province":"MO",
    "wof:name":"A K S Design & Marketing",
    "wof:placetype":"venue"
},
  "geometry": {"coordinates":[-90.33396,38.67183],"type":"Point"}
}