{
  "type": "Feature",
  "properties": {
    "iso:country":"US",
    "sg:address":"20941 140th St",
    "sg:city":"Clearmont",
    "sg:classifiers":[
        {
            "category":"Farming",
            "subcategory":"Farm",
            "type":"Manufacturing & Wholesale Goods"
        }
    ],
    "sg:phone":"+1 660 729 4413",
    "sg:postcode":"64431",
    "sg:province":"MO",
    "wof:name":"Steve Jackson",
    "wof:placetype":"venue"
},
  "geometry": {"coordinates":[-94.988938,40.520735],"type":"Point"}
}