{
  "type": "Feature",
  "properties": {
    "iso:country":"US",
    "sg:address":"134 Rock Industrial Park Dr",
    "sg:city":"Bridgeton",
    "sg:classifiers":[
        {
            "category":"Home & Garden",
            "subcategory":"Carpets & Floor Coverings",
            "type":"Retail Goods"
        },
        {
            "category":"Wholesale",
            "subcategory":"Chemicals & Plastics",
            "type":"Manufacturing & Wholesale Goods"
        }
    ],
    "sg:phone":"+1 314 739 7766",
    "sg:postcode":"63044",
    "sg:province":"MO",
    "sg:tags":[
        "product",
        "stamping",
        "hot",
        "foil",
        "vinyl",
        "dye",
        "distributes"
    ],
    "sg:website":"www.goldeneagleproduct.com",
    "wof:name":"Golden Eagle Products Inc",
    "wof:placetype":"venue"
},
  "geometry": {"coordinates":[-90.450519,38.778524],"type":"Point"}
}