{
  "type": "Feature",
  "properties": {
    "iso:country":"US",
    "sg:address":"671 N Benton Ave",
    "sg:city":"Marshall",
    "sg:classifiers":[
        {
            "category":"Professional",
            "subcategory":"Business Services",
            "type":"Services"
        }
    ],
    "sg:phone":"+1 660 886 5726",
    "sg:postcode":"65340",
    "sg:province":"MO",
    "wof:name":"Evds & Jrd LLC",
    "wof:placetype":"venue"
},
  "geometry": {"coordinates":[-93.20389400000001,39.127579],"type":"Point"}
}