{
  "type": "Feature",
  "properties": {
    "iso:country":"US",
    "sg:address":"205 Topton Way",
    "sg:city":"Saint Louis",
    "sg:classifiers":[
        {
            "category":"Real Estate",
            "subcategory":"Real Estate Agent",
            "type":"Services"
        }
    ],
    "sg:phone":"+1 314 727 1353",
    "sg:postcode":"63105",
    "sg:province":"MO",
    "wof:name":"Rubin Idahy",
    "wof:placetype":"venue"
},
  "geometry": {"coordinates":[-90.345574,38.653302],"type":"Point"}
}