{
  "type": "Feature",
  "properties": {
    "iso:country":"US",
    "sg:address":"29000 Washington School Rd",
    "sg:city":"Excelsior Springs",
    "sg:classifiers":[
        {
            "category":"Building & Trades",
            "subcategory":"Construction",
            "type":"Services"
        }
    ],
    "sg:phone":"+1 816 630 0387",
    "sg:postcode":"64024",
    "sg:province":"MO",
    "sg:tags":[
        "house"
    ],
    "wof:name":"Daniel Yelton Construction",
    "wof:placetype":"venue"
},
  "geometry": {"coordinates":[-94.238292,39.383119],"type":"Point"}
}