{
  "type": "Feature",
  "properties": {
    "iso:country":"US",
    "sg:address":"159 State Hwy P",
    "sg:city":"Clever",
    "sg:classifiers":[
        {
            "category":"Retail",
            "subcategory":"Auto Repair",
            "type":"Services"
        }
    ],
    "sg:phone":"+1 417 743 2646",
    "sg:postcode":"65631",
    "sg:province":"MO",
    "sg:tags":[
        "general"
    ],
    "wof:name":"S & S Auto",
    "wof:placetype":"venue"
},
  "geometry": {"coordinates":[-93.473084,37.03855],"type":"Point"}
}