{
  "type": "Feature",
  "properties": {
    "iso:country":"US",
    "sg:address":"315 S Ohio Ave",
    "sg:city":"Sedalia",
    "sg:classifiers":[
        {
            "category":"Building & Trades",
            "subcategory":"Construction",
            "type":"Services"
        }
    ],
    "sg:phone":"+1 660 826 4808",
    "sg:postcode":"65301",
    "sg:province":"MO",
    "sg:tags":[
        "contractor"
    ],
    "wof:name":"Perma-Glaze",
    "wof:placetype":"venue"
},
  "geometry": {"coordinates":[-93.228088,38.708511],"type":"Point"}
}