{
  "type": "Feature",
  "properties": {
    "iso:country":"US",
    "sg:address":"1401 N Ballenger Ln",
    "sg:city":"Columbia",
    "sg:classifiers":[
        {
            "category":"Place Of Worship",
            "subcategory":"Church",
            "type":"Public Place"
        },
        {
            "category":"Place Of Worship",
            "type":"Public Place"
        }
    ],
    "sg:phone":"+1 573 474 6895",
    "sg:postcode":"65202",
    "sg:province":"MO",
    "sg:tags":[
        "churches-baptist-general",
        "churches-baptist"
    ],
    "wof:name":"Charity Baptist Church",
    "wof:placetype":"venue"
},
  "geometry": {"coordinates":[-92.26899,38.963749],"type":"Point"}
}