{
  "type": "Feature",
  "properties": {
    "iso:country":"US",
    "sg:address":"4748 S Twin Lakes Ave",
    "sg:city":"Springfield",
    "sg:classifiers":[
        {
            "category":"Professional",
            "type":"Services"
        }
    ],
    "sg:phone":"+1 417 882 0044",
    "sg:postcode":"65810",
    "sg:province":"MO",
    "sg:tags":[
        "caterer"
    ],
    "wof:name":"Abbey Road Catering",
    "wof:placetype":"venue"
},
  "geometry": {"coordinates":[-93.322577,37.127901],"type":"Point"}
}