{
  "type": "Feature",
  "properties": {
    "iso:country":"US",
    "sg:address":"821 Arvin Rd",
    "sg:city":"Dexter",
    "sg:classifiers":[
        {
            "category":"Food & Beverages",
            "subcategory":"Groceries & Convenience Stores",
            "type":"Retail Goods"
        }
    ],
    "sg:phone":"+1 573 624 4085",
    "sg:postcode":"63841",
    "sg:province":"MO",
    "wof:name":"Amerimart",
    "wof:placetype":"venue"
},
  "geometry": {"coordinates":[-89.967697,36.799683],"type":"Point"}
}