{
  "type": "Feature",
  "properties": {
    "iso:country":"US",
    "sg:address":"115 W 18th Ave",
    "sg:city":"Kansas City",
    "sg:classifiers":[
        {
            "category":"Building & Trades",
            "subcategory":"Construction",
            "type":"Services"
        }
    ],
    "sg:phone":"+1 816 221 0878",
    "sg:postcode":"64116",
    "sg:province":"MO",
    "sg:tags":[
        "general",
        "contractor"
    ],
    "wof:name":"Costa Corporation",
    "wof:placetype":"venue"
},
  "geometry": {"coordinates":[-94.58265299999999,39.140202],"type":"Point"}
}