{
  "type": "Feature",
  "properties": {
    "iso:country":"US",
    "sg:address":"2800 SW Walnut St",
    "sg:city":"Blue Springs",
    "sg:classifiers":[
        {
            "category":"Real Estate",
            "subcategory":"Developer",
            "type":"Services"
        }
    ],
    "sg:phone":"+1 816 220 3151",
    "sg:postcode":"64015",
    "sg:province":"MO",
    "sg:tags":[
        "cemetery"
    ],
    "wof:name":"Blue Springs Cemetery",
    "wof:placetype":"venue"
},
  "geometry": {"coordinates":[-94.296132,39.017208],"type":"Point"}
}