{
  "type": "Feature",
  "properties": {
    "iso:country":"US",
    "sg:address":"105 Concord Plaza Shopping Center",
    "sg:city":"St Louis",
    "sg:classifiers":[
        {
            "category":"Restaurant",
            "type":"Food & Drink"
        }
    ],
    "sg:phone":"+1 314 205 3200",
    "sg:postcode":"63128",
    "sg:province":"MO",
    "sg:tags":[
        "management"
    ],
    "wof:name":"WESTERN & Southern Food Svc",
    "wof:placetype":"venue"
},
  "geometry": {"coordinates":[-90.36238400000001,38.524439],"type":"Point"}
}