{
  "type": "Feature",
  "properties": {
    "iso:country":"US",
    "sg:address":"8080 Ward Parkway Plz",
    "sg:city":"Kansas City",
    "sg:classifiers":[
        {
            "category":"Social Services",
            "type":"Services"
        }
    ],
    "sg:phone":"+1 816 361 2666",
    "sg:postcode":"64114",
    "sg:province":"MO",
    "sg:tags":[
        "counselor",
        "marriage",
        "family"
    ],
    "wof:name":"M A Nicholson & Assocs",
    "wof:placetype":"venue"
},
  "geometry": {"coordinates":[-94.60404200000001,38.983274],"type":"Point"}
}