{
  "type": "Feature",
  "properties": {
    "iso:country":"US",
    "sg:address":"115 E Gregory Blvd",
    "sg:city":"Kansas City",
    "sg:classifiers":[
        {
            "category":"Professional",
            "subcategory":"Business Services",
            "type":"Services"
        }
    ],
    "sg:phone":"+1 816 523 4447",
    "sg:postcode":"64114",
    "sg:province":"MO",
    "wof:name":"Highland Group",
    "wof:placetype":"venue"
},
  "geometry": {"coordinates":[-94.58692000000001,38.999243],"type":"Point"}
}