{
  "type": "Feature",
  "properties": {
    "iso:country":"US",
    "sg:address":"111 S Main St",
    "sg:city":"Charleston",
    "sg:classifiers":[
        {
            "category":"Building & Trades",
            "subcategory":"Equipment Rental",
            "type":"Services"
        }
    ],
    "sg:phone":"+1 573 683 6268",
    "sg:postcode":"63834",
    "sg:province":"MO",
    "sg:tags":[
        "leasing",
        "furniture"
    ],
    "wof:name":"Discount Merchandise",
    "wof:placetype":"venue"
},
  "geometry": {"coordinates":[-89.35014200000001,36.923315],"type":"Point"}
}