{
  "type": "Feature",
  "properties": {
    "iso:country":"US",
    "sg:address":"27573 CR 300",
    "sg:city":"Carrollton",
    "sg:classifiers":[
        {
            "category":"Manufacturing",
            "subcategory":"Food",
            "type":"Manufacturing & Wholesale Goods"
        },
        {
            "category":"Farming",
            "subcategory":"Farm",
            "type":"Manufacturing & Wholesale Goods"
        }
    ],
    "sg:phone":"+1 660 542 2722",
    "sg:postcode":"64633",
    "sg:province":"MO",
    "sg:tags":[
        "corn",
        "product"
    ],
    "wof:name":"Hensiek, Haroldea",
    "wof:placetype":"venue"
},
  "geometry": {"coordinates":[-93.42910500000001,39.327211],"type":"Point"}
}