{
  "type": "Feature",
  "properties": {
    "iso:country":"US",
    "sg:address":"336 N Gallatin St",
    "sg:city":"Liberty",
    "sg:classifiers":[
        {
            "category":"Organizations",
            "subcategory":"Religious Organization",
            "type":"Services"
        }
    ],
    "sg:phone":"+1 816 781 4385",
    "sg:postcode":"64068",
    "sg:province":"MO",
    "sg:tags":[
        "church"
    ],
    "wof:name":"First Baptist Church",
    "wof:placetype":"venue"
},
  "geometry": {"coordinates":[-94.42137099999999,39.249957],"type":"Point"}
}