{
  "type": "Feature",
  "properties": {
    "iso:country":"US",
    "sg:address":"258 US Hwy 60",
    "sg:city":"Republic",
    "sg:classifiers":[
        {
            "category":"Health Services",
            "subcategory":"Doctor",
            "type":"Services"
        }
    ],
    "sg:phone":"+1 417 732 2823",
    "sg:postcode":"65738",
    "sg:province":"MO",
    "wof:name":"Stephen D Maus DDS PC",
    "wof:placetype":"venue"
},
  "geometry": {"coordinates":[-93.476985,37.114537],"type":"Point"}
}