{
  "type": "Feature",
  "properties": {
    "iso:country":"US",
    "sg:address":"511 S Commercial St",
    "sg:city":"Branson",
    "sg:classifiers":[
        {
            "category":"Travel",
            "subcategory":"Hotels & Motels",
            "type":"Entertainment"
        }
    ],
    "sg:phone":"+1 417 334 3416",
    "sg:postcode":"65616",
    "sg:province":"MO",
    "wof:name":"Stonewall Motor Inn",
    "wof:placetype":"venue"
},
  "geometry": {"coordinates":[-93.217079,36.639831],"type":"Point"}
}