{
  "type": "Feature",
  "properties": {
    "iso:country":"US",
    "sg:address":"9381 Interstate 70 Dr NE",
    "sg:city":"Columbia",
    "sg:classifiers":[
        {
            "category":"Building & Trades",
            "subcategory":"Construction",
            "type":"Services"
        }
    ],
    "sg:phone":"+1 573 881 2349",
    "sg:postcode":"65202",
    "sg:province":"MO",
    "sg:tags":[
        "wallcoverings-installation",
        "wallpaper",
        "painting",
        "contractor"
    ],
    "wof:name":"After Five Painting",
    "wof:placetype":"venue"
},
  "geometry": {"coordinates":[-92.201334,38.95899],"type":"Point"}
}