{
  "type": "Feature",
  "properties": {
    "iso:country":"US",
    "sg:address":"406 S Carolina St",
    "sg:city":"Louisiana",
    "sg:classifiers":[
        {
            "category":"Organizations",
            "subcategory":"Labor Organization",
            "type":"Services"
        }
    ],
    "sg:phone":"+1 573 754 5670",
    "sg:postcode":"63353",
    "sg:province":"MO",
    "wof:name":"Brotherhood B International",
    "wof:placetype":"venue"
},
  "geometry": {"coordinates":[-91.04786900000001,39.448803],"type":"Point"}
}