{
  "type": "Feature",
  "properties": {
    "iso:country":"US",
    "sg:address":"2618 Woodson Rd",
    "sg:city":"Overland",
    "sg:classifiers":[
        {
            "category":"Retail",
            "subcategory":"Auto Repair",
            "type":"Services"
        }
    ],
    "sg:phone":"+1 314 426 1600",
    "sg:postcode":"63114",
    "sg:province":"MO",
    "sg:tags":[
        "body",
        "automobile",
        "painting"
    ],
    "wof:name":"Hi-Tech Collision Repair",
    "wof:placetype":"venue"
},
  "geometry": {"coordinates":[-90.36116699999999,38.706324],"type":"Point"}
}