{
  "type": "Feature",
  "properties": {
    "iso:country":"US",
    "sg:address":"562 N Taylor Ave",
    "sg:city":"Kirkwood",
    "sg:classifiers":[
        {
            "category":"Banks & Credit Unions",
            "subcategory":"Financial Services",
            "type":"Services"
        }
    ],
    "sg:phone":"+1 314 616 6117",
    "sg:postcode":"63122",
    "sg:province":"MO",
    "wof:name":"Riverway Financial",
    "wof:placetype":"venue"
},
  "geometry": {"coordinates":[-90.403907,38.588236],"type":"Point"}
}