{
  "type": "Feature",
  "properties": {
    "iso:country":"US",
    "sg:address":"19 Hazelwood Rd",
    "sg:city":"Eldon",
    "sg:classifiers":[
        {
            "category":"Home & Garden",
            "subcategory":"Building Materials",
            "type":"Retail Goods"
        }
    ],
    "sg:phone":"+1 573 392 7473",
    "sg:postcode":"65026",
    "sg:province":"MO",
    "wof:name":"T&T Surplus",
    "wof:placetype":"venue"
},
  "geometry": {"coordinates":[-92.58274299999999,38.266628],"type":"Point"}
}