{
  "type": "Feature",
  "properties": {
    "iso:country":"US",
    "sg:address":"601 S Chamber Dr",
    "sg:city":"Fredericktown",
    "sg:classifiers":[
        {
            "category":"Building & Trades",
            "subcategory":"Construction",
            "type":"Services"
        }
    ],
    "sg:phone":"+1 573 783 4510",
    "sg:postcode":"63645",
    "sg:province":"MO",
    "sg:tags":[
        "boring",
        "drilling",
        "contractor"
    ],
    "wof:name":"Hard Rock Drilling Supplies",
    "wof:placetype":"venue"
},
  "geometry": {"coordinates":[-90.28180399999999,37.552788],"type":"Point"}
}