{
  "type": "Feature",
  "properties": {
    "iso:country":"US",
    "sg:address":"13912 S Noland Ct",
    "sg:city":"Independence",
    "sg:classifiers":[
        {
            "category":"Insurance",
            "subcategory":"Insurance Agent",
            "type":"Services"
        }
    ],
    "sg:phone":"+1 816 836 1330",
    "sg:postcode":"64055",
    "sg:province":"MO",
    "wof:name":"Farmers Insurance Group",
    "wof:placetype":"venue"
},
  "geometry": {"coordinates":[-94.41543900000001,39.054457],"type":"Point"}
}