{
  "type": "Feature",
  "properties": {
    "iso:country":"US",
    "sg:address":"9245 Dielman Industrial Dr",
    "sg:city":"St Louis",
    "sg:classifiers":[
        {
            "category":"Wholesale",
            "subcategory":"Construction Materials",
            "type":"Manufacturing & Wholesale Goods"
        }
    ],
    "sg:phone":"+1 314 994 7100",
    "sg:postcode":"63132",
    "sg:province":"MO",
    "sg:tags":[
        "tile"
    ],
    "sg:website":"www.amctile.com",
    "wof:name":"AMC Tile",
    "wof:placetype":"venue"
},
  "geometry": {"coordinates":[-90.37211499999999,38.676797],"type":"Point"}
}