{
  "type": "Feature",
  "properties": {
    "iso:country":"US",
    "sg:address":"1711 S 9th St",
    "sg:city":"St. Louis",
    "sg:classifiers":[
        {
            "category":"Bars & Pubs",
            "type":"Food & Drink"
        }
    ],
    "sg:phone":"+1 314 621 4333",
    "sg:postcode":"63104",
    "sg:province":"MO",
    "sg:website":"www.internationaltaphouse.com/",
    "wof:name":"International Tap House",
    "wof:placetype":"venue"
},
  "geometry": {"coordinates":[-90.202984,38.61043],"type":"Point"}
}