{
  "type": "Feature",
  "properties": {
    "addr:full":"9226 Roger Lee Ln Saint Louis MO 63126",
    "addr:housenumber":"9226",
    "addr:postcode":"63126",
    "addr:street":"Roger Lee Ln",
    "iso:country":"US",
    "sg:address":"9226 Roger Lee Ln",
    "sg:city":"Saint Louis",
    "sg:classifiers":[
        {
            "category":"Health Services",
            "subcategory":"Clinic",
            "type":"Services"
        }
    ],
    "sg:phone":"+1 314 849 6421",
    "sg:postcode":"63126",
    "sg:province":"MO",
    "wof:name":"Red Cross",
    "wof:placetype":"venue"
},
  "geometry": {"coordinates":[-90.377613,38.549288],"type":"Point"}
}