{
  "type": "Feature",
  "properties": {
    "iso:country":"US",
    "sg:address":"229 E Commercial St",
    "sg:city":"Springfield",
    "sg:classifiers":[
        {
            "category":"Wholesale",
            "subcategory":"Medical Equipment & Supplies",
            "type":"Manufacturing & Wholesale Goods"
        }
    ],
    "sg:phone":"+1 417 863 9678",
    "sg:postcode":"65803",
    "sg:province":"MO",
    "sg:tags":[
        "massage"
    ],
    "wof:name":"Noble Path",
    "wof:placetype":"venue"
},
  "geometry": {"coordinates":[-93.291,37.229717],"type":"Point"}
}