{
  "type": "Feature",
  "properties": {
    "iso:country":"US",
    "sg:address":"10226 Page Ave",
    "sg:city":"St Louis",
    "sg:classifiers":[
        {
            "category":"Insurance",
            "subcategory":"Insurance Agent",
            "type":"Services"
        }
    ],
    "sg:phone":"+1 314 426 5818",
    "sg:postcode":"63132",
    "sg:province":"MO",
    "wof:name":"Direct General Ins Agency",
    "wof:placetype":"venue"
},
  "geometry": {"coordinates":[-90.38567999999999,38.691044],"type":"Point"}
}