{
  "type": "Feature",
  "properties": {
    "iso:country":"US",
    "sg:address":"1511 Christy Dr",
    "sg:city":"Jefferson City",
    "sg:classifiers":[
        {
            "category":"Social Services",
            "type":"Services"
        }
    ],
    "sg:phone":"+1 573 526 6516",
    "sg:postcode":"65101",
    "sg:province":"MO",
    "sg:tags":[
        "victim",
        "crime"
    ],
    "wof:name":"Victim Services Dept",
    "wof:placetype":"venue"
},
  "geometry": {"coordinates":[-92.189486,38.559879],"type":"Point"}
}