{
  "type": "Feature",
  "properties": {
    "iso:country":"US",
    "sg:address":"247 Jacob Ln",
    "sg:city":"Ballwin",
    "sg:classifiers":[
        {
            "category":"Banks & Credit Unions",
            "subcategory":"Financial Services",
            "type":"Services"
        }
    ],
    "sg:phone":"+1 636 256 9031",
    "sg:postcode":"63021",
    "sg:province":"MO",
    "sg:tags":[
        "investor"
    ],
    "wof:name":"Vignesh Investments LLC",
    "wof:placetype":"venue"
},
  "geometry": {"coordinates":[-90.571951,38.582701],"type":"Point"}
}