{
  "type": "Feature",
  "properties": {
    "addr:full":"6926 S Lindbergh Blvd St Louis MO 63125",
    "addr:housenumber":"6926",
    "addr:postcode":"63125",
    "addr:street":"S Lindbergh Blvd",
    "iso:country":"US",
    "sg:address":"6926 S Lindbergh Blvd",
    "sg:city":"St Louis",
    "sg:classifiers":[
        {
            "category":"Shopping",
            "subcategory":"Computers & Home Electronics",
            "type":"Retail Goods"
        }
    ],
    "sg:phone":"+1 314 845 2428",
    "sg:postcode":"63125",
    "sg:province":"MO",
    "sg:tags":[
        "equipment",
        "electronic",
        "supply"
    ],
    "wof:name":"Circuit City",
    "wof:placetype":"venue"
},
  "geometry": {"coordinates":[-90.334982,38.510876],"type":"Point"}
}