{
  "type": "Feature",
  "properties": {
    "iso:country":"US",
    "sg:address":"422 D St",
    "sg:city":"Belton",
    "sg:classifiers":[
        {
            "category":"Personal",
            "subcategory":"Beauty Salon",
            "type":"Services"
        }
    ],
    "sg:phone":"+1 816 322 3138",
    "sg:postcode":"64012",
    "sg:province":"MO",
    "wof:name":"Linda's",
    "wof:placetype":"venue"
},
  "geometry": {"coordinates":[-94.52794,38.814038],"type":"Point"}
}