{
  "type": "Feature",
  "properties": {
    "iso:country":"US",
    "sg:address":"765 S Glenstone Ave",
    "sg:city":"Springfield",
    "sg:classifiers":[
        {
            "category":"Bars & Pubs",
            "type":"Food & Drink"
        }
    ],
    "sg:phone":"+1 417 866 8901",
    "sg:postcode":"65802",
    "sg:province":"MO",
    "sg:tags":[
        "lounge",
        "cocktail"
    ],
    "wof:name":"Pink Cadillac",
    "wof:placetype":"venue"
},
  "geometry": {"coordinates":[-93.26200900000001,37.19923],"type":"Point"}
}