{
  "type": "Feature",
  "properties": {
    "iso:country":"US",
    "sg:address":"7025 Howdershell Rd",
    "sg:city":"Hazelwood",
    "sg:classifiers":[
        {
            "category":"Personal",
            "subcategory":"Beauty Salon",
            "type":"Services"
        }
    ],
    "sg:phone":"+1 314 731 7505",
    "sg:postcode":"63042",
    "sg:province":"MO",
    "sg:tags":[
        "manicuring"
    ],
    "wof:name":"Asia Nail Salon",
    "wof:placetype":"venue"
},
  "geometry": {"coordinates":[-90.37450699999999,38.790848],"type":"Point"}
}