{
  "type": "Feature",
  "properties": {
    "iso:country":"US",
    "sg:address":"1410 N Fremont Ave",
    "sg:city":"Springfield",
    "sg:classifiers":[
        {
            "category":"Social Services",
            "type":"Services"
        }
    ],
    "sg:phone":"+1 417 865 6082",
    "sg:postcode":"65802",
    "sg:province":"MO",
    "wof:name":"Hendirson Unit",
    "wof:placetype":"venue"
},
  "geometry": {"coordinates":[-93.270416,37.225446],"type":"Point"}
}