{
  "type": "Feature",
  "properties": {
    "iso:country":"US",
    "sg:address":"8438 N Lindbergh Blvd",
    "sg:city":"Florissant",
    "sg:classifiers":[
        {
            "category":"Personal",
            "type":"Services"
        }
    ],
    "sg:phone":"+1 314 837 7772",
    "sg:postcode":"63031",
    "sg:province":"MO",
    "sg:tags":[
        "therapist",
        "massage"
    ],
    "wof:name":"Kim's Total Relaxation Massage",
    "wof:placetype":"venue"
},
  "geometry": {"coordinates":[-90.343277,38.792644],"type":"Point"}
}