{
  "type": "Feature",
  "properties": {
    "iso:country":"US",
    "sg:address":"112 E Lincoln Ave",
    "sg:city":"Owensville",
    "sg:classifiers":[
        {
            "category":"Autos & Motor Vehicles",
            "subcategory":"Auto Supplies",
            "type":"Retail Goods"
        }
    ],
    "sg:phone":"+1 573 437 3305",
    "sg:postcode":"65066",
    "sg:province":"MO",
    "sg:tags":[
        "tire"
    ],
    "wof:name":"Dud's Tire Shop",
    "wof:placetype":"venue"
},
  "geometry": {"coordinates":[-91.50035699999999,38.344961],"type":"Point"}
}