{
  "type": "Feature",
  "properties": {
    "iso:country":"US",
    "sg:address":"914 E Washington Blvd",
    "sg:city":"Cuba",
    "sg:classifiers":[
        {
            "category":"Home & Garden",
            "subcategory":"Building Materials",
            "type":"Retail Goods"
        }
    ],
    "sg:phone":"+1 573 885 2555",
    "sg:postcode":"65453",
    "sg:province":"MO",
    "wof:name":"Wolfco",
    "wof:placetype":"venue"
},
  "geometry": {"coordinates":[-91.39520899999999,38.064342],"type":"Point"}
}