{
  "type": "Feature",
  "properties": {
    "iso:country":"US",
    "sg:address":"199 Main St",
    "sg:city":"Truxton",
    "sg:classifiers":[
        {
            "category":"Professional",
            "subcategory":"Computer Services",
            "type":"Services"
        }
    ],
    "sg:phone":"+1 636 597 3636",
    "sg:postcode":"63381",
    "sg:province":"MO",
    "sg:tags":[
        "internet"
    ],
    "wof:name":"Socket Internet",
    "wof:placetype":"venue"
},
  "geometry": {"coordinates":[-91.24156499999999,39.003157],"type":"Point"}
}