{
  "type": "Feature",
  "properties": {
    "iso:country":"US",
    "sg:address":"17 Pearl Dr",
    "sg:city":"Hillsboro",
    "sg:classifiers":[
        {
            "category":"Organizations",
            "subcategory":"Religious Organization",
            "type":"Services"
        }
    ],
    "sg:phone":"+1 636 797 3761",
    "sg:postcode":"63050",
    "sg:province":"MO",
    "sg:tags":[
        "church"
    ],
    "wof:name":"Peace Tabernacle",
    "wof:placetype":"venue"
},
  "geometry": {"coordinates":[-90.566947,38.225922],"type":"Point"}
}