{
  "type": "Feature",
  "properties": {
    "iso:country":"US",
    "sg:address":"904 W Main St",
    "sg:city":"West Plains",
    "sg:classifiers":[
        {
            "category":"Organizations",
            "subcategory":"Religious Organization",
            "type":"Services"
        }
    ],
    "sg:phone":"+1 417 256 7700",
    "sg:postcode":"65775",
    "sg:province":"MO",
    "sg:tags":[
        "church"
    ],
    "wof:name":"Victory Family Worship Center",
    "wof:placetype":"venue"
},
  "geometry": {"coordinates":[-91.861344,36.728275],"type":"Point"}
}