{
  "type": "Feature",
  "properties": {
    "iso:country":"US",
    "sg:address":"607 Whitney St",
    "sg:city":"Kennett",
    "sg:classifiers":[
        {
            "category":"Retail",
            "subcategory":"Repair Shop",
            "type":"Services"
        }
    ],
    "sg:phone":"+1 573 888 3060",
    "sg:postcode":"63857",
    "sg:province":"MO",
    "wof:name":"Goodriches Cleaning",
    "wof:placetype":"venue"
},
  "geometry": {"coordinates":[-90.050112,36.237318],"type":"Point"}
}