{
  "type": "Feature",
  "properties": {
    "iso:country":"US",
    "sg:address":"416 N College St",
    "sg:city":"Richmond",
    "sg:classifiers":[
        {
            "category":"Banks & Credit Unions",
            "subcategory":"Bank",
            "type":"Services"
        }
    ],
    "sg:phone":"+1 816 470 2020",
    "sg:postcode":"64085",
    "sg:province":"MO",
    "sg:tags":[
        "loan",
        "real estate"
    ],
    "wof:name":"Gateway Mortgage Group LLC",
    "wof:placetype":"venue"
},
  "geometry": {"coordinates":[-93.977968,39.282086],"type":"Point"}
}