{
  "type": "Feature",
  "properties": {
    "iso:country":"US",
    "sg:address":"102 Parkdale St",
    "sg:city":"Cuba",
    "sg:classifiers":[
        {
            "category":"Freight",
            "type":"Transportation"
        }
    ],
    "sg:phone":"+1 573 885 6775",
    "sg:postcode":"65453",
    "sg:province":"MO",
    "sg:tags":[
        "operator",
        "local",
        "trucking"
    ],
    "wof:name":"Volner Trucking",
    "wof:placetype":"venue"
},
  "geometry": {"coordinates":[-91.396934,38.057304],"type":"Point"}
}