{
  "type": "Feature",
  "properties": {
    "iso:country":"US",
    "sg:address":"6352 Forsyth Blvd",
    "sg:city":"Saint Louis",
    "sg:classifiers":[
        {
            "category":"Education",
            "subcategory":"University",
            "type":"Public Place"
        }
    ],
    "sg:phone":"+1 314 725 8134",
    "sg:postcode":"63105",
    "sg:province":"MO",
    "sg:tags":[
        "college"
    ],
    "wof:name":"Catholic Student Center At Washington University",
    "wof:placetype":"venue"
},
  "geometry": {"coordinates":[-90.305801,38.6465],"type":"Point"}
}