{
  "type": "Feature",
  "properties": {
    "iso:country":"US",
    "sg:address":"736 Crab Thicket Ln",
    "sg:city":"St Louis",
    "sg:classifiers":[
        {
            "category":"Professional",
            "subcategory":"Management & Consulting",
            "type":"Services"
        }
    ],
    "sg:phone":"+1 314 821 3316",
    "sg:postcode":"63131",
    "sg:province":"MO",
    "sg:tags":[
        "consultant",
        "business"
    ],
    "wof:name":"Community Resource Associates",
    "wof:placetype":"venue"
},
  "geometry": {"coordinates":[-90.456729,38.5922],"type":"Point"}
}