{
  "type": "Feature",
  "properties": {
    "iso:country":"US",
    "sg:address":"1426 Pointe Royale Dr",
    "sg:city":"Branson",
    "sg:classifiers":[
        {
            "category":"Shopping",
            "subcategory":"Bicycles & Sporting Goods",
            "type":"Retail Goods"
        },
        {
            "category":"Sports & Exercise",
            "subcategory":"Golf",
            "type":"Entertainment"
        }
    ],
    "sg:phone":"+1 417 336 2134",
    "sg:postcode":"65616",
    "sg:province":"MO",
    "sg:tags":[
        "equipment",
        "supply",
        "course"
    ],
    "wof:name":"Golf Usa",
    "wof:placetype":"venue"
},
  "geometry": {"coordinates":[-93.276695,36.600733],"type":"Point"}
}