{
  "type": "Feature",
  "properties": {
    "iso:country":"US",
    "sg:address":"103 N Walnut St",
    "sg:city":"Willow Springs",
    "sg:classifiers":[
        {
            "category":"Personal",
            "subcategory":"Beauty Salon",
            "type":"Services"
        }
    ],
    "sg:phone":"+1 417 469 3696",
    "sg:postcode":"65793",
    "sg:province":"MO",
    "sg:tags":[
        "shop"
    ],
    "wof:name":"Linda's Hair Affair",
    "wof:placetype":"venue"
},
  "geometry": {"coordinates":[-91.96841999999999,36.991293],"type":"Point"}
}