{
  "type": "Feature",
  "properties": {
    "iso:country":"US",
    "sg:address":"9301 Co Rd 607",
    "sg:city":"Dexter",
    "sg:classifiers":[
        {
            "category":"Professional",
            "type":"Services"
        }
    ],
    "sg:phone":"+1 573 624 3806",
    "sg:postcode":"63841",
    "sg:province":"MO",
    "wof:name":"Darrell Tipton",
    "wof:placetype":"venue"
},
  "geometry": {"coordinates":[-89.99032200000001,36.739461],"type":"Point"}
}