{
  "type": "Feature",
  "properties": {
    "iso:country":"US",
    "sg:address":"1933 NE 77 St",
    "sg:city":"Kansas City",
    "sg:classifiers":[
        {
            "category":"Recreation",
            "type":"Entertainment"
        }
    ],
    "sg:phone":"+1 816 769 9454",
    "sg:postcode":"64118",
    "sg:province":"MO",
    "sg:tags":[
        "aquarium"
    ],
    "wof:name":"Fish Man",
    "wof:placetype":"venue"
},
  "geometry": {"coordinates":[-94.55574300000001,39.233543],"type":"Point"}
}