{
  "type": "Feature",
  "properties": {
    "iso:country":"US",
    "sg:address":"633 Nave Ferry Rd",
    "sg:city":"Protem",
    "sg:classifiers":[
        {
            "category":"Farming",
            "subcategory":"Farm & Veterinary Services",
            "type":"Manufacturing & Wholesale Goods"
        }
    ],
    "sg:phone":"+1 417 785 4526",
    "sg:postcode":"65733",
    "sg:province":"MO",
    "sg:tags":[
        "livestock"
    ],
    "wof:name":"Forrest Cattle Co",
    "wof:placetype":"venue"
},
  "geometry": {"coordinates":[-92.91194400000001,36.49793],"type":"Point"}
}