{
  "type": "Feature",
  "properties": {
    "iso:country":"US",
    "sg:address":"1716 S Broadway",
    "sg:city":"St Louis",
    "sg:classifiers":[
        {
            "category":"Health Services",
            "subcategory":"Hospital",
            "type":"Services"
        }
    ],
    "sg:phone":"+1 314 241 9019",
    "sg:postcode":"63104",
    "sg:province":"MO",
    "sg:tags":[
        "mental"
    ],
    "wof:name":"Community Support",
    "wof:placetype":"venue"
},
  "geometry": {"coordinates":[-90.200789,38.607501],"type":"Point"}
}