{
  "type": "Feature",
  "properties": {
    "iso:country":"US",
    "sg:address":"7462 Old Highway 60",
    "sg:city":"Dudley",
    "sg:classifiers":[
        {
            "category":"Home & Garden",
            "subcategory":"Garden Supply",
            "type":"Retail Goods"
        },
        {
            "category":"Professional",
            "type":"Services"
        }
    ],
    "sg:phone":"+1 573 967 3747",
    "sg:postcode":"63936",
    "sg:province":"MO",
    "sg:tags":[
        "fertilizer",
        "fertilizing"
    ],
    "wof:name":"Farmers Fertilizer Service",
    "wof:placetype":"venue"
},
  "geometry": {"coordinates":[-90.152434,36.790589],"type":"Point"}
}