{
  "type": "Feature",
  "properties": {
    "iso:country":"US",
    "sg:address":"3645 South Ave",
    "sg:city":"Springfield",
    "sg:classifiers":[
        {
            "category":"Professional",
            "subcategory":"Accounting & Tax Preparation",
            "type":"Services"
        }
    ],
    "sg:phone":"+1 417 882 3040",
    "sg:postcode":"65807",
    "sg:province":"MO",
    "sg:tags":[
        "bookkeeping",
        "general"
    ],
    "wof:name":"ABC Tax & Accounting Svc",
    "wof:placetype":"venue"
},
  "geometry": {"coordinates":[-93.29372100000001,37.147238],"type":"Point"}
}