{
  "type": "Feature",
  "properties": {
    "iso:country":"US",
    "sg:address":"4101 E 185th St",
    "sg:city":"Belton",
    "sg:classifiers":[
        {
            "category":"Sports & Exercise",
            "subcategory":"Race Track",
            "type":"Entertainment"
        }
    ],
    "sg:phone":"+1 816 763 7898",
    "sg:postcode":"64012",
    "sg:province":"MO",
    "sg:tags":[
        "operation",
        "racing",
        "or"
    ],
    "wof:name":"Sackuvich Racing Inc",
    "wof:placetype":"venue"
},
  "geometry": {"coordinates":[-94.550777,38.789967],"type":"Point"}
}