{
  "type": "Feature",
  "properties": {
    "addr:full":"208 W Sunrise Dr Belton MO 64012",
    "addr:housenumber":"208",
    "addr:postcode":"64012",
    "addr:street":"W Sunrise Dr",
    "iso:country":"US",
    "sg:address":"208 W Sunrise Dr",
    "sg:city":"Belton",
    "sg:classifiers":[
        {
            "category":"Wholesale",
            "subcategory":"Construction Materials",
            "type":"Manufacturing & Wholesale Goods"
        }
    ],
    "sg:phone":"+1 816 667 5954",
    "sg:postcode":"64012",
    "sg:province":"MO",
    "sg:tags":[
        "lumber"
    ],
    "wof:name":"Weyerhaeuser Co",
    "wof:placetype":"venue"
},
  "geometry": {"coordinates":[-94.538152,38.807307],"type":"Point"}
}