{
  "type": "Feature",
  "properties": {
    "iso:country":"US",
    "sg:address":"1575 E State Hwy K",
    "sg:city":"West Plains",
    "sg:classifiers":[
        {
            "category":"Retail",
            "subcategory":"Auto Repair",
            "type":"Services"
        }
    ],
    "sg:phone":"+1 417 257 2580",
    "sg:postcode":"65775",
    "sg:province":"MO",
    "sg:tags":[
        "transmission",
        "general"
    ],
    "wof:name":"Barry's Auto & Transmission",
    "wof:placetype":"venue"
},
  "geometry": {"coordinates":[-91.890843,36.7268],"type":"Point"}
}