{
  "type": "Feature",
  "properties": {
    "iso:country":"US",
    "sg:address":"307 N Weller Ave",
    "sg:city":"Springfield",
    "sg:classifiers":[
        {
            "category":"Retail",
            "subcategory":"Auto Repair",
            "type":"Services"
        }
    ],
    "sg:phone":"+1 417 864 8989",
    "sg:postcode":"65802",
    "sg:province":"MO",
    "sg:tags":[
        "shop",
        "automotive",
        "general"
    ],
    "wof:name":"Hopkins Autoworks",
    "wof:placetype":"venue"
},
  "geometry": {"coordinates":[-93.268275,37.211037],"type":"Point"}
}