{
  "type": "Feature",
  "properties": {
    "iso:country":"US",
    "sg:address":"1515 S Morley St",
    "sg:city":"Moberly",
    "sg:classifiers":[
        {
            "category":"Retail",
            "subcategory":"Repair Shop",
            "type":"Services"
        }
    ],
    "sg:phone":"+1 660 263 0143",
    "sg:postcode":"65270",
    "sg:province":"MO",
    "sg:tags":[
        "plumbing",
        "drain",
        "cleaning",
        "sewer"
    ],
    "wof:name":"Frank Vorhees Plumbing",
    "wof:placetype":"venue"
},
  "geometry": {"coordinates":[-92.43440699999999,39.399167],"type":"Point"}
}