{
  "type": "Feature",
  "properties": {
    "iso:country":"US",
    "sg:address":"2450 Co Rd 629",
    "sg:city":"Fisk",
    "sg:phone":"+1 573 785 5521",
    "sg:postcode":"63940",
    "sg:province":"MO",
    "sg:tags":[
        "farm",
        "soybean"
    ],
    "wof:name":"Terry Acre",
    "wof:placetype":"venue"
},
  "geometry": {"coordinates":[-90.262952,36.735965],"type":"Point"}
}