{
  "type": "Feature",
  "properties": {
    "iso:country":"US",
    "sg:address":"17527 US Hwy 71 Bus",
    "sg:city":"St Joseph",
    "sg:classifiers":[
        {
            "category":"Shopping",
            "type":"Retail Goods"
        },
        {
            "category":"Food & Beverages",
            "subcategory":"Bakery",
            "type":"Retail Goods"
        }
    ],
    "sg:phone":"+1 816 324 3500",
    "sg:postcode":"64505",
    "sg:province":"MO",
    "sg:tags":[
        "baker",
        "merchandise"
    ],
    "wof:name":"Bev's Cakes With Class",
    "wof:placetype":"venue"
},
  "geometry": {"coordinates":[-94.80871399999999,39.880175],"type":"Point"}
}