{
  "type": "Feature",
  "properties": {
    "iso:country":"US",
    "sg:address":"1000 Goldenrod Rd",
    "sg:city":"Lake Ozark",
    "sg:classifiers":[
        {
            "category":"Travel",
            "subcategory":"Travel Agent",
            "type":"Entertainment"
        }
    ],
    "sg:phone":"+1 573 365 5281",
    "sg:postcode":"65049",
    "sg:province":"MO",
    "sg:tags":[
        "agency"
    ],
    "wof:name":"Just Travel",
    "wof:placetype":"venue"
},
  "geometry": {"coordinates":[-92.73809199999999,38.198924],"type":"Point"}
}