{
  "type": "Feature",
  "properties": {
    "iso:country":"US",
    "sg:address":"135 Spring Garden Rd",
    "sg:city":"Olean",
    "sg:classifiers":[
        {
            "category":"Building & Trades",
            "subcategory":"Plumbing",
            "type":"Services"
        }
    ],
    "sg:phone":"+1 573 498 3831",
    "sg:postcode":"65064",
    "sg:province":"MO",
    "sg:tags":[
        "plumbing",
        "contractor"
    ],
    "wof:name":"Dink's Plumbing Svc",
    "wof:placetype":"venue"
},
  "geometry": {"coordinates":[-92.422546,38.386527],"type":"Point"}
}