{
  "type": "Feature",
  "properties": {
    "iso:country":"US",
    "sg:address":"8228 Hickman Mills Dr",
    "sg:city":"Kansas City",
    "sg:classifiers":[
        {
            "category":"Home & Garden",
            "subcategory":"Furniture",
            "type":"Retail Goods"
        }
    ],
    "sg:phone":"+1 816 822 2622",
    "sg:postcode":"64132",
    "sg:province":"MO",
    "wof:name":"Merchandise World",
    "wof:placetype":"venue"
},
  "geometry": {"coordinates":[-94.555623,38.976605],"type":"Point"}
}