{
  "type": "Feature",
  "properties": {
    "iso:country":"US",
    "sg:address":"16369 Lawrence 2050",
    "sg:city":"Miller",
    "sg:classifiers":[
        {
            "category":"Health Services",
            "subcategory":"Clinic",
            "type":"Services"
        }
    ],
    "sg:phone":"+1 417 732 1534",
    "sg:postcode":"65707",
    "sg:province":"MO",
    "sg:tags":[
        "nutrition"
    ],
    "wof:name":"Total Beauty LLC",
    "wof:placetype":"venue"
},
  "geometry": {"coordinates":[-93.76510399999999,37.204209],"type":"Point"}
}