{
  "type": "Feature",
  "properties": {
    "iso:country":"US",
    "sg:address":"6003 Robert Dr",
    "sg:city":"Malden",
    "sg:classifiers":[
        {
            "category":"Retail",
            "subcategory":"Repair Shop",
            "type":"Services"
        },
        {
            "category":"Building & Trades",
            "subcategory":"Plumbing",
            "type":"Services"
        }
    ],
    "sg:phone":"+1 573 276 5319",
    "sg:postcode":"63863",
    "sg:province":"MO",
    "sg:tags":[
        "septic"
    ],
    "wof:name":"Malden Septic Tank Service",
    "wof:placetype":"venue"
},
  "geometry": {"coordinates":[-90.061285,36.561707],"type":"Point"}
}