{
  "type": "Feature",
  "properties": {
    "iso:country":"US",
    "sg:address":"5741 E Meadowmere St",
    "sg:city":"Springfield",
    "sg:classifiers":[
        {
            "category":"Retail",
            "subcategory":"Animal Services",
            "type":"Services"
        }
    ],
    "sg:phone":"+1 417 866 2088",
    "sg:postcode":"65809",
    "sg:province":"MO",
    "sg:tags":[
        "training",
        "dog"
    ],
    "wof:name":"Bradford Park Puppy Pre School",
    "wof:placetype":"venue"
},
  "geometry": {"coordinates":[-93.171441,37.187482],"type":"Point"}
}