{
  "type": "Feature",
  "properties": {
    "iso:country":"US",
    "sg:address":"8846 Indian Bend Rd",
    "sg:city":"Rosebud",
    "sg:classifiers":[
        {
            "category":"Farming",
            "subcategory":"Livestock Farm",
            "type":"Manufacturing & Wholesale Goods"
        }
    ],
    "sg:phone":"+1 573 764 2377",
    "sg:postcode":"63091",
    "sg:province":"MO",
    "sg:tags":[
        "beef",
        "feedlot",
        "cattle"
    ],
    "wof:name":"Joseph Zelch",
    "wof:placetype":"venue"
},
  "geometry": {"coordinates":[-91.36594700000001,38.293158],"type":"Point"}
}