{
  "type": "Feature",
  "properties": {
    "iso:country":"US",
    "sg:address":"2101 S Vandeventer Ave",
    "sg:city":"Saint Louis",
    "sg:classifiers":[
        {
            "category":"Shopping",
            "subcategory":"Beauty & Cosmetics",
            "type":"Retail Goods"
        }
    ],
    "sg:phone":"+1 314 664 5700",
    "sg:postcode":"63110",
    "sg:province":"MO",
    "sg:tags":[
        "supply"
    ],
    "wof:name":"Kings Beauty Distribution",
    "wof:placetype":"venue"
},
  "geometry": {"coordinates":[-90.264482,38.615172],"type":"Point"}
}