{
  "type": "Feature",
  "properties": {
    "iso:country":"US",
    "sg:address":"18225 Old Jamestown Rd",
    "sg:city":"Florissant",
    "sg:classifiers":[
        {
            "category":"Professional",
            "subcategory":"Lawyer & Legal Services",
            "type":"Services"
        }
    ],
    "sg:phone":"+1 314 921 5572",
    "sg:postcode":"63034",
    "sg:province":"MO",
    "sg:tags":[
        "convention",
        "reporters-court"
    ],
    "wof:name":"Willis Reporting Service",
    "wof:placetype":"venue"
},
  "geometry": {"coordinates":[-90.288911,38.849222],"type":"Point"}
}