{
  "type": "Feature",
  "properties": {
    "iso:country":"US",
    "sg:address":"16445 Village Plaza View Dr",
    "sg:city":"Ballwin",
    "sg:classifiers":[
        {
            "category":"Restaurant",
            "type":"Food & Drink"
        }
    ],
    "sg:menulink":"http://www.allmenus.com/mo/wildhorse/57749-hunan-express/menu/",
    "sg:phone":"+1 636 458 0898",
    "sg:postcode":"63011",
    "sg:province":"MO",
    "sg:tags":[
        "asian",
        "chinese"
    ],
    "wof:name":"Hunan Express",
    "wof:placetype":"venue"
},
  "geometry": {"coordinates":[-90.61739799999999,38.583134],"type":"Point"}
}