{
  "type": "Feature",
  "properties": {
    "iso:country":"US",
    "sg:address":"171 Osage Rd",
    "sg:city":"Urbana",
    "sg:classifiers":[
        {
            "category":"Farming",
            "subcategory":"Dairy Farm",
            "type":"Manufacturing & Wholesale Goods"
        }
    ],
    "sg:phone":"+1 417 993 4364",
    "sg:postcode":"65653",
    "sg:province":"MO",
    "wof:name":"Dryer Alivn",
    "wof:placetype":"venue"
},
  "geometry": {"coordinates":[-93.061612,36.722687],"type":"Point"}
}