{
  "type": "Feature",
  "properties": {
    "iso:country":"US",
    "sg:address":"2122 Parkway Dr",
    "sg:city":"St Peters",
    "sg:classifiers":[
        {
            "category":"Retail",
            "subcategory":"Laundry & Dry Cleaning",
            "type":"Services"
        }
    ],
    "sg:phone":"+1 636 498 1000",
    "sg:postcode":"63376",
    "sg:province":"MO",
    "sg:tags":[
        "cleaners",
        "rug",
        "carpet"
    ],
    "wof:name":"Bales Carpet Cleaning",
    "wof:placetype":"venue"
},
  "geometry": {"coordinates":[-90.572953,38.797539],"type":"Point"}
}