{
  "type": "Feature",
  "properties": {
    "iso:country":"US",
    "sg:address":"1100 S Powell Rd",
    "sg:city":"Independence",
    "sg:classifiers":[
        {
            "category":"Freight",
            "type":"Transportation"
        },
        {
            "category":"Utilities",
            "subcategory":"Refuse",
            "type":"Services"
        }
    ],
    "sg:phone":"+1 816 796 0220",
    "sg:postcode":"64056",
    "sg:province":"MO",
    "sg:tags":[
        "hauling",
        "system",
        "trucking"
    ],
    "wof:name":"Grimes Hauling Co",
    "wof:placetype":"venue"
},
  "geometry": {"coordinates":[-94.3289,39.092268],"type":"Point"}
}