{
  "type": "Feature",
  "properties": {
    "iso:country":"US",
    "sg:address":"447 E Karsch Blvd",
    "sg:city":"Farmington",
    "sg:classifiers":[
        {
            "category":"Shopping",
            "subcategory":"Bicycles & Sporting Goods",
            "type":"Retail Goods"
        }
    ],
    "sg:phone":"+1 573 756 3999",
    "sg:postcode":"63640",
    "sg:province":"MO",
    "sg:tags":[
        "sport",
        "clothing"
    ],
    "wof:name":"K & K Sports Inc",
    "wof:placetype":"venue"
},
  "geometry": {"coordinates":[-90.415093,37.786531],"type":"Point"}
}