{
  "type": "Feature",
  "properties": {
    "iso:country":"US",
    "sg:address":"3166 W Battlefield Rd",
    "sg:city":"Springfield",
    "sg:classifiers":[
        {
            "category":"Retail",
            "subcategory":"Auto Repair",
            "type":"Services"
        }
    ],
    "sg:phone":"+1 417 886 2212",
    "sg:postcode":"65807",
    "sg:province":"MO",
    "sg:tags":[
        "repairing",
        "automobile"
    ],
    "wof:name":"Mr Smith's Fast Lube Inc",
    "wof:placetype":"venue"
},
  "geometry": {"coordinates":[-93.34211999999999,37.160335],"type":"Point"}
}