{
  "type": "Feature",
  "properties": {
    "iso:country":"US",
    "sg:address":"1813 Missouri Ave",
    "sg:city":"Joplin",
    "sg:classifiers":[
        {
            "category":"Manufacturing",
            "subcategory":"Metals",
            "type":"Manufacturing & Wholesale Goods"
        },
        {
            "category":"Professional",
            "subcategory":"Art Services",
            "type":"Services"
        },
        {
            "category":"Building & Trades",
            "subcategory":"Construction",
            "type":"Services"
        },
        {
            "category":"Military Area",
            "subcategory":"Armory",
            "type":"Public Place"
        }
    ],
    "sg:phone":"+1 417 438 6084",
    "sg:postcode":"64804",
    "sg:province":"MO",
    "sg:tags":[
        "ornamental",
        "fence",
        "repair",
        "work",
        "contractor",
        "iron",
        "welder",
        "work-supplies",
        "fence-sales"
    ],
    "wof:name":"Joplin Welding Services",
    "wof:placetype":"venue"
},
  "geometry": {"coordinates":[-94.50856,37.071557],"type":"Point"}
}