{
  "type": "Feature",
  "properties": {
    "iso:country":"US",
    "sg:address":"537 US Hwy 24",
    "sg:city":"Independence",
    "sg:classifiers":[
        {
            "category":"Retail",
            "subcategory":"Auto Repair",
            "type":"Services"
        }
    ],
    "sg:phone":"+1 816 461 8811",
    "sg:postcode":"64050",
    "sg:province":"MO",
    "sg:tags":[
        "general",
        "supply"
    ],
    "wof:name":"Direct Tire Outlet Inc",
    "wof:placetype":"venue"
},
  "geometry": {"coordinates":[-94.42035300000001,39.101495],"type":"Point"}
}