{
  "type": "Feature",
  "properties": {
    "iso:country":"US",
    "sg:address":"7627 Wydown Blvd",
    "sg:city":"St Louis",
    "sg:classifiers":[
        {
            "category":"Health Services",
            "subcategory":"Doctor",
            "type":"Services"
        }
    ],
    "sg:phone":"+1 314 725 3839",
    "sg:postcode":"63105",
    "sg:province":"MO",
    "sg:tags":[
        "dentist"
    ],
    "wof:name":"Thomas A Switzer DDS",
    "wof:placetype":"venue"
},
  "geometry": {"coordinates":[-90.33502,38.643066],"type":"Point"}
}