{
  "type": "Feature",
  "properties": {
    "iso:country":"US",
    "sg:address":"1100 Farrar St",
    "sg:city":"Saint Louis",
    "sg:classifiers":[
        {
            "category":"Education",
            "subcategory":"Library",
            "type":"Public Place"
        }
    ],
    "sg:phone":"+1 314 436 4664",
    "sg:postcode":"63107",
    "sg:province":"MO",
    "wof:name":"Library Services Center",
    "wof:placetype":"venue"
},
  "geometry": {"coordinates":[-90.19938999999999,38.662494],"type":"Point"}
}