{
  "type": "Feature",
  "properties": {
    "iso:country":"US",
    "sg:address":"217 E Main St",
    "sg:city":"Stanberry",
    "sg:classifiers":[
        {
            "category":"Retail",
            "subcategory":"Auto Repair",
            "type":"Services"
        }
    ],
    "sg:phone":"+1 660 783 2145",
    "sg:postcode":"64489",
    "sg:province":"MO",
    "wof:name":"Redig Service Station",
    "wof:placetype":"venue"
},
  "geometry": {"coordinates":[-94.539835,40.213001],"type":"Point"}
}