{
  "type": "Feature",
  "properties": {
    "iso:country":"US",
    "sg:address":"2928 Main St",
    "sg:city":"Kansas City",
    "sg:classifiers":[
        {
            "category":"Health Services",
            "subcategory":"Doctor",
            "type":"Services"
        }
    ],
    "sg:phone":"+1 816 234 3899",
    "sg:postcode":"64108",
    "sg:province":"MO",
    "sg:tags":[
        "physician",
        "surgeon"
    ],
    "wof:name":"Pediatric Care Clinic",
    "wof:placetype":"venue"
},
  "geometry": {"coordinates":[-94.585337,39.073286],"type":"Point"}
}