{
  "type": "Feature",
  "properties": {
    "iso:country":"US",
    "sg:address":"21299 State Hwy 96",
    "sg:city":"Ash Grove",
    "sg:classifiers":[
        {
            "category":"Freight",
            "type":"Transportation"
        }
    ],
    "sg:phone":"+1 417 447 3742",
    "sg:postcode":"65604",
    "sg:province":"MO",
    "sg:tags":[
        "broker",
        "trucking"
    ],
    "wof:name":"Epic Inc",
    "wof:placetype":"venue"
},
  "geometry": {"coordinates":[-93.672989,37.19278],"type":"Point"}
}