{
  "type": "Feature",
  "properties": {
    "iso:country":"US",
    "sg:address":"1051 Washington Square Shopping Ctr",
    "sg:city":"Washington",
    "sg:classifiers":[
        {
            "category":"Restaurant",
            "type":"Food & Drink"
        }
    ],
    "sg:phone":"+1 636 239 9950",
    "sg:postcode":"63090",
    "sg:province":"MO",
    "sg:tags":[
        "asian",
        "chinese",
        "pan"
    ],
    "wof:name":"Beijing Chinese Restaurant",
    "wof:placetype":"venue"
},
  "geometry": {"coordinates":[-91.00411699999999,38.536064],"type":"Point"}
}