{
  "type": "Feature",
  "properties": {
    "iso:country":"US",
    "sg:address":"505 Nichols St",
    "sg:city":"Fulton",
    "sg:classifiers":[
        {
            "category":"Shopping",
            "subcategory":"Used Merchandise",
            "type":"Retail Goods"
        }
    ],
    "sg:phone":"+1 573 642 5564",
    "sg:postcode":"65251",
    "sg:province":"MO",
    "wof:name":"Ciniminbear Baby Shop",
    "wof:placetype":"venue"
},
  "geometry": {"coordinates":[-91.948829,38.848715],"type":"Point"}
}