{
  "type": "Feature",
  "properties": {
    "iso:country":"US",
    "sg:address":"639 Marshall Rd",
    "sg:city":"Valley Park",
    "sg:classifiers":[
        {
            "category":"Manufacturing",
            "subcategory":"Glass & Minerals",
            "type":"Manufacturing & Wholesale Goods"
        }
    ],
    "sg:phone":"+1 636 225 5857",
    "sg:postcode":"63088",
    "sg:province":"MO",
    "sg:tags":[
        "hydraulic",
        "cement",
        "mfg"
    ],
    "wof:name":"Lafarge North America Inc",
    "wof:placetype":"venue"
},
  "geometry": {"coordinates":[-90.480609,38.551013],"type":"Point"}
}