{
  "type": "Feature",
  "properties": {
    "iso:country":"US",
    "sg:address":"5924 NE Parks View Pl",
    "sg:city":"Lees Summit",
    "sg:classifiers":[
        {
            "category":"Building & Trades",
            "subcategory":"Construction",
            "type":"Services"
        }
    ],
    "sg:phone":"+1 816 350 1476",
    "sg:postcode":"64064",
    "sg:province":"MO",
    "sg:tags":[
        "hanging",
        "contractor"
    ],
    "wof:name":"Colony Painting LLC",
    "wof:placetype":"venue"
},
  "geometry": {"coordinates":[-94.37212,39.020794],"type":"Point"}
}