{
  "type": "Feature",
  "properties": {
    "iso:country":"US",
    "sg:address":"3330 N Range Line Rd",
    "sg:city":"Webb City",
    "sg:classifiers":[
        {
            "category":"Recreation",
            "type":"Entertainment"
        }
    ],
    "sg:phone":"+1 417 623 3116",
    "sg:postcode":"64870",
    "sg:province":"MO",
    "sg:tags":[
        "club",
        "membership"
    ],
    "wof:name":"Do Red Inc",
    "wof:placetype":"venue"
},
  "geometry": {"coordinates":[-94.475909,37.118421],"type":"Point"}
}