{
  "type": "Feature",
  "properties": {
    "iso:country":"US",
    "sg:address":"12440 E 40 St S",
    "sg:city":"Independence",
    "sg:classifiers":[
        {
            "category":"Retail",
            "subcategory":"Veterinary Services",
            "type":"Services"
        }
    ],
    "sg:phone":"+1 816 358 2857",
    "sg:postcode":"64055",
    "sg:province":"MO",
    "wof:name":"Chrysler Animal Hospital",
    "wof:placetype":"venue"
},
  "geometry": {"coordinates":[-94.430639,39.049378],"type":"Point"}
}