{
  "type": "Feature",
  "properties": {
    "iso:country":"US",
    "sg:address":"366 Co Rd 357",
    "sg:city":"Charleston",
    "sg:classifiers":[
        {
            "category":"Real Estate",
            "subcategory":"Real Estate Operator",
            "type":"Services"
        }
    ],
    "sg:phone":"+1 573 683 4362",
    "sg:postcode":"63834",
    "sg:province":"MO",
    "sg:tags":[
        "property",
        "lessor"
    ],
    "wof:name":"Robert Morgan",
    "wof:placetype":"venue"
},
  "geometry": {"coordinates":[-89.411214,36.967701],"type":"Point"}
}