{
  "type": "Feature",
  "properties": {
    "iso:country":"US",
    "sg:address":"7700 Ivory Ave",
    "sg:city":"Saint Louis",
    "sg:classifiers":[
        {
            "category":"Professional",
            "subcategory":"Management & Consulting",
            "type":"Services"
        }
    ],
    "sg:phone":"+1 314 544 2292",
    "sg:postcode":"63111",
    "sg:province":"MO",
    "wof:name":"Advanced Learning Systems",
    "wof:placetype":"venue"
},
  "geometry": {"coordinates":[-90.263114,38.548752],"type":"Point"}
}