{
  "type": "Feature",
  "properties": {
    "iso:country":"US",
    "sg:address":"1832 Seven Pines Dr",
    "sg:city":"St Louis",
    "sg:classifiers":[
        {
            "category":"Building & Trades",
            "subcategory":"Cleaning & Sanitation",
            "type":"Services"
        }
    ],
    "sg:phone":"+1 314 469 7406",
    "sg:postcode":"63146",
    "sg:province":"MO",
    "sg:tags":[
        "maintenance"
    ],
    "wof:name":"Tidy St Louis Svc Co",
    "wof:placetype":"venue"
},
  "geometry": {"coordinates":[-90.476174,38.694437],"type":"Point"}
}