{
  "type": "Feature",
  "properties": {
    "iso:country":"US",
    "sg:address":"4212 Gravois Ave",
    "sg:city":"Saint Louis",
    "sg:classifiers":[
        {
            "category":"Wholesale",
            "subcategory":"Durable Goods & Equipment",
            "type":"Manufacturing & Wholesale Goods"
        },
        {
            "category":"Shopping",
            "type":"Retail Goods"
        }
    ],
    "sg:phone":"+1 314 351 5005",
    "sg:postcode":"63116",
    "sg:province":"MO",
    "sg:tags":[
        "fire",
        "extinguisher",
        "lighting",
        "fixture"
    ],
    "wof:name":"Weber Fire & Safety Equip Co",
    "wof:placetype":"venue"
},
  "geometry": {"coordinates":[-90.2593,38.5877],"type":"Point"}
}