{
  "type": "Feature",
  "properties": {
    "iso:country":"US",
    "sg:address":"4520 Amazonia Rd",
    "sg:city":"Saint Joseph",
    "sg:classifiers":[
        {
            "category":"Retail",
            "subcategory":"Auto Repair",
            "type":"Services"
        }
    ],
    "sg:phone":"+1 816 232 5886",
    "sg:postcode":"64505",
    "sg:province":"MO",
    "sg:tags":[
        "automobile",
        "installation",
        "glass"
    ],
    "wof:name":"D & L Glass Co",
    "wof:placetype":"venue"
},
  "geometry": {"coordinates":[-94.85114400000001,39.807804],"type":"Point"}
}