{
  "type": "Feature",
  "properties": {
    "iso:country":"US",
    "sg:address":"4470 State Route U",
    "sg:city":"Pomona",
    "sg:classifiers":[
        {
            "category":"Retail",
            "subcategory":"Auto Repair",
            "type":"Services"
        }
    ],
    "sg:phone":"+1 417 469 5542",
    "sg:postcode":"65789",
    "sg:province":"MO",
    "sg:tags":[
        "body",
        "painting",
        "repairing",
        "automobile"
    ],
    "wof:name":"Harris Cstm Finishes & Offroad",
    "wof:placetype":"venue"
},
  "geometry": {"coordinates":[-91.875701,36.892391],"type":"Point"}
}