{
  "type": "Feature",
  "properties": {
    "iso:country":"US",
    "sg:address":"1200 S Jefferson Ave",
    "sg:city":"Saint Louis",
    "sg:classifiers":[
        {
            "category":"Personal",
            "subcategory":"Barber",
            "type":"Services"
        }
    ],
    "sg:phone":"+1 314 772 1797",
    "sg:postcode":"63104",
    "sg:province":"MO",
    "sg:tags":[
        "shop"
    ],
    "wof:name":"Yams Beauty & Barber Shop",
    "wof:placetype":"venue"
},
  "geometry": {"coordinates":[-90.219539,38.619844],"type":"Point"}
}