{
  "type": "Feature",
  "properties": {
    "iso:country":"US",
    "sg:address":"1525 S Kirkwood Rd",
    "sg:city":"Saint Louis",
    "sg:classifiers":[
        {
            "category":"Restaurant",
            "type":"Food & Drink"
        },
        {
            "category":"Ice Cream",
            "type":"Food & Drink"
        }
    ],
    "sg:menulink":"http://www.allmenus.com/mo/bonhomme/55517-steak-n-shake/menu/",
    "sg:phone":"+1 314 821 4117",
    "sg:postcode":"63127",
    "sg:province":"MO",
    "sg:tags":[
        "burger",
        "american",
        "ice",
        "cream"
    ],
    "wof:name":"Steak 'n Shake",
    "wof:placetype":"venue"
},
  "geometry": {"coordinates":[-90.40757000000001,38.556743],"type":"Point"}
}