{
  "type": "Feature",
  "properties": {
    "iso:country":"US",
    "sg:address":"1516 S Brentwood Blvd",
    "sg:city":"St Louis",
    "sg:classifiers":[
        {
            "category":"Government",
            "subcategory":"Office",
            "type":"Public Place"
        }
    ],
    "sg:phone":"+1 314 961 7877",
    "sg:postcode":"63144",
    "sg:province":"MO",
    "wof:name":"St Louis County Boundary Comm",
    "wof:placetype":"venue"
},
  "geometry": {"coordinates":[-90.34637600000001,38.627385],"type":"Point"}
}