{
  "type": "Feature",
  "properties": {
    "iso:country":"US",
    "sg:address":"3224 Burning Tree Ln",
    "sg:city":"Festus",
    "sg:classifiers":[
        {
            "category":"Fast Food",
            "type":"Food & Drink"
        },
        {
            "category":"Restaurant",
            "type":"Food & Drink"
        }
    ],
    "sg:phone":"+1 636 931 2434",
    "sg:postcode":"63028",
    "sg:province":"MO",
    "sg:tags":[
        "take"
    ],
    "wof:name":"Jts Partnership Dda Mcdonalds",
    "wof:placetype":"venue"
},
  "geometry": {"coordinates":[-90.45163599999999,38.221883],"type":"Point"}
}