{
  "type": "Feature",
  "properties": {
    "iso:country":"US",
    "sg:address":"219 Thresher Dr",
    "sg:city":"Eureka",
    "sg:classifiers":[
        {
            "category":"Banks & Credit Unions",
            "subcategory":"Investment Brokerage",
            "type":"Services"
        },
        {
            "category":"Banks & Credit Unions",
            "subcategory":"Bank",
            "type":"Services"
        },
        {
            "category":"Banks & Credit Unions",
            "subcategory":"Financial Services",
            "type":"Services"
        }
    ],
    "sg:phone":"+1 636 938 9222",
    "sg:postcode":"63025",
    "sg:province":"MO",
    "sg:tags":[
        "commercial",
        "loan",
        "saving",
        "mortgage"
    ],
    "wof:name":"Rockwood Bancshares Inc",
    "wof:placetype":"venue"
},
  "geometry": {"coordinates":[-90.62647699999999,38.500638],"type":"Point"}
}