{
  "type": "Feature",
  "properties": {
    "iso:country":"US",
    "sg:address":"517 State Hwy D",
    "sg:city":"Lawson",
    "sg:classifiers":[
        {
            "category":"Retail",
            "subcategory":"Self-service Laundry",
            "type":"Services"
        }
    ],
    "sg:phone":"+1 816 580 3619",
    "sg:postcode":"64062",
    "sg:province":"MO",
    "sg:tags":[
        "coin"
    ],
    "wof:name":"Millies Coin Laundry & Dry Clg",
    "wof:placetype":"venue"
},
  "geometry": {"coordinates":[-94.210758,39.440281],"type":"Point"}
}