{
  "type": "Feature",
  "properties": {
    "iso:country":"US",
    "sg:address":"5700 S Campbell Ave",
    "sg:city":"Springfield",
    "sg:classifiers":[
        {
            "category":"Social Services",
            "subcategory":"Child Care",
            "type":"Services"
        }
    ],
    "sg:phone":"+1 417 883 6640",
    "sg:postcode":"65810",
    "sg:province":"MO",
    "sg:tags":[
        "kindergarten",
        "academic",
        "school"
    ],
    "wof:name":"Promise Pre-School & Day Care",
    "wof:placetype":"venue"
},
  "geometry": {"coordinates":[-93.296471,37.116137],"type":"Point"}
}