{
  "type": "Feature",
  "properties": {
    "iso:country":"US",
    "sg:address":"1005 S Elliott Ave",
    "sg:city":"Aurora",
    "sg:classifiers":[
        {
            "category":"Banks & Credit Unions",
            "subcategory":"Bank",
            "type":"Services"
        }
    ],
    "sg:phone":"+1 417 678 0293",
    "sg:postcode":"65605",
    "sg:province":"MO",
    "sg:tags":[
        "loan"
    ],
    "wof:name":"Pay Day Loans",
    "wof:placetype":"venue"
},
  "geometry": {"coordinates":[-93.718208,36.965159],"type":"Point"}
}