{
  "type": "Feature",
  "properties": {
    "iso:country":"US",
    "sg:address":"1420 US Hwy 61 Bus",
    "sg:city":"Bowling Green",
    "sg:classifiers":[
        {
            "category":"Shopping",
            "subcategory":"Hobbies, Toys, & Games",
            "type":"Retail Goods"
        }
    ],
    "sg:phone":"+1 573 324 6185",
    "sg:postcode":"63334",
    "sg:province":"MO",
    "sg:tags":[
        "craft",
        "supply"
    ],
    "wof:name":"Cut It Out",
    "wof:placetype":"venue"
},
  "geometry": {"coordinates":[-91.18594,39.333408],"type":"Point"}
}