{
  "type": "Feature",
  "properties": {
    "iso:country":"US",
    "sg:address":"2542 S Brentwood Blvd",
    "sg:city":"St Louis",
    "sg:classifiers":[
        {
            "category":"Shopping",
            "subcategory":"Gifts & Souvenirs",
            "type":"Retail Goods"
        }
    ],
    "sg:phone":"+1 314 968 8482",
    "sg:postcode":"63144",
    "sg:province":"MO",
    "sg:tags":[
        "shop"
    ],
    "wof:name":"Viva Gifts & Home Furnishing",
    "wof:placetype":"venue"
},
  "geometry": {"coordinates":[-90.34864,38.615971],"type":"Point"}
}