{
  "type": "Feature",
  "properties": {
    "iso:country":"US",
    "sg:address":"537 S Highway 13",
    "sg:city":"Lexington",
    "sg:classifiers":[
        {
            "category":"Fast Food",
            "type":"Food & Drink"
        },
        {
            "category":"Restaurant",
            "type":"Food & Drink"
        },
        {
            "category":"Professional",
            "type":"Services"
        }
    ],
    "sg:phone":"+1 660 259 4389",
    "sg:postcode":"64067",
    "sg:province":"MO",
    "sg:tags":[
        "delivery",
        "take",
        "pizza"
    ],
    "sg:website":"http://www.pizzahut.com",
    "wof:name":"Pizza Hut",
    "wof:placetype":"venue"
},
  "geometry": {"coordinates":[-93.877954,39.178102],"type":"Point"}
}