{
  "type": "Feature",
  "properties": {
    "iso:country":"US",
    "sg:address":"1932 Lake Ter",
    "sg:city":"Independence",
    "sg:classifiers":[
        {
            "category":"Retail",
            "subcategory":"Veterinary Services",
            "type":"Services"
        }
    ],
    "sg:phone":"+1 816 833 1160",
    "sg:postcode":"64055",
    "sg:province":"MO",
    "sg:tags":[
        "veterinarian"
    ],
    "wof:name":"Roger L Becker DVM",
    "wof:placetype":"venue"
},
  "geometry": {"coordinates":[-94.40447899999999,39.064994],"type":"Point"}
}