{
  "type": "Feature",
  "properties": {
    "iso:country":"US",
    "sg:address":"8400 Hedges Ave",
    "sg:city":"Kansas City",
    "sg:classifiers":[
        {
            "category":"Professional",
            "subcategory":"Business Services",
            "type":"Services"
        }
    ],
    "sg:phone":"+1 816 358 7049",
    "sg:postcode":"64138",
    "sg:province":"MO",
    "sg:tags":[
        "transcribing",
        "disc"
    ],
    "wof:name":"Overload Transcription Inc",
    "wof:placetype":"venue"
},
  "geometry": {"coordinates":[-94.459536,38.970931],"type":"Point"}
}