{
  "type": "Feature",
  "properties": {
    "iso:country":"US",
    "sg:address":"2057 Exchange Dr",
    "sg:city":"Saint Charles",
    "sg:classifiers":[
        {
            "category":"Social Services",
            "type":"Services"
        }
    ],
    "sg:phone":"+1 636 723 2999",
    "sg:postcode":"63303",
    "sg:province":"MO",
    "wof:name":"Harvester Dac",
    "wof:placetype":"venue"
},
  "geometry": {"coordinates":[-90.53087499999999,38.757218],"type":"Point"}
}