{
  "type": "Feature",
  "properties": {
    "iso:country":"US",
    "sg:address":"716 Shirewood Rd",
    "sg:city":"Excelsior Springs",
    "sg:classifiers":[
        {
            "category":"Building & Trades",
            "subcategory":"Construction",
            "type":"Services"
        }
    ],
    "sg:phone":"+1 816 630 7652",
    "sg:postcode":"64024",
    "sg:province":"MO",
    "sg:tags":[
        "house"
    ],
    "wof:name":"Four Winds Construction LLC",
    "wof:placetype":"venue"
},
  "geometry": {"coordinates":[-94.22815799999999,39.330683],"type":"Point"}
}