{
  "type": "Feature",
  "properties": {
    "iso:country":"US",
    "sg:address":"4113 W 83rd St",
    "sg:city":"Prairie Village",
    "sg:classifiers":[
        {
            "category":"Shopping",
            "type":"Retail Goods"
        }
    ],
    "sg:phone":"+1 913 642 7092",
    "sg:postcode":"66208",
    "sg:province":"MO",
    "sg:tags":[
        "miscellaneous",
        "store"
    ],
    "wof:name":"Auntie's Beads",
    "wof:placetype":"venue"
},
  "geometry": {"coordinates":[-94.63426,38.978611],"type":"Point"}
}