{
  "type": "Feature",
  "properties": {
    "iso:country":"US",
    "sg:address":"9372 Ashbrook Farm Rd",
    "sg:city":"Hillsboro",
    "sg:classifiers":[
        {
            "category":"Freight",
            "type":"Transportation"
        }
    ],
    "sg:phone":"+1 636 475 9455",
    "sg:postcode":"63050",
    "sg:province":"MO",
    "sg:tags":[
        "operator",
        "local",
        "trucking"
    ],
    "wof:name":"Kevin Arnett Hauling",
    "wof:placetype":"venue"
},
  "geometry": {"coordinates":[-90.497208,38.278236],"type":"Point"}
}